Workbook

Sheet EBIDTA
B3: Name of the Company : - KPW I (2026-27)
B5: Particulars | C5: AUGUST.26 | D5: % | E5: JULY.26 | F5: % | G5: JUNE.26 | H5: % | I5: MAY.26 | J5: % | K5: APRIL.26 | L5: % | M5: YTD AUGUST.26 | N5: % | O5: YTD JULY.26 | P5: % | Q5: YTD JUNE.26 | R5: % | S5: YTD MAY.26 | T5: % | U5: YTD APRIL.26 | V5: % | X5: Particulars | Y5: AUGUST.26 | Z5: JULY.26 | AA5: JUNE.26 | AB5: MAY.26 | AC5: APRIL.26 | AF5: APRIL.26 | AG5: MAY.26 | AH5: JUNE.26 | AI5: JULY.26 | AJ5: AUG..26
B6: Revenue from operations | X6: Inventory at the beginning of the year:
B7: Sale of finished goods | C7: =M7-O7 -> 2.5754881e+08 | D7: =C7/$C$30 -> 0.86984527 | E7: =O7-Q7 -> 2.3382328e+08 | F7: =E7/$E$30 -> 0.93667298 | G7: =Q7-S7 -> 1.7991097e+08 | H7: =(G7/$G$30) -> 0.89920522 | I7: =S7-U7 -> 1.9791503e+08 | J7: =(I7/$I$30) -> 0.97072984 | K7: =U7 -> 1.7902816e+08 | L7: =(K7/$K$30) -> 0.97738124 | M7: =-SUMIF('AUGUST - TB'!H:H,EBIDTA!B7,'AUGUST - TB'!G:G) -> 1.0482262e+09 | N7: =M7/$M$30 -> 0.92530076 | O7: =-SUMIF('JULY-TB'!H:H,EBIDTA!B7,'JULY-TB'!G:G) -> 7.9067744e+08 | P7: =O7/$O$30 -> 0.94492349 | Q7: =-SUMIF('JUNE - TB -'!H:H,EBIDTA!B7,'JUNE - TB -'!G:G) -> 5.5685415e+08 | R7: =(Q7/$Q$30) -> 0.94843137 | S7: =-SUMIF('MAY- TB - '!H:H,EBIDTA!B7,'MAY- TB - '!E:E) -> 3.7694318e+08 | T7: =(S7/$S$30) -> 0.97387758 | U7: =-SUMIF('APRIL - TB -'!H:H,EBIDTA!B7,'APRIL - TB -'!G:G) -> 1.7902816e+08 | V7: =(U7/$U$30) -> 0.97738124 | X7: Opening Stock of Raw material | Y7: =Z7 -> 78409106 | Z7: =AA7 -> 78409106 | AA7: =AB7 -> 78409106 | AB7: =AC7 -> 78409106 | AC7: ='Stock Sheet - KPW'!O5 -> 78409106
B8: Sale of traded goods | C8: =M8-O8 -> 3350474.1 | D8: =C8/$C$30 -> 0.01131589 | E8: =O8-Q8 -> 919114.45 | F8: =E8/$E$30 -> 0.0036818817 | G8: =Q8-S8 -> 443540 | H8: =(G8/$G$30) -> 0.002216838 | I8: =S8-U8 -> 691772.73 | J8: =(I8/$I$30) -> 0.0033929937 | K8: =U8 -> 4108107.4 | L8: =(K8/$K$30) -> 0.022427685 | M8: =-SUMIF('AUGUST - TB'!H:H,EBIDTA!B8,'AUGUST - TB'!G:G) -> 9513008.6 | N8: =M8/$M$30 -> 0.0083974181 | O8: =-SUMIF('JULY-TB'!H:H,EBIDTA!B8,'JULY-TB'!G:G) -> 6162534.5 | P8: =O8/$O$30 -> 0.0073647272 | Q8: =-SUMIF('JUNE - TB -'!H:H,EBIDTA!B8,'JUNE - TB -'!G:G) -> 5243420.1 | R8: =(Q8/$Q$30) -> 0.0089305683 | S8: =-SUMIF('MAY- TB - '!H:H,EBIDTA!B8,'MAY- TB - '!E:E) -> 4799880.1 | T8: =(S8/$S$30) -> 0.012401062 | U8: =-SUMIF('APRIL - TB -'!H:H,EBIDTA!B8,'APRIL - TB -'!G:G) -> 4108107.4 | V8: =(U8/$U$30) -> 0.022427685 | X8: Opening Stock of Packing material | AC8: 0
B9: Total Revenue from operations | C9: =SUM(C7:C8) -> 2.6089929e+08 | D9: =C9/$C$30 -> 0.88116116 | E9: =SUM(E7:E8) -> 2.347424e+08 | F9: =E9/$E$30 -> 0.94035486 | G9: =SUM(G7:G8) -> 1.8035451e+08 | H9: =(G9/$G$30) -> 0.90142206 | I9: =SUM(I7:I8) -> 1.986068e+08 | J9: =(I9/$I$30) -> 0.97412284 | K9: =SUM(K7:K8) -> 1.8313626e+08 | L9: =(K9/$K$30) -> 0.99980892 | M9: =SUM(M7:M8) -> 1.0577393e+09 | N9: =M9/$M$30 -> 0.93369818 | O9: =SUM(O7:O8) -> 7.9683997e+08 | P9: =O9/$O$30 -> 0.95228821 | Q9: =SUM(Q7:Q8) -> 5.6209757e+08 | R9: =(Q9/$Q$30) -> 0.95736194 | S9: =SUM(S7:S8) -> 381743062 | T9: =(S9/$S$30) -> 0.98627864 | U9: =SUM(U7:U8) -> 1.8313626e+08 | V9: =(U9/$U$30) -> 0.99980892
X10: Add: Purchase of raw materials | Y10: =SUMIF('AUGUST - TB'!H:H,EBIDTA!X10,'AUGUST - TB'!G:G) -> 6.8290635e+08 | Z10: =SUMIF('JULY-TB'!H:H,EBIDTA!X10,'JULY-TB'!G:G) -> 4.8088707e+08 | AA10: =SUMIF('JUNE - TB -'!H1:H1325,EBIDTA!X10,'JUNE - TB -'!G1:G1325) -> 2.8824663e+08 | AB10: =SUMIF('MAY- TB - '!H1:H1317,EBIDTA!X10,'MAY- TB - '!G1:G1317) -> 1.769685e+08 | AC10: =SUMIF('APRIL - TB -'!H2:H1238,EBIDTA!X10,'APRIL - TB -'!G2:G1231) -> 1.2064284e+08 | AF10: =AC10/10^7 -> 12.064284 | AG10: =(AB10-AF10)/10^7 -> 17.696849 | AH10: =(AA10-AB10)/10^7 -> 11.127812 | AI10: =(Z10-AA10)/10^7 -> 19.264044 | AJ10: =(Y10-Z10)/10^7 -> 20.201928
B11: Income from Jobwork charges | C11: =M11-O11 -> 34912345 | E11: =O11-Q11 -> 13688319 | G11: =Q11-S11 -> 17493444 | I11: =S11-U11 -> 5117576 | K11: =U11 -> 0 | M11: =-SUMIF('AUGUST - TB'!H:H,EBIDTA!B11,'AUGUST - TB'!G:G) -> 71211684 | O11: =-SUMIF('JULY-TB'!H:H,EBIDTA!B11,'JULY-TB'!G:G) -> 36299339 | Q11: =-SUMIF('JUNE - TB -'!H:H,EBIDTA!B11,'JUNE - TB -'!G:G) -> 22611020 | S11: =-SUMIF('MAY- TB - '!H:H,EBIDTA!B11,'MAY- TB - '!E:E) -> 5117576 | U11: =-SUMIF('APRIL - TB -'!H:H,EBIDTA!B11,'APRIL - TB -'!G:G) -> 0 | X11: Add: Purchase of packing materials | Y11: =SUMIF('AUGUST - TB'!H:H,EBIDTA!X11,'AUGUST - TB'!G:G) -> 7638900.9 | Z11: =SUMIF('JULY-TB'!H:H,EBIDTA!X11,'JULY-TB'!G:G) -> 6188686.3 | AA11: =SUMIF('JUNE - TB -'!H2:H1326,EBIDTA!X11,'JUNE - TB -'!G2:G1326) -> 3902200.5 | AB11: =SUMIF('MAY- TB - '!H2:H1318,EBIDTA!X11,'MAY- TB - '!G2:G1318) -> 2830055.7 | AC11: =SUMIF('APRIL - TB -'!H3:H1239,EBIDTA!X11,'APRIL - TB -'!G3:G1232) -> 1127244.8 | AF11: =AC11/10^7 -> 0.11272448 | AG11: =(AB11-AF11)/10^7 -> 0.28300556 | AH11: =(AA11-AB11)/10^7 -> 0.10721448 | AI11: =(Z11-AA11)/10^7 -> 0.22864858 | AJ11: =(Y11-Z11)/10^7 -> 0.14502146
B12: Total Sales of services | C12: =SUM(C10:C11) -> 34912345 | D12: =C12/$C$30 -> 0.11791294 | E12: =SUM(E10:E11) -> 13688319 | F12: =E12/$E$30 -> 0.054834054 | G12: =SUM(G10:G11) -> 17493444 | H12: =(G12/$G$30) -> 0.087433223 | I12: =SUM(I10:I11) -> 5117576 | J12: =(I12/$I$30) -> 0.025100589 | K12: =SUM(K10:K11) -> 0 | L12: =(K12/$K$30) -> 0 | M12: =SUM(M10:M11) -> 71211684 | N12: =M12/$M$30 -> 0.06286069 | O12: =SUM(O10:O11) -> 36299339 | P12: =O12/$O$30 -> 0.043380646 | Q12: =SUM(Q10:Q11) -> 22611020 | S12: =SUM(S10:S11) -> 5117576 | T12: =(S12/$S$30) -> 0.013221867 | U12: =SUM(U10:U11) -> 0 | V12: =(U12/$U$30) -> 0 | X12: Add: Purchase expenses | Y12: =SUMIF('AUGUST - TB'!H:H,EBIDTA!X12,'AUGUST - TB'!G:G) -> 6533679.1 | Z12: =SUMIF('JULY-TB'!H:H,EBIDTA!X12,'JULY-TB'!G:G) -> 5898962.8 | AA12: =SUMIF('JUNE - TB -'!H3:H1329,EBIDTA!X12,'JUNE - TB -'!G3:G1329) -> 6340260.4 | AB12: =SUMIF('MAY- TB - '!H3:H1319,EBIDTA!X12,'MAY- TB - '!G3:G1319) -> 5936506 | AC12: =SUMIF('APRIL - TB -'!H4:H1240,EBIDTA!X12,'APRIL - TB -'!G4:G1233) -> 3603365.7 | AF12: =AC12/10^7 -> 0.36033657 | AG12: =(AB12-AF12)/10^7 -> 0.59365057 | AH12: =(AA12-AB12)/10^7 -> 0.040375438 | AI12: =(Z12-AA12)/10^7 -> -0.044129762 | AJ12: =(Y12-Z12)/10^7 -> 0.063471632
B13: Other operating revenue | G13: =Q13-S13 -> 0 | I13: =S13-U13 -> 0 | Q13: =-SUMIF('JUNE - TB -'!H:H,EBIDTA!B13,'JUNE - TB -'!G:G) -> 0 | U13: =-SUMIF('APRIL - TB -'!H:H,EBIDTA!B13,'APRIL - TB -'!G:G) -> 0 | X13: Closing Stock of Raw material | Y13: ='Stock Sheet - KPW'!T5 -> 1.1168642e+08 | Z13: ='Stock Sheet - KPW'!S5 -> 84892889 | AA13: ='Stock Sheet - KPW'!R5 -> 63882998 | AB13: ='Stock Sheet - KPW'!Q5 -> 78548384 | AC13: ='Stock Sheet - KPW'!P5 -> 1.1669902e+08 | AF13: =AC13/10^7 -> 11.669902 | AG13: =(AB13-AF13)/10^7 -> 7.8548373 | AH13: =(AA13-AB13)/10^7 -> -1.4665386 | AI13: =(Z13-AA13)/10^7 -> 2.1009891 | AJ13: =(Y13-Z13)/10^7 -> 2.6793533
B14: Export incentives | C14: =M14-O14 -> 0 | G14: =Q14-S14 -> 0 | I14: =S14-U14 -> 0 | K14: =U14 -> 0 | M14: =-SUMIF('AUGUST - TB'!H:H,EBIDTA!B14,'AUGUST - TB'!G:G) -> 0 | O14: =-SUMIF('JULY-TB'!H:H,EBIDTA!B14,'JULY-TB'!G:G) -> 0 | Q14: =-SUMIF('JUNE - TB -'!H:H,EBIDTA!B14,'JUNE - TB -'!G:G) -> 0 | S14: =-SUMIF('MAY- TB - '!H:H,EBIDTA!B14,'MAY- TB - '!E:E) -> 0 | U14: =-SUMIF('APRIL - TB -'!H:H,EBIDTA!B14,'APRIL - TB -'!G:G) -> 0 | X14: Closing Stock of Packing material | AB14: 0 | AC14: 0
B15: Commission income | C15: =M15-O15 -> 0 | G15: =Q15-S15 -> 0 | I15: =S15-U15 -> 0 | K15: =U15 -> 0 | M15: =-SUMIF('AUGUST - TB'!H:H,EBIDTA!B15,'AUGUST - TB'!G:G) -> 0 | O15: =-SUMIF('JULY-TB'!H:H,EBIDTA!B15,'JULY-TB'!G:G) -> 0 | Q15: =-SUMIF('JUNE - TB -'!H:H,EBIDTA!B15,'JUNE - TB -'!G:G) -> 0 | S15: =-SUMIF('MAY- TB - '!H:H,EBIDTA!B15,'MAY- TB - '!E:E) -> 0 | U15: =-SUMIF('APRIL - TB -'!H:H,EBIDTA!B15,'APRIL - TB -'!G:G) -> 0 | X15: Total Cost of material consumed | Y15: =Y7+Y8+Y10+Y11+Y12-Y13 -> 6.6380162e+08 | Z15: =Z7+Z8+Z10+Z11+Z12-Z13 -> 4.8649093e+08 | AA15: =AA7+AA8+AA10+AA11+AA12-AA13 -> 3.130152e+08 | AB15: =AB7+AB8+AB10+AB11+AB12-AB13 -> 1.8559579e+08 | AC15: =AC7+AC8+AC10+AC11+AC12-AC13 -> 87083536 | AF15: =AC15/10^7 -> 8.7083536 | AG15: =(AB15-AF15)/10^7 -> 18.559578 | AH15: =(AA15-AB15)/10^7 -> 12.741941 | AI15: =(Z15-AA15)/10^7 -> 17.347574 | AJ15: =(Y15-Z15)/10^7 -> 17.731068
B16: Sales - Waste & Scrape | C16: =M16-O16 -> 274145 | E16: =O16-Q16 -> 814311.7 | G16: =Q16-S16 -> 1988550 | I16: =S16-U16 -> 358330 | K16: =U16 -> 35000 | M16: =-SUMIF('AUGUST - TB'!H:H,EBIDTA!B16,'AUGUST - TB'!G:G) -> 3470336.7 | O16: =-SUMIF('JULY-TB'!H:H,EBIDTA!B16,'JULY-TB'!G:G) -> 3196191.7 | Q16: =-SUMIF('JUNE - TB -'!H:H,EBIDTA!B16,'JUNE - TB -'!G:G) -> 2381880 | S16: =-SUMIF('MAY- TB - '!H:H,EBIDTA!B16,'MAY- TB - '!E:E) -> 393330 | U16: =-SUMIF('APRIL - TB -'!H:H,EBIDTA!B16,'APRIL - TB -'!G:G) -> 35000
B17: Total Other operating revenue | C17: =SUM(C14:C16) -> 274145 | D17: =C17/$C$30 -> 0.00092589723 | E17: =SUM(E14:E16) -> 814311.7 | F17: =E17/$E$30 -> 0.0032620523 | G17: =SUM(G14:G16) -> 1988550 | H17: =(G17/$G$30) -> 0.0099388854 | I17: =SUM(I14:I16) -> 358330 | J17: =(I17/$I$30) -> 0.0017575301 | K17: =SUM(K14:K16) -> 35000 | L17: =(K17/$K$30) -> 0.00019107801 | M17: =SUM(M14:M16) -> 3470336.7 | N17: =M17/$M$30 -> 0.0030633703 | O17: =SUM(O14:O16) -> 3196191.7 | P17: =O17/$O$30 -> 0.0038197076 | Q17: =SUM(Q14:Q16) -> 2381880 | R17: =(Q17/$Q$30) -> 0.0040568068 | S17: =SUM(S14:S16) -> 393330 | T17: =(S17/$S$30) -> 0.0010162149 | U17: =SUM(U14:U16) -> 35000 | V17: =(U17/$U$30) -> 0.00019107801 | X17: Changes in inventory of finished goods and work-in-progress
B18: Other income | X18: Inventory at the beginning of the year:
B19: Interest income: | C19: =M19-O19 -> 0 | E19: =O19-Q19 -> 0 | G19: =Q19-S19 -> 0 | I19: =S19-U19 -> 0 | M19: =-SUMIF('AUGUST - TB'!H:H,EBIDTA!B19,'AUGUST - TB'!G:G) -> 0 | O19: =-SUMIF('JULY-TB'!H:H,EBIDTA!B19,'JULY-TB'!G:G) -> 0 | Q19: =-SUMIF('JUNE - TB -'!H:H,EBIDTA!B19,'JUNE - TB -'!G:G) -> 0 | S19: =-SUMIF('MAY- TB - '!H:H,EBIDTA!B19,'MAY- TB - '!E:E) -> 0 | U19: =-SUMIF('APRIL - TB -'!H:H,EBIDTA!B19,'APRIL - TB -'!G:G) -> 0 | X19: Opening Work-in-progress | Y19: 0 | Z19: 0 | AA19: 0 | AB19: 0 | AC19: 0
B20: - on fixed deposits with Banks | C20: =M20-O20 -> 0 | E20: =O20-Q20 -> 0 | G20: =Q20-S20 -> 0 | I20: =S20-U20 -> 0 | K20: =U20 -> 0 | M20: =-SUMIF('AUGUST - TB'!H:H,EBIDTA!B20,'AUGUST - TB'!G:G) -> 0 | O20: =-SUMIF('JULY-TB'!H:H,EBIDTA!B20,'JULY-TB'!G:G) -> 0 | Q20: =-SUMIF('JUNE - TB -'!H:H,EBIDTA!B20,'JUNE - TB -'!G:G) -> 0 | S20: =-SUMIF('MAY- TB - '!H:H,EBIDTA!B20,'MAY- TB - '!E:E) -> 0 | U20: =-SUMIF('APRIL - TB -'!H:H,EBIDTA!B20,'APRIL - TB -'!G:G) -> 0 | X20: Opening Stock of Finished goods | Y20: =Z20 -> 2.0644672e+08 | Z20: =AA20 -> 2.0644672e+08 | AA20: =AB20 -> 2.0644672e+08 | AB20: =AC20 -> 2.0644672e+08 | AC20: ='Stock Sheet - KPW'!O10 -> 2.0644672e+08 | AF20: =AC20/10^7 -> 20.644672 | AG20: 20.644672 | AH20: 20.644672 | AI20: 20.644672 | AJ20: 20.644672
B21: Wind mill income | C21: =M21-O21 -> 0 | E21: =O21-Q21 -> 0 | G21: =Q21-S21 -> 0 | I21: =S21-U21 -> 0 | K21: =U21 -> 0 | M21: =-SUMIF('AUGUST - TB'!H:H,EBIDTA!B21,'AUGUST - TB'!G:G) -> 0 | O21: =-SUMIF('JULY-TB'!H:H,EBIDTA!B21,'JULY-TB'!G:G) -> 0 | Q21: =-SUMIF('JUNE - TB -'!H:H,EBIDTA!B21,'JUNE - TB -'!G:G) -> 0 | S21: =-SUMIF('MAY- TB - '!H:H,EBIDTA!B21,'MAY- TB - '!E:E) -> 0 | U21: =-SUMIF('APRIL - TB -'!H:H,EBIDTA!B21,'APRIL - TB -'!G:G) -> 0
B22: Rent Income | C22: =M22-O22 -> 0 | E22: =O22-Q22 -> 0 | G22: =Q22-S22 -> 0 | I22: =S22-U22 -> -200000 | K22: =U22 -> 0 | M22: =-SUMIF('AUGUST - TB'!H:H,EBIDTA!B22,'AUGUST - TB'!G:G) -> -200000 | O22: =-SUMIF('JULY-TB'!H:H,EBIDTA!B22,'JULY-TB'!G:G) -> -200000 | Q22: =-SUMIF('JUNE - TB -'!H:H,EBIDTA!B22,'JUNE - TB -'!G:G) -> -200000 | S22: =-SUMIF('MAY- TB - '!H:H,EBIDTA!B22,'MAY- TB - '!E:E) -> -200000 | U22: =-SUMIF('APRIL - TB -'!H:H,EBIDTA!B22,'APRIL - TB -'!G:G) -> 0 | X22: Less:Inventory at the end of the year:
B23: Advance License Utilization | C23: =M23-O23 -> 0 | E23: =O23-Q23 -> 0 | G23: =Q23-S23 -> 0 | I23: =S23-U23 -> 0 | K23: =U23 -> 0 | M23: =-SUMIF('AUGUST - TB'!H:H,EBIDTA!B23,'AUGUST - TB'!G:G) -> 0 | O23: =-SUMIF('JULY-TB'!H:H,EBIDTA!B23,'JULY-TB'!G:G) -> 0 | Q23: =-SUMIF('JUNE - TB -'!H:H,EBIDTA!B23,'JUNE - TB -'!G:G) -> 0 | S23: =-SUMIF('MAY- TB - '!H:H,EBIDTA!B23,'MAY- TB - '!E:E) -> 0 | U23: =-SUMIF('APRIL - TB -'!H:H,EBIDTA!B23,'APRIL - TB -'!G:G) -> 0 | X23: Closing Stock of Finished goods | Y23: ='Stock Sheet - KPW'!T10 -> 1.7394276e+08 | Z23: ='Stock Sheet - KPW'!S10 -> 1.7503296e+08 | AA23: ='Stock Sheet - KPW'!R10 -> 1.8609886e+08 | AB23: ='Stock Sheet - KPW'!Q10 -> 1.7228635e+08 | AC23: ='Stock Sheet - KPW'!P10 -> 1.7144735e+08 | AF23: =(AC20-AC23)/10^7 -> 3.4999374 | AG23: =(AB23-AC23)/10^7 -> 0.083900428 | AH23: =(AA23-AB23)/10^7 -> 1.3812508 | AI23: =(Z23-AA23)/10^7 -> -1.1065904 | AJ23: =(Y23-Z23)/10^7 -> -0.10901962
B24: Profit on sale of fixed assets | C24: =M24-O24 -> 0 | E24: =O24-Q24 -> 386687 | G24: =Q24-S24 -> -313071.41 | I24: =S24-U24 -> 0 | K24: =U24 -> 0 | M24: =-SUMIF('AUGUST - TB'!H:H,EBIDTA!B24,'AUGUST - TB'!G:G) -> 73615.59 | O24: =-SUMIF('JULY-TB'!H:H,EBIDTA!B24,'JULY-TB'!G:G) -> 73615.59 | Q24: =-SUMIF('JUNE - TB -'!H:H,EBIDTA!B24,'JUNE - TB -'!G:G) -> -313071.41 | S24: =-SUMIF('MAY- TB - '!H:H,EBIDTA!B24,'MAY- TB - '!E:E) -> 0 | U24: =-SUMIF('APRIL - TB -'!H:H,EBIDTA!B24,'APRIL - TB -'!G:G) -> 0 | X24: Closing Stock of Finished goods
B25: Profit on sale of investments | C25: =M25-O25 -> 0 | E25: =O25-Q25 -> 0 | G25: =Q25-S25 -> 0 | I25: =S25-U25 -> 0 | K25: =U25 -> 0 | M25: =-SUMIF('AUGUST - TB'!H:H,EBIDTA!B25,'AUGUST - TB'!G:G) -> 0 | O25: =-SUMIF('JULY-TB'!H:H,EBIDTA!B25,'JULY-TB'!G:G) -> 0 | Q25: =-SUMIF('JUNE - TB -'!H:H,EBIDTA!B25,'JUNE - TB -'!G:G) -> 0 | S25: =-SUMIF('MAY- TB - '!H:H,EBIDTA!B25,'MAY- TB - '!E:E) -> 0 | U25: =-SUMIF('APRIL - TB -'!H:H,EBIDTA!B25,'APRIL - TB -'!G:G) -> 0 | X25: Net change in inventory | Y25: =(Y19+Y20)-(Y23+Y24) -> 32503962 | Z25: =(Z19+Z20)-(Z23+Z24) -> 31413765 | AA25: =(AA19+AA20)-(AA23+AA24) -> 20347861 | AB25: =(AB19+AB20)-(AB23+AB24) -> 34160369 | AC25: =(AC19+AC20)-(AC23+AC24) -> 34999374 | AF25: =AC25/10^7 -> 3.4999374 | AG25: =(AB25-AF25)/10^7 -> 3.4160366 | AH25: =(AA25-AB25)/10^7 -> -1.3812508 | AI25: =(Z25-AA25)/10^7 -> 1.1065904 | AJ25: =(Y25-Z25)/10^7 -> 0.10901962
B26: Sundry balance written off | C26: =M26-O26 -> 0 | E26: =O26-Q26 -> 0 | G26: =Q26-S26 -> 554332.08 | I26: =S26-U26 -> 0 | K26: =U26 -> 0 | M26: =-SUMIF('AUGUST - TB'!H:H,EBIDTA!B26,'AUGUST - TB'!G:G) -> 554332.08 | O26: =-SUMIF('JULY-TB'!H:H,EBIDTA!B26,'JULY-TB'!G:G) -> 554332.08 | Q26: =-SUMIF('JUNE - TB -'!H:H,EBIDTA!B26,'JUNE - TB -'!G:G) -> 554332.08 | S26: =-SUMIF('MAY- TB - '!H:H,EBIDTA!B26,'MAY- TB - '!E:E) -> 0 | U26: =-SUMIF('APRIL - TB -'!H:H,EBIDTA!B26,'APRIL - TB -'!G:G) -> 0
B27: Miscellaneous income | C27: =M27-O27 -> 0 | E27: =O27-Q27 -> 0 | G27: =Q27-S27 -> 0 | I27: =S27-U27 -> 0 | K27: =U27 -> 0 | M27: =-SUMIF('AUGUST - TB'!H:H,EBIDTA!B27,'AUGUST - TB'!G:G) -> 0 | O27: =-SUMIF('JULY-TB'!H:H,EBIDTA!B27,'JULY-TB'!G:G) -> 0 | Q27: =-SUMIF('JUNE - TB -'!H:H,EBIDTA!B27,'JUNE - TB -'!G:G) -> 0 | S27: =-SUMIF('MAY- TB - '!H:H,EBIDTA!B27,'MAY- TB - '!E:E) -> 0 | U27: =-SUMIF('APRIL - TB -'!H:H,EBIDTA!B27,'APRIL - TB -'!G:G) -> 0 | X27: Stores, Spares & Consumables
B28: Total Other income | C28: =SUM(C19:C27) -> 0 | D28: =C28/$C$30 -> 0 | E28: =SUM(E19:E27) -> 386687 | F28: =E28/$E$30 -> 0.0015490299 | G28: =SUM(G19:G27) -> 241260.67 | H28: =(G28/$G$30) -> 0.0012058345 | I28: =SUM(I19:I27) -> -200000 | J28: =(I28/$I$30) -> -0.00098095618 | K28: =SUM(K19:K27) -> 0 | L28: =(K28/$K$30) -> 0 | M28: =SUM(M19:M27) -> 427947.67 | N28: =M28/$M$30 -> 0.00037776225 | O28: =SUM(O19:O27) -> 427947.67 | P28: =O28/$O$30 -> 0.00051143208 | Q28: =SUM(Q19:Q27) -> 41260.67 | R28: =(Q28/$Q$30) -> 7.0274978e-05 | S28: =SUM(S19:S27) -> -200000 | T28: =(S28/$S$30) -> -0.00051672381 | U28: =SUM(U19:U27) -> 0 | V28: =(U28/$U$30) -> 0 | X28: Inventory at the beginning of the year:
B30: Total Turnover | C30: =C9+C12+C17+C28 -> 2.9608578e+08 | D30: =C30/$C$30 -> 1 | E30: =E9+E12+E17+E28 -> 2.4963171e+08 | F30: =E30/$E$30 -> 1 | G30: =G9+G12+G17+G28 -> 2.0007777e+08 | H30: =(G30/$G$30) -> 1 | I30: =I9+I12+I17+I28 -> 2.038827e+08 | J30: =(I30/$I$30) -> 1 | K30: =K9+K12+K17+K28 -> 1.8317126e+08 | L30: =(K30/$K$30) -> 1 | M30: =M9+M12+M17+M28 -> 1132849226 | N30: =M30/$M$30 -> 1 | O30: =O9+O12+O17+O28 -> 836763450 | P30: =(O30/$O$30) -> 1 | Q30: =Q9+Q12+Q17+Q28 -> 5.8713174e+08 | R30: =(Q30/$Q$30) -> 1 | S30: =S9+S12+S17+S28 -> 3.8705397e+08 | T30: =(S30/$S$30) -> 1 | U30: =U9+U12+U17+U28 -> 1.8317126e+08 | V30: =(U30/$U$30) -> 1 | X30: Opening Stock of Consumables | Y30: =Z30 -> 12898280 | Z30: =AA30 -> 12898280 | AA30: =AB30 -> 12898280 | AB30: =AC30 -> 12898280 | AC30: ='Stock Sheet - KPW'!O16 -> 12898280 | AF30: =(AC27-AC30)/10^7 -> -1.289828 | AG30: =(AB30-AC30)/10^7 -> 0 | AH30: =(AA30-AB30)/10^7 -> 0 | AI30: =(Z30-AA30)/10^7 -> 0
B31: Cost of Goods
B32: Cost of materials consumed | C32: =M32-O32 -> 1.7731068e+08 | D32: =C32/$C$30 -> 0.59884904 | E32: =O32-Q32 -> 1.7347574e+08 | F32: =E32/$E$30 -> 0.69492668 | G32: =Q32-S32 -> 1.2741941e+08 | H32: =(G32/$G$30) -> 0.63684941 | I32: =S32-U32 -> 98512251 | J32: =(I32/$I$30) -> 0.48318101 | K32: =U32 -> 87083536 | L32: =(K32/$K$30) -> 0.47542139 | M32: =Y15 -> 6.6380162e+08 | N32: =M32/$M$30 -> 0.5859576 | O32: =Z15 -> 4.8649093e+08 | P32: =O32/$O$30 -> 0.58139601 | Q32: =AA15 -> 3.130152e+08 | R32: =(Q32/$Q$30) -> 0.53312601 | S32: =AB15 -> 1.8559579e+08 | T32: =(S32/$S$30) -> 0.47950881 | U32: =AC15 -> 87083536 | V32: =(U32/$U$30) -> 0.47542139 | X32: Add: Purchase of Stores, Spares & Consumables | Y32: =SUMIF('AUGUST - TB'!H:H,EBIDTA!X32,'AUGUST - TB'!G:G) -> 18737647 | Z32: =SUMIF('JULY-TB'!H:H,EBIDTA!X32,'JULY-TB'!G:G) -> 14206510 | AA32: =SUMIF('JUNE - TB -'!H23:H1349,EBIDTA!X32,'JUNE - TB -'!G23:G1349) -> 10776091 | AB32: =SUMIF('MAY- TB - '!H23:H1339,EBIDTA!X32,'MAY- TB - '!G23:G1339) -> 7002670.9 | AC32: =SUMIF('APRIL - TB -'!H2:H1232,EBIDTA!X32,'APRIL - TB -'!G2:G1231) -> 3866573.4 | AF32: =(AC29-AC32)/10^7 -> -0.38665734 | AG32: =(AB32-AC32)/10^7 -> 0.31360974 | AH32: =(AA32-AB32)/10^7 -> 0.37734203 | AI32: =(Z32-AA32)/10^7 -> 0.34304185 | AJ32: 20.644672
B33: Purchase of stock-in-trade | C33: =M33-O33 -> 0 | D33: =C33/$C$30 -> 0 | E33: =O33-Q33 -> 0 | F33: =E33/$E$30 -> 0 | G33: =Q33-S33 -> 0 | H33: =(G33/$G$30) -> 0 | I33: =S33-U33 -> 0 | J33: =(I33/$I$30) -> 0 | K33: =U33 -> 0 | L33: =(K33/$K$30) -> 0 | M33: 0 | N33: =M33/$M$30 -> 0 | O33: 0 | P33: =O33/$O$30 -> 0 | Q33: 0 | R33: =(Q33/$Q$30) -> 0 | S33: 0 | T33: =(S33/$S$30) -> 0 | U33: 0 | V33: =(U33/$U$30) -> 0
B34: Changes in inventory of finished goods and work-in-progress | C34: =M34-O34 -> 1090196.2 | D34: =C34/$C$30 -> 0.0036820283 | E34: =O34-Q34 -> 11065904 | F34: =E34/$E$30 -> 0.044328919 | G34: =Q34-S34 -> -13812508 | H34: =(G34/$G$30) -> -0.069035697 | I34: =S34-U34 -> -839004.28 | J34: =(I34/$I$30) -> -0.0041151322 | K34: =U34 -> 34999374 | L34: =(K34/$K$30) -> 0.19107459 | M34: =Y25 -> 32503962 | N34: =M34/$M$30 -> 0.028692222 | O34: =Z25 -> 31413765 | P34: =O34/$O$30 -> 0.03754199 | Q34: =AA25 -> 20347861 | R34: =(Q34/$Q$30) -> 0.034656381 | S34: =AB25 -> 34160369 | T34: =(S34/$S$30) -> 0.08825738 | U34: =AC25 -> 34999374 | V34: =(U34/$U$30) -> 0.19107459 | X34: Less:
B35: Stores, Spares & Consumables | C35: =M35-O35 -> 3771955.4 | D35: =C35/$C$30 -> 0.012739401 | E35: =O35-Q35 -> 4435366.6 | F35: =E35/$E$30 -> 0.017767641 | G35: =Q35-S35 -> 5023463.8 | H35: =(G35/$G$30) -> 0.025107556 | I35: =S35-U35 -> 1896959.8 | J35: =(I35/$I$30) -> 0.0093041721 | K35: =U35 -> 829101.07 | L35: =(K35/$K$30) -> 0.0045263709 | M35: =Y36 -> 15956847 | N35: =M35/$M$30 -> 0.014085587 | O35: =Z36 -> 12184891 | P35: =O35/$O$30 -> 0.014561931 | Q35: =AA36 -> 7749524.6 | R35: =(Q35/$Q$30) -> 0.013198954 | S35: =AB36 -> 2726060.8 | T35: =(S35/$S$30) -> 0.0070431027 | U35: =AC36 -> 829101.07 | V35: =(U35/$U$30) -> 0.0045263709 | X35: Closing Stock of Consumables | Y35: ='Stock Sheet - KPW'!T16 -> 15679080 | Z35: ='Stock Sheet - KPW'!S16 -> 14919898 | AA35: ='Stock Sheet - KPW'!R16 -> 15924847 | AB35: =+'Stock Sheet - KPW'!Q16 -> 17174890 | AC35: ='Stock Sheet - KPW'!P16 -> 15935752 | AF35: =AC35/10^7 -> 1.5935752 | AG35: =(AB35-AC35)/10^7 -> 0.12391377 | AH35: =(AA35-AB35)/10^7 -> -0.12500434 | AI35: =(Z35-AA35)/10^7 -> -0.10049481 | AJ35: 20.644672
B36: Total Cost of goods | C36: =C32+C34+C35+C33 -> 1.8217283e+08 | D36: =C36/$C$30 -> 0.61527047 | E36: =E32+E34+E35+E33 -> 1.8897701e+08 | F36: =E36/$E$30 -> 0.75702324 | G36: =G32+G34+G35+G33 -> 1.1863036e+08 | H36: =(G36/$G$30) -> 0.59292127 | I36: =I32+I34+I35+I33 -> 99570207 | J36: =(I36/$I$30) -> 0.48837005 | K36: =K32+K34+K35+K33 -> 1.2291201e+08 | L36: =(K36/$K$30) -> 0.67102235 | M36: =M32+M34+M35+M33 -> 7.1226242e+08 | N36: =M36/$M$30 -> 0.62873541 | O36: =O32+O34+O35+O33 -> 5.3008959e+08 | P36: =O36/$O$30 -> 0.63349993 | Q36: =Q32+Q34+Q35+Q33 -> 3.4111258e+08 | R36: =(Q36/$Q$30) -> 0.58098134 | S36: =S32+S34+S35+S33 -> 2.2248222e+08 | T36: =(S36/$S$30) -> 0.57480929 | U36: =U32+U34+U35+U33 -> 1.2291201e+08 | V36: =(U36/$U$30) -> 0.67102235 | X36: Cost of Consumables | Y36: =Y30+Y32-Y35 -> 15956847 | Z36: =Z30+Z32-Z35 -> 12184891 | AA36: =AA30+AA32-AA35 -> 7749524.6 | AB36: =AB30+AB32-AB35 -> 2726060.8 | AC36: =AC30+AC32-AC35 -> 829101.07 | AF36: =AC36/10^7 -> 0.082910107 | AG36: =(AB36-AF36)/10^7 -> 0.27260608 | AH36: =(AA36-AB36)/10^7 -> 0.50234638 | AI36: =(Z36-AA36)/10^7 -> 0.44353666 | AJ36: =(Y36-Z36)/10^7 -> 0.37719554
B37: Employee benefit expenses
B38: Salaries, wages and bonus | C38: =M38-O38 -> 20556497 | E38: =O38-Q38 -> 15351917 | G38: =Q38-S38 -> 17889551 | I38: =S38-U38 -> 14699525 | K38: =U38 -> 15495083 | M38: =SUMIF('AUGUST - TB'!H:H,EBIDTA!B38,'AUGUST - TB'!G:G) -> 83992573 | O38: =SUMIF('JULY-TB'!H:H,EBIDTA!B38,'JULY-TB'!G:G) -> 63436076 | Q38: =SUMIF('JUNE - TB -'!H:H,EBIDTA!B38,'JUNE - TB -'!G:G) -> 48084159 | S38: =SUMIF('MAY- TB - '!H:H,EBIDTA!B38,'MAY- TB - '!G:G) -> 30194608 | U38: =SUMIF('APRIL - TB -'!H:H,EBIDTA!B38,'APRIL - TB -'!G:G) -> 15495083
B39: Contribution to provident and other funds | C39: =M39-O39 -> 793099 | E39: =O39-Q39 -> 715987 | G39: =Q39-S39 -> 645056 | I39: =S39-U39 -> 518741 | K39: =U39 -> 564270 | M39: =SUMIF('AUGUST - TB'!H:H,EBIDTA!B39,'AUGUST - TB'!G:G) -> 3237153 | O39: =SUMIF('JULY-TB'!H:H,EBIDTA!B39,'JULY-TB'!G:G) -> 2444054 | Q39: =SUMIF('JUNE - TB -'!H:H,EBIDTA!B39,'JUNE - TB -'!G:G) -> 1728067 | S39: =SUMIF('MAY- TB - '!H:H,EBIDTA!B39,'MAY- TB - '!G:G) -> 1083011 | U39: =SUMIF('APRIL - TB -'!H:H,EBIDTA!B39,'APRIL - TB -'!G:G) -> 564270
B40: Gratuity Expenses | C40: =M40-O40 -> 0 | E40: =O40-Q40 -> 0 | G40: =Q40-S40 -> 0 | I40: =S40-U40 -> 0 | K40: =U40 -> 0 | M40: =SUMIF('AUGUST - TB'!H:H,EBIDTA!B40,'AUGUST - TB'!G:G) -> 0 | O40: =SUMIF('JULY-TB'!H:H,EBIDTA!B40,'JULY-TB'!G:G) -> 0 | Q40: =SUMIF('JUNE - TB -'!H:H,EBIDTA!B40,'JUNE - TB -'!G:G) -> 0 | S40: =SUMIF('MAY- TB - '!H:H,EBIDTA!B40,'MAY- TB - '!G:G) -> 0 | U40: =SUMIF('APRIL - TB -'!H:H,EBIDTA!B40,'APRIL - TB -'!G:G) -> 0
B41: Staff welfare expenses | C41: =M41-O41 -> 621764.74 | E41: =O41-Q41 -> 233643 | G41: =Q41-S41 -> 759802 | I41: =S41-U41 -> 255704.24 | K41: =U41 -> 9522 | M41: =SUMIF('AUGUST - TB'!H:H,EBIDTA!B41,'AUGUST - TB'!G:G) -> 1880436 | O41: =SUMIF('JULY-TB'!H:H,EBIDTA!B41,'JULY-TB'!G:G) -> 1258671.2 | Q41: =SUMIF('JUNE - TB -'!H:H,EBIDTA!B41,'JUNE - TB -'!G:G) -> 1025028.2 | S41: =SUMIF('MAY- TB - '!H:H,EBIDTA!B41,'MAY- TB - '!G:G) -> 265226.24 | U41: =SUMIF('APRIL - TB -'!H:H,EBIDTA!B41,'APRIL - TB -'!G:G) -> 9522
B42: Labour charges | C42: =M42-O42 -> 8448378 | E42: =O42-Q42 -> 7287531.9 | G42: =Q42-S42 -> 5896886.8 | I42: =S42-U42 -> 5108656.4 | K42: =U42 -> 4542834 | M42: =SUMIF('AUGUST - TB'!H:H,EBIDTA!B42,'AUGUST - TB'!G:G) -> 31284287 | O42: =SUMIF('JULY-TB'!H:H,EBIDTA!B42,'JULY-TB'!G:G) -> 22835909 | Q42: =SUMIF('JUNE - TB -'!H:H,EBIDTA!B42,'JUNE - TB -'!G:G) -> 15548377 | S42: =SUMIF('MAY- TB - '!H:H,EBIDTA!B42,'MAY- TB - '!G:G) -> 9651490.4 | U42: =SUMIF('APRIL - TB -'!H:H,EBIDTA!B42,'APRIL - TB -'!G:G) -> 4542834
B43: Total Employee benefit expenses | C43: =SUM(C38:C42) -> 30419739 | D43: =C43/$C$30 -> 0.10273962 | E43: =SUM(E38:E42) -> 23589079 | F43: =E43/$E$30 -> 0.094495521 | G43: =SUM(G38:G42) -> 25191296 | H43: =(G43/$G$30) -> 0.12590752 | I43: =SUM(I38:I42) -> 20582626 | J43: =(I43/$I$30) -> 0.10095327 | K43: =SUM(K38:K42) -> 20611709 | L43: =(K43/$K$30) -> 0.11252698 | M43: =SUM(M38:M42) -> 1.2039445e+08 | N43: =M43/$M$30 -> 0.10627579 | O43: =SUM(O38:O42) -> 89974710 | P43: =O43/$O$30 -> 0.10752706 | Q43: =SUM(Q38:Q42) -> 66385631 | R43: =(Q43/$Q$30) -> 0.11306769 | S43: =SUM(S38:S42) -> 41194335 | T43: =(S43/$S$30) -> 0.10643047 | U43: =SUM(U38:U42) -> 20611709 | V43: =(U43/$U$30) -> 0.11252698
B44: Manufacturing Expenses
B45: Power and fuel | C45: =M45-O45 -> 5358995 | E45: =O45-Q45 -> 3174501 | G45: =Q45-S45 -> 4366664 | I45: =S45-U45 -> 4642624 | K45: =U45 -> 4652904 | M45: =SUMIF('AUGUST - TB'!H:H,EBIDTA!B45,'AUGUST - TB'!G:G) -> 22195688 | O45: =SUMIF('JULY-TB'!H:H,EBIDTA!B45,'JULY-TB'!G:G) -> 16836693 | Q45: =SUMIF('JUNE - TB -'!H:H,EBIDTA!B45,'JUNE - TB -'!G:G) -> 13662192 | S45: =SUMIF('MAY- TB - '!H:H,EBIDTA!B45,'MAY- TB - '!G:G) -> 9295528 | U45: =SUMIF('APRIL - TB -'!H:H,EBIDTA!B45,'APRIL - TB -'!G:G) -> 4652904
B46: Jobwork charges | C46: =M46-O46 -> 942445.98 | E46: =O46-Q46 -> 2235709.4 | G46: =Q46-S46 -> 14718245 | I46: =S46-U46 -> 26979617 | K46: =U46 -> 10974626 | M46: =SUMIF('AUGUST - TB'!H:H,EBIDTA!B46,'AUGUST - TB'!G:G) -> 55850644 | O46: =SUMIF('JULY-TB'!H:H,EBIDTA!B46,'JULY-TB'!G:G) -> 54908198 | Q46: =SUMIF('JUNE - TB -'!H:H,EBIDTA!B46,'JUNE - TB -'!G:G) -> 52672488 | S46: =SUMIF('MAY- TB - '!H:H,EBIDTA!B46,'MAY- TB - '!G:G) -> 37954244 | U46: =SUMIF('APRIL - TB -'!H:H,EBIDTA!B46,'APRIL - TB -'!G:G) -> 10974626
B47: Other Manufacturing Expenses | C47: =M47-O47 -> 1222751.7 | E47: =O47-Q47 -> 727506.6 | G47: =Q47-S47 -> 1008694.9 | I47: =S47-U47 -> 299882.86 | K47: =U47 -> 1789850.2 | M47: =SUMIF('AUGUST - TB'!H:H,EBIDTA!B47,'AUGUST - TB'!G:G) -> 5048686.3 | O47: =SUMIF('JULY-TB'!H:H,EBIDTA!B47,'JULY-TB'!G:G) -> 3825934.6 | Q47: =SUMIF('JUNE - TB -'!H:H,EBIDTA!B47,'JUNE - TB -'!G:G) -> 3098428 | S47: =SUMIF('MAY- TB - '!H:H,EBIDTA!B47,'MAY- TB - '!G:G) -> 2089733.1 | U47: =SUMIF('APRIL - TB -'!H:H,EBIDTA!B47,'APRIL - TB -'!G:G) -> 1789850.2
B48: Total Manufacturing Expenses | C48: =SUM(C45:C47) -> 7524192.7 | D48: =C48/$C$30 -> 0.025412206 | E48: =SUM(E45:E47) -> 6137717 | F48: =E48/$E$30 -> 0.024587088 | G48: =SUM(G45:G47) -> 20093604 | H48: =(G48/$G$30) -> 0.10042897 | I48: =SUM(I45:I47) -> 31922124 | J48: =(I48/$I$30) -> 0.15657102 | K48: =SUM(K45:K47) -> 17417381 | L48: =(K48/$K$30) -> 0.095087954 | M48: =SUM(M45:M47) -> 83095018 | N48: =M48/$M$30 -> 0.073350465 | O48: =SUM(O45:O47) -> 75570825 | P48: =O48/$O$30 -> 0.090313248 | Q48: =SUM(Q45:Q47) -> 69433108 | R48: =(Q48/$Q$30) -> 0.11825814 | S48: =SUM(S45:S47) -> 49339505 | T48: =(S48/$S$30) -> 0.12747448 | U48: =SUM(U45:U47) -> 17417381 | V48: =(U48/$U$30) -> 0.095087954
B49: Selling and Distribution Expenses
B50: Advertising and sales promotion expense | C50: =M50-O50 -> 0 | E50: =O50-Q50 -> 18000 | G50: =Q50-S50 -> 0 | I50: =S50-U50 -> 0 | K50: =U50 -> 0 | M50: =SUMIF('AUGUST - TB'!H:H,EBIDTA!B50,'AUGUST - TB'!G:G) -> 18000 | O50: =SUMIF('JULY-TB'!H:H,EBIDTA!B50,'JULY-TB'!G:G) -> 18000 | Q50: =SUMIF('JUNE - TB -'!H:H,EBIDTA!B50,'JUNE - TB -'!G:G) -> 0 | S50: =SUMIF('MAY- TB - '!H:H,EBIDTA!B50,'MAY- TB - '!G:G) -> 0 | U50: =SUMIF('APRIL - TB -'!H:H,EBIDTA!B50,'APRIL - TB -'!G:G) -> 0
B51: Travelling expense | C51: =M51-O51 -> 4940 | E51: =O51-Q51 -> -120788 | G51: =Q51-S51 -> 43944 | I51: =S51-U51 -> 16273 | K51: =U51 -> 486596 | M51: =SUMIF('AUGUST - TB'!H:H,EBIDTA!B51,'AUGUST - TB'!G:G) -> 430965 | O51: =SUMIF('JULY-TB'!H:H,EBIDTA!B51,'JULY-TB'!G:G) -> 426025 | Q51: =SUMIF('JUNE - TB -'!H:H,EBIDTA!B51,'JUNE - TB -'!G:G) -> 546813 | S51: =SUMIF('MAY- TB - '!H:H,EBIDTA!B51,'MAY- TB - '!G:G) -> 502869 | U51: =SUMIF('APRIL - TB -'!H:H,EBIDTA!B51,'APRIL - TB -'!G:G) -> 486596
B52: Brokerage & commission | C52: =M52-O52 -> 0 | E52: =O52-Q52 -> 0 | G52: =Q52-S52 -> 0 | I52: =S52-U52 -> 0 | K52: =U52 -> 0 | M52: =SUMIF('AUGUST - TB'!H:H,EBIDTA!B52,'AUGUST - TB'!G:G) -> 0 | O52: =SUMIF('JULY-TB'!H:H,EBIDTA!B52,'JULY-TB'!G:G) -> 0 | Q52: =SUMIF('JUNE - TB -'!H:H,EBIDTA!B52,'JUNE - TB -'!G:G) -> 0 | S52: =SUMIF('MAY- TB - '!H:H,EBIDTA!B52,'MAY- TB - '!G:G) -> 0 | U52: =SUMIF('APRIL - TB -'!H:H,EBIDTA!B52,'APRIL - TB -'!G:G) -> 0
B53: Conveyance, vehicle running and traveling expenses | C53: =M53-O53 -> 268975 | E53: =O53-Q53 -> 541081 | G53: =Q53-S53 -> 343372.2 | I53: =S53-U53 -> 256995 | K53: =U53 -> 63313 | M53: =SUMIF('AUGUST - TB'!H:H,EBIDTA!B53,'AUGUST - TB'!G:G) -> 1473736.2 | O53: =SUMIF('JULY-TB'!H:H,EBIDTA!B53,'JULY-TB'!G:G) -> 1204761.2 | Q53: =SUMIF('JUNE - TB -'!H:H,EBIDTA!B53,'JUNE - TB -'!G:G) -> 663680.2 | S53: =SUMIF('MAY- TB - '!H:H,EBIDTA!B53,'MAY- TB - '!G:G) -> 320308 | U53: =SUMIF('APRIL - TB -'!H:H,EBIDTA!B53,'APRIL - TB -'!G:G) -> 63313
B54: Freight Outward and C & F Charges | C54: =M54-O54 -> 2223454.9 | E54: =O54-Q54 -> 5791198.5 | G54: =Q54-S54 -> 5316801.5 | I54: =S54-U54 -> 1077057.1 | K54: =U54 -> 3599137.5 | M54: =SUMIF('AUGUST - TB'!H:H,EBIDTA!B54,'AUGUST - TB'!G:G) -> 18007650 | O54: =SUMIF('JULY-TB'!H:H,EBIDTA!B54,'JULY-TB'!G:G) -> 15784195 | Q54: =SUMIF('JUNE - TB -'!H:H,EBIDTA!B54,'JUNE - TB -'!G:G) -> 9992996.1 | S54: =SUMIF('MAY- TB - '!H:H,EBIDTA!B54,'MAY- TB - '!G:G) -> 4676194.6 | U54: =SUMIF('APRIL - TB -'!H:H,EBIDTA!B54,'APRIL - TB -'!G:G) -> 3599137.5
B55: Total Selling and Distribution Expenses | C55: =SUM(C50:C54) -> 2497369.9 | D55: =C55/$C$30 -> 0.0084346164 | E55: =SUM(E50:E54) -> 6229491.5 | F55: =E55/$E$30 -> 0.024954728 | G55: =SUM(G50:G54) -> 5704117.7 | H55: =(G55/$G$30) -> 0.028509503 | I55: =SUM(I50:I54) -> 1350325.1 | J55: =(I55/$I$30) -> 0.0066230486 | K55: =SUM(K50:K54) -> 4149046.5 | L55: =(K55/$K$30) -> 0.022651187 | M55: =SUM(M50:M54) -> 19930351 | N55: =M55/$M$30 -> 0.017593119 | O55: =SUM(O50:O54) -> 17432981 | P55: =O55/$O$30 -> 0.020833822 | Q55: =SUM(Q50:Q54) -> 11203489 | R55: =(Q55/$Q$30) -> 0.01908173 | S55: =SUM(S50:S54) -> 5499371.6 | T55: =(S55/$S$30) -> 0.014208281 | U55: =SUM(U50:U54) -> 4149046.5 | V55: =(U55/$U$30) -> 0.022651187
B56: Administrative Expenses
B57: Insurance | C57: =M57-O57 -> 0 | E57: =O57-Q57 -> 164606 | G57: =Q57-S57 -> -317080.2 | I57: =S57-U57 -> 183400 | K57: =U57 -> 526199 | M57: =SUMIF('AUGUST - TB'!H:H,EBIDTA!B57,'AUGUST - TB'!G:G) -> 557124.8 | O57: =SUMIF('JULY-TB'!H:H,EBIDTA!B57,'JULY-TB'!G:G) -> 557124.8 | Q57: =SUMIF('JUNE - TB -'!H:H,EBIDTA!B57,'JUNE - TB -'!G:G) -> 392518.8 | S57: =SUMIF('MAY- TB - '!H:H,EBIDTA!B57,'MAY- TB - '!G:G) -> 709599 | U57: =SUMIF('APRIL - TB -'!H:H,EBIDTA!B57,'APRIL - TB -'!G:G) -> 526199
B58: Other Administrative Expenses | C58: =M58-O58 -> 2370449.1 | E58: =O58-Q58 -> 2747544.7 | G58: =Q58-S58 -> 6037504.6 | I58: =S58-U58 -> 4439632 | K58: =U58 -> 1975224.4 | M58: =SUMIF('AUGUST - TB'!H:H,EBIDTA!B58,'AUGUST - TB'!G:G) -> 17570355 | O58: =SUMIF('JULY-TB'!H:H,EBIDTA!B58,'JULY-TB'!G:G) -> 15199906 | Q58: =SUMIF('JUNE - TB -'!H:H,EBIDTA!B58,'JUNE - TB -'!G:G) -> 12452361 | S58: =SUMIF('MAY- TB - '!H:H,EBIDTA!B58,'MAY- TB - '!G:G) -> 6414856.5 | U58: =SUMIF('APRIL - TB -'!H:H,EBIDTA!B58,'APRIL - TB -'!G:G) -> 1975224.4
B59: Common Expenses | C59: =M59-O59 -> 0 | E59: =O59-Q59 -> 0 | G59: =Q59-S59 -> 0 | I59: =S59-U59 -> 0 | K59: =U59 -> 0 | M59: =SUMIF('AUGUST - TB'!H:H,EBIDTA!B59,'AUGUST - TB'!G:G) -> 0
B60: Exchange Rate Difference | C60: =M60-O60 -> -1876018.6 | E60: =O60-Q60 -> -2844374.8 | G60: =Q60-S60 -> -19478596 | I60: =S60-U60 -> -4668659.6 | K60: =U60 -> -3924537.4 | M60: =SUMIF('AUGUST - TB'!H:H,EBIDTA!B60,'AUGUST - TB'!G:G) -> -32792186 | O60: =SUMIF('JULY-TB'!H:H,EBIDTA!B60,'JULY-TB'!G:G) -> -30916168 | Q60: =SUMIF('JUNE - TB -'!H:H,EBIDTA!B60,'JUNE - TB -'!G:G) -> -28071793 | S60: =SUMIF('MAY- TB - '!H:H,EBIDTA!B60,'MAY- TB - '!G:G) -> -8593197.1 | U60: =SUMIF('APRIL - TB -'!H:H,EBIDTA!B60,'APRIL - TB -'!G:G) -> -3924537.4
B61: Total Administrative Expenses | C61: =SUM(C57:C60) -> 494430.56 | D61: =C61/$C$30 -> 0.0016698896 | E61: =SUM(E57:E60) -> 67775.95 | F61: =E61/$E$30 -> 0.00027150376 | G61: =SUM(G57:G60) -> -13758171 | H61: =(G61/$G$30) -> -0.068764119 | I61: =SUM(I57:I60) -> -45627.6 | J61: =(I61/$I$30) -> -0.00022379338 | K61: =SUM(K57:K60) -> -1423114 | L61: =(K61/$K$30) -> -0.0077693083 | M61: =SUM(M57:M60) -> -14664706 | N61: =M61/$M$30 -> -0.012944976 | O61: =SUM(O57:O60) -> -15159137 | P61: =O61/$O$30 -> -0.018116395 | Q61: =SUM(Q57:Q60) -> -15226913 | R61: =(Q61/$Q$30) -> -0.025934406 | S61: =SUM(S57:S60) -> -1468741.6 | T61: =(S61/$S$30) -> -0.0037946688 | U61: =SUM(U57:U60) -> -1423114 | V61: =(U61/$U$30) -> -0.0077693083
B63: Total Cost of goods sold | C63: =C36+C43+C48+C55+C61 -> 2.2310857e+08 | D63: =C63/$C$30 -> 0.75352679 | E63: =E36+E43+E48+E55+E61 -> 2.2500107e+08 | F63: =(E63/$E$30) -> 0.90133208 | G63: =G36+G43+G48+G55+G61 -> 1.5586121e+08 | H63: =(G63/$G$30) -> 0.77900315 | I63: =I36+I43+I48+I55+I61 -> 1.5337965e+08 | J63: =(I63/$I$30) -> 0.7522936 | K63: =K36+K43+K48+K55+K61 -> 1.6366703e+08 | L63: =(K63/$K$30) -> 0.89351916 | M63: =M36+M43+M48+M55+M61 -> 9.2101754e+08 | N63: =M63/$M$30 -> 0.81300981 | O63: =O36+O43+O48+O55+O61 -> 6.9790897e+08 | P63: =(O63/$O$30) -> 0.83405767 | Q63: =Q36+Q43+Q48+Q55+Q61 -> 4.729079e+08 | R63: =(Q63/$Q$30) -> 0.8054545 | S63: =S36+S43+S48+S55+S61 -> 3.1704669e+08 | T63: =(S63/$S$30) -> 0.81912786 | U63: =U36+U43+U48+U55+U61 -> 1.6366703e+08 | V63: =(U63/$U$30) -> 0.89351916
B65: EBDITA | C65: =C30-C63 -> 72977210 | D65: =C65/$C$30 -> 0.24647321 | E65: =E30-E63 -> 24630643 | F65: =(E65/$E$30) -> 0.098667924 | G65: =G30-G63 -> 44216557 | H65: =(G65/$G$30) -> 0.22099685 | I65: =I30-I63 -> 50503050 | J65: =(I65/$I$30) -> 0.2477064 | K65: =K30-K63 -> 19504230 | L65: =(K65/$K$30) -> 0.10648084 | M65: =M30-M63 -> 2.1183169e+08 | N65: =M65/$M$30 -> 0.18699019 | O65: =O30-O63 -> 1.3885448e+08 | P65: =(O65/$O$30) -> 0.16594233 | Q65: =Q30-Q63 -> 1.1422384e+08 | R65: =(Q65/$Q$30) -> 0.1945455 | S65: =S30-S63 -> 70007280 | T65: =(S65/$S$30) -> 0.18087214 | U65: =U30-U63 -> 19504230 | V65: =(U65/$U$30) -> 0.10648084

Sheet Stock Sheet - KPW
C1: Stock sheet from Apr-24 to Mar-24
B3: Raw Material | O3: 26-27
B4: op.Stock | C4: 45383 | D4: MAY | E4: 45444 | F4: july.24 | G4: 45505 | H4: 45536 | I4: 45566 | J4: 45597 | K4: 45627 | L4: 45658 | M4: 45689 | N4: 45717 | O4: Op,stock 01.04.26 | P4: 46113 | Q4: MAY.26 | R4: 46174 | S4: July. 26 | T4: 46235 | U4: 46266 | V4: 46296 | W4: 46327 | X4: 46357 | Y4: 46388 | Z4: 46419 | AA4: 46447
C5: 40885502 | D5: 44690515 | E5: 59879823 | F5: 58718633 | G5: 60867855 | H5: 58655299 | I5: 49973632 | J5: 52326500 | K5: 51493051 | L5: 44011790 | M5: 61248778 | N5: 59069210 | O5: 78409106 | P5: 1.1669902e+08 | Q5: 78548384 | R5: 63882998 | S5: 84892889 | T5: 1.1168642e+08
B8: Finish Material
B9: op.Stock | C9: 45383 | D9: MAY | E9: 45444 | F9: july.24 | G9: 45505 | H9: 45536 | I9: 45566 | J9: 45597 | K9: 45627 | L9: 45658 | M9: 45689 | N9: 45717 | O9: Op,stock 01.04.26 | P9: 46113 | Q9: MAY.26 | R9: 46174 | S9: July. 26 | T9: 46235 | U9: 46266 | V9: 46296 | W9: 46327 | X9: 46357 | Y9: 46388 | Z9: 46419 | AA9: 46447
C10: 76985434 | D10: 73682752 | E10: 84421689 | F10: 87270138 | G10: 98165150 | H10: 1.1481412e+08 | I10: 109540747 | J10: 92932583 | K10: 1.0876437e+08 | L10: 1.1692796e+08 | M10: 1.203563e+08 | N10: 1.2409052e+08 | O10: 2.0644672e+08 | P10: 1.7144735e+08 | Q10: 1.7228635e+08 | R10: 1.8609886e+08 | S10: 1.7503296e+08 | T10: 1.7394276e+08
B13: Stores Spares
B14: op.Stock | C14: 45383 | D14: MAY | E14: 45444 | F14: july.24 | G14: 45505 | H14: 45536 | I14: 45566 | J14: 45597 | K14: 45627 | L14: 45658 | M14: 45689 | N14: 45717 | O14: Op,stock 01.04.26 | P14: 46113 | Q14: MAY.26 | R14: 46174 | S14: July. 26 | T14: 46235 | U14: 46266 | V14: 46296 | W14: 46327 | X14: 46357 | Y14: 46388 | Z14: 46419 | AA14: 46447
C16: 11212574 | D16: 11398463 | E16: 11966098 | F16: 11807893 | G16: 12281943 | H16: 11290716 | I16: 11937270 | J16: 11725252 | K16: 11462964 | L16: 10929459 | M16: 11096995 | N16: 10973564 | O16: 12898280 | P16: 15935752 | Q16: 17174890 | R16: 15924847 | S16: 14919898 | T16: 15679080

Sheet APRIL - TB -
A1: DOWNLOAD AS ON 11-08-26
A2: Perticular | B2: Opening | C2: Debit | D2: Credit | E2: Closing | F2: Provision | G2: Total | H2: Head
A3: Packing Forwading & Cartage Expense | B3: 0 | C3: 100 | D3: 0 | E3: 100 | G3: =E3+F3 -> 100 | H3: Add: Purchase expenses
A4: Freight Inward Expense (RCM) | B4: 0 | C4: 177110 | D4: 0 | E4: 177110 | G4: =E4+F4 -> 177110 | H4: Add: Purchase expenses
A5: Freight Inward Expense (With GST) | B5: 0 | C5: 62503.7 | D5: 0 | E5: 62503.7 | G5: =E5+F5 -> 62503.7 | H5: Add: Purchase expenses
A6: Purchase Withinstate- Packing Material | B6: 0 | C6: 1127244.8 | D6: 0 | E6: 1127244.8 | G6: =E6+F6 -> 1127244.8 | H6: Add: Purchase of packing materials
A7: Purchase Raw Material - Direct Import | B7: 0 | C7: 27922270 | D7: 0 | E7: 27922270 | G7: =E7+F7 -> 27922270 | H7: Add: Purchase of raw materials
A8: Purchase Interstate - Raw Material | B8: 0 | C8: 2231224.4 | D8: 0 | E8: 2231224.4 | G8: =E8+F8 -> 2231224.4 | H8: Add: Purchase of raw materials
A9: Purchase Withinstate - Raw Material | B9: 0 | C9: 73330942 | D9: 0 | E9: 73330942 | G9: =E9+F9 -> 73330942 | H9: Add: Purchase of raw materials
A10: Purchase Raw Material - High Seas | B10: 0 | C10: 17158400 | D10: 0 | E10: 17158400 | G10: =E10+F10 -> 17158400 | H10: Add: Purchase of raw materials
A11: Purchase Interstate- Stores, Spares & Consumable | B11: 0 | C11: 1436233.5 | D11: 0 | E11: 1436233.5 | G11: =E11+F11 -> 1436233.5 | H11: Add: Purchase of Stores, Spares & Consumables
A12: Purchase Return - Stores, Spares & Consumable | B12: 0 | C12: 54130 | D12: 0 | E12: 54130 | G12: =E12+F12 -> 54130 | H12: Add: Purchase of Stores, Spares & Consumables
A13: Purchase Withinstate- Stores, Spares & Consumable | B13: 0 | C13: 2376209.9 | D13: 0 | E13: 2376209.9 | G13: =E13+F13 -> 2376209.9 | H13: Add: Purchase of Stores, Spares & Consumables
A14: Bank Charges - Export Collection | B14: 0 | C14: 350726.34 | D14: 1669.95 | E14: 349056.39 | G14: =E14+F14 -> 349056.39 | H14: Bank Charges & Commission
... A23: Factoring Charges | B23: 0 | C23: 208120.64 | D23: 0 | E23: 208120.64 | G23: =E23+F23 -> 208120.64 | H23: Bank Charges & Commission
A24: P.F. Admin. Charge | B24: 0 | C24: 26644 | D24: 26644 | E24: 0 | F24: 21728 | G24: =E24+F24 -> 21728 | H24: Contribution to provident and other funds
A25: P.F. Contribution - Employer | B25: 0 | C25: 665196 | D25: 665196 | E25: 0 | F25: 542542 | G25: =E25+F25 -> 542542 | H25: Contribution to provident and other funds
A26: Conveyance Expenses | B26: 0 | C26: 5017 | D26: 0 | E26: 5017 | G26: =E26+F26 -> 5017 | H26: Conveyance, vehicle running and traveling expenses
A27: Petrol & Diesel Expense - Other Vehicles | B27: 0 | C27: 58296 | D27: 0 | E27: 58296 | G27: =E27+F27 -> 58296 | H27: Conveyance, vehicle running and traveling expenses
A28: Exchange Rate Difference - Debtors | B28: 0 | C28: 25161872 | D28: 3916167.8 | E28: 21245704 | F28: -25161872 | G28: =E28+F28 -> -3916167.8 | H28: Exchange Rate Difference
A29: Loading & Unloading Expense | B29: 0 | C29: 23680 | D29: 0 | E29: 23680 | F29: 100000 | G29: =E29+F29 -> 123680 | H29: Freight Outward and C & F Charges
A30: C & F Charges - Export | B30: 0 | C30: 972314.89 | D30: 0 | E30: 972314.89 | F30: 500000 | G30: =E30+F30 -> 1472314.9 | H30: Freight Outward and C & F Charges
A31: Discount -Early Payment - Sales | B31: 0 | C31: 16073.88 | D31: 0 | E31: 16073.88 | G31: =E31+F31 -> 16073.88 | H31: Freight Outward and C & F Charges
A32: Freight Outward Expense - Export | B32: 0 | C32: 298850 | D32: =12556110.47 -> 12556110 | E32: =C32-D32 -> -12257260 | F32: -10733989 | G32: =E32-F32 -> -1523271.5 | H32: Freight Outward and C & F Charges
A33: Freight Outward Expense (RCM) | B33: 0 | C33: 529500 | D33: 0 | E33: 529500 | G33: =E33+F33 -> 529500 | H33: Freight Outward and C & F Charges
A34: Freight Outward Expense (With GST) | B34: 0 | C34: 2102133.6 | D34: 1200 | E34: 2100933.6 | F34: 500000 | G34: =E34+F34 -> 2600933.6 | H34: Freight Outward and C & F Charges
A35: Insurance Expense - Ecgc - Pc | B35: 0 | C35: 379906.61 | D35: 0 | E35: 379906.61 | G35: =E35+F35 -> 379906.61 | H35: Freight Outward and C & F Charges
A36: Insurance Expenses - Other | B36: 0 | C36: 342799 | D36: 0 | E36: 342799 | F36: =2200800/12 -> 183400 | G36: =E36+F36 -> 526199 | H36: Insurance
A37: Accrued Interest -FDR | B37: 35987 | C37: 0 | D37: 0 | E37: 35987 | G37: =E37+F37 -> 35987 | H37: Interest Expense - Other
A38: Interest Expense - EPC | B38: 0 | C38: 2289146.4 | D38: 14014.17 | E38: 2275132.2 | G38: =E38+F38 -> 2275132.2 | H38: Interest Expense - Other
A39: Interest Expense - Factoring | B39: 0 | C39: 562528.38 | D39: 171590.28 | E39: 390938.1 | G39: =E39+F39 -> 390938.1 | H39: Interest Expense - Other
A40: Interest Expense - PCFC | B40: 0 | C40: 1081387.6 | D40: 0 | E40: 1081387.6 | G40: =E40+F40 -> 1081387.6 | H40: Interest Expense - Other
A41: Interest Expense - Other | B41: 0 | C41: 137378.57 | D41: 56823 | E41: 80555.57 | G41: =E41+F41 -> 80555.57 | H41: Interest Expense - Other
A42: Interest to MSME Vendors Payable | B42: -56823 | C42: 56823 | D42: 0 | E42: 0 | G42: =E42+F42 -> 0 | H42: Interest Expense - Other
A43: Interest Expense - Term Loan | B43: 0 | C43: 2113806 | D43: 0 | E43: 2113806 | G43: =E43+F43 -> 2113806 | H43: Interest on Term Loan
A44: Interest Expense - Working Capital | B44: 0 | C44: 1096147 | D44: 0 | E44: 1096147 | G44: =E44+F44 -> 1096147 | H44: Interest on Working Capital & Term Loan
A45: Job Charges | B45: 0 | C45: 11030011 | D45: 55384.56 | E45: 10974626 | G45: =E45+F45 -> 10974626 | H45: Jobwork charges
A46: Labour Charges | B46: 0 | C46: 129973 | D46: 129973 | E46: 0 | F46: =4436290+106544 -> 4542834 | G46: =E46+F46 -> 4542834 | H46: Labour charges
A47: Duty Clearing Account | B47: 0 | C47: 5144478 | D47: 5144478 | E47: 0 | G47: =E47+F47 -> 0 | H47: Not Applicable
A48: Income Tax Ay 2014-15 | B48: 1607000 | C48: 0 | D48: 0 | E48: 1607000 | G48: =E48+F48 -> 1607000 | H48: Not Applicable
A49: Income Tax Ay 2016-17 | B49: 2200000 | C49: 0 | D49: 0 | E49: 2200000 | G49: =E49+F49 -> 2200000 | H49: Not Applicable
A50: Income Tax Refund Receivable | B50: 108787 | C50: 0 | D50: 0 | E50: 108787 | G50: =E50+F50 -> 108787 | H50: Not Applicable
A51: TCS On Purchase 20-21 | B51: 0 | C51: 0 | D51: 0 | E51: 0 | G51: =E51+F51 -> 0 | H51: Not Applicable
A52: TCS On Purchase 21-22 | B52: 0 | C52: 0 | D52: 0 | E52: 0 | G52: =E52+F52 -> 0 | H52: Not Applicable
A53: TCS On Purchase 22-23 | B53: -18585.94 | C53: 0 | D53: 0 | E53: -18585.94 | G53: =E53+F53 -> -18585.94 | H53: Not Applicable
A54: TCS On Purchase 23-24 | B54: 1151 | C54: 0 | D54: 0 | E54: 1151 | G54: =E54+F54 -> 1151 | H54: Not Applicable
A55: Tcs On Purchase 24-25 | B55: 30286.3 | C55: 0 | D55: 0 | E55: 30286.3 | G55: =E55+F55 -> 30286.3 | H55: Not Applicable
A56: Tcs On Purchase 25-26 | B56: 1335.22 | C56: 0 | D56: 0 | E56: 1335.22 | G56: =E56+F56 -> 1335.22 | H56: Not Applicable
A57: TDS Receivable 2021-22 | B57: 0 | C57: 0 | D57: 0 | E57: 0 | G57: =E57+F57 -> 0 | H57: Not Applicable
A58: TDS Receivable 2022-23 | B58: -418818 | C58: 0 | D58: 0 | E58: -418818 | G58: =E58+F58 -> -418818 | H58: Not Applicable
... A1196: GIDC Gandhinagar | B1196: 31469 | C1196: 96272 | D1196: 96272 | E1196: 31469 | G1196: =E1196+F1196 -> 31469 | H1196: Other Administrative Expenses
A1197: Repairs & Maintenance Exp - Plant & Machinery | B1197: 0 | C1197: 989850.25 | D1197: 0 | E1197: 989850.25 | F1197: 300000 | G1197: =E1197+F1197 -> 1289850.2 | H1197: Other Manufacturing Expenses
A1198: Power Expense | B1198: 0 | C1198: 0 | D1198: 0 | E1198: 0 | F1198: 4652904 | G1198: =E1198+F1198 -> 4652904 | H1198: Power and fuel
A1199: Allowance - Books & Periodicals | B1199: 0 | C1199: 67427 | D1199: 0 | E1199: 67427 | G1199: =E1199+F1199 -> 67427 | H1199: Salaries, wages and bonus
A1200: Allowance - Canteen | B1200: 0 | C1200: 1542965.6 | D1200: 143840 | E1200: 1399125.6 | G1200: =E1200+F1200 -> 1399125.6 | H1200: Salaries, wages and bonus
A1201: Allowance - Children Education & Hostel | B1201: 0 | C1201: 4381 | D1201: 0 | E1201: 4381 | G1201: =E1201+F1201 -> 4381 | H1201: Salaries, wages and bonus
A1202: Allowance - Conveyance | B1202: 0 | C1202: 200 | D1202: 0 | E1202: 200 | G1202: =E1202+F1202 -> 200 | H1202: Salaries, wages and bonus
A1203: Allowance - House Rent | B1203: 0 | C1203: 3242936 | D1203: 0 | E1203: 3242936 | G1203: =E1203+F1203 -> 3242936 | H1203: Salaries, wages and bonus
A1204: Allowance - Leave Travels | B1204: 0 | C1204: 309015 | D1204: 0 | E1204: 309015 | G1204: =E1204+F1204 -> 309015 | H1204: Salaries, wages and bonus
A1205: Allowance - Medical | B1205: 0 | C1205: 144545 | D1205: 0 | E1205: 144545 | G1205: =E1205+F1205 -> 144545 | H1205: Salaries, wages and bonus
A1206: Allowance - Other | B1206: 0 | C1206: 175494 | D1206: 0 | E1206: 175494 | G1206: =E1206+F1206 -> 175494 | H1206: Salaries, wages and bonus
A1207: Allowance - Special | B1207: 0 | C1207: 295640 | D1207: 0 | E1207: 295640 | G1207: =E1207+F1207 -> 295640 | H1207: Salaries, wages and bonus
A1208: Allowance - Transport | B1208: 0 | C1208: 108046 | D1208: 0 | E1208: 108046 | G1208: =E1208+F1208 -> 108046 | H1208: Salaries, wages and bonus
A1209: Allowance - Uniform / Attire | B1209: 0 | C1209: 322078 | D1209: 0 | E1209: 322078 | G1209: =E1209+F1209 -> 322078 | H1209: Salaries, wages and bonus
A1210: Allowance - Washing | B1210: 0 | C1210: 1125313.3 | D1210: 0 | E1210: 1125313.3 | G1210: =E1210+F1210 -> 1125313.3 | H1210: Salaries, wages and bonus
A1211: Att. Bonus (Salary Part) | B1211: 0 | C1211: 90300 | D1211: 0 | E1211: 90300 | G1211: =E1211+F1211 -> 90300 | H1211: Salaries, wages and bonus
A1212: Employers Contribution to ESI | B1212: 0 | C1212: 321950 | D1212: 321950 | E1212: 0 | F1212: 259572 | G1212: =E1212+F1212 -> 259572 | H1212: Salaries, wages and bonus
A1213: Incentive Expense - Attendence | B1213: 0 | C1213: 533841 | D1213: 0 | E1213: 533841 | G1213: =E1213+F1213 -> 533841 | H1213: Salaries, wages and bonus
A1214: Incentive Expense - Production | B1214: 0 | C1214: 1953493 | D1214: 0 | E1214: 1953493 | G1214: =E1214+F1214 -> 1953493 | H1214: Salaries, wages and bonus
A1215: Other Deduction | B1215: 0 | C1215: 0 | D1215: 29771 | E1215: -29771 | G1215: =E1215+F1215 -> -29771 | H1215: Salaries, wages and bonus
A1216: Salaries Expense | B1216: 0 | C1216: 5079018 | D1216: 0 | E1216: 5079018 | G1216: =E1216+F1216 -> 5079018 | H1216: Salaries, wages and bonus
A1217: Salary - Arrears | B1217: 0 | C1217: 29564 | D1217: 0 | E1217: 29564 | G1217: =E1217+F1217 -> 29564 | H1217: Salaries, wages and bonus
A1218: Salary - Over Time | B1218: 0 | C1218: 384865 | D1218: 0 | E1218: 384865 | G1218: =E1218+F1218 -> 384865 | H1218: Salaries, wages and bonus
A1219: Sales - Interstate - Manufactured Goods | B1219: 0 | C1219: 0 | D1219: 2132234 | E1219: -2132234 | G1219: =E1219+F1219 -> -2132234 | H1219: Sale of Finished Goods
A1220: Sales - Within State Manufactured Goods | B1220: 0 | C1220: 0 | D1220: 1.0377948e+08 | E1220: -1.0377948e+08 | G1220: =E1220+F1220 -> -1.0377948e+08 | H1220: Sale of Finished Goods
A1221: Sales - Direct Export - Mfg - U/B | B1221: 0 | C1221: 0 | D1221: 44967399 | E1221: -44967399 | G1221: =E1221+F1221 -> -44967399 | H1221: Sale of Finished Goods
A1222: Sales - Direct Export - Mfg - U/R | B1222: 0 | C1222: 0 | D1222: 28149042 | E1222: -28149042 | G1222: =E1222+F1222 -> -28149042 | H1222: Sale of Finished Goods
A1223: Sales - Kasez - Trading - U/B | B1223: 0 | C1223: 0 | D1223: 60900 | E1223: -60900 | G1223: =E1223+F1223 -> -60900 | H1223: Sale of traded goods
A1224: Sales - Within State - Traded Goods | B1224: 0 | C1224: 0 | D1224: 4047207.4 | E1224: -4047207.4 | G1224: =E1224+F1224 -> -4047207.4 | H1224: Sale of Traded Goods
... A1228: Travelling Expense | B1228: 0 | C1228: 486596 | D1228: 0 | E1228: 486596 | G1228: =E1228+F1228 -> 486596 | H1228: Travelling expense
A1229: House Keeping Expense | B1229: 0 | C1229: 0 | D1229: 0 | E1229: 0 | F1229: 500000 | G1229: =E1229+F1229 -> 500000 | H1229: Other Manufacturing Expenses
A1230: C & F Charges - Import | B1230: 0 | C1230: 0 | D1230: 0 | E1230: 0 | F1230: 3363752 | G1230: =E1230+F1230 -> 3363752 | H1230: Add: Purchase expenses
E1232: =SUBTOTAL(9,E3:E1227) -> -486596 | G1232: =SUBTOTAL(9,G3:G1227) -> -3311499
E1233: =#REF! -> #REF! | O1233: April | P1233: May | Q1233: June | R1233: July
E1234: =E1233-E1232 -> #REF!
K1235: Hermione Renewables Private Limited | O1235: 27206 | P1235: 30000 | Q1235: 26611 | R1235: 30000 | T1235: Power procurement consulting fees
K1236: Surya Enegy Kutch | O1236: 683676 | P1236: 626931 | Q1236: 703380 | R1236: 635731
D1237: =SUBTOTAL(9,D3:D1230) -> 1.6009985e+09 | E1237: =SUBTOTAL(9,E3:E1229) -> 5.6391582e-07 | F1237: =SUBTOTAL(9,F3:F1229) -> -23792881 | G1237: =SUBTOTAL(9,G3:G1229) -> -2324903 | K1237: Sunscrap Solar Recycle Llp | O1237: 365575 | P1237: 200000 | Q1237: 200000 | R1237: 200000
K1238: UGVCL | O1238: 3576447 | P1238: 3367773 | Q1238: 3474593 | R1238: 3401688
O1240: =SUBTOTAL(9,O1235:O1239) -> 4652904 | P1240: =SUBTOTAL(9,P1235:P1239) -> 4224704 | Q1240: =SUBTOTAL(9,Q1235:Q1239) -> 4404584 | R1240: =SUBTOTAL(9,R1235:R1239) -> 4267419 | S1240: =SUM(O1240:R1240) -> 17549611

Sheet MAY- TB - 
A1: Perticular | B1: Opening | C1: Debit | D1: Credit | E1: Closing | F1: Provision | G1: Total | H1: Head | I1: April | J1: Net May | K1: sales - stock mov.
A2: Duty Clearing Account | B2: 0 | C2: 5144478 | D2: 5144478 | E2: 0 | G2: =E2+F2 -> 0 | H2: Not Applicable
A3: Income Tax Ay 2014-15 | B3: 1607000 | C3: 0 | D3: 0 | E3: 1607000 | G3: =E3+F3 -> 1607000 | H3: Not Applicable
A4: Income Tax Ay 2016-17 | B4: 2200000 | C4: 0 | D4: 0 | E4: 2200000 | G4: =E4+F4 -> 2200000 | H4: Not Applicable
A5: Income Tax Refund Receivable | B5: 108787 | C5: 0 | D5: 0 | E5: 108787 | G5: =E5+F5 -> 108787 | H5: Not Applicable
A6: TCS On Purchase 20-21 | B6: 0 | C6: 0 | D6: 0 | E6: 0 | G6: =E6+F6 -> 0 | H6: Not Applicable
A7: TCS On Purchase 21-22 | B7: 0 | C7: 0 | D7: 0 | E7: 0 | G7: =E7+F7 -> 0 | H7: Not Applicable
A8: TCS On Purchase 22-23 | B8: -18585.94 | C8: 0 | D8: 0 | E8: -18585.94 | G8: =E8+F8 -> -18585.94 | H8: Not Applicable
A9: TCS On Purchase 23-24 | B9: 1151 | C9: 0 | D9: 0 | E9: 1151 | G9: =E9+F9 -> 1151 | H9: Not Applicable
A10: Tcs On Purchase 24-25 | B10: 30286.3 | C10: 0 | D10: 0 | E10: 30286.3 | G10: =E10+F10 -> 30286.3 | H10: Not Applicable
A11: Tcs On Purchase 25-26 | B11: 1335.22 | C11: 0 | D11: 0 | E11: 1335.22 | G11: =E11+F11 -> 1335.22 | H11: Not Applicable
A12: TDS Receivable 2021-22 | B12: 0 | C12: 0 | D12: 0 | E12: 0 | G12: =E12+F12 -> 0 | H12: Not Applicable
A13: TDS Receivable 2022-23 | B13: -418818 | C13: 0 | D13: 0 | E13: -418818 | G13: =E13+F13 -> -418818 | H13: Not Applicable
... A383: Round Off - Purchases | B383: 0 | C383: 51.62 | D383: 52.4 | E383: -0.78 | G383: =E383+F383 -> -0.78 | H383: Not Applicable
A384: C & F Charges - Import | B384: 0 | C384: 6302314.7 | D384: 0 | E384: 6302314.7 | F384: 115969 | G384: =E384+F384 -> 6418283.7 | H384: Add: Purchase expenses
A385: Freight Inward Expense (RCM) | B385: 0 | C385: 396540 | D385: 35000 | E385: 361540 | G385: =E385+F385 -> 361540 | H385: Add: Purchase expenses
A386: Freight Inward Expense (With GST) | B386: 0 | C386: 107838.05 | D386: 200 | E386: 107638.05 | G386: =E386+F386 -> 107638.05 | H386: Add: Purchase expenses
A387: Advance Licence Fee Expense | B387: 0 | C387: 9500 | D387: 0 | E387: 9500 | G387: =E387+F387 -> 9500 | H387: Not Applicable
A388: Factory Expense | B388: 0 | C388: 251879 | D388: 0 | E388: 251879 | G388: =E388+F388 -> 251879 | H388: Other Administrative Expenses
A389: Labour Charges | B389: 0 | C389: 4566263.4 | D389: 129973 | E389: 4436290.4 | F389: =5215200 -> 5215200 | G389: =E389+F389 -> 9651490.4 | H389: Labour charges
A390: Power Expense | B390: 0 | C390: 4870824 | D390: 0 | E390: 4870824 | F390: 4424704 | G390: =E390+F390 -> 9295528 | H390: Power and fuel
A391: Rent Expense - Colony | B391: 0 | C391: 1265900 | D391: 0 | E391: 1265900 | G391: =E391+F391 -> 1265900 | H391: Other Administrative Expenses
A392: Rent Expenses - Machineries | B392: 0 | C392: 600000 | D392: 0 | E392: 600000 | G392: =E392+F392 -> 600000 | H392: Other Administrative Expenses
A393: Exchange Rate Difference - Creditor | B393: 0 | C393: 313632 | D393: 30486.47 | E393: 283145.53 | G393: =E393+F393 -> 283145.53 | H393: Exchange Rate Difference
A394: Job Charges | B394: 0 | C394: 38009628 | D394: 55384.56 | E394: 37954244 | G394: =E394+F394 -> 37954244 | H394: Jobwork charges
A395: Loading & Unloading Expense | B395: 0 | C395: 143950 | D395: 0 | E395: 143950 | G395: =E395+F395 -> 143950 | H395: Freight Outward and C & F Charges
A396: Water Charges | B396: 0 | C396: 254890 | D396: 96272 | E396: 158618 | G396: =E396+F396 -> 158618 | H396: Other Administrative Expenses
A397: Repairs & Maintenance Exp - Plant & Machinery | B397: 0 | C397: 1375818.1 | D397: 0 | E397: 1375818.1 | F397: 200000 | G397: =E397+F397 -> 1575818.1 | H397: Other Manufacturing Expenses
A398: Purchase Raw Material - Direct Import | B398: 0 | C398: 27922270 | D398: 0 | E398: 27922270 | G398: =E398+F398 -> 27922270 | H398: Add: Purchase of raw materials
A399: Purchase Withinstate- Packing Material | B399: 0 | C399: 2830055.7 | D399: 0 | E399: 2830055.7 | G399: =E399+F399 -> 2830055.7 | H399: Add: Purchase of packing materials
A400: Purchase In Transit | B400: 0 | C400: 0 | D400: 36870023 | E400: -36870023 | G400: =E400+F400 -> -36870023 | H400: Not Applicable
A401: Purchase Interstate - Raw Material | B401: 0 | C401: 3134409.4 | D401: 0 | E401: 3134409.4 | G401: =E401+F401 -> 3134409.4 | H401: Add: Purchase of raw materials
A402: Purchase Withinstate - Raw Material | B402: 0 | C402: 1.2875342e+08 | D402: 0 | E402: 1.2875342e+08 | G402: =E402+F402 -> 1.2875342e+08 | H402: Add: Purchase of raw materials
A403: Purchase - Urd - Stores, Spares & Consumable | B403: 0 | C403: 7813 | D403: 0 | E403: 7813 | G403: =E403+F403 -> 7813 | H403: Add: Purchase of Stores, Spares & Consumables
A404: Purchase Interstate- Stores, Spares & Consumable | B404: 0 | C404: 2418895.5 | D404: 0 | E404: 2418895.5 | G404: =E404+F404 -> 2418895.5 | H404: Add: Purchase of Stores, Spares & Consumables
A405: Purchase Return - Stores, Spares & Consumable | B405: 0 | C405: 54130 | D405: 1700 | E405: 52430 | G405: =E405+F405 -> 52430 | H405: Add: Purchase of Stores, Spares & Consumables
A406: Purchase Withinstate- Stores, Spares & Consumable | B406: 0 | C406: 4523532.4 | D406: 0 | E406: 4523532.4 | G406: =E406+F406 -> 4523532.4 | H406: Add: Purchase of Stores, Spares & Consumables
A407: Purchase Raw Material - High Seas | B407: 0 | C407: 17158400 | D407: 0 | E407: 17158400 | G407: =E407+F407 -> 17158400 | H407: Add: Purchase of raw materials
A408: Conveyance Expenses | B408: 0 | C408: 61288 | D408: 0 | E408: 61288 | G408: =E408+F408 -> 61288 | H408: Conveyance, vehicle running and traveling expenses
A409: Corporate social responsibility | B409: 0 | C409: 24880 | D409: 0 | E409: 24880 | G409: =E409+F409 -> 24880 | H409: Other Administrative Expenses
... A429: Vehicle Hire Charges - With Gst | B429: 0 | C429: 160000 | D429: 0 | E429: 160000 | G429: =E429+F429 -> 160000 | H429: Conveyance, vehicle running and traveling expenses
A430: P.F. Admin. Charge | B430: 0 | C430: 48372 | D430: 26644 | E430: 21728 | F430: 19956 | G430: =E430+F430 -> 41684 | H430: Contribution to provident and other funds
A431: P.F. Contribution - Employer | B431: 0 | C431: 1207738 | D431: 665196 | E431: 542542 | F431: 498785 | G431: =E431+F431 -> 1041327 | H431: Contribution to provident and other funds
A432: Allowance - Books & Periodicals | B432: 0 | C432: 123451 | D432: 0 | E432: 123451 | G432: =E432+F432 -> 123451 | H432: Salaries, wages and bonus | I432: =SUMIF('APRIL - TB -'!A:A,'MAY- TB - '!A432,'APRIL - TB -'!E:E) -> 67427 | J432: =E432-I432 -> 56024
A433: Allowance - Canteen | B433: 0 | C433: 2985079.7 | D433: 258768 | E433: 2726311.7 | G433: =E433+F433 -> 2726311.7 | H433: Salaries, wages and bonus | I433: =SUMIF('APRIL - TB -'!A:A,'MAY- TB - '!A433,'APRIL - TB -'!E:E) -> 1399125.6 | J433: =E433-I433 -> 1327186.1
A434: Allowance - Children Education & Hostel | B434: 0 | C434: 8242 | D434: 0 | E434: 8242 | G434: =E434+F434 -> 8242 | H434: Salaries, wages and bonus | I434: =SUMIF('APRIL - TB -'!A:A,'MAY- TB - '!A434,'APRIL - TB -'!E:E) -> 4381 | J434: =E434-I434 -> 3861
A435: Allowance - Conveyance | B435: 0 | C435: 400 | D435: 0 | E435: 400 | G435: =E435+F435 -> 400 | H435: Salaries, wages and bonus | I435: =SUMIF('APRIL - TB -'!A:A,'MAY- TB - '!A435,'APRIL - TB -'!E:E) -> 200 | J435: =E435-I435 -> 200
A436: Allowance - House Rent | B436: 0 | C436: 6257154 | D436: 0 | E436: 6257154 | G436: =E436+F436 -> 6257154 | H436: Salaries, wages and bonus | I436: =SUMIF('APRIL - TB -'!A:A,'MAY- TB - '!A436,'APRIL - TB -'!E:E) -> 3242936 | J436: =E436-I436 -> 3014218
A437: Allowance - Leave Travels | B437: 0 | C437: 580083 | D437: 0 | E437: 580083 | G437: =E437+F437 -> 580083 | H437: Salaries, wages and bonus | I437: =SUMIF('APRIL - TB -'!A:A,'MAY- TB - '!A437,'APRIL - TB -'!E:E) -> 309015 | J437: =E437-I437 -> 271068
A438: Allowance - Medical | B438: 0 | C438: 276156 | D438: 0 | E438: 276156 | G438: =E438+F438 -> 276156 | H438: Salaries, wages and bonus | I438: =SUMIF('APRIL - TB -'!A:A,'MAY- TB - '!A438,'APRIL - TB -'!E:E) -> 144545 | J438: =E438-I438 -> 131611
A439: Allowance - Other | B439: 0 | C439: 321180 | D439: 0 | E439: 321180 | G439: =E439+F439 -> 321180 | H439: Salaries, wages and bonus | I439: =SUMIF('APRIL - TB -'!A:A,'MAY- TB - '!A439,'APRIL - TB -'!E:E) -> 175494 | J439: =E439-I439 -> 145686
A440: Allowance - Special | B440: 0 | C440: 566368 | D440: 0 | E440: 566368 | G440: =E440+F440 -> 566368 | H440: Salaries, wages and bonus | I440: =SUMIF('APRIL - TB -'!A:A,'MAY- TB - '!A440,'APRIL - TB -'!E:E) -> 295640 | J440: =E440-I440 -> 270728
A441: Allowance - Transport | B441: 0 | C441: 196387 | D441: 0 | E441: 196387 | G441: =E441+F441 -> 196387 | H441: Salaries, wages and bonus | I441: =SUMIF('APRIL - TB -'!A:A,'MAY- TB - '!A441,'APRIL - TB -'!E:E) -> 108046 | J441: =E441-I441 -> 88341
A442: Allowance - Uniform / Attire | B442: 0 | C442: 609432 | D442: 0 | E442: 609432 | G442: =E442+F442 -> 609432 | H442: Salaries, wages and bonus | I442: =SUMIF('APRIL - TB -'!A:A,'MAY- TB - '!A442,'APRIL - TB -'!E:E) -> 322078 | J442: =E442-I442 -> 287354
A443: Allowance - Vehicle Maintenance | B443: 0 | C443: 10000 | D443: 0 | E443: 10000 | G443: =E443+F443 -> 10000 | H443: Salaries, wages and bonus | I443: =SUMIF('APRIL - TB -'!A:A,'MAY- TB - '!A443,'APRIL - TB -'!E:E) -> 0 | J443: =E443-I443 -> 10000
... A445: Att. Bonus (Salary Part) | B445: 0 | C445: 171450 | D445: 0 | E445: 171450 | G445: =E445+F445 -> 171450 | H445: Salaries, wages and bonus | I445: =SUMIF('APRIL - TB -'!A:A,'MAY- TB - '!A445,'APRIL - TB -'!E:E) -> 90300 | J445: =E445-I445 -> 81150
A446: Employers Contribution to ESI | B446: 0 | C446: 581522 | D446: 321950 | E446: 259572 | F446: 239694 | G446: =E446+F446 -> 499266 | H446: Salaries, wages and bonus | I446: =SUMIF('APRIL - TB -'!A:A,'MAY- TB - '!A446,'APRIL - TB -'!E:E) -> 0 | J446: =E446-I446 -> 259572
A447: Incentive Expense - Attendence | B447: 0 | C447: 1180256 | D447: 0 | E447: 1180256 | G447: =E447+F447 -> 1180256 | H447: Salaries, wages and bonus | I447: =SUMIF('APRIL - TB -'!A:A,'MAY- TB - '!A447,'APRIL - TB -'!E:E) -> 533841 | J447: =E447-I447 -> 646415
A448: Incentive Expense - Production | B448: 0 | C448: 3924466 | D448: 0 | E448: 3924466 | G448: =E448+F448 -> 3924466 | H448: Salaries, wages and bonus | I448: =SUMIF('APRIL - TB -'!A:A,'MAY- TB - '!A448,'APRIL - TB -'!E:E) -> 1953493 | J448: =E448-I448 -> 1970973
A449: Other Deduction | B449: 0 | C449: 0 | D449: 55771 | E449: -55771 | G449: =E449+F449 -> -55771 | H449: Salaries, wages and bonus | I449: =SUMIF('APRIL - TB -'!A:A,'MAY- TB - '!A449,'APRIL - TB -'!E:E) -> -29771 | J449: =E449-I449 -> -26000
A450: Salaries Expense | B450: 0 | C450: 9785172 | D450: 0 | E450: 9785172 | G450: =E450+F450 -> 9785172 | H450: Salaries, wages and bonus | I450: =SUMIF('APRIL - TB -'!A:A,'MAY- TB - '!A450,'APRIL - TB -'!E:E) -> 5079018 | J450: =E450-I450 -> 4706154
A451: Salary - Arrears | B451: 0 | C451: 66158 | D451: 0 | E451: 66158 | G451: =E451+F451 -> 66158 | H451: Salaries, wages and bonus | I451: =SUMIF('APRIL - TB -'!A:A,'MAY- TB - '!A451,'APRIL - TB -'!E:E) -> 29564 | J451: =E451-I451 -> 36594
A452: Salary - Over Time | B452: 0 | C452: 769212.5 | D452: 0 | E452: 769212.5 | G452: =E452+F452 -> 769212.5 | H452: Salaries, wages and bonus | I452: =SUMIF('APRIL - TB -'!A:A,'MAY- TB - '!A452,'APRIL - TB -'!E:E) -> 384865 | J452: =E452-I452 -> 384347.5
A453: Canteen Expense - Factory | B453: 0 | C453: 368305.24 | D453: 133060 | E453: 235245.24 | G453: =E453+F453 -> 235245.24 | H453: Staff welfare expenses
A454: Medical Expense | B454: 0 | C454: 29981 | D454: 0 | E454: 29981 | G454: =E454+F454 -> 29981 | H454: Staff welfare expenses
A455: Bank Charges - Export Collection | B455: 0 | C455: 506563.8 | D455: 1669.95 | E455: 504893.85 | G455: =E455+F455 -> 504893.85 | H455: Bank Charges & Commission
A456: Bank Charges - Inspection | B456: 0 | C456: 29500 | D456: 0 | E456: 29500 | G456: =E456+F456 -> 29500 | H456: Bank Charges & Commission
A457: Bank Charges - Export | B457: 0 | C457: 11254.8 | D457: 0 | E457: 11254.8 | G457: =E457+F457 -> 11254.8 | H457: Bank Charges & Commission
A458: Bank Charges - Export LC Advising | B458: 0 | C458: 2360 | D458: 0 | E458: 2360 | G458: =E458+F458 -> 2360 | H458: Bank Charges & Commission
A459: Bank Charges - Import | B459: 0 | C459: 71282.12 | D459: 0 | E459: 71282.12 | G459: =E459+F459 -> 71282.12 | H459: Bank Charges & Commission
A460: Bank Charges - LC | B460: 0 | C460: 2920 | D460: 0 | E460: 2920 | G460: =E460+F460 -> 2920 | H460: Bank Charges & Commission
A461: Bank Charges - Postage & Swift | B461: 0 | C461: 6000 | D461: 0 | E461: 6000 | G461: =E461+F461 -> 6000 | H461: Bank Charges & Commission
A462: Bank Charges - Processing Fees | B462: 0 | C462: 2360 | D462: 0 | E462: 2360 | G462: =E462+F462 -> 2360 | H462: Bank Charges & Commission
A463: Bank Charges- Others | B463: 0 | C463: 843629.25 | D463: 708677.28 | E463: 134951.97 | G463: =E463+F463 -> 134951.97 | H463: Bank Charges & Commission
A464: Exchange Rate Difference - Debtors | B464: 0 | C464: 25162830 | D464: 8899417.8 | E464: 16263413 | F464: -25161872 | G464: =E464+F464 -> -8898459.5 | H464: Exchange Rate Difference
A465: Exchange Rate Difference - Finance | B465: 0 | C465: 22116.86 | D465: 0 | E465: 22116.86 | G465: =E465+F465 -> 22116.86 | H465: Exchange Rate Difference
A466: Interest Expense - Term Loan | B466: 0 | C466: 4242539 | D466: 0 | E466: 4242539 | G466: =E466+F466 -> 4242539 | H466: Interest on Term Loan
A467: Factoring Charges | B467: 0 | C467: 261835.84 | D467: 0 | E467: 261835.84 | G467: =E467+F467 -> 261835.84 | H467: Bank Charges & Commission
A468: Interest Expense - EPC | B468: 0 | C468: 4626218.5 | D468: 129875.02 | E468: 4496343.5 | G468: =E468+F468 -> 4496343.5 | H468: Interest Expense - Other
A469: Interest Expense - Factoring | B469: 0 | C469: 1594988.9 | D469: 842849.76 | E469: 752139.18 | G469: =E469+F469 -> 752139.18 | H469: Interest Expense - Other
A470: Interest Expense - PCFC | B470: 0 | C470: 2094632.1 | D470: 0 | E470: 2094632.1 | G470: =E470+F470 -> 2094632.1 | H470: Interest Expense - Other
A471: Interest Expense - Working Capital | B471: 0 | C471: 2067437 | D471: 0 | E471: 2067437 | G471: =E471+F471 -> 2067437 | H471: Interest on Working Capital & Term Loan
A472: Interest Expense - Other | B472: 0 | C472: 271895.84 | D472: 56823 | E472: 215072.84 | G472: =E472+F472 -> 215072.84 | H472: Interest Expense - Other
A473: Audit Fees - Statutory Audit | B473: 0 | C473: 0 | D473: 500000 | E473: -500000 | F473: 500000 | G473: =E473+F473 -> 0 | H473: Other Administrative Expenses
A474: GST Expenses | B474: 0 | C474: 271.67 | D474: 0 | E474: 271.67 | G474: =E474+F474 -> 271.67 | H474: Not Applicable
A475: Interest On TDS | B475: 0 | C475: 890 | D475: 0 | E475: 890 | G475: =E475+F475 -> 890 | H475: Not Applicable
A476: Stamp Duty Expense | B476: 0 | C476: 2162641 | D476: 0 | E476: 2162641 | G476: =E476+F476 -> 2162641 | H476: Other Administrative Expenses
A477: Insurance Expenses - Other | B477: 0 | C477: 342799 | D477: 0 | E477: 342799 | F477: =2200800/12+183400 -> 366800 | G477: =E477+F477 -> 709599 | H477: Insurance
A478: Legal Expense | B478: 0 | C478: 3820 | D478: 0 | E478: 3820 | G478: =E478+F478 -> 3820 | H478: Other Administrative Expenses
A479: Professional & Consultancy Fees | B479: 0 | C479: 792788.9 | D479: 243750 | E479: 549038.9 | G479: =E479+F479 -> 549038.9 | H479: Other Administrative Expenses
A480: C & F Charges - Export | B480: 0 | C480: 2110569.3 | D480: 0 | E480: 2110569.3 | G480: =E480+F480 -> 2110569.3 | H480: Freight Outward and C & F Charges
A481: Discount & Rate Difference - Sales | B481: 0 | C481: 68300.73 | D481: 0 | E481: 68300.73 | G481: =E481+F481 -> 68300.73 | H481: Sale of Finished Goods | I481: =SUMIF('APRIL - TB -'!A:A,'MAY- TB - '!A481,'APRIL - TB -'!E:E) -> 0 | J481: =E481-I481 -> 68300.73 | L481: =J481-K481 -> 68300.73
A482: Discount -Early Payment - Sales | B482: 0 | C482: 16073.88 | D482: 0 | E482: 16073.88 | G482: =E482+F482 -> 16073.88 | H482: Freight Outward and C & F Charges
A483: Export related Certification Charges | B483: 0 | C483: 2036.06 | D483: 708 | E483: 1328.06 | G483: =E483+F483 -> 1328.06 | H483: Other Administrative Expenses
A484: Freight Outward Expense - Export | B484: 0 | C484: 994350 | D484: =13955372.74 -> 13955373 | E484: =C484-D484 -> -12961023 | F484: -10733989 | G484: =E484-F484 -> -2227033.7 | H484: Freight Outward and C & F Charges
A485: Freight Outward Expense (RCM) | B485: 0 | C485: 845000 | D485: 0 | E485: 845000 | G485: =E485+F485 -> 845000 | H485: Freight Outward and C & F Charges
A486: Freight Outward Expense (With GST) | B486: 0 | C486: 3010198.7 | D486: 4200 | E486: 3005998.7 | G486: =E486+F486 -> 3005998.7 | H486: Freight Outward and C & F Charges
A487: Fumigation Charges | B487: 0 | C487: 23800 | D487: 0 | E487: 23800 | G487: =E487+F487 -> 23800 | H487: Freight Outward and C & F Charges
A488: Ground Rent Charges | B488: 0 | C488: 11457.6 | D488: 0 | E488: 11457.6 | G488: =E488+F488 -> 11457.6 | H488: Freight Outward and C & F Charges
A489: Insurance Expense - Ecgc - Pc | B489: 0 | C489: 776350.38 | D489: 0 | E489: 776350.38 | G489: =E489+F489 -> 776350.38 | H489: Freight Outward and C & F Charges
...

Sheet JUNE - TB -
A1: Perticular | B1: Opening | C1: Debit | D1: Credit | E1: Closing | F1: Provision | G1: Total | H1: Head
A2: TDS Receivable 2022-23 | B2: -418818 | C2: 0 | D2: 0 | E2: -418818 | G2: =E2+F2 -> -418818 | H2: Not Applicable
A3: TDS Receivable 2023-24 | B3: 66480 | C3: 0 | D3: 0 | E3: 66480 | G3: =E3+F3 -> 66480 | H3: Not Applicable
A4: Tds Receivable 2024-25 | B4: 1767704.8 | C4: 0 | D4: 0 | E4: 1767704.8 | G4: =E4+F4 -> 1767704.8 | H4: Not Applicable
A5: Tds Receivable 2025-26 | B5: 1324336.4 | C5: 1788.8 | D5: 0 | E5: 1326125.2 | G5: =E5+F5 -> 1326125.2 | H5: Not Applicable
A6: Tds Receivable 2026-27 | B6: 0 | C6: 695424.7 | D6: 0 | E6: 695424.7 | G6: =E6+F6 -> 695424.7 | H6: Not Applicable
A7: Bank FDR BOB 73280300000558 | B7: 2176060 | C7: 0 | D7: 0 | E7: 2176060 | G7: =E7+F7 -> 2176060 | H7: Not Applicable
A8: Bank Fdr Bob 73280300001203 | B8: 2589775 | C8: 0 | D8: 0 | E8: 2589775 | G8: =E8+F8 -> 2589775 | H8: Not Applicable
A9: Bank FDR BOB 73280300001224 | B9: 6100000 | C9: 0 | D9: 6177119 | E9: -77119 | G9: =E9+F9 -> -77119 | H9: Not Applicable
A10: Bank Fdr Bob 73280300001261 | B10: 60017754 | C10: 0 | D10: 60142043 | E10: -124289 | G10: =E10+F10 -> -124289 | H10: Not Applicable
A11: Bank FDR The Karnataka Bank Ltd - 0021152400022801 | B11: 2300953 | C11: 33543 | D11: 0 | E11: 2334496 | G11: =E11+F11 -> 2334496 | H11: Not Applicable
A12: Bank Fdr The Karnataka Bank Ltd - 021152600003001 | B12: 50000000 | C12: 0 | D12: 532910 | E12: 49467090 | G12: =E12+F12 -> 49467090 | H12: Not Applicable
A13: Bank Fdr The Karnataka Bank Ltd - 021152600005001 | B13: 13000000 | C13: 0 | D13: 153952 | E13: 12846048 | G13: =E13+F13 -> 12846048 | H13: Not Applicable
... A116: Avira Naturals Pvt Ltd- Sales | B116: 0 | C116: 0 | D116: 0 | E116: 0 | G116: =E116+F116 -> 0 | H116: Not Applicable
A117: Accrued Interest -FDR | B117: 35987 | C117: 0 | D117: 0 | E117: 35987 | G117: =E117+F117 -> 35987 | H117: Interest Expense - Other | I117: =#REF! -> #REF! | J117: =G117-I117 -> #REF!
A118: Bhagwati Polyweave Private Limited | B118: -2088.7 | C118: 0 | D118: 0 | E118: -2088.7 | G118: =E118+F118 -> -2088.7 | H118: Not Applicable
A119: Bhagwati Products | B119: 0 | C119: 0 | D119: 0 | E119: 0 | G119: =E119+F119 -> 0 | H119: Not Applicable
A120: PI Industries Limited - 24AABCP2183M2ZA | B120: 675 | C120: 0 | D120: 0 | E120: 675 | G120: =E120+F120 -> 675 | H120: Not Applicable
A121: PI Industries Limited - 24AABCP2183M3Z9 | B121: 4692.88 | C121: 0 | D121: 0 | E121: 4692.88 | G121: =E121+F121 -> 4692.88 | H121: Not Applicable
A122: PI Polyblendz Private Limited | B122: 1789930 | C122: 0 | D122: 1300965 | E122: 488965 | G122: =E122+F122 -> 488965 | H122: Not Applicable
A123: Plastene India ltd - HO-Sales | B123: 0 | C123: 0 | D123: 0 | E123: 0 | G123: =E123+F123 -> 0 | H123: Not Applicable
A124: Plastene India ltd - Unit 1-Sales | B124: -2.677367e+08 | C124: 3.9899803e+08 | D124: 3.8207263e+08 | E124: -2.508113e+08 | G124: =E124+F124 -> -2.508113e+08 | H124: Not Applicable
A125: Plastene India ltd - Unit 2-Sales | B125: 1.1687861e+09 | C125: 95743361 | D125: 7700 | E125: 1.2645218e+09 | G125: =E125+F125 -> 1.2645218e+09 | H125: Not Applicable
A126: Plastene India ltd - Unit 6-Sales | B126: 4.3894615e+08 | C126: 0 | D126: 0 | E126: 4.3894615e+08 | G126: =E126+F126 -> 4.3894615e+08 | H126: Not Applicable
A127: Plastene Polyfilms Ltd-Sales | B127: 14316309 | C127: 49175816 | D127: 9000000 | E127: 54492125 | G127: =E127+F127 -> 54492125 | H127: Not Applicable
A128: Polytech International Pvt. Ltd | B128: 0 | C128: 0 | D128: 0 | E128: 0 | G128: =E128+F128 -> 0 | H128: Not Applicable
A129: Raajratna Metal Industries Limited | B129: 0 | C129: 138296 | D129: 138296 | E129: 0 | G129: =E129+F129 -> 0 | H129: Not Applicable
... A345: Round Off - Purchases | B345: 0 | C345: 86.97 | D345: 81.7 | E345: 5.27 | G345: =E345+F345 -> 5.27 | H345: Not Applicable
A346: C & F Charges - Import | B346: 0 | C346: 6428818.5 | D346: 0 | E346: 6428818.5 | F346: 216988 | G346: =E346+F346 -> 6645806.5 | H346: Add: Purchase expenses
A347: Freight Inward Expense (RCM) | B347: 0 | C347: 531840 | D347: 35000 | E347: 496840 | G347: =E347+F347 -> 496840 | H347: Add: Purchase expenses
A348: Freight Inward Expense (With GST) | B348: 0 | C348: 145339.39 | D348: 200 | E348: 145139.39 | G348: =E348+F348 -> 145139.39 | H348: Add: Purchase expenses
A349: Advance Licence Fee Expense | B349: 0 | C349: 26500 | D349: 0 | E349: 26500 | G349: =E349+F349 -> 26500 | H349: Not Applicable
A350: Factory Expense | B350: 0 | C350: 341749 | D350: 0 | E350: 341749 | G350: =E350+F350 -> 341749 | H350: Other Administrative Expenses | I350: =VLOOKUP(A350,'[1]JUNE - TB -'!$A:$G,7,0) -> 341749 | J350: =G350-I350 -> 0
A351: Labour Charges | B351: 0 | C351: 15692281 | D351: 143904 | E351: 15548377 | G351: =E351+F351 -> 15548377 | H351: Labour charges
A352: Power Expense | B352: 0 | C352: 12340121 | D352: 0 | E352: 12340121 | F352: 1322071 | G352: =E352+F352 -> 13662192 | H352: Power and fuel
A353: Rent Expense - Colony | B353: 0 | C353: 3887100 | D353: 0 | E353: 3887100 | G353: =E353+F353 -> 3887100 | H353: Other Administrative Expenses | J353: =G353-I353 -> 3887100
A354: Rent Expenses - Machineries | B354: 0 | C354: 1450000 | D354: 0 | E354: 1450000 | G354: =E354+F354 -> 1450000 | H354: Other Administrative Expenses | J354: =G354-I354 -> 1450000
A355: Exchange Rate Difference - Creditor | B355: 0 | C355: 313632 | D355: 30486.47 | E355: 283145.53 | G355: =E355+F355 -> 283145.53 | H355: Exchange Rate Difference
A356: Job Charges | B356: 0 | C356: 52727873 | D356: 55384.56 | E356: 52672488 | G356: =E356+F356 -> 52672488 | H356: Jobwork charges
A357: Loading & Unloading Expense | B357: 0 | C357: 181710 | D357: 0 | E357: 181710 | G357: =E357+F357 -> 181710 | H357: Freight Outward and C & F Charges
A358: Water Charges | B358: 0 | C358: 644249 | D358: 96272 | E358: 547977 | G358: =E358+F358 -> 547977 | H358: Other Administrative Expenses | J358: =G358-I358 -> 547977
A359: Repairs & Maintenance Exp - Plant & Machinery | B359: 0 | C359: 1622151.9 | D359: 0 | E359: 1622151.9 | G359: =E359+F359 -> 1622151.9 | H359: Other Manufacturing Expenses
A360: Purchase Raw Material - Direct Import | B360: 0 | C360: 27922270 | D360: 0 | E360: 27922270 | G360: =E360+F360 -> 27922270 | H360: Add: Purchase of raw materials
A361: Purchase Withinstate- Packing Material | B361: 0 | C361: 3903950.5 | D361: 1750 | E361: 3902200.5 | G361: =E361+F361 -> 3902200.5 | H361: Add: Purchase of packing materials
A362: Purchase In Transit | B362: 0 | C362: 0 | D362: 36870023 | E362: -36870023 | G362: =E362+F362 -> -36870023 | H362: Not Applicable
A363: Purchase Interstate - Raw Material | B363: 0 | C363: 6530859.4 | D363: 0 | E363: 6530859.4 | G363: =E363+F363 -> 6530859.4 | H363: Add: Purchase of raw materials
A364: Purchase Withinstate - Raw Material | B364: 0 | C364: 2.355627e+08 | D364: 0 | E364: 2.355627e+08 | G364: =E364+F364 -> 2.355627e+08 | H364: Add: Purchase of raw materials
A365: Purchase - Urd - Stores, Spares & Consumable | B365: 0 | C365: 13513 | D365: 0 | E365: 13513 | G365: =E365+F365 -> 13513 | H365: Add: Purchase of Stores, Spares & Consumables
A366: Purchase Interstate- Stores, Spares & Consumable | B366: 0 | C366: 4199693.8 | D366: 0 | E366: 4199693.8 | G366: =E366+F366 -> 4199693.8 | H366: Add: Purchase of Stores, Spares & Consumables
A367: Purchase Return - Stores, Spares & Consumable | B367: 0 | C367: 54130 | D367: 48300 | E367: 5830 | G367: =E367+F367 -> 5830 | H367: Add: Purchase of Stores, Spares & Consumables
A368: Purchase Withinstate- Stores, Spares & Consumable | B368: 0 | C368: 6557054.3 | D368: 0 | E368: 6557054.3 | G368: =E368+F368 -> 6557054.3 | H368: Add: Purchase of Stores, Spares & Consumables
A369: Purchase Raw Material - High Seas | B369: 0 | C369: 18230800 | D369: 0 | E369: 18230800 | G369: =E369+F369 -> 18230800 | H369: Add: Purchase of raw materials
A370: Business Promotion Expense | B370: 0 | C370: 58000 | D370: 0 | E370: 58000 | G370: =E370+F370 -> 58000 | H370: Other Administrative Expenses | I370: =#REF! -> #REF! | J370: =G370-I370 -> #REF!
A371: Conveyance Expenses | B371: 0 | C371: 103790 | D371: 0 | E371: 103790 | G371: =E371+F371 -> 103790 | H371: Conveyance, vehicle running and traveling expenses
A372: Corporate social responsibility | B372: 0 | C372: 137398 | D372: 0 | E372: 137398 | G372: =E372+F372 -> 137398 | H372: Other Administrative Expenses | J372: =G372-I372 -> 137398
A373: Discount & Rebate On Sale | B373: 0 | C373: 0 | D373: 1.11 | E373: -1.11 | G373: =E373+F373 -> -1.11 | H373: Not Applicable
A374: Donation & Charity A/C | B374: 0 | C374: 100000 | D374: 0 | E374: 100000 | G374: =E374+F374 -> 100000 | H374: Other Administrative Expenses | J374: =G374-I374 -> 100000
A375: Electrical Expense | B375: 0 | C375: 10000 | D375: 0 | E375: 10000 | G375: =E375+F375 -> 10000 | H375: Other Administrative Expenses | J375: =G375-I375 -> 10000
A376: House Keeping Expense | B376: 0 | C376: 1476276.2 | D376: 0 | E376: 1476276.2 | G376: =E376+F376 -> 1476276.2 | H376: Other Manufacturing Expenses
A377: Membership & Subscription Fees | B377: 0 | C377: 4550 | D377: 0 | E377: 4550 | F377: -4550 | G377: =E377+F377 -> 0 | H377: Other Administrative Expenses | J377: =G377-I377 -> 0
A378: Miscellaneous Expense | B378: 0 | C378: 70058 | D378: 0 | E378: 70058 | G378: =E378+F378 -> 70058 | H378: Other Administrative Expenses | I378: =#REF! -> #REF! | J378: =G378-I378 -> #REF!
A379: Mobile & Telephone Expense | B379: 0 | C379: 20137 | D379: 0 | E379: 20137 | G379: =E379+F379 -> 20137 | H379: Other Administrative Expenses | J379: =G379-I379 -> 20137
A380: Office Expenses | B380: 0 | C380: 95576 | D380: 0 | E380: 95576 | G380: =E380+F380 -> 95576 | H380: Other Administrative Expenses | J380: =G380-I380 -> 95576
A381: Petrol & Diesel Expense - Other Vehicles | B381: 0 | C381: 94290.2 | D381: 0 | E381: 94290.2 | G381: =E381+F381 -> 94290.2 | H381: Conveyance, vehicle running and traveling expenses
A382: Postage & Courier Expense | B382: 0 | C382: 33980 | D382: 0 | E382: 33980 | G382: =E382+F382 -> 33980 | H382: Other Administrative Expenses | J382: =G382-I382 -> 33980
A383: Printing & Stationery Expense | B383: 0 | C383: 130683 | D383: 0 | E383: 130683 | G383: =E383+F383 -> 130683 | H383: Other Administrative Expenses | J383: =G383-I383 -> 130683
A384: Round Off | B384: 0 | C384: 69.97 | D384: 57.17 | E384: 12.8 | G384: =E384+F384 -> 12.8 | H384: Not Applicable
A385: Security Expenses | B385: 0 | C385: 1125473 | D385: 287468 | E385: 838005 | G385: =E385+F385 -> 838005 | H385: Other Administrative Expenses | J385: =G385-I385 -> 838005
A386: Travelling Expense | B386: 0 | C386: 546813 | D386: 0 | E386: 546813 | G386: =E386+F386 -> 546813 | H386: Travelling expense
A387: Xerox Expense | B387: 0 | C387: 4500 | D387: 0 | E387: 4500 | G387: =E387+F387 -> 4500 | H387: Other Administrative Expenses | J387: =G387-I387 -> 4500
A388: Repairs & Maintenance Exp - Building | B388: 0 | C388: 777961.12 | D388: 0 | E388: 777961.12 | G388: =E388+F388 -> 777961.12 | H388: Other Administrative Expenses | J388: =G388-I388 -> 777961.12
A389: Repairs & Maintenance Exp - Computer & Printers | B389: 0 | C389: 10281.36 | D389: 0 | E389: 10281.36 | G389: =E389+F389 -> 10281.36 | H389: Other Administrative Expenses | J389: =G389-I389 -> 10281.36
A390: Repairs & Maintenance Exp - Electric | B390: 0 | C390: 53481.96 | D390: 0 | E390: 53481.96 | G390: =E390+F390 -> 53481.96 | H390: Other Administrative Expenses | J390: =G390-I390 -> 53481.96
A391: Repairs & Maintenance Exp - Motor Cars | B391: 0 | C391: 50 | D391: 0 | E391: 50 | G391: =E391+F391 -> 50 | H391: Other Administrative Expenses | J391: =G391-I391 -> 50
A392: Repairs & Maintenance Exp - Others | B392: 0 | C392: 44688.1 | D392: 2110 | E392: 42578.1 | G392: =E392+F392 -> 42578.1 | H392: Other Administrative Expenses | J392: =G392-I392 -> 42578.1
A393: Vehicle Hire Charges - RCM | B393: 0 | C393: 145600 | D393: 0 | E393: 145600 | G393: =E393+F393 -> 145600 | H393: Conveyance, vehicle running and traveling expenses
A394: Vehicle Hire Charges - With Gst | B394: 0 | C394: 320000 | D394: 0 | E394: 320000 | G394: =E394+F394 -> 320000 | H394: Conveyance, vehicle running and traveling expenses
A395: Depreciation Expenses | B395: 0 | C395: 12595510 | D395: 0 | E395: 12595510 | G395: =E395+F395 -> 12595510 | H395: Depreciation
A396: Employees Benefit Expense (Esop) | B396: 0 | C396: 60245 | D396: 0 | E396: 60245 | G396: =E396+F396 -> 60245 | H396: Staff welfare expenses
A397: P.F. Admin. Charge | B397: 0 | C397: 93158 | D397: 26644 | E397: 66514 | G397: =E397+F397 -> 66514 | H397: Contribution to provident and other funds
A398: P.F. Contribution - Employer | B398: 0 | C398: 2326749 | D398: 665196 | E398: 1661553 | G398: =E398+F398 -> 1661553 | H398: Contribution to provident and other funds
A399: Allowance - Books & Periodicals | B399: 0 | C399: 187196 | D399: 0 | E399: 187196 | G399: =E399+F399 -> 187196 | H399: Salaries, wages and bonus | I399: =#REF! -> #REF! | J399: =G399-I399 -> #REF!
A400: Allowance - Canteen | B400: 0 | C400: 4810535.7 | D400: 347978 | E400: 4462557.7 | G400: =E400+F400 -> 4462557.7 | H400: Salaries, wages and bonus | I400: =#REF! -> #REF! | J400: =G400-I400 -> #REF!
A401: Allowance - Children Education & Hostel | B401: 0 | C401: 12457 | D401: 0 | E401: 12457 | G401: =E401+F401 -> 12457 | H401: Salaries, wages and bonus | I401: =#REF! -> #REF! | J401: =G401-I401 -> #REF!
A402: Allowance - Conveyance | B402: 0 | C402: 600 | D402: 0 | E402: 600 | G402: =E402+F402 -> 600 | H402: Salaries, wages and bonus | I402: =#REF! -> #REF! | J402: =G402-I402 -> #REF!
A403: Allowance - House Rent | B403: 0 | C403: 9980884 | D403: 0 | E403: 9980884 | G403: =E403+F403 -> 9980884 | H403: Salaries, wages and bonus | I403: =#REF! -> #REF! | J403: =G403-I403 -> #REF!
A404: Allowance - Leave Travels | B404: 0 | C404: 884620 | D404: 0 | E404: 884620 | G404: =E404+F404 -> 884620 | H404: Salaries, wages and bonus | I404: =#REF! -> #REF! | J404: =G404-I404 -> #REF!
A405: Allowance - Medical | B405: 0 | C405: 410765 | D405: 0 | E405: 410765 | G405: =E405+F405 -> 410765 | H405: Salaries, wages and bonus | I405: =#REF! -> #REF! | J405: =G405-I405 -> #REF!
A406: Allowance - Other | B406: 0 | C406: 470369 | D406: 0 | E406: 470369 | G406: =E406+F406 -> 470369 | H406: Salaries, wages and bonus | I406: =#REF! -> #REF! | J406: =G406-I406 -> #REF!
A407: Allowance - Special | B407: 0 | C407: 880440 | D407: 0 | E407: 880440 | G407: =E407+F407 -> 880440 | H407: Salaries, wages and bonus | I407: =#REF! -> #REF! | J407: =G407-I407 -> #REF!
A408: Allowance - Transport | B408: 0 | C408: 299240 | D408: 0 | E408: 299240 | G408: =E408+F408 -> 299240 | H408: Salaries, wages and bonus | I408: =#REF! -> #REF! | J408: =G408-I408 -> #REF!
A409: Allowance - Uniform / Attire | B409: 0 | C409: 924371 | D409: 0 | E409: 924371 | G409: =E409+F409 -> 924371 | H409: Salaries, wages and bonus | I409: =#REF! -> #REF! | J409: =G409-I409 -> #REF!
A410: Allowance - Vehicle Maintenance | B410: 0 | C410: 20384 | D410: 0 | E410: 20384 | G410: =E410+F410 -> 20384 | H410: Salaries, wages and bonus | I410: =#REF! -> #REF! | J410: =G410-I410 -> #REF!
... A412: Att. Bonus (Salary Part) | B412: 0 | C412: 297150 | D412: 0 | E412: 297150 | G412: =E412+F412 -> 297150 | H412: Salaries, wages and bonus | I412: =#REF! -> #REF! | J412: =G412-I412 -> #REF!
A413: Employers Contribution to ESI | B413: 0 | C413: 1110240 | D413: 321950 | E413: 788290 | F413: 289024 | G413: =E413+F413 -> 1077314 | H413: Salaries, wages and bonus | I413: =#REF! -> #REF! | J413: =G413-I413 -> #REF!
A414: Gratuity Expense | B414: 0 | C414: 923585 | D414: 0 | E414: 923585 | G414: =E414+F414 -> 923585 | H414: Salaries, wages and bonus | J414: =G414-I414 -> 923585
A415: Incentive Expense - Attendence | B415: 0 | C415: 1735919 | D415: 0 | E415: 1735919 | G415: =E415+F415 -> 1735919 | H415: Salaries, wages and bonus | I415: =#REF! -> #REF! | J415: =G415-I415 -> #REF!
A416: Incentive Expense - Production | B416: 0 | C416: 5039456 | D416: 0 | E416: 5039456 | G416: =E416+F416 -> 5039456 | H416: Salaries, wages and bonus | I416: =#REF! -> #REF! | J416: =G416-I416 -> #REF!
A417: Other Deduction | B417: 0 | C417: 0 | D417: 102409 | E417: -102409 | G417: =E417+F417 -> -102409 | H417: Salaries, wages and bonus | I417: =#REF! -> #REF! | J417: =G417-I417 -> #REF!
A418: Salaries Expense | B418: 0 | C418: 15507686 | D418: 0 | E418: 15507686 | G418: =E418+F418 -> 15507686 | H418: Salaries, wages and bonus | I418: =#REF! -> #REF! | J418: =G418-I418 -> #REF!
...

Sheet JULY-TB
A1: Perticular | B1: Opening | C1: Debit | D1: Credit | E1: Closing | F1: Provision | G1: Total | H1: Head | I1: 1
A2: Duty Clearing Account | B2: 0 | C2: 12782932 | D2: 12782932 | E2: 0 | G2: =E2+F2 -> 0 | H2: Not Applicable
A3: Income Tax Ay 2014-15 | B3: 1607000 | C3: 0 | D3: 0 | E3: 1607000 | G3: =E3+F3 -> 1607000 | H3: Not Applicable
A4: Income Tax Ay 2016-17 | B4: 2200000 | C4: 0 | D4: 0 | E4: 2200000 | G4: =E4+F4 -> 2200000 | H4: Not Applicable
A5: Income Tax Refund Receivable | B5: 108787 | C5: 0 | D5: 0 | E5: 108787 | G5: =E5+F5 -> 108787 | H5: Not Applicable
A6: TCS On Purchase 20-21 | B6: 0 | C6: 0 | D6: 0 | E6: 0 | G6: =E6+F6 -> 0 | H6: Not Applicable
A7: TCS On Purchase 21-22 | B7: 0 | C7: 0 | D7: 0 | E7: 0 | G7: =E7+F7 -> 0 | H7: Not Applicable
A8: TCS On Purchase 22-23 | B8: -18585.94 | C8: 0 | D8: 0 | E8: -18585.94 | G8: =E8+F8 -> -18585.94 | H8: Not Applicable
A9: TCS On Purchase 23-24 | B9: 1151 | C9: 0 | D9: 0 | E9: 1151 | G9: =E9+F9 -> 1151 | H9: Not Applicable
A10: Tcs On Purchase 24-25 | B10: 30286.3 | C10: 0 | D10: 0 | E10: 30286.3 | G10: =E10+F10 -> 30286.3 | H10: Not Applicable
A11: Tcs On Purchase 25-26 | B11: 1335.22 | C11: 0 | D11: 0 | E11: 1335.22 | G11: =E11+F11 -> 1335.22 | H11: Not Applicable
A12: TDS Receivable 2021-22 | B12: 0 | C12: 0 | D12: 0 | E12: 0 | G12: =E12+F12 -> 0 | H12: Not Applicable
A13: TDS Receivable 2022-23 | B13: -418818 | C13: 0 | D13: 0 | E13: -418818 | G13: =E13+F13 -> -418818 | H13: Not Applicable
... A393: Advance Licence Fee Expense | B393: 0 | C393: 26500 | D393: 0 | E393: 26500 | G393: =E393+F393 -> 26500 | H393: Add: Purchase expenses
A394: Equipment Certification Charges | B394: 0 | C394: 122760 | D394: 0 | E394: 122760 | F394: 31748 | G394: =E394+F394 -> 154508 | H394: Other Administrative Expenses
A395: Factory Expense | B395: 0 | C395: 371344 | D395: 0 | E395: 371344 | F395: 6200 | G395: =E395+F395 -> 377544 | H395: Other Administrative Expenses
A396: Labour Charges | B396: 0 | C396: 21496544 | D396: 5975817 | E396: 15520727 | F396: 7315182 | G396: =E396+F396 -> 22835909 | H396: Labour charges
A397: Power Expense | B397: 0 | C397: 16180289 | D397: 3474593 | E397: 12705696 | F397: 4130997 | G397: =E397+F397 -> 16836693 | H397: Power and fuel
A398: Rent Expense - Colony | B398: 0 | C398: 5200400 | D398: 1313300 | E398: 3887100 | F398: 1313300 | G398: =E398+F398 -> 5200400 | H398: Other Administrative Expenses
A399: Rent Expenses - Machineries | B399: 0 | C399: 1450000 | D399: 1400000 | E399: 50000 | G399: =E399+F399 -> 50000 | H399: Other Administrative Expenses
A400: Exchange Rate Difference - Creditor | B400: 0 | C400: 313632 | D400: 30486.47 | E400: 283145.53 | G400: =E400+F400 -> 283145.53 | H400: Exchange Rate Difference
A401: Job Charges | B401: 0 | C401: 54735092 | D401: 55384.56 | E401: 54679708 | F401: 228490 | G401: =E401+F401 -> 54908198 | H401: Jobwork charges
A402: Loading & Unloading Expense | B402: 0 | C402: 192700 | D402: 0 | E402: 192700 | G402: =E402+F402 -> 192700 | H402: Freight Outward and C & F Charges
A403: Testing Charges | B403: 0 | C403: 0 | D403: 33844 | E403: -33844 | G403: =E403+F403 -> -33844 | H403: Other Administrative Expenses
A404: Water Charges | B404: 0 | C404: 837191 | D404: 289214 | E404: 547977 | F404: 184784 | G404: =E404+F404 -> 732761 | H404: Other Administrative Expenses
A405: Repairs & Maintenance Exp - Plant & Machinery | B405: 0 | C405: 1847132.2 | D405: 0 | E405: 1847132.2 | G405: =E405+F405 -> 1847132.2 | H405: Other Manufacturing Expenses
A406: Purchase Raw Material - Direct Import | B406: 0 | C406: 27922270 | D406: 0 | E406: 27922270 | G406: =E406+F406 -> 27922270 | H406: Add: Purchase of raw materials
A407: Purchase Withinstate- Packing Material | B407: 0 | C407: 6190436.3 | D407: 1750 | E407: 6188686.3 | G407: =E407+F407 -> 6188686.3 | H407: Add: Purchase of packing materials
A408: Purchase In Transit | B408: 0 | C408: 0 | D408: 36870023 | E408: -36870023 | G408: =E408+F408 -> -36870023 | H408: Not Applicable
A409: Purchase Interstate - Raw Material | B409: 0 | C409: 8179409.4 | D409: 0 | E409: 8179409.4 | G409: =E409+F409 -> 8179409.4 | H409: Add: Purchase of raw materials
A410: Purchase Withinstate - Raw Material | B410: 0 | C410: 3.8083725e+08 | D410: 0 | E410: 3.8083725e+08 | G410: =E410+F410 -> 3.8083725e+08 | H410: Add: Purchase of raw materials
A411: Purchase - Urd - Stores, Spares & Consumable | B411: 0 | C411: 18056 | D411: 0 | E411: 18056 | G411: =E411+F411 -> 18056 | H411: Add: Purchase of Stores, Spares & Consumables
A412: Purchase Interstate- Stores, Spares & Consumable | B412: 0 | C412: 5043460.2 | D412: 0 | E412: 5043460.2 | G412: =E412+F412 -> 5043460.2 | H412: Add: Purchase of Stores, Spares & Consumables
A413: Purchase Return - Stores, Spares & Consumable | B413: 0 | C413: 54130 | D413: 84770 | E413: -30640 | G413: =E413+F413 -> -30640 | H413: Add: Purchase of Stores, Spares & Consumables
A414: Purchase Withinstate- Stores, Spares & Consumable | B414: 0 | C414: 9175683.5 | D414: 50 | E414: 9175633.5 | G414: =E414+F414 -> 9175633.5 | H414: Add: Purchase of Stores, Spares & Consumables
A415: Purchase Raw Material - High Seas | B415: 0 | C415: 63948135 | D415: 0 | E415: 63948135 | G415: =E415+F415 -> 63948135 | H415: Add: Purchase of raw materials
A416: Business Promotion Expense | B416: 0 | C416: 58000 | D416: 0 | E416: 58000 | G416: =E416+F416 -> 58000 | H416: Other Administrative Expenses
... A422: Garden Mainteance Exp | B422: 0 | C422: 5450 | D422: 0 | E422: 5450 | G422: =E422+F422 -> 5450 | H422: Other Administrative Expenses
A423: House Keeping Expense | B423: 0 | C423: 1978802.4 | D423: 467310 | E423: 1511492.4 | F423: 467310 | G423: =E423+F423 -> 1978802.4 | H423: Other Manufacturing Expenses
A424: Membership & Subscription Fees | B424: 0 | C424: 4550 | D424: 0 | E424: 4550 | G424: =E424+F424 -> 4550 | H424: Other Administrative Expenses
A425: Miscellaneous Expense | B425: 0 | C425: 70058 | D425: 0 | E425: 70058 | G425: =E425+F425 -> 70058 | H425: Other Administrative Expenses
A426: Mobile & Telephone Expense | B426: 0 | C426: 24636.71 | D426: 3329.61 | E426: 21307.1 | G426: =E426+F426 -> 21307.1 | H426: Other Administrative Expenses
A427: Office Expenses | B427: 0 | C427: 98320 | D427: 0 | E427: 98320 | G427: =E427+F427 -> 98320 | H427: Other Administrative Expenses
A428: Petrol & Diesel Expense - Car | B428: 0 | C428: 143897 | D428: 0 | E428: 143897 | G428: =E428+F428 -> 143897 | H428: Other Administrative Expenses
A429: Petrol & Diesel Expense - Other Vehicles | B429: 0 | C429: 117996.2 | D429: 0 | E429: 117996.2 | G429: =E429+F429 -> 117996.2 | H429: Conveyance, vehicle running and traveling expenses
A430: Postage & Courier Expense | B430: 0 | C430: 38622 | D430: 0 | E430: 38622 | G430: =E430+F430 -> 38622 | H430: Other Administrative Expenses
A431: Printing & Stationery Expense | B431: 0 | C431: 154798 | D431: 0 | E431: 154798 | G431: =E431+F431 -> 154798 | H431: Other Administrative Expenses
A432: Round Off | B432: 0 | C432: 81.11 | D432: 58.19 | E432: 22.92 | G432: =E432+F432 -> 22.92 | H432: Not Applicable
A433: Security Expenses | B433: 0 | C433: 1438223 | D433: 600218 | E433: 838005 | F433: 324466 | G433: =E433+F433 -> 1162471 | H433: Other Administrative Expenses
A434: Travelling Expense | B434: 0 | C434: 631230 | D434: 205205 | E434: 426025 | G434: =E434+F434 -> 426025 | H434: Travelling expense
A435: Xerox Expense | B435: 0 | C435: 9000 | D435: 0 | E435: 9000 | F435: 4500 | G435: =E435+F435 -> 13500 | H435: Other Administrative Expenses
A436: Repairs & Maintenance Exp - Building | B436: 0 | C436: 820856.76 | D436: 0 | E436: 820856.76 | F436: 645623 | G436: =E436+F436 -> 1466479.8 | H436: Other Administrative Expenses
A437: Repairs & Maintenance Exp - Computer & Printers | B437: 0 | C437: 19285.36 | D437: 0 | E437: 19285.36 | G437: =E437+F437 -> 19285.36 | H437: Other Administrative Expenses
A438: Repairs & Maintenance Exp - Electric | B438: 0 | C438: 282312.96 | D438: 0 | E438: 282312.96 | G438: =E438+F438 -> 282312.96 | H438: Other Administrative Expenses
A439: Repairs & Maintenance Exp - Motor Cars | B439: 0 | C439: 50 | D439: 0 | E439: 50 | G439: =E439+F439 -> 50 | H439: Other Administrative Expenses
A440: Repairs & Maintenance Exp - Others | B440: 0 | C440: 74418.1 | D440: 2110 | E440: 72308.1 | G440: =E440+F440 -> 72308.1 | H440: Other Administrative Expenses
A441: Vehicle Hire Charges - RCM | B441: 0 | C441: 221100 | D441: 0 | E441: 221100 | F441: 75500 | G441: =E441+F441 -> 296600 | H441: Conveyance, vehicle running and traveling expenses
A442: Vehicle Hire Charges - With Gst | B442: 0 | C442: 480000 | D442: 0 | E442: 480000 | F442: 160000 | G442: =E442+F442 -> 640000 | H442: Conveyance, vehicle running and traveling expenses
A443: Depreciation Expenses | B443: 0 | C443: 12627025 | D443: 0 | E443: 12627025 | G443: =E443+F443 -> 12627025 | H443: Depreciation
A444: Employees Benefit Expense (Esop) | B444: 0 | C444: 60245 | D444: 0 | E444: 60245 | G444: =E444+F444 -> 60245 | H444: Staff welfare expenses
A445: P.F. Admin. Charge | B445: 0 | C445: 117988 | D445: 51474 | E445: 66514 | F445: 31714 | G445: =E445+F445 -> 98228 | H445: Contribution to provident and other funds
A446: P.F. Contribution - Employer | B446: 0 | C446: 2946975 | D446: 1285422 | E446: 1661553 | F446: 684273 | G446: =E446+F446 -> 2345826 | H446: Contribution to provident and other funds
A447: Allowance - Books & Periodicals | B447: 0 | C447: 187196 | D447: 0 | E447: 187196 | G447: =E447+F447 -> 187196 | H447: Salaries, wages and bonus
A448: Allowance - Canteen | B448: 0 | C448: 4810535.7 | D448: 347978 | E448: 4462557.7 | F448: 320910 | G448: =E448+F448 -> 4783467.7 | H448: Salaries, wages and bonus
A449: Allowance - Children Education & Hostel | B449: 0 | C449: 12457 | D449: 0 | E449: 12457 | G449: =E449+F449 -> 12457 | H449: Salaries, wages and bonus
A450: Allowance - Conveyance | B450: 0 | C450: 600 | D450: 0 | E450: 600 | G450: =E450+F450 -> 600 | H450: Salaries, wages and bonus
A451: Allowance - House Rent | B451: 0 | C451: 9980884 | D451: 0 | E451: 9980884 | G451: =E451+F451 -> 9980884 | H451: Salaries, wages and bonus
A452: Allowance - Leave Travels | B452: 0 | C452: 884620 | D452: 0 | E452: 884620 | G452: =E452+F452 -> 884620 | H452: Salaries, wages and bonus
A453: Allowance - Medical | B453: 0 | C453: 410765 | D453: 0 | E453: 410765 | G453: =E453+F453 -> 410765 | H453: Salaries, wages and bonus
A454: Allowance - Other | B454: 0 | C454: 470369 | D454: 0 | E454: 470369 | G454: =E454+F454 -> 470369 | H454: Salaries, wages and bonus
A455: Allowance - Special | B455: 0 | C455: 880440 | D455: 0 | E455: 880440 | G455: =E455+F455 -> 880440 | H455: Salaries, wages and bonus
A456: Allowance - Transport | B456: 0 | C456: 299240 | D456: 0 | E456: 299240 | G456: =E456+F456 -> 299240 | H456: Salaries, wages and bonus
A457: Allowance - Uniform / Attire | B457: 0 | C457: 924371 | D457: 0 | E457: 924371 | G457: =E457+F457 -> 924371 | H457: Salaries, wages and bonus
A458: Allowance - Vehicle Maintenance | B458: 0 | C458: 20384 | D458: 0 | E458: 20384 | G458: =E458+F458 -> 20384 | H458: Salaries, wages and bonus
A459: Allowance - Washing | B459: 0 | C459: 3491391.6 | D459: 0 | E459: 3491391.6 | G459: =E459+F459 -> 3491391.6 | H459: Salaries, wages and bonus
A460: Att. Bonus (Salary Part) | B460: 0 | C460: 297150 | D460: 0 | E460: 297150 | G460: =E460+F460 -> 297150 | H460: Salaries, wages and bonus
A461: Employers Contribution to ESI | B461: 0 | C461: 1399264 | D461: 610974 | E461: 788290 | F461: 344324 | G461: =E461+F461 -> 1132614 | H461: Salaries, wages and bonus
A462: Gratuity Expense | B462: 0 | C462: 923585 | D462: 0 | E462: 923585 | G462: =E462+F462 -> 923585 | H462: Salaries, wages and bonus
A463: Incentive Expense - Attendence | B463: 0 | C463: 1735919 | D463: 0 | E463: 1735919 | G463: =E463+F463 -> 1735919 | H463: Salaries, wages and bonus
A464: Incentive Expense - Production | B464: 0 | C464: 5039456 | D464: 0 | E464: 5039456 | G464: =E464+F464 -> 5039456 | H464: Salaries, wages and bonus
A465: Other Deduction | B465: 0 | C465: 0 | D465: 102409 | E465: -102409 | G465: =E465+F465 -> -102409 | H465: Salaries, wages and bonus
A466: Salaries Expense | B466: 0 | C466: 15507686 | D466: 0 | E466: 15507686 | F466: =20000+14955707 -> 14975707 | G466: =E466+F466 -> 30483393 | H466: Salaries, wages and bonus
A467: Salary - Arrears | B467: 0 | C467: 341631 | D467: 0 | E467: 341631 | G467: =E467+F467 -> 341631 | H467: Salaries, wages and bonus
A468: Salary - Over Time | B468: 0 | C468: 1238551.5 | D468: 0 | E468: 1238551.5 | G468: =E468+F468 -> 1238551.5 | H468: Salaries, wages and bonus
A469: Staff Welfare Expense | B469: 0 | C469: 27000 | D469: 0 | E469: 27000 | G469: =E469+F469 -> 27000 | H469: Not Applicable
A470: Canteen Expense - Factory | B470: 0 | C470: 1405307.2 | D470: 534775 | E470: 870532.24 | G470: =E470+F470 -> 870532.24 | H470: Staff welfare expenses
A471: Canteen Expense - Office | B471: 0 | C471: 480 | D471: 0 | E471: 480 | G471: =E471+F471 -> 480 | H471: Staff welfare expenses
A472: Medical Expense | B472: 0 | C472: 150602 | D472: 0 | E472: 150602 | F472: 176812 | G472: =E472+F472 -> 327414 | H472: Staff welfare expenses
A473: Bank Charges - Export Collection | B473: 0 | C473: 1000130.1 | D473: 1669.95 | E473: 998460.18 | G473: =E473+F473 -> 998460.18 | H473: Bank Charges & Commission
A474: Bank Charges - Inspection | B474: 0 | C474: 41300 | D474: 0 | E474: 41300 | G474: =E474+F474 -> 41300 | H474: Bank Charges & Commission
A475: Bank Charges - Export | B475: 0 | C475: 11254.8 | D475: 0 | E475: 11254.8 | G475: =E475+F475 -> 11254.8 | H475: Bank Charges & Commission
A476: Bank Charges - Export LC Advising | B476: 0 | C476: 2360 | D476: 0 | E476: 2360 | G476: =E476+F476 -> 2360 | H476: Bank Charges & Commission
A477: Bank Charges - Import | B477: 0 | C477: 87952.76 | D477: 0 | E477: 87952.76 | G477: =E477+F477 -> 87952.76 | H477: Bank Charges & Commission
A478: Bank Charges - LC | B478: 0 | C478: 2920 | D478: 0 | E478: 2920 | G478: =E478+F478 -> 2920 | H478: Bank Charges & Commission
A479: Bank Charges - Postage & Swift | B479: 0 | C479: 8500 | D479: 0 | E479: 8500 | G479: =E479+F479 -> 8500 | H479: Bank Charges & Commission
A480: Bank Charges - Processing Fees | B480: 0 | C480: 276710 | D480: 0 | E480: 276710 | G480: =E480+F480 -> 276710 | H480: Bank Charges & Commission
A481: Bank Charges- Others | B481: 0 | C481: 3453991.2 | D481: 3380095.7 | E481: 73895.5 | G481: =E481+F481 -> 73895.5 | H481: Bank Charges & Commission
A482: Exchange Rate Difference - Debtors | B482: 0 | C482: 25388182 | D482: 29844999 | E482: -4456817 | F482: -25161872 | G482: =E482+F482 -> -29618689 | H482: Exchange Rate Difference
A483: Exchange Rate Difference - Finance | B483: 0 | C483: 348061.53 | D483: 1928685.7 | E483: -1580624.2 | G483: =E483+F483 -> -1580624.2 | H483: Exchange Rate Difference
A484: Interest Expense - Term Loan | B484: 0 | C484: 7421781 | D484: 33543 | E484: 7388238 | G484: =E484+F484 -> 7388238 | H484: Interest on Term Loan
...

Sheet AUGUST - TB
A1: KPW I , Aug-26, T.B AS ON 11-09-26
A2: Perticular | B2: Opening | C2: Debit | D2: Credit | E2: Closing | F2: Provision | G2: Total | H2: Head | I2: 1 | J2: JULY TOTAL | K2: NET AUGSUT | L2: 1 | M2: 1
A3: Duty Clearing Account | B3: 0 | C3: 12782932 | D3: 12782932 | E3: 0 | G3: =E3+F3 -> 0 | H3: Not Applicable | J3: =VLOOKUP(A3,'JULY-TB'!A:G,7,0) -> 0
A4: Income Tax Ay 2014-15 | B4: 1607000 | C4: 0 | D4: 0 | E4: 1607000 | G4: =E4+F4 -> 1607000 | H4: Not Applicable | J4: =VLOOKUP(A4,'JULY-TB'!A:G,7,0) -> 1607000
A5: Income Tax Ay 2016-17 | B5: 2200000 | C5: 0 | D5: 0 | E5: 2200000 | G5: =E5+F5 -> 2200000 | H5: Not Applicable | J5: =VLOOKUP(A5,'JULY-TB'!A:G,7,0) -> 2200000
A6: Income Tax Refund Receivable | B6: 108787 | C6: 0 | D6: 0 | E6: 108787 | G6: =E6+F6 -> 108787 | H6: Not Applicable | J6: =VLOOKUP(A6,'JULY-TB'!A:G,7,0) -> 108787
A7: TCS On Purchase 20-21 | B7: 0 | C7: 0 | D7: 0 | E7: 0 | G7: =E7+F7 -> 0 | H7: Not Applicable | J7: =VLOOKUP(A7,'JULY-TB'!A:G,7,0) -> 0
A8: TCS On Purchase 21-22 | B8: 0 | C8: 0 | D8: 0 | E8: 0 | G8: =E8+F8 -> 0 | H8: Not Applicable | J8: =VLOOKUP(A8,'JULY-TB'!A:G,7,0) -> 0
A9: TCS On Purchase 22-23 | B9: -18585.94 | C9: 0 | D9: 0 | E9: -18585.94 | G9: =E9+F9 -> -18585.94 | H9: Not Applicable | J9: =VLOOKUP(A9,'JULY-TB'!A:G,7,0) -> -18585.94
A10: TCS On Purchase 23-24 | B10: 1151 | C10: 0 | D10: 0 | E10: 1151 | G10: =E10+F10 -> 1151 | H10: Not Applicable | J10: =VLOOKUP(A10,'JULY-TB'!A:G,7,0) -> 1151
A11: Tcs On Purchase 24-25 | B11: 30286.3 | C11: 0 | D11: 0 | E11: 30286.3 | G11: =E11+F11 -> 30286.3 | H11: Not Applicable | J11: =VLOOKUP(A11,'JULY-TB'!A:G,7,0) -> 30286.3
A12: Tcs On Purchase 25-26 | B12: 1335.22 | C12: 0 | D12: 0 | E12: 1335.22 | G12: =E12+F12 -> 1335.22 | H12: Not Applicable | J12: =VLOOKUP(A12,'JULY-TB'!A:G,7,0) -> 1335.22
A13: TDS Receivable 2021-22 | B13: 0 | C13: 0 | D13: 0 | E13: 0 | G13: =E13+F13 -> 0 | H13: Not Applicable | J13: =VLOOKUP(A13,'JULY-TB'!A:G,7,0) -> 0
A14: TDS Receivable 2022-23 | B14: -418818 | C14: 0 | D14: 0 | E14: -418818 | G14: =E14+F14 -> -418818 | H14: Not Applicable | J14: =VLOOKUP(A14,'JULY-TB'!A:G,7,0) -> -418818
... A401: Equipment Certification Charges | B401: 0 | C401: 201810 | D401: 0 | E401: 201810 | G401: =E401+F401 -> 201810 | H401: Other Administrative Expenses | J401: =VLOOKUP(A401,'JULY-TB'!A:G,7,0) -> 154508
A402: Factory Expense | B402: 0 | C402: 377544 | D402: 0 | E402: 377544 | F402: 5000 | G402: =E402+F402 -> 382544 | H402: Other Administrative Expenses | J402: =VLOOKUP(A402,'JULY-TB'!A:G,7,0) -> 377544
A403: Labour Charges | B403: 0 | C403: 29202215 | D403: 6030192 | E403: 23172023 | F403: 8112264 | G403: =E403+F403 -> 31284287 | H403: Labour charges | J403: =VLOOKUP(A403,'JULY-TB'!A:G,7,0) -> 22835909
A404: Power Expense | B404: 0 | C404: 21350160 | D404: 3474593 | E404: 17875567 | F404: =4215121+105000 -> 4320121 | G404: =E404+F404 -> 22195688 | H404: Power and fuel | J404: =VLOOKUP(A404,'JULY-TB'!A:G,7,0) -> 16836693
A405: Rent Expense - Colony | B405: 0 | C405: 6521700 | D405: 1313300 | E405: 5208400 | F405: 1321300 | G405: =E405+F405 -> 6529700 | H405: Other Administrative Expenses | J405: =VLOOKUP(A405,'JULY-TB'!A:G,7,0) -> 5200400
A406: Rent Expenses - Machineries | B406: 0 | C406: 1700000 | D406: 1400000 | E406: 300000 | G406: =E406+F406 -> 300000 | H406: Other Administrative Expenses | J406: =VLOOKUP(A406,'JULY-TB'!A:G,7,0) -> 50000
A407: Exchange Rate Difference - Creditor | B407: 0 | C407: 313632 | D407: 30486.47 | E407: 283145.53 | G407: =E407+F407 -> 283145.53 | H407: Exchange Rate Difference | J407: =VLOOKUP(A407,'JULY-TB'!A:G,7,0) -> 283145.53
A408: Job Charges | B408: 0 | C408: 55698265 | D408: 55384.56 | E408: 55642881 | F408: 207763 | G408: =E408+F408 -> 55850644 | H408: Jobwork charges | J408: =VLOOKUP(A408,'JULY-TB'!A:G,7,0) -> 54908198 | K408: =G408-J408 -> 942445.98
A409: Loading & Unloading Expense | B409: 0 | C409: 193430 | D409: 0 | E409: 193430 | G409: =E409+F409 -> 193430 | H409: Freight Outward and C & F Charges | J409: =VLOOKUP(A409,'JULY-TB'!A:G,7,0) -> 192700
A410: Testing Charges | B410: 0 | C410: 0 | D410: 33844 | E410: -33844 | G410: =E410+F410 -> -33844 | H410: Other Administrative Expenses | J410: =VLOOKUP(A410,'JULY-TB'!A:G,7,0) -> -33844
A411: Water Charges | B411: 0 | C411: 1021975 | D411: 289214 | E411: 732761 | F411: =87425+6680 -> 94105 | G411: =E411+F411 -> 826866 | H411: Other Administrative Expenses | J411: =VLOOKUP(A411,'JULY-TB'!A:G,7,0) -> 732761
A412: Repairs & Maintenance Exp - Plant & Machinery | B412: 0 | C412: 2776206.8 | D412: 0 | E412: 2776206.8 | F412: 164138 | G412: =E412+F412 -> 2940344.8 | H412: Other Manufacturing Expenses | J412: =VLOOKUP(A412,'JULY-TB'!A:G,7,0) -> 1847132.2
A413: Purchase Raw Material - Direct Import | B413: 0 | C413: 27922270 | D413: 0 | E413: 27922270 | G413: =E413+F413 -> 27922270 | H413: Add: Purchase of raw materials | J413: =VLOOKUP(A413,'JULY-TB'!A:G,7,0) -> 27922270
A414: Purchase Withinstate- Packing Material | B414: 0 | C414: 7640650.9 | D414: 1750 | E414: 7638900.9 | G414: =E414+F414 -> 7638900.9 | H414: Add: Purchase of packing materials | J414: =VLOOKUP(A414,'JULY-TB'!A:G,7,0) -> 6188686.3
A415: Purchase In Transit | B415: 0 | C415: 0 | D415: 36870023 | E415: -36870023 | G415: =E415+F415 -> -36870023 | H415: Add: Purchase of raw materials | J415: =VLOOKUP(A415,'JULY-TB'!A:G,7,0) -> -36870023
A416: Purchase Interstate - Raw Material | B416: 0 | C416: 8999989.4 | D416: 0 | E416: 8999989.4 | G416: =E416+F416 -> 8999989.4 | H416: Add: Purchase of raw materials | J416: =VLOOKUP(A416,'JULY-TB'!A:G,7,0) -> 8179409.4
A417: Purchase Return - Within State - Raw Material | B417: 0 | C417: 515217.19 | D417: 0 | E417: 515217.19 | G417: =E417+F417 -> 515217.19 | H417: Add: Purchase of raw materials | J417: =VLOOKUP(A417,'JULY-TB'!A:G,7,0) -> #N/A
A418: Purchase Withinstate - Raw Material | B418: 0 | C418: 5.6935576e+08 | D418: 0 | E418: 5.6935576e+08 | G418: =E418+F418 -> 5.6935576e+08 | H418: Add: Purchase of raw materials | J418: =VLOOKUP(A418,'JULY-TB'!A:G,7,0) -> 3.8083725e+08
A419: Purchase - Import - Stores, Spares & Consumable | B419: 0 | C419: 95444.93 | D419: 0 | E419: 95444.93 | G419: =E419+F419 -> 95444.93 | H419: Add: Purchase of Stores, Spares & Consumables | J419: =VLOOKUP(A419,'JULY-TB'!A:G,7,0) -> #N/A
A420: Purchase - Urd - Stores, Spares & Consumable | B420: 0 | C420: 23485 | D420: 0 | E420: 23485 | G420: =E420+F420 -> 23485 | H420: Add: Purchase of Stores, Spares & Consumables | J420: =VLOOKUP(A420,'JULY-TB'!A:G,7,0) -> 18056
A421: Purchase Interstate- Stores, Spares & Consumable | B421: 0 | C421: 6571202.7 | D421: 2000 | E421: 6569202.7 | G421: =E421+F421 -> 6569202.7 | H421: Add: Purchase of Stores, Spares & Consumables | J421: =VLOOKUP(A421,'JULY-TB'!A:G,7,0) -> 5043460.2
A422: Purchase Return - Stores, Spares & Consumable | B422: 0 | C422: 54130 | D422: 84770 | E422: -30640 | G422: =E422+F422 -> -30640 | H422: Add: Purchase of Stores, Spares & Consumables | J422: =VLOOKUP(A422,'JULY-TB'!A:G,7,0) -> -30640
A423: Purchase Withinstate- Stores, Spares & Consumable | B423: 0 | C423: 12080204 | D423: 50 | E423: 12080154 | G423: =E423+F423 -> 12080154 | H423: Add: Purchase of Stores, Spares & Consumables | J423: =VLOOKUP(A423,'JULY-TB'!A:G,7,0) -> 9175633.5
A424: Purchase Raw Material - High Seas | B424: 0 | C424: 1.1298313e+08 | D424: 0 | E424: 1.1298313e+08 | G424: =E424+F424 -> 1.1298313e+08 | H424: Add: Purchase of raw materials | J424: =VLOOKUP(A424,'JULY-TB'!A:G,7,0) -> 63948135
... A430: Garden Mainteance Exp | B430: 0 | C430: 5450 | D430: 0 | E430: 5450 | G430: =E430+F430 -> 5450 | H430: Other Administrative Expenses | J430: =VLOOKUP(A430,'JULY-TB'!A:G,7,0) -> 5450
A431: House Keeping Expense | B431: 0 | C431: 2021637.5 | D431: 467310 | E431: 1554327.5 | F431: 554014 | G431: =E431+F431 -> 2108341.5 | H431: Other Manufacturing Expenses | J431: =VLOOKUP(A431,'JULY-TB'!A:G,7,0) -> 1978802.4
A432: Membership & Subscription Fees | B432: 0 | C432: 4550 | D432: 0 | E432: 4550 | G432: =E432+F432 -> 4550 | H432: Other Administrative Expenses | J432: =VLOOKUP(A432,'JULY-TB'!A:G,7,0) -> 4550
A433: Miscellaneous Expense | B433: 0 | C433: 70058 | D433: 0 | E433: 70058 | G433: =E433+F433 -> 70058 | H433: Other Administrative Expenses | J433: =VLOOKUP(A433,'JULY-TB'!A:G,7,0) -> 70058
A434: Mobile & Telephone Expense | B434: 0 | C434: 27196.71 | D434: 3329.61 | E434: 23867.1 | G434: =E434+F434 -> 23867.1 | H434: Other Administrative Expenses | J434: =VLOOKUP(A434,'JULY-TB'!A:G,7,0) -> 21307.1
A435: Office Expenses | B435: 0 | C435: 115656 | D435: 0 | E435: 115656 | G435: =E435+F435 -> 115656 | H435: Other Administrative Expenses | J435: =VLOOKUP(A435,'JULY-TB'!A:G,7,0) -> 98320
A436: Petrol & Diesel Expense - Car | B436: 0 | C436: 143897 | D436: 0 | E436: 143897 | G436: =E436+F436 -> 143897 | H436: Other Administrative Expenses | J436: =VLOOKUP(A436,'JULY-TB'!A:G,7,0) -> 143897
A437: Petrol & Diesel Expense - Other Vehicles | B437: 0 | C437: 121996.2 | D437: 0 | E437: 121996.2 | G437: =E437+F437 -> 121996.2 | H437: Conveyance, vehicle running and traveling expenses | J437: =VLOOKUP(A437,'JULY-TB'!A:G,7,0) -> 117996.2
A438: Postage & Courier Expense | B438: 0 | C438: 76387 | D438: 0 | E438: 76387 | G438: =E438+F438 -> 76387 | H438: Other Administrative Expenses | J438: =VLOOKUP(A438,'JULY-TB'!A:G,7,0) -> 38622
A439: Printing & Stationery Expense | B439: 0 | C439: 164478 | D439: 0 | E439: 164478 | G439: =E439+F439 -> 164478 | H439: Other Administrative Expenses | J439: =VLOOKUP(A439,'JULY-TB'!A:G,7,0) -> 154798
A440: Round Off | B440: 0 | C440: 94.76 | D440: 63.39 | E440: 31.37 | G440: =E440+F440 -> 31.37 | H440: Not Applicable | J440: =VLOOKUP(A440,'JULY-TB'!A:G,7,0) -> 22.92
A441: Security Expenses | B441: 0 | C441: 1762689 | D441: 600218 | E441: 1162471 | F441: 415483 | G441: =E441+F441 -> 1577954 | H441: Other Administrative Expenses | J441: =VLOOKUP(A441,'JULY-TB'!A:G,7,0) -> 1162471
A442: Travelling Expense | B442: 0 | C442: 636170 | D442: 205205 | E442: 430965 | G442: =E442+F442 -> 430965 | H442: Travelling expense | J442: =VLOOKUP(A442,'JULY-TB'!A:G,7,0) -> 426025
A443: Xerox Expense | B443: 0 | C443: 13500 | D443: 0 | E443: 13500 | F443: 4500 | G443: =E443+F443 -> 18000 | H443: Other Administrative Expenses | J443: =VLOOKUP(A443,'JULY-TB'!A:G,7,0) -> 13500
A444: Repairs & Maintenance Exp - Building | B444: 0 | C444: 820856.76 | D444: 0 | E444: 820856.76 | G444: =E444+F444 -> 820856.76 | H444: Other Administrative Expenses | J444: =VLOOKUP(A444,'JULY-TB'!A:G,7,0) -> 1466479.8
A445: Repairs & Maintenance Exp - Computer & Printers | B445: 0 | C445: 19285.36 | D445: 0 | E445: 19285.36 | G445: =E445+F445 -> 19285.36 | H445: Other Administrative Expenses | J445: =VLOOKUP(A445,'JULY-TB'!A:G,7,0) -> 19285.36
A446: Repairs & Maintenance Exp - Electric | B446: 0 | C446: 337657.56 | D446: 0 | E446: 337657.56 | G446: =E446+F446 -> 337657.56 | H446: Other Administrative Expenses | J446: =VLOOKUP(A446,'JULY-TB'!A:G,7,0) -> 282312.96
A447: Repairs & Maintenance Exp - Motor Cars | B447: 0 | C447: 50 | D447: 0 | E447: 50 | G447: =E447+F447 -> 50 | H447: Other Administrative Expenses | J447: =VLOOKUP(A447,'JULY-TB'!A:G,7,0) -> 50
A448: Repairs & Maintenance Exp - Others | B448: 0 | C448: 82102.8 | D448: 2110 | E448: 79992.8 | G448: =E448+F448 -> 79992.8 | H448: Other Administrative Expenses | J448: =VLOOKUP(A448,'JULY-TB'!A:G,7,0) -> 72308.1
A449: Vehicle Hire Charges - RCM | B449: 0 | C449: 300375 | D449: 0 | E449: 300375 | F449: =37000+38500 -> 75500 | G449: =E449+F449 -> 375875 | H449: Conveyance, vehicle running and traveling expenses | J449: =VLOOKUP(A449,'JULY-TB'!A:G,7,0) -> 296600
A450: Vehicle Hire Charges - With Gst | B450: 0 | C450: 640000 | D450: 0 | E450: 640000 | F450: 160000 | G450: =E450+F450 -> 800000 | H450: Conveyance, vehicle running and traveling expenses | J450: =VLOOKUP(A450,'JULY-TB'!A:G,7,0) -> 640000
A451: Depreciation Expenses | B451: 0 | C451: 12627025 | D451: 0 | E451: 12627025 | G451: =E451+F451 -> 12627025 | H451: Depreciation | J451: =VLOOKUP(A451,'JULY-TB'!A:G,7,0) -> 12627025
A452: Employees Benefit Expense (Esop) | B452: 0 | C452: 60245 | D452: 0 | E452: 60245 | G452: =E452+F452 -> 60245 | H452: Staff welfare expenses | J452: =VLOOKUP(A452,'JULY-TB'!A:G,7,0) -> 60245
A453: P.F. Admin. Charge | B453: 0 | C453: 145380 | D453: 51474 | E453: 93906 | F453: 30689 | G453: =E453+F453 -> 124595 | H453: Contribution to provident and other funds | J453: =VLOOKUP(A453,'JULY-TB'!A:G,7,0) -> 98228
A454: P.F. Contribution - Employer | B454: 0 | C454: 3631248 | D454: 1285422 | E454: 2345826 | F454: 766732 | G454: =E454+F454 -> 3112558 | H454: Contribution to provident and other funds | J454: =VLOOKUP(A454,'JULY-TB'!A:G,7,0) -> 2345826
A455: Allowance - Books & Periodicals | B455: 0 | C455: 247587 | D455: 0 | E455: 247587 | G455: =E455+F455 -> 247587 | H455: Salaries, wages and bonus | J455: =VLOOKUP(A455,'JULY-TB'!A:G,7,0) -> 187196 | K455: =G455-J455 -> 60391
A456: Allowance - Canteen | B456: 0 | C456: 6891345.5 | D456: 734663 | E456: 6156682.5 | G456: =E456+F456 -> 6156682.5 | H456: Salaries, wages and bonus | J456: =VLOOKUP(A456,'JULY-TB'!A:G,7,0) -> 4783467.7 | K456: =G456-J456 -> 1373214.8
A457: Allowance - Children Education & Hostel | B457: 0 | C457: 15951 | D457: 0 | E457: 15951 | G457: =E457+F457 -> 15951 | H457: Salaries, wages and bonus | J457: =VLOOKUP(A457,'JULY-TB'!A:G,7,0) -> 12457 | K457: =G457-J457 -> 3494
A458: Allowance - Conveyance | B458: 0 | C458: 800 | D458: 0 | E458: 800 | G458: =E458+F458 -> 800 | H458: Salaries, wages and bonus | J458: =VLOOKUP(A458,'JULY-TB'!A:G,7,0) -> 600 | K458: =G458-J458 -> 200
A459: Allowance - House Rent | B459: 0 | C459: 14099033 | D459: 0 | E459: 14099033 | G459: =E459+F459 -> 14099033 | H459: Salaries, wages and bonus | J459: =VLOOKUP(A459,'JULY-TB'!A:G,7,0) -> 9980884 | K459: =G459-J459 -> 4118149
A460: Allowance - Leave Travels | B460: 0 | C460: 1167233 | D460: 0 | E460: 1167233 | G460: =E460+F460 -> 1167233 | H460: Salaries, wages and bonus | J460: =VLOOKUP(A460,'JULY-TB'!A:G,7,0) -> 884620 | K460: =G460-J460 -> 282613
A461: Allowance - Medical | B461: 0 | C461: 536581 | D461: 0 | E461: 536581 | G461: =E461+F461 -> 536581 | H461: Salaries, wages and bonus | J461: =VLOOKUP(A461,'JULY-TB'!A:G,7,0) -> 410765 | K461: =G461-J461 -> 125816
A462: Allowance - Other | B462: 0 | C462: 609240 | D462: 0 | E462: 609240 | G462: =E462+F462 -> 609240 | H462: Salaries, wages and bonus | J462: =VLOOKUP(A462,'JULY-TB'!A:G,7,0) -> 470369 | K462: =G462-J462 -> 138871
A463: Allowance - Special | B463: 0 | C463: 1889282 | D463: 0 | E463: 1889282 | G463: =E463+F463 -> 1889282 | H463: Salaries, wages and bonus | J463: =VLOOKUP(A463,'JULY-TB'!A:G,7,0) -> 880440 | K463: =G463-J463 -> 1008842
A464: Allowance - Transport | B464: 0 | C464: 400142 | D464: 0 | E464: 400142 | G464: =E464+F464 -> 400142 | H464: Salaries, wages and bonus | J464: =VLOOKUP(A464,'JULY-TB'!A:G,7,0) -> 299240 | K464: =G464-J464 -> 100902
A465: Allowance - Uniform / Attire | B465: 0 | C465: 1212792 | D465: 0 | E465: 1212792 | G465: =E465+F465 -> 1212792 | H465: Salaries, wages and bonus | J465: =VLOOKUP(A465,'JULY-TB'!A:G,7,0) -> 924371 | K465: =G465-J465 -> 288421
A466: Allowance - Vehicle Maintenance | B466: 0 | C466: 20384 | D466: 0 | E466: 20384 | G466: =E466+F466 -> 20384 | H466: Salaries, wages and bonus | J466: =VLOOKUP(A466,'JULY-TB'!A:G,7,0) -> 20384 | K466: =G466-J466 -> 0
... A473: Other Deduction | B473: 0 | C473: 0 | D473: 247853 | E473: -247853 | G473: =E473+F473 -> -247853 | H473: Salaries, wages and bonus | J473: =VLOOKUP(A473,'JULY-TB'!A:G,7,0) -> -102409 | K473: =G473-J473 -> -145444
A474: Salaries Expense | B474: 0 | C474: 21699114 | D474: 0 | E474: 21699114 | F474: 18707589 | G474: =E474+F474 -> 40406703 | H474: Salaries, wages and bonus | J474: =VLOOKUP(A474,'JULY-TB'!A:G,7,0) -> 30483393 | K474: =G474-J474 -> 9923309.8
A475: Salary - Arrears | B475: 0 | C475: 373641 | D475: 0 | E475: 373641 | G475: =E475+F475 -> 373641 | H475: Salaries, wages and bonus | J475: =VLOOKUP(A475,'JULY-TB'!A:G,7,0) -> 341631 | K475: =G475-J475 -> 32010
A476: Salary - Over Time | B476: 0 | C476: 1345862.5 | D476: 0 | E476: 1345862.5 | G476: =E476+F476 -> 1345862.5 | H476: Salaries, wages and bonus | J476: =VLOOKUP(A476,'JULY-TB'!A:G,7,0) -> 1238551.5 | K476: =G476-J476 -> 107311
A477: Staff Welfare Expense | B477: 0 | C477: 61230 | D477: 0 | E477: 61230 | G477: =E477+F477 -> 61230 | H477: Not Applicable | J477: =VLOOKUP(A477,'JULY-TB'!A:G,7,0) -> 27000
A478: Canteen Expense - Factory | B478: 0 | C478: 1801769 | D478: 570152 | E478: 1231617 | F478: 376290 | G478: =E478+F478 -> 1607907 | H478: Staff welfare expenses | J478: =VLOOKUP(A478,'JULY-TB'!A:G,7,0) -> 870532.24
A479: Canteen Expense - Office | B479: 0 | C479: 480 | D479: 0 | E479: 480 | G479: =E479+F479 -> 480 | H479: Staff welfare expenses | J479: =VLOOKUP(A479,'JULY-TB'!A:G,7,0) -> 480
A480: Medical Expense | B480: 0 | C480: 176812 | D480: 0 | E480: 176812 | F480: 34992 | G480: =E480+F480 -> 211804 | H480: Staff welfare expenses | J480: =VLOOKUP(A480,'JULY-TB'!A:G,7,0) -> 327414
A481: Bank Charges - Export Collection | B481: 0 | C481: 1082021.5 | D481: 1669.95 | E481: 1080351.6 | G481: =E481+F481 -> 1080351.6 | H481: Bank Charges & Commission | J481: =VLOOKUP(A481,'JULY-TB'!A:G,7,0) -> 998460.18
A482: Bank Charges - Inspection | B482: 0 | C482: 41300 | D482: 0 | E482: 41300 | G482: =E482+F482 -> 41300 | H482: Bank Charges & Commission | J482: =VLOOKUP(A482,'JULY-TB'!A:G,7,0) -> 41300
A483: Bank Charges - Export | B483: 0 | C483: 11254.8 | D483: 0 | E483: 11254.8 | G483: =E483+F483 -> 11254.8 | H483: Bank Charges & Commission | J483: =VLOOKUP(A483,'JULY-TB'!A:G,7,0) -> 11254.8
A484: Bank Charges - Export LC Advising | B484: 0 | C484: 2360 | D484: 0 | E484: 2360 | G484: =E484+F484 -> 2360 | H484: Bank Charges & Commission | J484: =VLOOKUP(A484,'JULY-TB'!A:G,7,0) -> 2360
A485: Bank Charges - Import | B485: 0 | C485: 89319.2 | D485: 0 | E485: 89319.2 | G485: =E485+F485 -> 89319.2 | H485: Bank Charges & Commission | J485: =VLOOKUP(A485,'JULY-TB'!A:G,7,0) -> 87952.76
A486: Bank Charges - LC | B486: 0 | C486: 2920 | D486: 0 | E486: 2920 | G486: =E486+F486 -> 2920 | H486: Bank Charges & Commission | J486: =VLOOKUP(A486,'JULY-TB'!A:G,7,0) -> 2920
A487: Bank Charges - Postage & Swift | B487: 0 | C487: 9500 | D487: 0 | E487: 9500 | G487: =E487+F487 -> 9500 | H487: Bank Charges & Commission | J487: =VLOOKUP(A487,'JULY-TB'!A:G,7,0) -> 8500
A488: Bank Charges - Processing Fees | B488: 0 | C488: 276710 | D488: 0 | E488: 276710 | G488: =E488+F488 -> 276710 | H488: Bank Charges & Commission | J488: =VLOOKUP(A488,'JULY-TB'!A:G,7,0) -> 276710
A489: Bank Charges- Others | B489: 0 | C489: 3579461.2 | D489: 3493110.7 | E489: 86350.55 | G489: =E489+F489 -> 86350.55 | H489: Bank Charges & Commission | J489: =VLOOKUP(A489,'JULY-TB'!A:G,7,0) -> 73895.5
A490: Exchange Rate Difference - Debtors | B490: 0 | C490: 25388182 | D490: 31687128 | E490: -6298946 | F490: -25161872 | G490: =E490+F490 -> -31460818 | H490: Exchange Rate Difference | J490: =VLOOKUP(A490,'JULY-TB'!A:G,7,0) -> -29618689
A491: Exchange Rate Difference - Finance | B491: 0 | C491: 314172.04 | D491: 1928685.7 | E491: -1614513.7 | G491: =E491+F491 -> -1614513.7 | H491: Exchange Rate Difference | J491: =VLOOKUP(A491,'JULY-TB'!A:G,7,0) -> -1580624.2
A492: Interest Expense - Term Loan | B492: 0 | C492: 8599620 | D492: 0 | E492: 8599620 | G492: =E492+F492 -> 8599620 | H492: Interest on Term Loan | J492: =VLOOKUP(A492,'JULY-TB'!A:G,7,0) -> 7388238
A493: Factoring Charges | B493: 0 | C493: 789574.84 | D493: 0 | E493: 789574.84 | G493: =E493+F493 -> 789574.84 | H493: Bank Charges & Commission | J493: =VLOOKUP(A493,'JULY-TB'!A:G,7,0) -> 704724.15
A494: Interest Expense - EPC | B494: 0 | C494: 11649643 | D494: 847727.4 | E494: 10801916 | G494: =E494+F494 -> 10801916 | H494: Interest Expense - Other | J494: =VLOOKUP(A494,'JULY-TB'!A:G,7,0) -> 8973718.6
A495: Interest Expense - Factoring | B495: 0 | C495: 2500989.8 | D495: 1685379.9 | E495: 815609.83 | G495: =E495+F495 -> 815609.83 | H495: Interest Expense - Other | J495: =VLOOKUP(A495,'JULY-TB'!A:G,7,0) -> 815971.29
A496: Interest Expense - Late Payment | B496: 0 | C496: 35791 | D496: 0 | E496: 35791 | G496: =E496+F496 -> 35791 | H496: Interest Expense - Other | J496: =VLOOKUP(A496,'JULY-TB'!A:G,7,0) -> 31469
A497: Interest Expense - PCFC | B497: 0 | C497: 5188306.7 | D497: 0 | E497: 5188306.7 | G497: =E497+F497 -> 5188306.7 | H497: Interest Expense - Other | J497: =VLOOKUP(A497,'JULY-TB'!A:G,7,0) -> 4150658.8
...
