Workbook
Name Domestic: 'Cust Master'!$D$346:$D$383
Name Export: Table13[Export]

Sheet Quote Exports
JE2: G
B4: Column1 | C4: Column2 | D4: Column3 | E4: Column1791040 | F4: Column1791041 | G4: Column1791026 | H4: Column1791027 | I4: Column1791028 | J4: Column1791029 | K4: Column1791030 | L4: Column1791031 | M4: Column1791032 | N4: Column1791033 | O4: Column1791018 | P4: Column1791019 | Q4: Column1791020 | R4: Column1791021 | S4: Column1791022 | T4: Column1791023 | U4: Column1791024 | V4: Column1791025 | W4: Column1791010 | X4: Column1791011 | Y4: Column1791012 | Z4: Column1791013 | AA4: Column1791014 | AB4: Column1791015 | AC4: Column1791016 | AD4: Column1791017 | AE4: Column179102 | AF4: Column179103 | AG4: Column179104 | AH4: Column179105 | AI4: Column179106 | AJ4: Column179107 | AK4: Column179108 | AL4: Column179109 | AM4: Column1799 | AN4: Column1798 | AO4: Column1797 | AP4: Column1796 | AQ4: Column1795 | AR4: Column1794 | AS4: Column1793 | AT4: Column1792 | AU4: Column15522221122 | AV4: Column156 | AW4: Column1492 | AX4: End
B5: 0 | C5: To Fill | D5: Date | E5: 46161 | F5: 46161 | G5: 46161 | H5: 46161 | I5: 46161 | J5: 46161 | K5: 46161 | L5: 46161 | M5: 46161 | N5: 46161 | O5: 46161 | P5: 46161 | Q5: 46161 | R5: 46163 | S5: 46163 | T5: 46163 | U5: 46164 | V5: 46167
C6: To Fill | D6: Sector | E6: Export | F6: Export | G6: Export | H6: Export | I6: Export | J6: Export | K6: Export | L6: Export | M6: Export | N6: Export | O6: Export | P6: Export | Q6: Export | R6: Export | S6: Export | T6: Export | U6: Export | V6: Export
B7: 1 | C7: To Fill | D7: Customer | E7: ISP Korea | F7: ISP Korea | G7: Desabag | H7: Desabag | I7: Desabag | J7: Desabag | K7: Desabag | L7: Desabag | M7: Desabag | N7: Desabag | O7: Desabag | P7: Desabag | Q7: Desabag | R7: Safesack Scand | S7: Safesack Scand | T7: Condepols | U7: ATEA Turkey | V7: Procon
C8: To Fill | D8: Our Ref | E8: 100X155 | F8: 100X160 | G8: 140X220 | H8: 140X220 | I8: 140X220 | J8: 140X220 | K8: 70X110 | L8: 40X60 | M8: 100X150 | N8: 60X100 | O8: 70X110 | P8: 90X130 | Q8: 60X100 | R8: 46X75 | S8: 72X110 | T8: SB4070N60-122 (1) | U8: 176.5x115 | V8: PP Bag
B9: 2 | C9: To Fill | D9: Customer Ref | E9: 100X155 | F9: 100X160 | G9: 3.3002 | H9: 3.3004 | I9: 3.3006 | J9: 3.3011 | K9: 3.9001 | L9: 3.9003 | M9: 3.9004 | N9: 3.9005 | O9: 3.9008 | P9: 3.9014 | Q9: 3.9015 | S9: ART58961 | T9: 30+10X70 | U9: 176.5x115 | V9: 234589
B10: 3 | C10: To Fill | D10: Type of Fabric/Bag | E10: Tubular Bag | F10: Tubular Bag | G10: Tubular Bag | H10: Tubular Bag | I10: Tubular Bag | J10: Tubular Bag | K10: Tubular Bag | L10: Tubular Bag | M10: Tubular Bag | N10: Tubular Bag | O10: Tubular Bag | P10: Tubular Bag | Q10: Tubular Bag | R10: Tubular Bag | S10: Tubular Bag | T10: Tubular Bag | U10: Tubular Fabric | V10: Tubular Bag
B11: 4 | C11: Spec | D11: Fabric Colour | E11: Coloured | F11: Coloured | G11: MW | H11: MW | I11: MW | J11: MW | K11: MW | L11: MW | M11: MW | N11: MW | O11: MW | P11: Coloured | Q11: MW | R11: Coloured | S11: MW | T11: Transparent | U11: MW | V11: MW
B12: 5 | C12: Spec | D12: Face Width Cm | E12: 100 | F12: 100 | G12: 140 | H12: 140 | I12: 140 | J12: 140 | K12: 70 | L12: 40 | M12: 100 | N12: 60 | O12: 70 | P12: 90 | Q12: 60 | R12: 46 | S12: 72 | T12: 30 | U12: 176.5 | V12: 50
B13: 6 | C13: Spec | D13: Gusset Cm (Both Side) Cm | E13: 0 | F13: 0 | G13: 0 | H13: 0 | I13: 0 | J13: 0 | K13: 0 | L13: 0 | M13: 0 | N13: 0 | O13: 0 | P13: 0 | Q13: 0 | R13: 0 | S13: 0 | T13: 10 | V13: 0
B14: 7 | C14: Spec | D14: Length Cm | E14: 155 | F14: 160 | G14: 220 | H14: 220 | I14: 220 | J14: 220 | K14: 110 | L14: 60 | M14: 150 | N14: 100 | O14: 110 | P14: 130 | Q14: 100 | R14: 75 | S14: 110 | T14: 70 | U14: 115 | V14: 80
B15: 8 | C15: Spec | D15: Top | E15: Hemmed | F15: Hemmed | G15: Hemmed | H15: Hemmed | I15: Hemmed | J15: Hemmed | K15: Hemmed | L15: Hemmed | M15: Hemmed | N15: Hemmed | O15: Hemmed | P15: Hemmed | Q15: Hemmed | R15: Hemmed | S15: Hemmed | T15: Heat Cut | U15: No Fold | V15: Hemmed
B16: 103 | D16: Cut Length Cm | E16: {=IF(E15="","",_xlfn.IFS(E15="Heat Cut",E14+5,E15="Hemmed",E14+8,E15="Ez Open",E14,E15="No Fold",E14+0))} -> 163 | F16: {=IF(F15="","",_xlfn.IFS(F15="Heat Cut",F14+5,F15="Hemmed",F14+8,F15="Ez Open",F14,F15="No Fold",F14+0))} -> 168 | G16: {=IF(G15="","",_xlfn.IFS(G15="Heat Cut",G14+5,G15="Hemmed",G14+8,G15="Ez Open",G14,G15="No Fold",G14+0))} -> 228 | H16: {=IF(H15="","",_xlfn.IFS(H15="Heat Cut",H14+5,H15="Hemmed",H14+8,H15="Ez Open",H14,H15="No Fold",H14+0))} -> 228 | I16: {=IF(I15="","",_xlfn.IFS(I15="Heat Cut",I14+5,I15="Hemmed",I14+8,I15="Ez Open",I14,I15="No Fold",I14+0))} -> 228 | J16: {=IF(J15="","",_xlfn.IFS(J15="Heat Cut",J14+5,J15="Hemmed",J14+8,J15="Ez Open",J14,J15="No Fold",J14+0))} -> 228 | K16: {=IF(K15="","",_xlfn.IFS(K15="Heat Cut",K14+5,K15="Hemmed",K14+8,K15="Ez Open",K14,K15="No Fold",K14+0))} -> 118 | L16: {=IF(L15="","",_xlfn.IFS(L15="Heat Cut",L14+5,L15="Hemmed",L14+8,L15="Ez Open",L14,L15="No Fold",L14+0))} -> 68 | ... V16: {=IF(V15="","",_xlfn.IFS(V15="Heat Cut",V14+5,V15="Hemmed",V14+8,V15="Ez Open",V14,V15="No Fold",V14+0))} -> 88
B17: 9 | C17: Spec | D17: Total Weight Gram | E17: 273 | F17: 377.74 | G17: 673.27 | H17: 609.43 | I17: 539.43 | J17: 409.93 | K17: 114.56 | L17: 46.61 | M17: 274.58 | N17: 88.71 | O17: 148.55 | P17: 219.25 | Q17: 80.71 | R17: 63.73 | S17: 160 | T17: 49.59 | U17: =U19 -> 1096.065 | V17: =V19 -> 59.659016
D18: Fabric GSM TBM | E18: 58 | F18: 58 | G18: 70 | H18: 60 | I18: 60 | J18: 60 | K18: 60 | L18: 60 | M18: 60 | N18: 60 | O18: 60 | P18: 60 | Q18: 60 | R18: 70 | S18: 62.5 | T18: 60 | U18: 270 | V18: 65
D19: Calculated Weight | E19: {=_xlfn.IFS(E18="",0,E10="Back Seam Bag",(E12+E13+2.5)*2*E16*E18/10000+SUM(E31:E43),E10="Tubular Bag",(E12+E13)*2*E16*E18/10000+SUM(E31:E43),E10="Tubular Fabric",(E12+E13)*2*E16*E18/10000+SUM(E31:E43),E10="Flat Fabric",(E12+E13)*2*E16*E18/10000+SUM(E31:E43))} -> 272.65851 | F19: {=_xlfn.IFS(F18="",0,F10="Back Seam Bag",(F12+F13+2.5)*2*F16*F18/10000+SUM(F31:F43),F10="Tubular Bag",(F12+F13)*2*F16*F18/10000+SUM(F31:F43),F10="Tubular Fabric",(F12+F13)*2*F16*F18/10000+SUM(F31:F43),F10="Flat Fabric",(F12+F13)*2*F16*F18/10000+SUM(F31:F43))} -> 377.74123 | G19: {=_xlfn.IFS(G18="",0,G10="Back Seam Bag",(G12+G13+2.5)*2*G16*G18/10000+SUM(G31:G43),G10="Tubular Bag",(G12+G13)*2*G16*G18/10000+SUM(G31:G43),G10="Tubular Fabric",(G12+G13)*2*G16*G18/10000+SUM(G31:G43),G10="Flat Fabric",(G12+G13)*2*G16*G18/10000+SUM(G31:G43))} -> 673.26925 | H19: {=_xlfn.IFS(H18="",0,H10="Back Seam Bag",(H12+H13+2.5)*2*H16*H18/10000+SUM(H31:H43),H10="Tubular Bag",(H12+H13)*2*H16*H18/10000+SUM(H31:H43),H10="Tubular Fabric",(H12+H13)*2*H16*H18/10000+SUM(H31:H43),H10="Flat Fabric",(H12+H13)*2*H16*H18/10000+SUM(H31:H43))} -> 609.42925 | I19: {=_xlfn.IFS(I18="",0,I10="Back Seam Bag",(I12+I13+2.5)*2*I16*I18/10000+SUM(I31:I43),I10="Tubular Bag",(I12+I13)*2*I16*I18/10000+SUM(I31:I43),I10="Tubular Fabric",(I12+I13)*2*I16*I18/10000+SUM(I31:I43),I10="Flat Fabric",(I12+I13)*2*I16*I18/10000+SUM(I31:I43))} -> 539.42925 | J19: {=_xlfn.IFS(J18="",0,J10="Back Seam Bag",(J12+J13+2.5)*2*J16*J18/10000+SUM(J31:J43),J10="Tubular Bag",(J12+J13)*2*J16*J18/10000+SUM(J31:J43),J10="Tubular Fabric",(J12+J13)*2*J16*J18/10000+SUM(J31:J43),J10="Flat Fabric",(J12+J13)*2*J16*J18/10000+SUM(J31:J43))} -> 409.92525 | K19: {=_xlfn.IFS(K18="",0,K10="Back Seam Bag",(K12+K13+2.5)*2*K16*K18/10000+SUM(K31:K43),K10="Tubular Bag",(K12+K13)*2*K16*K18/10000+SUM(K31:K43),K10="Tubular Fabric",(K12+K13)*2*K16*K18/10000+SUM(K31:K43),K10="Flat Fabric",(K12+K13)*2*K16*K18/10000+SUM(K31:K43))} -> 114.56262 | L19: {=_xlfn.IFS(L18="",0,L10="Back Seam Bag",(L12+L13+2.5)*2*L16*L18/10000+SUM(L31:L43),L10="Tubular Bag",(L12+L13)*2*L16*L18/10000+SUM(L31:L43),L10="Tubular Fabric",(L12+L13)*2*L16*L18/10000+SUM(L31:L43),L10="Flat Fabric",(L12+L13)*2*L16*L18/10000+SUM(L31:L43))} -> 46.607213 | ... V19: {=_xlfn.IFS(V18="",0,V10="Back Seam Bag",(V12+V13+2.5)*2*V16*V18/10000+SUM(V31:V43),V10="Tubular Bag",(V12+V13)*2*V16*V18/10000+SUM(V31:V43),V10="Tubular Fabric",(V12+V13)*2*V16*V18/10000+SUM(V31:V43),V10="Flat Fabric",(V12+V13)*2*V16*V18/10000+SUM(V31:V43))} -> 59.659016
B20: =B16+1 -> 104 | D20: Gross Width Cm | E20: =IF(E10="","",IF(E10="Back Seam Bag",E12+E13+2.5,E12+E13)) -> 100 | F20: =IF(F10="","",IF(F10="Back Seam Bag",F12+F13+2.5,F12+F13)) -> 100 | G20: =IF(G10="","",IF(G10="Back Seam Bag",G12+G13+2.5,G12+G13)) -> 140 | H20: =IF(H10="","",IF(H10="Back Seam Bag",H12+H13+2.5,H12+H13)) -> 140 | I20: =IF(I10="","",IF(I10="Back Seam Bag",I12+I13+2.5,I12+I13)) -> 140 | J20: =IF(J10="","",IF(J10="Back Seam Bag",J12+J13+2.5,J12+J13)) -> 140 | K20: =IF(K10="","",IF(K10="Back Seam Bag",K12+K13+2.5,K12+K13)) -> 70 | L20: =IF(L10="","",IF(L10="Back Seam Bag",L12+L13+2.5,L12+L13)) -> 40 | ... V20: =IF(V10="","",IF(V10="Back Seam Bag",V12+V13+2.5,V12+V13)) -> 50
B21: 10 | C21: Spec | D21: Liner Micron | E21: 20 | F21: 50 | G21: 0 | S21: 30 | T21: 0
B22: 11 | C22: Spec | D22: Glossy BOPP Micron
B23: 12 | C23: Spec | D23: Matt BOPP Micron
B24: 13 | C24: Spec | D24: Metalised BOPP Micron
D25: White Paper GSM
D26: Brown Paper GSM
B27: 14 | C27: Spec | D27: Adhesive GSM (Solvant Less)
B28: 15 | C28: Spec | D28: Ink GSM | E28: 0 | F28: 0 | G28: 0 | H28: 0 | I28: 0 | J28: 0 | K28: 0 | L28: 0 | M28: 0 | N28: 0 | O28: 0 | P28: 0 | Q28: 0 | R28: 0 | S28: 0 | T28: 0 | U28: 0 | V28: 0
B29: 105 | D29: Back Seam Coating Gr/Meter | E29: =IF(E$5="","",IF(E10="Back Seam Bag",2,0)) -> 0 | F29: =IF(F$5="","",IF(F10="Back Seam Bag",2,0)) -> 0 | G29: =IF(G$5="","",IF(G10="Back Seam Bag",2,0)) -> 0 | H29: =IF(H$5="","",IF(H10="Back Seam Bag",2,0)) -> 0 | I29: =IF(I$5="","",IF(I10="Back Seam Bag",2,0)) -> 0 | J29: =IF(J$5="","",IF(J10="Back Seam Bag",2,0)) -> 0 | K29: =IF(K$5="","",IF(K10="Back Seam Bag",2,0)) -> 0 | L29: =IF(L$5="","",IF(L10="Back Seam Bag",2,0)) -> 0 | ... V29: =IF(V$5="","",IF(V10="Back Seam Bag",2,0)) -> 0
B30: 16 | C30: Spec | D30: Coating GSM | E30: 0 | F30: 0 | G30: 20 | H30: 20 | I30: 20 | J30: 0 | K30: 0 | L30: 0 | M30: 20 | N30: 0 | O30: 20 | P30: 20 | Q30: 0 | R30: 0 | T30: 20
B31: 17 | C31: Spec | D31: Handle | E31: 15.6 | F31: 15.6 | G31: 90 | H31: 90 | I31: 20 | J31: 20 | K31: 12 | L31: 12 | M31: 15.6 | N31: 8 | O31: 12 | P31: 15 | Q31: 0 | R31: 8 | S31: 0 | T31: 0
B32: 106 | D32: Easy Open | E32: =IF(E5="","",IF(E15="Ez Open",7/100*(E12+10),0)) -> 0 | F32: =IF(F5="","",IF(F15="Ez Open",7/100*(F12+10),0)) -> 0 | G32: =IF(G5="","",IF(G15="Ez Open",7/100*(G12+10),0)) -> 0 | H32: =IF(H5="","",IF(H15="Ez Open",7/100*(H12+10),0)) -> 0 | I32: =IF(I5="","",IF(I15="Ez Open",7/100*(I12+10),0)) -> 0 | J32: =IF(J5="","",IF(J15="Ez Open",7/100*(J12+10),0)) -> 0 | K32: =IF(K5="","",IF(K15="Ez Open",7/100*(K12+10),0)) -> 0 | L32: =IF(L5="","",IF(L15="Ez Open",7/100*(L12+10),0)) -> 0 | ... V32: =IF(V5="","",IF(V15="Ez Open",7/100*(V12+10),0)) -> 0
B33: =B32+1 -> 107 | D33: Liner Wt | E33: =IFERROR((E$12+E$13+2)*2*(E$16+5)/10000*E21*0.92,"") -> 63.06048 | F33: =IFERROR((F$12+F$13+2)*2*(F$16+5)/10000*F21*0.92,"") -> 162.3432 | G33: =IFERROR((G$12+G$13+2)*2*(G$16+5)/10000*G21*0.92,"") -> 0 | H33: =IFERROR((H$12+H$13+2)*2*(H$16+5)/10000*H21*0.92,"") -> 0 | I33: =IFERROR((I$12+I$13+2)*2*(I$16+5)/10000*I21*0.92,"") -> 0 | J33: =IFERROR((J$12+J$13+2)*2*(J$16+5)/10000*J21*0.92,"") -> 0 | K33: =IFERROR((K$12+K$13+2)*2*(K$16+5)/10000*K21*0.92,"") -> 0 | L33: =IFERROR((L$12+L$13+2)*2*(L$16+5)/10000*L21*0.92,"") -> 0 | ... V33: =IFERROR((V$12+V$13+2)*2*(V$16+5)/10000*V21*0.92,"") -> 0
B34: =B33+1 -> 108 | D34: Glossy BOPP Wt | E34: =IFERROR((E$12+E$13+1.5)*2*E$16/10000*E22*0.92,"") -> 0 | F34: =IFERROR((F$12+F$13+1.5)*2*F$16/10000*F22*0.92,"") -> 0 | G34: =IFERROR((G$12+G$13+1.5)*2*G$16/10000*G22*0.92,"") -> 0 | H34: =IFERROR((H$12+H$13+1.5)*2*H$16/10000*H22*0.92,"") -> 0 | I34: =IFERROR((I$12+I$13+1.5)*2*I$16/10000*I22*0.92,"") -> 0 | J34: =IFERROR((J$12+J$13+1.5)*2*J$16/10000*J22*0.92,"") -> 0 | K34: =IFERROR((K$12+K$13+1.5)*2*K$16/10000*K22*0.92,"") -> 0 | L34: =IFERROR((L$12+L$13+1.5)*2*L$16/10000*L22*0.92,"") -> 0 | ... V34: =IFERROR((V$12+V$13+1.5)*2*V$16/10000*V22*0.92,"") -> 0
B35: =B34+1 -> 109 | D35: Matt BOPP Wt | E35: =IFERROR((E$12+E$13+1.5)*2*E$16/10000*E23*0.92,"") -> 0 | F35: =IFERROR((F$12+F$13+1.5)*2*F$16/10000*F23*0.92,"") -> 0 | G35: =IFERROR((G$12+G$13+1.5)*2*G$16/10000*G23*0.92,"") -> 0 | H35: =IFERROR((H$12+H$13+1.5)*2*H$16/10000*H23*0.92,"") -> 0 | I35: =IFERROR((I$12+I$13+1.5)*2*I$16/10000*I23*0.92,"") -> 0 | J35: =IFERROR((J$12+J$13+1.5)*2*J$16/10000*J23*0.92,"") -> 0 | K35: =IFERROR((K$12+K$13+1.5)*2*K$16/10000*K23*0.92,"") -> 0 | L35: =IFERROR((L$12+L$13+1.5)*2*L$16/10000*L23*0.92,"") -> 0 | ... V35: =IFERROR((V$12+V$13+1.5)*2*V$16/10000*V23*0.92,"") -> 0
B36: =B35+1 -> 110 | D36: Metalised BOPP Wt | E36: =IFERROR((E$12+E$13+1.5)*2*E$16/10000*E24*0.92,"") -> 0 | F36: =IFERROR((F$12+F$13+1.5)*2*F$16/10000*F24*0.92,"") -> 0 | G36: =IFERROR((G$12+G$13+1.5)*2*G$16/10000*G24*0.92,"") -> 0 | H36: =IFERROR((H$12+H$13+1.5)*2*H$16/10000*H24*0.92,"") -> 0 | I36: =IFERROR((I$12+I$13+1.5)*2*I$16/10000*I24*0.92,"") -> 0 | J36: =IFERROR((J$12+J$13+1.5)*2*J$16/10000*J24*0.92,"") -> 0 | K36: =IFERROR((K$12+K$13+1.5)*2*K$16/10000*K24*0.92,"") -> 0 | L36: =IFERROR((L$12+L$13+1.5)*2*L$16/10000*L24*0.92,"") -> 0 | ... V36: =IFERROR((V$12+V$13+1.5)*2*V$16/10000*V24*0.92,"") -> 0
D37: White Paper Wt | E37: =IFERROR((E$12+E$13+1.5)*2*E$16/10000*E25,"") -> 0 | F37: =IFERROR((F$12+F$13+1.5)*2*F$16/10000*F25,"") -> 0 | G37: =IFERROR((G$12+G$13+1.5)*2*G$16/10000*G25,"") -> 0 | H37: =IFERROR((H$12+H$13+1.5)*2*H$16/10000*H25,"") -> 0 | I37: =IFERROR((I$12+I$13+1.5)*2*I$16/10000*I25,"") -> 0 | J37: =IFERROR((J$12+J$13+1.5)*2*J$16/10000*J25,"") -> 0 | K37: =IFERROR((K$12+K$13+1.5)*2*K$16/10000*K25,"") -> 0 | L37: =IFERROR((L$12+L$13+1.5)*2*L$16/10000*L25,"") -> 0 | ... V37: =IFERROR((V$12+V$13+1.5)*2*V$16/10000*V25,"") -> 0
D38: Brown Paper Wt | E38: =IFERROR((E$12+E$13+1.5)*2*E$16/10000*E26,"") -> 0 | F38: =IFERROR((F$12+F$13+1.5)*2*F$16/10000*F26,"") -> 0 | G38: =IFERROR((G$12+G$13+1.5)*2*G$16/10000*G26,"") -> 0 | H38: =IFERROR((H$12+H$13+1.5)*2*H$16/10000*H26,"") -> 0 | I38: =IFERROR((I$12+I$13+1.5)*2*I$16/10000*I26,"") -> 0 | J38: =IFERROR((J$12+J$13+1.5)*2*J$16/10000*J26,"") -> 0 | K38: =IFERROR((K$12+K$13+1.5)*2*K$16/10000*K26,"") -> 0 | L38: =IFERROR((L$12+L$13+1.5)*2*L$16/10000*L26,"") -> 0 | ... V38: =IFERROR((V$12+V$13+1.5)*2*V$16/10000*V26,"") -> 0
B39: =B36+1 -> 111 | D39: Adhesive Wt | E39: =IFERROR((E$12+E$13+1.5)*2*E$16/10000*E27*0.92,"") -> 0 | F39: =IFERROR((F$12+F$13+1.5)*2*F$16/10000*F27*0.92,"") -> 0 | G39: =IFERROR((G$12+G$13+1.5)*2*G$16/10000*G27*0.92,"") -> 0 | H39: =IFERROR((H$12+H$13+1.5)*2*H$16/10000*H27*0.92,"") -> 0 | I39: =IFERROR((I$12+I$13+1.5)*2*I$16/10000*I27*0.92,"") -> 0 | J39: =IFERROR((J$12+J$13+1.5)*2*J$16/10000*J27*0.92,"") -> 0 | K39: =IFERROR((K$12+K$13+1.5)*2*K$16/10000*K27*0.92,"") -> 0 | L39: =IFERROR((L$12+L$13+1.5)*2*L$16/10000*L27*0.92,"") -> 0 | ... V39: =IFERROR((V$12+V$13+1.5)*2*V$16/10000*V27*0.92,"") -> 0
B40: =B39+1 -> 112 | D40: Ink Wt | E40: =IFERROR((E$12+E$13+1.5)*2*E$16/10000*E28,"") -> 0 | F40: =IFERROR((F$12+F$13+1.5)*2*F$16/10000*F28,"") -> 0 | G40: =IFERROR((G$12+G$13+1.5)*2*G$16/10000*G28,"") -> 0 | H40: =IFERROR((H$12+H$13+1.5)*2*H$16/10000*H28,"") -> 0 | I40: =IFERROR((I$12+I$13+1.5)*2*I$16/10000*I28,"") -> 0 | J40: =IFERROR((J$12+J$13+1.5)*2*J$16/10000*J28,"") -> 0 | K40: =IFERROR((K$12+K$13+1.5)*2*K$16/10000*K28,"") -> 0 | L40: =IFERROR((L$12+L$13+1.5)*2*L$16/10000*L28,"") -> 0 | ... V40: =IFERROR((V$12+V$13+1.5)*2*V$16/10000*V28,"") -> 0
B41: =B40+1 -> 113 | D41: Back Seam Coating Weight | E41: =IFERROR(E29*E16/100,"") -> 0 | F41: =IFERROR(F29*F16/100,"") -> 0 | G41: =IFERROR(G29*G16/100,"") -> 0 | H41: =IFERROR(H29*H16/100,"") -> 0 | I41: =IFERROR(I29*I16/100,"") -> 0 | J41: =IFERROR(J29*J16/100,"") -> 0 | K41: =IFERROR(K29*K16/100,"") -> 0 | L41: =IFERROR(L29*L16/100,"") -> 0 | ... V41: =IFERROR(V29*V16/100,"") -> 0
B42: =B41+1 -> 114 | D42: Coating Wt | E42: =IFERROR((E$12+E$13+2)*2*E$16/10000*E30,"") -> 0 | F42: =IFERROR((F$12+F$13+2)*2*F$16/10000*F30,"") -> 0 | G42: =IFERROR((G$12+G$13+2)*2*G$16/10000*G30,"") -> 129.504 | H42: =IFERROR((H$12+H$13+2)*2*H$16/10000*H30,"") -> 129.504 | I42: =IFERROR((I$12+I$13+2)*2*I$16/10000*I30,"") -> 129.504 | J42: =IFERROR((J$12+J$13+2)*2*J$16/10000*J30,"") -> 0 | K42: =IFERROR((K$12+K$13+2)*2*K$16/10000*K30,"") -> 0 | L42: =IFERROR((L$12+L$13+2)*2*L$16/10000*L30,"") -> 0 | ... V42: =IFERROR((V$12+V$13+2)*2*V$16/10000*V30,"") -> 0
B43: =B42+1 -> 115 | D43: Thread Wt | E43: {=IF(E5="","",IFERROR(IF(OR(E10="Tubular Bag",E10="Back Seam Bag"),_xlfn.IFS(E15="Hemmed",3/61*E12,E15="Heat Cut",2/61*E12,E15="Ez Open",1.2/61*(E12+10)),0),0))} -> 4.9180328 | F43: {=IF(F5="","",IFERROR(IF(OR(F10="Tubular Bag",F10="Back Seam Bag"),_xlfn.IFS(F15="Hemmed",3/61*F12,F15="Heat Cut",2/61*F12,F15="Ez Open",1.2/61*(F12+10)),0),0))} -> 4.9180328 | G43: {=IF(G5="","",IFERROR(IF(OR(G10="Tubular Bag",G10="Back Seam Bag"),_xlfn.IFS(G15="Hemmed",3/61*G12,G15="Heat Cut",2/61*G12,G15="Ez Open",1.2/61*(G12+10)),0),0))} -> 6.8852459 | H43: {=IF(H5="","",IFERROR(IF(OR(H10="Tubular Bag",H10="Back Seam Bag"),_xlfn.IFS(H15="Hemmed",3/61*H12,H15="Heat Cut",2/61*H12,H15="Ez Open",1.2/61*(H12+10)),0),0))} -> 6.8852459 | I43: {=IF(I5="","",IFERROR(IF(OR(I10="Tubular Bag",I10="Back Seam Bag"),_xlfn.IFS(I15="Hemmed",3/61*I12,I15="Heat Cut",2/61*I12,I15="Ez Open",1.2/61*(I12+10)),0),0))} -> 6.8852459 | J43: {=IF(J5="","",IFERROR(IF(OR(J10="Tubular Bag",J10="Back Seam Bag"),_xlfn.IFS(J15="Hemmed",3/61*J12,J15="Heat Cut",2/61*J12,J15="Ez Open",1.2/61*(J12+10)),0),0))} -> 6.8852459 | K43: {=IF(K5="","",IFERROR(IF(OR(K10="Tubular Bag",K10="Back Seam Bag"),_xlfn.IFS(K15="Hemmed",3/61*K12,K15="Heat Cut",2/61*K12,K15="Ez Open",1.2/61*(K12+10)),0),0))} -> 3.442623 | L43: {=IF(L5="","",IFERROR(IF(OR(L10="Tubular Bag",L10="Back Seam Bag"),_xlfn.IFS(L15="Hemmed",3/61*L12,L15="Heat Cut",2/61*L12,L15="Ez Open",1.2/61*(L12+10)),0),0))} -> 1.9672131 | ... V43: {=IF(V5="","",IFERROR(IF(OR(V10="Tubular Bag",V10="Back Seam Bag"),_xlfn.IFS(V15="Hemmed",3/61*V12,V15="Heat Cut",2/61*V12,V15="Ez Open",1.2/61*(V12+10)),0),0))} -> 2.4590164
B44: =B43+1 -> 116 | D44: Fabric Wt | E44: =IF(E$5="","",IFERROR(E17-SUM(E31:E43),"")) -> 189.42149 | F44: =IF(F$5="","",IFERROR(F17-SUM(F31:F43),"")) -> 194.87877 | G44: =IF(G$5="","",IFERROR(G17-SUM(G31:G43),"")) -> 446.88075 | H44: =IF(H$5="","",IFERROR(H17-SUM(H31:H43),"")) -> 383.04075 | I44: =IF(I$5="","",IFERROR(I17-SUM(I31:I43),"")) -> 383.04075 | J44: =IF(J$5="","",IFERROR(J17-SUM(J31:J43),"")) -> 383.04475 | K44: =IF(K$5="","",IFERROR(K17-SUM(K31:K43),"")) -> 99.117377 | L44: =IF(L$5="","",IFERROR(L17-SUM(L31:L43),"")) -> 32.642787 | ... V44: =IF(V$5="","",IFERROR(V17-SUM(V31:V43),"")) -> 57.2
D45: Fabric GSM | E45: =IFERROR(ROUND(E44/(E20*2*E16/10000),2),"") -> 58.1 | F45: =IFERROR(ROUND(F44/(F20*2*F16/10000),2),"") -> 58 | G45: =IFERROR(ROUND(G44/(G20*2*G16/10000),2),"") -> 70 | H45: =IFERROR(ROUND(H44/(H20*2*H16/10000),2),"") -> 60 | I45: =IFERROR(ROUND(I44/(I20*2*I16/10000),2),"") -> 60 | J45: =IFERROR(ROUND(J44/(J20*2*J16/10000),2),"") -> 60 | K45: =IFERROR(ROUND(K44/(K20*2*K16/10000),2),"") -> 60 | L45: =IFERROR(ROUND(L44/(L20*2*L16/10000),2),"") -> 60.01 | ... V45: =IFERROR(ROUND(V44/(V20*2*V16/10000),2),"") -> 65
B46: 18 | C46: RM Price | D46: PP Rafia | E46: {=IF(E$5="","",_xlfn.IFS(E$6="Export",LOOKUP(E$5,'RM Prices'!$C$4:$BJ$4,'RM Prices'!$C5:$BJ5),E$6="Domestic",LOOKUP(E$5,'RM Prices'!$C$31:$BJ$31,'RM Prices'!$C32:$BJ32)))} -> 133.274 | F46: {=IF(F$5="","",_xlfn.IFS(F$6="Export",LOOKUP(F$5,'RM Prices'!$C$4:$BJ$4,'RM Prices'!$C5:$BJ5),F$6="Domestic",LOOKUP(F$5,'RM Prices'!$C$31:$BJ$31,'RM Prices'!$C32:$BJ32)))} -> 133.274 | G46: {=IF(G$5="","",_xlfn.IFS(G$6="Export",LOOKUP(G$5,'RM Prices'!$C$4:$BJ$4,'RM Prices'!$C5:$BJ5),G$6="Domestic",LOOKUP(G$5,'RM Prices'!$C$31:$BJ$31,'RM Prices'!$C32:$BJ32)))} -> 133.274 | H46: {=IF(H$5="","",_xlfn.IFS(H$6="Export",LOOKUP(H$5,'RM Prices'!$C$4:$BJ$4,'RM Prices'!$C5:$BJ5),H$6="Domestic",LOOKUP(H$5,'RM Prices'!$C$31:$BJ$31,'RM Prices'!$C32:$BJ32)))} -> 133.274 | I46: {=IF(I$5="","",_xlfn.IFS(I$6="Export",LOOKUP(I$5,'RM Prices'!$C$4:$BJ$4,'RM Prices'!$C5:$BJ5),I$6="Domestic",LOOKUP(I$5,'RM Prices'!$C$31:$BJ$31,'RM Prices'!$C32:$BJ32)))} -> 133.274 | J46: {=IF(J$5="","",_xlfn.IFS(J$6="Export",LOOKUP(J$5,'RM Prices'!$C$4:$BJ$4,'RM Prices'!$C5:$BJ5),J$6="Domestic",LOOKUP(J$5,'RM Prices'!$C$31:$BJ$31,'RM Prices'!$C32:$BJ32)))} -> 133.274 | K46: {=IF(K$5="","",_xlfn.IFS(K$6="Export",LOOKUP(K$5,'RM Prices'!$C$4:$BJ$4,'RM Prices'!$C5:$BJ5),K$6="Domestic",LOOKUP(K$5,'RM Prices'!$C$31:$BJ$31,'RM Prices'!$C32:$BJ32)))} -> 133.274 | L46: {=IF(L$5="","",_xlfn.IFS(L$6="Export",LOOKUP(L$5,'RM Prices'!$C$4:$BJ$4,'RM Prices'!$C5:$BJ5),L$6="Domestic",LOOKUP(L$5,'RM Prices'!$C$31:$BJ$31,'RM Prices'!$C32:$BJ32)))} -> 133.274 | ... V46: {=IF(V$5="","",_xlfn.IFS(V$6="Export",LOOKUP(V$5,'RM Prices'!$C$4:$BJ$4,'RM Prices'!$C5:$BJ5),V$6="Domestic",LOOKUP(V$5,'RM Prices'!$C$31:$BJ$31,'RM Prices'!$C32:$BJ32)))} -> 133.274
B47: 19 | C47: RM Price | D47: HD Rafia | E47: {=IF(E$5="","",_xlfn.IFS(E$6="Export",LOOKUP(E$5,'RM Prices'!$C$4:$BJ$4,'RM Prices'!$C6:$BJ6),E$6="Domestic",LOOKUP(E$5,'RM Prices'!$C$31:$BJ$31,'RM Prices'!$C33:$BJ33)))} -> 155.837 | F47: {=IF(F$5="","",_xlfn.IFS(F$6="Export",LOOKUP(F$5,'RM Prices'!$C$4:$BJ$4,'RM Prices'!$C6:$BJ6),F$6="Domestic",LOOKUP(F$5,'RM Prices'!$C$31:$BJ$31,'RM Prices'!$C33:$BJ33)))} -> 155.837 | G47: {=IF(G$5="","",_xlfn.IFS(G$6="Export",LOOKUP(G$5,'RM Prices'!$C$4:$BJ$4,'RM Prices'!$C6:$BJ6),G$6="Domestic",LOOKUP(G$5,'RM Prices'!$C$31:$BJ$31,'RM Prices'!$C33:$BJ33)))} -> 155.837 | H47: {=IF(H$5="","",_xlfn.IFS(H$6="Export",LOOKUP(H$5,'RM Prices'!$C$4:$BJ$4,'RM Prices'!$C6:$BJ6),H$6="Domestic",LOOKUP(H$5,'RM Prices'!$C$31:$BJ$31,'RM Prices'!$C33:$BJ33)))} -> 155.837 | I47: {=IF(I$5="","",_xlfn.IFS(I$6="Export",LOOKUP(I$5,'RM Prices'!$C$4:$BJ$4,'RM Prices'!$C6:$BJ6),I$6="Domestic",LOOKUP(I$5,'RM Prices'!$C$31:$BJ$31,'RM Prices'!$C33:$BJ33)))} -> 155.837 | J47: {=IF(J$5="","",_xlfn.IFS(J$6="Export",LOOKUP(J$5,'RM Prices'!$C$4:$BJ$4,'RM Prices'!$C6:$BJ6),J$6="Domestic",LOOKUP(J$5,'RM Prices'!$C$31:$BJ$31,'RM Prices'!$C33:$BJ33)))} -> 155.837 | K47: {=IF(K$5="","",_xlfn.IFS(K$6="Export",LOOKUP(K$5,'RM Prices'!$C$4:$BJ$4,'RM Prices'!$C6:$BJ6),K$6="Domestic",LOOKUP(K$5,'RM Prices'!$C$31:$BJ$31,'RM Prices'!$C33:$BJ33)))} -> 155.837 | L47: {=IF(L$5="","",_xlfn.IFS(L$6="Export",LOOKUP(L$5,'RM Prices'!$C$4:$BJ$4,'RM Prices'!$C6:$BJ6),L$6="Domestic",LOOKUP(L$5,'RM Prices'!$C$31:$BJ$31,'RM Prices'!$C33:$BJ33)))} -> 155.837 | ... V47: {=IF(V$5="","",_xlfn.IFS(V$6="Export",LOOKUP(V$5,'RM Prices'!$C$4:$BJ$4,'RM Prices'!$C6:$BJ6),V$6="Domestic",LOOKUP(V$5,'RM Prices'!$C$31:$BJ$31,'RM Prices'!$C33:$BJ33)))} -> 155.837
B48: 20 | C48: RM Price | D48: LLDPE F19010 Film | E48: {=IF(E$5="","",_xlfn.IFS(E$6="Export",LOOKUP(E$5,'RM Prices'!$C$4:$BJ$4,'RM Prices'!$C7:$BJ7),E$6="Domestic",LOOKUP(E$5,'RM Prices'!$C$31:$BJ$31,'RM Prices'!$C34:$BJ34)))} -> 141.084 | F48: {=IF(F$5="","",_xlfn.IFS(F$6="Export",LOOKUP(F$5,'RM Prices'!$C$4:$BJ$4,'RM Prices'!$C7:$BJ7),F$6="Domestic",LOOKUP(F$5,'RM Prices'!$C$31:$BJ$31,'RM Prices'!$C34:$BJ34)))} -> 141.084 | G48: {=IF(G$5="","",_xlfn.IFS(G$6="Export",LOOKUP(G$5,'RM Prices'!$C$4:$BJ$4,'RM Prices'!$C7:$BJ7),G$6="Domestic",LOOKUP(G$5,'RM Prices'!$C$31:$BJ$31,'RM Prices'!$C34:$BJ34)))} -> 141.084 | H48: {=IF(H$5="","",_xlfn.IFS(H$6="Export",LOOKUP(H$5,'RM Prices'!$C$4:$BJ$4,'RM Prices'!$C7:$BJ7),H$6="Domestic",LOOKUP(H$5,'RM Prices'!$C$31:$BJ$31,'RM Prices'!$C34:$BJ34)))} -> 141.084 | I48: {=IF(I$5="","",_xlfn.IFS(I$6="Export",LOOKUP(I$5,'RM Prices'!$C$4:$BJ$4,'RM Prices'!$C7:$BJ7),I$6="Domestic",LOOKUP(I$5,'RM Prices'!$C$31:$BJ$31,'RM Prices'!$C34:$BJ34)))} -> 141.084 | J48: {=IF(J$5="","",_xlfn.IFS(J$6="Export",LOOKUP(J$5,'RM Prices'!$C$4:$BJ$4,'RM Prices'!$C7:$BJ7),J$6="Domestic",LOOKUP(J$5,'RM Prices'!$C$31:$BJ$31,'RM Prices'!$C34:$BJ34)))} -> 141.084 | K48: {=IF(K$5="","",_xlfn.IFS(K$6="Export",LOOKUP(K$5,'RM Prices'!$C$4:$BJ$4,'RM Prices'!$C7:$BJ7),K$6="Domestic",LOOKUP(K$5,'RM Prices'!$C$31:$BJ$31,'RM Prices'!$C34:$BJ34)))} -> 141.084 | L48: {=IF(L$5="","",_xlfn.IFS(L$6="Export",LOOKUP(L$5,'RM Prices'!$C$4:$BJ$4,'RM Prices'!$C7:$BJ7),L$6="Domestic",LOOKUP(L$5,'RM Prices'!$C$31:$BJ$31,'RM Prices'!$C34:$BJ34)))} -> 141.084 | ... V48: {=IF(V$5="","",_xlfn.IFS(V$6="Export",LOOKUP(V$5,'RM Prices'!$C$4:$BJ$4,'RM Prices'!$C7:$BJ7),V$6="Domestic",LOOKUP(V$5,'RM Prices'!$C$31:$BJ$31,'RM Prices'!$C34:$BJ34)))} -> 141.084
B49: 21 | C49: RM Price | D49: LDPE FY1005 Film | E49: {=IF(E$5="","",_xlfn.IFS(E$6="Export",LOOKUP(E$5,'RM Prices'!$C$4:$BJ$4,'RM Prices'!$C8:$BJ8),E$6="Domestic",LOOKUP(E$5,'RM Prices'!$C$31:$BJ$31,'RM Prices'!$C35:$BJ35)))} -> 170.884 | F49: {=IF(F$5="","",_xlfn.IFS(F$6="Export",LOOKUP(F$5,'RM Prices'!$C$4:$BJ$4,'RM Prices'!$C8:$BJ8),F$6="Domestic",LOOKUP(F$5,'RM Prices'!$C$31:$BJ$31,'RM Prices'!$C35:$BJ35)))} -> 170.884 | G49: {=IF(G$5="","",_xlfn.IFS(G$6="Export",LOOKUP(G$5,'RM Prices'!$C$4:$BJ$4,'RM Prices'!$C8:$BJ8),G$6="Domestic",LOOKUP(G$5,'RM Prices'!$C$31:$BJ$31,'RM Prices'!$C35:$BJ35)))} -> 170.884 | H49: {=IF(H$5="","",_xlfn.IFS(H$6="Export",LOOKUP(H$5,'RM Prices'!$C$4:$BJ$4,'RM Prices'!$C8:$BJ8),H$6="Domestic",LOOKUP(H$5,'RM Prices'!$C$31:$BJ$31,'RM Prices'!$C35:$BJ35)))} -> 170.884 | I49: {=IF(I$5="","",_xlfn.IFS(I$6="Export",LOOKUP(I$5,'RM Prices'!$C$4:$BJ$4,'RM Prices'!$C8:$BJ8),I$6="Domestic",LOOKUP(I$5,'RM Prices'!$C$31:$BJ$31,'RM Prices'!$C35:$BJ35)))} -> 170.884 | J49: {=IF(J$5="","",_xlfn.IFS(J$6="Export",LOOKUP(J$5,'RM Prices'!$C$4:$BJ$4,'RM Prices'!$C8:$BJ8),J$6="Domestic",LOOKUP(J$5,'RM Prices'!$C$31:$BJ$31,'RM Prices'!$C35:$BJ35)))} -> 170.884 | K49: {=IF(K$5="","",_xlfn.IFS(K$6="Export",LOOKUP(K$5,'RM Prices'!$C$4:$BJ$4,'RM Prices'!$C8:$BJ8),K$6="Domestic",LOOKUP(K$5,'RM Prices'!$C$31:$BJ$31,'RM Prices'!$C35:$BJ35)))} -> 170.884 | L49: {=IF(L$5="","",_xlfn.IFS(L$6="Export",LOOKUP(L$5,'RM Prices'!$C$4:$BJ$4,'RM Prices'!$C8:$BJ8),L$6="Domestic",LOOKUP(L$5,'RM Prices'!$C$31:$BJ$31,'RM Prices'!$C35:$BJ35)))} -> 170.884 | ... V49: {=IF(V$5="","",_xlfn.IFS(V$6="Export",LOOKUP(V$5,'RM Prices'!$C$4:$BJ$4,'RM Prices'!$C8:$BJ8),V$6="Domestic",LOOKUP(V$5,'RM Prices'!$C$31:$BJ$31,'RM Prices'!$C35:$BJ35)))} -> 170.884
B50: 22 | C50: RM Price | D50: LDPE 7 MFI | E50: {=IF(E$5="","",_xlfn.IFS(E$6="Export",LOOKUP(E$5,'RM Prices'!$C$4:$BJ$4,'RM Prices'!$C9:$BJ9),E$6="Domestic",LOOKUP(E$5,'RM Prices'!$C$31:$BJ$31,'RM Prices'!$C36:$BJ36)))} -> 173.632 | F50: {=IF(F$5="","",_xlfn.IFS(F$6="Export",LOOKUP(F$5,'RM Prices'!$C$4:$BJ$4,'RM Prices'!$C9:$BJ9),F$6="Domestic",LOOKUP(F$5,'RM Prices'!$C$31:$BJ$31,'RM Prices'!$C36:$BJ36)))} -> 173.632 | G50: {=IF(G$5="","",_xlfn.IFS(G$6="Export",LOOKUP(G$5,'RM Prices'!$C$4:$BJ$4,'RM Prices'!$C9:$BJ9),G$6="Domestic",LOOKUP(G$5,'RM Prices'!$C$31:$BJ$31,'RM Prices'!$C36:$BJ36)))} -> 173.632 | H50: {=IF(H$5="","",_xlfn.IFS(H$6="Export",LOOKUP(H$5,'RM Prices'!$C$4:$BJ$4,'RM Prices'!$C9:$BJ9),H$6="Domestic",LOOKUP(H$5,'RM Prices'!$C$31:$BJ$31,'RM Prices'!$C36:$BJ36)))} -> 173.632 | I50: {=IF(I$5="","",_xlfn.IFS(I$6="Export",LOOKUP(I$5,'RM Prices'!$C$4:$BJ$4,'RM Prices'!$C9:$BJ9),I$6="Domestic",LOOKUP(I$5,'RM Prices'!$C$31:$BJ$31,'RM Prices'!$C36:$BJ36)))} -> 173.632 | J50: {=IF(J$5="","",_xlfn.IFS(J$6="Export",LOOKUP(J$5,'RM Prices'!$C$4:$BJ$4,'RM Prices'!$C9:$BJ9),J$6="Domestic",LOOKUP(J$5,'RM Prices'!$C$31:$BJ$31,'RM Prices'!$C36:$BJ36)))} -> 173.632 | K50: {=IF(K$5="","",_xlfn.IFS(K$6="Export",LOOKUP(K$5,'RM Prices'!$C$4:$BJ$4,'RM Prices'!$C9:$BJ9),K$6="Domestic",LOOKUP(K$5,'RM Prices'!$C$31:$BJ$31,'RM Prices'!$C36:$BJ36)))} -> 173.632 | L50: {=IF(L$5="","",_xlfn.IFS(L$6="Export",LOOKUP(L$5,'RM Prices'!$C$4:$BJ$4,'RM Prices'!$C9:$BJ9),L$6="Domestic",LOOKUP(L$5,'RM Prices'!$C$31:$BJ$31,'RM Prices'!$C36:$BJ36)))} -> 173.632 | ... V50: {=IF(V$5="","",_xlfn.IFS(V$6="Export",LOOKUP(V$5,'RM Prices'!$C$4:$BJ$4,'RM Prices'!$C9:$BJ9),V$6="Domestic",LOOKUP(V$5,'RM Prices'!$C$31:$BJ$31,'RM Prices'!$C36:$BJ36)))} -> 173.632
B51: 23 | C51: RM Price | D51: PP H350FG | E51: {=IF(E$5="","",_xlfn.IFS(E$6="Export",LOOKUP(E$5,'RM Prices'!$C$4:$BJ$4,'RM Prices'!$C10:$BJ10),E$6="Domestic",LOOKUP(E$5,'RM Prices'!$C$31:$BJ$31,'RM Prices'!$C37:$BJ37)))} -> 134.564 | F51: {=IF(F$5="","",_xlfn.IFS(F$6="Export",LOOKUP(F$5,'RM Prices'!$C$4:$BJ$4,'RM Prices'!$C10:$BJ10),F$6="Domestic",LOOKUP(F$5,'RM Prices'!$C$31:$BJ$31,'RM Prices'!$C37:$BJ37)))} -> 134.564 | G51: {=IF(G$5="","",_xlfn.IFS(G$6="Export",LOOKUP(G$5,'RM Prices'!$C$4:$BJ$4,'RM Prices'!$C10:$BJ10),G$6="Domestic",LOOKUP(G$5,'RM Prices'!$C$31:$BJ$31,'RM Prices'!$C37:$BJ37)))} -> 134.564 | H51: {=IF(H$5="","",_xlfn.IFS(H$6="Export",LOOKUP(H$5,'RM Prices'!$C$4:$BJ$4,'RM Prices'!$C10:$BJ10),H$6="Domestic",LOOKUP(H$5,'RM Prices'!$C$31:$BJ$31,'RM Prices'!$C37:$BJ37)))} -> 134.564 | I51: {=IF(I$5="","",_xlfn.IFS(I$6="Export",LOOKUP(I$5,'RM Prices'!$C$4:$BJ$4,'RM Prices'!$C10:$BJ10),I$6="Domestic",LOOKUP(I$5,'RM Prices'!$C$31:$BJ$31,'RM Prices'!$C37:$BJ37)))} -> 134.564 | J51: {=IF(J$5="","",_xlfn.IFS(J$6="Export",LOOKUP(J$5,'RM Prices'!$C$4:$BJ$4,'RM Prices'!$C10:$BJ10),J$6="Domestic",LOOKUP(J$5,'RM Prices'!$C$31:$BJ$31,'RM Prices'!$C37:$BJ37)))} -> 134.564 | K51: {=IF(K$5="","",_xlfn.IFS(K$6="Export",LOOKUP(K$5,'RM Prices'!$C$4:$BJ$4,'RM Prices'!$C10:$BJ10),K$6="Domestic",LOOKUP(K$5,'RM Prices'!$C$31:$BJ$31,'RM Prices'!$C37:$BJ37)))} -> 134.564 | L51: {=IF(L$5="","",_xlfn.IFS(L$6="Export",LOOKUP(L$5,'RM Prices'!$C$4:$BJ$4,'RM Prices'!$C10:$BJ10),L$6="Domestic",LOOKUP(L$5,'RM Prices'!$C$31:$BJ$31,'RM Prices'!$C37:$BJ37)))} -> 134.564 | ... V51: {=IF(V$5="","",_xlfn.IFS(V$6="Export",LOOKUP(V$5,'RM Prices'!$C$4:$BJ$4,'RM Prices'!$C10:$BJ10),V$6="Domestic",LOOKUP(V$5,'RM Prices'!$C$31:$BJ$31,'RM Prices'!$C37:$BJ37)))} -> 134.564
B52: 24 | C52: RM Price | D52: LDPE 4 MFI | E52: {=IF(E$5="","",_xlfn.IFS(E$6="Export",LOOKUP(E$5,'RM Prices'!$C$4:$BJ$4,'RM Prices'!$C11:$BJ11),E$6="Domestic",LOOKUP(E$5,'RM Prices'!$C$31:$BJ$31,'RM Prices'!$C38:$BJ38)))} -> 170.884 | F52: {=IF(F$5="","",_xlfn.IFS(F$6="Export",LOOKUP(F$5,'RM Prices'!$C$4:$BJ$4,'RM Prices'!$C11:$BJ11),F$6="Domestic",LOOKUP(F$5,'RM Prices'!$C$31:$BJ$31,'RM Prices'!$C38:$BJ38)))} -> 170.884 | G52: {=IF(G$5="","",_xlfn.IFS(G$6="Export",LOOKUP(G$5,'RM Prices'!$C$4:$BJ$4,'RM Prices'!$C11:$BJ11),G$6="Domestic",LOOKUP(G$5,'RM Prices'!$C$31:$BJ$31,'RM Prices'!$C38:$BJ38)))} -> 170.884 | H52: {=IF(H$5="","",_xlfn.IFS(H$6="Export",LOOKUP(H$5,'RM Prices'!$C$4:$BJ$4,'RM Prices'!$C11:$BJ11),H$6="Domestic",LOOKUP(H$5,'RM Prices'!$C$31:$BJ$31,'RM Prices'!$C38:$BJ38)))} -> 170.884 | I52: {=IF(I$5="","",_xlfn.IFS(I$6="Export",LOOKUP(I$5,'RM Prices'!$C$4:$BJ$4,'RM Prices'!$C11:$BJ11),I$6="Domestic",LOOKUP(I$5,'RM Prices'!$C$31:$BJ$31,'RM Prices'!$C38:$BJ38)))} -> 170.884 | J52: {=IF(J$5="","",_xlfn.IFS(J$6="Export",LOOKUP(J$5,'RM Prices'!$C$4:$BJ$4,'RM Prices'!$C11:$BJ11),J$6="Domestic",LOOKUP(J$5,'RM Prices'!$C$31:$BJ$31,'RM Prices'!$C38:$BJ38)))} -> 170.884 | K52: {=IF(K$5="","",_xlfn.IFS(K$6="Export",LOOKUP(K$5,'RM Prices'!$C$4:$BJ$4,'RM Prices'!$C11:$BJ11),K$6="Domestic",LOOKUP(K$5,'RM Prices'!$C$31:$BJ$31,'RM Prices'!$C38:$BJ38)))} -> 170.884 | L52: {=IF(L$5="","",_xlfn.IFS(L$6="Export",LOOKUP(L$5,'RM Prices'!$C$4:$BJ$4,'RM Prices'!$C11:$BJ11),L$6="Domestic",LOOKUP(L$5,'RM Prices'!$C$31:$BJ$31,'RM Prices'!$C38:$BJ38)))} -> 170.884 | ... V52: {=IF(V$5="","",_xlfn.IFS(V$6="Export",LOOKUP(V$5,'RM Prices'!$C$4:$BJ$4,'RM Prices'!$C11:$BJ11),V$6="Domestic",LOOKUP(V$5,'RM Prices'!$C$31:$BJ$31,'RM Prices'!$C38:$BJ38)))} -> 170.884
B53: 25 | C53: RM Price | D53: RP | E53: {=IF(E$5="","",_xlfn.IFS(E$6="Export",LOOKUP(E$5,'RM Prices'!$C$4:$BJ$4,'RM Prices'!$C12:$BJ12),E$6="Domestic",LOOKUP(E$5,'RM Prices'!$C$31:$BJ$31,'RM Prices'!$C39:$BJ39)))} -> 70 | F53: {=IF(F$5="","",_xlfn.IFS(F$6="Export",LOOKUP(F$5,'RM Prices'!$C$4:$BJ$4,'RM Prices'!$C12:$BJ12),F$6="Domestic",LOOKUP(F$5,'RM Prices'!$C$31:$BJ$31,'RM Prices'!$C39:$BJ39)))} -> 70 | G53: {=IF(G$5="","",_xlfn.IFS(G$6="Export",LOOKUP(G$5,'RM Prices'!$C$4:$BJ$4,'RM Prices'!$C12:$BJ12),G$6="Domestic",LOOKUP(G$5,'RM Prices'!$C$31:$BJ$31,'RM Prices'!$C39:$BJ39)))} -> 70 | H53: {=IF(H$5="","",_xlfn.IFS(H$6="Export",LOOKUP(H$5,'RM Prices'!$C$4:$BJ$4,'RM Prices'!$C12:$BJ12),H$6="Domestic",LOOKUP(H$5,'RM Prices'!$C$31:$BJ$31,'RM Prices'!$C39:$BJ39)))} -> 70 | I53: {=IF(I$5="","",_xlfn.IFS(I$6="Export",LOOKUP(I$5,'RM Prices'!$C$4:$BJ$4,'RM Prices'!$C12:$BJ12),I$6="Domestic",LOOKUP(I$5,'RM Prices'!$C$31:$BJ$31,'RM Prices'!$C39:$BJ39)))} -> 70 | J53: {=IF(J$5="","",_xlfn.IFS(J$6="Export",LOOKUP(J$5,'RM Prices'!$C$4:$BJ$4,'RM Prices'!$C12:$BJ12),J$6="Domestic",LOOKUP(J$5,'RM Prices'!$C$31:$BJ$31,'RM Prices'!$C39:$BJ39)))} -> 70 | K53: {=IF(K$5="","",_xlfn.IFS(K$6="Export",LOOKUP(K$5,'RM Prices'!$C$4:$BJ$4,'RM Prices'!$C12:$BJ12),K$6="Domestic",LOOKUP(K$5,'RM Prices'!$C$31:$BJ$31,'RM Prices'!$C39:$BJ39)))} -> 70 | L53: {=IF(L$5="","",_xlfn.IFS(L$6="Export",LOOKUP(L$5,'RM Prices'!$C$4:$BJ$4,'RM Prices'!$C12:$BJ12),L$6="Domestic",LOOKUP(L$5,'RM Prices'!$C$31:$BJ$31,'RM Prices'!$C39:$BJ39)))} -> 70 | ... V53: {=IF(V$5="","",_xlfn.IFS(V$6="Export",LOOKUP(V$5,'RM Prices'!$C$4:$BJ$4,'RM Prices'!$C12:$BJ12),V$6="Domestic",LOOKUP(V$5,'RM Prices'!$C$31:$BJ$31,'RM Prices'!$C39:$BJ39)))} -> 70
B54: 26 | C54: RM Price | D54: Filler | E54: {=IF(E$5="","",_xlfn.IFS(E$6="Export",LOOKUP(E$5,'RM Prices'!$C$4:$BJ$4,'RM Prices'!$C13:$BJ13),E$6="Domestic",LOOKUP(E$5,'RM Prices'!$C$31:$BJ$31,'RM Prices'!$C40:$BJ40)))} -> 40 | F54: {=IF(F$5="","",_xlfn.IFS(F$6="Export",LOOKUP(F$5,'RM Prices'!$C$4:$BJ$4,'RM Prices'!$C13:$BJ13),F$6="Domestic",LOOKUP(F$5,'RM Prices'!$C$31:$BJ$31,'RM Prices'!$C40:$BJ40)))} -> 40 | G54: {=IF(G$5="","",_xlfn.IFS(G$6="Export",LOOKUP(G$5,'RM Prices'!$C$4:$BJ$4,'RM Prices'!$C13:$BJ13),G$6="Domestic",LOOKUP(G$5,'RM Prices'!$C$31:$BJ$31,'RM Prices'!$C40:$BJ40)))} -> 40 | H54: {=IF(H$5="","",_xlfn.IFS(H$6="Export",LOOKUP(H$5,'RM Prices'!$C$4:$BJ$4,'RM Prices'!$C13:$BJ13),H$6="Domestic",LOOKUP(H$5,'RM Prices'!$C$31:$BJ$31,'RM Prices'!$C40:$BJ40)))} -> 40 | I54: {=IF(I$5="","",_xlfn.IFS(I$6="Export",LOOKUP(I$5,'RM Prices'!$C$4:$BJ$4,'RM Prices'!$C13:$BJ13),I$6="Domestic",LOOKUP(I$5,'RM Prices'!$C$31:$BJ$31,'RM Prices'!$C40:$BJ40)))} -> 40 | J54: {=IF(J$5="","",_xlfn.IFS(J$6="Export",LOOKUP(J$5,'RM Prices'!$C$4:$BJ$4,'RM Prices'!$C13:$BJ13),J$6="Domestic",LOOKUP(J$5,'RM Prices'!$C$31:$BJ$31,'RM Prices'!$C40:$BJ40)))} -> 40 | K54: {=IF(K$5="","",_xlfn.IFS(K$6="Export",LOOKUP(K$5,'RM Prices'!$C$4:$BJ$4,'RM Prices'!$C13:$BJ13),K$6="Domestic",LOOKUP(K$5,'RM Prices'!$C$31:$BJ$31,'RM Prices'!$C40:$BJ40)))} -> 40 | L54: {=IF(L$5="","",_xlfn.IFS(L$6="Export",LOOKUP(L$5,'RM Prices'!$C$4:$BJ$4,'RM Prices'!$C13:$BJ13),L$6="Domestic",LOOKUP(L$5,'RM Prices'!$C$31:$BJ$31,'RM Prices'!$C40:$BJ40)))} -> 40 | ... V54: {=IF(V$5="","",_xlfn.IFS(V$6="Export",LOOKUP(V$5,'RM Prices'!$C$4:$BJ$4,'RM Prices'!$C13:$BJ13),V$6="Domestic",LOOKUP(V$5,'RM Prices'!$C$31:$BJ$31,'RM Prices'!$C40:$BJ40)))} -> 40
B55: 27 | C55: RM Price | D55: TPT | E55: {=IF(E$5="","",_xlfn.IFS(E$6="Export",LOOKUP(E$5,'RM Prices'!$C$4:$BJ$4,'RM Prices'!$C14:$BJ14),E$6="Domestic",LOOKUP(E$5,'RM Prices'!$C$31:$BJ$31,'RM Prices'!$C41:$BJ41)))} -> 56 | F55: {=IF(F$5="","",_xlfn.IFS(F$6="Export",LOOKUP(F$5,'RM Prices'!$C$4:$BJ$4,'RM Prices'!$C14:$BJ14),F$6="Domestic",LOOKUP(F$5,'RM Prices'!$C$31:$BJ$31,'RM Prices'!$C41:$BJ41)))} -> 56 | G55: {=IF(G$5="","",_xlfn.IFS(G$6="Export",LOOKUP(G$5,'RM Prices'!$C$4:$BJ$4,'RM Prices'!$C14:$BJ14),G$6="Domestic",LOOKUP(G$5,'RM Prices'!$C$31:$BJ$31,'RM Prices'!$C41:$BJ41)))} -> 56 | H55: {=IF(H$5="","",_xlfn.IFS(H$6="Export",LOOKUP(H$5,'RM Prices'!$C$4:$BJ$4,'RM Prices'!$C14:$BJ14),H$6="Domestic",LOOKUP(H$5,'RM Prices'!$C$31:$BJ$31,'RM Prices'!$C41:$BJ41)))} -> 56 | I55: {=IF(I$5="","",_xlfn.IFS(I$6="Export",LOOKUP(I$5,'RM Prices'!$C$4:$BJ$4,'RM Prices'!$C14:$BJ14),I$6="Domestic",LOOKUP(I$5,'RM Prices'!$C$31:$BJ$31,'RM Prices'!$C41:$BJ41)))} -> 56 | J55: {=IF(J$5="","",_xlfn.IFS(J$6="Export",LOOKUP(J$5,'RM Prices'!$C$4:$BJ$4,'RM Prices'!$C14:$BJ14),J$6="Domestic",LOOKUP(J$5,'RM Prices'!$C$31:$BJ$31,'RM Prices'!$C41:$BJ41)))} -> 56 | K55: {=IF(K$5="","",_xlfn.IFS(K$6="Export",LOOKUP(K$5,'RM Prices'!$C$4:$BJ$4,'RM Prices'!$C14:$BJ14),K$6="Domestic",LOOKUP(K$5,'RM Prices'!$C$31:$BJ$31,'RM Prices'!$C41:$BJ41)))} -> 56 | L55: {=IF(L$5="","",_xlfn.IFS(L$6="Export",LOOKUP(L$5,'RM Prices'!$C$4:$BJ$4,'RM Prices'!$C14:$BJ14),L$6="Domestic",LOOKUP(L$5,'RM Prices'!$C$31:$BJ$31,'RM Prices'!$C41:$BJ41)))} -> 56 | ... V55: {=IF(V$5="","",_xlfn.IFS(V$6="Export",LOOKUP(V$5,'RM Prices'!$C$4:$BJ$4,'RM Prices'!$C14:$BJ14),V$6="Domestic",LOOKUP(V$5,'RM Prices'!$C$31:$BJ$31,'RM Prices'!$C41:$BJ41)))} -> 56
B56: 28 | C56: RM Price | D56: UV | E56: {=IF(E$5="","",_xlfn.IFS(E$6="Export",LOOKUP(E$5,'RM Prices'!$C$4:$BJ$4,'RM Prices'!$C15:$BJ15),E$6="Domestic",LOOKUP(E$5,'RM Prices'!$C$31:$BJ$31,'RM Prices'!$C42:$BJ42)))} -> 280 | F56: {=IF(F$5="","",_xlfn.IFS(F$6="Export",LOOKUP(F$5,'RM Prices'!$C$4:$BJ$4,'RM Prices'!$C15:$BJ15),F$6="Domestic",LOOKUP(F$5,'RM Prices'!$C$31:$BJ$31,'RM Prices'!$C42:$BJ42)))} -> 280 | G56: {=IF(G$5="","",_xlfn.IFS(G$6="Export",LOOKUP(G$5,'RM Prices'!$C$4:$BJ$4,'RM Prices'!$C15:$BJ15),G$6="Domestic",LOOKUP(G$5,'RM Prices'!$C$31:$BJ$31,'RM Prices'!$C42:$BJ42)))} -> 280 | H56: {=IF(H$5="","",_xlfn.IFS(H$6="Export",LOOKUP(H$5,'RM Prices'!$C$4:$BJ$4,'RM Prices'!$C15:$BJ15),H$6="Domestic",LOOKUP(H$5,'RM Prices'!$C$31:$BJ$31,'RM Prices'!$C42:$BJ42)))} -> 280 | I56: {=IF(I$5="","",_xlfn.IFS(I$6="Export",LOOKUP(I$5,'RM Prices'!$C$4:$BJ$4,'RM Prices'!$C15:$BJ15),I$6="Domestic",LOOKUP(I$5,'RM Prices'!$C$31:$BJ$31,'RM Prices'!$C42:$BJ42)))} -> 280 | J56: {=IF(J$5="","",_xlfn.IFS(J$6="Export",LOOKUP(J$5,'RM Prices'!$C$4:$BJ$4,'RM Prices'!$C15:$BJ15),J$6="Domestic",LOOKUP(J$5,'RM Prices'!$C$31:$BJ$31,'RM Prices'!$C42:$BJ42)))} -> 280 | K56: {=IF(K$5="","",_xlfn.IFS(K$6="Export",LOOKUP(K$5,'RM Prices'!$C$4:$BJ$4,'RM Prices'!$C15:$BJ15),K$6="Domestic",LOOKUP(K$5,'RM Prices'!$C$31:$BJ$31,'RM Prices'!$C42:$BJ42)))} -> 280 | L56: {=IF(L$5="","",_xlfn.IFS(L$6="Export",LOOKUP(L$5,'RM Prices'!$C$4:$BJ$4,'RM Prices'!$C15:$BJ15),L$6="Domestic",LOOKUP(L$5,'RM Prices'!$C$31:$BJ$31,'RM Prices'!$C42:$BJ42)))} -> 280 | ... V56: {=IF(V$5="","",_xlfn.IFS(V$6="Export",LOOKUP(V$5,'RM Prices'!$C$4:$BJ$4,'RM Prices'!$C15:$BJ15),V$6="Domestic",LOOKUP(V$5,'RM Prices'!$C$31:$BJ$31,'RM Prices'!$C42:$BJ42)))} -> 280
B57: 29 | C57: RM Price | D57: Col MB | E57: {=IF(E$5="","",_xlfn.IFS(E$6="Export",LOOKUP(E$5,'RM Prices'!$C$4:$BJ$4,'RM Prices'!$C16:$BJ16),E$6="Domestic",LOOKUP(E$5,'RM Prices'!$C$31:$BJ$31,'RM Prices'!$C43:$BJ43)))} -> 250 | F57: {=IF(F$5="","",_xlfn.IFS(F$6="Export",LOOKUP(F$5,'RM Prices'!$C$4:$BJ$4,'RM Prices'!$C16:$BJ16),F$6="Domestic",LOOKUP(F$5,'RM Prices'!$C$31:$BJ$31,'RM Prices'!$C43:$BJ43)))} -> 250 | G57: {=IF(G$5="","",_xlfn.IFS(G$6="Export",LOOKUP(G$5,'RM Prices'!$C$4:$BJ$4,'RM Prices'!$C16:$BJ16),G$6="Domestic",LOOKUP(G$5,'RM Prices'!$C$31:$BJ$31,'RM Prices'!$C43:$BJ43)))} -> 250 | H57: {=IF(H$5="","",_xlfn.IFS(H$6="Export",LOOKUP(H$5,'RM Prices'!$C$4:$BJ$4,'RM Prices'!$C16:$BJ16),H$6="Domestic",LOOKUP(H$5,'RM Prices'!$C$31:$BJ$31,'RM Prices'!$C43:$BJ43)))} -> 250 | I57: {=IF(I$5="","",_xlfn.IFS(I$6="Export",LOOKUP(I$5,'RM Prices'!$C$4:$BJ$4,'RM Prices'!$C16:$BJ16),I$6="Domestic",LOOKUP(I$5,'RM Prices'!$C$31:$BJ$31,'RM Prices'!$C43:$BJ43)))} -> 250 | J57: {=IF(J$5="","",_xlfn.IFS(J$6="Export",LOOKUP(J$5,'RM Prices'!$C$4:$BJ$4,'RM Prices'!$C16:$BJ16),J$6="Domestic",LOOKUP(J$5,'RM Prices'!$C$31:$BJ$31,'RM Prices'!$C43:$BJ43)))} -> 250 | K57: {=IF(K$5="","",_xlfn.IFS(K$6="Export",LOOKUP(K$5,'RM Prices'!$C$4:$BJ$4,'RM Prices'!$C16:$BJ16),K$6="Domestic",LOOKUP(K$5,'RM Prices'!$C$31:$BJ$31,'RM Prices'!$C43:$BJ43)))} -> 250 | L57: {=IF(L$5="","",_xlfn.IFS(L$6="Export",LOOKUP(L$5,'RM Prices'!$C$4:$BJ$4,'RM Prices'!$C16:$BJ16),L$6="Domestic",LOOKUP(L$5,'RM Prices'!$C$31:$BJ$31,'RM Prices'!$C43:$BJ43)))} -> 250 | ... V57: {=IF(V$5="","",_xlfn.IFS(V$6="Export",LOOKUP(V$5,'RM Prices'!$C$4:$BJ$4,'RM Prices'!$C16:$BJ16),V$6="Domestic",LOOKUP(V$5,'RM Prices'!$C$31:$BJ$31,'RM Prices'!$C43:$BJ43)))} -> 250
... B60: 32 | C60: RM Price | D60: Back Seam Coating RM | E60: {=IF(E$5="","",_xlfn.IFS(E$6="Export",LOOKUP(E$5,'RM Prices'!$C$4:$BJ$4,'RM Prices'!$C19:$BJ19),E$6="Domestic",LOOKUP(E$5,'RM Prices'!$C$31:$BJ$31,'RM Prices'!$C46:$BJ46)))} -> 150.5562 | F60: {=IF(F$5="","",_xlfn.IFS(F$6="Export",LOOKUP(F$5,'RM Prices'!$C$4:$BJ$4,'RM Prices'!$C19:$BJ19),F$6="Domestic",LOOKUP(F$5,'RM Prices'!$C$31:$BJ$31,'RM Prices'!$C46:$BJ46)))} -> 150.5562 | G60: {=IF(G$5="","",_xlfn.IFS(G$6="Export",LOOKUP(G$5,'RM Prices'!$C$4:$BJ$4,'RM Prices'!$C19:$BJ19),G$6="Domestic",LOOKUP(G$5,'RM Prices'!$C$31:$BJ$31,'RM Prices'!$C46:$BJ46)))} -> 150.5562 | H60: {=IF(H$5="","",_xlfn.IFS(H$6="Export",LOOKUP(H$5,'RM Prices'!$C$4:$BJ$4,'RM Prices'!$C19:$BJ19),H$6="Domestic",LOOKUP(H$5,'RM Prices'!$C$31:$BJ$31,'RM Prices'!$C46:$BJ46)))} -> 150.5562 | I60: {=IF(I$5="","",_xlfn.IFS(I$6="Export",LOOKUP(I$5,'RM Prices'!$C$4:$BJ$4,'RM Prices'!$C19:$BJ19),I$6="Domestic",LOOKUP(I$5,'RM Prices'!$C$31:$BJ$31,'RM Prices'!$C46:$BJ46)))} -> 150.5562 | J60: {=IF(J$5="","",_xlfn.IFS(J$6="Export",LOOKUP(J$5,'RM Prices'!$C$4:$BJ$4,'RM Prices'!$C19:$BJ19),J$6="Domestic",LOOKUP(J$5,'RM Prices'!$C$31:$BJ$31,'RM Prices'!$C46:$BJ46)))} -> 150.5562 | K60: {=IF(K$5="","",_xlfn.IFS(K$6="Export",LOOKUP(K$5,'RM Prices'!$C$4:$BJ$4,'RM Prices'!$C19:$BJ19),K$6="Domestic",LOOKUP(K$5,'RM Prices'!$C$31:$BJ$31,'RM Prices'!$C46:$BJ46)))} -> 150.5562 | L60: {=IF(L$5="","",_xlfn.IFS(L$6="Export",LOOKUP(L$5,'RM Prices'!$C$4:$BJ$4,'RM Prices'!$C19:$BJ19),L$6="Domestic",LOOKUP(L$5,'RM Prices'!$C$31:$BJ$31,'RM Prices'!$C46:$BJ46)))} -> 150.5562 | ... V60: {=IF(V$5="","",_xlfn.IFS(V$6="Export",LOOKUP(V$5,'RM Prices'!$C$4:$BJ$4,'RM Prices'!$C19:$BJ19),V$6="Domestic",LOOKUP(V$5,'RM Prices'!$C$31:$BJ$31,'RM Prices'!$C46:$BJ46)))} -> 150.5562
C61: RM Price | D61: White Paper | E61: {=IF(E$5="","",_xlfn.IFS(E$6="Export",LOOKUP(E$5,'RM Prices'!$C$4:$BJ$4,'RM Prices'!$C20:$BJ20),E$6="Domestic",LOOKUP(E$5,'RM Prices'!$C$31:$BJ$31,'RM Prices'!$C47:$BJ47)))} -> 83 | F61: {=IF(F$5="","",_xlfn.IFS(F$6="Export",LOOKUP(F$5,'RM Prices'!$C$4:$BJ$4,'RM Prices'!$C20:$BJ20),F$6="Domestic",LOOKUP(F$5,'RM Prices'!$C$31:$BJ$31,'RM Prices'!$C47:$BJ47)))} -> 83 | G61: {=IF(G$5="","",_xlfn.IFS(G$6="Export",LOOKUP(G$5,'RM Prices'!$C$4:$BJ$4,'RM Prices'!$C20:$BJ20),G$6="Domestic",LOOKUP(G$5,'RM Prices'!$C$31:$BJ$31,'RM Prices'!$C47:$BJ47)))} -> 83 | H61: {=IF(H$5="","",_xlfn.IFS(H$6="Export",LOOKUP(H$5,'RM Prices'!$C$4:$BJ$4,'RM Prices'!$C20:$BJ20),H$6="Domestic",LOOKUP(H$5,'RM Prices'!$C$31:$BJ$31,'RM Prices'!$C47:$BJ47)))} -> 83 | I61: {=IF(I$5="","",_xlfn.IFS(I$6="Export",LOOKUP(I$5,'RM Prices'!$C$4:$BJ$4,'RM Prices'!$C20:$BJ20),I$6="Domestic",LOOKUP(I$5,'RM Prices'!$C$31:$BJ$31,'RM Prices'!$C47:$BJ47)))} -> 83 | J61: {=IF(J$5="","",_xlfn.IFS(J$6="Export",LOOKUP(J$5,'RM Prices'!$C$4:$BJ$4,'RM Prices'!$C20:$BJ20),J$6="Domestic",LOOKUP(J$5,'RM Prices'!$C$31:$BJ$31,'RM Prices'!$C47:$BJ47)))} -> 83 | K61: {=IF(K$5="","",_xlfn.IFS(K$6="Export",LOOKUP(K$5,'RM Prices'!$C$4:$BJ$4,'RM Prices'!$C20:$BJ20),K$6="Domestic",LOOKUP(K$5,'RM Prices'!$C$31:$BJ$31,'RM Prices'!$C47:$BJ47)))} -> 83 | L61: {=IF(L$5="","",_xlfn.IFS(L$6="Export",LOOKUP(L$5,'RM Prices'!$C$4:$BJ$4,'RM Prices'!$C20:$BJ20),L$6="Domestic",LOOKUP(L$5,'RM Prices'!$C$31:$BJ$31,'RM Prices'!$C47:$BJ47)))} -> 83 | ... V61: {=IF(V$5="","",_xlfn.IFS(V$6="Export",LOOKUP(V$5,'RM Prices'!$C$4:$BJ$4,'RM Prices'!$C20:$BJ20),V$6="Domestic",LOOKUP(V$5,'RM Prices'!$C$31:$BJ$31,'RM Prices'!$C47:$BJ47)))} -> 83
C62: RM Price | D62: Brown Paper | E62: {=IF(E$5="","",_xlfn.IFS(E$6="Export",LOOKUP(E$5,'RM Prices'!$C$4:$BJ$4,'RM Prices'!$C21:$BJ21),E$6="Domestic",LOOKUP(E$5,'RM Prices'!$C$31:$BJ$31,'RM Prices'!$C48:$BJ48)))} -> 80 | F62: {=IF(F$5="","",_xlfn.IFS(F$6="Export",LOOKUP(F$5,'RM Prices'!$C$4:$BJ$4,'RM Prices'!$C21:$BJ21),F$6="Domestic",LOOKUP(F$5,'RM Prices'!$C$31:$BJ$31,'RM Prices'!$C48:$BJ48)))} -> 80 | G62: {=IF(G$5="","",_xlfn.IFS(G$6="Export",LOOKUP(G$5,'RM Prices'!$C$4:$BJ$4,'RM Prices'!$C21:$BJ21),G$6="Domestic",LOOKUP(G$5,'RM Prices'!$C$31:$BJ$31,'RM Prices'!$C48:$BJ48)))} -> 80 | H62: {=IF(H$5="","",_xlfn.IFS(H$6="Export",LOOKUP(H$5,'RM Prices'!$C$4:$BJ$4,'RM Prices'!$C21:$BJ21),H$6="Domestic",LOOKUP(H$5,'RM Prices'!$C$31:$BJ$31,'RM Prices'!$C48:$BJ48)))} -> 80 | I62: {=IF(I$5="","",_xlfn.IFS(I$6="Export",LOOKUP(I$5,'RM Prices'!$C$4:$BJ$4,'RM Prices'!$C21:$BJ21),I$6="Domestic",LOOKUP(I$5,'RM Prices'!$C$31:$BJ$31,'RM Prices'!$C48:$BJ48)))} -> 80 | J62: {=IF(J$5="","",_xlfn.IFS(J$6="Export",LOOKUP(J$5,'RM Prices'!$C$4:$BJ$4,'RM Prices'!$C21:$BJ21),J$6="Domestic",LOOKUP(J$5,'RM Prices'!$C$31:$BJ$31,'RM Prices'!$C48:$BJ48)))} -> 80 | K62: {=IF(K$5="","",_xlfn.IFS(K$6="Export",LOOKUP(K$5,'RM Prices'!$C$4:$BJ$4,'RM Prices'!$C21:$BJ21),K$6="Domestic",LOOKUP(K$5,'RM Prices'!$C$31:$BJ$31,'RM Prices'!$C48:$BJ48)))} -> 80 | L62: {=IF(L$5="","",_xlfn.IFS(L$6="Export",LOOKUP(L$5,'RM Prices'!$C$4:$BJ$4,'RM Prices'!$C21:$BJ21),L$6="Domestic",LOOKUP(L$5,'RM Prices'!$C$31:$BJ$31,'RM Prices'!$C48:$BJ48)))} -> 80 | ... V62: {=IF(V$5="","",_xlfn.IFS(V$6="Export",LOOKUP(V$5,'RM Prices'!$C$4:$BJ$4,'RM Prices'!$C21:$BJ21),V$6="Domestic",LOOKUP(V$5,'RM Prices'!$C$31:$BJ$31,'RM Prices'!$C48:$BJ48)))} -> 80
B63: 33 | C63: RM Price | D63: Glossy BOPP | E63: {=IF(E$5="","",_xlfn.IFS(E$6="Export",LOOKUP(E$5,'RM Prices'!$C$4:$BJ$4,'RM Prices'!$C22:$BJ22),E$6="Domestic",LOOKUP(E$5,'RM Prices'!$C$31:$BJ$31,'RM Prices'!$C49:$BJ49)))} -> 230 | F63: {=IF(F$5="","",_xlfn.IFS(F$6="Export",LOOKUP(F$5,'RM Prices'!$C$4:$BJ$4,'RM Prices'!$C22:$BJ22),F$6="Domestic",LOOKUP(F$5,'RM Prices'!$C$31:$BJ$31,'RM Prices'!$C49:$BJ49)))} -> 230 | G63: {=IF(G$5="","",_xlfn.IFS(G$6="Export",LOOKUP(G$5,'RM Prices'!$C$4:$BJ$4,'RM Prices'!$C22:$BJ22),G$6="Domestic",LOOKUP(G$5,'RM Prices'!$C$31:$BJ$31,'RM Prices'!$C49:$BJ49)))} -> 230 | H63: {=IF(H$5="","",_xlfn.IFS(H$6="Export",LOOKUP(H$5,'RM Prices'!$C$4:$BJ$4,'RM Prices'!$C22:$BJ22),H$6="Domestic",LOOKUP(H$5,'RM Prices'!$C$31:$BJ$31,'RM Prices'!$C49:$BJ49)))} -> 230 | I63: {=IF(I$5="","",_xlfn.IFS(I$6="Export",LOOKUP(I$5,'RM Prices'!$C$4:$BJ$4,'RM Prices'!$C22:$BJ22),I$6="Domestic",LOOKUP(I$5,'RM Prices'!$C$31:$BJ$31,'RM Prices'!$C49:$BJ49)))} -> 230 | J63: {=IF(J$5="","",_xlfn.IFS(J$6="Export",LOOKUP(J$5,'RM Prices'!$C$4:$BJ$4,'RM Prices'!$C22:$BJ22),J$6="Domestic",LOOKUP(J$5,'RM Prices'!$C$31:$BJ$31,'RM Prices'!$C49:$BJ49)))} -> 230 | K63: {=IF(K$5="","",_xlfn.IFS(K$6="Export",LOOKUP(K$5,'RM Prices'!$C$4:$BJ$4,'RM Prices'!$C22:$BJ22),K$6="Domestic",LOOKUP(K$5,'RM Prices'!$C$31:$BJ$31,'RM Prices'!$C49:$BJ49)))} -> 230 | L63: {=IF(L$5="","",_xlfn.IFS(L$6="Export",LOOKUP(L$5,'RM Prices'!$C$4:$BJ$4,'RM Prices'!$C22:$BJ22),L$6="Domestic",LOOKUP(L$5,'RM Prices'!$C$31:$BJ$31,'RM Prices'!$C49:$BJ49)))} -> 230 | ... V63: {=IF(V$5="","",_xlfn.IFS(V$6="Export",LOOKUP(V$5,'RM Prices'!$C$4:$BJ$4,'RM Prices'!$C22:$BJ22),V$6="Domestic",LOOKUP(V$5,'RM Prices'!$C$31:$BJ$31,'RM Prices'!$C49:$BJ49)))} -> 230
B64: 34 | C64: RM Price | D64: Matt BOPP | E64: {=IF(E$5="","",_xlfn.IFS(E$6="Export",LOOKUP(E$5,'RM Prices'!$C$4:$BJ$4,'RM Prices'!$C23:$BJ23),E$6="Domestic",LOOKUP(E$5,'RM Prices'!$C$31:$BJ$31,'RM Prices'!$C50:$BJ50)))} -> 250 | F64: {=IF(F$5="","",_xlfn.IFS(F$6="Export",LOOKUP(F$5,'RM Prices'!$C$4:$BJ$4,'RM Prices'!$C23:$BJ23),F$6="Domestic",LOOKUP(F$5,'RM Prices'!$C$31:$BJ$31,'RM Prices'!$C50:$BJ50)))} -> 250 | G64: {=IF(G$5="","",_xlfn.IFS(G$6="Export",LOOKUP(G$5,'RM Prices'!$C$4:$BJ$4,'RM Prices'!$C23:$BJ23),G$6="Domestic",LOOKUP(G$5,'RM Prices'!$C$31:$BJ$31,'RM Prices'!$C50:$BJ50)))} -> 250 | H64: {=IF(H$5="","",_xlfn.IFS(H$6="Export",LOOKUP(H$5,'RM Prices'!$C$4:$BJ$4,'RM Prices'!$C23:$BJ23),H$6="Domestic",LOOKUP(H$5,'RM Prices'!$C$31:$BJ$31,'RM Prices'!$C50:$BJ50)))} -> 250 | I64: {=IF(I$5="","",_xlfn.IFS(I$6="Export",LOOKUP(I$5,'RM Prices'!$C$4:$BJ$4,'RM Prices'!$C23:$BJ23),I$6="Domestic",LOOKUP(I$5,'RM Prices'!$C$31:$BJ$31,'RM Prices'!$C50:$BJ50)))} -> 250 | J64: {=IF(J$5="","",_xlfn.IFS(J$6="Export",LOOKUP(J$5,'RM Prices'!$C$4:$BJ$4,'RM Prices'!$C23:$BJ23),J$6="Domestic",LOOKUP(J$5,'RM Prices'!$C$31:$BJ$31,'RM Prices'!$C50:$BJ50)))} -> 250 | K64: {=IF(K$5="","",_xlfn.IFS(K$6="Export",LOOKUP(K$5,'RM Prices'!$C$4:$BJ$4,'RM Prices'!$C23:$BJ23),K$6="Domestic",LOOKUP(K$5,'RM Prices'!$C$31:$BJ$31,'RM Prices'!$C50:$BJ50)))} -> 250 | L64: {=IF(L$5="","",_xlfn.IFS(L$6="Export",LOOKUP(L$5,'RM Prices'!$C$4:$BJ$4,'RM Prices'!$C23:$BJ23),L$6="Domestic",LOOKUP(L$5,'RM Prices'!$C$31:$BJ$31,'RM Prices'!$C50:$BJ50)))} -> 250 | ... V64: {=IF(V$5="","",_xlfn.IFS(V$6="Export",LOOKUP(V$5,'RM Prices'!$C$4:$BJ$4,'RM Prices'!$C23:$BJ23),V$6="Domestic",LOOKUP(V$5,'RM Prices'!$C$31:$BJ$31,'RM Prices'!$C50:$BJ50)))} -> 250
B65: 35 | C65: RM Price | D65: Metalised BOPP | E65: {=IF(E$5="","",_xlfn.IFS(E$6="Export",LOOKUP(E$5,'RM Prices'!$C$4:$BJ$4,'RM Prices'!$C24:$BJ24),E$6="Domestic",LOOKUP(E$5,'RM Prices'!$C$31:$BJ$31,'RM Prices'!$C51:$BJ51)))} -> 250 | F65: {=IF(F$5="","",_xlfn.IFS(F$6="Export",LOOKUP(F$5,'RM Prices'!$C$4:$BJ$4,'RM Prices'!$C24:$BJ24),F$6="Domestic",LOOKUP(F$5,'RM Prices'!$C$31:$BJ$31,'RM Prices'!$C51:$BJ51)))} -> 250 | G65: {=IF(G$5="","",_xlfn.IFS(G$6="Export",LOOKUP(G$5,'RM Prices'!$C$4:$BJ$4,'RM Prices'!$C24:$BJ24),G$6="Domestic",LOOKUP(G$5,'RM Prices'!$C$31:$BJ$31,'RM Prices'!$C51:$BJ51)))} -> 250 | H65: {=IF(H$5="","",_xlfn.IFS(H$6="Export",LOOKUP(H$5,'RM Prices'!$C$4:$BJ$4,'RM Prices'!$C24:$BJ24),H$6="Domestic",LOOKUP(H$5,'RM Prices'!$C$31:$BJ$31,'RM Prices'!$C51:$BJ51)))} -> 250 | I65: {=IF(I$5="","",_xlfn.IFS(I$6="Export",LOOKUP(I$5,'RM Prices'!$C$4:$BJ$4,'RM Prices'!$C24:$BJ24),I$6="Domestic",LOOKUP(I$5,'RM Prices'!$C$31:$BJ$31,'RM Prices'!$C51:$BJ51)))} -> 250 | J65: {=IF(J$5="","",_xlfn.IFS(J$6="Export",LOOKUP(J$5,'RM Prices'!$C$4:$BJ$4,'RM Prices'!$C24:$BJ24),J$6="Domestic",LOOKUP(J$5,'RM Prices'!$C$31:$BJ$31,'RM Prices'!$C51:$BJ51)))} -> 250 | K65: {=IF(K$5="","",_xlfn.IFS(K$6="Export",LOOKUP(K$5,'RM Prices'!$C$4:$BJ$4,'RM Prices'!$C24:$BJ24),K$6="Domestic",LOOKUP(K$5,'RM Prices'!$C$31:$BJ$31,'RM Prices'!$C51:$BJ51)))} -> 250 | L65: {=IF(L$5="","",_xlfn.IFS(L$6="Export",LOOKUP(L$5,'RM Prices'!$C$4:$BJ$4,'RM Prices'!$C24:$BJ24),L$6="Domestic",LOOKUP(L$5,'RM Prices'!$C$31:$BJ$31,'RM Prices'!$C51:$BJ51)))} -> 250 | ... V65: {=IF(V$5="","",_xlfn.IFS(V$6="Export",LOOKUP(V$5,'RM Prices'!$C$4:$BJ$4,'RM Prices'!$C24:$BJ24),V$6="Domestic",LOOKUP(V$5,'RM Prices'!$C$31:$BJ$31,'RM Prices'!$C51:$BJ51)))} -> 250
B66: 36 | C66: RM Price | D66: Adhesive | E66: {=IF(E$5="","",_xlfn.IFS(E$6="Export",LOOKUP(E$5,'RM Prices'!$C$4:$BJ$4,'RM Prices'!$C25:$BJ25),E$6="Domestic",LOOKUP(E$5,'RM Prices'!$C$31:$BJ$31,'RM Prices'!$C52:$BJ52)))} -> 320 | F66: {=IF(F$5="","",_xlfn.IFS(F$6="Export",LOOKUP(F$5,'RM Prices'!$C$4:$BJ$4,'RM Prices'!$C25:$BJ25),F$6="Domestic",LOOKUP(F$5,'RM Prices'!$C$31:$BJ$31,'RM Prices'!$C52:$BJ52)))} -> 320 | G66: {=IF(G$5="","",_xlfn.IFS(G$6="Export",LOOKUP(G$5,'RM Prices'!$C$4:$BJ$4,'RM Prices'!$C25:$BJ25),G$6="Domestic",LOOKUP(G$5,'RM Prices'!$C$31:$BJ$31,'RM Prices'!$C52:$BJ52)))} -> 320 | H66: {=IF(H$5="","",_xlfn.IFS(H$6="Export",LOOKUP(H$5,'RM Prices'!$C$4:$BJ$4,'RM Prices'!$C25:$BJ25),H$6="Domestic",LOOKUP(H$5,'RM Prices'!$C$31:$BJ$31,'RM Prices'!$C52:$BJ52)))} -> 320 | I66: {=IF(I$5="","",_xlfn.IFS(I$6="Export",LOOKUP(I$5,'RM Prices'!$C$4:$BJ$4,'RM Prices'!$C25:$BJ25),I$6="Domestic",LOOKUP(I$5,'RM Prices'!$C$31:$BJ$31,'RM Prices'!$C52:$BJ52)))} -> 320 | J66: {=IF(J$5="","",_xlfn.IFS(J$6="Export",LOOKUP(J$5,'RM Prices'!$C$4:$BJ$4,'RM Prices'!$C25:$BJ25),J$6="Domestic",LOOKUP(J$5,'RM Prices'!$C$31:$BJ$31,'RM Prices'!$C52:$BJ52)))} -> 320 | K66: {=IF(K$5="","",_xlfn.IFS(K$6="Export",LOOKUP(K$5,'RM Prices'!$C$4:$BJ$4,'RM Prices'!$C25:$BJ25),K$6="Domestic",LOOKUP(K$5,'RM Prices'!$C$31:$BJ$31,'RM Prices'!$C52:$BJ52)))} -> 320 | L66: {=IF(L$5="","",_xlfn.IFS(L$6="Export",LOOKUP(L$5,'RM Prices'!$C$4:$BJ$4,'RM Prices'!$C25:$BJ25),L$6="Domestic",LOOKUP(L$5,'RM Prices'!$C$31:$BJ$31,'RM Prices'!$C52:$BJ52)))} -> 320 | ... V66: {=IF(V$5="","",_xlfn.IFS(V$6="Export",LOOKUP(V$5,'RM Prices'!$C$4:$BJ$4,'RM Prices'!$C25:$BJ25),V$6="Domestic",LOOKUP(V$5,'RM Prices'!$C$31:$BJ$31,'RM Prices'!$C52:$BJ52)))} -> 320
B67: 37 | C67: RM Price | D67: Ink BOPP | E67: {=IF(E$5="","",_xlfn.IFS(E$6="Export",LOOKUP(E$5,'RM Prices'!$C$4:$BJ$4,'RM Prices'!$C26:$BJ26),E$6="Domestic",LOOKUP(E$5,'RM Prices'!$C$31:$BJ$31,'RM Prices'!$C53:$BJ53)))} -> 1600 | F67: {=IF(F$5="","",_xlfn.IFS(F$6="Export",LOOKUP(F$5,'RM Prices'!$C$4:$BJ$4,'RM Prices'!$C26:$BJ26),F$6="Domestic",LOOKUP(F$5,'RM Prices'!$C$31:$BJ$31,'RM Prices'!$C53:$BJ53)))} -> 1600 | G67: {=IF(G$5="","",_xlfn.IFS(G$6="Export",LOOKUP(G$5,'RM Prices'!$C$4:$BJ$4,'RM Prices'!$C26:$BJ26),G$6="Domestic",LOOKUP(G$5,'RM Prices'!$C$31:$BJ$31,'RM Prices'!$C53:$BJ53)))} -> 1600 | H67: {=IF(H$5="","",_xlfn.IFS(H$6="Export",LOOKUP(H$5,'RM Prices'!$C$4:$BJ$4,'RM Prices'!$C26:$BJ26),H$6="Domestic",LOOKUP(H$5,'RM Prices'!$C$31:$BJ$31,'RM Prices'!$C53:$BJ53)))} -> 1600 | I67: {=IF(I$5="","",_xlfn.IFS(I$6="Export",LOOKUP(I$5,'RM Prices'!$C$4:$BJ$4,'RM Prices'!$C26:$BJ26),I$6="Domestic",LOOKUP(I$5,'RM Prices'!$C$31:$BJ$31,'RM Prices'!$C53:$BJ53)))} -> 1600 | J67: {=IF(J$5="","",_xlfn.IFS(J$6="Export",LOOKUP(J$5,'RM Prices'!$C$4:$BJ$4,'RM Prices'!$C26:$BJ26),J$6="Domestic",LOOKUP(J$5,'RM Prices'!$C$31:$BJ$31,'RM Prices'!$C53:$BJ53)))} -> 1600 | K67: {=IF(K$5="","",_xlfn.IFS(K$6="Export",LOOKUP(K$5,'RM Prices'!$C$4:$BJ$4,'RM Prices'!$C26:$BJ26),K$6="Domestic",LOOKUP(K$5,'RM Prices'!$C$31:$BJ$31,'RM Prices'!$C53:$BJ53)))} -> 1600 | L67: {=IF(L$5="","",_xlfn.IFS(L$6="Export",LOOKUP(L$5,'RM Prices'!$C$4:$BJ$4,'RM Prices'!$C26:$BJ26),L$6="Domestic",LOOKUP(L$5,'RM Prices'!$C$31:$BJ$31,'RM Prices'!$C53:$BJ53)))} -> 1600 | ... V67: {=IF(V$5="","",_xlfn.IFS(V$6="Export",LOOKUP(V$5,'RM Prices'!$C$4:$BJ$4,'RM Prices'!$C26:$BJ26),V$6="Domestic",LOOKUP(V$5,'RM Prices'!$C$31:$BJ$31,'RM Prices'!$C53:$BJ53)))} -> 1600
B68: 38 | C68: RM Price | D68: Solvant BOPP | E68: {=IF(E$5="","",_xlfn.IFS(E$6="Export",LOOKUP(E$5,'RM Prices'!$C$4:$BJ$4,'RM Prices'!$C27:$BJ27),E$6="Domestic",LOOKUP(E$5,'RM Prices'!$C$31:$BJ$31,'RM Prices'!$C54:$BJ54)))} -> 170 | F68: {=IF(F$5="","",_xlfn.IFS(F$6="Export",LOOKUP(F$5,'RM Prices'!$C$4:$BJ$4,'RM Prices'!$C27:$BJ27),F$6="Domestic",LOOKUP(F$5,'RM Prices'!$C$31:$BJ$31,'RM Prices'!$C54:$BJ54)))} -> 170 | G68: {=IF(G$5="","",_xlfn.IFS(G$6="Export",LOOKUP(G$5,'RM Prices'!$C$4:$BJ$4,'RM Prices'!$C27:$BJ27),G$6="Domestic",LOOKUP(G$5,'RM Prices'!$C$31:$BJ$31,'RM Prices'!$C54:$BJ54)))} -> 170 | H68: {=IF(H$5="","",_xlfn.IFS(H$6="Export",LOOKUP(H$5,'RM Prices'!$C$4:$BJ$4,'RM Prices'!$C27:$BJ27),H$6="Domestic",LOOKUP(H$5,'RM Prices'!$C$31:$BJ$31,'RM Prices'!$C54:$BJ54)))} -> 170 | I68: {=IF(I$5="","",_xlfn.IFS(I$6="Export",LOOKUP(I$5,'RM Prices'!$C$4:$BJ$4,'RM Prices'!$C27:$BJ27),I$6="Domestic",LOOKUP(I$5,'RM Prices'!$C$31:$BJ$31,'RM Prices'!$C54:$BJ54)))} -> 170 | J68: {=IF(J$5="","",_xlfn.IFS(J$6="Export",LOOKUP(J$5,'RM Prices'!$C$4:$BJ$4,'RM Prices'!$C27:$BJ27),J$6="Domestic",LOOKUP(J$5,'RM Prices'!$C$31:$BJ$31,'RM Prices'!$C54:$BJ54)))} -> 170 | K68: {=IF(K$5="","",_xlfn.IFS(K$6="Export",LOOKUP(K$5,'RM Prices'!$C$4:$BJ$4,'RM Prices'!$C27:$BJ27),K$6="Domestic",LOOKUP(K$5,'RM Prices'!$C$31:$BJ$31,'RM Prices'!$C54:$BJ54)))} -> 170 | L68: {=IF(L$5="","",_xlfn.IFS(L$6="Export",LOOKUP(L$5,'RM Prices'!$C$4:$BJ$4,'RM Prices'!$C27:$BJ27),L$6="Domestic",LOOKUP(L$5,'RM Prices'!$C$31:$BJ$31,'RM Prices'!$C54:$BJ54)))} -> 170 | ... V68: {=IF(V$5="","",_xlfn.IFS(V$6="Export",LOOKUP(V$5,'RM Prices'!$C$4:$BJ$4,'RM Prices'!$C27:$BJ27),V$6="Domestic",LOOKUP(V$5,'RM Prices'!$C$31:$BJ$31,'RM Prices'!$C54:$BJ54)))} -> 170
D69: FABRIC Recipe
B70: 39 | C70: Fabric Reipe | D70: PP Rafia | E70: 92 | F70: 92 | G70: 92 | H70: 92 | I70: 92 | J70: 92 | K70: 92 | L70: 92 | M70: 92 | N70: 92 | O70: 92 | P70: 92 | Q70: 92 | R70: 90 | S70: 92 | T70: 97 | U70: 91 | V70: 92
B71: 40 | C71: Fabric Reipe | D71: HD Rafia
B72: 41 | C72: Fabric Reipe | D72: LLDPE F19010 Film
B73: 42 | C73: Fabric Reipe | D73: LDPE FY1005 Film
D74: LDPE 7 MFI
D75: PP H350FG
D76: LDPE 4 MFI
B77: 43 | C77: Fabric Reipe | D77: RP
B78: 44 | C78: Fabric Reipe | D78: Filler | E78: 5 | F78: 5 | G78: 5 | H78: 5 | I78: 5 | J78: 5 | K78: 5 | L78: 5 | M78: 5 | N78: 5 | O78: 5 | P78: 2 | Q78: 5 | R78: 4 | S78: 8 | T78: 0 | U78: 6 | V78: 8
B79: 45 | C79: Fabric Reipe | D79: TPT
B80: 46 | C80: Fabric Reipe | D80: UV | E80: 0 | F80: 0 | G80: 3 | H80: 3 | I80: 3 | J80: 3 | K80: 3 | L80: 3 | M80: 3 | N80: 3 | O80: 3 | P80: 3 | Q80: 3 | R80: 3 | S80: 0 | T80: 3 | U80: 3 | V80: 0
B81: 47 | C81: Fabric Reipe | D81: Col MB | E81: 3 | F81: 3 | G81: 0 | H81: 0 | I81: 0 | J81: 0 | K81: 0 | L81: 0 | M81: 0 | N81: 0 | O81: 0 | P81: 3 | Q81: 0 | R81: 3 | S81: 0 | T81: 0 | V81: 0
B82: 48 | C82: Fabric Reipe | D82: Black MB
B83: 49 | C83: Fabric Reipe | D83: Conductive Yarn
C84: Fabric RMC | D84: Fabric RMC | E84: {=IF(E$5="","",IFERROR(SUMPRODUCT(E70:E83*E46:E59)/SUM(E70:E83),0))} -> 132.11208 | F84: {=IF(F$5="","",IFERROR(SUMPRODUCT(F70:F83*F46:F59)/SUM(F70:F83),0))} -> 132.11208 | G84: {=IF(G$5="","",IFERROR(SUMPRODUCT(G70:G83*G46:G59)/SUM(G70:G83),0))} -> 133.01208 | H84: {=IF(H$5="","",IFERROR(SUMPRODUCT(H70:H83*H46:H59)/SUM(H70:H83),0))} -> 133.01208 | I84: {=IF(I$5="","",IFERROR(SUMPRODUCT(I70:I83*I46:I59)/SUM(I70:I83),0))} -> 133.01208 | J84: {=IF(J$5="","",IFERROR(SUMPRODUCT(J70:J83*J46:J59)/SUM(J70:J83),0))} -> 133.01208 | K84: {=IF(K$5="","",IFERROR(SUMPRODUCT(K70:K83*K46:K59)/SUM(K70:K83),0))} -> 133.01208 | L84: {=IF(L$5="","",IFERROR(SUMPRODUCT(L70:L83*L46:L59)/SUM(L70:L83),0))} -> 133.01208 | ... V84: {=IF(V$5="","",IFERROR(SUMPRODUCT(V70:V83*V46:V59)/SUM(V70:V83),0))} -> 125.81208
D85: Lamination Recipe
D86: PP Rafia
D87: HD Rafia
D88: LLDPE F19010 Film
D89: LDPE FY1005 Film
B90: 50 | C90: Coating Recp | D90: LDPE 7 MFI | E90: 20 | F90: 20 | G90: 25 | H90: 25 | I90: 25 | J90: 25 | K90: 25 | L90: 25 | M90: 25 | N90: 25 | O90: 25 | P90: 25 | Q90: 25 | R90: 25 | S90: 18 | T90: 18 | U90: 25 | V90: 25
B91: 51 | C91: Coating Recp | D91: PP H350FG | E91: 80 | F91: 80 | G91: 73 | H91: 73 | I91: 73 | J91: 73 | K91: 73 | L91: 73 | M91: 73 | N91: 73 | O91: 73 | P91: 73 | Q91: 73 | R91: 73 | S91: 82 | T91: 82 | U91: 73 | V91: 70
B92: 52 | C92: Coating Recp | D92: LDPE 4 MFI
B93: 53 | C93: Coating Recp | D93: RP
B94: 54 | C94: Coating Recp | D94: Filler
B95: 55 | C95: Coating Recp | D95: TPT
B96: 56 | C96: Coating Recp | D96: UV/Vistamax | G96: 2 | H96: 2 | I96: 2 | J96: 2 | K96: 2 | L96: 2 | M96: 2 | N96: 2 | O96: 2 | P96: 2 | Q96: 2 | R96: 2 | V96: 5
B97: 57 | C97: Coating Recp | D97: Col MB | E97: 0 | F97: 0 | G97: 0 | S97: 0 | T97: 0
B98: 58 | C98: Coating Recp | D98: Black MB
D99: Lamination RMC | E99: {=IF(E$5="","",IFERROR(SUMPRODUCT(E86:E98*E46:E58)/SUM(E86:E98),0))} -> 142.3776 | F99: {=IF(F$5="","",IFERROR(SUMPRODUCT(F86:F98*F46:F58)/SUM(F86:F98),0))} -> 142.3776 | G99: {=IF(G$5="","",IFERROR(SUMPRODUCT(G86:G98*G46:G58)/SUM(G86:G98),0))} -> 147.23972 | H99: {=IF(H$5="","",IFERROR(SUMPRODUCT(H86:H98*H46:H58)/SUM(H86:H98),0))} -> 147.23972 | I99: {=IF(I$5="","",IFERROR(SUMPRODUCT(I86:I98*I46:I58)/SUM(I86:I98),0))} -> 147.23972 | J99: {=IF(J$5="","",IFERROR(SUMPRODUCT(J86:J98*J46:J58)/SUM(J86:J98),0))} -> 147.23972 | K99: {=IF(K$5="","",IFERROR(SUMPRODUCT(K86:K98*K46:K58)/SUM(K86:K98),0))} -> 147.23972 | L99: {=IF(L$5="","",IFERROR(SUMPRODUCT(L86:L98*L46:L58)/SUM(L86:L98),0))} -> 147.23972 | ... V99: {=IF(V$5="","",IFERROR(SUMPRODUCT(V86:V98*V46:V58)/SUM(V86:V98),0))} -> 151.6028
D100: Liner
B101: 59 | C101: Liner Recp | D101: LLDPE F19010 Film | E101: 90 | F101: 90 | G101: 90 | H101: 90 | I101: 90 | J101: 90 | K101: 90 | L101: 90 | M101: 90 | N101: 90 | O101: 90 | P101: 90 | Q101: 90 | R101: 90 | S101: 90 | T101: 90 | U101: 90 | V101: 90
B102: 60 | C102: Liner Recp | D102: LDPE FY1005 Film | E102: 10 | F102: 10 | G102: 10 | H102: 10 | I102: 10 | J102: 10 | K102: 10 | L102: 10 | M102: 10 | N102: 10 | O102: 10 | P102: 10 | Q102: 10 | R102: 10 | S102: 10 | T102: 10 | U102: 10 | V102: 10
D103: LDPE 7 MFI
D104: PP H350FG
...

Sheet Filter CstWs DtWs
D1: Customer Name | E1: Desabag
D2: Date | E2: 46161
D3: Our Ref
C5: Print | D5: Date | E5: {=IFERROR(_xlfn.IFS(AND(E3="",E2="",E1=""),"Fill Customer Name",AND(E3="",E2=""),_xlfn._xlws.FILTER('Quote Exports'!D5:AX216,('Quote Exports'!D7:AX7=E1)),E3="",_xlfn._xlws.FILTER('Quote Exports'!D5:AX216,('Quote Exports'!D7:AX7=E1)*('Quote Exports'!D5:AX5=E2)),E3<>"",_xlfn._xlws.FILTER('Quote Exports'!D5:AX216,('Quote Exports'!D7:AX7=E1)*('Quote Exports'!D5:AX5=E2)*('Quote Exports'!D8:AX8=E3))),"Not Found")} -> 46161 | F5: 46161 | G5: 46161 | H5: 46161 | I5: 46161 | J5: 46161 | K5: 46161 | L5: 46161 | M5: 46161 | N5: 46161 | O5: 46161 | JF5: End
A6: =IF('Quote Exports'!C6="","",'Quote Exports'!C6) -> To Fill | D6: Sector | E6: Export | F6: Export | G6: Export | H6: Export | I6: Export | J6: Export | K6: Export | L6: Export | M6: Export | N6: Export | O6: Export | JF6: End
A7: =IF('Quote Exports'!C7="","",'Quote Exports'!C7) -> To Fill | D7: Customer | E7: Desabag | F7: Desabag | G7: Desabag | H7: Desabag | I7: Desabag | J7: Desabag | K7: Desabag | L7: Desabag | M7: Desabag | N7: Desabag | O7: Desabag | JF7: End
A8: =IF('Quote Exports'!C8="","",'Quote Exports'!C8) -> To Fill | D8: Our Ref | E8: 140X220 | F8: 140X220 | G8: 140X220 | H8: 140X220 | I8: 70X110 | J8: 40X60 | K8: 100X150 | L8: 60X100 | M8: 70X110 | N8: 90X130 | O8: 60X100 | JF8: End
A9: =IF('Quote Exports'!C9="","",'Quote Exports'!C9) -> To Fill | D9: Customer Ref | E9: 3.3002 | F9: 3.3004 | G9: 3.3006 | H9: 3.3011 | I9: 3.9001 | J9: 3.9003 | K9: 3.9004 | L9: 3.9005 | M9: 3.9008 | N9: 3.9014 | O9: 3.9015 | JF9: End
A10: =IF('Quote Exports'!C10="","",'Quote Exports'!C10) -> To Fill | D10: Type of Fabric/Bag | E10: Tubular Bag | F10: Tubular Bag | G10: Tubular Bag | H10: Tubular Bag | I10: Tubular Bag | J10: Tubular Bag | K10: Tubular Bag | L10: Tubular Bag | M10: Tubular Bag | N10: Tubular Bag | O10: Tubular Bag | JF10: End
A11: =IF('Quote Exports'!C11="","",'Quote Exports'!C11) -> Spec | D11: Fabric Colour | E11: MW | F11: MW | G11: MW | H11: MW | I11: MW | J11: MW | K11: MW | L11: MW | M11: MW | N11: Coloured | O11: MW | JF11: End
A12: =IF('Quote Exports'!C12="","",'Quote Exports'!C12) -> Spec | D12: Face Width Cm | E12: 140 | F12: 140 | G12: 140 | H12: 140 | I12: 70 | J12: 40 | K12: 100 | L12: 60 | M12: 70 | N12: 90 | O12: 60 | JF12: End
A13: =IF('Quote Exports'!C13="","",'Quote Exports'!C13) -> Spec | D13: Gusset Cm (Both Side) Cm | E13: 0 | F13: 0 | G13: 0 | H13: 0 | I13: 0 | J13: 0 | K13: 0 | L13: 0 | M13: 0 | N13: 0 | O13: 0 | JF13: End
A14: =IF('Quote Exports'!C14="","",'Quote Exports'!C14) -> Spec | D14: Length Cm | E14: 220 | F14: 220 | G14: 220 | H14: 220 | I14: 110 | J14: 60 | K14: 150 | L14: 100 | M14: 110 | N14: 130 | O14: 100 | JF14: End
A15: =IF('Quote Exports'!C15="","",'Quote Exports'!C15) -> Spec | D15: Top | E15: Hemmed | F15: Hemmed | G15: Hemmed | H15: Hemmed | I15: Hemmed | J15: Hemmed | K15: Hemmed | L15: Hemmed | M15: Hemmed | N15: Hemmed | O15: Hemmed | JF15: End
A16: =IF('Quote Exports'!C16="","",'Quote Exports'!C16) | D16: Cut Length Cm | E16: 228 | F16: 228 | G16: 228 | H16: 228 | I16: 118 | J16: 68 | K16: 158 | L16: 108 | M16: 118 | N16: 138 | O16: 108 | JF16: End
A17: =IF('Quote Exports'!C17="","",'Quote Exports'!C17) -> Spec | D17: Total Weight Gram | E17: 673.27 | F17: 609.43 | G17: 539.43 | H17: 409.93 | I17: 114.56 | J17: 46.61 | K17: 274.58 | L17: 88.71 | M17: 148.55 | N17: 219.25 | O17: 80.71 | JF17: End
D18: Fabric GSM TBM | E18: 70 | F18: 60 | G18: 60 | H18: 60 | I18: 60 | J18: 60 | K18: 60 | L18: 60 | M18: 60 | N18: 60 | O18: 60 | JF18: End
D19: Calculated Weight | E19: 673.26925 | F19: 609.42925 | G19: 539.42925 | H19: 409.92525 | I19: 114.56262 | J19: 46.607213 | K19: 274.58203 | L19: 88.71082 | M19: 148.54662 | N19: 219.25023 | O19: 80.71082 | JF19: End
A20: =IF('Quote Exports'!C20="","",'Quote Exports'!C20) | D20: Gross Width Cm | E20: 140 | F20: 140 | G20: 140 | H20: 140 | I20: 70 | J20: 40 | K20: 100 | L20: 60 | M20: 70 | N20: 90 | O20: 60 | JF20: End
A21: =IF('Quote Exports'!C21="","",'Quote Exports'!C21) -> Spec | D21: Liner Micron | E21: 0 | F21: 0 | G21: 0 | H21: 0 | I21: 0 | J21: 0 | K21: 0 | L21: 0 | M21: 0 | N21: 0 | O21: 0 | JF21: End
A22: =IF('Quote Exports'!C22="","",'Quote Exports'!C22) -> Spec | D22: Glossy BOPP Micron | E22: 0 | F22: 0 | G22: 0 | H22: 0 | I22: 0 | J22: 0 | K22: 0 | L22: 0 | M22: 0 | N22: 0 | O22: 0 | JF22: End
A23: =IF('Quote Exports'!C23="","",'Quote Exports'!C23) -> Spec | D23: Matt BOPP Micron | E23: 0 | F23: 0 | G23: 0 | H23: 0 | I23: 0 | J23: 0 | K23: 0 | L23: 0 | M23: 0 | N23: 0 | O23: 0 | JF23: End
A24: =IF('Quote Exports'!C24="","",'Quote Exports'!C24) -> Spec | D24: Metalised BOPP Micron | E24: 0 | F24: 0 | G24: 0 | H24: 0 | I24: 0 | J24: 0 | K24: 0 | L24: 0 | M24: 0 | N24: 0 | O24: 0 | JF24: End
A25: =IF('Quote Exports'!C27="","",'Quote Exports'!C27) -> Spec | D25: White Paper GSM | E25: 0 | F25: 0 | G25: 0 | H25: 0 | I25: 0 | J25: 0 | K25: 0 | L25: 0 | M25: 0 | N25: 0 | O25: 0 | JF25: End
A26: =IF('Quote Exports'!C28="","",'Quote Exports'!C28) -> Spec | D26: Brown Paper GSM | E26: 0 | F26: 0 | G26: 0 | H26: 0 | I26: 0 | J26: 0 | K26: 0 | L26: 0 | M26: 0 | N26: 0 | O26: 0 | JF26: End
A27: =IF('Quote Exports'!C29="","",'Quote Exports'!C29) | D27: Adhesive GSM (Solvant Less) | E27: 0 | F27: 0 | G27: 0 | H27: 0 | I27: 0 | J27: 0 | K27: 0 | L27: 0 | M27: 0 | N27: 0 | O27: 0 | JF27: End
A28: =IF('Quote Exports'!C30="","",'Quote Exports'!C30) -> Spec | D28: Ink GSM | E28: 0 | F28: 0 | G28: 0 | H28: 0 | I28: 0 | J28: 0 | K28: 0 | L28: 0 | M28: 0 | N28: 0 | O28: 0 | JF28: End
A29: =IF('Quote Exports'!C31="","",'Quote Exports'!C31) -> Spec | D29: Back Seam Coating Gr/Meter | E29: 0 | F29: 0 | G29: 0 | H29: 0 | I29: 0 | J29: 0 | K29: 0 | L29: 0 | M29: 0 | N29: 0 | O29: 0 | JF29: End
A30: =IF('Quote Exports'!C32="","",'Quote Exports'!C32) | D30: Coating GSM | E30: 20 | F30: 20 | G30: 20 | H30: 0 | I30: 0 | J30: 0 | K30: 20 | L30: 0 | M30: 20 | N30: 20 | O30: 0 | JF30: End
A31: =IF('Quote Exports'!C33="","",'Quote Exports'!C33) | D31: Handle | E31: 90 | F31: 90 | G31: 20 | H31: 20 | I31: 12 | J31: 12 | K31: 15.6 | L31: 8 | M31: 12 | N31: 15 | O31: 0 | JF31: End
A32: =IF('Quote Exports'!C34="","",'Quote Exports'!C34) | D32: Easy Open | E32: 0 | F32: 0 | G32: 0 | H32: 0 | I32: 0 | J32: 0 | K32: 0 | L32: 0 | M32: 0 | N32: 0 | O32: 0 | JF32: End
A33: =IF('Quote Exports'!C35="","",'Quote Exports'!C35) | D33: Liner Wt | E33: 0 | F33: 0 | G33: 0 | H33: 0 | I33: 0 | J33: 0 | K33: 0 | L33: 0 | M33: 0 | N33: 0 | O33: 0 | JF33: End
A34: =IF('Quote Exports'!C36="","",'Quote Exports'!C36) | D34: Glossy BOPP Wt | E34: 0 | F34: 0 | G34: 0 | H34: 0 | I34: 0 | J34: 0 | K34: 0 | L34: 0 | M34: 0 | N34: 0 | O34: 0 | JF34: End
A35: =IF('Quote Exports'!C39="","",'Quote Exports'!C39) | D35: Matt BOPP Wt | E35: 0 | F35: 0 | G35: 0 | H35: 0 | I35: 0 | J35: 0 | K35: 0 | L35: 0 | M35: 0 | N35: 0 | O35: 0 | JF35: End
A36: =IF('Quote Exports'!C40="","",'Quote Exports'!C40) | D36: Metalised BOPP Wt | E36: 0 | F36: 0 | G36: 0 | H36: 0 | I36: 0 | J36: 0 | K36: 0 | L36: 0 | M36: 0 | N36: 0 | O36: 0 | JF36: End
A37: =IF('Quote Exports'!C41="","",'Quote Exports'!C41) | D37: White Paper Wt | E37: 0 | F37: 0 | G37: 0 | H37: 0 | I37: 0 | J37: 0 | K37: 0 | L37: 0 | M37: 0 | N37: 0 | O37: 0 | JF37: End
A38: =IF('Quote Exports'!C42="","",'Quote Exports'!C42) | D38: Brown Paper Wt | E38: 0 | F38: 0 | G38: 0 | H38: 0 | I38: 0 | J38: 0 | K38: 0 | L38: 0 | M38: 0 | N38: 0 | O38: 0 | JF38: End
A39: =IF('Quote Exports'!C43="","",'Quote Exports'!C43) | D39: Adhesive Wt | E39: 0 | F39: 0 | G39: 0 | H39: 0 | I39: 0 | J39: 0 | K39: 0 | L39: 0 | M39: 0 | N39: 0 | O39: 0 | JF39: End
A40: =IF('Quote Exports'!C44="","",'Quote Exports'!C44) | D40: Ink Wt | E40: 0 | F40: 0 | G40: 0 | H40: 0 | I40: 0 | J40: 0 | K40: 0 | L40: 0 | M40: 0 | N40: 0 | O40: 0 | JF40: End
A41: =IF('Quote Exports'!C45="","",'Quote Exports'!C45) | B41: 1 | D41: Back Seam Coating Weight | E41: 0 | F41: 0 | G41: 0 | H41: 0 | I41: 0 | J41: 0 | K41: 0 | L41: 0 | M41: 0 | N41: 0 | O41: 0 | JF41: End
A42: =IF('Quote Exports'!C46="","",'Quote Exports'!C46) -> RM Price | B42: 1 | D42: Coating Wt | E42: 129.504 | F42: 129.504 | G42: 129.504 | H42: 0 | I42: 0 | J42: 0 | K42: 64.464 | L42: 0 | M42: 33.984 | N42: 50.784 | O42: 0 | JF42: End
A43: =IF('Quote Exports'!C47="","",'Quote Exports'!C47) -> RM Price | D43: Thread Wt | E43: 6.8852459 | F43: 6.8852459 | G43: 6.8852459 | H43: 6.8852459 | I43: 3.442623 | J43: 1.9672131 | K43: 4.9180328 | L43: 2.9508197 | M43: 3.442623 | N43: 4.4262295 | O43: 2.9508197 | JF43: End
A44: =IF('Quote Exports'!C48="","",'Quote Exports'!C48) -> RM Price | D44: Fabric Wt | E44: 446.88075 | F44: 383.04075 | G44: 383.04075 | H44: 383.04475 | I44: 99.117377 | J44: 32.642787 | K44: 189.59797 | L44: 77.75918 | M44: 99.123377 | N44: 149.03977 | O44: 77.75918 | JF44: End
A45: =IF('Quote Exports'!C49="","",'Quote Exports'!C49) -> RM Price | D45: Fabric GSM | E45: 70 | F45: 60 | G45: 60 | H45: 60 | I45: 60 | J45: 60.01 | K45: 60 | L45: 60 | M45: 60 | N45: 60 | O45: 60 | JF45: End
A46: =IF('Quote Exports'!C50="","",'Quote Exports'!C50) -> RM Price | D46: PP Rafia | E46: 133.274 | F46: 133.274 | G46: 133.274 | H46: 133.274 | I46: 133.274 | J46: 133.274 | K46: 133.274 | L46: 133.274 | M46: 133.274 | N46: 133.274 | O46: 133.274 | JF46: End
A47: =IF('Quote Exports'!C51="","",'Quote Exports'!C51) -> RM Price | D47: HD Rafia | E47: 155.837 | F47: 155.837 | G47: 155.837 | H47: 155.837 | I47: 155.837 | J47: 155.837 | K47: 155.837 | L47: 155.837 | M47: 155.837 | N47: 155.837 | O47: 155.837 | JF47: End
A48: =IF('Quote Exports'!C52="","",'Quote Exports'!C52) -> RM Price | D48: LLDPE F19010 Film | E48: 141.084 | F48: 141.084 | G48: 141.084 | H48: 141.084 | I48: 141.084 | J48: 141.084 | K48: 141.084 | L48: 141.084 | M48: 141.084 | N48: 141.084 | O48: 141.084 | JF48: End
A49: =IF('Quote Exports'!C53="","",'Quote Exports'!C53) -> RM Price | D49: LDPE FY1005 Film | E49: 170.884 | F49: 170.884 | G49: 170.884 | H49: 170.884 | I49: 170.884 | J49: 170.884 | K49: 170.884 | L49: 170.884 | M49: 170.884 | N49: 170.884 | O49: 170.884 | JF49: End
A50: =IF('Quote Exports'!C54="","",'Quote Exports'!C54) -> RM Price | B50: 1 | D50: LDPE 7 MFI | E50: 173.632 | F50: 173.632 | G50: 173.632 | H50: 173.632 | I50: 173.632 | J50: 173.632 | K50: 173.632 | L50: 173.632 | M50: 173.632 | N50: 173.632 | O50: 173.632 | JF50: End
A51: =IF('Quote Exports'!C55="","",'Quote Exports'!C55) -> RM Price | D51: PP H350FG | E51: 134.564 | F51: 134.564 | G51: 134.564 | H51: 134.564 | I51: 134.564 | J51: 134.564 | K51: 134.564 | L51: 134.564 | M51: 134.564 | N51: 134.564 | O51: 134.564 | JF51: End
A52: =IF('Quote Exports'!C56="","",'Quote Exports'!C56) -> RM Price | D52: LDPE 4 MFI | E52: 170.884 | F52: 170.884 | G52: 170.884 | H52: 170.884 | I52: 170.884 | J52: 170.884 | K52: 170.884 | L52: 170.884 | M52: 170.884 | N52: 170.884 | O52: 170.884 | JF52: End
A53: =IF('Quote Exports'!C57="","",'Quote Exports'!C57) -> RM Price | B53: 1 | D53: RP | E53: 70 | F53: 70 | G53: 70 | H53: 70 | I53: 70 | J53: 70 | K53: 70 | L53: 70 | M53: 70 | N53: 70 | O53: 70 | JF53: End
A54: =IF('Quote Exports'!C58="","",'Quote Exports'!C58) -> RM Price | D54: Filler | E54: 40 | F54: 40 | G54: 40 | H54: 40 | I54: 40 | J54: 40 | K54: 40 | L54: 40 | M54: 40 | N54: 40 | O54: 40 | JF54: End
A55: =IF('Quote Exports'!C59="","",'Quote Exports'!C59) -> RM Price | D55: TPT | E55: 56 | F55: 56 | G55: 56 | H55: 56 | I55: 56 | J55: 56 | K55: 56 | L55: 56 | M55: 56 | N55: 56 | O55: 56 | JF55: End
A56: =IF('Quote Exports'!C60="","",'Quote Exports'!C60) -> RM Price | D56: UV | E56: 280 | F56: 280 | G56: 280 | H56: 280 | I56: 280 | J56: 280 | K56: 280 | L56: 280 | M56: 280 | N56: 280 | O56: 280 | JF56: End
A57: =IF('Quote Exports'!C63="","",'Quote Exports'!C63) -> RM Price | D57: Col MB | E57: 250 | F57: 250 | G57: 250 | H57: 250 | I57: 250 | J57: 250 | K57: 250 | L57: 250 | M57: 250 | N57: 250 | O57: 250 | JF57: End
A58: =IF('Quote Exports'!C64="","",'Quote Exports'!C64) -> RM Price | D58: Black MB | E58: 160 | F58: 160 | G58: 160 | H58: 160 | I58: 160 | J58: 160 | K58: 160 | L58: 160 | M58: 160 | N58: 160 | O58: 160 | JF58: End
A59: =IF('Quote Exports'!C65="","",'Quote Exports'!C65) -> RM Price | D59: Conductive Yarn | E59: 600 | F59: 600 | G59: 600 | H59: 600 | I59: 600 | J59: 600 | K59: 600 | L59: 600 | M59: 600 | N59: 600 | O59: 600 | JF59: End
A60: =IF('Quote Exports'!C66="","",'Quote Exports'!C66) -> RM Price | D60: Back Seam Coating RM | E60: 150.5562 | F60: 150.5562 | G60: 150.5562 | H60: 150.5562 | I60: 150.5562 | J60: 150.5562 | K60: 150.5562 | L60: 150.5562 | M60: 150.5562 | N60: 150.5562 | O60: 150.5562 | JF60: End
A61: =IF('Quote Exports'!C67="","",'Quote Exports'!C67) -> RM Price | D61: White Paper | E61: 83 | F61: 83 | G61: 83 | H61: 83 | I61: 83 | J61: 83 | K61: 83 | L61: 83 | M61: 83 | N61: 83 | O61: 83 | JF61: End
A62: =IF('Quote Exports'!C68="","",'Quote Exports'!C68) -> RM Price | D62: Brown Paper | E62: 80 | F62: 80 | G62: 80 | H62: 80 | I62: 80 | J62: 80 | K62: 80 | L62: 80 | M62: 80 | N62: 80 | O62: 80 | JF62: End
A63: =IF('Quote Exports'!C69="","",'Quote Exports'!C69) | D63: Glossy BOPP | E63: 230 | F63: 230 | G63: 230 | H63: 230 | I63: 230 | J63: 230 | K63: 230 | L63: 230 | M63: 230 | N63: 230 | O63: 230 | JF63: End
A64: =IF('Quote Exports'!C70="","",'Quote Exports'!C70) -> Fabric Reipe | B64: 1 | D64: Matt BOPP | E64: 250 | F64: 250 | G64: 250 | H64: 250 | I64: 250 | J64: 250 | K64: 250 | L64: 250 | M64: 250 | N64: 250 | O64: 250 | JF64: End
A65: =IF('Quote Exports'!C71="","",'Quote Exports'!C71) -> Fabric Reipe | D65: Metalised BOPP | E65: 250 | F65: 250 | G65: 250 | H65: 250 | I65: 250 | J65: 250 | K65: 250 | L65: 250 | M65: 250 | N65: 250 | O65: 250 | JF65: End
A66: =IF('Quote Exports'!C72="","",'Quote Exports'!C72) -> Fabric Reipe | D66: Adhesive | E66: 320 | F66: 320 | G66: 320 | H66: 320 | I66: 320 | J66: 320 | K66: 320 | L66: 320 | M66: 320 | N66: 320 | O66: 320 | JF66: End
A67: =IF('Quote Exports'!C73="","",'Quote Exports'!C73) -> Fabric Reipe | D67: Ink BOPP | E67: 1600 | F67: 1600 | G67: 1600 | H67: 1600 | I67: 1600 | J67: 1600 | K67: 1600 | L67: 1600 | M67: 1600 | N67: 1600 | O67: 1600 | JF67: End
A68: =IF('Quote Exports'!C74="","",'Quote Exports'!C74) | D68: Solvant BOPP | E68: 170 | F68: 170 | G68: 170 | H68: 170 | I68: 170 | J68: 170 | K68: 170 | L68: 170 | M68: 170 | N68: 170 | O68: 170 | JF68: End
A69: =IF('Quote Exports'!C75="","",'Quote Exports'!C75) | D69: FABRIC Recipe | E69: 0 | F69: 0 | G69: 0 | H69: 0 | I69: 0 | J69: 0 | K69: 0 | L69: 0 | M69: 0 | N69: 0 | O69: 0 | JF69: End
A70: =IF('Quote Exports'!C76="","",'Quote Exports'!C76) | D70: PP Rafia | E70: 92 | F70: 92 | G70: 92 | H70: 92 | I70: 92 | J70: 92 | K70: 92 | L70: 92 | M70: 92 | N70: 92 | O70: 92 | JF70: End
A71: =IF('Quote Exports'!C77="","",'Quote Exports'!C77) -> Fabric Reipe | D71: HD Rafia | E71: 0 | F71: 0 | G71: 0 | H71: 0 | I71: 0 | J71: 0 | K71: 0 | L71: 0 | M71: 0 | N71: 0 | O71: 0 | JF71: End
A72: =IF('Quote Exports'!C78="","",'Quote Exports'!C78) -> Fabric Reipe | B72: 1 | D72: LLDPE F19010 Film | E72: 0 | F72: 0 | G72: 0 | H72: 0 | I72: 0 | J72: 0 | K72: 0 | L72: 0 | M72: 0 | N72: 0 | O72: 0 | JF72: End
A73: =IF('Quote Exports'!C79="","",'Quote Exports'!C79) -> Fabric Reipe | D73: LDPE FY1005 Film | E73: 0 | F73: 0 | G73: 0 | H73: 0 | I73: 0 | J73: 0 | K73: 0 | L73: 0 | M73: 0 | N73: 0 | O73: 0 | JF73: End
A74: =IF('Quote Exports'!C80="","",'Quote Exports'!C80) -> Fabric Reipe | B74: 1 | D74: LDPE 7 MFI | E74: 0 | F74: 0 | G74: 0 | H74: 0 | I74: 0 | J74: 0 | K74: 0 | L74: 0 | M74: 0 | N74: 0 | O74: 0 | JF74: End
A75: =IF('Quote Exports'!C81="","",'Quote Exports'!C81) -> Fabric Reipe | B75: 1 | D75: PP H350FG | E75: 0 | F75: 0 | G75: 0 | H75: 0 | I75: 0 | J75: 0 | K75: 0 | L75: 0 | M75: 0 | N75: 0 | O75: 0 | JF75: End
A76: =IF('Quote Exports'!C82="","",'Quote Exports'!C82) -> Fabric Reipe | D76: LDPE 4 MFI | E76: 0 | F76: 0 | G76: 0 | H76: 0 | I76: 0 | J76: 0 | K76: 0 | L76: 0 | M76: 0 | N76: 0 | O76: 0 | JF76: End
A77: =IF('Quote Exports'!C83="","",'Quote Exports'!C83) -> Fabric Reipe | D77: RP | E77: 0 | F77: 0 | G77: 0 | H77: 0 | I77: 0 | J77: 0 | K77: 0 | L77: 0 | M77: 0 | N77: 0 | O77: 0 | JF77: End
A78: =IF('Quote Exports'!#REF!="","",'Quote Exports'!#REF!) -> #REF! | D78: Filler | E78: 5 | F78: 5 | G78: 5 | H78: 5 | I78: 5 | J78: 5 | K78: 5 | L78: 5 | M78: 5 | N78: 2 | O78: 5 | JF78: End
A79: =IF('Quote Exports'!#REF!="","",'Quote Exports'!#REF!) -> #REF! | D79: TPT | E79: 0 | F79: 0 | G79: 0 | H79: 0 | I79: 0 | J79: 0 | K79: 0 | L79: 0 | M79: 0 | N79: 0 | O79: 0 | JF79: End
A80: =IF('Quote Exports'!#REF!="","",'Quote Exports'!#REF!) -> #REF! | D80: UV | E80: 3 | F80: 3 | G80: 3 | H80: 3 | I80: 3 | J80: 3 | K80: 3 | L80: 3 | M80: 3 | N80: 3 | O80: 3 | JF80: End
A81: =IF('Quote Exports'!#REF!="","",'Quote Exports'!#REF!) -> #REF! | D81: Col MB | E81: 0 | F81: 0 | G81: 0 | H81: 0 | I81: 0 | J81: 0 | K81: 0 | L81: 0 | M81: 0 | N81: 3 | O81: 0 | JF81: End
A82: =IF('Quote Exports'!#REF!="","",'Quote Exports'!#REF!) -> #REF! | D82: Black MB | E82: 0 | F82: 0 | G82: 0 | H82: 0 | I82: 0 | J82: 0 | K82: 0 | L82: 0 | M82: 0 | N82: 0 | O82: 0 | JF82: End
A83: =IF('Quote Exports'!#REF!="","",'Quote Exports'!#REF!) -> #REF! | D83: Conductive Yarn | E83: 0 | F83: 0 | G83: 0 | H83: 0 | I83: 0 | J83: 0 | K83: 0 | L83: 0 | M83: 0 | N83: 0 | O83: 0 | JF83: End
A84: =IF('Quote Exports'!#REF!="","",'Quote Exports'!#REF!) -> #REF! | D84: Fabric RMC | E84: 133.01208 | F84: 133.01208 | G84: 133.01208 | H84: 133.01208 | I84: 133.01208 | J84: 133.01208 | K84: 133.01208 | L84: 133.01208 | M84: 133.01208 | N84: 139.31208 | O84: 133.01208 | JF84: End
A85: =IF('Quote Exports'!C84="","",'Quote Exports'!C84) -> Fabric RMC | B85: 1 | D85: Lamination Recipe | E85: 0 | F85: 0 | G85: 0 | H85: 0 | I85: 0 | J85: 0 | K85: 0 | L85: 0 | M85: 0 | N85: 0 | O85: 0 | JF85: End
A86: =IF('Quote Exports'!C85="","",'Quote Exports'!C85) | D86: PP Rafia | E86: 0 | F86: 0 | G86: 0 | H86: 0 | I86: 0 | J86: 0 | K86: 0 | L86: 0 | M86: 0 | N86: 0 | O86: 0 | JF86: End
A87: =IF('Quote Exports'!C86="","",'Quote Exports'!C86) | D87: HD Rafia | E87: 0 | F87: 0 | G87: 0 | H87: 0 | I87: 0 | J87: 0 | K87: 0 | L87: 0 | M87: 0 | N87: 0 | O87: 0 | JF87: End
A88: =IF('Quote Exports'!C87="","",'Quote Exports'!C87) | D88: LLDPE F19010 Film | E88: 0 | F88: 0 | G88: 0 | H88: 0 | I88: 0 | J88: 0 | K88: 0 | L88: 0 | M88: 0 | N88: 0 | O88: 0 | JF88: End
A89: =IF('Quote Exports'!C88="","",'Quote Exports'!C88) | D89: LDPE FY1005 Film | E89: 0 | F89: 0 | G89: 0 | H89: 0 | I89: 0 | J89: 0 | K89: 0 | L89: 0 | M89: 0 | N89: 0 | O89: 0 | JF89: End
A90: =IF('Quote Exports'!C89="","",'Quote Exports'!C89) | D90: LDPE 7 MFI | E90: 25 | F90: 25 | G90: 25 | H90: 25 | I90: 25 | J90: 25 | K90: 25 | L90: 25 | M90: 25 | N90: 25 | O90: 25 | JF90: End
A91: =IF('Quote Exports'!C90="","",'Quote Exports'!C90) -> Coating Recp | D91: PP H350FG | E91: 73 | F91: 73 | G91: 73 | H91: 73 | I91: 73 | J91: 73 | K91: 73 | L91: 73 | M91: 73 | N91: 73 | O91: 73 | JF91: End
A92: =IF('Quote Exports'!C91="","",'Quote Exports'!C91) -> Coating Recp | D92: LDPE 4 MFI | E92: 0 | F92: 0 | G92: 0 | H92: 0 | I92: 0 | J92: 0 | K92: 0 | L92: 0 | M92: 0 | N92: 0 | O92: 0 | JF92: End
A93: =IF('Quote Exports'!C92="","",'Quote Exports'!C92) -> Coating Recp | D93: RP | E93: 0 | F93: 0 | G93: 0 | H93: 0 | I93: 0 | J93: 0 | K93: 0 | L93: 0 | M93: 0 | N93: 0 | O93: 0 | JF93: End
A94: =IF('Quote Exports'!C93="","",'Quote Exports'!C93) -> Coating Recp | D94: Filler | E94: 0 | F94: 0 | G94: 0 | H94: 0 | I94: 0 | J94: 0 | K94: 0 | L94: 0 | M94: 0 | N94: 0 | O94: 0 | JF94: End
A95: =IF('Quote Exports'!C94="","",'Quote Exports'!C94) -> Coating Recp | D95: TPT | E95: 0 | F95: 0 | G95: 0 | H95: 0 | I95: 0 | J95: 0 | K95: 0 | L95: 0 | M95: 0 | N95: 0 | O95: 0 | JF95: End
A96: =IF('Quote Exports'!C95="","",'Quote Exports'!C95) -> Coating Recp | D96: UV/Vistamax | E96: 2 | F96: 2 | G96: 2 | H96: 2 | I96: 2 | J96: 2 | K96: 2 | L96: 2 | M96: 2 | N96: 2 | O96: 2 | JF96: End
A97: =IF('Quote Exports'!C96="","",'Quote Exports'!C96) -> Coating Recp | D97: Col MB | E97: 0 | F97: 0 | G97: 0 | H97: 0 | I97: 0 | J97: 0 | K97: 0 | L97: 0 | M97: 0 | N97: 0 | O97: 0 | JF97: End
... A99: =IF('Quote Exports'!C98="","",'Quote Exports'!C98) -> Coating Recp | D99: Lamination RMC | E99: 147.23972 | F99: 147.23972 | G99: 147.23972 | H99: 147.23972 | I99: 147.23972 | J99: 147.23972 | K99: 147.23972 | L99: 147.23972 | M99: 147.23972 | N99: 147.23972 | O99: 147.23972 | JF99: End
A100: =IF('Quote Exports'!#REF!="","",'Quote Exports'!#REF!) -> #REF! | D100: Liner | E100: 0 | F100: 0 | G100: 0 | H100: 0 | I100: 0 | J100: 0 | K100: 0 | L100: 0 | M100: 0 | N100: 0 | O100: 0 | JF100: End
A101: =IF('Quote Exports'!#REF!="","",'Quote Exports'!#REF!) -> #REF! | D101: LLDPE F19010 Film | E101: 90 | F101: 90 | G101: 90 | H101: 90 | I101: 90 | J101: 90 | K101: 90 | L101: 90 | M101: 90 | N101: 90 | O101: 90 | JF101: End
A102: =IF('Quote Exports'!#REF!="","",'Quote Exports'!#REF!) -> #REF! | D102: LDPE FY1005 Film | E102: 10 | F102: 10 | G102: 10 | H102: 10 | I102: 10 | J102: 10 | K102: 10 | L102: 10 | M102: 10 | N102: 10 | O102: 10 | JF102: End
...

Sheet Z Ad Star Bag
B4: Date | C4: 45536 | D4: 45536 | E4: 45585 | F4: 45594 | G4: 45647 | H4: 45647 | I4: 45647 | J4: 45656 | K4: 45656 | L4: 45656 | M4: 45656 | N4: 45667 | O4: 45667 | P4: 45667 | Q4: 45678 | R4: 45698 | S4: 45699 | T4: 45699 | U4: 45667 | V4: 45667 | W4: 45712 | X4: 45735 | Y4: 45736 | Z4: 45736 | AA4: 45736 | AB4: 45736 | AC4: 45775 | AD4: 45775 | AE4: 45775 | AF4: 45783 | AG4: 45790 | AH4: 45819 | AI4: 45819 | AJ4: 45853 | AK4: 45853 | AL4: 45853 | AM4: 45856 | AN4: 45868 | AO4: 45875 | AP4: 45922 | AQ4: 45929 | AR4: 45951 | AS4: 45951 | AT4: 45952 | AU4: 45958 | AV4: 45964 | AW4: 45964 | AX4: 45964 | AY4: 45964 | AZ4: 45967 | BA4: 45967 | BB4: 46001 | BC4: 46029 | BD4: 46029 | BE4: 46029 | BF4: 46029 | BG4: 46038 | BH4: 46038 | BI4: 46043 | BJ4: 46043 | BK4: 46045 | BL4: 46045 | BM4: 45647 | BN4: 46045 | BO4: 46045 | BP4: 46045 | BQ4: 46051 | BR4: 46051 | BS4: 46052 | BT4: 46052 | BU4: 46052 | BV4: 46054 | BW4: 46054 | BX4: 46056 | BY4: 46061 | BZ4: 46070 | CA4: 46071 | CB4: 46071 | CC4: 46078 | CD4: 46078 | CE4: 46079 | CF4: 46080 | CG4: 46087 | CH4: 46088 | CI4: 46088 | CJ4: 46088 | CK4: 46090 | CL4: 46090 | CM4: 46091 | CN4: 46092 | CO4: 46092 | CP4: 46092 | CQ4: 46093 | CR4: 46099 | CS4: 46099 | CT4: 46099 | CU4: 46099 | CV4: 46099 | CW4: 46099 | CX4: 46101 | CY4: 46108 | CZ4: 46108 | DA4: 46118 | DB4: 46120 | DC4: 46135 | DD4: 46135 | DE4: 46135 | DF4: 46136 | DG4: 46136 | DH4: 46136 | DI4: 46136 | DJ4: 46136 | DK4: 46139 | DL4: 46139 | DM4: 46139 | DN4: 46139 | DO4: 46140 | DP4: 46141 | DQ4: 46160 | DR4: 46161 | DS4: 46162 | DT4: 46164 | DU4: 46165
B5: Sector | C5: Export | D5: Export | E5: Export | F5: Export | G5: Export | H5: Export | I5: Export | J5: Export | K5: Export | L5: Export | M5: Export | N5: Export | O5: Export | P5: Export | Q5: Export | R5: Export | S5: Export | T5: Export | U5: Export | V5: Export | W5: Domestic | X5: Export | Y5: Export | Z5: Export | AA5: Export | AB5: Export | AC5: Export | AD5: Export | AE5: Export | AF5: Export | AG5: Export | AH5: Domestic | AI5: Export | AJ5: Export | AK5: Export | AL5: Export | AM5: Domestic | AN5: Domestic | AO5: Domestic | AP5: Export | AQ5: Export | AR5: Export | AS5: Export | AT5: Export | AU5: Export | AV5: Export | AW5: Domestic | AX5: Domestic | AY5: Domestic | AZ5: Export | BA5: Export | BB5: Export | BC5: Domestic | BD5: Export | BE5: Export | BF5: Export | BG5: Export | BH5: Export | BI5: Export | BJ5: Export | BK5: Domestic | BL5: Domestic | BM5: Domestic | BN5: Domestic | BO5: Domestic | BP5: Export | BQ5: Export | BR5: Export | BS5: Domestic | BT5: Export | BU5: Export | BV5: Export | BW5: Export | BX5: Export | BY5: Domestic | BZ5: Export | CA5: Export | CB5: Export | CC5: Export | CD5: Export | CE5: Export | CF5: Export | CG5: Export | CH5: Export | CI5: Export | CJ5: Export | CK5: Export | CL5: Export | CM5: Domestic | CN5: Export | CO5: Export | CP5: Export | CQ5: Export | CR5: Export | CS5: Export | CT5: Export | CU5: Export | CV5: Export | CW5: Export | CX5: Domestic | CY5: Domestic | CZ5: Export | DA5: Domestic | DB5: Domestic | DC5: Export | DD5: Export | DE5: Export | DF5: Export | DG5: Export | DH5: Export | DI5: Export | DJ5: Domestic | DK5: Export | DL5: Export | DM5: Export | DN5: Export | DO5: Export | DP5: Export | DQ5: Domestic | DR5: Export | DS5: Domestic | DT5: Domestic | DU5: Domestic
B6: Customer | C6: Fibco | D6: Fibco | E6: Terceirence | F6: Fibco | G6: Ravitalment | H6: Ravitalment | I6: Ravitalment | J6: Ravitalment | K6: Ravitalment | L6: Ravitalment | M6: Ravitalment | N6: FIBCO | O6: Nuvi | P6: Nuvi | Q6: Jordan Minerals | R6: Uma Dutta | S6: Akash Wadhwa | T6: Akash Wadhwa | U6: FIBCO | V6: Gravis Global | W6: Nirmal | X6: Condepols | Y6: Tisser | Z6: Uma Dutta | AA6: Uma Dutta | AB6: Uma Dutta | AC6: Ravitalment | AD6: Ravitalment | AE6: Ravitalment | AF6: HL-TopMix | AG6: HL-TopMix | AH6: Sunil SHarma | AI6: Sunil SHarma | AJ6: JGL | AK6: JGL | AL6: JGL | AM6: Kyoson | AN6: Swastik | AO6: Amrfeo | AP6: Kenz Jordan | AQ6: Nirmal | AR6: Ameriglobe | AS6: Caspian Ind | AT6: Ameriglobe | AU6: Material Motion | AV6: SafeSack | AW6: Swastik | AX6: Swastik | AY6: Swastik | AZ6: Chinguitty Cement | BA6: Chinguitty Cement | BB6: Agroszemek | BC6: Swastik | BD6: FIBCO | BE6: FIBCO | BF6: FIBCO | BG6: Sadlier | BH6: Sadlier | BI6: Sadlier | BJ6: Sadlier | BK6: Exleeir | BL6: Exleeir | BM6: Exleeir | BN6: Swastik | BO6: Swastik | BP6: SafeSack | BQ6: Fibco | BR6: Fibco | BS6: Amrfeo | BT6: Bluepack | BU6: Bluepack | BV6: Fibco | BW6: Fibco | BX6: Ameriglobe | BY6: Kypson | BZ6: Bluepack | CA6: Agroszemek | CB6: Agroszemek | CC6: NNZ | CD6: NNZ | CE6: Minini | CF6: FPS Italy | CG6: Terceirence | CH6: Mam Platre | CI6: KM Obaly | CJ6: FPS Italy | CK6: Agroszemek | CL6: Agroszemek | CM6: Amrfeo | CN6: Ravitalment | CO6: Ravitalment | CP6: Ravitalment | CQ6: KM Obaly | CR6: Minini | CS6: Chinguitty Cement | CT6: Chinguitty Cement | CU6: KM Obaly | CV6: Agroszemek | CW6: Agroszemek | CX6: Kypson | CY6: Kypson | CZ6: FPS Italy | DA6: Zaak | DB6: Kypson | DC6: Ambiflex | DD6: Ambiflex | DE6: Ambiflex | DF6: Sunil Sharma | DG6: Sunil Sharma | DH6: Sunil Sharma | DI6: Sunil Sharma | DJ6: Swastik | DK6: Chinguitty Cement | DL6: Chinguitty Cement | DM6: Norus | DN6: Chinguitty Cement | DO6: Mam Platre | DP6: Sadliers | DQ6: Amrfeo | DR6: Minini | DS6: Aman | DT6: Zaak | DU6: Bharat Carbonates
B7: Our Ref | G7: PS2020 | H7: PS2040 | I7: PS2030 | J7: PS2030 | K7: PS2030 | L7: PS2030 | M7: PS2030 | N7: Phosphea | O7: Double Colour | P7: Single Colour | U7: Phosphea | V7: Phosphea | AC7: PS-2020 | AD7: PS-2030 | AE7: PS-2040 | BD7: RAK | BE7: RAK | BF7: RAK | BQ7: 2543 | BR7: 2126 | BV7: 2543 | BW7: 2126 | CN7: PS-2020 | CO7: PS-2030 | CP7: PS-2040
B8: Customer Ref
B9: Bag Width | C9: 45 | D9: 45 | E9: 40 | F9: 36 | G9: 37.5 | H9: 37.5 | I9: 38 | J9: 50 | K9: 50 | L9: 45 | M9: 47 | N9: 50 | O9: 51 | P9: 51 | Q9: 50 | R9: 40.5 | S9: 38 | T9: 38 | U9: 50 | V9: =15*2.54 -> 38.1 | W9: 57 | X9: 50 | Y9: 40 | Z9: 40 | AA9: 50 | AB9: 35 | AC9: 37.5 | AD9: 38 | AE9: 37.5 | AF9: 51 | AG9: 54 | AH9: 55 | AI9: 55 | AJ9: 47 | AK9: 48 | AL9: 50 | AM9: =17*2.54 -> 43.18 | AN9: 45 | AO9: =18*2.54 -> 45.72 | AP9: 45 | AQ9: 48 | AR9: =22*2.54 -> 55.88 | AS9: 54 | AT9: =22*2.54 -> 55.88 | AU9: =23.5*2.54 -> 59.69 | AV9: 49 | AW9: 43 | AX9: 50 | AY9: 43 | AZ9: 51 | BA9: 48 | BB9: 50 | BC9: 43 | BD9: 51 | BE9: 48.5 | BF9: 41 | BG9: 46 | BH9: 52 | BI9: 46 | BJ9: 52 | BK9: 50 | BL9: 50 | BM9: 37.5 | BN9: 43 | BO9: 45 | BP9: 47 | BQ9: 51 | BR9: 48 | BS9: 45 | BT9: 54 | BU9: 50 | BV9: 51 | BW9: 48 | BX9: =22*2.54 -> 55.88 | BY9: 50 | BZ9: 50 | CA9: 50 | CB9: 55 | CC9: 51 | CD9: 51 | CE9: 50 | CF9: 48 | CG9: 40 | CH9: 50 | CI9: 45 | CJ9: 48 | CK9: 50 | CL9: 55 | CM9: 45 | CN9: 37.5 | CO9: 38 | CP9: 37.5 | CQ9: 45 | CR9: 50 | CS9: 51 | CT9: 48 | CU9: 45 | CV9: 50 | CW9: 55 | CX9: 58.5 | CY9: 50 | CZ9: 48 | DA9: 50 | DB9: 50 | DC9: 45 | DD9: 45 | DE9: 40 | DF9: 58 | DG9: 50 | DH9: 50 | DI9: 49 | DJ9: 43 | DK9: 51 | DL9: 48 | DM9: 44.5 | DN9: 51 | DO9: 50 | DP9: 48 | DQ9: 45 | DR9: 59 | DS9: 55 | DT9: 35 | DU9: 50
B10: Length | C10: 71 | D10: 61 | E10: 52 | F10: 57 | G10: 48 | H10: 48 | I10: 50 | J10: 52 | K10: 56 | L10: 51 | M10: 57 | N10: 65 | O10: 76 | P10: 76 | Q10: 58 | R10: 67 | S10: 48 | T10: 48 | U10: 62 | V10: =19*2.54 -> 48.26 | W10: 67 | X10: 78 | Y10: 47 | Z10: 60 | AA10: 85 | AB10: 55 | AC10: 48 | AD10: 50 | AE10: 48 | AF10: 72 | AG10: 74 | AH10: =23.5*2.54 -> 59.69 | AI10: =23.5*2.54 -> 59.69 | AJ10: 55 | AK10: 55 | AL10: 55 | AM10: =20.5*2.54 -> 52.07 | AN10: 54 | AO10: =19*2.54 -> 48.26 | AP10: 67 | AQ10: 56 | AR10: =23.5*2.54 -> 59.69 | AS10: 92 | AT10: =23.5*2.54 -> 59.69 | AU10: =40.3*2.54 -> 102.362 | AV10: 85 | AW10: 48 | AX10: 54 | AY10: 48 | AZ10: 59 | BA10: 52 | BB10: 90 | BC10: 48 | BD10: 59.5 | BE10: 59.5 | BF10: 46 | BG10: 72 | BH10: 88 | BI10: 72 | BJ10: 88 | BK10: 62 | BL10: 62 | BM10: 48 | BN10: 48 | BO10: 56 | BP10: 85 | BQ10: 59 | BR10: 59 | BS10: 49 | BT10: 59 | BU10: 85 | BV10: 59 | BW10: 59 | BX10: =23.5*2.54 -> 59.69 | BY10: 63 | BZ10: 76 | CA10: 80 | CB10: 100.5 | CC10: 72 | CD10: 72 | CE10: 85 | CF10: 56 | CG10: 52 | CH10: 69 | CI10: 75 | CJ10: 56 | CK10: 80 | CL10: 100.5 | CM10: 49 | CN10: 48 | CO10: 50 | CP10: 48 | CQ10: 75 | CR10: 85 | CS10: 59 | CT10: 52 | CU10: 75 | CV10: 80 | CW10: 100.5 | CX10: 68.7 | CY10: 63 | CZ10: 56 | DA10: 52 | DB10: 65 | DC10: 70 | DD10: 70 | DE10: 68 | DF10: 63 | DG10: 63 | DH10: 59 | DI10: 55 | DJ10: 48 | DK10: 59 | DL10: 52 | DM10: 74.5 | DN10: 59 | DO10: 69 | DP10: 68.5 | DQ10: 49 | DR10: 70 | DS10: 80 | DT10: 46 | DU10: 52
B11: Patch | C11: 15 | D11: 11 | E11: 12 | F11: 10 | G11: 11 | H11: 11 | I11: 11 | J11: 14 | K11: 14 | L11: 10 | M11: 10 | N11: 10 | O11: 12 | P11: 12 | Q11: 10 | R11: 10 | S11: 10 | T11: 10 | U11: 11 | V11: =4*2.54 -> 10.16 | W11: 15 | X11: 16 | Y11: 12 | Z11: 9 | AA11: 10 | AB11: 8 | AC11: 11 | AD11: 11 | AE11: 11 | AF11: 16 | AG11: 18 | AH11: 14 | AI11: 14 | AJ11: 11 | AK11: 11 | AL11: 11 | AM11: =4.5*2.54 -> 11.43 | AN11: 13 | AO11: =4*2.54 -> 10.16 | AP11: 15 | AQ11: 11 | AR11: =6*2.54 -> 15.24 | AS11: 14 | AT11: =6*2.54 -> 15.24 | AU11: =5.5*2.54 -> 13.97 | AV11: 13 | AW11: 13 | AX11: 11 | AY11: 13 | AZ11: 12 | BA11: 11 | BB11: 14 | BC11: 13 | BD11: 12 | BE11: 9.5 | BF11: 9 | BG11: 10 | BH11: 10 | BI11: 10 | BJ11: 10 | BK11: 11 | BL11: 11 | BM11: 11 | BN11: 13 | BO11: 10 | BP11: 13 | BQ11: 12.5 | BR11: 10 | BS11: 10 | BT11: 16 | BU11: 13 | BV11: 12.5 | BW11: 10 | BX11: =6*2.54 -> 15.24 | BY11: 11 | BZ11: 14 | CA11: 18 | CB11: 17 | CC11: 16 | CD11: 16 | CE11: 13 | CF11: 15 | CG11: 12 | CH11: 10 | CI11: 13 | CJ11: 15 | CK11: 18 | CL11: 17 | CM11: 10 | CN11: 11 | CO11: 11 | CP11: 11 | CQ11: 13 | CR11: 13 | CS11: 12 | CT11: 11 | CU11: 13 | CV11: 18 | CW11: 17 | CX11: 15.3 | CY11: 11 | CZ11: 15 | DA11: 11 | DB11: 11 | DC11: 13 | DD11: 13 | DE11: 13 | DF11: 16 | DG11: 16 | DH11: 16 | DI11: 16 | DJ11: 13 | DK11: 12 | DL11: 11 | DM11: 12 | DN11: 12 | DO11: 10 | DP11: 12.5 | DQ11: 10 | DR11: 16 | DS11: 13 | DT11: 9 | DU11: 11
B12: Valve Length (Depth) | C12: 18 | D12: 13 | E12: 15 | F12: 13 | G12: 13 | H12: 13 | I12: 13 | J12: 18 | K12: 18 | L12: 14 | M12: 14 | N12: 14 | O12: 16 | P12: 16 | Q12: 14 | R12: 14 | S12: 14 | T12: 14 | U12: 15 | V12: 15 | W12: 22 | X12: 20 | Y12: 16 | Z12: 13 | AA12: 15 | AB12: 13 | AC12: 13 | AD12: 13 | AE12: 13 | AF12: 20 | AG12: 22 | AH12: 17 | AI12: 17 | AJ12: 16 | AK12: 16 | AL12: 16 | AM12: 16 | AN12: 15 | AO12: 16 | AP12: 20 | AQ12: 20 | AR12: 22 | AS12: 20 | AT12: 22 | AU12: 0 | AV12: 0 | AW12: 16 | AX12: 16 | AY12: 16 | AZ12: 16 | BA12: 15 | BB12: 0 | BC12: 16 | BD12: 15 | BE12: 12 | BF12: 12 | BG12: 13 | BH12: 13 | BI12: 13 | BJ12: 13 | BK12: 15 | BL12: 15 | BM12: 13 | BN12: 16 | BO12: 13 | BP12: 0 | BQ12: 15 | BR12: 15 | BS12: 15 | BT12: 20 | BU12: 16 | BV12: 15 | BW12: 15 | BX12: 22 | BY12: 14 | BZ12: 16 | CA12: 0 | CB12: 0 | CC12: 0 | CD12: 0 | CE12: 0 | CF12: 16 | CG12: 15 | CH12: 14 | CI12: 15 | CJ12: 16 | CK12: 0 | CL12: 0 | CM12: 15 | CN12: 13 | CO12: 13 | CP12: 13 | CQ12: 15 | CR12: 0 | CS12: 16 | CT12: 15 | CU12: 15 | CV12: 0 | CW12: 0 | CX12: 18 | CY12: 15 | CZ12: 16 | DA12: 15 | DB12: 15 | DC12: 16 | DD12: 16 | DE12: 16 | DF12: 18 | DG12: 18 | DH12: 18 | DI12: 18 | DJ12: 16 | DK12: 16 | DL12: 15 | DM12: 16 | DN12: 16 | DO12: 14 | DP12: 14 | DQ12: 15 | DR12: 0 | DS12: 0 | DT12: 13 | DU12: 15
B13: Extended Valve | C13: 0 | D13: 0 | E13: 0 | F13: 0 | G13: 1.5 | H13: 1.5 | I13: 1.5 | J13: 0 | K13: 0 | L13: 0 | M13: 0 | N13: 0 | O13: 0 | P13: 0 | Q13: 0 | R13: 0 | S13: 0 | T13: 0 | U13: 0 | V13: 0 | W13: 1.5 | X13: 0 | Y13: 0 | Z13: 0 | AA13: 0 | AB13: 0 | AC13: 1.5 | AD13: 1.5 | AE13: 1.5 | AF13: 0 | AG13: 0 | AH13: 0 | AI13: 0 | AJ13: 0 | AK13: 0 | AL13: 0 | AM13: 0 | AN13: 0 | AO13: 0 | AP13: 0 | AQ13: 0 | AR13: 0 | AS13: 0 | AT13: 0 | AU13: 0 | AV13: 0 | AW13: 0 | AX13: 0 | AY13: 0 | AZ13: 0 | BA13: 0 | BB13: 0 | BC13: 0 | BD13: 0 | BE13: 0 | BF13: 0 | BG13: 0 | BH13: 0 | BI13: 0 | BJ13: 0 | BK13: 0 | BL13: 0 | BM13: 1.5 | BN13: 0 | BO13: 0 | BP13: 0 | BQ13: 0 | BR13: 0 | BS13: 0 | BT13: 0 | BU13: 0 | BV13: 0 | BW13: 0 | BX13: 0 | BY13: 0 | BZ13: 2 | CA13: 0 | CB13: 0 | CC13: 0 | CD13: 0 | CE13: 0 | CF13: 0 | CG13: 0 | CH13: 0 | CI13: 0 | CJ13: 0 | CK13: 0 | CL13: 0 | CM13: 0 | CN13: 1.5 | CO13: 1.5 | CP13: 1.5 | CQ13: 0 | CR13: 0 | CS13: 0 | CT13: 0 | CU13: 0 | CV13: 0 | CW13: 0 | CX13: 1.5 | CY13: 0 | CZ13: 0 | DA13: 0 | DB13: 0 | DC13: 0 | DD13: 0 | DE13: 0 | DF13: 0 | DG13: 0 | DH13: 0 | DI13: 0 | DJ13: 0 | DK13: 0 | DL13: 0 | DM13: 0 | DN13: 0 | DO13: 0 | DP13: 0 | DQ13: 0 | DR13: 0 | DS13: 0 | DT13: 0 | DU13: 0
B14: Fabric GSM | C14: 65 | D14: 65 | E14: 65 | F14: 65 | G14: 66 | H14: 66 | I14: 67.1 | J14: 53 | K14: 45 | L14: 47 | M14: 52 | N14: 60 | O14: 65 | P14: 65 | Q14: 55 | R14: 55 | S14: 65 | T14: 63 | U14: 55 | V14: 65 | W14: 57 | X14: 65 | Y14: 66 | Z14: 59.1 | AA14: 57 | AB14: 57 | AC14: 66 | AD14: 67.1 | AE14: 66 | AF14: 65 | AG14: 60 | AH14: 64 | AI14: 64 | AJ14: 65 | AK14: 65 | AL14: 65 | AM14: 60 | AN14: 66 | AO14: 68 | AP14: 100 | AQ14: 50 | AR14: 65 | AS14: 53 | AT14: 65 | AU14: 68 | AV14: 67 | AW14: 60 | AX14: 60 | AY14: 66 | AZ14: 58 | BA14: 58 | BB14: 65 | BC14: 64 | BD14: 65.04 | BE14: 66.1 | BF14: 68.9 | BG14: 65 | BH14: 68.9 | BI14: 65 | BJ14: 68.9 | BK14: 65 | BL14: 61 | BM14: 66 | BN14: 64 | BO14: 62 | BP14: 70 | BQ14: 65 | BR14: 65.7 | BS14: 70 | BT14: 65 | BU14: 65 | BV14: 64.53 | BW14: 65.66 | BX14: 65 | BY14: 65.6 | BZ14: 65 | CA14: 65 | CB14: 65 | CC14: 65 | CD14: 65 | CE14: 65 | CF14: 65 | CG14: 66 | CH14: 61 | CI14: 65 | CJ14: 65 | CK14: 65 | CL14: 65 | CM14: 70 | CN14: 70.3 | CO14: 71.5 | CP14: 70.3 | CQ14: 65 | CR14: 65 | CS14: 58 | CT14: 58 | CU14: 65 | CV14: 65 | CW14: 65 | CX14: 60 | CY14: 63.9 | CZ14: 65 | DA14: 59.62 | DB14: 63.41 | DC14: 61 | DD14: 61 | DE14: 61 | DF14: 52 | DG14: 52 | DH14: 52 | DI14: 52 | DJ14: 64 | DK14: 58 | DL14: 58 | DM14: 68 | DN14: 57.4 | DO14: 61 | DP14: 75 | DQ14: 70 | DR14: 60 | DS14: 65 | DT14: 65 | DU14: 63
B15: Coating GSM | C15: 22 | D15: 22 | E15: 22 | F15: 22 | G15: 22 | H15: 22 | I15: 22 | J15: 22 | K15: 22 | L15: 22 | M15: 22 | N15: 22 | O15: 23 | P15: 23 | Q15: 22 | R15: 22 | S15: 25 | T15: 22 | U15: 22 | V15: 22 | W15: 22 | X15: 23 | Y15: 23 | Z15: 23 | AA15: 22 | AB15: 22 | AC15: 22 | AD15: 22 | AE15: 22 | AF15: 22 | AG15: 22 | AH15: 23 | AI15: 23 | AJ15: 22 | AK15: 22 | AL15: 22 | AM15: 22 | AN15: 22 | AO15: 22 | AP15: 22 | AQ15: 22 | AR15: 22 | AS15: 22 | AT15: 22 | AU15: 22 | AV15: 22 | AW15: 22 | AX15: 22 | AY15: 22 | AZ15: 22 | BA15: 22 | BB15: 22 | BC15: 22 | BD15: 22 | BE15: 22 | BF15: 22 | BG15: 22 | BH15: 22 | BI15: 22 | BJ15: 22 | BK15: 22 | BL15: 22 | BM15: 22 | BN15: 22 | BO15: 22 | BP15: 22 | BQ15: 22 | BR15: 22 | BS15: 23 | BT15: 22 | BU15: 22 | BV15: 22 | BW15: 22 | BX15: 22 | BY15: 22 | BZ15: 22 | CA15: 23 | CB15: 22 | CC15: 23 | CD15: 23 | CE15: 25 | CF15: 25 | CG15: 23 | CH15: 22 | CI15: 23 | CJ15: 25 | CK15: 23 | CL15: 22 | CM15: 23 | CN15: 22 | CO15: 22 | CP15: 22 | CQ15: 23 | CR15: 25 | CS15: 22 | CT15: 22 | CU15: 23 | CV15: 23 | CW15: 22 | CX15: 22 | CY15: 22 | CZ15: 25 | DA15: 23 | DB15: 22 | DC15: 24.85 | DD15: 24.85 | DE15: 24.85 | DF15: 23 | DG15: 23 | DH15: 23 | DI15: 23.5 | DJ15: 22 | DK15: 22 | DL15: 22 | DM15: 24 | DN15: 22 | DO15: 22 | DP15: 22.9 | DQ15: 23 | DR15: 25 | DS15: 23 | DT15: 23 | DU15: 23
B16: BOPP GSM | C16: 15 | D16: 15 | E16: 0 | F16: 0 | G16: 0 | H16: 0 | I16: 0 | J16: 0 | K16: 0 | L16: 0 | M16: 0 | N16: 18 | O16: 0 | P16: 0 | Q16: 0 | R16: 0 | S16: 0 | T16: 0 | U16: 0 | V16: 0 | W16: 0 | X16: 0 | Y16: 0 | Z16: 0 | AA16: 0 | AB16: 0 | AC16: 0 | AD16: 0 | AE16: 0 | AF16: 18 | AT16: 20 | AU16: 20 | AV16: 0 | BD16: 0 | BE16: 0 | BF16: 0 | BG16: 0 | BH16: 0 | BI16: 18 | BJ16: 18 | BL16: 18 | BM16: 0 | BP16: 0 | BQ16: 0 | BR16: 0 | BT16: 0 | BU16: 0 | BV16: 0 | BW16: 0 | CC16: 18 | CF16: 18 | CG16: 0 | CH16: 0 | CI16: 20 | CJ16: 18 | CN16: 0 | CO16: 0 | CP16: 0 | CQ16: 20 | CU16: 20 | CX16: 15 | CZ16: 18 | DA16: 0 | DD16: 20.15 | DE16: 20.15 | DM16: 20 | DO16: 0 | DP16: 19 | DS16: 18 | DT16: 0 | DU16: 0
B17: Open Mouth | C17: Yes | D17: No | E17: Yes | F17: Yes | G17: No | H17: No | I17: No | J17: No | K17: No | L17: No | M17: No | N17: No | O17: Yes | P17: Yes | Q17: No | R17: Yes | S17: No | T17: No | U17: No | V17: No | W17: No | X17: Yes | Y17: Yes | Z17: Yes | AA17: Yes | AB17: Yes | AC17: No | AD17: No | AE17: No | AF17: Yes | AG17: Yes | AH17: No | AI17: No | AJ17: No | AK17: No | AL17: No | AM17: Yes | AN17: No | AO17: No | AP17: Yes | AQ17: No | AR17: No | AS17: No | AT17: No | AU17: Yes | AV17: Yes | AW17: No | AX17: No | AY17: No | AZ17: No | BA17: No | BB17: Yes | BC17: No | BD17: No | BE17: No | BF17: No | BG17: No | BH17: No | BI17: No | BJ17: No | BK17: No | BL17: No | BM17: No | BN17: No | BO17: No | BP17: Yes | BQ17: No | BR17: No | BS17: No | BT17: No | BU17: Yes | BV17: No | BW17: No | BX17: No | BY17: No | BZ17: No | CA17: Yes | CB17: Yes | CC17: Yes | CD17: Yes | CE17: Yes | CF17: No | CG17: Yes | CH17: No | CI17: No | CJ17: No | CK17: Yes | CL17: Yes | CM17: No | CN17: No | CO17: No | CP17: No | CQ17: No | CR17: Yes | CS17: No | CT17: No | CU17: No | CV17: Yes | CW17: Yes | CX17: No | CY17: No | CZ17: No | DA17: No | DB17: No | DC17: Yes | DD17: Yes | DE17: Yes | DF17: No | DG17: No | DH17: No | DI17: No | DJ17: No | DK17: No | DL17: No | DM17: Yes | DN17: No | DO17: No | DP17: Yes | DQ17: No | DR17: No | DS17: Yes | DT17: No | DU17: No
B18: UV (Y/N) | C18: No | D18: No | E18: No | F18: Yes | G18: Yes | H18: Yes | I18: Yes | J18: Yes | K18: Yes | L18: Yes | M18: Yes | N18: Yes | O18: No | P18: No | Q18: No | R18: Yes | S18: No | T18: No | U18: No | V18: No | W18: No | X18: Yes | Y18: Yes | Z18: No | AA18: No | AB18: No | AC18: Yes | AD18: Yes | AE18: Yes | AF18: No | AG18: No | AH18: No | AI18: No | AJ18: No | AK18: No | AL18: No | AM18: No | AN18: No | AO18: No | AP18: Yes | AQ18: Yes | AR18: No | AS18: No | AT18: No | AU18: Yes | AV18: Yes | AW18: No | AX18: No | AY18: No | AZ18: Yes | BA18: Yes | BB18: No | BC18: No | BD18: No | BE18: No | BF18: No | BG18: No | BH18: No | BI18: No | BJ18: No | BK18: No | BL18: No | BM18: No | BN18: No | BO18: No | BP18: Yes | BQ18: Yes | BR18: Yes | BS18: No | BT18: No | BU18: No | BV18: Yes | BW18: Yes | BX18: No | BY18: No | BZ18: Yes | CA18: No | CB18: No | CC18: Yes | CD18: Yes | CE18: Yes | CF18: Yes | CG18: No | CH18: No | CI18: No | CJ18: Yes | CK18: No | CL18: No | CM18: No | CN18: Yes | CO18: Yes | CP18: Yes | CQ18: No | CR18: Yes | CS18: Yes | CT18: Yes | CU18: No | CV18: No | CW18: No | CX18: No | CY18: No | CZ18: Yes | DA18: No | DB18: No | DC18: No | DD18: No | DE18: No | DF18: No | DG18: No | DH18: No | DI18: No | DJ18: No | DK18: Yes | DL18: Yes | DM18: No | DN18: Yes | DO18: No | DP18: No | DQ18: No | DR18: Yes | DS18: Yes | DT18: No | DU18: Yes
B19: Printing | C19: 2/2 | D19: 2/2 | E19: 2/2 | F19: 2/2 | G19: 2/2 | H19: 2/2 | I19: 2/2 | J19: 2/2 | K19: 2/2 | L19: 2/2 | M19: 2/2 | O19: 2/2 | P19: 2/2 | Q19: 2/2 | V19: 1/1 | W19: 1/1 | AC19: 2/2 | AD19: 2/2 | AE19: 2/2 | BM19: 2/2 | CG19: 2/2 | CN19: 2/2 | CO19: 2/2 | CP19: 2/2
B20: Bag Weight | C20: {=_xlfn.IFS(C17="No",((C9*2*(C10+C11+3)/10000*(C14+C15+C16))+(C9*C11*2*(C14+C15+C16+20)/10000)+(C11*(C12+C13)*2/10000*(C14+C15+C15))),C17="Yes",(C9*2*(C10+C11/2+1.5)/10000*(C14+C15+C16)+(((C14+C15+C16+20))*C9*C11/10000)))} -> 81.675 | D20: {=_xlfn.IFS(D17="No",((D9*2*(D10+D11+3)/10000*(D14+D15+D16))+(D9*D11*2*(D14+D15+D16+20)/10000)+(D11*(D12+D13)*2/10000*(D14+D15+D15))),D17="Yes",(D9*2*(D10+D11/2+1.5)/10000*(D14+D15+D16)+(((D14+D15+D16+20))*D9*D11/10000)))} -> 84.0454 | E20: {=_xlfn.IFS(E17="No",((E9*2*(E10+E11+3)/10000*(E14+E15+E16))+(E9*E11*2*(E14+E15+E16+20)/10000)+(E11*(E12+E13)*2/10000*(E14+E15+E15))),E17="Yes",(E9*2*(E10+E11/2+1.5)/10000*(E14+E15+E16)+(((E14+E15+E16+20))*E9*E11/10000)))} -> 46.548 | F20: {=_xlfn.IFS(F17="No",((F9*2*(F10+F11+3)/10000*(F14+F15+F16))+(F9*F11*2*(F14+F15+F16+20)/10000)+(F11*(F12+F13)*2/10000*(F14+F15+F15))),F17="Yes",(F9*2*(F10+F11/2+1.5)/10000*(F14+F15+F16)+(((F14+F15+F16+20))*F9*F11/10000)))} -> 43.6284 | G20: {=_xlfn.IFS(G17="No",((G9*2*(G10+G11+3)/10000*(G14+G15+G16))+(G9*G11*2*(G14+G15+G16+20)/10000)+(G11*(G12+G13)*2/10000*(G14+G15+G15))),G17="Yes",(G9*2*(G10+G11/2+1.5)/10000*(G14+G15+G16)+(((G14+G15+G16+20))*G9*G11/10000)))} -> 53.339 | H20: {=_xlfn.IFS(H17="No",((H9*2*(H10+H11+3)/10000*(H14+H15+H16))+(H9*H11*2*(H14+H15+H16+20)/10000)+(H11*(H12+H13)*2/10000*(H14+H15+H15))),H17="Yes",(H9*2*(H10+H11/2+1.5)/10000*(H14+H15+H16)+(((H14+H15+H16+20))*H9*H11/10000)))} -> 53.339 | I20: {=_xlfn.IFS(I17="No",((I9*2*(I10+I11+3)/10000*(I14+I15+I16))+(I9*I11*2*(I14+I15+I16+20)/10000)+(I11*(I12+I13)*2/10000*(I14+I15+I15))),I17="Yes",(I9*2*(I10+I11/2+1.5)/10000*(I14+I15+I16)+(((I14+I15+I16+20))*I9*I11/10000)))} -> 56.00309 | J20: {=_xlfn.IFS(J17="No",((J9*2*(J10+J11+3)/10000*(J14+J15+J16))+(J9*J11*2*(J14+J15+J16+20)/10000)+(J11*(J12+J13)*2/10000*(J14+J15+J15))),J17="Yes",(J9*2*(J10+J11/2+1.5)/10000*(J14+J15+J16)+(((J14+J15+J16+20))*J9*J11/10000)))} -> 69.9388 | ... AM20: {=_xlfn.IFS(AM17="No",((AM9*2*(AM10+AM11+3)/10000*(AM14+AM15+AM16))+(AM9*AM11*2*(AM14+AM15+AM16+20)/10000)+(AM11*(AM12+AM13)*2/10000*(AM14+AM15+AM15))),AM17="Yes",(AM9*2*(AM10+AM11/2+1.5)/10000*(AM14+AM15+AM16)+(((AM14+AM15+AM16+20))*AM9*AM11/10000)))} -> 47.016975 | AN20: {=_xlfn.IFS(AN17="No",((AN9*2*(AN10+AN11+3)/10000*(AN14+AN15+AN16))+((AN9-AN11)*AN11*2*(AN14+AN15+AN16+20)/10000)+(AN11*(AN12+AN13)*2/10000*(AN14+AN15+20))),AN17="Yes",(AN9*2*(AN10+AN11/2+1.5)/10000*(AN14+AN15+AN16)+(((AN14+AN15+AN16+20))*(AN9-AN11)*AN11/10000)))} -> 68.6376 | AO20: {=_xlfn.IFS(AO17="No",((AO9*2*(AO10+AO11+3)/10000*(AO14+AO15+AO16))+((AO9-AO11)*AO11*2*(AO14+AO15+AO16+20)/10000)+(AO11*(AO12+AO13)*2/10000*(AO14+AO15+20))),AO17="Yes",(AO9*2*(AO10+AO11/2+1.5)/10000*(AO14+AO15+AO16)+(((AO14+AO15+AO16+20))*(AO9-AO11)*AO11/10000)))} -> 62.070894 | AP20: {=_xlfn.IFS(AP17="No",((AP9*2*(AP10+AP11+3)/10000*(AP14+AP15+AP16))+(AP9*AP11*2*(AP14+AP15+AP16+20)/10000)+(AP11*(AP12+AP13)*2/10000*(AP14+AP15+AP15))),AP17="Yes",(AP9*2*(AP10+AP11/2+1.5)/10000*(AP14+AP15+AP16)+(((AP14+AP15+AP16+20))*AP9*AP11/10000)))} -> 93.033 | AQ20: {=_xlfn.IFS(AQ17="No",((AQ9*2*(AQ10+AQ11+3)/10000*(AQ14+AQ15+AQ16))+(AQ9*AQ11*2*(AQ14+AQ15+AQ16+20)/10000)+(AQ11*(AQ12+AQ13)*2/10000*(AQ14+AQ15+AQ15))),AQ17="Yes",(AQ9*2*(AQ10+AQ11/2+1.5)/10000*(AQ14+AQ15+AQ16)+(((AQ14+AQ15+AQ16+20))*AQ9*AQ11/10000)))} -> 62.2352 | AR20: {=_xlfn.IFS(AR17="No",((AR9*2*(AR10+AR11+3)/10000*(AR14+AR15+AR16))+(AR9*AR11*2*(AR14+AR15+AR16+20)/10000)+(AR11*(AR12+AR13)*2/10000*(AR14+AR15+AR15))),AR17="Yes",(AR9*2*(AR10+AR11/2+1.5)/10000*(AR14+AR15+AR16)+(((AR14+AR15+AR16+20))*AR9*AR11/10000)))} -> 101.30586 | AS20: {=_xlfn.IFS(AS17="No",((AS9*2*(AS10+AS11+3)/10000*(AS14+AS15+AS16))+(AS9*AS11*2*(AS14+AS15+AS16+20)/10000)+(AS11*(AS12+AS13)*2/10000*(AS14+AS15+AS15))),AS17="Yes",(AS9*2*(AS10+AS11/2+1.5)/10000*(AS14+AS15+AS16)+(((AS14+AS15+AS16+20))*AS9*AS11/10000)))} -> 108.086 | AT20: {=_xlfn.IFS(AT17="No",((AT9*2*(AT10+AT11+3)/10000*(AT14+AT15+AT16))+(AT9*AT11*2*(AT14+AT15+AT16+20)/10000)+(AT11*(AT12+AT13)*2/10000*(AT14+AT15+AT15))),AT17="Yes",(AT9*2*(AT10+AT11/2+1.5)/10000*(AT14+AT15+AT16)+(((AT14+AT15+AT16+20))*AT9*AT11/10000)))} -> 122.13122 | AU20: {=_xlfn.IFS(AU17="No",((AU9*2*(AU10+AU11+3)/10000*(AU14+AU15+AU16))+(AU9*AU11*2*(AU14+AU15+AU16+20)/10000)+(AU11*(AU12+AU13)*2/10000*(AU14+AU15+AU15))),AU17="Yes",(AU9*2*(AU10+AU11/2+1.5)/10000*(AU14+AU15+AU16)+(((AU14+AU15+AU16+20))*AU9*AU11/10000)))} -> 156.40236 | AV20: {=_xlfn.IFS(AV17="No",((AV9*2*(AV10+AV11+3)/10000*(AV14+AV15+AV16))+(AV9*AV11*2*(AV14+AV15+AV16+20)/10000)+(AV11*(AV12+AV13)*2/10000*(AV14+AV15+AV15))),AV17="Yes",(AV9*2*(AV10+AV11/2+1.5)/10000*(AV14+AV15+AV16)+(((AV14+AV15+AV16+20))*AV9*AV11/10000)))} -> 88.0579 | AW20: {=_xlfn.IFS(AW17="No",((AW9*2*(AW10+AW11+3)/10000*(AW14+AW15+AW16))+((AW9-AW11)*AW11*2*(AW14+AW15+AW16+20)/10000)+(AW11*(AW12+AW13)*2/10000*(AW14+AW15+20))),AW17="Yes",(AW9*2*(AW10+AW11/2+1.5)/10000*(AW14+AW15+AW16)+(((AW14+AW15+AW16+20))*(AW9-AW11)*AW11/10000)))} -> 57.332 | AX20: {=_xlfn.IFS(AX17="No",((AX9*2*(AX10+AX11+3)/10000*(AX14+AX15+AX16))+((AX9-AX11)*AX11*2*(AX14+AX15+AX16+20)/10000)+(AX11*(AX12+AX13)*2/10000*(AX14+AX15+20))),AX17="Yes",(AX9*2*(AX10+AX11/2+1.5)/10000*(AX14+AX15+AX16)+(((AX14+AX15+AX16+20))*(AX9-AX11)*AX11/10000)))} -> 68.102 | AY20: {=_xlfn.IFS(AY17="No",((AY9*2*(AY10+AY11+3)/10000*(AY14+AY15+AY16))+((AY9-AY11)*AY11*2*(AY14+AY15+AY16+20)/10000)+(AY11*(AY12+AY13)*2/10000*(AY14+AY15+20))),AY17="Yes",(AY9*2*(AY10+AY11/2+1.5)/10000*(AY14+AY15+AY16)+(((AY14+AY15+AY16+20))*(AY9-AY11)*AY11/10000)))} -> 61.352 | AZ20: {=_xlfn.IFS(AZ17="No",((AZ9*2*(AZ10+AZ11+3)/10000*(AZ14+AZ15+AZ16))+((AZ9-AZ11)*AZ11*2*(AZ14+AZ15+AZ16+20)/10000)+(AZ11*(AZ12+AZ13)*2/10000*(AZ14+AZ15+20))),AZ17="Yes",(AZ9*2*(AZ10+AZ11/2+1.5)/10000*(AZ14+AZ15+AZ16)+(((AZ14+AZ15+AZ16+20))*(AZ9-AZ11)*AZ11/10000)))} -> 73.584 | BA20: {=_xlfn.IFS(BA17="No",((BA9*2*(BA10+BA11+3)/10000*(BA14+BA15+BA16))+((BA9-BA11)*BA11*2*(BA14+BA15+BA16+28)/10000)+((BA11+1)*(BA12+BA13)*2/10000*(BA14+BA15+28))),BA17="Yes",(BA9*2*(BA10+BA11/2+1.5)/10000*(BA14+BA15+BA16)+(((BA14+BA15+BA16+28))*(BA9-BA11)*BA11/10000)))} -> 63.3672 | BB20: {=_xlfn.IFS(BB17="No",((BB9*2*(BB10+BB11+3)/10000*(BB14+BB15+BB16))+((BB9-BB11)*BB11*2*(BB14+BB15+BB16+28)/10000)+((BB11+1)*(BB12+BB13)*2/10000*(BB14+BB15+28))),BB17="Yes",(BB9*2*(BB10+BB11/2+1.5)/10000*(BB14+BB15+BB16)+(((BB14+BB15+BB16+28))*(BB9-BB11)*BB11/10000)))} -> 91.491 | BC20: {=_xlfn.IFS(BC17="No",((BC9*2*(BC10+BC11+3)/10000*(BC14+BC15+BC16))+((BC9-BC11)*BC11*2*(BC14+BC15+BC16+20)/10000)+(BC11*(BC12+BC13)*2/10000*(BC14+BC15+20))),BC17="Yes",(BC9*2*(BC10+BC11/2+1.5)/10000*(BC14+BC15+BC16)+(((BC14+BC15+BC16+20))*(BC9-BC11)*BC11/10000)))} -> 60.012 | BD20: {=_xlfn.IFS(BD17="No",((BD9*2*(BD10+BD11+3)/10000*(BD14+BD15+BD16))+((BD9-BD11)*BD11*2*(BD14+BD15+BD16+20)/10000)+(BD11*(BD12+BD13)*2/10000*(BD14+BD15+20))),BD17="Yes",(BD9*2*(BD10+BD11/2+1.5)/10000*(BD14+BD15+BD16)+(((BD14+BD15+BD16+20))*(BD9-BD11)*BD11/10000)))} -> 80.01408 | BE20: {=_xlfn.IFS(BE17="No",((BE9*2*(BE10+BE11+3)/10000*(BE14+BE15+BE16))+((BE9-BE11)*BE11*2*(BE14+BE15+BE16+20)/10000)+(BE11*(BE12+BE13)*2/10000*(BE14+BE15+20))),BE17="Yes",(BE9*2*(BE10+BE11/2+1.5)/10000*(BE14+BE15+BE16)+(((BE14+BE15+BE16+20))*(BE9-BE11)*BE11/10000)))} -> 72.00393 | BF20: {=_xlfn.IFS(BF17="No",((BF9*2*(BF10+BF11+3)/10000*(BF14+BF15+BF16))+((BF9-BF11)*BF11*2*(BF14+BF15+BF16+20)/10000)+(BF11*(BF12+BF13)*2/10000*(BF14+BF15+20))),BF17="Yes",(BF9*2*(BF10+BF11/2+1.5)/10000*(BF14+BF15+BF16)+(((BF14+BF15+BF16+20))*(BF9-BF11)*BF11/10000)))} -> 52.01532 | BG20: {=_xlfn.IFS(BG17="No",((BG9*2*(BG10+BG11+3)/10000*(BG14+BG15+BG16))+((BG9-BG11)*BG11*2*(BG14+BG15+BG16+20)/10000)+(BG11*(BG12+BG13)*2/10000*(BG14+BG15+20))),BG17="Yes",(BG9*2*(BG10+BG11/2+1.5)/10000*(BG14+BG15+BG16)+(((BG14+BG15+BG16+20))*(BG9-BG11)*BG11/10000)))} -> 78.52 | BH20: {=_xlfn.IFS(BH17="No",((BH9*2*(BH10+BH11+3)/10000*(BH14+BH15+BH16))+((BH9-BH11)*BH11*2*(BH14+BH15+BH16+20)/10000)+(BH11*(BH12+BH13)*2/10000*(BH14+BH15+20))),BH17="Yes",(BH9*2*(BH10+BH11/2+1.5)/10000*(BH14+BH15+BH16)+(((BH14+BH15+BH16+20))*(BH9-BH11)*BH11/10000)))} -> 107.68036 | BI20: {=_xlfn.IFS(BI17="No",((BI9*2*(BI10+BI11+3)/10000*(BI14+BI15+BI16))+((BI9-BI11)*BI11*2*(BI14+BI15+BI16+20)/10000)+(BI11*(BI12+BI13)*2/10000*(BI14+BI15+20))),BI17="Yes",(BI9*2*(BI10+BI11/2+1.5)/10000*(BI14+BI15+BI16)+(((BI14+BI15+BI16+20))*(BI9-BI11)*BI11/10000)))} -> 93.892 | BJ20: {=_xlfn.IFS(BJ17="No",((BJ9*2*(BJ10+BJ11+3)/10000*(BJ14+BJ15+BJ16))+((BJ9-BJ11)*BJ11*2*(BJ14+BJ15+BJ16+20)/10000)+(BJ11*(BJ12+BJ13)*2/10000*(BJ14+BJ15+20))),BJ17="Yes",(BJ9*2*(BJ10+BJ11/2+1.5)/10000*(BJ14+BJ15+BJ16)+(((BJ14+BJ15+BJ16+20))*(BJ9-BJ11)*BJ11/10000)))} -> 128.09956 | ... BZ20: {=_xlfn.IFS(BZ17="No",((BZ9*2*(BZ10+BZ11+3)/10000*(BZ14+BZ15+BZ16))+((BZ9-BZ11)*BZ11*2*(BZ14+BZ15+BZ16+20)/10000)+(BZ11*(BZ12+BZ13)*2/10000*(BZ14+BZ15+20))),BZ17="Yes",(BZ9*2*(BZ10+BZ11/2+1.5)/10000*(BZ14+BZ15+BZ16)+(((BZ14+BZ15+BZ16+20))*(BZ9-BZ11)*BZ11/10000)))} -> 97.0884 | CA20: {=_xlfn.IFS(CA17="No",((CA9*2*(CA10+CA11+3)/10000*(CA14+CA15+CA16))+((CA9-CA11)*CA11*2*(CA14+CA15+CA16+28)/10000)+((CA11+1)*(CA12+CA13)*2/10000*(CA14+CA15+28))),CA17="Yes",(CA9*2*(CA10+CA11/2+1.5)/10000*(CA14+CA15+CA16)+(((CA14+CA15+CA16+28))*(CA9-CA11)*CA11/10000)))} -> 86.3216 | CB20: {=_xlfn.IFS(CB17="No",((CB9*2*(CB10+CB11+3)/10000*(CB14+CB15+CB16))+((CB9-CB11)*CB11*2*(CB14+CB15+CB16+28)/10000)+((CB11+1)*(CB12+CB13)*2/10000*(CB14+CB15+28))),CB17="Yes",(CB9*2*(CB10+CB11/2+1.5)/10000*(CB14+CB15+CB16)+(((CB14+CB15+CB16+28))*(CB9-CB11)*CB11/10000)))} -> 113.1775 | CC20: {=_xlfn.IFS(CC17="No",((CC9*2*(CC10+CC11+3)/10000*(CC14+CC15+CC16))+((CC9-CC11)*CC11*2*(CC14+CC15+CC16+28)/10000)+((CC11+1)*(CC12+CC13)*2/10000*(CC14+CC15+28))),CC17="Yes",(CC9*2*(CC10+CC11/2+1.5)/10000*(CC14+CC15+CC16)+(((CC14+CC15+CC16+28))*(CC9-CC11)*CC11/10000)))} -> 95.6218 | CD20: {=_xlfn.IFS(CD17="No",((CD9*2*(CD10+CD11+3)/10000*(CD14+CD15+CD16))+((CD9-CD11)*CD11*2*(CD14+CD15+CD16+28)/10000)+((CD11+1)*(CD12+CD13)*2/10000*(CD14+CD15+28))),CD17="Yes",(CD9*2*(CD10+CD11/2+1.5)/10000*(CD14+CD15+CD16)+(((CD14+CD15+CD16+28))*(CD9-CD11)*CD11/10000)))} -> 79.6504 | CE20: {=_xlfn.IFS(CE17="No",((CE9*2*(CE10+CE11+3)/10000*(CE14+CE15+CE16))+((CE9-CE11)*CE11*2*(CE14+CE15+CE16+28)/10000)+((CE11+1)*(CE12+CE13)*2/10000*(CE14+CE15+28))),CE17="Yes",(CE9*2*(CE10+CE11/2+1.5)/10000*(CE14+CE15+CE16)+(((CE14+CE15+CE16+28))*(CE9-CE11)*CE11/10000)))} -> 89.3758 | CF20: {=_xlfn.IFS(CF17="No",((CF9*2*(CF10+CF11+3)/10000*(CF14+CF15+CF16))+((CF9-CF11)*CF11*2*(CF14+CF15+CF16+28)/10000)+((CF11+1)*(CF12+CF13)*2/10000*(CF14+CF15+28))),CF17="Yes",(CF9*2*(CF10+CF11/2+1.5)/10000*(CF14+CF15+CF16)+(((CF14+CF15+CF16+28))*(CF9-CF11)*CF11/10000)))} -> 96.2288 | CG20: {=_xlfn.IFS(CG17="No",((CG9*2*(CG10+CG11+3)/10000*(CG14+CG15+CG16))+((CG9-CG11)*CG11*2*(CG14+CG15+CG16+28)/10000)+((CG11+1)*(CG12+CG13)*2/10000*(CG14+CG15+28))),CG17="Yes",(CG9*2*(CG10+CG11/2+1.5)/10000*(CG14+CG15+CG16)+(((CG14+CG15+CG16+28))*(CG9-CG11)*CG11/10000)))} -> 46.2952 | CH20: {=_xlfn.IFS(CH17="No",((CH9*2*(CH10+CH11+3)/10000*(CH14+CH15+CH16))+((CH9-CH11)*CH11*2*(CH14+CH15+CH16+28)/10000)+((CH11+1)*(CH12+CH13)*2/10000*(CH14+CH15+28))),CH17="Yes",(CH9*2*(CH10+CH11/2+1.5)/10000*(CH14+CH15+CH16)+(((CH14+CH15+CH16+28))*(CH9-CH11)*CH11/10000)))} -> 80.3588 | ... CL20: {=_xlfn.IFS(CL17="No",((CL9*2*(CL10+CL11+3)/10000*(CL14+CL15+CL16))+((CL9-CL11)*CL11*2*(CL14+CL15+CL16+28)/10000)+((CL11+1)*(CL12+CL13)*2/10000*(CL14+CL15+28))),CL17="Yes",(CL9*2*(CL10+CL11/2+1.5)/10000*(CL14+CL15+CL16)+(((CL14+CL15+CL16+28))*(CL9-CL11)*CL11/10000)))} -> 113.1775 | CM20: {=_xlfn.IFS(CM17="No",((CM9*2*(CM10+CM11+3)/10000*(CM14+CM15+CM16))+((CM9-CM11)*CM11*2*(CM14+CM15+CM16+20)/10000)+(CM11*(CM12+CM13)*2/10000*(CM14+CM15+20))),CM17="Yes",(CM9*2*(CM10+CM11/2+1.5)/10000*(CM14+CM15+CM16)+(((CM14+CM15+CM16+20))*(CM9-CM11)*CM11/10000)))} -> 63.194 | CN20: {=_xlfn.IFS(CN17="No",((CN9*2*(CN10+CN11+3)/10000*(CN14+CN15+CN16))+((CN9-CN11)*CN11*2*(CN14+CN15+CN16+20)/10000)+(CN11*(CN12+CN13)*2/10000*(CN14+CN15+20))),CN17="Yes",(CN9*2*(CN10+CN11/2+1.5)/10000*(CN14+CN15+CN16)+(((CN14+CN15+CN16+20))*(CN9-CN11)*CN11/10000)))} -> 53.04896 | CO20: {=_xlfn.IFS(CO17="No",((CO9*2*(CO10+CO11+3)/10000*(CO14+CO15+CO16))+((CO9-CO11)*CO11*2*(CO14+CO15+CO16+20)/10000)+(CO11*(CO12+CO13)*2/10000*(CO14+CO15+20))),CO17="Yes",(CO9*2*(CO10+CO11/2+1.5)/10000*(CO14+CO15+CO16)+(((CO14+CO15+CO16+20))*(CO9-CO11)*CO11/10000)))} -> 55.84095 | CP20: {=_xlfn.IFS(CP17="No",((CP9*2*(CP10+CP11+3)/10000*(CP14+CP15+CP16))+((CP9-CP11)*CP11*2*(CP14+CP15+CP16+20)/10000)+(CP11*(CP12+CP13)*2/10000*(CP14+CP15+20))),CP17="Yes",(CP9*2*(CP10+CP11/2+1.5)/10000*(CP14+CP15+CP16)+(((CP14+CP15+CP16+20))*(CP9-CP11)*CP11/10000)))} -> 53.04896 | CQ20: {=_xlfn.IFS(CQ17="No",((CQ9*2*(CQ10+CQ11+3)/10000*(CQ14+CQ15+CQ16))+((CQ9-CQ11)*CQ11*2*(CQ14+CQ15+CQ16+28)/10000)+((CQ11+1)*(CQ12+CQ13)*2/10000*(CQ14+CQ15+28))),CQ17="Yes",(CQ9*2*(CQ10+CQ11/2+1.5)/10000*(CQ14+CQ15+CQ16)+(((CQ14+CQ15+CQ16+28))*(CQ9-CQ11)*CQ11/10000)))} -> 104.6392 | CR20: {=_xlfn.IFS(CR17="No",((CR9*2*(CR10+CR11+3)/10000*(CR14+CR15+CR16))+((CR9-CR11)*CR11*2*(CR14+CR15+CR16+28)/10000)+((CR11+1)*(CR12+CR13)*2/10000*(CR14+CR15+28))),CR17="Yes",(CR9*2*(CR10+CR11/2+1.5)/10000*(CR14+CR15+CR16)+(((CR14+CR15+CR16+28))*(CR9-CR11)*CR11/10000)))} -> 89.3758 | CS20: {=_xlfn.IFS(CS17="No",((CS9*2*(CS10+CS11+3)/10000*(CS14+CS15+CS16))+((CS9-CS11)*CS11*2*(CS14+CS15+CS16+20)/10000)+(CS11*(CS12+CS13)*2/10000*(CS14+CS15+20))),CS17="Yes",(CS9*2*(CS10+CS11/2+1.5)/10000*(CS14+CS15+CS16)+(((CS14+CS15+CS16+20))*(CS9-CS11)*CS11/10000)))} -> 73.584 | CT20: {=_xlfn.IFS(CT17="No",((CT9*2*(CT10+CT11+3)/10000*(CT14+CT15+CT16))+((CT9-CT11)*CT11*2*(CT14+CT15+CT16+28)/10000)+((CT11+1)*(CT12+CT13)*2/10000*(CT14+CT15+28))),CT17="Yes",(CT9*2*(CT10+CT11/2+1.5)/10000*(CT14+CT15+CT16)+(((CT14+CT15+CT16+28))*(CT9-CT11)*CT11/10000)))} -> 63.3672 | CU20: {=_xlfn.IFS(CU17="No",((CU9*2*(CU10+CU11+3)/10000*(CU14+CU15+CU16))+((CU9-CU11)*CU11*2*(CU14+CU15+CU16+28)/10000)+((CU11+1)*(CU12+CU13)*2/10000*(CU14+CU15+28))),CU17="Yes",(CU9*2*(CU10+CU11/2+1.5)/10000*(CU14+CU15+CU16)+(((CU14+CU15+CU16+28))*(CU9-CU11)*CU11/10000)))} -> 104.6392 | CV20: {=_xlfn.IFS(CV17="No",((CV9*2*(CV10+CV11+3)/10000*(CV14+CV15+CV16))+((CV9-CV11)*CV11*2*(CV14+CV15+CV16+28)/10000)+((CV11+1)*(CV12+CV13)*2/10000*(CV14+CV15+28))),CV17="Yes",(CV9*2*(CV10+CV11/2+1.5)/10000*(CV14+CV15+CV16)+(((CV14+CV15+CV16+28))*(CV9-CV11)*CV11/10000)))} -> 86.3216 | CW20: {=_xlfn.IFS(CW17="No",((CW9*2*(CW10+CW11+3)/10000*(CW14+CW15+CW16))+((CW9-CW11)*CW11*2*(CW14+CW15+CW16+28)/10000)+((CW11+1)*(CW12+CW13)*2/10000*(CW14+CW15+28))),CW17="Yes",(CW9*2*(CW10+CW11/2+1.5)/10000*(CW14+CW15+CW16)+(((CW14+CW15+CW16+28))*(CW9-CW11)*CW11/10000)))} -> 113.1775 | CX20: {=_xlfn.IFS(CX17="No",((CX9*2*(CX10+CX11+3)/10000*(CX14+CX15+CX16))+((CX9-CX11)*CX11*2*(CX14+CX15+CX16+28)/10000)+((CX11+1)*(CX12+CX13)*2/10000*(CX14+CX15+28))),CX17="Yes",(CX9*2*(CX10+CX11/2+1.5)/10000*(CX14+CX15+CX16)+(((CX14+CX15+CX16+28))*(CX9-CX11)*CX11/10000)))} -> 122.253 | CY20: {=_xlfn.IFS(CY17="No",((CY9*2*(CY10+CY11+3)/10000*(CY14+CY15+CY16))+((CY9-CY11)*CY11*2*(CY14+CY15+CY16+28)/10000)+((CY11+1)*(CY12+CY13)*2/10000*(CY14+CY15+28))),CY17="Yes",(CY9*2*(CY10+CY11/2+1.5)/10000*(CY14+CY15+CY16)+(((CY14+CY15+CY16+28))*(CY9-CY11)*CY11/10000)))} -> 80.01602 | CZ20: {=_xlfn.IFS(CZ17="No",((CZ9*2*(CZ10+CZ11+3)/10000*(CZ14+CZ15+CZ16))+((CZ9-CZ11)*CZ11*2*(CZ14+CZ15+CZ16+28)/10000)+((CZ11+1)*(CZ12+CZ13)*2/10000*(CZ14+CZ15+28))),CZ17="Yes",(CZ9*2*(CZ10+CZ11/2+1.5)/10000*(CZ14+CZ15+CZ16)+(((CZ14+CZ15+CZ16+28))*(CZ9-CZ11)*CZ11/10000)))} -> 96.2288 | DA20: {=_xlfn.IFS(DA17="No",((DA9*2*(DA10+DA11+3)/10000*(DA14+DA15+DA16))+((DA9-DA11)*DA11*2*(DA14+DA15+DA16+28)/10000)+((DA11+1)*(DA12+DA13)*2/10000*(DA14+DA15+28))),DA17="Yes",(DA9*2*(DA10+DA11/2+1.5)/10000*(DA14+DA15+DA16)+(((DA14+DA15+DA16+28))*(DA9-DA11)*DA11/10000)))} -> 68.002716 | DB20: {=_xlfn.IFS(DB17="No",((DB9*2*(DB10+DB11+3)/10000*(DB14+DB15+DB16))+((DB9-DB11)*DB11*2*(DB14+DB15+DB16+20)/10000)+(DB11*(DB12+DB13)*2/10000*(DB14+DB15+20))),DB17="Yes",(DB9*2*(DB10+DB11/2+1.5)/10000*(DB14+DB15+DB16)+(((DB14+DB15+DB16+20))*(DB9-DB11)*DB11/10000)))} -> 79.996608 | DC20: {=_xlfn.IFS(DC17="No",((DC9*2*(DC10+DC11+3)/10000*(DC14+DC15+DC16))+((DC9-DC11)*DC11*2*(DC14+DC15+DC16+28)/10000)+((DC11+1)*(DC12+DC13)*2/10000*(DC14+DC15+28))),DC17="Yes",(DC9*2*(DC10+DC11/2+1.5)/10000*(DC14+DC15+DC16)+(((DC14+DC15+DC16+28))*(DC9-DC11)*DC11/10000)))} -> 65.00286 | DD20: {=_xlfn.IFS(DD17="No",((DD9*2*(DD10+DD11+3)/10000*(DD14+DD15+DD16))+((DD9-DD11)*DD11*2*(DD14+DD15+DD16+28)/10000)+((DD11+1)*(DD12+DD13)*2/10000*(DD14+DD15+28))),DD17="Yes",(DD9*2*(DD10+DD11/2+1.5)/10000*(DD14+DD15+DD16)+(((DD14+DD15+DD16+28))*(DD9-DD11)*DD11/10000)))} -> 79.9864 | DE20: {=_xlfn.IFS(DE17="No",((DE9*2*(DE10+DE11+3)/10000*(DE14+DE15+DE16))+((DE9-DE11)*DE11*2*(DE14+DE15+DE16+28)/10000)+((DE11+1)*(DE12+DE13)*2/10000*(DE14+DE15+28))),DE17="Yes",(DE9*2*(DE10+DE11/2+1.5)/10000*(DE14+DE15+DE16)+(((DE14+DE15+DE16+28))*(DE9-DE11)*DE11/10000)))} -> 69.1514 | DF20: {=_xlfn.IFS(DF17="No",((DF9*2*(DF10+DF11+3)/10000*(DF14+DF15+DF16))+((DF9-DF11)*DF11*2*(DF14+DF15+DF16+28)/10000)+((DF11+1)*(DF12+DF13)*2/10000*(DF14+DF15+28))),DF17="Yes",(DF9*2*(DF10+DF11/2+1.5)/10000*(DF14+DF15+DF16)+(((DF14+DF15+DF16+28))*(DF9-DF11)*DF11/10000)))} -> 91.4868 | DG20: {=_xlfn.IFS(DG17="No",((DG9*2*(DG10+DG11+3)/10000*(DG14+DG15+DG16))+((DG9-DG11)*DG11*2*(DG14+DG15+DG16+28)/10000)+((DG11+1)*(DG12+DG13)*2/10000*(DG14+DG15+28))),DG17="Yes",(DG9*2*(DG10+DG11/2+1.5)/10000*(DG14+DG15+DG16)+(((DG14+DG15+DG16+28))*(DG9-DG11)*DG11/10000)))} -> 79.01 | DH20: {=_xlfn.IFS(DH17="No",((DH9*2*(DH10+DH11+3)/10000*(DH14+DH15+DH16))+((DH9-DH11)*DH11*2*(DH14+DH15+DH16+28)/10000)+((DH11+1)*(DH12+DH13)*2/10000*(DH14+DH15+28))),DH17="Yes",(DH9*2*(DH10+DH11/2+1.5)/10000*(DH14+DH15+DH16)+(((DH14+DH15+DH16+28))*(DH9-DH11)*DH11/10000)))} -> 76.01 | DI20: {=_xlfn.IFS(DI17="No",((DI9*2*(DI10+DI11+3)/10000*(DI14+DI15+DI16))+((DI9-DI11)*DI11*2*(DI14+DI15+DI16+28)/10000)+((DI11+1)*(DI12+DI13)*2/10000*(DI14+DI15+28))),DI17="Yes",(DI9*2*(DI10+DI11/2+1.5)/10000*(DI14+DI15+DI16)+(((DI14+DI15+DI16+28))*(DI9-DI11)*DI11/10000)))} -> 72.0164 | DJ20: {=_xlfn.IFS(DJ17="No",((DJ9*2*(DJ10+DJ11+3)/10000*(DJ14+DJ15+DJ16))+((DJ9-DJ11)*DJ11*2*(DJ14+DJ15+DJ16+20)/10000)+(DJ11*(DJ12+DJ13)*2/10000*(DJ14+DJ15+20))),DJ17="Yes",(DJ9*2*(DJ10+DJ11/2+1.5)/10000*(DJ14+DJ15+DJ16)+(((DJ14+DJ15+DJ16+20))*(DJ9-DJ11)*DJ11/10000)))} -> 60.012 | DK20: {=_xlfn.IFS(DK17="No",((DK9*2*(DK10+DK11+3)/10000*(DK14+DK15+DK16))+((DK9-DK11)*DK11*2*(DK14+DK15+DK16+20)/10000)+(DK11*(DK12+DK13)*2/10000*(DK14+DK15+20))),DK17="Yes",(DK9*2*(DK10+DK11/2+1.5)/10000*(DK14+DK15+DK16)+(((DK14+DK15+DK16+20))*(DK9-DK11)*DK11/10000)))} -> 73.584 | DL20: {=_xlfn.IFS(DL17="No",((DL9*2*(DL10+DL11+3)/10000*(DL14+DL15+DL16))+((DL9-DL11)*DL11*2*(DL14+DL15+DL16+28)/10000)+((DL11+1)*(DL12+DL13)*2/10000*(DL14+DL15+28))),DL17="Yes",(DL9*2*(DL10+DL11/2+1.5)/10000*(DL14+DL15+DL16)+(((DL14+DL15+DL16+28))*(DL9-DL11)*DL11/10000)))} -> 63.3672 | DM20: {=_xlfn.IFS(DM17="No",((DM9*2*(DM10+DM11+3)/10000*(DM14+DM15+DM16))+((DM9-DM11)*DM11*2*(DM14+DM15+DM16+28)/10000)+((DM11+1)*(DM12+DM13)*2/10000*(DM14+DM15+28))),DM17="Yes",(DM9*2*(DM10+DM11/2+1.5)/10000*(DM14+DM15+DM16)+(((DM14+DM15+DM16+28))*(DM9-DM11)*DM11/10000)))} -> 87.1976 | DN20: {=_xlfn.IFS(DN17="No",((DN9*2*(DN10+DN11+3)/10000*(DN14+DN15+DN16))+((DN9-DN11)*DN11*2*(DN14+DN15+DN16+20)/10000)+(DN11*(DN12+DN13)*2/10000*(DN14+DN15+20))),DN17="Yes",(DN9*2*(DN10+DN11/2+1.5)/10000*(DN14+DN15+DN16)+(((DN14+DN15+DN16+20))*(DN9-DN11)*DN11/10000)))} -> 73.05192 | DO20: {=_xlfn.IFS(DO17="No",((DO9*2*(DO10+DO11+3)/10000*(DO14+DO15+DO16))+((DO9-DO11)*DO11*2*(DO14+DO15+DO16+28)/10000)+((DO11+1)*(DO12+DO13)*2/10000*(DO14+DO15+28))),DO17="Yes",(DO9*2*(DO10+DO11/2+1.5)/10000*(DO14+DO15+DO16)+(((DO14+DO15+DO16+28))*(DO9-DO11)*DO11/10000)))} -> 80.3588 | DP20: {=_xlfn.IFS(DP17="No",((DP9*2*(DP10+DP11+3)/10000*(DP14+DP15+DP16))+((DP9-DP11)*DP11*2*(DP14+DP15+DP16+28)/10000)+((DP11+1)*(DP12+DP13)*2/10000*(DP14+DP15+28))),DP17="Yes",(DP9*2*(DP10+DP11/2+1.5)/10000*(DP14+DP15+DP16)+(((DP14+DP15+DP16+28))*(DP9-DP11)*DP11/10000)))} -> 92.000737 | DQ20: {=_xlfn.IFS(DQ17="No",((DQ9*2*(DQ10+DQ11+3)/10000*(DQ14+DQ15+DQ16))+((DQ9-DQ11)*DQ11*2*(DQ14+DQ15+DQ16+20)/10000)+(DQ11*(DQ12+DQ13)*2/10000*(DQ14+DQ15+20))),DQ17="Yes",(DQ9*2*(DQ10+DQ11/2+1.5)/10000*(DQ14+DQ15+DQ16)+(((DQ14+DQ15+DQ16+20))*(DQ9-DQ11)*DQ11/10000)))} -> 63.194 | DR20: {=_xlfn.IFS(DR17="No",((DR9*2*(DR10+DR11+3)/10000*(DR14+DR15+DR16))+((DR9-DR11)*DR11*2*(DR14+DR15+DR16+28)/10000)+((DR11+1)*(DR12+DR13)*2/10000*(DR14+DR15+28))),DR17="Yes",(DR9*2*(DR10+DR11/2+1.5)/10000*(DR14+DR15+DR16)+(((DR14+DR15+DR16+28))*(DR9-DR11)*DR11/10000)))} -> 104.8158 | DS20: {=_xlfn.IFS(DS17="No",((DS9*2*(DS10+DS11+3)/10000*(DS14+DS15+DS16))+((DS9-DS11)*DS11*2*(DS14+DS15+DS16+28)/10000)+((DS11+1)*(DS12+DS13)*2/10000*(DS14+DS15+28))),DS17="Yes",(DS9*2*(DS10+DS11/2+1.5)/10000*(DS14+DS15+DS16)+(((DS14+DS15+DS16+28))*(DS9-DS11)*DS11/10000)))} -> 109.9244 | DT20: {=_xlfn.IFS(DT17="No",((DT9*2*(DT10+DT11+3)/10000*(DT14+DT15+DT16))+((DT9-DT11)*DT11*2*(DT14+DT15+DT16+28)/10000)+((DT11+1)*(DT12+DT13)*2/10000*(DT14+DT15+28))),DT17="Yes",(DT9*2*(DT10+DT11/2+1.5)/10000*(DT14+DT15+DT16)+(((DT14+DT15+DT16+28))*(DT9-DT11)*DT11/10000)))} -> 44.1728 | DU20: {=_xlfn.IFS(DU17="No",((DU9*2*(DU10+DU11+3)/10000*(DU14+DU15+DU16))+((DU9-DU11)*DU11*2*(DU14+DU15+DU16+28)/10000)+((DU11+1)*(DU12+DU13)*2/10000*(DU14+DU15+28))),DU17="Yes",(DU9*2*(DU10+DU11/2+1.5)/10000*(DU14+DU15+DU16)+(((DU14+DU15+DU16+28))*(DU9-DU11)*DU11/10000)))} -> 70.6452
B21: Liner Micron | N21: 30 | O21: 0 | P21: 0 | R21: 0 | S21: 0 | T21: 0 | X21: 0 | Y21: 0 | Z21: 0 | AA21: 0 | AB21: 0 | AF21: 0 | AG21: 0 | AH21: 0 | AI21: 0 | AJ21: 0 | AK21: 0 | AL21: 0 | AM21: 0 | AN21: 0 | AO21: 0 | AP21: 80 | AQ21: 0 | AR21: 0 | AS21: 0 | AT21: 0 | AU21: 0 | AV21: 0 | AW21: 0 | AX21: 0 | AY21: 0 | AZ21: 0 | BA21: 0 | BB21: 0 | BC21: 0 | BK21: 0 | BL21: 0 | BN21: 0 | BO21: 0 | BP21: 0 | BQ21: 0 | BR21: 0 | BS21: 0 | BT21: 0 | BU21: 0 | BV21: 0 | BW21: 0 | BX21: 0 | BY21: 0 | BZ21: 0 | CA21: 0 | CB21: 0 | CC21: 0 | CD21: 0 | CE21: 0 | CF21: 0 | CH21: 0 | CI21: 0 | CJ21: 0 | CK21: 0 | CL21: 0 | CM21: 0 | CQ21: 0 | CR21: 0 | CS21: 0 | CT21: 0 | CU21: 0 | CV21: 0 | CW21: 0 | CX21: 0 | CY21: 0 | CZ21: 0 | DA21: 0 | DB21: 0 | DC21: 0 | DD21: 0 | DE21: 0 | DF21: 0 | DG21: 0 | DH21: 0 | DI21: 0 | DJ21: 0 | DK21: 0 | DL21: 0 | DM21: 40 | DN21: 0 | DO21: 0 | DP21: 0 | DQ21: 0 | DR21: 0 | DS21: 50 | DT21: 0 | DU21: 0
B22: Liner Wt | C22: =(C9+3)*2*(C10+C11)*C21*0.92/10000 -> 0 | D22: =(D9+3)*2*(D10+D11)*D21*0.92/10000 -> 0 | E22: =(E9+3)*2*(E10+E11)*E21*0.92/10000 -> 0 | F22: =(F9+3)*2*(F10+F11)*F21*0.92/10000 -> 0 | G22: =(G9+3)*2*(G10+G11)*G21*0.92/10000 -> 0 | H22: =(H9+3)*2*(H10+H11)*H21*0.92/10000 -> 0 | I22: =(I9+3)*2*(I10+I11)*I21*0.92/10000 -> 0 | J22: =(J9+3)*2*(J10+J11)*J21*0.92/10000 -> 0 | ... DU22: =(DU9+3)*2*(DU10+DU11)*DU21*0.92/10000 -> 0
B23: Total Wt | C23: =C20+C22 -> 81.675 | D23: =D20+D22 -> 84.0454 | E23: =E20+E22 -> 46.548 | F23: =F20+F22 -> 43.6284 | G23: =G20+G22 -> 53.339 | H23: =H20+H22 -> 53.339 | I23: =I20+I22 -> 56.00309 | J23: =J20+J22 -> 69.9388 | ... DU23: =DU20+DU22 -> 70.6452
B24: Pcs/Bale | C24: 500 | D24: 500 | E24: 500 | F24: 500 | O24: 1000 | P24: 1000 | AP24: 500 | AQ24: 500 | AR24: 500 | AS24: 500 | AT24: 500 | AU24: 500 | AV24: 4000 | BP24: 4000 | BQ24: 5000 | BR24: 5000 | BT24: 4000 | BU24: 4000 | BV24: 5000 | BW24: 5000 | BX24: 500 | BZ24: 500 | CG24: 500 | CH24: 500 | CI24: 500 | CQ24: 500 | CU24: 500 | CY24: 1000 | DO24: 500
B25: Pc/Pallet | C25: 6000 | D25: 6000 | E25: 6000 | F25: 6000 | G25: 6000 | H25: 6000 | I25: 6000 | J25: 6000 | K25: 6000 | L25: 6000 | M25: 6000 | N25: 6000 | Q25: 6000 | R25: 6000 | S25: 8000 | T25: 8000 | U25: 6000 | V25: 8000 | W25: 8000 | X25: 5000 | Y25: 5000 | Z25: 6000 | AA25: 6000 | AB25: 6000 | AC25: 6000 | AD25: 6000 | AE25: 6000 | AF25: 4000 | AG25: 4000 | AH25: 5000 | AI25: 5000 | AJ25: 4000 | AK25: 4000 | AL25: 4000 | AM25: 4000 | AN25: 4000 | AO25: 4000 | AW25: 4000 | AX25: 4000 | AY25: 4000 | AZ25: 5000 | BA25: 5000 | BB25: 5000 | BC25: 4000 | BD25: 6000 | BE25: 6000 | BF25: 6000 | BG25: 5000 | BH25: 4000 | BI25: 5000 | BJ25: 4000 | BK25: 4000 | BL25: 4000 | BM25: 6000 | BN25: 4000 | BO25: 4000 | BS25: 4000 | CA25: 6000 | CB25: 6000 | CC25: 6000 | CD25: 6000 | CE25: 5000 | CF25: 5000 | CG25: 6000 | CJ25: 5000 | CK25: 6000 | CL25: 6000 | CM25: 4000 | CN25: 7500 | CO25: 6000 | CP25: 7500 | CR25: 5000 | CS25: 5000 | CT25: 5000 | CV25: 6000 | CW25: 6000 | CX25: 6000 | CZ25: 5000 | DA25: 5000 | DC25: 5000 | DD25: 5000 | DE25: 5000 | DF25: 4000 | DG25: 4000 | DH25: 4000 | DI25: 4000 | DJ25: 4000 | DK25: 5000 | DL25: 5000 | DM25: 4000 | DN25: 5000 | DP25: 4000 | DQ25: 4000 | DR25: 4000 | DS25: 4000 | DT25: 5000 | DU25: 5000
B26: PP Rafia | C26: {=IF(C$4="","",_xlfn.IFS(C$5="Export",LOOKUP(C$4,'RM Prices'!$C$4:$DG$4,'RM Prices'!$C5:$DG5),C$5="Domestic",LOOKUP(C$4,'RM Prices'!$C$31:$DG$31,'RM Prices'!$C32:$DG32)))} -> 87.256 | D26: {=IF(D$4="","",_xlfn.IFS(D$5="Export",LOOKUP(D$4,'RM Prices'!$C$4:$DG$4,'RM Prices'!$C5:$DG5),D$5="Domestic",LOOKUP(D$4,'RM Prices'!$C$31:$DG$31,'RM Prices'!$C32:$DG32)))} -> 87.256 | E26: {=IF(E$4="","",_xlfn.IFS(E$5="Export",LOOKUP(E$4,'RM Prices'!$C$4:$DG$4,'RM Prices'!$C5:$DG5),E$5="Domestic",LOOKUP(E$4,'RM Prices'!$C$31:$DG$31,'RM Prices'!$C32:$DG32)))} -> 87.256 | F26: {=IF(F$4="","",_xlfn.IFS(F$5="Export",LOOKUP(F$4,'RM Prices'!$C$4:$DG$4,'RM Prices'!$C5:$DG5),F$5="Domestic",LOOKUP(F$4,'RM Prices'!$C$31:$DG$31,'RM Prices'!$C32:$DG32)))} -> 87.256 | G26: {=IF(G$4="","",_xlfn.IFS(G$5="Export",LOOKUP(G$4,'RM Prices'!$C$4:$DG$4,'RM Prices'!$C5:$DG5),G$5="Domestic",LOOKUP(G$4,'RM Prices'!$C$31:$DG$31,'RM Prices'!$C32:$DG32)))} -> 84.494 | H26: {=IF(H$4="","",_xlfn.IFS(H$5="Export",LOOKUP(H$4,'RM Prices'!$C$4:$DG$4,'RM Prices'!$C5:$DG5),H$5="Domestic",LOOKUP(H$4,'RM Prices'!$C$31:$DG$31,'RM Prices'!$C32:$DG32)))} -> 84.494 | I26: {=IF(I$4="","",_xlfn.IFS(I$5="Export",LOOKUP(I$4,'RM Prices'!$C$4:$DG$4,'RM Prices'!$C5:$DG5),I$5="Domestic",LOOKUP(I$4,'RM Prices'!$C$31:$DG$31,'RM Prices'!$C32:$DG32)))} -> 84.494 | J26: {=IF(J$4="","",_xlfn.IFS(J$5="Export",LOOKUP(J$4,'RM Prices'!$C$4:$DG$4,'RM Prices'!$C5:$DG5),J$5="Domestic",LOOKUP(J$4,'RM Prices'!$C$31:$DG$31,'RM Prices'!$C32:$DG32)))} -> 84.494 | ... DU26: {=IF(DU$4="","",_xlfn.IFS(DU$5="Export",LOOKUP(DU$4,'RM Prices'!$C$4:$DG$4,'RM Prices'!$C5:$DG5),DU$5="Domestic",LOOKUP(DU$4,'RM Prices'!$C$31:$DG$31,'RM Prices'!$C32:$DG32)))} -> 135.557
B27: Conversion INR | C27: 100 | D27: 100 | E27: 100 | F27: 110 | G27: 87.6 | H27: 87.6 | I27: 87.6 | J27: 87.6 | K27: 87.6 | L27: 87.6 | M27: 87.6 | N27: 132 | O27: 87.6 | P27: 87.6 | Q27: 60 | R27: 85 | S27: 95.8 | T27: 76 | U27: 132 | V27: 120 | W27: 55 | X27: 64 | Y27: 64 | Z27: 80 | AA27: 80 | AB27: 90 | AC27: 87.6 | AD27: 87.6 | AE27: 87.6 | AF27: 135 | AG27: 65 | AH27: 70 | AI27: 70 | AJ27: 70 | AK27: 70 | AL27: 70 | AM27: 55 | AN27: 60 | AO27: 70 | AP27: 90 | AQ27: 90 | AR27: 85 | AS27: 75 | AT27: 150 | AU27: 160 | AV27: 80 | AW27: 65 | AX27: 65 | AY27: 65 | AZ27: 65 | BA27: 67 | BB27: 70 | BC27: 56 | BD27: 61 | BE27: 61 | BF27: 64 | BG27: 70 | BH27: 70 | BI27: 145 | BJ27: 145 | BK27: 65 | BL27: 130 | BM27: 85 | BN27: 56 | BO27: 56 | BP27: 82 | BQ27: 57 | BR27: 57 | BS27: 65 | BT27: 78 | BU27: 78 | BV27: 38 | BW27: 37.8 | BX27: 85 | BY27: 65 | BZ27: 80 | CA27: 77 | CB27: 74 | CC27: 145 | CD27: 78 | CE27: 78 | CF27: 145 | CG27: 100 | CH27: 75 | CI27: 160 | CJ27: 158 | CK27: 90 | CL27: 88 | CM27: 65 | CN27: 87.6 | CO27: 87.6 | CP27: 87.6 | CQ27: 160 | CR27: 78 | CS27: 65 | CT27: 67 | CU27: 190 | CV27: 90 | CW27: 88 | CX27: 140 | CY27: 65 | CZ27: 158 | DA27: 68 | DB27: 65 | DC27: 75 | DD27: 140 | DE27: 140 | DF27: 70 | DG27: 65 | DH27: 65 | DI27: 65 | DJ27: 80 | DK27: 60 | DL27: 62 | DM27: 135 | DN27: 50 | DO27: 60 | DP27: 165 | DQ27: 68 | DR27: 75 | DS27: 109.2 | DT27: 76 | DU27: 55
B28: FOB Cost INR/Kg | C28: =C26+C27 -> 187.256 | D28: =D26+D27 -> 187.256 | E28: =E26+E27 -> 187.256 | F28: =F26+F27 -> 197.256 | G28: =G26+G27 -> 172.094 | H28: =H26+H27 -> 172.094 | I28: =I26+I27 -> 172.094 | J28: =J26+J27 -> 172.094 | ... DU28: =DU26+DU27 -> 190.557
B29: Sea Freight Kg | C29: 14.43 | D29: 14.43 | E29: =4000/21000*84 -> 16 | F29: 0 | G29: 0 | H29: 0 | I29: 0 | J29: 0 | K29: 0 | L29: 0 | M29: 0 | N29: 0 | O29: 0 | P29: 0 | Q29: =1850*87/20000 -> 8.0475 | R29: 0 | S29: 0 | T29: 0 | U29: 0 | V29: 0 | W29: 0 | X29: 0 | Y29: =2100/21000*85 -> 8.5 | Z29: 0 | AA29: 0 | AB29: 0 | AC29: 0 | AD29: 0 | AE29: 0 | AF29: 0 | AG29: 0 | AH29: 0 | AI29: 0 | AJ29: 0 | AK29: 0 | AL29: 0 | AM29: 0 | AN29: 0 | AO29: 0 | AP29: 0 | AQ29: 0 | AR29: 0 | AS29: 0 | AT29: 0 | AU29: 0 | AV29: 0 | AW29: 0 | AX29: 0 | AY29: 0 | AZ29: =3700/20000*88 -> 16.28 | BA29: =3700/20000*88 -> 16.28 | BB29: 0 | BC29: 0 | BD29: 0 | BE29: 0 | BF29: 0 | BG29: 0 | BH29: 0 | BI29: 0 | BJ29: 0 | BK29: 0 | BL29: 0 | BM29: 0 | BN29: 0 | BO29: 0 | BP29: 0 | BQ29: 0 | BR29: 0 | BS29: 0 | BT29: 0 | BU29: 0 | BV29: 0 | BW29: 0 | BX29: 0 | BY29: 0 | BZ29: 0 | CA29: 0 | CB29: 0 | CC29: 0 | CD29: 0 | CE29: =8 -> 8 | CF29: =8 -> 8 | CG29: =16-13 -> 3 | CH29: 0 | CI29: 0 | CK29: 0 | CL29: 0 | CM29: 0 | CN29: 0 | CO29: 0 | CP29: 0 | CQ29: 0 | CR29: =8 -> 8 | CS29: =3700/20000*93 -> 17.205 | CT29: =3700/20000*93 -> 17.205 | CU29: 0 | CV29: 0 | CW29: 0 | CX29: 0 | CY29: 0 | DB29: 0 | DJ29: 0 | DK29: =5100/20000*94 -> 23.97 | DL29: =5100/20000*94 -> 23.97 | DN29: =5100/20000*94 -> 23.97 | DO29: =5100/20000*94 -> 23.97 | DQ29: 0 | DR29: 0 | DS29: 0
B30: USD/INR | C30: 83 | D30: 83 | E30: 83 | F30: 83 | G30: 83 | H30: 83 | I30: 83 | J30: 83 | K30: 83 | L30: 83 | M30: 83 | N30: 84 | O30: 84 | P30: 84 | Q30: 85 | R30: 84 | S30: 86 | T30: 86 | U30: 84 | V30: 84 | W30: 84 | X30: 85 | Y30: 85 | Z30: 84 | AA30: 84 | AB30: 84 | AC30: 83 | AD30: 83 | AE30: 83 | AF30: 83 | AG30: 83 | AH30: 83 | AI30: 83 | AJ30: 84 | AK30: 84 | AL30: 84 | AM30: 84 | AN30: 84 | AO30: 84 | AP30: 86 | AQ30: 86 | AR30: 86 | AS30: 86 | AT30: 86 | AU30: 86 | AV30: 86 | AW30: 84 | AX30: 84 | AY30: 84 | AZ30: 86 | BA30: 86 | BB30: 86 | BC30: 84 | BD30: 89 | BE30: 89 | BF30: 89 | BG30: 88 | BH30: 88 | BI30: 88 | BJ30: 88 | BK30: 84 | BL30: 84 | BM30: 83 | BN30: 84 | BO30: 84 | BP30: 86 | BQ30: 90 | BR30: 90 | BS30: 84 | BT30: 88 | BU30: 88 | BV30: 91 | BW30: 91 | BX30: 86 | BY30: 84 | BZ30: 87 | CA30: 86 | CB30: 86 | CC30: 86 | CD30: 86 | CE30: 86 | CF30: 86 | CG30: 86 | CH30: 86 | CI30: 86 | CJ30: 86 | CK30: 86 | CL30: 86 | CM30: 84 | CN30: 85 | CO30: 85 | CP30: 85 | CQ30: 86 | CR30: 86 | CS30: 86 | CT30: 86 | CU30: 86 | CV30: 86 | CW30: 86 | CX30: 86 | CY30: 86 | CZ30: 88 | DA30: 88 | DB30: 84 | DC30: 87 | DD30: 87 | DE30: 87 | DF30: 87 | DG30: 87 | DH30: 87 | DI30: 87 | DJ30: 84 | DK30: 86 | DL30: 88 | DM30: 88 | DN30: 90 | DO30: 88 | DP30: 88 | DQ30: 84 | DR30: 86 | DS30: 86 | DT30: 88 | DU30: 88
B31: Exchange-Euro | C31: 1.08 | D31: 1.08 | E31: 1.08 | F31: 1.08 | G31: 1.08 | H31: 1.08 | I31: 1.08 | J31: 1.08 | K31: 1.08 | L31: 1.08 | M31: 1.08 | N31: 1.08 | O31: 1.08 | P31: 1.08 | Q31: 1.08 | R31: 1.08 | S31: 1.08 | T31: 1.08 | U31: 1.08 | V31: 1.08 | W31: 1.08 | X31: 1.08 | Y31: 1.08 | Z31: 1.08 | AA31: 1.08 | AB31: 1.08 | AC31: 1.08 | AD31: 1.08 | AE31: 1.08 | AF31: 1.08 | AG31: 1.08 | AH31: 1.08 | AI31: 1.08 | AJ31: 1.08 | AK31: 1.08 | AL31: 1.08 | AM31: 1.08 | AN31: 1.08 | AO31: 1.08 | AP31: 1.08 | AQ31: 1.08 | AR31: 1.17 | AS31: 1.17 | AT31: 1.17 | AU31: 1.17 | AV31: 1.17 | AW31: 1.08 | AX31: 1.08 | AY31: 1.08 | AZ31: 1.08 | BA31: 1.08 | BB31: 1.08 | BC31: 1.08 | BD31: 1.08 | BE31: 1.08 | BF31: 1.08 | BG31: 1.08 | BH31: 1.08 | BI31: 1.08 | BJ31: 1.08 | BK31: 1.08 | BL31: 1.08 | BM31: 1.08 | BN31: 1.08 | BO31: 1.08 | BP31: 1.17 | BQ31: 1.17 | BR31: 1.17 | BS31: 1.08 | BT31: 1.17 | BU31: 1.17 | BV31: 1.17 | BW31: 1.17 | BX31: 1.17 | BY31: 1.08 | BZ31: 1.17 | CA31: 1.08 | CB31: 1.08 | CC31: 1.08 | CD31: 1.08 | CE31: 1.16 | CF31: 1.16 | CG31: 1.14 | CH31: 1.16 | CI31: 1.16 | CJ31: 1.16 | CK31: 1.08 | CL31: 1.08 | CM31: 1.08 | CN31: 1.08 | CO31: 1.08 | CP31: 1.08 | CQ31: 1.16 | CR31: 1.16 | CS31: 1.08 | CT31: 1.08 | CU31: 1.16 | CV31: 1.08 | CW31: 1.08 | CX31: 1.08 | CY31: 1.08 | CZ31: 1.16 | DA31: 1.16 | DB31: 1.08 | DC31: 1.16 | DD31: 1.16 | DE31: 1.16 | DF31: 1.16 | DG31: 1.16 | DH31: 1.16 | DI31: 1.16 | DJ31: 1.08 | DK31: 1.08 | DL31: 1.08 | DM31: 1.16 | DN31: 1.08 | DO31: 1.16 | DP31: 1.16 | DQ31: 1.08 | DR31: 1.16 | DS31: 1.16 | DT31: 1.16 | DU31: 1.16
B32: Exchange-GBP | C32: 1.2 | D32: 1.2 | E32: 1.2 | F32: 1.2 | G32: 1.2 | H32: 1.2 | I32: 1.2 | J32: 1.2 | K32: 1.2 | L32: 1.2 | M32: 1.2 | N32: 1.2 | O32: 1.2 | P32: 1.2 | Q32: 1.2 | R32: 1.2 | S32: 1.2 | T32: 1.2 | U32: 1.2 | V32: 1.2 | W32: 1.2 | X32: 1.2 | Y32: 1.2 | Z32: 1.2 | AA32: 1.2 | AB32: 1.2 | AC32: 1.2 | AD32: 1.2 | AE32: 1.2 | AF32: 1.2 | AG32: 1.2 | AH32: 1.2 | AI32: 1.2 | AJ32: 1.2 | AK32: 1.2 | AL32: 1.2 | AM32: 1.2 | AN32: 1.2 | AO32: 1.2 | AP32: 1.2 | AQ32: 1.2 | AR32: 1.2 | AS32: 1.2 | AT32: 1.2 | AU32: 1.2 | AV32: 1.2 | AW32: 1.2 | AX32: 1.2 | AY32: 1.2 | AZ32: 1.2 | BA32: 1.2 | BB32: 1.2 | BC32: 1.2 | BD32: 1.2 | BE32: 1.2 | BF32: 1.2 | BG32: 1.2 | BH32: 1.2 | BI32: 1.2 | BJ32: 1.2 | BK32: 1.2 | BL32: 1.2 | BM32: 1.2 | BN32: 1.2 | BO32: 1.2 | BP32: 1.2 | BQ32: 1.2 | BR32: 1.2 | BS32: 1.2 | BT32: 1.2 | BU32: 1.2 | BV32: 1.2 | BW32: 1.2 | BX32: 1.2 | BY32: 1.2 | BZ32: 1.2 | CA32: 1.2 | CB32: 1.2 | CC32: 1.2 | CD32: 1.2 | CE32: 1.2 | CF32: 1.2 | CG32: 1.2 | CH32: 1.2 | CI32: 1.2 | CJ32: 1.2 | CK32: 1.2 | CL32: 1.2 | CM32: 1.2 | CN32: 1.2 | CO32: 1.2 | CP32: 1.2 | CQ32: 1.2 | CR32: 1.2 | CS32: 1.2 | CT32: 1.2 | CU32: 1.2 | CV32: 1.2 | CW32: 1.2 | CX32: 1.2 | CY32: 1.2 | CZ32: 1.2 | DA32: 1.2 | DB32: 1.2 | DC32: 1.2 | DD32: 1.2 | DE32: 1.2 | DF32: 1.2 | DG32: 1.2 | DH32: 1.2 | DI32: 1.2 | DJ32: 1.2 | DK32: 1.2 | DL32: 1.2 | DM32: 1.2 | DN32: 1.2 | DO32: 1.2 | DP32: 1.2 | DQ32: 1.2 | DR32: 1.2 | DS32: 1.2 | DT32: 1.2 | DU32: 1.2
B33: USD/Pc | C33: =(C28+C29)/C30*C23/1000 -> 0.19846631 | D33: =(D28+D29)/D30*D23/1000 -> 0.20422627 | E33: =(E28+E29)/E30*E23/1000 -> 0.11398988 | F33: =(F28+F29)/F30*F23/1000 -> 0.10368631 | G33: =(G28+G29)/G30*G23/1000 -> 0.11059424 | H33: =(H28+H29)/H30*H23/1000 -> 0.11059424 | I33: =(I28+I29)/I30*I23/1000 -> 0.11611802 | J33: =(J28+J29)/J30*J23/1000 -> 0.14501262 | ... DU33: =(DU28+DU29)/DU30*DU23/1000 -> 0.15297656
B34: Euro/Pc | C34: =C33/C31 -> 0.18376511 | D34: =D33/D31 -> 0.1890984 | E34: =E33/E31 -> 0.10554619 | F34: =F33/F31 -> 0.096005842 | G34: =G33/G31 -> 0.10240207 | H34: =H33/H31 -> 0.10240207 | I34: =I33/I31 -> 0.10751669 | J34: =J33/J31 -> 0.13427095 | ... DU34: =DU33/DU31 -> 0.13187635
AT36: =AT28/AT30 -> 2.6864767 | AU36: =AU28/AU30 -> 2.8027558 | AW36: =AW28*AW23/1000 -> 9.0601186 | AX36: =AX28*AX23/1000 -> 10.762091 | AY36: =AY28*AY23/1000 -> 9.6953952 | BC36: =BC28*BC23/1000 -> 8.9137024 | BD36: =BD28/BD30 -> 1.5625506 | BE36: =BE28/BE30 -> 1.5625506 | BF36: =BF28/BF30 -> 1.5962584 | BK36: =BK28*BK23/1000 -> 12.615579 | BL36: =BL28*BL23/1000 -> 20.374577 | BM36: =BM28*BM23/1000 -> 9.2727953 | BN36: =BN28*BN23/1000 -> 9.0637324 | BO36: =BO28*BO23/1000 -> 9.3863367 | BQ36: 0.1069 | BR36: 0.096 | BS36: =BS28*BS23/1000 -> 10.113062 | BV36: 0.1069 | BW36: 0.096 | BY36: =BY28*BY23/1000 -> 13.082259 | CM36: =CM28*CM23/1000 -> 14.568239 | CX36: =CX28*CX23/1000 -> 37.352204 | CY36: =CY28*CY23/1000 -> 18.446253 | DA36: =DA28*DA23/1000 -> 15.88081 | DB36: =DB28*DB23/1000 -> 18.441778 | DJ36: =DJ28*DJ23/1000 -> 13.236067 | DQ36: =DQ28*DQ23/1000 -> 12.800387 | DS36: =DS28*DS23/1000 -> 39.050784 | DT36: =DT28*DT23/1000 -> 9.345065 | DU36: =DU28*DU23/1000 -> 13.461937
AH37: =170*0.095 -> 16.15 | AI37: =160*0.095 -> 15.2 | AY37: 0.25 | BC37: 0.25
AT38: =AT36*1.03 -> 2.767071 | AY38: Printing | BC38: Printing
AI39: =14.6/0.095 -> 153.68421 | AT39: =AT33*1.03 -> 0.33794575 | AY39: moq 50000 | BC39: moq 50000
AY41: 10.1 | BC41: 10.1
AY42: if 25000 | BC42: if 25000

Sheet Working
B1: Working of Interest on Fixed Assets
B2: Land | C2: 160x80 Meter | E2: =15000*5000 -> 75000000
B3: Building | E3: =150000*1000 -> 150000000
B4: Machines | E4: =SUM(D4:D25) -> 150233000
C5: Tape Plant | D5: 30000000
C6: Looms | D6: =50*400000 -> 20000000
C7: Lamination | D7: 10000000
C8: Utility | D8: 10000000
C9: Tuber | D9: 12000000
C10: Printing Machine | D10: 15000000
C11: Bale Press | D11: 1000000
C12: Slitting Machines | D12: 900000
C13: Thumb Notch | D13: 200000
C14: Web Inspection | D14: 1800000
C15: Metal Detector | D15: 233000
C16: HVAC | D16: 17000000
C17: Electrical Installation | D17: 20000000
C18: QC Equipments | D18: 1000000
... C24: Forklift | D24: 1500000
B26: Total Investment | E26: =SUM(E2:E25) -> 375233000
B28: Interest @ | D28: 0.12 | E28: =E26*D28 -> 45027960
B29: Per Month | E29: =E28/12 -> 3752330
B30: Per Kg | E30: =E29/400000 -> 9.380825
B32: Packing Cost (Including Incoming Freight)
C33: Box | D33: 850
C34: Pallet | D34: 1200
C35: Stretch Film | D35: 17
C36: Strap | D36: 32
C38: Total | D38: =SUM(D33:D37) -> 2099
C39: Average Wt | D39: 370
C40: Per Kg Cost | D40: =D38/D39 -> 5.672973
B43: Ez Open - 7 Gram Per Meter
C44: Considered Bag Face Width + 50 MM Extra on both side
C48: Bag Finishing Cost
C49: ManPower Detail | D49: HeadCount | E49: Salary | F49: Total | G49: Capacity/Month | H49: Per 1000 Bag
C50: Plant Head | D50: 1 | E50: 185000 | F50: =D50*E50 -> 185000 | G50: =120000*26 -> 3120000 | H50: =F50/G50*1000 -> 59.294872
C51: Assistant Plant Head | D51: 1 | E51: 30000 | F51: =D51*E51 -> 30000 | G51: =120000*26 -> 3120000 | H51: =F51/G51*1000 -> 9.6153846
C52: House Keeping | D52: 6 | E52: 15000 | F52: =D52*E52 -> 90000 | G52: =120000*26 -> 3120000 | H52: =F52/G52*1000 -> 28.846154
C53: Cylindre Incharge | D53: 1 | E53: 30000 | F53: =D53*E53 -> 30000 | G53: =120000*26 -> 3120000 | H53: =F53/G53*1000 -> 9.6153846
C54: Cylinder Helper/Assistant | D54: 2 | E54: 18000 | F54: =D54*E54 -> 36000 | G54: =120000*26 -> 3120000 | H54: =F54/G54*1000 -> 11.538462
C55: Operator Slitting | D55: 1 | E55: 30000 | F55: =D55*E55 -> 30000 | G55: =120000*26 -> 3120000 | H55: =F55/G55*1000 -> 9.6153846
C56: Assistant Slitting Machine | D56: 1 | E56: 18000 | F56: =D56*E56 -> 18000 | G56: =120000*26 -> 3120000 | H56: =F56/G56*1000 -> 5.7692308
C57: Web Inspection M/c Op | D57: 2 | E57: 30000 | F57: =D57*E57 -> 60000 | G57: =120000*26 -> 3120000 | H57: =F57/G57*1000 -> 19.230769
C58: Helper | D58: 2 | E58: 18000 | F58: =D58*E58 -> 36000 | G58: =120000*26 -> 3120000 | H58: =F58/G58*1000 -> 11.538462
C59: Tuber Operator | D59: 2 | E59: 36000 | F59: =D59*E59 -> 72000 | G59: =120000*26 -> 3120000 | H59: =F59/G59*1000 -> 23.076923
C60: Helper | D60: 6 | E60: 18000 | F60: =D60*E60 -> 108000 | G60: =120000*26 -> 3120000 | H60: =F60/G60*1000 -> 34.615385
C61: Stitching Operator | D61: 4 | E61: 22000 | F61: =D61*E61 -> 88000 | G61: =120000*26 -> 3120000 | H61: =F61/G61*1000 -> 28.205128
... C66: Baling Supervision | D66: 2 | E66: 30000 | F66: =D66*E66 -> 60000 | G66: =120000*26 -> 3120000 | H66: =F66/G66*1000 -> 19.230769
C67: Pallet Packing (250/Pallet) | F67: 312000 | G67: =120000*26 -> 3120000 | H67: =F67/G67*1000 -> 100
C68: Forklift Driver | D68: 1 | E68: 22000 | F68: =D68*E68 -> 22000 | G68: =120000*26 -> 3120000 | H68: =F68/G68*1000 -> 7.0512821
C70: Total Salary Cost | H70: =SUM(H50:H69) -> 546.15385
C71: Additional 15% for Bonus/Leave Etc | H71: =H70*0.15 -> 81.923077
C72: Power Cost | H72: =0.25*1000 -> 250
C73: Maintanance/Consumables Cost | H73: 150
C75: Total Finishing Cost/1000 Bags | H75: =SUM(H70:H74) -> 1028.0769
C76: (If we run on Full Capacity)
C78: Thunb Notch - Cost | H78: 400
C79: Metal Detection Cost | H79: 300

Sheet Master
B2: Top
B3: Heat Cut
B4: Hemmed
B5: Ez Open
B6: No Fold
B9: Back Seam Bag
B10: Tubular Bag
B11: Tubular Fabric
B12: Flat Fabric
B15: MW
B16: Black/White
B17: Transparent
... B40: Palletised
B43: {=_xlfn.UNIQUE(_xlfn._xlws.SORT((TRANSPOSE('Quote Exports'!E7:AX7))))} -> ATEA Turkey
B44: Condepols
B45: Desabag
B46: ISP Korea
B47: Procon
B48: Safesack Scand
B49: 0

Sheet RM Prices
AM1: =AM5/92.5 -> 1.6172649
B3: RM Price Master | BZ3: Insert Row Before this
B4: Name | C4: 45505 | D4: 45524 | E4: 45536 | F4: 45580 | G4: 45605 | H4: 45606 | I4: 45632 | J4: 45642 | K4: 45659 | L4: 45673 | M4: 45689 | N4: 45706 | O4: 45707 | P4: 45717 | Q4: 45731 | R4: 45748 | S4: 45768 | T4: 45778 | U4: 45792 | V4: 45825 | W4: 45839 | X4: 45870 | Y4: 45889 | Z4: 45903 | AA4: 45906 | AB4: 45933 | AC4: 45968 | AD4: 45976 | AE4: 46023 | AF4: 46039 | AG4: 46043 | AH4: 46054 | AI4: 46066 | AJ4: 46070 | AK4: 46083 | AL4: 46087 | AM4: 46091 | AN4: 46096 | AO4: 46113 | AP4: 46115 | AQ4: 46128 | AR4: 46133 | AS4: 46144 | AT4: 46153 | AU4: 46161 | BZ4: End
B5: PP Rafia H030SG | C5: 90.456 | D5: 88.466 | E5: 87.256 | F5: 87.256 | G5: 86.474 | H5: 86.474 | I5: 86.474 | J5: 84.494 | K5: 85.657 | L5: 87.677 | M5: 89.679 | N5: 90.68 | O5: 90.68 | P5: 90.69 | Q5: 90.69 | R5: 89.157 | S5: 87.657 | T5: 85.447 | U5: 85.447 | V5: 86.467 | W5: 86.513 | X5: 85.561 | Y5: 84.061 | Z5: 82.061 | AA5: 82.061 | AB5: 81.037 | AC5: 80.027 | AD5: 79.037 | AE5: 78.067 | AF5: 79.567 | AG5: 79.567 | AH5: 83.617 | AI5: 83.617 | AJ5: 87.577 | AK5: 94.597 | AL5: =AK5+25 -> 119.597 | AM5: =AL5+30 -> 149.597 | AN5: 150 | AO5: 150 | AP5: 154 | AQ5: =154-7 -> 147 | AR5: 141.254 | AS5: 131.254 | AT5: 132.254 | AU5: 133.274 | BZ5: End
B6: HD Rafia E52009 | C6: 99.479 | D6: 97.939 | E6: 97.969 | F6: 97.969 | G6: 97.267 | H6: 97.267 | I6: 93.227 | J6: 93.227 | K6: 94.471 | L6: 95.411 | M6: 96.445 | N6: 96.445 | O6: 96.445 | P6: 97.825 | Q6: 97.825 | R6: 97.831 | S6: 95.791 | T6: 90.761 | U6: 91.021 | V6: 90.841 | W6: 92.382 | X6: 94.86 | Y6: 94.86 | Z6: 92.232 | AA6: 92.232 | AB6: 91.449 | AC6: 91.299 | AD6: 91.299 | AE6: 88.602 | AF6: 89.142 | AG6: 89.142 | AH6: 91.742 | AI6: 91.742 | AJ6: 94.262 | AK6: =94.262+6 -> 100.262 | AL6: =AK6+25 -> 125.262 | AM6: =AL6+30 -> 155.262 | AN6: 160 | AO6: 160 | AP6: 166.812 | AQ6: 166.812 | AR6: 156.837 | AS6: 153.837 | AT6: 154.837 | AU6: 155.837 | BZ6: End
B7: LLDPE F19010 Film | C7: 85.576 | D7: 83.576 | E7: 84.956 | F7: 84.956 | G7: 84.324 | H7: 84.324 | I7: 82.584 | J7: 82.584 | K7: 85.127 | L7: 86.587 | M7: 88.649 | N7: 88.649 | O7: 88.649 | P7: 89.99 | Q7: 89.99 | R7: 89.997 | S7: 87.867 | T7: 85.707 | U7: 85.707 | V7: 84.427 | W7: 85.503 | X7: 87.191 | Y7: 87.191 | Z7: 85.981 | AA7: 85.981 | AB7: 83.867 | AC7: 83.867 | AD7: 83.867 | AE7: 80.917 | AF7: 81.427 | AG7: 81.427 | AH7: 83.977 | AI7: 83.977 | AJ7: 86.967 | AK7: =86.967+6 -> 92.967 | AL7: =AK7+25 -> 117.967 | AM7: =AL7+30 -> 147.967 | AN7: 150 | AO7: 150 | AP7: 163.084 | AQ7: 163.084 | AR7: 146.084 | AS7: 139.084 | AT7: 140.084 | AU7: 141.084 | BZ7: End
B8: LDPE FY1005 Film | C8: 104.836 | D8: 102.886 | E8: 102.926 | F8: 102.926 | G8: 100.464 | H8: 100.464 | I8: 98.974 | J8: 98.974 | K8: 100.287 | L8: 101.807 | M8: 103.889 | N8: 103.889 | O8: 103.889 | P8: 106.03 | Q8: 106.03 | R8: 107.017 | S8: 105.937 | T8: 105.397 | U8: 105.397 | V8: 103.137 | W8: 104.583 | X8: 106.761 | Y8: 106.761 | Z8: 104.491 | AA8: 104.491 | AB8: 101.887 | AC8: 101.717 | AD8: 101.717 | AE8: 99.247 | AF8: 99.547 | AG8: 99.547 | AH8: 102.167 | AI8: 102.167 | AJ8: 103.187 | AK8: =103.187+6 -> 109.187 | AL8: =AK8+25 -> 134.187 | AM8: =AL8+30 -> 164.187 | AN8: 170 | AO8: 171.274 | AP8: 180.884 | AQ8: 180.884 | AR8: 174.884 | AS8: 168.884 | AT8: 169.884 | AU8: 170.884 | BZ8: End
B9: LDPE 7 MFI 1070LA17 | C9: 129.293 | D9: 127.743 | E9: 127.783 | F9: 127.783 | G9: 124.513 | H9: 124.513 | I9: 114.173 | J9: 114.173 | K9: 115.701 | L9: 117.211 | M9: 118.259 | N9: 118.259 | O9: 118.259 | P9: 120.33 | Q9: 120.33 | R9: 122.492 | S9: 120.222 | T9: 119.612 | U9: 119.612 | V9: 115.612 | W9: 116.696 | X9: 118.476 | Y9: 118.476 | Z9: 113.426 | AA9: 113.426 | AB9: 110.362 | AC9: 110.182 | AD9: 110.182 | AE9: 105.642 | AF9: 105.991 | AG9: 105.991 | AH9: 108.541 | AI9: 108.541 | AJ9: 109.571 | AK9: =109.571+7 -> 116.571 | AL9: =AK9+25 -> 141.571 | AM9: =AL9+30 -> 171.571 | AN9: 175 | AO9: 185.922 | AP9: 196.632 | AQ9: 196.632 | AR9: 183.632 | AS9: 173.632 | AT9: 173.632 | AU9: 173.632 | BZ9: End
B10: PP H350FG | C10: 94.446 | D10: 92.456 | E10: 91.246 | F10: 91.246 | G10: 90.464 | H10: 90.464 | I10: 90.464 | J10: 88.484 | K10: 89.647 | L10: 91.667 | M10: 93.669 | N10: 94.67 | O10: 94.67 | P10: 94.68 | Q10: 94.68 | R10: 93.147 | S10: 91.447 | T10: 88.437 | U10: 88.437 | V10: 89.457 | W10: 89.503 | X10: 88.551 | Y10: 87.051 | Z10: 85.051 | AA10: 85.051 | AB10: 84.027 | AC10: 83.017 | AD10: 82.027 | AE10: 81.047 | AF10: 82.557 | AG10: 82.557 | AH10: 86.607 | AI10: 86.607 | AJ10: 90.567 | AK10: =90.567+6 -> 96.567 | AL10: =AK10+25 -> 121.567 | AM10: =AL10+30 -> 151.567 | AN10: 160 | AO10: 160 | AP10: 160 | AQ10: =160-7 -> 153 | AR10: 142.494 | AS10: 132.544 | AT10: 133.544 | AU10: 134.564 | BZ10: End
B11: LDPE 4 MFI J24FS040 | C11: 103.156 | D11: 101.206 | E11: 101.246 | F11: 101.246 | G11: 98.784 | H11: 98.784 | I11: 97.284 | J11: 97.284 | K11: 98.577 | L11: 100.077 | M11: 102.159 | N11: 102.159 | O11: 102.159 | P11: 104.289 | Q11: 104.289 | R11: 105.297 | S11: 104.217 | T11: 103.687 | U11: 103.687 | V11: 103.687 | W11: 102.863 | X11: 104.991 | Y11: 104.991 | Z11: 102.721 | AA11: 102.721 | AB11: 100.097 | AC11: 99.937 | AD11: 99.937 | AE11: 97.447 | AF11: 97.737 | AG11: 97.737 | AH11: 100.327 | AI11: 100.327 | AJ11: 101.367 | AK11: 101.367 | AL11: =AK11+25 -> 126.367 | AM11: =AL11+30 -> 156.367 | AN11: 164 | AO11: 169.354 | AP11: 179.204 | AQ11: 179.204 | AR11: 170.204 | AS11: 161.204 | AT11: 161.204 | AU11: 170.884 | BZ11: End
B12: RP | C12: 60 | D12: 60 | E12: 60 | F12: 60 | G12: 60 | H12: 60 | I12: 60 | J12: 60 | K12: 60 | L12: 60 | M12: 60 | N12: 60 | O12: 60 | P12: 60 | Q12: 60 | R12: 60 | S12: 60 | T12: 60 | U12: 60 | V12: 60 | W12: 60 | X12: 60 | Y12: 60 | Z12: 60 | AA12: 60 | AB12: 60 | AC12: 60 | AD12: 60 | AE12: 60 | AF12: 60 | AG12: 60 | AH12: 60 | AI12: 60 | AJ12: 60 | AK12: 60 | AL12: 60 | AM12: 70 | AN12: 70 | AO12: 70 | AP12: 70 | AQ12: 70 | AR12: 70 | AS12: 70 | AT12: 70 | AU12: 70 | BZ12: End
B13: Filler | C13: 32 | D13: 32 | E13: 32 | F13: 32 | G13: 32 | H13: 32 | I13: 32 | J13: 32 | K13: 32 | L13: 32 | M13: 32 | N13: 32 | O13: 32 | P13: 32 | Q13: 32 | R13: 32 | S13: 32 | T13: 32 | U13: 32 | V13: 32 | W13: 32 | X13: 32 | Y13: 32 | Z13: 32 | AA13: 32 | AB13: 32 | AC13: 32 | AD13: 32 | AE13: 32 | AF13: 32 | AG13: 32 | AH13: 32 | AI13: 32 | AJ13: 32 | AK13: 32 | AL13: 36 | AM13: 41 | AN13: 41 | AO13: 41 | AP13: 41 | AQ13: 41 | AR13: 40 | AS13: 40 | AT13: 40 | AU13: 40 | BZ13: End
B14: TPT | C14: 44 | D14: 44 | E14: 44 | F14: 44 | G14: 44 | H14: 44 | I14: 44 | J14: 44 | K14: 44 | L14: 44 | M14: 44 | N14: 44 | O14: 44 | P14: 44 | Q14: 44 | R14: 44 | S14: 44 | T14: 44 | U14: 44 | V14: 44 | W14: 44 | X14: 44 | Y14: 44 | Z14: 44 | AA14: 44 | AB14: 44 | AC14: 44 | AD14: 44 | AE14: 44 | AF14: 44 | AG14: 44 | AH14: 44 | AI14: 44 | AJ14: 44 | AK14: 44 | AL14: 52 | AM14: 56 | AN14: 56 | AO14: 56 | AP14: 56 | AQ14: 56 | AR14: 56 | AS14: 56 | AT14: 56 | AU14: 56 | BZ14: End
B15: UV | C15: 220 | D15: 220 | E15: 220 | F15: 220 | G15: 220 | H15: 220 | I15: 220 | J15: 220 | K15: 220 | L15: 220 | M15: 220 | N15: 220 | O15: 220 | P15: 220 | Q15: 220 | R15: 220 | S15: 220 | T15: 220 | U15: 220 | V15: 220 | W15: 220 | X15: 220 | Y15: 220 | Z15: 220 | AA15: 220 | AB15: 220 | AC15: 220 | AD15: 220 | AE15: 220 | AF15: 220 | AG15: 220 | AH15: 220 | AI15: 220 | AJ15: 220 | AK15: 220 | AL15: 240 | AM15: 240 | AN15: 240 | AO15: 240 | AP15: 280 | AQ15: 280 | AR15: 280 | AS15: 280 | AT15: 280 | AU15: 280 | BZ15: End
B16: Col MB | C16: 190 | D16: 190 | E16: 190 | F16: 190 | G16: 190 | H16: 190 | I16: 190 | J16: 190 | K16: 190 | L16: 190 | M16: 190 | N16: 190 | O16: 190 | P16: 190 | Q16: 190 | R16: 190 | S16: 190 | T16: 190 | U16: 190 | V16: 190 | W16: 190 | X16: 190 | Y16: 190 | Z16: 190 | AA16: 190 | AB16: 190 | AC16: 190 | AD16: 190 | AE16: 190 | AF16: 190 | AG16: 190 | AH16: 190 | AI16: 190 | AJ16: 190 | AK16: 190 | AL16: 220 | AM16: 230 | AN16: 230 | AO16: 230 | AP16: 250 | AQ16: 250 | AR16: 250 | AS16: 250 | AT16: 250 | AU16: 250 | BZ16: End
B17: Black MB | C17: 140 | D17: 140 | E17: 140 | F17: 140 | G17: 1800 | H17: 140 | I17: 140 | J17: 140 | K17: 140 | L17: 140 | M17: 140 | N17: 140 | O17: 140 | P17: 140 | Q17: 140 | R17: 140 | S17: 140 | T17: 140 | U17: 140 | V17: 140 | W17: 140 | X17: 140 | Y17: 140 | Z17: 140 | AA17: 140 | AB17: 140 | AC17: 140 | AD17: 140 | AE17: 140 | AF17: 140 | AG17: 140 | AH17: 140 | AI17: 140 | AJ17: 140 | AK17: 140 | AL17: 160 | AM17: 160 | AN17: 160 | AO17: 160 | AP17: 160 | AQ17: 160 | AR17: 160 | AS17: 160 | AT17: 160 | AU17: 160 | BZ17: End
B18: Conductive Yarn | C18: 500 | D18: 500 | E18: 500 | F18: 500 | G18: 500 | H18: 500 | I18: 500 | J18: 500 | K18: 500 | L18: 500 | M18: 500 | N18: 500 | O18: 500 | P18: 500 | Q18: 500 | R18: 500 | S18: 500 | T18: 500 | U18: 500 | V18: 500 | W18: 500 | X18: 500 | Y18: 500 | Z18: 500 | AA18: 500 | AB18: 500 | AC18: 500 | AD18: 500 | AE18: 500 | AF18: 500 | AG18: 500 | AH18: 500 | AI18: 500 | AJ18: 500 | AK18: 500 | AL18: 500 | AM18: 600 | AN18: 600 | AO18: 600 | AP18: 600 | AQ18: 600 | AR18: 600 | AS18: 600 | AT18: 600 | AU18: 600 | BZ18: End
B19: Back Seam Coating RM | C19: =(68*C10+30*C9+2*220)/100 -> 107.41118 | D19: =(68*D10+30*D9+2*220)/100 -> 105.59298 | E19: =(68*E10+30*E9+2*220)/100 -> 104.78218 | F19: =(68*F10+30*F9+2*220)/100 -> 104.78218 | G19: =(68*G10+30*G9+2*220)/100 -> 103.26942 | H19: =(68*H10+30*H9+2*220)/100 -> 103.26942 | I19: =(68*I10+30*I9+2*220)/100 -> 100.16742 | J19: =(68*J10+30*J9+2*220)/100 -> 98.82102 | ... V19: =(68*V10+30*V9+2*220)/100 -> 99.91436 | W19: =(65*W10+30*W9+5*220)/100 -> 104.18575 | X19: =(65*X10+30*X9+5*220)/100 -> 104.10095 | Y19: =(65*Y10+30*Y9+5*220)/100 -> 103.12595 | Z19: =(65*Z10+30*Z9+5*220)/100 -> 100.31095 | AA19: =(65*AA10+30*AA9+5*220)/100 -> 100.31095 | AB19: =(65*AB10+30*AB9+5*220)/100 -> 98.72615 | AC19: =(65*AC10+30*AC9+5*220)/100 -> 98.01565 | AD19: =(65*AD10+30*AD9+5*220)/100 -> 97.37215 | ... AU19: =(65*AU10+30*AU9+5*220)/100 -> 150.5562 | BZ19: End
B20: White Paper | C20: 86 | D20: 86 | E20: 86 | F20: 86 | G20: 86 | H20: 86 | I20: 86 | J20: 86 | K20: 86 | L20: 86 | M20: 88 | N20: 88 | O20: 88 | P20: 88 | Q20: 88 | R20: 88 | S20: 88 | T20: 88 | U20: 88 | V20: 88 | W20: 88 | X20: 88 | Y20: 88 | Z20: 88 | AA20: 88 | AB20: 88 | AC20: 88 | AD20: 88 | AE20: 88 | AF20: 88 | AG20: 88 | AH20: 88 | AI20: 88 | AJ20: 88 | AK20: 88 | AL20: 88 | AM20: 92 | AN20: 92 | AO20: 92 | AP20: 92 | AQ20: 92 | AR20: 83 | AS20: 83 | AT20: 83 | AU20: 83 | BZ20: End
B21: Brown Paper | C21: 76 | D21: 76 | E21: 76 | F21: 84 | G21: 84 | H21: 84 | I21: 84 | J21: 84 | K21: 84 | L21: 84 | M21: 84 | N21: 76 | O21: 84 | P21: 84 | Q21: 76 | R21: 76 | S21: 76 | T21: 76 | U21: 76 | V21: 76 | W21: 76 | X21: 76 | Y21: 76 | Z21: 76 | AA21: 76 | AB21: 76 | AC21: 76 | AD21: 76 | AE21: 76 | AF21: 76 | AG21: 76 | AH21: 76 | AI21: 76 | AJ21: 76 | AK21: 76 | AL21: 76 | AM21: 80 | AN21: 80 | AO21: 80 | AP21: 80 | AQ21: 80 | AR21: 80 | AS21: 80 | AT21: 80 | AU21: 80 | BZ21: End
B22: Glossy BOPP | C22: 155 | D22: 155 | E22: 155 | F22: 155 | G22: 155 | H22: 155 | I22: 155 | J22: 155 | K22: 155 | L22: 155 | M22: 155 | N22: 155 | O22: 155 | P22: 155 | Q22: 155 | R22: 155 | S22: 155 | T22: 155 | U22: 155 | V22: 155 | W22: 170 | X22: 170 | Y22: 170 | Z22: 170 | AA22: 170 | AB22: 170 | AC22: 170 | AD22: 170 | AE22: 170 | AF22: 170 | AG22: 170 | AH22: 170 | AI22: 170 | AJ22: 170 | AK22: 170 | AL22: 200 | AM22: 230 | AN22: 230 | AO22: 230 | AP22: 230 | AQ22: 230 | AR22: 230 | AS22: 230 | AT22: 230 | AU22: 230 | BZ22: End
B23: Matt BOPP | C23: 175 | D23: 175 | E23: 175 | F23: 175 | G23: 175 | H23: 175 | I23: 175 | J23: 175 | K23: 175 | L23: 175 | M23: 175 | N23: 175 | O23: 175 | P23: 175 | Q23: 175 | R23: 175 | S23: 175 | T23: 175 | U23: 175 | V23: 175 | W23: 190 | X23: 190 | Y23: 190 | Z23: 190 | AA23: 190 | AB23: 190 | AC23: 190 | AD23: 190 | AE23: 190 | AF23: 190 | AG23: 190 | AH23: 190 | AI23: 190 | AJ23: 190 | AK23: 190 | AL23: 220 | AM23: 250 | AN23: 250 | AO23: 250 | AP23: 250 | AQ23: 250 | AR23: 250 | AS23: 250 | AT23: 250 | AU23: 250 | BZ23: End
B24: Metalised BOPP | C24: 175 | D24: 175 | E24: 175 | F24: 175 | G24: 175 | H24: 175 | I24: 175 | J24: 175 | K24: 175 | L24: 175 | M24: 175 | N24: 175 | O24: 175 | P24: 175 | Q24: 175 | R24: 175 | S24: 175 | T24: 175 | U24: 175 | V24: 175 | W24: 190 | X24: 190 | Y24: 190 | Z24: 190 | AA24: 190 | AB24: 190 | AC24: 190 | AD24: 190 | AE24: 190 | AF24: 190 | AG24: 190 | AH24: 190 | AI24: 190 | AJ24: 190 | AK24: 190 | AL24: 220 | AM24: 250 | AN24: 250 | AO24: 250 | AP24: 250 | AQ24: 250 | AR24: 250 | AS24: 250 | AT24: 250 | AU24: 250 | BZ24: End
B25: Adhesive | C25: 230 | D25: 230 | E25: 230 | F25: 230 | G25: 230 | H25: 230 | I25: 230 | J25: 230 | K25: 230 | L25: 230 | M25: 230 | N25: 230 | O25: 230 | P25: 230 | Q25: 230 | R25: 230 | S25: 230 | T25: 230 | U25: 230 | V25: 230 | W25: 230 | X25: 230 | Y25: 230 | Z25: 230 | AA25: 230 | AB25: 230 | AC25: 230 | AD25: 230 | AE25: 230 | AF25: 230 | AG25: 230 | AH25: 230 | AI25: 230 | AJ25: 230 | AK25: 230 | AL25: 230 | AM25: 260 | AN25: 260 | AO25: 260 | AP25: 320 | AQ25: 320 | AR25: 320 | AS25: 320 | AT25: 320 | AU25: 320 | BZ25: End
B26: Ink BOPP | C26: 1400 | D26: 1400 | E26: 1400 | F26: 1400 | G26: 1400 | H26: 1400 | I26: 1400 | J26: 1400 | K26: 1400 | L26: 1400 | M26: 1400 | N26: 1400 | O26: 1400 | P26: 1400 | Q26: 1400 | R26: 1400 | S26: 1400 | T26: 1400 | U26: 1400 | V26: 1400 | W26: 1400 | X26: 1400 | Y26: 1400 | Z26: 1400 | AA26: 1400 | AB26: 1400 | AC26: 1400 | AD26: 1400 | AE26: 1400 | AF26: 1400 | AG26: 1400 | AH26: 1400 | AI26: 1400 | AJ26: 1400 | AK26: 1400 | AL26: 1500 | AM26: 1600 | AN26: 1600 | AO26: 1600 | AP26: 1600 | AQ26: 1600 | AR26: 1600 | AS26: 1600 | AT26: 1600 | AU26: 1600 | BZ26: End
B27: Solvant BOPP | C27: 140 | D27: 140 | E27: 140 | F27: 140 | G27: 140 | H27: 140 | I27: 140 | J27: 140 | K27: 140 | L27: 140 | M27: 140 | N27: 140 | O27: 140 | P27: 140 | Q27: 140 | R27: 140 | S27: 140 | T27: 140 | U27: 140 | V27: 140 | W27: 140 | X27: 140 | Y27: 140 | Z27: 140 | AA27: 140 | AB27: 140 | AC27: 140 | AD27: 140 | AE27: 140 | AF27: 140 | AG27: 140 | AH27: 140 | AI27: 140 | AJ27: 140 | AK27: 140 | AL27: 150 | AM27: 160 | AN27: 160 | AO27: 160 | AP27: 170 | AQ27: 170 | AR27: 170 | AS27: 170 | AT27: 170 | AU27: 170 | BZ27: End
B30: RM Price Master | BZ30: Insert Row Before this
B31: Name | C31: 45474 | D31: 45524 | E31: 45536 | F31: 45605 | G31: 45632 | H31: 45642 | I31: 45659 | J31: 45673 | K31: 45689 | L31: 45717 | M31: 45748 | N31: 45768 | O31: 45778 | P31: 45792 | Q31: 45825 | R31: 45827 | S31: 45839 | T31: 45870 | U31: 45898 | V31: 45903 | W31: 45906 | X31: 45933 | Y31: 45968 | Z31: 45976 | AA31: 46023 | AB31: 46039 | AC31: 46043 | AD31: 46054 | AE31: 46066 | AF31: 46083 | AG31: 46087 | AH31: 46091 | AI31: 46096 | AJ31: 46113 | AK31: 46128 | AL31: 46133 | AM31: 46144 | AN31: 46153 | AO31: 46161 | BZ31: End
B32: PP Rafia H030SG | C32: 102.029 | D32: 102.29 | E32: 100.029 | F32: 100.034 | G32: 100.034 | H32: 98.034 | I32: 99.031 | J32: 100.031 | K32: 101.884 | L32: 102.029 | M32: 102.031 | N32: 102.031 | O32: 102.031 | P32: 99.983 | Q32: 100.031 | R32: 101.531 | S32: 102.583 | T32: 101.081 | U32: 101.081 | V32: 98.581 | W32: 94.581 | X32: 93.029 | Y32: 92.029 | Z32: 91.029 | AA32: 92.532 | AB32: 93.532 | AC32: 95.032 | AD32: 98.532 | AE32: 100.532 | AF32: =100.532+6 -> 106.532 | AG32: 123.532 | AH32: =AG32+42 -> 165.532 | AI32: 165.532 | AJ32: 165.532 | AK32: 145.557 | AL32: 140.557 | AM32: 133.557 | AN32: 134.557 | AO32: 135.557 | BZ32: End
B33: HD Rafia E52009 | C33: 103.309 | D33: 103.309 | E33: 102.309 | F33: 102.307 | G33: 100.307 | H33: 100.307 | I33: 100.311 | J33: 101.311 | K33: 102.305 | L33: 103.305 | M33: 103.311 | N33: 103.311 | O33: 98.811 | P33: 98.642 | Q33: 98.811 | R33: 99.642 | S33: 101.862 | T33: 103.36 | U33: 103.36 | V33: 103.36 | W33: 103.36 | X33: 101.142 | Y33: 101.142 | Z33: 99.809 | AA33: 100.812 | AB33: 101.832 | AC33: 102.812 | AD33: 105.312 | AE33: 107.312 | AF33: =107.312+6 -> 113.312 | AG33: 130.812 | AH33: =AG33+42 -> 172.812 | AI33: 172.812 | AJ33: 172.812 | AK33: 161.837 | AL33: 157.837 | AM33: 154.837 | AN33: 154.812 | AO33: 156.812 | BZ33: End
B34: LLDPE F19010 Film | C34: 95.556 | D34: 95.556 | E34: 95.315 | F34: 96.564 | G34: 96.564 | H34: 96.564 | I34: 96.557 | J34: 98.557 | K34: 100.559 | L34: 101.559 | M34: 101.557 | N34: 99.557 | O34: 99.557 | P34: 99.557 | Q34: 97.557 | R34: 98.557 | S34: 100.113 | T34: 100.113 | U34: 100.113 | V34: 100.113 | W34: 100.113 | X34: 97.057 | Y34: 97.057 | Z34: 95.557 | AA34: 96.557 | AB34: 98.557 | AC34: 98.557 | AD34: 101.057 | AE34: 103.557 | AF34: =103.557+6 -> 109.557 | AG34: 127.057 | AH34: =AG34+42 -> 169.057 | AI34: 169.057 | AJ34: 169.057 | AK34: 153.084 | AL34: 147.084 | AM34: 140.084 | AN34: 141.084 | AO34: 142.084 | BZ34: End
B35: LDPE FY1005 Film | C35: 122.356 | D35: 117.356 | E35: 117.356 | F35: 114.364 | G35: 111.864 | H35: 111.864 | I35: 111.857 | J35: 113.357 | K35: 115.359 | L35: 117.359 | M35: 119.357 | N35: 119.357 | O35: 119.357 | P35: 119.357 | Q35: 119.357 | R35: 119.357 | S35: 120.913 | T35: 121.911 | U35: 121.911 | V35: 119.911 | W35: 119.911 | X35: 117.857 | Y35: 117.857 | Z35: 115.857 | AA35: 115.857 | AB35: 115.857 | AC35: 116.857 | AD35: 118.857 | AE35: 118.857 | AF35: =118.857+6 -> 124.857 | AG35: 143.857 | AH35: =AG35+42 -> 185.857 | AI35: 185.857 | AJ35: 185.857 | AK35: 178.884 | AL35: 175.884 | AM35: 169.884 | AN35: 170.884 | AO35: 171.884 | BZ35: End
B36: LDPE 7 MFI 1070LA17 | C36: 139.613 | D36: 139.612 | E36: 139.612 | F36: 135.613 | G36: 124.613 | H36: 124.613 | I36: 124.609 | J36: 125.609 | K36: 126.609 | L36: 128.609 | M36: 132.112 | N36: 132.112 | O36: 132.112 | P36: 132.112 | Q36: 130.112 | R36: 130.112 | S36: 130.156 | T36: 130.156 | U36: 130.156 | V36: 128.157 | W36: 128.157 | X36: 126.106 | Y36: 126.112 | Z36: 123.612 | AA36: 123.611 | AB36: 123.611 | AC36: 123.611 | AD36: 125.614 | AE36: 125.614 | AF36: =125.614+7 -> 132.614 | AG36: 153.611 | AH36: =AG36+42 -> 195.611 | AI36: 195.611 | AJ36: 196.929 | AK36: 190.632 | AL36: 184.632 | AM36: 174.632 | AN36: 174.632 | AO36: 174.632 | BZ36: End
B37: PP H350FG | C37: 108.819 | D37: 108.819 | E37: 106.819 | F37: 106.824 | G37: 106.824 | H37: 104.824 | I37: 105.821 | J37: 106.821 | K37: 108.819 | L37: 108.819 | M37: 106.821 | N37: 106.821 | O37: 106.821 | P37: 102.821 | Q37: 102.821 | R37: 104.321 | S37: 105.373 | T37: 103.871 | U37: 103.871 | V37: 101.371 | W37: 97.371 | X37: 95.819 | Y37: 94.819 | Z37: 93.819 | AA37: 95.322 | AB37: 96.322 | AC37: 97.322 | AD37: 100.822 | AE37: 102.822 | AF37: =102.822+6 -> 108.822 | AG37: 125.822 | AH37: =AG37+42 -> 167.822 | AI37: 167.822 | AJ37: 167.822 | AK37: 146.847 | AL37: 141.847 | AM37: 134.947 | AN37: 135.847 | AO37: 136.847 | BZ37: End
B38: LDPE 4 MFI J24FS040 | C38: 122.356 | D38: 112.176 | E38: 112.176 | F38: 112.184 | G38: 112.184 | H38: 112.184 | I38: 112.177 | J38: 113.677 | K38: 115.679 | L38: 117.679 | M38: 119.677 | N38: 119.677 | O38: 119.677 | P38: 119.677 | Q38: 119.677 | R38: 117.677 | S38: 119.213 | T38: 120.231 | U38: 120.231 | V38: 118.231 | W38: 118.231 | X38: 116.177 | Y38: 116.177 | Z38: 114.177 | AA38: 114.177 | AB38: 114.177 | AC38: 115.177 | AD38: 117.117 | AE38: 117.177 | AF38: =117.177+6 -> 123.177 | AG38: 142.177 | AH38: =AG38+42 -> 184.177 | AI38: 184.177 | AJ38: 184.177 | AK38: 173.204 | AL38: 169.204 | AM38: 162.204 | AN38: 162.204 | AO38: 163.204 | BZ38: End
B39: RP | C39: 60 | D39: 60 | E39: 60 | F39: 60 | G39: 60 | H39: 60 | I39: 60 | J39: 60 | K39: 60 | L39: 60 | M39: 60 | N39: 60 | O39: 60 | P39: 60 | Q39: 60 | R39: 60 | S39: 60 | T39: 60 | U39: 60 | V39: 60 | W39: 60 | X39: 60 | Y39: 60 | Z39: 60 | AA39: 60 | AB39: 60 | AC39: 60 | AD39: 60 | AE39: 60 | AF39: 60 | AG39: 60 | AH39: 75 | AI39: 75 | AJ39: 75 | AK39: 75 | AL39: 75 | AM39: 75 | AN39: 75 | AO39: 75 | BZ39: End
B40: Filler | C40: 32 | D40: 32 | E40: 32 | F40: 32 | G40: 32 | H40: 32 | I40: 32 | J40: 32 | K40: 32 | L40: 32 | M40: 32 | N40: 32 | O40: 32 | P40: 32 | Q40: 32 | R40: 32 | S40: 32 | T40: 32 | U40: 32 | V40: 32 | W40: 32 | X40: 32 | Y40: 32 | Z40: 32 | AA40: 32 | AB40: 32 | AC40: 32 | AD40: 32 | AE40: 32 | AF40: 32 | AG40: 32 | AH40: 41 | AI40: 41 | AJ40: 41 | AK40: 41 | AL40: 41 | AM40: 41 | AN40: 41 | AO40: 41 | BZ40: End
B41: TPT | C41: 44 | D41: 44 | E41: 44 | F41: 44 | G41: 44 | H41: 44 | I41: 44 | J41: 44 | K41: 44 | L41: 44 | M41: 44 | N41: 44 | O41: 44 | P41: 44 | Q41: 44 | R41: 44 | S41: 44 | T41: 44 | U41: 44 | V41: 44 | W41: 44 | X41: 44 | Y41: 44 | Z41: 44 | AA41: 44 | AB41: 44 | AC41: 44 | AD41: 44 | AE41: 44 | AF41: 44 | AG41: 44 | AH41: 54 | AI41: 54 | AJ41: 54 | AK41: 54 | AL41: 54 | AM41: 54 | AN41: 54 | AO41: 54 | BZ41: End
B42: UV | C42: 220 | D42: 220 | E42: 220 | F42: 220 | G42: 220 | H42: 220 | I42: 220 | J42: 220 | K42: 220 | L42: 220 | M42: 220 | N42: 220 | O42: 220 | P42: 220 | Q42: 220 | R42: 220 | S42: 220 | T42: 220 | U42: 220 | V42: 220 | W42: 220 | X42: 220 | Y42: 220 | Z42: 220 | AA42: 220 | AB42: 220 | AC42: 220 | AD42: 220 | AE42: 220 | AF42: 220 | AG42: 220 | AH42: 230 | AI42: 230 | AJ42: 230 | AK42: 230 | AL42: 230 | AM42: 230 | AN42: 230 | AO42: 230 | BZ42: End
B43: Col MB | C43: 190 | D43: 190 | E43: 190 | F43: 190 | G43: 190 | H43: 190 | I43: 190 | J43: 190 | K43: 190 | L43: 190 | M43: 190 | N43: 190 | O43: 190 | P43: 190 | Q43: 190 | R43: 190 | S43: 190 | T43: 190 | U43: 190 | V43: 190 | W43: 190 | X43: 190 | Y43: 190 | Z43: 190 | AA43: 190 | AB43: 190 | AC43: 190 | AD43: 190 | AE43: 190 | AF43: 190 | AG43: 190 | AH43: 220 | AI43: 220 | AJ43: 220 | AK43: 220 | AL43: 220 | AM43: 220 | AN43: 220 | AO43: 220 | BZ43: End
B44: Black MB | C44: 140 | D44: 140 | E44: 140 | F44: 140 | G44: 140 | H44: 140 | I44: 140 | J44: 140 | K44: 140 | L44: 140 | M44: 140 | N44: 140 | O44: 140 | P44: 140 | Q44: 140 | R44: 140 | S44: 140 | T44: 140 | U44: 140 | V44: 140 | W44: 140 | X44: 140 | Y44: 140 | Z44: 140 | AA44: 140 | AB44: 140 | AC44: 140 | AD44: 140 | AE44: 140 | AF44: 140 | AG44: 140 | AH44: 155 | AI44: 155 | AJ44: 155 | AK44: 155 | AL44: 155 | AM44: 155 | AN44: 155 | AO44: 155 | BZ44: End
B45: Conductive Yarn | C45: 500 | D45: 500 | E45: 500 | F45: 500 | G45: 500 | H45: 500 | I45: 500 | J45: 500 | K45: 500 | L45: 500 | M45: 500 | N45: 500 | O45: 500 | P45: 500 | Q45: 500 | R45: 500 | S45: 500 | T45: 500 | U45: 500 | V45: 500 | W45: 500 | X45: 500 | Y45: 500 | Z45: 500 | AA45: 500 | AB45: 500 | AC45: 500 | AD45: 500 | AE45: 500 | AF45: 500 | AG45: 500 | AH45: 500 | AI45: 500 | AJ45: 500 | AK45: 500 | AL45: 500 | AM45: 500 | AN45: 500 | AO45: 500 | BZ45: End
B46: Back Seam Coating RM | C46: =(68*C37+30*C36+2*220)/100 -> 120.28082 | D46: =(68*D37+30*D36+2*220)/100 -> 120.28052 | E46: =(68*E37+30*E36+2*220)/100 -> 118.92052 | F46: =(68*F37+30*F36+2*220)/100 -> 117.72422 | G46: =(68*G37+30*G36+2*220)/100 -> 114.42422 | H46: =(68*H37+30*H36+2*220)/100 -> 113.06422 | I46: =(68*I37+30*I36+2*220)/100 -> 113.74098 | J46: =(68*J37+30*J36+2*220)/100 -> 114.72098 | ... AH46: =(68*AH37+30*AH36+2*220)/100 -> 177.20226 | AI46: 177.20226 | AJ46: 177.20226 | AK46: 177.20226 | AL46: 177.20226 | AM46: 177.20226 | AN46: 177.20226 | AO46: 177.20226 | BZ46: End
B47: White Paper | C47: 84 | D47: 84 | E47: 84 | F47: 84 | G47: 84 | H47: 84 | I47: 84 | J47: 84 | K47: 84 | L47: 84 | M47: 84 | N47: 84 | O47: 84 | P47: 84 | Q47: 84 | R47: 84 | S47: 84 | T47: 84 | U47: 84 | V47: 84 | W47: 84 | X47: 84 | Y47: 84 | Z47: 84 | AA47: 84 | AB47: 84 | AC47: 84 | AD47: 84 | AE47: 84 | AF47: 84 | AG47: 84 | AH47: 84 | AI47: 84 | AJ47: 84 | AK47: 84 | AL47: 84 | AM47: 84 | AN47: 84 | AO47: 84 | BZ47: End
B48: Brown Paper | C48: 76 | D48: 76 | E48: 76 | F48: 76 | G48: 76 | H48: 76 | I48: 76 | J48: 76 | K48: 76 | L48: 76 | M48: 76 | N48: 76 | O48: 76 | P48: 76 | Q48: 76 | R48: 76 | S48: 76 | T48: 76 | U48: 76 | V48: 76 | W48: 76 | X48: 76 | Y48: 76 | Z48: 76 | AA48: 76 | AB48: 76 | AC48: 76 | AD48: 76 | AE48: 76 | AF48: 76 | AG48: 76 | AH48: 76 | AI48: 76 | AJ48: 76 | AK48: 76 | AL48: 76 | AM48: 76 | AN48: 76 | AO48: 76
B49: Plain BOPP | C49: 160 | D49: 160 | E49: 160 | F49: 160 | G49: 160 | H49: 160 | I49: 160 | J49: 160 | K49: 160 | L49: 160 | M49: 160 | N49: 160 | O49: 160 | P49: 160 | Q49: 160 | R49: 160 | S49: 160 | T49: 160 | U49: 160 | V49: 160 | W49: 160 | X49: 160 | Y49: 160 | Z49: 150 | AA49: 150 | AB49: 150 | AC49: 150 | AD49: 150 | AE49: 150 | AF49: 150 | AG49: 150 | AH49: 150 | AI49: 150 | AJ49: 150 | AK49: 150 | AL49: 150 | AM49: 150 | AN49: 150 | AO49: 150 | BZ49: End
B50: Matt BOPP | C50: 180 | D50: 180 | E50: 180 | F50: 180 | G50: 180 | H50: 180 | I50: 180 | J50: 180 | K50: 180 | L50: 180 | M50: 180 | N50: 180 | O50: 180 | P50: 180 | Q50: 180 | R50: 180 | S50: 180 | T50: 180 | U50: 180 | V50: 180 | W50: 180 | X50: 180 | Y50: 180 | Z50: 170 | AA50: 170 | AB50: 170 | AC50: 170 | AD50: 170 | AE50: 170 | AF50: 170 | AG50: 170 | AH50: 170 | AI50: 170 | AJ50: 170 | AK50: 170 | AL50: 170 | AM50: 170 | AN50: 170 | AO50: 170 | BZ50: End
B51: Metalised BOPP | C51: 180 | D51: 180 | E51: 180 | F51: 180 | G51: 180 | H51: 180 | I51: 180 | J51: 180 | K51: 180 | L51: 180 | M51: 180 | N51: 180 | O51: 180 | P51: 180 | Q51: 180 | R51: 180 | S51: 180 | T51: 180 | U51: 180 | V51: 180 | W51: 180 | X51: 180 | Y51: 180 | Z51: 180 | AA51: 180 | AB51: 180 | AC51: 180 | AD51: 180 | AE51: 180 | AF51: 180 | AG51: 180 | AH51: 180 | AI51: 180 | AJ51: 180 | AK51: 180 | AL51: 180 | AM51: 180 | AN51: 180 | AO51: 180 | BZ51: End
B52: Adhesive | C52: 230 | D52: 230 | E52: 230 | F52: 230 | G52: 230 | H52: 230 | I52: 230 | J52: 230 | K52: 230 | L52: 230 | M52: 230 | N52: 230 | O52: 230 | P52: 230 | Q52: 230 | R52: 230 | S52: 230 | T52: 230 | U52: 230 | V52: 230 | W52: 230 | X52: 230 | Y52: 230 | Z52: 230 | AA52: 230 | AB52: 230 | AC52: 230 | AD52: 230 | AE52: 230 | AF52: 230 | AG52: 230 | AH52: 230 | AI52: 230 | AJ52: 230 | AK52: 230 | AL52: 230 | AM52: 230 | AN52: 230 | AO52: 230 | BZ52: End
B53: Ink BOPP | C53: 1400 | D53: 1400 | E53: 1400 | F53: 1400 | G53: 1400 | H53: 1400 | I53: 1400 | J53: 1400 | K53: 1400 | L53: 1400 | M53: 1400 | N53: 1400 | O53: 1400 | P53: 1400 | Q53: 1400 | R53: 1400 | S53: 1400 | T53: 1400 | U53: 1400 | V53: 1400 | W53: 1400 | X53: 1400 | Y53: 1400 | Z53: 1400 | AA53: 1400 | AB53: 1400 | AC53: 1400 | AD53: 1400 | AE53: 1400 | AF53: 1400 | AG53: 1400 | AH53: 1400 | AI53: 1400 | AJ53: 1400 | AK53: 1400 | AL53: 1400 | AM53: 1400 | AN53: 1400 | AO53: 1400 | BZ53: End
B54: Solvant BOPP | C54: 140 | D54: 140 | E54: 140 | F54: 140 | G54: 140 | H54: 140 | I54: 140 | J54: 140 | K54: 140 | L54: 140 | M54: 140 | N54: 140 | O54: 140 | P54: 140 | Q54: 140 | R54: 140 | S54: 140 | T54: 140 | U54: 140 | V54: 140 | W54: 140 | X54: 140 | Y54: 140 | Z54: 140 | AA54: 140 | AB54: 140 | AC54: 140 | AD54: 140 | AE54: 140 | AF54: 140 | AG54: 140 | AH54: 140 | AI54: 140 | AJ54: 140 | AK54: 140 | AL54: 140 | AM54: 140 | AN54: 140 | AO54: 140 | BZ54: End

Sheet Cust Master
B1: Customer Master
B2: S No | C2: Export Customers | D2: Export
B3: =ROW(B3)-2 -> 1 | C3: Access Freight Africa (Pty) Ltd | D3: Access Freight
B4: =ROW(B4)-2 -> 2 | C4: ADM Philipines | D4: ADM Philipines
B5: =ROW(B5)-2 -> 3 | C5: ADM Vietnam | D5: ADM Vietnam
B6: =ROW(B6)-2 -> 4 | C6: ADM China | D6: ADM China
B7: =ROW(B7)-2 -> 5 | C7: Aduantec | D7: Aduantec
B8: =ROW(B8)-2 -> 6 | C8: Advanced Flexible Containers, Inc. | D8: Adv Flexible
B9: =ROW(B9)-2 -> 7 | C9: Afri Global Trading | D9: AGT
B10: =ROW(B10)-2 -> 8 | C10: Adler Grosshandel | D10: Adler
B11: =ROW(B11)-2 -> 9 | C11: Agnes International USA | D11: Agnes Nick
B12: =ROW(B12)-2 -> 10 | C12: Agon A/s | D12: Agon
B13: =ROW(B13)-2 -> 11 | C13: Agro Life SA. | D13: Agro Life
B14: =ROW(B14)-2 -> 12 | C14: Agro Perlite SA | D14: Agro Perlite
... B336: =ROW(B336)-2 -> 334 | C336: Polymero, Bulgaria | D336: Polymero
B337: =ROW(B337)-2 -> 335
B338: =ROW(B338)-2 -> 336
B339: =ROW(B339)-2 -> 337
B340: =ROW(B340)-2 -> 338
B346: S No | C346: Domectic Customers | D346: Domestic
B347: =ROW(B347)-330 -> 17 | C347: 20 MICRONS LIMITED | D347: 20 Microns
B348: =ROW(B348)-330 -> 18 | C348: Aman | D348: Aman
B349: =ROW(B349)-330 -> 19 | C349: Anay Global Service | D349: Anay
B350: =ROW(B350)-330 -> 20 | C350: Ashapura Minechem | D350: Ashapura
B351: =ROW(B351)-330 -> 21 | C351: Ankur | D351: Ankur
B352: =ROW(B352)-330 -> 22 | C352: ADM India | D352: ADM India
B353: =ROW(B353)-330 -> 23 | C353: Bomgim Courier | D353: Bomgim
B354: =ROW(B354)-330 -> 24 | C354: Belgaum Sugars Pvt Ltd | D354: BSPL
C355: Camex | D355: Camex
B356: =ROW(B356)-330 -> 26 | C356: Chirag bhai | D356: Chirag bhai
B357: =ROW(B357)-330 -> 27 | C357: Fuji Technical Services Pvt. Ltd | D357: Fuji
B358: =ROW(B358)-330 -> 28 | C358: Hindustan Gunny Bags | D358: Bafnaji
B359: =ROW(B359)-330 -> 29 | C359: Bhavik Industries | D359: Barkat
B360: =ROW(B360)-330 -> 30 | C360: Gaj Kesari | D360: Anup Bora
B361: =ROW(B361)-330 -> 31 | C361: Natural Sugar & Allied | D361: Binodji
B362: =ROW(B362)-330 -> 32 | C362: Osia | D362: Osia
B363: =ROW(B363)-330 -> 33 | C363: Paramount Rice Mills | D363: Maheshji
B364: =ROW(B364)-330 -> 34 | C364: Pavitra Jain | D364: Pavitra
B365: =ROW(B365)-330 -> 35 | C365: Ramesh Solanki | D365: Ramesh
B366: =ROW(B366)-330 -> 36 | C366: Relalia Agrovat | D366: Regalia
B367: =ROW(B367)-330 -> 37 | C367: Shree Renuka Sugars | D367: Renuka
... B371: =ROW(B371)-330 -> 41 | C371: Swayam Poly | D371: SPPL
C372: Transfurt Kandla | D372: Transfurt
B373: =ROW(B373)-330 -> 43 | C373: VuraBao Chemical | D373: VuraBao
B374: =ROW(B374)-330 -> 44 | C374: Gokul overseas - SEZ | D374: Gokul
C375: Nuvoco Vista | D375: Nuvoco
B376: =ROW(B376)-330 -> 46 | C376: Value Ingredient | D376: Value Ingredient
B377: =ROW(B377)-330 -> 47 | C377: Moglix India Pvt Ltd | D377: Moglix
B378: =ROW(B378)-330 -> 48 | C378: Kutch Bentonite | D378: Kutch Bento
B379: =ROW(B379)-330 -> 49 | C379: Satyen Chattarji | D379: Satyen Chattarji
B380: =ROW(B380)-330 -> 50 | C380: Shyamvandan | D380: Shyamvandan
B381: =ROW(B381)-330 -> 51 | C381: Awffan/Fulmix | D381: Awffan/Fulmix
B382: =ROW(B382)-330 -> 52 | C382: Livegreen Clean Tech Pvt Ltd | D382: Livegreen
B383: =ROW(B383)-330 -> 53 | C383: Ones Ltd | D383: Ones Minal

Sheet Master1
B2: Quotations Made for Below Customers
B3: {=_xlfn.UNIQUE(_xlfn._xlws.SORT((TRANSPOSE('Quote Exports'!E7:AW7))))} -> ATEA Turkey
B4: Condepols
B5: Desabag
B6: ISP Korea
B7: Procon
B8: Safesack Scand
B9: 0
