Workbook

Sheet Master
A2: SubGroupName | B2: Item Name | C2: GroupName | D2: MainGroupName | E2: SubGroupName | F2: Opening | G2: Closing
A3: Beam Stock | B3: PP Tape on Beams | C3: Tape Stock | D3: SF | E3: Beam Stock | F3: 0 | G3: 0
A4: BOPP Film | B4: BOPP Film | C4: Films All | D4: RM | E4: BOPP Film | F4: 0 | G4: 0
A5: BOPP Film | B5: BOPP Film Printed | C5: Films All | D5: RM | E5: BOPP Film | F5: 0 | G5: 0
A6: Enable Granuals | B6: Enable Exxon 2005MC | C6: Granuals | D6: RM | E6: Enable Granuals | F6: 0 | G6: 0
A7: Enable Granuals | B7: Enable Exxon 2005ME | C7: Granuals | D7: RM | E7: Enable Granuals | F7: 0 | G7: 0
A8: EVA Granuals | B8: EVA Granuals | C8: Granuals | D8: RM | E8: EVA Granuals | F8: 0 | G8: 0
A9: FIBC Accessories | B9: Non Woven Fabric (Felt) 170Gsm.Pati Cut Length- 2" ( 5 Cm ) | C9: FIBC Accessories | D9: RM | E9: FIBC Accessories | F9: 0 | G9: 0
A10: FIBC Accessories | B10: Spun Bound Non Woven Fabric 118 Cm 90 Gsm Uncoated | C10: FIBC Accessories | D10: RM | E10: FIBC Accessories | F10: 0 | G10: 0
A11: FIBC Accessories | B11: Non Woven Fabric (Felt) 170Gsm.Pati Cut Length- 2" ( 5 Cm ) (Food Grade Quality) | C11: FIBC Accessories | D11: RM | E11: FIBC Accessories | F11: 0 | G11: 0
A12: FIBC Accessories | B12: Non Woven Fabric (Felt) 200 Gsm.Pati Cut Length- 4" (10 Cm) | C12: FIBC Accessories | D12: RM | E12: FIBC Accessories | F12: 0 | G12: 0
A13: FIBC Accessories | B13: Non Woven Fabric (Felt) | C13: FIBC Accessories | D13: RM | E13: FIBC Accessories | F13: 0 | G13: 0
A14: FIBC Accessories | B14: Non Woven Fabric (Felt) 170Gsm.Pati Cut Length- 4" ( 10 Cm ) | C14: FIBC Accessories | D14: RM | E14: FIBC Accessories | F14: 0 | G14: 0
... A928: Wastage/Scrap | B928: PP/HD Wastage/Scrap | C928: Wastage/Scrap | D928: SF | E928: Wastage/Scrap | F928: 0 | G928: 0

Sheet Summary
D2: Opening Stock | G2: Inventory movement fo the month of APRIL 2026 | W2: Closing Stock -As per Movement Sheet | Z2: Closing Stock - As per Actual (Physical) | AC2: Difference
A3: Group | B3: Sub group | C3: Details of Items / Products | D3: Factory Owned | E3: Factory JW (Others) | F3: At JW (Own) | G3: Branch Tfr Recd | H3: Purchase | I3: Recd from JW (Own) | J3: Recd For JW (Others) | K3: Sales | L3: Br Transfer Sent | M3: Sent for JW (Own) | N3: Return JW(Others) | O3: Total Production Own+JW | P3: Total Consumption Own+JW | Q3: Production at JW | R3: Consumption At JW | S3: Pord of JW | T3: Consumption of JW | U3: Net Production Own | V3: Net Consumption Own | W3: Factory Owned | X3: Factory JW (Others) | Y3: At JW (Own) | Z3: Factory Owned | AA3: Factory JW (Others) | AB3: At JW (Own) | AC3: Factory Owned | AD3: Factory JW (Others) | AE3: At JW (Own) | AF3: Remark for Difference, If any | AG3: Rate | AH3: Value Factory Own
A4: =VLOOKUP(C4,Master!A:D,4,0) -> RM | B4: =VLOOKUP(C4,Master!A:C,3,0) -> Granuals | C4: Masterbatch | D4: 1834.7 | E4: 350 | F4: 0 | J4: 700 | P4: 287.9 | T4: 50 | U4: =O4-S4 -> 0 | V4: =P4-T4 -> 237.9 | W4: =D4+G4+H4+I4-K4-L4-M4-V4+U4 -> 1596.8 | X4: =E4+J4-N4-T4+S4 -> 1000 | Y4: =F4-I4+M4-R4+Q4 -> 0 | Z4: 1596.8 | AA4: 1000 | AB4: 0 | AC4: =W4-Z4 -> 0 | AD4: =X4-AA4 -> 0 | AE4: =Y4-AB4 -> 0 | AG4: 201 | AH4: =+W4*AG4 -> 320956.8
A5: =VLOOKUP(C5,Master!A:D,4,0) -> RM | B5: =VLOOKUP(C5,Master!A:C,3,0) -> Granuals | C5: PP Granuals | D5: 23534.349 | E5: 579675.5 | F5: 0 | H5: 112000 | J5: 196000 | P5: 299193.15 | T5: 238057.96 | U5: =O5-S5 -> 0 | V5: =P5-T5 -> 61135.189 | W5: =D5+G5+H5+I5-K5-L5-M5-V5+U5 -> 74399.16 | X5: =E5+J5-N5-T5+S5 -> 537617.54 | Y5: =F5-I5+M5-R5+Q5 -> 0 | Z5: 74399.16 | AA5: 537617.54 | AB5: 0 | AC5: =W5-Z5 -> 0 | AD5: =X5-AA5 -> 0 | AE5: =Y5-AB5 -> 0 | AG5: 108 | AH5: =+W5*AG5 -> 8035109.3
A6: =VLOOKUP(C6,Master!A:D,4,0) -> RM | B6: =VLOOKUP(C6,Master!A:C,3,0) -> Granuals | C6: HDPE Granuals | D6: 0 | E6: 0 | F6: 0 | T6: 0 | U6: =O6-S6 -> 0 | V6: =P6-T6 -> 0 | W6: =D6+G6+H6+I6-K6-L6-M6-V6+U6 -> 0 | X6: =E6+J6-N6-T6+S6 -> 0 | Y6: =F6-I6+M6-R6+Q6 -> 0 | Z6: 0 | AA6: 0 | AB6: 0 | AC6: =W6-Z6 -> 0 | AD6: =X6-AA6 -> 0 | AE6: =Y6-AB6 -> 0 | AH6: =+W6*AG6 -> 0
A7: =VLOOKUP(C7,Master!A:D,4,0) -> RM | B7: =VLOOKUP(C7,Master!A:C,3,0) -> Granuals | C7: LDPE Granuals | D7: 0 | E7: 13000 | F7: 0 | T7: 0 | U7: =O7-S7 -> 0 | V7: =P7-T7 -> 0 | W7: =D7+G7+H7+I7-K7-L7-M7-V7+U7 -> 0 | X7: =E7+J7-N7-T7+S7 -> 13000 | Y7: =F7-I7+M7-R7+Q7 -> 0 | Z7: 0 | AA7: 13000 | AB7: 0 | AC7: =W7-Z7 -> 0 | AD7: =X7-AA7 -> 0 | AE7: =Y7-AB7 -> 0 | AH7: =+W7*AG7 -> 0
A8: =VLOOKUP(C8,Master!A:D,4,0) -> RM | B8: =VLOOKUP(C8,Master!A:C,3,0) -> Granuals | C8: LLDPE Granuals | D8: 0 | E8: 0 | F8: 0 | T8: 0 | U8: =O8-S8 -> 0 | V8: =P8-T8 -> 0 | W8: =D8+G8+H8+I8-K8-L8-M8-V8+U8 -> 0 | X8: =E8+J8-N8-T8+S8 -> 0 | Y8: =F8-I8+M8-R8+Q8 -> 0 | Z8: 0 | AA8: 0 | AB8: 0 | AC8: =W8-Z8 -> 0 | AD8: =X8-AA8 -> 0 | AE8: =Y8-AB8 -> 0 | AH8: =+W8*AG8 -> 0
A9: =VLOOKUP(C9,Master!A:D,4,0) -> RM | B9: =VLOOKUP(C9,Master!A:C,3,0) -> Granuals | C9: UV MB | D9: 0 | E9: 15000 | F9: 0 | J9: 6575 | T9: 0 | U9: =O9-S9 -> 0 | V9: =P9-T9 -> 0 | W9: =D9+G9+H9+I9-K9-L9-M9-V9+U9 -> 0 | X9: =E9+J9-N9-T9+S9 -> 21575 | Y9: =F9-I9+M9-R9+Q9 -> 0 | Z9: 0 | AA9: 21575 | AB9: 0 | AC9: =W9-Z9 -> 0 | AD9: =X9-AA9 -> 0 | AE9: =Y9-AB9 -> 0 | AH9: =+W9*AG9 -> 0
A10: =VLOOKUP(C10,Master!A:D,4,0) -> RM | B10: =VLOOKUP(C10,Master!A:C,3,0) -> FIBC Accessories | C10: FIBC Accessories | D10: 0 | E10: 0 | F10: 0 | T10: 0 | U10: =O10-S10 -> 0 | V10: =P10-T10 -> 0 | W10: =D10+G10+H10+I10-K10-L10-M10-V10+U10 -> 0 | X10: =E10+J10-N10-T10+S10 -> 0 | Y10: =F10-I10+M10-R10+Q10 -> 0 | Z10: 0 | AA10: 0 | AB10: 0 | AC10: =W10-Z10 -> 0 | AD10: =X10-AA10 -> 0 | AE10: =Y10-AB10 -> 0 | AH10: =+W10*AG10 -> 0
A11: =VLOOKUP(C11,Master!A:D,4,0) -> RM | B11: =VLOOKUP(C11,Master!A:C,3,0) -> Films All | C11: Polyester Film | D11: 0 | E11: 0 | F11: 0 | T11: 0 | U11: =O11-S11 -> 0 | V11: =P11-T11 -> 0 | W11: =D11+G11+H11+I11-K11-L11-M11-V11+U11 -> 0 | X11: =E11+J11-N11-T11+S11 -> 0 | Y11: =F11-I11+M11-R11+Q11 -> 0 | Z11: 0 | AA11: 0 | AB11: 0 | AC11: =W11-Z11 -> 0 | AD11: =X11-AA11 -> 0 | AE11: =Y11-AB11 -> 0 | AH11: =+W11*AG11 -> 0
A12: =VLOOKUP(C12,Master!A:D,4,0) -> RM | B12: =VLOOKUP(C12,Master!A:C,3,0) -> Granuals | C12: Filler | D12: 0 | E12: 0 | F12: 0 | J12: 6000 | T12: 0 | U12: =O12-S12 -> 0 | V12: =P12-T12 -> 0 | W12: =D12+G12+H12+I12-K12-L12-M12-V12+U12 -> 0 | X12: =E12+J12-N12-T12+S12 -> 6000 | Y12: =F12-I12+M12-R12+Q12 -> 0 | Z12: 0 | AA12: 6000 | AB12: 0 | AC12: =W12-Z12 -> 0 | AD12: =X12-AA12 -> 0 | AE12: =Y12-AB12 -> 0 | AH12: =+W12*AG12 -> 0
A13: =VLOOKUP(C13,Master!A:D,4,0) -> RM | B13: =VLOOKUP(C13,Master!A:C,3,0) -> Films All | C13: PE Film | D13: 0 | E13: 0 | F13: 0 | T13: 0 | U13: =O13-S13 -> 0 | V13: =P13-T13 -> 0 | W13: =D13+G13+H13+I13-K13-L13-M13-V13+U13 -> 0 | X13: =E13+J13-N13-T13+S13 -> 0 | Y13: =F13-I13+M13-R13+Q13 -> 0 | Z13: 0 | AA13: 0 | AB13: 0 | AC13: =W13-Z13 -> 0 | AD13: =X13-AA13 -> 0 | AE13: =Y13-AB13 -> 0 | AH13: =+W13*AG13 -> 0
A14: =VLOOKUP(C14,Master!A:D,4,0) -> RM | B14: =VLOOKUP(C14,Master!A:C,3,0) -> Granuals | C14: EVA Granuals | D14: 0 | E14: 0 | F14: 0 | T14: 0 | U14: =O14-S14 -> 0 | V14: =P14-T14 -> 0 | W14: =D14+G14+H14+I14-K14-L14-M14-V14+U14 -> 0 | X14: =E14+J14-N14-T14+S14 -> 0 | Y14: =F14-I14+M14-R14+Q14 -> 0 | Z14: 0 | AA14: 0 | AB14: 0 | AC14: =W14-Z14 -> 0 | AD14: =X14-AA14 -> 0 | AE14: =Y14-AB14 -> 0 | AH14: =+W14*AG14 -> 0
A15: =VLOOKUP(C15,Master!A:D,4,0) -> RM | B15: =VLOOKUP(C15,Master!A:C,3,0) -> Granuals | C15: mLLDPE Granuals | D15: 0 | E15: 0 | F15: 0 | T15: 0 | U15: =O15-S15 -> 0 | V15: =P15-T15 -> 0 | W15: =D15+G15+H15+I15-K15-L15-M15-V15+U15 -> 0 | X15: =E15+J15-N15-T15+S15 -> 0 | Y15: =F15-I15+M15-R15+Q15 -> 0 | Z15: 0 | AA15: 0 | AB15: 0 | AC15: =W15-Z15 -> 0 | AD15: =X15-AA15 -> 0 | AE15: =Y15-AB15 -> 0 | AH15: =+W15*AG15 -> 0
A16: =VLOOKUP(C16,Master!A:D,4,0) -> RM | B16: =VLOOKUP(C16,Master!A:C,3,0) -> Films All | C16: BOPP Film | D16: 0 | E16: 0 | F16: 0 | T16: 0 | U16: =O16-S16 -> 0 | V16: =P16-T16 -> 0 | W16: =D16+G16+H16+I16-K16-L16-M16-V16+U16 -> 0 | X16: =E16+J16-N16-T16+S16 -> 0 | Y16: =F16-I16+M16-R16+Q16 -> 0 | Z16: 0 | AA16: 0 | AB16: 0 | AC16: =W16-Z16 -> 0 | AD16: =X16-AA16 -> 0 | AE16: =Y16-AB16 -> 0 | AH16: =+W16*AG16 -> 0
A17: =VLOOKUP(C17,Master!A:D,4,0) -> RM | B17: =VLOOKUP(C17,Master!A:C,3,0) -> Granuals | C17: Enable Granuals | D17: 0 | E17: 0 | F17: 0 | T17: 0 | U17: =O17-S17 -> 0 | V17: =P17-T17 -> 0 | W17: =D17+G17+H17+I17-K17-L17-M17-V17+U17 -> 0 | X17: =E17+J17-N17-T17+S17 -> 0 | Y17: =F17-I17+M17-R17+Q17 -> 0 | Z17: 0 | AA17: 0 | AB17: 0 | AC17: =W17-Z17 -> 0 | AD17: =X17-AA17 -> 0 | AE17: =Y17-AB17 -> 0 | AH17: =+W17*AG17 -> 0
A18: =VLOOKUP(C18,Master!A:D,4,0) -> SF | B18: =VLOOKUP(C18,Master!A:C,3,0) -> Yarn All | C18: PP Yarn | D18: 0 | E18: 15276.14 | F18: 0 | H18: 3286.76 | J18: 13674.7 | O18: 1796.3 | P18: 16825.6 | T18: 11742.54 | U18: =O18-S18 -> 1796.3 | V18: =P18-T18 -> 5083.06 | W18: =D18+G18+H18+I18-K18-L18-M18-V18+U18 -> 0 | X18: =E18+J18-N18-T18+S18 -> 17208.3 | Z18: 0 | AA18: 17208.3 | AB18: 0 | AC18: =W18-Z18 -> 0 | AD18: =X18-AA18 -> 0 | AE18: =Y18-AB18 -> 0 | AH18: =+W18*AG18 -> 0
A19: =VLOOKUP(C19,Master!A:D,4,0) -> SF | B19: =VLOOKUP(C19,Master!A:C,3,0) -> PP/PE Fabric | C19: PP UL Fabric | D19: 0 | E19: 11815 | F19: 0 | H19: 767.8 | J19: 47218.9 | K19: 27139.1 | O19: 156688 | P19: 142132 | T19: 11815.3 | U19: =O19-S19 -> 156688 | V19: =P19-T19 -> 130316.7 | W19: =D19+G19+H19+I19-K19-L19-M19-V19+U19 -> 0 | X19: =E19+J19-N19-T19+S19 -> 47218.6 | Y19: =F19-I19+M19-R19+Q19 -> 0 | Z19: 0 | AA19: 47218.6 | AB19: 0 | AC19: =W19-Z19 -> 0 | AD19: =X19-AA19 -> 0 | AE19: =Y19-AB19 -> 0 | AH19: =+W19*AG19 -> 0
A20: =VLOOKUP(C20,Master!A:D,4,0) -> SF | B20: =VLOOKUP(C20,Master!A:C,3,0) -> Flexitank Accessories | C20: Flexitank Accessories | D20: 0 | E20: 0 | F20: 0 | T20: 0 | U20: =O20-S20 -> 0 | V20: =P20-T20 -> 0 | W20: =D20+G20+H20+I20-K20-L20-M20-V20+U20 -> 0 | X20: =E20+J20-N20-T20+S20 -> 0 | Y20: =F20-I20+M20-R20+Q20 -> 0 | Z20: 0 | AA20: 0 | AB20: 0 | AC20: =W20-Z20 -> 0 | AD20: =X20-AA20 -> 0 | AE20: =Y20-AB20 -> 0 | AH20: =+W20*AG20 -> 0
A21: =VLOOKUP(C21,Master!A:D,4,0) -> SF | B21: =VLOOKUP(C21,Master!A:C,3,0) -> PP/PE Fabric | C21: PP Lam Fabric | D21: 0 | E21: 9587 | F21: 0 | J21: 18916 | O21: 106320 | P21: 115906.7 | T21: 9586.7 | U21: =O21-S21 -> 106320 | V21: =P21-T21 -> 106320 | W21: =D21+G21+H21+I21-K21-L21-M21-V21+U21 -> 0 | X21: =E21+J21-N21-T21+S21 -> 18916.3 | Y21: =F21-I21+M21-R21+Q21 -> 0 | Z21: 0 | AA21: 18916.3 | AB21: 0 | AC21: =W21-Z21 -> 0 | AD21: =X21-AA21 -> 0 | AE21: =Y21-AB21 -> 0 | AH21: =+W21*AG21 -> 0
A22: =VLOOKUP(C22,Master!A:D,4,0) -> SF | B22: =VLOOKUP(C22,Master!A:C,3,0) -> PP/PE Fabric | C22: HD UL Fabric | D22: 0 | E22: 0 | F22: 0 | T22: 0 | U22: =O22-S22 -> 0 | V22: =P22-T22 -> 0 | W22: =D22+G22+H22+I22-K22-L22-M22-V22+U22 -> 0 | X22: =E22+J22-N22-T22+S22 -> 0 | Y22: =F22-I22+M22-R22+Q22 -> 0 | Z22: 0 | AA22: 0 | AB22: 0 | AC22: =W22-Z22 -> 0 | AD22: =X22-AA22 -> 0 | AE22: =Y22-AB22 -> 0 | AH22: =+W22*AG22 -> 0
A23: =VLOOKUP(C23,Master!A:D,4,0) -> SF | B23: =VLOOKUP(C23,Master!A:C,3,0) -> PP/PE Fabric | C23: HD Lam Fabric | D23: 0 | E23: 0 | F23: 0 | T23: 0 | U23: =O23-S23 -> 0 | V23: =P23-T23 -> 0 | W23: =D23+G23+H23+I23-K23-L23-M23-V23+U23 -> 0 | X23: =E23+J23-N23-T23+S23 -> 0 | Y23: =F23-I23+M23-R23+Q23 -> 0 | Z23: 0 | AA23: 0 | AB23: 0 | AC23: =W23-Z23 -> 0 | AD23: =X23-AA23 -> 0 | AE23: =Y23-AB23 -> 0 | AH23: =+W23*AG23 -> 0
A24: =VLOOKUP(C24,Master!A:D,4,0) -> SF | B24: =VLOOKUP(C24,Master!A:C,3,0) -> Granuals | C24: RP Granuals | D24: 46952.75 | E24: 0 | F24: 0 | J24: 3000 | K24: 76000 | O24: 64525 | P24: 35477.75 | T24: 0 | U24: =O24-S24 -> 64525 | V24: =P24-T24 -> 35477.75 | W24: =D24+G24+H24+I24-K24-L24-M24-V24+U24 -> 0 | X24: =E24+J24-N24-T24+S24 -> 3000 | Y24: =F24-I24+M24-R24+Q24 -> 0 | Z24: 0 | AA24: 3000 | AB24: 0 | AC24: =W24-Z24 -> 0 | AD24: =X24-AA24 -> 0 | AE24: =Y24-AB24 -> 0 | AH24: =+W24*AG24 -> 0
A25: =VLOOKUP(C25,Master!A:D,4,0) -> SF | B25: =VLOOKUP(C25,Master!A:C,3,0) -> Liners | C25: Liner for Flexitank | D25: 0 | E25: 0 | F25: 0 | T25: 0 | U25: =O25-S25 -> 0 | V25: =P25-T25 -> 0 | W25: =D25+G25+H25+I25-K25-L25-M25-V25+U25 -> 0 | X25: =E25+J25-N25-T25+S25 -> 0 | Y25: =F25-I25+M25-R25+Q25 -> 0 | Z25: 0 | AA25: 0 | AB25: 0 | AC25: =W25-Z25 -> 0 | AD25: =X25-AA25 -> 0 | AE25: =Y25-AB25 -> 0 | AH25: =+W25*AG25 -> 0
A26: =VLOOKUP(C26,Master!A:D,4,0) -> SF | B26: =VLOOKUP(C26,Master!A:C,3,0) -> Webbing | C26: PP Webbing | D26: 0 | E26: 1656.1 | F26: 0 | J26: 81 | K26: 5343.8 | O26: 57195.2 | P26: 51851.4 | T26: 0 | U26: =O26-S26 -> 57195.2 | V26: =P26-T26 -> 51851.4 | W26: =D26+G26+H26+I26-K26-L26-M26-V26+U26 -> 0 | X26: =E26+J26-N26-T26+S26 -> 1737.1 | Y26: =F26-I26+M26-R26+Q26 -> 0 | Z26: 0 | AA26: 1737.1 | AB26: 0 | AC26: =W26-Z26 -> 0 | AD26: =X26-AA26 -> 0 | AE26: =Y26-AB26 -> 0 | AH26: =+W26*AG26 -> 0
A27: =VLOOKUP(C27,Master!A:D,4,0) -> SF | B27: =VLOOKUP(C27,Master!A:C,3,0) -> Liners | C27: LDPE/LLDPE Bags | D27: 0 | E27: 8281.3 | F27: 0 | J27: 39624.8 | P27: 8281.3 | T27: 8281.3 | U27: =O27-S27 -> 0 | V27: =P27-T27 -> 0 | W27: =D27+G27+H27+I27-K27-L27-M27-V27+U27 -> 0 | X27: =E27+J27-N27-T27+S27 -> 39624.8 | Y27: =F27-I27+M27-R27+Q27 -> 0 | Z27: 0 | AA27: 39624.8 | AB27: 0 | AC27: =W27-Z27 -> 0 | AD27: =X27-AA27 -> 0 | AE27: =Y27-AB27 -> 0 | AH27: =+W27*AG27 -> 0
A28: =VLOOKUP(C28,Master!A:D,4,0) -> SF | B28: =VLOOKUP(C28,Master!A:C,3,0) -> Tape Stock | C28: Beam Stock | D28: 0 | E28: 0 | F28: 0 | T28: 0 | U28: =O28-S28 -> 0 | V28: =P28-T28 -> 0 | W28: =D28+G28+H28+I28-K28-L28-M28-V28+U28 -> 0 | X28: =E28+J28-N28-T28+S28 -> 0 | Y28: =F28-I28+M28-R28+Q28 -> 0 | Z28: 0 | AA28: 0 | AB28: 0 | AC28: =W28-Z28 -> 0 | AD28: =X28-AA28 -> 0 | AE28: =Y28-AB28 -> 0 | AH28: =+W28*AG28 -> 0
A29: =VLOOKUP(C29,Master!A:D,4,0) -> SF | B29: =VLOOKUP(C29,Master!A:C,3,0) -> Tape Stock | C29: PP Tapes | D29: 0 | E29: 3243.2 | F29: 0 | J29: 8730.6 | O29: 193076 | P29: 196319.2 | T29: 3243.2 | U29: =O29-S29 -> 193076 | V29: =P29-T29 -> 193076 | W29: =D29+G29+H29+I29-K29-L29-M29-V29+U29 -> 0 | X29: =E29+J29-N29-T29+S29 -> 8730.6 | Y29: =F29-I29+M29-R29+Q29 -> 0 | Z29: 0 | AA29: 8730.6 | AB29: 0 | AC29: =W29-Z29 -> 0 | AD29: =X29-AA29 -> 0 | AE29: =Y29-AB29 -> 0 | AH29: =+W29*AG29 -> 0
A30: =VLOOKUP(C30,Master!A:D,4,0) -> SF | B30: =VLOOKUP(C30,Master!A:C,3,0) -> RP Agglo | C30: RP Agglo | D30: 0 | E30: 0 | F30: 0 | T30: 0 | U30: =O30-S30 -> 0 | V30: =P30-T30 -> 0 | W30: =D30+G30+H30+I30-K30-L30-M30-V30+U30 -> 0 | X30: =E30+J30-N30-T30+S30 -> 0 | Y30: =F30-I30+M30-R30+Q30 -> 0 | Z30: 0 | AA30: 0 | AB30: 0 | AC30: =W30-Z30 -> 0 | AD30: =X30-AA30 -> 0 | AE30: =Y30-AB30 -> 0 | AH30: =+W30*AG30 -> 0
A31: =VLOOKUP(C31,Master!A:D,4,0) -> SF | B31: =VLOOKUP(C31,Master!A:C,3,0) -> Wastage/Scrap | C31: Wastage/Scrap | D31: 17957.96 | E31: 0 | F31: 0 | H31: 20774 | K31: 16000 | N31: 20774 | O31: 39203 | P31: 11334.5 | S31: 20774 | T31: 0 | U31: =O31-S31 -> 18429 | V31: =P31-T31 -> 11334.5 | W31: =D31+G31+H31+I31-K31-L31-M31-V31+U31 -> 29826.46 | X31: =E31+J31-N31-T31+S31 -> 0 | Y31: =F31-I31+M31-R31+Q31 -> 0 | Z31: 29826.46 | AA31: 0 | AB31: 0 | AC31: =W31-Z31 -> 0 | AD31: =X31-AA31 -> 0 | AE31: =Y31-AB31 -> 0 | AG31: 60 | AH31: =+W31*AG31 -> 1789587.6
A32: =VLOOKUP(C32,Master!A:D,4,0) -> FG | B32: =VLOOKUP(C32,Master!A:C,3,0) -> FIBC WIP | C32: FIBC WIP | D32: 40457 | E32: 0 | F32: 0 | O32: 296532 | P32: 301629 | T32: 0 | U32: =O32-S32 -> 296532 | V32: =P32-T32 -> 301629 | W32: =D32+G32+H32+I32-K32-L32-M32-V32+U32 -> 35359.999 | X32: =E32+J32-N32-T32+S32 -> 0 | Y32: =F32-I32+M32-R32+Q32 -> 0 | Z32: 35359.999 | AA32: 0 | AB32: 0 | AC32: =W32-Z32 -> 0 | AD32: =X32-AA32 -> 0 | AE32: =Y32-AB32 -> 0 | AG32: 135 | AH32: =+W32*AG32 -> 4773599.8
A33: =VLOOKUP(C33,Master!A:D,4,0) -> FG | B33: =VLOOKUP(C33,Master!A:C,3,0) -> Label Div | C33: Label Div | D33: 0 | E33: 0 | F33: 0 | T33: 0 | U33: =O33-S33 -> 0 | V33: =P33-T33 -> 0 | W33: =D33+G33+H33+I33-K33-L33-M33-V33+U33 -> 0 | X33: =E33+J33-N33-T33+S33 -> 0 | Y33: =F33-I33+M33-R33+Q33 -> 0 | Z33: 0 | AA33: 0 | AB33: 0 | AC33: =W33-Z33 -> 0 | AD33: =X33-AA33 -> 0 | AE33: =Y33-AB33 -> 0 | AH33: =+W33*AG33 -> 0
A34: =VLOOKUP(C34,Master!A:D,4,0) -> FG | B34: =VLOOKUP(C34,Master!A:C,3,0) -> FIBC Bags | C34: FIBC Bags | D34: 0 | E34: 0 | F34: 0 | K34: 1900 | N34: 262003 | O34: 263903 | S34: 262003 | T34: 0 | U34: =O34-S34 -> 1900 | V34: =P34-T34 -> 0 | W34: =D34+G34+H34+I34-K34-L34-M34-V34+U34 -> 0 | X34: =E34+J34-N34-T34+S34 -> 0 | Y34: =F34-I34+M34-R34+Q34 -> 0 | Z34: 0 | AA34: 0 | AB34: 0 | AC34: =W34-Z34 -> 0 | AD34: =X34-AA34 -> 0 | AE34: =Y34-AB34 -> 0 | AH34: =+W34*AG34 -> 0
A35: =VLOOKUP(C35,Master!A:D,4,0) -> FG | B35: =VLOOKUP(C35,Master!A:C,3,0) -> Small Bags | C35: HDPE Bags | D35: 0 | E35: 0 | F35: 0 | T35: 0 | U35: =O35-S35 -> 0 | V35: =P35-T35 -> 0 | W35: =D35+G35+H35+I35-K35-L35-M35-V35+U35 -> 0 | X35: =E35+J35-N35-T35+S35 -> 0 | Y35: =F35-I35+M35-R35+Q35 -> 0 | Z35: 0 | AA35: 0 | AB35: 0 | AC35: =W35-Z35 -> 0 | AD35: =X35-AA35 -> 0 | AE35: =Y35-AB35 -> 0 | AH35: =+W35*AG35 -> 0
A36: =VLOOKUP(C36,Master!A:D,4,0) -> FG | B36: =VLOOKUP(C36,Master!A:C,3,0) -> Tarps | C36: Tarpauline | D36: 0 | E36: 0 | F36: 0 | T36: 0 | U36: =O36-S36 -> 0 | V36: =P36-T36 -> 0 | W36: =D36+G36+H36+I36-K36-L36-M36-V36+U36 -> 0 | X36: =E36+J36-N36-T36+S36 -> 0 | Y36: =F36-I36+M36-R36+Q36 -> 0 | Z36: 0 | AA36: 0 | AB36: 0 | AC36: =W36-Z36 -> 0 | AD36: =X36-AA36 -> 0 | AE36: =Y36-AB36 -> 0 | AH36: =+W36*AG36 -> 0
A37: =VLOOKUP(C37,Master!A:D,4,0) -> FG | B37: =VLOOKUP(C37,Master!A:C,3,0) -> Trading Items | C37: Trading Items | D37: 0 | E37: 0 | F37: 0 | T37: 0 | U37: =O37-S37 -> 0 | V37: =P37-T37 -> 0 | W37: =D37+G37+H37+I37-K37-L37-M37-V37+U37 -> 0 | X37: =E37+J37-N37-T37+S37 -> 0 | Y37: =F37-I37+M37-R37+Q37 -> 0 | Z37: 0 | AA37: 0 | AB37: 0 | AC37: =W37-Z37 -> 0 | AD37: =X37-AA37 -> 0 | AE37: =Y37-AB37 -> 0 | AH37: =+W37*AG37 -> 0
A38: =VLOOKUP(C38,Master!A:D,4,0) -> FG | B38: =VLOOKUP(C38,Master!A:C,3,0) -> Small Bags | C38: PP Bags | D38: 0 | E38: 0 | F38: 0 | T38: 0 | U38: =O38-S38 -> 0 | V38: =P38-T38 -> 0 | W38: =D38+G38+H38+I38-K38-L38-M38-V38+U38 -> 0 | X38: =E38+J38-N38-T38+S38 -> 0 | Y38: =F38-I38+M38-R38+Q38 -> 0 | Z38: 0 | AA38: 0 | AB38: 0 | AC38: =W38-Z38 -> 0 | AD38: =X38-AA38 -> 0 | AE38: =Y38-AB38 -> 0 | AH38: =+W38*AG38 -> 0
A39: =VLOOKUP(C39,Master!A:D,4,0) -> FG | B39: =VLOOKUP(C39,Master!A:C,3,0) -> Small Bags WIP | C39: Small Bags WIP | D39: 0 | E39: 0 | F39: 0 | T39: 0 | U39: =O39-S39 -> 0 | V39: =P39-T39 -> 0 | W39: =D39+G39+H39+I39-K39-L39-M39-V39+U39 -> 0 | X39: =E39+J39-N39-T39+S39 -> 0 | Y39: =F39-I39+M39-R39+Q39 -> 0 | Z39: 0 | AA39: 0 | AB39: 0 | AC39: =W39-Z39 -> 0 | AD39: =X39-AA39 -> 0 | AE39: =Y39-AB39 -> 0 | AH39: =+W39*AG39 -> 0
A40: =VLOOKUP(C40,Master!A:D,4,0) -> FG | B40: =VLOOKUP(C40,Master!A:C,3,0) -> Flexitank | C40: Flexitank | D40: 0 | E40: 0 | F40: 0 | T40: 0 | U40: =O40-S40 -> 0 | V40: =P40-T40 -> 0 | W40: =D40+G40+H40+I40-K40-L40-M40-V40+U40 -> 0 | X40: =E40+J40-N40-T40+S40 -> 0 | Y40: =F40-I40+M40-R40+Q40 -> 0 | Z40: 0 | AA40: 0 | AB40: 0 | AC40: =W40-Z40 -> 0 | AD40: =X40-AA40 -> 0 | AE40: =Y40-AB40 -> 0 | AH40: =+W40*AG40 -> 0
A41: Total | D41: =SUM(D4:D40) -> 130736.76 | E41: =SUM(E4:E40) -> 657884.24 | F41: =SUM(F4:F40) -> 0 | G41: =SUM(G4:G40) -> 0 | H41: =SUM(H4:H40) -> 136828.56 | I41: =SUM(I4:I40) -> 0 | J41: =SUM(J4:J40) -> 340521 | K41: =SUM(K4:K40) -> 126382.9 | ... AF41: =SUM(AF4:AF40) -> 0 | AH41: =SUM(AH4:AH40) -> 14919254
A42: Sales/Purchase/Job in/Job out as per ERP report | H42: 136828.56 | J42: 340521 | K42: 128662.9 | N42: 282777 | AA42: 715628.24
A43: Difference | H43: =H41-H42 -> 0 | J43: =J41-J42 -> 0 | K43: =K41-K42 -> -2280 | N43: =N41-N42 -> 0 | AA43: =+AA41-AA42 -> 0
O44: Diff | P44: =+O41-P41 -> 0 | S44: Diff | T44: =+S41-T41 -> 0
W45: =+D41+H41-K41 -> 141182.42 | X45: =+E41+J41-N41 -> 715628.24 | AH45: =+AH4+AH7+AH18+AH5 -> 8356066.1 | AI45: Closing Stock of Raw material
W46: =+W41-W45 -> 0 | X46: =+X41-X45 -> 0 | AH46: =+AH32 -> 4773599.8 | AI46: Closing Work-in-progress
AH47: =+AH24+AH31 -> 1789587.6 | AI47: Closing Stock of Finished goods
AH48: =+AH41-AH45-AH46-AH47 -> 0
D51: Opening Stock | G51: Inventory movement fo the month of MAY 2026 | W51: Closing Stock -As per Movement Sheet | Z51: Closing Stock - As per Actual (Physical) | AC51: Difference
A52: Group | B52: Sub group | C52: Details of Items / Products | D52: Factory Owned | E52: Factory JW (Others) | F52: At JW (Own) | G52: Branch Tfr Recd | H52: Purchase | I52: Recd from JW (Own) | J52: Recd For JW (Others) | K52: Sales | L52: Br Transfer Sent | M52: Sent for JW (Own) | N52: Return JW(Others) | O52: Total Production Own+JW | P52: Total Consumption Own+JW | Q52: Production at JW | R52: Consumption At JW | S52: Pord of JW | T52: Consumption of JW | U52: Net Production Own | V52: Net Consumption Own | W52: Factory Owned | X52: Factory JW (Others) | Y52: At JW (Own) | Z52: Factory Owned | AA52: Factory JW (Others) | AB52: At JW (Own) | AC52: Factory Owned | AD52: Factory JW (Others) | AE52: At JW (Own) | AF52: Remark for Difference, If any | AG52: Rate | AH52: Value Factory Own
A53: =VLOOKUP(C53,Master!A:D,4,0) -> RM | B53: =VLOOKUP(C53,Master!A:C,3,0) -> Granuals | C53: Masterbatch | D53: =+W4 -> 1596.8 | E53: =+X4 -> 1000 | F53: =+Y4 -> 0 | P53: 477 | T53: 450 | U53: =O53-S53 -> 0 | V53: =P53-T53 -> 27 | W53: =D53+G53+H53+I53-K53-L53-M53-V53+U53 -> 1569.8 | X53: =E53+J53-N53-T53+S53 -> 550 | Y53: =F53-I53+M53-R53+Q53 -> 0 | Z53: =+W53 -> 1569.8 | AA53: 550 | AB53: 0 | AC53: =W53-Z53 -> 0 | AD53: =X53-AA53 -> 0 | AE53: =Y53-AB53 -> 0 | AG53: 201 | AH53: =+W53*AG53 -> 315529.8
A54: =VLOOKUP(C54,Master!A:D,4,0) -> RM | B54: =VLOOKUP(C54,Master!A:C,3,0) -> Granuals | C54: PP Granuals | D54: =+W5 -> 74399.16 | E54: =+X5 -> 537617.54 | F54: =+Y5 -> 0 | P54: 207661.97 | T54: 153341.97 | U54: =O54-S54 -> 0 | V54: =P54-T54 -> 54320 | W54: =D54+G54+H54+I54-K54-L54-M54-V54+U54 -> 20079.16 | X54: =E54+J54-N54-T54+S54 -> 384275.57 | Y54: =F54-I54+M54-R54+Q54 -> 0 | Z54: =+W54 -> 20079.16 | AA54: 384275.57 | AB54: 0 | AC54: =W54-Z54 -> 0 | AD54: =X54-AA54 -> 0 | AE54: =Y54-AB54 -> 0 | AG54: 108 | AH54: =+W54*AG54 -> 2168549.3
A55: =VLOOKUP(C55,Master!A:D,4,0) -> RM | B55: =VLOOKUP(C55,Master!A:C,3,0) -> Granuals | C55: HDPE Granuals | D55: =+W6 -> 0 | E55: =+X6 -> 0 | F55: =+Y6 -> 0 | T55: 0 | U55: =O55-S55 -> 0 | V55: =P55-T55 -> 0 | W55: =D55+G55+H55+I55-K55-L55-M55-V55+U55 -> 0 | X55: =E55+J55-N55-T55+S55 -> 0 | Y55: =F55-I55+M55-R55+Q55 -> 0 | Z55: =+W55 -> 0 | AA55: 0 | AB55: 0 | AC55: =W55-Z55 -> 0 | AD55: =X55-AA55 -> 0 | AE55: =Y55-AB55 -> 0 | AH55: =+W55*AG55 -> 0
A56: =VLOOKUP(C56,Master!A:D,4,0) -> RM | B56: =VLOOKUP(C56,Master!A:C,3,0) -> Granuals | C56: LDPE Granuals | D56: =+W7 -> 0 | E56: =+X7 -> 13000 | F56: =+Y7 -> 0 | T56: 0 | U56: =O56-S56 -> 0 | V56: =P56-T56 -> 0 | W56: =D56+G56+H56+I56-K56-L56-M56-V56+U56 -> 0 | X56: =E56+J56-N56-T56+S56 -> 13000 | Y56: =F56-I56+M56-R56+Q56 -> 0 | Z56: =+W56 -> 0 | AA56: 13000 | AB56: 0 | AC56: =W56-Z56 -> 0 | AD56: =X56-AA56 -> 0 | AE56: =Y56-AB56 -> 0 | AH56: =+W56*AG56 -> 0
A57: =VLOOKUP(C57,Master!A:D,4,0) -> RM | B57: =VLOOKUP(C57,Master!A:C,3,0) -> Granuals | C57: LLDPE Granuals | D57: =+W8 -> 0 | E57: =+X8 -> 0 | F57: =+Y8 -> 0 | T57: 0 | U57: =O57-S57 -> 0 | V57: =P57-T57 -> 0 | W57: =D57+G57+H57+I57-K57-L57-M57-V57+U57 -> 0 | X57: =E57+J57-N57-T57+S57 -> 0 | Y57: =F57-I57+M57-R57+Q57 -> 0 | Z57: =+W57 -> 0 | AA57: 0 | AB57: 0 | AC57: =W57-Z57 -> 0 | AD57: =X57-AA57 -> 0 | AE57: =Y57-AB57 -> 0 | AH57: =+W57*AG57 -> 0
A58: =VLOOKUP(C58,Master!A:D,4,0) -> RM | B58: =VLOOKUP(C58,Master!A:C,3,0) -> Granuals | C58: UV MB | D58: =+W9 -> 0 | E58: =+X9 -> 21575 | F58: =+Y9 -> 0 | J58: 800 | T58: 0 | U58: =O58-S58 -> 0 | V58: =P58-T58 -> 0 | W58: =D58+G58+H58+I58-K58-L58-M58-V58+U58 -> 0 | X58: =E58+J58-N58-T58+S58 -> 22375 | Y58: =F58-I58+M58-R58+Q58 -> 0 | Z58: =+W58 -> 0 | AA58: 22375 | AB58: 0 | AC58: =W58-Z58 -> 0 | AD58: =X58-AA58 -> 0 | AE58: =Y58-AB58 -> 0 | AH58: =+W58*AG58 -> 0
A59: =VLOOKUP(C59,Master!A:D,4,0) -> RM | B59: =VLOOKUP(C59,Master!A:C,3,0) -> FIBC Accessories | C59: FIBC Accessories | D59: =+W10 -> 0 | E59: =+X10 -> 0 | F59: =+Y10 -> 0 | T59: 0 | U59: =O59-S59 -> 0 | V59: =P59-T59 -> 0 | W59: =D59+G59+H59+I59-K59-L59-M59-V59+U59 -> 0 | X59: =E59+J59-N59-T59+S59 -> 0 | Y59: =F59-I59+M59-R59+Q59 -> 0 | Z59: =+W59 -> 0 | AA59: 0 | AB59: 0 | AC59: =W59-Z59 -> 0 | AD59: =X59-AA59 -> 0 | AE59: =Y59-AB59 -> 0 | AH59: =+W59*AG59 -> 0
A60: =VLOOKUP(C60,Master!A:D,4,0) -> RM | B60: =VLOOKUP(C60,Master!A:C,3,0) -> Films All | C60: Polyester Film | D60: =+W11 -> 0 | E60: =+X11 -> 0 | F60: =+Y11 -> 0 | T60: 0 | U60: =O60-S60 -> 0 | V60: =P60-T60 -> 0 | W60: =D60+G60+H60+I60-K60-L60-M60-V60+U60 -> 0 | X60: =E60+J60-N60-T60+S60 -> 0 | Y60: =F60-I60+M60-R60+Q60 -> 0 | Z60: =+W60 -> 0 | AA60: 0 | AB60: 0 | AC60: =W60-Z60 -> 0 | AD60: =X60-AA60 -> 0 | AE60: =Y60-AB60 -> 0 | AH60: =+W60*AG60 -> 0
A61: =VLOOKUP(C61,Master!A:D,4,0) -> RM | B61: =VLOOKUP(C61,Master!A:C,3,0) -> Granuals | C61: Filler | D61: =+W12 -> 0 | E61: =+X12 -> 6000 | F61: =+Y12 -> 0 | J61: 2000 | P61: 6000 | T61: 6000 | U61: =O61-S61 -> 0 | V61: =P61-T61 -> 0 | W61: =D61+G61+H61+I61-K61-L61-M61-V61+U61 -> 0 | X61: =E61+J61-N61-T61+S61 -> 2000 | Y61: =F61-I61+M61-R61+Q61 -> 0 | Z61: =+W61 -> 0 | AA61: 2000 | AB61: 0 | AC61: =W61-Z61 -> 0 | AD61: =X61-AA61 -> 0 | AE61: =Y61-AB61 -> 0 | AH61: =+W61*AG61 -> 0
A62: =VLOOKUP(C62,Master!A:D,4,0) -> RM | B62: =VLOOKUP(C62,Master!A:C,3,0) -> Films All | C62: PE Film | D62: =+W13 -> 0 | E62: =+X13 -> 0 | F62: =+Y13 -> 0 | T62: 0 | U62: =O62-S62 -> 0 | V62: =P62-T62 -> 0 | W62: =D62+G62+H62+I62-K62-L62-M62-V62+U62 -> 0 | X62: =E62+J62-N62-T62+S62 -> 0 | Y62: =F62-I62+M62-R62+Q62 -> 0 | Z62: =+W62 -> 0 | AA62: 0 | AB62: 0 | AC62: =W62-Z62 -> 0 | AD62: =X62-AA62 -> 0 | AE62: =Y62-AB62 -> 0 | AH62: =+W62*AG62 -> 0
A63: =VLOOKUP(C63,Master!A:D,4,0) -> RM | B63: =VLOOKUP(C63,Master!A:C,3,0) -> Granuals | C63: EVA Granuals | D63: =+W14 -> 0 | E63: =+X14 -> 0 | F63: =+Y14 -> 0 | T63: 0 | U63: =O63-S63 -> 0 | V63: =P63-T63 -> 0 | W63: =D63+G63+H63+I63-K63-L63-M63-V63+U63 -> 0 | X63: =E63+J63-N63-T63+S63 -> 0 | Y63: =F63-I63+M63-R63+Q63 -> 0 | Z63: =+W63 -> 0 | AA63: 0 | AB63: 0 | AC63: =W63-Z63 -> 0 | AD63: =X63-AA63 -> 0 | AE63: =Y63-AB63 -> 0 | AH63: =+W63*AG63 -> 0
A64: =VLOOKUP(C64,Master!A:D,4,0) -> RM | B64: =VLOOKUP(C64,Master!A:C,3,0) -> Granuals | C64: mLLDPE Granuals | D64: =+W15 -> 0 | E64: =+X15 -> 0 | F64: =+Y15 -> 0 | T64: 0 | U64: =O64-S64 -> 0 | V64: =P64-T64 -> 0 | W64: =D64+G64+H64+I64-K64-L64-M64-V64+U64 -> 0 | X64: =E64+J64-N64-T64+S64 -> 0 | Y64: =F64-I64+M64-R64+Q64 -> 0 | Z64: =+W64 -> 0 | AA64: 0 | AB64: 0 | AC64: =W64-Z64 -> 0 | AD64: =X64-AA64 -> 0 | AE64: =Y64-AB64 -> 0 | AH64: =+W64*AG64 -> 0
A65: =VLOOKUP(C65,Master!A:D,4,0) -> RM | B65: =VLOOKUP(C65,Master!A:C,3,0) -> Films All | C65: BOPP Film | D65: =+W16 -> 0 | E65: =+X16 -> 0 | F65: =+Y16 -> 0 | T65: 0 | U65: =O65-S65 -> 0 | V65: =P65-T65 -> 0 | W65: =D65+G65+H65+I65-K65-L65-M65-V65+U65 -> 0 | X65: =E65+J65-N65-T65+S65 -> 0 | Y65: =F65-I65+M65-R65+Q65 -> 0 | Z65: =+W65 -> 0 | AA65: 0 | AB65: 0 | AC65: =W65-Z65 -> 0 | AD65: =X65-AA65 -> 0 | AE65: =Y65-AB65 -> 0 | AH65: =+W65*AG65 -> 0
A66: =VLOOKUP(C66,Master!A:D,4,0) -> RM | B66: =VLOOKUP(C66,Master!A:C,3,0) -> Granuals | C66: Enable Granuals | D66: =+W17 -> 0 | E66: =+X17 -> 0 | F66: =+Y17 -> 0 | T66: 0 | U66: =O66-S66 -> 0 | V66: =P66-T66 -> 0 | W66: =D66+G66+H66+I66-K66-L66-M66-V66+U66 -> 0 | X66: =E66+J66-N66-T66+S66 -> 0 | Y66: =F66-I66+M66-R66+Q66 -> 0 | Z66: =+W66 -> 0 | AA66: 0 | AB66: 0 | AC66: =W66-Z66 -> 0 | AD66: =X66-AA66 -> 0 | AE66: =Y66-AB66 -> 0 | AH66: =+W66*AG66 -> 0
A67: =VLOOKUP(C67,Master!A:D,4,0) -> SF | B67: =VLOOKUP(C67,Master!A:C,3,0) -> Yarn All | C67: PP Yarn | D67: =+W18 -> 0 | E67: =+X18 -> 17208.3 | F67: =+Y18 -> 0 | H67: 7163.78 | J67: 15419.3 | O67: 832.8 | P67: 19937.48 | T67: 12588.9 | U67: =O67-S67 -> 832.8 | V67: =P67-T67 -> 7348.58 | W67: =D67+G67+H67+I67-K67-L67-M67-V67+U67 -> 648 | X67: =E67+J67-N67-T67+S67 -> 20038.7 | Y67: =F67-I67+M67-R67+Q67 -> 0 | Z67: =+W67 -> 648 | AA67: 20038.7 | AB67: 0 | AC67: =W67-Z67 -> 0 | AD67: =X67-AA67 -> 0 | AE67: =Y67-AB67 -> 0 | AG67: 123.63752 | AH67: =+W67*AG67 -> 80117.114
A68: =VLOOKUP(C68,Master!A:D,4,0) -> SF | B68: =VLOOKUP(C68,Master!A:C,3,0) -> PP/PE Fabric | C68: PP UL Fabric | D68: =+W19 -> 0 | E68: =+X19 -> 47218.6 | F68: =+Y19 -> 0 | J68: 42872.1 | K68: 34349 | O68: 160931 | P68: 162472.4 | T68: 35890.4 | U68: =O68-S68 -> 160931 | V68: =P68-T68 -> 126582 | W68: =D68+G68+H68+I68-K68-L68-M68-V68+U68 -> 0 | X68: =E68+J68-N68-T68+S68 -> 54200.3 | Y68: =F68-I68+M68-R68+Q68 -> 0 | Z68: =+W68 -> 0 | AA68: 54200.3 | AB68: 0 | AC68: =W68-Z68 -> 0 | AD68: =X68-AA68 -> 0 | AE68: =Y68-AB68 -> 0 | AH68: =+W68*AG68 -> 0
A69: =VLOOKUP(C69,Master!A:D,4,0) -> SF | B69: =VLOOKUP(C69,Master!A:C,3,0) -> Flexitank Accessories | C69: Flexitank Accessories | D69: =+W20 -> 0 | E69: =+X20 -> 0 | F69: =+Y20 -> 0 | T69: 0 | U69: =O69-S69 -> 0 | V69: =P69-T69 -> 0 | W69: =D69+G69+H69+I69-K69-L69-M69-V69+U69 -> 0 | X69: =E69+J69-N69-T69+S69 -> 0 | Y69: =F69-I69+M69-R69+Q69 -> 0 | Z69: =+W69 -> 0 | AA69: 0 | AB69: 0 | AC69: =W69-Z69 -> 0 | AD69: =X69-AA69 -> 0 | AE69: =Y69-AB69 -> 0 | AH69: =+W69*AG69 -> 0
A70: =VLOOKUP(C70,Master!A:D,4,0) -> SF | B70: =VLOOKUP(C70,Master!A:C,3,0) -> PP/PE Fabric | C70: PP Lam Fabric | D70: =+W21 -> 0 | E70: =+X21 -> 18916.3 | F70: =+Y21 -> 0 | J70: 2331 | O70: 104076 | P70: 122887.3 | T70: 18811.3 | U70: =O70-S70 -> 104076 | V70: =P70-T70 -> 104076 | W70: =D70+G70+H70+I70-K70-L70-M70-V70+U70 -> 0 | X70: =E70+J70-N70-T70+S70 -> 2436 | Y70: =F70-I70+M70-R70+Q70 -> 0 | Z70: =+W70 -> 0 | AA70: 2436 | AB70: 0 | AC70: =W70-Z70 -> 0 | AD70: =X70-AA70 -> 0 | AE70: =Y70-AB70 -> 0 | AH70: =+W70*AG70 -> 0
A71: =VLOOKUP(C71,Master!A:D,4,0) -> SF | B71: =VLOOKUP(C71,Master!A:C,3,0) -> PP/PE Fabric | C71: HD UL Fabric | D71: =+W22 -> 0 | E71: =+X22 -> 0 | F71: =+Y22 -> 0 | T71: 0 | U71: =O71-S71 -> 0 | V71: =P71-T71 -> 0 | W71: =D71+G71+H71+I71-K71-L71-M71-V71+U71 -> 0 | X71: =E71+J71-N71-T71+S71 -> 0 | Y71: =F71-I71+M71-R71+Q71 -> 0 | Z71: =+W71 -> 0 | AA71: 0 | AB71: 0 | AC71: =W71-Z71 -> 0 | AD71: =X71-AA71 -> 0 | AE71: =Y71-AB71 -> 0 | AH71: =+W71*AG71 -> 0
A72: =VLOOKUP(C72,Master!A:D,4,0) -> SF | B72: =VLOOKUP(C72,Master!A:C,3,0) -> PP/PE Fabric | C72: HD Lam Fabric | D72: =+W23 -> 0 | E72: =+X23 -> 0 | F72: =+Y23 -> 0 | T72: 0 | U72: =O72-S72 -> 0 | V72: =P72-T72 -> 0 | W72: =D72+G72+H72+I72-K72-L72-M72-V72+U72 -> 0 | X72: =E72+J72-N72-T72+S72 -> 0 | Y72: =F72-I72+M72-R72+Q72 -> 0 | Z72: =+W72 -> 0 | AA72: 0 | AB72: 0 | AC72: =W72-Z72 -> 0 | AD72: =X72-AA72 -> 0 | AE72: =Y72-AB72 -> 0 | AH72: =+W72*AG72 -> 0
A73: =VLOOKUP(C73,Master!A:D,4,0) -> SF | B73: =VLOOKUP(C73,Master!A:C,3,0) -> Granuals | C73: RP Granuals | D73: =+W24 -> 0 | E73: =+X24 -> 3000 | F73: =+Y24 -> 0 | J73: 1000 | K73: 46000 | O73: 63600 | P73: 3000 | T73: 3000 | U73: =O73-S73 -> 63600 | V73: =P73-T73 -> 0 | W73: =D73+G73+H73+I73-K73-L73-M73-V73+U73 -> 17600 | X73: =E73+J73-N73-T73+S73 -> 1000 | Y73: =F73-I73+M73-R73+Q73 -> 0 | Z73: =+W73 -> 17600 | AA73: 1000 | AB73: 0 | AC73: =W73-Z73 -> 0 | AD73: =X73-AA73 -> 0 | AE73: =Y73-AB73 -> 0 | AG73: 52 | AH73: =+W73*AG73 -> 915200
A74: =VLOOKUP(C74,Master!A:D,4,0) -> SF | B74: =VLOOKUP(C74,Master!A:C,3,0) -> Liners | C74: Liner for Flexitank | D74: =+W25 -> 0 | E74: =+X25 -> 0 | F74: =+Y25 -> 0 | T74: 0 | U74: =O74-S74 -> 0 | V74: =P74-T74 -> 0 | W74: =D74+G74+H74+I74-K74-L74-M74-V74+U74 -> 0 | X74: =E74+J74-N74-T74+S74 -> 0 | Y74: =F74-I74+M74-R74+Q74 -> 0 | Z74: =+W74 -> 0 | AA74: 0 | AB74: 0 | AC74: =W74-Z74 -> 0 | AD74: =X74-AA74 -> 0 | AE74: =Y74-AB74 -> 0 | AH74: =+W74*AG74 -> 0
A75: =VLOOKUP(C75,Master!A:D,4,0) -> SF | B75: =VLOOKUP(C75,Master!A:C,3,0) -> Webbing | C75: PP Webbing | D75: =+W26 -> 0 | E75: =+X26 -> 1737.1 | F75: =+Y26 -> 0 | J75: 468.9 | K75: 411.3 | O75: 45595.6 | P75: 45265.3 | T75: 81 | U75: =O75-S75 -> 45595.6 | V75: =P75-T75 -> 45184.3 | W75: =D75+G75+H75+I75-K75-L75-M75-V75+U75 -> 0 | X75: =E75+J75-N75-T75+S75 -> 2125 | Y75: =F75-I75+M75-R75+Q75 -> 0 | Z75: =+W75 -> 0 | AA75: 2125 | AB75: 0 | AC75: =W75-Z75 -> 0 | AD75: =X75-AA75 -> 0 | AE75: =Y75-AB75 -> 0 | AH75: =+W75*AG75 -> 0
A76: =VLOOKUP(C76,Master!A:D,4,0) -> SF | B76: =VLOOKUP(C76,Master!A:C,3,0) -> Liners | C76: LDPE/LLDPE Bags | D76: =+W27 -> 0 | E76: =+X27 -> 39624.8 | F76: =+Y27 -> 0 | J76: 79673.2 | P76: 23451.8 | T76: 23451.8 | U76: =O76-S76 -> 0 | V76: =P76-T76 -> 0 | W76: =D76+G76+H76+I76-K76-L76-M76-V76+U76 -> 0 | X76: =E76+J76-N76-T76+S76 -> 95846.2 | Y76: =F76-I76+M76-R76+Q76 -> 0 | Z76: =+W76 -> 0 | AA76: 95846.2 | AB76: 0 | AC76: =W76-Z76 -> 0 | AD76: =X76-AA76 -> 0 | AE76: =Y76-AB76 -> 0 | AH76: =+W76*AG76 -> 0
A77: =VLOOKUP(C77,Master!A:D,4,0) -> SF | B77: =VLOOKUP(C77,Master!A:C,3,0) -> Tape Stock | C77: Beam Stock | D77: =+W28 -> 0 | E77: =+X28 -> 0 | F77: =+Y28 -> 0 | T77: 0 | U77: =O77-S77 -> 0 | V77: =P77-T77 -> 0 | W77: =D77+G77+H77+I77-K77-L77-M77-V77+U77 -> 0 | X77: =E77+J77-N77-T77+S77 -> 0 | Y77: =F77-I77+M77-R77+Q77 -> 0 | Z77: =+W77 -> 0 | AA77: 0 | AB77: 0 | AC77: =W77-Z77 -> 0 | AD77: =X77-AA77 -> 0 | AE77: =Y77-AB77 -> 0 | AH77: =+W77*AG77 -> 0
A78: =VLOOKUP(C78,Master!A:D,4,0) -> SF | B78: =VLOOKUP(C78,Master!A:C,3,0) -> Tape Stock | C78: PP Tapes | D78: =+W29 -> 0 | E78: =+X29 -> 8730.6 | F78: =+Y29 -> 0 | J78: 135746.05 | O78: 66554 | P78: 71812.6 | T78: 5258.6 | U78: =O78-S78 -> 66554 | V78: =P78-T78 -> 66554 | W78: =D78+G78+H78+I78-K78-L78-M78-V78+U78 -> 0 | X78: =E78+J78-N78-T78+S78 -> 139218.05 | Y78: =F78-I78+M78-R78+Q78 -> 0 | Z78: =+W78 -> 0 | AA78: 139218.05 | AB78: 0 | AC78: =W78-Z78 -> 0 | AD78: =X78-AA78 -> 0 | AE78: =Y78-AB78 -> 0 | AH78: =+W78*AG78 -> 0
A79: =VLOOKUP(C79,Master!A:D,4,0) -> SF | B79: =VLOOKUP(C79,Master!A:C,3,0) -> RP Agglo | C79: RP Agglo | D79: =+W30 -> 0 | E79: =+X30 -> 0 | F79: =+Y30 -> 0 | P79: 0 | T79: 0 | U79: =O79-S79 -> 0 | V79: =P79-T79 -> 0 | W79: =D79+G79+H79+I79-K79-L79-M79-V79+U79 -> 0 | X79: =E79+J79-N79-T79+S79 -> 0 | Y79: =F79-I79+M79-R79+Q79 -> 0 | Z79: =+W79 -> 0 | AA79: 0 | AB79: 0 | AC79: =W79-Z79 -> 0 | AD79: =X79-AA79 -> 0 | AE79: =Y79-AB79 -> 0 | AH79: =+W79*AG79 -> 0
A80: =VLOOKUP(C80,Master!A:D,4,0) -> SF | B80: =VLOOKUP(C80,Master!A:C,3,0) -> Wastage/Scrap | C80: Wastage/Scrap | D80: =+W31 -> 29826.46 | E80: =+X31 -> 0 | F80: =+Y31 -> 0 | N80: 7291.97 | O80: 29019 | P80: 51553.49 | S80: 7291.97 | T80: 0 | U80: =O80-S80 -> 21727.03 | V80: =P80-T80 -> 51553.49 | W80: =D80+G80+H80+I80-K80-L80-M80-V80+U80 -> 0 | X80: =E80+J80-N80-T80+S80 -> 0 | Y80: =F80-I80+M80-R80+Q80 -> 0 | Z80: =+W80 -> 0 | AA80: 0 | AB80: 0 | AC80: =W80-Z80 -> 0 | AD80: =X80-AA80 -> 0 | AE80: =Y80-AB80 -> 0 | AH80: =+W80*AG80 -> 0
A81: =VLOOKUP(C81,Master!A:D,4,0) -> FG | B81: =VLOOKUP(C81,Master!A:C,3,0) -> FIBC WIP | C81: FIBC WIP | D81: =+W32 -> 35359.999 | E81: =+X32 -> 0 | F81: =+Y32 -> 0 | O81: 24647.939 | P81: 36007.999 | T81: 0 | U81: =O81-S81 -> 24647.939 | V81: =P81-T81 -> 36007.999 | W81: =D81+G81+H81+I81-K81-L81-M81-V81+U81 -> 23999.939 | X81: =E81+J81-N81-T81+S81 -> 0 | Y81: =F81-I81+M81-R81+Q81 -> 0 | Z81: =+W81 -> 23999.939 | AA81: 0 | AB81: 0 | AC81: =W81-Z81 -> 0 | AD81: =X81-AA81 -> 0 | AE81: =Y81-AB81 -> 0 | AG81: 135 | AH81: =+W81*AG81 -> 3239991.7
A82: =VLOOKUP(C82,Master!A:D,4,0) -> FG | B82: =VLOOKUP(C82,Master!A:C,3,0) -> Label Div | C82: Label Div | D82: =+W33 -> 0 | E82: =+X33 -> 0 | F82: =+Y33 -> 0 | T82: 0 | U82: =O82-S82 -> 0 | V82: =P82-T82 -> 0 | W82: =D82+G82+H82+I82-K82-L82-M82-V82+U82 -> 0 | X82: =E82+J82-N82-T82+S82 -> 0 | Y82: =F82-I82+M82-R82+Q82 -> 0 | Z82: =+W82 -> 0 | AA82: 0 | AB82: 0 | AC82: =W82-Z82 -> 0 | AD82: =X82-AA82 -> 0 | AE82: =Y82-AB82 -> 0 | AH82: =+W82*AG82 -> 0
A83: =VLOOKUP(C83,Master!A:D,4,0) -> FG | B83: =VLOOKUP(C83,Master!A:C,3,0) -> FIBC Bags | C83: FIBC Bags | D83: =+W34 -> 0 | E83: =+X34 -> 0 | F83: =+Y34 -> 0 | K83: 3689 | N83: 251582 | O83: 255271 | S83: 251582 | T83: 0 | U83: =O83-S83 -> 3689 | V83: =P83-T83 -> 0 | W83: =D83+G83+H83+I83-K83-L83-M83-V83+U83 -> 0 | X83: =E83+J83-N83-T83+S83 -> 0 | Y83: =F83-I83+M83-R83+Q83 -> 0 | Z83: =+W83 -> 0 | AA83: 0 | AB83: 0 | AC83: =W83-Z83 -> 0 | AD83: =X83-AA83 -> 0 | AE83: =Y83-AB83 -> 0 | AH83: =+W83*AG83 -> 0
A84: =VLOOKUP(C84,Master!A:D,4,0) -> FG | B84: =VLOOKUP(C84,Master!A:C,3,0) -> Small Bags | C84: HDPE Bags | D84: =+W35 -> 0 | E84: =+X35 -> 0 | F84: =+Y35 -> 0 | T84: 0 | U84: =O84-S84 -> 0 | V84: =P84-T84 -> 0 | W84: =D84+G84+H84+I84-K84-L84-M84-V84+U84 -> 0 | X84: =E84+J84-N84-T84+S84 -> 0 | Y84: =F84-I84+M84-R84+Q84 -> 0 | Z84: =+W84 -> 0 | AA84: 0 | AB84: 0 | AC84: =W84-Z84 -> 0 | AD84: =X84-AA84 -> 0 | AE84: =Y84-AB84 -> 0 | AH84: =+W84*AG84 -> 0
A85: =VLOOKUP(C85,Master!A:D,4,0) -> FG | B85: =VLOOKUP(C85,Master!A:C,3,0) -> Tarps | C85: Tarpauline | D85: =+W36 -> 0 | E85: =+X36 -> 0 | F85: =+Y36 -> 0 | T85: 0 | U85: =O85-S85 -> 0 | V85: =P85-T85 -> 0 | W85: =D85+G85+H85+I85-K85-L85-M85-V85+U85 -> 0 | X85: =E85+J85-N85-T85+S85 -> 0 | Y85: =F85-I85+M85-R85+Q85 -> 0 | Z85: =+W85 -> 0 | AA85: 0 | AB85: 0 | AC85: =W85-Z85 -> 0 | AD85: =X85-AA85 -> 0 | AE85: =Y85-AB85 -> 0 | AH85: =+W85*AG85 -> 0
A86: =VLOOKUP(C86,Master!A:D,4,0) -> FG | B86: =VLOOKUP(C86,Master!A:C,3,0) -> Trading Items | C86: Trading Items | D86: =+W37 -> 0 | E86: =+X37 -> 0 | F86: =+Y37 -> 0 | T86: 0 | U86: =O86-S86 -> 0 | V86: =P86-T86 -> 0 | W86: =D86+G86+H86+I86-K86-L86-M86-V86+U86 -> 0 | X86: =E86+J86-N86-T86+S86 -> 0 | Y86: =F86-I86+M86-R86+Q86 -> 0 | Z86: =+W86 -> 0 | AA86: 0 | AB86: 0 | AC86: =W86-Z86 -> 0 | AD86: =X86-AA86 -> 0 | AE86: =Y86-AB86 -> 0 | AH86: =+W86*AG86 -> 0
A87: =VLOOKUP(C87,Master!A:D,4,0) -> FG | B87: =VLOOKUP(C87,Master!A:C,3,0) -> Small Bags | C87: PP Bags | D87: =+W38 -> 0 | E87: =+X38 -> 0 | F87: =+Y38 -> 0 | T87: 0 | U87: =O87-S87 -> 0 | V87: =P87-T87 -> 0 | W87: =D87+G87+H87+I87-K87-L87-M87-V87+U87 -> 0 | X87: =E87+J87-N87-T87+S87 -> 0 | Y87: =F87-I87+M87-R87+Q87 -> 0 | Z87: =+W87 -> 0 | AA87: 0 | AB87: 0 | AC87: =W87-Z87 -> 0 | AD87: =X87-AA87 -> 0 | AE87: =Y87-AB87 -> 0 | AH87: =+W87*AG87 -> 0
A88: =VLOOKUP(C88,Master!A:D,4,0) -> FG | B88: =VLOOKUP(C88,Master!A:C,3,0) -> Small Bags WIP | C88: Small Bags WIP | D88: =+W39 -> 0 | E88: =+X39 -> 0 | F88: =+Y39 -> 0 | T88: 0 | U88: =O88-S88 -> 0 | V88: =P88-T88 -> 0 | W88: =D88+G88+H88+I88-K88-L88-M88-V88+U88 -> 0 | X88: =E88+J88-N88-T88+S88 -> 0 | Y88: =F88-I88+M88-R88+Q88 -> 0 | Z88: =+W88 -> 0 | AA88: 0 | AB88: 0 | AC88: =W88-Z88 -> 0 | AD88: =X88-AA88 -> 0 | AE88: =Y88-AB88 -> 0 | AH88: =+W88*AG88 -> 0
A89: =VLOOKUP(C89,Master!A:D,4,0) -> FG | B89: =VLOOKUP(C89,Master!A:C,3,0) -> Flexitank | C89: Flexitank | D89: =+W40 -> 0 | E89: =+X40 -> 0 | F89: =+Y40 -> 0 | T89: 0 | U89: =O89-S89 -> 0 | V89: =P89-T89 -> 0 | W89: =D89+G89+H89+I89-K89-L89-M89-V89+U89 -> 0 | X89: =E89+J89-N89-T89+S89 -> 0 | Y89: =F89-I89+M89-R89+Q89 -> 0 | Z89: =+W89 -> 0 | AA89: 0 | AB89: 0 | AC89: =W89-Z89 -> 0 | AD89: =X89-AA89 -> 0 | AE89: =Y89-AB89 -> 0 | AH89: =+W89*AG89 -> 0
A90: Total | D90: =SUM(D53:D89) -> 141182.42 | E90: =SUM(E53:E89) -> 715628.24 | F90: =SUM(F53:F89) -> 0 | G90: =SUM(G53:G89) -> 0 | H90: =SUM(H53:H89) -> 7163.78 | I90: =SUM(I53:I89) -> 0 | J90: =SUM(J53:J89) -> 280310.55 | K90: =SUM(K53:K89) -> 84449.3 | ... AF90: =SUM(AF53:AF89) -> 0 | AH90: =SUM(AH53:AH89) -> 6719387.9
A91: Sales/Purchase/Job in/Job out as per ERP report | H91: 7163.78 | J91: 280310.55 | K91: 84449.3 | N91: 258873.97 | AA91: 737064.82
A92: Difference | G92: =G90-G91 -> 0 | H92: =H90-H91 -> 0 | I92: =I90-I91 -> 0 | J92: =J90-J91 -> 0 | K92: =K90-K91 -> 0 | L92: =L90-L91 -> 0 | M92: =M90-M91 -> 0 | N92: =N90-N91 -> 0 | AA92: =+AA90-AA91 -> 0
O93: Diff | P93: =+O90-P90 -> 0 | S93: Diff | T93: =+S90-T90 -> 0
W94: =+D90+H90-K90 -> 63896.899 | X94: =+E90+J90-N90 -> 737064.82 | AH94: =+AH53+AH67+AH68+AH70+AH75+AH78+AH54+AH56+AH61 -> 2564196.2 | AI94: Closing Stock of Raw material
W95: =+W90-W94 -> 1.3096724e-10 | X95: =+X90-X94 -> 0 | AH95: =+AH81 -> 3239991.7 | AI95: Closing Work-in-progress
AH96: =+AH73+AH80+AH83+AH87 -> 915200 | AI96: Closing Stock of Finished goods
AH97: =+AH90-AH94-AH95-AH96 -> 0
D100: Opening Stock | G100: Inventory movement fo the month of June 2026 | W100: Closing Stock -As per Movement Sheet | Z100: Closing Stock - As per Actual (Physical) | AC100: Difference
A101: Group | B101: Sub group | C101: Details of Items / Products | D101: Factory Owned | E101: Factory JW (Others) | F101: At JW (Own) | G101: Branch Tfr Recd | H101: Purchase | I101: Recd from JW (Own) | J101: Recd For JW (Others) | K101: Sales | L101: Br Transfer Sent | M101: Sent for JW (Own) | N101: Return JW(Others) | O101: Total Production Own+JW | P101: Total Consumption Own+JW | Q101: Production at JW | R101: Consumption At JW | S101: Pord of JW | T101: Consumption of JW | U101: Net Production Own | V101: Net Consumption Own | W101: Factory Owned | X101: Factory JW (Others) | Y101: At JW (Own) | Z101: Factory Owned | AA101: Factory JW (Others) | AB101: At JW (Own) | AC101: Factory Owned | AD101: Factory JW (Others) | AE101: At JW (Own) | AF101: Remark for Difference, If any | AG101: Rate | AH101: Value Factory Own
A102: =VLOOKUP(C102,Master!A:D,4,0) -> RM | B102: =VLOOKUP(C102,Master!A:C,3,0) -> Granuals | C102: Masterbatch | D102: =+W53 -> 1569.8 | E102: =+X53 -> 550 | F102: =+Y53 -> 0 | J102: 325 | P102: 500 | T102: 500 | U102: =O102-S102 -> 0 | V102: =P102-T102 -> 0 | W102: =D102+G102+H102+I102-K102-L102-M102-V102+U102 -> 1569.8 | X102: =E102+J102-N102-T102+S102 -> 375 | Y102: =F102-I102+M102-R102+Q102 -> 0 | Z102: 1569.8 | AA102: 375 | AB102: 0 | AC102: =W102-Z102 -> 0 | AD102: =X102-AA102 -> 0 | AE102: =Y102-AB102 -> 0 | AG102: 201 | AH102: =+W102*AG102 -> 315529.8
A103: =VLOOKUP(C103,Master!A:D,4,0) -> RM | B103: =VLOOKUP(C103,Master!A:C,3,0) -> Granuals | C103: PP Granuals | D103: =+W54 -> 20079.16 | E103: =+X54 -> 384275.57 | F103: =+Y54 -> 0 | J103: 1250 | P103: 121104.73 | T103: 101025.57 | U103: =O103-S103 -> 0 | V103: =P103-T103 -> 20079.16 | W103: =D103+G103+H103+I103-K103-L103-M103-V103+U103 -> 0 | X103: =E103+J103-N103-T103+S103 -> 284500 | Y103: =F103-I103+M103-R103+Q103 -> 0 | Z103: 0 | AA103: 284500 | AB103: 0 | AC103: =W103-Z103 -> 0 | AD103: =X103-AA103 -> 0 | AE103: =Y103-AB103 -> 0 | AH103: =+W103*AG103 -> 0
A104: =VLOOKUP(C104,Master!A:D,4,0) -> RM | B104: =VLOOKUP(C104,Master!A:C,3,0) -> Granuals | C104: HDPE Granuals | D104: =+W55 -> 0 | E104: =+X55 -> 0 | F104: =+Y55 -> 0 | T104: 0 | U104: =O104-S104 -> 0 | V104: =P104-T104 -> 0 | W104: =D104+G104+H104+I104-K104-L104-M104-V104+U104 -> 0 | X104: =E104+J104-N104-T104+S104 -> 0 | Y104: =F104-I104+M104-R104+Q104 -> 0 | Z104: 0 | AA104: 0 | AB104: 0 | AC104: =W104-Z104 -> 0 | AD104: =X104-AA104 -> 0 | AE104: =Y104-AB104 -> 0 | AH104: =+W104*AG104 -> 0
A105: =VLOOKUP(C105,Master!A:D,4,0) -> RM | B105: =VLOOKUP(C105,Master!A:C,3,0) -> Granuals | C105: LDPE Granuals | D105: =+W56 -> 0 | E105: =+X56 -> 13000 | F105: =+Y56 -> 0 | T105: 0 | U105: =O105-S105 -> 0 | V105: =P105-T105 -> 0 | W105: =D105+G105+H105+I105-K105-L105-M105-V105+U105 -> 0 | X105: =E105+J105-N105-T105+S105 -> 13000 | Y105: =F105-I105+M105-R105+Q105 -> 0 | Z105: 0 | AA105: 13000 | AB105: 0 | AC105: =W105-Z105 -> 0 | AD105: =X105-AA105 -> 0 | AE105: =Y105-AB105 -> 0 | AH105: =+W105*AG105 -> 0
...

Sheet Sheet1
B2: Physical | F2: JOB Stock | H2: AS PER REPORT
A3: Details of Items / Products | B3: OEL-1 | C3: KPW-3
A4: Masterbatch | B4: 5172 | D4: =+B4+C4 -> 5172 | F4: 6325 | G4: =+D4-F4 -> -1153 | H4: 0
A5: PP Granuals | B5: 76937 | D5: =+B5+C5 -> 76937 | F5: =162178.34+4500 -> 166678.34 | G5: =+D5-F5 -> -89741.34 | H5: 0
A6: Filler | B6: 4613 | D6: =+B6+C6 -> 4613 | F6: 10202 | G6: =+D6-F6 -> -5589 | H6: 0
A7: PP Yarn | B7: 43813.92 | D7: =+B7+C7 -> 43813.92 | F7: 18694.3 | G7: =+D7-F7 -> 25119.62 | H7: 15119.28
A8: PP UL Fabric | B8: 65408 | D8: =+B8+C8 -> 65408 | F8: 11978.4 | G8: =+D8-F8 -> 53429.6 | H8: 13429.6
A9: PP Lam Fabric | B9: 78964 | D9: =+B9+C9 -> 78964 | F9: 22509 | G9: =+D9-F9 -> 56455 | H9: 26455
A10: RP Granuals | B10: 56144 | D10: =+B10+C10 -> 56144 | G10: =+D10-F10 -> 56144 | H10: 56144
A11: PP Webbing | B11: 28984 | D11: =+B11+C11 -> 28984 | F11: 5791.74 | G11: =+D11-F11 -> 23192.26 | H11: 16709.3
A12: LDPE/LLDPE Bags | B12: 7178.6 | D12: =+B12+C12 -> 7178.6 | F12: 7178.56 | G12: =+D12-F12 -> 0.04 | H12: 0
A13: PP Tapes | B13: 35300 | D13: =+B13+C13 -> 35300 | F13: 5595.4 | G13: =+D13-F13 -> 29704.6 | H13: 19704.6
A14: Wastage/Scrap | B14: 27372 | D14: =+B14+C14 -> 27372 | G14: =+D14-F14 -> 27372 | H14: 27372
A15: FIBC WIP | B15: 63870.5 | D15: =+B15+C15 -> 63870.5 | G15: =+D15-F15 -> 63870.5 | H15: 63870.5
A16: FIBC Bags | B16: =247069.9-C16-B17 -> 208673.9 | C16: 35271 | D16: =+B16+C16 -> 243944.9 | G16: =+D16-F16 -> 243944.9 | H16: 186365.57
A17: PP Bags | B17: 3125 | D17: =+B17+C17 -> 3125 | G17: =+D17-F17 -> 3125 | H17: 3125
G18: =+D18-F18 -> 0
A19: Total | B19: =SUM(B4:B18) -> 705555.92 | C19: =SUM(C4:C18) -> 35271 | D19: =SUM(D4:D18) -> 740826.92 | F19: =SUM(F4:F18) -> 254952.74 | G19: =SUM(G4:G18) -> 485874.18 | H19: =SUM(H4:H18) -> 428294.85

Sheet Sales 
A1: Row Labels | B1: Sum of Quantity | C1: Sum of Amount
A2: Jambo Bag/Fibc Bag Mfr (Kg) | B2: 4752 | C2: 1241120 | D2: =C2/B2 -> 261.17845
A3: PP Webbing | B3: 1566.9 | C3: 159824 | D3: =C3/B3 -> 102.00013
A4: PP Woven Fabric | B4: 76072.4 | C4: 10649973 | D4: =C4/B4 -> 139.99786
A5: Reprocessed Granules | B5: 69750 | C5: 3627000 | D5: =C5/B5 -> 52
A6: Other Scrap | B6: 15864.2 | C6: 15025 | D6: =C6/B6 -> 0.94710102
A7: Grand Total | B7: 168005.5 | C7: 15692942
A24: Date | B24: Particular | C24: Voucher Type | D24: Voucher No | E24: Type | F24: Invoice No | G24: Invoice Date | H24: Main Grp | I24: Group Name | J24: Sub Grup | K24: sales Group Name | L24: Item Name | M24: Quantity | N24: Amount | O24: Item Desc | P24: Bill Amount | Q24: CGST Rate | R24: CGST Amt | S24: SGST Rate | T24: SGST Amt | U24: IGST Rate | V24: IGST Amt | W24: Freight GST | X24: Total GST | Y24: TCS | Z24: GST-IN | AA24: Unit | AB24: HSN Code | AC24: Currencty | AD24: Exc.Rate | AE24: Net Wt
A25: 46060 | B25: Plastene India ltd - Unit 1-Sales | C25: Deemed Export | D25: OEL1/DE/051/26-27 | E25: Sales - Interstate - Manufactured Goods | F25: OEL1/DE/051/26-27 | G25: 46060 | H25: SF | I25: PP/PE Fabric | J25: PP UL Fabric | K25: PP Woven Fabric | L25: PP UL Fabric With UV | M25: 2670 | N25: 373789 | O25: PP WOVEN FABRICS | P25: 373415.21 | Q25: 0 | R25: 0 | S25: 0 | T25: 0 | U25: 0 | V25: 0 | W25: 0 | X25: 0 | Y25: 0 | Z25: 24AAACO3087C1ZT | AA25: KGS | AB25: 39269080 | AC25: Rs. | AD25: 1 | AE25: 2670 | AF25: India
A26: 46088 | B26: Plastene India ltd - Unit 1-Sales | C26: Deemed Export | D26: OEL1/DE/052/26-27 | E26: Sales - Interstate - Manufactured Goods | F26: OEL1/DE/052/26-27 | G26: 46088 | H26: SF | I26: PP/PE Fabric | J26: PP UL Fabric | K26: PP Woven Fabric | L26: PP UL Fabric With UV | M26: 2543 | N26: 356009 | O26: PP WOVEN FABRICS | P26: 355652.99 | Q26: 0 | R26: 0 | S26: 0 | T26: 0 | U26: 0 | V26: 0 | W26: 0 | X26: 0 | Y26: 0 | Z26: 24AAACO3087C1ZT | AA26: KGS | AB26: 392690 | AC26: Rs. | AD26: 1 | AE26: 2543 | AF26: India
A27: 46180 | B27: Plastene India ltd - Unit 1-Sales | C27: Deemed Export | D27: OEL1/DE/053/26-27 | E27: Sales - Interstate - Manufactured Goods | F27: OEL1/DE/053/26-27 | G27: 46180 | H27: SF | I27: PP/PE Fabric | J27: PP UL Fabric | K27: PP Woven Fabric | L27: PP UL Fabric With UV | M27: 6681 | N27: 935311 | O27: PP WOVEN FABRICS | P27: 934375.69 | Q27: 0 | R27: 0 | S27: 0 | T27: 0 | U27: 0 | V27: 0 | W27: 0 | X27: 0 | Y27: 0 | Z27: 24AAACO3087C1ZT | AA27: KGS | AB27: 39269080 | AC27: Rs. | AD27: 1 | AE27: 6681 | AF27: India
A28: 46241 | B28: Plastene India ltd - Unit 1-Sales | C28: Domestic Sales | D28: OEL/DTA/019/26-27 | E28: Sales - Waste & Scrape | F28: OEL/DTA/019/26-27 | G28: 46241 | H28: Other Scrap | I28: Wastage/Scrap | J28: Misc | K28: Other Scrap | L28: MS/Other Scrap | M28: 3040 | N28: 1520 | O28: OTHER SCRAPS | P28: 1560 | Q28: 0 | R28: 0 | S28: 0 | T28: 0 | U28: 0 | V28: 0 | W28: 0 | X28: 0 | Y28: 39.82 | Z28: 24AAACO3087C1ZT | AA28: KGS | AB28: 68114010 | AC28: Rs. | AD28: 1 | AE28: 3040 | AF28: India
A29: 46241 | B29: Plastene India ltd - Unit 1-Sales | C29: Deemed Export | D29: OEL1/DE/054/26-27 | E29: Sales - Interstate - Manufactured Goods | F29: OEL1/DE/054/26-27 | G29: 46241 | H29: SF | I29: PP/PE Fabric | J29: PP UL Fabric | K29: PP Woven Fabric | L29: PP UL Fabric With UV | M29: 4172 | N29: 584062 | O29: PP WOVEN FABRICS | P29: 583477.94 | Q29: 0 | R29: 0 | S29: 0 | T29: 0 | U29: 0 | V29: 0 | W29: 0 | X29: 0 | Y29: 0 | Z29: 24AAACO3087C1ZT | AA29: KGS | AB29: 39269080 | AC29: Rs. | AD29: 1 | AE29: 4172 | AF29: India
A30: 46272 | B30: Plastene India ltd - Unit 1-Sales | C30: Domestic Sales | D30: OEL/DTA/020/26-27 | E30: Sales - Interstate - Manufactured Goods | F30: OEL/DTA/020/26-27 | G30: 46272 | H30: SF | I30: RP Granules | J30: RP Granules | K30: Reprocessed Granules | L30: RP Granules | M30: 15000 | N30: 780000 | O30: RP GRANULES | P30: 779220 | Q30: 0 | R30: 0 | S30: 0 | T30: 0 | U30: 0 | V30: 0 | W30: 0 | X30: 0 | Y30: 0 | Z30: 24AAACO3087C1ZT | AA30: KGS | AB30: 39021000 | AC30: Rs. | AD30: 1 | AE30: 15000 | AF30: India
A31: 46272 | B31: Plastene India ltd - Unit 1-Sales | C31: Deemed Export | D31: OEL1/DE/055/26-27 | E31: Sales - Interstate - Manufactured Goods | F31: OEL1/DE/055/26-27 | G31: 46272 | H31: SF | I31: PP/PE Fabric | J31: PP UL Fabric | K31: PP Woven Fabric | L31: PP UL Fabric With UV | M31: 646 | N31: 90437 | O31: PP WOVEN FABRICS | P31: 90346.56 | Q31: 0 | R31: 0 | S31: 0 | T31: 0 | U31: 0 | V31: 0 | W31: 0 | X31: 0 | Y31: 0 | Z31: 24AAACO3087C1ZT | AA31: KGS | AB31: 39269080 | AC31: Rs. | AD31: 1 | AE31: 646 | AF31: India
A32: 46302 | B32: Gokul Overseas | C32: Deemed Export | D32: OEL/IZS/26-27/007 | E32: Sales - Kasez - Mfg - U/B | F32: OEL/IZS/26-27/007 | G32: 46302 | H32: FG | I32: FIBC Bags | J32: FIBC Bags | K32: Jambo Bag/Fibc Bag Mfr (Kg) | L32: FIBC Bags With UV With Liner | M32: 226 | N32: 69200 | O32: PP WOVEN BIG BAGS | P32: 69200 | Q32: 0 | R32: 0 | S32: 0 | T32: 0 | U32: 0 | V32: 0 | W32: 0 | X32: 0 | Y32: 0 | Z32: 24AACFG9539L2Z0 | AA32: KGS | AB32: 63053200 | AC32: Rs. | AD32: 1 | AE32: 226 | AF32: India
A33: 46302 | B33: Plastene India ltd - Unit 1-Sales | C33: Domestic Sales | D33: OEL/DTA/021/26-27 | E33: Sales - Interstate - Manufactured Goods | F33: OEL/DTA/021/26-27 | G33: 46302 | H33: SF | I33: RP Granules | J33: RP Granules | K33: Reprocessed Granules | L33: RP Granules | M33: 22500 | N33: 1170000 | O33: RP GRANULES | P33: 1168830 | Q33: 0 | R33: 0 | S33: 0 | T33: 0 | U33: 0 | V33: 0 | W33: 0 | X33: 0 | Y33: 0 | Z33: 24AAACO3087C1ZT | AA33: KGS | AB33: 39029080 | AC33: Rs. | AD33: 1 | AE33: 22500 | AF33: India
A34: 46302 | B34: Plastene India ltd - Unit 1-Sales | C34: Domestic Sales | D34: OEL/DTA/022/26-27 | E34: Sales - Interstate - Manufactured Goods | F34: OEL/DTA/022/26-27 | G34: 46302 | H34: SF | I34: RP Granules | J34: RP Granules | K34: Reprocessed Granules | L34: RP Granules | M34: 2250 | N34: 117000 | O34: RP GRANULES | P34: 116883 | Q34: 0 | R34: 0 | S34: 0 | T34: 0 | U34: 0 | V34: 0 | W34: 0 | X34: 0 | Y34: 0 | Z34: 24AAACO3087C1ZT | AA34: KGS | AB34: 39011090 | AC34: Rs. | AD34: 1 | AE34: 2250 | AF34: India
A35: 46333 | B35: Plastene India ltd - Unit 1-Sales | C35: Deemed Export | D35: OEL1/DE/056/26-27 | E35: Sales - Interstate - Manufactured Goods | F35: OEL1/DE/056/26-27 | G35: 46333 | H35: SF | I35: PP/PE Fabric | J35: PP UL Fabric | K35: PP Woven Fabric | L35: PP UL Fabric With UV | M35: 4518 | N35: 632501 | O35: PP WOVEN FABRICS | P35: 631868.5 | Q35: 0 | R35: 0 | S35: 0 | T35: 0 | U35: 0 | V35: 0 | W35: 0 | X35: 0 | Y35: 0 | Z35: 24AAACO3087C1ZT | AA35: KGS | AB35: 39269080 | AC35: Rs. | AD35: 1 | AE35: 4518 | AF35: India
A36: 14-07-2026 | B36: Plastene India ltd - Unit 1-Sales | C36: Deemed Export | D36: OEL1/DE/057/26-27 | E36: Sales - Interstate - Manufactured Goods | F36: OEL1/DE/057/26-27 | G36: 14-07-2026 | H36: SF | I36: PP/PE Fabric | J36: PP UL Fabric | K36: PP Woven Fabric | L36: PP UL Fabric With UV | M36: 5080 | N36: 711178 | O36: PP WOVEN FABRICS | P36: 710466.82 | Q36: 0 | R36: 0 | S36: 0 | T36: 0 | U36: 0 | V36: 0 | W36: 0 | X36: 0 | Y36: 0 | Z36: 24AAACO3087C1ZT | AA36: KGS | AB36: 39269080 | AC36: Rs. | AD36: 1 | AE36: 5080 | AF36: India
A37: 16-07-2026 | B37: Plastene India ltd - Unit 1-Sales | C37: Deemed Export | D37: OEL1/DE/058/26-27 | E37: Sales - Interstate - Manufactured Goods | F37: OEL1/DE/058/26-27 | G37: 16-07-2026 | H37: SF | I37: PP/PE Fabric | J37: PP UL Fabric | K37: PP Woven Fabric | L37: PP UL Fabric With UV | M37: 2434 | N37: 340750 | O37: PP WOVEN FABRICS | P37: 340409.25 | Q37: 0 | R37: 0 | S37: 0 | T37: 0 | U37: 0 | V37: 0 | W37: 0 | X37: 0 | Y37: 0 | Z37: 24AAACO3087C1ZT | AA37: KGS | AB37: 39269080 | AC37: Rs. | AD37: 1 | AE37: 2434 | AF37: India
A38: 17-07-2026 | B38: Plastene India ltd - Unit 1-Sales | C38: Deemed Export | D38: OEL1/DE/059/26-27 | E38: Sales - Interstate - Manufactured Goods | F38: OEL1/DE/059/26-27 | G38: 17-07-2026 | H38: SF | I38: PP/PE Fabric | J38: PP UL Fabric | K38: PP Woven Fabric | L38: PP UL Fabric With UV | M38: 5328 | N38: 745897 | O38: PP WOVEN FABRICS | P38: 745151.1 | Q38: 0 | R38: 0 | S38: 0 | T38: 0 | U38: 0 | V38: 0 | W38: 0 | X38: 0 | Y38: 0 | Z38: 24AAACO3087C1ZT | AA38: KGS | AB38: 39269080 | AC38: Rs. | AD38: 1 | AE38: 5328 | AF38: India
A39: 17-07-2026 | B39: Plastene India ltd - Unit 1-Sales | C39: Deemed Export | D39: OEL1/DE/060/26-27 | E39: Sales - Interstate - Manufactured Goods | F39: OEL1/DE/060/26-27 | G39: 17-07-2026 | H39: SF | I39: Webbing | J39: PP Webbing | K39: PP Webbing | L39: Webbing | M39: 553.4 | N39: 56447 | O39: PP WEBBING | P39: 56390.55 | Q39: 0 | R39: 0 | S39: 0 | T39: 0 | U39: 0 | V39: 0 | W39: 0 | X39: 0 | Y39: 0 | Z39: 24AAACO3087C1ZT | AA39: KGS | AB39: 39269080 | AC39: Rs. | AD39: 1 | AE39: 553.4 | AF39: India
A40: 18-07-2026 | B40: Plastene India ltd - Unit 1-Sales | C40: Deemed Export | D40: OEL/DTA/023/26-27 | E40: Sales - Interstate - Manufactured Goods | F40: OEL/DTA/023/26-27 | G40: 18-07-2026 | H40: SF | I40: RP Granules | J40: RP Granules | K40: Reprocessed Granules | L40: RP Granules | M40: 30000 | N40: 1560000 | O40: RP GRNULES | P40: 1558440 | Q40: 0 | R40: 0 | S40: 0 | T40: 0 | U40: 0 | V40: 0 | W40: 0 | X40: 0 | Y40: 0 | Z40: 24AAACO3087C1ZT | AA40: KGS | AB40: 39021000 | AC40: Rs. | AD40: 1 | AE40: 30000 | AF40: India
A41: 20-07-2026 | B41: Plastene India ltd - Unit 1-Sales | C41: Domestic Sales | D41: OEL/DTA/024/26-27 | E41: Sales - Waste & Scrape | F41: OEL/DTA/024/26-27 | G41: 20-07-2026 | H41: Other Scrap | I41: Wastage/Scrap | J41: Misc | K41: Other Scrap | L41: MS/Other Scrap | M41: 14.2 | N41: 7100 | O41: OTHER SCRAPS | P41: 7286 | Q41: 0 | R41: 0 | S41: 0 | T41: 0 | U41: 0 | V41: 0 | W41: 0 | X41: 0 | Y41: 185.99 | Z41: 24AAACO3087C1ZT | AA41: KGS | AB41: 68114010 | AC41: Rs. | AD41: 1 | AE41: 14.2 | AF41: India
A42: 20-07-2026 | B42: Plastene India ltd - Unit 1-Sales | C42: Deemed Export | D42: OEL1/DE/061/26-27 | E42: Sales - Interstate - Manufactured Goods | F42: OEL1/DE/061/26-27 | G42: 20-07-2026 | H42: SF | I42: PP/PE Fabric | J42: PP UL Fabric | K42: PP Woven Fabric | L42: PP UL Fabric With UV | M42: 4542 | N42: 635860 | O42: PP WOVEN FABRICS | P42: 635224.14 | Q42: 0 | R42: 0 | S42: 0 | T42: 0 | U42: 0 | V42: 0 | W42: 0 | X42: 0 | Y42: 0 | Z42: 24AAACO3087C1ZT | AA42: KGS | AB42: 39269080 | AC42: Rs. | AD42: 1 | AE42: 4542 | AF42: India
A43: 20-07-2026 | B43: Plastene India ltd - Unit 1-Sales | C43: Deemed Export | D43: OEL1/DE/062/26-27 | E43: Sales - Interstate - Manufactured Goods | F43: OEL1/DE/062/26-27 | G43: 20-07-2026 | H43: SF | I43: Webbing | J43: PP Webbing | K43: PP Webbing | L43: Webbing | M43: 519.5 | N43: 52989 | O43: PP WEBBING | P43: 52936.01 | Q43: 0 | R43: 0 | S43: 0 | T43: 0 | U43: 0 | V43: 0 | W43: 0 | X43: 0 | Y43: 0 | Z43: 24AAACO3087C1ZT | AA43: KGS | AB43: 39269080 | AC43: Rs. | AD43: 1 | AE43: 519.5 | AF43: India
A44: 22-07-2026 | B44: Plastene India ltd - Unit 1-Sales | C44: Deemed Export | D44: OEL1/DE/063/26-27 | E44: Sales - Interstate - Manufactured Goods | F44: OEL1/DE/063/26-27 | G44: 22-07-2026 | H44: SF | I44: PP/PE Fabric | J44: PP UL Fabric | K44: PP Woven Fabric | L44: PP UL Fabric With UV | M44: 7157 | N44: 1001981 | O44: PP WOVEN FABRICS | P44: 1000979 | Q44: 0 | R44: 0 | S44: 0 | T44: 0 | U44: 0 | V44: 0 | W44: 0 | X44: 0 | Y44: 0 | Z44: 24AAACO3087C1ZT | AA44: KGS | AB44: 39269080 | AC44: Rs. | AD44: 1 | AE44: 7157 | AF44: India
A45: 22-07-2026 | B45: Plastene India ltd - Unit 1-Sales | C45: Deemed Export | D45: OEL1/DE/064/26-27 | E45: Sales - Interstate - Manufactured Goods | F45: OEL1/DE/064/26-27 | G45: 22-07-2026 | H45: SF | I45: Webbing | J45: PP Webbing | K45: PP Webbing | L45: Webbing | M45: 494 | N45: 50388 | O45: PP WEBBING | P45: 50337.61 | Q45: 0 | R45: 0 | S45: 0 | T45: 0 | U45: 0 | V45: 0 | W45: 0 | X45: 0 | Y45: 0 | Z45: 24AAACO3087C1ZT | AA45: KGS | AB45: 39269080 | AC45: Rs. | AD45: 1 | AE45: 494 | AF45: India
A46: 23-07-2026 | B46: Plastene India ltd - Unit 1-Sales | C46: Deemed Export | D46: OEL1/DE/065/26-27 | E46: Sales - Interstate - Manufactured Goods | F46: OEL1/DE/065/26-27 | G46: 23-07-2026 | H46: SF | I46: PP/PE Fabric | J46: PP UL Fabric | K46: PP Woven Fabric | L46: PP UL Fabric With UV | M46: 3223 | N46: 451220 | O46: PP WOVEN FABRICS | P46: 450768.78 | Q46: 0 | R46: 0 | S46: 0 | T46: 0 | U46: 0 | V46: 0 | W46: 0 | X46: 0 | Y46: 0 | Z46: 24AAACO3087C1ZT | AA46: KGS | AB46: 39269080 | AC46: Rs. | AD46: 1 | AE46: 3223 | AF46: India
A47: 24-07-2026 | B47: OCCL Limited | C47: Deemed Export | D47: OEL/IZS/26-27/008 | E47: Sales - Kasez - Mfg - U/B | F47: OEL/IZS/26-27/008 | G47: 24-07-2026 | H47: FG | I47: FIBC Bags | J47: FIBC Bags | K47: Jambo Bag/Fibc Bag Mfr (Kg) | L47: FIBC Bags With UV With Liner | M47: 4300 | N47: 1102720 | O47: FIBC JUMBO BAG | P47: 1102720 | Q47: 0 | R47: 0 | S47: 0 | T47: 0 | U47: 0 | V47: 0 | W47: 0 | X47: 0 | Y47: 0 | Z47: 24AADCO7609P2ZY | AA47: KGS | AB47: 63053200 | AC47: Rs. | AD47: 1 | AE47: 4300 | AF47: India
... A53: 31-07-2026 | B53: Plastene India ltd - Unit 1-Sales | C53: Deemed Export | D53: OEL1/DE/069/26-27 | E53: Sales - Interstate - Manufactured Goods | F53: OEL1/DE/069/26-27 | G53: 31-07-2026 | H53: SF | I53: PP/PE Fabric | J53: PP UL Fabric | K53: PP Woven Fabric | L53: PP UL Fabric With UV | M53: 9851.4 | N53: 1379197 | O53: PP WOVEN FABRICS | P53: 1377817.8 | Q53: 0 | R53: 0 | S53: 0 | T53: 0 | U53: 0 | V53: 0 | W53: 0 | X53: 0 | Y53: 0 | Z53: 24AAACO3087C1ZT | AA53: KGS | AB53: 39269080 | AC53: Rs. | AD53: 1 | AE53: 9851.4 | AF53: India

Sheet Purchase
A1: Row Labels | B1: Sum of Acceptedqty | C1: Sum of Basic Amount
A2: PP Granules | B2: 182900 | C2: 21226637 | D2: =C2/B2 -> 116.05597
A3: PP MF Yarn Twisted | B3: 12102.53 | C3: 1466330 | D3: =C3/B3 -> 121.15896
A4: PP/HD Wastage/Scrap | B4: 10643 | C4: 106430 | D4: =C4/B4 -> 10
A5: MB Karnavati Polyplast Blue | B5: 925 | C5: 175875 | D5: =C5/B5 -> 190.13514
A6: PP Woven Fabric | B6: 3006.7 | C6: 485155 | D6: =C6/B6 -> 161.35797
A7: LDPE/LLDPE Bags/Liner | B7: 136 | C7: 36856 | D7: =C7/B7 -> 271
A8: LDPE Granuals | B8: 1000 | C8: 145000 | D8: =C8/B8 -> 145
A9: Grand Total | B9: 210713.23 | C9: 23642283
B27: CompanyName | C27: Date | D27: srno | E27: Itemcode | F27: Itemname | G27: Indentsubcode | H27: PoNO | I27: OrderQty | J27: Challanqty | K27: Unit | L27: Recdqty | M27: PendingQty | N27: Acceptedqty | O27: Vehicalno | P27: Partyname | Q27: Suppliername | R27: ChallanNo | S27: Challan Date | T27: category | U27: subcategory | V27: MRno | W27: Rate | X27: Amount | Y27: BillNo | Z27: Bill Date | AA27: ItemRemarks | AB27: Remarks | AC27: Note | AD27: Transportname | AE27: Lrnodate | AF27: Discamt | AG27: Discamt1 | AH27: ExciseAmount | AI27: EducessAmount | AJ27: HiEducessamount | AK27: InwardVatType | AL27: Vatamount | AM27: Addvatamount | AN27: Frieght | AO27: Pkgfwd | AP27: Otherchg | AQ27: Spdutyname | AR27: Spdutyamt | AS27: Additionalduty | AT27: Billamount | AU27: Deptt | AV27: GroupName | AW27: SubGroupName | AX27: Deptt Po Indent | AY27: LoginName | AZ27: servicetax | BA27: Basic Amount | BB27: GateInwardNo | BC27: GateInwardDate | BD27: VendorGST | BE27: MRN User | BF27: POUserName | BG27: CGSTPer | BH27: CGSTAmount | BI27: SGSTPer | BJ27: SGSTAmount | BK27: IGSTPer | BL27: IGSTAmount | BM27: RBIllmount | BN27: EWayNo | BO27: EWayDt | BP27: netwt
B28: Oswal Extrusion Limited | C28: 46060 | D28: OEL/26-27/SII00487 | E28: WIP00022 | F28: PP MF Yarn Twisted | H28: OEL/RAW/26-27/17 | I28: 6000 | J28: 6000 | K28: Kgs | L28: 6000 | M28: 0 | N28: 6000 | O28: GJ12BZ8686 | P28: Plastene India ltd - Unit 2-Purchase | Q28: Plastene India ltd - Unit 2-Purchase | R28: PIL2/E/79 | S28: 46029 | T28: RAW MATERIAL | U28: INDIGENOUS | V28: RM 13 | W28: 120.1 | X28: 120.1 | Y28: PIL2/E/79 | Z28: 46029 | AD28: PARTY SELF | AE28: - | AF28: 0 | AG28: 0 | AH28: 0 | AI28: 0 | AJ28: 0 | AK28: VAT | AL28: 0 | AM28: 0 | AN28: 0 | AO28: 0 | AP28: 0 | AR28: 0 | AS28: 0 | AT28: 720600 | AU28: SF | AV28: Yarn All | AW28: PP Yarn | AX28: RM | AY28: erp | AZ28: 0 | BA28: 720600 | BB28: 524 | BC28: 46060 | BD28: 24AAACO3087C1ZT | BE28: bharatd | BF28: bharatd | BG28: 0 | BH28: 0 | BI28: 0 | BJ28: 0 | BK28: 0 | BL28: 0 | BM28: 720600 | BN28: 682138252973 | BO28: 46204 | BP28: 0
B29: Oswal Extrusion Limited | C29: 46241 | D29: OEL/26-27/SII00519 | E29: FIB10766 | F29: PP Woven Fabric | G29: OEL/26-27/STR00097/01 | H29: OEL/RAW/26-27/10 | I29: 2000 | J29: 2000.1 | K29: Kgs | L29: 2000.1 | M29: -0.1 | N29: 2000.1 | O29: RJ47GA4382 | P29: Dynamic Wooltex | Q29: Dynamic Wooltex | R29: 13526 | S29: 46029 | T29: RAW MATERIAL | U29: INDIGENOUS | V29: RM 14 | W29: 150 | X29: 160.99945 | Y29: 13526 | Z29: 46029 | AD29: PARTY SELF | AE29: - | AF29: 0 | AG29: 0 | AH29: 0 | AI29: 0 | AJ29: 0 | AK29: VAT | AL29: 0 | AM29: 0 | AN29: 22000 | AO29: 0 | AP29: 0 | AR29: 0 | AS29: 0 | AT29: 322015 | AU29: RM | AV29: FIBC Accessories | AW29: FIBC Accessories | AX29: Consumables | AY29: erp | AZ29: 0 | BA29: 322015 | BB29: 555 | BC29: 46210 | BD29: 08ABFPB2251A1ZI | BE29: bharatd | BF29: shyam | BG29: 0 | BH29: 0 | BI29: 0 | BJ29: 0 | BK29: 0 | BL29: 0 | BM29: 322015 | BN29: 721647716182 | BO29: 46204 | BP29: 2000.1
B30: Oswal Extrusion Limited | C30: 14-07-2026 | D30: OEL/26-27/SII00554 | E30: RAW05065 | F30: MB Karnavati Polyplast Blue | H30: OEL/RAW/26-27/18 | I30: 50 | J30: 50 | K30: Kgs | L30: 50 | M30: 0 | N30: 50 | O30: GJ12BY1595 | P30: Plastene India ltd - Unit 1-Purchase | Q30: Plastene India ltd - Unit 1-Purchase | R30: PIL1/E/367 | S30: 46363 | T30: RAW MATERIAL | U30: INDIGENOUS | V30: RM 17 | W30: 216 | X30: 216 | Y30: PIL1/E/367 | Z30: 46363 | AD30: - | AE30: - | AF30: 0 | AG30: 0 | AH30: 0 | AI30: 0 | AJ30: 0 | AK30: VAT | AL30: 0 | AM30: 0 | AN30: 0 | AO30: 0 | AP30: 0 | AR30: 0 | AS30: 0 | AT30: 660474 | AU30: RM | AV30: Granules | AW30: Masterbatch | AX30: RM | AY30: erp | AZ30: 0 | BA30: 10800 | BB30: 591 | BC30: 13-07-2026 | BD30: 24AAACO3087C1ZT | BE30: bharatd | BF30: bharatd | BG30: 0 | BH30: 0 | BI30: 0 | BJ30: 0 | BK30: 0 | BL30: 0 | BM30: 660474 | BN30: 642143935223 | BO30: 46215 | BP30: 50
B31: Oswal Extrusion Limited | C31: 14-07-2026 | D31: OEL/26-27/SII00554 | E31: RAW05067 | F31: MB Karnavati Polyplast Blue | H31: OEL/RAW/26-27/18 | I31: 50 | J31: 50 | K31: Kgs | L31: 50 | M31: 0 | N31: 50 | O31: GJ12BY1595 | P31: Plastene India ltd - Unit 1-Purchase | Q31: Plastene India ltd - Unit 1-Purchase | R31: PIL1/E/367 | S31: 46363 | T31: RAW MATERIAL | U31: INDIGENOUS | V31: RM 17 | W31: 236 | X31: 236 | Y31: PIL1/E/367 | Z31: 46363 | AD31: - | AE31: - | AF31: 0 | AG31: 0 | AH31: 0 | AI31: 0 | AJ31: 0 | AK31: VAT | AL31: 0 | AM31: 0 | AN31: 0 | AO31: 0 | AP31: 0 | AR31: 0 | AS31: 0 | AT31: 660474 | AU31: RM | AV31: Granules | AW31: Masterbatch | AX31: RM | AY31: erp | AZ31: 0 | BA31: 11800 | BB31: 591 | BC31: 13-07-2026 | BD31: 24AAACO3087C1ZT | BE31: bharatd | BF31: bharatd | BG31: 0 | BH31: 0 | BI31: 0 | BJ31: 0 | BK31: 0 | BL31: 0 | BM31: 0 | BN31: 642143935223 | BO31: 46215 | BP31: 50
B32: Oswal Extrusion Limited | C32: 14-07-2026 | D32: OEL/26-27/SII00554 | E32: RAW05075 | F32: MB Karnavati Polyplast Blue | H32: OEL/RAW/26-27/18 | I32: 200 | J32: 200 | K32: Kgs | L32: 200 | M32: 0 | N32: 200 | O32: GJ12BY1595 | P32: Plastene India ltd - Unit 1-Purchase | Q32: Plastene India ltd - Unit 1-Purchase | R32: PIL1/E/367 | S32: 46363 | T32: RAW MATERIAL | U32: INDIGENOUS | V32: RM 17 | W32: 264 | X32: 264 | Y32: PIL1/E/367 | Z32: 46363 | AD32: - | AE32: - | AF32: 0 | AG32: 0 | AH32: 0 | AI32: 0 | AJ32: 0 | AK32: VAT | AL32: 0 | AM32: 0 | AN32: 0 | AO32: 0 | AP32: 0 | AR32: 0 | AS32: 0 | AT32: 660474 | AU32: RM | AV32: Granules | AW32: Masterbatch | AX32: RM | AY32: erp | AZ32: 0 | BA32: 52800 | BB32: 591 | BC32: 13-07-2026 | BD32: 24AAACO3087C1ZT | BE32: bharatd | BF32: bharatd | BG32: 0 | BH32: 0 | BI32: 0 | BJ32: 0 | BK32: 0 | BL32: 0 | BM32: 0 | BN32: 642143935223 | BO32: 46215 | BP32: 200
B33: Oswal Extrusion Limited | C33: 14-07-2026 | D33: OEL/26-27/SII00554 | E33: RAW06258 | F33: PP Granules | H33: OEL/RAW/26-27/18 | I33: 4000 | J33: 4000 | K33: Kgs | L33: 4000 | M33: 0 | N33: 4000 | O33: GJ12BY1595 | P33: Plastene India ltd - Unit 1-Purchase | Q33: Plastene India ltd - Unit 1-Purchase | R33: PIL1/E/367 | S33: 46363 | T33: RAW MATERIAL | U33: INDIGENOUS | V33: RM 17 | W33: 136.331 | X33: 136.331 | Y33: PIL1/E/367 | Z33: 46363 | AD33: - | AE33: - | AF33: 0 | AG33: 0 | AH33: 0 | AI33: 0 | AJ33: 0 | AK33: VAT | AL33: 0 | AM33: 0 | AN33: 0 | AO33: 0 | AP33: 0 | AR33: 0 | AS33: 0 | AT33: 660474 | AU33: RM | AV33: Granules | AW33: PP Granules | AX33: RM | AY33: mani | AZ33: 0 | BA33: 545324 | BB33: 591 | BC33: 13-07-2026 | BD33: 24AAACO3087C1ZT | BE33: bharatd | BF33: bharatd | BG33: 0 | BH33: 0 | BI33: 0 | BJ33: 0 | BK33: 0 | BL33: 0 | BM33: 0 | BN33: 642143935223 | BO33: 46215 | BP33: 4000
B34: Oswal Extrusion Limited | C34: 14-07-2026 | D34: OEL/26-27/SII00554 | E34: RAW06279 | F34: MB Karnavati Polyplast Blue | H34: OEL/RAW/26-27/18 | I34: 250 | J34: 250 | K34: Kgs | L34: 250 | M34: 0 | N34: 250 | O34: GJ12BY1595 | P34: Plastene India ltd - Unit 1-Purchase | Q34: Plastene India ltd - Unit 1-Purchase | R34: PIL1/E/367 | S34: 46363 | T34: RAW MATERIAL | U34: INDIGENOUS | V34: RM 17 | W34: 159 | X34: 159 | Y34: PIL1/E/367 | Z34: 46363 | AD34: - | AE34: - | AF34: 0 | AG34: 0 | AH34: 0 | AI34: 0 | AJ34: 0 | AK34: VAT | AL34: 0 | AM34: 0 | AN34: 0 | AO34: 0 | AP34: 0 | AR34: 0 | AS34: 0 | AT34: 660474 | AU34: RM | AV34: Granules | AW34: Masterbatch | AX34: RM | AZ34: 0 | BA34: 39750 | BB34: 591 | BC34: 13-07-2026 | BD34: 24AAACO3087C1ZT | BE34: bharatd | BF34: bharatd | BG34: 0 | BH34: 0 | BI34: 0 | BJ34: 0 | BK34: 0 | BL34: 0 | BM34: 0 | BN34: 642143935223 | BO34: 46215 | BP34: 250
B35: Oswal Extrusion Limited | C35: 14-07-2026 | D35: OEL/26-27/SII00555 | E35: RAW06223 | F35: PP Granules | H35: OEL/RAW/26-27/18 | I35: 14000 | J35: 14000 | K35: Kgs | L35: 14000 | M35: 0 | N35: 14000 | O35: GJ12BY1595 | P35: Plastene India ltd - Unit 1-Purchase | Q35: Plastene India ltd - Unit 1-Purchase | R35: PIL1/E/372 | S35: 46363 | T35: RAW MATERIAL | U35: INDIGENOUS | V35: RM 18 | W35: 115 | X35: 115 | Y35: PIL1/E/372 | Z35: 46363 | AD35: - | AE35: - | AF35: 0 | AG35: 0 | AH35: 0 | AI35: 0 | AJ35: 0 | AK35: VAT | AL35: 0 | AM35: 0 | AN35: 0 | AO35: 0 | AP35: 0 | AR35: 0 | AS35: 0 | AT35: 1610000 | AU35: RM | AV35: Granules | AW35: PP Granules | AX35: RM | AY35: mani | AZ35: 0 | BA35: 1610000 | BB35: 597 | BC35: 13-07-2026 | BD35: 24AAACO3087C1ZT | BE35: bharatd | BF35: bharatd | BG35: 0 | BH35: 0 | BI35: 0 | BJ35: 0 | BK35: 0 | BL35: 0 | BM35: 1610000 | BN35: 602144460805 | BO35: 46215 | BP35: 14000
B36: Oswal Extrusion Limited | C36: 15-07-2026 | D36: OEL/26-27/SII00558 | E36: RAW06348 | F36: PP Granules | H36: OEL/RAW/26-27/19 | I36: 15500 | J36: 15500 | K36: Kgs | L36: 15500 | M36: 0 | N36: 15500 | O36: GJ14Z0334 | P36: Plastene India ltd - Unit 1-Purchase | Q36: Plastene India ltd - Unit 1-Purchase | R36: PIL1/E/375 | S36: 14-07-2026 | T36: RAW MATERIAL | U36: INDIGENOUS | V36: RM 19 | W36: 82.8 | X36: 82.8 | Y36: PIL1/E/375 | Z36: 14-07-2026 | AD36: - | AE36: - | AF36: 0 | AG36: 0 | AH36: 0 | AI36: 0 | AJ36: 0 | AK36: VAT | AL36: 0 | AM36: 0 | AN36: 0 | AO36: 0 | AP36: 0 | AR36: 0 | AS36: 0 | AT36: 1896200 | AU36: RM | AV36: Granules | AW36: PP Granules | AX36: RM | AZ36: 0 | BA36: 1283400 | BB36: 599 | BC36: 14-07-2026 | BD36: 24AAACO3087C1ZT | BE36: bharatd | BF36: bharatd | BG36: 0 | BH36: 0 | BI36: 0 | BJ36: 0 | BK36: 0 | BL36: 0 | BM36: 1896200 | BN36: 672144908278 | BO36: 46217 | BP36: 15500
B37: Oswal Extrusion Limited | C37: 15-07-2026 | D37: OEL/26-27/SII00558 | E37: RAW06011 | F37: PP Granules | H37: OEL/RAW/26-27/19 | I37: 8000 | J37: 8000 | K37: Kgs | L37: 8000 | M37: 0 | N37: 8000 | O37: GJ14Z0334 | P37: Plastene India ltd - Unit 1-Purchase | Q37: Plastene India ltd - Unit 1-Purchase | R37: PIL1/E/375 | S37: 14-07-2026 | T37: RAW MATERIAL | U37: INDIGENOUS | V37: RM 19 | W37: 76.6 | X37: 76.6 | Y37: PIL1/E/375 | Z37: 14-07-2026 | AD37: - | AE37: - | AF37: 0 | AG37: 0 | AH37: 0 | AI37: 0 | AJ37: 0 | AK37: VAT | AL37: 0 | AM37: 0 | AN37: 0 | AO37: 0 | AP37: 0 | AR37: 0 | AS37: 0 | AT37: 1896200 | AU37: RM | AV37: Granules | AW37: PP Granules | AX37: RM | AY37: anil | AZ37: 0 | BA37: 612800 | BB37: 599 | BC37: 14-07-2026 | BD37: 24AAACO3087C1ZT | BE37: bharatd | BF37: bharatd | BG37: 0 | BH37: 0 | BI37: 0 | BJ37: 0 | BK37: 0 | BL37: 0 | BM37: 0 | BN37: 672144908278 | BO37: 46217 | BP37: 8000
B38: Oswal Extrusion Limited | C38: 15-07-2026 | D38: OEL/26-27/SII00560 | E38: FIB21881 | F38: PP Woven Fabric | G38: OEL/26-27/RWM00002/01 | H38: OEL/RAW/26-27/15 | I38: 1000 | J38: 1006.6 | K38: Kgs | L38: 1006.6 | M38: -6.6 | N38: 1006.6 | O38: GJ12BT4481 | P38: Dynamic Wooltex | Q38: Dynamic Wooltex | R38: 13552 | S38: 46272 | T38: RAW MATERIAL | U38: INDIGENOUS | V38: RM 20 | W38: 150 | X38: 162.07034 | Y38: 13552 | Z38: 46272 | AD38: PARTY SELF | AE38: 88/25293 | AF38: 0 | AG38: 0 | AH38: 0 | AI38: 0 | AJ38: 0 | AK38: VAT | AL38: 0 | AM38: 0 | AN38: 12150 | AO38: 0 | AP38: 0 | AR38: 0 | AS38: 0 | AT38: 163140 | AU38: RM | AV38: FIBC Accessories | AW38: FIBC Accessories | AX38: RM | AY38: erp | AZ38: 0 | BA38: 163140 | BB38: 593 | BC38: 13-07-2026 | BD38: 08ABFPB2251A1ZI | BE38: bharatd | BF38: shyam | BG38: 0 | BH38: 0 | BI38: 0 | BJ38: 0 | BK38: 0 | BL38: 0 | BM38: 163140 | BN38: 701649864777 | BO38: 46212 | BP38: 1006.6
B39: Oswal Extrusion Limited | C39: 18-07-2026 | D39: OEL/26-27/SII00582 | E39: RAW06398 | F39: LDPE Granuals | H39: OEL/RAW/26-27/20 | I39: 1000 | J39: 1000 | K39: Kgs | L39: 1000 | M39: 0 | N39: 1000 | O39: GJ09Z0572 | P39: Plastene India ltd - Unit 1-Purchase | Q39: Plastene India ltd - Unit 1-Purchase | R39: PIL1/E/385 | S39: 17-07-2026 | T39: RAW MATERIAL | U39: INDIGENOUS | V39: RM 21 | W39: 145 | X39: 145 | Y39: PIL1/E/385 | Z39: 17-07-2026 | AD39: - | AE39: - | AF39: 0 | AG39: 0 | AH39: 0 | AI39: 0 | AJ39: 0 | AK39: VAT | AL39: 0 | AM39: 0 | AN39: 0 | AO39: 0 | AP39: 0 | AR39: 0 | AS39: 0 | AT39: 145000 | AU39: RM | AV39: Granules | AW39: LDPE Granules | AX39: RM | AZ39: 0 | BA39: 145000 | BB39: 622 | BC39: 17-07-2026 | BD39: 24AAACO3087C1ZT | BE39: bharatd | BF39: bharatd | BG39: 0 | BH39: 0 | BI39: 0 | BJ39: 0 | BK39: 0 | BL39: 0 | BM39: 145000 | BN39: 682146825150 | BO39: 46220 | BP39: 1000
B40: Oswal Extrusion Limited | C40: 18-07-2026 | D40: OEL/26-27/SII00583 | E40: RAW06251 | F40: PP Granules | H40: OEL/26-27/IMP/2 | I40: 135000 | J40: 135000 | K40: Kgs | L40: 135000 | M40: 0 | N40: 135000 | O40: GJ14Z6310/ GJ39TA0541/ GJ14Z0613/ GJ39TA3007/ GJ14Z0406 | P40: HCP Enterprise Ltd-Purchase | Q40: HCP Enterprise Ltd-Purchase | R40: HCP/26-27/25 | S40: 30-06-2026 | T40: RAW MATERIAL | U40: IMPORT/HIGH SEA SALES | V40: RMIMP 2 | W40: 121.55 | X40: 121.55 | Y40: HCP/26-27/25 | Z40: 30-06-2026 | AD40: SELF | AE40: - | AF40: 0 | AG40: 0 | AH40: 0 | AI40: 0 | AJ40: 0 | AK40: VAT | AL40: 0 | AM40: 0 | AN40: 0 | AO40: 0 | AP40: 0 | AR40: 0 | AS40: 0 | AT40: 16409250 | AU40: RM | AV40: Granules | AW40: PP Granules | AX40: RM | AZ40: 0 | BA40: 16409250 | BB40: 620 | BC40: 17-07-2026 | BD40: 24AAACC7815N1ZI | BE40: bharatd | BG40: 0 | BH40: 0 | BI40: 0 | BJ40: 0 | BK40: 0 | BL40: 0 | BM40: 16409250 | BN40: - | BO40: 46220.432 | BP40: 135000
B41: Oswal Extrusion Limited | C41: 18-07-2026 | D41: OEL/26-27/SII00585 | E41: WIP00017 | F41: PP MF Yarn Twisted | H41: OEL/RAW/26-27/21 | I41: 1077.01 | J41: 1077.01 | K41: Kgs | L41: 1077.01 | M41: 0 | N41: 1077.01 | O41: GJ12CT6064 | P41: Plastene India ltd - Unit 2-Purchase | Q41: Plastene India ltd - Unit 2-Purchase | R41: PIL2/E/97 | S41: 18-07-2026 | T41: RAW MATERIAL | U41: INDIGENOUS | V41: RM 22 | W41: 132 | X41: 131.99995 | Y41: PIL2/E/97 | Z41: 18-07-2026 | AD41: PARTY SELF | AE41: - | AF41: 0 | AG41: 0 | AH41: 0 | AI41: 0 | AJ41: 0 | AK41: VAT | AL41: 0 | AM41: 0 | AN41: 0 | AO41: 0 | AP41: 0 | AR41: 0 | AS41: 0 | AT41: 745730 | AU41: SF | AV41: Yarn All | AW41: Polyester Yarn | AX41: RM | AY41: erp | AZ41: 0 | BA41: 142165.27 | BB41: 629 | BC41: 18-07-2026 | BD41: 24AAACO3087C1ZT | BE41: bharatd | BF41: bharatd | BG41: 0 | BH41: 0 | BI41: 0 | BJ41: 0 | BK41: 0 | BL41: 0 | BM41: 745730 | BN41: 692147548655 | BO41: 46221 | BP41: 1077.01
B42: Oswal Extrusion Limited | C42: 18-07-2026 | D42: OEL/26-27/SII00585 | E42: WIP00022 | F42: PP MF Yarn Twisted | H42: OEL/RAW/26-27/21 | I42: 5025.52 | J42: 5025.52 | K42: Kgs | L42: 5025.52 | M42: 0 | N42: 5025.52 | O42: GJ12CT6064 | P42: Plastene India ltd - Unit 2-Purchase | Q42: Plastene India ltd - Unit 2-Purchase | R42: PIL2/E/97 | S42: 18-07-2026 | T42: RAW MATERIAL | U42: INDIGENOUS | V42: RM 22 | W42: 120.1 | X42: 120.09996 | Y42: PIL2/E/97 | Z42: 18-07-2026 | AD42: PARTY SELF | AE42: - | AF42: 0 | AG42: 0 | AH42: 0 | AI42: 0 | AJ42: 0 | AK42: VAT | AL42: 0 | AM42: 0 | AN42: 0 | AO42: 0 | AP42: 0 | AR42: 0 | AS42: 0 | AT42: 745730 | AU42: SF | AV42: Yarn All | AW42: PP Yarn | AX42: RM | AY42: erp | AZ42: 0 | BA42: 603564.73 | BB42: 629 | BC42: 18-07-2026 | BD42: 24AAACO3087C1ZT | BE42: bharatd | BF42: bharatd | BG42: 0 | BH42: 0 | BI42: 0 | BJ42: 0 | BK42: 0 | BL42: 0 | BM42: 0 | BN42: 692147548655 | BO42: 46221 | BP42: 5025.52
B43: Oswal Extrusion Limited | C43: 22-07-2026 | D43: OEL/26-27/SII00598 | E43: RAW06279 | F43: MB Karnavati Polyplast Blue | H43: OEL/RAW/26-27/23 | I43: 275 | J43: 275 | K43: Kgs | L43: 275 | M43: 0 | N43: 275 | O43: GJ12BY1595 | P43: Plastene India ltd - Unit 1-Purchase | Q43: Plastene India ltd - Unit 1-Purchase | R43: PIL1/E/399 | S43: 21-07-2026 | T43: RAW MATERIAL | U43: INDIGENOUS | V43: RM 23 | W43: 155 | X43: 155 | Y43: PIL1/E/399 | Z43: 21-07-2026 | AD43: - | AF43: 0 | AG43: 0 | AH43: 0 | AI43: 0 | AJ43: 0 | AK43: VAT | AL43: 0 | AM43: 0 | AN43: 0 | AO43: 0 | AP43: 0 | AR43: 0 | AS43: 0 | AT43: 635725 | AU43: RM | AV43: Granules | AW43: Masterbatch | AX43: RM | AZ43: 0 | BA43: 42625 | BB43: 651 | BC43: 21-07-2026 | BD43: 24AAACO3087C1ZT | BE43: bharatd | BF43: bharatd | BG43: 0 | BH43: 0 | BI43: 0 | BJ43: 0 | BK43: 0 | BL43: 0 | BM43: 635725 | BN43: - | BO43: 46224 | BP43: 275
B44: Oswal Extrusion Limited | C44: 22-07-2026 | D44: OEL/26-27/SII00598 | E44: RAW05527 | F44: MB Karnavati Polyplast Blue | H44: OEL/RAW/26-27/23 | I44: 100 | J44: 100 | K44: Kgs | L44: 100 | M44: 0 | N44: 100 | O44: GJ12BY1595 | P44: Plastene India ltd - Unit 1-Purchase | Q44: Plastene India ltd - Unit 1-Purchase | R44: PIL1/E/399 | S44: 21-07-2026 | T44: RAW MATERIAL | U44: INDIGENOUS | V44: RM 23 | W44: 181 | X44: 181 | Y44: PIL1/E/399 | Z44: 21-07-2026 | AD44: - | AF44: 0 | AG44: 0 | AH44: 0 | AI44: 0 | AJ44: 0 | AK44: VAT | AL44: 0 | AM44: 0 | AN44: 0 | AO44: 0 | AP44: 0 | AR44: 0 | AS44: 0 | AT44: 635725 | AU44: RM | AV44: Granules | AW44: Masterbatch | AX44: RM | AY44: erp | AZ44: 0 | BA44: 18100 | BB44: 651 | BC44: 21-07-2026 | BD44: 24AAACO3087C1ZT | BE44: bharatd | BF44: bharatd | BG44: 0 | BH44: 0 | BI44: 0 | BJ44: 0 | BK44: 0 | BL44: 0 | BM44: 0 | BN44: - | BO44: 46224 | BP44: 100
B45: Oswal Extrusion Limited | C45: 22-07-2026 | D45: OEL/26-27/SII00598 | E45: RAW05187 | F45: PP Granules | H45: OEL/RAW/26-27/23 | I45: 5000 | J45: 5000 | K45: Kgs | L45: 5000 | M45: 0 | N45: 5000 | O45: GJ12BY1595 | P45: Plastene India ltd - Unit 1-Purchase | Q45: Plastene India ltd - Unit 1-Purchase | R45: PIL1/E/399 | S45: 21-07-2026 | T45: RAW MATERIAL | U45: INDIGENOUS | V45: RM 23 | W45: 115 | X45: 115 | Y45: PIL1/E/399 | Z45: 21-07-2026 | AD45: - | AF45: 0 | AG45: 0 | AH45: 0 | AI45: 0 | AJ45: 0 | AK45: VAT | AL45: 0 | AM45: 0 | AN45: 0 | AO45: 0 | AP45: 0 | AR45: 0 | AS45: 0 | AT45: 635725 | AU45: RM | AV45: Granules | AW45: PP Granules | AX45: RM | AY45: erp | AZ45: 0 | BA45: 575000 | BB45: 651 | BC45: 21-07-2026 | BD45: 24AAACO3087C1ZT | BE45: bharatd | BF45: bharatd | BG45: 0 | BH45: 0 | BI45: 0 | BJ45: 0 | BK45: 0 | BL45: 0 | BM45: 0 | BN45: - | BO45: 46224 | BP45: 5000
B46: Oswal Extrusion Limited | C46: 23-07-2026 | D46: OEL/26-27/SII00603 | E46: RAW05187 | F46: PP Granules | H46: OEL/RAW/26-27/24 | I46: 400 | J46: 400 | K46: Kgs | L46: 400 | M46: 0 | N46: 400 | O46: GJ12BY0479 | P46: Plastene India ltd - Unit 1-Purchase | Q46: Plastene India ltd - Unit 1-Purchase | R46: PIL1/E/405 | S46: 22-07-2026 | T46: RAW MATERIAL | U46: INDIGENOUS | V46: RM 24 | W46: 136.331 | X46: 136.33 | Y46: PIL1/E/405 | Z46: 22-07-2026 | AD46: - | AF46: 0 | AG46: 0 | AH46: 0 | AI46: 0 | AJ46: 0 | AK46: VAT | AL46: 0 | AM46: 0 | AN46: 0 | AO46: 0 | AP46: 0 | AR46: 0 | AS46: 0 | AT46: 54532 | AU46: RM | AV46: Granules | AW46: PP Granules | AX46: RM | AY46: erp | AZ46: 0 | BA46: 54532 | BB46: - | BC46: 22-07-2026 | BD46: 24AAACO3087C1ZT | BE46: bharatd | BF46: bharatd | BG46: 0 | BH46: 0 | BI46: 0 | BJ46: 0 | BK46: 0 | BL46: 0 | BM46: 54532 | BN46: - | BO46: 46225 | BP46: 400
B47: Oswal Extrusion Limited | C47: 24-07-2026 | D47: OEL/26-27/SII00605 | E47: RAW05187 | F47: PP Granules | H47: OEL/RAW/26-27/25 | I47: 1000 | J47: 1000 | K47: Kgs | L47: 1000 | M47: 0 | N47: 1000 | O47: GJ27T3559 | P47: Plastene India ltd - Unit 1-Purchase | Q47: Plastene India ltd - Unit 1-Purchase | R47: PIL1/E/408 | S47: 23-07-2026 | T47: RAW MATERIAL | U47: INDIGENOUS | V47: RM 25 | W47: 136.331 | X47: 136.331 | Y47: PIL1/E/408 | Z47: 23-07-2026 | AD47: - | AF47: 0 | AG47: 0 | AH47: 0 | AI47: 0 | AJ47: 0 | AK47: VAT | AL47: 0 | AM47: 0 | AN47: 0 | AO47: 0 | AP47: 0 | AR47: 0 | AS47: 0 | AT47: 136331 | AU47: RM | AV47: Granules | AW47: PP Granules | AX47: RM | AY47: erp | AZ47: 0 | BA47: 136331 | BB47: 661 | BC47: 23-07-2026 | BD47: 24AAACO3087C1ZT | BE47: bharatd | BF47: bharatd | BG47: 0 | BH47: 0 | BI47: 0 | BJ47: 0 | BK47: 0 | BL47: 0 | BM47: 136331 | BN47: - | BO47: 46226 | BP47: 1000
B48: Oswal Extrusion Limited | C48: 26-07-2026 | D48: OEL/26-27/SII00619 | E48: WIP00031 | F48: PP/HD Wastage/Scrap | H48: OEL/RAW/26-27/26 | I48: 10643 | J48: 10643 | K48: Kgs | L48: 10643 | M48: 0 | N48: 10643 | O48: GJ02Z4078 | P48: K.P. Woven Pvt Ltd - Unit 3 -Purchase | Q48: K.P. Woven Pvt Ltd - Unit 3 -Purchase | R48: KPW3/IZS/26-27/04 | S48: 25-07-2026 | T48: RAW MATERIAL | U48: INDIGENOUS | V48: RM 26 | W48: 10 | X48: 10 | Y48: KPW3/IZS/26-27/04 | Z48: 25-07-2026 | AD48: - | AF48: 0 | AG48: 0 | AH48: 0 | AI48: 0 | AJ48: 0 | AK48: VAT | AL48: 0 | AM48: 0 | AN48: 0 | AO48: 0 | AP48: 0 | AR48: 0 | AS48: 0 | AT48: 106430 | AU48: SF | AV48: Wastage/Scrap | AW48: Wastage/Scrap | AX48: RM | AY48: erp | AZ48: 0 | BA48: 106430 | BB48: 671 | BC48: 25-07-2026 | BD48: 24AAECK6307M2ZE | BE48: bharatd | BF48: bharatd | BG48: 0 | BH48: 0 | BI48: 0 | BJ48: 0 | BK48: 0 | BL48: 0 | BM48: 106430 | BN48: - | BO48: 46228 | BP48: 0
B49: Oswal Extrusion Limited | C49: 31-07-2026 | D49: OEL/26-27/SII00663 | E49: SMF00147 | F49: LDPE/LLDPE Bags/Liner | H49: OEL/RAW/26-27/27 | I49: 136 | J49: 136 | K49: Kgs | L49: 136 | M49: 0 | N49: 136 | O49: GJ09Z0572 | P49: Plastene Polyfilms Ltd-Purchase | Q49: Plastene Polyfilms Ltd-Purchase | R49: PPL/E/60 | S49: 25-07-2026 | T49: RAW MATERIAL | U49: INDIGENOUS | V49: RM 28 | W49: 271 | X49: 271 | Y49: PPL/E/60 | Z49: 25-07-2026 | AD49: - | AF49: 0 | AG49: 0 | AH49: 0 | AI49: 0 | AJ49: 0 | AK49: VAT | AL49: 0 | AM49: 0 | AN49: 0 | AO49: 0 | AP49: 0 | AR49: 0 | AS49: 0 | AT49: 36856 | AU49: SF | AV49: Liners | AW49: LDPE/LLDPE Bags | AX49: RM | AY49: erp | AZ49: 0 | BA49: 36856 | BB49: 668 | BC49: 25-08-2026 | BD49: 24AAFCP2956A1ZR | BE49: bharatd | BF49: bharatd | BG49: 0 | BH49: 0 | BI49: 0 | BJ49: 0 | BK49: 0 | BL49: 0 | BM49: 36856 | BN49: - | BO49: 46228 | BP49: 0

Sheet JOB issued
A1: Row Labels | B1: Sum of Quantity | C1: Sum of Amount
A2: Jambo Bag/Fibc Bag Mfr (Kg) | B2: 417716.34 | C2: 43947990 | D2: =C2/B2 -> 105.21013
A3: Scrap | B3: 10643 | C3: 0 | D3: =C3/B3 -> 0
A4: Grand Total | B4: 428359.34 | C4: 43947990
A21: Date | B21: Particular | C21: Voucher Type | D21: Voucher No | E21: Type | F21: Invoice No | G21: Invoice Date | H21: Main Grp | I21: Group Name | J21: Sub Grup | K21: sales Group Name | L21: Item Name | M21: Quantity | N21: Amount | O21: Item Desc | P21: Bill Amount | Q21: CGST Rate | R21: CGST Amt | S21: SGST Rate | T21: SGST Amt | U21: IGST Rate | V21: IGST Amt | W21: Freight GST | X21: Total GST | Y21: TCS | Z21: GST-IN | AA21: Unit | AB21: HSN Code | AC21: Currencty | AD21: Exc.Rate | AE21: Net Wt
A22: 46241 | B22: K.P. Woven Pvt Ltd - Unit 3 -Sales | C22: Job Invoice | D22: OEL1/D/23 | E22: Job Work Income | F22: OEL1/D/23 | G22: 46241 | H22: FG | I22: FIBC Bags | J22: FIBC Bags | K22: Jambo Bag/Fibc Bag Mfr (Kg) | L22: FIBC Bags With UV With Liner | M22: 1230 | N22: 114943.5 | O22: MANUFACTURER OF PP WOVEN BIG BAGS/SACKS | P22: 7832868 | Q22: 0 | R22: 0 | S22: 0 | T22: 0 | U22: 0 | V22: 0 | W22: 0 | X22: 0 | Y22: 0 | Z22: 24AAECK6307M2ZE | AA22: KGS | AB22: 998852 | AC22: Rs. | AD22: 1 | AE22: 1230 | AF22: India
A23: 46241 | B23: K.P. Woven Pvt Ltd - Unit 3 -Sales | C23: Job Invoice | D23: OEL1/D/23 | E23: Job Work Income | F23: OEL1/D/23 | G23: 46241 | H23: FG | I23: FIBC Bags | J23: FIBC Bags | K23: Jambo Bag/Fibc Bag Mfr (Kg) | L23: FIBC Bags With UV With Liner | M23: 4214 | N23: 393798.3 | O23: MANUFACTURER OF PP WOVEN BIG BAGS/SACKS | P23: 0 | Q23: 0 | R23: 0 | S23: 0 | T23: 0 | U23: 0 | V23: 0 | W23: 0 | X23: 0 | Y23: 0 | Z23: 24AAECK6307M2ZE | AA23: KGS | AB23: 998852 | AC23: Rs. | AD23: 1 | AE23: 4214 | AF23: India
A24: 46241 | B24: K.P. Woven Pvt Ltd - Unit 3 -Sales | C24: Job Invoice | D24: OEL1/D/23 | E24: Job Work Income | F24: OEL1/D/23 | G24: 46241 | H24: FG | I24: FIBC Bags | J24: FIBC Bags | K24: Jambo Bag/Fibc Bag Mfr (Kg) | L24: FIBC Bags With UV With Liner | M24: 1220 | N24: 114009 | O24: MANUFACTURER OF PP WOVEN BIG BAGS/SACKS | P24: 0 | Q24: 0 | R24: 0 | S24: 0 | T24: 0 | U24: 0 | V24: 0 | W24: 0 | X24: 0 | Y24: 0 | Z24: 24AAECK6307M2ZE | AA24: KGS | AB24: 998852 | AC24: Rs. | AD24: 1 | AE24: 1220 | AF24: India
A25: 46241 | B25: K.P. Woven Pvt Ltd - Unit 3 -Sales | C25: Job Invoice | D25: OEL1/D/23 | E25: Job Work Income | F25: OEL1/D/23 | G25: 46241 | H25: FG | I25: FIBC Bags | J25: FIBC Bags | K25: Jambo Bag/Fibc Bag Mfr (Kg) | L25: FIBC Bags With UV With Liner | M25: 977.9 | N25: 91384.76 | O25: MANUFACTURER OF PP WOVEN BIG BAGS/SACKS | P25: 0 | Q25: 0 | R25: 0 | S25: 0 | T25: 0 | U25: 0 | V25: 0 | W25: 0 | X25: 0 | Y25: 0 | Z25: 24AAECK6307M2ZE | AA25: KGS | AB25: 998852 | AC25: Rs. | AD25: 1 | AE25: 977.9 | AF25: India
A26: 46241 | B26: K.P. Woven Pvt Ltd - Unit 3 -Sales | C26: Job Invoice | D26: OEL1/D/23 | E26: Job Work Income | F26: OEL1/D/23 | G26: 46241 | H26: FG | I26: FIBC Bags | J26: FIBC Bags | K26: Jambo Bag/Fibc Bag Mfr (Kg) | L26: FIBC Bags With UV With Liner | M26: 937 | N26: 87562.65 | O26: MANUFACTURER OF PP WOVEN BIG BAGS/SACKS | P26: 0 | Q26: 0 | R26: 0 | S26: 0 | T26: 0 | U26: 0 | V26: 0 | W26: 0 | X26: 0 | Y26: 0 | Z26: 24AAECK6307M2ZE | AA26: KGS | AB26: 998852 | AC26: Rs. | AD26: 1 | AE26: 937 | AF26: India
A27: 46241 | B27: K.P. Woven Pvt Ltd - Unit 3 -Sales | C27: Job Invoice | D27: OEL1/D/23 | E27: Job Work Income | F27: OEL1/D/23 | G27: 46241 | H27: FG | I27: FIBC Bags | J27: FIBC Bags | K27: Jambo Bag/Fibc Bag Mfr (Kg) | L27: FIBC Bags With UV With Liner | M27: 6725.8 | N27: 628526.01 | O27: MANUFACTURER OF PP WOVEN BIG BAGS/SACKS | P27: 0 | Q27: 0 | R27: 0 | S27: 0 | T27: 0 | U27: 0 | V27: 0 | W27: 0 | X27: 0 | Y27: 0 | Z27: 24AAECK6307M2ZE | AA27: KGS | AB27: 998852 | AC27: Rs. | AD27: 1 | AE27: 6725.8 | AF27: India
A28: 46241 | B28: K.P. Woven Pvt Ltd - Unit 3 -Sales | C28: Job Invoice | D28: OEL1/D/23 | E28: Job Work Income | F28: OEL1/D/23 | G28: 46241 | H28: FG | I28: FIBC Bags | J28: FIBC Bags | K28: Jambo Bag/Fibc Bag Mfr (Kg) | L28: FIBC Bags With UV With Liner | M28: 1212 | N28: 113261.4 | O28: MANUFACTURER OF PP WOVEN BIG BAGS/SACKS | P28: 0 | Q28: 0 | R28: 0 | S28: 0 | T28: 0 | U28: 0 | V28: 0 | W28: 0 | X28: 0 | Y28: 0 | Z28: 24AAECK6307M2ZE | AA28: KGS | AB28: 998852 | AC28: Rs. | AD28: 1 | AE28: 1212 | AF28: India
A29: 46241 | B29: K.P. Woven Pvt Ltd - Unit 3 -Sales | C29: Job Invoice | D29: OEL1/D/23 | E29: Job Work Income | F29: OEL1/D/23 | G29: 46241 | H29: FG | I29: FIBC Bags | J29: FIBC Bags | K29: Jambo Bag/Fibc Bag Mfr (Kg) | L29: FIBC Bags With UV With Liner | M29: 2713 | N29: 253529.85 | O29: MANUFACTURER OF PP WOVEN BIG BAGS/SACKS | P29: 0 | Q29: 0 | R29: 0 | S29: 0 | T29: 0 | U29: 0 | V29: 0 | W29: 0 | X29: 0 | Y29: 0 | Z29: 24AAECK6307M2ZE | AA29: KGS | AB29: 998852 | AC29: Rs. | AD29: 1 | AE29: 2713 | AF29: India
A30: 46241 | B30: K.P. Woven Pvt Ltd - Unit 3 -Sales | C30: Job Invoice | D30: OEL1/D/23 | E30: Job Work Income | F30: OEL1/D/23 | G30: 46241 | H30: FG | I30: FIBC Bags | J30: FIBC Bags | K30: Jambo Bag/Fibc Bag Mfr (Kg) | L30: FIBC Bags With UV With Liner | M30: 535 | N30: 49995.75 | O30: MANUFACTURER OF PP WOVEN BIG BAGS/SACKS | P30: 0 | Q30: 0 | R30: 0 | S30: 0 | T30: 0 | U30: 0 | V30: 0 | W30: 0 | X30: 0 | Y30: 0 | Z30: 24AAECK6307M2ZE | AA30: KGS | AB30: 998852 | AC30: Rs. | AD30: 1 | AE30: 535 | AF30: India
A31: 46241 | B31: K.P. Woven Pvt Ltd - Unit 3 -Sales | C31: Job Invoice | D31: OEL1/D/23 | E31: Job Work Income | F31: OEL1/D/23 | G31: 46241 | H31: FG | I31: FIBC Bags | J31: FIBC Bags | K31: Jambo Bag/Fibc Bag Mfr (Kg) | L31: FIBC Bags With UV With Liner | M31: 1775 | N31: 165873.75 | O31: MANUFACTURER OF PP WOVEN BIG BAGS/SACKS | P31: 0 | Q31: 0 | R31: 0 | S31: 0 | T31: 0 | U31: 0 | V31: 0 | W31: 0 | X31: 0 | Y31: 0 | Z31: 24AAECK6307M2ZE | AA31: KGS | AB31: 998852 | AC31: Rs. | AD31: 1 | AE31: 1775 | AF31: India
A32: 46241 | B32: K.P. Woven Pvt Ltd - Unit 3 -Sales | C32: Job Invoice | D32: OEL1/D/23 | E32: Job Work Income | F32: OEL1/D/23 | G32: 46241 | H32: FG | I32: FIBC Bags | J32: FIBC Bags | K32: Jambo Bag/Fibc Bag Mfr (Kg) | L32: FIBC Bags With UV With Liner | M32: 6687.3 | N32: 624928.19 | O32: MANUFACTURER OF PP WOVEN BIG BAGS/SACKS | P32: 0 | Q32: 0 | R32: 0 | S32: 0 | T32: 0 | U32: 0 | V32: 0 | W32: 0 | X32: 0 | Y32: 0 | Z32: 24AAECK6307M2ZE | AA32: KGS | AB32: 998852 | AC32: Rs. | AD32: 1 | AE32: 6687.3 | AF32: India
A33: 46241 | B33: K.P. Woven Pvt Ltd - Unit 3 -Sales | C33: Job Invoice | D33: OEL1/D/23 | E33: Job Work Income | F33: OEL1/D/23 | G33: 46241 | H33: FG | I33: FIBC Bags | J33: FIBC Bags | K33: Jambo Bag/Fibc Bag Mfr (Kg) | L33: FIBC Bags With UV With Liner | M33: 9918 | N33: 926837.1 | O33: MANUFACTURER OF PP WOVEN BIG BAGS/SACKS | P33: 0 | Q33: 0 | R33: 0 | S33: 0 | T33: 0 | U33: 0 | V33: 0 | W33: 0 | X33: 0 | Y33: 0 | Z33: 24AAECK6307M2ZE | AA33: KGS | AB33: 998852 | AC33: Rs. | AD33: 1 | AE33: 9918 | AF33: India
... A39: 46241 | B39: K.P. Woven Pvt Ltd - Unit 3 -Sales | C39: Job Invoice | D39: OEL1/D/23 | E39: Job Work Income | F39: OEL1/D/23 | G39: 46241 | H39: FG | I39: FIBC Bags | J39: FIBC Bags | K39: Jambo Bag/Fibc Bag Mfr (Kg) | L39: FIBC Bags With UV With Liner | M39: 10123 | N39: 945994.35 | O39: MANUFACTURER OF PP WOVEN BIG BAGS/SACKS | P39: 0 | Q39: 0 | R39: 0 | S39: 0 | T39: 0 | U39: 0 | V39: 0 | W39: 0 | X39: 0 | Y39: 0 | Z39: 24AAECK6307M2ZE | AA39: KGS | AB39: 998852 | AC39: Rs. | AD39: 1 | AE39: 10123 | AF39: India
A40: 15-07-2026 | B40: K.P. Woven Pvt Ltd - Unit 3 -Sales | C40: Job Invoice | D40: OEL1/D/24 | E40: Job Work Income | F40: OEL1/D/24 | G40: 15-07-2026 | H40: FG | I40: FIBC Bags | J40: FIBC Bags | K40: Jambo Bag/Fibc Bag Mfr (Kg) | L40: FIBC Bags With UV With Liner | M40: 619.4 | N40: 56582.19 | O40: MANUFACTURER OF PP WOVEN BIG BAGS/SACKS | P40: 7693171.5 | Q40: 0 | R40: 0 | S40: 0 | T40: 0 | U40: 0 | V40: 0 | W40: 0 | X40: 0 | Y40: 0 | Z40: 24AAECK6307M2ZE | AA40: KGS | AB40: 998852 | AC40: Rs. | AD40: 1 | AE40: 619.4 | AF40: India
A41: 15-07-2026 | B41: K.P. Woven Pvt Ltd - Unit 3 -Sales | C41: Job Invoice | D41: OEL1/D/24 | E41: Job Work Income | F41: OEL1/D/24 | G41: 15-07-2026 | H41: FG | I41: FIBC Bags | J41: FIBC Bags | K41: Jambo Bag/Fibc Bag Mfr (Kg) | L41: FIBC Bags With UV With Liner | M41: 4788.99 | N41: 437474.24 | O41: MANUFACTURER OF PP WOVEN BIG BAGS/SACKS | P41: 0 | Q41: 0 | R41: 0 | S41: 0 | T41: 0 | U41: 0 | V41: 0 | W41: 0 | X41: 0 | Y41: 0 | Z41: 24AAECK6307M2ZE | AA41: KGS | AB41: 998852 | AC41: Rs. | AD41: 1 | AE41: 4788.99 | AF41: India
A42: 15-07-2026 | B42: K.P. Woven Pvt Ltd - Unit 3 -Sales | C42: Job Invoice | D42: OEL1/D/24 | E42: Job Work Income | F42: OEL1/D/24 | G42: 15-07-2026 | H42: FG | I42: FIBC Bags | J42: FIBC Bags | K42: Jambo Bag/Fibc Bag Mfr (Kg) | L42: FIBC Bags With UV With Liner | M42: 3283.25 | N42: 299924.89 | O42: MANUFACTURER OF PP WOVEN BIG BAGS/SACKS | P42: 0 | Q42: 0 | R42: 0 | S42: 0 | T42: 0 | U42: 0 | V42: 0 | W42: 0 | X42: 0 | Y42: 0 | Z42: 24AAECK6307M2ZE | AA42: KGS | AB42: 998852 | AC42: Rs. | AD42: 1 | AE42: 3283.25 | AF42: India
A43: 15-07-2026 | B43: K.P. Woven Pvt Ltd - Unit 3 -Sales | C43: Job Invoice | D43: OEL1/D/24 | E43: Job Work Income | F43: OEL1/D/24 | G43: 15-07-2026 | H43: FG | I43: FIBC Bags | J43: FIBC Bags | K43: Jambo Bag/Fibc Bag Mfr (Kg) | L43: FIBC Bags With UV With Liner | M43: 800 | N43: 73080 | O43: MANUFACTURER OF PP WOVEN BIG BAGS/SACKS | P43: 0 | Q43: 0 | R43: 0 | S43: 0 | T43: 0 | U43: 0 | V43: 0 | W43: 0 | X43: 0 | Y43: 0 | Z43: 24AAECK6307M2ZE | AA43: KGS | AB43: 998852 | AC43: Rs. | AD43: 1 | AE43: 800 | AF43: India
A44: 15-07-2026 | B44: K.P. Woven Pvt Ltd - Unit 3 -Sales | C44: Job Invoice | D44: OEL1/D/24 | E44: Job Work Income | F44: OEL1/D/24 | G44: 15-07-2026 | H44: FG | I44: FIBC Bags | J44: FIBC Bags | K44: Jambo Bag/Fibc Bag Mfr (Kg) | L44: FIBC Bags With UV With Liner | M44: 715 | N44: 65315.25 | O44: MANUFACTURER OF PP WOVEN BIG BAGS/SACKS | P44: 0 | Q44: 0 | R44: 0 | S44: 0 | T44: 0 | U44: 0 | V44: 0 | W44: 0 | X44: 0 | Y44: 0 | Z44: 24AAECK6307M2ZE | AA44: KGS | AB44: 998852 | AC44: Rs. | AD44: 1 | AE44: 715 | AF44: India
A45: 15-07-2026 | B45: K.P. Woven Pvt Ltd - Unit 3 -Sales | C45: Job Invoice | D45: OEL1/D/24 | E45: Job Work Income | F45: OEL1/D/24 | G45: 15-07-2026 | H45: FG | I45: FIBC Bags | J45: FIBC Bags | K45: Jambo Bag/Fibc Bag Mfr (Kg) | L45: FIBC Bags With UV With Liner | M45: 529 | N45: 48324.15 | O45: MANUFACTURER OF PP WOVEN BIG BAGS/SACKS | P45: 0 | Q45: 0 | R45: 0 | S45: 0 | T45: 0 | U45: 0 | V45: 0 | W45: 0 | X45: 0 | Y45: 0 | Z45: 24AAECK6307M2ZE | AA45: KGS | AB45: 998852 | AC45: Rs. | AD45: 1 | AE45: 529 | AF45: India
A46: 15-07-2026 | B46: K.P. Woven Pvt Ltd - Unit 3 -Sales | C46: Job Invoice | D46: OEL1/D/24 | E46: Job Work Income | F46: OEL1/D/24 | G46: 15-07-2026 | H46: FG | I46: FIBC Bags | J46: FIBC Bags | K46: Jambo Bag/Fibc Bag Mfr (Kg) | L46: FIBC Bags With UV With Liner | M46: 334.6 | N46: 30565.71 | O46: MANUFACTURER OF PP WOVEN BIG BAGS/SACKS | P46: 0 | Q46: 0 | R46: 0 | S46: 0 | T46: 0 | U46: 0 | V46: 0 | W46: 0 | X46: 0 | Y46: 0 | Z46: 24AAECK6307M2ZE | AA46: KGS | AB46: 998852 | AC46: Rs. | AD46: 1 | AE46: 334.6 | AF46: India
A47: 15-07-2026 | B47: K.P. Woven Pvt Ltd - Unit 3 -Sales | C47: Job Invoice | D47: OEL1/D/24 | E47: Job Work Income | F47: OEL1/D/24 | G47: 15-07-2026 | H47: FG | I47: FIBC Bags | J47: FIBC Bags | K47: Jambo Bag/Fibc Bag Mfr (Kg) | L47: FIBC Bags With UV With Liner | M47: 7562 | N47: 690788.7 | O47: MANUFACTURER OF PP WOVEN BIG BAGS/SACKS | P47: 0 | Q47: 0 | R47: 0 | S47: 0 | T47: 0 | U47: 0 | V47: 0 | W47: 0 | X47: 0 | Y47: 0 | Z47: 24AAECK6307M2ZE | AA47: KGS | AB47: 998852 | AC47: Rs. | AD47: 1 | AE47: 7562 | AF47: India
A48: 15-07-2026 | B48: K.P. Woven Pvt Ltd - Unit 3 -Sales | C48: Job Invoice | D48: OEL1/D/24 | E48: Job Work Income | F48: OEL1/D/24 | G48: 15-07-2026 | H48: FG | I48: FIBC Bags | J48: FIBC Bags | K48: Jambo Bag/Fibc Bag Mfr (Kg) | L48: FIBC Bags With UV With Liner | M48: 4709.9 | N48: 430249.37 | O48: MANUFACTURER OF PP WOVEN BIG BAGS/SACKS | P48: 0 | Q48: 0 | R48: 0 | S48: 0 | T48: 0 | U48: 0 | V48: 0 | W48: 0 | X48: 0 | Y48: 0 | Z48: 24AAECK6307M2ZE | AA48: KGS | AB48: 998852 | AC48: Rs. | AD48: 1 | AE48: 4709.9 | AF48: India
A49: 15-07-2026 | B49: K.P. Woven Pvt Ltd - Unit 3 -Sales | C49: Job Invoice | D49: OEL1/D/24 | E49: Job Work Income | F49: OEL1/D/24 | G49: 15-07-2026 | H49: FG | I49: FIBC Bags | J49: FIBC Bags | K49: Jambo Bag/Fibc Bag Mfr (Kg) | L49: FIBC Bags With UV With Liner | M49: 1100.8 | N49: 100558.08 | O49: MANUFACTURER OF PP WOVEN BIG BAGS/SACKS | P49: 0 | Q49: 0 | R49: 0 | S49: 0 | T49: 0 | U49: 0 | V49: 0 | W49: 0 | X49: 0 | Y49: 0 | Z49: 24AAECK6307M2ZE | AA49: KGS | AB49: 998852 | AC49: Rs. | AD49: 1 | AE49: 1100.8 | AF49: India
A50: 15-07-2026 | B50: K.P. Woven Pvt Ltd - Unit 3 -Sales | C50: Job Invoice | D50: OEL1/D/24 | E50: Job Work Income | F50: OEL1/D/24 | G50: 15-07-2026 | H50: FG | I50: FIBC Bags | J50: FIBC Bags | K50: Jambo Bag/Fibc Bag Mfr (Kg) | L50: FIBC Bags With UV With Liner | M50: 4003 | N50: 365674.05 | O50: MANUFACTURER OF PP WOVEN BIG BAGS/SACKS | P50: 0 | Q50: 0 | R50: 0 | S50: 0 | T50: 0 | U50: 0 | V50: 0 | W50: 0 | X50: 0 | Y50: 0 | Z50: 24AAECK6307M2ZE | AA50: KGS | AB50: 998852 | AC50: Rs. | AD50: 1 | AE50: 4003 | AF50: India
A51: 15-07-2026 | B51: K.P. Woven Pvt Ltd - Unit 3 -Sales | C51: Job Invoice | D51: OEL1/D/24 | E51: Job Work Income | F51: OEL1/D/24 | G51: 15-07-2026 | H51: FG | I51: FIBC Bags | J51: FIBC Bags | K51: Jambo Bag/Fibc Bag Mfr (Kg) | L51: FIBC Bags With UV With Liner | M51: 6986 | N51: 638171.1 | O51: MANUFACTURER OF PP WOVEN BIG BAGS/SACKS | P51: 0 | Q51: 0 | R51: 0 | S51: 0 | T51: 0 | U51: 0 | V51: 0 | W51: 0 | X51: 0 | Y51: 0 | Z51: 24AAECK6307M2ZE | AA51: KGS | AB51: 998852 | AC51: Rs. | AD51: 1 | AE51: 6986 | AF51: India
... A207: 31-07-2026 | B207: Plastene India ltd - Unit 1-Sales | C207: Job Invoice | D207: OEL1/D/30 | E207: Job Work Income | F207: OEL1/D/30 | G207: 31-07-2026 | H207: FG | I207: FIBC Bags | J207: FIBC Bags | K207: Jambo Bag/Fibc Bag Mfr (Kg) | L207: FIBC Bags With UV Without Liner | M207: 23518.3 | N207: 2936965.3 | O207: MANUFACTURER OF PP WOVEN BIG BAGS/SACKS | P207: 0 | Q207: 0 | R207: 0 | S207: 0 | T207: 0 | U207: 18 | V207: 528653.75 | W207: 0 | X207: 528653.75 | Y207: 0 | Z207: 24AAACO3087C1ZT | AA207: KGS | AB207: 998852 | AC207: Rs. | AD207: 1 | AE207: 23518.3 | AF207: India

Sheet Job Received
A1: Row Labels | B1: Sum of Acceptedqty
A2: LDPE/LLDPE Bags/Liner | B2: 36603.67
A3: PP Lam Fabric With UV | B3: 50112.1
A4: PP MF Yarn Twisted | B4: 17007.23
A5: PP Tapes | B5: 8814.4
A6: PP UL Fabric With UV | B6: 30749.3
A7: UV Arguvin FG 626 LD | B7: 3975
A8: Webbing | B8: 100
A9: MB Karnavati Polyplast Blue | B9: 150
A10: PP Granules | B10: 117000
A11: LDPE Sumitomo L705 | B11: 2000
A12: Grand Total | B12: 266511.7

Sheet Rece Chalan
B1: CompanyName | C1: Date | D1: srno | E1: Itemcode | F1: Itemname | G1: Indentsubcode | H1: PoNO | I1: OrderQty | J1: Challanqty | K1: Unit | L1: Recdqty | M1: PendingQty | N1: Acceptedqty | O1: Vehicalno | P1: Partyname | Q1: Suppliername | R1: ChallanNo | S1: Challan Date | T1: category | U1: subcategory | V1: MRno | W1: Rate | X1: Amount | Y1: BillNo | Z1: Bill Date | AA1: ItemRemarks | AB1: Remarks | AC1: Note | AD1: Transportname | AE1: Lrnodate | AF1: Discamt | AG1: Discamt1 | AH1: ExciseAmount | AI1: EducessAmount | AJ1: HiEducessamount | AK1: InwardVatType | AL1: Vatamount | AM1: Addvatamount | AN1: Frieght | AO1: Pkgfwd | AP1: Otherchg | AQ1: Spdutyname | AR1: Spdutyamt | AS1: Additionalduty | AT1: Billamount | AU1: Deptt | AV1: GroupName | AW1: SubGroupName | AX1: Deptt Po Indent | AY1: LoginName | AZ1: servicetax | BA1: Basic Amount | BB1: GateInwardNo | BC1: GateInwardDate | BD1: VendorGST | BE1: MRN User | BF1: POUserName | BG1: CGSTPer | BH1: CGSTAmount | BI1: SGSTPer | BJ1: SGSTAmount | BK1: IGSTPer | BL1: IGSTAmount | BM1: RBIllmount | BN1: EWayNo | BO1: EWayDt | BP1: netwt
B2: Oswal Extrusion Limited | C2: 46060 | D2: OEL/26-27/SII00482 | E2: WIP00013 | F2: LDPE/LLDPE Bags/Liner | G2: 3 | H2: No PO | I2: 0 | J2: 227 | K2: Kgs | L2: 227 | M2: 0 | N2: 227 | O2: GJ12BT4781, GJ12BY1595 | P2: K.P. Woven Pvt Ltd - Unit 3 -Purchase | Q2: K.P. Woven Pvt Ltd - Unit 3 -Purchase | R2: KPW/JW/072 | S2: 46029 | T2: JOB IN | U2: OTHER | V2: JBIN-OT 77 | W2: 173.99291 | X2: 0 | Y2: KPW/JW/072 | Z2: 46029 | AD2: by Truck | AE2: 46029 | AF2: 0 | AG2: 0 | AH2: 0 | AI2: 0 | AJ2: 0 | AK2: VAT | AL2: 0 | AM2: 0 | AN2: 0 | AO2: 0 | AP2: 0 | AR2: 0 | AS2: 0 | AT2: 0 | AU2: SF | AV2: Liners | AW2: LDPE/LLDPE Bags | AX2: RM | AY2: erp | AZ2: 0 | BA2: 0 | BB2: 522 | BC2: 46029 | BD2: 24AAECK6307M2ZE | BE2: bharatd | BG2: 0 | BH2: 0 | BI2: 0 | BJ2: 0 | BK2: 0 | BL2: 0 | BM2: 0 | BN2: - | BO2: 46204.483 | BP2: 227
B3: Oswal Extrusion Limited | C3: 46060 | D3: OEL/26-27/SII00482 | E3: WIP00015 | F3: PP MF Yarn Twisted | G3: 5 | H3: No PO | I3: 0 | J3: 256.3 | K3: Kgs | L3: 256.3 | M3: 0 | N3: 256.3 | O3: GJ12BT4781, GJ12BY1595 | P3: K.P. Woven Pvt Ltd - Unit 3 -Purchase | Q3: K.P. Woven Pvt Ltd - Unit 3 -Purchase | R3: KPW/JW/072 | S3: 46029 | T3: JOB IN | U3: OTHER | V3: JBIN-OT 77 | W3: 155.06591 | X3: 0 | Y3: KPW/JW/072 | Z3: 46029 | AD3: by Truck | AE3: 46029 | AF3: 0 | AG3: 0 | AH3: 0 | AI3: 0 | AJ3: 0 | AK3: VAT | AL3: 0 | AM3: 0 | AN3: 0 | AO3: 0 | AP3: 0 | AR3: 0 | AS3: 0 | AT3: 0 | AU3: SF | AV3: Yarn All | AW3: PP Yarn | AX3: RM | AY3: erp | AZ3: 0 | BA3: 0 | BB3: 522 | BC3: 46029 | BD3: 24AAECK6307M2ZE | BE3: bharatd | BG3: 0 | BH3: 0 | BI3: 0 | BJ3: 0 | BK3: 0 | BL3: 0 | BM3: 0 | BN3: - | BO3: 46204.483 | BP3: 256.3
B4: Oswal Extrusion Limited | C4: 46060 | D4: OEL/26-27/SII00482 | E4: WIP00025 | F4: PP Lam Fabric With UV | G4: 4 | H4: No PO | I4: 0 | J4: 595 | K4: Kgs | L4: 595 | M4: 0 | N4: 595 | O4: GJ12BT4781, GJ12BY1595 | P4: K.P. Woven Pvt Ltd - Unit 3 -Purchase | Q4: K.P. Woven Pvt Ltd - Unit 3 -Purchase | R4: KPW/JW/072 | S4: 46029 | T4: JOB IN | U4: OTHER | V4: JBIN-OT 77 | W4: 178.03007 | X4: 0 | Y4: KPW/JW/072 | Z4: 46029 | AD4: by Truck | AE4: 46029 | AF4: 0 | AG4: 0 | AH4: 0 | AI4: 0 | AJ4: 0 | AK4: VAT | AL4: 0 | AM4: 0 | AN4: 0 | AO4: 0 | AP4: 0 | AR4: 0 | AS4: 0 | AT4: 0 | AU4: SF | AV4: PP/PE Fabric | AW4: PP Lam Fabric | AX4: RM | AY4: erp | AZ4: 0 | BA4: 0 | BB4: 522 | BC4: 46029 | BD4: 24AAECK6307M2ZE | BE4: bharatd | BG4: 0 | BH4: 0 | BI4: 0 | BJ4: 0 | BK4: 0 | BL4: 0 | BM4: 0 | BN4: - | BO4: 46204.483 | BP4: 595
B5: Oswal Extrusion Limited | C5: 46060 | D5: OEL/26-27/SII00482 | E5: WIP00032 | F5: Webbing | G5: 1 | H5: No PO | I5: 0 | J5: 100 | K5: Kgs | L5: 100 | M5: 0 | N5: 100 | O5: GJ12BT4781, GJ12BY1595 | P5: K.P. Woven Pvt Ltd - Unit 3 -Purchase | Q5: K.P. Woven Pvt Ltd - Unit 3 -Purchase | R5: KPW/JW/072 | S5: 46029 | T5: JOB IN | U5: OTHER | V5: JBIN-OT 77 | W5: 158.4 | X5: 0 | Y5: KPW/JW/072 | Z5: 46029 | AD5: by Truck | AE5: 46029 | AF5: 0 | AG5: 0 | AH5: 0 | AI5: 0 | AJ5: 0 | AK5: VAT | AL5: 0 | AM5: 0 | AN5: 0 | AO5: 0 | AP5: 0 | AR5: 0 | AS5: 0 | AT5: 0 | AU5: SF | AV5: Webbing | AW5: PP Webbing | AX5: RM | AY5: erp | AZ5: 0 | BA5: 0 | BB5: 522 | BC5: 46029 | BD5: 24AAECK6307M2ZE | BE5: bharatd | BG5: 0 | BH5: 0 | BI5: 0 | BJ5: 0 | BK5: 0 | BL5: 0 | BM5: 0 | BN5: - | BO5: 46204.483 | BP5: 100
B6: Oswal Extrusion Limited | C6: 46060 | D6: OEL/26-27/SII00482 | E6: WIP00236 | F6: PP MF Yarn Twisted | G6: 2 | H6: No PO | I6: 0 | J6: 29.7 | K6: Kgs | L6: 29.7 | M6: 0 | N6: 29.7 | O6: GJ12BT4781, GJ12BY1595 | P6: K.P. Woven Pvt Ltd - Unit 3 -Purchase | Q6: K.P. Woven Pvt Ltd - Unit 3 -Purchase | R6: KPW/JW/072 | S6: 46029 | T6: JOB IN | U6: OTHER | V6: JBIN-OT 77 | W6: 155.06591 | X6: 0 | Y6: KPW/JW/072 | Z6: 46029 | AD6: by Truck | AE6: 46029 | AF6: 0 | AG6: 0 | AH6: 0 | AI6: 0 | AJ6: 0 | AK6: VAT | AL6: 0 | AM6: 0 | AN6: 0 | AO6: 0 | AP6: 0 | AR6: 0 | AS6: 0 | AT6: 0 | AU6: SF | AV6: Yarn All | AW6: PP Yarn | AX6: RM | AY6: erp | AZ6: 0 | BA6: 0 | BB6: 522 | BC6: 46029 | BD6: 24AAECK6307M2ZE | BE6: bharatd | BG6: 0 | BH6: 0 | BI6: 0 | BJ6: 0 | BK6: 0 | BL6: 0 | BM6: 0 | BN6: - | BO6: 46204.483 | BP6: 29.7
B7: Oswal Extrusion Limited | C7: 46088 | D7: OEL/26-27/SII00497 | E7: WIP00017 | F7: PP MF Yarn Twisted | G7: 2 | H7: No PO | I7: 0 | J7: 2651.1 | K7: Kgs | L7: 2651.1 | M7: 0 | N7: 2651.1 | O7: GJ16Z8614, GJ09Z0572 | P7: K.P. Woven Pvt Ltd - Unit 3 -Purchase | Q7: K.P. Woven Pvt Ltd - Unit 3 -Purchase | R7: KPW/JW/073 | S7: 46060 | T7: JOB IN | U7: OTHER | V7: JBIN-OT 78 | W7: 132 | X7: 0 | Y7: KPW/JW/073 | Z7: 46060 | AD7: by Truck | AE7: 46060 | AF7: 0 | AG7: 0 | AH7: 0 | AI7: 0 | AJ7: 0 | AK7: VAT | AL7: 0 | AM7: 0 | AN7: 0 | AO7: 0 | AP7: 0 | AR7: 0 | AS7: 0 | AT7: 0 | AU7: SF | AV7: Yarn All | AW7: Polyester Yarn | AX7: RM | AY7: erp | AZ7: 0 | BA7: 0 | BB7: 532 | BC7: 46060 | BD7: 24AAECK6307M2ZE | BE7: bharatd | BG7: 0 | BH7: 0 | BI7: 0 | BJ7: 0 | BK7: 0 | BL7: 0 | BM7: 0 | BN7: - | BO7: 46205.743 | BP7: 2651.1
B8: Oswal Extrusion Limited | C8: 46088 | D8: OEL/26-27/SII00497 | E8: RAW05951 | F8: PP Tapes | G8: 1 | H8: No PO | I8: 0 | J8: 1210 | K8: Kgs | L8: 1210 | M8: 0 | N8: 1210 | O8: GJ16Z8614, GJ09Z0572 | P8: K.P. Woven Pvt Ltd - Unit 3 -Purchase | Q8: K.P. Woven Pvt Ltd - Unit 3 -Purchase | R8: KPW/JW/073 | S8: 46060 | T8: JOB IN | U8: OTHER | V8: JBIN-OT 78 | W8: 137.50069 | X8: 0 | Y8: KPW/JW/073 | Z8: 46060 | AD8: by Truck | AE8: 46060 | AF8: 0 | AG8: 0 | AH8: 0 | AI8: 0 | AJ8: 0 | AK8: VAT | AL8: 0 | AM8: 0 | AN8: 0 | AO8: 0 | AP8: 0 | AR8: 0 | AS8: 0 | AT8: 0 | AU8: SF | AV8: Tape Stock | AW8: PP Tapes | AX8: RM | AY8: erp | AZ8: 0 | BA8: 0 | BB8: 532 | BC8: 46060 | BD8: 24AAECK6307M2ZE | BE8: bharatd | BG8: 0 | BH8: 0 | BI8: 0 | BJ8: 0 | BK8: 0 | BL8: 0 | BM8: 0 | BN8: - | BO8: 46205.743 | BP8: 1210
B9: Oswal Extrusion Limited | C9: 46180 | D9: OEL/26-27/SII00505 | E9: WIP00025 | F9: PP Lam Fabric With UV | G9: 4 | H9: No PO | I9: 0 | J9: 1207 | K9: Kgs | L9: 1207 | M9: 0 | N9: 1207 | O9: GJ12BV1841, GJ12BY0479 | P9: K.P. Woven Pvt Ltd - Unit 3 -Purchase | Q9: K.P. Woven Pvt Ltd - Unit 3 -Purchase | R9: KPW/JW/074 | S9: 46119 | T9: JOB IN | U9: OTHER | V9: JBIN-OT 79 | W9: 178.02922 | X9: 0 | Y9: KPW/JW/074 | Z9: 46119 | AD9: by Truck | AE9: 46149 | AF9: 0 | AG9: 0 | AH9: 0 | AI9: 0 | AJ9: 0 | AK9: VAT | AL9: 0 | AM9: 0 | AN9: 0 | AO9: 0 | AP9: 0 | AR9: 0 | AS9: 0 | AT9: 0 | AU9: SF | AV9: PP/PE Fabric | AW9: PP Lam Fabric | AX9: RM | AY9: erp | AZ9: 0 | BA9: 0 | BB9: 543 | BC9: 46119 | BD9: 24AAECK6307M2ZE | BE9: bharatd | BG9: 0 | BH9: 0 | BI9: 0 | BJ9: 0 | BK9: 0 | BL9: 0 | BM9: 0 | BN9: - | BO9: 46207.465 | BP9: 1207
B10: Oswal Extrusion Limited | C10: 46180 | D10: OEL/26-27/SII00505 | E10: RAW05130 | F10: PP Granules | G10: 3 | H10: No PO | I10: 0 | J10: 2000 | K10: Kgs | L10: 2000 | M10: 0 | N10: 2000 | O10: GJ12BV1841, GJ12BY0479 | P10: K.P. Woven Pvt Ltd - Unit 3 -Purchase | Q10: K.P. Woven Pvt Ltd - Unit 3 -Purchase | R10: KPW/JW/074 | S10: 46119 | T10: JOB IN | U10: OTHER | V10: JBIN-OT 79 | W10: 150 | X10: 0 | Y10: KPW/JW/074 | Z10: 46119 | AD10: by Truck | AE10: 46149 | AF10: 0 | AG10: 0 | AH10: 0 | AI10: 0 | AJ10: 0 | AK10: VAT | AL10: 0 | AM10: 0 | AN10: 0 | AO10: 0 | AP10: 0 | AR10: 0 | AS10: 0 | AT10: 0 | AU10: RM | AV10: Granules | AW10: PP Granules | AX10: RM | AY10: erp | AZ10: 0 | BA10: 0 | BB10: 543 | BC10: 46119 | BD10: 24AAECK6307M2ZE | BE10: bharatd | BG10: 0 | BH10: 0 | BI10: 0 | BJ10: 0 | BK10: 0 | BL10: 0 | BM10: 0 | BN10: - | BO10: 46207.465 | BP10: 2000
B11: Oswal Extrusion Limited | C11: 46180 | D11: OEL/26-27/SII00505 | E11: RAW05951 | F11: PP Tapes | G11: 2 | H11: No PO | I11: 0 | J11: 1480 | K11: Kgs | L11: 1480 | M11: 0 | N11: 1480 | O11: GJ12BV1841, GJ12BY0479 | P11: K.P. Woven Pvt Ltd - Unit 3 -Purchase | Q11: K.P. Woven Pvt Ltd - Unit 3 -Purchase | R11: KPW/JW/074 | S11: 46119 | T11: JOB IN | U11: OTHER | V11: JBIN-OT 79 | W11: 137.50048 | X11: 0 | Y11: KPW/JW/074 | Z11: 46119 | AD11: by Truck | AE11: 46149 | AF11: 0 | AG11: 0 | AH11: 0 | AI11: 0 | AJ11: 0 | AK11: VAT | AL11: 0 | AM11: 0 | AN11: 0 | AO11: 0 | AP11: 0 | AR11: 0 | AS11: 0 | AT11: 0 | AU11: SF | AV11: Tape Stock | AW11: PP Tapes | AX11: RM | AY11: erp | AZ11: 0 | BA11: 0 | BB11: 543 | BC11: 46119 | BD11: 24AAECK6307M2ZE | BE11: bharatd | BG11: 0 | BH11: 0 | BI11: 0 | BJ11: 0 | BK11: 0 | BL11: 0 | BM11: 0 | BN11: - | BO11: 46207.465 | BP11: 1480
B12: Oswal Extrusion Limited | C12: 46180 | D12: OEL/26-27/SII00505 | E12: WIP00023 | F12: PP UL Fabric With UV | G12: 1 | H12: No PO | I12: 0 | J12: 2836.5 | K12: Kgs | L12: 2836.5 | M12: 0 | N12: 2836.5 | O12: GJ12BV1841, GJ12BY0479 | P12: K.P. Woven Pvt Ltd - Unit 3 -Purchase | Q12: K.P. Woven Pvt Ltd - Unit 3 -Purchase | R12: KPW/JW/074 | S12: 46119 | T12: JOB IN | U12: OTHER | V12: JBIN-OT 79 | W12: 138.99592 | X12: 0 | Y12: KPW/JW/074 | Z12: 46119 | AD12: by Truck | AE12: 46149 | AF12: 0 | AG12: 0 | AH12: 0 | AI12: 0 | AJ12: 0 | AK12: VAT | AL12: 0 | AM12: 0 | AN12: 0 | AO12: 0 | AP12: 0 | AR12: 0 | AS12: 0 | AT12: 0 | AU12: SF | AV12: PP/PE Fabric | AW12: PP UL Fabric | AX12: RM | AY12: erp | AZ12: 0 | BA12: 0 | BB12: 543 | BC12: 46119 | BD12: 24AAECK6307M2ZE | BE12: bharatd | BG12: 0 | BH12: 0 | BI12: 0 | BJ12: 0 | BK12: 0 | BL12: 0 | BM12: 0 | BN12: - | BO12: 46207.465 | BP12: 2836.5
B13: Oswal Extrusion Limited | C13: 46210 | D13: OEL/26-27/SII00514 | E13: WIP00023 | F13: PP UL Fabric With UV | G13: 1 | H13: No PO | I13: 0 | J13: 2568 | K13: Kgs | L13: 2568 | M13: 0 | N13: 2568 | O13: GJ17XX0310 | P13: K.P. Woven Pvt Ltd - Unit 3 -Purchase | Q13: K.P. Woven Pvt Ltd - Unit 3 -Purchase | R13: KPW/JW/075 | S13: 46180 | T13: JOB IN | U13: OTHER | V13: JBIN-OT 80 | W13: 138.996 | X13: 0 | Y13: KPW/JW/075 | Z13: 46180 | AD13: by Truck | AE13: 46180 | AF13: 0 | AG13: 0 | AH13: 0 | AI13: 0 | AJ13: 0 | AK13: VAT | AL13: 0 | AM13: 0 | AN13: 0 | AO13: 0 | AP13: 0 | AR13: 0 | AS13: 0 | AT13: 0 | AU13: SF | AV13: PP/PE Fabric | AW13: PP UL Fabric | AX13: RM | AY13: erp | AZ13: 0 | BA13: 0 | BB13: 554 | BC13: 46180 | BD13: 24AAECK6307M2ZE | BE13: bharatd | BG13: 0 | BH13: 0 | BI13: 0 | BJ13: 0 | BK13: 0 | BL13: 0 | BM13: 0 | BN13: - | BO13: 46209.502 | BP13: 2568
B14: Oswal Extrusion Limited | C14: 46241 | D14: OEL/26-27/SII00522 | E14: WIP00013 | F14: LDPE/LLDPE Bags/Liner | G14: 1 | H14: No PO | I14: 0 | J14: 123.2 | K14: Kgs | L14: 123.2 | M14: 0 | N14: 123.2 | O14: GJ39T9710 | P14: K.P. Woven Pvt Ltd - Unit 3 -Purchase | Q14: K.P. Woven Pvt Ltd - Unit 3 -Purchase | R14: KPW/JW/076 | S14: 46210 | T14: JOB IN | U14: OTHER | V14: JBIN-OT 81 | W14: 173.9957 | X14: 0 | Y14: KPW/JW/076 | Z14: 46210 | AD14: by Truck | AE14: 46210 | AF14: 0 | AG14: 0 | AH14: 0 | AI14: 0 | AJ14: 0 | AK14: VAT | AL14: 0 | AM14: 0 | AN14: 0 | AO14: 0 | AP14: 0 | AR14: 0 | AS14: 0 | AT14: 0 | AU14: SF | AV14: Liners | AW14: LDPE/LLDPE Bags | AX14: RM | AY14: erp | AZ14: 0 | BA14: 0 | BB14: 562 | BC14: 46210 | BD14: 24AAECK6307M2ZE | BE14: bharatd | BG14: 0 | BH14: 0 | BI14: 0 | BJ14: 0 | BK14: 0 | BL14: 0 | BM14: 0 | BN14: - | BO14: 46210.411 | BP14: 123.2
B15: Oswal Extrusion Limited | C15: 46241 | D15: OEL/26-27/SII00524 | E15: RAW06279 | F15: MB Karnavati Polyplast Blue | G15: 2 | H15: No PO | I15: 0 | J15: 150 | K15: Kgs | L15: 150 | M15: 0 | N15: 150 | O15: GJ39T9710 | P15: Plastene India ltd - Unit 1-Purchase | Q15: Plastene India ltd - Unit 1-Purchase | R15: PIL1/JW/44 | S15: 46210 | T15: JOB IN | U15: OTHER | V15: JBIN-OT 82 | W15: 139 | X15: 0 | Y15: PIL1/JW/44 | Z15: 46210 | AD15: LAXMAN B BAKUTRA | AE15: 181 07-07-2026 | AF15: 0 | AG15: 0 | AH15: 0 | AI15: 0 | AJ15: 0 | AK15: VAT | AL15: 0 | AM15: 0 | AN15: 0 | AO15: 0 | AP15: 0 | AR15: 0 | AS15: 0 | AT15: 0 | AU15: RM | AV15: Granules | AW15: Masterbatch | AX15: RM | AZ15: 0 | BA15: 0 | BB15: 561 | BC15: 46210 | BD15: 24AAACO3087C1ZT | BE15: bharatd | BG15: 9 | BH15: 1876.5 | BI15: 9 | BJ15: 1876.5 | BK15: 0 | BL15: 0 | BM15: 0 | BN15: 652141134416 | BO15: 46210.683 | BP15: 150
B16: Oswal Extrusion Limited | C16: 46241 | D16: OEL/26-27/SII00524 | E16: RAW05130 | F16: PP Granules | G16: 1 | H16: No PO | I16: 0 | J16: 2000 | K16: Kgs | L16: 2000 | M16: 0 | N16: 2000 | O16: GJ39T9710 | P16: Plastene India ltd - Unit 1-Purchase | Q16: Plastene India ltd - Unit 1-Purchase | R16: PIL1/JW/44 | S16: 46210 | T16: JOB IN | U16: OTHER | V16: JBIN-OT 82 | W16: 115 | X16: 0 | Y16: PIL1/JW/44 | Z16: 46210 | AD16: LAXMAN B BAKUTRA | AE16: 181 07-07-2026 | AF16: 0 | AG16: 0 | AH16: 0 | AI16: 0 | AJ16: 0 | AK16: VAT | AL16: 0 | AM16: 0 | AN16: 0 | AO16: 0 | AP16: 0 | AR16: 0 | AS16: 0 | AT16: 0 | AU16: RM | AV16: Granules | AW16: PP Granules | AX16: RM | AY16: erp | AZ16: 0 | BA16: 0 | BB16: 561 | BC16: 46210 | BD16: 24AAACO3087C1ZT | BE16: bharatd | BG16: 9 | BH16: 20700 | BI16: 9 | BJ16: 20700 | BK16: 0 | BL16: 0 | BM16: 0 | BN16: 652141134416 | BO16: 46210.683 | BP16: 2000
B17: Oswal Extrusion Limited | C17: 46272 | D17: OEL/26-27/SII00525 | E17: RAW05124 | F17: LDPE/LLDPE Bags/Liner | G17: 2 | H17: No PO | I17: 0 | J17: 119 | K17: Kgs | L17: 119 | M17: 0 | N17: 119 | O17: GJ12BY0479 | P17: K.P. Woven Pvt Ltd - Unit 3 -Purchase | Q17: K.P. Woven Pvt Ltd - Unit 3 -Purchase | R17: KPW/JW/077 | S17: 46241 | T17: JOB IN | U17: OTHER | V17: JBIN-OT 83 | W17: 172.78 | X17: 0 | Y17: KPW/JW/077 | Z17: 46241 | AD17: by Truck | AE17: 46241 | AF17: 0 | AG17: 0 | AH17: 0 | AI17: 0 | AJ17: 0 | AK17: VAT | AL17: 0 | AM17: 0 | AN17: 0 | AO17: 0 | AP17: 0 | AR17: 0 | AS17: 0 | AT17: 0 | AU17: SF | AV17: Films All (SF) | AW17: PE Film | AX17: RM | AY17: erp | AZ17: 0 | BA17: 0 | BB17: 568 | BC17: 46241 | BD17: 24AAECK6307M2ZE | BE17: bharatd | BG17: 0 | BH17: 0 | BI17: 0 | BJ17: 0 | BK17: 0 | BL17: 0 | BM17: 0 | BN17: - | BO17: 46211.429 | BP17: 119
B18: Oswal Extrusion Limited | C18: 46272 | D18: OEL/26-27/SII00525 | E18: WIP00013 | F18: LDPE/LLDPE Bags/Liner | G18: 3 | H18: No PO | I18: 0 | J18: 446.3 | K18: Kgs | L18: 446.3 | M18: 0 | N18: 446.3 | O18: GJ12BY0479 | P18: K.P. Woven Pvt Ltd - Unit 3 -Purchase | Q18: K.P. Woven Pvt Ltd - Unit 3 -Purchase | R18: KPW/JW/077 | S18: 46241 | T18: JOB IN | U18: OTHER | V18: JBIN-OT 83 | W18: 173.99366 | X18: 0 | Y18: KPW/JW/077 | Z18: 46241 | AD18: by Truck | AE18: 46241 | AF18: 0 | AG18: 0 | AH18: 0 | AI18: 0 | AJ18: 0 | AK18: VAT | AL18: 0 | AM18: 0 | AN18: 0 | AO18: 0 | AP18: 0 | AR18: 0 | AS18: 0 | AT18: 0 | AU18: SF | AV18: Liners | AW18: LDPE/LLDPE Bags | AX18: RM | AY18: erp | AZ18: 0 | BA18: 0 | BB18: 568 | BC18: 46241 | BD18: 24AAECK6307M2ZE | BE18: bharatd | BG18: 0 | BH18: 0 | BI18: 0 | BJ18: 0 | BK18: 0 | BL18: 0 | BM18: 0 | BN18: - | BO18: 46211.429 | BP18: 446.3
B19: Oswal Extrusion Limited | C19: 46272 | D19: OEL/26-27/SII00525 | E19: WIP00025 | F19: PP Lam Fabric With UV | G19: 1 | H19: No PO | I19: 0 | J19: 2887 | K19: Kgs | L19: 2887 | M19: 0 | N19: 2887 | O19: GJ12BY0479 | P19: K.P. Woven Pvt Ltd - Unit 3 -Purchase | Q19: K.P. Woven Pvt Ltd - Unit 3 -Purchase | R19: KPW/JW/077 | S19: 46241 | T19: JOB IN | U19: OTHER | V19: JBIN-OT 83 | W19: 178.02927 | X19: 0 | Y19: KPW/JW/077 | Z19: 46241 | AD19: by Truck | AE19: 46241 | AF19: 0 | AG19: 0 | AH19: 0 | AI19: 0 | AJ19: 0 | AK19: VAT | AL19: 0 | AM19: 0 | AN19: 0 | AO19: 0 | AP19: 0 | AR19: 0 | AS19: 0 | AT19: 0 | AU19: SF | AV19: PP/PE Fabric | AW19: PP Lam Fabric | AX19: RM | AY19: erp | AZ19: 0 | BA19: 0 | BB19: 568 | BC19: 46241 | BD19: 24AAECK6307M2ZE | BE19: bharatd | BG19: 0 | BH19: 0 | BI19: 0 | BJ19: 0 | BK19: 0 | BL19: 0 | BM19: 0 | BN19: - | BO19: 46211.429 | BP19: 2887
B20: Oswal Extrusion Limited | C20: 46302 | D20: OEL/26-27/SII00528 | E20: WIP00023 | F20: PP UL Fabric With UV | G20: 2 | H20: No PO | I20: 0 | J20: 812.1 | K20: Kgs | L20: 812.1 | M20: 0 | N20: 812.1 | O20: GJ24X8795 | P20: K.P. Woven Pvt Ltd - Unit 3 -Purchase | Q20: K.P. Woven Pvt Ltd - Unit 3 -Purchase | R20: KPW/JW/078 | S20: 46272 | T20: JOB IN | U20: OTHER | V20: JBIN-OT 84 | W20: 138.99617 | X20: 0 | Y20: KPW/JW/078 | Z20: 46272 | AD20: by Truck | AE20: 46272 | AF20: 0 | AG20: 0 | AH20: 0 | AI20: 0 | AJ20: 0 | AK20: VAT | AL20: 0 | AM20: 0 | AN20: 0 | AO20: 0 | AP20: 0 | AR20: 0 | AS20: 0 | AT20: 0 | AU20: SF | AV20: PP/PE Fabric | AW20: PP UL Fabric | AX20: RM | AY20: erp | AZ20: 0 | BA20: 0 | BB20: 578 | BC20: 46272 | BD20: 24AAECK6307M2ZE | BE20: bharatd | BG20: 0 | BH20: 0 | BI20: 0 | BJ20: 0 | BK20: 0 | BL20: 0 | BM20: 0 | BN20: - | BO20: 46212.495 | BP20: 812.1
B21: Oswal Extrusion Limited | C21: 46302 | D21: OEL/26-27/SII00528 | E21: RAW05951 | F21: PP Tapes | G21: 1 | H21: No PO | I21: 0 | J21: 1761.1 | K21: Kgs | L21: 1761.1 | M21: 0 | N21: 1761.1 | O21: GJ24X8795 | P21: K.P. Woven Pvt Ltd - Unit 3 -Purchase | Q21: K.P. Woven Pvt Ltd - Unit 3 -Purchase | R21: KPW/JW/078 | S21: 46272 | T21: JOB IN | U21: OTHER | V21: JBIN-OT 84 | W21: 135.60855 | X21: 0 | Y21: KPW/JW/078 | Z21: 46272 | AD21: by Truck | AE21: 46272 | AF21: 0 | AG21: 0 | AH21: 0 | AI21: 0 | AJ21: 0 | AK21: VAT | AL21: 0 | AM21: 0 | AN21: 0 | AO21: 0 | AP21: 0 | AR21: 0 | AS21: 0 | AT21: 0 | AU21: SF | AV21: Tape Stock | AW21: PP Tapes | AX21: RM | AY21: erp | AZ21: 0 | BA21: 0 | BB21: 578 | BC21: 46272 | BD21: 24AAECK6307M2ZE | BE21: bharatd | BG21: 0 | BH21: 0 | BI21: 0 | BJ21: 0 | BK21: 0 | BL21: 0 | BM21: 0 | BN21: - | BO21: 46212.495 | BP21: 1761.1
B22: Oswal Extrusion Limited | C22: 46333 | D22: OEL/26-27/SII00530 | E22: WIP00025 | F22: PP Lam Fabric With UV | G22: 3 | H22: No PO | I22: 0 | J22: 2850 | K22: Kgs | L22: 2850 | M22: 0 | N22: 2850 | O22: GJ12BV1841, GJ12BY0479... | P22: K.P. Woven Pvt Ltd - Unit 3 -Purchase | Q22: K.P. Woven Pvt Ltd - Unit 3 -Purchase | R22: KPW/JW/079 | S22: 46302 | T22: JOB IN | U22: OTHER | V22: JBIN-OT 85 | W22: 172.82565 | X22: 0 | Y22: KPW/JW/079 | Z22: 46302 | AD22: by Truck | AE22: 46302 | AF22: 0 | AG22: 0 | AH22: 0 | AI22: 0 | AJ22: 0 | AK22: VAT | AL22: 0 | AM22: 0 | AN22: 0 | AO22: 0 | AP22: 0 | AR22: 0 | AS22: 0 | AT22: 0 | AU22: SF | AV22: PP/PE Fabric | AW22: PP Lam Fabric | AX22: RM | AY22: erp | AZ22: 0 | BA22: 0 | BB22: 584 | BC22: 46302 | BD22: 24AAECK6307M2ZE | BE22: bharatd | BG22: 0 | BH22: 0 | BI22: 0 | BJ22: 0 | BK22: 0 | BL22: 0 | BM22: 0 | BN22: - | BO22: 46213.512 | BP22: 2850
B23: Oswal Extrusion Limited | C23: 46333 | D23: OEL/26-27/SII00530 | E23: WIP00013 | F23: LDPE/LLDPE Bags/Liner | G23: 2 | H23: No PO | I23: 0 | J23: 4994 | K23: Kgs | L23: 4994 | M23: 0 | N23: 4994 | O23: GJ12BV1841, GJ12BY0479... | P23: K.P. Woven Pvt Ltd - Unit 3 -Purchase | Q23: K.P. Woven Pvt Ltd - Unit 3 -Purchase | R23: KPW/JW/079 | S23: 46302 | T23: JOB IN | U23: OTHER | V23: JBIN-OT 85 | W23: 174.19334 | X23: 0 | Y23: KPW/JW/079 | Z23: 46302 | AD23: by Truck | AE23: 46302 | AF23: 0 | AG23: 0 | AH23: 0 | AI23: 0 | AJ23: 0 | AK23: VAT | AL23: 0 | AM23: 0 | AN23: 0 | AO23: 0 | AP23: 0 | AR23: 0 | AS23: 0 | AT23: 0 | AU23: SF | AV23: Liners | AW23: LDPE/LLDPE Bags | AX23: RM | AY23: erp | AZ23: 0 | BA23: 0 | BB23: 584 | BC23: 46302 | BD23: 24AAECK6307M2ZE | BE23: bharatd | BG23: 0 | BH23: 0 | BI23: 0 | BJ23: 0 | BK23: 0 | BL23: 0 | BM23: 0 | BN23: - | BO23: 46213.512 | BP23: 4994
B24: Oswal Extrusion Limited | C24: 46333 | D24: OEL/26-27/SII00530 | E24: WIP00015 | F24: PP MF Yarn Twisted | G24: 4 | H24: No PO | I24: 0 | J24: 3300.6 | K24: Kgs | L24: 3300.6 | M24: 0 | N24: 3300.6 | O24: GJ12BV1841, GJ12BY0479... | P24: K.P. Woven Pvt Ltd - Unit 3 -Purchase | Q24: K.P. Woven Pvt Ltd - Unit 3 -Purchase | R24: KPW/JW/079 | S24: 46302 | T24: JOB IN | U24: OTHER | V24: JBIN-OT 85 | W24: 148.13232 | X24: 0 | Y24: KPW/JW/079 | Z24: 46302 | AD24: by Truck | AE24: 46302 | AF24: 0 | AG24: 0 | AH24: 0 | AI24: 0 | AJ24: 0 | AK24: VAT | AL24: 0 | AM24: 0 | AN24: 0 | AO24: 0 | AP24: 0 | AR24: 0 | AS24: 0 | AT24: 0 | AU24: SF | AV24: Yarn All | AW24: PP Yarn | AX24: RM | AY24: erp | AZ24: 0 | BA24: 0 | BB24: 584 | BC24: 46302 | BD24: 24AAECK6307M2ZE | BE24: bharatd | BG24: 0 | BH24: 0 | BI24: 0 | BJ24: 0 | BK24: 0 | BL24: 0 | BM24: 0 | BN24: - | BO24: 46213.512 | BP24: 3300.6
B25: Oswal Extrusion Limited | C25: 46333 | D25: OEL/26-27/SII00530 | E25: WIP00023 | F25: PP UL Fabric With UV | G25: 1 | H25: No PO | I25: 0 | J25: 2060 | K25: Kgs | L25: 2060 | M25: 0 | N25: 2060 | O25: GJ12BV1841, GJ12BY0479... | P25: K.P. Woven Pvt Ltd - Unit 3 -Purchase | Q25: K.P. Woven Pvt Ltd - Unit 3 -Purchase | R25: KPW/JW/079 | S25: 46302 | T25: JOB IN | U25: OTHER | V25: JBIN-OT 85 | W25: 138.996 | X25: 0 | Y25: KPW/JW/079 | Z25: 46302 | AD25: by Truck | AE25: 46302 | AF25: 0 | AG25: 0 | AH25: 0 | AI25: 0 | AJ25: 0 | AK25: VAT | AL25: 0 | AM25: 0 | AN25: 0 | AO25: 0 | AP25: 0 | AR25: 0 | AS25: 0 | AT25: 0 | AU25: SF | AV25: PP/PE Fabric | AW25: PP UL Fabric | AX25: RM | AY25: erp | AZ25: 0 | BA25: 0 | BB25: 584 | BC25: 46302 | BD25: 24AAECK6307M2ZE | BE25: bharatd | BG25: 0 | BH25: 0 | BI25: 0 | BJ25: 0 | BK25: 0 | BL25: 0 | BM25: 0 | BN25: - | BO25: 46213.512 | BP25: 2060
B26: Oswal Extrusion Limited | C26: 14-07-2026 | D26: OEL/26-27/SII00553 | E26: WIP00013 | F26: LDPE/LLDPE Bags/Liner | G26: 3 | H26: No PO | I26: 0 | J26: 4140.17 | K26: Kgs | L26: 4140.17 | M26: 0 | N26: =4140.17 -> 4140.17 | O26: GJ08AW4250, GJ12BY1595 | P26: K.P. Woven Pvt Ltd - Unit 3 -Purchase | Q26: K.P. Woven Pvt Ltd - Unit 3 -Purchase | R26: KPW/JW/081 | S26: 13-07-2026 | T26: JOB IN | U26: OTHER | V26: JBIN-OT 86 | W26: 174.50979 | X26: 0 | Y26: KPW/JW/081 | Z26: 13-07-2026 | AD26: by Truck | AE26: 13-07-2026 | AF26: 0 | AG26: 0 | AH26: 0 | AI26: 0 | AJ26: 0 | AK26: VAT | AL26: 0 | AM26: 0 | AN26: 0 | AO26: 0 | AP26: 0 | AR26: 0 | AS26: 0 | AT26: 0 | AU26: SF | AV26: Liners | AW26: LDPE/LLDPE Bags | AX26: RM | AY26: erp | AZ26: 0 | BA26: 0 | BB26: 596 | BC26: 13-07-2026 | BD26: 24AAECK6307M2ZE | BE26: bharatd | BG26: 0 | BH26: 0 | BI26: 0 | BJ26: 0 | BK26: 0 | BL26: 0 | BM26: 0 | BN26: - | BO26: 46216.651 | BP26: 4140.17
B27: Oswal Extrusion Limited | C27: 14-07-2026 | D27: OEL/26-27/SII00553 | E27: WIP00025 | F27: PP Lam Fabric With UV | G27: 2 | H27: No PO | I27: 0 | J27: 726 | K27: Kgs | L27: 726 | M27: 0 | N27: =726 -> 726 | O27: GJ08AW4250, GJ12BY1595 | P27: K.P. Woven Pvt Ltd - Unit 3 -Purchase | Q27: K.P. Woven Pvt Ltd - Unit 3 -Purchase | R27: KPW/JW/081 | S27: 13-07-2026 | T27: JOB IN | U27: OTHER | V27: JBIN-OT 86 | W27: 142.00796 | X27: 0 | Y27: KPW/JW/081 | Z27: 13-07-2026 | AD27: by Truck | AE27: 13-07-2026 | AF27: 0 | AG27: 0 | AH27: 0 | AI27: 0 | AJ27: 0 | AK27: VAT | AL27: 0 | AM27: 0 | AN27: 0 | AO27: 0 | AP27: 0 | AR27: 0 | AS27: 0 | AT27: 0 | AU27: SF | AV27: PP/PE Fabric | AW27: PP Lam Fabric | AX27: RM | AY27: erp | AZ27: 0 | BA27: 0 | BB27: 596 | BC27: 13-07-2026 | BD27: 24AAECK6307M2ZE | BE27: bharatd | BG27: 0 | BH27: 0 | BI27: 0 | BJ27: 0 | BK27: 0 | BL27: 0 | BM27: 0 | BN27: - | BO27: 46216.651 | BP27: 726
B28: Oswal Extrusion Limited | C28: 14-07-2026 | D28: OEL/26-27/SII00553 | E28: WIP00023 | F28: PP UL Fabric With UV | G28: 1 | H28: No PO | I28: 0 | J28: 1653 | K28: Kgs | L28: 1653 | M28: 0 | N28: 1653 | O28: GJ08AW4250, GJ12BY1595 | P28: K.P. Woven Pvt Ltd - Unit 3 -Purchase | Q28: K.P. Woven Pvt Ltd - Unit 3 -Purchase | R28: KPW/JW/081 | S28: 13-07-2026 | T28: JOB IN | U28: OTHER | V28: JBIN-OT 86 | W28: 102.85 | X28: 0 | Y28: KPW/JW/081 | Z28: 13-07-2026 | AD28: by Truck | AE28: 13-07-2026 | AF28: 0 | AG28: 0 | AH28: 0 | AI28: 0 | AJ28: 0 | AK28: VAT | AL28: 0 | AM28: 0 | AN28: 0 | AO28: 0 | AP28: 0 | AR28: 0 | AS28: 0 | AT28: 0 | AU28: SF | AV28: PP/PE Fabric | AW28: PP UL Fabric | AX28: RM | AY28: erp | AZ28: 0 | BA28: 0 | BB28: 596 | BC28: 13-07-2026 | BD28: 24AAECK6307M2ZE | BE28: bharatd | BG28: 0 | BH28: 0 | BI28: 0 | BJ28: 0 | BK28: 0 | BL28: 0 | BM28: 0 | BN28: - | BO28: 46216.651 | BP28: 1653
B29: Oswal Extrusion Limited | C29: 14-07-2026 | D29: OEL/26-27/SII00556 | E29: WIP00023 | F29: PP UL Fabric With UV | G29: 1 | H29: No PO | I29: 0 | J29: 178 | K29: Kgs | L29: 178 | M29: 0 | N29: =178 -> 178 | O29: GJ12BY1595 | P29: K.P. Woven Pvt Ltd - Unit 3 -Purchase | Q29: K.P. Woven Pvt Ltd - Unit 3 -Purchase | R29: KPW/JW/080 | S29: 46333 | T29: JOB IN | U29: OTHER | V29: JBIN-OT 87 | W29: 103.09753 | X29: 0 | Y29: KPW/JW/080 | Z29: 46333 | AD29: by Truck | AE29: 46333 | AF29: 0 | AG29: 0 | AH29: 0 | AI29: 0 | AJ29: 0 | AK29: VAT | AL29: 0 | AM29: 0 | AN29: 0 | AO29: 0 | AP29: 0 | AR29: 0 | AS29: 0 | AT29: 0 | AU29: SF | AV29: PP/PE Fabric | AW29: PP UL Fabric | AX29: RM | AY29: erp | AZ29: 0 | BA29: 0 | BB29: 589 | BC29: 46333 | BD29: 24AAECK6307M2ZE | BE29: bharatd | BG29: 0 | BH29: 0 | BI29: 0 | BJ29: 0 | BK29: 0 | BL29: 0 | BM29: 0 | BN29: - | BO29: 46214.685 | BP29: 178
B30: Oswal Extrusion Limited | C30: 14-07-2026 | D30: OEL/26-27/SII00556 | E30: WIP00025 | F30: PP Lam Fabric With UV | G30: 2 | H30: No PO | I30: 0 | J30: 285 | K30: Kgs | L30: 285 | M30: 0 | N30: =285 -> 285 | O30: GJ12BY1595 | P30: K.P. Woven Pvt Ltd - Unit 3 -Purchase | Q30: K.P. Woven Pvt Ltd - Unit 3 -Purchase | R30: KPW/JW/080 | S30: 46333 | T30: JOB IN | U30: OTHER | V30: JBIN-OT 87 | W30: 148.47 | X30: 0 | Y30: KPW/JW/080 | Z30: 46333 | AD30: by Truck | AE30: 46333 | AF30: 0 | AG30: 0 | AH30: 0 | AI30: 0 | AJ30: 0 | AK30: VAT | AL30: 0 | AM30: 0 | AN30: 0 | AO30: 0 | AP30: 0 | AR30: 0 | AS30: 0 | AT30: 0 | AU30: SF | AV30: PP/PE Fabric | AW30: PP Lam Fabric | AX30: RM | AY30: erp | AZ30: 0 | BA30: 0 | BB30: 589 | BC30: 46333 | BD30: 24AAECK6307M2ZE | BE30: bharatd | BG30: 0 | BH30: 0 | BI30: 0 | BJ30: 0 | BK30: 0 | BL30: 0 | BM30: 0 | BN30: - | BO30: 46214.685 | BP30: 285
B31: Oswal Extrusion Limited | C31: 14-07-2026 | D31: OEL/26-27/SII00556 | E31: SMF00240 | F31: PP MF Yarn Twisted | G31: 3 | H31: No PO | I31: 0 | J31: 118.3 | K31: Kgs | L31: 118.3 | M31: 0 | N31: 118.3 | O31: GJ12BY1595 | P31: K.P. Woven Pvt Ltd - Unit 3 -Purchase | Q31: K.P. Woven Pvt Ltd - Unit 3 -Purchase | R31: KPW/JW/080 | S31: 46333 | T31: JOB IN | U31: OTHER | V31: JBIN-OT 87 | W31: 160 | X31: 0 | Y31: KPW/JW/080 | Z31: 46333 | AD31: by Truck | AE31: 46333 | AF31: 0 | AG31: 0 | AH31: 0 | AI31: 0 | AJ31: 0 | AK31: VAT | AL31: 0 | AM31: 0 | AN31: 0 | AO31: 0 | AP31: 0 | AR31: 0 | AS31: 0 | AT31: 0 | AU31: SF | AV31: Yarn All | AW31: PP Yarn | AX31: RM | AY31: erp | AZ31: 0 | BA31: 0 | BB31: 589 | BC31: 46333 | BD31: 24AAECK6307M2ZE | BE31: bharatd | BG31: 0 | BH31: 0 | BI31: 0 | BJ31: 0 | BK31: 0 | BL31: 0 | BM31: 0 | BN31: - | BO31: 46214.685 | BP31: 118.3
B32: Oswal Extrusion Limited | C32: 15-07-2026 | D32: OEL/26-27/SII00559 | E32: WIP00023 | F32: PP UL Fabric With UV | G32: 1 | H32: No PO | I32: 0 | J32: 2063 | K32: Kgs | L32: 2063 | M32: 0 | N32: 2063 | O32: GJ01LT7680, GJ12BY0479 | P32: K.P. Woven Pvt Ltd - Unit 3 -Purchase | Q32: K.P. Woven Pvt Ltd - Unit 3 -Purchase | R32: KPW/JW/082 | S32: 14-07-2026 | T32: JOB IN | U32: OTHER | V32: JBIN-OT 88 | W32: 138.99623 | X32: 0 | Y32: KPW/JW/082 | Z32: 14-07-2026 | AD32: by Truck | AE32: 14-07-2026 | AF32: 0 | AG32: 0 | AH32: 0 | AI32: 0 | AJ32: 0 | AK32: VAT | AL32: 0 | AM32: 0 | AN32: 0 | AO32: 0 | AP32: 0 | AR32: 0 | AS32: 0 | AT32: 0 | AU32: SF | AV32: PP/PE Fabric | AW32: PP UL Fabric | AX32: RM | AY32: erp | AZ32: 0 | BA32: 0 | BB32: 601 | BC32: 14-07-2026 | BD32: 24AAECK6307M2ZE | BE32: bharatd | BG32: 0 | BH32: 0 | BI32: 0 | BJ32: 0 | BK32: 0 | BL32: 0 | BM32: 0 | BN32: - | BO32: 46217.621 | BP32: 2063
B33: Oswal Extrusion Limited | C33: 15-07-2026 | D33: OEL/26-27/SII00559 | E33: WIP00025 | F33: PP Lam Fabric With UV | G33: 2 | H33: No PO | I33: 0 | J33: 1614 | K33: Kgs | L33: 1614 | M33: 0 | N33: =1614 -> 1614 | O33: GJ01LT7680, GJ12BY0479 | P33: K.P. Woven Pvt Ltd - Unit 3 -Purchase | Q33: K.P. Woven Pvt Ltd - Unit 3 -Purchase | R33: KPW/JW/082 | S33: 14-07-2026 | T33: JOB IN | U33: OTHER | V33: JBIN-OT 88 | W33: 142.00761 | X33: 0 | Y33: KPW/JW/082 | Z33: 14-07-2026 | AD33: by Truck | AE33: 14-07-2026 | AF33: 0 | AG33: 0 | AH33: 0 | AI33: 0 | AJ33: 0 | AK33: VAT | AL33: 0 | AM33: 0 | AN33: 0 | AO33: 0 | AP33: 0 | AR33: 0 | AS33: 0 | AT33: 0 | AU33: SF | AV33: PP/PE Fabric | AW33: PP Lam Fabric | AX33: RM | AY33: erp | AZ33: 0 | BA33: 0 | BB33: 601 | BC33: 14-07-2026 | BD33: 24AAECK6307M2ZE | BE33: bharatd | BG33: 0 | BH33: 0 | BI33: 0 | BJ33: 0 | BK33: 0 | BL33: 0 | BM33: 0 | BN33: - | BO33: 46217.621 | BP33: 1614
B34: Oswal Extrusion Limited | C34: 16-07-2026 | D34: OEL/26-27/SII00573 | E34: WIP00022 | F34: PP MF Yarn Twisted | G34: 1 | H34: No PO | I34: 0 | J34: 1963 | K34: Kgs | L34: 1963 | M34: 0 | N34: 1963 | O34: GJ09Z0572 | P34: K.P. Woven Pvt Ltd - Unit 3 -Purchase | Q34: K.P. Woven Pvt Ltd - Unit 3 -Purchase | R34: KPW/JW/083 | S34: 15-07-2026 | T34: JOB IN | U34: OTHER | V34: JBIN-OT 89 | W34: 177 | X34: 0 | Y34: KPW/JW/083 | Z34: 15-07-2026 | AD34: by Truck | AE34: 15-07-2026 | AF34: 0 | AG34: 0 | AH34: 0 | AI34: 0 | AJ34: 0 | AK34: VAT | AL34: 0 | AM34: 0 | AN34: 0 | AO34: 0 | AP34: 0 | AR34: 0 | AS34: 0 | AT34: 0 | AU34: SF | AV34: Yarn All | AW34: PP Yarn | AX34: RM | AY34: erp | AZ34: 0 | BA34: 0 | BB34: 614 | BC34: 15-07-2026 | BD34: 24AAECK6307M2ZE | BE34: bharatd | BG34: 0 | BH34: 0 | BI34: 0 | BJ34: 0 | BK34: 0 | BL34: 0 | BM34: 0 | BN34: - | BO34: 46218.44 | BP34: 1963
B35: Oswal Extrusion Limited | C35: 17-07-2026 | D35: OEL/26-27/SII00577 | E35: WIP00023 | F35: PP UL Fabric With UV | G35: 4 | H35: No PO | I35: 0 | J35: 1058.7 | K35: Kgs | L35: 1058.7 | M35: 0 | N35: 1058.7 | O35: GJ12BY0479, GJ16Z8614 | P35: K.P. Woven Pvt Ltd - Unit 3 -Purchase | Q35: K.P. Woven Pvt Ltd - Unit 3 -Purchase | R35: KPW/JW/84 | S35: 16-07-2026 | T35: JOB IN | U35: OTHER | V35: JBIN-OT 90 | W35: 138.99604 | X35: 0 | Y35: KPW/JW/84 | Z35: 16-07-2026 | AD35: by Truck | AE35: 16-07-2026 | AF35: 0 | AG35: 0 | AH35: 0 | AI35: 0 | AJ35: 0 | AK35: VAT | AL35: 0 | AM35: 0 | AN35: 0 | AO35: 0 | AP35: 0 | AR35: 0 | AS35: 0 | AT35: 0 | AU35: SF | AV35: PP/PE Fabric | AW35: PP UL Fabric | AX35: RM | AY35: erp | AZ35: 0 | BA35: 0 | BB35: 619 | BC35: 16-07-2026 | BD35: 24AAECK6307M2ZE | BE35: bharatd | BG35: 0 | BH35: 0 | BI35: 0 | BJ35: 0 | BK35: 0 | BL35: 0 | BM35: 0 | BN35: - | BO35: 46219.61 | BP35: 1058.7
B36: Oswal Extrusion Limited | C36: 17-07-2026 | D36: OEL/26-27/SII00577 | E36: WIP00013 | F36: LDPE/LLDPE Bags/Liner | G36: 2 | H36: No PO | I36: 0 | J36: 201.1 | K36: Kgs | L36: 201.1 | M36: 0 | N36: 201.1 | O36: GJ12BY0479, GJ16Z8614 | P36: K.P. Woven Pvt Ltd - Unit 3 -Purchase | Q36: K.P. Woven Pvt Ltd - Unit 3 -Purchase | R36: KPW/JW/84 | S36: 16-07-2026 | T36: JOB IN | U36: OTHER | V36: JBIN-OT 90 | W36: 174.6 | X36: 0 | Y36: KPW/JW/84 | Z36: 16-07-2026 | AD36: by Truck | AE36: 16-07-2026 | AF36: 0 | AG36: 0 | AH36: 0 | AI36: 0 | AJ36: 0 | AK36: VAT | AL36: 0 | AM36: 0 | AN36: 0 | AO36: 0 | AP36: 0 | AR36: 0 | AS36: 0 | AT36: 0 | AU36: SF | AV36: Liners | AW36: LDPE/LLDPE Bags | AX36: RM | AY36: erp | AZ36: 0 | BA36: 0 | BB36: 619 | BC36: 16-07-2026 | BD36: 24AAECK6307M2ZE | BE36: bharatd | BG36: 0 | BH36: 0 | BI36: 0 | BJ36: 0 | BK36: 0 | BL36: 0 | BM36: 0 | BN36: - | BO36: 46219.61 | BP36: 201.1
B37: Oswal Extrusion Limited | C37: 17-07-2026 | D37: OEL/26-27/SII00577 | E37: WIP00025 | F37: PP Lam Fabric With UV | G37: 1 | H37: No PO | I37: 0 | J37: 2369 | K37: Kgs | L37: 2369 | M37: 0 | N37: 2369 | O37: GJ12BY0479, GJ16Z8614 | P37: K.P. Woven Pvt Ltd - Unit 3 -Purchase | Q37: K.P. Woven Pvt Ltd - Unit 3 -Purchase | R37: KPW/JW/84 | S37: 16-07-2026 | T37: JOB IN | U37: OTHER | V37: JBIN-OT 90 | W37: 142.00791 | X37: 0 | Y37: KPW/JW/84 | Z37: 16-07-2026 | AD37: by Truck | AE37: 16-07-2026 | AF37: 0 | AG37: 0 | AH37: 0 | AI37: 0 | AJ37: 0 | AK37: VAT | AL37: 0 | AM37: 0 | AN37: 0 | AO37: 0 | AP37: 0 | AR37: 0 | AS37: 0 | AT37: 0 | AU37: SF | AV37: PP/PE Fabric | AW37: PP Lam Fabric | AX37: RM | AY37: erp | AZ37: 0 | BA37: 0 | BB37: 619 | BC37: 16-07-2026 | BD37: 24AAECK6307M2ZE | BE37: bharatd | BG37: 0 | BH37: 0 | BI37: 0 | BJ37: 0 | BK37: 0 | BL37: 0 | BM37: 0 | BN37: - | BO37: 46219.61 | BP37: 2369
B38: Oswal Extrusion Limited | C38: 17-07-2026 | D38: OEL/26-27/SII00577 | E38: RAW05124 | F38: LDPE/LLDPE Bags/Liner | G38: 3 | H38: No PO | I38: 0 | J38: 444 | K38: Kgs | L38: 444 | M38: 0 | N38: 444 | O38: GJ12BY0479, GJ16Z8614 | P38: K.P. Woven Pvt Ltd - Unit 3 -Purchase | Q38: K.P. Woven Pvt Ltd - Unit 3 -Purchase | R38: KPW/JW/84 | S38: 16-07-2026 | T38: JOB IN | U38: OTHER | V38: JBIN-OT 90 | W38: 160.59468 | X38: 0 | Y38: KPW/JW/84 | Z38: 16-07-2026 | AD38: by Truck | AE38: 16-07-2026 | AF38: 0 | AG38: 0 | AH38: 0 | AI38: 0 | AJ38: 0 | AK38: VAT | AL38: 0 | AM38: 0 | AN38: 0 | AO38: 0 | AP38: 0 | AR38: 0 | AS38: 0 | AT38: 0 | AU38: SF | AV38: Films All (SF) | AW38: PE Film | AX38: RM | AY38: erp | AZ38: 0 | BA38: 0 | BB38: 619 | BC38: 16-07-2026 | BD38: 24AAECK6307M2ZE | BE38: bharatd | BG38: 0 | BH38: 0 | BI38: 0 | BJ38: 0 | BK38: 0 | BL38: 0 | BM38: 0 | BN38: - | BO38: 46219.61 | BP38: 444
B39: Oswal Extrusion Limited | C39: 18-07-2026 | D39: OEL/26-27/SII00581 | E39: RAW05516 | F39: UV Arguvin FG 626 LD | G39: 1 | H39: No PO | I39: 0 | J39: 1500 | K39: Kgs | L39: 1500 | M39: 0 | N39: 1500 | O39: GJ09Z0572 | P39: Plastene India ltd - Unit 1-Purchase | Q39: Plastene India ltd - Unit 1-Purchase | R39: PIL1/JW/49 | S39: 17-07-2026 | T39: JOB IN | U39: OTHER | V39: JBIN-OT 91 | W39: 194.99 | X39: 0 | Y39: PIL1/JW/49 | Z39: 17-07-2026 | AD39: LAXMAN B BAKUTRA | AE39: 200 17-07-2026 | AF39: 0 | AG39: 0 | AH39: 0 | AI39: 0 | AJ39: 0 | AK39: VAT | AL39: 0 | AM39: 0 | AN39: 0 | AO39: 0 | AP39: 0 | AR39: 0 | AS39: 0 | AT39: 0 | AU39: RM | AV39: Granules | AW39: UV MB | AX39: RM | AY39: erp | AZ39: 0 | BA39: 0 | BB39: 623 | BC39: 17-07-2026 | BD39: 24AAACO3087C1ZT | BE39: bharatd | BG39: 0 | BH39: 0 | BI39: 0 | BJ39: 0 | BK39: 0 | BL39: 0 | BM39: 0 | BN39: - | BO39: 46220.388 | BP39: 1500
B40: Oswal Extrusion Limited | C40: 18-07-2026 | D40: OEL/26-27/SII00584 | E40: WIP00025 | F40: PP Lam Fabric With UV | G40: 3 | H40: No PO | I40: 0 | J40: 3887 | K40: Kgs | L40: 3887 | M40: 0 | N40: 3887 | O40: GJ09Z0572 | P40: K.P. Woven Pvt Ltd - Unit 3 -Purchase | Q40: K.P. Woven Pvt Ltd - Unit 3 -Purchase | R40: KPW/JW/85 | S40: 17-07-2026 | T40: JOB IN | U40: OTHER | V40: JBIN-OT 92 | W40: 142.00791 | X40: 0 | Y40: KPW/JW/85 | Z40: 17-07-2026 | AD40: by Truck | AE40: 17-07-2026 | AF40: 0 | AG40: 0 | AH40: 0 | AI40: 0 | AJ40: 0 | AK40: VAT | AL40: 0 | AM40: 0 | AN40: 0 | AO40: 0 | AP40: 0 | AR40: 0 | AS40: 0 | AT40: 0 | AU40: SF | AV40: PP/PE Fabric | AW40: PP Lam Fabric | AX40: RM | AY40: erp | AZ40: 0 | BA40: 0 | BB40: 624 | BC40: 17-07-2026 | BD40: 24AAECK6307M2ZE | BE40: bharatd | BG40: 0 | BH40: 0 | BI40: 0 | BJ40: 0 | BK40: 0 | BL40: 0 | BM40: 0 | BN40: - | BO40: 46220.495 | BP40: 3887
B41: Oswal Extrusion Limited | C41: 18-07-2026 | D41: OEL/26-27/SII00584 | E41: WIP00013 | F41: LDPE/LLDPE Bags/Liner | G41: 2 | H41: No PO | I41: 0 | J41: 123 | K41: Kgs | L41: 123 | M41: 0 | N41: 123 | O41: GJ09Z0572 | P41: K.P. Woven Pvt Ltd - Unit 3 -Purchase | Q41: K.P. Woven Pvt Ltd - Unit 3 -Purchase | R41: KPW/JW/85 | S41: 17-07-2026 | T41: JOB IN | U41: OTHER | V41: JBIN-OT 92 | W41: 174.60179 | X41: 0 | Y41: KPW/JW/85 | Z41: 17-07-2026 | AD41: by Truck | AE41: 17-07-2026 | AF41: 0 | AG41: 0 | AH41: 0 | AI41: 0 | AJ41: 0 | AK41: VAT | AL41: 0 | AM41: 0 | AN41: 0 | AO41: 0 | AP41: 0 | AR41: 0 | AS41: 0 | AT41: 0 | AU41: SF | AV41: Liners | AW41: LDPE/LLDPE Bags | AX41: RM | AY41: erp | AZ41: 0 | BA41: 0 | BB41: 624 | BC41: 17-07-2026 | BD41: 24AAECK6307M2ZE | BE41: bharatd | BG41: 0 | BH41: 0 | BI41: 0 | BJ41: 0 | BK41: 0 | BL41: 0 | BM41: 0 | BN41: - | BO41: 46220.495 | BP41: 123
B42: Oswal Extrusion Limited | C42: 18-07-2026 | D42: OEL/26-27/SII00584 | E42: WIP00015 | F42: PP MF Yarn Twisted | G42: 1 | H42: No PO | I42: 0 | J42: 2188.3 | K42: Kgs | L42: 2188.3 | M42: 0 | N42: 2188.3 | O42: GJ09Z0572 | P42: K.P. Woven Pvt Ltd - Unit 3 -Purchase | Q42: K.P. Woven Pvt Ltd - Unit 3 -Purchase | R42: KPW/JW/85 | S42: 17-07-2026 | T42: JOB IN | U42: OTHER | V42: JBIN-OT 92 | W42: 148.6443 | X42: 0 | Y42: KPW/JW/85 | Z42: 17-07-2026 | AD42: by Truck | AE42: 17-07-2026 | AF42: 0 | AG42: 0 | AH42: 0 | AI42: 0 | AJ42: 0 | AK42: VAT | AL42: 0 | AM42: 0 | AN42: 0 | AO42: 0 | AP42: 0 | AR42: 0 | AS42: 0 | AT42: 0 | AU42: SF | AV42: Yarn All | AW42: PP Yarn | AX42: RM | AY42: erp | AZ42: 0 | BA42: 0 | BB42: 624 | BC42: 17-07-2026 | BD42: 24AAECK6307M2ZE | BE42: bharatd | BG42: 0 | BH42: 0 | BI42: 0 | BJ42: 0 | BK42: 0 | BL42: 0 | BM42: 0 | BN42: - | BO42: 46220.495 | BP42: 2188.3
B43: Oswal Extrusion Limited | C43: 20-07-2026 | D43: OEL/26-27/SII00586 | E43: WIP00023 | F43: PP UL Fabric With UV | G43: 1 | H43: No PO | I43: 0 | J43: 1763 | K43: Kgs | L43: 1763 | M43: 0 | N43: 1763 | O43: GJ06AX2024, GJ12BY0479 | P43: K.P. Woven Pvt Ltd - Unit 3 -Purchase | Q43: K.P. Woven Pvt Ltd - Unit 3 -Purchase | R43: KPW/JW/86 | S43: 18-07-2026 | T43: JOB IN | U43: OTHER | V43: JBIN-OT 93 | W43: 138.99627 | X43: 0 | Y43: KPW/JW/86 | Z43: 18-07-2026 | AD43: by Truck | AE43: 18-07-2026 | AF43: 0 | AG43: 0 | AH43: 0 | AI43: 0 | AJ43: 0 | AK43: VAT | AL43: 0 | AM43: 0 | AN43: 0 | AO43: 0 | AP43: 0 | AR43: 0 | AS43: 0 | AT43: 0 | AU43: SF | AV43: PP/PE Fabric | AW43: PP UL Fabric | AX43: RM | AY43: erp | AZ43: 0 | BA43: 0 | BB43: 630 | BC43: 18-07-2026 | BD43: 24AAECK6307M2ZE | BE43: bharatd | BG43: 0 | BH43: 0 | BI43: 0 | BJ43: 0 | BK43: 0 | BL43: 0 | BM43: 0 | BN43: - | BO43: 46221.494 | BP43: 1763
B44: Oswal Extrusion Limited | C44: 20-07-2026 | D44: OEL/26-27/SII00586 | E44: WIP00013 | F44: LDPE/LLDPE Bags/Liner | G44: 2 | H44: No PO | I44: 0 | J44: 6952 | K44: Kgs | L44: 6952 | M44: 0 | N44: 6952 | O44: GJ06AX2024, GJ12BY0479 | P44: K.P. Woven Pvt Ltd - Unit 3 -Purchase | Q44: K.P. Woven Pvt Ltd - Unit 3 -Purchase | R44: KPW/JW/86 | S44: 18-07-2026 | T44: JOB IN | U44: OTHER | V44: JBIN-OT 93 | W44: 174.60197 | X44: 0 | Y44: KPW/JW/86 | Z44: 18-07-2026 | AD44: by Truck | AE44: 18-07-2026 | AF44: 0 | AG44: 0 | AH44: 0 | AI44: 0 | AJ44: 0 | AK44: VAT | AL44: 0 | AM44: 0 | AN44: 0 | AO44: 0 | AP44: 0 | AR44: 0 | AS44: 0 | AT44: 0 | AU44: SF | AV44: Liners | AW44: LDPE/LLDPE Bags | AX44: RM | AY44: erp | AZ44: 0 | BA44: 0 | BB44: 630 | BC44: 18-07-2026 | BD44: 24AAECK6307M2ZE | BE44: bharatd | BG44: 0 | BH44: 0 | BI44: 0 | BJ44: 0 | BK44: 0 | BL44: 0 | BM44: 0 | BN44: - | BO44: 46221.494 | BP44: 6952
B45: Oswal Extrusion Limited | C45: 20-07-2026 | D45: OEL/26-27/SII00586 | E45: RAW05124 | F45: LDPE/LLDPE Bags/Liner | G45: 4 | H45: No PO | I45: 0 | J45: 10.7 | K45: Kgs | L45: 10.7 | M45: 0 | N45: 10.7 | O45: GJ06AX2024, GJ12BY0479 | P45: K.P. Woven Pvt Ltd - Unit 3 -Purchase | Q45: K.P. Woven Pvt Ltd - Unit 3 -Purchase | R45: KPW/JW/86 | S45: 18-07-2026 | T45: JOB IN | U45: OTHER | V45: JBIN-OT 93 | W45: 350 | X45: 0 | Y45: KPW/JW/86 | Z45: 18-07-2026 | AD45: by Truck | AE45: 18-07-2026 | AF45: 0 | AG45: 0 | AH45: 0 | AI45: 0 | AJ45: 0 | AK45: VAT | AL45: 0 | AM45: 0 | AN45: 0 | AO45: 0 | AP45: 0 | AR45: 0 | AS45: 0 | AT45: 0 | AU45: SF | AV45: Films All (SF) | AW45: PE Film | AX45: RM | AY45: erp | AZ45: 0 | BA45: 0 | BB45: 630 | BC45: 18-07-2026 | BD45: 24AAECK6307M2ZE | BE45: bharatd | BG45: 0 | BH45: 0 | BI45: 0 | BJ45: 0 | BK45: 0 | BL45: 0 | BM45: 0 | BN45: - | BO45: 46221.494 | BP45: 10.7
... B54: Oswal Extrusion Limited | C54: 25-07-2026 | D54: OEL/26-27/SII00615 | E54: WIP00013 | F54: LDPE/LLDPE Bags/Liner | G54: 5 | H54: No PO | I54: 0 | J54: 6980.4 | K54: Kgs | L54: 6980.4 | M54: 0 | N54: 6980.4 | O54: GJ12BV1841, GJ12BY0479 | P54: Oswal Extrusion Ltd- KASEZ-Purchase | Q54: Oswal Extrusion Ltd- KASEZ-Purchase | R54: KPW/JW/90 | S54: 24-07-2026 | T54: JOB IN | U54: OTHER | V54: JBIN-OT 97 | W54: 174.60178 | X54: 0 | Y54: KPW/JW/90 | Z54: 24-07-2026 | AD54: by Truck | AE54: 24-07-2026 | AF54: 0 | AG54: 0 | AH54: 0 | AI54: 0 | AJ54: 0 | AK54: VAT | AL54: 0 | AM54: 0 | AN54: 0 | AO54: 0 | AP54: 0 | AR54: 0 | AS54: 0 | AT54: 0 | AU54: SF | AV54: Liners | AW54: LDPE/LLDPE Bags | AX54: RM | AY54: erp | AZ54: 0 | BA54: 0 | BB54: 664 | BC54: 24-07-2026 | BD54: 24AAACO7290H4ZB | BE54: bharatd | BG54: 0 | BH54: 0 | BI54: 0 | BJ54: 0 | BK54: 0 | BL54: 0 | BM54: 0 | BN54: - | BO54: 46227.494 | BP54: 6980.4
B55: Oswal Extrusion Limited | C55: 25-07-2026 | D55: OEL/26-27/SII00615 | E55: WIP00025 | F55: PP Lam Fabric With UV | G55: 3 | H55: No PO | I55: 0 | J55: 4164 | K55: Kgs | L55: 4164 | M55: 0 | N55: =4164 -> 4164 | O55: GJ12BV1841, GJ12BY0479 | P55: Oswal Extrusion Ltd- KASEZ-Purchase | Q55: Oswal Extrusion Ltd- KASEZ-Purchase | R55: KPW/JW/90 | S55: 24-07-2026 | T55: JOB IN | U55: OTHER | V55: JBIN-OT 97 | W55: 142.00773 | X55: 0 | Y55: KPW/JW/90 | Z55: 24-07-2026 | AD55: by Truck | AE55: 24-07-2026 | AF55: 0 | AG55: 0 | AH55: 0 | AI55: 0 | AJ55: 0 | AK55: VAT | AL55: 0 | AM55: 0 | AN55: 0 | AO55: 0 | AP55: 0 | AR55: 0 | AS55: 0 | AT55: 0 | AU55: SF | AV55: PP/PE Fabric | AW55: PP Lam Fabric | AX55: RM | AY55: erp | AZ55: 0 | BA55: 0 | BB55: 664 | BC55: 24-07-2026 | BD55: 24AAACO7290H4ZB | BE55: bharatd | BG55: 0 | BH55: 0 | BI55: 0 | BJ55: 0 | BK55: 0 | BL55: 0 | BM55: 0 | BN55: - | BO55: 46227.494 | BP55: 4164
B56: Oswal Extrusion Limited | C56: 25-07-2026 | D56: OEL/26-27/SII00615 | E56: WIP00023 | F56: PP UL Fabric With UV | G56: 2 | H56: No PO | I56: 0 | J56: 2698 | K56: Kgs | L56: 2698 | M56: 0 | N56: 2698 | O56: GJ12BV1841, GJ12BY0479 | P56: Oswal Extrusion Ltd- KASEZ-Purchase | Q56: Oswal Extrusion Ltd- KASEZ-Purchase | R56: KPW/JW/90 | S56: 24-07-2026 | T56: JOB IN | U56: OTHER | V56: JBIN-OT 97 | W56: 138.94107 | X56: 0 | Y56: KPW/JW/90 | Z56: 24-07-2026 | AD56: by Truck | AE56: 24-07-2026 | AF56: 0 | AG56: 0 | AH56: 0 | AI56: 0 | AJ56: 0 | AK56: VAT | AL56: 0 | AM56: 0 | AN56: 0 | AO56: 0 | AP56: 0 | AR56: 0 | AS56: 0 | AT56: 0 | AU56: SF | AV56: PP/PE Fabric | AW56: PP UL Fabric | AX56: RM | AY56: erp | AZ56: 0 | BA56: 0 | BB56: 664 | BC56: 24-07-2026 | BD56: 24AAACO7290H4ZB | BE56: bharatd | BG56: 0 | BH56: 0 | BI56: 0 | BJ56: 0 | BK56: 0 | BL56: 0 | BM56: 0 | BN56: - | BO56: 46227.494 | BP56: 2698
B57: Oswal Extrusion Limited | C57: 25-07-2026 | D57: OEL/26-27/SII00615 | E57: WIP00015 | F57: PP MF Yarn Twisted | G57: 4 | H57: No PO | I57: 0 | J57: 2166.2 | K57: Kgs | L57: 2166.2 | M57: 0 | N57: 2166.2 | O57: GJ12BV1841, GJ12BY0479 | P57: Oswal Extrusion Ltd- KASEZ-Purchase | Q57: Oswal Extrusion Ltd- KASEZ-Purchase | R57: KPW/JW/90 | S57: 24-07-2026 | T57: JOB IN | U57: OTHER | V57: JBIN-OT 97 | W57: 148.73007 | X57: 0 | Y57: KPW/JW/90 | Z57: 24-07-2026 | AD57: by Truck | AE57: 24-07-2026 | AF57: 0 | AG57: 0 | AH57: 0 | AI57: 0 | AJ57: 0 | AK57: VAT | AL57: 0 | AM57: 0 | AN57: 0 | AO57: 0 | AP57: 0 | AR57: 0 | AS57: 0 | AT57: 0 | AU57: SF | AV57: Yarn All | AW57: PP Yarn | AX57: RM | AY57: erp | AZ57: 0 | BA57: 0 | BB57: 664 | BC57: 24-07-2026 | BD57: 24AAACO7290H4ZB | BE57: bharatd | BG57: 0 | BH57: 0 | BI57: 0 | BJ57: 0 | BK57: 0 | BL57: 0 | BM57: 0 | BN57: - | BO57: 46227.494 | BP57: 2166.2
B58: Oswal Extrusion Limited | C58: 25-07-2026 | D58: OEL/26-27/SII00615 | E58: RAW05124 | F58: LDPE/LLDPE Bags/Liner | G58: 1 | H58: No PO | I58: 0 | J58: 104 | K58: Kgs | L58: 104 | M58: 0 | N58: 104 | O58: GJ12BV1841, GJ12BY0479 | P58: Oswal Extrusion Ltd- KASEZ-Purchase | Q58: Oswal Extrusion Ltd- KASEZ-Purchase | R58: KPW/JW/90 | S58: 24-07-2026 | T58: JOB IN | U58: OTHER | V58: JBIN-OT 97 | W58: 160.59529 | X58: 0 | Y58: KPW/JW/90 | Z58: 24-07-2026 | AD58: by Truck | AE58: 24-07-2026 | AF58: 0 | AG58: 0 | AH58: 0 | AI58: 0 | AJ58: 0 | AK58: VAT | AL58: 0 | AM58: 0 | AN58: 0 | AO58: 0 | AP58: 0 | AR58: 0 | AS58: 0 | AT58: 0 | AU58: SF | AV58: Films All (SF) | AW58: PE Film | AX58: RM | AY58: erp | AZ58: 0 | BA58: 0 | BB58: 664 | BC58: 24-07-2026 | BD58: 24AAACO7290H4ZB | BE58: bharatd | BG58: 0 | BH58: 0 | BI58: 0 | BJ58: 0 | BK58: 0 | BL58: 0 | BM58: 0 | BN58: - | BO58: 46227.494 | BP58: 104
B59: Oswal Extrusion Limited | C59: 27-07-2026 | D59: OEL/26-27/SII00620 | E59: RAW05089 | F59: UV Arguvin FG 626 LD | G59: 1 | H59: No PO | I59: 0 | J59: 2475 | K59: Kgs | L59: 2475 | M59: 0 | N59: 2475 | O59: GJ12BY0479 | P59: Plastene India ltd - Unit 1-Purchase | Q59: Plastene India ltd - Unit 1-Purchase | R59: PIL1/JW/65 | S59: 25-07-2026 | T59: JOB IN | U59: OTHER | V59: JBIN-OT 98 | W59: 195 | X59: 0 | Y59: PIL1/JW/65 | Z59: 25-07-2026 | AD59: LAXMAN B BAKUTRA | AE59: 219 25-07-2026 | AF59: 0 | AG59: 0 | AH59: 0 | AI59: 0 | AJ59: 0 | AK59: VAT | AL59: 0 | AM59: 0 | AN59: 0 | AO59: 0 | AP59: 0 | AR59: 0 | AS59: 0 | AT59: 0 | AU59: RM | AV59: Granules | AW59: UV MB | AX59: RM | AY59: erp | AZ59: 0 | BA59: 0 | BB59: 669 | BC59: 25-07-2026 | BD59: 24AAACO3087C1ZT | BE59: bharatd | BG59: 0 | BH59: 0 | BI59: 0 | BJ59: 0 | BK59: 0 | BL59: 0 | BM59: 0 | BN59: - | BO59: 46228.427 | BP59: 2475
B60: Oswal Extrusion Limited | C60: 27-07-2026 | D60: OEL/26-27/SII00620 | E60: RAW06268 | F60: PP Granules | G60: 2 | H60: No PO | I60: 0 | J60: 5000 | K60: Kgs | L60: 5000 | M60: 0 | N60: 5000 | O60: GJ12BY0479 | P60: Plastene India ltd - Unit 1-Purchase | Q60: Plastene India ltd - Unit 1-Purchase | R60: PIL1/JW/65 | S60: 25-07-2026 | T60: JOB IN | U60: OTHER | V60: JBIN-OT 98 | W60: 115 | X60: 0 | Y60: PIL1/JW/65 | Z60: 25-07-2026 | AD60: LAXMAN B BAKUTRA | AE60: 219 25-07-2026 | AF60: 0 | AG60: 0 | AH60: 0 | AI60: 0 | AJ60: 0 | AK60: VAT | AL60: 0 | AM60: 0 | AN60: 0 | AO60: 0 | AP60: 0 | AR60: 0 | AS60: 0 | AT60: 0 | AU60: RM | AV60: Granules | AW60: PP Granules | AX60: RM | AZ60: 0 | BA60: 0 | BB60: 669 | BC60: 25-07-2026 | BD60: 24AAACO3087C1ZT | BE60: bharatd | BG60: 0 | BH60: 0 | BI60: 0 | BJ60: 0 | BK60: 0 | BL60: 0 | BM60: 0 | BN60: - | BO60: 46228.427 | BP60: 5000
B61: Oswal Extrusion Limited | C61: 27-07-2026 | D61: OEL/26-27/SII00621 | E61: RAW05124 | F61: LDPE/LLDPE Bags/Liner | G61: 1 | H61: No PO | I61: 0 | J61: 311.8 | K61: Kgs | L61: 311.8 | M61: 0 | N61: =311.8 -> 311.8 | O61: GJ09Z0572, GJ12BY0479 | P61: K.P. Woven Pvt Ltd - Unit 3 -Purchase | Q61: K.P. Woven Pvt Ltd - Unit 3 -Purchase | R61: KPW/JW/91 | S61: 25-07-2026 | T61: JOB IN | U61: OTHER | V61: JBIN-OT 99 | W61: 160.59631 | X61: 0 | Y61: KPW/JW/91 | Z61: 25-07-2026 | AD61: by Truck | AE61: 25-07-2026 | AF61: 0 | AG61: 0 | AH61: 0 | AI61: 0 | AJ61: 0 | AK61: VAT | AL61: 0 | AM61: 0 | AN61: 0 | AO61: 0 | AP61: 0 | AR61: 0 | AS61: 0 | AT61: 0 | AU61: SF | AV61: Films All (SF) | AW61: PE Film | AX61: RM | AY61: erp | AZ61: 0 | BA61: 0 | BB61: 670 | BC61: 25-07-2026 | BD61: 24AAECK6307M2ZE | BE61: bharatd | BG61: 0 | BH61: 0 | BI61: 0 | BJ61: 0 | BK61: 0 | BL61: 0 | BM61: 0 | BN61: - | BO61: 46228.435 | BP61: 311.8
B62: Oswal Extrusion Limited | C62: 27-07-2026 | D62: OEL/26-27/SII00621 | E62: RAW05951 | F62: PP Tapes | G62: 3 | H62: No PO | I62: 0 | J62: 495.8 | K62: Kgs | L62: 495.8 | M62: 0 | N62: =495.8 -> 495.8 | O62: GJ09Z0572, GJ12BY0479 | P62: K.P. Woven Pvt Ltd - Unit 3 -Purchase | Q62: K.P. Woven Pvt Ltd - Unit 3 -Purchase | R62: KPW/JW/91 | S62: 25-07-2026 | T62: JOB IN | U62: OTHER | V62: JBIN-OT 99 | W62: 134.50008 | X62: 0 | Y62: KPW/JW/91 | Z62: 25-07-2026 | AD62: by Truck | AE62: 25-07-2026 | AF62: 0 | AG62: 0 | AH62: 0 | AI62: 0 | AJ62: 0 | AK62: VAT | AL62: 0 | AM62: 0 | AN62: 0 | AO62: 0 | AP62: 0 | AR62: 0 | AS62: 0 | AT62: 0 | AU62: SF | AV62: Tape Stock | AW62: PP Tapes | AX62: RM | AY62: erp | AZ62: 0 | BA62: 0 | BB62: 670 | BC62: 25-07-2026 | BD62: 24AAECK6307M2ZE | BE62: bharatd | BG62: 0 | BH62: 0 | BI62: 0 | BJ62: 0 | BK62: 0 | BL62: 0 | BM62: 0 | BN62: - | BO62: 46228.435 | BP62: 495.8
B63: Oswal Extrusion Limited | C63: 27-07-2026 | D63: OEL/26-27/SII00621 | E63: WIP00023 | F63: PP UL Fabric With UV | G63: 4 | H63: No PO | I63: 0 | J63: 268 | K63: Kgs | L63: 268 | M63: 0 | N63: =268 -> 268 | O63: GJ09Z0572, GJ12BY0479 | P63: K.P. Woven Pvt Ltd - Unit 3 -Purchase | Q63: K.P. Woven Pvt Ltd - Unit 3 -Purchase | R63: KPW/JW/91 | S63: 25-07-2026 | T63: JOB IN | U63: OTHER | V63: JBIN-OT 99 | W63: 103.04 | X63: 0 | Y63: KPW/JW/91 | Z63: 25-07-2026 | AD63: by Truck | AE63: 25-07-2026 | AF63: 0 | AG63: 0 | AH63: 0 | AI63: 0 | AJ63: 0 | AK63: VAT | AL63: 0 | AM63: 0 | AN63: 0 | AO63: 0 | AP63: 0 | AR63: 0 | AS63: 0 | AT63: 0 | AU63: SF | AV63: PP/PE Fabric | AW63: PP UL Fabric | AX63: RM | AY63: erp | AZ63: 0 | BA63: 0 | BB63: 670 | BC63: 25-07-2026 | BD63: 24AAECK6307M2ZE | BE63: bharatd | BG63: 0 | BH63: 0 | BI63: 0 | BJ63: 0 | BK63: 0 | BL63: 0 | BM63: 0 | BN63: - | BO63: 46228.435 | BP63: 268
B64: Oswal Extrusion Limited | C64: 27-07-2026 | D64: OEL/26-27/SII00621 | E64: WIP00025 | F64: PP Lam Fabric With UV | G64: 2 | H64: No PO | I64: 0 | J64: 3592.8 | K64: Kgs | L64: 3592.8 | M64: 0 | N64: 3592.8 | O64: GJ09Z0572, GJ12BY0479 | P64: K.P. Woven Pvt Ltd - Unit 3 -Purchase | Q64: K.P. Woven Pvt Ltd - Unit 3 -Purchase | R64: KPW/JW/91 | S64: 25-07-2026 | T64: JOB IN | U64: OTHER | V64: JBIN-OT 99 | W64: 142.74665 | X64: 0 | Y64: KPW/JW/91 | Z64: 25-07-2026 | AD64: by Truck | AE64: 25-07-2026 | AF64: 0 | AG64: 0 | AH64: 0 | AI64: 0 | AJ64: 0 | AK64: VAT | AL64: 0 | AM64: 0 | AN64: 0 | AO64: 0 | AP64: 0 | AR64: 0 | AS64: 0 | AT64: 0 | AU64: SF | AV64: PP/PE Fabric | AW64: PP Lam Fabric | AX64: RM | AY64: erp | AZ64: 0 | BA64: 0 | BB64: 670 | BC64: 25-07-2026 | BD64: 24AAECK6307M2ZE | BE64: bharatd | BG64: 0 | BH64: 0 | BI64: 0 | BJ64: 0 | BK64: 0 | BL64: 0 | BM64: 0 | BN64: - | BO64: 46228.435 | BP64: 3592.8
B65: Oswal Extrusion Limited | C65: 28-07-2026 | D65: OEL/26-27/SII00626 | E65: WIP00023 | F65: PP UL Fabric With UV | G65: 4 | H65: No PO | I65: 0 | J65: 5258 | K65: Kgs | L65: 5258 | M65: 0 | N65: 5258 | O65: GJ24X5687, GJ12BY0479 | P65: K.P. Woven Pvt Ltd - Unit 3 -Purchase | Q65: K.P. Woven Pvt Ltd - Unit 3 -Purchase | R65: KPW/JW/92 | S65: 27-07-2026 | T65: JOB IN | U65: OTHER | V65: JBIN-OT 100 | W65: 138.941 | X65: 0 | Y65: KPW/JW/92 | Z65: 27-07-2026 | AD65: by Truck | AE65: 27-07-2026 | AF65: 0 | AG65: 0 | AH65: 0 | AI65: 0 | AJ65: 0 | AK65: VAT | AL65: 0 | AM65: 0 | AN65: 0 | AO65: 0 | AP65: 0 | AR65: 0 | AS65: 0 | AT65: 0 | AU65: SF | AV65: PP/PE Fabric | AW65: PP UL Fabric | AX65: RM | AY65: erp | AZ65: 0 | BA65: 0 | BB65: 683 | BC65: 27-07-2026 | BD65: 24AAECK6307M2ZE | BE65: bharatd | BG65: 0 | BH65: 0 | BI65: 0 | BJ65: 0 | BK65: 0 | BL65: 0 | BM65: 0 | BN65: - | BO65: 46230.607 | BP65: 5258
B66: Oswal Extrusion Limited | C66: 28-07-2026 | D66: OEL/26-27/SII00626 | E66: WIP00024 | F66: PP UL Fabric With UV | G66: 6 | H66: No PO | I66: 0 | J66: 30 | K66: Kgs | L66: 30 | M66: 0 | N66: 30 | O66: GJ24X5687, GJ12BY0479 | P66: K.P. Woven Pvt Ltd - Unit 3 -Purchase | Q66: K.P. Woven Pvt Ltd - Unit 3 -Purchase | R66: KPW/JW/92 | S66: 27-07-2026 | T66: JOB IN | U66: OTHER | V66: JBIN-OT 100 | W66: 138.941 | X66: 0 | Y66: KPW/JW/92 | Z66: 27-07-2026 | AD66: by Truck | AE66: 27-07-2026 | AF66: 0 | AG66: 0 | AH66: 0 | AI66: 0 | AJ66: 0 | AK66: VAT | AL66: 0 | AM66: 0 | AN66: 0 | AO66: 0 | AP66: 0 | AR66: 0 | AS66: 0 | AT66: 0 | AU66: SF | AV66: PP/PE Fabric | AW66: PP UL Fabric | AX66: RM | AY66: erp | AZ66: 0 | BA66: 0 | BB66: 683 | BC66: 27-07-2026 | BD66: 24AAECK6307M2ZE | BE66: bharatd | BG66: 0 | BH66: 0 | BI66: 0 | BJ66: 0 | BK66: 0 | BL66: 0 | BM66: 0 | BN66: - | BO66: 46230.607 | BP66: 30
B67: Oswal Extrusion Limited | C67: 28-07-2026 | D67: OEL/26-27/SII00626 | E67: WIP00025 | F67: PP Lam Fabric With UV | G67: 5 | H67: No PO | I67: 0 | J67: 6551 | K67: Kgs | L67: 6551 | M67: 0 | N67: 6551 | O67: GJ24X5687, GJ12BY0479 | P67: K.P. Woven Pvt Ltd - Unit 3 -Purchase | Q67: K.P. Woven Pvt Ltd - Unit 3 -Purchase | R67: KPW/JW/92 | S67: 27-07-2026 | T67: JOB IN | U67: OTHER | V67: JBIN-OT 100 | W67: 142.0075 | X67: 0 | Y67: KPW/JW/92 | Z67: 27-07-2026 | AD67: by Truck | AE67: 27-07-2026 | AF67: 0 | AG67: 0 | AH67: 0 | AI67: 0 | AJ67: 0 | AK67: VAT | AL67: 0 | AM67: 0 | AN67: 0 | AO67: 0 | AP67: 0 | AR67: 0 | AS67: 0 | AT67: 0 | AU67: SF | AV67: PP/PE Fabric | AW67: PP Lam Fabric | AX67: RM | AY67: erp | AZ67: 0 | BA67: 0 | BB67: 683 | BC67: 27-07-2026 | BD67: 24AAECK6307M2ZE | BE67: bharatd | BG67: 0 | BH67: 0 | BI67: 0 | BJ67: 0 | BK67: 0 | BL67: 0 | BM67: 0 | BN67: - | BO67: 46230.607 | BP67: 6551
B68: Oswal Extrusion Limited | C68: 28-07-2026 | D68: OEL/26-27/SII00626 | E68: WIP00013 | F68: LDPE/LLDPE Bags/Liner | G68: 1 | H68: No PO | I68: 0 | J68: 3545.5 | K68: Kgs | L68: 3545.5 | M68: 0 | N68: 3545.5 | O68: GJ24X5687, GJ12BY0479 | P68: K.P. Woven Pvt Ltd - Unit 3 -Purchase | Q68: K.P. Woven Pvt Ltd - Unit 3 -Purchase | R68: KPW/JW/92 | S68: 27-07-2026 | T68: JOB IN | U68: OTHER | V68: JBIN-OT 100 | W68: 174.6017 | X68: 0 | Y68: KPW/JW/92 | Z68: 27-07-2026 | AD68: by Truck | AE68: 27-07-2026 | AF68: 0 | AG68: 0 | AH68: 0 | AI68: 0 | AJ68: 0 | AK68: VAT | AL68: 0 | AM68: 0 | AN68: 0 | AO68: 0 | AP68: 0 | AR68: 0 | AS68: 0 | AT68: 0 | AU68: SF | AV68: Liners | AW68: LDPE/LLDPE Bags | AX68: RM | AY68: erp | AZ68: 0 | BA68: 0 | BB68: 683 | BC68: 27-07-2026 | BD68: 24AAECK6307M2ZE | BE68: bharatd | BG68: 0 | BH68: 0 | BI68: 0 | BJ68: 0 | BK68: 0 | BL68: 0 | BM68: 0 | BN68: - | BO68: 46230.607 | BP68: 3545.5
B69: Oswal Extrusion Limited | C69: 28-07-2026 | D69: OEL/26-27/SII00626 | E69: RAW05951 | F69: PP Tapes | G69: 3 | H69: No PO | I69: 0 | J69: 1092 | K69: Kgs | L69: 1092 | M69: 0 | N69: 1092 | O69: GJ24X5687, GJ12BY0479 | P69: K.P. Woven Pvt Ltd - Unit 3 -Purchase | Q69: K.P. Woven Pvt Ltd - Unit 3 -Purchase | R69: KPW/JW/92 | S69: 27-07-2026 | T69: JOB IN | U69: OTHER | V69: JBIN-OT 100 | W69: 134.4996 | X69: 0 | Y69: KPW/JW/92 | Z69: 27-07-2026 | AD69: by Truck | AE69: 27-07-2026 | AF69: 0 | AG69: 0 | AH69: 0 | AI69: 0 | AJ69: 0 | AK69: VAT | AL69: 0 | AM69: 0 | AN69: 0 | AO69: 0 | AP69: 0 | AR69: 0 | AS69: 0 | AT69: 0 | AU69: SF | AV69: Tape Stock | AW69: PP Tapes | AX69: RM | AY69: erp | AZ69: 0 | BA69: 0 | BB69: 683 | BC69: 27-07-2026 | BD69: 24AAECK6307M2ZE | BE69: bharatd | BG69: 0 | BH69: 0 | BI69: 0 | BJ69: 0 | BK69: 0 | BL69: 0 | BM69: 0 | BN69: - | BO69: 46230.607 | BP69: 1092
B70: Oswal Extrusion Limited | C70: 28-07-2026 | D70: OEL/26-27/SII00626 | E70: RAW05124 | F70: LDPE/LLDPE Bags/Liner | G70: 2 | H70: No PO | I70: 0 | J70: 187 | K70: Kgs | L70: 187 | M70: 0 | N70: 187 | O70: GJ24X5687, GJ12BY0479 | P70: K.P. Woven Pvt Ltd - Unit 3 -Purchase | Q70: K.P. Woven Pvt Ltd - Unit 3 -Purchase | R70: KPW/JW/92 | S70: 27-07-2026 | T70: JOB IN | U70: OTHER | V70: JBIN-OT 100 | W70: 160.59503 | X70: 0 | Y70: KPW/JW/92 | Z70: 27-07-2026 | AD70: by Truck | AE70: 27-07-2026 | AF70: 0 | AG70: 0 | AH70: 0 | AI70: 0 | AJ70: 0 | AK70: VAT | AL70: 0 | AM70: 0 | AN70: 0 | AO70: 0 | AP70: 0 | AR70: 0 | AS70: 0 | AT70: 0 | AU70: SF | AV70: Films All (SF) | AW70: PE Film | AX70: RM | AY70: erp | AZ70: 0 | BA70: 0 | BB70: 683 | BC70: 27-07-2026 | BD70: 24AAECK6307M2ZE | BE70: bharatd | BG70: 0 | BH70: 0 | BI70: 0 | BJ70: 0 | BK70: 0 | BL70: 0 | BM70: 0 | BN70: - | BO70: 46230.607 | BP70: 187
B71: Oswal Extrusion Limited | C71: 29-07-2026 | D71: OEL/26-27/SII00632 | E71: RAW05270 | F71: LDPE Sumitomo L705 | G71: 1 | H71: No PO | I71: 0 | J71: 2000 | K71: Kgs | L71: 2000 | M71: 0 | N71: 2000 | O71: GJ09Z0572 | P71: Plastene India ltd - Unit 1-Purchase | Q71: Plastene India ltd - Unit 1-Purchase | R71: PIL1/JW/71 | S71: 28-07-2026 | T71: JOB IN | U71: OTHER | V71: JBIN-OT 101 | W71: 163.72 | X71: 0 | Y71: PIL1/JW/71 | Z71: 28-07-2026 | AD71: LAXMAN B BAKUTRA | AE71: 225 28-07-2026 | AF71: 0 | AG71: 0 | AH71: 0 | AI71: 0 | AJ71: 0 | AK71: VAT | AL71: 0 | AM71: 0 | AN71: 0 | AO71: 0 | AP71: 0 | AR71: 0 | AS71: 0 | AT71: 0 | AU71: RM | AV71: Granules | AW71: LDPE Granules | AX71: RM | AY71: erp | AZ71: 0 | BA71: 0 | BB71: 686 | BC71: 28-07-2026 | BD71: 24AAACO3087C1ZT | BE71: bharatd | BG71: 0 | BH71: 0 | BI71: 0 | BJ71: 0 | BK71: 0 | BL71: 0 | BM71: 0 | BN71: - | BO71: 46231.452 | BP71: 2000
B72: Oswal Extrusion Limited | C72: 29-07-2026 | D72: OEL/26-27/SII00633 | E72: WIP00015 | F72: PP MF Yarn Twisted | G72: 1 | H72: No PO | I72: 0 | J72: 1185.23 | K72: Kgs | L72: 1185.23 | M72: 0 | N72: 1185.23 | O72: GJ12BY0479, GJ09Z0572 | P72: K.P. Woven Pvt Ltd - Unit 3 -Purchase | Q72: K.P. Woven Pvt Ltd - Unit 3 -Purchase | R72: KPW/JW/93 | S72: 28-07-2026 | T72: JOB IN | U72: OTHER | V72: JBIN-OT 102 | W72: 146.99266 | X72: 0 | Y72: KPW/JW/93 | Z72: 28-07-2026 | AD72: by Truck | AE72: 28-07-2026 | AF72: 0 | AG72: 0 | AH72: 0 | AI72: 0 | AJ72: 0 | AK72: VAT | AL72: 0 | AM72: 0 | AN72: 0 | AO72: 0 | AP72: 0 | AR72: 0 | AS72: 0 | AT72: 0 | AU72: SF | AV72: Yarn All | AW72: PP Yarn | AX72: RM | AY72: erp | AZ72: 0 | BA72: 0 | BB72: 687 | BC72: 28-07-2026 | BD72: 24AAECK6307M2ZE | BE72: bharatd | BG72: 0 | BH72: 0 | BI72: 0 | BJ72: 0 | BK72: 0 | BL72: 0 | BM72: 0 | BN72: - | BO72: 46231.472 | BP72: 1185.23
B73: Oswal Extrusion Limited | C73: 29-07-2026 | D73: OEL/26-27/SII00633 | E73: WIP00013 | F73: LDPE/LLDPE Bags/Liner | G73: 2 | H73: No PO | I73: 0 | J73: 930 | K73: Kgs | L73: 930 | M73: 0 | N73: 930 | O73: GJ12BY0479, GJ09Z0572 | P73: K.P. Woven Pvt Ltd - Unit 3 -Purchase | Q73: K.P. Woven Pvt Ltd - Unit 3 -Purchase | R73: KPW/JW/93 | S73: 28-07-2026 | T73: JOB IN | U73: OTHER | V73: JBIN-OT 102 | W73: 174.60165 | X73: 0 | Y73: KPW/JW/93 | Z73: 28-07-2026 | AD73: by Truck | AE73: 28-07-2026 | AF73: 0 | AG73: 0 | AH73: 0 | AI73: 0 | AJ73: 0 | AK73: VAT | AL73: 0 | AM73: 0 | AN73: 0 | AO73: 0 | AP73: 0 | AR73: 0 | AS73: 0 | AT73: 0 | AU73: SF | AV73: Liners | AW73: LDPE/LLDPE Bags | AX73: RM | AY73: erp | AZ73: 0 | BA73: 0 | BB73: 687 | BC73: 28-07-2026 | BD73: 24AAECK6307M2ZE | BE73: bharatd | BG73: 0 | BH73: 0 | BI73: 0 | BJ73: 0 | BK73: 0 | BL73: 0 | BM73: 0 | BN73: - | BO73: 46231.472 | BP73: 930
B74: Oswal Extrusion Limited | C74: 29-07-2026 | D74: OEL/26-27/SII00633 | E74: WIP00025 | F74: PP Lam Fabric With UV | G74: 3 | H74: No PO | I74: 0 | J74: 2382 | K74: Kgs | L74: 2382 | M74: 0 | N74: 2382 | O74: GJ12BY0479, GJ09Z0572 | P74: K.P. Woven Pvt Ltd - Unit 3 -Purchase | Q74: K.P. Woven Pvt Ltd - Unit 3 -Purchase | R74: KPW/JW/93 | S74: 28-07-2026 | T74: JOB IN | U74: OTHER | V74: JBIN-OT 102 | W74: 142.00091 | X74: 0 | Y74: KPW/JW/93 | Z74: 28-07-2026 | AD74: by Truck | AE74: 28-07-2026 | AF74: 0 | AG74: 0 | AH74: 0 | AI74: 0 | AJ74: 0 | AK74: VAT | AL74: 0 | AM74: 0 | AN74: 0 | AO74: 0 | AP74: 0 | AR74: 0 | AS74: 0 | AT74: 0 | AU74: SF | AV74: PP/PE Fabric | AW74: PP Lam Fabric | AX74: RM | AY74: erp | AZ74: 0 | BA74: 0 | BB74: 687 | BC74: 28-07-2026 | BD74: 24AAECK6307M2ZE | BE74: bharatd | BG74: 0 | BH74: 0 | BI74: 0 | BJ74: 0 | BK74: 0 | BL74: 0 | BM74: 0 | BN74: - | BO74: 46231.472 | BP74: 2382
B75: Oswal Extrusion Limited | C75: 29-07-2026 | D75: OEL/26-27/SII00633 | E75: WIP00022 | F75: PP MF Yarn Twisted | G75: 4 | H75: No PO | I75: 0 | J75: 2019.7 | K75: Kgs | L75: 2019.7 | M75: 0 | N75: 2019.7 | O75: GJ12BY0479, GJ09Z0572 | P75: K.P. Woven Pvt Ltd - Unit 3 -Purchase | Q75: K.P. Woven Pvt Ltd - Unit 3 -Purchase | R75: KPW/JW/93 | S75: 28-07-2026 | T75: JOB IN | U75: OTHER | V75: JBIN-OT 102 | W75: 137 | X75: 0 | Y75: KPW/JW/93 | Z75: 28-07-2026 | AD75: by Truck | AE75: 28-07-2026 | AF75: 0 | AG75: 0 | AH75: 0 | AI75: 0 | AJ75: 0 | AK75: VAT | AL75: 0 | AM75: 0 | AN75: 0 | AO75: 0 | AP75: 0 | AR75: 0 | AS75: 0 | AT75: 0 | AU75: SF | AV75: Yarn All | AW75: PP Yarn | AX75: RM | AY75: erp | AZ75: 0 | BA75: 0 | BB75: 687 | BC75: 28-07-2026 | BD75: 24AAECK6307M2ZE | BE75: bharatd | BG75: 0 | BH75: 0 | BI75: 0 | BJ75: 0 | BK75: 0 | BL75: 0 | BM75: 0 | BN75: - | BO75: 46231.472 | BP75: 2019.7
B76: Oswal Extrusion Limited | C76: 30-07-2026 | D76: OEL/26-27/SII00638 | E76: WIP00025 | F76: PP Lam Fabric With UV | G76: 1 | H76: No PO | I76: 0 | J76: 4404 | K76: Kgs | L76: 4404 | M76: 0 | N76: 4404 | O76: GJ12BT2409 | P76: K.P. Woven Pvt Ltd - Unit 3 -Purchase | Q76: K.P. Woven Pvt Ltd - Unit 3 -Purchase | R76: KPW/JW/94 | S76: 29-07-2026 | T76: JOB IN | U76: OTHER | V76: JBIN-OT 103 | W76: 142.00095 | X76: 0 | Y76: KPW/JW/94 | Z76: 29-07-2026 | AD76: by Truck | AE76: 29-07-2026 | AF76: 0 | AG76: 0 | AH76: 0 | AI76: 0 | AJ76: 0 | AK76: VAT | AL76: 0 | AM76: 0 | AN76: 0 | AO76: 0 | AP76: 0 | AR76: 0 | AS76: 0 | AT76: 0 | AU76: SF | AV76: PP/PE Fabric | AW76: PP Lam Fabric | AX76: RM | AY76: erp | AZ76: 0 | BA76: 0 | BB76: 706 | BC76: 29-07-2026 | BD76: 24AAECK6307M2ZE | BE76: bharatd | BG76: 0 | BH76: 0 | BI76: 0 | BJ76: 0 | BK76: 0 | BL76: 0 | BM76: 0 | BN76: - | BO76: 46232.446 | BP76: 4404
B77: Oswal Extrusion Limited | C77: 31-07-2026 | D77: OEL/26-27/SII00649 | E77: WIP00023 | F77: PP UL Fabric With UV | G77: 1 | H77: No PO | I77: 0 | J77: 966 | K77: Kgs | L77: 966 | M77: 0 | N77: 966 | O77: GJ39T9710 | P77: K.P. Woven Pvt Ltd - Unit 3 -Purchase | Q77: K.P. Woven Pvt Ltd - Unit 3 -Purchase | R77: KPW/JW/95 | S77: 30-07-2026 | T77: JOB IN | U77: OTHER | V77: JBIN-OT 104 | W77: 103.04 | X77: 0 | Y77: KPW/JW/95 | Z77: 30-07-2026 | AD77: by Truck | AE77: 30-07-2026 | AF77: 0 | AG77: 0 | AH77: 0 | AI77: 0 | AJ77: 0 | AK77: VAT | AL77: 0 | AM77: 0 | AN77: 0 | AO77: 0 | AP77: 0 | AR77: 0 | AS77: 0 | AT77: 0 | AU77: SF | AV77: PP/PE Fabric | AW77: PP UL Fabric | AX77: RM | AY77: erp | AZ77: 0 | BA77: 0 | BB77: 718 | BC77: 30-07-2026 | BD77: 24AAECK6307M2ZE | BE77: bharatd | BG77: 0 | BH77: 0 | BI77: 0 | BJ77: 0 | BK77: 0 | BL77: 0 | BM77: 0 | BN77: - | BO77: 46233.505 | BP77: 966 | BQ77: 966
B78: Oswal Extrusion Limited | C78: 31-07-2026 | D78: OEL/26-27/SII00661 | E78: RAW06251 | F78: PP Granules | G78: 1 | H78: No PO | I78: 0 | J78: 108000 | K78: Kgs | L78: 108000 | M78: 0 | N78: 108000 | O78: GJ02Z4078 | P78: K.P. Woven Pvt Ltd - Unit 3 -Purchase | Q78: K.P. Woven Pvt Ltd - Unit 3 -Purchase | R78: KPW/JW/97 | S78: 31-07-2026 | T78: JOB IN | U78: OTHER | V78: JBIN-OT 105 | W78: 123.81319 | X78: 0 | Y78: KPW/JW/97 | Z78: 31-07-2026 | AD78: by Truck | AE78: 31-07-2026 | AF78: 0 | AG78: 0 | AH78: 0 | AI78: 0 | AJ78: 0 | AK78: VAT | AL78: 0 | AM78: 0 | AN78: 0 | AO78: 0 | AP78: 0 | AR78: 0 | AS78: 0 | AT78: 0 | AU78: RM | AV78: Granules | AW78: PP Granules | AX78: RM | AZ78: 0 | BA78: 0 | BB78: 727 | BC78: 31-07-2026 | BD78: 24AAECK6307M2ZE | BE78: bharatd | BG78: 0 | BH78: 0 | BI78: 0 | BJ78: 0 | BK78: 0 | BL78: 0 | BM78: 0 | BN78: - | BO78: 46234.675 | BP78: 108000
B79: Oswal Extrusion Limited | C79: 31-07-2026 | D79: OEL/26-27/SII00662 | E79: RAW05951 | F79: PP Tapes | G79: 2 | H79: No PO | I79: 0 | J79: 930.5 | K79: Kgs | L79: 930.5 | M79: 0 | N79: 930.5 | O79: GJ03CU3638, GJ03AX2024... | P79: K.P. Woven Pvt Ltd - Unit 3 -Purchase | Q79: K.P. Woven Pvt Ltd - Unit 3 -Purchase | R79: KPW/JW/96 | S79: 31-07-2026 | T79: JOB IN | U79: OTHER | V79: JBIN-OT 106 | W79: 134.49932 | X79: 0 | Y79: KPW/JW/96 | Z79: 31-07-2026 | AD79: by Truck | AE79: 31-07-2026 | AF79: 0 | AG79: 0 | AH79: 0 | AI79: 0 | AJ79: 0 | AK79: VAT | AL79: 0 | AM79: 0 | AN79: 0 | AO79: 0 | AP79: 0 | AR79: 0 | AS79: 0 | AT79: 0 | AU79: SF | AV79: Tape Stock | AW79: PP Tapes | AX79: RM | AY79: erp | AZ79: 0 | BA79: 0 | BB79: 726 | BC79: 31-07-2026 | BD79: 24AAECK6307M2ZE | BE79: bharatd | BG79: 0 | BH79: 0 | BI79: 0 | BJ79: 0 | BK79: 0 | BL79: 0 | BM79: 0 | BN79: - | BO79: 46234.681 | BP79: 930.5
B80: Oswal Extrusion Limited | C80: 31-07-2026 | D80: OEL/26-27/SII00662 | E80: WIP00025 | F80: PP Lam Fabric With UV | G80: 3 | H80: No PO | I80: 0 | J80: 5252 | K80: Kgs | L80: 5252 | M80: 0 | N80: 5252 | O80: GJ03CU3638, GJ03AX2024... | P80: K.P. Woven Pvt Ltd - Unit 3 -Purchase | Q80: K.P. Woven Pvt Ltd - Unit 3 -Purchase | R80: KPW/JW/96 | S80: 31-07-2026 | T80: JOB IN | U80: OTHER | V80: JBIN-OT 106 | W80: 142.00096 | X80: 0 | Y80: KPW/JW/96 | Z80: 31-07-2026 | AD80: by Truck | AE80: 31-07-2026 | AF80: 0 | AG80: 0 | AH80: 0 | AI80: 0 | AJ80: 0 | AK80: VAT | AL80: 0 | AM80: 0 | AN80: 0 | AO80: 0 | AP80: 0 | AR80: 0 | AS80: 0 | AT80: 0 | AU80: SF | AV80: PP/PE Fabric | AW80: PP Lam Fabric | AX80: RM | AY80: erp | AZ80: 0 | BA80: 0 | BB80: 726 | BC80: 31-07-2026 | BD80: 24AAECK6307M2ZE | BE80: bharatd | BG80: 0 | BH80: 0 | BI80: 0 | BJ80: 0 | BK80: 0 | BL80: 0 | BM80: 0 | BN80: - | BO80: 46234.681 | BP80: 5252
B81: Oswal Extrusion Limited | C81: 31-07-2026 | D81: OEL/26-27/SII00662 | E81: WIP00023 | F81: PP UL Fabric With UV | G81: 1 | H81: No PO | I81: 0 | J81: 3403 | K81: Kgs | L81: 3403 | M81: 0 | N81: 3403 | O81: GJ03CU3638, GJ03AX2024... | P81: K.P. Woven Pvt Ltd - Unit 3 -Purchase | Q81: K.P. Woven Pvt Ltd - Unit 3 -Purchase | R81: KPW/JW/96 | S81: 31-07-2026 | T81: JOB IN | U81: OTHER | V81: JBIN-OT 106 | W81: 138.94105 | X81: 0 | Y81: KPW/JW/96 | Z81: 31-07-2026 | AD81: by Truck | AE81: 31-07-2026 | AF81: 0 | AG81: 0 | AH81: 0 | AI81: 0 | AJ81: 0 | AK81: VAT | AL81: 0 | AM81: 0 | AN81: 0 | AO81: 0 | AP81: 0 | AR81: 0 | AS81: 0 | AT81: 0 | AU81: SF | AV81: PP/PE Fabric | AW81: PP UL Fabric | AX81: RM | AY81: erp | AZ81: 0 | BA81: 0 | BB81: 726 | BC81: 31-07-2026 | BD81: 24AAECK6307M2ZE | BE81: bharatd | BG81: 0 | BH81: 0 | BI81: 0 | BJ81: 0 | BK81: 0 | BL81: 0 | BM81: 0 | BN81: - | BO81: 46234.681 | BP81: 3403
B82: Oswal Extrusion Limited | C82: 31-07-2026 | D82: OEL/26-27/SII00662 | E82: WIP00015 | F82: PP MF Yarn Twisted | G82: 5 | H82: No PO | I82: 0 | J82: 1128.8 | K82: Kgs | L82: 1128.8 | M82: 0 | N82: 1128.8 | O82: GJ03CU3638, GJ03AX2024... | P82: K.P. Woven Pvt Ltd - Unit 3 -Purchase | Q82: K.P. Woven Pvt Ltd - Unit 3 -Purchase | R82: KPW/JW/96 | S82: 31-07-2026 | T82: JOB IN | U82: OTHER | V82: JBIN-OT 106 | W82: 148.55802 | X82: 0 | Y82: KPW/JW/96 | Z82: 31-07-2026 | AD82: by Truck | AE82: 31-07-2026 | AF82: 0 | AG82: 0 | AH82: 0 | AI82: 0 | AJ82: 0 | AK82: VAT | AL82: 0 | AM82: 0 | AN82: 0 | AO82: 0 | AP82: 0 | AR82: 0 | AS82: 0 | AT82: 0 | AU82: SF | AV82: Yarn All | AW82: PP Yarn | AX82: RM | AY82: erp | AZ82: 0 | BA82: 0 | BB82: 726 | BC82: 31-07-2026 | BD82: 24AAECK6307M2ZE | BE82: bharatd | BG82: 0 | BH82: 0 | BI82: 0 | BJ82: 0 | BK82: 0 | BL82: 0 | BM82: 0 | BN82: - | BO82: 46234.681 | BP82: 1128.8
B83: Oswal Extrusion Limited | C83: 31-07-2026 | D83: OEL/26-27/SII00662 | E83: WIP00013 | F83: LDPE/LLDPE Bags/Liner | G83: 4 | H83: No PO | I83: 0 | J83: 2594 | K83: Kgs | L83: 2594 | M83: 0 | N83: 2594 | O83: GJ03CU3638, GJ03AX2024... | P83: K.P. Woven Pvt Ltd - Unit 3 -Purchase | Q83: K.P. Woven Pvt Ltd - Unit 3 -Purchase | R83: KPW/JW/96 | S83: 31-07-2026 | T83: JOB IN | U83: OTHER | V83: JBIN-OT 106 | W83: 174.60206 | X83: 0 | Y83: KPW/JW/96 | Z83: 31-07-2026 | AD83: by Truck | AE83: 31-07-2026 | AF83: 0 | AG83: 0 | AH83: 0 | AI83: 0 | AJ83: 0 | AK83: VAT | AL83: 0 | AM83: 0 | AN83: 0 | AO83: 0 | AP83: 0 | AR83: 0 | AS83: 0 | AT83: 0 | AU83: SF | AV83: Liners | AW83: LDPE/LLDPE Bags | AX83: RM | AY83: erp | AZ83: 0 | BA83: 0 | BB83: 726 | BC83: 31-07-2026 | BD83: 24AAECK6307M2ZE | BE83: bharatd | BG83: 0 | BH83: 0 | BI83: 0 | BJ83: 0 | BK83: 0 | BL83: 0 | BM83: 0 | BN83: - | BO83: 46234.681 | BP83: 2594

Sheet Job Work Summary 
A1: Sr. No. | B1: Months | C1: Received Material | S1: Total Received Qty | U1: Opning Balance | V1: TOTAL Received Raw Material | W1: Total Send FIBC Jumbo & Fabrics Bags Qty | X1: Scrap | Y1: Closing Balance Qty
C2: PP Woven Fabric | D2: LLDPE Liner | E2: PP Webbing | F2: MASTERBATCH | G2: UV/MB | H2: LLDPE BLENDED FILM IN TUBULAR ROLLS | I2: PP GRANULES | J2: LDPE Granuals | K2: PP WOVEN FABRIC LAMINATED/COATED | L2: PP MF Yarn | M2: RP Granules | N2: FILLER | O2: PP/HD/LD WASTE | P2: FILLER CORD | Q2: PP TAPE | R2: HDPE Granuals | Z2: acc. Pro
B3: March Closing | C3: Kgs | D3: Kgs | E3: Kgs | F3: Kgs | G3: Kgs | H3: Kgs | I3: Kgs | J3: Kgs | K3: Kgs | L3: Kgs | M3: Kgs | N3: Kgs | O3: Kgs | Q3: Kgs | R3: Kgs | S3: Kgs | U3: Kgs | V3: Kgs | W3: Kgs | X3: Kgs | Y3: 657884.23
A4: 1 | B4: April | C4: 47218.9 | D4: 39624.8 | E4: 81 | F4: 700 | G4: 6575 | H4: 0 | I4: 196000 | J4: 0 | K4: 18916 | L4: 13674.7 | M4: 3000 | N4: 6000 | O4: 0 | P4: 0 | Q4: 8730.6 | R4: 0 | S4: =SUM(C4:R4) -> 340521 | U4: =+Y3 -> 657884.23 | V4: =+S4 -> 340521 | W4: 262003 | X4: 20774 | Y4: =+U4+V4-W4-X4+0.01 -> 715628.24 | Z4: 261837 | AA4: =+W4-Z4 -> 166
A5: =+A4+1 -> 2 | B5: May | C5: 42872.1 | D5: 79673.2 | E5: 468.9 | F5: 0 | G5: 800 | H5: 0 | I5: 0 | J5: 0 | K5: 2331 | L5: 15419.3 | M5: 1000 | N5: 2000 | O5: 0 | P5: 0 | Q5: 135746.05 | R5: 0 | S5: =SUM(C5:R5) -> 280310.55 | U5: =+Y4 -> 715628.24 | V5: =+S5 -> 280310.55 | W5: 251582 | X5: 7291.97 | Y5: =+U5+V5-W5-X5 -> 737064.82 | Z5: 253837 | AA5: =+W5-Z5 -> -2255
A6: =+A5+1 -> 3 | B6: June | C6: 55526.8 | D6: 50844.13 | E6: 171.4 | F6: 325 | G6: 8000 | H6: 0 | I6: 1250 | J6: 0 | K6: 24413 | L6: 17110.84 | M6: 0 | N6: 0 | O6: 0 | P6: 0 | Q6: 10984.1 | R6: 0 | S6: =SUM(C6:R6) -> 168625.27 | U6: =+Y5 -> 737064.82 | V6: =+S6 -> 168625.27 | W6: 283931.32 | X6: 10251 | Y6: =+U6+V6-W6-X6 -> 611507.77 | Z6: 306443 | AA6: =+W6-Z6 -> -22511.68
A7: =+A6+1 -> 4 | B7: July | C7: =+GETPIVOTDATA("Acceptedqty",'Job Received'!$A$1,"Itemname","PP UL Fabric With UV") -> 30749.3 | D7: =+GETPIVOTDATA("Acceptedqty",'Job Received'!$A$1,"Itemname","LDPE/LLDPE Bags/Liner") -> 36603.67 | E7: =+GETPIVOTDATA("Acceptedqty",'Job Received'!$A$1,"Itemname","Webbing") -> 100 | F7: =+GETPIVOTDATA("Acceptedqty",'Job Received'!$A$1,"Itemname","MB Karnavati Polyplast Blue") -> 150 | G7: =+GETPIVOTDATA("Acceptedqty",'Job Received'!$A$1,"Itemname","UV Arguvin FG 626 LD") -> 3975 | H7: 0 | I7: =+GETPIVOTDATA("Acceptedqty",'Job Received'!$A$1,"Itemname","PP Granules") -> 117000 | J7: =+GETPIVOTDATA("Acceptedqty",'Job Received'!$A$1,"Itemname","LDPE Sumitomo L705") -> 2000 | K7: =+GETPIVOTDATA("Acceptedqty",'Job Received'!$A$1,"Itemname","PP Lam Fabric With UV") -> 50112.1 | L7: =+GETPIVOTDATA("Acceptedqty",'Job Received'!$A$1,"Itemname","PP MF Yarn Twisted") -> 17007.23 | M7: 0 | N7: 0 | O7: 0 | P7: 0 | Q7: =+GETPIVOTDATA("Acceptedqty",'Job Received'!$A$1,"Itemname","PP Tapes") -> 8814.4 | R7: 0 | S7: =SUM(C7:R7) -> 266511.7 | U7: =+Y6 -> 611507.77 | V7: =+S7 -> 266511.7 | W7: =+GETPIVOTDATA("Sum of Quantity",'JOB issued'!$A$1,"sales Group Name","Jambo Bag/Fibc Bag Mfr (Kg)") -> 417716.34 | X7: =+GETPIVOTDATA("Sum of Quantity",'JOB issued'!$A$1,"sales Group Name","Scrap") -> 10643 | Y7: =+U7+V7-W7-X7 -> 449660.13 | Z7: 392491 | AA7: =+W7-Z7 -> 25225.34
A8: =+A7+1 -> 5 | B8: August | S8: =SUM(C8:R8) -> 0 | U8: =+Y7 -> 449660.13 | V8: =+S8 -> 0 | Y8: =+U8+V8-W8-X8 -> 449660.13 | AA8: =+W8-Z8 -> 0
A9: =+A8+1 -> 6 | B9: September | S9: =SUM(C9:R9) -> 0 | U9: =+Y8 -> 449660.13 | V9: =+S9 -> 0 | Y9: =+U9+V9-W9-X9 -> 449660.13 | AA9: =+W9-Z9 -> 0
A10: =+A9+1 -> 7 | B10: October | S10: =SUM(C10:R10) -> 0 | U10: =+Y9 -> 449660.13 | V10: =+S10 -> 0 | Y10: =+U10+V10-W10-X10 -> 449660.13 | AA10: =+W10-Z10 -> 0
A11: =+A10+1 -> 8 | B11: November | S11: =SUM(C11:R11) -> 0 | U11: =+Y10 -> 449660.13 | V11: =+S11 -> 0 | Y11: =+U11+V11-W11-X11 -> 449660.13 | AA11: =+W11-Z11 -> 0
A12: =+A11+1 -> 9 | B12: December | S12: =SUM(C12:R12) -> 0 | U12: =+Y11 -> 449660.13 | V12: =+S12 -> 0 | Y12: =+U12+V12-W12-X12 -> 449660.13 | AA12: =+W12-Z12 -> 0
A13: =+A12+1 -> 10 | B13: January | S13: =SUM(C13:R13) -> 0 | U13: =+Y12 -> 449660.13 | V13: =+S13 -> 0 | Y13: =+U13+V13-W13-X13 -> 449660.13 | AA13: =+W13-Z13 -> 0
A14: =+A13+1 -> 11 | B14: February | S14: =SUM(C14:R14) -> 0 | U14: =+Y13 -> 449660.13 | V14: =+S14 -> 0 | Y14: =+U14+V14-W14-X14 -> 449660.13 | AA14: =+W14-Z14 -> 0
A15: =+A14+1 -> 12 | B15: March | S15: =SUM(C15:R15) -> 0 | U15: =+Y14 -> 449660.13 | V15: =+S15 -> 0 | Y15: =+U15+V15-W15-X15 -> 449660.13 | AA15: =+W15-Z15 -> 0
U17: PIL-1 | V17: PP WOVEN BIG BAGS | Y17: =+'[1]Received from PIL 1165'!N427 -> 0
U19: PIL-1 | V19: PP WOVEN BIG BAGS | Y19: =+'Received from PIL 1060'!N362 -> 0
U21: PIL-1 | V21: PP WOVEN BIG BAGS | Y21: =+'Received from PIL 836'!N313 -> 277529.4 | AA21: =SUM(AA4:AA16) -> 624.66
U23: KPW-3 | V23: PP WOVEN BIG BAGS | Y23: =+'Received from KPW3'!N4301 -> 172130.73
U25: PPL | V25: PP WOVEN BIG BAGS | Y25: =+'[1]Received from PPL 1594'!N193 -> 0
V27: TOTAL BALANCE | Y27: =Y23+Y25+Y17+Y19+Y21 -> 449660.13
V29: DIFFRENCE BALANCE | Y29: =+Y15-Y27 -> -4.1909516e-09

Sheet Challan
A1: Sum of Balanced Qty | B1: Column Labels
A2: Row Labels | B2: K.P. Woven Pvt Ltd - Unit 3 -Sales | C2: Plastene India ltd - Unit 1-Sales | D2: Grand Total
A3: Filler Cord | B3: 2097.7 | D3: 2097.7
A4: LDPE/LLDPE Bags/Liner | B4: 14049.9 | D4: 14049.9
A5: LDPE/LLDPE Film | B5: 602.8 | D5: 602.8
A6: PP Lam Fabric With UV | B6: 27104.8 | D6: 27104.8
A7: PP MF Yarn Twisted | B7: 4480.23 | C7: 1707.9 | D7: 6188.13
A8: PP Tapes | B8: 2518.3 | D8: 2518.3
A9: PP UL Fabric With UV | B9: 13277 | D9: 13277
A10: Webbing | C10: 1771.8 | D10: 1771.8
A11: PP Granules | B11: 108000 | C11: 233299.7 | D11: 341299.7
A12: UV MB | C12: 25550 | D12: 25550
A13: LDPE Granules | C13: 15000 | D13: 15000
A14: MB | C14: 200 | D14: 200
A15: Grand Total | B15: 172130.73 | C15: 277529.4 | D15: 449660.13
D20: =+'Received from KPW3'!N4299+'Received from PIL 836'!N311 -> 449660.13
D22: =D15-D20 -> 0 | E22: Diff
B36: Year | C36: ProcessorName | D36: SubsidiaryBuyer | E36: MainChallan No | F36: MainChallan Date | G36: CommodityName | H36: THeading | I36: OrderQty | J36: QtyUnit | K36: Balanced Qty | L36: ChallanSrno | M36: ProcessorAddress | N36: SubsidiaryAddress | O36: subsidiaryyear | P36: Iteam Code | Q36: Deptt | R36: Group Name | S36: Sub Group Name | T36: Iteam Name | U36: Issu
B37: 26-27 | C37: Oswal Extrusion Limited | D37: K.P. Woven Pvt Ltd - Unit 3 -Sales | E37: 96 | F37: 46234 | G37: PP Woven Fabrics | H37: 39269080 | I37: 3403 | J37: Kgs | K37: 3403 | L37: 14113 | M37: Sector - 2, KASEZ, Plot No. 73/74/75 - A & A, Gandhidham - 370 230 Kutch | N37: PLOT NO. 27 TO 30,, SECTOR-1,, ,KANDLA SPECIAL ECONOMIC,,GANDHIDHAM, | O37: PP WOVEN BAGS/SACK | P37: WIP00023 | Q37: SF | R37: PP/PE Fabric | S37: PP UL Fabric | T37: PP UL Fabric With UV | U37: FALSE
B38: 26-27 | C38: Oswal Extrusion Limited | D38: K.P. Woven Pvt Ltd - Unit 3 -Sales | E38: 096-2 | F38: 46234 | G38: PP TAPE | H38: 39199090 | I38: 930.5 | J38: Kgs | K38: 930.5 | L38: 14113 | M38: Sector - 2, KASEZ, Plot No. 73/74/75 - A & A, Gandhidham - 370 230 Kutch | N38: PLOT NO. 27 TO 30,, SECTOR-1,, ,KANDLA SPECIAL ECONOMIC,,GANDHIDHAM, | O38: PP WOVEN BAGS/SACK | P38: RAW05951 | Q38: SF | R38: Tape Stock | S38: PP Tapes | T38: PP Tapes | U38: FALSE
B39: 26-27 | C39: Oswal Extrusion Limited | D39: K.P. Woven Pvt Ltd - Unit 3 -Sales | E39: 096-3 | F39: 46234 | G39: PP Woven Fabrics Laminated / Coated | H39: 39269080 | I39: 5252 | J39: Kgs | K39: 5252 | L39: 14113 | M39: Sector - 2, KASEZ, Plot No. 73/74/75 - A & A, Gandhidham - 370 230 Kutch | N39: PLOT NO. 27 TO 30,, SECTOR-1,, ,KANDLA SPECIAL ECONOMIC,,GANDHIDHAM, | O39: PP WOVEN BAGS/SACK | P39: WIP00025 | Q39: SF | R39: PP/PE Fabric | S39: PP Lam Fabric | T39: PP Lam Fabric With UV | U39: FALSE
B40: 26-27 | C40: Oswal Extrusion Limited | D40: K.P. Woven Pvt Ltd - Unit 3 -Sales | E40: 096-4 | F40: 46234 | G40: LD/LLDPE BAGS | H40: 39232100 | I40: 2594 | J40: Kgs | K40: 2594 | L40: 14113 | M40: Sector - 2, KASEZ, Plot No. 73/74/75 - A & A, Gandhidham - 370 230 Kutch | N40: PLOT NO. 27 TO 30,, SECTOR-1,, ,KANDLA SPECIAL ECONOMIC,,GANDHIDHAM, | O40: PP WOVEN BAGS/SACK | P40: WIP00013 | Q40: SF | R40: Liners | S40: LDPE/LLDPE Bags | T40: LDPE/LLDPE Bags/Liner | U40: FALSE
B41: 26-27 | C41: Oswal Extrusion Limited | D41: K.P. Woven Pvt Ltd - Unit 3 -Sales | E41: 096-5 | F41: 46234 | G41: Polypropylene Multifilament Yarn | H41: 54026930 | I41: 1128.8 | J41: Kgs | K41: 1128.8 | L41: 14113 | M41: Sector - 2, KASEZ, Plot No. 73/74/75 - A & A, Gandhidham - 370 230 Kutch | N41: PLOT NO. 27 TO 30,, SECTOR-1,, ,KANDLA SPECIAL ECONOMIC,,GANDHIDHAM, | O41: PP WOVEN BAGS/SACK | P41: WIP00015 | Q41: SF | R41: Yarn All | S41: PP Yarn | T41: PP MF Yarn Twisted | U41: FALSE
B42: 26-27 | C42: Oswal Extrusion Limited | D42: K.P. Woven Pvt Ltd - Unit 3 -Sales | E42: 97 | F42: 46234 | G42: Polypropylene Granuals | H42: 39021000 | I42: 108000 | J42: Kgs | K42: 108000 | L42: 14113 | M42: Sector - 2, KASEZ, Plot No. 73/74/75 - A & A, Gandhidham - 370 230 Kutch | N42: PLOT NO. 27 TO 30,, SECTOR-1,, ,KANDLA SPECIAL ECONOMIC,,GANDHIDHAM, | O42: PP WOVEN BAGS/SACK | P42: RAW06251 | Q42: RM | R42: Granules | S42: PP Granules | T42: PP Granules | U42: FALSE
B43: 26-27 | C43: Oswal Extrusion Limited | D43: K.P. Woven Pvt Ltd - Unit 3 -Sales | E43: 95 | F43: 46233 | G43: PP Woven Fabrics | H43: 39269080 | I43: 966 | J43: Kgs | K43: 966 | L43: 14112 | M43: Sector - 2, KASEZ, Plot No. 73/74/75 - A & A, Gandhidham - 370 230 Kutch | N43: PLOT NO. 27 TO 30,, SECTOR-1,, ,KANDLA SPECIAL ECONOMIC,,GANDHIDHAM, | O43: PP WOVEN BAGS/SACK | P43: WIP00023 | Q43: SF | R43: PP/PE Fabric | S43: PP UL Fabric | T43: PP UL Fabric With UV | U43: FALSE
B44: 26-27 | C44: Oswal Extrusion Limited | D44: K.P. Woven Pvt Ltd - Unit 3 -Sales | E44: 94 | F44: 46232 | G44: PP Woven Fabrics Laminated / Coated | H44: 39269080 | I44: 4404 | J44: Kgs | K44: 4404 | L44: 14111 | M44: Sector - 2, KASEZ, Plot No. 73/74/75 - A & A, Gandhidham - 370 230 Kutch | N44: PLOT NO. 27 TO 30,, SECTOR-1,, ,KANDLA SPECIAL ECONOMIC,,GANDHIDHAM, | O44: PP WOVEN BAGS/SACK | P44: WIP00025 | Q44: SF | R44: PP/PE Fabric | S44: PP Lam Fabric | T44: PP Lam Fabric With UV | U44: FALSE
B45: 26-27 | C45: Oswal Extrusion Limited | D45: Plastene India ltd - Unit 1-Sales | E45: 71 | F45: 46231 | G45: LDPE GRANULE | H45: 39011090 | I45: 2000 | J45: Kgs | K45: 2000 | L45: 14110 | M45: Sector - 2, KASEZ, Plot No. 73/74/75 - A & A, Gandhidham - 370 230 Kutch | N45: Survey No 315/1,315/2,316 & 317,Nani Chirai Nr.Softel Company ,Taluka-Bhachau | O45: PP WOVEN BAGS/SACK | P45: RAW05270 | Q45: RM | R45: Granules | S45: LDPE Granules | T45: LDPE Granules | U45: FALSE
B46: 26-27 | C46: Oswal Extrusion Limited | D46: K.P. Woven Pvt Ltd - Unit 3 -Sales | E46: 93 | F46: 46231 | G46: Polypropylene Multifilament Yarn | H46: 54026930 | I46: 1185.23 | J46: Kgs | K46: 1185.23 | L46: 14109 | M46: Sector - 2, KASEZ, Plot No. 73/74/75 - A & A, Gandhidham - 370 230 Kutch | N46: PLOT NO. 27 TO 30,, SECTOR-1,, ,KANDLA SPECIAL ECONOMIC,,GANDHIDHAM, | O46: PP WOVEN BAGS/SACK | P46: WIP00015 | Q46: SF | R46: Yarn All | S46: PP Yarn | T46: PP MF Yarn Twisted | U46: FALSE
B47: 26-27 | C47: Oswal Extrusion Limited | D47: K.P. Woven Pvt Ltd - Unit 3 -Sales | E47: 093-2 | F47: 46231 | G47: LD/LLDPE BAGS | H47: 39232100 | I47: 930 | J47: Kgs | K47: 930 | L47: 14109 | M47: Sector - 2, KASEZ, Plot No. 73/74/75 - A & A, Gandhidham - 370 230 Kutch | N47: PLOT NO. 27 TO 30,, SECTOR-1,, ,KANDLA SPECIAL ECONOMIC,,GANDHIDHAM, | O47: PP WOVEN BAGS/SACK | P47: WIP00013 | Q47: SF | R47: Liners | S47: LDPE/LLDPE Bags | T47: LDPE/LLDPE Bags/Liner | U47: FALSE
B48: 26-27 | C48: Oswal Extrusion Limited | D48: K.P. Woven Pvt Ltd - Unit 3 -Sales | E48: 093-3 | F48: 46231 | G48: PP Woven Fabrics Laminated / Coated | H48: 39269080 | I48: 2382 | J48: Kgs | K48: 2382 | L48: 14109 | M48: Sector - 2, KASEZ, Plot No. 73/74/75 - A & A, Gandhidham - 370 230 Kutch | N48: PLOT NO. 27 TO 30,, SECTOR-1,, ,KANDLA SPECIAL ECONOMIC,,GANDHIDHAM, | O48: PP WOVEN BAGS/SACK | P48: WIP00025 | Q48: SF | R48: PP/PE Fabric | S48: PP Lam Fabric | T48: PP Lam Fabric With UV | U48: FALSE
B49: 26-27 | C49: Oswal Extrusion Limited | D49: K.P. Woven Pvt Ltd - Unit 3 -Sales | E49: 093-4 | F49: 46231 | G49: FILLER CORD | H49: 54026300 | I49: 2019.7 | J49: Kgs | K49: 2019.7 | L49: 14109 | M49: Sector - 2, KASEZ, Plot No. 73/74/75 - A & A, Gandhidham - 370 230 Kutch | N49: PLOT NO. 27 TO 30,, SECTOR-1,, ,KANDLA SPECIAL ECONOMIC,,GANDHIDHAM, | O49: PP WOVEN BAGS/SACK | P49: WIP00022 | Q49: SF | R49: Yarn All | S49: PP Yarn | T49: Filler Cord | U49: FALSE
B50: 26-27 | C50: Oswal Extrusion Limited | D50: Plastene India ltd - Unit 1-Sales | E50: 65 | F50: 46228 | G50: Polypropylene Granuals | H50: 39021000 | I50: 5000 | J50: Kgs | K50: 5000 | L50: 14108 | M50: Sector - 2, KASEZ, Plot No. 73/74/75 - A & A, Gandhidham - 370 230 Kutch | N50: Survey No 315/1,315/2,316 & 317,Nani Chirai Nr.Softel Company ,Taluka-Bhachau | O50: PP WOVEN BAGS/SACK | P50: RAW06268 | Q50: RM | R50: Granules | S50: PP Granules | T50: PP Granules | U50: FALSE
B51: 26-27 | C51: Oswal Extrusion Limited | D51: Plastene India ltd - Unit 1-Sales | E51: 65-2 | F51: 46228 | G51: U.V. STABILIZER MASTER BATCH | H51: 38123990 | I51: 2475 | J51: Kgs | K51: 2475 | L51: 14108 | M51: Sector - 2, KASEZ, Plot No. 73/74/75 - A & A, Gandhidham - 370 230 Kutch | N51: Survey No 315/1,315/2,316 & 317,Nani Chirai Nr.Softel Company ,Taluka-Bhachau | O51: PP WOVEN BAGS/SACK | P51: RAW05089 | Q51: RM | R51: Granules | S51: UV MB | T51: UV MB | U51: FALSE
B52: 26-27 | C52: Oswal Extrusion Limited | D52: K.P. Woven Pvt Ltd - Unit 3 -Sales | E52: 92 | F52: 46230 | G52: PP Woven Fabrics | H52: 39269080 | I52: 5288 | J52: Kgs | K52: 5288 | L52: 14107 | M52: Sector - 2, KASEZ, Plot No. 73/74/75 - A & A, Gandhidham - 370 230 Kutch | N52: PLOT NO. 27 TO 30,, SECTOR-1,, ,KANDLA SPECIAL ECONOMIC,,GANDHIDHAM, | O52: PP WOVEN BAGS/SACK | P52: WIP00023 | Q52: SF | R52: PP/PE Fabric | S52: PP UL Fabric | T52: PP UL Fabric With UV | U52: FALSE
B53: 26-27 | C53: Oswal Extrusion Limited | D53: K.P. Woven Pvt Ltd - Unit 3 -Sales | E53: 092-2 | F53: 46230 | G53: LD/LLDPE BAGS | H53: 39232100 | I53: 3545.5 | J53: Kgs | K53: 3545.5 | L53: 14107 | M53: Sector - 2, KASEZ, Plot No. 73/74/75 - A & A, Gandhidham - 370 230 Kutch | N53: PLOT NO. 27 TO 30,, SECTOR-1,, ,KANDLA SPECIAL ECONOMIC,,GANDHIDHAM, | O53: PP WOVEN BAGS/SACK | P53: WIP00013 | Q53: SF | R53: Liners | S53: LDPE/LLDPE Bags | T53: LDPE/LLDPE Bags/Liner | U53: FALSE
B54: 26-27 | C54: Oswal Extrusion Limited | D54: K.P. Woven Pvt Ltd - Unit 3 -Sales | E54: 092-3 | F54: 46230 | G54: LLDPE BLENDED FILM IN TUBULAR ROLLS | H54: 39201019 | I54: 187 | J54: Kgs | K54: 187 | L54: 14107 | M54: Sector - 2, KASEZ, Plot No. 73/74/75 - A & A, Gandhidham - 370 230 Kutch | N54: PLOT NO. 27 TO 30,, SECTOR-1,, ,KANDLA SPECIAL ECONOMIC,,GANDHIDHAM, | O54: PP WOVEN BAGS/SACK | P54: RAW05124 | Q54: SF | R54: Films All (SF) | S54: PE Film | T54: LDPE/LLDPE Film | U54: FALSE
B55: 26-27 | C55: Oswal Extrusion Limited | D55: K.P. Woven Pvt Ltd - Unit 3 -Sales | E55: 092-4 | F55: 46230 | G55: PP TAPE | H55: 39199090 | I55: 1092 | J55: Kgs | K55: 1092 | L55: 14107 | M55: Sector - 2, KASEZ, Plot No. 73/74/75 - A & A, Gandhidham - 370 230 Kutch | N55: PLOT NO. 27 TO 30,, SECTOR-1,, ,KANDLA SPECIAL ECONOMIC,,GANDHIDHAM, | O55: PP WOVEN BAGS/SACK | P55: RAW05951 | Q55: SF | R55: Tape Stock | S55: PP Tapes | T55: PP Tapes | U55: FALSE
B56: 26-27 | C56: Oswal Extrusion Limited | D56: K.P. Woven Pvt Ltd - Unit 3 -Sales | E56: 092-5 | F56: 46230 | G56: PP woven fabrics laminated/ coated | H56: 39269080 | I56: 6551 | J56: Kgs | K56: 6551 | L56: 14107 | M56: Sector - 2, KASEZ, Plot No. 73/74/75 - A & A, Gandhidham - 370 230 Kutch | N56: PLOT NO. 27 TO 30,, SECTOR-1,, ,KANDLA SPECIAL ECONOMIC,,GANDHIDHAM, | O56: PP WOVEN BAGS/SACK | P56: WIP00025 | Q56: SF | R56: PP/PE Fabric | S56: PP Lam Fabric | T56: PP Lam Fabric With UV | U56: FALSE
B57: 26-27 | C57: Oswal Extrusion Limited | D57: K.P. Woven Pvt Ltd - Unit 3 -Sales | E57: 91 | F57: 46228 | G57: LLDPE BLENDED FILM IN TUBULAR ROLLS | H57: 39201019 | I57: 311.8 | J57: Kgs | K57: 311.8 | L57: 14105 | M57: Sector - 2, KASEZ, Plot No. 73/74/75 - A & A, Gandhidham - 370 230 Kutch | N57: PLOT NO. 27 TO 30,, SECTOR-1,, ,KANDLA SPECIAL ECONOMIC,,GANDHIDHAM, | O57: PP WOVEN BAGS/SACK | P57: RAW05124 | Q57: SF | R57: Films All (SF) | S57: PE Film | T57: LDPE/LLDPE Film | U57: FALSE
B58: 26-27 | C58: Oswal Extrusion Limited | D58: K.P. Woven Pvt Ltd - Unit 3 -Sales | E58: 091-2 | F58: 46228 | G58: PP woven fabrics laminated/ coated | H58: 39269080 | I58: 3592.8 | J58: Kgs | K58: 3592.8 | L58: 14105 | M58: Sector - 2, KASEZ, Plot No. 73/74/75 - A & A, Gandhidham - 370 230 Kutch | N58: PLOT NO. 27 TO 30,, SECTOR-1,, ,KANDLA SPECIAL ECONOMIC,,GANDHIDHAM, | O58: PP WOVEN BAGS/SACK | P58: WIP00025 | Q58: SF | R58: PP/PE Fabric | S58: PP Lam Fabric | T58: PP Lam Fabric With UV | U58: FALSE
B59: 26-27 | C59: Oswal Extrusion Limited | D59: K.P. Woven Pvt Ltd - Unit 3 -Sales | E59: 091-3 | F59: 46228 | G59: PP TAPE | H59: 39199090 | I59: 495.8 | J59: Kgs | K59: 495.8 | L59: 14105 | M59: Sector - 2, KASEZ, Plot No. 73/74/75 - A & A, Gandhidham - 370 230 Kutch | N59: PLOT NO. 27 TO 30,, SECTOR-1,, ,KANDLA SPECIAL ECONOMIC,,GANDHIDHAM, | O59: PP WOVEN BAGS/SACK | P59: RAW05951 | Q59: SF | R59: Tape Stock | S59: PP Tapes | T59: PP Tapes | U59: FALSE
B60: 26-27 | C60: Oswal Extrusion Limited | D60: K.P. Woven Pvt Ltd - Unit 3 -Sales | E60: 091-4 | F60: 46228 | G60: PP Woven Fabrics | H60: 39269080 | I60: 268 | J60: Kgs | K60: 268 | L60: 14105 | M60: Sector - 2, KASEZ, Plot No. 73/74/75 - A & A, Gandhidham - 370 230 Kutch | N60: PLOT NO. 27 TO 30,, SECTOR-1,, ,KANDLA SPECIAL ECONOMIC,,GANDHIDHAM, | O60: PP WOVEN BAGS/SACK | P60: WIP00023 | Q60: SF | R60: PP/PE Fabric | S60: PP UL Fabric | T60: PP UL Fabric With UV | U60: FALSE
B61: 26-27 | C61: Oswal Extrusion Limited | D61: K.P. Woven Pvt Ltd - Unit 3 -Sales | E61: 90 | F61: 46227 | G61: LLDPE BLENDED FILM IN TUBULAR ROLLS | H61: 39201019 | I61: 104 | J61: Kgs | K61: 104 | L61: 14103 | M61: Sector - 2, KASEZ, Plot No. 73/74/75 - A & A, Gandhidham - 370 230 Kutch | N61: PLOT NO. 27 TO 30,, SECTOR-1,, ,KANDLA SPECIAL ECONOMIC,,GANDHIDHAM, | O61: PP WOVEN BAGS/SACK | P61: RAW05124 | Q61: SF | R61: Films All (SF) | S61: PE Film | T61: LDPE/LLDPE Film | U61: FALSE
B62: 26-27 | C62: Oswal Extrusion Limited | D62: K.P. Woven Pvt Ltd - Unit 3 -Sales | E62: 090-2 | F62: 46227 | G62: PP Woven Fabrics | H62: 39269080 | I62: 2698 | J62: Kgs | K62: 2698 | L62: 14103 | M62: Sector - 2, KASEZ, Plot No. 73/74/75 - A & A, Gandhidham - 370 230 Kutch | N62: PLOT NO. 27 TO 30,, SECTOR-1,, ,KANDLA SPECIAL ECONOMIC,,GANDHIDHAM, | O62: PP WOVEN BAGS/SACK | P62: WIP00023 | Q62: SF | R62: PP/PE Fabric | S62: PP UL Fabric | T62: PP UL Fabric With UV | U62: FALSE
B63: 26-27 | C63: Oswal Extrusion Limited | D63: K.P. Woven Pvt Ltd - Unit 3 -Sales | E63: 090-3 | F63: 46227 | G63: PP woven fabrics laminated/ coated | H63: 39269080 | I63: 4164 | J63: Kgs | K63: 4164 | L63: 14103 | M63: Sector - 2, KASEZ, Plot No. 73/74/75 - A & A, Gandhidham - 370 230 Kutch | N63: PLOT NO. 27 TO 30,, SECTOR-1,, ,KANDLA SPECIAL ECONOMIC,,GANDHIDHAM, | O63: PP WOVEN BAGS/SACK | P63: WIP00025 | Q63: SF | R63: PP/PE Fabric | S63: PP Lam Fabric | T63: PP Lam Fabric With UV | U63: FALSE
B64: 26-27 | C64: Oswal Extrusion Limited | D64: K.P. Woven Pvt Ltd - Unit 3 -Sales | E64: 090-4 | F64: 46227 | G64: Polypropylene Multifilament Yarn | H64: 54026930 | I64: 2166.2 | J64: Kgs | K64: 2166.2 | L64: 14103 | M64: Sector - 2, KASEZ, Plot No. 73/74/75 - A & A, Gandhidham - 370 230 Kutch | N64: PLOT NO. 27 TO 30,, SECTOR-1,, ,KANDLA SPECIAL ECONOMIC,,GANDHIDHAM, | O64: PP WOVEN BAGS/SACK | P64: WIP00015 | Q64: SF | R64: Yarn All | S64: PP Yarn | T64: PP MF Yarn Twisted | U64: FALSE
B65: 26-27 | C65: Oswal Extrusion Limited | D65: K.P. Woven Pvt Ltd - Unit 3 -Sales | E65: 090-5 | F65: 46227 | G65: LD/LLDPE BAGS | H65: 39232100 | I65: 6980.4 | J65: Kgs | K65: 6980.4 | L65: 14103 | M65: Sector - 2, KASEZ, Plot No. 73/74/75 - A & A, Gandhidham - 370 230 Kutch | N65: PLOT NO. 27 TO 30,, SECTOR-1,, ,KANDLA SPECIAL ECONOMIC,,GANDHIDHAM, | O65: PP WOVEN BAGS/SACK | P65: WIP00013 | Q65: SF | R65: Liners | S65: LDPE/LLDPE Bags | T65: LDPE/LLDPE Bags/Liner | U65: FALSE
B66: 26-27 | C66: Oswal Extrusion Limited | D66: K.P. Woven Pvt Ltd - Unit 3 -Sales | E66: 089-2 | F66: 46225 | G66: PP woven fabrics laminated/ coated | H66: 39269080 | I66: 2479 | J66: Kgs | K66: 114 | L66: 14102 | M66: Sector - 2, KASEZ, Plot No. 73/74/75 - A & A, Gandhidham - 370 230 Kutch | N66: PLOT NO. 27 TO 30,, SECTOR-1,, ,KANDLA SPECIAL ECONOMIC,,GANDHIDHAM, | O66: PP WOVEN BAGS/SACK | P66: WIP00025 | Q66: SF | R66: PP/PE Fabric | S66: PP Lam Fabric | T66: PP Lam Fabric With UV | U66: FALSE
B67: 26-27 | C67: Oswal Extrusion Limited | D67: K.P. Woven Pvt Ltd - Unit 3 -Sales | E67: 88 | F67: 46224 | G67: PP Woven Fabrics | H67: 39269080 | I67: 3134 | J67: Kgs | K67: 264 | L67: 14101 | M67: Sector - 2, KASEZ, Plot No. 73/74/75 - A & A, Gandhidham - 370 230 Kutch | N67: PLOT NO. 27 TO 30,, SECTOR-1,, ,KANDLA SPECIAL ECONOMIC,,GANDHIDHAM, | O67: PP WOVEN BAGS/SACK | P67: WIP00023 | Q67: SF | R67: PP/PE Fabric | S67: PP UL Fabric | T67: PP UL Fabric With UV | U67: FALSE
B68: 26-27 | C68: Oswal Extrusion Limited | D68: K.P. Woven Pvt Ltd - Unit 3 -Sales | E68: 087-2 | F68: 46223 | G68: PP Woven Fabrics Laminated/ Coated | H68: 39269080 | I68: 3710.3 | J68: Kgs | K68: 235 | L68: 14100 | M68: Sector - 2, KASEZ, Plot No. 73/74/75 - A & A, Gandhidham - 370 230 Kutch | N68: PLOT NO. 27 TO 30,, SECTOR-1,, ,KANDLA SPECIAL ECONOMIC,,GANDHIDHAM, | O68: PP WOVEN BAGS/SACK | P68: WIP00025 | Q68: SF | R68: PP/PE Fabric | S68: PP Lam Fabric | T68: PP Lam Fabric With UV | U68: FALSE
B69: 26-27 | C69: Oswal Extrusion Limited | D69: K.P. Woven Pvt Ltd - Unit 3 -Sales | E69: 86 | F69: 46221 | G69: PP Woven Fabrics | H69: 39269080 | I69: 1763 | J69: Kgs | K69: 390 | L69: 14099 | M69: Sector - 2, KASEZ, Plot No. 73/74/75 - A & A, Gandhidham - 370 230 Kutch | N69: PLOT NO. 27 TO 30,, SECTOR-1,, ,KANDLA SPECIAL ECONOMIC,,GANDHIDHAM, | O69: PP WOVEN BAGS/SACK | P69: WIP00023 | Q69: SF | R69: PP/PE Fabric | S69: PP UL Fabric | T69: PP UL Fabric With UV | U69: FALSE
B70: 26-27 | C70: Oswal Extrusion Limited | D70: Plastene India ltd - Unit 1-Sales | E70: 49 | F70: 46220 | G70: MASTERBATCH/UV | H70: 32061190 | I70: 1500 | J70: Kgs | K70: 1500 | L70: 14098 | M70: Sector - 2, KASEZ, Plot No. 73/74/75 - A & A, Gandhidham - 370 230 Kutch | N70: Survey No 315/1,315/2,316 & 317,Nani Chirai Nr.Softel Company ,Taluka-Bhachau | O70: PP WOVEN BAGS/SACK | P70: RAW05516 | Q70: RM | R70: Granules | S70: UV MB | T70: UV MB | U70: FALSE
B71: 26-27 | C71: Oswal Extrusion Limited | D71: K.P. Woven Pvt Ltd - Unit 3 -Sales | E71: 085-3 | F71: 46220 | G71: PP Woven Fabrics Laminated/ Coated | H71: 39269080 | I71: 3887 | J71: Kgs | K71: 248 | L71: 14097 | M71: Sector - 2, KASEZ, Plot No. 73/74/75 - A & A, Gandhidham - 370 230 Kutch | N71: PLOT NO. 27 TO 30,, SECTOR-1,, ,KANDLA SPECIAL ECONOMIC,,GANDHIDHAM, | O71: PP WOVEN BAGS/SACK | P71: WIP00025 | Q71: SF | R71: PP/PE Fabric | S71: PP Lam Fabric | T71: PP Lam Fabric With UV | U71: FALSE
B72: 26-27 | C72: Oswal Extrusion Limited | D72: K.P. Woven Pvt Ltd - Unit 3 -Sales | E72: 84 | F72: 46219 | G72: PP Woven Fabrics Laminated/ Coated | H72: 39269080 | I72: 2369 | J72: Kgs | K72: 162 | L72: 14095 | M72: Sector - 2, KASEZ, Plot No. 73/74/75 - A & A, Gandhidham - 370 230 Kutch | N72: PLOT NO. 27 TO 30,, SECTOR-1,, ,KANDLA SPECIAL ECONOMIC,,GANDHIDHAM, | O72: PP WOVEN BAGS/SACK | P72: WIP00025 | Q72: SF | R72: PP/PE Fabric | S72: PP Lam Fabric | T72: PP Lam Fabric With UV | U72: FALSE
B73: 26-27 | C73: Oswal Extrusion Limited | D73: K.P. Woven Pvt Ltd - Unit 3 -Sales | E73: 83 | F73: 46218 | G73: FILLERCORD | H73: 54026300 | I73: 1963 | J73: Kgs | K73: 78 | L73: 14094 | M73: Sector - 2, KASEZ, Plot No. 73/74/75 - A & A, Gandhidham - 370 230 Kutch | N73: PLOT NO. 27 TO 30,, SECTOR-1,, ,KANDLA SPECIAL ECONOMIC,,GANDHIDHAM, | O73: PP WOVEN BAGS/SACK | P73: WIP00022 | Q73: SF | R73: Yarn All | S73: PP Yarn | T73: Filler Cord | U73: FALSE
B74: 26-27 | C74: Oswal Extrusion Limited | D74: Plastene India ltd - Unit 1-Sales | E74: 44 | F74: 46211 | G74: MASTERBATCH | H74: 32064990 | I74: 150 | J74: Kgs | K74: 150 | L74: 14076 | M74: Sector - 2, KASEZ, Plot No. 73/74/75 - A & A, Gandhidham - 370 230 Kutch | N74: Survey No 315/1,315/2,316 & 317,Nani Chirai Nr.Softel Company ,Taluka-Bhachau | O74: PP WOVEN BAGS/SACK | P74: RAW06279 | Q74: RM | R74: Granules | S74: Masterbatch | T74: MB | U74: FALSE
B75: 26-27 | C75: Oswal Extrusion Limited | D75: Plastene India ltd - Unit 1-Sales | E75: 44-2 | F75: 46211 | G75: Polypropylene Granuals | H75: 39021000 | I75: 2000 | J75: Kgs | K75: 2000 | L75: 14076 | M75: Sector - 2, KASEZ, Plot No. 73/74/75 - A & A, Gandhidham - 370 230 Kutch | N75: Survey No 315/1,315/2,316 & 317,Nani Chirai Nr.Softel Company ,Taluka-Bhachau | O75: PP WOVEN BAGS/SACK | P75: RAW05130 | Q75: RM | R75: Granules | S75: PP Granules | T75: PP Granules | U75: FALSE
B76: 26-27 | C76: Oswal Extrusion Limited | D76: Plastene India ltd - Unit 1-Sales | E76: 36 | F76: 46197 | G76: PP WEBBING | H76: 39269080 | I76: 115.7 | J76: Kgs | K76: 115.7 | L76: 14059 | M76: Sector - 2, KASEZ, Plot No. 73/74/75 - A & A, Gandhidham - 370 230 Kutch | N76: Survey No 315/1,315/2,316 & 317,Nani Chirai Nr.Softel Company ,Taluka-Bhachau | O76: PP WOVEN BAGS/SACK | P76: WIP00032 | Q76: SF | R76: Webbing | S76: PP Webbing | T76: Webbing | U76: FALSE
B77: 26-27 | C77: Oswal Extrusion Limited | D77: Plastene India ltd - Unit 1-Sales | E77: 34 | F77: 46195 | G77: U.V. Stabilizer Master Batch | H77: 38123990 | I77: 2000 | J77: Kgs | K77: 2000 | L77: 14051 | M77: Sector - 2, KASEZ, Plot No. 73/74/75 - A & A, Gandhidham - 370 230 Kutch | N77: Survey No 315/1,315/2,316 & 317,Nani Chirai Nr.Softel Company ,Taluka-Bhachau | O77: PP WOVEN BIG BAGS/SACKS | P77: RAW05516 | Q77: RM | R77: Granules | S77: UV MB | T77: UV MB | U77: FALSE
B78: 26-27 | C78: Oswal Extrusion Limited | D78: Plastene India ltd - Unit 1-Sales | E78: 33 | F78: 46192 | G78: U.V. Stabilizer Master Batch | H78: 38123990 | I78: 3000 | J78: Kgs | K78: 3000 | L78: 14051 | M78: Sector - 2, KASEZ, Plot No. 73/74/75 - A & A, Gandhidham - 370 230 Kutch | N78: Survey No 315/1,315/2,316 & 317,Nani Chirai Nr.Softel Company ,Taluka-Bhachau | O78: PP WOVEN BIG BAGS/SACKS | P78: RAW05516 | Q78: RM | R78: Granules | S78: UV MB | T78: UV MB | U78: FALSE
B79: 26-27 | C79: Oswal Extrusion Limited | D79: Plastene India ltd - Unit 1-Sales | E79: 31 | F79: 46181 | G79: U.V. Stabilizer Master Batch | H79: 38123990 | I79: 3000 | J79: Kgs | K79: 3000 | L79: 14037 | M79: Sector - 2, KASEZ, Plot No. 73/74/75 - A & A, Gandhidham - 370 230 Kutch | N79: Survey No 315/1,315/2,316 & 317,Nani Chirai Nr.Softel Company ,Taluka-Bhachau | O79: PP WOVEN BIG BAGS/SACKS | P79: RAW05516 | Q79: RM | R79: Granules | S79: UV MB | T79: UV MB | U79: FALSE
B80: 26-27 | C80: Oswal Extrusion Limited | D80: Plastene India ltd - Unit 1-Sales | E80: 1 | F80: 46114 | G80: MASTERBATCH/UV | H80: 32061190 | I80: 6575 | J80: Kgs | K80: 6575 | L80: 13942 | M80: Sector - 2, KASEZ, Plot No. 73/74/75 - A & A, Gandhidham - 370 230 Kutch | N80: Survey No 315/1,315/2,316 & 317,Nani Chirai Nr.Softel Company ,Taluka-Bhachau | O80: PP WOVEN BAGS/SACK | P80: RAW05516 | Q80: RM | R80: Granules | S80: UV MB | T80: UV MB | U80: FALSE
B81: 25-26 | C81: Oswal Extrusion Limited | D81: Plastene India ltd - Unit 1-Sales | E81: 246 | F81: 46103 | G81: LDPE Granuals | H81: 39011090 | I81: 3000 | J81: Kgs | K81: 3000 | L81: 13919 | M81: Sector - 2, KASEZ, Plot No. 73/74/75 - A & A, Gandhidham - 370 230 Kutch | N81: Survey No 315/1,315/2,316 & 317,Nani Chirai Nr.Softel Company ,Taluka-Bhachau | O81: PP WOVEN BIG BAGS/SACKS | P81: RAW05810 | Q81: RM | R81: Granules | S81: LDPE Granules | T81: LDPE Granules | U81: FALSE
B82: 25-26 | C82: Oswal Extrusion Limited | D82: Plastene India ltd - Unit 1-Sales | E82: 244 | F82: 46101 | G82: PP WEBBING | H82: 39269080 | I82: 198.3 | J82: Kgs | K82: 198.3 | L82: 13916 | M82: Sector - 2, KASEZ, Plot No. 73/74/75 - A & A, Gandhidham - 370 230 Kutch | N82: Survey No 315/1,315/2,316 & 317,Nani Chirai Nr.Softel Company ,Taluka-Bhachau | O82: PP WOVEN BIG BAGS/SACKS | P82: WIP00032 | Q82: SF | R82: Webbing | S82: PP Webbing | T82: Webbing | U82: FALSE
B83: 25-26 | C83: Oswal Extrusion Limited | D83: Plastene India ltd - Unit 1-Sales | E83: 242 | F83: 46100 | G83: PP WEBBING | H83: 39269080 | I83: 525 | J83: Kgs | K83: 525 | L83: 13914 | M83: Sector - 2, KASEZ, Plot No. 73/74/75 - A & A, Gandhidham - 370 230 Kutch | N83: Survey No 315/1,315/2,316 & 317,Nani Chirai Nr.Softel Company ,Taluka-Bhachau | O83: PP WOVEN BIG BAGS/SACKS | P83: WIP00032 | Q83: SF | R83: Webbing | S83: PP Webbing | T83: Webbing | U83: FALSE
B84: 25-26 | C84: Oswal Extrusion Limited | D84: Plastene India ltd - Unit 1-Sales | E84: 243 | F84: 46100 | G84: PP WEBBING | H84: 39269080 | I84: 932.8 | J84: Kgs | K84: 932.8 | L84: 13914 | M84: Sector - 2, KASEZ, Plot No. 73/74/75 - A & A, Gandhidham - 370 230 Kutch | N84: Survey No 315/1,315/2,316 & 317,Nani Chirai Nr.Softel Company ,Taluka-Bhachau | O84: PP WOVEN BIG BAGS/SACKS | P84: WIP00032 | Q84: SF | R84: Webbing | S84: PP Webbing | T84: Webbing | U84: FALSE
B85: 25-26 | C85: Oswal Extrusion Limited | D85: Plastene India ltd - Unit 1-Sales | E85: 232 | F85: 46087 | G85: Polypropylene Granuals | H85: 39021000 | I85: 24750 | J85: Kgs | K85: 24750 | L85: 13887 | M85: Sector - 2, KASEZ, Plot No. 73/74/75 - A & A, Gandhidham - 370 230 Kutch | N85: Survey No 315/1,315/2,316 & 317,Nani Chirai Nr.Softel Company ,Taluka-Bhachau | O85: PP WOVEN BIG BAGS/SACKS | P85: RAW05127 | Q85: RM | R85: Granules | S85: PP Granules | T85: PP Granules | U85: FALSE
B86: 25-26 | C86: Oswal Extrusion Limited | D86: Plastene India ltd - Unit 1-Sales | E86: 233 | F86: 46087 | G86: Polypropylene Granuals | H86: 39021000 | I86: 24750 | J86: Kgs | K86: 24750 | L86: 13887 | M86: Sector - 2, KASEZ, Plot No. 73/74/75 - A & A, Gandhidham - 370 230 Kutch | N86: Survey No 315/1,315/2,316 & 317,Nani Chirai Nr.Softel Company ,Taluka-Bhachau | O86: PP WOVEN BIG BAGS/SACKS | P86: RAW05127 | Q86: RM | R86: Granules | S86: PP Granules | T86: PP Granules | U86: FALSE
B87: 25-26 | C87: Oswal Extrusion Limited | D87: Plastene India ltd - Unit 1-Sales | E87: 234 | F87: 46087 | G87: Polypropylene Granuals | H87: 39021000 | I87: 24750 | J87: Kgs | K87: 24750 | L87: 13887 | M87: Sector - 2, KASEZ, Plot No. 73/74/75 - A & A, Gandhidham - 370 230 Kutch | N87: Survey No 315/1,315/2,316 & 317,Nani Chirai Nr.Softel Company ,Taluka-Bhachau | O87: PP WOVEN BIG BAGS/SACKS | P87: RAW05127 | Q87: RM | R87: Granules | S87: PP Granules | T87: PP Granules | U87: FALSE
... B98: 25-26 | C98: Oswal Extrusion Limited | D98: Plastene India ltd - Unit 1-Sales | E98: 207 | F98: 46071 | G98: Masterbatch | H98: 32064990 | I98: 50 | J98: Kgs | K98: 50 | L98: 13827 | M98: Sector - 2, KASEZ, Plot No. 73/74/75 - A & A, Gandhidham - 370 230 Kutch | N98: Survey No 315/1,315/2,316 & 317,Nani Chirai Nr.Softel Company ,Taluka-Bhachau | O98: PP WOVEN BAGS/SACK | P98: RAW05067 | Q98: RM | R98: Granules | S98: Masterbatch | T98: MB | U98: FALSE
B99: 25-26 | C99: Oswal Extrusion Limited | D99: Plastene India ltd - Unit 1-Sales | E99: 207-2 | F99: 46071 | G99: Polypropylene Granuals | H99: 39021000 | I99: 6000 | J99: Kgs | K99: 6000 | L99: 13827 | M99: Sector - 2, KASEZ, Plot No. 73/74/75 - A & A, Gandhidham - 370 230 Kutch | N99: Survey No 315/1,315/2,316 & 317,Nani Chirai Nr.Softel Company ,Taluka-Bhachau | O99: PP WOVEN BAGS/SACK | P99: RAW05130 | Q99: RM | R99: Granules | S99: PP Granules | T99: PP Granules | U99: FALSE
B100: 25-26 | C100: Oswal Extrusion Limited | D100: Plastene India ltd - Unit 1-Sales | E100: 206 | F100: 46070 | G100: Polypropylene Granuals | H100: 39021000 | I100: 9000 | J100: Kgs | K100: 9000 | L100: 13826 | M100: Sector - 2, KASEZ, Plot No. 73/74/75 - A & A, Gandhidham - 370 230 Kutch | N100: Survey No 315/1,315/2,316 & 317,Nani Chirai Nr.Softel Company ,Taluka-Bhachau | O100: PP WOVEN BAGS/SACK | P100: RAW05130 | Q100: RM | R100: Granules | S100: PP Granules | T100: PP Granules | U100: FALSE
B101: 25-26 | C101: Oswal Extrusion Limited | D101: Plastene India ltd - Unit 1-Sales | E101: 206-2 | F101: 46070 | G101: U.V. STABILIZER MASTER BATCH | H101: 38123990 | I101: 7000 | J101: Kgs | K101: 7000 | L101: 13826 | M101: Sector - 2, KASEZ, Plot No. 73/74/75 - A & A, Gandhidham - 370 230 Kutch | N101: Survey No 315/1,315/2,316 & 317,Nani Chirai Nr.Softel Company ,Taluka-Bhachau | O101: PP WOVEN BAGS/SACK | P101: RAW05089 | Q101: RM | R101: Granules | S101: UV MB | T101: UV MB | U101: FALSE
B102: 25-26 | C102: Oswal Extrusion Limited | D102: Plastene India ltd - Unit 1-Sales | E102: 195 | F102: 46056 | G102: Polypropylene Granuals | H102: 39021000 | I102: 24750 | J102: Kgs | K102: 1231.7 | L102: 13795 | M102: Sector - 2, KASEZ, Plot No. 73/74/75 - A & A, Gandhidham - 370 230 Kutch | N102: Survey No 315/1,315/2,316 & 317,Nani Chirai Nr.Softel Company ,Taluka-Bhachau | O102: PP WOVEN BAGS/SACK | P102: RAW06278 | Q102: RM | R102: Granules | S102: PP Granules | T102: PP Granules | U102: FALSE
B103: 25-26 | C103: Oswal Extrusion Limited | D103: Plastene India ltd - Unit 1-Sales | E103: 194 | F103: 46056 | G103: Polypropylene Granuals | H103: 39021000 | I103: 24750 | J103: Kgs | K103: 918 | L103: 13794 | M103: Sector - 2, KASEZ, Plot No. 73/74/75 - A & A, Gandhidham - 370 230 Kutch | N103: Survey No 315/1,315/2,316 & 317,Nani Chirai Nr.Softel Company ,Taluka-Bhachau | O103: PP WOVEN BAGS/SACK | P103: RAW06278 | Q103: RM | R103: Granules | S103: PP Granules | T103: PP Granules | U103: FALSE
B104: 25-26 | C104: Oswal Extrusion Limited | D104: Plastene India ltd - Unit 1-Sales | E104: 191-3 | F104: 46050 | G104: Polypropylene Granuals | H104: 39021000 | I104: 10000 | J104: Kgs | K104: 400 | L104: 13777 | M104: Sector - 2, KASEZ, Plot No. 73/74/75 - A & A, Gandhidham - 370 230 Kutch | N104: Survey No 315/1,315/2,316 & 317,Nani Chirai Nr.Softel Company ,Taluka-Bhachau | O104: PP WOVEN BAGS/SACK | P104: RAW06049 | Q104: RM | R104: Granules | S104: PP Granules | T104: PP Granules | U104: FALSE
T105: Filler Cord
T106: RP Granules
T107: Filler Soltex PTUFF23

Sheet Received from KPW3
A1: Oswal Extrusion Ltd- KASEZ- Permission No : KASEZ/CUS/01/38/05-06/Pt-IV/ date : 12.05.2021
A2: Sr. No. | B2: Month | C2: Party Challan (Ann-II)No.& Date | D2: Recd. Date | E2: Material | F2: As Per Ch. | G2: Party Name | H2: Address | I2: Process | J2: Sc Challan & Return Dt | K2: Month | L2: Discriptions Of sent Goods | M2: Return Qty | N2: Balance Qty. | O2: manufacturer of fibc jumbo bags
A3: 1 | B3: 45017 | C3: KPW3/JW/001 | D3: 01.04.2023 | E3: PP WOVEN FABRIC LAMINATED/COATED | F3: 3551 | G3: KPW-3 | H3: KASEZ | I3: PP WOVEN BIG BAGS | J3: 026/29.05.23 | K3: 45047 | L3: PP WOVEN BIG BAGS | M3: 4171.1 | N3: =+F3+F4-M3-M4 -> 0
E4: LD/LLDPE BAGS | F4: 839.1 | G4: KPW-3 | H4: KASEZ | I4: PP WOVEN BIG BAGS | J4: 036/23.06.23 | K4: 45078 | L4: SCRAPS | M4: 219
A6: 2 | B6: 45017 | C6: KPW3/JW/002 | D6: 03.04.2023 | E6: PP TAPE | F6: 1523 | G6: KPW-3 | H6: KASEZ | I6: PP WOVEN BIG BAGS | J6: 026/29.05.23 | K6: 45047 | L6: PP WOVEN BIG BAGS | M6: 468.1 | N6: =+F6+F7+F8+F9-M6-M7-M8 -> 0
E7: LD/LLDPE BAGS | F7: 6647 | G7: KPW-3 | H7: KASEZ | I7: PP WOVEN BIG BAGS | J7: 028/05.06.23 | K7: 45078 | L7: PP WOVEN BIG BAGS | M7: 11423.3
E8: PP WOVEN FABRICS | F8: 2373.4 | G8: KPW-3 | H8: KASEZ | I8: PP WOVEN BIG BAGS | J8: 036/23.06.23 | K8: 45078 | L8: SCRAPS | M8: 626
E9: PP WOVEN FABRIC LAMINATED/COATED | F9: 1974
