Workbook

Sheet Summary
B2: EBIDTA - Summary
B3: Plant | C3: EBIDTA | E3: PBT | G3: EBIDTA | I3: PBT | K3: EBIDTA | M3: PBT | O3: EBIDTA | Q3: PBT | S3: EBIDTA | U3: PBT | W3: EBIDTA | Y3: PBT | AA3: EBIDTA | AC3: PBT | AE3: EBIDTA | AG3: PBT | AI3: EBIDTA | AK3: PBT | AM3: EBIDTA | AO3: PBT | AQ3: EBIDTA | AS3: PBT | AU3: EBIDTA | AW3: PBT
A4: 0 | C4: April'2026 | D4: YTD | E4: =C4 -> April'2026 | F4: YTD | G4: May'2025 | H4: YTD | I4: =G4 -> May'2025 | J4: YTD | K4: Jun'2025 | L4: YTD | M4: =K4 -> Jun'2025 | N4: YTD | O4: Jul'2025 | P4: YTD | Q4: =O4 -> Jul'2025 | R4: YTD | S4: Aug'2025 | T4: YTD | U4: =S4 -> Aug'2025 | V4: YTD | W4: Sep'2025 | X4: YTD | Y4: =W4 -> Sep'2025 | Z4: YTD | AA4: Oct'2025 | AB4: YTD | AC4: =AA4 -> Oct'2025 | AD4: YTD | AE4: Nov'2025 | AF4: YTD | AG4: =AE4 -> Nov'2025 | AH4: YTD | AI4: Dec'2025 | AJ4: YTD | AK4: =AI4 -> Dec'2025 | AL4: YTD | AM4: Jan'2026 | AN4: YTD | AO4: =AM4 -> Jan'2026 | AP4: YTD | AQ4: Feb'2026 | AR4: YTD | AS4: =AQ4 -> Feb'2026 | AT4: YTD | AU4: Mar'2026 | AV4: YTD | AW4: =AU4 -> Mar'2026 | AX4: YTD
B5: PIL I | C5: =+'Apr-26'!$C$82 -> 727.75151 | D5: =+'Apr-26'!$E$82 -> 727.75151 | E5: =+'Apr-26'!$C$89 -> 604.44113 | F5: =+'Apr-26'!$E$89 -> 604.44113 | G5: =+'May-26'!$C$82 -> 382.62154 | H5: =+'May-26'!$E$82 -> 1110.3731 | I5: =+'May-26'!$C$89 -> 144.29429 | J5: =+'May-26'!$E$89 -> 872.04581
B6: PIL II | C6: =+'Apr-26'!$G$82 -> 225.11669 | D6: =+'Apr-26'!$I$82 -> 225.11669 | E6: =+'Apr-26'!$G$89 -> 218.65362 | F6: =+'Apr-26'!$I$89 -> 218.65362 | G6: =+'May-26'!$G$82 -> 212.48089 | H6: =+'May-26'!$I$82 -> 437.59757 | I6: =+'May-26'!$G$89 -> 179.88929 | J6: =+'May-26'!$I$89 -> 405.00598
B7: PIL III | C7: =+'Apr-26'!$K$82 -> 37.266779 | D7: =+'Apr-26'!$M$82 -> 37.266779 | E7: =+'Apr-26'!$K$89 -> 15.992645 | F7: =+'Apr-26'!$M$89 -> 15.992645 | G7: =+'May-26'!$K$82 -> 19.081349 | H7: =+'May-26'!$M$82 -> 56.348128 | I7: =+'May-26'!$K$89 -> -31.006677 | J7: =+'May-26'!$M$89 -> 6.2601022
B8: HPBL4 | C8: =+'Apr-26'!$O$82 -> 135.03311 | D8: =+'Apr-26'!$Q$82 -> 135.03311 | E8: =+'Apr-26'!$O$89 -> 133.93357 | F8: =+'Apr-26'!$Q$89 -> 133.93357 | G8: =+'May-26'!$O$82 -> 303.63346 | H8: =+'May-26'!$Q$82 -> 438.66658 | I8: =+'May-26'!$O$89 -> 301.19332 | J8: =+'May-26'!$Q$89 -> 436.22644
B9: PIL HO | C9: =+'Apr-26'!$S$82 -> -10.92026 | D9: =+'Apr-26'!$U$82 -> -10.92026 | E9: =+'Apr-26'!$S$89 -> -18.961649 | F9: =+'Apr-26'!$U$89 -> -18.961649 | G9: =+'May-26'!$S$82 -> -18.114826 | H9: =+'May-26'!$U$82 -> -29.035086 | I9: =+'May-26'!$S$89 -> -15.065947 | J9: =+'May-26'!$U$89 -> -25.986207
B10: HCP | C10: =+'Apr-26'!$W$82 -> 34.936401 | D10: =+'Apr-26'!$Y$82 -> 34.936401 | E10: =+'Apr-26'!$W$89 -> 33.868702 | F10: =+'Apr-26'!$Y$89 -> 33.868702 | G10: =+'May-26'!$W$82 -> -64.340984 | H10: =+'May-26'!$Y$82 -> -29.404583 | I10: =+'May-26'!$W$89 -> -64.834428 | J10: =+'May-26'!$Y$89 -> -29.898027 | BF10: =59.57-59.25 -> 0.32
B11: OEL I | C11: =+'Apr-26'!$AG$82 -> 71.725646 | D11: =+'Apr-26'!$AI$82 -> 71.725646 | E11: =+'Apr-26'!$AG$89 -> 51.229445 | F11: =+'Apr-26'!$AI$89 -> 51.229445 | G11: =+'May-26'!$AG$82 -> 36.774061 | H11: =+'May-26'!$AI$82 -> 108.49971 | I11: =+'May-26'!$AG$89 -> -5.5149987 | J11: =+'May-26'!$AI$89 -> 66.210647
B12: PPL | C12: =+'Apr-26'!$AL$82 -> 164.56858 | D12: =+'Apr-26'!$AN$82 -> 164.56858 | E12: =+'Apr-26'!$AL$89 -> 140.97763 | F12: =+'Apr-26'!$AN$89 -> 140.97763 | G12: =+'May-26'!$AL$82 -> -113.8955 | H12: =+'May-26'!$AN$82 -> 50.67308 | I12: =+'May-26'!$AL$89 -> -177.49363 | J12: =+'May-26'!$AN$89 -> -12.925049
B13: KP I | C13: =+'Apr-26'!$AQ$82 -> 568.90214 | D13: =+'Apr-26'!$AS$82 -> 568.90214 | E13: =+'Apr-26'!$AQ$89 -> 505.99822 | F13: =+'Apr-26'!$AS$89 -> 505.99822 | G13: =+'May-26'!$AQ$82 -> 741.82315 | H13: =+'May-26'!$AS$82 -> 1310.7253 | I13: =+'May-26'!$AQ$89 -> 592.64676 | J13: =+'May-26'!$AS$89 -> 1161.5489
B14: KP III | C14: =+'Apr-26'!$AU$82 -> 126.07635 | D14: =+'Apr-26'!$AW$82 -> 126.07635 | E14: =+'Apr-26'!$AU$89 -> 119.87334 | F14: =+'Apr-26'!$AW$89 -> 119.87334 | G14: =+'May-26'!$AU$82 -> 303.92958 | H14: =+'May-26'!$AW$82 -> 430.00593 | I14: =+'May-26'!$AU$89 -> 292.28164 | J14: =+'May-26'!$AW$89 -> 418.35799
B15: HPBL I | C15: =+'Apr-26'!$BE$82 -> 24.908538 | D15: =+'Apr-26'!$BG$82 -> 24.908538 | E15: =+'Apr-26'!$BE$89 -> -11.892947 | F15: =+'Apr-26'!$BG$89 -> -11.892947 | G15: =+'May-26'!$BE$82 -> -115.29488 | H15: =+'May-26'!$BG$82 -> -90.386341 | I15: =+'May-26'!$BE$89 -> -152.09636 | J15: =+'May-26'!$BG$89 -> -127.18783
B16: HPBL II | C16: =+'Apr-26'!$BI$82 -> -6.1781505 | D16: =+'Apr-26'!$BK$82 -> -6.1781505 | E16: =+'Apr-26'!$BI$89 -> -6.1781505 | F16: =+'Apr-26'!$BK$89 -> -6.1781505 | G16: =+'May-26'!$BI$82 -> 10.591816 | H16: =+'May-26'!$BK$82 -> 4.413665 | I16: =+'May-26'!$BI$89 -> 10.591816 | J16: =+'May-26'!$BK$89 -> 4.413665
B17: HPBL III | C17: =+'Apr-26'!$BM$82 -> 0.07617 | D17: =+'Apr-26'!$BO$82 -> 0.07617 | E17: =+'Apr-26'!$BM$89 -> 0.07617 | F17: =+'Apr-26'!$BO$89 -> 0.07617 | G17: =+'May-26'!$BM$82 -> 0 | H17: =+'May-26'!$BO$82 -> 0.07617 | I17: =+'May-26'!$BM$89 -> 0 | J17: =+'May-26'!$BO$89 -> 0.07617
B18: OCPL | C18: =+'Apr-26'!$BW$82 -> 52.699454 | D18: =+'Apr-26'!$BY$82 -> 52.699454 | E18: =+'Apr-26'!$BW$89 -> 52.699454 | F18: =+'Apr-26'!$BY$89 -> 52.699454 | G18: =+'May-26'!$BW$82 -> 49.856209 | H18: =+'May-26'!$BY$82 -> 102.55566 | I18: =+'May-26'!$BW$89 -> 49.856209 | J18: =+'May-26'!$BY$89 -> 102.55566
B19: Total Group | C19: =SUM(C5:C18) -> 2151.963 | D19: =SUM(D5:D18) -> 2151.963 | E19: =SUM(E5:E18) -> 1840.7112 | F19: =SUM(F5:F18) -> 1840.7112 | G19: =SUM(G5:G18) -> 1749.1459 | H19: =SUM(H5:H18) -> 3901.1088 | I19: =SUM(I5:I18) -> 1124.7413 | J19: =SUM(J5:J18) -> 3276.7043 | ... AX19: =SUM(AX5:AX18) -> 0 | BC19: =+AQ19-#REF! -> #REF! | BD19: =+#REF!-Summary!AR19 -> #REF! | BG19: =+AM19-#REF! -> #REF! | BH19: =+#REF!-Summary!AN19 -> #REF!
B20: Cash PBT
B21: % | C21: ='[1]APR-2022'!CQ86 -> #REF! | D21: ='[2]APR-2022'!CT86 -> 0.14263615 | F21: ='[2]APR-2022'!CT91 -> 0.073411415 | G21: ='[2]May-2022'!CQ86 -> 0.090850873 | H21: ='[2]May-2022'!CT86 -> 0.090527574 | J21: ='[2]May-2022'!CT91 -> 0.0045169428 | K21: ='[2]May-2022'!CU86 -> 0 | L21: ='[2]May-2022'!CX86 -> 0 | N21: ='[2]May-2022'!CX91 -> 0 | O21: ='[2]May-2022'!CY86 -> 0 | P21: ='[2]May-2022'!DB86 -> 0 | R21: ='[2]May-2022'!DB91 -> 0 | S21: ='[2]May-2022'!DC86 -> 0 | T21: ='[2]May-2022'!DF86 -> 0 | V21: ='[2]May-2022'!DF91 -> 0 | W21: ='[2]May-2022'!DG86 -> 0 | X21: ='[2]May-2022'!DJ86 -> 0 | Z21: ='[2]May-2022'!DJ91 -> 0
C23: =+C19-'Apr-26'!CE82 -> 0 | D23: =+D19-'Apr-26'!CG82 -> 0 | E23: =+E19-'Apr-26'!CE88 -> 2.9558578e-12 | F23: =+F19-'Apr-26'!CG88 -> 2.9558578e-12 | G23: =+G19-'May-26'!CE82 -> 0 | H23: =+H19-'May-26'!CG82 -> 6.3664629e-12 | I23: =I19-'May-26'!CE89 -> 0 | J23: =J19-'May-26'!CG89 -> 6.3664629e-12

Sheet Sheet1
B2: PIL I | C2: PIL II | D2: PIL III | E2: PIL VI | F2: PIL HO | G2: HCP | H2: OEL | I2: PPL | J2: KPW | K2: KPW II | L2: HPBL I | M2: HPBL II | N2: HPBL III | O2: JBP | P2: Total
A3: Jan | B3: =#REF! -> #REF! | C3: =#REF! -> #REF! | D3: =#REF! -> #REF! | E3: =#REF! -> #REF! | F3: =#REF! -> #REF! | G3: =#REF! -> #REF! | H3: =#REF! -> #REF! | I3: =#REF! -> #REF! | ... O3: =#REF! -> #REF! | P3: =SUM(B3:O3) -> #REF!
A4: Feb | B4: =#REF! -> #REF! | C4: =#REF! -> #REF! | D4: =#REF! -> #REF! | E4: =#REF! -> #REF! | F4: =#REF! -> #REF! | G4: =#REF! -> #REF! | H4: =#REF! -> #REF! | I4: =#REF! -> #REF! | ... N4: =#REF! -> #REF! | O4: =#REF!+26.52 -> #REF! | P4: =SUM(B4:O4) -> #REF!
A5: Total | B5: =SUM(B3:B4) -> #REF! | C5: =SUM(C3:C4) -> #REF! | D5: =SUM(D3:D4) -> #REF! | E5: =SUM(E3:E4) -> #REF! | F5: =SUM(F3:F4) -> #REF! | G5: =SUM(G3:G4) -> #REF! | H5: =SUM(H3:H4) -> #REF! | I5: =SUM(I3:I4) -> #REF! | ... P5: =SUM(P3:P4) -> #REF!
A6: Avg | B6: =B5/2 -> #REF! | C6: =C5/2 -> #REF! | D6: =D5/2 -> #REF! | E6: =E5/2 -> #REF! | F6: =F5/2 -> #REF! | G6: =G5/2 -> #REF! | H6: =H5/2 -> #REF! | I6: =I5/2 -> #REF! | ... P6: =P5/2 -> #REF!

Sheet May-26
B1: GROUP EBIDTA & PBT FOR THE MONTH OF | D1: May-26 | AG1: 367529 | AL1: 441624 | AQ1: 597025 | CE1: =SUM(G1:BZ1) -> 1406178
B3: PARTICULARS | C3: QTY | D3: SALES/PUR QTY | E3: SALE/PUR RATE | G3: QTY | H3: SALE IN LACS | I3: SALE/PUR RATE | O3: QTY | P3: SALE IN LACS | Q3: SALE/PUR RATE | AG3: QTY | AH3: SALE IN LACS | AI3: SALE/PUR RATE | AL3: QTY | AM3: SALE IN LACS | AN3: SALE/PUR RATE | AQ3: QTY | AR3: SALE IN LACS | AS3: SALE/PUR RATE | AU3: QTY | AV3: SALE IN LACS | AW3: SALE/PUR RATE | BE3: QTY | BF3: SALE IN LACS | BG3: SALE/PUR RATE | BM3: QTY | BN3: SALE IN LACS | BO3: SALE/PUR RATE
B4: BUDGETED / PLANNED
B6: PRODUCTION
B7: FIBC | C7: 0 | G7: 0 | I7: 0 | O7: 0 | Q7: 0 | AG7: 0 | AL7: 0 | AN7: 0 | AQ7: 0 | AS7: 0 | AU7: 0 | BE7: 0 | BG7: 0 | BM7: 0 | BN7: 0 | BO7: 0 | CE7: =SUM(C7:CD7) -> 0 | CF7: 165.52
B8: Fabric (Liner Mtr) | BM8: 0 | CE8: =SUM(C8:CD8) -> 0
C9: =(C8*0.4)+C7 -> 0 | G9: =(G8*0.4)+G7 -> 0 | O9: =(O8*0.4)+O7 -> 0 | AG9: =(AG8*0.4)+AG7 -> 0 | AL9: =(AL8*0.4)+AL7 -> 0 | AQ9: =(AQ8*0.4)+AQ7 -> 0 | AU9: 0 | BE9: 0 | BM9: =(BM8*0.4)+BM7 -> 0 | CE9: =SUM(C9:CD9) -> 0
B10: DISPATCH | CE10: =SUM(C10:CD10) -> 0
B11: FIBC | CE11: =SUM(C11:CD11) -> 0
B12: Fabric | CE12: =SUM(C12:CD12) -> 0
CE13: =SUM(C13:CD13) -> 0
B14: PURCHASE | CE14: =SUM(C14:CD14) -> 0
B15: Fabric | CE15: =SUM(C15:CD15) -> 0
B16: PP Granules | CE16: =SUM(C16:CD16) -> 0
B17: Conversion Cost per KG | C17: =#REF!-#REF!+#REF! -> #REF! | G17: =#REF!-#REF!+#REF! -> #REF! | O17: =#REF!-#REF!+#REF! -> #REF! | AG17: =#REF!-#REF!+#REF! -> #REF! | AL17: =#REF!-#REF!+#REF! -> #REF! | AQ17: =#REF!-#REF!+#REF! -> #REF! | AU17: =#REF!-#REF!+#REF! -> #REF! | BM17: =#REF!-#REF!+#REF! -> #REF! | CE17: =+#REF!-#REF!+#REF! -> #REF!
B19: Particulars | C19: May-26 | D19: % To Sales | E19: YTD | F19: % To Sales | G19: =C19 -> May-26 | H19: % To Sales | I19: YTD | J19: % To Sales | K19: =C19 -> May-26 | L19: % To Sales | M19: YTD | N19: % To Sales | O19: =C19 -> May-26 | P19: % To Sales | Q19: YTD | R19: % To Sales | S19: =K19 -> May-26 | T19: % Tw Sales | U19: YTD | V19: % To Sales | W19: =O19 -> May-26 | X19: % To Sales | Y19: YTD | Z19: % To Sales | AA19: InterUnit Elimination | AB19: =C19 -> May-26 | AC19: % To Sales | AD19: YTD | AE19: % To Sales | AG19: =AB19 -> May-26 | AH19: % To Sales | AI19: YTD | AJ19: % To Sales | AL19: =AG19 -> May-26 | AM19: % To Sales | AN19: YTD | AO19: % To Sales | AQ19: =AL19 -> May-26 | AR19: % To Sales | AS19: YTD | AT19: % To Sales | AU19: =AQ19 -> May-26 | AV19: % To Sales | AW19: YTD | AX19: % To Sales | AY19: InterUnit Elimination | AZ19: =AU19 -> May-26 | BA19: % To Sales | BB19: YTD | BC19: % To Sales | BE19: =AZ19 -> May-26 | BF19: % To Sales | BG19: YTD | BH19: % To Sales | BI19: =BE19 -> May-26 | BJ19: % To Sales | BK19: YTD | BL19: % To Sales | BM19: =BE19 -> May-26 | BN19: % To Sales | BO19: YTD | BP19: % To Sales | BQ19: Inter Unit Elimination | BR19: =BM19 -> May-26 | BS19: % To Sales | BT19: YTD | BU19: % To Sales | BW19: =BM19 -> May-26 | BX19: % To Sales | BY19: YTD | BZ19: % To Sales | CB19: Inter Company Elimination During the month | CC19: Inter Company Elimination YTD | CE19: =BR19 -> May-26 | CF19: % To Sales | CG19: YTD | CH19: % To Sales
C21: PIL I | G21: PIL II | K21: PIL III | O21: HPBL4 | S21: PIL HO | W21: HCP | AB21: PIL & HCP Consol | AG21: OSWAL - KASEZ | AL21: PLASTENE POLYFILM LTD. | AQ21: K P WOVEN PVT LTD - UNIT - I | AU21: K P WOVEN PVT LTD - UNIT -III | AZ21: K P WOVEN PVT LTD - CONSOLIDATED | BE21: HCP PLASTENE BULKPACK LTD. - UNIT - I | BI21: HCP PLASTENE BULKPACK LTD. - UNIT - II | BM21: HCP PLASTENE BULKPACK LTD. - UNIT - III | BR21: HCP PLASTENE BULKPACK LTD - CONSOLIDATED | BW21: OCPL | CE21: GROUP CONSOLIDATED
B22: Revenue from operations
B23: Sale of finished goods | C23: =E23-'Apr-26'!E23 -> 2048.0603 | D23: =C23/$C$46*100% -> 0.65558118 | E23: =-SUMIF('05.conso TB'!A:A,'May-26'!B23,'05.conso TB'!R:R)/10^5 -> 4945.3445 | F23: =E23/$E$46*100% -> 0.76539717 | G23: =I23-'Apr-26'!I23 -> 1059.1801 | H23: =G23/$G$46*100% -> 0.79745099 | I23: =-SUMIF('05.conso TB'!A:A,'May-26'!B23,'05.conso TB'!S:S)/10^5 -> 2073.1202 | J23: =I23/$I$46*100% -> 0.82609095 | K23: =M23-'Apr-26'!M23 -> 0 | L23: =K23/$C$46*100% -> 0 | M23: =-SUMIF('05.conso TB'!A:A,'May-26'!B23,'05.conso TB'!T:T)/10^5 -> 0 | N23: =M23/$C$46*100% -> 0 | O23: =Q23-'Apr-26'!Q23 -> 1225.1445 | P23: =O23/$O$46*100% -> 0.98638587 | Q23: =-SUMIF('05.conso TB'!A:A,'May-26'!B23,'05.conso TB'!U:U)/10^5 -> 2147.1778 | R23: =Q23/$Q$46*100% -> 0.98546637 | S23: =U23-'Apr-26'!U23 -> 0 | T23: =S23/$S$46*100% -> 0 | U23: =SUMIF('05.conso TB'!A:A,'May-26'!B23,'05.conso TB'!V:V) -> 0 | V23: =U23/$U$46*100% -> 0 | W23: =Y23-'Apr-26'!Y23 -> 0 | X23: =W23/$W$46*100% -> 0 | Y23: =-SUMIF('05.conso TB'!A:A,'May-26'!B23,'05.conso TB'!G:G)/10^5 -> 0 | Z23: =Y23/$Y$46*100% -> 0 | AA23: 317.57266 | AB23: =AD23-'Apr-26'!AD23 -> 4141.1887 | AC23: =AB23/$AB$46*100% -> 0.44908491 | AD23: =E23+I23+M23+Q23+U23+Y23-AA23 -> 8848.0699 | AE23: =AD23/$AD$46*100% -> 0.61219768 | AG23: =AI23-'Apr-26'!AI23 -> 95.60983 | AH23: =AG23/$AG$46*100% -> 0.26015644 | AI23: =-SUMIF('05.conso TB'!A:A,'May-26'!B23,'05.conso TB'!Q:Q)/10^5 -> 184.39779 | AJ23: =AI23/$AI$46*100% -> 0.2498606 | AL23: =AN23-'Apr-26'!AN23 -> 653.79373 | AM23: =AL23/$AL$46*100% -> 0.55207972 | AN23: =-SUMIF('05.conso TB'!A:A,'May-26'!B23,'05.conso TB'!W:W)/10^5 -> 1478.0791 | AO23: =AN23/$AN$46*100% -> 0.63645888 | AQ23: =AS23-'Apr-26'!AS23 -> 1982.7336 | AR23: =AQ23/$AQ$46*100% -> 0.97248742 | AS23: =-SUMIF('05.conso TB'!A:A,'May-26'!B23,'05.conso TB'!M:M)/10^5 -> 3773.3651 | AT23: =AS23/$AS$46*100% -> 0.97489384 | AU23: =AW23-'Apr-26'!AW23 -> -2.2135648 | AV23: =AU23/$AU$46*100% -> -0.0022216101 | AW23: =-SUMIF('05.conso TB'!A:A,'May-26'!B23,'05.conso TB'!P:P)/10^5 -> -4.5173012 | AX23: =AW23/$AW$46*100% -> -0.0024454424 | AY23: 0 | AZ23: =BB23-'Apr-26'!BB23 -> 1980.52 | BA23: =AZ23/$AZ$46*100% -> 0.65251593 | BB23: =AS23+AW23 -> 3768.8478 | BC23: =BB23/$BB$46*100% -> 0.6591462 | BE23: =BG23-'Apr-26'!BG23 -> 2505.1055 | BF23: =BE23/$BE$46*100% -> 0.89630582 | BG23: =-SUMIF('05.conso TB'!A:A,'May-26'!B23,'05.conso TB'!H:H)/10^5 -> 3942.6624 | BH23: =BG23/$BG$46*100% -> 0.83901799 | BI23: =BK23-'Apr-26'!BK23 -> 19.219115 | BJ23: =BI23/$BI$46*100% -> 1 | BK23: =-SUMIF('05.conso TB'!A:A,'May-26'!B23,'05.conso TB'!I:I)/10^5 -> 38.599737 | BL23: =BK23/$BK$46*100% -> 1.0000004 | BM23: =BO23-'Apr-26'!BO23 -> 0 | BN23: =BM23/$C$46*100% -> 0 | BO23: =-SUMIF('05.conso TB'!A:A,'May-26'!B23,'05.conso TB'!J:J)/10^5 -> 0 | BP23: =BO23/$C$46*100% -> 0 | BQ23: 0 | BR23: =BT23-'Apr-26'!BT23 -> 2524.3247 | BS23: =BR23/$BR$46*100% -> 0.95455775 | BT23: =BG23+BK23+BO23-BQ23 -> 3981.2621 | BU23: =BT23/$BT$46*100% -> 0.88714051 | BW23: =BY23-'Apr-26'!BY23 -> -5.448775 | BX23: =BW23/$BW$46*100% -> -0.012040756 | BY23: =-SUMIF('05.conso TB'!A:A,'May-26'!B23,'05.conso TB'!L:L)/10^5 -> -9.883575 | BZ23: =BY23/$BY$46*100% -> -0.0045738579 | CB23: =CC23-'Apr-26'!CC23 -> 4547.8678 | CC23: 9013.7446 | CE23: =AB23+AG23+AL23+AZ23+BR23+BW23-CA23 -> 9389.9881 | CF23: =CE23/$CE$46*100% -> 0.5554441 | CG23: =AD23+AI23+AN23+BB23+BT23+BY23-CC23 -> 9237.0285 | CH23: =CG23/$CG$46*100% -> 0.75530694
B24: Sale of traded goods | C24: =E24-'Apr-26'!E24 -> 955.64633 | D24: =C24/$C$46*100% -> 0.30590102 | E24: =-SUMIF('05.conso TB'!A:A,'May-26'!B24,'05.conso TB'!R:R)/10^5 -> 1352.4291 | F24: =E24/$E$46*100% -> 0.20931714 | G24: =I24-'Apr-26'!I24 -> 96.525998 | H24: =G24/$G$46*100% -> 0.072673904 | I24: =-SUMIF('05.conso TB'!A:A,'May-26'!B24,'05.conso TB'!S:S)/10^5 -> 216.41929 | J24: =I24/$I$46*100% -> 0.086238134 | K24: =M24-'Apr-26'!M24 -> 0 | L24: =K24/$C$46*100% -> 0 | M24: =-SUMIF('05.conso TB'!A:A,'May-26'!B24,'05.conso TB'!T:T) -> 0 | N24: =M24/$C$46*100% -> 0 | O24: =Q24-'Apr-26'!Q24 -> 16.909453 | P24: =O24/$O$46*100% -> 0.013614105 | Q24: =-SUMIF('05.conso TB'!A:A,'May-26'!B24,'05.conso TB'!U:U)/10^5 -> 31.66651 | R24: =Q24/$Q$46*100% -> 0.014533627 | S24: =U24-'Apr-26'!U24 -> 0 | T24: =S24/$S$46*100% -> 0 | U24: =-SUMIF('05.conso TB'!A:A,'May-26'!B24,'05.conso TB'!V:V)/10^5 -> 48.765062 | V24: =U24/$U$46*100% -> 1.0004615 | W24: =Y24-'Apr-26'!Y24 -> 3763.6996 | X24: =W24/$W$46*100% -> 1.0119789 | Y24: =-SUMIF('05.conso TB'!A:A,'May-26'!B24,'05.conso TB'!G:G)/10^5 -> 3837.7156 | Z24: =Y24/$Y$46*100% -> 1.0116251 | AA24: 286.05227 | AB24: =AD24-'Apr-26'!AD24 -> 4808.5836 | AC24: =AB24/$AB$46*100% -> 0.52145954 | AD24: =E24+I24+M24+Q24+U24+Y24-AA24 -> 5200.9433 | AE24: =AD24/$AD$46*100% -> 0.3598531 | AG24: =AI24-'Apr-26'!AI24 -> 0 | AH24: =AG24/$AG$46*100% -> 0 | AI24: =-SUMIF('05.conso TB'!A:A,'May-26'!B24,'05.conso TB'!Q:Q)/10^5 -> 0 | AJ24: =AI24/$AI$46*100% -> 0 | AL24: =AN24-'Apr-26'!AN24 -> 288.92677 | AM24: =AL24/$AL$46*100% -> 0.24397697 | AN24: =-SUMIF('05.conso TB'!A:A,'May-26'!B24,'05.conso TB'!W:W)/10^5 -> 418.00919 | AO24: =AN24/$AN$46*100% -> 0.1799942 | AQ24: =AS24-'Apr-26'!AS24 -> 6.9177273 | AR24: =AQ24/$AQ$46*100% -> 0.0033929938 | AS24: =-SUMIF('05.conso TB'!A:A,'May-26'!B24,'05.conso TB'!M:M)/10^5 -> 47.998801 | AT24: =AS24/$AS$46*100% -> 0.012401062 | AU24: =AW24-'Apr-26'!AW24 -> 998.58378 | AV24: =AU24/$C$46*100% -> 0.31964524 | AW24: =-SUMIF('05.conso TB'!A:A,'May-26'!B24,'05.conso TB'!P:P)/10^5 -> 1851.7416 | AX24: =AW24/$AW$46*100% -> 1.0024409 | AZ24: =BB24-'Apr-26'!BB24 -> 1005.5015 | BA24: =AZ24/$AZ$46*100% -> 0.33127954 | BB24: =AS24+AW24 -> 1899.7404 | BC24: =BB24/$BB$46*100% -> 0.33225185 | BE24: =BG24-'Apr-26'!BG24 -> 280.77199 | BF24: =BE24/$BE$46*100% -> 0.10045787 | BG24: =-SUMIF('05.conso TB'!A:A,'May-26'!B24,'05.conso TB'!H:H)/10^5 -> 701.17177 | BH24: =BG24/$BG$46*100% -> 0.14921281 | BI24: =BK24-'Apr-26'!BK24 -> 0 | BJ24: =BI24/$BI$46*100% -> 0 | BK24: =-SUMIF('05.conso TB'!A:A,'May-26'!B24,'05.conso TB'!I:I)/10^5 -> 0 | BL24: =BK24/$BK$46*100% -> 0 | BM24: =BO24-'Apr-26'!BO24 -> 0 | BN24: =BM24/$C$46*100% -> 0 | BO24: =-SUMIF('05.conso TB'!A:A,'May-26'!B24,'05.conso TB'!J:J)/10^5 -> 0 | BP24: =BO24/$C$46*100% -> 0 | BQ24: 250.06819 | BR24: =BT24-'Apr-26'!BT24 -> 111.12664 | BS24: =BR24/$BR$46*100% -> 0.04202185 | BT24: =BG24+BK24+BO24-BQ24 -> 451.10358 | BU24: =BT24/$BT$46*100% -> 0.10051894 | BW24: =BY24-'Apr-26'!BY24 -> 450.37712 | BX24: =BW24/$BW$46*100% -> 0.99524777 | BY24: =-SUMIF('05.conso TB'!A:A,'May-26'!B24,'05.conso TB'!L:L)/10^5 -> 2161.2577 | BZ24: =BY24/$BY$46*100% -> 1.0001731 | CB24: =CC24-'Apr-26'!CC24 -> 4633.0065 | CC24: 7261.0698 | CE24: =AB24+AG24+AL24+AZ24+BR24+BW24-CA24 -> 6664.5157 | CF24: =CE24/$CE$46*100% -> 0.39422477 | CG24: =AD24+AI24+AN24+BB24+BT24+BY24-CC24 -> 2869.9844 | CH24: =CG24/$CG$46*100% -> 0.23467711
B25: Total Revenue from operations | C25: =SUM(C23:C24) -> 3003.7067 | D25: =SUM(D23:D24) -> 0.9614822 | E25: =SUM(E23:E24) -> 6297.7736 | F25: =E25/$E$46*100% -> 0.97471431 | G25: =SUM(G23:G24) -> 1155.7061 | H25: =G25/$G$46*100% -> 0.8701249 | I25: =SUM(I23:I24) -> 2289.5395 | J25: =I25/$I$46*100% -> 0.91232908 | K25: =SUM(K23:K24) -> 0 | L25: =SUM(L23:L24) -> 0 | M25: =SUM(M23:M24) -> 0 | N25: =SUM(N23:N24) -> 0 | O25: =SUM(O23:O24) -> 1242.0539 | P25: =O25/$O$46*100% -> 0.99999998 | Q25: =SUM(Q23:Q24) -> 2178.8443 | R25: =Q25/$Q$46*100% -> 0.99999999 | S25: =SUM(S23:S24) -> 0 | T25: =S25/$S$46*100% -> 0 | U25: =SUM(U23:U24) -> 48.765062 | V25: =U25/$U$46*100% -> 1.0004615 | W25: =SUM(W23:W24) -> 3763.6996 | X25: =W25/$W$46*100% -> 1.0119789 | Y25: =SUM(Y23:Y24) -> 3837.7156 | Z25: =Y25/$Y$46*100% -> 1.0116251 | AA25: =SUM(AA23:AA24) -> 603.62492 | AB25: =SUM(AB23:AB24) -> 8949.7723 | AC25: =AB25/$AB$46*100% -> 0.97054444 | AD25: =SUM(AD23:AD24) -> 14049.013 | AE25: =AD25/$AD$46*100% -> 0.97205078 | AG25: =SUM(AG23:AG24) -> 95.60983 | AH25: =AG25/$AG$46*100% -> 0.26015644 | AI25: =SUM(AI23:AI24) -> 184.39779 | AJ25: =SUM(AJ23:AJ24) -> 0.2498606 | AL25: =SUM(AL23:AL24) -> 942.7205 | AM25: =AL25/$AL$46*100% -> 0.79605669 | AN25: =SUM(AN23:AN24) -> 1896.0883 | AO25: =SUM(AO23:AO24) -> 0.81645308 | AQ25: =SUM(AQ23:AQ24) -> 1989.6513 | AR25: =AQ25/$AQ$46*100% -> 0.97588041 | AS25: =SUM(AS23:AS24) -> 3821.3639 | AT25: =SUM(AT23:AT24) -> 0.9872949 | AU25: =SUM(AU23:AU24) -> 996.37022 | AV25: =SUM(AV23:AV24) -> 0.31742363 | AW25: =SUM(AW23:AW24) -> 1847.2243 | AX25: =SUM(AX23:AX24) -> 0.99999545 | AY25: =SUM(AY23:AY24) -> 0 | AZ25: =SUM(AZ23:AZ24) -> 2986.0215 | BA25: =AZ25/$AZ$46*100% -> 0.98379547 | BB25: =SUM(BB23:BB24) -> 5668.5882 | BC25: =SUM(BC23:BC24) -> 0.99139805 | BE25: =SUM(BE23:BE24) -> 2785.8775 | BF25: =BE25/$BE$46*100% -> 0.99676369 | BG25: =SUM(BG23:BG24) -> 4643.8342 | BH25: =SUM(BH23:BH24) -> 0.9882308 | BI25: =SUM(BI23:BI24) -> 19.219115 | BJ25: =BI25/$BI$46*100% -> 1 | BK25: =SUM(BK23:BK24) -> 38.599737 | BL25: =SUM(BL23:BL24) -> 1.0000004 | BM25: =SUM(BM23:BM24) -> 0 | BN25: =SUM(BN23:BN24) -> 0 | BO25: =SUM(BO23:BO24) -> 0 | BP25: =SUM(BP23:BP24) -> 0 | BQ25: =SUM(BQ23:BQ24) -> 250.06819 | BR25: =SUM(BR23:BR24) -> 2635.4513 | BS25: =BR25/$BR$46*100% -> 0.9965796 | BT25: =BG25+BK25+BO25-BQ25 -> 4432.3657 | BU25: =BT25/$BT$46*100% -> 0.98765945 | BW25: =SUM(BW23:BW24) -> 444.92835 | BX25: =BW25/$BW$46*100% -> 0.98320701 | BY25: =SUM(BY23:BY24) -> 2151.3742 | BZ25: =BY25/$BY$46*100% -> 0.99559924 | CB25: =SUM(CB23:CB24) -> 9180.8743 | CC25: =SUM(CC23:CC24) -> 16274.814 | CE25: =SUM(CE23:CE24) -> 16054.504 | CF25: =CE25/$CE$46*100% -> 0.94966887 | CG25: =SUM(CG23:CG24) -> 12107.013 | CH25: =CG25/$CG$46*100% -> 0.98998404
B26: Sale of services | F26: =E26/$E$46*100% -> 0 | H26: =G26/$G$46*100% -> 0 | J26: =I26/$I$46*100% -> 0 | P26: =O26/$O$46*100% -> 0 | R26: =Q26/$Q$46*100% -> 0 | T26: =S26/$S$46*100% -> 0 | V26: =U26/$U$46*100% -> 0 | X26: =W26/$W$46*100% -> 0 | Z26: =Y26/$Y$46*100% -> 0 | AC26: =AB26/$AB$46*100% -> 0 | AE26: =AD26/$AD$46*100% -> 0 | AH26: =AG26/$AG$46*100% -> 0 | AM26: =AL26/$AL$46*100% -> 0 | AR26: =AQ26/$AQ$46*100% -> 0 | BA26: =AZ26/$AZ$46*100% -> 0 | BF26: =BE26/$BE$46*100% -> 0 | BJ26: =BI26/$BI$46*100% -> 0 | BS26: =BR26/$BR$46*100% -> 0 | BT26: =BG26+BK26+BO26-BQ26 -> 0 | BU26: =BT26/$BT$46*100% -> 0 | BX26: =BW26/$BW$46*100% -> 0 | BZ26: =BY26/$BY$46*100% -> 0 | CF26: =CE26/$CE$46*100% -> 0 | CH26: =CG26/$CG$46*100% -> 0
B27: Income from Jobwork charges | C27: =E27-'Apr-26'!E27 -> 104.42654 | D27: =C27/$C$46*100% -> 0.033426787 | E27: =-SUMIF('05.conso TB'!A:A,'May-26'!B27,'05.conso TB'!R:R)/10^5 -> 138.36163 | F27: =E27/$E$46*100% -> 0.021414403 | G27: =I27-'Apr-26'!I27 -> 158.09572 | H27: =G27/$G$46*100% -> 0.11902941 | I27: =-SUMIF('05.conso TB'!A:A,'May-26'!B27,'05.conso TB'!S:S)/10^5 -> 196.36106 | J27: =I27/$I$46*100% -> 0.078245388 | K27: =M27-'Apr-26'!M27 -> 0 | L27: =K27/$C$46*100% -> 0 | M27: =-SUMIF('05.conso TB'!A:A,'May-26'!B27,'05.conso TB'!T:T) -> 0 | N27: =M27/$C$46*100% -> 0 | O27: =Q27-'Apr-26'!Q27 -> 0 | P27: =O27/$O$46*100% -> 0 | Q27: =-SUMIF('05.conso TB'!A:A,'May-26'!B27,'05.conso TB'!U:U)/10^5 -> 0 | R27: =Q27/$Q$46*100% -> 0 | S27: =U27-'Apr-26'!U27 -> 0 | T27: =S27/$S$46*100% -> 0 | U27: =-SUMIF('05.conso TB'!A:A,'May-26'!B27,'05.conso TB'!V:V)/10^5 -> 0 | V27: =U27/$U$46*100% -> 0 | W27: =Y27-'Apr-26'!Y27 -> 0 | X27: =W27/$W$46*100% -> 0 | Y27: =-SUMIF('05.conso TB'!A:A,'May-26'!B27,'05.conso TB'!G:G)/10^5 -> 0 | Z27: =Y27/$Y$46*100% -> 0 | AB27: =AD27-'Apr-26'!AD27 -> 262.52226 | AC27: =AB27/$AB$46*100% -> 0.028468827 | AD27: =E27+I27+M27+Q27+U27+Y27 -> 334.7227 | AE27: =AD27/$AD$46*100% -> 0.023159453 | AG27: =AI27-'Apr-26'!AI27 -> 271.89915 | AH27: =AG27/$AG$46*100% -> 0.73984355 | AI27: =-SUMIF('05.conso TB'!A:A,'May-26'!B27,'05.conso TB'!Q:Q)/10^5 -> 553.60487 | AJ27: =AI27/$AI$46*100% -> 0.75013939 | AL27: =AN27-'Apr-26'!AN27 -> 235.35333 | AM27: =AL27/$AL$46*100% -> 0.19873822 | AN27: =-SUMIF('05.conso TB'!A:A,'May-26'!B27,'05.conso TB'!W:W)/10^5 -> 418.92558 | AO27: =AN27/$AN$46*100% -> 0.1803888 | AQ27: =AS27-'Apr-26'!AS27 -> 51.17576 | AR27: =AQ27/$AQ$46*100% -> 0.02510059 | AS27: =-SUMIF('05.conso TB'!A:A,'May-26'!B27,'05.conso TB'!M:M)/10^5 -> 51.17576 | AT27: =AS27/$AS$46*100% -> 0.013221867 | AU27: =AW27-'Apr-26'!AW27 -> 0 | AV27: =AU27/$C$46*100% -> 0 | AW27: =-SUMIF('05.conso TB'!A:A,'May-26'!B27,'05.conso TB'!P:P)/10^5 -> 0 | AX27: =AW27/$AW$46*100% -> 0 | AZ27: =BB27-'Apr-26'!BB27 -> 51.17576 | BA27: =AZ27/$AZ$46*100% -> 0.016860723 | BB27: =AS27+AW27 -> 51.17576 | BC27: =BB27/$BB$46*100% -> 0.0089502971 | BE27: =BG27-'Apr-26'!BG27 -> 8.799365 | BF27: =BE27/$BE$46*100% -> 0.0031483392 | BG27: =-SUMIF('05.conso TB'!A:A,'May-26'!B27,'05.conso TB'!H:H)/10^5 -> 54.608609 | BH27: =BG27/$BG$46*100% -> 0.011620981 | BI27: =BK27-'Apr-26'!BK27 -> 0 | BJ27: =BI27/$BI$46*100% -> 0 | BK27: =-SUMIF('05.conso TB'!A:A,'May-26'!B27,'05.conso TB'!I:I)/10^5 -> 0 | BL27: =BK27/$BK$46*100% -> 0 | BM27: =BO27-'Apr-26'!BO27 -> 0 | BN27: =BM27/$C$46*100% -> 0 | BO27: =-SUMIF('05.conso TB'!A:A,'May-26'!B27,'05.conso TB'!J:J)/10^5 -> 0 | BP27: =BO27/$C$46*100% -> 0 | BQ27: 0 | BR27: =BT27-'Apr-26'!BT27 -> 8.799365 | BS27: =BR27/$BR$46*100% -> 0.0033274254 | BT27: =BG27+BK27+BO27-BQ27 -> 54.608609 | BU27: =BT27/$BT$46*100% -> 0.01216838 | BW27: =BY27-'Apr-26'!BY27 -> 0 | BX27: =BW27/$BW$46*100% -> 0 | BY27: =-SUMIF('05.conso TB'!A:A,'May-26'!B27,'05.conso TB'!L:L)/10^5 -> 0 | BZ27: =BY27/$BY$46*100% -> 0 | CB27: =CC27-'Apr-26'!CC27 -> 848.4175 | CC27: 1375.3983 | CE27: =AB27+AG27+AL27+AZ27+BR27+BW27-CA27 -> 829.74987 | CF27: =CE27/$CE$46*100% -> 0.049082029 | CG27: =AD27+AI27+AN27+BB27+BT27+BY27-CC27 -> 37.639178 | CH27: =CG27/$CG$46*100% -> 0.0030777357
B28: Total Sales of services | C28: =E28-'Apr-26'!E28 -> 104.42654 | D28: =SUM(D27) -> 0.033426787 | E28: =SUM(E27) -> 138.36163 | F28: =E28/$E$46*100% -> 0.021414403 | G28: =I28-'Apr-26'!I28 -> 158.09572 | H28: =G28/$G$46*100% -> 0.11902941 | I28: =SUM(I27) -> 196.36106 | J28: =I28/$I$46*100% -> 0.078245388 | K28: =M28-'Apr-26'!M28 -> 0 | L28: =SUM(L27) -> 0 | M28: =SUM(M27) -> 0 | N28: =SUM(N27) -> 0 | O28: =Q28-'Apr-26'!Q28 -> 0 | P28: =O28/$O$46*100% -> 0 | Q28: =Q27 -> 0 | R28: =Q28/$Q$46*100% -> 0 | S28: =U28-'Apr-26'!U28 -> 0 | T28: =S28/$S$46*100% -> 0 | U28: =-SUMIF('05.conso TB'!A:A,'May-26'!B28,'05.conso TB'!V:V)/10^5 -> 0 | V28: =U28/$U$46*100% -> 0 | W28: =Y28-'Apr-26'!Y28 -> 0 | X28: =W28/$W$46*100% -> 0 | Y28: =-SUMIF('05.conso TB'!A:A,'May-26'!B28,'05.conso TB'!G:G)/10^5 -> 0 | Z28: =Y28/$Y$46*100% -> 0 | AA28: =SUM(AA27) -> 0 | AB28: =AD28-'Apr-26'!AD28 -> 262.52226 | AC28: =AB28/$AB$46*100% -> 0.028468827 | AD28: =SUM(AD27) -> 334.7227 | AE28: =AD28/$AD$46*100% -> 0.023159453 | AG28: =AI28-'Apr-26'!AI28 -> 271.89915 | AH28: =AG28/$AG$46*100% -> 0.73984355 | AI28: =SUM(AI27) -> 553.60487 | AJ28: =SUM(AJ27) -> 0.75013939 | AL28: =AN28-'Apr-26'!AN28 -> 235.35333 | AM28: =AL28/$AL$46*100% -> 0.19873822 | AN28: =AN27 -> 418.92558 | AO28: =SUM(AO27) -> 0.1803888 | AP28: =AQ28/$AQ$1*10^5 -> 8.5717952 | AQ28: =AS28-'Apr-26'!AS28 -> 51.17576 | AR28: =AQ28/$AQ$46*100% -> 0.02510059 | AS28: =SUM(AS27) -> 51.17576 | AT28: =SUM(AT27) -> 0.013221867 | AU28: =AW28-'Apr-26'!AW28 -> 0 | AV28: =SUM(AV27) -> 0 | AW28: =SUM(AW27) -> 0 | AX28: =SUM(AX27) -> 0 | AZ28: =BB28-'Apr-26'!BB28 -> 51.17576 | BA28: =AZ28/$AZ$46*100% -> 0.016860723 | BB28: =SUM(BB27) -> 51.17576 | BC28: =SUM(BC27) -> 0.0089502971 | BE28: =BG28-'Apr-26'!BG28 -> 8.799365 | BF28: =BE28/$BE$46*100% -> 0.0031483392 | BG28: =SUM(BG27) -> 54.608609 | BH28: =SUM(BH27) -> 0.011620981 | BI28: =BK28-'Apr-26'!BK28 -> 0 | BJ28: =BI28/$BI$46*100% -> 0 | BK28: =SUM(BK27) -> 0 | BL28: =SUM(BL27) -> 0 | BM28: =BO28-'Apr-26'!BO28 -> 0 | BN28: =SUM(BN27) -> 0 | BO28: =SUM(BO27) -> 0 | BP28: =SUM(BP27) -> 0 | BQ28: =BQ27 -> 0 | BR28: =BT28-'Apr-26'!BT28 -> 8.799365 | BS28: =BR28/$BR$46*100% -> 0.0033274254 | BT28: =BG28+BK28+BO28-BQ28 -> 54.608609 | BU28: =BT28/$BT$46*100% -> 0.01216838 | BW28: =BY28-'Apr-26'!BY28 -> 0 | BX28: =BW28/$BW$46*100% -> 0 | BY28: =SUM(BY27) -> 0 | BZ28: =BY28/$BY$46*100% -> 0 | CB28: =CC28-'Apr-26'!CC28 -> 848.4175 | CC28: =SUM(CC27) -> 1375.3983 | CE28: =SUM(CE27) -> 829.74987 | CF28: =CE28/$CE$46*100% -> 0.049082029 | CG28: =SUM(CG27) -> 37.639178 | CH28: =CG28/$CG$46*100% -> 0.0030777357
B29: Other operating revenue | C29: =E29-'Apr-26'!E29 -> 0 | F29: =E29/$E$46*100% -> 0 | G29: =I29-'Apr-26'!I29 -> 0 | H29: =G29/$G$46*100% -> 0 | J29: =I29/$I$46*100% -> 0 | K29: =M29-'Apr-26'!M29 -> 0 | O29: =Q29-'Apr-26'!Q29 -> 0 | P29: =O29/$O$46*100% -> 0 | Q29: =-SUMIF('05.conso TB'!A:A,'May-26'!B29,'05.conso TB'!U:U)/10^5 -> 0 | R29: =Q29/$Q$46*100% -> 0 | S29: =U29-'Apr-26'!U29 -> 0 | T29: =S29/$S$46*100% -> 0 | U29: =-SUMIF('05.conso TB'!A:A,'May-26'!B29,'05.conso TB'!V:V)/10^5 -> 0 | V29: =U29/$U$46*100% -> 0 | W29: =Y29-'Apr-26'!Y29 -> 0 | X29: =W29/$W$46*100% -> 0 | Y29: =-SUMIF('05.conso TB'!A:A,'May-26'!B29,'05.conso TB'!G:G)/10^5 -> 0 | Z29: =Y29/$Y$46*100% -> 0 | AB29: =AD29-'Apr-26'!AD29 -> 0 | AC29: =AB29/$AB$46*100% -> 0 | AE29: =AD29/$AD$46*100% -> 0 | AG29: =AI29-'Apr-26'!AI29 -> 0 | AH29: =AG29/$AG$46*100% -> 0 | AI29: =-SUMIF('05.conso TB'!A:A,'May-26'!B29,'05.conso TB'!Q:Q)/10^5 -> 0 | AL29: =AN29-'Apr-26'!AN29 -> 0 | AM29: =AL29/$AL$46*100% -> 0 | AN29: =-SUMIF('05.conso TB'!A:A,'May-26'!B29,'05.conso TB'!W:W)/10^5 -> 0 | AQ29: =AS29-'Apr-26'!AS29 -> 0 | AR29: =AQ29/$AQ$46*100% -> 0 | AU29: =AW29-'Apr-26'!AW29 -> 0 | AZ29: =BB29-'Apr-26'!BB29 -> 0 | BA29: =AZ29/$AZ$46*100% -> 0 | BE29: =BG29-'Apr-26'!BG29 -> 0 | BF29: =BE29/$BE$46*100% -> 0 | BI29: =BK29-'Apr-26'!BK29 -> 0 | BJ29: =BI29/$BI$46*100% -> 0 | BM29: =BO29-'Apr-26'!BO29 -> 0 | BR29: =BT29-'Apr-26'!BT29 -> 0 | BS29: =BR29/$BR$46*100% -> 0 | BT29: =BG29+BK29+BO29-BQ29 -> 0 | BU29: =BT29/$BT$46*100% -> 0 | BW29: =BY29-'Apr-26'!BY29 -> 0 | BX29: =BW29/$BW$46*100% -> 0 | BZ29: =BY29/$BY$46*100% -> 0 | CB29: =CD29-'Apr-26'!CD29 -> 0 | CF29: =CE29/$CE$46*100% -> 0 | CH29: =CG29/$CG$46*100% -> 0
B30: Export incentives | C30: =E30-'Apr-26'!E30 -> 0 | D30: =C30/$C$46*100% -> 0 | E30: =-SUMIF('05.conso TB'!A:A,'May-26'!B30,'05.conso TB'!R:R)/10^5 -> 0 | F30: =E30/$E$46*100% -> 0 | G30: =I30-'Apr-26'!I30 -> 0 | H30: =G30/$G$46*100% -> 0 | I30: =-SUMIF('05.conso TB'!A:A,'May-26'!B30,'05.conso TB'!S:S)/10^5 -> 0 | J30: =I30/$I$46*100% -> 0 | K30: =M30-'Apr-26'!M30 -> 0 | L30: =K30/$C$46*100% -> 0 | M30: =-SUMIF('05.conso TB'!A:A,'May-26'!B30,'05.conso TB'!T:T) -> 0 | N30: =M30/$C$46*100% -> 0 | O30: =Q30-'Apr-26'!Q30 -> 0 | P30: =O30/$O$46*100% -> 0 | Q30: =-SUMIF('05.conso TB'!A:A,'May-26'!B30,'05.conso TB'!U:U)/10^5 -> 0 | R30: =Q30/$Q$46*100% -> 0 | S30: =U30-'Apr-26'!U30 -> 0 | T30: =S30/$S$46*100% -> 0 | U30: =-SUMIF('05.conso TB'!A:A,'May-26'!B30,'05.conso TB'!V:V)/10^5 -> 0 | V30: =U30/$U$46*100% -> 0 | W30: =Y30-'Apr-26'!Y30 -> 0 | X30: =W30/$W$46*100% -> 0 | Y30: =-SUMIF('05.conso TB'!A:A,'May-26'!B30,'05.conso TB'!G:G)/10^5 -> 0 | Z30: =Y30/$Y$46*100% -> 0 | AB30: =AD30-'Apr-26'!AD30 -> 0 | AC30: =AB30/$AB$46*100% -> 0 | AD30: =E30+I30+M30+Q30+U30+Y30 -> 0 | AE30: =AD30/$AD$46*100% -> 0 | AG30: =AI30-'Apr-26'!AI30 -> 0 | AH30: =AG30/$AG$46*100% -> 0 | AI30: =-SUMIF('05.conso TB'!A:A,'May-26'!B30,'05.conso TB'!Q:Q)/10^5 -> 0 | AJ30: =AI30/$AI$46*100% -> 0 | AL30: =AN30-'Apr-26'!AN30 -> 0 | AM30: =AL30/$AL$46*100% -> 0 | AN30: =-SUMIF('05.conso TB'!A:A,'May-26'!B30,'05.conso TB'!W:W)/10^5 -> 0 | AO30: =AN30/$AN$46*100% -> 0 | AQ30: =AS30-'Apr-26'!AS30 -> 0 | AR30: =AQ30/$AQ$46*100% -> 0 | AS30: =-SUMIF('05.conso TB'!A:A,'May-26'!B30,'05.conso TB'!M:M)/10^5 -> 0 | AT30: =AS30/$AS$46*100% -> 0 | AU30: =AW30-'Apr-26'!AW30 -> 0 | AV30: =AU30/$C$46*100% -> 0 | AW30: =-SUMIF('05.conso TB'!A:A,'May-26'!B30,'05.conso TB'!P:P)/10^5 -> 0 | AX30: =AW30/$AW$46*100% -> 0 | AZ30: =BB30-'Apr-26'!BB30 -> 0 | BA30: =AZ30/$AZ$46*100% -> 0 | BB30: =AS30+AW30 -> 0 | BC30: =BB30/$BB$46*100% -> 0 | BE30: =BG30-'Apr-26'!BG30 -> 0 | BF30: =BE30/$BE$46*100% -> 0 | BG30: =-SUMIF('05.conso TB'!A:A,'May-26'!B30,'05.conso TB'!H:H)/10^5 -> 0.21065 | BH30: =BG30/$BG$46*100% -> 4.4827359e-05 | BI30: =BK30-'Apr-26'!BK30 -> 0 | BJ30: =BI30/$BI$46*100% -> 0 | BK30: =-SUMIF('05.conso TB'!A:A,'May-26'!B30,'05.conso TB'!I:I)/10^5 -> 0 | BL30: =BK30/$BK$46*100% -> 0 | BM30: =BO30-'Apr-26'!BO30 -> 0 | BN30: =BM30/$C$46*100% -> 0 | BO30: =-SUMIF('05.conso TB'!A:A,'May-26'!B30,'05.conso TB'!J:J)/10^5 -> 0 | BP30: =BO30/$C$46*100% -> 0 | BR30: =BT30-'Apr-26'!BT30 -> 0 | BS30: =BR30/$BR$46*100% -> 0 | BT30: =BG30+BK30+BO30-BQ30 -> 0.21065 | BU30: =BT30/$BT$46*100% -> 4.6938921e-05 | BW30: =BY30-'Apr-26'!BY30 -> 0 | BX30: =BW30/$BW$46*100% -> 0 | BY30: =-SUMIF('05.conso TB'!A:A,'May-26'!B30,'05.conso TB'!L:L)/10^5 -> 0 | BZ30: =BY30/$BY$46*100% -> 0 | CB30: =CD30-'Apr-26'!CD30 -> 0 | CE30: =AB30+AG30+AL30+AZ30+BR30+BW30 -> 0 | CF30: =CE30/$CE$46*100% -> 0 | CG30: =AD30+AI30+AN30+BB30+BT30+BY30 -> 0.21065 | CH30: =CG30/$CG$46*100% -> 1.7224739e-05
B31: Commission income | C31: =E31-'Apr-26'!E31 -> 0 | D31: =C31/$C$46*100% -> 0 | E31: =-SUMIF('05.conso TB'!A:A,'May-26'!B31,'05.conso TB'!R:R) -> 0 | F31: =E31/$E$46*100% -> 0 | G31: =I31-'Apr-26'!I31 -> 0 | H31: =G31/$G$46*100% -> 0 | I31: =-SUMIF('05.conso TB'!A:A,'May-26'!B31,'05.conso TB'!S:S)/10^5 -> 0 | J31: =I31/$I$46*100% -> 0 | K31: =M31-'Apr-26'!M31 -> 7.41585 | L31: =K31/$C$46*100% -> 0.002373803 | M31: =-SUMIF('05.conso TB'!A:A,'May-26'!B31,'05.conso TB'!T:T)/10^5 -> 26.462942 | N31: =M31/$C$46*100% -> 0.0084707498 | O31: =Q31-'Apr-26'!Q31 -> 0 | P31: =O31/$O$46*100% -> 0 | Q31: =-SUMIF('05.conso TB'!A:A,'May-26'!B31,'05.conso TB'!U:U)/10^5 -> 0 | R31: =Q31/$Q$46*100% -> 0 | S31: =U31-'Apr-26'!U31 -> 0 | T31: =S31/$S$46*100% -> 0 | U31: =-SUMIF('05.conso TB'!A:A,'May-26'!B31,'05.conso TB'!V:V)/10^5 -> 0 | V31: =U31/$U$46*100% -> 0 | W31: =Y31-'Apr-26'!Y31 -> 0 | X31: =W31/$W$46*100% -> 0 | Y31: =-SUMIF('05.conso TB'!A:A,'May-26'!B31,'05.conso TB'!G:G)/10^5 -> 0 | Z31: =Y31/$Y$46*100% -> 0 | AB31: =AD31-'Apr-26'!AD31 -> 7.41585 | AC31: =AB31/$AB$46*100% -> 0.00080420057 | AD31: =E31+I31+M31+Q31+U31+Y31 -> 26.462942 | AE31: =AD31/$AD$46*100% -> 0.0018309701 | AG31: =AI31-'Apr-26'!AI31 -> 0 | AH31: =AG31/$AG$46*100% -> 0 | AI31: =-SUMIF('05.conso TB'!A:A,'May-26'!B31,'05.conso TB'!Q:Q)/10^5 -> 0 | AJ31: =AI31/$AI$46*100% -> 0 | AL31: =AN31-'Apr-26'!AN31 -> 0 | AM31: =AL31/$AL$46*100% -> 0 | AN31: =-SUMIF('05.conso TB'!A:A,'May-26'!B31,'05.conso TB'!W:W)/10^5 -> 0 | AO31: =AN31/$AN$46*100% -> 0 | AQ31: =AS31-'Apr-26'!AS31 -> 0 | AR31: =AQ31/$AQ$46*100% -> 0 | AS31: =-SUMIF('05.conso TB'!A:A,'May-26'!B31,'05.conso TB'!M:M)/10^5 -> 0 | AT31: =AS31/$AS$46*100% -> 0 | AU31: =AW31-'Apr-26'!AW31 -> 0 | AV31: =AU31/$C$46*100% -> 0 | AW31: =-SUMIF('05.conso TB'!A:A,'May-26'!B31,'05.conso TB'!P:P)/10^5 -> 0 | AX31: =AW31/$AW$46*100% -> 0 | AZ31: =BB31-'Apr-26'!BB31 -> 0 | BA31: =AZ31/$AZ$46*100% -> 0 | BB31: =AS31+AW31 -> 0 | BC31: =BB31/$BB$46*100% -> 0 | BE31: =BG31-'Apr-26'!BG31 -> 0 | BF31: =BE31/$BE$46*100% -> 0 | BG31: =-SUMIF('05.conso TB'!A:A,'May-26'!B31,'05.conso TB'!H:H)/10^5 -> 0 | BH31: =BG31/$BG$46*100% -> 0 | BI31: =BK31-'Apr-26'!BK31 -> 0 | BJ31: =BI31/$BI$46*100% -> 0 | BK31: =-SUMIF('05.conso TB'!A:A,'May-26'!B31,'05.conso TB'!I:I)/10^5 -> 0 | BL31: =BK31/$BK$46*100% -> 0 | BM31: =BO31-'Apr-26'!BO31 -> 0 | BN31: =BM31/$C$46*100% -> 0 | BO31: =-SUMIF('05.conso TB'!A:A,'May-26'!B31,'05.conso TB'!J:J)/10^5 -> 0 | BP31: =BO31/$C$46*100% -> 0 | BR31: =BT31-'Apr-26'!BT31 -> 0 | BS31: =BR31/$BR$46*100% -> 0 | BT31: =BG31+BK31+BO31-BQ31 -> 0 | BU31: =BT31/$BT$46*100% -> 0 | BW31: =BY31-'Apr-26'!BY31 -> 0 | BX31: =BW31/$BW$46*100% -> 0 | BY31: =-SUMIF('05.conso TB'!A:A,'May-26'!B31,'05.conso TB'!L:L)/10^5 -> 0 | BZ31: =BY31/$BY$46*100% -> 0 | CB31: =CD31-'Apr-26'!CD31 -> 0 | CE31: =AB31+AG31+AL31+AZ31+BR31+BW31 -> 7.41585 | CF31: =CE31/$CE$46*100% -> 0.0004386683 | CG31: =AD31+AI31+AN31+BB31+BT31+BY31 -> 26.462942 | CH31: =CG31/$CG$46*100% -> 0.0021638608
B32: Scrap sales | C32: =E32-'Apr-26'!E32 -> 0 | D32: =C32/$C$46*100% -> 0 | E32: =-SUMIF('05.conso TB'!A:A,'May-26'!B32,'05.conso TB'!R:R) -> 0 | F32: =E32/$E$46*100% -> 0 | G32: =I32-'Apr-26'!I32 -> 0 | H32: =G32/$G$46*100% -> 0 | I32: =-SUMIF('05.conso TB'!A:A,'May-26'!B32,'05.conso TB'!S:S)/10^5 -> 0 | J32: =I32/$I$46*100% -> 0 | K32: =M32-'Apr-26'!M32 -> 0 | L32: =K32/$C$46*100% -> 0 | M32: =-SUMIF('05.conso TB'!A:A,'May-26'!B32,'05.conso TB'!T:T) -> 0 | N32: =M32/$C$46*100% -> 0 | O32: =Q32-'Apr-26'!Q32 -> 0 | P32: =O32/$O$46*100% -> 0 | Q32: =-SUMIF('05.conso TB'!A:A,'May-26'!B32,'05.conso TB'!U:U)/10^5 -> 0 | R32: =Q32/$Q$46*100% -> 0 | S32: =U32-'Apr-26'!U32 -> 0 | T32: =S32/$S$46*100% -> 0 | U32: =-SUMIF('05.conso TB'!A:A,'May-26'!B32,'05.conso TB'!V:V)/10^5 -> 0 | V32: =U32/$U$46*100% -> 0 | W32: =Y32-'Apr-26'!Y32 -> 0 | X32: =W32/$W$46*100% -> 0 | Y32: =-SUMIF('05.conso TB'!A:A,'May-26'!B32,'05.conso TB'!G:G)/10^5 -> 0 | Z32: =Y32/$Y$46*100% -> 0 | AB32: =AD32-'Apr-26'!AD32 -> 0 | AC32: =AB32/$AB$46*100% -> 0 | AD32: =E32+I32+M32+Q32+U32+Y32 -> 0 | AE32: =AD32/$AD$46*100% -> 0 | AG32: =AI32-'Apr-26'!AI32 -> 0 | AH32: =AG32/$AG$46*100% -> 0 | AI32: =-SUMIF('05.conso TB'!A:A,'May-26'!B32,'05.conso TB'!Q:Q)/10^5 -> 0 | AJ32: =AI32/$AI$46*100% -> 0 | AL32: =AN32-'Apr-26'!AN32 -> 0 | AM32: =AL32/$AL$46*100% -> 0 | AN32: =-SUMIF('05.conso TB'!A:A,'May-26'!B32,'05.conso TB'!W:W)/10^5 -> 0 | AO32: =AN32/$AN$46*100% -> 0 | AQ32: =AS32-'Apr-26'!AS32 -> 0 | AR32: =AQ32/$AQ$46*100% -> 0 | AS32: =-SUMIF('05.conso TB'!A:A,'May-26'!B32,'05.conso TB'!M:M)/10^5 -> 0 | AT32: =AS32/$AS$46*100% -> 0 | AU32: =AW32-'Apr-26'!AW32 -> 0 | AV32: =AU32/$C$46*100% -> 0 | AW32: =-SUMIF('05.conso TB'!A:A,'May-26'!B32,'05.conso TB'!P:P)/10^5 -> 0 | AX32: =AW32/$AW$46*100% -> 0 | AZ32: =BB32-'Apr-26'!BB32 -> 0 | BA32: =AZ32/$AZ$46*100% -> 0 | BB32: =AS32+AW32 -> 0 | BC32: =BB32/$BB$46*100% -> 0 | BE32: =BG32-'Apr-26'!BG32 -> 0 | BF32: =BE32/$BE$46*100% -> 0 | BG32: =-SUMIF('05.conso TB'!A:A,'May-26'!B32,'05.conso TB'!H:H)/10^5 -> 0 | BH32: =BG32/$BG$46*100% -> 0 | BI32: =BK32-'Apr-26'!BK32 -> 0 | BJ32: =BI32/$BI$46*100% -> 0 | BK32: =-SUMIF('05.conso TB'!A:A,'May-26'!B32,'05.conso TB'!I:I)/10^5 -> 0 | BL32: =BK32/$BK$46*100% -> 0 | BM32: =BO32-'Apr-26'!BO32 -> 0 | BN32: =BM32/$C$46*100% -> 0 | BO32: =-SUMIF('05.conso TB'!A:A,'May-26'!B32,'05.conso TB'!J:J)/10^5 -> 0 | BP32: =BO32/$C$46*100% -> 0 | BR32: =BT32-'Apr-26'!BT32 -> 0 | BS32: =BR32/$BR$46*100% -> 0 | BT32: =BG32+BK32+BO32-BQ32 -> 0 | BU32: =BT32/$BT$46*100% -> 0 | BW32: =BY32-'Apr-26'!BY32 -> 0 | BX32: =BW32/$BW$46*100% -> 0 | BY32: =-SUMIF('05.conso TB'!A:A,'May-26'!B32,'05.conso TB'!L:L)/10^5 -> 0 | BZ32: =BY32/$BY$46*100% -> 0 | CB32: =CD32-'Apr-26'!CD32 -> 0 | CE32: =AB32+AG32+AL32+AZ32+BR32+BW32 -> 0 | CF32: =CE32/$CE$46*100% -> 0 | CG32: =AD32+AI32+AN32+BB32+BT32+BY32 -> 0 | CH32: =CG32/$CG$46*100% -> 0
B33: Total Other operating revenue | C33: =SUM(C30:C32) -> 0 | D33: =SUM(D30:D32) -> 0 | E33: =SUM(E30:E32) -> 0 | F33: =E33/$E$46*100% -> 0 | G33: =SUM(G30:G32) -> 0 | H33: =G33/$G$46*100% -> 0 | I33: =-SUMIF('05.conso TB'!A:A,'May-26'!B33,'05.conso TB'!S:S)/10^5 -> 0 | J33: =I33/$I$46*100% -> 0 | K33: =SUM(K30:K32) -> 7.41585 | L33: =SUM(L30:L32) -> 0.002373803 | M33: =SUM(M30:M32) -> 26.462942 | N33: =SUM(N30:N32) -> 0.0084707498 | O33: =SUM(O30:O32) -> 0 | P33: =O33/$O$46*100% -> 0 | Q33: =SUM(Q30:Q32) -> 0 | R33: =Q33/$Q$46*100% -> 0 | S33: =SUM(S30:S32) -> 0 | T33: =S33/$S$46*100% -> 0 | U33: =SUM(U30:U32) -> 0 | V33: =U33/$U$46*100% -> 0 | W33: =SUM(W30:W32) -> 0 | X33: =W33/$W$46*100% -> 0 | Y33: =SUM(Y30:Y32) -> 0 | Z33: =Y33/$Y$46*100% -> 0 | AA33: =SUM(AA30:AA32) -> 0 | AB33: =SUM(AB30:AB32) -> 7.41585 | AC33: =AB33/$AB$46*100% -> 0.00080420057 | AD33: =SUM(AD30:AD32) -> 26.462942 | AE33: =AD33/$AD$46*100% -> 0.0018309701 | AG33: =SUM(AG30:AG32) -> 0 | AH33: =AG33/$AG$46*100% -> 0 | AI33: =SUM(AI30:AI32) -> 0 | AJ33: =SUM(AJ30:AJ32) -> 0 | AL33: =SUM(AL30:AL32) -> 0 | AM33: =AL33/$AL$46*100% -> 0 | AN33: =SUM(AN30:AN32) -> 0 | AO33: =SUM(AO30:AO32) -> 0 | AP33: =AQ33/$AQ$1*10^5 -> 0 | AQ33: =SUM(AQ30:AQ32) -> 0 | AR33: =AQ33/$AQ$46*100% -> 0 | AS33: =SUM(AS30:AS32) -> 0 | AT33: =SUM(AT30:AT32) -> 0 | AU33: =SUM(AU30:AU32) -> 0 | AV33: =SUM(AV30:AV32) -> 0 | AW33: =SUM(AW30:AW32) -> 0 | AX33: =SUM(AX30:AX32) -> 0 | AZ33: =SUM(AZ30:AZ32) -> 0 | BA33: =AZ33/$AZ$46*100% -> 0 | BB33: =SUM(BB30:BB32) -> 0 | BC33: =SUM(BC30:BC32) -> 0 | BE33: =SUM(BE30:BE32) -> 0 | BF33: =BE33/$BE$46*100% -> 0 | BG33: =SUM(BG30:BG32) -> 0.21065 | BH33: =SUM(BH30:BH32) -> 4.4827359e-05 | BI33: =SUM(BI30:BI32) -> 0 | BJ33: =BI33/$BI$46*100% -> 0 | BK33: =SUM(BK30:BK32) -> 0 | BL33: =SUM(BL30:BL32) -> 0 | BM33: =SUM(BM30:BM32) -> 0 | BN33: =SUM(BN30:BN32) -> 0 | BO33: =SUM(BO30:BO32) -> 0 | BP33: =SUM(BP30:BP32) -> 0 | BR33: =SUM(BR30:BR32) -> 0 | BS33: =BR33/$BR$46*100% -> 0 | BT33: =BG33+BK33+BO33-BQ33 -> 0.21065 | BU33: =BT33/$BT$46*100% -> 4.6938921e-05 | BW33: =SUM(BW30:BW32) -> 0 | BX33: =BW33/$BW$46*100% -> 0 | BY33: =SUM(BY30:BY32) -> 0 | BZ33: =BY33/$BY$46*100% -> 0 | CB33: =SUM(CB30:CB32) -> 0 | CE33: =SUM(CE30:CE32) -> 7.41585 | CF33: =CE33/$CE$46*100% -> 0.0004386683 | CG33: =SUM(CG30:CG32) -> 26.673592 | CH33: =CG33/$CG$46*100% -> 0.0021810855
B34: Other income | F34: =E34/$E$46*100% -> 0 | H34: =G34/$G$46*100% -> 0 | I34: =-SUMIF('05.conso TB'!A:A,'May-26'!B34,'05.conso TB'!S:S)/10^5 -> 0 | J34: =I34/$I$46*100% -> 0 | P34: =O34/$O$46*100% -> 0 | R34: =Q34/$Q$46*100% -> 0 | T34: =S34/$S$46*100% -> 0 | V34: =U34/$U$46*100% -> 0 | X34: =W34/$W$46*100% -> 0 | Z34: =Y34/$Y$46*100% -> 0 | AC34: =AB34/$AB$46*100% -> 0 | AE34: =AD34/$AD$46*100% -> 0 | AH34: =AG34/$AG$46*100% -> 0 | AM34: =AL34/$AL$46*100% -> 0 | AR34: =AQ34/$AQ$46*100% -> 0 | BA34: =AZ34/$AZ$46*100% -> 0 | BF34: =BE34/$BE$46*100% -> 0 | BJ34: =BI34/$BI$46*100% -> 0 | BS34: =BR34/$BR$46*100% -> 0 | BT34: =BG34+BK34+BO34-BQ34 -> 0 | BU34: =BT34/$BT$46*100% -> 0 | BX34: =BW34/$BW$46*100% -> 0 | BZ34: =BY34/$BY$46*100% -> 0 | CF34: =CE34/$CE$46*100% -> 0 | CH34: =CG34/$CG$46*100% -> 0
B35: Wind mill income | C35: =E35-'Apr-26'!E35 -> 12.60319 | D35: =C35/$C$46*100% -> 0.0040342631 | E35: =-SUMIF('05.conso TB'!A:A,'May-26'!B35,'05.conso TB'!R:R)/10^5 -> 18.60616 | F35: =E35/$E$46*100% -> 0.0028796987 | G35: =I35-'Apr-26'!I35 -> 11.2517 | H35: =G35/$G$46*100% -> 0.0084713443 | I35: =-SUMIF('05.conso TB'!A:A,'May-26'!B35,'05.conso TB'!S:S)/10^5 -> 20.50025 | J35: =I35/$I$46*100% -> 0.0081688803 | K35: =M35-'Apr-26'!M35 -> 0 | L35: =K35/$C$46*100% -> 0 | M35: =-SUMIF('05.conso TB'!A:A,'May-26'!B35,'05.conso TB'!T:T)/10^5 -> 0 | N35: =M35/$C$46*100% -> 0 | O35: =Q35-'Apr-26'!Q35 -> 0 | P35: =O35/$O$46*100% -> 0 | Q35: =-SUMIF('05.conso TB'!A:A,'May-26'!B35,'05.conso TB'!U:U)/10^5 -> 0 | R35: =Q35/$Q$46*100% -> 0 | S35: =U35-'Apr-26'!U35 -> 0 | T35: =S35/$S$46*100% -> 0 | U35: =-SUMIF('05.conso TB'!A:A,'May-26'!B35,'05.conso TB'!V:V)/10^5 -> 0 | V35: =U35/$U$46*100% -> 0 | W35: =Y35-'Apr-26'!Y35 -> 0 | X35: =W35/$W$46*100% -> 0 | Y35: =-SUMIF('05.conso TB'!A:A,'May-26'!B35,'05.conso TB'!G:G)/10^5 -> 0 | Z35: =Y35/$Y$46*100% -> 0 | AB35: =AD35-'Apr-26'!AD35 -> 23.85489 | AC35: =AB35/$AB$46*100% -> 0.0025869072 | AD35: =E35+I35+M35+Q35+U35+Y35 -> 39.10641 | AE35: =AD35/$AD$46*100% -> 0.0027057713 | AG35: =AI35-'Apr-26'!AI35 -> 0 | AH35: =AG35/$AG$46*100% -> 0 | AI35: =-SUMIF('05.conso TB'!A:A,'May-26'!B35,'05.conso TB'!Q:Q)/10^5 -> 0 | AJ35: =AI35/$AI$46*100% -> 0 | AL35: =AN35-'Apr-26'!AN35 -> 0 | AM35: =AL35/$AL$46*100% -> 0 | AN35: =-SUMIF('05.conso TB'!A:A,'May-26'!B35,'05.conso TB'!W:W)/10^5 -> 0 | AO35: =AN35/$AN$46*100% -> 0 | AQ35: =AS35-'Apr-26'!AS35 -> 0 | AR35: =AQ35/$AQ$46*100% -> 0 | AS35: =-SUMIF('05.conso TB'!A:A,'May-26'!B35,'05.conso TB'!M:M)/10^5 -> 0 | AT35: =AS35/$AS$46*100% -> 0 | AU35: =AW35-'Apr-26'!AW35 -> 0 | AV35: =AU35/$C$46*100% -> 0 | AW35: =-SUMIF('05.conso TB'!A:A,'May-26'!B35,'05.conso TB'!P:P)/10^5 -> 0 | AX35: =AW35/$AW$46*100% -> 0 | AZ35: =BB35-'Apr-26'!BB35 -> 0 | BA35: =AZ35/$AZ$46*100% -> 0 | BB35: =AS35+AW35 -> 0 | BC35: =BB35/$BB$46*100% -> 0 | BE35: =BG35-'Apr-26'!BG35 -> 0 | BF35: =BE35/$BE$46*100% -> 0 | BG35: =-SUMIF('05.conso TB'!A:A,'May-26'!B35,'05.conso TB'!H:H)/10^5 -> 0 | BH35: =BG35/$BG$46*100% -> 0 | BI35: =BK35-'Apr-26'!BK35 -> 0 | BJ35: =BI35/$BI$46*100% -> 0 | BK35: =-SUMIF('05.conso TB'!A:A,'May-26'!B35,'05.conso TB'!I:I)/10^5 -> 0 | BL35: =BK35/$BK$46*100% -> 0 | BM35: =BO35-'Apr-26'!BO35 -> 0 | BN35: =BM35/$C$46*100% -> 0 | BO35: =-SUMIF('05.conso TB'!A:A,'May-26'!B35,'05.conso TB'!J:J)/10^5 -> 0 | BP35: =BO35/$C$46*100% -> 0 | BR35: =BT35-'Apr-26'!BT35 -> 0 | BS35: =BR35/$BR$46*100% -> 0 | BT35: =BG35+BK35+BO35-BQ35 -> 0 | BU35: =BT35/$BT$46*100% -> 0 | BW35: =BY35-'Apr-26'!BY35 -> 0 | BX35: =BW35/$BW$46*100% -> 0 | BY35: =-SUMIF('05.conso TB'!A:A,'May-26'!B35,'05.conso TB'!L:L)/10^5 -> 0 | BZ35: =BY35/$BY$46*100% -> 0 | CB35: =CD35-'Apr-26'!CD35 -> 0 | CE35: =AB35+AG35+AL35+AZ35+BR35+BW35 -> 23.85489 | CF35: =CE35/$CE$46*100% -> 0.0014110836 | CG35: =AD35+AI35+AN35+BB35+BT35+BY35 -> 39.10641 | CH35: =CG35/$CG$46*100% -> 0.0031977105
B36: Interest income: | C36: =E36-'Apr-26'!E36 -> 0 | D36: =C36/$C$46*100% -> 0 | E36: =-SUMIF('05.conso TB'!A:A,'May-26'!B36,'05.conso TB'!R:R)/10^5 -> 0 | F36: =E36/$E$46*100% -> 0 | G36: =I36-'Apr-26'!I36 -> 0 | H36: =G36/$G$46*100% -> 0 | I36: =-SUMIF('05.conso TB'!A:A,'May-26'!B36,'05.conso TB'!S:S)/10^5 -> 0 | J36: =I36/$I$46*100% -> 0 | K36: =M36-'Apr-26'!M36 -> 0 | L36: =K36/$C$46*100% -> 0 | M36: =-SUMIF('05.conso TB'!A:A,'May-26'!B36,'05.conso TB'!T:T)/10^5 -> 0 | N36: =M36/$C$46*100% -> 0 | O36: =Q36-'Apr-26'!Q36 -> 0 | P36: =O36/$O$46*100% -> 0 | Q36: =-SUMIF('05.conso TB'!A:A,'May-26'!B36,'05.conso TB'!U:U)/10^5 -> 0 | R36: =Q36/$Q$46*100% -> 0 | S36: =U36-'Apr-26'!U36 -> 0 | T36: =S36/$S$46*100% -> 0 | U36: =-SUMIF('05.conso TB'!A:A,'May-26'!B36,'05.conso TB'!V:V)/10^5 -> 0 | V36: =U36/$U$46*100% -> 0 | W36: =Y36-'Apr-26'!Y36 -> 0 | X36: =W36/$W$46*100% -> 0 | Y36: =-SUMIF('05.conso TB'!A:A,'May-26'!B36,'05.conso TB'!G:G)/10^5 -> 0 | Z36: =Y36/$Y$46*100% -> 0 | AB36: =AD36-'Apr-26'!AD36 -> 0 | AC36: =AB36/$AB$46*100% -> 0 | AD36: =E36+I36+M36+Q36+U36+Y36 -> 0 | AE36: =AD36/$AD$46*100% -> 0 | AG36: =AI36-'Apr-26'!AI36 -> 0 | AH36: =AG36/$AG$46*100% -> 0 | AI36: =-SUMIF('05.conso TB'!A:A,'May-26'!B36,'05.conso TB'!Q:Q)/10^5 -> 0 | AJ36: =AI36/$AI$46*100% -> 0 | AL36: =AN36-'Apr-26'!AN36 -> 0 | AM36: =AL36/$AL$46*100% -> 0 | AN36: =-SUMIF('05.conso TB'!A:A,'May-26'!B36,'05.conso TB'!W:W)/10^5 -> 0 | AO36: =AN36/$AN$46*100% -> 0 | AQ36: =AS36-'Apr-26'!AS36 -> 0 | AR36: =AQ36/$AQ$46*100% -> 0 | AS36: =-SUMIF('05.conso TB'!A:A,'May-26'!B36,'05.conso TB'!M:M)/10^5 -> 0 | AT36: =AS36/$AS$46*100% -> 0 | AU36: =AW36-'Apr-26'!AW36 -> 0 | AV36: =AU36/$C$46*100% -> 0 | AW36: =-SUMIF('05.conso TB'!A:A,'May-26'!B36,'05.conso TB'!P:P)/10^5 -> 0 | AX36: =AW36/$AW$46*100% -> 0 | AZ36: =BB36-'Apr-26'!BB36 -> 0 | BA36: =AZ36/$AZ$46*100% -> 0 | BB36: =AS36+AW36 -> 0 | BC36: =BB36/$BB$46*100% -> 0 | BE36: =BG36-'Apr-26'!BG36 -> 0 | BF36: =BE36/$BE$46*100% -> 0 | BG36: =-SUMIF('05.conso TB'!A:A,'May-26'!B36,'05.conso TB'!H:H)/10^5 -> 0 | BH36: =BG36/$BG$46*100% -> 0 | BI36: =BK36-'Apr-26'!BK36 -> 0 | BJ36: =BI36/$BI$46*100% -> 0 | BK36: =-SUMIF('05.conso TB'!A:A,'May-26'!B36,'05.conso TB'!I:I)/10^5 -> 0 | BL36: =BK36/$BK$46*100% -> 0 | BM36: =BO36-'Apr-26'!BO36 -> 0 | BN36: =BM36/$C$46*100% -> 0 | BO36: =-SUMIF('05.conso TB'!A:A,'May-26'!B36,'05.conso TB'!J:J)/10^5 -> 0 | BP36: =BO36/$C$46*100% -> 0 | BR36: =BT36-'Apr-26'!BT36 -> 0 | BS36: =BR36/$BR$46*100% -> 0 | BT36: =BG36+BK36+BO36-BQ36 -> 0 | BU36: =BT36/$BT$46*100% -> 0 | BW36: =BY36-'Apr-26'!BY36 -> 0 | BX36: =BW36/$BW$46*100% -> 0 | BY36: =-SUMIF('05.conso TB'!A:A,'May-26'!B36,'05.conso TB'!L:L)/10^5 -> 0 | BZ36: =BY36/$BY$46*100% -> 0 | CB36: =CD36-'Apr-26'!CD36 -> 0 | CE36: =AB36+AG36+AL36+AZ36+BR36+BW36 -> 0 | CF36: =CE36/$CE$46*100% -> 0 | CG36: =AD36+AI36+AN36+BB36+BT36+BY36 -> 0 | CH36: =CG36/$CG$46*100% -> 0
B37: - on fixed deposits with Banks | C37: =E37-'Apr-26'!E37 -> 0.30794 | D37: =C37/$C$46*100% -> 9.8571153e-05 | E37: =-SUMIF('05.conso TB'!A:A,'May-26'!B37,'05.conso TB'!R:R)/10^5 -> 1.07873 | F37: =E37/$E$46*100% -> 0.00016695639 | G37: =I37-'Apr-26'!I37 -> 0 | H37: =G37/$G$46*100% -> 0 | I37: =-SUMIF('05.conso TB'!A:A,'May-26'!B37,'05.conso TB'!S:S)/10^5 -> 0 | J37: =I37/$I$46*100% -> 0 | K37: =M37-'Apr-26'!M37 -> 0 | L37: =K37/$C$46*100% -> 0 | M37: =-SUMIF('05.conso TB'!A:A,'May-26'!B37,'05.conso TB'!T:T)/10^5 -> 0 | N37: =M37/$C$46*100% -> 0 | O37: =Q37-'Apr-26'!Q37 -> 0 | P37: =O37/$O$46*100% -> 0 | Q37: =-SUMIF('05.conso TB'!A:A,'May-26'!B37,'05.conso TB'!U:U)/10^5 -> 0 | R37: =Q37/$Q$46*100% -> 0 | S37: =U37-'Apr-26'!U37 -> 0 | T37: =S37/$S$46*100% -> 0 | U37: =-SUMIF('05.conso TB'!A:A,'May-26'!B37,'05.conso TB'!V:V)/10^5 -> 0 | V37: =U37/$U$46*100% -> 0 | W37: =Y37-'Apr-26'!Y37 -> 0 | X37: =W37/$W$46*100% -> 0 | Y37: =-SUMIF('05.conso TB'!A:A,'May-26'!B37,'05.conso TB'!G:G)/10^5 -> 0 | Z37: =Y37/$Y$46*100% -> 0 | AB37: =AD37-'Apr-26'!AD37 -> 0.30794 | AC37: =AB37/$AB$46*100% -> 3.3394085e-05 | AD37: =E37+I37+M37+Q37+U37+Y37 -> 1.07873 | AE37: =AD37/$AD$46*100% -> 7.4637295e-05 | AG37: =AI37-'Apr-26'!AI37 -> 0 | AH37: =AG37/$AG$46*100% -> 0 | AI37: =-SUMIF('05.conso TB'!A:A,'May-26'!B37,'05.conso TB'!Q:Q)/10^5 -> 0 | AJ37: =AI37/$AI$46*100% -> 0 | AL37: =AN37-'Apr-26'!AN37 -> 6.1641 | AM37: =AL37/$AL$46*100% -> 0.0052051197 | AN37: =-SUMIF('05.conso TB'!A:A,'May-26'!B37,'05.conso TB'!W:W)/10^5 -> 7.33435 | AO37: =AN37/$AN$46*100% -> 0.0031581614 | AQ37: =AS37-'Apr-26'!AS37 -> 0 | AR37: =AQ37/$AQ$46*100% -> 0 | AS37: =-SUMIF('05.conso TB'!A:A,'May-26'!B37,'05.conso TB'!M:M)/10^5 -> 0 | AT37: =AS37/$AS$46*100% -> 0 | AU37: =AW37-'Apr-26'!AW37 -> 0 | AV37: =AU37/$C$46*100% -> 0 | AW37: =-SUMIF('05.conso TB'!A:A,'May-26'!B37,'05.conso TB'!P:P)/10^5 -> 0 | AX37: =AW37/$AW$46*100% -> 0 | AZ37: =BB37-'Apr-26'!BB37 -> 0 | BA37: =AZ37/$AZ$46*100% -> 0 | BB37: =AS37+AW37 -> 0 | BC37: =BB37/$BB$46*100% -> 0 | BE37: =BG37-'Apr-26'!BG37 -> 0 | BF37: =BE37/$BE$46*100% -> 0 | BG37: =-SUMIF('05.conso TB'!A:A,'May-26'!B37,'05.conso TB'!H:H)/10^5 -> 0 | BH37: =BG37/$BG$46*100% -> 0 | BI37: =BK37-'Apr-26'!BK37 -> 0 | BJ37: =BI37/$BI$46*100% -> 0 | BK37: =-SUMIF('05.conso TB'!A:A,'May-26'!B37,'05.conso TB'!I:I)/10^5 -> 0 | BL37: =BK37/$BK$46*100% -> 0 | BM37: =BO37-'Apr-26'!BO37 -> 0 | BN37: =BM37/$C$46*100% -> 0 | BO37: =-SUMIF('05.conso TB'!A:A,'May-26'!B37,'05.conso TB'!J:J)/10^5 -> 0 | BP37: =BO37/$C$46*100% -> 0 | BR37: =BT37-'Apr-26'!BT37 -> 0 | BS37: =BR37/$BR$46*100% -> 0 | BT37: =BG37+BK37+BO37-BQ37 -> 0 | BU37: =BT37/$BT$46*100% -> 0 | BW37: =BY37-'Apr-26'!BY37 -> 0 | BX37: =BW37/$BW$46*100% -> 0 | BY37: =-SUMIF('05.conso TB'!A:A,'May-26'!B37,'05.conso TB'!L:L)/10^5 -> 0 | BZ37: =BY37/$BY$46*100% -> 0 | CB37: =CD37-'Apr-26'!CD37 -> 0 | CE37: =AB37+AG37+AL37+AZ37+BR37+BW37 -> 6.47204 | CF37: =CE37/$CE$46*100% -> 0.00038283929 | CG37: =AD37+AI37+AN37+BB37+BT37+BY37 -> 8.41308 | CH37: =CG37/$CG$46*100% -> 0.00068793311
B38: - from others | C38: =E38-'Apr-26'!E38 -> 0 | D38: =C38/$C$46*100% -> 0 | E38: =-SUMIF('05.conso TB'!A:A,'May-26'!B38,'05.conso TB'!R:R)/10^5 -> 0 | F38: =E38/$E$46*100% -> 0 | G38: =I38-'Apr-26'!I38 -> 0 | H38: =G38/$G$46*100% -> 0 | I38: =-SUMIF('05.conso TB'!A:A,'May-26'!B38,'05.conso TB'!S:S)/10^5 -> 0 | J38: =I38/$I$46*100% -> 0 | K38: =M38-'Apr-26'!M38 -> 0 | L38: =K38/$C$46*100% -> 0 | M38: =-SUMIF('05.conso TB'!A:A,'May-26'!B38,'05.conso TB'!T:T)/10^5 -> 0 | N38: =M38/$C$46*100% -> 0 | O38: =Q38-'Apr-26'!Q38 -> 0 | P38: =O38/$O$46*100% -> 0 | Q38: =-SUMIF('05.conso TB'!A:A,'May-26'!B38,'05.conso TB'!U:U)/10^5 -> 0 | R38: =Q38/$Q$46*100% -> 0 | S38: =U38-'Apr-26'!U38 -> 0 | T38: =S38/$S$46*100% -> 0 | U38: =-SUMIF('05.conso TB'!A:A,'May-26'!B38,'05.conso TB'!V:V)/10^5 -> 0 | V38: =U38/$U$46*100% -> 0 | W38: =Y38-'Apr-26'!Y38 -> 0 | X38: =W38/$W$46*100% -> 0 | Y38: =-SUMIF('05.conso TB'!A:A,'May-26'!B38,'05.conso TB'!G:G)/10^5 -> 0 | Z38: =Y38/$Y$46*100% -> 0 | AB38: =AD38-'Apr-26'!AD38 -> 0 | AC38: =AB38/$AB$46*100% -> 0 | AD38: =E38+I38+M38+Q38+U38+Y38 -> 0 | AE38: =AD38/$AD$46*100% -> 0 | AG38: =AI38-'Apr-26'!AI38 -> 0 | AH38: =AG38/$AG$46*100% -> 0 | AI38: =-SUMIF('05.conso TB'!A:A,'May-26'!B38,'05.conso TB'!Q:Q)/10^5 -> 0 | AJ38: =AI38/$AI$46*100% -> 0 | AL38: =AN38-'Apr-26'!AN38 -> 0 | AM38: =AL38/$AL$46*100% -> 0 | AN38: =-SUMIF('05.conso TB'!A:A,'May-26'!B38,'05.conso TB'!W:W)/10^5 -> 0 | AO38: =AN38/$AN$46*100% -> 0 | AQ38: =AS38-'Apr-26'!AS38 -> 0 | AR38: =AQ38/$AQ$46*100% -> 0 | AS38: =-SUMIF('05.conso TB'!A:A,'May-26'!B38,'05.conso TB'!M:M)/10^5 -> 0 | AT38: =AS38/$AS$46*100% -> 0 | AU38: =AW38-'Apr-26'!AW38 -> 0 | AV38: =AU38/$C$46*100% -> 0 | AW38: =-SUMIF('05.conso TB'!A:A,'May-26'!B38,'05.conso TB'!P:P)/10^5 -> 0 | AX38: =AW38/$AW$46*100% -> 0 | AZ38: =BB38-'Apr-26'!BB38 -> 0 | BA38: =AZ38/$AZ$46*100% -> 0 | BB38: =AS38+AW38 -> 0 | BC38: =BB38/$BB$46*100% -> 0 | BE38: =BG38-'Apr-26'!BG38 -> 0 | BF38: =BE38/$BE$46*100% -> 0 | BG38: =-SUMIF('05.conso TB'!A:A,'May-26'!B38,'05.conso TB'!H:H)/10^5 -> 0 | BH38: =BG38/$BG$46*100% -> 0 | BI38: =BK38-'Apr-26'!BK38 -> 0 | BJ38: =BI38/$BI$46*100% -> 0 | BK38: =-SUMIF('05.conso TB'!A:A,'May-26'!B38,'05.conso TB'!I:I)/10^5 -> 0 | BL38: =BK38/$BK$46*100% -> 0 | BM38: =BO38-'Apr-26'!BO38 -> 0 | BN38: =BM38/$C$46*100% -> 0 | BO38: =-SUMIF('05.conso TB'!A:A,'May-26'!B38,'05.conso TB'!J:J)/10^5 -> 0 | BP38: =BO38/$C$46*100% -> 0 | BR38: =BT38-'Apr-26'!BT38 -> 0 | BS38: =BR38/$BR$46*100% -> 0 | BT38: =BG38+BK38+BO38-BQ38 -> 0 | BU38: =BT38/$BT$46*100% -> 0 | BW38: =BY38-'Apr-26'!BY38 -> 0 | BX38: =BW38/$BW$46*100% -> 0 | BY38: =-SUMIF('05.conso TB'!A:A,'May-26'!B38,'05.conso TB'!L:L)/10^5 -> 0 | BZ38: =BY38/$BY$46*100% -> 0 | CB38: =CD38-'Apr-26'!CD38 -> 0 | CE38: =AB38+AG38+AL38+AZ38+BR38+BW38 -> 0 | CF38: =CE38/$CE$46*100% -> 0 | CG38: =AD38+AI38+AN38+BB38+BT38+BY38 -> 0 | CH38: =CG38/$CG$46*100% -> 0
B39: Rent Income | C39: =E39-'Apr-26'!E39 -> 2.34013 | D39: =C39/$C$46*100% -> 0.00074907226 | E39: =-SUMIF('05.conso TB'!A:A,'May-26'!B39,'05.conso TB'!R:R)/10^5 -> 4.68026 | F39: =E39/$E$46*100% -> 0.00072436971 | G39: =I39-'Apr-26'!I39 -> 0 | H39: =G39/$G$46*100% -> 0 | I39: =-SUMIF('05.conso TB'!A:A,'May-26'!B39,'05.conso TB'!S:S)/10^5 -> 0 | J39: =I39/$I$46*100% -> 0 | K39: =M39-'Apr-26'!M39 -> 0 | L39: =K39/$C$46*100% -> 0 | M39: =-SUMIF('05.conso TB'!A:A,'May-26'!B39,'05.conso TB'!T:T)/10^5 -> 0 | N39: =M39/$C$46*100% -> 0 | O39: =Q39-'Apr-26'!Q39 -> 0 | P39: =O39/$O$46*100% -> 0 | Q39: =-SUMIF('05.conso TB'!A:A,'May-26'!B39,'05.conso TB'!U:U)/10^5 -> 0 | R39: =Q39/$Q$46*100% -> 0 | S39: =U39-'Apr-26'!U39 -> 0 | T39: =S39/$S$46*100% -> 0 | U39: =-SUMIF('05.conso TB'!A:A,'May-26'!B39,'05.conso TB'!V:V)/10^5 -> 0 | V39: =U39/$U$46*100% -> 0 | W39: =Y39-'Apr-26'!Y39 -> 0.45 | X39: =W39/$W$46*100% -> 0.00012099544 | Y39: =-SUMIF('05.conso TB'!A:A,'May-26'!B39,'05.conso TB'!G:G)/10^5 -> 0.9 | Z39: =Y39/$Y$46*100% -> 0.00023724077 | AB39: =AD39-'Apr-26'!AD39 -> 2.79013 | AC39: =AB39/$AB$46*100% -> 0.0003025714 | AD39: =E39+I39+M39+Q39+U39+Y39 -> 5.58026 | AE39: =AD39/$AD$46*100% -> 0.00038609801 | AG39: =AI39-'Apr-26'!AI39 -> 0 | AH39: =AG39/$AG$46*100% -> 0 | AI39: =-SUMIF('05.conso TB'!A:A,'May-26'!B39,'05.conso TB'!Q:Q)/10^5 -> 0 | AJ39: =AI39/$AI$46*100% -> 0 | AL39: =AN39-'Apr-26'!AN39 -> 0 | AM39: =AL39/$AL$46*100% -> 0 | AN39: =-SUMIF('05.conso TB'!A:A,'May-26'!B39,'05.conso TB'!W:W)/10^5 -> 0 | AO39: =AN39/$AN$46*100% -> 0 | AQ39: =AS39-'Apr-26'!AS39 -> -2 | AR39: =AQ39/$AQ$46*100% -> -0.00098095623 | AS39: =-SUMIF('05.conso TB'!A:A,'May-26'!B39,'05.conso TB'!M:M)/10^5 -> -2 | AT39: =AS39/$AS$46*100% -> -0.00051672383 | AU39: =AW39-'Apr-26'!AW39 -> 0 | AV39: =AU39/$C$46*100% -> 0 | AW39: =-SUMIF('05.conso TB'!A:A,'May-26'!B39,'05.conso TB'!P:P)/10^5 -> 0 | AX39: =AW39/$AW$46*100% -> 0 | AZ39: =BB39-'Apr-26'!BB39 -> -2 | BA39: =AZ39/$AZ$46*100% -> -0.00065893395 | BB39: =AS39+AW39 -> -2 | BC39: =BB39/$BB$46*100% -> -0.00034978658 | BE39: =BG39-'Apr-26'!BG39 -> 0.24 | BF39: =BE39/$BE$46*100% -> 8.5869993e-05 | BG39: =-SUMIF('05.conso TB'!A:A,'May-26'!B39,'05.conso TB'!H:H)/10^5 -> 0.48 | BH39: =BG39/$BG$46*100% -> 0.00010214637 | BI39: =BK39-'Apr-26'!BK39 -> 0 | BJ39: =BI39/$BI$46*100% -> 0 | BK39: =-SUMIF('05.conso TB'!A:A,'May-26'!B39,'05.conso TB'!I:I)/10^5 -> 0 | BL39: =BK39/$BK$46*100% -> 0 | BM39: =BO39-'Apr-26'!BO39 -> 0 | BN39: =BM39/$C$46*100% -> 0 | BO39: =-SUMIF('05.conso TB'!A:A,'May-26'!B39,'05.conso TB'!J:J)/10^5 -> 0 | BP39: =BO39/$C$46*100% -> 0 | BR39: =BT39-'Apr-26'!BT39 -> 0.24 | BS39: =BR39/$BR$46*100% -> 9.0754515e-05 | BT39: =BG39+BK39+BO39-BQ39 -> 0.48 | BU39: =BT39/$BT$46*100% -> 0.0001069579 | BW39: =BY39-'Apr-26'!BY39 -> 0 | BX39: =BW39/$BW$46*100% -> 0 | BY39: =-SUMIF('05.conso TB'!A:A,'May-26'!B39,'05.conso TB'!L:L)/10^5 -> 0 | BZ39: =BY39/$BY$46*100% -> 0 | CB39: =CC39-'Apr-26'!CC39 -> 4.69 | CC39: 7.38 | CE39: =AB39+AG39+AL39+AZ39+BR39+BW39 -> 1.03013 | CF39: =CE39/$CE$46*100% -> 6.0935075e-05 | CG39: =AD39+AI39+AN39+BB39+BT39+BY39 -> 4.06026 | CH39: =CG39/$CG$46*100% -> 0.00033200532
B40: Interest Received From Customers | C40: =E40-'Apr-26'!E40 -> 0 | D40: =C40/$C$46*100% -> 0 | E40: =-SUMIF('05.conso TB'!A:A,'May-26'!B40,'05.conso TB'!R:R)/10^5 -> 0 | F40: =E40/$E$46*100% -> 0 | G40: =I40-'Apr-26'!I40 -> 0 | H40: =G40/$G$46*100% -> 0 | I40: =-SUMIF('05.conso TB'!A:A,'May-26'!B40,'05.conso TB'!S:S)/10^5 -> 0 | J40: =I40/$I$46*100% -> 0 | K40: =M40-'Apr-26'!M40 -> 15.94895 | L40: =K40/$C$46*100% -> 0.0051052361 | M40: =-SUMIF('05.conso TB'!A:A,'May-26'!B40,'05.conso TB'!T:T)/10^5 -> 38.22116 | N40: =M40/$C$46*100% -> 0.012234539 | O40: =Q40-'Apr-26'!Q40 -> 0 | P40: =O40/$O$46*100% -> 0 | Q40: =-SUMIF('05.conso TB'!A:A,'May-26'!B40,'05.conso TB'!U:U)/10^5 -> 0 | R40: =Q40/$Q$46*100% -> 0 | S40: =U40-'Apr-26'!U40 -> 0 | T40: =S40/$S$46*100% -> 0 | U40: =-SUMIF('05.conso TB'!A:A,'May-26'!B40,'05.conso TB'!V:V)/10^5 -> 0 | V40: =U40/$U$46*100% -> 0 | W40: =Y40-'Apr-26'!Y40 -> 0 | X40: =W40/$W$46*100% -> 0 | Y40: =-SUMIF('05.conso TB'!A:A,'May-26'!B40,'05.conso TB'!G:G)/10^5 -> 0 | Z40: =Y40/$Y$46*100% -> 0 | AB40: =AD40-'Apr-26'!AD40 -> 15.94895 | AC40: =AB40/$AB$46*100% -> 0.0017295596 | AD40: =E40+I40+M40+Q40+U40+Y40 -> 38.22116 | AE40: =AD40/$AD$46*100% -> 0.0026445209 | AG40: =AI40-'Apr-26'!AI40 -> 0 | AH40: =AG40/$AG$46*100% -> 0 | AI40: =-SUMIF('05.conso TB'!A:A,'May-26'!B40,'05.conso TB'!Q:Q)/10^5 -> 0 | AJ40: =AI40/$AI$46*100% -> 0 | AL40: =AN40-'Apr-26'!AN40 -> 0 | AM40: =AL40/$AL$46*100% -> 0 | AN40: =-SUMIF('05.conso TB'!A:A,'May-26'!B40,'05.conso TB'!W:W)/10^5 -> 0 | AO40: =AN40/$AN$46*100% -> 0 | AQ40: =AS40-'Apr-26'!AS40 -> 0 | AR40: =AQ40/$AQ$46*100% -> 0 | AS40: =-SUMIF('05.conso TB'!A:A,'May-26'!B40,'05.conso TB'!M:M)/10^5 -> 0 | AT40: =AS40/$AS$46*100% -> 0 | AU40: =AW40-'Apr-26'!AW40 -> 0 | AV40: =AU40/$C$46*100% -> 0 | AW40: =-SUMIF('05.conso TB'!A:A,'May-26'!B40,'05.conso TB'!P:P)/10^5 -> 0 | AX40: =AW40/$AW$46*100% -> 0 | AZ40: =BB40-'Apr-26'!BB40 -> 0 | BA40: =AZ40/$AZ$46*100% -> 0 | BB40: =AS40+AW40 -> 0 | BC40: =BB40/$BB$46*100% -> 0 | BE40: =BG40-'Apr-26'!BG40 -> 0 | BF40: =BE40/$BE$46*100% -> 0 | BG40: =-SUMIF('05.conso TB'!A:A,'May-26'!B40,'05.conso TB'!H:H)/10^5 -> 0 | BH40: =BG40/$BG$46*100% -> 0 | BI40: =BK40-'Apr-26'!BK40 -> 0 | BJ40: =BI40/$BI$46*100% -> 0 | BK40: =-SUMIF('05.conso TB'!A:A,'May-26'!B40,'05.conso TB'!I:I)/10^5 -> 0 | BL40: =BK40/$BK$46*100% -> 0 | BM40: =BO40-'Apr-26'!BO40 -> 0 | BN40: =BM40/$C$46*100% -> 0 | BO40: =-SUMIF('05.conso TB'!A:A,'May-26'!B40,'05.conso TB'!J:J)/10^5 -> 0 | BP40: =BO40/$C$46*100% -> 0 | BR40: =BT40-'Apr-26'!BT40 -> 0 | BS40: =BR40/$BR$46*100% -> 0 | BT40: =BG40+BK40+BO40-BQ40 -> 0 | BU40: =BT40/$BT$46*100% -> 0 | BW40: =BY40-'Apr-26'!BY40 -> 7.59931 | BX40: =BW40/$BW$46*100% -> 0.01679303 | BY40: =-SUMIF('05.conso TB'!A:A,'May-26'!B40,'05.conso TB'!L:L)/10^5 -> 9.50958 | BZ40: =BY40/$BY$46*100% -> 0.0044007829 | CB40: =CD40-'Apr-26'!CD40 -> 0 | CE40: =AB40+AG40+AL40+AZ40+BR40+BW40 -> 23.54826 | CF40: =CE40/$CE$46*100% -> 0.0013929455 | CG40: =AD40+AI40+AN40+BB40+BT40+BY40 -> 47.73074 | CH40: =CG40/$CG$46*100% -> 0.0039029174
B41: Profit on sale of fixed assets | C41: =E41-'Apr-26'!E41 -> 0 | D41: =C41/$C$46*100% -> 0 | E41: =-SUMIF('05.conso TB'!A:A,'May-26'!B41,'05.conso TB'!R:R)/10^5 -> 0 | F41: =E41/$E$46*100% -> 0 | G41: =I41-'Apr-26'!I41 -> 0 | H41: =G41/$G$46*100% -> 0 | I41: =-SUMIF('05.conso TB'!A:A,'May-26'!B41,'05.conso TB'!S:S)/10^5 -> 0 | J41: =I41/$I$46*100% -> 0 | K41: =M41-'Apr-26'!M41 -> 0 | L41: =K41/$C$46*100% -> 0 | M41: =-SUMIF('05.conso TB'!A:A,'May-26'!B41,'05.conso TB'!T:T)/10^5 -> 0 | N41: =M41/$C$46*100% -> 0 | O41: =Q41-'Apr-26'!Q41 -> 0 | P41: =O41/$O$46*100% -> 0 | Q41: =-SUMIF('05.conso TB'!A:A,'May-26'!B41,'05.conso TB'!U:U)/10^5 -> 0 | R41: =Q41/$Q$46*100% -> 0 | S41: =U41-'Apr-26'!U41 -> 0 | T41: =S41/$S$46*100% -> 0 | U41: =-SUMIF('05.conso TB'!A:A,'May-26'!B41,'05.conso TB'!V:V)/10^5 -> 0 | V41: =U41/$U$46*100% -> 0 | W41: =Y41-'Apr-26'!Y41 -> 0 | X41: =W41/$W$46*100% -> 0 | Y41: =-SUMIF('05.conso TB'!A:A,'May-26'!B41,'05.conso TB'!G:G)/10^5 -> 0 | Z41: =Y41/$Y$46*100% -> 0 | AB41: =AD41-'Apr-26'!AD41 -> 0 | AC41: =AB41/$AB$46*100% -> 0 | AD41: =E41+I41+M41+Q41+U41+Y41 -> 0 | AE41: =AD41/$AD$46*100% -> 0 | AG41: =AI41-'Apr-26'!AI41 -> 0 | AH41: =AG41/$AG$46*100% -> 0 | AI41: =-SUMIF('05.conso TB'!A:A,'May-26'!B41,'05.conso TB'!Q:Q)/10^5 -> 0 | AJ41: =AI41/$AI$46*100% -> 0 | AL41: =AN41-'Apr-26'!AN41 -> 0 | AM41: =AL41/$AL$46*100% -> 0 | AN41: =-SUMIF('05.conso TB'!A:A,'May-26'!B41,'05.conso TB'!W:W)/10^5 -> 0 | AO41: =AN41/$AN$46*100% -> 0 | AQ41: =AS41-'Apr-26'!AS41 -> 0 | AR41: =AQ41/$AQ$46*100% -> 0 | AS41: =-SUMIF('05.conso TB'!A:A,'May-26'!B41,'05.conso TB'!M:M)/10^5 -> 0 | AT41: =AS41/$AS$46*100% -> 0 | AU41: =AW41-'Apr-26'!AW41 -> 0 | AV41: =AU41/$C$46*100% -> 0 | AW41: =-SUMIF('05.conso TB'!A:A,'May-26'!B41,'05.conso TB'!P:P)/10^5 -> 0 | AX41: =AW41/$AW$46*100% -> 0 | AZ41: =BB41-'Apr-26'!BB41 -> 0 | BA41: =AZ41/$AZ$46*100% -> 0 | BB41: =AS41+AW41 -> 0 | BC41: =BB41/$BB$46*100% -> 0 | BE41: =BG41-'Apr-26'!BG41 -> 0 | BF41: =BE41/$BE$46*100% -> 0 | BG41: =-SUMIF('05.conso TB'!A:A,'May-26'!B41,'05.conso TB'!H:H)/10^5 -> 0 | BH41: =BG41/$BG$46*100% -> 0 | BI41: =BK41-'Apr-26'!BK41 -> 0 | BJ41: =BI41/$BI$46*100% -> 0 | BK41: =-SUMIF('05.conso TB'!A:A,'May-26'!B41,'05.conso TB'!I:I)/10^5 -> 0 | BL41: =BK41/$BK$46*100% -> 0 | BM41: =BO41-'Apr-26'!BO41 -> 0 | BN41: =BM41/$C$46*100% -> 0 | BO41: =-SUMIF('05.conso TB'!A:A,'May-26'!B41,'05.conso TB'!J:J)/10^5 -> 0 | BP41: =BO41/$C$46*100% -> 0 | BR41: =BT41-'Apr-26'!BT41 -> 0 | BS41: =BR41/$BR$46*100% -> 0 | BT41: =BG41+BK41+BO41-BQ41 -> 0 | BU41: =BT41/$BT$46*100% -> 0 | BW41: =BY41-'Apr-26'!BY41 -> 0 | BX41: =BW41/$BW$46*100% -> 0 | BY41: =-SUMIF('05.conso TB'!A:A,'May-26'!B41,'05.conso TB'!L:L)/10^5 -> 0 | BZ41: =BY41/$BY$46*100% -> 0 | CB41: =CD41-'Apr-26'!CD41 -> 0 | CE41: =AB41+AG41+AL41+AZ41+BR41+BW41 -> 0 | CF41: =CE41/$CE$46*100% -> 0 | CG41: =AD41+AI41+AN41+BB41+BT41+BY41 -> 0 | CH41: =CG41/$CG$46*100% -> 0
B42: Profit on sale of investments | C42: =E42-'Apr-26'!E42 -> 0 | D42: =C42/$C$46*100% -> 0 | E42: =-SUMIF('05.conso TB'!A:A,'May-26'!B42,'05.conso TB'!R:R)/10^5 -> 0 | F42: =E42/$E$46*100% -> 0 | G42: =I42-'Apr-26'!I42 -> 0 | H42: =G42/$G$46*100% -> 0 | I42: =-SUMIF('05.conso TB'!A:A,'May-26'!B42,'05.conso TB'!S:S)/10^5 -> 0 | J42: =I42/$I$46*100% -> 0 | K42: =M42-'Apr-26'!M42 -> 0 | L42: =K42/$C$46*100% -> 0 | M42: =-SUMIF('05.conso TB'!A:A,'May-26'!B42,'05.conso TB'!T:T)/10^5 -> 0 | N42: =M42/$C$46*100% -> 0 | O42: =Q42-'Apr-26'!Q42 -> 0 | P42: =O42/$O$46*100% -> 0 | Q42: =-SUMIF('05.conso TB'!A:A,'May-26'!B42,'05.conso TB'!U:U)/10^5 -> 0 | R42: =Q42/$Q$46*100% -> 0 | S42: =U42-'Apr-26'!U42 -> 0 | T42: =S42/$S$46*100% -> 0 | U42: =-SUMIF('05.conso TB'!A:A,'May-26'!B42,'05.conso TB'!V:V)/10^5 -> 0 | V42: =U42/$U$46*100% -> 0 | W42: =Y42-'Apr-26'!Y42 -> 0 | X42: =W42/$W$46*100% -> 0 | Y42: =-SUMIF('05.conso TB'!A:A,'May-26'!B42,'05.conso TB'!G:G)/10^5 -> 0 | Z42: =Y42/$Y$46*100% -> 0 | AB42: =AD42-'Apr-26'!AD42 -> 0 | AC42: =AB42/$AB$46*100% -> 0 | AD42: =E42+I42+M42+Q42+U42+Y42 -> 0 | AE42: =AD42/$AD$46*100% -> 0 | AG42: =AI42-'Apr-26'!AI42 -> 0 | AH42: =AG42/$AG$46*100% -> 0 | AI42: =-SUMIF('05.conso TB'!A:A,'May-26'!B42,'05.conso TB'!Q:Q)/10^5 -> 0 | AJ42: =AI42/$AI$46*100% -> 0 | AL42: =AN42-'Apr-26'!AN42 -> 0 | AM42: =AL42/$AL$46*100% -> 0 | AN42: =-SUMIF('05.conso TB'!A:A,'May-26'!B42,'05.conso TB'!W:W)/10^5 -> 0 | AO42: =AN42/$AN$46*100% -> 0 | AQ42: =AS42-'Apr-26'!AS42 -> 0 | AR42: =AQ42/$AQ$46*100% -> 0 | AS42: =-SUMIF('05.conso TB'!A:A,'May-26'!B42,'05.conso TB'!M:M)/10^5 -> 0 | AT42: =AS42/$AS$46*100% -> 0 | AU42: =AW42-'Apr-26'!AW42 -> 0 | AV42: =AU42/$C$46*100% -> 0 | AW42: =-SUMIF('05.conso TB'!A:A,'May-26'!B42,'05.conso TB'!P:P)/10^5 -> 0 | AX42: =AW42/$AW$46*100% -> 0 | AZ42: =BB42-'Apr-26'!BB42 -> 0 | BA42: =AZ42/$AZ$46*100% -> 0 | BB42: =AS42+AW42 -> 0 | BC42: =BB42/$BB$46*100% -> 0 | BE42: =BG42-'Apr-26'!BG42 -> 0 | BF42: =BE42/$BE$46*100% -> 0 | BG42: =-SUMIF('05.conso TB'!A:A,'May-26'!B42,'05.conso TB'!H:H)/10^5 -> 0 | BH42: =BG42/$BG$46*100% -> 0 | BI42: =BK42-'Apr-26'!BK42 -> 0 | BJ42: =BI42/$BI$46*100% -> 0 | BK42: =-SUMIF('05.conso TB'!A:A,'May-26'!B42,'05.conso TB'!I:I)/10^5 -> 0 | BL42: =BK42/$BK$46*100% -> 0 | BM42: =BO42-'Apr-26'!BO42 -> 0 | BN42: =BM42/$C$46*100% -> 0 | BO42: =-SUMIF('05.conso TB'!A:A,'May-26'!B42,'05.conso TB'!J:J)/10^5 -> 0 | BP42: =BO42/$C$46*100% -> 0 | BR42: =BT42-'Apr-26'!BT42 -> 0 | BS42: =BR42/$BR$46*100% -> 0 | BT42: =BG42+BK42+BO42-BQ42 -> 0 | BU42: =BT42/$BT$46*100% -> 0 | BW42: =BY42-'Apr-26'!BY42 -> 0 | BX42: =BW42/$BW$46*100% -> 0 | BY42: =-SUMIF('05.conso TB'!A:A,'May-26'!B42,'05.conso TB'!L:L)/10^5 -> 0 | BZ42: =BY42/$BY$46*100% -> 0 | CB42: =CD42-'Apr-26'!CD42 -> 0 | CE42: =AB42+AG42+AL42+AZ42+BR42+BW42 -> 0 | CF42: =CE42/$CE$46*100% -> 0 | CG42: =AD42+AI42+AN42+BB42+BT42+BY42 -> 0 | CH42: =CG42/$CG$46*100% -> 0
B43: Sundry balance written off | C43: =E43-'Apr-26'!E43 -> 0.0583621 | D43: =C43/$C$46*100% -> 1.8681625e-05 | E43: =-SUMIF('05.conso TB'!A:A,'May-26'!B43,'05.conso TB'!R:R)/10^5 -> 0.0529441 | F43: =E43/$E$46*100% -> 8.1942247e-06 | G43: =I43-'Apr-26'!I43 -> 3.15368 | H43: =G43/$G$46*100% -> 0.0023743887 | I43: =-SUMIF('05.conso TB'!A:A,'May-26'!B43,'05.conso TB'!S:S)/10^5 -> 3.15368 | J43: =I43/$I$46*100% -> 0.0012566693 | K43: =M43-'Apr-26'!M43 -> 0 | L43: =K43/$C$46*100% -> 0 | M43: =-SUMIF('05.conso TB'!A:A,'May-26'!B43,'05.conso TB'!T:T)/10^5 -> 0 | N43: =M43/$C$46*100% -> 0 | O43: =Q43-'Apr-26'!Q43 -> 0 | P43: =O43/$O$46*100% -> 0 | Q43: =-SUMIF('05.conso TB'!A:A,'May-26'!B43,'05.conso TB'!U:U)/10^5 -> 0 | R43: =Q43/$Q$46*100% -> 0 | S43: =U43-'Apr-26'!U43 -> -0.02043 | T43: =S43/$S$46*100% -> 0.86999847 | U43: =-SUMIF('05.conso TB'!A:A,'May-26'!B43,'05.conso TB'!V:V)/10^5 -> -0.02043 | V43: =U43/$U$46*100% -> -0.00041914084 | W43: =Y43-'Apr-26'!Y43 -> -45.00124 | X43: =W43/$W$46*100% -> -0.012099878 | Y43: =-SUMIF('05.conso TB'!A:A,'May-26'!B43,'05.conso TB'!G:G)/10^5 -> -45.00124 | Z43: =Y43/$Y$46*100% -> -0.011862365 | AB43: =AD43-'Apr-26'!AD43 -> -41.809628 | AC43: =AB43/$AB$46*100% -> -0.0045339815 | AD43: =E43+I43+M43+Q43+U43+Y43 -> -41.815046 | AE43: =AD43/$AD$46*100% -> -0.0028931817 | AG43: =AI43-'Apr-26'!AI43 -> 0 | AH43: =AG43/$AG$46*100% -> 0 | AI43: =-SUMIF('05.conso TB'!A:A,'May-26'!B43,'05.conso TB'!Q:Q)/10^5 -> 0 | AJ43: =AI43/$AI$46*100% -> 0 | AL43: =AN43-'Apr-26'!AN43 -> 0 | AM43: =AL43/$AL$46*100% -> 0 | AN43: =-SUMIF('05.conso TB'!A:A,'May-26'!B43,'05.conso TB'!W:W)/10^5 -> 0 | AO43: =AN43/$AN$46*100% -> 0 | AQ43: =AS43-'Apr-26'!AS43 -> 0 | AR43: =AQ43/$AQ$46*100% -> 0 | AS43: =-SUMIF('05.conso TB'!A:A,'May-26'!B43,'05.conso TB'!M:M)/10^5 -> 0 | AT43: =AS43/$AS$46*100% -> 0 | AU43: =AW43-'Apr-26'!AW43 -> 0 | AV43: =AU43/$C$46*100% -> 0 | AW43: =-SUMIF('05.conso TB'!A:A,'May-26'!B43,'05.conso TB'!P:P)/10^5 -> 0 | AX43: =AW43/$AW$46*100% -> 0 | AZ43: =BB43-'Apr-26'!BB43 -> 0 | BA43: =AZ43/$AZ$46*100% -> 0 | BB43: =AS43+AW43 -> 0 | BC43: =BB43/$BB$46*100% -> 0 | BE43: =BG43-'Apr-26'!BG43 -> 0.005633 | BF43: =BE43/$BE$46*100% -> 2.0154403e-06 | BG43: =-SUMIF('05.conso TB'!A:A,'May-26'!B43,'05.conso TB'!H:H)/10^5 -> 0.005633 | BH43: =BG43/$BG$46*100% -> 1.1987302e-06 | BI43: =BK43-'Apr-26'!BK43 -> 0 | BJ43: =BI43/$BI$46*100% -> 0 | BK43: =-SUMIF('05.conso TB'!A:A,'May-26'!B43,'05.conso TB'!I:I)/10^5 -> 0 | BL43: =BK43/$BK$46*100% -> 0 | BM43: =BO43-'Apr-26'!BO43 -> 0 | BN43: =BM43/$C$46*100% -> 0 | BO43: =-SUMIF('05.conso TB'!A:A,'May-26'!B43,'05.conso TB'!J:J)/10^5 -> 0.07617 | BP43: =BO43/$C$46*100% -> 2.4381908e-05 | BR43: =BT43-'Apr-26'!BT43 -> 0.005633 | BS43: =BR43/$BR$46*100% -> 2.1300841e-06 | BT43: =BG43+BK43+BO43-BQ43 -> 0.081803 | BU43: =BT43/$BT$46*100% -> 1.8228078e-05 | BW43: =BY43-'Apr-26'!BY43 -> 0 | BX43: =BW43/$BW$46*100% -> 0 | BY43: =-SUMIF('05.conso TB'!A:A,'May-26'!B43,'05.conso TB'!L:L)/10^5 -> 0 | BZ43: =BY43/$BY$46*100% -> 0 | CB43: =CD43-'Apr-26'!CD43 -> 0 | CE43: =AB43+AG43+AL43+AZ43+BR43+BW43 -> -41.803995 | CF43: =CE43/$CE$46*100% -> -0.0024728234 | CG43: =AD43+AI43+AN43+BB43+BT43+BY43 -> -41.733243 | CH43: =CG43/$CG$46*100% -> -0.0034125052
B44: Miscellaneous income | C44: =E44-'Apr-26'!E44 -> 0.5948953 | D44: =C44/$C$46*100% -> 0.00019042513 | E44: =-SUMIF('05.conso TB'!A:A,'May-26'!B44,'05.conso TB'!R:R)/10^5 -> 0.5948443 | F44: =E44/$E$46*100% -> 9.2064798e-05 | G44: =I44-'Apr-26'!I44 -> -5.89e-05 | H44: =G44/$G$46*100% -> -4.4345493e-08 | I44: =-SUMIF('05.conso TB'!A:A,'May-26'!B44,'05.conso TB'!S:S)/10^5 -> -4.63e-05 | J44: =I44/$I$46*100% -> -1.844949e-08 | K44: =M44-'Apr-26'!M44 -> -0.0009215 | L44: =K44/$C$46*100% -> -2.9497083e-07 | M44: =-SUMIF('05.conso TB'!A:A,'May-26'!B44,'05.conso TB'!T:T)/10^5 -> -0.0009221 | N44: =M44/$C$46*100% -> -2.9516289e-07 | O44: =Q44-'Apr-26'!Q44 -> 2.78e-05 | P44: =O44/$O$46*100% -> 2.238228e-08 | Q44: =-SUMIF('05.conso TB'!A:A,'May-26'!B44,'05.conso TB'!U:U)/10^5 -> 1.81e-05 | R44: =Q44/$Q$46*100% -> 8.3071561e-09 | S44: =U44-'Apr-26'!U44 -> -0.0030528 | T44: =S44/$S$46*100% -> 0.13000153 | U44: =-SUMIF('05.conso TB'!A:A,'May-26'!B44,'05.conso TB'!V:V)/10^5 -> -0.002067 | V44: =U44/$U$46*100% -> -4.2406467e-05 | W44: =Y44-'Apr-26'!Y44 -> 1e-06 | X44: =W44/$W$46*100% -> 2.6887876e-10 | Y44: =-SUMIF('05.conso TB'!A:A,'May-26'!B44,'05.conso TB'!G:G)/10^5 -> 5.8e-06 | Z44: =Y44/$Y$46*100% -> 1.528885e-09 | AB44: =AD44-'Apr-26'!AD44 -> 0.5908909 | AC44: =AB44/$AB$46*100% -> 6.4078265e-05 | AD44: =E44+I44+M44+Q44+U44+Y44 -> 0.5918328 | AE44: =AD44/$AD$46*100% -> 4.0948893e-05 | AG44: =AI44-'Apr-26'!AI44 -> 5.6e-06 | AH44: =AG44/$AG$46*100% -> 1.5237723e-08 | AI44: =-SUMIF('05.conso TB'!A:A,'May-26'!B44,'05.conso TB'!Q:Q)/10^5 -> 1.36e-05 | AJ44: =AI44/$AI$46*100% -> 1.8428118e-08 | AL44: =AN44-'Apr-26'!AN44 -> -3.68e-05 | AM44: =AL44/$AL$46*100% -> -3.1074837e-08 | AN44: =-SUMIF('05.conso TB'!A:A,'May-26'!B44,'05.conso TB'!W:W)/10^5 -> -8.61e-05 | AO44: =AN44/$AN$46*100% -> -3.7074545e-08 | AQ44: =AS44-'Apr-26'!AS44 -> -9.33e-05 | AR44: =AQ44/$AQ$46*100% -> -4.5761608e-08 | AS44: =-SUMIF('05.conso TB'!A:A,'May-26'!B44,'05.conso TB'!M:M)/10^5 -> -0.0001781 | AT44: =AS44/$AS$46*100% -> -4.6014257e-08 | AU44: =AW44-'Apr-26'!AW44 -> 0.008403 | AV44: =AU44/$C$46*100% -> 2.6897883e-06 | AW44: =-SUMIF('05.conso TB'!A:A,'May-26'!B44,'05.conso TB'!P:P)/10^5 -> 0.0084132 | AX44: =AW44/$AW$46*100% -> 4.5544884e-06 | AZ44: =BB44-'Apr-26'!BB44 -> 0.0083097 | BA44: =AZ44/$AZ$46*100% -> 2.7377717e-06 | BB44: =AS44+AW44 -> 0.0082351 | BC44: =BB44/$BB$46*100% -> 1.4402637e-06 | BE44: =BG44-'Apr-26'!BG44 -> 0.0002435 | BF44: =BE44/$BE$46*100% -> 8.7122264e-08 | BG44: =-SUMIF('05.conso TB'!A:A,'May-26'!B44,'05.conso TB'!H:H)/10^5 -> 0.0001962 | BH44: =BG44/$BG$46*100% -> 4.1752327e-08 | BI44: =BK44-'Apr-26'!BK44 -> -6e-07 | BJ44: =BI44/$BI$46*100% -> -3.121892e-08 | BK44: =-SUMIF('05.conso TB'!A:A,'May-26'!B44,'05.conso TB'!I:I)/10^5 -> -1.41e-05 | BL44: =BK44/$BK$46*100% -> -3.652876e-07 | BM44: =BO44-'Apr-26'!BO44 -> 0 | BN44: =BM44/$C$46*100% -> 0 | BO44: =-SUMIF('05.conso TB'!A:A,'May-26'!B44,'05.conso TB'!J:J)/10^5 -> 0 | BP44: =BO44/$C$46*100% -> 0 | BR44: =BT44-'Apr-26'!BT44 -> 0.0002429 | BS44: =BR44/$BR$46*100% -> 9.1851132e-08 | BT44: =BG44+BK44+BO44-BQ44 -> 0.0001821 | BU44: =BT44/$BT$46*100% -> 4.0577154e-08 | BW44: =BY44-'Apr-26'!BY44 -> -1.79e-05 | BX44: =BW44/$BW$46*100% -> -3.9555595e-08 | BY44: =-SUMIF('05.conso TB'!A:A,'May-26'!B44,'05.conso TB'!L:L)/10^5 -> -4.19e-05 | BZ44: =BY44/$BY$46*100% -> -1.9390215e-08 | CB44: =CD44-'Apr-26'!CD44 -> 0 | CE44: =AB44+AG44+AL44+AZ44+BR44+BW44 -> 0.5993944 | CF44: =CE44/$CE$46*100% -> 3.5455858e-05 | CG44: =AD44+AI44+AN44+BB44+BT44+BY44 -> 0.6001356 | CH44: =CG44/$CG$46*100% -> 4.9072771e-05
B45: Total Other income | C45: =SUM(C35:C44) -> 15.904517 | D45: =SUM(D35:D44) -> 0.0050910133 | E45: =SUM(E35:E44) -> 25.012938 | F45: =E45/$E$46*100% -> 0.0038712838 | G45: =SUM(G35:G44) -> 14.405321 | H45: =G45/$G$46*100% -> 0.010845689 | I45: =SUM(I35:I44) -> 23.653884 | J45: =I45/$I$46*100% -> 0.0094255311 | K45: =SUM(K35:K44) -> 15.948028 | L45: =SUM(L35:L44) -> 0.0051049411 | M45: =SUM(M35:M44) -> 38.220238 | N45: =SUM(N35:N44) -> 0.012234243 | O45: =SUM(O35:O44) -> 2.78e-05 | P45: =O45/$O$46*100% -> 2.238228e-08 | Q45: =SUM(Q35:Q44) -> 1.81e-05 | R45: =Q45/$Q$46*100% -> 8.3071561e-09 | S45: =SUM(S35:S44) -> -0.0234828 | T45: =S45/$S$46*100% -> 1 | U45: =SUM(U35:U44) -> -0.022497 | V45: =U45/$U$46*100% -> -0.00046154731 | W45: =SUM(W35:W44) -> -44.551239 | X45: =W45/$W$46*100% -> -0.011978882 | Y45: =SUM(Y35:Y44) -> -44.101234 | Z45: =Y45/$Y$46*100% -> -0.011625123 | AA45: =SUM(AA35:AA44) -> 0 | AB45: =C45+G45+K45+O45+S45+W45 -> 1.683173 | AC45: =AB45/$AB$46*100% -> 0.00018252913 | AD45: =E45+I45+M45+Q45+U45+Y45 -> 42.763347 | AE45: =AD45/$AD$46*100% -> 0.0029587946 | AG45: =SUM(AG35:AG44) -> 5.6e-06 | AH45: =AG45/$AG$46*100% -> 1.5237723e-08 | AI45: =SUM(AI35:AI44) -> 1.36e-05 | AJ45: =SUM(AJ35:AJ44) -> 1.8428118e-08 | AL45: =SUM(AL35:AL44) -> 6.1640632 | AM45: =AL45/$AL$46*100% -> 0.0052050886 | AN45: =SUM(AN35:AN44) -> 7.3342639 | AO45: =SUM(AO35:AO44) -> 0.0031581243 | AQ45: =SUM(AQ35:AQ44) -> -2.0000933 | AR45: =AQ45/$AQ$46*100% -> -0.00098100199 | AS45: =SUM(AS35:AS44) -> -2.0001781 | AT45: =SUM(AT35:AT44) -> -0.00051676985 | AU45: =SUM(AU35:AU44) -> 0.008403 | AV45: =SUM(AV35:AV44) -> 2.6897883e-06 | AW45: =SUM(AW35:AW44) -> 0.0084132 | AX45: =SUM(AX35:AX44) -> 4.5544884e-06 | AZ45: =SUM(AZ35:AZ44) -> -1.9916903 | BA45: =AZ45/$AZ$46*100% -> -0.00065619618 | BB45: =SUM(BB35:BB44) -> -1.9917649 | BC45: =SUM(BC35:BC44) -> -0.00034834632 | BE45: =SUM(BE35:BE44) -> 0.2458765 | BF45: =BE45/$BE$46*100% -> 8.7972556e-05 | BG45: =SUM(BG35:BG44) -> 0.4858292 | BH45: =SUM(BH35:BH44) -> 0.00010338685 | BI45: =SUM(BI35:BI44) -> -6e-07 | BJ45: =BI45/$BI$46*100% -> -3.121892e-08 | BK45: =SUM(BK35:BK44) -> -1.41e-05 | BL45: =SUM(BL35:BL44) -> -3.652876e-07 | BM45: =SUM(BM35:BM44) -> 0 | BN45: =SUM(BN35:BN44) -> 0 | BO45: =SUM(BO35:BO44) -> 0.07617 | BP45: =SUM(BP35:BP44) -> 2.4381908e-05 | BR45: =SUM(BR35:BR44) -> 0.2458759 | BS45: =BR45/$BR$46*100% -> 9.297645e-05 | BT45: =BG45+BK45+BO45-BQ45 -> 0.5619851 | BU45: =BT45/$BT$46*100% -> 0.00012522656 | BW45: =SUM(BW35:BW44) -> 7.5992921 | BX45: =BW45/$BW$46*100% -> 0.01679299 | BY45: =SUM(BY35:BY44) -> 9.5095381 | BZ45: =BY45/$BY$46*100% -> 0.0044007635 | CB45: =SUM(CB35:CB44) -> 4.69 | CC45: =SUM(CC35:CC44) -> 7.38 | CE45: =AB45+AG45+AL45+AZ45+BR45+BW45 -> 13.700719 | CF45: =CE45/$CE$46*100% -> 0.00081043593 | CG45: =AD45+AI45+AN45+BB45+BT45+BY45 -> 58.177383 | CH45: =CG45/$CG$46*100% -> 0.0047571339
B46: Total Turnover | C46: =C25+C28+C33+C45 -> 3124.0377 | D46: =D25+D28+D33+D45 -> 1 | E46: =E25+E28+E33+E45 -> 6461.1482 | F46: =E46/$E$46*100% -> 1 | G46: =G25+G28+G33+G45 -> 1328.2071 | H46: =G46/$G$46*100% -> 1 | I46: =I25+I28+I33+I45 -> 2509.5545 | J46: =I46/$I$46*100% -> 1 | K46: =K25+K28+K33+K45 -> 23.363878 | L46: =L25+L28+L33+L45 -> 0.0074787441 | M46: =M25+M28+M33+M45 -> 64.68318 | N46: =N25+N28+N33+N45 -> 0.020704993 | O46: =O25+O28+O33+O45 -> 1242.054 | P46: =O46/$O$46*100% -> 1 | Q46: =Q25+Q28+Q33+Q45 -> 2178.8443 | R46: =Q46/$Q$46*100% -> 1 | S46: =S25+S28+S33+S45 -> -0.0234828 | T46: =S46/$S$46*100% -> 1 | U46: =U25+U28+U33+U45 -> 48.742565 | V46: =U46/$U$46*100% -> 1 | W46: =W25+W28+W33+W45 -> 3719.1484 | X46: =W46/$W$46*100% -> 1 | Y46: =Y25+Y28+Y33+Y45 -> 3793.6144 | Z46: =Y46/$Y$46*100% -> 1 | AA46: =AA25+AA28+AA33+AA45 -> 603.62492 | AB46: =AB25+AB28+AB33+AB45 -> 9221.3936 | AC46: =AB46/$AB$46*100% -> 1 | AD46: =AD25+AD28+AD33+AD45 -> 14452.962 | AE46: =AD46/$AD$46*100% -> 1 | AF46: =AG46/$AG$1*10^5 -> 99.994555 | AG46: =AG25+AG28+AG33+AG45 -> 367.50899 | AH46: =AG46/$AG$46*100% -> 1 | AI46: =AI25+AI28+AI33+AI45 -> 738.00267 | AJ46: =AJ25+AJ28+AJ33+AJ45 -> 1 | AK46: =AL46/$AL$1*10^5 -> 268.15524 | AL46: =AL25+AL28+AL33+AL45 -> 1184.2379 | AM46: =AL46/$AL$46*100% -> 1 | AN46: =AN25+AN28+AN33+AN45 -> 2322.3481 | AO46: =AO25+AO28+AO33+AO45 -> 1 | AP46: =AQ46/$AQ$1*10^5 -> 341.49775 | AQ46: =AQ25+AQ28+AQ33+AQ45 -> 2038.827 | AR46: =AQ46/$AQ$46*100% -> 1 | AS46: =AS25+AS28+AS33+AS45 -> 3870.5395 | AT46: =AT25+AT28+AT33+AT45 -> 1 | AU46: =AU25+AU28+AU33+AU45 -> 996.37862 | AV46: =AV25+AV28+AV33+AV45 -> 0.31742632 | AW46: =AW25+AW28+AW33+AW45 -> 1847.2327 | AX46: =AX25+AX28+AX33+AX45 -> 1 | AZ46: =AZ25+AZ28+AZ33+AZ45 -> 3035.2056 | BA46: =AZ46/$AZ$46*100% -> 1 | BB46: =BB25+BB28+BB33+BB45 -> 5717.7722 | BC46: =BC25+BC28+BC33+BC45 -> 1 | BE46: =BE25+BE28+BE33+BE45 -> 2794.9228 | BF46: =BE46/$BE$46*100% -> 1 | BG46: =BG25+BG28+BG33+BG45 -> 4699.1392 | BH46: =BH25+BH28+BH33+BH45 -> 1 | BI46: =BI25+BI28+BI33+BI45 -> 19.219114 | BJ46: =BI46/$BI$46*100% -> 1 | BK46: =BK25+BK28+BK33+BK45 -> 38.599723 | BL46: =BL25+BL28+BL33+BL45 -> 1 | BM46: =BM25+BM28+BM33+BM45 -> 0 | BN46: =BN25+BN28+BN33+BN45 -> 0 | BO46: =BO25+BO28+BO33+BO45 -> 0.07617 | BP46: =BP25+BP28+BP33+BP45 -> 2.4381908e-05 | BQ46: =BQ25+BQ28+BQ33+BQ45 -> 250.06819 | BR46: =BR25+BR28+BR33+BR45 -> 2644.4965 | BS46: =BR46/$BR$46*100% -> 1 | BT46: =BG46+BK46+BO46-BQ46 -> 4487.7469 | BU46: =BT46/$BT$46*100% -> 1 | BW46: =BW25+BW28+BW33+BW45 -> 452.52764 | BX46: =BW46/$BW$46*100% -> 1 | BY46: =BY25+BY28+BY33+BY45 -> 2160.8837 | BZ46: =BY46/$BY$46*100% -> 1 | CB46: =CB25+CB28+CB33+CB45 -> 10033.982 | CC46: =CC25+CC28+CC33+CC45 -> 17657.593 | CE46: =CE25+CE28+CE33+CE45 -> 16905.37 | CF46: =CE46/$CE$46*100% -> 1 | CG46: =CG25+CG28+CG33+CG45 -> 12229.503 | CH46: =CG46/$CG$46*100% -> 1
F47: =E47/$E$46*100% -> 0 | H47: =G47/$G$46*100% -> 0 | J47: =I47/$I$46*100% -> 0 | P47: =O47/$O$46*100% -> 0 | R47: =Q47/$Q$46*100% -> 0 | T47: =S47/$S$46*100% -> 0 | V47: =U47/$U$46*100% -> 0 | X47: =W47/$W$46*100% -> 0 | Z47: =Y47/$Y$46*100% -> 0 | AC47: =AB47/$AB$46*100% -> 0 | AE47: =AD47/$AD$46*100% -> 0 | AH47: =AG47/$AG$46*100% -> 0 | AM47: =AL47/$AL$46*100% -> 0 | AR47: =AQ47/$AQ$46*100% -> 0 | AS47: =(AS46-AQ46)/11 -> 166.51932 | BA47: =AZ47/$AZ$46*100% -> 0 | BF47: =BE47/$BE$46*100% -> 0 | BJ47: =BI47/$BI$46*100% -> 0 | BS47: =BR47/$BR$46*100% -> 0 | BT47: =BG47+BK47+BO47-BQ47 -> 0 | BU47: =BT47/$BT$46*100% -> 0 | BX47: =BW47/$BW$46*100% -> 0 | BZ47: =BY47/$BY$46*100% -> 0 | CF47: =CE47/$CE$46*100% -> 0 | CH47: =CG47/$CG$46*100% -> 0
B48: Cost of Goods | F48: =E48/$E$46*100% -> 0 | H48: =G48/$G$46*100% -> 0 | J48: =I48/$I$46*100% -> 0 | P48: =O48/$O$46*100% -> 0 | R48: =Q48/$Q$46*100% -> 0 | T48: =S48/$S$46*100% -> 0 | V48: =U48/$U$46*100% -> 0 | X48: =W48/$W$46*100% -> 0 | Z48: =Y48/$Y$46*100% -> 0 | AC48: =AB48/$AB$46*100% -> 0 | AE48: =AD48/$AD$46*100% -> 0 | AH48: =AG48/$AG$46*100% -> 0 | AM48: =AL48/$AL$46*100% -> 0 | AR48: =AQ48/$AQ$46*100% -> 0 | BA48: =AZ48/$AZ$46*100% -> 0 | BF48: =BE48/$BE$46*100% -> 0 | BJ48: =BI48/$BI$46*100% -> 0 | BS48: =BR48/$BR$46*100% -> 0 | BT48: =BG48+BK48+BO48-BQ48 -> 0 | BU48: =BT48/$BT$46*100% -> 0 | BX48: =BW48/$BW$46*100% -> 0 | BZ48: =BY48/$BY$46*100% -> 0 | CF48: =CE48/$CE$46*100% -> 0 | CH48: =CG48/$CG$46*100% -> 0
B49: Cost of materials consumed | C49: =E49-'Apr-26'!E49 -> 2250.9285 | D49: =C49/$C$46*100% -> 0.720519 | E49: =E114 -> 4363.1335 | F49: =E49/$E$46*100% -> 0.67528764 | G49: =I49-'Apr-26'!I49 -> 659.15561 | H49: =G49/$G$46*100% -> 0.49627471 | I49: =I114 -> 1451.8446 | J49: =I49/$I$46*100% -> 0.57852685 | K49: =M49-'Apr-26'!M49 -> 0 | L49: =K49/$C$46*100% -> 0 | M49: =SUMIF('05.conso TB'!A:A,'May-26'!B49,'05.conso TB'!T:T) -> 0 | N49: =M49/$C$46*100% -> 0 | O49: =Q49-'Apr-26'!Q49 -> 808.44162 | P49: =O49/$O$46*100% -> 0.6508909 | Q49: =Q114 -> 1626.0565 | R49: =Q49/$Q$46*100% -> 0.74629308 | S49: =U49-'Apr-26'!U49 -> 0 | T49: =S49/$S$46*100% -> 0 | U49: =U114 -> 0 | V49: =U49/$U$46*100% -> 0 | W49: =Y49-'Apr-26'!Y49 -> 3780.8801 | X49: =W49/$W$46*100% -> 1.0165984 | Y49: =Y114 -> 3819.5417 | Z49: =Y49/$Y$46*100% -> 1.0068345 | AA49: =AA23 -> 317.57266 | AB49: =AD49-'Apr-26'!AD49 -> 7308.2097 | AC49: =AB49/$AB$46*100% -> 0.79252768 | AD49: =E49+I49+M49+Q49+U49+Y49-AA49 -> 10943.004 | AE49: =AD49/$AD$46*100% -> 0.75714608 | AG49: =AI49-'Apr-26'!AI49 -> 76.380956 | AH49: =AG49/$AG$46*100% -> 0.20783425 | AI49: =AI114 -> 154.55398 | AJ49: =AI49/$AI$46*100% -> 0.20942198 | AL49: =AN49-'Apr-26'!AN49 -> 586.06298 | AM49: =AL49/$AL$46*100% -> 0.49488619 | AN49: =AN114 -> 1377.7248 | AO49: =AN49/$AN$46*100% -> 0.59324646 | AQ49: =AS49-'Apr-26'!AS49 -> 865.47213 | AR49: =AQ49/$AQ$46*100% -> 0.42449514 | AS49: =AS114 -> 2107.2344 | AT49: =AS49/$AS$46*100% -> 0.54442911 | AU49: =AW49-'Apr-26'!AW49 -> 592.72467 | AV49: =AU49/$C$46*100% -> 0.18973032 | AW49: =AW114 -> 1137.5888 | AX49: =AW49/$AW$46*100% -> 0.61583407 | AY49: =AY23 -> 0 | AZ49: =BB49-'Apr-26'!BB49 -> 1458.1968 | BA49: =AZ49/$AZ$46*100% -> 0.48042769 | BB49: =AS49+AW49 -> 3244.8232 | BC49: =BB49/$BB$46*100% -> 0.56749781 | BE49: =BG49-'Apr-26'!BG49 -> 2282.3378 | BF49: =BE49/$BE$46*100% -> 0.81660139 | BG49: =BG114 -> 3421.9024 | BH49: =BG49/$BG$46*100% -> 0.72819771 | BI49: =BK49-'Apr-26'!BK49 -> 4.2892374 | BJ49: =BI49/$BI$46*100% -> 0.2231756 | BK49: =BK114 -> 7.8503508 | BL49: =BK49/$BK$46*100% -> 0.20337842 | BM49: =BO49-'Apr-26'!BO49 -> 0 | BN49: =BM49/$C$46*100% -> 0 | BO49: =BO114 -> 0 | BP49: =BO49/$C$46*100% -> 0 | BQ49: =BQ23 -> 0 | BR49: =BT49-'Apr-26'!BT49 -> 2286.6271 | BS49: =BR49/$BR$46*100% -> 0.86467387 | BT49: =BG49+BK49+BO49-BQ49 -> 3429.7528 | BU49: =BT49/$BT$46*100% -> 0.76424826 | BW49: =BY49-'Apr-26'!BY49 -> 397.16709 | BX49: =BW49/$BW$46*100% -> 0.87766372 | BY49: =BY114 -> 2050.8491 | BZ49: =BY49/$BY$46*100% -> 0.94907887 | CB49: =CC49-'Apr-26'!CC49 -> 9180.8743 | CC49: =CC25 -> 16274.814 | CE49: =AB49+AG49+AL49+AZ49+BR49+BW49-CA49 -> 12112.645 | CF49: =CE49/$CE$46*100% -> 0.71649685 | CG49: =AD49+AI49+AN49+BB49+BT49+BY49-CC49 -> 4925.893 | CH49: =CG49/$CG$46*100% -> 0.40278767
B50: Purchase of stock-in-trade | C50: =E50-'Apr-26'!E50 -> 250.1425 | D50: =C50/$C$46*100% -> 0.080070256 | E50: =E124 -> 250.3925 | F50: =E50/$E$46*100% -> 0.038753561 | G50: =I50-'Apr-26'!I50 -> 0 | H50: =G50/$G$46*100% -> 0 | I50: =I124 -> 0.32596 | J50: =I50/$I$46*100% -> 0.0001298876 | K50: =M50-'Apr-26'!M50 -> 0 | L50: =K50/$C$46*100% -> 0 | M50: =SUMIF('05.conso TB'!A:A,'May-26'!B50,'05.conso TB'!T:T) -> 0 | N50: =M50/$C$46*100% -> 0 | O50: =Q50-'Apr-26'!Q50 -> 0 | P50: =O50/$O$46*100% -> 0 | Q50: =Q124 -> 15.433167 | R50: =Q50/$Q$46*100% -> 0.0070831894 | S50: =U50-'Apr-26'!U50 -> 0 | T50: =S50/$S$46*100% -> 0 | U50: =U124 -> 48.76994 | V50: =U50/$U$46*100% -> 1.0005616 | W50: =Y50-'Apr-26'!Y50 -> 0 | X50: =W50/$W$46*100% -> 0 | Y50: =Y124 -> 0 | Z50: =Y50/$Y$46*100% -> 0 | AA50: =AA24 -> 286.05227 | AB50: =AD50-'Apr-26'!AD50 -> 225.94476 | AC50: =AB50/$AB$46*100% -> 0.024502235 | AD50: =E50+I50+M50+Q50+U50+Y50-AA50 -> 28.869303 | AE50: =AD50/$AD$46*100% -> 0.0019974661 | AG50: =AI50-'Apr-26'!AI50 -> 0 | AH50: =AG50/$AG$46*100% -> 0 | AI50: =AI124 -> 0 | AJ50: =AI50/$AI$46*100% -> 0 | AL50: =AN50-'Apr-26'!AN50 -> 459.52827 | AM50: =AL50/$AL$46*100% -> 0.38803713 | AN50: =AN124 -> 546.42793 | AO50: =AN50/$AN$46*100% -> 0.23529114 | AQ50: =AS50-'Apr-26'!AS50 -> 0 | AR50: =AQ50/$AQ$46*100% -> 0 | AS50: =AS124 -> 0 | AT50: =AS50/$AS$46*100% -> 0 | AU50: =AW50-'Apr-26'!AW50 -> 0 | AV50: =AU50/$C$46*100% -> 0 | AW50: =AW124 -> 0 | AX50: =AW50/$AW$46*100% -> 0 | AY50: =AY24 -> 0 | AZ50: =BB50-'Apr-26'!BB50 -> 0 | BA50: =AZ50/$AZ$46*100% -> 0 | BB50: =AS50+AW50 -> 0 | BC50: =BB50/$BB$46*100% -> 0 | BE50: =BG50-'Apr-26'!BG50 -> 159.31999 | BF50: =BE50/$BE$46*100% -> 0.057003361 | BG50: =BG124 -> 575.32657 | BH50: =BG50/$BG$46*100% -> 0.12243233 | BI50: =BK50-'Apr-26'!BK50 -> 0 | BJ50: =BI50/$BI$46*100% -> 0 | BK50: =BK124 -> 0 | BL50: =BK50/$BK$46*100% -> 0 | BM50: =BO50-'Apr-26'!BO50 -> 0 | BN50: =BM50/$C$46*100% -> 0 | BO50: =BO124 -> 0 | BP50: =BO50/$C$46*100% -> 0 | BQ50: =BQ24 -> 250.06819 | BR50: =BT50-'Apr-26'!BT50 -> -10.325365 | BS50: =BR50/$BR$46*100% -> -0.003904473 | BT50: =BG50+BK50+BO50-BQ50 -> 325.25838 | BU50: =BT50/$BT$46*100% -> 0.072476988 | BW50: =BY50-'Apr-26'!BY50 -> 0 | BX50: =BW50/$BW$46*100% -> 0 | BY50: =BY124 -> 0 | BZ50: =BY50/$BY$46*100% -> 0 | CB50: =CD50-'Apr-26'!CD50 -> 0 | CE50: =AB50+AG50+AL50+AZ50+BR50+BW50 -> 675.14766 | CF50: =CE50/$CE$46*100% -> 0.039936875 | CG50: =AD50+AI50+AN50+BB50+BT50+BY50 -> 900.55562 | CH50: =CG50/$CG$46*100% -> 0.073637957
B51: Changes in inventory of finished goods and work-in-progress | C51: =E51-'Apr-26'!E51 -> -165.83024 | D51: =C51/$C$46*100% -> -0.053082024 | E51: =E132 -> -99.144551 | F51: =E51/$E$46*100% -> -0.015344726 | G51: =I51-'Apr-26'!I51 -> 154.83652 | H51: =G51/$G$46*100% -> 0.11657558 | I51: =I132 -> -2.6233151 | J51: =I51/$I$46*100% -> -0.001045331 | K51: =M51-'Apr-26'!M51 -> 0 | L51: =K51/$C$46*100% -> 0 | M51: =SUMIF('05.conso TB'!A:A,'May-26'!B51,'05.conso TB'!T:T) -> 0 | N51: =M51/$C$46*100% -> 0 | O51: =Q51-'Apr-26'!Q51 -> 5.6409203 | P51: =O51/$O$46*100% -> 0.0045416064 | Q51: =Q132 -> -149.58632 | R51: =Q51/$Q$46*100% -> -0.068653972 | S51: =U51-'Apr-26'!U51 -> 0 | T51: =S51/$S$46*100% -> 0 | U51: =U132 -> 0 | V51: =U51/$U$46*100% -> 0 | W51: =Y51-'Apr-26'!Y51 -> 0 | X51: =W51/$W$46*100% -> 0 | Y51: =Y132 -> 0 | Z51: =Y51/$Y$46*100% -> 0 | AB51: =AD51-'Apr-26'!AD51 -> -5.3528005 | AC51: =AB51/$AB$46*100% -> -0.00058047631 | AD51: =E51+I51+M51+Q51+U51+Y51 -> -251.35418 | AE51: =AD51/$AD$46*100% -> -0.017391188 | AG51: =AI51-'Apr-26'!AI51 -> 24.079957 | AH51: =AG51/$AG$46*100% -> 0.06552209 | AI51: =AI132 -> 48.255239 | AJ51: =AI51/$AI$46*100% -> 0.065386265 | AL51: =AN51-'Apr-26'!AN51 -> 2.2500647 | AM51: =AL51/$AL$46*100% -> 0.0019000107 | AN51: =AN132 -> -95.012191 | AO51: =AN51/$AN$46*100% -> -0.040912123 | AQ51: =AS51-'Apr-26'!AS51 -> -498.90357 | AR51: =AQ51/$AQ$46*100% -> -0.24470128 | AS51: =AS132 -> -997.56394 | AT51: =AS51/$AS$46*100% -> -0.25773253 | AU51: =AW51-'Apr-26'!AW51 -> -140.59837 | AV51: =AU51/$C$46*100% -> -0.045005338 | AW51: =AW132 -> -214.35476 | AX51: =AW51/$AW$46*100% -> -0.11604101 | AZ51: =BB51-'Apr-26'!BB51 -> -639.50194 | BA51: =AZ51/$AZ$46*100% -> -0.21069477 | BB51: =AS51+AW51 -> -1211.9187 | BC51: =BB51/$BB$46*100% -> -0.21195645 | BE51: =BG51-'Apr-26'!BG51 -> -81.8625 | BF51: =BE51/$BE$46*100% -> -0.029289718 | BG51: =BG132 -> 26.46032 | BH51: =BG51/$BG$46*100% -> 0.0056308866 | BI51: =BK51-'Apr-26'!BK51 -> -2.25918 | BJ51: =BI51/$BI$46*100% -> -0.1175486 | BK51: =BK132 -> 7.61103 | BL51: =BK51/$BK$46*100% -> 0.19717836 | BM51: =BO51-'Apr-26'!BO51 -> 0 | BN51: =BM51/$C$46*100% -> 0 | BO51: =BO132 -> 0 | BP51: =BO51/$C$46*100% -> 0 | BR51: =BT51-'Apr-26'!BT51 -> -84.12168 | BS51: =BR51/$BR$46*100% -> -0.031810093 | BT51: =BG51+BK51+BO51-BQ51 -> 34.07135 | BU51: =BT51/$BT$46*100% -> 0.0075920836 | BW51: =BY51-'Apr-26'!BY51 -> 0 | BX51: =BW51/$BW$46*100% -> 0 | BY51: =BY132 -> 0 | BZ51: =BY51/$BY$46*100% -> 0 | CB51: =CD51-'Apr-26'!CD51 -> 0 | CE51: =AB51+AG51+AL51+AZ51+BR51+BW51 -> -702.6464 | CF51: =CE51/$CE$46*100% -> -0.041563503 | CG51: =AD51+AI51+AN51+BB51+BT51+BY51 -> -1475.9585 | CH51: =CG51/$CG$46*100% -> -0.12068835
B52: Stores, Spares & Consumables | C52: =E52-'Apr-26'!E52 -> 36.410483 | D52: =C52/$C$46*100% -> 0.011654944 | E52: =E140 -> 70.5128 | F52: =E52/$E$46*100% -> 0.010913354 | G52: =I52-'Apr-26'!I52 -> 14.770488 | H52: =G52/$G$46*100% -> 0.01112062 | I52: =I140 -> 44.499429 | J52: =I52/$I$46*100% -> 0.017732004 | K52: =M52-'Apr-26'!M52 -> 0 | L52: =K52/$C$46*100% -> 0 | M52: =SUMIF('05.conso TB'!A:A,'May-26'!B52,'05.conso TB'!T:T) -> 0 | N52: =M52/$C$46*100% -> 0 | O52: =Q52-'Apr-26'!Q52 -> 13.481976 | P52: =O52/$O$46*100% -> 0.010854581 | Q52: =Q140 -> 24.750573 | R52: =Q52/$Q$46*100% -> 0.011359496 | S52: =U52-'Apr-26'!U52 -> 0 | T52: =S52/$S$46*100% -> 0 | U52: =U140 -> 0 | V52: =U52/$U$46*100% -> 0 | W52: =Y52-'Apr-26'!Y52 -> 0 | X52: =W52/$W$46*100% -> 0 | Y52: =Y140 -> 0 | Z52: =Y52/$Y$46*100% -> 0 | AB52: =AD52-'Apr-26'!AD52 -> 64.662947 | AC52: =AB52/$AB$46*100% -> 0.0070122748 | AD52: =E52+I52+M52+Q52+U52+Y52 -> 139.7628 | AE52: =AD52/$AD$46*100% -> 0.0096701839 | AF52: =AG52/$AG$1*10^5 -> 7.6437014 | AG52: =AI52-'Apr-26'!AI52 -> 28.092819 | AH52: =AG52/$AG$46*100% -> 0.076441176 | AI52: =AI140 -> 54.716383 | AJ52: =AI52/$AI$46*100% -> 0.074141172 | AK52: =AL52/$AL$1*10^5 -> 3.3392375 | AL52: =AN52-'Apr-26'!AN52 -> 14.746874 | AM52: =AL52/$AL$46*100% -> 0.012452628 | AN52: =AN140 -> 29.170036 | AO52: =AN52/$AN$46*100% -> 0.012560579 | AP52: =AQ52/$AQ$1*10^5 -> 3.177354 | AQ52: =AS52-'Apr-26'!AS52 -> 18.969598 | AR52: =AQ52/$AQ$46*100% -> 0.0093041725 | AS52: =AS140 -> 27.260608 | AT52: =AS52/$AS$46*100% -> 0.007043103 | AU52: =AW52-'Apr-26'!AW52 -> 0 | AV52: =AU52/$C$46*100% -> 0 | AW52: =AW140 -> 0 | AX52: =AW52/$AW$46*100% -> 0 | AZ52: =BB52-'Apr-26'!BB52 -> 18.969598 | BA52: =AZ52/$AZ$46*100% -> 0.006249856 | BB52: =AS52+AW52 -> 27.260608 | BC52: =BB52/$BB$46*100% -> 0.0047676975 | BE52: =BG52-'Apr-26'!BG52 -> 10.446038 | BF52: =BE52/$BE$46*100% -> 0.003737505 | BG52: =BG140 -> 9.1025263 | BH52: =BG52/$BG$46*100% -> 0.0019370625 | BI52: =BK52-'Apr-26'!BK52 -> -0.3495145 | BJ52: =BI52/$BI$46*100% -> -0.018185776 | BK52: =BK140 -> -0.4959745 | BL52: =BK52/$BK$46*100% -> -0.012849173 | BM52: =BO52-'Apr-26'!BO52 -> 0 | BN52: =BM52/$C$46*100% -> 0 | BO52: =BO140 -> 0 | BP52: =BO52/$C$46*100% -> 0 | BR52: =BT52-'Apr-26'!BT52 -> 10.096523 | BS52: =BR52/$BR$46*100% -> 0.0038179378 | BT52: =BG52+BK52+BO52-BQ52 -> 8.6065518 | BU52: =BT52/$BT$46*100% -> 0.001917789 | BW52: =BY52-'Apr-26'!BY52 -> 0 | BX52: =BW52/$BW$46*100% -> 0 | BY52: =BY140 -> 0 | BZ52: =BY52/$BY$46*100% -> 0 | CB52: =CD52-'Apr-26'!CD52 -> 0 | CE52: =AB52+AG52+AL52+AZ52+BR52+BW52 -> 136.56876 | CF52: =CE52/$CE$46*100% -> 0.0080784247 | CG52: =AD52+AI52+AN52+BB52+BT52+BY52 -> 259.51638 | CH52: =CG52/$CG$46*100% -> 0.021220517
B53: Total Cost of goods | C53: =SUM(C49:C52) -> 2371.6513 | D53: =SUM(D49:D52) -> 0.75916218 | E53: =SUM(E49:E52) -> 4584.8943 | F53: =E53/$E$46*100% -> 0.70960983 | G53: =SUM(G49:G52) -> 828.76262 | H53: =G53/$G$46*100% -> 0.62397091 | I53: =SUM(I49:I52) -> 1494.0467 | J53: =I53/$I$46*100% -> 0.59534341 | K53: =SUM(K49:K52) -> 0 | L53: =SUM(L49:L52) -> 0 | M53: =SUM(M49:M52) -> 0 | N53: =SUM(N49:N52) -> 0 | O53: =SUM(O49:O52) -> 827.56452 | P53: =O53/$O$46*100% -> 0.66628708 | Q53: =SUM(Q49:Q52) -> 1516.6539 | R53: =Q53/$Q$46*100% -> 0.69608179 | S53: =SUM(S49:S52) -> 0 | T53: =S53/$S$46*100% -> 0 | U53: =SUM(U49:U52) -> 48.76994 | V53: =U53/$U$46*100% -> 1.0005616 | W53: =SUM(W49:W52) -> 3780.8801 | X53: =W53/$W$46*100% -> 1.0165984 | Y53: =SUM(Y49:Y52) -> 3819.5417 | Z53: =Y53/$Y$46*100% -> 1.0068345 | AA53: =SUM(AA49:AA52) -> 603.62492 | AB53: =SUM(AB49:AB52) -> 7593.4646 | AC53: =AB53/$AB$46*100% -> 0.82346171 | AD53: =SUM(AD49:AD52) -> 10860.282 | AE53: =AD53/$AD$46*100% -> 0.75142254 | AF53: =AG53/$AG$1*10^5 -> 34.977847 | AG53: =SUM(AG49:AG52) -> 128.55373 | AH53: =AG53/$AG$46*100% -> 0.34979752 | AI53: =SUM(AI49:AI52) -> 257.5256 | AJ53: =SUM(AJ49:AJ52) -> 0.34894942 | AK53: =AL53/$AL$1*10^5 -> 240.60925 | AL53: =SUM(AL49:AL52) -> 1062.5882 | AM53: =AL53/$AL$46*100% -> 0.89727596 | AN53: =SUM(AN49:AN52) -> 1858.3106 | AO53: =SUM(AO49:AO52) -> 0.80018606 | AP53: =AQ53/$AQ$1*10^5 -> 64.576552 | AQ53: =SUM(AQ49:AQ52) -> 385.53816 | AR53: =AQ53/$AQ$46*100% -> 0.18909803 | AS53: =SUM(AS49:AS52) -> 1136.931 | AT53: =SUM(AT49:AT52) -> 0.29373968 | AU53: =SUM(AU49:AU52) -> 452.1263 | AV53: =SUM(AV49:AV52) -> 0.14472498 | AW53: =SUM(AW49:AW52) -> 923.23409 | AX53: =SUM(AX49:AX52) -> 0.49979306 | AY53: =SUM(AY49:AY52) -> 0 | AZ53: =SUM(AZ49:AZ52) -> 837.66446 | BA53: =AZ53/$AZ$46*100% -> 0.27598278 | BB53: =SUM(BB49:BB52) -> 2060.1651 | BC53: =SUM(BC49:BC52) -> 0.36030906 | BE53: =SUM(BE49:BE52) -> 2370.2413 | BF53: =BE53/$BE$46*100% -> 0.84805254 | BG53: =SUM(BG49:BG52) -> 4032.7918 | BH53: =SUM(BH49:BH52) -> 0.85819799 | BI53: =SUM(BI49:BI52) -> 1.6805429 | BJ53: =BI53/$BI$46*100% -> 0.087441225 | BK53: =SUM(BK49:BK52) -> 14.965406 | BL53: =SUM(BL49:BL52) -> 0.38770761 | BM53: =SUM(BM49:BM52) -> 0 | BN53: =SUM(BN49:BN52) -> 0 | BO53: =SUM(BO49:BO52) -> 0 | BP53: =SUM(BP49:BP52) -> 0 | BQ53: =SUM(BQ49:BQ52) -> 250.06819 | BR53: =SUM(BR49:BR52) -> 2202.2765 | BS53: =BR53/$BR$46*100% -> 0.83277724 | BT53: =BG53+BK53+BO53-BQ53 -> 3797.6891 | BU53: =BT53/$BT$46*100% -> 0.84623512 | BW53: =SUM(BW49:BW52) -> 397.16709 | BX53: =BW53/$BW$46*100% -> 0.87766372 | BY53: =SUM(BY49:BY52) -> 2050.8491 | BZ53: =BY53/$BY$46*100% -> 0.94907887 | CB53: =SUM(CB49:CB52) -> 9180.8743 | CC53: =SUM(CC49:CC52) -> 16274.814 | CE53: =SUM(CE49:CE52) -> 12221.715 | CF53: =CE53/$CE$46*100% -> 0.72294865 | CG53: =SUM(CG49:CG52) -> 4610.0065 | CH53: =CG53/$CG$46*100% -> 0.3769578
B54: Employee benefit expenses | F54: =E54/$E$46*100% -> 0 | H54: =G54/$G$46*100% -> 0 | J54: =I54/$I$46*100% -> 0 | P54: =O54/$O$46*100% -> 0 | R54: =Q54/$Q$46*100% -> 0 | T54: =S54/$S$46*100% -> 0 | V54: =U54/$U$46*100% -> 0 | X54: =W54/$W$46*100% -> 0 | Z54: =Y54/$Y$46*100% -> 0 | AC54: =AB54/$AB$46*100% -> 0 | AE54: =AD54/$AD$46*100% -> 0 | AH54: =AG54/$AG$46*100% -> 0 | AM54: =AL54/$AL$46*100% -> 0 | AR54: =AQ54/$AQ$46*100% -> 0 | BA54: =AZ54/$AZ$46*100% -> 0 | BF54: =BE54/$BE$46*100% -> 0 | BJ54: =BI54/$BI$46*100% -> 0 | BS54: =BR54/$BR$46*100% -> 0 | BT54: =BG54+BK54+BO54-BQ54 -> 0 | BU54: =BT54/$BT$46*100% -> 0 | BX54: =BW54/$BW$46*100% -> 0 | BZ54: =BY54/$BY$46*100% -> 0 | CF54: =CE54/$CE$46*100% -> 0 | CH54: =CG54/$CG$46*100% -> 0
B55: Salaries, wages and bonus | C55: =E55-'Apr-26'!E55 -> 58.084748 | D55: =C55/$C$46*100% -> 0.018592845 | E55: =SUMIF('05.conso TB'!A:A,'May-26'!B55,'05.conso TB'!R:R)/10^5 -> 118.54096 | F55: =E55/$E$46*100% -> 0.018346733 | G55: =I55-'Apr-26'!I55 -> 10.00502 | H55: =G55/$G$46*100% -> 0.0075327257 | I55: =SUMIF('05.conso TB'!A:A,'May-26'!B55,'05.conso TB'!S:S)/10^5 -> 185.38622 | J55: =I55/$I$46*100% -> 0.073872164 | K55: =M55-'Apr-26'!M55 -> 2.42838 | L55: =K55/$C$46*100% -> 0.00077732096 | M55: =SUMIF('05.conso TB'!A:A,'May-26'!B55,'05.conso TB'!T:T)/10^5 -> 4.85676 | N55: =M55/$C$46*100% -> 0.0015546419 | O55: =Q55-'Apr-26'!Q55 -> 10.82961 | P55: =O55/$O$46*100% -> 0.0087191139 | Q55: =SUMIF('05.conso TB'!A:A,'May-26'!B55,'05.conso TB'!U:U)/10^5 -> 21.80721 | R55: =Q55/$Q$46*100% -> 0.010008613 | S55: =U55-'Apr-26'!U55 -> 14.85721 | T55: =S55/$S$46*100% -> -632.68477 | U55: =SUMIF('05.conso TB'!A:A,'May-26'!B55,'05.conso TB'!V:V)/10^5 -> 39.85721 | V55: =U55/$U$46*100% -> 0.8177085 | W55: =Y55-'Apr-26'!Y55 -> 1.01636 | X55: =W55/$W$46*100% -> 0.00027327762 | Y55: =SUMIF('05.conso TB'!A:A,'May-26'!B55,'05.conso TB'!G:G)/10^5 -> 1.01636 | Z55: =Y55/$Y$46*100% -> 0.00026791337 | AB55: =AD55-'Apr-26'!AD55 -> 97.221328 | AC55: =AB55/$AB$46*100% -> 0.010543019 | AD55: =E55+I55+M55+Q55+U55+Y55 -> 371.46472 | AE55: =AD55/$AD$46*100% -> 0.025701632 | AG55: =AI55-'Apr-26'!AI55 -> 51.75408 | AH55: =AG55/$AG$46*100% -> 0.14082398 | AI55: =SUMIF('05.conso TB'!A:A,'May-26'!B55,'05.conso TB'!Q:Q)/10^5 -> 95.76619 | AJ55: =AI55/$AI$46*100% -> 0.12976402 | AL55: =AN55-'Apr-26'!AN55 -> 33.102206 | AM55: =AL55/$AL$46*100% -> 0.027952328 | AN55: =SUMIF('05.conso TB'!A:A,'May-26'!B55,'05.conso TB'!W:W)/10^5 -> 61.517033 | AO55: =AN55/$AN$46*100% -> 0.026489153 | AQ55: =AS55-'Apr-26'!AS55 -> 288.57818 | AR55: =AQ55/$AQ$46*100% -> 0.14154128 | AS55: =SUMIF('05.conso TB'!A:A,'May-26'!B55,'05.conso TB'!M:M)/10^5 -> 442.56966 | AT55: =AS55/$AS$46*100% -> 0.11434314 | AU55: =AW55-'Apr-26'!AW55 -> 1.49999 | AV55: =AU55/$C$46*100% -> 0.00048014465 | AW55: =SUMIF('05.conso TB'!A:A,'May-26'!B55,'05.conso TB'!P:P)/10^5 -> 2.53709 | AX55: =AW55/$AW$46*100% -> 0.0013734545 | AZ55: =BB55-'Apr-26'!BB55 -> 290.07817 | BA55: =AZ55/$AZ$46*100% -> 0.095571176 | BB55: =AS55+AW55 -> 445.10675 | BC55: =BB55/$BB$46*100% -> 0.077846184 | BE55: =BG55-'Apr-26'!BG55 -> 43.63635 | BF55: =BE55/$BE$46*100% -> 0.015612721 | BG55: =SUMIF('05.conso TB'!A:A,'May-26'!B55,'05.conso TB'!H:H)/10^5 -> 104.00973 | BH55: =BG55/$BG$46*100% -> 0.022133783 | BI55: =BK55-'Apr-26'!BK55 -> 4.17755 | BJ55: =BI55/$BI$46*100% -> 0.21736433 | BK55: =SUMIF('05.conso TB'!A:A,'May-26'!B55,'05.conso TB'!I:I)/10^5 -> 13.17618 | BL55: =BK55/$BK$46*100% -> 0.34135426 | BM55: =BO55-'Apr-26'!BO55 -> 0 | BN55: =BM55/$C$46*100% -> 0 | BO55: =SUMIF('05.conso TB'!A:A,'May-26'!B55,'05.conso TB'!J:J)/10^5 -> 0 | BP55: =BO55/$C$46*100% -> 0 | BR55: =BT55-'Apr-26'!BT55 -> 47.8139 | BS55: =BR55/$BR$46*100% -> 0.01808053 | BT55: =BG55+BK55+BO55-BQ55 -> 117.18591 | BU55: =BT55/$BT$46*100% -> 0.026112415 | BW55: =BY55-'Apr-26'!BY55 -> 0.4267 | BX55: =BW55/$BW$46*100% -> 0.00094292583 | BY55: =SUMIF('05.conso TB'!A:A,'May-26'!B55,'05.conso TB'!L:L)/10^5 -> 0.8534 | BZ55: =BY55/$BY$46*100% -> 0.00039493102 | CB55: =CD55-'Apr-26'!CD55 -> 0 | CE55: =AB55+AG55+AL55+AZ55+BR55+BW55 -> 520.39638 | CF55: =CE55/$CE$46*100% -> 0.030782903 | CG55: =AD55+AI55+AN55+BB55+BT55+BY55 -> 1091.894 | CH55: =CG55/$CG$46*100% -> 0.089283596
B56: Contribution to provident and other funds | C56: =E56-'Apr-26'!E56 -> 1.63034 | D56: =C56/$C$46*100% -> 0.0005218695 | E56: =SUMIF('05.conso TB'!A:A,'May-26'!B56,'05.conso TB'!R:R)/10^5 -> 3.44199 | F56: =E56/$E$46*100% -> 0.00053272111 | G56: =I56-'Apr-26'!I56 -> 3.00205 | H56: =G56/$G$46*100% -> 0.0022602273 | I56: =SUMIF('05.conso TB'!A:A,'May-26'!B56,'05.conso TB'!S:S)/10^5 -> 6.37132 | J56: =I56/$I$46*100% -> 0.0025388251 | K56: =M56-'Apr-26'!M56 -> 0 | L56: =K56/$C$46*100% -> 0 | M56: =SUMIF('05.conso TB'!A:A,'May-26'!B56,'05.conso TB'!T:T)/10^5 -> 0 | N56: =M56/$C$46*100% -> 0 | O56: =Q56-'Apr-26'!Q56 -> 0.33466 | P56: =O56/$O$46*100% -> 0.00026944079 | Q56: =SUMIF('05.conso TB'!A:A,'May-26'!B56,'05.conso TB'!U:U)/10^5 -> 0.68871 | R56: =Q56/$Q$46*100% -> 0.00031608958 | S56: =U56-'Apr-26'!U56 -> 0 | T56: =S56/$S$46*100% -> 0 | U56: =SUMIF('05.conso TB'!A:A,'May-26'!B56,'05.conso TB'!V:V)/10^5 -> 0.13672 | V56: =U56/$U$46*100% -> 0.0028049406 | W56: =Y56-'Apr-26'!Y56 -> 0 | X56: =W56/$W$46*100% -> 0 | Y56: =SUMIF('05.conso TB'!A:A,'May-26'!B56,'05.conso TB'!G:G)/10^5 -> 0 | Z56: =Y56/$Y$46*100% -> 0 | AB56: =AD56-'Apr-26'!AD56 -> 4.96705 | AC56: =AB56/$AB$46*100% -> 0.00053864418 | AD56: =E56+I56+M56+Q56+U56+Y56 -> 10.63874 | AE56: =AD56/$AD$46*100% -> 0.00073609409 | AG56: =AI56-'Apr-26'!AI56 -> 1.59471 | AH56: =AG56/$AG$46*100% -> 0.0043392408 | AI56: =SUMIF('05.conso TB'!A:A,'May-26'!B56,'05.conso TB'!Q:Q)/10^5 -> 2.99837 | AJ56: =AI56/$AI$46*100% -> 0.0040628173 | AL56: =AN56-'Apr-26'!AN56 -> 1.41856 | AM56: =AL56/$AL$46*100% -> 0.0011978674 | AN56: =SUMIF('05.conso TB'!A:A,'May-26'!B56,'05.conso TB'!W:W)/10^5 -> 1.41856 | AO56: =AN56/$AN$46*100% -> 0.00061083005 | AQ56: =AS56-'Apr-26'!AS56 -> -1.89948 | AR56: =AQ56/$AQ$46*100% -> -0.00093165337 | AS56: =SUMIF('05.conso TB'!A:A,'May-26'!B56,'05.conso TB'!M:M)/10^5 -> 8.23842 | AT56: =AS56/$AS$46*100% -> 0.002128494 | AU56: =AW56-'Apr-26'!AW56 -> 0 | AV56: =AU56/$C$46*100% -> 0 | AW56: =SUMIF('05.conso TB'!A:A,'May-26'!B56,'05.conso TB'!P:P)/10^5 -> 0 | AX56: =AW56/$AW$46*100% -> 0 | AZ56: =BB56-'Apr-26'!BB56 -> -1.89948 | BA56: =AZ56/$AZ$46*100% -> -0.00062581593 | BB56: =AS56+AW56 -> 8.23842 | BC56: =BB56/$BB$46*100% -> 0.0014408444 | BE56: =BG56-'Apr-26'!BG56 -> 1.4254631 | BF56: =BE56/$BE$46*100% -> 0.00051001878 | BG56: =SUMIF('05.conso TB'!A:A,'May-26'!B56,'05.conso TB'!H:H)/10^5 -> 2.9043131 | BH56: =BG56/$BG$46*100% -> 0.00061805215 | BI56: =BK56-'Apr-26'!BK56 -> 0.21661 | BJ56: =BI56/$BI$46*100% -> 0.011270551 | BK56: =SUMIF('05.conso TB'!A:A,'May-26'!B56,'05.conso TB'!I:I)/10^5 -> 0.30161 | BL56: =BK56/$BK$46*100% -> 0.0078137867 | BM56: =BO56-'Apr-26'!BO56 -> 0 | BN56: =BM56/$C$46*100% -> 0 | BO56: =SUMIF('05.conso TB'!A:A,'May-26'!B56,'05.conso TB'!J:J)/10^5 -> 0 | BP56: =BO56/$C$46*100% -> 0 | BR56: =BT56-'Apr-26'!BT56 -> 1.6420731 | BS56: =BR56/$BR$46*100% -> 0.00062093978 | BT56: =BG56+BK56+BO56-BQ56 -> 3.2059231 | BU56: =BT56/$BT$46*100% -> 0.00071437252 | BW56: =BY56-'Apr-26'!BY56 -> 0 | BX56: =BW56/$BW$46*100% -> 0 | BY56: =SUMIF('05.conso TB'!A:A,'May-26'!B56,'05.conso TB'!L:L)/10^5 -> 0 | BZ56: =BY56/$BY$46*100% -> 0 | CB56: =CD56-'Apr-26'!CD56 -> 0 | CE56: =AB56+AG56+AL56+AZ56+BR56+BW56 -> 7.7229131 | CF56: =CE56/$CE$46*100% -> 0.00045683194 | CG56: =AD56+AI56+AN56+BB56+BT56+BY56 -> 26.500013 | CH56: =CG56/$CG$46*100% -> 0.0021668921
B57: Gratuity Expenses | C57: =E57-'Apr-26'!E57 -> 0 | D57: =C57/$C$46*100% -> 0 | E57: =SUMIF('05.conso TB'!A:A,'May-26'!B57,'05.conso TB'!R:R)/10^5 -> 0 | F57: =E57/$E$46*100% -> 0 | G57: =I57-'Apr-26'!I57 -> 0 | H57: =G57/$G$46*100% -> 0 | I57: =SUMIF('05.conso TB'!A:A,'May-26'!B57,'05.conso TB'!S:S)/10^5 -> 0 | J57: =I57/$I$46*100% -> 0 | K57: =M57-'Apr-26'!M57 -> 0 | L57: =K57/$C$46*100% -> 0 | M57: =SUMIF('05.conso TB'!A:A,'May-26'!B57,'05.conso TB'!T:T)/10^5 -> 0 | N57: =M57/$C$46*100% -> 0 | O57: =Q57-'Apr-26'!Q57 -> 0 | P57: =O57/$O$46*100% -> 0 | Q57: =SUMIF('05.conso TB'!A:A,'May-26'!B57,'05.conso TB'!U:U)/10^5 -> 0 | R57: =Q57/$Q$46*100% -> 0 | S57: =U57-'Apr-26'!U57 -> 0 | T57: =S57/$S$46*100% -> 0 | U57: =SUMIF('05.conso TB'!A:A,'May-26'!B57,'05.conso TB'!V:V)/10^5 -> 0 | V57: =U57/$U$46*100% -> 0 | W57: =Y57-'Apr-26'!Y57 -> 0 | X57: =W57/$W$46*100% -> 0 | Y57: =SUMIF('05.conso TB'!A:A,'May-26'!B57,'05.conso TB'!G:G)/10^5 -> 0 | Z57: =Y57/$Y$46*100% -> 0 | AB57: =AD57-'Apr-26'!AD57 -> 0 | AC57: =AB57/$AB$46*100% -> 0 | AD57: =E57+I57+M57+Q57+U57+Y57 -> 0 | AE57: =AD57/$AD$46*100% -> 0 | AG57: =AI57-'Apr-26'!AI57 -> 0 | AH57: =AG57/$AG$46*100% -> 0 | AI57: =SUMIF('05.conso TB'!A:A,'May-26'!B57,'05.conso TB'!Q:Q)/10^5 -> 1.29974 | AJ57: =AI57/$AI$46*100% -> 0.0017611589 | AL57: =AN57-'Apr-26'!AN57 -> 0.50261 | AM57: =AL57/$AL$46*100% -> 0.00042441641 | AN57: =SUMIF('05.conso TB'!A:A,'May-26'!B57,'05.conso TB'!W:W)/10^5 -> 0.50261 | AO57: =AN57/$AN$46*100% -> 0.0002164232 | AQ57: =AS57-'Apr-26'!AS57 -> 0 | AR57: =AQ57/$AQ$46*100% -> 0 | AS57: =SUMIF('05.conso TB'!A:A,'May-26'!B57,'05.conso TB'!M:M)/10^5 -> 0 | AT57: =AS57/$AS$46*100% -> 0 | AU57: =AW57-'Apr-26'!AW57 -> 0 | AV57: =AU57/$C$46*100% -> 0 | AW57: =SUMIF('05.conso TB'!A:A,'May-26'!B57,'05.conso TB'!P:P)/10^5 -> 0 | AX57: =AW57/$AW$46*100% -> 0 | AZ57: =BB57-'Apr-26'!BB57 -> 0 | BA57: =AZ57/$AZ$46*100% -> 0 | BB57: =AS57+AW57 -> 0 | BC57: =BB57/$BB$46*100% -> 0 | BE57: =BG57-'Apr-26'!BG57 -> 0 | BF57: =BE57/$BE$46*100% -> 0 | BG57: =SUMIF('05.conso TB'!A:A,'May-26'!B57,'05.conso TB'!H:H)/10^5 -> 0 | BH57: =BG57/$BG$46*100% -> 0 | BI57: =BK57-'Apr-26'!BK57 -> 0 | BJ57: =BI57/$BI$46*100% -> 0 | BK57: =SUMIF('05.conso TB'!A:A,'May-26'!B57,'05.conso TB'!I:I)/10^5 -> 0 | BL57: =BK57/$BK$46*100% -> 0 | BM57: =BO57-'Apr-26'!BO57 -> 0 | BN57: =BM57/$C$46*100% -> 0 | BO57: =SUMIF('05.conso TB'!A:A,'May-26'!B57,'05.conso TB'!J:J)/10^5 -> 0 | BP57: =BO57/$C$46*100% -> 0 | BR57: =BT57-'Apr-26'!BT57 -> 0 | BS57: =BR57/$BR$46*100% -> 0 | BT57: =BG57+BK57+BO57-BQ57 -> 0 | BU57: =BT57/$BT$46*100% -> 0 | BW57: =BY57-'Apr-26'!BY57 -> 0 | BX57: =BW57/$BW$46*100% -> 0 | BY57: =SUMIF('05.conso TB'!A:A,'May-26'!B57,'05.conso TB'!L:L)/10^5 -> 0 | BZ57: =BY57/$BY$46*100% -> 0 | CB57: =CD57-'Apr-26'!CD57 -> 0 | CE57: =AB57+AG57+AL57+AZ57+BR57+BW57 -> 0.50261 | CF57: =CE57/$CE$46*100% -> 2.9730789e-05 | CG57: =AD57+AI57+AN57+BB57+BT57+BY57 -> 1.80235 | CH57: =CG57/$CG$46*100% -> 0.00014737721
B58: Staff welfare expenses | C58: =E58-'Apr-26'!E58 -> 1.34156 | D58: =C58/$C$46*100% -> 0.00042943144 | E58: =SUMIF('05.conso TB'!A:A,'May-26'!B58,'05.conso TB'!R:R)/10^5 -> 5.02186 | F58: =E58/$E$46*100% -> 0.00077723957 | G58: =I58-'Apr-26'!I58 -> 2.40817 | H58: =G58/$G$46*100% -> 0.0018130982 | I58: =SUMIF('05.conso TB'!A:A,'May-26'!B58,'05.conso TB'!S:S)/10^5 -> 4.58363 | J58: =I58/$I$46*100% -> 0.0018264716 | K58: =M58-'Apr-26'!M58 -> 0 | L58: =K58/$C$46*100% -> 0 | M58: =SUMIF('05.conso TB'!A:A,'May-26'!B58,'05.conso TB'!T:T)/10^5 -> 0 | N58: =M58/$C$46*100% -> 0 | O58: =Q58-'Apr-26'!Q58 -> 0.31197 | P58: =O58/$O$46*100% -> 0.00025117266 | Q58: =SUMIF('05.conso TB'!A:A,'May-26'!B58,'05.conso TB'!U:U)/10^5 -> 0.77927 | R58: =Q58/$Q$46*100% -> 0.0003576529 | S58: =U58-'Apr-26'!U58 -> 0.40752 | T58: =S58/$S$46*100% -> -17.353978 | U58: =SUMIF('05.conso TB'!A:A,'May-26'!B58,'05.conso TB'!V:V)/10^5 -> 0.57878 | V58: =U58/$U$46*100% -> 0.011874221 | W58: =Y58-'Apr-26'!Y58 -> 0.34286 | X58: =W58/$W$46*100% -> 9.2187772e-05 | Y58: =SUMIF('05.conso TB'!A:A,'May-26'!B58,'05.conso TB'!G:G)/10^5 -> 0.73405 | Z58: =Y58/$Y$46*100% -> 0.00019349621 | AB58: =AD58-'Apr-26'!AD58 -> 4.81208 | AC58: =AB58/$AB$46*100% -> 0.00052183869 | AD58: =E58+I58+M58+Q58+U58+Y58 -> 11.69759 | AE58: =AD58/$AD$46*100% -> 0.00080935589 | AG58: =AI58-'Apr-26'!AI58 -> 1.69658 | AH58: =AG58/$AG$46*100% -> 0.0046164313 | AI58: =SUMIF('05.conso TB'!A:A,'May-26'!B58,'05.conso TB'!Q:Q)/10^5 -> 2.99037 | AJ58: =AI58/$AI$46*100% -> 0.0040519772 | AL58: =AN58-'Apr-26'!AN58 -> 5.7137 | AM58: =AL58/$AL$46*100% -> 0.0048247907 | AN58: =SUMIF('05.conso TB'!A:A,'May-26'!B58,'05.conso TB'!W:W)/10^5 -> 6.09541 | AO58: =AN58/$AN$46*100% -> 0.0026246754 | AQ58: =AS58-'Apr-26'!AS58 -> 3.4243424 | AR58: =AQ58/$AQ$46*100% -> 0.001679565 | AS58: =SUMIF('05.conso TB'!A:A,'May-26'!B58,'05.conso TB'!M:M)/10^5 -> 6.0554124 | AT58: =AS58/$AS$46*100% -> 0.0015644879 | AU58: =AW58-'Apr-26'!AW58 -> 0 | AV58: =AU58/$C$46*100% -> 0 | AW58: =SUMIF('05.conso TB'!A:A,'May-26'!B58,'05.conso TB'!P:P)/10^5 -> 0 | AX58: =AW58/$AW$46*100% -> 0 | AZ58: =BB58-'Apr-26'!BB58 -> 3.4243424 | BA58: =AZ58/$AZ$46*100% -> 0.0011282077 | BB58: =AS58+AW58 -> 6.0554124 | BC58: =BB58/$BB$46*100% -> 0.001059051 | BE58: =BG58-'Apr-26'!BG58 -> 0.25688 | BF58: =BE58/$BE$46*100% -> 9.1909516e-05 | BG58: =SUMIF('05.conso TB'!A:A,'May-26'!B58,'05.conso TB'!H:H)/10^5 -> 0.36718 | BH58: =BG58/$BG$46*100% -> 7.8137714e-05 | BI58: =BK58-'Apr-26'!BK58 -> -0.04005 | BJ58: =BI58/$BI$46*100% -> -0.0020838629 | BK58: =SUMIF('05.conso TB'!A:A,'May-26'!B58,'05.conso TB'!I:I)/10^5 -> -0.08865 | BL58: =BK58/$BK$46*100% -> -0.0022966486 | BM58: =BO58-'Apr-26'!BO58 -> 0 | BN58: =BM58/$C$46*100% -> 0 | BO58: =SUMIF('05.conso TB'!A:A,'May-26'!B58,'05.conso TB'!J:J)/10^5 -> 0 | BP58: =BO58/$C$46*100% -> 0 | BR58: =BT58-'Apr-26'!BT58 -> 0.21683 | BS58: =BR58/$BR$46*100% -> 8.1992923e-05 | BT58: =BG58+BK58+BO58-BQ58 -> 0.27853 | BU58: =BT58/$BT$46*100% -> 6.2064551e-05 | BW58: =BY58-'Apr-26'!BY58 -> 0 | BX58: =BW58/$BW$46*100% -> 0 | BY58: =SUMIF('05.conso TB'!A:A,'May-26'!B58,'05.conso TB'!L:L)/10^5 -> 0 | BZ58: =BY58/$BY$46*100% -> 0 | CB58: =CD58-'Apr-26'!CD58 -> 0 | CE58: =AB58+AG58+AL58+AZ58+BR58+BW58 -> 15.863532 | CF58: =CE58/$CE$46*100% -> 0.00093837237 | CG58: =AD58+AI58+AN58+BB58+BT58+BY58 -> 27.117312 | CH58: =CG58/$CG$46*100% -> 0.0022173683
B59: Labour charges | C59: =E59-'Apr-26'!E59 -> 71.96571 | D59: =C59/$C$46*100% -> 0.023036121 | E59: =SUMIF('05.conso TB'!A:A,'May-26'!B59,'05.conso TB'!R:R)/10^5 -> 134.82776 | F59: =E59/$E$46*100% -> 0.020867461 | G59: =I59-'Apr-26'!I59 -> 147.84965 | H59: =G59/$G$46*100% -> 0.1113152 | I59: =SUMIF('05.conso TB'!A:A,'May-26'!B59,'05.conso TB'!S:S)/10^5 -> 149.33898 | J59: =I59/$I$46*100% -> 0.059508164 | K59: =M59-'Apr-26'!M59 -> 0 | L59: =K59/$C$46*100% -> 0 | M59: =SUMIF('05.conso TB'!A:A,'May-26'!B59,'05.conso TB'!T:T)/10^5 -> 0 | N59: =M59/$C$46*100% -> 0 | O59: =Q59-'Apr-26'!Q59 -> 71.423061 | P59: =O59/$O$46*100% -> 0.057503992 | Q59: =SUMIF('05.conso TB'!A:A,'May-26'!B59,'05.conso TB'!U:U)/10^5 -> 143.48536 | R59: =Q59/$Q$46*100% -> 0.065853883 | S59: =U59-'Apr-26'!U59 -> 0 | T59: =S59/$S$46*100% -> 0 | U59: =SUMIF('05.conso TB'!A:A,'May-26'!B59,'05.conso TB'!V:V)/10^5 -> 0 | V59: =U59/$U$46*100% -> 0 | W59: =Y59-'Apr-26'!Y59 -> 0 | X59: =W59/$W$46*100% -> 0 | Y59: =SUMIF('05.conso TB'!A:A,'May-26'!B59,'05.conso TB'!G:G)/10^5 -> 0 | Z59: =Y59/$Y$46*100% -> 0 | AB59: =AD59-'Apr-26'!AD59 -> 291.23842 | AC59: =AB59/$AB$46*100% -> 0.031582907 | AD59: =E59+I59+M59+Q59+U59+Y59 -> 427.6521 | AE59: =AD59/$AD$46*100% -> 0.029589235 | AG59: =AI59-'Apr-26'!AI59 -> 99.18793 | AH59: =AG59/$AG$46*100% -> 0.26989253 | AI59: =SUMIF('05.conso TB'!A:A,'May-26'!B59,'05.conso TB'!Q:Q)/10^5 -> 191.72584 | AJ59: =AI59/$AI$46*100% -> 0.25979017 | AL59: =AN59-'Apr-26'!AN59 -> 67.486146 | AM59: =AL59/$AL$46*100% -> 0.056986984 | AN59: =SUMIF('05.conso TB'!A:A,'May-26'!B59,'05.conso TB'!W:W)/10^5 -> 144.09383 | AO59: =AN59/$AN$46*100% -> 0.06204661 | AQ59: =AS59-'Apr-26'!AS59 -> 50.873384 | AR59: =AQ59/$AQ$46*100% -> 0.024952281 | AS59: =SUMIF('05.conso TB'!A:A,'May-26'!B59,'05.conso TB'!M:M)/10^5 -> 97.717284 | AT59: =AS59/$AS$46*100% -> 0.025246425 | AU59: =AW59-'Apr-26'!AW59 -> 0 | AV59: =AU59/$C$46*100% -> 0 | AW59: =SUMIF('05.conso TB'!A:A,'May-26'!B59,'05.conso TB'!P:P)/10^5 -> 0 | AX59: =AW59/$AW$46*100% -> 0 | AZ59: =BB59-'Apr-26'!BB59 -> 50.873384 | BA59: =AZ59/$AZ$46*100% -> 0.0167611 | BB59: =AS59+AW59 -> 97.717284 | BC59: =BB59/$BB$46*100% -> 0.017090097 | BE59: =BG59-'Apr-26'!BG59 -> 25.812807 | BF59: =BE59/$BE$46*100% -> 0.0092356065 | BG59: =SUMIF('05.conso TB'!A:A,'May-26'!B59,'05.conso TB'!H:H)/10^5 -> 52.931267 | BH59: =BG59/$BG$46*100% -> 0.011264035 | BI59: =BK59-'Apr-26'!BK59 -> 0.88628 | BJ59: =BI59/$BI$46*100% -> 0.046114508 | BK59: =SUMIF('05.conso TB'!A:A,'May-26'!B59,'05.conso TB'!I:I)/10^5 -> 1.43168 | BL59: =BK59/$BK$46*100% -> 0.037090422 | BM59: =BO59-'Apr-26'!BO59 -> 0 | BN59: =BM59/$C$46*100% -> 0 | BO59: =SUMIF('05.conso TB'!A:A,'May-26'!B59,'05.conso TB'!J:J)/10^5 -> 0 | BP59: =BO59/$C$46*100% -> 0 | BR59: =BT59-'Apr-26'!BT59 -> 26.699087 | BS59: =BR59/$BR$46*100% -> 0.010096095 | BT59: =BG59+BK59+BO59-BQ59 -> 54.362947 | BU59: =BT59/$BT$46*100% -> 0.012113639 | BW59: =BY59-'Apr-26'!BY59 -> 0 | BX59: =BW59/$BW$46*100% -> 0 | BY59: =SUMIF('05.conso TB'!A:A,'May-26'!B59,'05.conso TB'!L:L)/10^5 -> 0 | BZ59: =BY59/$BY$46*100% -> 0 | CB59: =CD59-'Apr-26'!CD59 -> 0 | CE59: =AB59+AG59+AL59+AZ59+BR59+BW59 -> 535.48497 | CF59: =CE59/$CE$46*100% -> 0.031675436 | CG59: =AD59+AI59+AN59+BB59+BT59+BY59 -> 915.552 | CH59: =CG59/$CG$46*100% -> 0.074864203
B60: Total Employee benefit expenses | C60: =SUM(C55:C59) -> 133.02236 | D60: =SUM(D55:D59) -> 0.042580266 | E60: =SUM(E55:E59) -> 261.83257 | F60: =E60/$E$46*100% -> 0.040524155 | G60: =SUM(G55:G59) -> 163.26489 | H60: =G60/$G$46*100% -> 0.12292125 | I60: =SUM(I55:I59) -> 345.68015 | J60: =I60/$I$46*100% -> 0.13774562 | K60: =SUM(K55:K59) -> 2.42838 | L60: =SUM(L55:L59) -> 0.00077732096 | M60: =SUM(M55:M59) -> 4.85676 | N60: =SUM(N55:N59) -> 0.0015546419 | O60: =SUM(O55:O59) -> 82.899301 | P60: =O60/$O$46*100% -> 0.066743719 | Q60: =SUM(Q55:Q59) -> 166.76055 | R60: =Q60/$Q$46*100% -> 0.076536239 | S60: =SUM(S55:S59) -> 15.26473 | T60: =S60/$S$46*100% -> -650.03875 | U60: =SUM(U55:U59) -> 40.57271 | V60: =U60/$U$46*100% -> 0.83238766 | W60: =SUM(W55:W59) -> 1.35922 | X60: =W60/$W$46*100% -> 0.00036546539 | Y60: =SUM(Y55:Y59) -> 1.75041 | Z60: =Y60/$Y$46*100% -> 0.00046140958 | AA60: =SUM(AA55:AA59) -> 0 | AB60: =SUM(AB55:AB59) -> 398.23888 | AC60: =AB60/$AB$46*100% -> 0.043186409 | AD60: =SUM(AD55:AD59) -> 821.45315 | AE60: =AD60/$AD$46*100% -> 0.056836318 | AF60: =AG60/$AG$1*10^5 -> 41.964933 | AG60: =SUM(AG55:AG59) -> 154.2333 | AH60: =AG60/$AG$46*100% -> 0.41967218 | AI60: =SUM(AI55:AI59) -> 294.78051 | AJ60: =SUM(AJ55:AJ59) -> 0.39943014 | AK60: =AL60/$AL$1*10^5 -> 24.505738 | AL60: =SUM(AL55:AL59) -> 108.22322 | AM60: =AL60/$AL$46*100% -> 0.091386387 | AN60: =SUM(AN55:AN59) -> 213.62744 | AO60: =SUM(AO55:AO59) -> 0.091987691 | AP60: =AQ60/$AQ$1*10^5 -> 57.112587 | AQ60: =SUM(AQ55:AQ59) -> 340.97642 | AR60: =AQ60/$AQ$46*100% -> 0.16724147 | AS60: =SUM(AS55:AS59) -> 554.58077 | AT60: =SUM(AT55:AT59) -> 0.14328255 | AU60: =SUM(AU55:AU59) -> 1.49999 | AV60: =SUM(AV55:AV59) -> 0.00048014465 | AW60: =SUM(AW55:AW59) -> 2.53709 | AX60: =SUM(AX55:AX59) -> 0.0013734545 | AZ60: =SUM(AZ55:AZ59) -> 342.47641 | BA60: =AZ60/$AZ$46*100% -> 0.11283467 | BB60: =SUM(BB55:BB59) -> 557.11786 | BC60: =SUM(BC55:BC59) -> 0.097436176 | BE60: =SUM(BE55:BE59) -> 71.1315 | BF60: =BE60/$BE$46*100% -> 0.025450256 | BG60: =SUM(BG55:BG59) -> 160.21249 | BH60: =SUM(BH55:BH59) -> 0.034094008 | BI60: =SUM(BI55:BI59) -> 5.24039 | BJ60: =BI60/$BI$46*100% -> 0.27266553 | BK60: =SUM(BK55:BK59) -> 14.82082 | BL60: =SUM(BL55:BL59) -> 0.38396182 | BM60: =SUM(BM55:BM59) -> 0 | BN60: =SUM(BN55:BN59) -> 0 | BO60: =SUM(BO55:BO59) -> 0 | BP60: =SUM(BP55:BP59) -> 0 | BR60: =SUM(BR55:BR59) -> 76.37189 | BS60: =BR60/$BR$46*100% -> 0.028879558 | BT60: =BG60+BK60+BO60-BQ60 -> 175.03331 | BU60: =BT60/$BT$46*100% -> 0.039002491 | BW60: =SUM(BW55:BW59) -> 0.4267 | BX60: =BW60/$BW$46*100% -> 0.00094292583 | BY60: =SUM(BY55:BY59) -> 0.8534 | BZ60: =BY60/$BY$46*100% -> 0.00039493102 | CB60: =SUM(CB55:CB59) -> 0 | CE60: =SUM(CE55:CE59) -> 1079.9704 | CF60: =CE60/$CE$46*100% -> 0.063883274 | CG60: =SUM(CG55:CG59) -> 2062.8657 | CH60: =CG60/$CG$46*100% -> 0.16867944
B61: Manufacturing Expenses | F61: =E61/$E$46*100% -> 0 | H61: =G61/$G$46*100% -> 0 | J61: =I61/$I$46*100% -> 0 | P61: =O61/$O$46*100% -> 0 | R61: =Q61/$Q$46*100% -> 0 | T61: =S61/$S$46*100% -> 0 | V61: =U61/$U$46*100% -> 0 | X61: =W61/$W$46*100% -> 0 | Z61: =Y61/$Y$46*100% -> 0 | AC61: =AB61/$AB$46*100% -> 0 | AE61: =AD61/$AD$46*100% -> 0 | AH61: =AG61/$AG$46*100% -> 0 | AM61: =AL61/$AL$46*100% -> 0 | AR61: =AQ61/$AQ$46*100% -> 0 | BA61: =AZ61/$AZ$46*100% -> 0 | BF61: =BE61/$BE$46*100% -> 0 | BJ61: =BI61/$BI$46*100% -> 0 | BS61: =BR61/$BR$46*100% -> 0 | BT61: =BG61+BK61+BO61-BQ61 -> 0 | BU61: =BT61/$BT$46*100% -> 0 | BX61: =BW61/$BW$46*100% -> 0 | BZ61: =BY61/$BY$46*100% -> 0 | CF61: =CE61/$CE$46*100% -> 0 | CH61: =CG61/$CG$46*100% -> 0
B62: Power and fuel | C62: =E62-'Apr-26'!E62 -> 90.1595 | D62: =C62/$C$46*100% -> 0.028859927 | E62: =SUMIF('05.conso TB'!A:A,'May-26'!B62,'05.conso TB'!R:R)/10^5 -> 203.12544 | F62: =E62/$E$46*100% -> 0.03143798 | G62: =I62-'Apr-26'!I62 -> 36.01098 | H62: =G62/$G$46*100% -> 0.027112473 | I62: =SUMIF('05.conso TB'!A:A,'May-26'!B62,'05.conso TB'!S:S)/10^5 -> 81.62252 | J62: =I62/$I$46*100% -> 0.032524705 | K62: =M62-'Apr-26'!M62 -> 0 | L62: =K62/$C$46*100% -> 0 | M62: =SUMIF('05.conso TB'!A:A,'May-26'!B62,'05.conso TB'!T:T)/10^5 -> 0 | N62: =M62/$C$46*100% -> 0 | O62: =Q62-'Apr-26'!Q62 -> 3.7824078 | P62: =O62/$O$46*100% -> 0.0030452846 | Q62: =SUMIF('05.conso TB'!A:A,'May-26'!B62,'05.conso TB'!U:U)/10^5 -> 9.3234203 | R62: =Q62/$Q$46*100% -> 0.0042790667 | S62: =U62-'Apr-26'!U62 -> 0 | T62: =S62/$S$46*100% -> 0 | U62: =SUMIF('05.conso TB'!A:A,'May-26'!B62,'05.conso TB'!V:V)/10^5 -> 0 | V62: =U62/$U$46*100% -> 0 | W62: =Y62-'Apr-26'!Y62 -> 0.0406935 | X62: =W62/$W$46*100% -> 1.0941618e-05 | Y62: =SUMIF('05.conso TB'!A:A,'May-26'!B62,'05.conso TB'!G:G)/10^5 -> 0.2665446 | Z62: =Y62/$Y$46*100% -> 7.0261385e-05 | AB62: =AD62-'Apr-26'!AD62 -> 129.99358 | AC62: =AB62/$AB$46*100% -> 0.014096956 | AD62: =E62+I62+M62+Q62+U62+Y62 -> 294.33793 | AE62: =AD62/$AD$46*100% -> 0.020365232 | AF62: =AG62/$AG$1*10^5 -> 5.8536905 | AG62: =AI62-'Apr-26'!AI62 -> 21.51401 | AH62: =AG62/$AG$46*100% -> 0.058540092 | AI62: =SUMIF('05.conso TB'!A:A,'May-26'!B62,'05.conso TB'!Q:Q)/10^5 -> 41.82664 | AJ62: =AI62/$AI$46*100% -> 0.056675459 | AK62: =AL62/$AL$1*10^5 -> 4.2097649 | AL62: =AN62-'Apr-26'!AN62 -> 18.591332 | AM62: =AL62/$AL$46*100% -> 0.015698984 | AN62: =SUMIF('05.conso TB'!A:A,'May-26'!B62,'05.conso TB'!W:W)/10^5 -> 57.739351 | AO62: =AN62/$AN$46*100% -> 0.024862488 | AP62: =AQ62/$AQ$1*10^5 -> 8.8590612 | AQ62: =AS62-'Apr-26'!AS62 -> 52.89081 | AR62: =AQ62/$AQ$46*100% -> 0.025941785 | AS62: =SUMIF('05.conso TB'!A:A,'May-26'!B62,'05.conso TB'!M:M)/10^5 -> 88.65528 | AT62: =AS62/$AS$46*100% -> 0.022905148 | AU62: =AW62-'Apr-26'!AW62 -> 0 | AV62: =AU62/$C$46*100% -> 0 | AW62: =SUMIF('05.conso TB'!A:A,'May-26'!B62,'05.conso TB'!P:P)/10^5 -> 0.01498 | AX62: =AW62/$AW$46*100% -> 8.1094276e-06 | AZ62: =BB62-'Apr-26'!BB62 -> 52.89081 | BA62: =AZ62/$AZ$46*100% -> 0.017425775 | BB62: =AS62+AW62 -> 88.67026 | BC62: =BB62/$BB$46*100% -> 0.015507834 | BE62: =BG62-'Apr-26'!BG62 -> 30.330062 | BF62: =BE62/$BE$46*100% -> 0.010851843 | BG62: =SUMIF('05.conso TB'!A:A,'May-26'!B62,'05.conso TB'!H:H)/10^5 -> 115.02364 | BH62: =BG62/$BG$46*100% -> 0.024477597 | BI62: =BK62-'Apr-26'!BK62 -> 0 | BJ62: =BI62/$BI$46*100% -> 0 | BK62: =SUMIF('05.conso TB'!A:A,'May-26'!B62,'05.conso TB'!I:I)/10^5 -> 0 | BL62: =BK62/$BK$46*100% -> 0 | BM62: =BO62-'Apr-26'!BO62 -> 0 | BN62: =BM62/$C$46*100% -> 0 | BO62: =SUMIF('05.conso TB'!A:A,'May-26'!B62,'05.conso TB'!J:J)/10^5 -> 0 | BP62: =BO62/$C$46*100% -> 0 | BR62: =BT62-'Apr-26'!BT62 -> 30.330062 | BS62: =BR62/$BR$46*100% -> 0.011469125 | BT62: =BG62+BK62+BO62-BQ62 -> 115.02364 | BU62: =BT62/$BT$46*100% -> 0.025630598 | BW62: =BY62-'Apr-26'!BY62 -> 0 | BX62: =BW62/$BW$46*100% -> 0 | BY62: =SUMIF('05.conso TB'!A:A,'May-26'!B62,'05.conso TB'!L:L)/10^5 -> 0 | BZ62: =BY62/$BY$46*100% -> 0 | CB62: =CD62-'Apr-26'!CD62 -> 0 | CE62: =AB62+AG62+AL62+AZ62+BR62+BW62 -> 253.3198 | CF62: =CE62/$CE$46*100% -> 0.014984575 | CG62: =AD62+AI62+AN62+BB62+BT62+BY62 -> 597.59782 | CH62: =CG62/$CG$46*100% -> 0.048865258
B63: Jobwork charges | C63: =E63-'Apr-26'!E63 -> 124.13154 | D63: =C63/$C$46*100% -> 0.039734328 | E63: =SUMIF('05.conso TB'!A:A,'May-26'!B63,'05.conso TB'!R:R)/10^5 -> 245.2525 | F63: =E63/$E$46*100% -> 0.037958037 | G63: =I63-'Apr-26'!I63 -> 40.432061 | H63: =G63/$G$46*100% -> 0.030441081 | I63: =SUMIF('05.conso TB'!A:A,'May-26'!B63,'05.conso TB'!S:S)/10^5 -> 57.166916 | J63: =I63/$I$46*100% -> 0.022779707 | K63: =M63-'Apr-26'!M63 -> 0 | L63: =K63/$C$46*100% -> 0 | M63: =SUMIF('05.conso TB'!A:A,'May-26'!B63,'05.conso TB'!T:T)/10^5 -> 0 | N63: =M63/$C$46*100% -> 0 | O63: =Q63-'Apr-26'!Q63 -> 1.067995 | P63: =O63/$O$46*100% -> 0.00085986199 | Q63: =SUMIF('05.conso TB'!A:A,'May-26'!B63,'05.conso TB'!U:U)/10^5 -> 2.453055 | R63: =Q63/$Q$46*100% -> 0.0011258514 | S63: =U63-'Apr-26'!U63 -> 0 | T63: =S63/$S$46*100% -> 0 | U63: =SUMIF('05.conso TB'!A:A,'May-26'!B63,'05.conso TB'!V:V)/10^5 -> 0 | V63: =U63/$U$46*100% -> 0 | W63: =Y63-'Apr-26'!Y63 -> 0 | X63: =W63/$W$46*100% -> 0 | Y63: =SUMIF('05.conso TB'!A:A,'May-26'!B63,'05.conso TB'!G:G)/10^5 -> 0 | Z63: =Y63/$Y$46*100% -> 0 | AB63: =AD63-'Apr-26'!AD63 -> 165.63159 | AC63: =AB63/$AB$46*100% -> 0.017961666 | AD63: =E63+I63+M63+Q63+U63+Y63 -> 304.87247 | AE63: =AD63/$AD$46*100% -> 0.021094117 | AG63: =AI63-'Apr-26'!AI63 -> 0 | AH63: =AG63/$AG$46*100% -> 0 | AI63: =SUMIF('05.conso TB'!A:A,'May-26'!B63,'05.conso TB'!Q:Q)/10^5 -> 0.9017642 | AJ63: =AI63/$AI$46*100% -> 0.0012218983 | AL63: =AN63-'Apr-26'!AN63 -> 4.2795498 | AM63: =AL63/$AL$46*100% -> 0.0036137585 | AN63: =SUMIF('05.conso TB'!A:A,'May-26'!B63,'05.conso TB'!W:W)/10^5 -> 8.0672677 | AO63: =AN63/$AN$46*100% -> 0.0034737547 | AQ63: =AS63-'Apr-26'!AS63 -> 318.53976 | AR63: =AQ63/$AQ$46*100% -> 0.15623678 | AS63: =SUMIF('05.conso TB'!A:A,'May-26'!B63,'05.conso TB'!M:M)/10^5 -> 478.38761 | AT63: =AS63/$AS$46*100% -> 0.12359714 | AU63: =AW63-'Apr-26'!AW63 -> 275.56307 | AV63: =AU63/$C$46*100% -> 0.088207344 | AW63: =SUMIF('05.conso TB'!A:A,'May-26'!B63,'05.conso TB'!P:P)/10^5 -> 538.05598 | AX63: =AW63/$AW$46*100% -> 0.29127677 | AZ63: =BB63-'Apr-26'!BB63 -> 594.10283 | BA63: =AZ63/$AZ$46*100% -> 0.19573726 | BB63: =AS63+AW63 -> 1016.4436 | BC63: =BB63/$BB$46*100% -> 0.17776916 | BE63: =BG63-'Apr-26'!BG63 -> 227.08363 | BF63: =BE63/$BE$46*100% -> 0.081248623 | BG63: =SUMIF('05.conso TB'!A:A,'May-26'!B63,'05.conso TB'!H:H)/10^5 -> 251.80141 | BH63: =BG63/$BG$46*100% -> 0.053584581 | BI63: =BK63-'Apr-26'!BK63 -> 0.018636 | BJ63: =BI63/$BI$46*100% -> 0.00096965966 | BK63: =SUMIF('05.conso TB'!A:A,'May-26'!B63,'05.conso TB'!I:I)/10^5 -> 0.018636 | BL63: =BK63/$BK$46*100% -> 0.00048280139 | BM63: =BO63-'Apr-26'!BO63 -> 0 | BN63: =BM63/$C$46*100% -> 0 | BO63: =SUMIF('05.conso TB'!A:A,'May-26'!B63,'05.conso TB'!J:J)/10^5 -> 0 | BP63: =BO63/$C$46*100% -> 0 | BQ63: =BQ27 -> 0 | BR63: =BT63-'Apr-26'!BT63 -> 227.10226 | BS63: =BR63/$BR$46*100% -> 0.085877315 | BT63: =BG63+BK63+BO63-BQ63 -> 251.82004 | BU63: =BT63/$BT$46*100% -> 0.056112799 | BW63: =BY63-'Apr-26'!BY63 -> 0 | BX63: =BW63/$BW$46*100% -> 0 | BY63: =SUMIF('05.conso TB'!A:A,'May-26'!B63,'05.conso TB'!L:L)/10^5 -> 0 | BZ63: =BY63/$BY$46*100% -> 0 | CB63: =CC63-'Apr-26'!CC63 -> 848.4175 | CC63: =+CC28 -> 1375.3983 | CE63: =AB63+AG63+AL63+AZ63+BR63+BW63-CA63 -> 991.11623 | CF63: =CE63/$CE$46*100% -> 0.058627301 | CG63: =AD63+AI63+AN63+BB63+BT63+BY63-CC63 -> 206.70679 | CH63: =CG63/$CG$46*100% -> 0.016902305
B64: Other Manufacturing Expenses | C64: =E64-'Apr-26'!E64 -> 8.3444167 | D64: =C64/$C$46*100% -> 0.0026710358 | E64: =SUMIF('05.conso TB'!A:A,'May-26'!B64,'05.conso TB'!R:R)/10^5 -> 17.165475 | F64: =E64/$E$46*100% -> 0.002656722 | G64: =I64-'Apr-26'!I64 -> 7.9387644 | H64: =G64/$G$46*100% -> 0.005977053 | I64: =SUMIF('05.conso TB'!A:A,'May-26'!B64,'05.conso TB'!S:S)/10^5 -> 17.598175 | J64: =I64/$I$46*100% -> 0.0070124697 | K64: =M64-'Apr-26'!M64 -> 0.05021 | L64: =K64/$C$46*100% -> 1.6072149e-05 | M64: =SUMIF('05.conso TB'!A:A,'May-26'!B64,'05.conso TB'!T:T)/10^5 -> 0.12518 | N64: =M64/$C$46*100% -> 4.0069939e-05 | O64: =Q64-'Apr-26'!Q64 -> 4.93985 | P64: =O64/$O$46*100% -> 0.0039771621 | Q64: =SUMIF('05.conso TB'!A:A,'May-26'!B64,'05.conso TB'!U:U)/10^5 -> 10.11192 | R64: =Q64/$Q$46*100% -> 0.0046409557 | S64: =U64-'Apr-26'!U64 -> 3.2612004 | T64: =S64/$S$46*100% -> -138.87613 | U64: =SUMIF('05.conso TB'!A:A,'May-26'!B64,'05.conso TB'!V:V)/10^5 -> 3.2612004 | V64: =U64/$U$46*100% -> 0.066906622 | W64: =Y64-'Apr-26'!Y64 -> 0.001 | X64: =W64/$W$46*100% -> 2.6887876e-07 | Y64: =SUMIF('05.conso TB'!A:A,'May-26'!B64,'05.conso TB'!G:G)/10^5 -> 0.001 | Z64: =Y64/$Y$46*100% -> 2.6360086e-07 | AB64: =AD64-'Apr-26'!AD64 -> 24.535441 | AC64: =AB64/$AB$46*100% -> 0.0026607086 | AD64: =E64+I64+M64+Q64+U64+Y64 -> 48.26295 | AE64: =AD64/$AD$46*100% -> 0.003339312 | AG64: =AI64-'Apr-26'!AI64 -> 6.39723 | AH64: =AG64/$AG$46*100% -> 0.017407003 | AI64: =SUMIF('05.conso TB'!A:A,'May-26'!B64,'05.conso TB'!Q:Q)/10^5 -> 9.670185 | AJ64: =AI64/$AI$46*100% -> 0.013103184 | AL64: =AN64-'Apr-26'!AN64 -> 0.56282 | AM64: =AL64/$AL$46*100% -> 0.00047525924 | AN64: =SUMIF('05.conso TB'!A:A,'May-26'!B64,'05.conso TB'!W:W)/10^5 -> 1.4334931 | AO64: =AN64/$AN$46*100% -> 0.00061726022 | AQ64: =AS64-'Apr-26'!AS64 -> 6.2811964 | AR64: =AQ64/$AQ$46*100% -> 0.0030807894 | AS64: =SUMIF('05.conso TB'!A:A,'May-26'!B64,'05.conso TB'!M:M)/10^5 -> 30.024921 | AT64: =AS64/$AS$46*100% -> 0.007757296 | AU64: =AW64-'Apr-26'!AW64 -> -0.394 | AV64: =AU64/$C$46*100% -> -0.00012611884 | AW64: =SUMIF('05.conso TB'!A:A,'May-26'!B64,'05.conso TB'!P:P)/10^5 -> 3.24391 | AX64: =AW64/$AW$46*100% -> 0.0017560917 | AZ64: =BB64-'Apr-26'!BB64 -> 5.8871964 | BA64: =AZ64/$AZ$46*100% -> 0.0019396368 | BB64: =AS64+AW64 -> 33.268831 | BC64: =BB64/$BB$46*100% -> 0.0058184953 | BE64: =BG64-'Apr-26'!BG64 -> 0.826473 | BF64: =BE64/$BE$46*100% -> 0.00029570513 | BG64: =SUMIF('05.conso TB'!A:A,'May-26'!B64,'05.conso TB'!H:H)/10^5 -> 5.859821 | BH64: =BG64/$BG$46*100% -> 0.0012469988 | BI64: =BK64-'Apr-26'!BK64 -> 0.043 | BJ64: =BI64/$BI$46*100% -> 0.002237356 | BK64: =SUMIF('05.conso TB'!A:A,'May-26'!B64,'05.conso TB'!I:I)/10^5 -> 0.609 | BL64: =BK64/$BK$46*100% -> 0.015777315 | BM64: =BO64-'Apr-26'!BO64 -> 0 | BN64: =BM64/$C$46*100% -> 0 | BO64: =SUMIF('05.conso TB'!A:A,'May-26'!B64,'05.conso TB'!J:J)/10^5 -> 0 | BP64: =BO64/$C$46*100% -> 0 | BR64: =BT64-'Apr-26'!BT64 -> 0.869473 | BS64: =BR64/$BR$46*100% -> 0.00032878584 | BT64: =BG64+BK64+BO64-BQ64 -> 6.468821 | BU64: =BT64/$BT$46*100% -> 0.0014414407 | BW64: =BY64-'Apr-26'!BY64 -> 0 | BX64: =BW64/$BW$46*100% -> 0 | BY64: =SUMIF('05.conso TB'!A:A,'May-26'!B64,'05.conso TB'!L:L)/10^5 -> 0 | BZ64: =BY64/$BY$46*100% -> 0 | CB64: =CD64-'Apr-26'!CD64 -> 0 | CE64: =AB64+AG64+AL64+AZ64+BR64+BW64 -> 38.252161 | CF64: =CE64/$CE$46*100% -> 0.0022627225 | CG64: =AD64+AI64+AN64+BB64+BT64+BY64 -> 99.10428 | CH64: =CG64/$CG$46*100% -> 0.0081037046
B65: Total Manufacturing Expenses | C65: =SUM(C62:C64) -> 222.63546 | D65: =SUM(D62:D64) -> 0.071265291 | E65: =SUM(E62:E64) -> 465.54342 | F65: =E65/$E$46*100% -> 0.072052739 | G65: =SUM(G62:G64) -> 84.381805 | H65: =G65/$G$46*100% -> 0.063530607 | I65: =SUM(I62:I64) -> 156.38761 | J65: =I65/$I$46*100% -> 0.062316882 | K65: =SUM(K62:K64) -> 0.05021 | L65: =SUM(L62:L64) -> 1.6072149e-05 | M65: =SUM(M62:M64) -> 0.12518 | N65: =SUM(N62:N64) -> 4.0069939e-05 | O65: =SUM(O62:O64) -> 9.7902528 | P65: =O65/$O$46*100% -> 0.0078823087 | Q65: =SUM(Q62:Q64) -> 21.888395 | R65: =Q65/$Q$46*100% -> 0.010045874 | S65: =SUM(S62:S64) -> 3.2612004 | T65: =S65/$S$46*100% -> -138.87613 | U65: =SUM(U62:U64) -> 3.2612004 | V65: =U65/$U$46*100% -> 0.066906622 | W65: =SUM(W62:W64) -> 0.0416935 | X65: =W65/$W$46*100% -> 1.1210497e-05 | Y65: =SUM(Y62:Y64) -> 0.2675446 | Z65: =Y65/$Y$46*100% -> 7.0524986e-05 | AA65: =SUM(AA62:AA64) -> 0 | AB65: =SUM(AB62:AB64) -> 320.16062 | AC65: =AB65/$AB$46*100% -> 0.034719331 | AD65: =SUM(AD62:AD64) -> 647.47335 | AE65: =AD65/$AD$46*100% -> 0.044798661 | AF65: =AG65/$AG$1*10^5 -> 7.594296 | AG65: =SUM(AG62:AG64) -> 27.91124 | AH65: =AG65/$AG$46*100% -> 0.075947095 | AI65: =SUM(AI62:AI64) -> 52.398589 | AJ65: =SUM(AJ62:AJ64) -> 0.071000541 | AK65: =AL65/$AL$1*10^5 -> 5.3062565 | AL65: =SUM(AL62:AL64) -> 23.433702 | AM65: =AL65/$AL$46*100% -> 0.019788002 | AN65: =SUM(AN62:AN64) -> 67.240112 | AO65: =SUM(AO62:AO64) -> 0.028953503 | AP65: =AQ65/$AQ$1*10^5 -> 63.265653 | AQ65: =SUM(AQ62:AQ64) -> 377.71176 | AR65: =AQ65/$AQ$46*100% -> 0.18525935 | AS65: =SUM(AS62:AS64) -> 597.06781 | AT65: =SUM(AT62:AT64) -> 0.15425958 | AU65: =SUM(AU62:AU64) -> 275.16907 | AV65: =SUM(AV62:AV64) -> 0.088081226 | AW65: =SUM(AW62:AW64) -> 541.31487 | AX65: =SUM(AX62:AX64) -> 0.29304097 | AZ65: =SUM(AZ62:AZ64) -> 652.88083 | BA65: =AZ65/$AZ$46*100% -> 0.21510267 | BB65: =SUM(BB62:BB64) -> 1138.3827 | BC65: =SUM(BC62:BC64) -> 0.19909549 | BE65: =SUM(BE62:BE64) -> 258.24016 | BF65: =BE65/$BE$46*100% -> 0.09239617 | BG65: =SUM(BG62:BG64) -> 372.68486 | BH65: =SUM(BH62:BH64) -> 0.079309177 | BI65: =SUM(BI62:BI64) -> 0.061636 | BJ65: =BI65/$BI$46*100% -> 0.0032070156 | BK65: =SUM(BK62:BK64) -> 0.627636 | BL65: =SUM(BL62:BL64) -> 0.016260117 | BM65: =SUM(BM62:BM64) -> 0 | BN65: =SUM(BN62:BN64) -> 0 | BO65: =SUM(BO62:BO64) -> 0 | BP65: =SUM(BP62:BP64) -> 0 | BQ65: =BQ63 -> 0 | BR65: =SUM(BR62:BR64) -> 258.3018 | BS65: =BR65/$BR$46*100% -> 0.097675226 | BT65: =BG65+BK65+BO65-BQ65 -> 373.3125 | BU65: =BT65/$BT$46*100% -> 0.083184838 | BW65: =SUM(BW62:BW64) -> 0 | BX65: =BW65/$BW$46*100% -> 0 | BY65: =SUM(BY62:BY64) -> 0 | BZ65: =BY65/$BY$46*100% -> 0 | CB65: =SUM(CB62:CB64) -> 848.4175 | CC65: =SUM(CC62:CC64) -> 1375.3983 | CE65: =SUM(CE62:CE64) -> 1282.6882 | CF65: =CE65/$CE$46*100% -> 0.075874599 | CG65: =SUM(CG62:CG64) -> 903.40889 | CH65: =CG65/$CG$46*100% -> 0.073871268
B66: Selling and Distribution Expenses | F66: =E66/$E$46*100% -> 0 | H66: =G66/$G$46*100% -> 0 | I66: =SUMIF('05.conso TB'!A:A,'May-26'!B66,'05.conso TB'!S:S)/10^5 -> 0 | J66: =I66/$I$46*100% -> 0 | M66: =SUMIF('05.conso TB'!A:A,'May-26'!B66,'05.conso TB'!T:T)/10^5 -> 0 | P66: =O66/$O$46*100% -> 0 | R66: =Q66/$Q$46*100% -> 0 | T66: =S66/$S$46*100% -> 0 | V66: =U66/$U$46*100% -> 0 | X66: =W66/$W$46*100% -> 0 | Z66: =Y66/$Y$46*100% -> 0 | AC66: =AB66/$AB$46*100% -> 0 | AE66: =AD66/$AD$46*100% -> 0 | AH66: =AG66/$AG$46*100% -> 0 | AM66: =AL66/$AL$46*100% -> 0 | AR66: =AQ66/$AQ$46*100% -> 0 | BA66: =AZ66/$AZ$46*100% -> 0 | BF66: =BE66/$BE$46*100% -> 0 | BJ66: =BI66/$BI$46*100% -> 0 | BS66: =BR66/$BR$46*100% -> 0 | BT66: =BG66+BK66+BO66-BQ66 -> 0 | BU66: =BT66/$BT$46*100% -> 0 | BX66: =BW66/$BW$46*100% -> 0 | BZ66: =BY66/$BY$46*100% -> 0 | CF66: =CE66/$CE$46*100% -> 0 | CH66: =CG66/$CG$46*100% -> 0
B67: Advertising and sales promotion expense | C67: =E67-'Apr-26'!E67 -> 0 | D67: =C67/$C$46*100% -> 0 | E67: =SUMIF('05.conso TB'!A:A,'May-26'!B67,'05.conso TB'!R:R)/10^5 -> 0 | F67: =E67/$E$46*100% -> 0 | G67: =I67-'Apr-26'!I67 -> 0 | H67: =G67/$G$46*100% -> 0 | I67: =SUMIF('05.conso TB'!A:A,'May-26'!B67,'05.conso TB'!S:S)/10^5 -> 0 | J67: =I67/$I$46*100% -> 0 | K67: =M67-'Apr-26'!M67 -> 0 | L67: =K67/$C$46*100% -> 0 | M67: =SUMIF('05.conso TB'!A:A,'May-26'!B67,'05.conso TB'!T:T)/10^5 -> 0 | N67: =M67/$C$46*100% -> 0 | O67: =Q67-'Apr-26'!Q67 -> 0 | P67: =O67/$O$46*100% -> 0 | Q67: =SUMIF('05.conso TB'!A:A,'May-26'!B67,'05.conso TB'!U:U)/10^5 -> 0 | R67: =Q67/$Q$46*100% -> 0 | S67: =U67-'Apr-26'!U67 -> 0.05099 | T67: =S67/$S$46*100% -> -2.1713765 | U67: =SUMIF('05.conso TB'!A:A,'May-26'!B67,'05.conso TB'!V:V)/10^5 -> 0.37526 | V67: =U67/$U$46*100% -> 0.0076988151 | W67: =Y67-'Apr-26'!Y67 -> 0.06707 | X67: =W67/$W$46*100% -> 1.8033698e-05 | Y67: =SUMIF('05.conso TB'!A:A,'May-26'!B67,'05.conso TB'!G:G)/10^5 -> 0.38207 | Z67: =Y67/$Y$46*100% -> 0.00010071398 | AB67: =AD67-'Apr-26'!AD67 -> 0.11806 | AC67: =AB67/$AB$46*100% -> 1.2802837e-05 | AD67: =E67+I67+M67+Q67+U67+Y67 -> 0.75733 | AE67: =AD67/$AD$46*100% -> 5.2399639e-05 | AG67: =AI67-'Apr-26'!AI67 -> 0 | AH67: =AG67/$AG$46*100% -> 0 | AI67: =SUMIF('05.conso TB'!A:A,'May-26'!B67,'05.conso TB'!Q:Q)/10^5 -> 0 | AJ67: =AI67/$AI$46*100% -> 0 | AL67: =AN67-'Apr-26'!AN67 -> 0 | AM67: =AL67/$AL$46*100% -> 0 | AN67: =SUMIF('05.conso TB'!A:A,'May-26'!B67,'05.conso TB'!W:W)/10^5 -> 0 | AO67: =AN67/$AN$46*100% -> 0 | AQ67: =AS67-'Apr-26'!AS67 -> 0 | AR67: =AQ67/$AQ$46*100% -> 0 | AS67: =SUMIF('05.conso TB'!A:A,'May-26'!B67,'05.conso TB'!M:M)/10^5 -> 0.1607388 | AT67: =AS67/$AS$46*100% -> 4.1528784e-05 | AU67: =AW67-'Apr-26'!AW67 -> 0 | AV67: =AU67/$C$46*100% -> 0 | AW67: =SUMIF('05.conso TB'!A:A,'May-26'!B67,'05.conso TB'!P:P)/10^5 -> 0 | AX67: =AW67/$AW$46*100% -> 0 | AZ67: =BB67-'Apr-26'!BB67 -> 0 | BA67: =AZ67/$AZ$46*100% -> 0 | BB67: =AS67+AW67 -> 0.1607388 | BC67: =BB67/$BB$46*100% -> 2.8112138e-05 | BE67: =BG67-'Apr-26'!BG67 -> 26.293005 | BF67: =BE67/$BE$46*100% -> 0.0094074174 | BG67: =SUMIF('05.conso TB'!A:A,'May-26'!B67,'05.conso TB'!H:H)/10^5 -> 35.10816 | BH67: =BG67/$BG$46*100% -> 0.0074711896 | BI67: =BK67-'Apr-26'!BK67 -> 0 | BJ67: =BI67/$BI$46*100% -> 0 | BK67: =SUMIF('05.conso TB'!A:A,'May-26'!B67,'05.conso TB'!I:I)/10^5 -> 0 | BL67: =BK67/$BK$46*100% -> 0 | BM67: =BO67-'Apr-26'!BO67 -> 0 | BN67: =BM67/$C$46*100% -> 0 | BO67: =SUMIF('05.conso TB'!A:A,'May-26'!B67,'05.conso TB'!J:J)/10^5 -> 0 | BP67: =BO67/$C$46*100% -> 0 | BR67: =BT67-'Apr-26'!BT67 -> 26.293005 | BS67: =BR67/$BR$46*100% -> 0.0099425372 | BT67: =BG67+BK67+BO67-BQ67 -> 35.10816 | BU67: =BT67/$BT$46*100% -> 0.007823115 | BW67: =BY67-'Apr-26'!BY67 -> 0 | BX67: =BW67/$BW$46*100% -> 0 | BY67: =SUMIF('05.conso TB'!A:A,'May-26'!B67,'05.conso TB'!L:L)/10^5 -> 0 | BZ67: =BY67/$BY$46*100% -> 0 | CB67: =CD67-'Apr-26'!CD67 -> 0 | CE67: =AB67+AG67+AL67+AZ67+BR67+BW67 -> 26.411065 | CF67: =CE67/$CE$46*100% -> 0.0015622885 | CG67: =AD67+AI67+AN67+BB67+BT67+BY67 -> 36.026229 | CH67: =CG67/$CG$46*100% -> 0.0029458457
B68: Travelling expense | C68: =E68-'Apr-26'!E68 -> 0.17505 | D68: =C68/$C$46*100% -> 5.6033254e-05 | E68: =SUMIF('05.conso TB'!A:A,'May-26'!B68,'05.conso TB'!R:R)/10^5 -> 0.18827 | F68: =E68/$E$46*100% -> 2.9138784e-05 | G68: =I68-'Apr-26'!I68 -> 0 | H68: =G68/$G$46*100% -> 0 | I68: =SUMIF('05.conso TB'!A:A,'May-26'!B68,'05.conso TB'!S:S)/10^5 -> 0 | J68: =I68/$I$46*100% -> 0 | K68: =M68-'Apr-26'!M68 -> 0 | L68: =K68/$C$46*100% -> 0 | M68: =SUMIF('05.conso TB'!A:A,'May-26'!B68,'05.conso TB'!T:T)/10^5 -> 0 | N68: =M68/$C$46*100% -> 0 | O68: =Q68-'Apr-26'!Q68 -> 0 | P68: =O68/$O$46*100% -> 0 | Q68: =SUMIF('05.conso TB'!A:A,'May-26'!B68,'05.conso TB'!U:U)/10^5 -> 0 | R68: =Q68/$Q$46*100% -> 0 | S68: =U68-'Apr-26'!U68 -> 13.282731 | T68: =S68/$S$46*100% -> -565.63659 | U68: =SUMIF('05.conso TB'!A:A,'May-26'!B68,'05.conso TB'!V:V)/10^5 -> 22.697924 | V68: =U68/$U$46*100% -> 0.46566945 | W68: =Y68-'Apr-26'!Y68 -> 0.0087 | X68: =W68/$W$46*100% -> 2.3392452e-06 | Y68: =SUMIF('05.conso TB'!A:A,'May-26'!B68,'05.conso TB'!G:G)/10^5 -> 0.1472 | Z68: =Y68/$Y$46*100% -> 3.8802046e-05 | AB68: =AD68-'Apr-26'!AD68 -> 13.466481 | AC68: =AB68/$AB$46*100% -> 0.001460352 | AD68: =E68+I68+M68+Q68+U68+Y68 -> 23.033394 | AE68: =AD68/$AD$46*100% -> 0.0015936798 | AG68: =AI68-'Apr-26'!AI68 -> 0.21892 | AH68: =AG68/$AG$46*100% -> 0.00059568611 | AI68: =SUMIF('05.conso TB'!A:A,'May-26'!B68,'05.conso TB'!Q:Q)/10^5 -> 0.22717 | AJ68: =AI68/$AI$46*100% -> 0.00030781731 | AL68: =AN68-'Apr-26'!AN68 -> 13.980738 | AM68: =AL68/$AL$46*100% -> 0.011805684 | AN68: =SUMIF('05.conso TB'!A:A,'May-26'!B68,'05.conso TB'!W:W)/10^5 -> 14.846216 | AO68: =AN68/$AN$46*100% -> 0.0063927608 | AQ68: =AS68-'Apr-26'!AS68 -> 2.2782 | AR68: =AQ68/$AQ$46*100% -> 0.0011174072 | AS68: =SUMIF('05.conso TB'!A:A,'May-26'!B68,'05.conso TB'!M:M)/10^5 -> 5.02869 | AT68: =AS68/$AS$46*100% -> 0.001299222 | AU68: =AW68-'Apr-26'!AW68 -> 0 | AV68: =AU68/$C$46*100% -> 0 | AW68: =SUMIF('05.conso TB'!A:A,'May-26'!B68,'05.conso TB'!P:P)/10^5 -> 0 | AX68: =AW68/$AW$46*100% -> 0 | AZ68: =BB68-'Apr-26'!BB68 -> 2.2782 | BA68: =AZ68/$AZ$46*100% -> 0.00075059166 | BB68: =AS68+AW68 -> 5.02869 | BC68: =BB68/$BB$46*100% -> 0.00087948414 | BE68: =BG68-'Apr-26'!BG68 -> 2.82 | BF68: =BE68/$BE$46*100% -> 0.0010089724 | BG68: =SUMIF('05.conso TB'!A:A,'May-26'!B68,'05.conso TB'!H:H)/10^5 -> 2.99188 | BH68: =BG68/$BG$46*100% -> 0.00063668682 | BI68: =BK68-'Apr-26'!BK68 -> 0.18343 | BJ68: =BI68/$BI$46*100% -> 0.0095441442 | BK68: =SUMIF('05.conso TB'!A:A,'May-26'!B68,'05.conso TB'!I:I)/10^5 -> 0.58585 | BL68: =BK68/$BK$46*100% -> 0.01517757 | BM68: =BO68-'Apr-26'!BO68 -> 0 | BN68: =BM68/$C$46*100% -> 0 | BO68: =SUMIF('05.conso TB'!A:A,'May-26'!B68,'05.conso TB'!J:J)/10^5 -> 0 | BP68: =BO68/$C$46*100% -> 0 | BR68: =BT68-'Apr-26'!BT68 -> 3.00343 | BS68: =BR68/$BR$46*100% -> 0.0011357285 | BT68: =BG68+BK68+BO68-BQ68 -> 3.57773 | BU68: =BT68/$BT$46*100% -> 0.00079722187 | BW68: =BY68-'Apr-26'!BY68 -> 0 | BX68: =BW68/$BW$46*100% -> 0 | BY68: =SUMIF('05.conso TB'!A:A,'May-26'!B68,'05.conso TB'!L:L)/10^5 -> 0 | BZ68: =BY68/$BY$46*100% -> 0 | CB68: =CD68-'Apr-26'!CD68 -> 0 | CE68: =AB68+AG68+AL68+AZ68+BR68+BW68 -> 32.947769 | CF68: =CE68/$CE$46*100% -> 0.0019489528 | CG68: =AD68+AI68+AN68+BB68+BT68+BY68 -> 46.713199 | CH68: =CG68/$CG$46*100% -> 0.0038197136
B69: Brokerage & commission | C69: =E69-'Apr-26'!E69 -> 0 | D69: =C69/$C$46*100% -> 0 | E69: =SUMIF('05.conso TB'!A:A,'May-26'!B69,'05.conso TB'!R:R)/10^5 -> 0 | F69: =E69/$E$46*100% -> 0 | G69: =I69-'Apr-26'!I69 -> 0 | H69: =G69/$G$46*100% -> 0 | I69: =SUMIF('05.conso TB'!A:A,'May-26'!B69,'05.conso TB'!S:S)/10^5 -> 0 | J69: =I69/$I$46*100% -> 0 | K69: =M69-'Apr-26'!M69 -> 0 | L69: =K69/$C$46*100% -> 0 | M69: =SUMIF('05.conso TB'!A:A,'May-26'!B69,'05.conso TB'!T:T)/10^5 -> 0 | N69: =M69/$C$46*100% -> 0 | O69: =Q69-'Apr-26'!Q69 -> 0 | P69: =O69/$O$46*100% -> 0 | Q69: =SUMIF('05.conso TB'!A:A,'May-26'!B69,'05.conso TB'!U:U)/10^5 -> 0 | R69: =Q69/$Q$46*100% -> 0 | S69: =U69-'Apr-26'!U69 -> 3 | T69: =S69/$S$46*100% -> -127.75308 | U69: =SUMIF('05.conso TB'!A:A,'May-26'!B69,'05.conso TB'!V:V)/10^5 -> 3 | V69: =U69/$U$46*100% -> 0.061547848 | W69: =Y69-'Apr-26'!Y69 -> 0 | X69: =W69/$W$46*100% -> 0 | Y69: =SUMIF('05.conso TB'!A:A,'May-26'!B69,'05.conso TB'!G:G)/10^5 -> 0 | Z69: =Y69/$Y$46*100% -> 0 | AB69: =AD69-'Apr-26'!AD69 -> 3 | AC69: =AB69/$AB$46*100% -> 0.00032533044 | AD69: =E69+I69+M69+Q69+U69+Y69 -> 3 | AE69: =AD69/$AD$46*100% -> 0.00020756991 | AG69: =AI69-'Apr-26'!AI69 -> 0 | AH69: =AG69/$AG$46*100% -> 0 | AI69: =SUMIF('05.conso TB'!A:A,'May-26'!B69,'05.conso TB'!Q:Q)/10^5 -> 0 | AJ69: =AI69/$AI$46*100% -> 0 | AL69: =AN69-'Apr-26'!AN69 -> 0 | AM69: =AL69/$AL$46*100% -> 0 | AN69: =SUMIF('05.conso TB'!A:A,'May-26'!B69,'05.conso TB'!W:W)/10^5 -> 0 | AO69: =AN69/$AN$46*100% -> 0 | AQ69: =AS69-'Apr-26'!AS69 -> 0 | AR69: =AQ69/$AQ$46*100% -> 0 | AS69: =SUMIF('05.conso TB'!A:A,'May-26'!B69,'05.conso TB'!M:M)/10^5 -> 0 | AT69: =AS69/$AS$46*100% -> 0 | AU69: =AW69-'Apr-26'!AW69 -> 0 | AV69: =AU69/$C$46*100% -> 0 | AW69: =SUMIF('05.conso TB'!A:A,'May-26'!B69,'05.conso TB'!P:P)/10^5 -> 0 | AX69: =AW69/$AW$46*100% -> 0 | AZ69: =BB69-'Apr-26'!BB69 -> 0 | BA69: =AZ69/$AZ$46*100% -> 0 | BB69: =AS69+AW69 -> 0 | BC69: =BB69/$BB$46*100% -> 0 | BE69: =BG69-'Apr-26'!BG69 -> 0 | BF69: =BE69/$BE$46*100% -> 0 | BG69: =SUMIF('05.conso TB'!A:A,'May-26'!B69,'05.conso TB'!H:H)/10^5 -> 0 | BH69: =BG69/$BG$46*100% -> 0 | BI69: =BK69-'Apr-26'!BK69 -> 0 | BJ69: =BI69/$BI$46*100% -> 0 | BK69: =SUMIF('05.conso TB'!A:A,'May-26'!B69,'05.conso TB'!I:I)/10^5 -> 0 | BL69: =BK69/$BK$46*100% -> 0 | BM69: =BO69-'Apr-26'!BO69 -> 0 | BN69: =BM69/$C$46*100% -> 0 | BO69: =SUMIF('05.conso TB'!A:A,'May-26'!B69,'05.conso TB'!J:J)/10^5 -> 0 | BP69: =BO69/$C$46*100% -> 0 | BR69: =BT69-'Apr-26'!BT69 -> 0 | BS69: =BR69/$BR$46*100% -> 0 | BT69: =BG69+BK69+BO69-BQ69 -> 0 | BU69: =BT69/$BT$46*100% -> 0 | BW69: =BY69-'Apr-26'!BY69 -> 0 | BX69: =BW69/$BW$46*100% -> 0 | BY69: =SUMIF('05.conso TB'!A:A,'May-26'!B69,'05.conso TB'!L:L)/10^5 -> 0 | BZ69: =BY69/$BY$46*100% -> 0 | CB69: =CD69-'Apr-26'!CD69 -> 0 | CE69: =AB69+AG69+AL69+AZ69+BR69+BW69 -> 3 | CF69: =CE69/$CE$46*100% -> 0.0001774584 | CG69: =AD69+AI69+AN69+BB69+BT69+BY69 -> 3 | CH69: =CG69/$CG$46*100% -> 0.00024530842
B70: Conveyance, vehicle running and traveling expenses | C70: =E70-'Apr-26'!E70 -> 1.1932 | D70: =C70/$C$46*100% -> 0.00038194161 | E70: =SUMIF('05.conso TB'!A:A,'May-26'!B70,'05.conso TB'!R:R)/10^5 -> 2.61037 | F70: =E70/$E$46*100% -> 0.00040401024 | G70: =I70-'Apr-26'!I70 -> 6.19365 | H70: =G70/$G$46*100% -> 0.0046631657 | I70: =SUMIF('05.conso TB'!A:A,'May-26'!B70,'05.conso TB'!S:S)/10^5 -> 8.7428884 | J70: =I70/$I$46*100% -> 0.0034838409 | K70: =M70-'Apr-26'!M70 -> 0.25414 | L70: =K70/$C$46*100% -> 8.134985e-05 | M70: =SUMIF('05.conso TB'!A:A,'May-26'!B70,'05.conso TB'!T:T)/10^5 -> 0.4462 | N70: =M70/$C$46*100% -> 0.00014282798 | O70: =Q70-'Apr-26'!Q70 -> 2.0785 | P70: =O70/$O$46*100% -> 0.0016734377 | Q70: =SUMIF('05.conso TB'!A:A,'May-26'!B70,'05.conso TB'!U:U)/10^5 -> 4.0624 | R70: =Q70/$Q$46*100% -> 0.0018644746 | S70: =U70-'Apr-26'!U70 -> 0.37782 | T70: =S70/$S$46*100% -> -16.089223 | U70: =SUMIF('05.conso TB'!A:A,'May-26'!B70,'05.conso TB'!V:V)/10^5 -> 1.50213 | V70: =U70/$U$46*100% -> 0.030817623 | W70: =Y70-'Apr-26'!Y70 -> 0.25029 | X70: =W70/$W$46*100% -> 6.7297665e-05 | Y70: =SUMIF('05.conso TB'!A:A,'May-26'!B70,'05.conso TB'!G:G)/10^5 -> 0.47297 | Z70: =Y70/$Y$46*100% -> 0.0001246753 | AB70: =AD70-'Apr-26'!AD70 -> 10.3476 | AC70: =AB70/$AB$46*100% -> 0.0011221297 | AD70: =E70+I70+M70+Q70+U70+Y70 -> 17.836958 | AE70: =AD70/$AD$46*100% -> 0.0012341386 | AG70: =AI70-'Apr-26'!AI70 -> 4.1593 | AH70: =AG70/$AG$46*100% -> 0.011317546 | AI70: =SUMIF('05.conso TB'!A:A,'May-26'!B70,'05.conso TB'!Q:Q)/10^5 -> 8.21735 | AJ70: =AI70/$AI$46*100% -> 0.01113458 | AL70: =AN70-'Apr-26'!AN70 -> 0.549479 | AM70: =AL70/$AL$46*100% -> 0.00046399377 | AN70: =SUMIF('05.conso TB'!A:A,'May-26'!B70,'05.conso TB'!W:W)/10^5 -> 0.8999958 | AO70: =AN70/$AN$46*100% -> 0.00038753699 | AQ70: =AS70-'Apr-26'!AS70 -> 2.58995 | AR70: =AQ70/$AQ$46*100% -> 0.0012703138 | AS70: =SUMIF('05.conso TB'!A:A,'May-26'!B70,'05.conso TB'!M:M)/10^5 -> 5.17308 | AT70: =AS70/$AS$46*100% -> 0.0013365269 | AU70: =AW70-'Apr-26'!AW70 -> 0.16006 | AV70: =AU70/$C$46*100% -> 5.1234977e-05 | AW70: =SUMIF('05.conso TB'!A:A,'May-26'!B70,'05.conso TB'!P:P)/10^5 -> 0.16006 | AX70: =AW70/$AW$46*100% -> 8.664853e-05 | AZ70: =BB70-'Apr-26'!BB70 -> 2.75001 | BA70: =AZ70/$AZ$46*100% -> 0.00090603748 | BB70: =AS70+AW70 -> 5.33314 | BC70: =BB70/$BB$46*100% -> 0.00093273041 | BE70: =BG70-'Apr-26'!BG70 -> 1.47882 | BF70: =BE70/$BE$46*100% -> 0.00052910943 | BG70: =SUMIF('05.conso TB'!A:A,'May-26'!B70,'05.conso TB'!H:H)/10^5 -> 2.65888 | BH70: =BG70/$BG$46*100% -> 0.00056582277 | BI70: =BK70-'Apr-26'!BK70 -> 0.02 | BJ70: =BI70/$BI$46*100% -> 0.0010406307 | BK70: =SUMIF('05.conso TB'!A:A,'May-26'!B70,'05.conso TB'!I:I)/10^5 -> 0.06 | BL70: =BK70/$BK$46*100% -> 0.0015544153 | BM70: =BO70-'Apr-26'!BO70 -> 0 | BN70: =BM70/$C$46*100% -> 0 | BO70: =SUMIF('05.conso TB'!A:A,'May-26'!B70,'05.conso TB'!J:J)/10^5 -> 0 | BP70: =BO70/$C$46*100% -> 0 | BR70: =BT70-'Apr-26'!BT70 -> 1.49882 | BS70: =BR70/$BR$46*100% -> 0.00056676951 | BT70: =BG70+BK70+BO70-BQ70 -> 2.71888 | BU70: =BT70/$BT$46*100% -> 0.00060584521 | BW70: =BY70-'Apr-26'!BY70 -> 0 | BX70: =BW70/$BW$46*100% -> 0 | BY70: =SUMIF('05.conso TB'!A:A,'May-26'!B70,'05.conso TB'!L:L)/10^5 -> 0 | BZ70: =BY70/$BY$46*100% -> 0 | CB70: =CD70-'Apr-26'!CD70 -> 0 | CE70: =AB70+AG70+AL70+AZ70+BR70+BW70 -> 19.305209 | CF70: =CE70/$CE$46*100% -> 0.0011419572 | CG70: =AD70+AI70+AN70+BB70+BT70+BY70 -> 35.006324 | CH70: =CG70/$CG$46*100% -> 0.0028624486
B71: Freight Outward and C & F Charges | C71: =E71-'Apr-26'!E71 -> 32.803314 | D71: =C71/$C$46*100% -> 0.010500294 | E71: =SUMIF('05.conso TB'!A:A,'May-26'!B71,'05.conso TB'!R:R)/10^5 -> 47.496631 | F71: =E71/$E$46*100% -> 0.0073511131 | G71: =I71-'Apr-26'!I71 -> 26.065784 | H71: =G71/$G$46*100% -> 0.019624789 | I71: =SUMIF('05.conso TB'!A:A,'May-26'!B71,'05.conso TB'!S:S)/10^5 -> 54.127398 | J71: =I71/$I$46*100% -> 0.021568529 | K71: =M71-'Apr-26'!M71 -> 0 | L71: =K71/$C$46*100% -> 0 | M71: =SUMIF('05.conso TB'!A:A,'May-26'!B71,'05.conso TB'!T:T)/10^5 -> 0 | N71: =M71/$C$46*100% -> 0 | O71: =Q71-'Apr-26'!Q71 -> 12.066478 | P71: =O71/$O$46*100% -> 0.0097149382 | Q71: =SUMIF('05.conso TB'!A:A,'May-26'!B71,'05.conso TB'!U:U)/10^5 -> 18.0445 | R71: =Q71/$Q$46*100% -> 0.008281684 | S71: =U71-'Apr-26'!U71 -> 0 | T71: =S71/$S$46*100% -> 0 | U71: =SUMIF('05.conso TB'!A:A,'May-26'!B71,'05.conso TB'!V:V)/10^5 -> 0.046695 | V71: =U71/$U$46*100% -> 0.00095799225 | W71: =Y71-'Apr-26'!Y71 -> 0 | X71: =W71/$W$46*100% -> 0 | Y71: =SUMIF('05.conso TB'!A:A,'May-26'!B71,'05.conso TB'!G:G)/10^5 -> 0 | Z71: =Y71/$Y$46*100% -> 0 | AB71: =AD71-'Apr-26'!AD71 -> 70.935576 | AC71: =AB71/$AB$46*100% -> 0.0076925006 | AD71: =E71+I71+M71+Q71+U71+Y71 -> 119.71522 | AE71: =AD71/$AD$46*100% -> 0.0082830926 | AG71: =AI71-'Apr-26'!AI71 -> 6.87118 | AH71: =AG71/$AG$46*100% -> 0.018696631 | AI71: =SUMIF('05.conso TB'!A:A,'May-26'!B71,'05.conso TB'!Q:Q)/10^5 -> 9.43324 | AJ71: =AI71/$AI$46*100% -> 0.012782122 | AL71: =AN71-'Apr-26'!AN71 -> 10.538693 | AM71: =AL71/$AL$46*100% -> 0.008899135 | AN71: =SUMIF('05.conso TB'!A:A,'May-26'!B71,'05.conso TB'!W:W)/10^5 -> 14.997895 | AO71: =AN71/$AN$46*100% -> 0.0064580738 | AQ71: =AS71-'Apr-26'!AS71 -> -74.256651 | AR71: =AQ71/$AQ$46*100% -> -0.036421262 | AS71: =SUMIF('05.conso TB'!A:A,'May-26'!B71,'05.conso TB'!M:M)/10^5 -> -38.791691 | AT71: =AS71/$AS$46*100% -> -0.010022296 | AU71: =AW71-'Apr-26'!AW71 -> 1.2155399 | AV71: =AU71/$C$46*100% -> 0.00038909258 | AW71: =SUMIF('05.conso TB'!A:A,'May-26'!B71,'05.conso TB'!P:P)/10^5 -> 6.7256448 | AX71: =AW71/$AW$46*100% -> 0.0036409299 | AZ71: =BB71-'Apr-26'!BB71 -> -73.041112 | BA71: =AZ71/$AZ$46*100% -> -0.024064634 | BB71: =AS71+AW71 -> -32.066046 | BC71: =BB71/$BB$46*100% -> -0.0056081364 | BE71: =BG71-'Apr-26'!BG71 -> 51.257199 | BF71: =BE71/$BE$46*100% -> 0.018339397 | BG71: =SUMIF('05.conso TB'!A:A,'May-26'!B71,'05.conso TB'!H:H)/10^5 -> 51.940085 | BH71: =BG71/$BG$46*100% -> 0.011053106 | BI71: =BK71-'Apr-26'!BK71 -> 0.12254 | BJ71: =BI71/$BI$46*100% -> 0.0063759441 | BK71: =SUMIF('05.conso TB'!A:A,'May-26'!B71,'05.conso TB'!I:I)/10^5 -> 0.3595856 | BL71: =BK71/$BK$46*100% -> 0.009315756 | BM71: =BO71-'Apr-26'!BO71 -> 0 | BN71: =BM71/$C$46*100% -> 0 | BO71: =SUMIF('05.conso TB'!A:A,'May-26'!B71,'05.conso TB'!J:J)/10^5 -> 0 | BP71: =BO71/$C$46*100% -> 0 | BR71: =BT71-'Apr-26'!BT71 -> 51.379739 | BS71: =BR71/$BR$46*100% -> 0.019428931 | BT71: =BG71+BK71+BO71-BQ71 -> 52.29967 | BU71: =BT71/$BT$46*100% -> 0.011653881 | BW71: =BY71-'Apr-26'!BY71 -> 0.9605 | BX71: =BW71/$BW$46*100% -> 0.0021225223 | BY71: =SUMIF('05.conso TB'!A:A,'May-26'!B71,'05.conso TB'!L:L)/10^5 -> 1.8412 | BZ71: =BY71/$BY$46*100% -> 0.00085205881 | CB71: =CD71-'Apr-26'!CD71 -> 0 | CE71: =AB71+AG71+AL71+AZ71+BR71+BW71 -> 67.644577 | CF71: =CE71/$CE$46*100% -> 0.0040013662 | CG71: =AD71+AI71+AN71+BB71+BT71+BY71 -> 166.22118 | CH71: =CG71/$CG$46*100% -> 0.013591818
B72: Total Selling and Distribution Expenses | C72: =SUM(C67:C71) -> 34.171564 | D72: =SUM(D67:D71) -> 0.010938269 | E72: =SUM(E67:E71) -> 50.295271 | F72: =E72/$E$46*100% -> 0.0077842621 | G72: =SUM(G67:G71) -> 32.259434 | H72: =G72/$G$46*100% -> 0.024287954 | I72: =SUM(I67:I71) -> 62.870287 | J72: =I72/$I$46*100% -> 0.02505237 | K72: =SUM(K67:K71) -> 0.25414 | L72: =SUM(L67:L71) -> 8.134985e-05 | M72: =SUM(M67:M71) -> 0.4462 | N72: =SUM(N67:N71) -> 0.00014282798 | O72: =SUM(O67:O71) -> 14.144978 | P72: =O72/$O$46*100% -> 0.011388376 | Q72: =SUM(Q67:Q71) -> 22.1069 | R72: =Q72/$Q$46*100% -> 0.010146159 | S72: =SUM(S67:S71) -> 16.711541 | T72: =S72/$S$46*100% -> -711.65026 | U72: =SUM(U67:U71) -> 27.622009 | V72: =U72/$U$46*100% -> 0.56669173 | W72: =SUM(W67:W71) -> 0.32606 | X72: =W72/$W$46*100% -> 8.7670609e-05 | Y72: =SUM(Y67:Y71) -> 1.00224 | Z72: =Y72/$Y$46*100% -> 0.00026419132 | AA72: =SUM(AA67:AA71) -> 0 | AB72: =SUM(AB67:AB71) -> 97.867717 | AC72: =AB72/$AB$46*100% -> 0.010613116 | AD72: =SUM(AD67:AD71) -> 164.34291 | AE72: =AD72/$AD$46*100% -> 0.011370881 | AF72: =AG72/$AG$1*10^5 -> 3.0608197 | AG72: =SUM(AG67:AG71) -> 11.2494 | AH72: =AG72/$AG$46*100% -> 0.030609864 | AI72: =SUM(AI67:AI71) -> 17.87776 | AJ72: =SUM(AJ67:AJ71) -> 0.024224519 | AK72: =AL72/$AL$1*10^5 -> 5.676528 | AL72: =SUM(AL67:AL71) -> 25.06891 | AM72: =AL72/$AL$46*100% -> 0.021168812 | AN72: =SUM(AN67:AN71) -> 30.744107 | AO72: =SUM(AO67:AO71) -> 0.013238372 | AP72: =AQ72/$AQ$1*10^5 -> -11.622378 | AQ72: =SUM(AQ67:AQ71) -> -69.388501 | AR72: =AQ72/$AQ$46*100% -> -0.034033541 | AS72: =SUM(AS67:AS71) -> -28.429182 | AT72: =SUM(AT67:AT71) -> -0.007345018 | AU72: =SUM(AU67:AU71) -> 1.3755999 | AV72: =SUM(AV67:AV71) -> 0.00044032756 | AW72: =SUM(AW67:AW71) -> 6.8857048 | AX72: =SUM(AX67:AX71) -> 0.0037275784 | AZ72: =SUM(AZ67:AZ71) -> -68.012902 | BA72: =AZ72/$AZ$46*100% -> -0.022408005 | BB72: =SUM(BB67:BB71) -> -21.543478 | BC72: =SUM(BC67:BC71) -> -0.0037678097 | BE72: =SUM(BE67:BE71) -> 81.849025 | BF72: =BE72/$BE$46*100% -> 0.029284897 | BG72: =SUM(BG67:BG71) -> 92.699005 | BH72: =SUM(BH67:BH71) -> 0.019726805 | BI72: =SUM(BI67:BI71) -> 0.32597 | BJ72: =BI72/$BI$46*100% -> 0.016960719 | BK72: =SUM(BK67:BK71) -> 1.0054356 | BL72: =SUM(BL67:BL71) -> 0.026047741 | BM72: =SUM(BM67:BM71) -> 0 | BN72: =SUM(BN67:BN71) -> 0 | BO72: =SUM(BO67:BO71) -> 0 | BP72: =SUM(BP67:BP71) -> 0 | BR72: =SUM(BR67:BR71) -> 82.174995 | BS72: =BR72/$BR$46*100% -> 0.031073966 | BT72: =BG72+BK72+BO72-BQ72 -> 93.704441 | BU72: =BT72/$BT$46*100% -> 0.020880063 | BW72: =SUM(BW67:BW71) -> 0.9605 | BX72: =BW72/$BW$46*100% -> 0.0021225223 | BY72: =SUM(BY67:BY71) -> 1.8412 | BZ72: =BY72/$BY$46*100% -> 0.00085205881 | CB72: =SUM(CB67:CB71) -> 0 | CE72: =SUM(CE67:CE71) -> 149.30862 | CF72: =CE72/$CE$46*100% -> 0.0088320231 | CG72: =SUM(CG67:CG71) -> 286.96694 | CH72: =CG72/$CG$46*100% -> 0.023465135
B73: Administrative Expenses | F73: =E73/$E$46*100% -> 0 | H73: =G73/$G$46*100% -> 0 | I73: =SUMIF('05.conso TB'!A:A,'May-26'!B73,'05.conso TB'!S:S)/10^5 -> 0 | J73: =I73/$I$46*100% -> 0 | P73: =O73/$O$46*100% -> 0 | R73: =Q73/$Q$46*100% -> 0 | T73: =S73/$S$46*100% -> 0 | V73: =U73/$U$46*100% -> 0 | X73: =W73/$W$46*100% -> 0 | Z73: =Y73/$Y$46*100% -> 0 | AC73: =AB73/$AB$46*100% -> 0 | AE73: =AD73/$AD$46*100% -> 0 | AH73: =AG73/$AG$46*100% -> 0 | AM73: =AL73/$AL$46*100% -> 0 | AR73: =AQ73/$AQ$46*100% -> 0 | BA73: =AZ73/$AZ$46*100% -> 0 | BF73: =BE73/$BE$46*100% -> 0 | BJ73: =BI73/$BI$46*100% -> 0 | BS73: =BR73/$BR$46*100% -> 0 | BT73: =BG73+BK73+BO73-BQ73 -> 0 | BU73: =BT73/$BT$46*100% -> 0 | BX73: =BW73/$BW$46*100% -> 0 | BZ73: =BY73/$BY$46*100% -> 0 | CF73: =CE73/$CE$46*100% -> 0 | CH73: =CG73/$CG$46*100% -> 0
B74: Insurance | C74: =E74-'Apr-26'!E74 -> 2.4287715 | D74: =C74/$C$46*100% -> 0.00077744628 | E74: =SUMIF('05.conso TB'!A:A,'May-26'!B74,'05.conso TB'!R:R)/10^5 -> 4.4124134 | F74: =E74/$E$46*100% -> 0.00068291475 | G74: =I74-'Apr-26'!I74 -> 0.2097627 | H74: =G74/$G$46*100% -> 0.00015792921 | I74: =SUMIF('05.conso TB'!A:A,'May-26'!B74,'05.conso TB'!S:S)/10^5 -> 0.1322708 | J74: =I74/$I$46*100% -> 5.2706885e-05 | K74: =M74-'Apr-26'!M74 -> 0 | L74: =K74/$C$46*100% -> 0 | M74: =SUMIF('05.conso TB'!A:A,'May-26'!B74,'05.conso TB'!T:T)/10^5 -> 0 | N74: =M74/$C$46*100% -> 0 | O74: =Q74-'Apr-26'!Q74 -> 0 | P74: =O74/$O$46*100% -> 0 | Q74: =SUMIF('05.conso TB'!A:A,'May-26'!B74,'05.conso TB'!U:U)/10^5 -> 0 | R74: =Q74/$Q$46*100% -> 0 | S74: =U74-'Apr-26'!U74 -> 0 | T74: =S74/$S$46*100% -> 0 | U74: =SUMIF('05.conso TB'!A:A,'May-26'!B74,'05.conso TB'!V:V)/10^5 -> 0.0059 | V74: =U74/$U$46*100% -> 0.0001210441 | W74: =Y74-'Apr-26'!Y74 -> 0 | X74: =W74/$W$46*100% -> 0 | Y74: =SUMIF('05.conso TB'!A:A,'May-26'!B74,'05.conso TB'!G:G)/10^5 -> 0 | Z74: =Y74/$Y$46*100% -> 0 | AB74: =AD74-'Apr-26'!AD74 -> 2.6385342 | AC74: =AB74/$AB$46*100% -> 0.00028613183 | AD74: =E74+I74+M74+Q74+U74+Y74 -> 4.5505842 | AE74: =AD74/$AD$46*100% -> 0.00031485478 | AG74: =AI74-'Apr-26'!AI74 -> 0.069 | AH74: =AG74/$AG$46*100% -> 0.00018775051 | AI74: =SUMIF('05.conso TB'!A:A,'May-26'!B74,'05.conso TB'!Q:Q)/10^5 -> 0.1159 | AJ74: =AI74/$AI$46*100% -> 0.0001570455 | AL74: =AN74-'Apr-26'!AN74 -> 1.41238 | AM74: =AL74/$AL$46*100% -> 0.0011926489 | AN74: =SUMIF('05.conso TB'!A:A,'May-26'!B74,'05.conso TB'!W:W)/10^5 -> 2.83405 | AO74: =AN74/$AN$46*100% -> 0.0012203382 | AQ74: =AS74-'Apr-26'!AS74 -> 7.241441 | AR74: =AQ74/$AQ$46*100% -> 0.0035517683 | AS74: =SUMIF('05.conso TB'!A:A,'May-26'!B74,'05.conso TB'!M:M)/10^5 -> 10.891778 | AT74: =AS74/$AS$46*100% -> 0.0028140207 | AU74: =AW74-'Apr-26'!AW74 -> 0.0799447 | AV74: =AU74/$C$46*100% -> 2.5590184e-05 | AW74: =SUMIF('05.conso TB'!A:A,'May-26'!B74,'05.conso TB'!P:P)/10^5 -> 0.5065847 | AX74: =AW74/$AW$46*100% -> 0.00027423978 | AZ74: =BB74-'Apr-26'!BB74 -> 7.3213857 | BA74: =AZ74/$AZ$46*100% -> 0.0024121548 | BB74: =AS74+AW74 -> 11.398363 | BC74: =BB74/$BB$46*100% -> 0.0019934972 | BE74: =BG74-'Apr-26'!BG74 -> 2.0763921 | BF74: =BE74/$BE$46*100% -> 0.00074291573 | BG74: =SUMIF('05.conso TB'!A:A,'May-26'!B74,'05.conso TB'!H:H)/10^5 -> 1.9870998 | BH74: =BG74/$BG$46*100% -> 0.00042286464 | BI74: =BK74-'Apr-26'!BK74 -> 0 | BJ74: =BI74/$BI$46*100% -> 0 | BK74: =SUMIF('05.conso TB'!A:A,'May-26'!B74,'05.conso TB'!I:I)/10^5 -> 0 | BL74: =BK74/$BK$46*100% -> 0 | BM74: =BO74-'Apr-26'!BO74 -> 0 | BN74: =BM74/$C$46*100% -> 0 | BO74: =SUMIF('05.conso TB'!A:A,'May-26'!B74,'05.conso TB'!J:J)/10^5 -> 0 | BP74: =BO74/$C$46*100% -> 0 | BR74: =BT74-'Apr-26'!BT74 -> 2.0763921 | BS74: =BR74/$BR$46*100% -> 0.00078517483 | BT74: =BG74+BK74+BO74-BQ74 -> 1.9870998 | BU74: =BT74/$BT$46*100% -> 0.00044278339 | BW74: =BY74-'Apr-26'!BY74 -> 0 | BX74: =BW74/$BW$46*100% -> 0 | BY74: =SUMIF('05.conso TB'!A:A,'May-26'!B74,'05.conso TB'!L:L)/10^5 -> 0 | BZ74: =BY74/$BY$46*100% -> 0 | CB74: =CD74-'Apr-26'!CD74 -> 0 | CE74: =AB74+AG74+AL74+AZ74+BR74+BW74 -> 13.517692 | CF74: =CE74/$CE$46*100% -> 0.00079960934 | CG74: =AD74+AI74+AN74+BB74+BT74+BY74 -> 20.885997 | CH74: =CG74/$CG$46*100% -> 0.0017078369
B75: Miscellaneous Expense | C75: =E75-'Apr-26'!E75 -> 0 | D75: =C75/$C$46*100% -> 0 | E75: =SUMIF('05.conso TB'!A:A,'May-26'!B75,'05.conso TB'!R:R)/10^5 -> 0 | F75: =E75/$E$46*100% -> 0 | G75: =I75-'Apr-26'!I75 -> 0 | H75: =G75/$G$46*100% -> 0 | I75: =SUMIF('05.conso TB'!A:A,'May-26'!B75,'05.conso TB'!S:S)/10^5 -> 0 | J75: =I75/$I$46*100% -> 0 | K75: =M75-'Apr-26'!M75 -> 0 | L75: =K75/$C$46*100% -> 0 | M75: =SUMIF('05.conso TB'!A:A,'May-26'!B75,'05.conso TB'!T:T)/10^5 -> 0 | N75: =M75/$C$46*100% -> 0 | O75: =Q75-'Apr-26'!Q75 -> 0 | P75: =O75/$O$46*100% -> 0 | Q75: =SUMIF('05.conso TB'!A:A,'May-26'!B75,'05.conso TB'!U:U)/10^5 -> 0 | R75: =Q75/$Q$46*100% -> 0 | S75: =U75-'Apr-26'!U75 -> 0 | T75: =S75/$S$46*100% -> 0 | U75: =SUMIF('05.conso TB'!A:A,'May-26'!B75,'05.conso TB'!V:V)/10^5 -> 0 | V75: =U75/$U$46*100% -> 0 | W75: =Y75-'Apr-26'!Y75 -> 0 | X75: =W75/$W$46*100% -> 0 | Y75: =SUMIF('05.conso TB'!A:A,'May-26'!B75,'05.conso TB'!G:G)/10^5 -> 0 | Z75: =Y75/$Y$46*100% -> 0 | AB75: =AD75-'Apr-26'!AD75 -> 0 | AC75: =AB75/$AB$46*100% -> 0 | AD75: =E75+I75+M75+Q75+U75+Y75 -> 0 | AE75: =AD75/$AD$46*100% -> 0 | AG75: =AI75-'Apr-26'!AI75 -> 0 | AH75: =AG75/$AG$46*100% -> 0 | AI75: =SUMIF('05.conso TB'!A:A,'May-26'!B75,'05.conso TB'!Q:Q)/10^5 -> 0 | AJ75: =AI75/$AI$46*100% -> 0 | AL75: =AN75-'Apr-26'!AN75 -> 0 | AM75: =AL75/$AL$46*100% -> 0 | AN75: =SUMIF('05.conso TB'!A:A,'May-26'!B75,'05.conso TB'!W:W)/10^5 -> 0 | AO75: =AN75/$AN$46*100% -> 0 | AQ75: =AS75-'Apr-26'!AS75 -> 0 | AR75: =AQ75/$AQ$46*100% -> 0 | AS75: =SUMIF('05.conso TB'!A:A,'May-26'!B75,'05.conso TB'!M:M)/10^5 -> 0 | AT75: =AS75/$AS$46*100% -> 0 | AU75: =AW75-'Apr-26'!AW75 -> 0 | AV75: =AU75/$C$46*100% -> 0 | AW75: =SUMIF('05.conso TB'!A:A,'May-26'!B75,'05.conso TB'!P:P)/10^5 -> 0 | AX75: =AW75/$AW$46*100% -> 0 | AZ75: =BB75-'Apr-26'!BB75 -> 0 | BA75: =AZ75/$AZ$46*100% -> 0 | BB75: =AS75+AW75 -> 0 | BC75: =BB75/$BB$46*100% -> 0 | BE75: =BG75-'Apr-26'!BG75 -> 0 | BF75: =BE75/$BE$46*100% -> 0 | BG75: =SUMIF('05.conso TB'!A:A,'May-26'!B75,'05.conso TB'!H:H)/10^5 -> 0 | BH75: =BG75/$BG$46*100% -> 0 | BI75: =BK75-'Apr-26'!BK75 -> 0 | BJ75: =BI75/$BI$46*100% -> 0 | BK75: =SUMIF('05.conso TB'!A:A,'May-26'!B75,'05.conso TB'!I:I)/10^5 -> 0 | BL75: =BK75/$BK$46*100% -> 0 | BM75: =BO75-'Apr-26'!BO75 -> 0 | BN75: =BM75/$C$46*100% -> 0 | BO75: =SUMIF('05.conso TB'!A:A,'May-26'!B75,'05.conso TB'!J:J)/10^5 -> 0 | BP75: =BO75/$C$46*100% -> 0 | BR75: =BT75-'Apr-26'!BT75 -> 0 | BS75: =BR75/$BR$46*100% -> 0 | BT75: =BG75+BK75+BO75-BQ75 -> 0 | BU75: =BT75/$BT$46*100% -> 0 | BW75: =BY75-'Apr-26'!BY75 -> 0 | BX75: =BW75/$BW$46*100% -> 0 | BY75: =SUMIF('05.conso TB'!A:A,'May-26'!B75,'05.conso TB'!L:L)/10^5 -> 0 | BZ75: =BY75/$BY$46*100% -> 0 | CB75: =CD75-'Apr-26'!CD75 -> 0 | CE75: =AB75+AG75+AL75+AZ75+BR75+BW75 -> 0 | CF75: =CE75/$CE$46*100% -> 0 | CG75: =AD75+AI75+AN75+BB75+BT75+BY75 -> 0 | CH75: =CG75/$CG$46*100% -> 0
B76: Other Administrative Expenses | C76: =E76-'Apr-26'!E76 -> 46.217535 | D76: =C76/$C$46*100% -> 0.014794167 | E76: =SUMIF('05.conso TB'!A:A,'May-26'!B76,'05.conso TB'!R:R)/10^5 -> 69.155083 | F76: =E76/$E$46*100% -> 0.010703219 | G76: =I76-'Apr-26'!I76 -> 24.168932 | H76: =G76/$G$46*100% -> 0.018196659 | I76: =SUMIF('05.conso TB'!A:A,'May-26'!B76,'05.conso TB'!S:S)/10^5 -> 47.293316 | J76: =I76/$I$46*100% -> 0.018845304 | K76: =M76-'Apr-26'!M76 -> 1.5497999 | L76: =K76/$C$46*100% -> 0.00049608873 | M76: =SUMIF('05.conso TB'!A:A,'May-26'!B76,'05.conso TB'!T:T)/10^5 -> 2.9069121 | N76: =M76/$C$46*100% -> 0.0009304984 | O76: =Q76-'Apr-26'!Q76 -> 4.860205 | P76: =O76/$O$46*100% -> 0.0039130385 | Q76: =SUMIF('05.conso TB'!A:A,'May-26'!B76,'05.conso TB'!U:U)/10^5 -> 9.1330605 | R76: =Q76/$Q$46*100% -> 0.0041916994 | S76: =U76-'Apr-26'!U76 -> 37.425196 | U76: =SUMIF('05.conso TB'!A:A,'May-26'!B76,'05.conso TB'!V:V)/10^5 -> 45.519293 | V76: =U76/$U$46*100% -> 0.93387152 | W76: =Y76-'Apr-26'!Y76 -> 2.37084 | X76: =W76/$W$46*100% -> 0.00063746852 | Y76: =SUMIF('05.conso TB'!A:A,'May-26'!B76,'05.conso TB'!G:G)/10^5 -> 3.60087 | Z76: =Y76/$Y$46*100% -> 0.00094919242 | AB76: =AD76-'Apr-26'!AD76 -> 116.59251 | AC76: =AB76/$AB$46*100% -> 0.012643697 | AD76: =E76+I76+M76+Q76+U76+Y76 -> 177.60854 | AE76: =AD76/$AD$46*100% -> 0.012288729 | AG76: =AI76-'Apr-26'!AI76 -> 20.31773 | AH76: =AG76/$AG$46*100% -> 0.055284988 | AI76: =SUMIF('05.conso TB'!A:A,'May-26'!B76,'05.conso TB'!Q:Q)/10^5 -> 32.47336 | AJ76: =AI76/$AI$46*100% -> 0.044001683 | AL76: =AN76-'Apr-26'!AN76 -> 12.416983 | AM76: =AL76/$AL$46*100% -> 0.01048521 | AN76: =SUMIF('05.conso TB'!A:A,'May-26'!B76,'05.conso TB'!W:W)/10^5 -> 22.888888 | AO76: =AN76/$AN$46*100% -> 0.0098559246 | AQ76: =AS76-'Apr-26'!AS76 -> 41.7966 | AR76: =AQ76/$AQ$46*100% -> 0.020500318 | AS76: =SUMIF('05.conso TB'!A:A,'May-26'!B76,'05.conso TB'!M:M)/10^5 -> 94.716471 | AT76: =AS76/$AS$46*100% -> 0.024471129 | AU76: =AW76-'Apr-26'!AW76 -> 0.55639 | AV76: =AU76/$C$46*100% -> 0.00017809964 | AW76: =SUMIF('05.conso TB'!A:A,'May-26'!B76,'05.conso TB'!P:P)/10^5 -> 1.01896 | AX76: =AW76/$AW$46*100% -> 0.00055161431 | AZ76: =BB76-'Apr-26'!BB76 -> 42.35299 | BA76: =AZ76/$AZ$46*100% -> 0.013953912 | BB76: =AS76+AW76 -> 95.735431 | BC76: =BB76/$BB$46*100% -> 0.016743485 | BE76: =BG76-'Apr-26'!BG76 -> 27.088711 | BF76: =BE76/$BE$46*100% -> 0.0096921144 | BG76: =SUMIF('05.conso TB'!A:A,'May-26'!B76,'05.conso TB'!H:H)/10^5 -> 44.570414 | BH76: =BG76/$BG$46*100% -> 0.0094848039 | BI76: =BK76-'Apr-26'!BK76 -> 1.31876 | BJ76: =BI76/$BI$46*100% -> 0.068617105 | BK76: =SUMIF('05.conso TB'!A:A,'May-26'!B76,'05.conso TB'!I:I)/10^5 -> 2.76676 | BL76: =BK76/$BK$46*100% -> 0.071678235 | BM76: =BO76-'Apr-26'!BO76 -> 0 | BN76: =BM76/$C$46*100% -> 0 | BO76: =SUMIF('05.conso TB'!A:A,'May-26'!B76,'05.conso TB'!J:J)/10^5 -> 0 | BP76: =BO76/$C$46*100% -> 0 | BR76: =BT76-'Apr-26'!BT76 -> 28.407471 | BS76: =BR76/$BR$46*100% -> 0.010742109 | BT76: =BG76+BK76+BO76-BQ76 -> 47.337174 | BU76: =BT76/$BT$46*100% -> 0.010548093 | BW76: =BY76-'Apr-26'!BY76 -> 4.11714 | BX76: =BW76/$BW$46*100% -> 0.0090980963 | BY76: =SUMIF('05.conso TB'!A:A,'May-26'!B76,'05.conso TB'!L:L)/10^5 -> 4.78438 | BZ76: =BY76/$BY$46*100% -> 0.0022140849 | CB76: =CC76-'Apr-26'!CC76 -> 4.69 | CC76: =+CC39 -> 7.38 | CE76: =AB76+AG76+AL76+AZ76+BR76+BW76 -> 224.20482 | CF76: =CE76/$CE$46*100% -> 0.013262343 | CG76: =AD76+AI76+AN76+BB76+BT76+BY76 -> 380.82777 | CH76: =CG76/$CG$46*100% -> 0.031140085
B77: Exchange Rate Difference | C77: =E77-'Apr-26'!E77 -> -77.681407 | D77: =C77/$C$46*100% -> -0.024865707 | E77: =SUMIF('05.conso TB'!A:A,'May-26'!B77,'05.conso TB'!R:R)/10^5 -> -100.95244 | F77: =E77/$E$46*100% -> -0.015624536 | G77: =I77-'Apr-26'!I77 -> -32.272216 | H77: =G77/$G$46*100% -> -0.024297577 | I77: =SUMIF('05.conso TB'!A:A,'May-26'!B77,'05.conso TB'!S:S)/10^5 -> -60.44432 | J77: =I77/$I$46*100% -> -0.024085678 | K77: =M77-'Apr-26'!M77 -> 0 | L77: =K77/$C$46*100% -> 0 | M77: =SUMIF('05.conso TB'!A:A,'May-26'!B77,'05.conso TB'!T:T)/10^5 -> 0 | N77: =M77/$C$46*100% -> 0 | O77: =Q77-'Apr-26'!Q77 -> -9.8093599 | P77: =O77/$O$46*100% -> -0.0078976922 | Q77: =SUMIF('05.conso TB'!A:A,'May-26'!B77,'05.conso TB'!U:U)/10^5 -> -11.959544 | R77: =Q77/$Q$46*100% -> -0.0054889392 | S77: =U77-'Apr-26'!U77 -> -1.8813982 | U77: =SUMIF('05.conso TB'!A:A,'May-26'!B77,'05.conso TB'!V:V)/10^5 -> -1.8813982 | V77: =U77/$U$46*100% -> -0.03859867 | W77: =Y77-'Apr-26'!Y77 -> -1.488564 | X77: =W77/$W$46*100% -> -0.00040024324 | Y77: =SUMIF('05.conso TB'!A:A,'May-26'!B77,'05.conso TB'!G:G)/10^5 -> -3.1438152 | Z77: =Y77/$Y$46*100% -> -0.00082871238 | AB77: =AD77-'Apr-26'!AD77 -> -123.13294 | AC77: =AB77/$AB$46*100% -> -0.013352965 | AD77: =E77+I77+M77+Q77+U77+Y77 -> -178.38152 | AE77: =AD77/$AD$46*100% -> -0.012342212 | AG77: =AI77-'Apr-26'!AI77 -> 0 | AH77: =AG77/$AG$46*100% -> 0 | AI77: =SUMIF('05.conso TB'!A:A,'May-26'!B77,'05.conso TB'!Q:Q)/10^5 -> 0 | AJ77: =AI77/$AI$46*100% -> 0 | AL77: =AN77-'Apr-26'!AN77 -> 50.038984 | AM77: =AL77/$AL$46*100% -> 0.042254166 | AN77: =SUMIF('05.conso TB'!A:A,'May-26'!B77,'05.conso TB'!W:W)/10^5 -> 50.038984 | AO77: =AN77/$AN$46*100% -> 0.02154672 | AQ77: =AS77-'Apr-26'!AS77 -> 196.68179 | AR77: =AQ77/$AQ$46*100% -> 0.096468114 | AS77: =SUMIF('05.conso TB'!A:A,'May-26'!B77,'05.conso TB'!M:M)/10^5 -> 165.46558 | AT77: =AS77/$AS$46*100% -> 0.042750004 | AU77: =AW77-'Apr-26'!AW77 -> -38.35825 | AV77: =AU77/$C$46*100% -> -0.012278421 | AW77: =SUMIF('05.conso TB'!A:A,'May-26'!B77,'05.conso TB'!P:P)/10^5 -> -58.270508 | AX77: =AW77/$AW$46*100% -> -0.031544757 | AZ77: =BB77-'Apr-26'!BB77 -> 158.32354 | BA77: =AZ77/$AZ$46*100% -> 0.052162378 | BB77: =AS77+AW77 -> 107.19507 | BC77: =BB77/$BB$46*100% -> 0.018747699 | BE77: =BG77-'Apr-26'!BG77 -> 99.590514 | BF77: =BE77/$BE$46*100% -> 0.035632653 | BG77: =SUMIF('05.conso TB'!A:A,'May-26'!B77,'05.conso TB'!H:H)/10^5 -> 84.579859 | BH77: =BG77/$BG$46*100% -> 0.017999011 | BI77: =BK77-'Apr-26'!BK77 -> 0 | BJ77: =BI77/$BI$46*100% -> 0 | BK77: =SUMIF('05.conso TB'!A:A,'May-26'!B77,'05.conso TB'!I:I)/10^5 -> 0 | BL77: =BK77/$BK$46*100% -> 0 | BM77: =BO77-'Apr-26'!BO77 -> 0 | BN77: =BM77/$C$46*100% -> 0 | BO77: =SUMIF('05.conso TB'!A:A,'May-26'!B77,'05.conso TB'!J:J)/10^5 -> 0 | BP77: =BO77/$C$46*100% -> 0 | BR77: =BT77-'Apr-26'!BT77 -> 99.590514 | BS77: =BR77/$BR$46*100% -> 0.037659537 | BT77: =BG77+BK77+BO77-BQ77 -> 84.579859 | BU77: =BT77/$BT$46*100% -> 0.018846842 | BW77: =BY77-'Apr-26'!BY77 -> 0 | BX77: =BW77/$BW$46*100% -> 0 | BY77: =SUMIF('05.conso TB'!A:A,'May-26'!B77,'05.conso TB'!L:L)/10^5 -> 0 | BZ77: =BY77/$BY$46*100% -> 0 | CB77: =SUM(CB67:CB76) -> 4.69 | CE77: =AB77+AG77+AL77+AZ77+BR77+BW77 -> 184.82009 | CF77: =CE77/$CE$46*100% -> 0.010932626 | CG77: =AD77+AI77+AN77+BB77+BT77+BY77 -> 63.432399 | CH77: =CG77/$CG$46*100% -> 0.0051868338
B78: Common Expenses | C78: =E78-'Apr-26'!E78 -> 2.6478228 | D78: =C78/$C$46*100% -> 0.00084756429 | E78: =+'common exp'!O5/100000 -> 5.2634844 | F78: =E78/$E$46*100% -> 0.00081463608 | G78: =I78-'Apr-26'!I78 -> 4.413038 | H78: =G78/$G$46*100% -> 0.0033225525 | I78: =+'common exp'!O6/100000 -> 8.772474 | J78: =I78/$I$46*100% -> 0.00349563 | K78: =M78-'Apr-26'!M78 -> 0 | L78: =K78/$C$46*100% -> 0 | M78: 0 | N78: =M78/$C$46*100% -> 0 | O78: =Q78-'Apr-26'!Q78 -> 2.6478228 | P78: =O78/$O$46*100% -> 0.0021318098 | Q78: =+'common exp'!O7/100000 -> 5.2634844 | R78: =Q78/$Q$46*100% -> 0.002415723 | S78: =U78-'Apr-26'!U78 -> 0 | U78: 0 | V78: =U78/$U$46*100% -> 0 | W78: =Y78-'Apr-26'!Y78 -> 0 | X78: =W78/$W$46*100% -> 0 | Y78: 0 | Z78: =Y78/$Y$46*100% -> 0 | AB78: =AD78-'Apr-26'!AD78 -> 9.7086836 | AC78: =AB78/$AB$46*100% -> 0.0010528434 | AD78: =E78+I78+M78+Q78+U78+Y78 -> 19.299443 | AE78: =AD78/$AD$46*100% -> 0.0013353278 | AG78: =AI78-'Apr-26'!AI78 -> -18.976063 | AH78: =AG78/$AG$46*100% -> -0.051634284 | AI78: =+'common exp'!O11/100000 -> -37.721638 | AJ78: =AI78/$AI$46*100% -> -0.051113146 | AL78: =AN78-'Apr-26'!AN78 -> 4.413038 | AM78: =AL78/$AL$46*100% -> 0.0037264793 | AN78: =+'common exp'!O8/100000 -> 8.772474 | AO78: =AN78/$AN$46*100% -> 0.0037774156 | AQ78: =AS78-'Apr-26'!AS78 -> 4.8543418 | AR78: =AQ78/$AQ$46*100% -> 0.0023809484 | AS78: =+'common exp'!O9/100000 -> 9.6497214 | AT78: =AS78/$AS$46*100% -> 0.0024931205 | AU78: =AW78-'Apr-26'!AW78 -> 0 | AV78: =AU78/$C$46*100% -> 0 | AW78: =SUMIF('05.conso TB'!A:A,'May-26'!B78,'05.conso TB'!P:P)/10^5 -> 0 | AX78: =AW78/$AW$46*100% -> 0 | AZ78: =BB78-'Apr-26'!BB78 -> 4.8543418 | BA78: =AZ78/$AZ$46*100% -> 0.0015993453 | BB78: =AS78+AW78 -> 9.6497214 | BC78: =BB78/$BB$46*100% -> 0.0016876715 | BE78: =BG78-'Apr-26'!BG78 -> 0 | BF78: =BE78/$BE$46*100% -> 0 | BG78: =SUMIF('05.conso TB'!A:A,'May-26'!B78,'05.conso TB'!H:H)/10^5 -> 0 | BH78: =BG78/$BG$46*100% -> 0 | BI78: =BK78-'Apr-26'!BK78 -> 0 | BJ78: =BI78/$BI$46*100% -> 0 | BK78: =SUMIF('05.conso TB'!A:A,'May-26'!B78,'05.conso TB'!I:I)/10^5 -> 0 | BL78: =BK78/$BK$46*100% -> 0 | BM78: =BO78-'Apr-26'!BO78 -> 0 | BN78: =BM78/$C$46*100% -> 0 | BO78: =SUMIF('05.conso TB'!A:A,'May-26'!B78,'05.conso TB'!J:J)/10^5 -> 0 | BP78: =BO78/$C$46*100% -> 0 | BR78: =BT78-'Apr-26'!BT78 -> 0 | BS78: =BR78/$BR$46*100% -> 0 | BT78: =BG78+BK78+BO78-BQ78 -> 0 | BU78: =BT78/$BT$46*100% -> 0 | BW78: =BY78-'Apr-26'!BY78 -> 0 | BX78: =BW78/$BW$46*100% -> 0 | BY78: =SUMIF('05.conso TB'!A:A,'May-26'!B78,'05.conso TB'!L:L)/10^5 -> 0 | BZ78: =BY78/$BY$46*100% -> 0 | CB78: =CD78-'Apr-26'!CD78 -> 0 | CE78: =AB78+AG78+AL78+AZ78+BR78+BW78 -> 8.8817842e-16 | CF78: =CE78/$CE$46*100% -> 5.2538241e-20 | CG78: =AD78+AI78+AN78+BB78+BT78+BY78 -> 1.7763568e-15 | CH78: =CG78/$CG$46*100% -> 1.4525176e-19
B79: HO Expenses | C79: =E79-'Apr-26'!E79 -> 6.3227911 | D79: =C79/$C$46*100% -> 0.0020239164 | E79: =+'common exp'!D18 -> 10.33104 | F79: =E79/$E$46*100% -> 0.0015989481 | G79: =I79-'Apr-26'!I79 -> 10.537985 | H79: =G79/$G$46*100% -> 0.0079339923 | I79: =+'common exp'!D19 -> 17.218401 | J79: =I79/$I$46*100% -> 0.0068611385 | K79: =M79-'Apr-26'!M79 -> 0 | L79: =K79/$C$46*100% -> 0 | M79: 0 | N79: =M79/$C$46*100% -> 0 | O79: =Q79-'Apr-26'!Q79 -> 6.3227911 | P79: =O79/$O$46*100% -> 0.0050905929 | Q79: =+'common exp'!D20 -> 10.33104 | R79: =Q79/$Q$46*100% -> 0.0047415229 | S79: =U79-'Apr-26'!U79 -> -52.689926 | U79: =-'common exp'!D23 -> -86.092003 | V79: =U79/$U$46*100% -> -1.7662592 | W79: =Y79-'Apr-26'!Y79 -> 0 | X79: =W79/$W$46*100% -> 0 | Y79: 0 | Z79: =Y79/$Y$46*100% -> 0 | AB79: =AD79-'Apr-26'!AD79 -> -29.506359 | AC79: =AB79/$AB$46*100% -> -0.0031997722 | AD79: =E79+I79+M79+Q79+U79+Y79 -> -48.211522 | AE79: =AD79/$AD$46*100% -> -0.0033357537 | AG79: =AI79-'Apr-26'!AI79 -> 7.3765896 | AH79: =AG79/$AG$46*100% -> 0.020071862 | AI79: =+'common exp'!D17 -> 12.05288 | AJ79: =AI79/$AI$46*100% -> 0.016331757 | AL79: =AN79-'Apr-26'!AN79 -> 10.537985 | AM79: =AL79/$AL$46*100% -> 0.0088985374 | AN79: =+'common exp'!D21 -> 17.218401 | AO79: =AN79/$AN$46*100% -> 0.0074142204 | AQ79: =AS79-'Apr-26'!AS79 -> 11.591784 | AR79: =AQ79/$AQ$46*100% -> 0.0056855162 | AS79: =+'common exp'!D22 -> 18.940241 | AT79: =AS79/$AS$46*100% -> 0.0048934369 | AU79: =AW79-'Apr-26'!AW79 -> 0 | AV79: =AU79/$C$46*100% -> 0 | AW79: =SUMIF('05.conso TB'!A:A,'May-26'!B79,'05.conso TB'!P:P)/10^5 -> 0 | AX79: =AW79/$AW$46*100% -> 0 | AZ79: =BB79-'Apr-26'!BB79 -> 11.591784 | BA79: =AZ79/$AZ$46*100% -> 0.0038191099 | BB79: =AS79+AW79 -> 18.940241 | BC79: =BB79/$BB$46*100% -> 0.003312521 | BE79: =BG79-'Apr-26'!BG79 -> 0 | BF79: =BE79/$BE$46*100% -> 0 | BG79: =SUMIF('05.conso TB'!A:A,'May-26'!B79,'05.conso TB'!H:H)/10^5 -> 0 | BH79: =BG79/$BG$46*100% -> 0 | BI79: =BK79-'Apr-26'!BK79 -> 0 | BJ79: =BI79/$BI$46*100% -> 0 | BK79: =SUMIF('05.conso TB'!A:A,'May-26'!B79,'05.conso TB'!I:I)/10^5 -> 0 | BL79: =BK79/$BK$46*100% -> 0 | BM79: =BO79-'Apr-26'!BO79 -> 0 | BN79: =BM79/$C$46*100% -> 0 | BO79: =SUMIF('05.conso TB'!A:A,'May-26'!B79,'05.conso TB'!J:J)/10^5 -> 0 | BP79: =BO79/$C$46*100% -> 0 | BR79: =BT79-'Apr-26'!BT79 -> 0 | BS79: =BR79/$BR$46*100% -> 0 | BT79: =BG79+BK79+BO79-BQ79 -> 0 | BU79: =BT79/$BT$46*100% -> 0 | BW79: =BY79-'Apr-26'!BY79 -> 0 | BX79: =BW79/$BW$46*100% -> 0 | BY79: =SUMIF('05.conso TB'!A:A,'May-26'!B79,'05.conso TB'!L:L)/10^5 -> 0 | BZ79: =BY79/$BY$46*100% -> 0 | CB79: =CD79-'Apr-26'!CD79 -> 0 | CE79: =AB79+AG79+AL79+AZ79+BR79+BW79 -> -3.5527137e-15 | CF79: =CE79/$CE$46*100% -> -2.1015296e-19 | CG79: =AD79+AI79+AN79+BB79+BT79+BY79 -> 0 | CH79: =CG79/$CG$46*100% -> 0
B80: Total Administrative Expenses | C80: =SUM(C74:C79) -> -20.064486 | D80: =SUM(D74:D79) -> -0.0064226133 | E80: =SUM(E74:E79) -> -11.790418 | F80: =E80/$E$46*100% -> -0.0018248178 | G80: =SUM(G74:G79) -> 7.0575018 | H80: =G80/$G$46*100% -> 0.0053135551 | I80: =SUM(I74:I79) -> 12.972141 | J80: =I80/$I$46*100% -> 0.0051691013 | K80: =SUM(K74:K79) -> 1.5497999 | L80: =SUM(L74:L79) -> 0.00049608873 | M80: =SUM(M74:M79) -> 2.9069121 | N80: =SUM(N74:N79) -> 0.0009304984 | O80: =SUM(O74:O79) -> 4.021459 | P80: =O80/$O$46*100% -> 0.003237749 | Q80: =SUM(Q74:Q79) -> 12.768041 | R80: =Q80/$Q$46*100% -> 0.0058600061 | S80: =SUM(S74:S79) -> -17.146128 | U80: =SUM(U74:U79) -> -42.448208 | V80: =U80/$U$46*100% -> -0.87086529 | W80: =SUM(W74:W79) -> 0.882276 | X80: =W80/$W$46*100% -> 0.00023722528 | Y80: =SUM(Y74:Y79) -> 0.4570548 | Z80: =Y80/$Y$46*100% -> 0.00012048004 | AB80: =SUM(AB74:AB79) -> -23.699578 | AC80: =AB80/$AB$46*100% -> -0.0025700646 | AD80: =SUM(AD74:AD79) -> -25.134477 | AE80: =AD80/$AD$46*100% -> -0.0017390537 | AG80: =SUM(AG74:AG79) -> 8.7872562 | AH80: =AG80/$AG$46*100% -> 0.023910316 | AI80: =SUM(AI74:AI79) -> 6.9205023 | AJ80: =SUM(AJ74:AJ79) -> 0.0093773404 | AL80: =SUM(AL74:AL79) -> 78.81937 | AM80: =AL80/$AL$46*100% -> 0.066557041 | AN80: =SUM(AN74:AN79) -> 101.7528 | AO80: =SUM(AO74:AO79) -> 0.043814619 | AQ80: =SUM(AQ74:AQ79) -> 262.16596 | AR80: =AQ80/$AQ$46*100% -> 0.12858666 | AS80: =SUM(AS74:AS79) -> 299.66379 | AT80: =SUM(AT74:AT79) -> 0.077421711 | AU80: =SUM(AU74:AU79) -> -37.721916 | AV80: =SUM(AV74:AV79) -> -0.012074731 | AW80: =SUM(AW74:AW79) -> -56.744963 | AX80: =SUM(AX74:AX79) -> -0.030718903 | AZ80: =SUM(AZ74:AZ79) -> 224.44404 | BA80: =AZ80/$AZ$46*100% -> 0.0739469 | BB80: =SUM(BB74:BB79) -> 242.91883 | BC80: =SUM(BC74:BC79) -> 0.042484873 | BE80: =SUM(BE74:BE79) -> 128.75562 | BF80: =BE80/$BE$46*100% -> 0.046067683 | BG80: =SUM(BG74:BG79) -> 131.13737 | BH80: =SUM(BH74:BH79) -> 0.02790668 | BI80: =SUM(BI74:BI79) -> 1.31876 | BJ80: =BI80/$BI$46*100% -> 0.068617105 | BK80: =SUM(BK74:BK79) -> 2.76676 | BL80: =SUM(BL74:BL79) -> 0.071678235 | BM80: =SUM(BM74:BM79) -> 0 | BN80: =SUM(BN74:BN79) -> 0 | BO80: =SUM(BO74:BO79) -> 0 | BP80: =SUM(BP74:BP79) -> 0 | BR80: =BE80+BI80+BM80-BO80 -> 130.07438 | BS80: =BR80/$BR$46*100% -> 0.049186821 | BT80: =BG80+BK80+BO80-BQ80 -> 133.90413 | BU80: =BT80/$BT$46*100% -> 0.029837719 | BW80: =SUM(BW74:BW79) -> 4.11714 | BX80: =BW80/$BW$46*100% -> 0.0090980963 | BY80: =SUM(BY74:BY79) -> 4.78438 | BZ80: =BY80/$BY$46*100% -> 0.0022140849 | CB80: =SUM(CB74:CB79) -> 9.38 | CC80: =SUM(CC74:CC79) -> 7.38 | CE80: =SUM(CE74:CE79) -> 422.54261 | CF80: =CE80/$CE$46*100% -> 0.024994579 | CG80: =SUM(CG74:CG79) -> 465.14616 | CH80: =CG80/$CG$46*100% -> 0.038034756
B81: Total Cost of goods sold | C81: =C53+C60+C65+C72+C80 -> 2741.4162 | D81: =D53+D60+D65+D72+D80 -> 0.87752339 | E81: =E53+E60+E65+E72+E80 -> 5350.7751 | F81: =E81/$E$46*100% -> 0.82814617 | G81: =G53+G60+G65+G72+G80 -> 1115.7262 | H81: =G81/$G$46*100% -> 0.84002428 | I81: =I53+I60+I65+I72+I80 -> 2071.9569 | J81: =I81/$I$46*100% -> 0.82562739 | K81: =K53+K60+K65+K72+K80 -> 4.2825299 | L81: =L53+L60+L65+L72+L80 -> 0.0013708317 | M81: =M53+M60+M65+M72+M80 -> 8.3350521 | N81: =N53+N60+N65+N72+N80 -> 0.0026680382 | O81: =O53+O60+O65+O72+O80 -> 938.42051 | P81: =O81/$O$46*100% -> 0.75553924 | Q81: =Q53+Q60+Q65+Q72+Q80 -> 1740.1778 | R81: =Q81/$Q$46*100% -> 0.79867007 | S81: =S53+S60+S65+S72+S80 -> 18.091343 | U81: =U53+U60+U65+U72+U80 -> 77.777651 | V81: =U81/$U$46*100% -> 1.5956823 | W81: =W53+W60+W65+W72+W80 -> 3783.4893 | X81: =W81/$W$46*100% -> 1.0172999 | Y81: =Y53+Y60+Y65+Y72+Y80 -> 3823.0189 | Z81: =Y81/$Y$46*100% -> 1.0077511 | AB81: =AB53+AB60+AB65+AB72+AB80 -> 8386.0322 | AC81: =AB81/$AB$46*100% -> 0.9094105 | AD81: =AD53+AD60+AD65+AD72+AD80 -> 12468.417 | AE81: =AD81/$AD$46*100% -> 0.86268935 | AG81: =AG53+AG60+AG65+AG72+AG80 -> 330.73493 | AH81: =AG81/$AG$46*100% -> 0.89993698 | AI81: =AI53+AI60+AI65+AI72+AI80 -> 629.50297 | AJ81: =AJ53+AJ60+AJ65+AJ72+AJ80 -> 0.85298196 | AL81: =AL53+AL60+AL65+AL72+AL80 -> 1298.1334 | AM81: =AL81/$AL$46*100% -> 1.0961762 | AN81: =AN53+AN60+AN65+AN72+AN80 -> 2271.675 | AO81: =AO53+AO60+AO65+AO72+AO80 -> 0.97818024 | AQ81: =AQ53+AQ60+AQ65+AQ72+AQ80 -> 1297.0038 | AR81: =AQ81/$AQ$46*100% -> 0.63615198 | AS81: =AS53+AS60+AS65+AS72+AS80 -> 2559.8142 | AT81: =AT53+AT60+AT65+AT72+AT80 -> 0.6613585 | AU81: =AU53+AU60+AU65+AU72+AU80 -> 692.44904 | AV81: =AV53+AV60+AV65+AV72+AV80 -> 0.22165195 | AW81: =AW53+AW60+AW65+AW72+AW80 -> 1417.2268 | AX81: =AX53+AX60+AX65+AX72+AX80 -> 0.76721616 | AZ81: =AZ53+AZ60+AZ65+AZ72+AZ80 -> 1989.4528 | BA81: =AZ81/$AZ$46*100% -> 0.65545901 | BB81: =BB53+BB60+BB65+BB72+BB80 -> 3977.041 | BC81: =BC53+BC60+BC65+BC72+BC80 -> 0.69555779 | BE81: =BE53+BE60+BE65+BE72+BE80 -> 2910.2176 | BF81: =BE81/$BE$46*100% -> 1.0412515 | BG81: =BG53+BG60+BG65+BG72+BG80 -> 4789.5256 | BH81: =BH53+BH60+BH65+BH72+BH80 -> 1.0192347 | BI81: =BI53+BI60+BI65+BI72+BI80 -> 8.6272989 | BJ81: =BI81/$BI$46*100% -> 0.44889159 | BK81: =BK53+BK60+BK65+BK72+BK80 -> 34.186058 | BL81: =BL53+BL60+BL65+BL72+BL80 -> 0.88565553 | BM81: =BM53+BM60+BM65+BM72+BM80 -> 0 | BN81: =BN53+BN60+BN65+BN72+BN80 -> 0 | BO81: =BO53+BO60+BO65+BO72+BO80 -> 0 | BP81: =BP53+BP60+BP65+BP72+BP80 -> 0 | BQ81: =BQ53+BQ60+BQ65+BQ72+BQ80 -> 250.06819 | BR81: =BR53+BR60+BR65+BR72+BR80 -> 2749.1996 | BS81: =BR81/$BR$46*100% -> 1.0395928 | BT81: =BG81+BK81+BO81-BQ81 -> 4573.6434 | BU81: =BT81/$BT$46*100% -> 1.0191402 | BW81: =BW53+BW60+BW65+BW72+BW80 -> 402.67143 | BX81: =BW81/$BW$46*100% -> 0.88982726 | BY81: =BY53+BY60+BY65+BY72+BY80 -> 2058.328 | BZ81: =BY81/$BY$46*100% -> 0.95253994 | CB81: =CB53+CB60+CB65+CB72+CB80 -> 10038.672 | CC81: =CC53+CC60+CC65+CC72+CC80 -> 17657.593 | CE81: =CE53+CE60+CE65+CE72+CE80 -> 15156.224 | CF81: =CE81/$CE$46*100% -> 0.89653312 | CG81: =CG53+CG60+CG65+CG72+CG80 -> 8328.3941 | CH81: =CG81/$CG$46*100% -> 0.68100839
B82: EBDITA | C82: =C46-C81 -> 382.62154 | D82: =D46-D81 -> 0.12247661 | E82: =E46-E81 -> 1110.3731 | F82: =E82/$E$46*100% -> 0.17185383 | G82: =G46-G81 -> 212.48089 | H82: =G82/$G$46*100% -> 0.15997572 | I82: =I46-I81 -> 437.59757 | J82: =I82/$I$46*100% -> 0.17437261 | K82: =K46-K81 -> 19.081349 | L82: =L46-L81 -> 0.0061079124 | M82: =M46-M81 -> 56.348128 | N82: =N46-N81 -> 0.018036955 | O82: =O46-O81 -> 303.63346 | P82: =O82/$O$46*100% -> 0.24446076 | Q82: =Q46-Q81 -> 438.66658 | R82: =Q82/$Q$46*100% -> 0.20132993 | S82: =S46-S81 -> -18.114826 | U82: =U46-U81 -> -29.035086 | V82: =U82/$U$46*100% -> -0.59568235 | W82: =W46-W81 -> -64.340984 | X82: =W82/$W$46*100% -> -0.017299924 | Y82: =Y46-Y81 -> -29.404583 | Z82: =Y82/$Y$46*100% -> -0.0077510734 | AB82: =AB46-AB81 -> 835.36143 | AC82: =AB82/$AB$46*100% -> 0.090589499 | AD82: =AD46-AD81 -> 1984.5457 | AE82: =AD82/$AD$46*100% -> 0.13731065 | AG82: =AG46-AG81 -> 36.774061 | AH82: =AG82/$AG$46*100% -> 0.10006302 | AI82: =AI46-AI81 -> 108.49971 | AJ82: =AJ46-AJ81 -> 0.14701804 | AL82: =AL46-AL81 -> -113.8955 | AM82: =AL82/$AL$46*100% -> -0.096176198 | AN82: =AN46-AN81 -> 50.67308 | AO82: =AO46-AO81 -> 0.021819761 | AQ82: =AQ46-AQ81 -> 741.82315 | AR82: =AQ82/$AQ$46*100% -> 0.36384802 | AS82: =AS46-AS81 -> 1310.7253 | AT82: =AT46-AT81 -> 0.3386415 | AU82: =AU46-AU81 -> 303.92958 | AV82: =AV46-AV81 -> 0.095774371 | AW82: =AW46-AW81 -> 430.00593 | AX82: =AX46-AX81 -> 0.23278384 | AY82: =AY25-AY53 -> 0 | AZ82: =AZ46-AZ81 -> 1045.7527 | BA82: =AZ82/$AZ$46*100% -> 0.34454099 | BB82: =BB46-BB81 -> 1740.7312 | BC82: =BC46-BC81 -> 0.30444221 | BE82: =BE46-BE81 -> -115.29488 | BF82: =BE82/$BE$46*100% -> -0.041251544 | BG82: =BG46-BG81 -> -90.386341 | BH82: =BH46-BH81 -> -0.019234659 | BI82: =BI46-BI81 -> 10.591816 | BJ82: =BI82/$BI$46*100% -> 0.55110841 | BK82: =BK46-BK81 -> 4.413665 | BL82: =BL46-BL81 -> 0.11434447 | BM82: =BM46-BM81 -> 0 | BN82: =BN46-BN81 -> 0 | BO82: =BO46-BO81 -> 0.07617 | BP82: =BP46-BP81 -> 2.4381908e-05 | BQ82: =BQ46-BQ81 -> 0 | BR82: =BR46-BR81 -> -104.70306 | BS82: =BR82/$BR$46*100% -> -0.039592816 | BT82: =BG82+BK82+BO82-BQ82 -> -85.896506 | BU82: =BT82/$BT$46*100% -> -0.019140229 | BW82: =BW46-BW81 -> 49.856209 | BX82: =BW82/$BW$46*100% -> 0.11017274 | BY82: =BY46-BY81 -> 102.55566 | BZ82: =BY82/$BY$46*100% -> 0.047460056 | CB82: 0 | CC82: =CC46-CC81 -> 0 | CE82: =CE46-CE81 -> 1749.1459 | CF82: =CE82/$CE$46*100% -> 0.10346688 | CG82: =CG46-CG81 -> 3901.1088 | CH82: =CG82/$CG$46*100% -> 0.31899161
B83: Depreciation | C83: =E83 -> 0 | E83: =SUMIF('05.conso TB'!A:A,'May-26'!B83,'05.conso TB'!R:R) -> 0 | G83: 0 | I83: 0 | K83: 0 | M83: =SUMIF('05.conso TB'!A:A,'May-26'!B83,'05.conso TB'!T:T)/10^5 -> 0 | O83: 0 | Q83: =SUMIF('05.conso TB'!A:A,'May-26'!B83,'05.conso TB'!U:U)/10^5 -> 0 | S83: 0 | U83: =SUMIF('05.conso TB'!A:A,'May-26'!B83,'05.conso TB'!V:V)/10^5 -> 0 | W83: 0 | Y83: =SUMIF('05.conso TB'!A:A,'May-26'!B83,'05.conso TB'!G:G)/10^5 -> 0 | AB83: 0 | AD83: =E83+I83+M83+Q83+U83+Y83 -> 0 | AG83: 0 | AI83: =SUMIF('05.conso TB'!A:A,'May-26'!B83,'05.conso TB'!Q:Q)/10^5 -> 0 | AL83: 0 | AN83: =SUMIF('05.conso TB'!A:A,'May-26'!B83,'05.conso TB'!W:W)/10^5 -> 0 | AQ83: 0 | AS83: 0 | AU83: 0 | AW83: =SUMIF('05.conso TB'!A:A,'May-26'!B83,'05.conso TB'!P:P)/10^5 -> 0 | AZ83: 0 | BB83: =AS83+AW83 -> 0 | BE83: 0 | BI83: 0 | BK83: =SUMIF('05.conso TB'!A:A,'May-26'!B83,'05.conso TB'!I:I)/10^5 -> 0 | BM83: 0 | BO83: =SUMIF('05.conso TB'!A:A,'May-26'!B83,'05.conso TB'!J:J)/10^5 -> 0 | BR83: 0 | BT83: =BG83+BK83+BO83-BQ83 -> 0 | BW83: 0 | BY83: =SUMIF('05.conso TB'!A:A,'May-26'!B83,'05.conso TB'!L:L)/10^5 -> 0 | CB83: 0 | CE83: =AB83+AG83+AL83+AZ83+BR83+BW83 -> 0 | CG83: =AD83+AI83+AN83+BB83+BT83+BY83 -> 0
B84: Bank Charges & Commission | C84: =E84 -> 21.387097 | E84: =SUMIF('05.conso TB'!A:A,'May-26'!B84,'05.conso TB'!R:R)/10^5 -> 21.387097 | G84: =I84 -> 11.838293 | I84: =SUMIF('05.conso TB'!A:A,'May-26'!B84,'05.conso TB'!S:S)/10^5 -> 11.838293 | K84: =M84 -> 0 | M84: =SUMIF('05.conso TB'!A:A,'May-26'!B84,'05.conso TB'!T:T)/10^5 -> 0 | O84: =Q84 -> 1.4571534 | Q84: =SUMIF('05.conso TB'!A:A,'May-26'!B84,'05.conso TB'!U:U)/10^5 -> 1.4571534 | S84: =U84 -> -3.0507387 | U84: =SUMIF('05.conso TB'!A:A,'May-26'!B84,'05.conso TB'!V:V)/10^5 -> -3.0507387 | W84: =Y84 -> 0.2834436 | Y84: =SUMIF('05.conso TB'!A:A,'May-26'!B84,'05.conso TB'!G:G)/10^5 -> 0.2834436 | AB84: =AD84 -> 31.915248 | AD84: =E84+I84+M84+Q84+U84+Y84 -> 31.915248 | AG84: =AI84 -> 0.0025891 | AI84: =SUMIF('05.conso TB'!A:A,'May-26'!B84,'05.conso TB'!Q:Q)/10^5 -> 0.0025891 | AL84: =AN84 -> 14.216924 | AN84: =SUMIF('05.conso TB'!A:A,'May-26'!B84,'05.conso TB'!W:W)/10^5 -> 14.216924 | AQ84: =AS84 -> 10.494754 | AS84: =SUMIF('05.conso TB'!A:A,'May-26'!B84,'05.conso TB'!M:M)/10^5 -> 10.494754 | AU84: =AW84 -> 9.4096732 | AW84: =SUMIF('05.conso TB'!A:A,'May-26'!B84,'05.conso TB'!P:P)/10^5 -> 9.4096732 | AZ84: =BB84 -> 19.904428 | BB84: =AS84+AW84 -> 19.904428 | BE84: =BG84 -> 0 | BI84: =BK84 -> 0 | BK84: =SUMIF('05.conso TB'!A:A,'May-26'!B84,'05.conso TB'!I:I)/10^5 -> 0 | BM84: =BO84 -> 0 | BO84: =SUMIF('05.conso TB'!A:A,'May-26'!B84,'05.conso TB'!J:J)/10^5 -> 0 | BR84: =BT84 -> 0 | BT84: =BG84+BK84+BO84-BQ84 -> 0 | BW84: =BY84 -> 0 | BY84: =SUMIF('05.conso TB'!A:A,'May-26'!B84,'05.conso TB'!L:L)/10^5 -> 0 | CB84: =CD84 -> 0 | CE84: =AB84+AG84+AL84+AZ84+BR84+BW84 -> 66.039188 | CG84: =AD84+AI84+AN84+BB84+BT84+BY84 -> 66.039188
B85: Interest Expense - Other | C85: =E85 -> 12.715768 | E85: =SUMIF('05.conso TB'!A:A,'May-26'!B85,'05.conso TB'!R:R)/10^5 -> 12.715768 | G85: =I85 -> 2.3349707 | I85: =SUMIF('05.conso TB'!A:A,'May-26'!B85,'05.conso TB'!S:S)/10^5 -> 2.3349707 | K85: =M85 -> 0.1293892 | M85: =SUMIF('05.conso TB'!A:A,'May-26'!B85,'05.conso TB'!T:T)/10^5 -> 0.1293892 | O85: =Q85 -> 0.00014 | Q85: =SUMIF('05.conso TB'!A:A,'May-26'!B85,'05.conso TB'!U:U)/10^5 -> 0.00014 | S85: =U85 -> 0.00186 | U85: =SUMIF('05.conso TB'!A:A,'May-26'!B85,'05.conso TB'!V:V)/10^5 -> 0.00186 | W85: =Y85 -> 0.21 | Y85: =SUMIF('05.conso TB'!A:A,'May-26'!B85,'05.conso TB'!G:G)/10^5 -> 0.21 | AB85: =AD85 -> 15.392128 | AD85: =E85+I85+M85+Q85+U85+Y85 -> 15.392128 | AG85: =AI85 -> 0.4405506 | AI85: =SUMIF('05.conso TB'!A:A,'May-26'!B85,'05.conso TB'!Q:Q)/10^5 -> 0.4405506 | AL85: =AN85 -> 0.1430595 | AN85: =SUMIF('05.conso TB'!A:A,'May-26'!B85,'05.conso TB'!W:W)/10^5 -> 0.1430595 | AQ85: =AS85 -> 23.097049 | AS85: =SUMIF('05.conso TB'!A:A,'May-26'!B85,'05.conso TB'!M:M)/10^5 -> 23.097049 | AU85: =AW85 -> 0 | AW85: =SUMIF('05.conso TB'!A:A,'May-26'!B85,'05.conso TB'!P:P)/10^5 -> 0 | AZ85: =BB85 -> 23.097049 | BB85: =AS85+AW85 -> 23.097049 | BE85: =BG85 -> 0 | BI85: =BK85 -> 0 | BK85: =SUMIF('05.conso TB'!A:A,'May-26'!B85,'05.conso TB'!I:I)/10^5 -> 0 | BM85: =BO85 -> 0 | BO85: =SUMIF('05.conso TB'!A:A,'May-26'!B85,'05.conso TB'!J:J)/10^5 -> 0 | BR85: =BT85 -> 0 | BT85: =BG85+BK85+BO85-BQ85 -> 0 | BW85: =BY85 -> 0 | BY85: =SUMIF('05.conso TB'!A:A,'May-26'!B85,'05.conso TB'!L:L)/10^5 -> 0 | CB85: =CD85 -> 0 | CE85: =AB85+AG85+AL85+AZ85+BR85+BW85 -> 39.072788 | CG85: =AD85+AI85+AN85+BB85+BT85+BY85 -> 39.072788
B86: Interest on Term Loan | C86: =E86 -> 0 | E86: =SUMIF('05.conso TB'!A:A,'May-26'!B86,'05.conso TB'!R:R)/10^5 -> 0 | G86: =I86 -> 0 | I86: =SUMIF('05.conso TB'!A:A,'May-26'!B86,'05.conso TB'!S:S)/10^5 -> 0 | K86: =M86 -> 0 | M86: =SUMIF('05.conso TB'!A:A,'May-26'!B86,'05.conso TB'!T:T)/10^5 -> 0 | O86: =Q86 -> 0 | Q86: =SUMIF('05.conso TB'!A:A,'May-26'!B86,'05.conso TB'!U:U)/10^5 -> 0 | S86: =U86 -> 0 | U86: =SUMIF('05.conso TB'!A:A,'May-26'!B86,'05.conso TB'!V:V)/10^5 -> 0 | W86: =Y86 -> 0 | Y86: =SUMIF('05.conso TB'!A:A,'May-26'!B86,'05.conso TB'!G:G)/10^5 -> 0 | AB86: =AD86 -> 0 | AD86: =E86+I86+M86+Q86+U86+Y86 -> 0 | AG86: =AI86 -> 0 | AI86: =SUMIF('05.conso TB'!A:A,'May-26'!B86,'05.conso TB'!Q:Q)/10^5 -> 0 | AL86: =AN86 -> 0 | AN86: =SUMIF('05.conso TB'!A:A,'May-26'!B86,'05.conso TB'!W:W)/10^5 -> 0 | AQ86: =AS86 -> 0 | AS86: =SUMIF('05.conso TB'!A:A,'May-26'!B86,'05.conso TB'!M:M)/10^5 -> 0 | AU86: =AW86 -> 0 | AW86: =SUMIF('05.conso TB'!A:A,'May-26'!B86,'05.conso TB'!P:P)/10^5 -> 0 | AZ86: =BB86 -> 0 | BB86: =AS86+AW86 -> 0 | BE86: =BG86 -> 0 | BG86: =SUMIF('05.conso TB'!A:A,'May-26'!B86,'05.conso TB'!H:H)/10^5 -> 0 | BI86: =BK86 -> 0 | BK86: =SUMIF('05.conso TB'!A:A,'May-26'!B86,'05.conso TB'!I:I)/10^5 -> 0 | BM86: =BO86 -> 0 | BO86: =SUMIF('05.conso TB'!A:A,'May-26'!B86,'05.conso TB'!J:J)/10^5 -> 0 | BR86: =BT86 -> 0 | BT86: =BG86+BK86+BO86-BQ86 -> 0 | BW86: =BY86 -> 0 | BY86: =SUMIF('05.conso TB'!A:A,'May-26'!B86,'05.conso TB'!L:L)/10^5 -> 0 | CB86: =CD86 -> 0 | CE86: =AB86+AG86+AL86+AZ86+BR86+BW86 -> 0 | CG86: =AD86+AI86+AN86+BB86+BT86+BY86 -> 0
B87: Interest on Working Capital & Term Loan | C87: =E87 -> 204.22438 | E87: =SUMIF('05.conso TB'!A:A,'May-26'!B87,'05.conso TB'!R:R)/10^5 -> 204.22438 | G87: =I87 -> 18.418334 | I87: =SUMIF('05.conso TB'!A:A,'May-26'!B87,'05.conso TB'!S:S)/10^5 -> 18.418334 | K87: =M87 -> 49.958636 | M87: =SUMIF('05.conso TB'!A:A,'May-26'!B87,'05.conso TB'!T:T)/10^5 -> 49.958636 | O87: =Q87 -> 0.9828456 | Q87: =SUMIF('05.conso TB'!A:A,'May-26'!B87,'05.conso TB'!U:U)/10^5 -> 0.9828456 | S87: =U87 -> 0 | U87: =SUMIF('05.conso TB'!A:A,'May-26'!B87,'05.conso TB'!V:V)/10^5 -> 0 | W87: =Y87 -> 0 | Y87: =SUMIF('05.conso TB'!A:A,'May-26'!B87,'05.conso TB'!G:G)/10^5 -> 0 | AB87: =AD87 -> 273.5842 | AD87: =E87+I87+M87+Q87+U87+Y87 -> 273.5842 | AG87: =AI87 -> 41.84592 | AI87: =SUMIF('05.conso TB'!A:A,'May-26'!B87,'05.conso TB'!Q:Q)/10^5 -> 41.84592 | AL87: =AN87 -> 49.238146 | AN87: =SUMIF('05.conso TB'!A:A,'May-26'!B87,'05.conso TB'!W:W)/10^5 -> 49.238146 | AQ87: =AS87 -> 115.58459 | AS87: =SUMIF('05.conso TB'!A:A,'May-26'!B87,'05.conso TB'!M:M)/10^5 -> 115.58459 | AU87: =AW87 -> 2.2382627 | AW87: =SUMIF('05.conso TB'!A:A,'May-26'!B87,'05.conso TB'!P:P)/10^5 -> 2.2382627 | AZ87: =BB87 -> 117.82285 | BB87: =AS87+AW87 -> 117.82285 | BE87: =BG87 -> 36.801485 | BG87: 36.801485 | BI87: =BK87 -> 0 | BK87: =SUMIF('05.conso TB'!A:A,'May-26'!B87,'05.conso TB'!I:I)/10^5 -> 0 | BM87: =BO87 -> 0 | BO87: =SUMIF('05.conso TB'!A:A,'May-26'!B87,'05.conso TB'!J:J)/10^5 -> 0 | BR87: =BT87 -> 36.801485 | BT87: =BG87+BK87+BO87-BQ87 -> 36.801485 | BW87: =BY87 -> 0 | BY87: =SUMIF('05.conso TB'!A:A,'May-26'!B87,'05.conso TB'!L:L)/10^5 -> 0 | CB87: =CD87 -> 0 | CE87: =AB87+AG87+AL87+AZ87+BR87+BW87 -> 519.2926 | CG87: =AD87+AI87+AN87+BB87+BT87+BY87 -> 519.2926
B88: PBT | C88: =C82-C83-C84-C86-C87-C85 -> 144.29429 | E88: =E82-E83-E84-E86-E87-E85 -> 872.04581 | G88: =G82-G83-G84-G86-G87-G85 -> 179.88929 | I88: =I82-I83-I84-I86-I87-I85 -> 405.00598 | K88: =K82-K83-K84-K86-K87-K85 -> -31.006677 | M88: =M82-M83-M84-M86-M87-M85 -> 6.2601022 | O88: =O82-O83-O84-O86-O87-O85 -> 301.19332 | Q88: =Q82-Q83-Q84-Q86-Q87-Q85 -> 436.22644 | S88: =S82-S83-S84-S86-S87-S85 -> -15.065947 | U88: =U82-U83-U84-U86-U87-U85 -> -25.986207 | W88: =W82-W83-W84-W86-W87-W85 -> -64.834428 | Y88: =Y82-Y83-Y84-Y86-Y87-Y85 -> -29.898027 | AB88: =AB82-AB83-AB84-AB86-AB87-AB85 -> 514.46986 | AC88: =AD88/AD46 -> 0.11510817 | AD88: =AD82-AD83-AD84-AD86-AD87-AD85 -> 1663.6541 | AG88: =AG82-AG83-AG84-AG86-AG87-AG85 -> -5.5149987 | AI88: =AI82-AI83-AI84-AI86-AI87-AI85 -> 66.210647 | AL88: =AL82-AL83-AL84-AL86-AL87-AL85 -> -177.49363 | AN88: =AN82-AN83-AN84-AN86-AN87-AN85 -> -12.925049 | AQ88: =AQ82-AQ83-AQ84-AQ86-AQ87-AQ85 -> 592.64676 | AS88: =AS82-AS83-AS84-AS86-AS87-AS85 -> 1161.5489 | AU88: =AU82-AU83-AU84-AU86-AU87-AU85 -> 292.28164 | AW88: =AW82-AW83-AW84-AW86-AW87-AW85 -> 418.35799 | AZ88: =AZ82-AZ83-AZ84-AZ86-AZ87-AZ85 -> 884.9284 | BB88: =BB82-BB83-BB84-BB86-BB87-BB85 -> 1579.9069 | BE88: =BE82-BE83-BE84-BE86-BE87-BE85 -> -152.09636 | BG88: =BG82-BG83-BG84-BG86-BG87-BG85 -> -127.18783 | BI88: =BI82-BI83-BI84-BI86-BI87-BI85 -> 10.591816 | BK88: =BK82-BK83-BK84-BK86-BK87-BK85 -> 4.413665 | BM88: =BM82-BM83-BM84-BM86-BM87-BM85 -> 0 | BO88: =BO82-BO83-BO84-BO86-BO87-BO85 -> 0.07617 | BQ88: =BQ82-BQ83 -> 0 | BR88: =BR82-BR83-BR84-BR86-BR87-BR85 -> -141.50455 | BT88: =BG88+BK88+BO88-BQ88 -> -122.69799 | BW88: =BW82-BW83-BW84-BW86-BW87-BW85 -> 49.856209 | BY88: =BY82-BY83-BY84-BY86-BY87-BY85 -> 102.55566 | CB88: =CB82-CB83-CB84-CB86-CB87-CB85 -> 0 | CE88: =CE82-CE83-CE84-CE86-CE87-CE85 -> 1124.7413 | CG88: =CG82-CG83-CG84-CG86-CG87-CG85 -> 3276.7043
B89: Cash PBT | C89: =C88+C83 -> 144.29429 | E89: =E88+E83 -> 872.04581 | G89: =G88+G83 -> 179.88929 | I89: =I88+I83 -> 405.00598 | K89: =K88+K83 -> -31.006677 | M89: =M88+M83 -> 6.2601022 | O89: =O88+O83 -> 301.19332 | Q89: =Q88+Q83 -> 436.22644 | S89: =S88+S83 -> -15.065947 | U89: =U88+U83 -> -25.986207 | W89: =W88+W83 -> -64.834428 | Y89: =Y88+Y83 -> -29.898027 | AB89: =AB88+AB83 -> 514.46986 | AD89: =AD88+AD83 -> 1663.6541 | AG89: =AG88+AG83 -> -5.5149987 | AI89: =AI88+AI83 -> 66.210647 | AL89: =AL88+AL83 -> -177.49363 | AN89: =AN88+AN83 -> -12.925049 | AQ89: =AQ88+AQ83 -> 592.64676 | AS89: =AS88+AS83 -> 1161.5489 | AU89: =AU88+AU83 -> 292.28164 | AW89: =AW88+AW83 -> 418.35799 | AZ89: =AZ88+AZ83 -> 884.9284 | BB89: =BB88+BB83 -> 1579.9069 | BE89: =BE88+BE83 -> -152.09636 | BG89: =BG88+BG83 -> -127.18783 | BI89: =BI88+BI83 -> 10.591816 | BK89: =BK88+BK83 -> 4.413665 | BM89: =BM88+BM83 -> 0 | BO89: =BO88+BO83 -> 0.07617 | BR89: =BR88+BR83 -> -141.50455 | BT89: =BG89+BK89+BO89-BQ89 -> -122.69799 | BW89: =BW88+BW83 -> 49.856209 | BY89: =BY88+BY83 -> 102.55566 | CB89: =CB88+CB83 -> 0 | CE89: =CE88+CE83 -> 1124.7413 | CG89: =CG88+CG83 -> 3276.7043
C90: check | E90: =#REF!+'May-26'!C82-'May-26'!E82 -> #REF! | I90: =#REF!+'May-26'!G82-'May-26'!I82 -> #REF! | M90: =#REF!+'May-26'!K82-'May-26'!M82 -> #REF! | Q90: =#REF!+'May-26'!O82-'May-26'!Q82 -> #REF! | U90: =#REF!+'May-26'!S82-'May-26'!U82 -> #REF! | Y90: =#REF!+'May-26'!W82-'May-26'!Y82 -> #REF! | AD90: =#REF!+'May-26'!AB82-'May-26'!AD82 -> #REF! | AI90: =#REF!+'May-26'!AG82-'May-26'!AI82 -> #REF! | AN90: =#REF!+'May-26'!AL82-'May-26'!AN82 -> #REF! | AS90: =#REF!+'May-26'!AQ82-'May-26'!AS82 -> #REF! | AW90: =#REF!+'May-26'!AU82-'May-26'!AW82 -> #REF! | BB90: =#REF!+'May-26'!AZ82-'May-26'!BB82 -> #REF! | BG90: =#REF!+'May-26'!BE82-'May-26'!BG82 -> #REF! | BK90: =#REF!+'May-26'!BI82-'May-26'!BK82 -> #REF! | BO90: =#REF!+'May-26'!BM82-'May-26'!BO82 -> #REF! | BT90: =#REF!+'May-26'!BR82-'May-26'!BT82 -> #REF! | BY90: =#REF!+'May-26'!BW82-'May-26'!BY82 -> #REF! | CG90: =#REF!+'May-26'!CE82-'May-26'!CG82 -> #REF!
C91: check | E91: =#REF!+'May-26'!C88-'May-26'!E88 -> #REF! | I91: =#REF!+'May-26'!G88-'May-26'!I88 -> #REF! | M91: =#REF!+'May-26'!K88-'May-26'!M88 -> #REF! | Q91: =#REF!+'May-26'!O88-'May-26'!Q88 -> #REF! | U91: =#REF!+'May-26'!S88-'May-26'!U88 -> #REF! | Y91: =#REF!+'May-26'!W88-'May-26'!Y88 -> #REF! | AD91: =#REF!+'May-26'!AB88-'May-26'!AD88 -> #REF! | AI91: =#REF!+'May-26'!AG88-'May-26'!AI88 -> #REF! | AN91: =#REF!+'May-26'!AL88-'May-26'!AN88 -> #REF! | AS91: =#REF!+'May-26'!AQ88-'May-26'!AS88 -> #REF! | AW91: =#REF!+'May-26'!AU88-'May-26'!AW88 -> #REF! | BB91: =#REF!+'May-26'!AZ88-'May-26'!BB88 -> #REF! | BG91: =#REF!+'May-26'!BE88-'May-26'!BG88 -> #REF! | BK91: =#REF!+'May-26'!BI88-'May-26'!BK88 -> #REF! | BO91: =#REF!+'May-26'!BM88-'May-26'!BO88 -> #REF! | BT91: =#REF!+'May-26'!BR88-'May-26'!BT88 -> #REF! | BY91: =#REF!+'May-26'!BW88-'May-26'!BY88 -> #REF! | CE91: =+CE89-Summary!AC19 -> 1124.7413 | CG91: =#REF!+'May-26'!CE88-'May-26'!CG88 -> #REF!
G92: =G81-G53+G52 -> 301.73412 | O92: =O81-O53+O52 -> 124.33797 | AF92: =AG92/$AG$1*10^5 -> 62.654652 | AG92: =AG81-AG53+AG52 -> 230.27402 | AL92: =AL81-AL53+AL52 -> 250.29208 | AP92: =AQ92/AQ1*10^5 -> 155.84527 | AQ92: =AQ81-AQ53+AQ52 -> 930.43524 | AZ92: =AZ81-AZ53+AZ52 -> 1170.758 | CE92: =CE81-CE53+CE52 -> 3071.0786 | CG92: =+CG89-Summary!AD19 -> 3276.7043
G93: =G92/G1*10^5 -> #DIV/0! | O93: =O92/O1*10^5 -> #DIV/0! | AL93: =AL92/AL1*10^5 -> 56.67538
B103: Inventory Data | E103: PIL-1 | I103: PIL-2 | Q103: =+'Stock sheet'!A25 -> HPBL4 | AI103: OEL-1 | AN103: PPL | AS103: KPW-1 | AW103: KPW-3 | BG103: HPBL-1 | BK103: HPBL-2 | BO103: HPBL-3 | BY103: JBP
B104: Cost of materials consumed
B105: Opening Stock of Raw material | E105: =('Stock sheet'!B23) -> 1183.6308 | I105: =('Stock sheet'!B24) -> 777.0744 | Q105: ='Stock sheet'!B25 -> 311.5977 | AI105: =+'Stock sheet'!B34 -> 21.170826 | AN105: ='Stock sheet'!B33 -> 78.787352 | AS105: ='Stock sheet'!B26 -> 784.09106 | AW105: ='Stock sheet'!B28 -> 238.54651 | BG105: ='Stock sheet'!B29 -> 168.89589 | BK105: ='Stock sheet'!B30 -> 26.89946 | BO105: ='Stock sheet'!B31 -> 22.11854
B106: Opening Stock of Packing material | E106: =('Stock sheet'!B39) -> 7.8284833 | Q106: ='Stock sheet'!B41 -> 12.59 | AI106: =+'Stock sheet'!B50 -> 17.46414 | AN106: ='Stock sheet'!B49 -> 13.241029 | AS106: ='Stock sheet'!B42 -> 0 | BG106: ='Stock sheet'!B45 -> 0 | BO106: ='Stock sheet'!B47 -> 0
B108: Add: Purchase of raw materials | E108: =SUMIF('05.conso TB'!A:A,'May-26'!B108,'05.conso TB'!R:R)/10^5 -> 5159.7462 | I108: =SUMIF('05.conso TB'!A:A,'May-26'!B108,'05.conso TB'!S:S)/10^5 -> 1575.6703 | Q108: =SUMIF('05.conso TB'!A:A,'May-26'!B108,'05.conso TB'!U:U)/10^5 -> 1520.1646 | U108: =SUMIF('05.conso TB'!A:A,'May-26'!B108,'05.conso TB'!V:V)/10^5 -> 0 | Y108: =SUMIF('05.conso TB'!A:A,'May-26'!B108,'05.conso TB'!G:G)/10^5 -> 3819.5417 | AI108: =SUMIF('05.conso TB'!A:A,'May-26'!B108,'05.conso TB'!Q:Q)/10^5 -> 139.98074 | AN108: =SUMIF('05.conso TB'!A:A,'May-26'!B108,'05.conso TB'!W:W)/10^5 -> 1496.496 | AS108: =SUMIF('05.conso TB'!A:A,'May-26'!B108,'05.conso TB'!M:M)/10^5 -> 1769.685 | AW108: =SUMIF('05.conso TB'!A:A,'May-26'!B108,'05.conso TB'!P:P)/10^5 -> 1360.4118 | BG108: =SUMIF('05.conso TB'!A:A,'May-26'!B108,'05.conso TB'!H:H)/10^5 -> 4572.725 | BK108: =SUMIF('05.conso TB'!A:A,'May-26'!B108,'05.conso TB'!I:I)/10^5 -> 2.9028744 | BO108: =SUMIF('05.conso TB'!A:A,'May-26'!B108,'05.conso TB'!J:J)/10^5 -> 0 | BY108: =SUMIF('05.conso TB'!A:A,'May-26'!B108,'05.conso TB'!L:L)/10^5 -> 2050.8491
B109: Add: Purchase of packing materials | E109: =SUMIF('05.conso TB'!A:A,'May-26'!B109,'05.conso TB'!R:R)/10^5 -> 27.781294 | I109: =SUMIF('05.conso TB'!A:A,'May-26'!B109,'05.conso TB'!S:S)/10^5 -> 11.077915 | Q109: =SUMIF('05.conso TB'!A:A,'May-26'!B109,'05.conso TB'!U:U)/10^5 -> 24.21009 | U109: =SUMIF('05.conso TB'!A:A,'May-26'!B109,'05.conso TB'!V:V)/10^5 -> 0 | Y109: =SUMIF('05.conso TB'!A:A,'May-26'!B109,'05.conso TB'!G:G)/10^5 -> 0 | AI109: =SUMIF('05.conso TB'!A:A,'May-26'!B109,'05.conso TB'!Q:Q)/10^5 -> 17.031479 | AN109: =SUMIF('05.conso TB'!A:A,'May-26'!B109,'05.conso TB'!W:W)/10^5 -> 7.9225 | AS109: =SUMIF('05.conso TB'!A:A,'May-26'!B109,'05.conso TB'!M:M)/10^5 -> 27.988357 | AW109: =SUMIF('05.conso TB'!A:A,'May-26'!B109,'05.conso TB'!P:P)/10^5 -> -0.0921 | BG109: =SUMIF('05.conso TB'!A:A,'May-26'!B109,'05.conso TB'!H:H)/10^5 -> 9.66763 | BK109: =SUMIF('05.conso TB'!A:A,'May-26'!B109,'05.conso TB'!I:I)/10^5 -> -0.11 | BO109: =SUMIF('05.conso TB'!A:A,'May-26'!B109,'05.conso TB'!J:J)/10^5 -> 0 | BY109: =SUMIF('05.conso TB'!A:A,'May-26'!B109,'05.conso TB'!L:L)/10^5 -> 0
B110: Add: Purchase expenses | E110: =SUMIF('05.conso TB'!A:A,'May-26'!B110,'05.conso TB'!R:R)/10^5 -> -29.667527 | I110: =SUMIF('05.conso TB'!A:A,'May-26'!B110,'05.conso TB'!S:S)/10^5 -> -50.708533 | Q110: =SUMIF('05.conso TB'!A:A,'May-26'!B110,'05.conso TB'!U:U)/10^5 -> 1.1235299 | U110: =SUMIF('05.conso TB'!A:A,'May-26'!B110,'05.conso TB'!V:V)/10^5 -> 0 | Y110: =SUMIF('05.conso TB'!A:A,'May-26'!B110,'05.conso TB'!G:G)/10^5 -> 0 | AI110: =SUMIF('05.conso TB'!A:A,'May-26'!B110,'05.conso TB'!Q:Q)/10^5 -> 4.7048089 | AN110: =SUMIF('05.conso TB'!A:A,'May-26'!B110,'05.conso TB'!W:W)/10^5 -> 0.7588338 | AS110: =SUMIF('05.conso TB'!A:A,'May-26'!B110,'05.conso TB'!M:M)/10^5 -> 58.517563 | AW110: =SUMIF('05.conso TB'!A:A,'May-26'!B110,'05.conso TB'!P:P)/10^5 -> -0.0275807 | BG110: =SUMIF('05.conso TB'!A:A,'May-26'!B110,'05.conso TB'!H:H)/10^5 -> 46.250896 | BK110: =SUMIF('05.conso TB'!A:A,'May-26'!B110,'05.conso TB'!I:I)/10^5 -> 0.0769864 | BO110: =SUMIF('05.conso TB'!A:A,'May-26'!B110,'05.conso TB'!J:J)/10^5 -> 0 | BY110: =SUMIF('05.conso TB'!A:A,'May-26'!B110,'05.conso TB'!L:L)/10^5 -> 0
B112: Closing Stock of Raw material | E112: =+'Stock sheet'!D23 -> 1978.2852 | I112: =+'Stock sheet'!D24 -> 861.26945 | Q112: =+'Stock sheet'!D25 -> 233.13947 | AI112: =+'Stock sheet'!D34 -> 25.641962 | AN112: =+'Stock sheet'!D33 -> 209.31104 | AS112: =+'Stock sheet'!D26 -> 533.04766 | AW112: =+'Stock sheet'!D28 -> 461.24977 | BG112: =+'Stock sheet'!D29 -> 1375.637 | BK112: =+'Stock sheet'!D30 -> 21.91897 | BO112: =+'Stock sheet'!D31 -> 22.11854 | BY112: 0
B113: Closing Stock of Packing material | E113: =+'Stock sheet'!D39 -> 7.9004311 | I113: =+'Stock sheet'!D40 -> 0 | Q113: =+'Stock sheet'!D41 -> 10.49 | AI113: =+'Stock sheet'!D50 -> 20.15605 | AN113: =+'Stock sheet'!D49 -> 10.169866 | AS113: =+'Stock sheet'!D42 -> 0 | AW113: =+'Stock sheet'!D44 -> 0 | BG113: =+'Stock sheet'!D45 -> 0 | BK113: =+'Stock sheet'!D46 -> 0 | BO113: =+'Stock sheet'!D47 -> 0
B114: Total Cost of material consumed | C114: =SUM(C105:C110)-SUM(C112:C113) -> 0 | E114: =E105+E106+SUM(E108:E110)-E112-E113 -> 4363.1335 | F114: =F105+F106+SUM(F108:F110)-F112-F113 -> 0 | G114: =G105+G106+SUM(G108:G110)-G112-G113 -> 0 | H114: =H105+H106+SUM(H108:H110)-H112-H113 -> 0 | I114: =I105+I106+SUM(I108:I110)-I112-I113 -> 1451.8446 | J114: =J105+J106+SUM(J108:J110)-J112-J113 -> 0 | K114: =K105+K106+SUM(K108:K110)-K112-K113 -> 0 | L114: =L105+L106+SUM(L108:L110)-L112-L113 -> 0 | ... BU114: =BU105+BU106+SUM(BU108:BU110)-BU112-BU113 -> 0 | BW114: =BW105+BW106+SUM(BW108:BW110)-BW112-BW113 -> 0 | BX114: =BX105+BX106+SUM(BX108:BX110)-BX112-BX113 -> 0 | BY114: =BY105+BY106+SUM(BY108:BY110)-BY112-BY113 -> 2050.8491 | BZ114: =BZ105+BZ106+SUM(BZ108:BZ110)-BZ112-BZ113 -> 0 | CA114: =CA105+CA106+SUM(CA108:CA110)-CA112-CA113 -> 0 | CB114: =CB105+CB106+SUM(CB108:CB110)-CB112-CB113 -> 0 | CC114: =CC105+CC106+SUM(CC108:CC110)-CC112-CC113 -> 0 | CE114: =CE105+CE106+SUM(CE108:CE110)-CE112-CE113 -> 0 | CF114: =CF105+CF106+SUM(CF108:CF110)-CF112-CF113 -> 0 | CG114: =CG105+CG106+SUM(CG108:CG110)-CG112-CG113 -> 0 | CH114: =CH105+CH106+SUM(CH108:CH110)-CH112-CH113 -> 0
B116: Purchase of stock-in-trade
...

Sheet Apr-26
B1: GROUP EBIDTA & PBT FOR THE MONTH OF | D1: Apr-26 | O1: =157219+185345 -> 342564 | AG1: 367529 | AL1: 441624 | AQ1: 597025 | CE1: =SUM(G1:BZ1) -> 1748742
B3: PARTICULARS | C3: QTY | D3: SALES/PUR QTY | E3: SALE/PUR RATE | G3: QTY | H3: SALE IN LACS | I3: SALE/PUR RATE | O3: QTY | P3: SALE IN LACS | Q3: SALE/PUR RATE | AG3: QTY | AH3: SALE IN LACS | AI3: SALE/PUR RATE | AL3: QTY | AM3: SALE IN LACS | AN3: SALE/PUR RATE | AQ3: QTY | AR3: SALE IN LACS | AS3: SALE/PUR RATE | AU3: QTY | AV3: SALE IN LACS | AW3: SALE/PUR RATE | BE3: QTY | BF3: SALE IN LACS | BG3: SALE/PUR RATE | BM3: QTY | BN3: SALE IN LACS | BO3: SALE/PUR RATE
B4: BUDGETED / PLANNED
B6: PRODUCTION
B7: FIBC | C7: 0 | G7: 0 | I7: 0 | O7: 0 | Q7: 0 | AG7: 0 | AL7: 0 | AN7: 0 | AQ7: 0 | AS7: 0 | AU7: 0 | BE7: 0 | BG7: 0 | BM7: 0 | BN7: 0 | BO7: 0 | CE7: =SUM(C7:CD7) -> 0 | CF7: 165.52
B8: Fabric (Liner Mtr) | BM8: 0 | CE8: =SUM(C8:CD8) -> 0
C9: =(C8*0.4)+C7 -> 0 | G9: =(G8*0.4)+G7 -> 0 | O9: =(O8*0.4)+O7 -> 0 | AG9: =(AG8*0.4)+AG7 -> 0 | AL9: =(AL8*0.4)+AL7 -> 0 | AQ9: =(AQ8*0.4)+AQ7 -> 0 | AU9: 0 | BE9: 0 | BM9: =(BM8*0.4)+BM7 -> 0 | CE9: =SUM(C9:CD9) -> 0
B10: DISPATCH | CE10: =SUM(C10:CD10) -> 0
B11: FIBC | CE11: =SUM(C11:CD11) -> 0
B12: Fabric | CE12: =SUM(C12:CD12) -> 0
CE13: =SUM(C13:CD13) -> 0
B14: PURCHASE | CE14: =SUM(C14:CD14) -> 0
B15: Fabric | CE15: =SUM(C15:CD15) -> 0
B16: PP Granules | CE16: =SUM(C16:CD16) -> 0
B17: Conversion Cost per KG | C17: =#REF!-#REF!+#REF! -> #REF! | G17: =#REF!-#REF!+#REF! -> #REF! | O17: =#REF!-#REF!+#REF! -> #REF! | AG17: =#REF!-#REF!+#REF! -> #REF! | AL17: =#REF!-#REF!+#REF! -> #REF! | AQ17: =#REF!-#REF!+#REF! -> #REF! | AU17: =#REF!-#REF!+#REF! -> #REF! | BM17: =#REF!-#REF!+#REF! -> #REF! | CE17: =+#REF!-#REF!+#REF! -> #REF!
B19: Particulars | C19: Apr-26 | D19: % To Sales | E19: YTD | F19: % To Sales | G19: =C19 -> Apr-26 | H19: % To Sales | I19: YTD | J19: % To Sales | K19: =C19 -> Apr-26 | L19: % To Sales | M19: YTD | N19: % To Sales | O19: =C19 -> Apr-26 | P19: % To Sales | Q19: YTD | R19: % To Sales | S19: =K19 -> Apr-26 | T19: % Tw Sales | U19: YTD | V19: % To Sales | W19: =O19 -> Apr-26 | X19: % To Sales | Y19: YTD | Z19: % To Sales | AA19: InterUnit Elimination | AB19: =C19 -> Apr-26 | AC19: % To Sales | AD19: YTD | AE19: % To Sales | AG19: =AB19 -> Apr-26 | AH19: % To Sales | AI19: YTD | AJ19: % To Sales | AL19: =AG19 -> Apr-26 | AM19: % To Sales | AN19: YTD | AO19: % To Sales | AQ19: =AL19 -> Apr-26 | AR19: % To Sales | AS19: YTD | AT19: % To Sales | AU19: =AQ19 -> Apr-26 | AV19: % To Sales | AW19: YTD | AX19: % To Sales | AY19: InterUnit Elimination | AZ19: =AU19 -> Apr-26 | BA19: % To Sales | BB19: YTD | BC19: % To Sales | BE19: =AZ19 -> Apr-26 | BF19: % To Sales | BG19: YTD | BH19: % To Sales | BI19: =BE19 -> Apr-26 | BJ19: % To Sales | BK19: YTD | BL19: % To Sales | BM19: =BE19 -> Apr-26 | BN19: % To Sales | BO19: YTD | BP19: % To Sales | BQ19: Inter Unit Elimination | BR19: =BM19 -> Apr-26 | BS19: % To Sales | BT19: YTD | BU19: % To Sales | BW19: =BN19 -> % To Sales | BX19: % To Sales | BY19: YTD | BZ19: % To Sales | CB19: Inter Company Elimination During the month | CC19: Inter Company Elimination YTD | CE19: =BR19 -> Apr-26 | CF19: % To Sales | CG19: YTD | CH19: % To Sales
C21: PIL I | G21: PIL II | K21: PIL III | O21: HPBL4 | S21: PIL HO | W21: HCP | AB21: PIL & HCP Consol | AG21: OSWAL - KASEZ | AL21: PLASTENE POLYFILM LTD. | AQ21: K P WOVEN PVT LTD - UNIT - I | AU21: K P WOVEN PVT LTD - UNIT -III | AZ21: K P WOVEN PVT LTD - CONSOLIDATED | BE21: HCP PLASTENE BULKPACK LTD. - UNIT - I | BI21: HCP PLASTENE BULKPACK LTD. - UNIT - II | BM21: HCP PLASTENE BULKPACK LTD. - UNIT - III | BR21: HCP PLASTENE BULKPACK LTD - CONSOLIDATED | BW21: OCPL | CE21: GROUP CONSOLIDATED
B22: Revenue from operations
