Workbook

Sheet JOb Out Loss
A1: ChallanNo | B1: sysdate | C1: Company Name | D1: NatureProc | E1: DescriptionGoods | F1: Identification | G1: QtyDesc | H1: ItemUnit | I1: ItemQty | J1: ItemValue | K1: TotalAmt | L1: VehicalNo | M1: LRNo | N1: TransportName | P1: Avg. Rate | R1: Cl. Rate | T1: Profit / (Loss)
T123: =R123-P123 -> 0
T124: =R124-P124 -> 0
T125: =R125-P125 -> 0
P160: =SUM(P2:P159) -> 0 | R160: =SUM(R2:R159) -> 0 | T160: =SUM(T2:T159) -> 0

Sheet Sheet11
B1: Plastene India Limited Unit - II (PIA) | F1: Date | I1: 8
C2: Monthly Budget | I2: Till Date Budget | M2: Actual
B5: PP | C5: =+D5/$D$14 -> 0.65188 | D5: 488910 | E5: 70.31 | F5: =E5*D5 -> 34375262 | H5: =+I5/$I$14 -> 0.65188 | I5: =+D5/31*$I$1 -> 126170.32 | J5: =+E5 -> 70.31 | K5: =J5*I5 -> 8871035.4 | M5: =+N5/$N$14 -> #REF! | N5: =#REF! -> #REF! | O5: =#REF! -> #REF! | P5: =O5*N5 -> #REF! | Q5: =+N5-I5 -> #REF! | R5: =+O5-J5 -> #REF! | S5: =+P5-K5 -> #REF!
B6: Filler | C6: =+D6/$D$14 -> 0.075 | D6: 56250 | E6: 26.5 | F6: =E6*D6 -> 1490625 | H6: =+I6/$I$14 -> 0.075 | I6: =+D6/31*$I$1 -> 14516.129 | J6: =+E6 -> 26.5 | K6: =J6*I6 -> 384677.42 | M6: =+N6/$N$14 -> #REF! | N6: =#REF! -> #REF! | O6: =FillerSoltex!Y6 -> #REF! | P6: =O6*N6 -> #REF! | Q6: =+N6-I6 -> #REF! | R6: =+O6-J6 -> #REF! | S6: =+P6-K6 -> #REF!
B7: MB | C7: =+D7/$D$14 -> 0.005 | D7: 3750 | E7: 170 | F7: =E7*D7 -> 637500 | H7: =+I7/$I$14 -> 0.005 | I7: =+D7/31*$I$1 -> 967.74194 | J7: =+E7 -> 170 | K7: =J7*I7 -> 164516.13 | M7: =+N7/$N$14 -> #REF! | N7: =#REF! -> #REF! | O7: =MB!Y6 -> #REF! | P7: =O7*N7 -> #REF! | Q7: =+N7-I7 -> #REF! | R7: =+O7-J7 -> #REF! | S7: =+P7-K7 -> #REF!
B8: UV | C8: =+D8/$D$14 -> 0.018373333 | D8: 13780 | E8: 171 | F8: =E8*D8 -> 2356380 | H8: =+I8/$I$14 -> 0.018373333 | I8: =+D8/31*$I$1 -> 3556.129 | J8: =+E8 -> 171 | K8: =J8*I8 -> 608098.06 | M8: =+N8/$N$14 -> #REF! | N8: =#REF! -> #REF! | O8: =UV!Y6 -> #REF! | P8: =O8*N8 -> #REF! | Q8: =+N8-I8 -> #REF! | R8: =+O8-J8 -> #REF! | S8: =+P8-K8 -> #REF!
B9: HDPE | C9: =+D9/$D$14 -> 0.0012466667 | D9: 935 | E9: 80.41 | F9: =E9*D9 -> 75183.35 | H9: =+I9/$I$14 -> 0.0012466667 | I9: =+D9/31*$I$1 -> 241.29032 | J9: =+E9 -> 80.41 | K9: =J9*I9 -> 19402.155 | M9: =+N9/$N$14 -> #REF! | N9: =#REF! -> #REF! | O9: =#REF! -> #REF! | P9: =O9*N9 -> #REF! | Q9: =+N9-I9 -> #REF! | R9: =+O9-J9 -> #REF! | S9: =+P9-K9 -> #REF!
B10: LLDPE | C10: =+D10/$D$14 -> 0.029753333 | D10: 22315 | E10: 67.9 | F10: =E10*D10 -> 1515188.5 | H10: =+I10/$I$14 -> 0.029753333 | I10: =+D10/31*$I$1 -> 5758.7097 | J10: =+E10 -> 67.9 | K10: =J10*I10 -> 391016.39 | M10: =+N10/$N$14 -> #REF! | N10: =#REF! -> #REF! | O10: =#REF! -> #REF! | P10: =O10*N10 -> #REF! | Q10: =+N10-I10 -> #REF! | R10: =+O10-J10 -> #REF! | S10: =+P10-K10 -> #REF!
B11: LDPE | D11: 0 | J11: =+E11 -> 0 | M11: =+N11/$N$14 -> #REF! | N11: =#REF! -> #REF! | O11: =LLDP!Z6 -> #REF! | P11: =O11*N11 -> #REF! | Q11: =+N11-I11 -> #REF! | R11: =+O11-J11 -> #REF! | S11: =+P11-K11 -> #REF!
B12: RP-Purchase | D12: 64060 | E12: 60 | F12: =E12*D12 -> 3843600 | I12: =+D12/31*$I$1 -> 16531.613 | J12: =+E12 -> 60 | K12: =J12*I12 -> 991896.77 | N12: =#REF! -> #REF! | O12: =+P12/N12 -> #REF! | P12: =RP!T35 -> 452640 | Q12: =+N12-I12 -> #REF! | R12: =+O12-J12 -> #REF! | S12: =+P12-K12 -> -539256.77
B13: RP-Self | C13: =+(D12+D13)/$D$14 -> 0.21874667 | D13: 100000 | E13: 0 | F13: =E13*D13 -> 0 | H13: =+(I12+I13)/$I$14 -> 0.21874667 | I13: =+D13/31*$I$1 -> 25806.452 | J13: =+E13 -> 0 | K13: =J13*I13 -> 0 | M13: =+(N12+N13)/$N$14 -> #REF! | N13: =#REF!-N12 -> #REF! | O13: 0 | P13: =O13*N13 -> #REF! | S13: =+P13-K13 -> #REF!
D14: =SUM(D5:D13) -> 750000 | E14: =F14/D14 -> 59.058319 | F14: =SUM(F5:F13) -> 44293739 | I14: =SUM(I5:I13) -> 193548.39 | J14: =+K14/I14 -> 59.058319 | K14: =SUM(K5:K13) -> 11430642 | N14: =SUM(N5:N13) -> #REF! | O14: =+P14/N14 -> #REF! | P14: =SUM(P5:P13) -> #REF! | Q14: =+N14-I14 -> #REF! | R14: =+O14-J14 -> #REF! | S14: =+P14-K14 -> #REF!
B16: Tape waste | C16: 0.02 | D16: =D14*C16 -> 15000 | H16: =+I16/I14 -> 0.02 | I16: =I14*C16 -> 3870.9677 | M16: =+N16/N14 -> #REF! | N16: =#REF! -> #REF!
B17: Net Plant Production | D17: =D14-D16 -> 735000 | I17: =I14-I16 -> 189677.42 | N17: =N14-N16 -> #REF!
B18: Weaving wastage | C18: 0.02 | D18: =D17*C18 -> 14700 | H18: =+I18/I17 -> 0.02 | I18: =I17*C18 -> 3793.5484 | M18: =+N18/N17 -> #REF! | N18: =#REF!+#REF!+#REF! -> #REF!
B19: Net Fabric Production | D19: =D17-D18 -> 720300 | I19: =I17-I18 -> 185883.87 | N19: =N17-N18 -> #REF!
B21: Lamination-PP | D21: 36000 | E21: 77.597 | F21: =E21*D21 -> 2793492 | I21: =+D21/31*$I$1 -> 9290.3226 | J21: =+E21 -> 77.597 | K21: =J21*I21 -> 720901.16 | N21: =#REF! -> #REF! | O21: =#REF! -> #REF! | P21: =O21*N21 -> #REF! | Q21: =+N21-I21 -> #REF! | R21: =+O21-J21 -> #REF! | S21: =+P21-K21 -> #REF!
B22: LDPE | D22: 6870 | E22: 79.615 | F22: =E22*D22 -> 546955.05 | I22: =+D22/31*$I$1 -> 1772.9032 | J22: =+E22 -> 79.615 | K22: =J22*I22 -> 141149.69 | N22: =#REF! -> #REF! | O22: =LLDP!Z6 -> #REF! | P22: =O22*N22 -> #REF! | Q22: =+N22-I22 -> #REF! | R22: =+O22-J22 -> #REF! | S22: =+P22-K22 -> #REF!
B23: MB | D23: 260 | E23: 170 | F23: =E23*D23 -> 44200 | I23: =+D23/31*$I$1 -> 67.096774 | J23: =+E23 -> 170 | K23: =J23*I23 -> 11406.452 | N23: =#REF! -> #REF! | O23: =O7 -> #REF! | P23: =O23*N23 -> #REF! | Q23: =+N23-I23 -> #REF! | R23: =+O23-J23 -> #REF! | S23: =+P23-K23 -> #REF!
B24: Filler | D24: 325 | E24: 26.5 | F24: =E24*D24 -> 8612.5 | I24: =+D24/31*$I$1 -> 83.870968 | J24: =+E24 -> 26.5 | K24: =J24*I24 -> 2222.5806 | N24: =#REF! -> #REF! | O24: =O6 -> #REF! | P24: =O24*N24 -> #REF! | Q24: =+N24-I24 -> #REF! | R24: =+O24-J24 -> #REF! | S24: =+P24-K24 -> #REF!
B25: Lamination-RMC | D25: =SUM(D21:D24) -> 43455 | I25: =SUM(I21:I24) -> 11214.194 | N25: =SUM(N21:N24) -> #REF! | Q25: =+N25-I25 -> #REF! | R25: =+O25-J25 -> 0 | S25: =+P25-K25 -> 0
B26: Wastage | C26: 0.2 | D26: =D25*C26 -> 8691 | H26: =+I26/I25 -> 0.2 | I26: =I25*C26 -> 2242.8387 | M26: =+N26/N25 -> #REF! | N26: =#REF! -> #REF! | Q26: =+N26-I26 -> #REF! | R26: =+O26-J26 -> 0 | S26: =+P26-K26 -> 0
B27: Total After Lamination | D27: =D19+D25-D26 -> 755064 | E27: =F27/D25 -> 78.086746 | F27: =SUM(F21:F26) -> 3393259.5 | I27: =I19+I25-I26 -> 194855.23 | J27: =K27/I25 -> 78.086746 | K27: =SUM(K21:K26) -> 875679.88 | N27: =N19+N25-N26 -> #REF! | O27: =P27/N25 -> #REF! | P27: =SUM(P21:P26) -> #REF! | Q27: =+N27-I27 -> #REF! | R27: =+O27-J27 -> #REF! | S27: =+P27-K27 -> #REF!
B29: Yarn | D29: 51550 | E29: 120 | F29: =E29*D29 -> 6186000 | I29: =+D29/31*$I$1 -> 13303.226 | J29: =+E29 -> 120 | K29: =J29*I29 -> 1596387.1 | N29: =#REF!-#REF! -> #REF! | O29: =Yarn!AB6 -> #REF! | P29: =O29*N29 -> #REF! | Q29: =+N29-I29 -> #REF! | R29: =+O29-J29 -> #REF! | S29: =+P29-K29 -> #REF!
B30: Liner Bags | D30: 13330 | E30: 100 | F30: =E30*D30 -> 1333000 | I30: =+D30/31*$I$1 -> 3440 | J30: =+E30 -> 100 | K30: =J30*I30 -> 344000 | N30: =#REF!+#REF! -> #REF! | O30: =#REF! -> #REF! | P30: =O30*N30 -> #REF! | Q30: =+N30-I30 -> #REF! | R30: =+O30-J30 -> #REF! | S30: =+P30-K30 -> #REF!
B31: Film | D31: 1775 | E31: 110 | F31: =E31*D31 -> 195250 | I31: =+D31/31*$I$1 -> 458.06452 | J31: =+E31 -> 110 | K31: =J31*I31 -> 50387.097 | N31: =#REF!+#REF! -> #REF! | O31: 0 | P31: =O31*N31 -> #REF! | Q31: =+N31-I31 -> #REF! | R31: =+O31-J31 -> -110 | S31: =+P31-K31 -> #REF!
B32: Other RM | D32: =SUM(D29:D31) -> 66655 | E32: =F32/D32 -> 115.734 | F32: =SUM(F29:F31) -> 7714250 | I32: =SUM(I29:I31) -> 17201.29 | J32: =K32/I32 -> 115.734 | K32: =SUM(K29:K31) -> 1990774.2 | N32: =SUM(N29:N31) -> #REF! | O32: =P32/N32 -> #REF! | P32: =SUM(P29:P31) -> #REF! | Q32: =+N32-I32 -> #REF! | R32: =+O32-J32 -> #REF! | S32: =+P32-K32 -> #REF!
B33: Total After Other RM | D33: =D27+D32 -> 821719 | I33: =I27+I32 -> 212056.52 | N33: =N27+N32 -> #REF! | Q33: =+N33-I33 -> #REF! | R33: =+O33-J33 -> 0 | S33: =+P33-K33 -> 0
A34: 511364 | B34: FIBC wastage | C34: 0.12 | D34: =A34*C34 -> 61363.68 | H34: =+A34/31*I1 -> 131964.9 | I34: =C34*H34 -> 15835.788 | M34: =+N34/#REF! -> #REF! | N34: =#REF!+#REF! -> #REF! | Q34: =+N34-I34 -> #REF! | R34: =+O34-J34 -> 0 | S34: =+P34-K34 -> 0
Q35: =+N35-I35 -> 0 | R35: =+O35-J35 -> 0 | S35: =+P35-K35 -> 0
B36: Net After All wastage | D36: =D33-D34 -> 760355.32 | I36: =I33-I34 -> 196220.73 | N36: =N33-N34 -> #REF! | Q36: =+N36-I36 -> #REF! | R36: =+O36-J36 -> 0 | S36: =+P36-K36 -> 0
Q37: =+N37-I37 -> 0 | R37: =+O37-J37 -> 0 | S37: =+P37-K37 -> 0
B38: Plant Waste | D38: =D16 -> 15000 | I38: =I16 -> 3870.9677 | N38: =N16 -> #REF! | Q38: =+N38-I38 -> #REF! | R38: =+O38-J38 -> 0 | S38: =+P38-K38 -> 0
B39: Looms Waste | D39: =D18 -> 14700 | I39: =I18 -> 3793.5484 | N39: =N18 -> #REF! | Q39: =+N39-I39 -> #REF! | R39: =+O39-J39 -> 0 | S39: =+P39-K39 -> 0
B40: Lamination Waste | D40: =D26 -> 8691 | I40: =I26 -> 2242.8387 | N40: =N26 -> #REF! | Q40: =+N40-I40 -> #REF! | R40: =+O40-J40 -> 0 | S40: =+P40-K40 -> 0
B41: Fibc Waste | D41: =D34 -> 61363.68 | I41: =I34 -> 15835.788 | N41: =N34 -> #REF! | Q41: =+N41-I41 -> #REF! | R41: =+O41-J41 -> 0 | S41: =+P41-K41 -> 0
B42: Total Waste | C42: =+D42/D54 -> 0.13123716 | D42: =SUM(D38:D41) -> 99754.68 | H42: =+I42/I54 -> 0.13123716 | I42: =SUM(I38:I41) -> 25743.143 | M42: =+N42/N54 -> #REF! | N42: =SUM(N38:N41) -> #REF! | Q42: =+N42-I42 -> #REF! | R42: =+O42-J42 -> 0 | S42: =+P42-K42 -> 0
B43: Sale of waste | D43: =D42-D45 -> -245.32 | E43: 20 | F43: =E43*D43 -> -4906.4 | I43: =I42-I45 -> -63.308387 | J43: =+E43 -> 20 | K43: =J43*I43 -> -1266.1677 | N43: =#REF! -> #REF! | O43: =+P43/N43 -> #REF! | P43: =Sheet3!L12+Sheet3!L13 -> 119400 | Q43: =+N43-I43 -> #REF! | R43: =+O43-J43 -> #REF! | S43: =+P43-K43 -> 120666.17
B44: Wastage Purchase | N44: =-#REF! -> #REF! | O44: =+P44/N44 -> #REF! | P44: =-Wastage!AD21 -> 0 | Q44: =+N44-I44 -> #REF! | R44: =+O44-J44 -> #REF! | S44: =+P44-K44 -> 0
B45: Send to RP | D45: =D13 -> 100000 | E45: 0 | F45: =E45*D45 -> 0 | I45: =I13 -> 25806.452 | J45: =+E45 -> 0 | K45: =J45*I45 -> 0 | N45: =#REF!-#REF! -> #REF! | P45: =O45*N45 -> #REF! | Q45: =+N45-I45 -> #REF! | R45: =+O45-J45 -> 0 | S45: =+P45-K45 -> #REF!
B46: FIBC Sale | D46: =A34-D34 -> 450000.32 | E46: 155 | F46: =E46*D46 -> 69750050 | I46: =H34-I34 -> 116129.11 | J46: =+E46 -> 155 | K46: =J46*I46 -> 18000013 | N46: =#REF!+#REF! -> #REF! | O46: =+P46/N46 -> #REF! | P46: =Sheet3!L7+Sheet3!L14 -> 49706724 | Q46: =+N46-I46 -> #REF! | R46: =+O46-J46 -> #REF! | S46: =+P46-K46 -> 31706711
B47: FIBC Purchase | N47: =-#REF!-#REF! -> #REF! | O47: =+P47/N47 -> #REF! | P47: =-#REF!-#REF! -> #REF! | Q47: =+N47-I47 -> #REF! | R47: =+O47-J47 -> #REF! | S47: =+P47-K47 -> #REF!
B48: Fabric Sale | D48: =D36-D46 -> 310355 | E48: 92 | F48: =E48*D48 -> 28552660 | I48: =I36-I46 -> 80091.613 | J48: =+E48 -> 92 | K48: =J48*I48 -> 7368428.4 | N48: =+#REF!+#REF!+Sheet3!J11+Sheet3!J14 -> #REF! | O48: =+P48/N48 -> #REF! | P48: =Sheet3!L8+Sheet3!L9+Sheet3!L11 -> 13140502 | Q48: =+N48-I48 -> #REF! | R48: =+O48-J48 -> #REF! | S48: =+P48-K48 -> 5772073.2
B49: Fabric Purchase | N49: =-#REF!-#REF!-#REF!-#REF! -> #REF! | O49: =+P49/N49 -> #REF! | P49: =-'Unlaminated Fabric'!U34-'Lam Fabric'!U16-Tape!S9-#REF! -> #REF! | Q49: =+N49-I49 -> #REF! | R49: =+O49-J49 -> #REF! | S49: =+P49-K49 -> #REF!
Q50: =+N50-I50 -> 0 | R50: =+O50-J50 -> 0 | S50: =+P50-K50 -> 0
B51: Total Inflow | D51: =SUM(D43:D50)-D45 -> 760110 | E51: =+F51/D51 -> 129.3205 | F51: =SUM(F43:F50) -> 98297803 | I51: =SUM(I43:I50)-I45 -> 196157.42 | J51: =+K51/I51 -> 129.3205 | K51: =SUM(K43:K50) -> 25367175 | N51: =SUM(N43:N50)-N45 -> #REF! | O51: =P51/N51 -> #REF! | P51: =SUM(P43:P50) -> #REF! | Q51: =+N51-I51 -> #REF! | R51: =+O51-J51 -> #REF! | S51: =+P51-K51 -> #REF! | U51: =+P43+P46+P48+SUM(F74:F81) -> 64943957
Q52: =+N52-I52 -> 0 | R52: =+O52-J52 -> 0 | S52: =+P52-K52 -> 0
B53: Outflows | Q53: =+N53-I53 -> 0 | R53: =+O53-J53 -> 0 | S53: =+P53-K53 -> 0
B54: RM | D54: =+D43+D46+D48 -> 760110 | E54: =F54/D54 -> 72.88583 | F54: =F14+F27+F32 -> 55401248 | G54: =+E51-E54 -> 56.434667 | I54: =+I43+I46+I48 -> 196157.42 | J54: =K54/I54 -> 72.88583 | K54: =K14+K27+K32 -> 14297096 | M54: =+O51-O54-O62-O63-O64 -> #REF! | N54: =N14+N25+N32-N42 -> #REF! | O54: =P54/$N$54 -> #REF! | P54: =P14+P27+P32 -> #REF! | Q54: =+N54-I54 -> #REF! | R54: =+O54-J54 -> #REF! | S54: =+P54-K54 -> #REF! | U54: =+P54-P44-P47-P49+K82 -> #REF! | V54: =#REF! -> #REF! | W54: =+V54-U54 -> #REF!
B55: Salary | E55: =+F55/D54 -> 17.760587 | F55: 13500000 | J55: =+K55/I54 -> 17.760587 | K55: =+F55/31*$I$1 -> 3483871 | M55: =+G54-M54 -> #REF! | O55: =P55/$N$54 -> #REF! | P55: =Budget!L16 -> #REF! | Q55: =+N55-I55 -> 0 | R55: =+O55-J55 -> #REF! | S55: =+P55-K55 -> #REF!
B56: Power | E56: =+F56/D54 -> 7.6304745 | F56: 5800000 | J56: =+K56/I54 -> 7.6304745 | K56: =+F56/31*$I$1 -> 1496774.2 | M56: =+M55*N54 -> #REF! | O56: =P56/$N$54 -> #REF! | P56: =Budget!L17 -> #REF! | Q56: =+N56-I56 -> 0 | R56: =+O56-J56 -> #REF! | S56: =+P56-K56 -> #REF!
B57: Consumables | E57: =+F57/D54 -> 3.6836774 | F57: 2800000 | J57: =+K57/I54 -> 3.6836774 | K57: =+F57/31*$I$1 -> 722580.65 | M57: =+N54*1.45 -> #REF! | O57: =P57/$N$54 -> #REF! | P57: =Budget!L18 -> #REF! | Q57: =+N57-I57 -> 0 | R57: =+O57-J57 -> #REF! | S57: =+P57-K57 -> #REF!
B58: Other Fix | E58: =+F58/D54 -> 6.5779953 | F58: 5000000 | J58: =+K58/I54 -> 6.5779953 | K58: =+F58/31*$I$1 -> 1290322.6 | O58: =P58/$N$54 -> #REF! | P58: =#REF!-#REF!-#REF!-#REF! -> #REF! | Q58: =+N58-I58 -> 0 | R58: =+O58-J58 -> #REF! | S58: =+P58-K58 -> #REF!
B59: Export Expense | E59: =+F59/D54 -> 2.9601 | F59: =+D46*5 -> 2250001.6 | J59: =+K59/I54 -> 2.9601 | K59: =+F59/31*$I$1 -> 580645.57 | O59: =P59/$N$54 -> #REF! | P59: =Budget!L21 -> #REF! | Q59: =+N59-I59 -> 0 | R59: =+O59-J59 -> #REF! | S59: =+P59-K59 -> #REF!
B60: MEIS Benefits | E60: =+F60/D54 -> -2.752893 | F60: =-F46*3% -> -2092501.5 | J60: =+K60/I54 -> -2.752893 | K60: =+F60/31*$I$1 -> -540000.38 | O60: =P60/$N$54 -> #REF! | P60: =Budget!L24 -> #REF! | Q60: =+N60-I60 -> 0 | R60: =+O60-J60 -> #REF! | S60: =+P60-K60 -> #REF!
B61: Exchage Rate Diff | E61: =+F61/D54 -> 0 | F61: =-2000000*0 -> 0 | J61: =+K61/I54 -> 0 | K61: =+F61/31*$I$1 -> 0 | O61: =P61/$N$54 -> #REF! | P61: =Budget!L25+#REF! -> #REF! | Q61: =+N61-I61 -> 0 | R61: =+O61-J61 -> #REF! | S61: =+P61-K61 -> #REF!
B62: Custom Duty on RM Pur | O62: =P62/$N$54 -> #REF! | P62: =#REF! -> #REF! | Q62: =+N62-I62 -> 0 | R62: =+O62-J62 -> #REF! | S62: =+P62-K62 -> #REF!
B63: RM Inter Co. PUR Exp. | O63: =P63/$N$54 -> #REF! | P63: 0 | Q63: =+N63-I63 -> 0 | R63: =+O63-J63 -> #REF! | S63: =+P63-K63 -> 0
B64: Advance License Accrued | O64: =P64/$N$54 -> #REF! | P64: =Budget!L26 -> #REF! | Q64: =+N64-I64 -> 0 | R64: =+O64-J64 -> #REF! | S64: =+P64-K64 -> #REF!
B65: Stock Impact | F65: =#REF! -> #REF! | K65: =+F65/31*$I$1 -> #REF! | Q65: =+N65-I65 -> 0 | R65: =+O65-J65 -> 0 | S65: =+P65-K65 -> #REF!
B67: Job Work Consumption | N67: =#REF!-#REF! -> #REF! | O67: =P67/N67 -> #REF! | P67: =-#REF!+#REF! -> #REF! | Q67: =+N67-I67 -> #REF! | R67: =+O67-J67 -> #REF! | S67: =+P67-K67 -> #REF!
B68: Job Charges | N68: =+N67 -> #REF! | O68: =P68/N68 -> #REF! | P68: =Budget!P19 -> #REF! | Q68: =+N68-I68 -> #REF! | R68: =+O68-J68 -> #REF! | S68: =+P68-K68 -> #REF!
D69: =+D54 -> 760110 | E69: =+F69/D69 -> #REF! | F69: =SUM(F54:F68) -> #REF! | I69: =+I54 -> 196157.42 | J69: =+K69/I69 -> #REF! | K69: =SUM(K54:K68) -> #REF! | N69: =+N54+N68 -> #REF! | O69: =P69/N69 -> #REF! | P69: =SUM(P54:P68) -> #REF! | Q69: =+N69-I69 -> #REF! | R69: =+O69-J69 -> #REF! | S69: =+P69-K69 -> #REF!
Q70: =+N70-I70 -> 0 | R70: =+O70-J70 -> 0 | S70: =+P70-K70 -> 0
B71: Net EBDITA | D71: =+D69 -> 760110 | E71: =+F71/D71 -> #REF! | F71: =F51-F69 -> #REF! | I71: =+I69 -> 196157.42 | J71: =+K71/I71 -> #REF! | K71: =K51-K69 -> #REF! | N71: =+N69 -> #REF! | O71: =+P71/N71 -> #REF! | P71: =P51-P69 -> #REF! | Q71: =+N71-I71 -> #REF! | R71: =+O71-J71 -> #REF! | S71: =+P71-K71 -> #REF!
Q72: =+N72-I72 -> 0 | R72: =+O72-J72 -> 0 | S72: =+P72-K72 -> 0
B73: RM Sales - Purchase | D73: Sales | I73: Purchase / Stock Price | Q73: =+N73-I73 -> #VALUE! | R73: =+O73-J73 -> 0 | S73: =+P73-K73 -> 0
B74: Filler | D74: =Sheet3!J15 -> 8500 | E74: =+F74/D74 -> 29.5 | F74: =Sheet3!L15 -> 250750 | I74: =D74 -> 8500 | J74: =FillerSoltex!Y6 -> #REF! | K74: =I74*J74 -> #REF! | N74: =+D74-I74 -> 0 | P74: =+F74-K74 -> #REF! | Q74: =+N74-I74 -> -8500 | R74: =+O74-J74 -> #REF! | S74: =+P74-K74 -> #REF!
B75: Master Batch | D75: =Sheet3!J16 -> 500 | E75: =+F75/D75 -> 141 | F75: =Sheet3!L16 -> 70500 | I75: =D75 -> 500 | J75: =MB!Y6 -> #REF! | K75: =I75*J75 -> #REF! | N75: =+D75-I75 -> 0 | P75: =+F75-K75 -> #REF! | Q75: =+N75-I75 -> -500 | R75: =+O75-J75 -> #REF! | S75: =+P75-K75 -> #REF!
B76: LLDPE GRANULES | D76: =Sheet3!J17 -> 125 | E76: =+F76/D76 -> 68.248 | F76: =Sheet3!L17 -> 8531 | I76: =D76 -> 125 | J76: 0 | K76: =I76*J76 -> 0 | N76: =+D76-I76 -> 0 | P76: =+F76-K76 -> 8531 | Q76: =+N76-I76 -> -125 | R76: =+O76-J76 -> 0 | S76: =+P76-K76 -> 8531
B77: Pp Granuales | D77: =Sheet3!J18 -> 18000 | E77: =+F77/D77 -> 75.863889 | F77: =Sheet3!L18 -> 1365550 | I77: =D77 -> 18000 | J77: =#REF! -> #REF! | K77: =I77*J77 -> #REF! | N77: =+D77-I77 -> 0 | P77: =+F77-K77 -> #REF! | Q77: =+N77-I77 -> -18000 | R77: =+O77-J77 -> #REF! | S77: =+P77-K77 -> #REF!
B78: Pp Granuales | D78: 0 | E78: =+F78/D78 -> #DIV/0! | F78: 0 | I78: 0 | J78: 0 | K78: 0 | N78: =+D78-I78 -> 0 | P78: =+F78-K78 -> 0 | Q78: =+N78-I78 -> 0 | R78: =+O78-J78 -> 0 | S78: =+P78-K78 -> 0
B79: LLDPE BAGS (LINER) | D79: =Sheet3!J19 -> 0 | E79: =+F79/D79 -> #DIV/0! | F79: =Sheet3!L19 -> 0 | I79: =D79 -> 0 | J79: 0 | K79: =I79*J79 -> 0 | N79: =+D79-I79 -> 0 | P79: =+F79-K79 -> 0 | Q79: =+N79-I79 -> 0 | R79: =+O79-J79 -> 0 | S79: =+P79-K79 -> 0
B80: LDPE GRANULES | D80: =Sheet3!J20 -> 0 | E80: =+F80/D80 -> #DIV/0! | F80: =Sheet3!L20 -> 0 | I80: =D80 -> 0 | J80: =LLDP!Z6 -> #REF! | K80: =I80*J80 -> #REF! | N80: =+D80-I80 -> 0 | P80: =+F80-K80 -> #REF! | Q80: =+N80-I80 -> 0 | R80: =+O80-J80 -> #REF! | S80: =+P80-K80 -> #REF!
B81: REPROCESS GRANULES (FG) | D81: =Sheet3!J10 -> 14100 | E81: =+F81/D81 -> 20 | F81: =Sheet3!L10 -> 282000 | I81: =D81 -> 14100 | J81: 0 | K81: =I81*J81 -> 0 | N81: =+D81-I81 -> 0 | P81: =+F81-K81 -> 282000 | Q81: =+N81-I81 -> -14100 | R81: =+O81-J81 -> 0 | S81: =+P81-K81 -> 282000
F82: =SUM(F74:F81) -> 1977331 | K82: =SUM(K74:K81) -> #REF! | Q82: =+N82-I82 -> 0 | R82: =+O82-J82 -> 0 | S82: =+P82-K82 -> #REF!
B83: Profit / (Loss) on Account of RM | N83: =SUM(N74:N82) -> 0 | P83: =SUM(P74:P82) -> #REF! | Q83: =+N83-I83 -> 0 | R83: =+O83-J83 -> 0 | S83: =+P83-K83 -> #REF!
B84: Total EBDITA | D84: =+D71 -> 760110 | E84: =+F84/D84 -> #REF! | F84: =+F71 -> #REF! | I84: =+I71 -> 196157.42 | J84: =+K84/I84 -> #REF! | K84: =+K71 -> #REF! | N84: =+N71+N83 -> #REF! | O84: =+P84/N84 -> #REF! | P84: =+P71+P83 -> #REF! | Q84: =+N84-I84 -> #REF! | R84: =+O84-J84 -> #REF! | S84: =+P84-K84 -> #REF!
P85: =Budget!L31 -> #REF! | Q85: =+N85-I85 -> 0 | R85: =+O85-J85 -> 0 | S85: =+P85-K85 -> #REF!
P86: =+P84-P85 -> #REF! | Q86: =+N86-I86 -> 0 | R86: =+O86-J86 -> 0 | S86: =+P86-K86 -> #REF!
Q87: =+N87-I87 -> 0 | R87: =+O87-J87 -> 0 | S87: =+P87-K87 -> 0
Q88: =+N88-I88 -> 0 | R88: =+O88-J88 -> 0 | S88: =+P88-K88 -> 0
B89: Increase / (Decrese) in Closing Stock | N89: =#REF!-#REF! -> #REF! | O89: =+P89/N89 -> #REF! | P89: =+P95-P96 -> #REF! | Q89: =+N89-I89 -> #REF! | R89: =+O89-J89 -> #REF! | S89: =+P89-K89 -> #REF!
B90: Profit / (Loss) on Stock Valuation | N90: =N95 -> #REF! | O90: =+O95 -> #REF! | P90: =P95 -> #REF! | Q90: =+N90-I90 -> #REF! | R90: =+O90-J90 -> #REF! | S90: =+P90-K90 -> #REF!
B91: Net EBDITA Stock Impact | D91: =+D84 -> 760110 | E91: =+F91/D91 -> #REF! | F91: =F84+F90 -> #REF! | I91: =+I84 -> 196157.42 | J91: =+K91/I91 -> #REF! | K91: =K84+K90 -> #REF! | N91: =+N84 -> #REF! | O91: =+P91/N91 -> #REF! | P91: =P84+P90 -> #REF! | Q91: =+N91-I91 -> #REF! | R91: =+O91-J91 -> #REF! | S91: =+P91-K91 -> #REF! | U91: =#REF! -> #REF! | V91: =+P91-U91 -> #REF! | W91: =+W54-V91 -> #REF!
B93: Closing Stock | N93: =#REF! -> #REF! | O93: =P93/N93 -> #REF! | P93: =#REF! -> #REF!
B94: Opening Stock | N94: =#REF! -> #REF! | O94: =P94/N94 -> #REF! | P94: =#REF! -> #REF!
B95: Difference | N95: =+N93-N94 -> #REF! | O95: =+O93-O94 -> #REF! | P95: =+P93-P94 -> #REF!
P96: =+P84+P95 -> #REF!
N98: =N69-N51 -> #REF! | P98: =P69-P51 -> #REF!
N99: =+N98-N95 -> #REF!

Sheet Budget
F1: 10
B2: Monthly Budget | F2: Budget till Date | J2: Actual | N2: Variance
B3: Qty | C3: Avg. Rate | D3: Amount | F3: Qty | G3: Avg. Rate | H3: Amount | J3: Qty | K3: Avg. Rate | L3: Amount | N3: Qty | P3: Amount
A4: Sales | B4: =Sheet11!D43+Sheet11!D46+Sheet11!D48 -> 760110 | C4: =+D4/B4 -> 129.3205 | D4: =Sheet11!F43+Sheet11!F46+Sheet11!F48 -> 98297803 | F4: =B4/31*F1 -> 245196.77 | G4: =+C4 -> 129.3205 | H4: =+F4*G4 -> 31708969 | J4: =SUM(J5:J7) -> #REF! | K4: =L4/J4 -> #REF! | L4: =SUM(L5:L7) -> #REF! | N4: =+J4-F4 -> #REF! | O4: =+P4/J4 -> #REF! | P4: =+L4-H4 -> #REF! | W4: 44677903 | X4: =+L4-W4 -> #REF!
A5: Trading Sale | J5: ='PUR-SALE'!#REF! -> #REF! | K5: =+L5/J5 -> #REF! | L5: ='PUR-SALE'!#REF! -> #REF! | W5: 13975498 | X5: =+L5-W5 -> #REF!
A6: Inter Unit Sale | J6: ='PUR-SALE'!#REF! -> #REF! | K6: =+L6/J6 -> #REF! | L6: ='PUR-SALE'!#REF! -> #REF! | W6: 18303636 | X6: =+L6-W6 -> #REF!
A7: Other Sales | J7: =Sheet3!J22-J5-J6 -> #REF! | K7: =+L7/J7 -> #REF! | L7: =Sheet3!L22-L5-L6 -> #REF! | W7: 12398769 | X7: =+L7-W7 -> #REF!
A9: RMC | B9: =+Sheet11!D14-Sheet11!D13+Sheet11!D25+Sheet11!D32 -> 760110 | C9: =+D9/B9 -> 72.88583 | D9: =Sheet11!F14+Sheet11!F27+Sheet11!F32 -> 55401248 | F9: =B9/31*F1 -> 245196.77 | G9: =+C9 -> 72.88583 | H9: =+F9*G9 -> 17871370 | J9: =SUM(J10:J12) -> #REF! | K9: =L9/J9 -> #REF! | L9: =SUM(L10:L12) -> #REF! | N9: =+J9-F9 -> #REF! | O9: =+P9/(J9+J10+J11) -> #REF! | P9: =+L9-H9 -> #REF! | W9: 36261657 | X9: =+L9-W9 -> #REF!
A10: Trading Purchase | J10: ='PUR-SALE'!#REF! -> #REF! | K10: =L10/J10 -> #REF! | L10: ='PUR-SALE'!#REF! -> #REF! | Q10: =+J10-J5 -> #REF! | W10: 15116340 | X10: =+L10-W10 -> #REF!
A11: Inter Unit Purchase | J11: ='PUR-SALE'!#REF! -> #REF! | K11: =L11/J11 -> #REF! | L11: ='PUR-SALE'!#REF!-L22-L23 -> #REF! | W11: 13737148 | X11: =+L11-W11 -> #REF!
A12: Other RMC | J12: =(Sheet3!F17*1000)-J10-J11 -> #REF! | K12: =L12/J12 -> #REF! | L12: =Sheet3!E17*100000-L10-L11-L22-L23 -> #REF! | W12: 7408168.8 | X12: =+L12-W12 -> #REF!
A14: NET ADDITION | B14: =B4 -> 760110 | C14: =C4-C9 -> 56.434667 | D14: =+D4-D9 -> 42896555 | F14: =F4 -> 245196.77 | G14: =G4-G9 -> 56.434667 | H14: =+H4-H9 -> 13837598 | J14: =+J4-J9 -> #REF! | K14: =K4-K9 -> #REF! | L14: =+L4-L9 -> #REF! | P14: =+P4-P9 -> #REF! | W14: 8416246.4 | X14: =+L14-W14 -> #REF!
A16: Salary | D16: 15000000 | H16: =D16/31*$F$1 -> 4838709.7 | L16: =Sheet6!E39 -> #REF! | P16: =+L16-H16 -> #REF! | W16: 3727653.9 | X16: =+L16-W16 -> #REF!
A17: Power | D17: 7000000 | H17: =D17/31*$F$1 -> 2258064.5 | L17: =Sheet6!E38 -> #REF! | P17: =+L17-H17 -> #REF! | W17: 1631584.2 | X17: =+L17-W17 -> #REF!
A18: Consumables | D18: 2500000 | H18: =D18/31*$F$1 -> 806451.61 | L18: =Sheet6!E40 -> #REF! | P18: =+L18-H18 -> #REF! | W18: 558284.88 | X18: =+L18-W18 -> #REF!
A19: Job Charges | L19: =Sheet6!E41 -> #REF! | P19: =+L19-H19 -> #REF! | W19: 49428 | X19: =+L19-W19 -> #REF!
A20: Other Expenses | D20: 2000000 | H20: =D20/31*$F$1 -> 645161.29 | L20: =Sheet6!E42-#REF! -> #REF! | P20: =+L20-H20 -> #REF! | W20: 724676.82 | X20: =+L20-W20 -> #REF!
A21: Export Expenses | D21: 3000000 | H21: =D21/31*$F$1 -> 967741.94 | L21: =#REF! -> #REF! | P21: =+L21-H21 -> #REF! | W21: 379997.75 | X21: =+L21-W21 -> #REF!
A22: Custom Duty on RM Pur | L22: =(6.31*99000)+(6.03*99000) -> 1221660 | P22: =+L22-H22 -> 1221660
A23: RM Inter Co. PUR Exp. | L23: =155995+471701.8 -> 627696.8 | P23: =+L23-H23 -> 627696.8 | W23: 780734.5 | X23: =+L23-W23 -> -153037.7
A24: MEIS Benefit | D24: -2076444.5 | H24: =D24/31*$F$1 -> -669820.8 | L24: =Sheet6!E43 -> #REF! | P24: =+L24-H24 -> #REF! | W24: -664193 | X24: =+L24-W24 -> #REF!
A25: Exchange Rate Differences | D25: -2000000 | H25: =D25/31*$F$1 -> -645161.29 | L25: =Sheet6!E46 -> #REF! | P25: =+L25-H25 -> #REF! | W25: -179034.71 | X25: =+L25-W25 -> #REF!
A26: Advance License Income | L26: =-#REF! -> #REF! | P26: =+L26-H26 -> #REF!
A27: Income From Windmill | L27: =-#REF! -> #REF!
A29: TOTAL EXPENSE | B29: =B4 -> 760110 | C29: =+D29/B29 -> 33.447206 | D29: =SUM(D16:D28) -> 25423556 | F29: =F4 -> 245196.77 | G29: =+H29/F29 -> 33.447206 | H29: =SUM(H16:H28) -> 8201146.9 | J29: =J4 -> #REF! | K29: =+L29/J29 -> #REF! | L29: =SUM(L16:L28) -> #REF! | N29: =N4 -> #REF! | O29: =+P29/J29 -> #REF! | P29: =SUM(P16:P28) -> #REF! | W29: 7009132.3 | X29: =+L29-W29 -> #REF!
A31: NET EBDITA | B31: =B4 -> 760110 | C31: =+D31/B31 -> 22.987461 | D31: =D14-D29 -> 17472999 | F31: =F4 -> 245196.77 | G31: =+G14-G29 -> 22.987461 | H31: =H14-H29 -> 5636451.3 | J31: =J4 -> #REF! | K31: =+K14-K29 -> #REF! | L31: =L14-L29 -> #REF! | N31: =N4 -> #REF! | O31: =+P31/J31 -> #REF! | P31: =+P14-P29 -> #REF! | W31: 1407114.1 | X31: =+L31-W31 -> #REF!
A35: Inter Co. Purchase | L35: =-'PUR-SALE'!#REF! -> #REF!
A36: Inter Co. Sale | L36: ='PUR-SALE'!#REF! -> #REF! | S36: =4095-460-270 -> 3365 | T36: 357.06 | U36: =+S36*T36 -> 1201506.9
A37: Trading Impact | L37: =-'PUR-SALE'!#REF! -> #REF! | S37: =4095-460-270 -> 3365 | T37: =#REF! -> #REF! | U37: =+S37*T37 -> #REF!
A38: Advance Lic. Benefit on Trading Trx. | L38: =-('PUR-SALE'!#REF!+'PUR-SALE'!#REF!+'PUR-SALE'!#REF!+'PUR-SALE'!#REF!)*1.1*6 -> #REF!
A39: RM Price Reduction Impact | L39: =#REF! -> #REF! | S39: =+S36-S37 -> 0 | T39: =+T36-T37 -> #REF! | U39: =+U36-U37 -> #REF!
A40: Oswal MEIS Benefit | L40: =#REF! -> #REF!
A41: Total Impact of Above | L41: =SUM(L35:L40) -> #REF!
L43: =+L31+L39 -> #REF!
L45: =L31+L23+L39 -> #REF!
A49: Export | J49: =#REF! -> #REF!
A50: Eligible Import | J50: =+J49*1.1 -> #REF!
A51: Actual Import | J51: 49500
J52: =+J50-J51 -> #REF!
J53: 6
J54: =+J52*J53 -> #REF!
J61: 0 | K61: 0 | L61: 0
J62: 0 | K62: 0 | L62: 0
J63: 0 | K63: 0 | L63: 0
L64: =SUM(L61:L63) -> 0

Sheet PUR-SALE

Sheet Sheet6
B3: Particulars | C3: Qty | D3: Rate | E3: Amount
B4: Sales | C4: Qty | D4: Rate | E4: Value
B5: PP WOVEN BIG BAGS / SACKS | C5: ='New Working'!B5 -> 306664.9 | D5: ='New Working'!C5 -> 157.96893 | E5: ='New Working'!D5 -> 48443526
B6: PP Woven Fabrics(FG) | C6: ='New Working'!B6 -> 85056.5 | D6: ='New Working'!C6 -> 105.13316 | E6: ='New Working'!D6 -> 8942258.9
B7: PP Laminated Fabric | C7: ='New Working'!B7 -> 40640.5 | D7: ='New Working'!C7 -> 103.30194 | E7: ='New Working'!D7 -> 4198242.7
B8: REPROCESS GRANULES (FG) | C8: ='New Working'!B8 -> 14100 | D8: ='New Working'!C8 -> 20 | E8: ='New Working'!D8 -> 282000
B9: PP TAPE / YARN | C9: ='New Working'!B9 -> 0 | D9: ='New Working'!C9 -> #DIV/0! | E9: ='New Working'!D9 -> 0
B10: PP Fabric Wastage | C10: ='New Working'!B10 -> 0 | D10: ='New Working'!C10 -> #DIV/0! | E10: ='New Working'!D10 -> 0
B11: PP Tape Wastage | C11: ='New Working'!B11 -> 7960 | D11: ='New Working'!C11 -> 15 | E11: ='New Working'!D11 -> 119400
B12: PP WEBBING (FG) | C12: ='New Working'!B12 -> 12228.8 | D12: ='New Working'!C12 -> 103.29697 | E12: ='New Working'!D12 -> 1263198
B13: Filler | C13: ='New Working'!B13 -> 8500 | D13: ='New Working'!C13 -> 29.5 | E13: ='New Working'!D13 -> 250750
B14: Master Batch | C14: ='New Working'!B14 -> 500 | D14: ='New Working'!C14 -> 141 | E14: ='New Working'!D14 -> 70500
B15: LLDPE GRANULES | C15: ='New Working'!B15 -> 125 | D15: ='New Working'!C15 -> 68.248 | E15: ='New Working'!D15 -> 8531
B16: Pp Granuales | C16: ='New Working'!B16 -> 18000 | D16: ='New Working'!C16 -> 75.863889 | E16: ='New Working'!D16 -> 1365550
B17: LLDPE BAGS (LINER) | C17: ='New Working'!B17 -> 0 | D17: ='New Working'!C17 -> #DIV/0! | E17: ='New Working'!D17 -> 0
C18: ='New Working'!B18 -> 0 | D18: ='New Working'!C18 -> #DIV/0! | E18: ='New Working'!D18 -> 0
B20: TOTAL SALE | C20: =SUM(C5:C17) -> 493775.7 | D20: =E20/C20 -> 131.52522 | E20: =SUM(E5:E17) -> 64943957
B21: Less: Avg. RMC Cost of the Material Consumed | C21: ='New Working'!B75 -> #REF! | D21: ='New Working'!C75 -> #REF! | E21: =+C21*D21 -> #REF!
B23: Value Addition on Sales (A) | C23: =+C20 -> 493775.7 | D23: =+D20-D21 -> #REF! | E23: =C23*D23 -> #REF!
B25: Sock Impact
B26: Op. Stock Impact | C26: ='New Working'!B118 -> #REF! | D26: =-'New Working'!C119 -> #REF! | E26: =C26*D26 -> #REF!
B27: Current Month Proccessed Stock Impact
B28: Tape | C28: =-#REF!-#REF! -> #REF! | D28: 15 | E28: =C28*D28 -> #REF!
B29: Unlaminated Fabric | C29: =-#REF!-#REF!-#REF! -> #REF! | D29: 36 | E29: =C29*D29 -> #REF!
B30: Laminated Fabric | C30: =-#REF!-#REF! -> #REF! | D30: 36 | E30: =C30*D30 -> #REF!
B31: Webbing | C31: =-#REF!-#REF! -> #REF! | D31: 36 | E31: =C31*D31 -> #REF!
B32: FIBC | C32: =-#REF! -> #REF! | D32: 80 | E32: =C32*D32 -> #REF!
B33: Small Bags | C33: =-#REF! -> #REF! | D33: 70 | E33: =C33*D33 -> #REF!
B34: RM Stock Impact | E34: 1571475.4
B36: Total Stock Impact (B) | C36: =$C$23 -> 493775.7 | D36: =E36/C36 -> #REF! | E36: =SUM(E26:E35) -> #REF!
B38: Power | C38: =$C$23 -> 493775.7 | D38: =E38/C38 -> #REF! | E38: ='New Working'!D79 -> #REF!
B39: Salary | C39: =$C$23 -> 493775.7 | D39: =E39/C39 -> #REF! | E39: ='New Working'!D80 -> #REF!
B40: Consumables and Stores | C40: =$C$23 -> 493775.7 | D40: =E40/C40 -> #REF! | E40: ='New Working'!D81 -> #REF!
B41: Job Charges | C41: =$C$23 -> 493775.7 | D41: =E41/C41 -> #REF! | E41: ='New Working'!D82 -> #REF!
B42: Other | C42: =$C$23 -> 493775.7 | D42: =E42/C42 -> #REF! | E42: ='New Working'!D83 -> #REF!
B43: MEIS Benefit | C43: =$C$23 -> 493775.7 | D43: =E43/C43 -> #REF! | E43: =-'New Working'!D89 -> #REF!
B44: Import Duty on Excess Material | C44: =$C$23 -> 493775.7 | D44: =E44/C44 -> #REF! | E44: =-'New Working'!D90 -> #REF!
B45: Income from Windmill | C45: =$C$23 -> 493775.7 | D45: =E45/C45 -> 0 | E45: 0
B46: Exchange Rate Benefit | C46: =$C$23 -> 493775.7 | D46: =E46/C46 -> #REF! | E46: =-'New Working'!D92 -> #REF!
B48: Total Expenses (C ) | E48: =SUM(E38:E47) -> #REF!
B50: Net EBIDTA (A+B-C) | E50: =E23+E36-E48 -> #REF! | F50: =#REF! -> #REF! | G50: =+E50-F50 -> #REF!
E51: =+E50-E36 -> #REF!

Sheet Sheet5
A3: Item Name | B3: Opening Balance | C3: Inward | F3: Outward | I3: Closing Balance | J3: Qty At Job Worker | K3: Rate | L3: Value
C4: Purchase | D4: Production | E4: Received Job IN | F4: Sale | G4: Issue / Consumption | H4: Sent To Job OUT
A6: SF
A7: R.P. GRANULES | B7: ='ERP STOCK'!B7 -> 36409.13 | C7: ='ERP STOCK'!C7 -> 11390 | D7: ='ERP STOCK'!D7 -> 173100 | E7: ='ERP STOCK'!E7 -> 28116.2 | F7: ='ERP STOCK'!F7 -> 49171.2 | G7: ='ERP STOCK'!G7 -> 174000 | H7: ='ERP STOCK'!H7 -> 0 | I7: ='ERP STOCK'!I7 -> 25844.13 | ... L7: ='ERP STOCK'!L7 -> 1292206.5
B8: =#REF! -> #REF! | C8: =#REF! -> #REF! | D8: =#REF! -> #REF! | E8: =#REF! -> #REF! | F8: =#REF! -> #REF! | G8: =#REF! -> #REF! | H8: =#REF! -> #REF! | I8: =#REF! -> #REF!
B9: =+B7-B8 -> #REF! | C9: =+C7-C8 -> #REF! | D9: =+D7-D8 -> #REF! | E9: =+E7-E8 -> #REF! | F9: =+F7-F8 -> #REF! | G9: =+G7-G8 -> #REF! | H9: =+H7-H8 -> #REF! | I9: =+I7-I8 -> #REF!
A10: PP/HD TAPE | B10: ='ERP STOCK'!B8 -> 182370.98 | C10: ='ERP STOCK'!C8 -> 5495.1 | D10: ='ERP STOCK'!D8 -> 690008.29 | E10: ='ERP STOCK'!E8 -> 8597.3 | F10: ='ERP STOCK'!F8 -> 10.6 | G10: ='ERP STOCK'!G8 -> 705935.42 | H10: ='ERP STOCK'!H8 -> 0 | I10: ='ERP STOCK'!I8 -> 180525.65 | ... L10: ='ERP STOCK'!L8 -> 1624730.8
B11: =#REF! -> #REF! | C11: =#REF! -> #REF! | D11: =#REF! -> #REF! | E11: =#REF! -> #REF! | F11: =#REF! -> #REF! | G11: =#REF! -> #REF! | H11: =#REF! -> #REF! | I11: =#REF! -> #REF!
B12: =+B10-B11 -> #REF! | C12: =+C10-C11 -> #REF! | D12: =+D10-D11 -> #REF! | E12: =+E10-E11 -> #REF! | F12: =+F10-F11 -> #REF! | G12: =+G10-G11 -> #REF! | H12: =+H10-H11 -> #REF! | I12: =+I10-I11 -> #REF!
A13: UL FABRIC | B13: ='ERP STOCK'!B9 -> 5623632.4 | C13: ='ERP STOCK'!C9 -> 73519 | D13: ='ERP STOCK'!D9 -> 578465 | E13: ='ERP STOCK'!E9 -> 176380.3 | F13: ='ERP STOCK'!F9 -> 213703.5 | G13: ='ERP STOCK'!G9 -> 428251.45 | H13: ='ERP STOCK'!H9 -> 128775.9 | I13: ='ERP STOCK'!I9 -> 5681265.8 | ... L13: ='ERP STOCK'!L9 -> 90900253
B14: =#REF! -> #REF! | C14: =#REF! -> #REF! | D14: =#REF! -> #REF! | E14: =#REF! -> #REF! | F14: =#REF! -> #REF! | G14: =#REF! -> #REF! | H14: =#REF! -> #REF! | I14: =#REF! -> #REF!
B15: =+B13-B14 -> #REF! | C15: =+C13-C14 -> #REF! | D15: =+D13-D14 -> #REF! | E15: =+E13-E14 -> #REF! | F15: =+F13-F14 -> #REF! | G15: =+G13-G14 -> #REF! | H15: =+H13-H14 -> #REF! | I15: =+I13-I14 -> #REF!
A16: LAMINETED FABRIC | B16: ='ERP STOCK'!B10 -> 771450.44 | C16: ='ERP STOCK'!C10 -> 3003.4 | D16: ='ERP STOCK'!D10 -> 275216.2 | E16: ='ERP STOCK'!E10 -> 68732.7 | F16: ='ERP STOCK'!F10 -> 115312.1 | G16: ='ERP STOCK'!G10 -> 245377.7 | H16: ='ERP STOCK'!H10 -> 14916.3 | I16: ='ERP STOCK'!I10 -> 742796.64 | ... L16: ='ERP STOCK'!L10 -> 15598729
B17: =#REF! -> #REF! | C17: =#REF! -> #REF! | D17: =#REF! -> #REF! | E17: =#REF! -> #REF! | F17: =#REF! -> #REF! | G17: =#REF! -> #REF! | H17: =#REF! -> #REF! | I17: =#REF! -> #REF!
B18: =+B16-B17 -> #REF! | C18: =+C16-C17 -> #REF! | D18: =+D16-D17 -> #REF! | E18: =+E16-E17 -> #REF! | F18: =+F16-F17 -> #REF! | G18: =+G16-G17 -> #REF! | H18: =+H16-H17 -> #REF! | I18: =+I16-I17 -> #REF!
A19: WEBBING | B19: ='ERP STOCK'!B11 -> 682335.87 | C19: ='ERP STOCK'!C11 -> 2804.7 | D19: ='ERP STOCK'!D11 -> 114635.1 | E19: ='ERP STOCK'!E11 -> 4950.5 | F19: ='ERP STOCK'!F11 -> 27043.2 | G19: ='ERP STOCK'!G11 -> 88553.3 | H19: ='ERP STOCK'!H11 -> 3777.4 | I19: ='ERP STOCK'!I11 -> 685352.27 | ... L19: ='ERP STOCK'!L11 -> 10965636
B20: =#REF! -> #REF! | C20: =#REF! -> #REF! | D20: =#REF! -> #REF! | E20: =#REF! -> #REF! | F20: =#REF! -> #REF! | G20: =#REF! -> #REF! | H20: =#REF! -> #REF! | I20: =#REF! -> #REF!
B21: =+B19-B20 -> #REF! | C21: =+C19-C20 -> #REF! | D21: =+D19-D20 -> #REF! | E21: =+E19-E20 -> #REF! | F21: =+F19-F20 -> #REF! | G21: =+G19-G20 -> #REF! | H21: =+H19-H20 -> #REF! | I21: =+I19-I20 -> #REF!
A22: TAPE WASTE | B22: ='ERP STOCK'!B12 -> -151002.69 | C22: ='ERP STOCK'!C12 -> 0 | D22: ='ERP STOCK'!D12 -> 42534 | E22: ='ERP STOCK'!E12 -> 0 | F22: ='ERP STOCK'!F12 -> 0 | G22: ='ERP STOCK'!G12 -> 179189 | H22: ='ERP STOCK'!H12 -> 0 | I22: ='ERP STOCK'!I12 -> -287657.69 | ... L22: ='ERP STOCK'!L12 -> -4314865.3
A23: PP WASTE | B23: ='ERP STOCK'!B19 -> -21868 | C23: ='ERP STOCK'!C19 -> 0 | D23: ='ERP STOCK'!D19 -> 0 | E23: ='ERP STOCK'!E19 -> 0 | F23: ='ERP STOCK'!F19 -> 3978 | G23: ='ERP STOCK'!G19 -> 0 | H23: ='ERP STOCK'!H19 -> 0 | I23: ='ERP STOCK'!I19 -> -25846 | ... L23: ='ERP STOCK'!L19 -> -387690
A24: FABRIC WASTE | B24: ='ERP STOCK'!B13 -> -38316.75 | C24: ='ERP STOCK'!C13 -> 38647.85 | D24: ='ERP STOCK'!D13 -> 71320.42 | E24: ='ERP STOCK'!E13 -> 64792.2 | F24: ='ERP STOCK'!F13 -> 18635 | G24: ='ERP STOCK'!G13 -> 179189 | H24: ='ERP STOCK'!H13 -> 0 | I24: ='ERP STOCK'!I13 -> -61380.28 | ... L24: ='ERP STOCK'!L13 -> -920704.2
B25: =#REF! -> #REF! | C25: =#REF! -> #REF! | D25: =#REF! -> #REF! | E25: =#REF! -> #REF! | F25: =#REF! -> #REF! | G25: =#REF! -> #REF! | H25: =#REF! -> #REF! | I25: =#REF! -> #REF!
B26: =+B22+B23+B24-B25 -> #REF! | C26: =+C22+C23+C24-C25 -> #REF! | D26: =+D22+D23+D24-D25 -> #REF! | E26: =+E22+E23+E24-E25 -> #REF! | F26: =+F22+F23+F24-F25 -> #REF! | G26: =+G22+G23+G24-G25 -> #REF! | H26: =+H22+H23+H24-H25 -> #REF! | I26: =+I22+I23+I24-I25 -> #REF!
A27: PP MF YARN | B27: ='ERP STOCK'!B14 -> 44360.71 | C27: ='ERP STOCK'!C14 -> 35352.2 | D27: ='ERP STOCK'!D14 -> 0 | E27: ='ERP STOCK'!E14 -> 2433.24 | F27: ='ERP STOCK'!F14 -> 176.4 | G27: ='ERP STOCK'!G14 -> 33533.3 | H27: ='ERP STOCK'!H14 -> 6496.6 | I27: ='ERP STOCK'!I14 -> 41939.85 | ... L27: ='ERP STOCK'!L14 -> 5255956.6
A28: Crimp Yarn (Texurise Yarn) | B28: ='ERP STOCK'!B15 -> -12123.14 | C28: ='ERP STOCK'!C15 -> 0 | D28: ='ERP STOCK'!D15 -> 0 | E28: ='ERP STOCK'!E15 -> 0 | F28: ='ERP STOCK'!F15 -> 2013.74 | G28: ='ERP STOCK'!G15 -> 0 | H28: ='ERP STOCK'!H15 -> 0 | I28: ='ERP STOCK'!I15 -> -14136.88 | ... L28: ='ERP STOCK'!L15 -> -1574046.1
A29: PP FABRILATED YARN(TAPE) | B29: ='ERP STOCK'!B18 -> -10553.18 | C29: ='ERP STOCK'!C18 -> 5834.3 | D29: ='ERP STOCK'!D18 -> 1723.26 | E29: ='ERP STOCK'!E18 -> 2164.8 | F29: ='ERP STOCK'!F18 -> 0 | G29: ='ERP STOCK'!G18 -> 14882 | H29: ='ERP STOCK'!H18 -> 0 | I29: ='ERP STOCK'!I18 -> -15712.82 | ... L29: ='ERP STOCK'!L18 -> -1637171.1
A30: Filler Cord | B30: ='ERP STOCK'!B22 -> 17502.87 | C30: ='ERP STOCK'!C22 -> 8104.91 | D30: ='ERP STOCK'!D22 -> 1955.6 | E30: ='ERP STOCK'!E22 -> 0 | F30: ='ERP STOCK'!F22 -> 0 | G30: ='ERP STOCK'!G22 -> 9192 | H30: ='ERP STOCK'!H22 -> 0 | I30: ='ERP STOCK'!I22 -> 18371.38 | ... L30: ='ERP STOCK'!L22 -> 220456.56
B31: =#REF! -> #REF! | C31: =#REF! -> #REF! | D31: =#REF! -> #REF! | E31: =#REF! -> #REF! | F31: =#REF! -> #REF! | G31: =#REF! -> #REF! | H31: =#REF! -> #REF! | I31: =#REF! -> #REF!
B32: =+B27+B28+B29+B30-B31 -> #REF! | C32: =+C27+C28+C29+C30-C31 -> #REF! | D32: =+D27+D28+D29+D30-D31 -> #REF! | E32: =+E27+E28+E29+E30-E31 -> #REF! | F32: =+F27+F28+F29+F30-F31 -> #REF! | G32: =+G27+G28+G29+G30-G31 -> #REF! | H32: =+H27+H28+H29+H30-H31 -> #REF! | I32: =+I27+I28+I29+I30-I31 -> #REF!
A33: LLDPE Liner Bags | B33: ='ERP STOCK'!B16 -> 28833.32 | C33: ='ERP STOCK'!C16 -> 19858.6 | D33: ='ERP STOCK'!D16 -> 0 | E33: ='ERP STOCK'!E16 -> 0 | F33: ='ERP STOCK'!F16 -> 0 | G33: ='ERP STOCK'!G16 -> 26234 | H33: ='ERP STOCK'!H16 -> 20708.6 | I33: ='ERP STOCK'!I16 -> 1749.32 | ... L33: ='ERP STOCK'!L16 -> 226584.16
B34: =#REF! -> #REF! | C34: =#REF! -> #REF! | D34: =#REF! -> #REF! | E34: =#REF! -> #REF! | F34: =#REF! -> #REF! | G34: =#REF! -> #REF! | H34: =#REF! -> #REF! | I34: =#REF! -> #REF!
B35: =+B33-B34 -> #REF! | C35: =+C33-C34 -> #REF! | D35: =+D33-D34 -> #REF! | E35: =+E33-E34 -> #REF! | F35: =+F33-F34 -> #REF! | G35: =+G33-G34 -> #REF! | H35: =+H33-H34 -> #REF! | I35: =+I33-I34 -> #REF!
A36: LLDPE Film | B36: ='ERP STOCK'!B17 -> 26898.11 | C36: ='ERP STOCK'!C17 -> 1315.84 | D36: ='ERP STOCK'!D17 -> 0 | E36: ='ERP STOCK'!E17 -> 0 | F36: ='ERP STOCK'!F17 -> 0 | G36: ='ERP STOCK'!G17 -> 1307.89 | H36: ='ERP STOCK'!H17 -> 1111.09 | I36: ='ERP STOCK'!I17 -> 25794.97 | ... L36: ='ERP STOCK'!L17 -> 3001532.1
B37: =#REF! -> #REF! | C37: =#REF! -> #REF! | D37: =#REF! -> #REF! | E37: =#REF! -> #REF! | F37: =#REF! -> #REF! | G37: =#REF! -> #REF! | H37: =#REF! -> #REF! | I37: =#REF! -> #REF!
B38: =B36-B37 -> #REF! | C38: =C36-C37 -> #REF! | D38: =D36-D37 -> #REF! | E38: =E36-E37 -> #REF! | F38: =F36-F37 -> #REF! | G38: =G36-G37 -> #REF! | H38: =H36-H37 -> #REF! | I38: =I36-I37 -> #REF!
A39: MB | B39: ='ERP STOCK'!B20 -> 6045.179 | C39: ='ERP STOCK'!C20 -> 7573.9 | D39: ='ERP STOCK'!D20 -> 0 | E39: ='ERP STOCK'!E20 -> 50 | F39: ='ERP STOCK'!F20 -> 2800 | G39: ='ERP STOCK'!G20 -> 3934.985 | H39: ='ERP STOCK'!H20 -> 0 | I39: ='ERP STOCK'!I20 -> 6934.094 | ... L39: ='ERP STOCK'!L20 -> 1196058
B40: =#REF! -> #REF! | C40: =#REF! -> #REF! | D40: =#REF! -> #REF! | E40: =#REF! -> #REF! | F40: =#REF! -> #REF! | G40: =#REF! -> #REF! | H40: =#REF! -> #REF! | I40: =#REF! -> #REF!
B41: =+B39-B40 -> #REF! | C41: =+C39-C40 -> #REF! | D41: =+D39-D40 -> #REF! | E41: =+E39-E40 -> #REF! | F41: =+F39-F40 -> #REF! | G41: =+G39-G40 -> #REF! | H41: =+H39-H40 -> #REF! | I41: =+I39-I40 -> #REF!
A42: UV | B42: ='ERP STOCK'!B21 -> 34787.135 | C42: ='ERP STOCK'!C21 -> 15045 | D42: ='ERP STOCK'!D21 -> 0 | E42: ='ERP STOCK'!E21 -> 0 | F42: ='ERP STOCK'!F21 -> 0 | G42: ='ERP STOCK'!G21 -> 13989.215 | H42: ='ERP STOCK'!H21 -> 0 | I42: ='ERP STOCK'!I21 -> 35842.92 | ... L42: ='ERP STOCK'!L21 -> 6136551.6
B43: =#REF! -> #REF! | C43: =#REF! -> #REF! | D43: =#REF! -> #REF! | E43: =#REF! -> #REF! | F43: =#REF! -> #REF! | G43: =#REF! -> #REF! | H43: =#REF! -> #REF! | I43: =#REF! -> #REF!
B44: =+B42-B43 -> #REF! | C44: =+C42-C43 -> #REF! | D44: =+D42-D43 -> #REF! | E44: =+E42-E43 -> #REF! | F44: =+F42-F43 -> #REF! | G44: =+G42-G43 -> #REF! | H44: =+H42-H43 -> #REF! | I44: =+I42-I43 -> #REF!
A45: Total | B45: =+B7+B10+B13+B16+B19+B22+B23+B24+B27+B28+B29+B30+B33+B36+B39+B42 -> 7220762.4 | C45: =+C7+C10+C13+C16+C19+C22+C23+C24+C27+C28+C29+C30+C33+C36+C39+C42 -> 227944.8 | D45: =+D7+D10+D13+D16+D19+D22+D23+D24+D27+D28+D29+D30+D33+D36+D39+D42 -> 1948957.9 | E45: =+E7+E10+E13+E16+E19+E22+E23+E24+E27+E28+E29+E30+E33+E36+E39+E42 -> 356217.24 | F45: =+F7+F10+F13+F16+F19+F22+F23+F24+F27+F28+F29+F30+F33+F36+F39+F42 -> 432843.74 | G45: =+G7+G10+G13+G16+G19+G22+G23+G24+G27+G28+G29+G30+G33+G36+G39+G42 -> 2103569.3 | H45: =+H7+H10+H13+H16+H19+H22+H23+H24+H27+H28+H29+H30+H33+H36+H39+H42 -> 175785.89 | I45: =+I7+I10+I13+I16+I19+I22+I23+I24+I27+I28+I29+I30+I33+I36+I39+I42 -> 7041683.4 | J45: =+J7+J10+J13+J16+J19+J22+J23+J24+J27+J28+J29+J30+J33+J36+J39+J42 -> 1568583.8 | L45: =+L7+L10+L13+L16+L19+L22+L23+L24+L27+L28+L29+L30+L33+L36+L39+L42 -> 1.2758422e+08
B46: =B8+B11+B14+B17+B20+B25+B31+B34+B40+B43+B37 -> #REF! | C46: =C8+C11+C14+C17+C20+C25+C31+C34+C40+C43+C37 -> #REF! | D46: =D8+D11+D14+D17+D20+D25+D31+D34+D40+D43+D37 -> #REF! | E46: =E8+E11+E14+E17+E20+E25+E31+E34+E40+E43+E37 -> #REF! | F46: =F8+F11+F14+F17+F20+F25+F31+F34+F40+F43+F37 -> #REF! | G46: =G8+G11+G14+G17+G20+G25+G31+G34+G40+G43+G37 -> #REF! | H46: =H8+H11+H14+H17+H20+H25+H31+H34+H40+H43+H37 -> #REF! | I46: =I8+I11+I14+I17+I20+I25+I31+I34+I40+I43+I37 -> #REF! | L46: =L8+L11+L14+L17+L20+L25+L31+L34+L40+L43 -> 0
B47: =+B45-B46 -> #REF! | C47: =+C45-C46 -> #REF! | D47: =+D45-D46 -> #REF! | E47: =+E45-E46 -> #REF! | F47: =+F45-F46 -> #REF! | G47: =+G45-G46 -> #REF! | H47: =+H45-H46 -> #REF! | I47: =+I45-I46 -> #REF!
A49: FG
A50: PP/ HDPE BAGS | B50: ='ERP STOCK'!B26 -> 2758.6 | C50: ='ERP STOCK'!C26 -> 0 | D50: ='ERP STOCK'!D26 -> 17602 | E50: ='ERP STOCK'!E26 -> 0 | F50: ='ERP STOCK'!F26 -> 22274 | G50: ='ERP STOCK'!G26 -> 0 | H50: ='ERP STOCK'!H26 -> 0 | I50: ='ERP STOCK'!I26 -> -1913.4 | ... L50: ='ERP STOCK'!L26 -> -163933.41
B52: =+B50-B51 -> 2758.6 | C52: =+C50-C51 -> 0 | D52: =+D50-D51 -> 17602 | E52: =+E50-E51 -> 0 | F52: =+F50-F51 -> 22274 | G52: =+G50-G51 -> 0 | H52: =+H50-H51 -> 0 | I52: =+I50-I51 -> -1913.4
A53: PP BAGS | B53: ='ERP STOCK'!B27 -> 8807.4 | C53: ='ERP STOCK'!C27 -> 1253.9 | D53: ='ERP STOCK'!D27 -> 0 | E53: ='ERP STOCK'!E27 -> 0 | F53: ='ERP STOCK'!F27 -> 0 | G53: ='ERP STOCK'!G27 -> 0 | H53: ='ERP STOCK'!H27 -> 0 | I53: ='ERP STOCK'!I27 -> 10061.3 | ... L53: ='ERP STOCK'!L27 -> 0
B54: =#REF! -> #REF! | C54: =#REF! -> #REF! | D54: =#REF! -> #REF! | E54: =#REF! -> #REF! | F54: =#REF! -> #REF! | G54: =#REF! -> #REF! | H54: =#REF! -> #REF! | I54: =#REF! -> #REF!
B55: =+B53-B54 -> #REF! | C55: =+C53-C54 -> #REF! | D55: =+D53-D54 -> #REF! | E55: =+E53-E54 -> #REF! | F55: =+F53-F54 -> #REF! | G55: =+G53-G54 -> #REF! | H55: =+H53-H54 -> #REF! | I55: =+I53-I54 -> #REF!
A56: PP WOVEN BIG BAGS | B56: ='ERP STOCK'!B28 -> 267536.18 | C56: ='ERP STOCK'!C28 -> 18506 | D56: ='ERP STOCK'!D28 -> 481097 | E56: ='ERP STOCK'!E28 -> 175106.5 | F56: ='ERP STOCK'!F28 -> 520652.9 | G56: ='ERP STOCK'!G28 -> 0 | H56: ='ERP STOCK'!H28 -> 0 | I56: ='ERP STOCK'!I28 -> 421592.78 | ... L56: ='ERP STOCK'!L28 -> 66749398
B57: =#REF! -> #REF! | C57: =#REF! -> #REF! | D57: =#REF! -> #REF! | E57: =#REF! -> #REF! | F57: =#REF! -> #REF! | G57: =#REF! -> #REF! | H57: =#REF! -> #REF! | I57: =#REF! -> #REF!
B58: =+B56-B57 -> #REF! | C58: =+C56-C57 -> #REF! | D58: =+D56-D57 -> #REF! | E58: =+E56-E57 -> #REF! | F58: =+F56-F57 -> #REF! | G58: =+G56-G57 -> #REF! | H58: =+H56-H57 -> #REF! | I58: =+I56-I57 -> #REF!
A59: Total | B59: =+B50+B53+B56 -> 279102.18 | C59: =+C50+C53+C56 -> 19759.9 | D59: =+D50+D53+D56 -> 498699 | E59: =+E50+E53+E56 -> 175106.5 | F59: =+F50+F53+F56 -> 542926.9 | G59: =+G50+G53+G56 -> 0 | H59: =+H50+H53+H56 -> 0 | I59: =+I50+I53+I56 -> 429740.68 | J59: =+J50+J53+J56 -> 815 | L59: =+L50+L53+L56 -> 66585464
B60: =B51+B54+B57 -> #REF! | C60: =C51+C54+C57 -> #REF! | D60: =D51+D54+D57 -> #REF! | E60: =E51+E54+E57 -> #REF! | F60: =F51+F54+F57 -> #REF! | G60: =G51+G54+G57 -> #REF! | H60: =H51+H54+H57 -> #REF! | I60: =I51+I54+I57 -> #REF! | J60: =J51+J54+J57 -> 0 | L60: =L51+L54+L57 -> 0
B61: =+B59-B60 -> #REF! | C61: =+C59-C60 -> #REF! | D61: =+D59-D60 -> #REF! | E61: =+E59-E60 -> #REF! | F61: =+F59-F60 -> #REF! | G61: =+G59-G60 -> #REF! | H61: =+H59-H60 -> #REF! | I61: =+I59-I60 -> #REF!
A63: CN
A64: All Ink | B64: ='ERP STOCK'!B32 -> 12133 | C64: ='ERP STOCK'!C32 -> 270 | D64: ='ERP STOCK'!D32 -> 0 | E64: ='ERP STOCK'!E32 -> 0 | F64: ='ERP STOCK'!F32 -> 0 | G64: ='ERP STOCK'!G32 -> 530 | H64: ='ERP STOCK'!H32 -> 0 | I64: ='ERP STOCK'!I32 -> 11873 | ... L64: ='ERP STOCK'!L32 -> 2403269.9
B65: =#REF! -> #REF! | C65: =#REF! -> #REF! | D65: =#REF! -> #REF! | E65: =#REF! -> #REF! | F65: =#REF! -> #REF! | G65: =#REF! -> #REF! | H65: =#REF! -> #REF! | I65: =#REF! -> #REF!
B66: =+B64-B65 -> #REF! | C66: =+C64-C65 -> #REF! | D66: =+D64-D65 -> #REF! | E66: =+E64-E65 -> #REF! | F66: =+F64-F65 -> #REF! | G66: =+G64-G65 -> #REF! | H66: =+H64-H65 -> #REF! | I66: =+I64-I65 -> #REF!
A67: Thinner | B67: ='ERP STOCK'!B33 -> 10403.3 | C67: ='ERP STOCK'!C33 -> 2210 | D67: ='ERP STOCK'!D33 -> 0 | E67: ='ERP STOCK'!E33 -> 0 | F67: ='ERP STOCK'!F33 -> 0 | G67: ='ERP STOCK'!G33 -> 1680 | H67: ='ERP STOCK'!H33 -> 0 | I67: ='ERP STOCK'!I33 -> 10933.3 | ... L67: ='ERP STOCK'!L33 -> 829064.14
B68: =#REF! -> #REF! | C68: =#REF! -> #REF! | D68: =#REF! -> #REF! | E68: =#REF! -> #REF! | F68: =#REF! -> #REF! | G68: =#REF! -> #REF! | H68: =#REF! -> #REF! | I68: =#REF! -> #REF!
B69: =+B67-B68 -> #REF! | C69: =+C67-C68 -> #REF! | D69: =+D67-D68 -> #REF! | E69: =+E67-E68 -> #REF! | F69: =+F67-F68 -> #REF! | G69: =+G67-G68 -> #REF! | H69: =+H67-H68 -> #REF! | I69: =+I67-I68 -> #REF!
A70: Total | B70: =+B64+B67 -> 22536.3 | C70: =+C64+C67 -> 2480 | D70: =+D64+D67 -> 0 | E70: =+E64+E67 -> 0 | F70: =+F64+F67 -> 0 | G70: =+G64+G67 -> 2210 | H70: =+H64+H67 -> 0 | I70: =+I64+I67 -> 22806.3 | J70: =+J64+J67 -> 850 | L70: =+L64+L67 -> 3232334
B71: =B65+B68 -> #REF! | C71: =C65+C68 -> #REF! | D71: =D65+D68 -> #REF! | E71: =E65+E68 -> #REF! | F71: =F65+F68 -> #REF! | G71: =G65+G68 -> #REF! | H71: =H65+H68 -> #REF! | I71: =I65+I68 -> #REF! | J71: =J65+J68 -> 0 | L71: =L65+L68 -> 0
B72: =+B70-B71 -> #REF! | C72: =+C70-C71 -> #REF! | D72: =+D70-D71 -> #REF! | E72: =+E70-E71 -> #REF! | F72: =+F70-F71 -> #REF! | G72: =+G70-G71 -> #REF! | H72: =+H70-H71 -> #REF! | I72: =+I70-I71 -> #REF!
A74: RM
A75: PP | B75: ='ERP STOCK'!B37 -> 136400.33 | C75: ='ERP STOCK'!C37 -> 963286 | D75: ='ERP STOCK'!D37 -> 0 | E75: ='ERP STOCK'!E37 -> 13500 | F75: ='ERP STOCK'!F37 -> 213775 | G75: ='ERP STOCK'!G37 -> 483033.14 | H75: ='ERP STOCK'!H37 -> 306195 | I75: ='ERP STOCK'!I37 -> 110183.19 | ... L75: ='ERP STOCK'!L37 -> 8024422.6
B76: =#REF!+#REF! -> #REF! | C76: =#REF!+#REF! -> #REF! | D76: =#REF!+#REF! -> #REF! | E76: =#REF!+#REF! -> #REF! | F76: =#REF!+#REF! -> #REF! | G76: =#REF!+#REF! -> #REF! | H76: =#REF!+#REF! -> #REF! | I76: =#REF!+#REF! -> #REF!
B77: =B75-B76 -> #REF! | C77: =C75-C76 -> #REF! | D77: =D75-D76 -> #REF! | E77: =E75-E76 -> #REF! | F77: =F75-F76 -> #REF! | G77: =G75-G76 -> #REF! | H77: =H75-H76 -> #REF! | I77: =I75-I76 -> #REF!
A78: LDPE | B78: ='ERP STOCK'!B38 -> 31719.681 | C78: ='ERP STOCK'!C38 -> 8100 | D78: ='ERP STOCK'!D38 -> 0 | E78: ='ERP STOCK'!E38 -> 0 | F78: ='ERP STOCK'!F38 -> 0 | G78: ='ERP STOCK'!G38 -> 10859.25 | H78: ='ERP STOCK'!H38 -> 2550 | I78: ='ERP STOCK'!I38 -> 26410.431 | ... L78: ='ERP STOCK'!L38 -> 2676324.4
B79: =+#REF!+#REF! -> #REF! | C79: =+#REF!+#REF! -> #REF! | D79: =+#REF!+#REF! -> #REF! | E79: =+#REF!+#REF! -> #REF! | F79: =+#REF!+#REF! -> #REF! | G79: =+#REF!+#REF! -> #REF! | H79: =+#REF!+#REF! -> #REF! | I79: =+#REF!+#REF! -> #REF!
B80: =B78-B79 -> #REF! | C80: =C78-C79 -> #REF! | D80: =D78-D79 -> #REF! | E80: =E78-E79 -> #REF! | F80: =F78-F79 -> #REF! | G80: =G78-G79 -> #REF! | H80: =H78-H79 -> #REF! | I80: =I78-I79 -> #REF!
A81: LLDPE | B81: ='ERP STOCK'!B39 -> 14658.539 | C81: ='ERP STOCK'!C39 -> 23000 | D81: ='ERP STOCK'!D39 -> 0 | E81: ='ERP STOCK'!E39 -> 0 | F81: ='ERP STOCK'!F39 -> 2600 | G81: ='ERP STOCK'!G39 -> 17509.25 | H81: ='ERP STOCK'!H39 -> 350 | I81: ='ERP STOCK'!I39 -> 17199.289 | ... L81: ='ERP STOCK'!L39 -> 1542131.2
B82: =#REF! -> #REF! | C82: =#REF! -> #REF! | D82: =#REF! -> #REF! | E82: =#REF! -> #REF! | F82: =#REF! -> #REF! | G82: =#REF! -> #REF! | H82: =#REF! -> #REF! | I82: =#REF! -> #REF!
B83: =B81-B82 -> #REF! | C83: =C81-C82 -> #REF! | D83: =D81-D82 -> #REF! | E83: =E81-E82 -> #REF! | F83: =F81-F82 -> #REF! | G83: =G81-G82 -> #REF! | H83: =H81-H82 -> #REF! | I83: =I81-I82 -> #REF!
A84: HDPE | B84: ='ERP STOCK'!B40 -> 1093.32 | C84: ='ERP STOCK'!C40 -> 0 | D84: ='ERP STOCK'!D40 -> 0 | E84: ='ERP STOCK'!E40 -> 0 | F84: ='ERP STOCK'!F40 -> 0 | G84: ='ERP STOCK'!G40 -> 158.75 | H84: ='ERP STOCK'!H40 -> 0 | I84: ='ERP STOCK'!I40 -> 934.57 | ... L84: ='ERP STOCK'!L40 -> 86774.82
B85: =#REF! -> #REF! | C85: =#REF! -> #REF! | D85: =#REF! -> #REF! | E85: =#REF! -> #REF! | F85: =#REF! -> #REF! | G85: =#REF! -> #REF! | H85: =#REF! -> #REF! | I85: =#REF! -> #REF!
B86: =B84-B85 -> #REF! | C86: =C84-C85 -> #REF! | D86: =D84-D85 -> #REF! | E86: =E84-E85 -> #REF! | F86: =F84-F85 -> #REF! | G86: =G84-G85 -> #REF! | H86: =H84-H85 -> #REF! | I86: =I84-I85 -> #REF!
A87: FILLER | B87: ='ERP STOCK'!B41 -> 55988.7 | C87: ='ERP STOCK'!C41 -> 64175 | D87: ='ERP STOCK'!D41 -> 0 | E87: ='ERP STOCK'!E41 -> 0 | F87: ='ERP STOCK'!F41 -> 14425 | G87: ='ERP STOCK'!G41 -> 51317.2 | H87: ='ERP STOCK'!H41 -> 5530 | I87: ='ERP STOCK'!I41 -> 48891.5 | ... L87: ='ERP STOCK'!L41 -> 1524747.1
B88: =#REF!+#REF!+#REF! -> #REF! | C88: =#REF!+#REF!+#REF! -> #REF! | D88: =#REF!+#REF!+#REF! -> #REF! | E88: =#REF!+#REF!+#REF! -> #REF! | F88: =#REF!+#REF!+#REF! -> #REF! | G88: =#REF!+#REF!+#REF! -> #REF! | H88: =#REF!+#REF!+#REF! -> #REF! | I88: =#REF!+#REF!+#REF! -> #REF!
B89: =B87-B88 -> #REF! | C89: =C87-C88 -> #REF! | D89: =D87-D88 -> #REF! | E89: =E87-E88 -> #REF! | F89: =F87-F88 -> #REF! | G89: =G87-G88 -> #REF! | H89: =H87-H88 -> #REF! | I89: =I87-I88 -> #REF!
A90: OTHER | B90: ='ERP STOCK'!B42 -> 3770.46 | C90: ='ERP STOCK'!C42 -> 277.32 | D90: ='ERP STOCK'!D42 -> 0 | E90: ='ERP STOCK'!E42 -> 0 | F90: ='ERP STOCK'!F42 -> 0 | G90: ='ERP STOCK'!G42 -> 0 | H90: ='ERP STOCK'!H42 -> 0 | I90: ='ERP STOCK'!I42 -> 4047.78 | ... L90: ='ERP STOCK'!L42 -> 0
B92: =B90-B91 -> 3770.46 | C92: =C90-C91 -> 277.32 | D92: =D90-D91 -> 0 | E92: =E90-E91 -> 0 | F92: =F90-F91 -> 0 | G92: =G90-G91 -> 0 | H92: =H90-H91 -> 0 | I92: =I90-I91 -> 4047.78
A93: Total | B93: =+B75+B78+B81+B84+B87+B90 -> 243631.03 | C93: =+C75+C78+C81+C84+C87+C90 -> 1058838.3 | D93: =+D75+D78+D81+D84+D87+D90 -> 0 | E93: =+E75+E78+E81+E84+E87+E90 -> 13500 | F93: =+F75+F78+F81+F84+F87+F90 -> 230800 | G93: =+G75+G78+G81+G84+G87+G90 -> 562877.59 | H93: =+H75+H78+H81+H84+H87+H90 -> 314625 | I93: =+I75+I78+I81+I84+I87+I90 -> 207666.76 | J93: =+J75+J78+J81+J84+J87+J90 -> 3747252 | L93: =+L75+L78+L81+L84+L87+L90 -> 13854400
B94: =B76+B79+B82+B85+B88+B91 -> #REF! | C94: =C76+C79+C82+C85+C88+C91 -> #REF! | D94: =D76+D79+D82+D85+D88+D91 -> #REF! | E94: =E76+E79+E82+E85+E88+E91 -> #REF! | F94: =F76+F79+F82+F85+F88+F91 -> #REF! | G94: =G76+G79+G82+G85+G88+G91 -> #REF! | H94: =H76+H79+H82+H85+H88+H91 -> #REF! | I94: =I76+I79+I82+I85+I88+I91 -> #REF! | J94: =J76+J79+J82+J85+J88+J91 -> 0 | L94: =L88+L91 -> 0
B95: =+B93-B94 -> #REF! | C95: =+C93-C94 -> #REF! | D95: =+D93-D94 -> #REF! | E95: =+E93-E94 -> #REF! | F95: =+F93-F94 -> #REF! | G95: =+G93-G94 -> #REF! | H95: =+H93-H94 -> #REF! | I95: =+I93-I94 -> #REF!
A97: AS PER ERP | B97: =B45+B59+B70+B93 -> 7766031.9 | C97: =C45+C59+C70+C93 -> 1309023 | D97: =D45+D59+D70+D93 -> 2447656.9 | E97: =E45+E59+E70+E93 -> 544823.74 | F97: =F45+F59+F70+F93 -> 1206570.6 | G97: =G45+G59+G70+G93 -> 2668656.9 | H97: =H45+H59+H70+H93 -> 490410.89 | I97: =I45+I59+I70+I93 -> 7701897.1 | J97: =J45+J59+J70+J93 -> 5317500.9 | L97: =L45+L59+L70+L93 -> 2.1125642e+08
A98: AS PER WORKING | B98: =B46+B60+B71+B94 -> #REF! | C98: =C46+C60+C71+C94 -> #REF! | D98: =D46+D60+D71+D94 -> #REF! | E98: =E46+E60+E71+E94 -> #REF! | F98: =F46+F60+F71+F94 -> #REF! | G98: =G46+G60+G71+G94 -> #REF! | H98: =H46+H60+H71+H94 -> #REF! | I98: =I46+I60+I71+I94 -> #REF! | J98: =J46+J60+J71+J94 -> 0 | L98: =L46+L60+L71+L94 -> 0
A99: DIFFERENCE | B99: =B97-B98 -> #REF! | C99: =C97-C98 -> #REF! | D99: =D97-D98 -> #REF! | E99: =E97-E98 -> #REF! | F99: =F97-F98 -> #REF! | G99: =G97-G98 -> #REF! | H99: =H97-H98 -> #REF! | I99: =I97-I98 -> #REF! | ... L99: =L97-L98 -> 2.1125642e+08
B101: =B98-#REF! -> #REF! | C101: =C98-#REF! -> #REF! | D101: =D98-#REF! -> #REF! | E101: =E98-#REF! -> #REF! | F101: =F98-#REF! -> #REF! | G101: =G98-#REF! -> #REF! | H101: =H98-#REF! -> #REF! | I101: =I98-#REF! -> #REF!
B106: AS PER ERP | C106: AS PER WORKING | D106: DIFF
A107: LAMINATION | B107: ='Lam Fabric'!D34 -> 130741 | C107: =#REF! -> #REF! | D107: =B107-C107 -> #REF! | G107: =D107-D18 -> #REF!
A108: UL FABRIC | B108: ='Unlaminated Fabric'!K34 -> 110635.3 | C108: =#REF! -> #REF! | D108: =B108-C108 -> #REF! | E108: =+D108+D117 -> #REF! | G108: =E108-G15 -> #REF!
A109: PP | B109: =#REF! -> #REF! | C109: =#REF! -> #REF! | D109: =B109-C109 -> #REF! | G109: =D109-G77 -> #REF!
A110: LD | B110: =LLDP!G34 -> 0 | C110: =#REF! -> #REF! | D110: =B110-C110 -> #REF!
A111: FILLER | B111: =FillerSoltex!H34 -> 0 | C111: =#REF! -> #REF! | D111: =B111-C111 -> #REF!
A112: MB | B112: =MB!H34 -> 400 | C112: =#REF! -> #REF! | D112: =B112-C112 -> #REF!
A113: WASTAGE | B113: =Wastage!F34 -> 5677 | C113: =#REF! -> #REF! | D113: =B113-C113 -> #REF! | E113: =D113+D117 -> #REF! | F113: =E113+D131 -> #REF!
B115: =B107+B113-B108-B109-B110-B111-B112 -> #REF! | C115: =C107+C113-C108-C109-C110-C111-C112 -> #REF!
...

Sheet New Working
A1: PLASTENE INDIA LIMITED UNIT - II
A2: EBDITA from 1st Dec 2019 to 14th Dec 2019
A3: Sales | B3: Qty | C3: Rate | D3: Value
A4: Plastic Used Bags | B4: =Sheet3!J6 -> 0 | C4: =D4/B4 -> #DIV/0! | D4: =Sheet3!L6 -> 0
A5: PP WOVEN BIG BAGS / SACKS | B5: =Sheet3!J7 -> 306664.9 | C5: =D5/B5 -> 157.96893 | D5: =Sheet3!L7 -> 48443526
A6: PP Woven Fabrics(FG) | B6: =Sheet3!J8 -> 85056.5 | C6: =D6/B6 -> 105.13316 | D6: =Sheet3!L8 -> 8942258.9
A7: PP Laminated Fabric | B7: =Sheet3!J9 -> 40640.5 | C7: =D7/B7 -> 103.30194 | D7: =Sheet3!L9 -> 4198242.7
A8: REPROCESS GRANULES (FG) | B8: =Sheet3!J10 -> 14100 | C8: =D8/B8 -> 20 | D8: =Sheet3!L10 -> 282000
A9: PP TAPE / YARN | B9: =Sheet3!J11 -> 0 | C9: =D9/B9 -> #DIV/0! | D9: =Sheet3!L11 -> 0
A10: PP Fabric Wastage | B10: =Sheet3!J12 -> 0 | C10: =D10/B10 -> #DIV/0! | D10: =Sheet3!L12 -> 0
A11: PP Tape Wastage | B11: =Sheet3!J13 -> 7960 | C11: =D11/B11 -> 15 | D11: =Sheet3!L13 -> 119400
A12: PP WEBBING (FG) | B12: =Sheet3!J14 -> 12228.8 | C12: =D12/B12 -> 103.29697 | D12: =Sheet3!L14 -> 1263198
A13: Filler | B13: =Sheet3!J15 -> 8500 | C13: =D13/B13 -> 29.5 | D13: =Sheet3!L15 -> 250750
A14: Master Batch | B14: =Sheet3!J16 -> 500 | C14: =D14/B14 -> 141 | D14: =Sheet3!L16 -> 70500
A15: LLDPE GRANULES | B15: =Sheet3!J17 -> 125 | C15: =D15/B15 -> 68.248 | D15: =Sheet3!L17 -> 8531
... A18: LDPE GRANUALES | B18: =Sheet3!J20 -> 0 | C18: =D18/B18 -> #DIV/0! | D18: =Sheet3!L20 -> 0
A20: TOTAL SALE | B20: =SUM(B4:B19) -> 493775.7 | C20: =D20/B20 -> 131.52522 | D20: =SUM(D4:D19) -> 64943957
A24: Raw Material Consumption | B24: Qty | C24: Rate | D24: Value | E24: Rate Ref
A25: For Tape Plant
A26: PP | B26: =#REF! -> #REF! | C26: =#REF! -> #REF! | D26: =B26*C26 -> #REF! | E26: FIFO
A27: Filler | B27: =#REF! -> #REF! | C27: =FillerSoltex!Y6 -> #REF! | D27: =B27*C27 -> #REF! | E27: FIFO
A28: MB | B28: =#REF! -> #REF! | C28: =MB!Y6 -> #REF! | D28: =B28*C28 -> #REF! | E28: FIFO
A29: UV | B29: =#REF! -> #REF! | C29: =UV!Y6 -> #REF! | D29: =B29*C29 -> #REF! | E29: FIFO
A30: HDPE | B30: =#REF! -> #REF! | C30: =#REF! -> #REF! | D30: =B30*C30 -> #REF! | E30: FIFO
A31: LLDPE | B31: =#REF! -> #REF! | C31: =#REF! -> #REF! | D31: =B31*C31 -> #REF! | E31: FIFO
A32: RP | B32: =#REF!*0 -> #REF! | C32: 0 | D32: =B32*C32 -> #REF! | E32: Wastage
A34: TOTAL PLANT CONSUMPTION | B34: =SUM(B26:B33) -> #REF! | C34: =D34/B34 -> #REF! | D34: =SUM(D26:D33) -> #REF!
A36: For Yarn
A37: Yarn | B37: =SUMIF(#REF!,"YARN",#REF!) -> #REF! | C37: =D37/B37 -> #REF! | D37: =SUMIF(#REF!,"YARN",#REF!) -> #REF! | E37: FIFO
A39: For Lamination
A40: PP | B40: =#REF! -> #REF! | C40: =#REF! -> #REF! | D40: =B40*C40 -> #REF! | E40: FIFO
A41: LDPE | B41: =#REF! -> #REF! | C41: =LLDP!Z6 -> #REF! | D41: =B41*C41 -> #REF! | E41: FIFO
A42: MB | B42: =#REF! -> #REF! | C42: =MB!Y6 -> #REF! | D42: =B42*C42 -> #REF! | E42: FIFO
A43: Filler | B43: =#REF! -> #REF! | C43: =FillerSoltex!Y6 -> #REF! | D43: =B43*C43 -> #REF! | E43: FIFO
A44: UV | C44: =UV!Y6 -> #REF! | D44: =B44*C44 -> #REF! | E44: FIFO
A45: RP | D45: =B45*C45 -> 0 | E45: FIFO
A47: OUTSIDE PURCHASE
A48: Fabric UL | B48: =SUMIF(#REF!,"UL FABRIC",#REF!) -> #REF! | C48: =D48/B48 -> #REF! | D48: =SUMIF(#REF!,"UL FABRIC",#REF!) -> #REF! | E48: Pur Rate
A49: FIBC | B49: =SUMIF(#REF!,"FIBC",#REF!) -> #REF! | C49: =D49/B49 -> #REF! | D49: =SUMIF(#REF!,"FIBC",#REF!) -> #REF! | E49: Pur Rate
A50: Film | B50: =SUMIF(#REF!,"FILM",#REF!) -> #REF! | C50: =D50/B50 -> #REF! | D50: =SUMIF(#REF!,"FILM",#REF!) -> #REF! | E50: Pur Rate
A51: Fabric Lam | B51: =SUMIF(#REF!,"LAM FABRIC",#REF!) -> #REF! | C51: =D51/B51 -> #REF! | D51: =SUMIF(#REF!,"LAM FABRIC",#REF!) -> #REF! | E51: Pur Rate
A52: Liner Bags | B52: =SUMIF(#REF!,"LLDPE BAGS",#REF!) -> #REF! | C52: =D52/B52 -> #REF! | D52: =SUMIF(#REF!,"LLDPE BAGS",#REF!) -> #REF! | E52: Pur Rate
A53: RP | B53: =SUMIF(#REF!,"RP",#REF!) -> #REF! | C53: =D53/B53 -> #REF! | D53: =SUMIF(#REF!,"RP",#REF!) -> #REF! | E53: Pur Rate
A54: Ink | B54: =SUMIF(#REF!,"Ink",#REF!) -> #REF! | C54: =D54/B54 -> #REF! | D54: =SUMIF(#REF!,"Ink",#REF!) -> #REF! | E54: Pur Rate
A55: Special Tape | B55: 0 | C55: =D55/B55 -> #DIV/0! | D55: 0 | E55: Pur Rate
A56: Tape | B56: =SUMIF(#REF!,"TAPE",#REF!) -> #REF! | C56: =D56/B56 -> #REF! | D56: =SUMIF(#REF!,"TAPE",#REF!) -> #REF! | E56: Pur Rate
A57: Wastage | B57: =SUMIF(#REF!,"WASTAGE",#REF!) -> #REF! | C57: =D57/B57 -> #REF! | D57: =SUMIF(#REF!,"WASTAGE",#REF!) -> #REF! | E57: Pur Rate
A58: Webbing | B58: =SUMIF(#REF!,"WEBBING",#REF!) -> #REF! | C58: =D58/B58 -> #REF! | D58: =SUMIF(#REF!,"WEBBING",#REF!) -> #REF! | E58: Pur Rate | G58: =SUMIF(#REF!,"RM",#REF!) -> #REF! | I58: =SUMIF(#REF!,"RM",#REF!) -> #REF!
A59: THINNER | B59: =SUMIF(#REF!,"THINNER",#REF!) -> #REF! | C59: =D59/B59 -> #REF! | D59: =SUMIF(#REF!,"THINNER",#REF!) -> #REF! | E59: Pur Rate | G59: =SUM(B48:B59)+G58+B37-#REF! -> #REF! | I59: =SUM(D48:D59)+I58+D37-#REF! -> #REF!
A61: Job Consumption
A62: Liner Bags | B62: =#REF!*0 -> #REF! | C62: 0 | D62: =B62*C62 -> #REF! | E62: Pur Rate
A63: LDPE | B63: =#REF! -> #REF! | C63: 0 | D63: =B63*C63 -> #REF! | E63: FIFO
A64: LLDPE | B64: =#REF! -> #REF! | C64: =#REF! -> #REF! | D64: =B64*C64 -> #REF! | E64: FIFO
A65: MB | B65: =#REF! -> #REF! | C65: =#REF! -> #REF! | D65: =B65*C65 -> #REF! | E65: FIFO
A66: Yarn | B66: =(#REF!+#REF!+#REF!+#REF!+#REF!+#REF!)*0 -> #REF! | C66: =C37 -> #REF! | D66: =B66*C66 -> #REF! | E66: Pur Rate
A67: PP | B67: =#REF!+#REF! -> #REF! | C67: =#REF! -> #REF! | D67: =B67*C67 -> #REF! | E67: FIFO
A68: RP | B68: =#REF!*0 -> #REF! | C68: =C32 -> 0 | D68: =B68*C68 -> #REF! | E68: Wastage
A69: PP Laminated Fabrics | B69: =#REF!*0 -> #REF! | C69: =C48 -> #REF! | D69: =B69*C69 -> #REF! | E69: Pur Rate
A70: PP WOVEN FABRIC | B70: =#REF!*0 -> #REF! | C70: =C48 -> #REF! | D70: =B70*C70 -> #REF! | E70: Pur Rate
A71: Webbing | B71: =#REF!*0 -> #REF! | C71: 0 | D71: =B71*C71 -> #REF! | E71: Pur Rate
A72: Tape | B72: =#REF!*0 -> #REF! | C72: =C56 -> #REF! | D72: 0 | E72: Pur Rate
A73: Wastage | B73: 0 | C73: 0 | D73: =B73*C73 -> 0 | G73: =SUM(B62:B73)-#REF!-#REF! -> #REF!
B74: =B154 -> #REF! | C74: =D74/B74 -> #REF! | D74: =D154 -> #REF!
A75: TOTAL RMC | B75: =SUM(B34:B74) -> #REF! | C75: =D75/B75 -> #REF! | D75: =SUM(D34:D74) -> #REF! | E75: =B75-B20 -> #REF!
B76: =B75-B20+B121 -> #REF!
A77: Value Addition on Sales | B77: =B20 -> 493775.7 | C77: =C20-C75 -> #REF! | D77: =B77*C77 -> #REF! | E77: =D77+E93 -> #REF! | F77: =#REF!-#REF! -> #REF! | G77: =+E77-F77 -> #REF! | H77: =D20-D75 -> #REF! | I77: =#REF!-#REF!-#REF! -> #REF! | J77: =H77-I77 -> #REF! | K77: =J77/B76 -> #REF!
A79: Power | D79: =#REF! -> #REF! | E79: =D79 -> #REF! | F79: =#REF! -> #REF! | G79: =+E79-F79 -> #REF! | H79: =D79 -> #REF! | I79: =#REF! -> #REF! | J79: =H79-I79 -> #REF!
A80: Salary | D80: =#REF! -> #REF! | E80: =D80 -> #REF! | F80: =#REF! -> #REF! | G80: =+E80-F80 -> #REF! | H80: =D80 -> #REF! | I80: =#REF! -> #REF! | J80: =H80-I80 -> #REF!
A81: Consumables and Stores | D81: =#REF!+#REF! -> #REF! | E81: =D81 -> #REF! | F81: =#REF!+#REF! -> #REF! | G81: =+E81-F81 -> #REF! | H81: =D81 -> #REF! | I81: =#REF!+#REF! -> #REF! | J81: =H81-I81 -> #REF!
A82: Job Charges | D82: =#REF! -> #REF! | E82: =D82 -> #REF! | F82: =#REF! -> #REF! | G82: =+E82-F82 -> #REF! | H82: =D82 -> #REF! | I82: =#REF! -> #REF! | J82: =H82-I82 -> #REF!
A83: Other | D83: =SUM(#REF!)-#REF! -> #REF! | E83: =D83 -> #REF! | F83: =#REF!-#REF! -> #REF! | G83: =+E83-F83 -> #REF! | H83: =D83 -> #REF! | I83: =#REF!-#REF! -> #REF! | J83: =H83-I83 -> #REF!
A85: Total Expenses | D85: =SUM(D79:D84) -> #REF! | E85: =SUM(E79:E84) -> #REF! | F85: =SUM(F79:F84) -> #REF! | G85: =SUM(G79:G84) -> #REF! | H85: =SUM(H79:H84) -> #REF! | I85: =SUM(I79:I84) -> #REF!
A87: Net Value Addition | D87: =D77-D85 -> #REF! | E87: =E77-E85 -> #REF! | F87: =F77-F85 -> #REF! | G87: =G77-G85 -> #REF! | H87: =H77-H85 -> #REF! | I87: =I77-I85 -> #REF!
A89: MEIS Benefit | D89: =#REF! -> #REF! | E89: =D89 -> #REF! | F89: =#REF! -> #REF! | G89: =+E89-F89 -> #REF! | H89: =D89 -> #REF! | I89: =#REF! -> #REF! | J89: =H89-I89 -> #REF!
A90: Import Duty on Excess Material | D90: =C129*0 -> #REF! | E90: =D90 -> #REF! | F90: 0 | G90: =+E90-F90 -> #REF! | H90: =D90 -> #REF! | I90: 0 | J90: =H90-I90 -> #REF!
A91: Income from Windmill | D91: =#REF! -> #REF! | E91: =D91 -> #REF! | G91: =+E91-F91 -> #REF! | H91: =D91 -> #REF! | I91: 0 | J91: =H91-I91 -> #REF!
A92: Exchange Rate Benefit | D92: =-#REF! -> #REF! | E92: =D92 -> #REF! | F92: =-#REF! -> #REF! | G92: =+E92-F92 -> #REF! | H92: =D92 -> #REF! | I92: =-#REF! -> #REF! | J92: =H92-I92 -> #REF!
A93: Stock Impact | D93: =-D120 -> #REF! | E93: =D93 -> #REF! | I93: =-SUM(#REF!) -> #REF! | J93: =H93-I93 -> #REF!
A95: Other Income | D95: =SUM(D89:D94) -> #REF! | E95: =SUM(E89:E94) -> #REF! | F95: =SUM(F89:F94) -> #REF! | G95: =SUM(G89:G94) -> #REF! | H95: =SUM(H89:H94) -> #REF! | I95: =SUM(I89:I94) -> #REF!
A97: Net EBIDTA | D97: =D87+D95 -> #REF! | E97: =E87+E95 -> #REF! | F97: =F87+F95 -> #REF! | G97: =G87+G95 -> #REF! | H97: =H87+H95 -> #REF! | I97: =I87+I95 -> #REF!
A100: Op. Stock | B100: =#REF!+#REF! -> #REF!
A101: Cl. Stock | B101: =#REF!+#REF! -> #REF!
B102: =B101-B100 -> #REF!
A107: Op. Stock | B107: =B100 -> #REF!
A108: Pur | B108: =#REF! -> #REF!
A109: Sale | B109: =-#REF! -> #REF!
A110: Cl. Stock | B110: =-B101 -> #REF!
B112: =SUM(B107:B111) -> #REF!
A117: Cl. Stock | B117: =-#REF!-#REF!-#REF! -> #REF! | C117: =-D117/B117 -> #REF! | D117: =#REF!+#REF!+#REF! -> #REF!
A118: OP. Stock | B118: =#REF!+#REF!+#REF! -> #REF! | C118: =D118/B118 -> #REF! | D118: =#REF!+#REF!+#REF! -> #REF!
A119: Diff | B119: =SUM(B117:B118) -> #REF! | C119: =SUM(C117:C118) -> #REF! | D119: =B119*C119 -> #REF!
A120: Stock Impact | D120: =B118*C119 -> #REF!
B121: =SUM(B117:B118) -> #REF! | C121: =D121/B121 -> #REF! | D121: =SUM(D117:D118) -> #REF!
A126: Export Sale | B126: =#REF! -> #REF!
A127: Eligible Import | B127: =B126*1.1 -> #REF!
A128: Less: Actual Import | B128: 908000
B129: =+B127-B128 -> #REF! | C129: =B129*6.33 -> #REF!
A141: PP | B141: =D168-109446 -> #REF! | C141: =C26 -> #REF! | D141: =+B141*C141 -> #REF! | F141: =B141+B26+B67 -> #REF! | G141: =B168 -> #REF! | H141: =+G141-F141 -> #REF!
A142: PP | B142: =D169-3005.09 -> #REF! | C142: =C40 -> #REF! | D142: =+B142*C142 -> #REF! | F142: =+B40+B142 -> #REF! | G142: =B169 -> #REF! | H142: =+G142-F142 -> #REF!
A143: Filler | B143: =D170-3675.15 -> #REF! | C143: =C27 -> #REF! | D143: =+B143*C143 -> #REF! | F143: =+B27+B143 -> #REF! | G143: =B170 -> #REF! | H143: =+G143-F143 -> #REF!
...

Sheet ERP STOCK
A3: Item Name | B3: Opening Balance | C3: Inward | F3: Outward | I3: Closing Balance | J3: Qty At Job Worker | K3: Rate | L3: Value
C4: Purchase | D4: Production | E4: Received Job IN | F4: Sale | G4: Issue / Consumption | H4: Sent To Job OUT
A5: 29-02-2020
A6: SF
A7: R.P. GRANULES | B7: 36409.13 | C7: 11390 | D7: 173100 | E7: 28116.2 | F7: 49171.2 | G7: 174000 | H7: 0 | I7: 25844.13 | J7: 40500 | K7: 50 | L7: 1292206.5
A8: PP/HD TAPE | B8: 182370.98 | C8: 5495.1 | D8: 690008.29 | E8: 8597.3 | F8: 10.6 | G8: 705935.42 | H8: 0 | I8: 180525.65 | J8: 89833.87 | K8: 9 | L8: 1624730.8
A9: UL FABRIC | B9: 5623632.4 | C9: 73519 | D9: 578465 | E9: 176380.3 | F9: 213703.5 | G9: 428251.45 | H9: 128775.9 | I9: 5681265.8 | J9: 519703.9 | K9: 16 | L9: 90900253
A10: LAMINETED FABRIC | B10: 771450.44 | C10: 3003.4 | D10: 275216.2 | E10: 68732.7 | F10: 115312.1 | G10: 245377.7 | H10: 14916.3 | I10: 742796.64 | J10: 274076.48 | K10: 21 | L10: 15598729
A11: WEBBING | B11: 682335.87 | C11: 2804.7 | D11: 114635.1 | E11: 4950.5 | F11: 27043.2 | G11: 88553.3 | H11: 3777.4 | I11: 685352.27 | J11: 146015.04 | K11: 16 | L11: 10965636
A12: TAPE WASTE | B12: -151002.69 | C12: 0 | D12: 42534 | E12: 0 | F12: 0 | G12: 179189 | H12: 0 | I12: -287657.69 | J12: 0 | K12: 15 | L12: -4314865.3
A13: FABRIC WASTE | B13: -38316.75 | C13: 38647.85 | D13: 71320.42 | E13: 64792.2 | F13: 18635 | G13: 179189 | H13: 0 | I13: -61380.28 | J13: 132065 | K13: 15 | L13: -920704.2
A14: PP MF YARN | B14: 44360.71 | C14: 35352.2 | D14: 0 | E14: 2433.24 | F14: 176.4 | G14: 33533.3 | H14: 6496.6 | I14: 41939.85 | J14: 155020.37 | K14: 125.32 | L14: 5255956.6
A15: Crimp Yarn (Texurise Yarn) | B15: -12123.14 | C15: 0 | D15: 0 | E15: 0 | F15: 2013.74 | G15: 0 | H15: 0 | I15: -14136.88 | J15: 13651.03 | K15: 111.34 | L15: -1574046.1
A16: LLDPE Liner Bags | B16: 28833.32 | C16: 19858.6 | D16: 0 | E16: 0 | F16: 0 | G16: 26234 | H16: 20708.6 | I16: 1749.32 | J16: 172321.68 | K16: 129.53 | L16: 226584.16
A17: LLDPE Film | B17: 26898.11 | C17: 1315.84 | D17: 0 | E17: 0 | F17: 0 | G17: 1307.89 | H17: 1111.09 | I17: 25794.97 | J17: 1999.09 | K17: 116.36 | L17: 3001532.1
A18: PP FABRILATED YARN(TAPE) | B18: -10553.18 | C18: 5834.3 | D18: 1723.26 | E18: 2164.8 | F18: 0 | G18: 14882 | H18: 0 | I18: -15712.82 | J18: 21942.25 | K18: 104.19 | L18: -1637171.1
... A22: Filler Cord | B22: 17502.87 | C22: 8104.91 | D22: 1955.6 | E22: 0 | F22: 0 | G22: 9192 | H22: 0 | I22: 18371.38 | J22: 746.1 | K22: 12 | L22: 220456.56
A23: Total | B23: 7220762.4 | C23: 227944.8 | D23: 1948957.9 | E23: 356217.24 | F23: 432843.74 | G23: 2103569.3 | H23: 175785.89 | I23: 7041683.4 | J23: 1568583.8 | L23: 1.2758422e+08
A25: FG
A26: PP/ HDPE BAGS | B26: 2758.6 | C26: 0 | D26: 17602 | E26: 0 | F26: 22274 | G26: 0 | H26: 0 | I26: -1913.4 | J26: 0 | K26: 85.68 | L26: -163933.41
A27: PP BAGS | B27: 8807.4 | C27: 1253.9 | D27: 0 | E27: 0 | F27: 0 | G27: 0 | H27: 0 | I27: 10061.3 | J27: 0 | K27: 0 | L27: 0
A28: PP WOVEN BIG BAGS | B28: 267536.18 | C28: 18506 | D28: 481097 | E28: 175106.5 | F28: 520652.9 | G28: 0 | H28: 0 | I28: 421592.78 | J28: 815 | K28: 158.33 | L28: 66749398
A29: Total | B29: 279102.18 | C29: 19759.9 | D29: 498699 | E29: 175106.5 | F29: 542926.9 | G29: 0 | H29: 0 | I29: 429740.68 | J29: 815 | L29: 66585464
A31: CN
A32: All Ink | B32: 12133 | C32: 270 | D32: 0 | E32: 0 | F32: 0 | G32: 530 | H32: 0 | I32: 11873 | J32: 340 | K32: 202.41 | L32: 2403269.9
A33: Thinner | B33: 10403.3 | C33: 2210 | D33: 0 | E33: 0 | F33: 0 | G33: 1680 | H33: 0 | I33: 10933.3 | J33: 510 | K33: 75.83 | L33: 829064.14
A34: Total | B34: 22536.3 | C34: 2480 | D34: 0 | E34: 0 | F34: 0 | G34: 2210 | H34: 0 | I34: 22806.3 | J34: 850 | L34: 3232334
A36: RM
A37: PP | B37: 136400.33 | C37: 963286 | D37: 0 | E37: 13500 | F37: 213775 | G37: 483033.14 | H37: 306195 | I37: 110183.19 | J37: 3560688.4 | K37: 72.83 | L37: 8024422.6
A38: LDPE | B38: 31719.681 | C38: 8100 | D38: 0 | E38: 0 | F38: 0 | G38: 10859.25 | H38: 2550 | I38: 26410.431 | J38: 23206.99 | K38: 101.34 | L38: 2676324.4
A39: LLDPE | B39: 14658.539 | C39: 23000 | D39: 0 | E39: 0 | F39: 2600 | G39: 17509.25 | H39: 350 | I39: 17199.289 | J39: 75037.28 | K39: 89.66 | L39: 1542131.2
A40: HDPE | B40: 1093.32 | C40: 0 | D40: 0 | E40: 0 | F40: 0 | G40: 158.75 | H40: 0 | I40: 934.57 | J40: 5030 | K40: 92.85 | L40: 86774.82
A41: FILLER | B41: 55988.7 | C41: 64175 | D41: 0 | E41: 0 | F41: 14425 | G41: 51317.2 | H41: 5530 | I41: 48891.5 | J41: 83289.34 | K41: 31.19 | L41: 1524747.1
A42: OTHER | B42: 3770.46 | C42: 277.32 | D42: 0 | E42: 0 | F42: 0 | G42: 0 | H42: 0 | I42: 4047.78 | J42: 0 | K42: 0 | L42: 0
A43: Total | B43: 243631.03 | C43: 1058838.3 | D43: 0 | E43: 13500 | F43: 230800 | G43: 562877.59 | H43: 314625 | I43: 207666.76 | J43: 3747252 | L43: 13854400

Sheet Sheet3
D1: 20
A2: SN | B2: Particulars | C2: Budget | E2: Actual
C3: Jan-20 | D3: Upto Date | E3: Upto Date | F3: Kg (in Ton) | G3: Rate per Kg
A4: A | B4: Quantitative Details - MT
A5: 1 | B5: Capacity | C5: 900 | D5: =C5/31*$D$1 -> 580.64516 | E5: =D5 -> 580.64516 | I5: Item Name | J5: Quantity | K5: Rate | L5: Amount | O5: Values
A6: =A5+1 -> 2 | B6: Production | C6: 800 | D6: =C6/31*$D$1 -> 516.12903 | E6: =#REF!/1000 -> #REF! | N6: Item Name | O6: Sum of Quantity | P6: Sum of Amount
A7: =A6+1 -> 3 | B7: Utilization (%) | C7: =C6/C5 -> 0.88888889 | D7: =D6/D5 -> 0.88888889 | E7: =E6/E5 -> #REF! | I7: PP WOVEN BIG BAGS / SACKS | J7: =+GETPIVOTDATA("Sum of Quantity",$N$5,"Item Name","PP WOVEN BIG BAGS / SACKS")+GETPIVOTDATA("Sum of Quantity",$N$5,"Item Name","Pp Woven Bgas(FG)") -> 306664.9 | K7: =L7/J7 -> 157.96893 | L7: =+GETPIVOTDATA("Sum of Amount",$N$5,"Item Name","PP WOVEN BIG BAGS / SACKS")+GETPIVOTDATA("Sum of Amount",$N$5,"Item Name","Pp Woven Bgas(FG)") -> 48443526 | N7: PP WOVEN BIG BAGS / SACKS | O7: 300706.8 | P7: 47512219
A8: =A7+1 -> 4 | B8: Opening Stock | C8: 0 | D8: 0 | E8: =(#REF!+#REF!)/1000 -> #REF! | I8: PP Woven Fabrics(FG) | J8: =GETPIVOTDATA("Sum of Quantity",$N$5,"Item Name","PP Woven Fabrics(FG)") -> 85056.5 | K8: =L8/J8 -> 105.13316 | L8: =GETPIVOTDATA("Sum of Amount",$N$5,"Item Name","PP Woven Fabrics(FG)") -> 8942258.9 | N8: PP Woven Fabrics(FG) | O8: 85056.5 | P8: 8942258.9
A9: =A8+1 -> 5 | B9: Sales | C9: =C6 -> 800 | D9: =C9/31*$D$1 -> 516.12903 | E9: =#REF!/1000 -> #REF! | I9: PP Laminated Fabric | J9: =GETPIVOTDATA("Sum of Quantity",$N$5,"Item Name","PP Laminated Fabric") -> 40640.5 | K9: =L9/J9 -> 103.30194 | L9: =GETPIVOTDATA("Sum of Amount",$N$5,"Item Name","PP Laminated Fabric") -> 4198242.7 | N9: REPROCESS GRANULES (FG) | O9: 14100 | P9: 282000
A10: =A9+1 -> 6 | B10: Closing Stock | C10: 0 | D10: 0 | E10: =(#REF!+#REF!)/1000 -> #REF! | I10: REPROCESS GRANULES (FG) | J10: =GETPIVOTDATA("Sum of Quantity",$N$5,"Item Name","REPROCESS GRANULES (FG)") -> 14100 | K10: =L10/J10 -> 20 | L10: =GETPIVOTDATA("Sum of Amount",$N$5,"Item Name","REPROCESS GRANULES (FG)") -> 282000 | N10: PP Laminated Fabric | O10: 40640.5 | P10: 4198242.7
A11: B | B11: Revenue | I11: PP TAPE / YARN | J11: 0 | K11: =L11/J11 -> #DIV/0! | L11: 0 | N11: PP WEBBING (FG) | O11: 12228.8 | P11: 1263198
A12: 1 | B12: Sales | C12: 1117.55 | D12: =C12/31*$D$1 -> 721 | E12: =Sheet2!B3/100000 -> #REF! | F12: =$J$22/1000 -> 493.7757 | G12: =+E12/F12*100 -> #REF! | I12: PP Fabric Wastage | K12: =L12/J12 -> #DIV/0! | N12: Pp Wastage | O12: 7960 | P12: 119400
A13: 2 | B13: Increase / Decrease in Stock | C13: 0 | D13: =C13/31*$D$1 -> 0 | I13: PP Tape Wastage | J13: =GETPIVOTDATA("Sum of Quantity",$N$5,"Item Name","Pp Wastage") -> 7960 | K13: =L13/J13 -> 15 | L13: =GETPIVOTDATA("Sum of Amount",$N$5,"Item Name","Pp Wastage") -> 119400 | N13: Pp Granuales | O13: 18000 | P13: 1365550
A14: 3 | B14: Other Income | C14: 0 | D14: =C14/31*$D$1 -> 0 | E14: =(Sheet2!B15+Sheet2!B27)/100000 -> #REF! | F14: =F12 -> 493.7757 | G14: =+E14/F14*100 -> #REF! | I14: PP WEBBING (FG) | J14: =GETPIVOTDATA("Sum of Quantity",$N$5,"Item Name","PP WEBBING (FG)") -> 12228.8 | K14: =L14/J14 -> 103.29697 | L14: =GETPIVOTDATA("Sum of Amount",$N$5,"Item Name","PP WEBBING (FG)") -> 1263198 | N14: Filler | O14: 8500 | P14: 250750
B15: Total | C15: =SUM(C12:C14) -> 1117.55 | D15: =SUM(D12:D14) -> 721 | E15: =SUM(E12:E14) -> #REF! | G15: =SUM(G12:G14) -> #REF! | I15: Filler | J15: =GETPIVOTDATA("Sum of Quantity",$N$5,"Item Name","Filler") -> 8500 | K15: =L15/J15 -> 29.5 | L15: =GETPIVOTDATA("Sum of Amount",$N$5,"Item Name","Filler") -> 250750 | N15: Master Batch | O15: 500 | P15: 70500
A16: C | B16: Eexpenses | I16: Master Batch | J16: =GETPIVOTDATA("Sum of Quantity",$N$5,"Item Name","Master Batch") -> 500 | K16: =L16/J16 -> 141 | L16: =GETPIVOTDATA("Sum of Amount",$N$5,"Item Name","Master Batch") -> 70500 | N16: LLDPE GRANULES | O16: 125 | P16: 8531
A17: 1 | B17: Raw Material | C17: 540.75 | D17: =C17/31*$D$1 -> 348.87097 | E17: =#REF!/100000 -> #REF! | F17: =#REF!/1000 -> #REF! | G17: =+E17/F17*100 -> #REF! | I17: LLDPE GRANULES | J17: =GETPIVOTDATA("Sum of Quantity",$N$5,"Item Name","LLDPE GRANULES") -> 125 | K17: =L17/J17 -> 68.248 | L17: =GETPIVOTDATA("Sum of Amount",$N$5,"Item Name","LLDPE GRANULES") -> 8531 | N17: Pp Woven Bgas(FG) | O17: 5958.1 | P17: 931307
A18: =A17+1 -> 2 | B18: Power | C18: 61.285 | D18: =C18/31*$D$1 -> 39.53871 | E18: =Sheet2!B44/100000 -> #REF! | F18: =F12 -> 493.7757 | G18: =+E18/F18*100 -> #REF! | I18: Pp Granuales | J18: =GETPIVOTDATA("Sum of Quantity",$N$5,"Item Name","Pp Granuales") -> 18000 | K18: =L18/J18 -> 75.863889 | L18: =GETPIVOTDATA("Sum of Amount",$N$5,"Item Name","Pp Granuales") -> 1365550 | N18: Grand Total | O18: 493775.7 | P18: 64943957
A19: =A18+1 -> 3 | B19: Labour | C19: 158.62 | D19: =C19/31*$D$1 -> 102.33548 | E19: =Sheet2!B42/100000 -> #REF! | F19: =F18 -> 493.7757 | G19: =+E19/F19*100 -> #REF! | I19: LLDPE BAGS (LINER) | K19: =L19/J19 -> #DIV/0!
A20: =A19+1 -> 4 | B20: RP | C20: 14.42 | D20: =C20/31*$D$1 -> 9.3032258 | E20: 0 | F20: =F19 -> 493.7757 | G20: =+E20/F20*100 -> 0 | I20: LDPE GRANULES | K20: =L20/J20 -> #DIV/0!
A21: =A20+1 -> 5 | B21: Stores | C21: 14.42 | D21: =C21/31*$D$1 -> 9.3032258 | E21: =Sheet2!B34/100000 -> #REF! | F21: =F20 -> 493.7757 | G21: =+E21/F21*100 -> #REF!
A22: =A21+1 -> 6 | B22: Consumables | C22: 10.815 | D22: =C22/31*$D$1 -> 6.9774194 | E22: 0 | F22: =F21 -> 493.7757 | G22: =+E22/F22*100 -> 0 | I22: TOTAL | J22: =SUM(J6:J21) -> 493775.7 | K22: =L22/J22 -> 131.52522 | L22: =SUM(L6:L21) -> 64943957
A23: 7 | B23: Jobwork | C23: 0 | D23: 0 | E23: =Sheet2!B45/100000 -> #REF! | F23: =F22 -> 493.7757 | G23: =+E23/F23*100 -> #REF! | J23: =J22-GETPIVOTDATA("Sum of Quantity",$N$5) -> 0 | L23: =L22-GETPIVOTDATA("Sum of Amount",$N$5) -> 0
A24: 8 | B24: Other Expenses | C24: 0 | D24: 0 | E24: =(Sheet2!B46+Sheet2!B54+Sheet2!B61)/100000 -> #REF! | F24: =#REF!/1000 -> #REF! | G24: =+E24/F24*100 -> #REF! | J24: =+J8+J9 -> 125697 | K24: =+L24/J24 -> 104.54109 | L24: =+L8+L9 -> 13140502
B25: Total | C25: =SUM(C17:C24) -> 800.31 | D25: =SUM(D17:D24) -> 516.32903 | E25: =SUM(E17:E24) -> #REF! | G25: =SUM(G17:G24) -> #REF!
A26: D | B26: EBIDTA | C26: =C15-C25 -> 317.24 | D26: =D15-D25 -> 204.67097 | E26: =E15-E25 -> #REF! | G26: =G15-G25 -> #REF!
B27: EBIDTA Margin - % | C27: =C26/C12 -> 0.28387097 | D27: =D26/D12 -> 0.28387097 | E27: =E26/E12 -> #REF! | G27: =G26/G12 -> #REF!
O28: =+GETPIVOTDATA("Sum of Quantity",$N$5)-J22 -> 0 | P28: =+GETPIVOTDATA("Sum of Amount",$N$5)-L22 -> 0
E29: =#REF!/100000 -> #REF! | P29: =GETPIVOTDATA("Sum of Amount",$N$5)/GETPIVOTDATA("Sum of Quantity",$N$5) -> 131.52522
E30: =+E26-E29 -> #REF!
O32: =+J22-GETPIVOTDATA("Sum of Quantity",$N$5) -> 0 | P32: =+L22-GETPIVOTDATA("Sum of Amount",$N$5) -> 0
C35: RM | D35: JW | E35: WIP&FG
B36: OP. Stock | C36: =#REF!/1000 -> #REF! | D36: =(#REF!++#REF!)/1000 -> #REF! | E36: =#REF!/1000 -> #REF!
B37: Purchase | C37: =(#REF!+#REF!)/1000 -> #REF! | D37: =(#REF!+#REF!)/1000 -> #REF!
D38: =(#REF!+#REF!)/1000 -> #REF!
B39: Closing Stock | C39: =#REF!/1000 -> #REF! | D39: =(#REF!+#REF!)/1000 -> #REF! | E39: =#REF!/1000 -> #REF!
E41: =+E39-E36 -> #REF!
E42: =+E41*165 -> #REF!

Sheet Sheet2
A1: Particulars | B1: Amount Rs. | D1: Jul | E1: Aug
A3: Sale of finished goods | B3: =#REF! -> #REF!
A4: Sale of traded goods | B4: 0
A5: Total Revenue from operations | B5: =SUM(B3:B4) -> #REF! | D5: 115693026 | E5: 150815314
A6: Sale of services
A7: Income from Jobwork charges | B7: 0
A8: Total Sales of services | B8: =SUM(B7) -> 0
A9: Other operating revenue
A10: Export incentives | B10: =#REF! -> #REF! | D10: 1429262 | E10: 2578757
A11: Stores sales | B11: =-#REF! -> #REF!
A12: Advance License Receivable | B12: =#REF! -> #REF!
A13: Commission income | B13: 0
A14: Scrap sales | B14: 0
A15: Total Other operating revenue | B15: =SUM(B10:B14) -> #REF! | D15: =SUM(D10:D14) -> 1429262 | E15: =SUM(E10:E14) -> 2578757
A16: Other income
A17: Wind mill income | B17: =#REF! -> #REF! | D17: 258868 | E17: 289012
A18: Interest income: | B18: 0
A19: - on fixed deposits with Banks | B19: 0
A20: - from others | B20: 0
A21: Rent Income
A22: Advance License Utilization | B22: 0
A23: Profit on sale of fixed assets | B23: 0
A24: Profit on sale of investments | B24: 0
A25: Sundry balance written off
A26: Miscellaneous income | B26: 0 | D26: 0 | E26: 0
A27: Total Other income | B27: =SUM(B17:B26) -> #REF! | D27: =SUM(E17:E26) -> 289012 | E27: =SUM(D17:D26) -> 258868
A28: Total Turnover | B28: =B5+B8+B15+B27 -> #REF! | D28: =D5+D8+D15+E27 -> 117381156 | E28: =E5+E8+E15+D27 -> 153683083
B29: 0
A30: Cost of Goods
A31: Cost of materials consumed | B31: =SUM(#REF!)+C31 -> #REF! | C31: =SUMIF(#REF!,"Add: Purchase expenses",#REF!) -> #REF! | D31: 71292822 | E31: 111910571
A32: Purchase of stock-in-trade | B32: 0
A33: Changes in inventory of finished goods and work-in-progress | B33: =SUM(#REF!) -> #REF! | D33: -3450754 | E33: -5251988
A34: Stores, Spares & Consumables | B34: =#REF! -> #REF! | D34: 1844344 | E34: 743991
A35: Total Cost of goods | B35: =SUM(B31:B34) -> #REF! | D35: =SUM(D31:D34) -> 69686412 | E35: =SUM(E31:E34) -> 107402574
A36: Employee benefit expenses
A37: Salaries, wages and bonus | B37: =SUMIF(#REF!,A37,#REF!)+#REF! -> #REF! | D37: 13443755 | E37: 13987529
A38: Contribution to provident and other funds
A39: Gratuity Expenses
A40: Staff welfare expenses | B40: =SUMIF(#REF!,A40,#REF!) -> #REF!
A41: Labour charges
A42: Total Employee benefit expenses | B42: =SUM(B37:B41) -> #REF! | D42: =SUM(D37:D41) -> 13443755 | E42: =SUM(E37:E41) -> 13987529
A43: Manufacturing Expenses
A44: Power and fuel | B44: =#REF! -> #REF! | D44: 4727953 | E44: 5745647
A45: Jobwork charges | B45: =#REF! -> #REF! | D45: 16638975 | E45: 14963019
A46: Other Manufacturing Expenses | B46: =SUMIF(#REF!,A46,#REF!) -> #REF! | D46: 315701 | E46: 286873
A47: Total Manufacturing Expenses | B47: =SUM(B44:B46) -> #REF! | D47: =SUM(D44:D46) -> 21682629 | E47: =SUM(E44:E46) -> 20995539
A48: Selling and Distribution Expenses
A49: Advertising and sales promotion expense | B49: =SUMIF(#REF!,A49,#REF!) -> #REF!
A50: Travelling expense | B50: =SUMIF(#REF!,A50,#REF!) -> #REF!
A51: Brokerage & commission | B51: =SUMIF(#REF!,A51,#REF!) -> #REF! | D51: 206883 | E51: 325633
A52: Conveyance, vehicle running and traveling expenses | B52: =SUMIF(#REF!,A52,#REF!) -> #REF! | D52: 45214 | E52: 39522
A53: Freight Outward and C & F Charges | B53: =SUMIF(#REF!,A53,#REF!) -> #REF! | D53: 1097780 | E53: 1381255
A54: Total Selling and Distribution Expenses | B54: =SUM(B49:B53) -> #REF! | D54: =SUM(D49:D53) -> 1349877 | E54: =SUM(E49:E53) -> 1746410
A55: Administrative Expenses
A56: Insurance | B56: =SUMIF(#REF!,A56,#REF!) -> #REF!
A57: Miscellaneous Expense | B57: =SUMIF(#REF!,A57,#REF!) -> #REF!
A58: Other Administrative Expenses | B58: =SUMIF(#REF!,A58,#REF!) -> #REF! | D58: 2023815 | E58: 459349
A59: Common Expenses | B59: =#REF! -> #REF! | D59: 500000 | E59: 500000
A60: HO Expenses | D60: 500000 | E60: 0
A61: Total Administrative Expenses | B61: =SUM(B56:B60) -> #REF! | D61: =SUM(D56:D60) -> 3023815 | E61: =SUM(E56:E60) -> 959349
A62: Total Cost of goods sold | B62: =B35+B42+B47+B54+B61 -> #REF! | D62: =D35+D42+D47+D54+D61 -> 109186488 | E62: =E35+E42+E47+E54+E61 -> 145091401
A63: EBDITA | B63: =B28-B62 -> #REF! | D63: =D28-D62 -> 8194668 | E63: =E28-E62 -> 8591682
A64: Depreciation
A65: Interest
A66: On Term Loan | B66: 0
A67: On Working Capital | B67: 0
A68: PBT | B68: =B63-B64-B66-B67 -> #REF!
B72: =#REF! -> #REF!
B73: =B68-B72 -> #REF!

Sheet Sheet1
B1: Tape | G1: Lamination | J1: Loom | M1: Yarn | P1: Webbing | S1: Webbing
B3: Unlaminated Fabric | D3: =IFERROR(VLOOKUP(B3,#REF!,15,0),0) -> 0 | G3: =IFERROR(VLOOKUP(B3,#REF!,3,0),0) -> 0 | H3: =G3*D3 -> 0
B4: Yarn | D4: =IFERROR(VLOOKUP(B4,#REF!,15,0),0) -> 0 | P4: =IFERROR(VLOOKUP(B4,#REF!,7,0),0) -> 0 | Q4: =P4*D4 -> 0 | S4: =IFERROR(VLOOKUP(B4,#REF!,10,0),0) -> 0 | T4: =S4*D4 -> 0
B5: Laminated Fabric | D5: =IFERROR(VLOOKUP(B5,#REF!,15,0),0) -> 0
B6: Webbing | D6: =IFERROR(VLOOKUP(B6,#REF!,15,0),0) -> 0
B7: Tape | D7: =IFERROR(VLOOKUP(B7,#REF!,15,0),0) -> 0 | J7: =IFERROR(VLOOKUP(B7,#REF!,4,0),0) -> 0 | K7: =J7*D7 -> 0 | P7: =IFERROR(VLOOKUP(B7,#REF!,7,0),0) -> 0 | Q7: =P7*D7 -> 0 | S7: =IFERROR(VLOOKUP(B7,#REF!,10,0),0) -> 0 | T7: =S7*D7 -> 0
D8: =IFERROR(VLOOKUP(B8,#REF!,15,0),0) -> 0
A9: =C9/$C$27 -> #REF! | B9: PP 30SG | C9: =IFERROR(VLOOKUP(B9,#REF!,2,0),0) -> 0 | D9: =IFERROR(VLOOKUP(B9,#REF!,15,0),0) -> 0 | E9: =C9*D9 -> 0 | G9: =IFERROR(VLOOKUP(B9,#REF!,3,0),0) -> 0 | H9: =G9*D9 -> 0 | J9: =IFERROR(VLOOKUP(B9,#REF!,4,0),0) -> 0 | K9: =J9*D9 -> 0 | M9: =IFERROR(VLOOKUP(B9,#REF!,6,0),0) -> 0 | N9: =M9*D9 -> 0 | P9: =IFERROR(VLOOKUP(B9,#REF!,7,0),0) -> 0 | Q9: =P9*D9 -> 0 | S9: =IFERROR(VLOOKUP(B9,#REF!,10,0),0) -> 0 | T9: =S9*D9 -> 0
A10: =C10/$C$27 -> #REF! | B10: PP 462 | C10: =IFERROR(VLOOKUP(B10,#REF!,2,0),0) -> 0 | D10: =IFERROR(VLOOKUP(B10,#REF!,15,0),0) -> 0 | E10: =C10*D10 -> 0 | G10: =IFERROR(VLOOKUP(B10,#REF!,3,0),0) -> 0 | H10: =G10*D10 -> 0 | J10: =IFERROR(VLOOKUP(B10,#REF!,4,0),0) -> 0 | K10: =J10*D10 -> 0 | M10: =IFERROR(VLOOKUP(B10,#REF!,6,0),0) -> 0 | N10: =M10*D10 -> 0 | P10: =IFERROR(VLOOKUP(B10,#REF!,7,0),0) -> 0 | Q10: =P10*D10 -> 0 | S10: =IFERROR(VLOOKUP(B10,#REF!,10,0),0) -> 0 | T10: =S10*D10 -> 0
A11: =C11/$C$27 -> #REF! | B11: Filer Soltex | C11: =IFERROR(VLOOKUP(B11,#REF!,2,0),0) -> 0 | D11: =IFERROR(VLOOKUP(B11,#REF!,15,0),0) -> 0 | E11: =C11*D11 -> 0 | G11: =IFERROR(VLOOKUP(B11,#REF!,3,0),0) -> 0 | H11: =G11*D11 -> 0 | J11: =IFERROR(VLOOKUP(B11,#REF!,4,0),0) -> 0 | K11: =J11*D11 -> 0 | M11: =IFERROR(VLOOKUP(B11,#REF!,6,0),0) -> 0 | N11: =M11*D11 -> 0 | P11: =IFERROR(VLOOKUP(B11,#REF!,7,0),0) -> 0 | Q11: =P11*D11 -> 0 | S11: =IFERROR(VLOOKUP(B11,#REF!,10,0),0) -> 0 | T11: =S11*D11 -> 0
A12: =C12/$C$27 -> #REF! | B12: UV | C12: =IFERROR(VLOOKUP(B12,#REF!,2,0),0) -> 0 | D12: =IFERROR(VLOOKUP(B12,#REF!,15,0),0) -> 0 | E12: =C12*D12 -> 0 | G12: =IFERROR(VLOOKUP(B12,#REF!,3,0),0) -> 0 | H12: =G12*D12 -> 0 | J12: =IFERROR(VLOOKUP(B12,#REF!,4,0),0) -> 0 | K12: =J12*D12 -> 0 | M12: =IFERROR(VLOOKUP(B12,#REF!,6,0),0) -> 0 | N12: =M12*D12 -> 0 | P12: =IFERROR(VLOOKUP(B12,#REF!,7,0),0) -> 0 | Q12: =P12*D12 -> 0 | S12: =IFERROR(VLOOKUP(B12,#REF!,10,0),0) -> 0 | T12: =S12*D12 -> 0
A13: =C13/$C$27 -> #REF! | B13: MB | C13: =IFERROR(VLOOKUP(B13,#REF!,2,0),0) -> 0 | D13: =IFERROR(VLOOKUP(B13,#REF!,15,0),0) -> 0 | E13: =C13*D13 -> 0 | G13: =IFERROR(VLOOKUP(B13,#REF!,3,0),0) -> 0 | H13: =G13*D13 -> 0 | J13: =IFERROR(VLOOKUP(B13,#REF!,4,0),0) -> 0 | K13: =J13*D13 -> 0 | M13: =IFERROR(VLOOKUP(B13,#REF!,6,0),0) -> 0 | N13: =M13*D13 -> 0 | P13: =IFERROR(VLOOKUP(B13,#REF!,7,0),0) -> 0 | Q13: =P13*D13 -> 0 | S13: =IFERROR(VLOOKUP(B13,#REF!,10,0),0) -> 0 | T13: =S13*D13 -> 0
A14: =C14/$C$27 -> #REF! | B14: LD | C14: =IFERROR(VLOOKUP(B14,#REF!,2,0),0) -> 0 | D14: =IFERROR(VLOOKUP(B14,#REF!,15,0),0) -> 0 | E14: =C14*D14 -> 0 | G14: =IFERROR(VLOOKUP(B14,#REF!,3,0),0) -> 0 | H14: =G14*D14 -> 0 | J14: =IFERROR(VLOOKUP(B14,#REF!,4,0),0) -> 0 | K14: =J14*D14 -> 0 | M14: =IFERROR(VLOOKUP(B14,#REF!,6,0),0) -> 0 | N14: =M14*D14 -> 0 | P14: =IFERROR(VLOOKUP(B14,#REF!,7,0),0) -> 0 | Q14: =P14*D14 -> 0 | S14: =IFERROR(VLOOKUP(B14,#REF!,10,0),0) -> 0 | T14: =S14*D14 -> 0
A15: =C15/$C$27 -> #REF! | B15: LLDPE | C15: =IFERROR(VLOOKUP(B15,#REF!,2,0),0) -> 0 | D15: =IFERROR(VLOOKUP(B15,#REF!,15,0),0) -> 0 | E15: =C15*D15 -> 0 | G15: =IFERROR(VLOOKUP(B15,#REF!,3,0),0) -> 0 | H15: =G15*D15 -> 0 | J15: =IFERROR(VLOOKUP(B15,#REF!,4,0),0) -> 0 | K15: =J15*D15 -> 0 | M15: =IFERROR(VLOOKUP(B15,#REF!,6,0),0) -> 0 | N15: =M15*D15 -> 0 | P15: =IFERROR(VLOOKUP(B15,#REF!,7,0),0) -> 0 | Q15: =P15*D15 -> 0 | S15: =IFERROR(VLOOKUP(B15,#REF!,10,0),0) -> 0 | T15: =S15*D15 -> 0
A16: =C16/$C$27 -> #REF! | B16: HDPE | C16: =IFERROR(VLOOKUP(B16,#REF!,2,0),0) -> 0 | D16: =IFERROR(VLOOKUP(B16,#REF!,15,0),0) -> 0 | E16: =C16*D16 -> 0 | G16: =IFERROR(VLOOKUP(B16,#REF!,3,0),0) -> 0 | H16: =G16*D16 -> 0 | J16: =IFERROR(VLOOKUP(B16,#REF!,4,0),0) -> 0 | K16: =J16*D16 -> 0 | M16: =IFERROR(VLOOKUP(B16,#REF!,6,0),0) -> 0 | N16: =M16*D16 -> 0 | P16: =IFERROR(VLOOKUP(B16,#REF!,7,0),0) -> 0 | Q16: =P16*D16 -> 0 | S16: =IFERROR(VLOOKUP(B16,#REF!,10,0),0) -> 0 | T16: =S16*D16 -> 0
A17: =C17/$C$27 -> #REF! | B17: LLDPE FILM | C17: =IFERROR(VLOOKUP(B17,#REF!,2,0),0) -> 0 | D17: =IFERROR(VLOOKUP(B17,#REF!,15,0),0) -> 0 | E17: =C17*D17 -> 0 | G17: =IFERROR(VLOOKUP(B17,#REF!,3,0),0) -> 0 | H17: =G17*D17 -> 0 | J17: =IFERROR(VLOOKUP(B17,#REF!,4,0),0) -> 0 | K17: =J17*D17 -> 0 | M17: =IFERROR(VLOOKUP(B17,#REF!,6,0),0) -> 0 | N17: =M17*D17 -> 0 | P17: =IFERROR(VLOOKUP(B17,#REF!,7,0),0) -> 0 | Q17: =P17*D17 -> 0 | S17: =IFERROR(VLOOKUP(B17,#REF!,10,0),0) -> 0 | T17: =S17*D17 -> 0
A18: =C18/$C$27 -> #REF! | B18: Multiliyer Laminated Film | C18: =IFERROR(VLOOKUP(B18,#REF!,2,0),0) -> 0 | D18: =IFERROR(VLOOKUP(B18,#REF!,15,0),0) -> 0 | E18: =C18*D18 -> 0 | G18: =IFERROR(VLOOKUP(B18,#REF!,3,0),0) -> 0 | H18: =G18*D18 -> 0 | J18: =IFERROR(VLOOKUP(B18,#REF!,4,0),0) -> 0 | K18: =J18*D18 -> 0 | M18: =IFERROR(VLOOKUP(B18,#REF!,6,0),0) -> 0 | N18: =M18*D18 -> 0 | P18: =IFERROR(VLOOKUP(B18,#REF!,7,0),0) -> 0 | Q18: =P18*D18 -> 0 | S18: =IFERROR(VLOOKUP(B18,#REF!,10,0),0) -> 0 | T18: =S18*D18 -> 0
A19: =C19/$C$27 -> #REF! | B19: Filler cord | C19: =IFERROR(VLOOKUP(B19,#REF!,2,0),0) -> 0 | D19: =IFERROR(VLOOKUP(B19,#REF!,15,0),0) -> 0 | E19: =C19*D19 -> 0 | G19: =IFERROR(VLOOKUP(B19,#REF!,3,0),0) -> 0 | H19: =G19*D19 -> 0 | J19: =IFERROR(VLOOKUP(B19,#REF!,4,0),0) -> 0 | K19: =J19*D19 -> 0 | M19: =IFERROR(VLOOKUP(B19,#REF!,6,0),0) -> 0 | N19: =M19*D19 -> 0 | P19: =IFERROR(VLOOKUP(B19,#REF!,7,0),0) -> 0 | Q19: =P19*D19 -> 0 | S19: =IFERROR(VLOOKUP(B19,#REF!,10,0),0) -> 0 | T19: =S19*D19 -> 0
A20: =C20/$C$27 -> #REF! | B20: Rop | C20: =IFERROR(VLOOKUP(B20,#REF!,2,0),0) -> 0 | D20: =IFERROR(VLOOKUP(B20,#REF!,15,0),0) -> 0 | E20: =C20*D20 -> 0 | G20: =IFERROR(VLOOKUP(B20,#REF!,3,0),0) -> 0 | H20: =G20*D20 -> 0 | J20: =IFERROR(VLOOKUP(B20,#REF!,4,0),0) -> 0 | K20: =J20*D20 -> 0 | M20: =IFERROR(VLOOKUP(B20,#REF!,6,0),0) -> 0 | N20: =M20*D20 -> 0 | P20: =IFERROR(VLOOKUP(B20,#REF!,7,0),0) -> 0 | Q20: =P20*D20 -> 0 | S20: =IFERROR(VLOOKUP(B20,#REF!,10,0),0) -> 0 | T20: =S20*D20 -> 0
... A24: =C24/$C$27 -> #REF! | B24: RP | C24: =IFERROR(VLOOKUP(B24,#REF!,2,0),0) -> 0 | D24: =IFERROR(VLOOKUP(B24,#REF!,15,0),0) -> 0 | E24: =C24*D24 -> 0 | G24: =IFERROR(VLOOKUP(B24,#REF!,3,0),0) -> 0 | H24: =G24*D24 -> 0 | J24: =IFERROR(VLOOKUP(B24,#REF!,4,0),0) -> 0 | K24: =J24*D24 -> 0 | M24: =IFERROR(VLOOKUP(B24,#REF!,6,0),0) -> 0 | N24: =M24*D24 -> 0 | P24: =IFERROR(VLOOKUP(B24,#REF!,7,0),0) -> 0 | Q24: =P24*D24 -> 0 | S24: =IFERROR(VLOOKUP(B24,#REF!,10,0),0) -> 0 | T24: =S24*D24 -> 0
C25: =SUM(C3:C24) -> 0 | E25: =SUM(E3:E24) -> 0 | G25: =SUM(G3:G24) -> 0 | H25: =SUM(H3:H24) -> 0 | J25: =SUM(J3:J24) -> 0 | K25: =SUM(K3:K24) -> 0 | M25: =SUM(M3:M24) -> 0 | N25: =SUM(N3:N24) -> 0 | P25: =SUM(P3:P24) -> 0 | Q25: =SUM(Q3:Q24) -> 0 | S25: =SUM(S3:S24) -> 0 | T25: =SUM(T3:T24) -> 0
B26: Wastage | C26: =#REF! -> #REF! | G26: =#REF! -> #REF! | J26: =#REF! -> #REF! | M26: =#REF! -> #REF! | P26: =#REF! -> #REF! | S26: =#REF! -> #REF!
C27: =C25-C26 -> #REF! | D27: =IFERROR(E27/C27,0) -> 0 | E27: =SUM(E25:E26) -> 0 | G27: =G25-G26 -> #REF! | H27: =SUM(H25:H26) -> 0 | J27: =J25-J26 -> #REF! | K27: =SUM(K25:K26) -> 0 | M27: =M25-M26 -> #REF! | N27: =SUM(N25:N26) -> 0 | P27: =P25-P26 -> #REF! | Q27: =SUM(Q25:Q26) -> 0 | S27: =S25-S26 -> #REF! | T27: =SUM(T25:T26) -> 0
H28: =IFERROR(H27/G27,0) -> 0 | K28: =IFERROR(K27/J27,0) -> 0 | N28: =IFERROR(N27/M27,0) -> 0 | Q28: =IFERROR(Q27/P27,0) -> 0 | T28: =IFERROR(T27/S27,0) -> 0

Sheet Report
A1: Plasten India Limited (Unit - 1)
A2: EBDITA SUMMERY FOR THE PERIOD OF 20th Aug 2026
A4: Particulars | B4: Qty | C4: Rate | D4: 20th Aug-26
A5: Sales
A6: MFG Goods | B6: ='Cons Prod'!B16 -> 112139.2 | C6: =D6/B6 -> 128.76043 | D6: ='Cons Prod'!D16 -> 14439092
A7: Traded goods | C7: =D7/B7 -> #DIV/0!
A8: Job Income
A10: Total Income | B10: =SUM(B6:B9) -> 112139.2 | D10: =SUM(D6:D9) -> 14439092
A12: Cost of Materials Consumed | B12: =B6 -> 112139.2 | C12: =D12/B12 -> 112.82942 | D12: ='Cons Prod'!I21 -> 12652601
A13: Cost of goods sold of traded goods | B13: =B7 -> 0 | C13: =D13/B13 -> #DIV/0!
A14: Job work Charges
A15: Total | D15: =SUM(D12:D14) -> 12652601
A17: Delta | C17: =D17/D10 -> 0.123726 | D17: =+D10-D15 -> 1786491
A18: Traded Delta Margin % | C18: =D18/D7 -> #DIV/0! | D18: =D7-D13 -> 0
A19: Process Delta Margin % | C19: =D19/D6 -> 0.123726 | D19: =D6-D12 -> 1786491
A21: Exchange Rate Difference | C21: =D21/$D$10 -> 0
A22: Salary(inc Pf and all) | C22: =D22/$D$10 -> 0.041756035 | D22: 602919.22
A23: Power | C23: =D23/$D$10 -> 0.024883144 | D23: 359290 | Q23: 8.44
A24: Stores & Consumables | C24: =D24/$D$10 -> 0.0096043389 | D24: ='Consumables and Stores'!I71 -> 138677.93
A25: Factory Rent Expense | C25: =D25/$D$10 -> 0
A27: Total Direct Expenses | C27: =D27/D10 -> 0.076243518 | D27: =SUM(D21:D26) -> 1100887.1
A28: Gross Margin | C28: =D28/D10 -> 0.04748248 | D28: =D17-D27 -> 685603.88
A30: Administrative & Selling Expense
A31: Insurance | D31: 16667
A32: Freight outward expense | D32: 75000
A33: Other Admin Expense | D33: 66667
A34: Total Admin & Selling Expense | D34: =SUM(D31:D33) -> 158334
A37: Net EBIDATA | C37: =D37/D10 -> 0.036516832 | D37: =D28-D34 -> 527269.88
A38: Finanace Cost | D38: =5000000/31*1 -> 161290.32
A39: Depreciation | D39: =1800000/31*1 -> 58064.516
A40: Net PBT | C40: =D40/D10 -> 0.021325098 | D40: =+D37-D38-D39 -> 307915.05
A42: EBIDATA/kg | D42: =(D37-D18)/B6 -> 4.701923
A43: PBT/kg | D43: =(D40-D18)/B6 -> 2.7458288

Sheet Cons Prod
A2: Production | F2: Consumption
A4: Item Name | B4: Qty | C4: Rate | D4: Value | F4: Item Name | G4: Qty | H4: Rate | I4: Value
A5: PP Tape | B5: 31373.4 | C5: =H12 -> 119.58 | D5: =B5*C5 -> 3751631.2 | F5: PP Granule | G5: =27175+1725+24+2700 -> 31624 | H5: 109.58 | I5: =G5*H5 -> 3465357.9
A6: PP Fabric | B6: 26119 | C6: =H13 -> 129.58 | D6: =B6*C6 -> 3384500 | F6: Filler | G6: =25+1861.3 -> 1886.3 | H6: 37.39 | I6: =G6*H6 -> 70528.757
A7: PP Laminated Fabric | B7: 9745 | C7: =H14 -> 134.58 | D7: =B7*C7 -> 1311482.1 | F7: MB | G7: =75+1139.3+76 -> 1290.3 | H7: 213.89 | I7: =G7*H7 -> 275982.27
A8: PP Webbing | B8: 3896.8 | C8: =H15 -> 129.58 | D8: =B8*C8 -> 504947.34 | F8: LDPE Granule | G8: =2925+305 -> 3230 | H8: 131.71 | I8: =G8*H8 -> 425423.3
A9: PP Filament Yarn | B9: 2716 | C9: =H16 -> 154.55 | D9: =B9*C9 -> 419757.8 | F9: LLDPE Granule | G9: 6068 | H9: 136.4 | I9: =G9*H9 -> 827675.2
A10: LLDPE Film | B10: 10521 | C10: =H17 -> 156.4 | D10: =B10*C10 -> 1645484.4 | F10: HDPE Granule | H10: 141.8 | I10: =G10*H10 -> 0
A11: LLDPE Bags | B11: 7528 | C11: 195.34 | D11: =B11*C11 -> 1470519.5 | F11: RP Granule | G11: =1438+1674.8+133 -> 3245.8 | H11: 28 | I11: =G11*H11 -> 90882.4
A12: FIBC Bags | B12: 5723 | C12: 218.32 | D12: =B12*C12 -> 1249445.4 | F12: PP Tape | G12: =26491+3234.8 -> 29725.8 | H12: =H5+10 -> 119.58 | I12: =G12*H12 -> 3554611.2
A13: BOPP Bags | B13: 1770 | C13: 232.2 | D13: =B13*C13 -> 410994 | F13: PP Fabric | G13: =4286.1+8034 -> 12320.1 | H13: =H5+20 -> 129.58 | I13: =G13*H13 -> 1596438.6
A14: RP Granule | B14: 7625 | C14: 28 | D14: =B14*C14 -> 213500 | F14: PP Laminated Fabric | G14: 1595.01 | H14: =H5+25 -> 134.58 | I14: =G14*H14 -> 214656.45
A15: Wastage | B15: =113+10+2669+372+400+249+477+734+60+38 -> 5122 | C15: 15 | D15: =B15*C15 -> 76830 | F15: PP Webbing | G15: 918.45 | H15: =H5+20 -> 129.58 | I15: =G15*H15 -> 119012.75
A16: Total | B16: =SUM(B5:B15) -> 112139.2 | D16: =SUM(D5:D15) -> 14439092 | F16: PP Filament Yarn | G16: =918.45+700 -> 1618.45 | H16: 154.55 | I16: =G16*H16 -> 250131.45
F17: LLDPE Film | G17: 10197 | H17: =H9+20 -> 156.4 | I17: =G17*H17 -> 1594810.8
F18: BOPP Film | H18: 215.33 | I18: =G18*H18 -> 0
F19: Craft Paper | G19: =423.99+258 -> 681.99 | H19: 74.81 | I19: =G19*H19 -> 51019.672
F20: Wastage | G20: 7738 | H20: 15 | I20: =G20*H20 -> 116070
F21: Total | G21: =SUM(G5:G20) -> 112139.2 | I21: =SUM(I5:I20) -> 12652601 | K21: =B16-G21 -> 0

Sheet Sheet4

Sheet Consumables and Stores
B3: Compname | C3: Itemcode | D3: Itemname | E3: Unit | F3: Qty | G3: QtyInKgs | H3: Rate | I3: Amount | J3: IssueTo | K3: Deptt | L3: GroupName | M3: SubGroupName | N3: Subdept | O3: LoginName
B4: Plastene India Limited | C4: GEN00057 | D4: White Sheet Felt 07 mm +/- 1 mm | E4: KGS | F4: 1 | G4: 0 | H4: 180 | I4: 180 | J4: Circ Looms | K4: Consumables | L4: Consumables | N4: LOOM | O4: inder
B5: Plastene India Limited | C5: LAM00180 | D5: Double Side Tape 20 mm | E5: ROLLS | F5: 2 | G5: 0 | H5: 66.66 | I5: 133.32 | J5: Circ Looms | K5: Consumables | L5: Adhesive Tapes | N5: LOOM | O5: inder
B6: Plastene India Limited | C6: LOO00010 | D6: Heddle Belt Upper 230X122 - 12 Hole | E6: PCS | F6: 86 | G6: 0 | H6: 21.32 | I6: 1833.52 | J6: Circ Looms | K6: Stores/Spares | L6: Circular Loom Spares | N6: Loom | O6: inder
B7: Plastene India Limited | C7: LOO00011 | D7: Heddle Belt Lower 472X122 - 12 Hole | E7: PCS | F7: 60 | G7: 0 | H7: 41.82 | I7: 2509.2 | J7: Circ Looms | K7: Stores/Spares | L7: Circular Loom Spares | N7: Loom | O7: inder
B8: Plastene India Limited | C8: LOO00444 | D8: Compensator Hook | E8: Pcs | F8: 300 | G8: 0 | H8: 0.59 | I8: 178.5 | J8: Circ Looms | K8: Stores/Spares | L8: Circular Loom Spares | N8: LOOM | O8: inder
B9: Plastene India Limited | C9: LOO01284 | D9: White Oil:- 12 No | E9: Ltr | F9: 97 | G9: 0 | H9: 130 | I9: 12610 | J9: Circ Looms | K9: Consumables | L9: Oil & Greases | N9: LOOM | O9: inder
B10: Plastene India Limited | C10: OTH00163 | D10: Blade Prabhat | E10: Pkts | F10: 3 | G10: 0 | H10: 63 | I10: 189 | J10: Circ Looms | K10: Stores/Spares | L10: Cutter Blades | N10: LOOM | O10: inder
B11: Plastene India Limited | C11: OTH00168 | D11: Brown Tape W-2" X L-65 Mtr | E11: PCS | F11: 6 | G11: 0 | H11: 25 | I11: 150 | J11: Circ Looms | K11: Consumables | L11: Adhesive Tapes | N11: LOOM | O11: inder
B12: Plastene India Limited | C12: OTH00202 | D12: Cotton Waste | E12: Kgs | F12: 4 | G12: 0 | H12: 16 | I12: 64 | J12: Circ Looms | K12: Consumables | L12: Housekeeping Material | N12: LOOM | O12: inder
B13: Plastene India Limited | C13: OTH00356 | D13: Allen Bolt 10X30 mm-2 | E13: PCS | F13: 4 | G13: 0 | H13: 6.18 | I13: 24.71 | J13: Circ Looms | K13: Stores/Spares | L13: Hardware Items | N13: LOOM | O13: inder
B14: Plastene India Limited | C14: OTH00527 | D14: Diesel | E14: LTR | F14: 5 | G14: 0 | H14: 97.88 | I14: 489.4 | J14: Circ Looms | K14: Consumables | L14: Oil & Greases | N14: LOOM | O14: inder
B15: Plastene India Limited | C15: OTH00929 | D15: Hex Nut 10 mm | E15: Pcs | F15: 17 | G15: 0 | H15: 2.05 | I15: 34.92 | J15: Circ Looms | K15: Stores/Spares | L15: Hardware Items | N15: LOOM | O15: inder
... B45: Plastene India Limited | C45: OTH00255 | D45: Nirma Powder | E45: Kgs | F45: 1 | G45: 0 | H45: 53 | I45: 53 | J45: Office/General | K45: Consumables | L45: Housekeeping Material | N45: HK | O45: inder
B46: Plastene India Limited | C46: OTH00770 | D46: Water Bottle | E46: Pcs | F46: 2 | G46: 0 | H46: 25 | I46: 50 | J46: Office/General | K46: Consumables | L46: Consumables | M46: Consumables | N46: Office | O46: inder
B47: Plastene India Limited | C47: CON00102 | D47: Ss Screen Mesh Dia.148 mm 120 Mesh | E47: Pcs | F47: 100 | G47: 0 | H47: 5.1 | I47: 510 | J47: RP | K47: Consumables | L47: Filters for Extrusion | M47: 0 | N47: RP | O47: inder
B48: Plastene India Limited | C48: MMU00196 | D48: Allen Bolt 04X08 mm | E48: Pcs | F48: 8 | G48: 0 | H48: 3.02 | I48: 24.16 | J48: RP | K48: Stores/Spares | L48: Hardware Items | N48: RP | O48: inder
B49: Plastene India Limited | C49: OTH00490 | D49: Washer Plain 05 mm | E49: PCS | F49: 35 | G49: 0 | H49: 0.29 | I49: 10.15 | J49: RP | K49: Stores/Spares | L49: Hardware Items | N49: LINER | O49: inder
B50: Plastene India Limited | C50: R.P00286 | D50: Ss Screen Mesh Dia.148 mm Multimesh 24X110 | E50: Pcs | F50: 100 | G50: 0 | H50: 18 | I50: 1800 | J50: RP | K50: Consumables | L50: Filters for Extrusion | N50: RP | O50: inder
B51: Plastene India Limited | C51: R.P00287 | D51: Ss Screen Mesh Dia.148 mm 20 Mesh | E51: Pcs | F51: 100 | G51: 0 | H51: 6.9 | I51: 690 | J51: RP | K51: Consumables | L51: Filters for Extrusion | N51: RP | O51: inder
B52: Plastene India Limited | C52: R.P00292 | D52: Pelletizing Knife0.9mm/17 Degree ( Item No.A-05085-08013-V01) | E52: PCS | F52: 6 | G52: 0 | H52: 20 | I52: 120 | J52: RP | K52: Stores/Spares | L52: RP M/c Spares | N52: RP | O52: inder
B53: Plastene India Limited | C53: R.P00390 | D53: Ss Screen Mesh Dia.148 mm40 Mesh | E53: Pcs | F53: 100 | G53: 0 | H53: 5.5 | I53: 550 | J53: RP | K53: Consumables | L53: Filters for Extrusion | N53: RP | O53: inder
B54: Plastene India Limited | C54: MUL02874 | D54: Bearing | E54: Pcs | F54: 4 | G54: 0 | H54: 2425 | I54: 9700 | J54: Small Bags | K54: Stores/Spares | L54: Bearings | N54: BOPP | O54: inder
B55: Plastene India Limited | C55: OTH00177 | D55: Cello Tape W-2" Natural X L-65 Mtr | E55: PCS | F55: 6 | G55: 0 | H55: 25 | I55: 150 | J55: Small Bags | K55: Consumables | L55: Adhesive Tapes | N55: BOPP | O55: inder
B56: Plastene India Limited | C56: OTH00695 | D56: Bearing 1208 Tv Skf | E56: PCS | F56: 4 | G56: 0 | H56: 780 | I56: 3120 | J56: Small Bags | K56: Stores/Spares | L56: Bearings | N56: BOPP | O56: inder
B57: Plastene India Limited | C57: UTI01777 | D57: Bearing 6202 Zz C3 Skf | E57: Pcs | F57: 4 | G57: 0 | H57: 76.4 | I57: 305.6 | J57: Small Bags | K57: Stores/Spares | L57: Bearings | N57: BOPP | O57: inder
B58: Plastene India Limited | C58: CAP02167 | D58: Cheese Winder Model Lfw-200 Cm | E58: Pcs | F58: 3 | G58: 0 | H58: 4410 | I58: 13230 | J58: Tape Plant | K58: Capex | L58: Winders | N58: TAPE PLANT | O58: inder
B59: Plastene India Limited | C59: MUL04482 | D59: Topaz Blade | E59: Pcs | F59: 2000 | G59: 0 | H59: 0.91 | I59: 1820 | J59: Tape Plant | K59: Stores/Spares | L59: Cutter Blades | N59: TAPE PLANT | O59: inder
... B70: Plastene India Limited | C70: UTI03437 | D70: Pu Tee Connector - 8 mm | E70: Pcs | F70: 10 | G70: 0 | H70: 33.12 | I70: 331.2 | J70: Utility/Maint | K70: Stores/Spares | L70: PVC Fittings | N70: UTILITY | O70: inder
I71: =SUM(I4:I70) -> 138677.93

Sheet Flowchart
A1: PLASTENE INDIA LIMITED - UNIT II | I1: =TODAY()-1 -> 46259
I2: RM+RP = | N2: =#REF! -> #REF!
G6: TAPE | T6: WASTAGE
T7: =T8/(G8+T8) -> #REF!
G8: =#REF! -> #REF! | T8: =#REF! -> #REF!
D11: UNLAMINATED FABRIC | H11: TFO | T11: WASTAGE (U/L FABRIC)
T12: =T13/(T13+D13) -> #REF!
D13: =#REF! -> #REF! | H13: =#REF! -> #REF! | T13: =#REF! -> #REF!
K15: NEEDLE LOOM | T15: WASTAGE (TFO)
K16: TAPE | O16: YARN | T16: =T17/(T17+H13) -> #REF!
K17: =#REF! -> #REF! | O17: =#REF! -> #REF! | T17: =#REF! -> #REF!
K21: WEBBING | T21: WASTAGE (NEEDLE LOOM)
T22: =T23/(T23+K23) -> #REF!
K23: =#REF! -> #REF! | T23: =#REF! -> #REF!
D26: SALES | G26: JOB | P26: JOB | S26: SALES
D27: =#REF!-#REF! -> #REF! | G27: =#REF!-#REF! -> #REF! | P27: =#REF!-#REF! -> #REF! | S27: =#REF! -> #REF!
A30: LAMINATION U/L FABRIC | D30: LAMINATION RM
A31: =#REF! -> #REF! | D31: =#REF!-#REF! -> #REF!
A35: LAMINATED FABRIC | H35: WASTAGE
H36: =H37/(A31+D31) -> #REF!
A37: =#REF! -> #REF! | H37: =#REF! -> #REF!
B40: SALE | E40: JOB
B41: =#REF!-#REF! -> #REF! | E41: =#REF!-#REF! -> #REF!
G44: FIBC/SMALL BAGS LAMI. FABRIC | J44: FIBC/SMALL BAGS UNLAMI FABRIC | M44: FIBC/SMALL BAGS WEBBING | P44: LINER / LLDPE BAGS | S44: YARN | V44: OTHER
G45: =#REF!+#REF! -> #REF! | J45: =#REF!+#REF! -> #REF! | M45: =#REF! -> #REF! | P45: =#REF!+#REF! -> #REF! | S45: =#REF!+#REF! -> #REF! | V45: =#REF! -> #REF!
G49: FIBC BAGS/SMALL BAGS | T49: WASTAGE
T50: =T51/(G51+T51) -> #REF!
G51: =#REF!+#REF! -> #REF! | T51: =#REF!+#REF! -> #REF!
A53: TOTAL WASTAGE | G53: =T51+H37+T23+T17+T13+T8 -> #REF!
A54: TOTAL MATERIAL CONSUMPTION | G54: =N2+O17+D31+P45+S45-H13 -> #REF!
A55: WASTAGE RATIO | G55: =G53/G54 -> #REF!
A56: * RM Consu and Plast Wastage include Sweeping Wastage of 4613 kg. (Nov-1550, Dec-3063)
A57: * FIBC Wastage includes wastage of 980 Kg of Liner wastage
A58: * FIBC Wastage includes wastage of 10578 Kg of Fabric wastage trf. From RMD Dept.

Sheet FillerSoltex
M2: 9100 | N2: =#REF!-M2 -> #REF! | O2: 0 | P2: =+#REF!-O2 -> #REF! | Q2: 1351.72 | R2: 25.823134 | S2: =+Q2*R2 -> 34905.646 | AD2: OP | AE2: 849.515 | AF2: =+#REF! -> #REF! | AG2: =+AE2-AF2 -> #REF!
M3: 5700 | N3: =#REF!-M3 -> #REF! | O3: 1895.5 | P3: =+#REF!-O3 -> #REF! | Q3: 8500 | R3: 27 | S3: =+Q3*R3 -> 229500 | T3: 43952 | W3: OP. Stock | X3: =Q2 -> 1351.72 | Y3: =R2 -> 25.823134 | Z3: =X3*Y3 -> 34905.646 | AD3: Cons | AE3: -36034.05 | AF3: =-G33 -> #REF! | AG3: =+AE3-AF3 -> #REF!
M4: 4000 | N4: =#REF!-M4 -> #REF! | O4: 1558.8 | P4: =+#REF!-O4 -> #REF! | Q4: 250 | R4: 27 | S4: =+Q4*R4 -> 6750 | T4: 43952 | W4: Pur | X4: =SUM(Q3:Q7) -> 27750 | Y4: =Z4/X4 -> 25.612614 | Z4: =SUM(S3:S7) -> 710750.04 | AD4: Pur | AE4: 87250 | AF4: =+C33 -> #REF! | AG4: =+AE4-AF4 -> #REF!
M5: 17750 | N5: =#REF!-M5 -> #REF! | O5: 1621.65 | P5: =+#REF!-O5 -> #REF! | Q5: 16000 | R5: 24.5 | S5: =+Q5*R5 -> 392000 | T5: 43955 | W5: Less: Closing Stock | X5: =-#REF! -> #REF! | Y5: =R18 -> #REF! | Z5: =X5*Y5 -> #REF! | AD5: Sales/Job Out | AE5: -25690 | AF5: =-I33-J33 -> #REF! | AG5: =+AE5-AF5 -> #REF!
M6: 14850 | N6: =#REF!-M6 -> #REF! | O6: 1350 | P6: =+#REF!-O6 -> #REF! | Q6: 2000 | R6: 27.500019 | S6: =+Q6*R6 -> 55000.037 | T6: 43962 | W6: Consumption | X6: =SUM(X3:X5) -> #REF! | Y6: =Z6/X6 -> #REF! | Z6: =SUM(Z3:Z5) -> #REF!
M7: 10325 | N7: =#REF!-M7 -> #REF! | O7: 1529 | P7: =+#REF!-O7 -> #REF! | Q7: 1000 | R7: 27.500003 | S7: =+Q7*R7 -> 27500.003 | T7: 43965 | AE7: =SUM(AE2:AE6) -> 26375.465 | AF7: =SUM(AF2:AF6) -> #REF! | AG7: =SUM(AG2:AG6) -> #REF!
M8: 5500 | N8: =#REF!-M8 -> #REF! | O8: 1807 | P8: =+#REF!-O8 -> #REF! | Q8: 1000 | R8: 27.5 | S8: =+Q8*R8 -> 27500 | T8: 43965
M9: 3550 | N9: =#REF!-M9 -> #REF! | O9: 1401.5 | P9: =+#REF!-O9 -> #REF! | Q9: 16000 | R9: 24.5 | S9: =+Q9*R9 -> 392000 | T9: 43966
M10: 2300 | N10: =#REF!-M10 -> #REF! | O10: 1234.6 | P10: =+#REF!-O10 -> #REF! | Q10: 1500 | R10: 27.4 | S10: =+Q10*R10 -> 41100 | T10: 43968
M11: 1500 | N11: =#REF!-M11 -> #REF! | O11: 892 | P11: =+#REF!-O11 -> #REF! | Q11: 16000 | R11: 24.5 | S11: =+Q11*R11 -> 392000 | T11: 43969
M12: 1975 | N12: =#REF!-M12 -> #REF! | O12: 1086.5 | P12: =+#REF!-O12 -> #REF! | Q12: 25000 | R12: 24.7 | S12: =+Q12*R12 -> 617500 | T12: 43974
M13: 625 | N13: =#REF!-M13 -> #REF! | O13: 1345 | P13: =+#REF!-O13 -> #REF!
M14: 625 | N14: =#REF!-M14 -> #REF! | O14: 1045 | P14: =+#REF!-O14 -> #REF!
M15: 500 | N15: =#REF!-M15 -> #REF! | O15: 1222 | P15: =+#REF!-O15 -> #REF!
M16: 14975 | N16: =#REF!-M16 -> #REF! | O16: 885 | P16: =+#REF!-O16 -> #REF! | Q16: =SUM(Q12:Q12) -> 25000 | R16: =S16/Q16 -> 24.7 | S16: =SUM(S12:S12) -> 617500
M17: 8850 | N17: =#REF!-M17 -> #REF! | O17: 119 | P17: =+#REF!-O17 -> #REF! | Q17: =-X5-Q16 -> #REF! | R17: =+R11 -> 24.5 | S17: =Q17*R17 -> #REF!
M18: 8325 | N18: =#REF!-M18 -> #REF! | O18: 522 | P18: =+#REF!-O18 -> #REF! | Q18: =SUM(Q16:Q17) -> #REF! | R18: =S18/Q18 -> #REF! | S18: =SUM(S16:S17) -> #REF!
M19: 22900 | N19: =#REF!-M19 -> #REF! | O19: 1345 | P19: =+#REF!-O19 -> #REF!
M20: 21700 | N20: =#REF!-M20 -> #REF! | O20: 1210.5 | P20: =+#REF!-O20 -> #REF!
M21: 20450 | N21: =#REF!-M21 -> #REF! | O21: 1280 | P21: =+#REF!-O21 -> #REF!
M22: 17800 | N22: =#REF!-M22 -> #REF! | O22: 958.25 | P22: =+#REF!-O22 -> #REF!
M23: 16200 | N23: =#REF!-M23 -> #REF! | O23: 1757.5 | P23: =+#REF!-O23 -> #REF!
M24: 40175 | N24: =#REF!-M24 -> #REF! | O24: 1102.5 | P24: =+#REF!-O24 -> #REF!
M25: 39550 | N25: =#REF!-M25 -> #REF! | O25: 712 | P25: =+#REF!-O25 -> #REF!
M26: 36500 | N26: =#REF!-M26 -> #REF! | O26: 1185 | P26: =+#REF!-O26 -> #REF!
M27: 34450 | N27: =#REF!-M27 -> #REF! | O27: 1174.5 | P27: =+#REF!-O27 -> #REF!
M28: 33675 | N28: =#REF!-M28 -> #REF! | O28: 753 | P28: =+#REF!-O28 -> #REF!
M29: 31850 | N29: =#REF!-M29 -> #REF! | O29: 1088.5 | P29: =+#REF!-O29 -> #REF!
M30: 29875 | N30: =#REF!-M30 -> #REF! | O30: 1283.5 | P30: =+#REF!-O30 -> #REF!
... M32: 26500 | N32: =#REF!-M32 -> #REF! | O32: 1522 | P32: =+#REF!-O32 -> #REF!
B33: =#REF! -> #REF! | C33: =SUM(#REF!) -> #REF! | D33: =SUM(#REF!) -> #REF! | E33: =SUM(#REF!) -> #REF! | F33: =SUM(#REF!) -> #REF! | G33: =SUM(#REF!) -> #REF! | H33: =SUM(#REF!) -> #REF! | I33: =SUM(#REF!) -> #REF! | J33: =SUM(#REF!) -> #REF! | K33: =SUM(#REF!) -> #REF! | L33: =+B33+F33-K33 -> #REF! | O33: =SUM(O3:O32) -> 36034.05 | P33: =SUM(P3:P32) -> #REF!
G34: 36034.06
G35: =+G33-G34 -> #REF! | H35: =+H33-H34 -> #REF!

Sheet UV
M2: 18475 | N2: =#REF!-M2 -> #REF! | O2: 0 | P2: =+#REF!-O2 -> #REF! | Q2: 17176.08 | R2: 171.86702 | S2: =+Q2*R2 -> 2952001.6 | AC2: OP | AD2: 18999.405 | AE2: =+#REF! -> #REF! | AF2: =+AD2-AE2 -> #REF!
M3: 17550 | N3: =#REF!-M3 -> #REF! | O3: 410.8 | P3: =+#REF!-O3 -> #REF! | Q3: 5000 | R3: 238.34 | S3: =+Q3*R3 -> 1191700 | W3: OP. Stock | X3: =Q2 -> 17176.08 | Y3: =R2 -> 171.86702 | Z3: =X3*Y3 -> 2952001.6 | AC3: Cons | AD3: -9000.205 | AE3: =-#REF! -> #REF! | AF3: =+AD3-AE3 -> #REF!
M4: 22100 | N4: =#REF!-M4 -> #REF! | O4: 356.48 | P4: =+#REF!-O4 -> #REF! | Q4: 4000 | R4: 169 | S4: =+Q4*R4 -> 676000 | W4: Pur | X4: =SUM(Q3:Q8) -> 23000 | Y4: =Z4/X4 -> 185.03043 | Z4: =SUM(S3:S8) -> 4255700 | AC4: Pur | AD4: 19000 | AE4: =+#REF! -> #REF! | AF4: =+AD4-AE4 -> #REF!
M5: 21550 | N5: =#REF!-M5 -> #REF! | O5: 570 | P5: =+#REF!-O5 -> #REF! | Q5: 4000 | R5: 169 | S5: =+Q5*R5 -> 676000 | W5: Less: Closing Stock | X5: =-#REF! -> #REF! | Y5: =R14 -> #REF! | Z5: =X5*Y5 -> #REF! | AC5: Sales/Job Out | AD5: -5975 | AE5: =-#REF!-#REF! -> #REF! | AF5: =+AD5-AE5 -> #REF!
M6: 21075 | N6: =#REF!-M6 -> #REF! | O6: 371.4 | P6: =+#REF!-O6 -> #REF! | Q6: 1000 | R6: 174.1 | S6: =+Q6*R6 -> 174100 | T6: 43970 | W6: Consumption | X6: =SUM(X3:X5) -> #REF! | Y6: =Z6/X6 -> #REF! | Z6: =SUM(Z3:Z5) -> #REF!
M7: 20775 | N7: =#REF!-M7 -> #REF! | O7: 305.8 | P7: =+#REF!-O7 -> #REF! | Q7: 4000 | R7: 169 | S7: =+Q7*R7 -> 676000 | T7: 43974 | AD7: =SUM(AD2:AD6) -> 23024.2 | AE7: =SUM(AE2:AE6) -> #REF! | AF7: =SUM(AF2:AF6) -> #REF!
M8: 20475 | N8: =#REF!-M8 -> #REF! | O8: 352.2 | P8: =+#REF!-O8 -> #REF! | Q8: 5000 | R8: 172.38 | S8: =+Q8*R8 -> 861900 | T8: 43979
M9: 19875 | N9: =#REF!-M9 -> #REF! | O9: 290.5 | P9: =+#REF!-O9 -> #REF! | X9: =+X4+MB!X4 -> 26225 | Y9: =+Z9/X9 -> 177.99964 | Z9: =+Z4+MB!Z4 -> 4668040.7
M10: 19475 | N10: =#REF!-M10 -> #REF! | O10: 271.4 | P10: =+#REF!-O10 -> #REF!
M11: 23075 | N11: =#REF!-M11 -> #REF! | O11: 337 | P11: =+#REF!-O11 -> #REF!
M12: 22050 | N12: =#REF!-M12 -> #REF! | O12: 286.4 | P12: =+#REF!-O12 -> #REF! | Q12: =SUM(Q4:Q10) -> 18000 | R12: =+S12/Q12 -> 170.22222 | S12: =SUM(S4:S10) -> 3064000
M13: 21700 | N13: =#REF!-M13 -> #REF! | O13: 354.475 | P13: =+#REF!-O13 -> #REF! | Q13: =-X5-Q12 -> #REF! | R13: =R3 -> 238.34 | S13: =Q13*R13 -> #REF!
M14: 21200 | N14: =#REF!-M14 -> #REF! | O14: 230.4 | P14: =+#REF!-O14 -> #REF! | Q14: =SUM(Q12:Q13) -> #REF! | R14: =S14/Q14 -> #REF! | S14: =SUM(S12:S13) -> #REF!
M15: 20850 | N15: =#REF!-M15 -> #REF! | O15: 276.8 | P15: =+#REF!-O15 -> #REF!
M16: 19875 | N16: =#REF!-M16 -> #REF! | O16: 241.525 | P16: =+#REF!-O16 -> #REF!
M17: 19475 | N17: =#REF!-M17 -> #REF! | O17: 0 | P17: =+#REF!-O17 -> #REF!
M18: 19275 | N18: =#REF!-M18 -> #REF! | O18: 191 | P18: =+#REF!-O18 -> #REF!
M19: 18875 | N19: =#REF!-M19 -> #REF! | O19: 333.6 | P19: =+#REF!-O19 -> #REF!
M20: 19625 | N20: =#REF!-M20 -> #REF! | O20: 243.2 | P20: =+#REF!-O20 -> #REF!
M21: 19950 | N21: =#REF!-M21 -> #REF! | O21: 270.5 | P21: =+#REF!-O21 -> #REF!
M22: 18925 | N22: =#REF!-M22 -> #REF! | O22: 321.4 | P22: =+#REF!-O22 -> #REF!
M23: 22625 | N23: =#REF!-M23 -> #REF! | O23: 333.6 | P23: =+#REF!-O23 -> #REF!
M24: 22525 | N24: =#REF!-M24 -> #REF! | O24: 202.8 | P24: =+#REF!-O24 -> #REF!
M25: 22275 | N25: =#REF!-M25 -> #REF! | O25: 226 | P25: =+#REF!-O25 -> #REF!
M26: 21075 | N26: =#REF!-M26 -> #REF! | O26: 336.35 | P26: =+#REF!-O26 -> #REF!
... M32: 22650 | N32: =#REF!-M32 -> #REF! | O32: 369.275 | P32: =+#REF!-O32 -> #REF!
O33: =SUM(O3:O32) -> 9000.205 | P33: =SUM(P3:P32) -> #REF!
G34: 8875.2
G35: =+#REF!-G34 -> #REF!

Sheet MB
M2: 12475 | N2: =#REF!-M2 -> #REF! | O2: 0 | P2: =+#REF!+#REF!-O2 -> #REF! | Q2: 15623.29 | R2: 159.20728 | S2: =+Q2*R2 -> 2487341.6 | AC2: OP | AD2: 12779.031 | AE2: =+#REF! -> #REF! | AF2: =+AD2-AE2 -> #REF!
M3: 12475 | N3: =#REF!-M3 -> #REF! | O3: 0 | P3: =+#REF!+#REF!-O3 -> #REF! | Q3: 125 | R3: 142 | S3: =+Q3*R3 -> 17750 | T3: 43963 | W3: OP. Stock | X3: =Q2 -> 15623.29 | Y3: =R2 -> 159.20728 | Z3: =X3*Y3 -> 2487341.6 | AC3: Cons | AD3: -2269.965 | AE3: =-#REF!-#REF! -> #REF! | AF3: =+AD3-AE3 -> #REF!
M4: 12350 | N4: =#REF!-M4 -> #REF! | O4: 123.89 | P4: =+#REF!+#REF!-O4 -> #REF! | Q4: 475 | R4: 142 | S4: =+Q4*R4 -> 67450 | T4: 43968 | W4: Pur | X4: =SUM(Q3:Q27) -> 3225 | Y4: =Z4/X4 -> 127.85757 | Z4: =SUM(S3:S27) -> 412340.68 | AC4: Pur | AD4: 3225 | AE4: =+#REF! -> #REF! | AF4: =+AD4-AE4 -> #REF!
M5: 12900 | N5: =#REF!-M5 -> #REF! | O5: 74.4 | P5: =+#REF!+#REF!-O5 -> #REF! | Q5: 500 | R5: 164.43051 | S5: =+Q5*R5 -> 82215.254 | T5: 43968 | W5: Less: Closing Stock | X5: =-#REF! -> #REF! | Y5: =R31 -> #REF! | Z5: =X5*Y5 -> #REF! | AC5: Sales/Job Out | AD5: -2550 | AE5: =-#REF!-#REF! -> #REF! | AF5: =+AD5-AE5 -> #REF!
M6: 12775 | N6: =#REF!-M6 -> #REF! | O6: 131 | P6: =+#REF!+#REF!-O6 -> #REF! | Q6: 1000 | R6: 96 | S6: =+Q6*R6 -> 96000 | T6: 43975 | W6: Consumption | X6: =SUM(X3:X5) -> #REF! | Y6: =Z6/X6 -> #REF! | Z6: =SUM(Z3:Z5) -> #REF!
M7: 12075 | N7: =#REF!-M7 -> #REF! | O7: 80.5 | P7: =+#REF!+#REF!-O7 -> #REF! | Q7: 100 | R7: 196 | S7: =+Q7*R7 -> 19600 | T7: 43975 | AD7: =SUM(AD2:AD6) -> 11184.066 | AE7: =SUM(AE2:AE6) -> #REF! | AF7: =SUM(AF2:AF6) -> #REF!
M8: 12075 | N8: =#REF!-M8 -> #REF! | O8: 0 | P8: =+#REF!+#REF!-O8 -> #REF! | Q8: 500 | R8: 98 | S8: =+Q8*R8 -> 49000 | T8: 43979
M9: 11950 | N9: =#REF!-M9 -> #REF! | O9: 121.25 | P9: =+#REF!+#REF!-O9 -> #REF! | Q9: 25 | R9: 173.01695 | S9: =+Q9*R9 -> 4325.4237 | T9: 43979
M10: 11875 | N10: =#REF!-M10 -> #REF! | O10: 70.6 | P10: =+#REF!+#REF!-O10 -> #REF! | Q10: 500 | R10: 152 | S10: =+Q10*R10 -> 76000 | T10: 43982
M11: 11575 | N11: =#REF!-M11 -> #REF! | O11: 200 | P11: =+#REF!+#REF!-O11 -> #REF!
M12: 11025 | N12: =#REF!-M12 -> #REF! | O12: 0 | P12: =+#REF!+#REF!-O12 -> #REF!
M13: 11150 | N13: =#REF!-M13 -> #REF! | O13: 8.625 | P13: =+#REF!+#REF!-O13 -> #REF!
M14: 11125 | N14: =#REF!-M14 -> #REF! | O14: 25 | P14: =+#REF!+#REF!-O14 -> #REF!
M15: 11575 | N15: =#REF!-M15 -> #REF! | O15: 25 | P15: =+#REF!+#REF!-O15 -> #REF!
M16: 11550 | N16: =#REF!-M16 -> #REF! | O16: 34.375 | P16: =+#REF!+#REF!-O16 -> #REF!
M17: 11425 | N17: =#REF!-M17 -> #REF! | O17: 22 | P17: =+#REF!+#REF!-O17 -> #REF!
M18: 11325 | N18: =#REF!-M18 -> #REF! | O18: 75.05 | P18: =+#REF!+#REF!-O18 -> #REF!
M19: 11325 | N19: =#REF!-M19 -> #REF! | O19: 25 | P19: =+#REF!+#REF!-O19 -> #REF!
M20: 11250 | N20: =#REF!-M20 -> #REF! | O20: 50 | P20: =+#REF!+#REF!-O20 -> #REF!
M21: 11150 | N21: =#REF!-M21 -> #REF! | O21: 140 | P21: =+#REF!+#REF!-O21 -> #REF!
M22: 10725 | N22: =#REF!-M22 -> #REF! | O22: 181.8 | P22: =+#REF!+#REF!-O22 -> #REF!
... M28: 10650 | N28: =#REF!-M28 -> #REF! | O28: 229.5 | P28: =+#REF!+#REF!-O28 -> #REF!
M29: 10825 | N29: =#REF!-M29 -> #REF! | O29: 118.225 | P29: =+#REF!+#REF!-O29 -> #REF! | Q29: =SUM(Q3:Q26) -> 3225 | S29: =SUM(S3:S26) -> 412340.68
M30: 11300 | N30: =#REF!-M30 -> #REF! | O30: 30 | P30: =+#REF!+#REF!-O30 -> #REF! | Q30: =-X5-Q29 -> #REF! | R30: =R2 -> 159.20728 | S30: =Q30*R30 -> #REF!
M31: 11200 | N31: =#REF!-M31 -> #REF! | O31: 13.375 | P31: =+#REF!+#REF!-O31 -> #REF! | Q31: =SUM(Q29:Q30) -> #REF! | R31: =+S31/Q31 -> #REF! | S31: =SUM(S29:S30) -> #REF!
M32: 11200 | N32: =#REF!-M32 -> #REF! | O32: 5.875 | P32: =+#REF!+#REF!-O32 -> #REF!
O33: =SUM(O3:O32) -> 2269.965 | P33: =SUM(P3:P32) -> #REF!
G34: 1619.92 | H34: 400
G35: =#REF!-G34 -> #REF! | H35: =#REF!-H34 -> #REF!

Sheet RP
N2: 53897.5 | O2: =#REF!-N2 -> #REF! | P2: 0 | Q2: =+#REF!-P2 -> #REF! | R2: 50087.5 | S2: 45 | T2: =+R2*S2 -> 2253937.5 | AD2: OP | AE2: 50087.5 | AF2: =+#REF! -> #REF! | AG2: =+AE2-AF2 -> #REF!
N3: 56087.5 | O3: =#REF!-N3 -> #REF! | P3: 2670 | Q3: =+#REF!-P3 -> #REF! | R3: 9840 | S3: 46 | T3: =+R3*S3 -> 452640 | U3: 43979 | Y3: OP. Stock | Z3: =R2 -> 50087.5 | AA3: =S2 -> 45 | AB3: =Z3*AA3 -> 2253937.5 | AD3: Cons | AE3: -86940 | AF3: =-#REF!-#REF! -> #REF! | AG3: =+AE3-AF3 -> #REF!
N4: 53567.5 | O4: =#REF!-N4 -> #REF! | P4: 5430 | Q4: =+#REF!-P4 -> #REF! | Y4: Production | Z4: =#REF! -> #REF! | AA4: 45 | AB4: =Z4*AA4 -> #REF! | AD4: Pur/Prod/Job In | AE4: 119670 | AF4: =+#REF!+#REF!+#REF! -> #REF! | AG4: =+AE4-AF4 -> #REF!
N5: 50267.5 | O5: =#REF!-N5 -> #REF! | P5: 3300 | Q5: =+#REF!-P5 -> #REF! | Y5: Pur | Z5: =SUM(R3:R7) -> 9840 | AA5: =AB5/Z5 -> 46 | AB5: =SUM(T3:T7) -> 452640 | AD5: Sales/Job Out | AE5: -20040 | AF5: =-#REF!-#REF! -> #REF! | AG5: =+AE5-AF5 -> #REF!
N6: 51947.5 | O6: =#REF!-N6 -> #REF! | P6: 4530 | Q6: =+#REF!-P6 -> #REF! | Y6: Less: Closing Stock | Z6: =-#REF! -> #REF! | AA6: 45 | AB6: =Z6*AA6 -> #REF!
N7: 55007.5 | O7: =#REF!-N7 -> #REF! | P7: 2220 | Q7: =+#REF!-P7 -> #REF! | Y7: Consumption | Z7: =SUM(Z3:Z6) -> #REF! | AA7: =AB7/Z7 -> #REF! | AB7: =SUM(AB3:AB6) -> #REF! | AE7: =SUM(AE2:AE6) -> 62777.5 | AF7: =SUM(AF2:AF6) -> #REF! | AG7: =SUM(AG2:AG6) -> #REF!
N8: 55277.5 | O8: =#REF!-N8 -> #REF! | P8: 3870 | Q8: =+#REF!-P8 -> #REF!
N9: 57227.5 | O9: =#REF!-N9 -> #REF! | P9: 3570 | Q9: =+#REF!-P9 -> #REF!
N10: 52637.5 | O10: =#REF!-N10 -> #REF! | P10: 4590 | Q10: =+#REF!-P10 -> #REF!
N11: 54017.5 | O11: =#REF!-N11 -> #REF! | P11: 4830 | Q11: =+#REF!-P11 -> #REF!
N12: 59477.5 | O12: =#REF!-N12 -> #REF! | P12: 3030 | Q12: =+#REF!-P12 -> #REF!
N13: 60827.5 | O13: =#REF!-N13 -> #REF! | P13: 3510 | Q13: =+#REF!-P13 -> #REF!
N14: 64547.5 | O14: =#REF!-N14 -> #REF! | P14: 2250 | Q14: =+#REF!-P14 -> #REF!
N15: 66287.5 | O15: =#REF!-N15 -> #REF! | P15: 2760 | Q15: =+#REF!-P15 -> #REF!
N16: 69587.5 | O16: =#REF!-N16 -> #REF! | P16: 2610 | Q16: =+#REF!-P16 -> #REF!
N17: 71387.5 | O17: =#REF!-N17 -> #REF! | P17: 60 | Q17: =+#REF!-P17 -> #REF!
N18: 69827.5 | O18: =#REF!-N18 -> #REF! | P18: 1560 | Q18: =+#REF!-P18 -> #REF!
N19: 66767.5 | O19: =#REF!-N19 -> #REF! | P19: 3060 | Q19: =+#REF!-P19 -> #REF!
... N23: 60767.5 | O23: =#REF!-N23 -> #REF! | P23: 3390 | Q23: =+#REF!-P23 -> #REF!
O24: =#REF!-N24 -> #REF! | P24: 870 | Q24: =+#REF!-P24 -> #REF!
O25: =#REF!-N25 -> #REF! | P25: 1200 | Q25: =+#REF!-P25 -> #REF!
O26: =#REF!-N26 -> #REF! | P26: 4470 | Q26: =+#REF!-P26 -> #REF!
O27: =#REF!-N27 -> #REF! | P27: 2760 | Q27: =+#REF!-P27 -> #REF!
O28: =#REF!-N28 -> #REF! | P28: 2430 | Q28: =+#REF!-P28 -> #REF!
O29: =#REF!-N29 -> #REF! | P29: 3390 | Q29: =+#REF!-P29 -> #REF!
O30: =#REF!-N30 -> #REF! | P30: 1380 | Q30: =+#REF!-P30 -> #REF!
O31: =#REF!-N31 -> #REF! | P31: 3000 | Q31: =+#REF!-P31 -> #REF!
O32: =#REF!-N32 -> #REF! | P32: 2610 | Q32: =+#REF!-P32 -> #REF!
P33: =SUM(P3:P32) -> 86940 | Q33: =SUM(Q3:Q32) -> #REF!
D34: 104100 | G34: 86940
D35: =#REF!-D34 -> #REF! | G35: =#REF!-G34 -> #REF! | R35: =SUM(R3:R34) -> 9840 | T35: =SUM(T3:T34) -> 452640

Sheet LD
M2: 172600 | N2: =(+#REF!-M2)+0 -> #REF! | Q2: 298058.04 | R2: 71.410138 | S2: =+Q2*R2 -> 21284366 | AC2: OP | AD2: 183106.85 | AE2: =+#REF! -> #REF! | AF2: =+AD2-AE2 -> #REF!
M3: 264200 | N3: =+#REF!-M3 -> #REF! | O3: 13650 | P3: =+#REF!-O3 -> #REF! | Q3: 24750 | R3: 70.295 | S3: =+Q3*R3 -> 1739801.2 | T3: 43953 | W3: OP. Stock | X3: =Q2 -> 298058.04 | Y3: =R2 -> 71.410138 | Z3: =X3*Y3 -> 21284366 | AC3: Cons | AD3: -288500 | AE3: =-#REF! -> #REF! | AF3: =+AD3-AE3 -> #REF!
M4: 313475 | N4: =+#REF!-M4 -> #REF! | O4: 11700 | P4: =+#REF!-O4 -> #REF! | Q4: 24750 | R4: 70.295 | S4: =+Q4*R4 -> 1739801.2 | T4: 43953 | W4: Pur | X4: =SUM(Q3:Q68) -> 817000 | Y4: =Z4/X4 -> 63.497343 | Z4: =SUM(S3:S68) -> 51877329 | AC4: Pur | AD4: =503500+413625 -> 917125 | AE4: =+#REF! -> #REF! | AF4: =+AD4-AE4 -> #REF!
M5: 298300 | N5: =+#REF!-M5 -> #REF! | O5: 13275 | P5: =+#REF!-O5 -> #REF! | Q5: 24750 | R5: 70.295 | S5: =+Q5*R5 -> 1739801.2 | T5: 43953 | W5: Less: Closing Stock | X5: =-#REF! -> #REF! | Y5: =R77 -> 65.612455 | Z5: =X5*Y5 -> #REF! | AC5: Sales/Job Out | AD5: =-192767-10200-413625 -> -616592 | AE5: =-#REF!-#REF! -> #REF! | AF5: =+AD5-AE5 -> #REF!
M6: 276300 | N6: =+#REF!-M6 -> #REF! | O6: 11750 | P6: =+#REF!-O6 -> #REF! | Q6: 24750 | R6: 70.295 | S6: =+Q6*R6 -> 1739801.2 | T6: 43953 | W6: Consumption | X6: =SUM(X3:X5) -> #REF! | Y6: =Z6/X6 -> #REF! | Z6: =SUM(Z3:Z5) -> #REF!
M7: 257050 | N7: =+#REF!-M7 -> #REF! | O7: 12075 | P7: =+#REF!-O7 -> #REF! | Q7: 31000 | R7: 60.01 | S7: =+Q7*R7 -> 1860310 | T7: 43953 | AD7: =SUM(AD2:AD6) -> 195139.85 | AE7: =SUM(AE2:AE6) -> #REF! | AF7: =SUM(AF2:AF6) -> #REF!
M8: 266900 | N8: =+#REF!-M8 -> #REF! | O8: 11250 | P8: =+#REF!-O8 -> #REF! | Q8: 30000 | R8: 60.01 | S8: =+Q8*R8 -> 1800300 | T8: 43954
M9: 247825 | N9: =+#REF!-M9 -> #REF! | O9: 10725 | P9: =+#REF!-O9 -> #REF! | Q9: 31000 | R9: 60.01 | S9: =+Q9*R9 -> 1860310 | T9: 43954
M10: 240950 | N10: =+#REF!-M10 -> #REF! | O10: 8500 | P10: =+#REF!-O10 -> #REF! | Q10: 31000 | R10: 66.08 | S10: =+Q10*R10 -> 2048480 | T10: 43958
M11: 218050 | N11: =+#REF!-M11 -> #REF! | O11: 11900 | P11: =+#REF!-O11 -> #REF! | Q11: 31000 | R11: 60.01 | S11: =+Q11*R11 -> 1860310 | T11: 43962
M12: 251725 | N12: =+#REF!-M12 -> #REF! | O12: 8050 | P12: =+#REF!-O12 -> #REF! | Q12: 31000 | R12: 60.01 | S12: =+Q12*R12 -> 1860310 | T12: 43962
M13: 242500 | N13: =+#REF!-M13 -> #REF! | O13: 10575 | P13: =+#REF!-O13 -> #REF! | Q13: 31000 | R13: 66.08 | S13: =+Q13*R13 -> 2048480 | T13: 43964
M14: 287800 | N14: =+#REF!-M14 -> #REF! | O14: 7200 | P14: =+#REF!-O14 -> #REF! | Q14: 31000 | R14: 66.08 | S14: =+Q14*R14 -> 2048480 | T14: 43964
M15: 347600 | N15: =+#REF!-M15 -> #REF! | O15: 8250 | P15: =+#REF!-O15 -> #REF! | Q15: 24750 | R15: 69.05375 | S15: =+Q15*R15 -> 1709080.3 | T15: 43964
M16: 293350 | N16: =+#REF!-M16 -> #REF! | O16: 7175 | P16: =+#REF!-O16 -> #REF! | Q16: 24750 | R16: 69.05375 | S16: =+Q16*R16 -> 1709080.3 | T16: 43964
M17: 290200 | N17: =+#REF!-M17 -> #REF! | O17: 1450 | P17: =+#REF!-O17 -> #REF! | Q17: 24000 | R17: 66.08 | S17: =+Q17*R17 -> 1585920 | T17: 43965
M18: 282650 | N18: =+#REF!-M18 -> #REF! | O18: 7550 | P18: =+#REF!-O18 -> #REF! | Q18: 7000 | R18: 66.08 | S18: =+Q18*R18 -> 462560 | T18: 43965
M19: 273850 | N19: =+#REF!-M19 -> #REF! | O19: 9250 | P19: =+#REF!-O19 -> #REF! | Q19: 31000 | R19: 66.08 | S19: =+Q19*R19 -> 2048480 | T19: 43965
... M32: 195900 | N32: =+#REF!-M32 -> #REF! | O32: 11725 | P32: =+#REF!-O32 -> #REF! | Q32: 24750 | R32: 56.1075 | S32: =+Q32*R32 -> 1388660.6 | T32: 43980
O33: =SUM(O3:O32) -> 288500 | P33: =SUM(P3:P32) -> #REF! | Q33: 24750 | R33: 56.1075 | S33: =+Q33*R33 -> 1388660.6 | T33: 43980
G34: 290117.54 | Q34: 24750 | R34: 56.1075 | S34: =+Q34*R34 -> 1388660.6 | T34: 43981
B35: =+#REF!-B34 -> #REF! | G35: =+#REF!-G34 -> #REF! | L35: =+#REF!-L34 -> #REF! | Q35: 24750 | R35: 56.1075 | S35: =+Q35*R35 -> 1388660.6 | T35: 43981
F40: =#REF! -> #REF!
F41: =#REF! -> #REF!
F42: =#REF! -> #REF!
F43: =#REF! -> #REF!
F44: =#REF! -> #REF!
F45: =#REF! -> #REF!
F46: =#REF! -> #REF!
F47: =#REF! -> #REF!
F48: =#REF! -> #REF!
F49: =#REF! -> #REF!
F50: =#REF! -> #REF!
F51: =#REF! -> #REF!
... F70: =#REF! -> #REF!
Q77: =SUM(Q2:Q76) -> 1115058 | R77: =+S77/Q77 -> 65.612455 | S77: =SUM(S2:S76) -> 73161695

Sheet LLDP
M2: 16725 | N2: =(+#REF!-M2)+0 -> #REF! | O2: 164.8 | P2: =+#REF!-O2 -> #REF! | Q2: 15529.26 | R2: 96.495748 | S2: =+Q2*R2 -> 1498507.6 | AD2: OP | AE2: 16483.971 | AF2: =+#REF! -> #REF! | AG2: =+AE2-AF2 -> #REF!
M3: 16550 | N3: =(+#REF!-M3)+0 -> #REF! | O3: 176.04 | P3: =+#REF!-O3 -> #REF! | Q3: 24750 | R3: 84.25025 | S3: =+Q3*R3 -> 2085193.7 | X3: OP. Stock | Y3: =Q2 -> 15529.26 | Z3: =R2 -> 96.495748 | AA3: =Y3*Z3 -> 1498507.6 | AD3: Cons | AE3: -6167.96 | AF3: =-G33-H33 -> #REF! | AG3: =+AE3-AF3 -> #REF!
M4: 16300 | N4: =(+#REF!-M4)+0 -> #REF! | O4: 152.8 | P4: =+#REF!-O4 -> #REF! | Q4: 9000 | R4: 95.17 | S4: =+Q4*R4 -> 856530 | X4: Pur | Y4: =Q3 -> 24750 | Z4: =AA4/Y4 -> 84.25025 | AA4: =S3 -> 2085193.7 | AD4: Pur/Prod/Job In | AE4: 34425 | AF4: =+C33+D33+E33 -> #REF! | AG4: =+AE4-AF4 -> #REF!
M5: 16025 | N5: =(+#REF!-M5)+0 -> #REF! | O5: 174.4 | P5: =+#REF!-O5 -> #REF! | Q5: 15750 | R5: 95.170032 | S5: =+Q5*R5 -> 1498928 | X5: Less: Closing Stock | Y5: =-#REF! -> #REF! | Z5: =R19 -> #REF! | AA5: =Y5*Z5 -> #REF! | AD5: Sales/Job Out | AE5: -22625 | AF5: =-I33-J33 -> #REF! | AG5: =+AE5-AF5 -> #REF!
M6: 15925 | N6: =(+#REF!-M6)+0 -> #REF! | O6: 207.4 | P6: =+#REF!-O6 -> #REF! | Q6: 24750 | R6: 84.25 | S6: =+Q6*R6 -> 2085187.5 | X6: Consumption | Y6: =SUM(Y3:Y5) -> #REF! | Z6: =AA6/Y6 -> #REF! | AA6: =SUM(AA3:AA5) -> #REF!
M7: 15650 | N7: =(+#REF!-M7)+0 -> #REF! | O7: 213.2 | P7: =+#REF!-O7 -> #REF! | Q7: 1675 | R7: 76.899954 | S7: =+Q7*R7 -> 128807.42 | T7: 43974 | AE7: =SUM(AE2:AE6) -> 22116.011 | AF7: =SUM(AF2:AF6) -> #REF! | AG7: =SUM(AG2:AG6) -> #REF!
M8: 14950 | N8: =(+#REF!-M8)+0 -> #REF! | O8: 159.34 | P8: =+#REF!-O8 -> #REF! | Q8: 4000 | R8: 73.719954 | S8: =+Q8*R8 -> 294879.82 | T8: 43974
M9: 14725 | N9: =(+#REF!-M9)+0 -> #REF! | O9: 192.46 | P9: =+#REF!-O9 -> #REF! | Q9: 24750 | R9: 84.25 | S9: =+Q9*R9 -> 2085187.5 | T9: 43974
M10: 14525 | N10: =(+#REF!-M10)+0 -> #REF! | O10: 172.8 | P10: =+#REF!-O10 -> #REF! | Q10: 2125 | R10: 76.899954 | S10: =+Q10*R10 -> 163412.4 | T10: 43979
M11: 14425 | N11: =(+#REF!-M11)+0 -> #REF! | O11: 217.64 | P11: =+#REF!-O11 -> #REF! | Q11: 4000 | R11: 89.649924 | S11: =+Q11*R11 -> 358599.69 | T11: 43981
M12: 13775 | N12: =(+#REF!-M12)+0 -> #REF! | O12: 234.8 | P12: =+#REF!-O12 -> #REF!
M13: 13625 | N13: =(+#REF!-M13)+0 -> #REF! | O13: 187.2 | P13: =+#REF!-O13 -> #REF!
M14: 13475 | N14: =(+#REF!-M14)+0 -> #REF! | O14: 13.5 | P14: =+#REF!-O14 -> #REF!
M15: 13275 | N15: =(+#REF!-M15)+0 -> #REF! | O15: 175.3 | P15: =+#REF!-O15 -> #REF!
M16: 13050 | N16: =(+#REF!-M16)+0 -> #REF! | O16: 241 | P16: =+#REF!-O16 -> #REF!
M17: 12825 | N17: =(+#REF!-M17)+0 -> #REF! | O17: 278.2 | P17: =+#REF!-O17 -> #REF! | Q17: =SUM(Q9:Q15) -> 30875 | R17: =S17/Q17 -> 84.443712 | S17: =SUM(S9:S15) -> 2607199.6
M18: 12625 | N18: =(+#REF!-M18)+0 -> #REF! | O18: 208.2 | P18: =+#REF!-O18 -> #REF! | Q18: =-Y5-Q17 -> #REF! | R18: =+R9 -> 84.25 | S18: =+Q18*R18 -> #REF!
M19: 12350 | N19: =(+#REF!-M19)+0 -> #REF! | O19: 203.8 | P19: =+#REF!-O19 -> #REF! | Q19: =SUM(Q17:Q18) -> #REF! | R19: =S19/Q19 -> #REF! | S19: =SUM(S17:S18) -> #REF!
M20: 12150 | N20: =(+#REF!-M20)+0 -> #REF! | O20: 204.4 | P20: =+#REF!-O20 -> #REF!
M21: 11800 | N21: =(+#REF!-M21)+0 -> #REF! | O21: 235.6 | P21: =+#REF!-O21 -> #REF!
M22: 11525 | N22: =(+#REF!-M22)+0 -> #REF! | O22: 264.82 | P22: =+#REF!-O22 -> #REF!
M23: 11550 | N23: =(+#REF!-M23)+0 -> #REF! | O23: 148.8 | P23: =+#REF!-O23 -> #REF!
M24: 22975 | N24: =(+#REF!-M24)+0 -> #REF! | O24: 154.2 | P24: =+#REF!-O24 -> #REF!
M25: 19725 | N25: =(+#REF!-M25)+0 -> #REF! | O25: 184.1 | P25: =+#REF!-O25 -> #REF!
M26: 19675 | N26: =(+#REF!-M26)+0 -> #REF! | O26: 152.8 | P26: =+#REF!-O26 -> #REF!
M27: 19400 | N27: =(+#REF!-M27)+0 -> #REF! | O27: 273.8 | P27: =+#REF!-O27 -> #REF!
M28: 9125 | N28: =(+#REF!-M28)+0 -> #REF! | O28: 199.54 | P28: =+#REF!-O28 -> #REF!
M29: 18900 | N29: =(+#REF!-M29)+0 -> #REF! | O29: 261.44 | P29: =+#REF!-O29 -> #REF!
M30: 18675 | N30: =(+#REF!-M30)+0 -> #REF! | O30: 206.04 | P30: =+#REF!-O30 -> #REF!
M31: 22125 | N31: =(+#REF!-M31)+0 -> #REF! | O31: 239.2 | P31: =+#REF!-O31 -> #REF!
M32: 22000 | N32: =(+#REF!-M32)+0 -> #REF! | O32: 270.34 | P32: =+#REF!-O32 -> #REF!
B33: =#REF! -> #REF! | C33: =SUM(#REF!) -> #REF! | D33: =SUM(#REF!) -> #REF! | E33: =SUM(#REF!) -> #REF! | F33: =SUM(#REF!) -> #REF! | G33: =SUM(#REF!) -> #REF! | H33: =SUM(#REF!) -> #REF! | I33: =SUM(#REF!) -> #REF! | J33: =SUM(#REF!) -> #REF! | K33: =SUM(#REF!) -> #REF! | L33: =+B33+F33-K33 -> #REF! | O33: =SUM(O3:O32) -> 6003.16 | P33: =SUM(P3:P32) -> #REF!
G34: 0 | H34: 5534.1
G35: =+G33-G34 -> #REF! | H35: =+H33-H34 -> #REF!
C42: 34425 | E42: 0 | J42: 0 | K42: 22625
C43: =+C33-C42 -> #REF! | E43: =+E33-E42 -> #REF! | J43: =+J33-J42 -> #REF! | K43: =+K33-K42 -> #REF!

Sheet HD
M2: 172600 | N2: =(+#REF!-M2)+0 -> #REF! | Q2: 298058.04 | R2: 71.410138 | S2: =+Q2*R2 -> 21284366 | AC2: OP | AD2: 183106.85 | AE2: =+#REF! -> #REF! | AF2: =+AD2-AE2 -> #REF!
M3: 264200 | N3: =+#REF!-M3 -> #REF! | O3: 13650 | P3: =+#REF!-O3 -> #REF! | Q3: 24750 | R3: 70.295 | S3: =+Q3*R3 -> 1739801.2 | T3: 43953 | W3: OP. Stock | X3: =Q2 -> 298058.04 | Y3: =R2 -> 71.410138 | Z3: =X3*Y3 -> 21284366 | AC3: Cons | AD3: -288500 | AE3: =-#REF! -> #REF! | AF3: =+AD3-AE3 -> #REF!
M4: 313475 | N4: =+#REF!-M4 -> #REF! | O4: 11700 | P4: =+#REF!-O4 -> #REF! | Q4: 24750 | R4: 70.295 | S4: =+Q4*R4 -> 1739801.2 | T4: 43953 | W4: Pur | X4: =SUM(Q3:Q68) -> 817000 | Y4: =Z4/X4 -> 63.497343 | Z4: =SUM(S3:S68) -> 51877329 | AC4: Pur | AD4: =503500+413625 -> 917125 | AE4: =+#REF! -> #REF! | AF4: =+AD4-AE4 -> #REF!
M5: 298300 | N5: =+#REF!-M5 -> #REF! | O5: 13275 | P5: =+#REF!-O5 -> #REF! | Q5: 24750 | R5: 70.295 | S5: =+Q5*R5 -> 1739801.2 | T5: 43953 | W5: Less: Closing Stock | X5: =-#REF! -> #REF! | Y5: =R77 -> 65.612455 | Z5: =X5*Y5 -> #REF! | AC5: Sales/Job Out | AD5: =-192767-10200-413625 -> -616592 | AE5: =-#REF!-#REF! -> #REF! | AF5: =+AD5-AE5 -> #REF!
M6: 276300 | N6: =+#REF!-M6 -> #REF! | O6: 11750 | P6: =+#REF!-O6 -> #REF! | Q6: 24750 | R6: 70.295 | S6: =+Q6*R6 -> 1739801.2 | T6: 43953 | W6: Consumption | X6: =SUM(X3:X5) -> #REF! | Y6: =Z6/X6 -> #REF! | Z6: =SUM(Z3:Z5) -> #REF!
M7: 257050 | N7: =+#REF!-M7 -> #REF! | O7: 12075 | P7: =+#REF!-O7 -> #REF! | Q7: 31000 | R7: 60.01 | S7: =+Q7*R7 -> 1860310 | T7: 43953 | AD7: =SUM(AD2:AD6) -> 195139.85 | AE7: =SUM(AE2:AE6) -> #REF! | AF7: =SUM(AF2:AF6) -> #REF!
M8: 266900 | N8: =+#REF!-M8 -> #REF! | O8: 11250 | P8: =+#REF!-O8 -> #REF! | Q8: 30000 | R8: 60.01 | S8: =+Q8*R8 -> 1800300 | T8: 43954
M9: 247825 | N9: =+#REF!-M9 -> #REF! | O9: 10725 | P9: =+#REF!-O9 -> #REF! | Q9: 31000 | R9: 60.01 | S9: =+Q9*R9 -> 1860310 | T9: 43954
M10: 240950 | N10: =+#REF!-M10 -> #REF! | O10: 8500 | P10: =+#REF!-O10 -> #REF! | Q10: 31000 | R10: 66.08 | S10: =+Q10*R10 -> 2048480 | T10: 43958
M11: 218050 | N11: =+#REF!-M11 -> #REF! | O11: 11900 | P11: =+#REF!-O11 -> #REF! | Q11: 31000 | R11: 60.01 | S11: =+Q11*R11 -> 1860310 | T11: 43962
M12: 251725 | N12: =+#REF!-M12 -> #REF! | O12: 8050 | P12: =+#REF!-O12 -> #REF! | Q12: 31000 | R12: 60.01 | S12: =+Q12*R12 -> 1860310 | T12: 43962
M13: 242500 | N13: =+#REF!-M13 -> #REF! | O13: 10575 | P13: =+#REF!-O13 -> #REF! | Q13: 31000 | R13: 66.08 | S13: =+Q13*R13 -> 2048480 | T13: 43964
M14: 287800 | N14: =+#REF!-M14 -> #REF! | O14: 7200 | P14: =+#REF!-O14 -> #REF! | Q14: 31000 | R14: 66.08 | S14: =+Q14*R14 -> 2048480 | T14: 43964
M15: 347600 | N15: =+#REF!-M15 -> #REF! | O15: 8250 | P15: =+#REF!-O15 -> #REF! | Q15: 24750 | R15: 69.05375 | S15: =+Q15*R15 -> 1709080.3 | T15: 43964
M16: 293350 | N16: =+#REF!-M16 -> #REF! | O16: 7175 | P16: =+#REF!-O16 -> #REF! | Q16: 24750 | R16: 69.05375 | S16: =+Q16*R16 -> 1709080.3 | T16: 43964
M17: 290200 | N17: =+#REF!-M17 -> #REF! | O17: 1450 | P17: =+#REF!-O17 -> #REF! | Q17: 24000 | R17: 66.08 | S17: =+Q17*R17 -> 1585920 | T17: 43965
M18: 282650 | N18: =+#REF!-M18 -> #REF! | O18: 7550 | P18: =+#REF!-O18 -> #REF! | Q18: 7000 | R18: 66.08 | S18: =+Q18*R18 -> 462560 | T18: 43965
M19: 273850 | N19: =+#REF!-M19 -> #REF! | O19: 9250 | P19: =+#REF!-O19 -> #REF! | Q19: 31000 | R19: 66.08 | S19: =+Q19*R19 -> 2048480 | T19: 43965
... M32: 195900 | N32: =+#REF!-M32 -> #REF! | O32: 11725 | P32: =+#REF!-O32 -> #REF! | Q32: 24750 | R32: 56.1075 | S32: =+Q32*R32 -> 1388660.6 | T32: 43980
O33: =SUM(O3:O32) -> 288500 | P33: =SUM(P3:P32) -> #REF! | Q33: 24750 | R33: 56.1075 | S33: =+Q33*R33 -> 1388660.6 | T33: 43980
G34: 290117.54 | Q34: 24750 | R34: 56.1075 | S34: =+Q34*R34 -> 1388660.6 | T34: 43981
B35: =+#REF!-B34 -> #REF! | G35: =+#REF!-G34 -> #REF! | L35: =+#REF!-L34 -> #REF! | Q35: 24750 | R35: 56.1075 | S35: =+Q35*R35 -> 1388660.6 | T35: 43981
Q77: =SUM(Q2:Q76) -> 1115058 | R77: =+S77/Q77 -> 65.612455 | S77: =SUM(S2:S76) -> 73161695

Sheet Film
N2: =#REF!-M2 -> #REF! | Q2: 0 | R2: 0 | S2: =+Q2*R2 -> 0
N3: =#REF!-M3 -> #REF! | W3: OP. Stock | X3: =Q2 -> 0 | Y3: =R2 -> 0 | Z3: =X3*Y3 -> 0
N4: =#REF!-M4 -> #REF! | W4: Pur | X4: =SUM(Q3:Q5) -> 0 | Y4: =Z4/X4 -> #DIV/0! | Z4: =SUM(S3:S5) -> 0
N5: =#REF!-M5 -> #REF! | W5: Less: Closing Stock | X5: =-#REF! -> #REF! | Y5: =R12 -> #REF! | Z5: =X5*Y5 -> #REF!
N6: =#REF!-M6 -> #REF! | W6: Consumption | X6: =SUM(X3:X5) -> #REF! | Y6: =Z6/X6 -> #REF! | Z6: =SUM(Z3:Z5) -> #REF!
N7: =#REF!-M7 -> #REF!
N8: =#REF!-M8 -> #REF!
N9: =#REF!-M9 -> #REF!
N10: =#REF!-M10 -> #REF! | Q10: =SUM(Q3:Q7) -> 0 | R10: =R6 -> 0 | S10: =SUM(S3:S7) -> 0
N11: =#REF!-M11 -> #REF! | Q11: =-X5-Q10 -> #REF! | R11: =R2 -> 0 | S11: =+Q11*R11 -> #REF!
N12: =#REF!-M12 -> #REF! | Q12: =SUM(Q10:Q11) -> #REF! | R12: =S12/Q12 -> #REF! | S12: =SUM(S10:S11) -> #REF!
N13: =#REF!-M13 -> #REF!
N14: =#REF!-M14 -> #REF!
N15: =#REF!-M15 -> #REF!
N16: =#REF!-M16 -> #REF!
N17: =#REF!-M17 -> #REF!
N18: =#REF!-M18 -> #REF!
N19: =#REF!-M19 -> #REF!
N20: =#REF!-M20 -> #REF!
N21: =#REF!-M21 -> #REF!
N22: =#REF!-M22 -> #REF!
N23: =#REF!-M23 -> #REF!
N24: =#REF!-M24 -> #REF!
... N32: =#REF!-M32 -> #REF!

Sheet Yarn
Q2: =#REF!-P2 -> #REF! | T2: 20523.2 | U2: 114.84944 | V2: =+T2*U2 -> 2357078
Q3: =#REF!-P3 -> #REF! | T3: 2545.16 | U3: 102.08989 | V3: =+T3*U3 -> 259835.09 | W3: 43956 | Z3: OP. Stock | AA3: =T2 -> 20523.2 | AB3: =U2 -> 114.84944 | AC3: =AA3*AB3 -> 2357078
Q4: =#REF!-P4 -> #REF! | T4: 2395.7 | U4: 108.08988 | V4: =+T4*U4 -> 258950.92 | W4: 43956 | Z4: Pur | AA4: =SUM(T3:T32) -> 51532.16 | AB4: =AC4/AA4 -> 99.38232 | AC4: =SUM(V3:V32) -> 5121385.6
Q5: =#REF!-P5 -> #REF! | T5: 1180.5 | U5: 108.08988 | V5: =+T5*U5 -> 127600.1 | W5: 43956 | Z5: Less: Closing Stock | AA5: =-#REF! -> #REF! | AB5: =U52 -> #REF! | AC5: =AA5*AB5 -> #REF!
Q6: =#REF!-P6 -> #REF! | T6: 2757.8 | U6: 105.08988 | V6: =+T6*U6 -> 289816.88 | W6: 43956 | Z6: Consumption | AA6: =SUM(AA3:AA5) -> #REF! | AB6: =AC6/AA6 -> #REF! | AC6: =SUM(AC3:AC5) -> #REF!
Q7: =#REF!-P7 -> #REF! | T7: 2505.51 | U7: 125.49983 | V7: =+T7*U7 -> 314441.07 | W7: 43956
Q8: =#REF!-P8 -> #REF! | T8: 1097 | U8: 85.069841 | V8: =+T8*U8 -> 93321.615 | W8: 43957
Q9: =#REF!-P9 -> #REF! | T9: 281.4 | U9: 88.069835 | V9: =+T9*U9 -> 24782.852 | W9: 43957
Q10: =#REF!-P10 -> #REF! | T10: 501.4 | U10: 113.2101 | V10: =+T10*U10 -> 56763.544 | W10: 43960
Q11: =#REF!-P11 -> #REF! | T11: 1009.5 | U11: 107.24011 | V11: =+T11*U11 -> 108258.89 | W11: 43961
Q12: =#REF!-P12 -> #REF! | T12: 3999.7 | U12: 104.2401 | V12: =+T12*U12 -> 416929.14 | W12: 43961
Q13: =#REF!-P13 -> #REF! | T13: 103.4 | U13: 110.24011 | V13: =+T13*U13 -> 11398.827 | W13: 43961
Q14: =#REF!-P14 -> #REF! | T14: 867.1 | U14: 107.24011 | V14: =+T14*U14 -> 92987.897 | W14: 43961
Q15: =#REF!-P15 -> #REF! | T15: 306.1 | U15: 107.24011 | V15: =+T15*U15 -> 32826.197 | W15: 43961
Q16: =#REF!-P16 -> #REF! | T16: 11520 | U16: 90.506 | V16: =+T16*U16 -> 1042629.1 | W16: 43965
Q17: =#REF!-P17 -> #REF! | T17: 644.3 | U17: 85.07001 | V17: =+T17*U17 -> 54810.608 | W17: 43965
Q18: =#REF!-P18 -> #REF! | T18: 578 | U18: 88.070011 | V18: =+T18*U18 -> 50904.466 | W18: 43965
... Q32: =#REF!-P32 -> #REF! | T32: 1706.7 | U32: 85.069981 | V32: =+T32*U32 -> 145188.94 | W32: 43974
T33: 201 | U33: 184.99977 | V33: =+T33*U33 -> 37184.953 | W33: 43974
J34: 15166.6 | T34: 231.1 | U34: 88.069921 | V34: =+T34*U34 -> 20352.959 | W34: 43974
D35: =+#REF!-D34 -> #REF! | E35: =+#REF!-E34 -> #REF! | H35: =+#REF!-H34 -> #REF! | I35: =+#REF!-I34 -> #REF! | J35: =+#REF!-J34 -> #REF! | K35: =#REF!-K34 -> #REF! | O35: 20523.2 | T35: 517.6 | U35: 85.069923 | V35: =+T35*U35 -> 44032.192 | W35: 43974
O36: =+#REF!-O35 -> #REF! | T36: 787.3 | U36: 105.31988 | V36: =+T36*U36 -> 82918.345 | W36: 43975
T37: 2037.1 | U37: 111.31988 | V37: =+T37*U37 -> 226769.72 | W37: 43975
T38: 2978.4 | U38: 108.31988 | V38: =+T38*U38 -> 322619.93 | W38: 43975
T39: 764.3 | U39: 88.070061 | V39: =+T39*U39 -> 67311.948 | W39: 43975
T40: 7253.2 | U40: 105.32002 | V40: =+T40*U40 -> 763907.14 | W40: 43977
T41: 423.3 | U41: 108.32002 | V41: =+T41*U41 -> 45851.863 | W41: 43977
T42: 1751 | U42: 85.070044 | V42: =+T42*U42 -> 148957.65 | W42: 43977
T43: 494.8 | U43: 88.070046 | V43: =+T43*U43 -> 43577.059 | W43: 43977
T44: 6423.8 | U44: 105.32006 | V44: =+T44*U44 -> 676555 | W44: 43979
T45: 507 | U45: 122.12995 | V45: =+T45*U45 -> 61919.887 | W45: 43979
T46: 639.16 | U46: 126.49975 | V46: =+T46*U46 -> 80853.579 | W46: 43980
T47: 519.8 | U47: 85.069935 | V47: =+T47*U47 -> 44219.352 | W47: 43981
T48: 429.5 | U48: 88.069933 | V48: =+T48*U48 -> 37826.036 | W48: 43981
T50: =SUM(T17:T49) -> 46420.25 | U50: =V50/T50 -> 101.15631 | V50: =SUM(V17:V49) -> 4695701.1
T51: =-AA5-T50 -> #REF! | U51: =U16 -> 90.506 | V51: =+T51*U51 -> #REF!
T52: =SUM(T50:T51) -> #REF! | U52: =V52/T52 -> #REF! | V52: =SUM(V50:V51) -> #REF!

Sheet Lam Fabric
Q2: =#REF!-P2 -> #REF! | S2: 55175.3 | T2: 93.410138 | U2: =+S2*T2 -> 5153932.4 | Y2: OP. Stock | Z2: =S2 -> 55175.3 | AA2: =T2 -> 93.410138 | AB2: =Z2*AA2 -> 5153932.4
Q3: =#REF!-P3 -> #REF! | Y3: Pur | Z3: =SUM(S3:S6) -> 0 | AA3: =AB3/Z3 -> #DIV/0! | AB3: =SUM(U3:U6) -> 0
Q4: =#REF!-P4 -> #REF! | Y4: Production | Z4: =#REF!+#REF!-#REF! -> #REF! | AA4: 78.105943 | AB4: =Z4*AA4 -> #REF!
Q5: =#REF!-P5 -> #REF! | Y5: Less: Closing Stock | Z5: =-#REF! -> #REF! | AA5: =AA4 -> 78.105943 | AB5: =Z5*AA5 -> #REF!
Q6: =#REF!-P6 -> #REF! | Y6: Consumption | Z6: =SUM(Z2:Z5) -> #REF! | AA6: =AB6/Z6 -> #REF! | AB6: =SUM(AB2:AB5) -> #REF!
Q7: =#REF!-P7 -> #REF!
Q8: =#REF!-P8 -> #REF!
Q9: =#REF!-P9 -> #REF!
Q10: =#REF!-P10 -> #REF!
Q11: =#REF!-P11 -> #REF!
Q12: =#REF!-P12 -> #REF!
Q13: =#REF!-P13 -> #REF!
Q14: =#REF!-P14 -> #REF!
Q15: =#REF!-P15 -> #REF!
Q16: =#REF!-P16 -> #REF! | S16: =SUM(S3:S14) -> 0 | T16: =U16/S16 -> #DIV/0! | U16: =SUM(U3:U14) -> 0
Q17: =#REF!-P17 -> #REF!
Q18: =#REF!-P18 -> #REF!
Q19: =#REF!-P19 -> #REF!
Q20: =#REF!-P20 -> #REF!
Q21: =#REF!-P21 -> #REF!
Q22: =#REF!-P22 -> #REF!
Q23: =#REF!-P23 -> #REF!
Q24: =#REF!-P24 -> #REF!
Q25: =#REF!-P25 -> #REF!
Q26: =#REF!-P26 -> #REF!
Q27: =#REF!-P27 -> #REF!
Q28: =#REF!-P28 -> #REF!
... Q32: =#REF!-P32 -> #REF!
D34: 130741
D35: =#REF!-D34 -> #REF! | H35: =+#REF!-H34 -> #REF! | I35: =+#REF!-I34 -> #REF! | O35: 55175.3
O36: =+O35-#REF! -> #REF!

Sheet Wastage
Z2: =#REF!-Y2 -> #REF! | AB2: 15079 | AC2: 15 | AD2: =+AB2*AC2 -> 226185 | AF2: =SUM(#REF!) -> #REF! | AH2: OP. Stock | AI2: =AB2 -> 15079 | AJ2: =AC2 -> 15 | AK2: =AI2*AJ2 -> 226185 | AN2: =SUM(#REF!) -> #REF! | AO2: =SUM(#REF!) -> #REF!
Z3: =#REF!-Y3 -> #REF! | AF3: =SUM(#REF!) -> #REF! | AH3: Pur | AI3: =SUM(AB3:AB6) -> 0 | AJ3: =AK3/AI3 -> #DIV/0! | AK3: =SUM(AD3:AD6) -> 0 | AN3: =SUM(#REF!) -> #REF! | AO3: =SUM(#REF!) -> #REF!
Z4: =#REF!-Y4 -> #REF! | AF4: =SUM(#REF!) -> #REF! | AH4: Less: Closing Stock | AI4: =-#REF! -> #REF! | AJ4: 15 | AK4: =AI4*AJ4 -> #REF! | AN4: =SUM(#REF!) -> #REF! | AO4: =SUM(#REF!) -> #REF!
Z5: =#REF!-Y5 -> #REF! | AF5: =SUM(#REF!) -> #REF! | AH5: Consumption | AI5: =SUM(AI2:AI4) -> #REF! | AJ5: =AK5/AI5 -> #REF! | AK5: =SUM(AK2:AK4) -> #REF! | AN5: =SUM(#REF!) -> #REF! | AO5: =SUM(#REF!) -> #REF!
Z6: =#REF!-Y6 -> #REF! | AF6: =SUM(#REF!) -> #REF! | AN6: =SUM(#REF!) -> #REF! | AO6: =SUM(#REF!) -> #REF!
Z7: =#REF!-Y7 -> #REF! | AF7: =SUM(#REF!) -> #REF! | AN7: =SUM(#REF!) -> #REF! | AO7: =SUM(#REF!) -> #REF!
Z8: =#REF!-Y8 -> #REF! | AF8: =SUM(#REF!) -> #REF! | AN8: =SUM(#REF!) -> #REF! | AO8: =SUM(#REF!) -> #REF!
Z9: =#REF!-Y9 -> #REF! | AF9: =SUM(#REF!) -> #REF! | AN9: =SUM(#REF!) -> #REF! | AO9: =SUM(#REF!) -> #REF!
Z10: =#REF!-Y10 -> #REF! | AF10: =SUM(#REF!) -> #REF! | AN10: =SUM(#REF!) -> #REF! | AO10: =SUM(#REF!) -> #REF!
Z11: =#REF!-Y11 -> #REF! | AF11: =SUM(#REF!) -> #REF! | AN11: =SUM(#REF!) -> #REF! | AO11: =SUM(#REF!) -> #REF!
Z12: =#REF!-Y12 -> #REF! | AF12: =SUM(#REF!) -> #REF! | AN12: =SUM(#REF!) -> #REF! | AO12: =SUM(#REF!) -> #REF!
Z13: =#REF!-Y13 -> #REF! | AF13: =SUM(#REF!) -> #REF! | AN13: =SUM(#REF!) -> #REF! | AO13: =SUM(#REF!) -> #REF!
Z14: =#REF!-Y14 -> #REF! | AF14: =SUM(#REF!) -> #REF! | AN14: =SUM(#REF!) -> #REF! | AO14: =SUM(#REF!) -> #REF!
Z15: =#REF!-Y15 -> #REF! | AF15: =SUM(#REF!) -> #REF! | AN15: =SUM(#REF!) -> #REF! | AO15: =SUM(#REF!) -> #REF!
Z16: =#REF!-Y16 -> #REF! | AF16: =SUM(#REF!) -> #REF! | AN16: =SUM(#REF!) -> #REF! | AO16: =SUM(#REF!) -> #REF!
Z17: =#REF!-Y17 -> #REF! | AF17: =SUM(#REF!) -> #REF! | AN17: =SUM(#REF!) -> #REF! | AO17: =SUM(#REF!) -> #REF!
... Z20: =#REF!-Y20 -> #REF! | AF20: =SUM(#REF!) -> #REF! | AN20: =SUM(#REF!) -> #REF! | AO20: =SUM(#REF!) -> #REF!
Z21: =#REF!-Y21 -> #REF! | AB21: =SUM(AB3:AB20) -> 0 | AC21: =AD21/AB21 -> #DIV/0! | AD21: =SUM(AD3:AD20) -> 0 | AF21: =SUM(#REF!) -> #REF! | AN21: =SUM(#REF!) -> #REF!
Z22: =#REF!-Y22 -> #REF! | AF22: =SUM(#REF!) -> #REF! | AN22: =SUM(#REF!) -> #REF!
Z23: =#REF!-Y23 -> #REF! | AF23: =SUM(#REF!) -> #REF! | AN23: =SUM(#REF!) -> #REF!
Z24: =#REF!-Y24 -> #REF! | AF24: =SUM(#REF!) -> #REF! | AN24: =SUM(#REF!) -> #REF!
Z25: =#REF!-Y25 -> #REF! | AF25: =SUM(#REF!) -> #REF! | AN25: =SUM(#REF!) -> #REF!
Z26: =#REF!-Y26 -> #REF! | AF26: =SUM(#REF!) -> #REF! | AN26: =SUM(#REF!) -> #REF!
Z27: =#REF!-Y27 -> #REF! | AF27: =SUM(#REF!) -> #REF! | AN27: =SUM(#REF!) -> #REF!
Z28: =#REF!-Y28 -> #REF! | AF28: =SUM(#REF!) -> #REF! | AN28: =SUM(#REF!) -> #REF!
Z29: =#REF!-Y29 -> #REF! | AF29: =SUM(#REF!) -> #REF! | AN29: =SUM(#REF!) -> #REF!
Z30: =#REF!-Y30 -> #REF! | AF30: =SUM(#REF!) -> #REF! | AN30: =SUM(#REF!) -> #REF!
Z31: =#REF!-Y31 -> #REF! | AF31: =SUM(#REF!) -> #REF! | AN31: =SUM(#REF!) -> #REF!
Z32: =#REF!-Y32 -> #REF!
D34: 10476 | E34: 11604 | F34: 5677 | G34: 2204 | M34: 53758 | N34: 130 | P34: 3835 | S34: 107935
D35: =+#REF!-D34 -> #REF! | E35: =+#REF!-E34 -> #REF! | F35: =+#REF!-F34 -> #REF! | G35: =+#REF!-G34 -> #REF! | I35: =+#REF!-I34 -> #REF! | J35: =+#REF!-J34 -> #REF! | K35: =+#REF!-K34 -> #REF! | L35: =+#REF!-L34 -> #REF! | M35: =+#REF!-M34 -> #REF! | N35: =+#REF!-N34 -> #REF! | O35: =+#REF!-O34 -> #REF! | P35: =+#REF!-P34 -> #REF! | S35: =+#REF!-S34 -> #REF! | X35: 15079
X36: =+X35-#REF! -> #REF!
D41: 6027 | E41: 6610 | F41: 3618 | G41: 1203
D42: =+#REF!-D41 -> #REF! | E42: =+#REF!-E41 -> #REF! | F42: =+#REF!-F41 -> #REF! | G42: =+#REF!-G41 -> #REF!

Sheet Tape
O2: =#REF!-N2 -> #REF! | Q2: 106148.81 | R2: 81.410138 | S2: =+Q2*R2 -> 8641589.3 | V2: OP. Stock | W2: =Q2 -> 106148.81 | X2: =R2 -> 81.410138 | Y2: =W2*X2 -> 8641589.3
O3: =#REF!-N3 -> #REF! | V3: Pur | W3: 0 | X3: =Y3/W3 -> #DIV/0! | Y3: 0
O4: =#REF!-N4 -> #REF! | V4: Production | W4: =#REF! -> #REF! | X4: 70.240414 | Y4: =W4*X4 -> #REF!
O5: =#REF!-N5 -> #REF! | V5: Less: Closing Stock | W5: =-#REF! -> #REF! | X5: =X4 -> 70.240414 | Y5: =W5*X5 -> #REF!
O6: =#REF!-N6 -> #REF! | V6: Consumption | W6: =SUM(W2:W5) -> #REF! | X6: =Y6/W6 -> #REF! | Y6: =SUM(Y2:Y5) -> #REF!
O7: =#REF!-N7 -> #REF!
O8: =#REF!-N8 -> #REF!
O9: =#REF!-N9 -> #REF! | Q9: =SUM(Q3:Q7) -> 0 | R9: =S9/Q9 -> #DIV/0! | S9: =SUM(S3:S7) -> 0
O10: =#REF!-N10 -> #REF!
O11: =#REF!-N11 -> #REF!
O12: =#REF!-N12 -> #REF!
O13: =#REF!-N13 -> #REF!
O14: =#REF!-N14 -> #REF!
O15: =#REF!-N15 -> #REF!
O16: =#REF!-N16 -> #REF!
O17: =#REF!-N17 -> #REF!
O18: =#REF!-N18 -> #REF!
O19: =#REF!-N19 -> #REF!
O20: =#REF!-N20 -> #REF!
O21: =#REF!-N21 -> #REF!
... O32: =#REF!-N32 -> #REF!
D34: 422813.54 | G34: 359691.5 | H34: 61020
D35: =+#REF!-D34 -> #REF! | G35: =+#REF!-G34 -> #REF! | H35: =+#REF!-H34 -> #REF! | I35: =+#REF!-I34 -> #REF! | M35: 106148.81
M36: =+M35-#REF! -> #REF!

Sheet Unlaminated Fabric
Q2: =#REF!-P2 -> #REF! | S2: 297806.5 | T2: 91.410138 | U2: =+S2*T2 -> 27222533
Q3: =#REF!-P3 -> #REF! | S3: 284.02 | T3: =+U3/S3 -> 250.71009 | U3: 71206.68 | X3: OP. Stock | Y3: =S2 -> 297806.5 | Z3: =T2 -> 91.410138 | AA3: =Y3*Z3 -> 27222533
Q4: =#REF!-P4 -> #REF! | S4: 2505.6 | T4: 103.06995 | U4: =+S4*T4 -> 258252.08 | X4: Pur | Y4: =SUM(S3:S4) -> 2789.62 | Z4: =AA4/Y4 -> 118.10166 | AA4: =SUM(U3:U4) -> 329458.76
Q5: =#REF!-P5 -> #REF! | S5: 350.3 | T5: 95.069958 | U5: =+S5*T5 -> 33303.006 | X5: Production | Y5: =#REF!+#REF!-#REF! -> #REF! | Z5: 72.983409 | AA5: =Y5*Z5 -> #REF!
Q6: =#REF!-P6 -> #REF! | S6: 8012.1 | T6: 87.049962 | U6: =+S6*T6 -> 697453 | X6: Less: Closing Stock | Y6: =-#REF! -> #REF! | Z6: =Z5 -> 72.983409 | AA6: =Y6*Z6 -> #REF!
Q7: =#REF!-P7 -> #REF! | S7: 408.5 | T7: 102.22814 | U7: =+S7*T7 -> 41760.194 | X7: Consumption | Y7: =SUM(Y3:Y6) -> #REF! | Z7: =AA7/Y7 -> #REF! | AA7: =SUM(AA3:AA6) -> #REF! | AD7: =1405.27+314.43 -> 1719.7
Q8: =#REF!-P8 -> #REF! | S8: 310 | T8: 97.21013 | U8: =+S8*T8 -> 30135.14
Q9: =#REF!-P9 -> #REF! | S9: 3241 | T9: 103.59012 | U9: =+S9*T9 -> 335735.59 | AD9: 1465.62
Q10: =#REF!-P10 -> #REF! | S10: 2453.9 | T10: 95.070084 | U10: =+S10*T10 -> 233292.48
Q11: =#REF!-P11 -> #REF! | S11: 1200.9 | T11: 103.07009 | U11: =+S11*T11 -> 123776.87
Q12: =#REF!-P12 -> #REF! | S12: 316 | T12: 87.050487 | U12: =+S12*T12 -> 27507.954
Q13: =#REF!-P13 -> #REF! | S13: 2979.2 | T13: 95.070064 | U13: =+S13*T13 -> 283232.74
Q14: =#REF!-P14 -> #REF! | S14: 1030.6 | T14: 103.07007 | U14: =+S14*T14 -> 106224.01
Q15: =#REF!-P15 -> #REF! | S15: 833 | T15: 95.070012 | U15: =+S15*T15 -> 79193.32 | V15: 43965
Q16: =#REF!-P16 -> #REF! | S16: 356.2 | T16: 103.07001 | U16: =+S16*T16 -> 36713.538 | V16: 43965
Q17: =#REF!-P17 -> #REF! | S17: 7592.3 | T17: 129.14002 | U17: =+S17*T17 -> 980469.78 | V17: 43967
Q18: =#REF!-P18 -> #REF! | S18: 10475.2 | T18: 129.88002 | U18: =+S18*T18 -> 1360519.2 | V18: 43967
Q19: =#REF!-P19 -> #REF! | S19: 1612.4 | T19: 95.059886 | U19: =+S19*T19 -> 153274.56 | V19: 43968
Q20: =#REF!-P20 -> #REF! | S20: 823.9 | T20: 103.05988 | U20: =+S20*T20 -> 84911.032 | V20: 43968
Q21: =#REF!-P21 -> #REF! | S21: 5105.2 | T21: 103.07005 | U21: =+S21*T21 -> 526193.21 | V21: 43969
Q22: =#REF!-P22 -> #REF! | S22: 3090.3 | T22: 95.069979 | U22: =+S22*T22 -> 293794.76 | V22: 43974
Q23: =#REF!-P23 -> #REF! | S23: 722.2 | T23: 103.06998 | U23: =+S23*T23 -> 74437.138 | V23: 43974
Q24: =#REF!-P24 -> #REF! | S24: 1857 | T24: 89.119887 | U24: =+S24*T24 -> 165495.63 | V24: 43974
Q25: =#REF!-P25 -> #REF! | S25: 3613.8 | T25: 110 | U25: =+S25*T25 -> 397518 | V25: 43977
Q26: =#REF!-P26 -> #REF! | S26: 2238.5 | T26: 95.07005 | U26: =+S26*T26 -> 212814.31 | V26: 43977
Q27: =#REF!-P27 -> #REF! | S27: 683.6 | T27: 103.07005 | U27: =+S27*T27 -> 70458.689 | V27: 43977
Q28: =#REF!-P28 -> #REF!
Q29: =#REF!-P29 -> #REF!
Q30: =#REF!-P30 -> #REF!
Q31: =#REF!-P31 -> #REF!
Q32: =#REF!-P32 -> #REF!
D34: 348087.5 | J34: 20729 | K34: 110635.3
D35: =+#REF!-D34 -> #REF! | H35: =+#REF!-H34 -> #REF! | J35: =+#REF!-J34 -> #REF! | K35: =+#REF!-K34 -> #REF! | O35: 297806.5
O36: =+O35-#REF! -> #REF!
S64: 1405.27 | T64: =+U64/S64 -> 233.44978 | U64: 328059.97 | V64: 43896
S65: 314.43 | T65: =+U65/S65 -> 237.67866 | U65: 74733.3 | V65: 43896
S66: 814.98 | T66: =+U66/S66 -> 234.36391 | U66: 191001.9 | V66: 43898
S67: 650.64 | T67: =+U67/S67 -> 242.7222 | U67: 157924.77 | V67: 43898 | W67: =SUM(U64:U67)/SUM(S64:S67) -> 235.99511
S68: 683.95 | T68: =+U68/S68 -> 243.87191 | U68: 166796.19 | V68: 43904 | W68: =SUM(S64:S67) -> 3185.32
S69: 678.77 | T69: =+U69/S69 -> 248.03688 | U69: 168359.99 | V69: 43904
S70: 508.64 | T70: =+U70/S70 -> 239.35536 | U70: 121745.71 | V70: 43909
S71: 800.76 | T71: =+U71/S71 -> 240.65472 | U71: 192706.67 | V71: 43909
S74: =SUM(S64:S73) -> 5857.44 | U74: =SUM(U64:U73) -> 1401328.5

Sheet Tape (2)
A2: =C2/$C$10 -> #REF! | B2: PP | C2: =#REF! -> #REF! | D2: =#REF! -> #REF! | E2: =+C2*D2 -> #REF!
A3: =C3/$C$10 -> #REF! | B3: Filler | C3: =#REF! -> #REF! | D3: =FillerSoltex!Y6 -> #REF! | E3: =+C3*D3 -> #REF!
A4: =C4/$C$10 -> #REF! | B4: MB | C4: =#REF! -> #REF! | D4: =MB!Y6 -> #REF! | E4: =+C4*D4 -> #REF!
A5: =C5/$C$10 -> #REF! | B5: UV | C5: =#REF! -> #REF! | D5: =UV!Y6 -> #REF! | E5: =+C5*D5 -> #REF!
A6: =C6/$C$10 -> #REF! | B6: HDPE | C6: =#REF! -> #REF! | D6: =#REF! -> #REF! | E6: =+C6*D6 -> #REF!
A7: =C7/$C$10 -> #REF! | B7: LLDPE | C7: =#REF! -> #REF! | D7: =#REF! -> #REF! | E7: =+C7*D7 -> #REF!
A8: =C8/$C$10 -> #REF! | B8: RP | C8: =#REF! -> #REF! | D8: 42 | E8: =+C8*D8 -> #REF!
C10: =SUM(C2:C9) -> #REF! | D10: =+E10/C10 -> #REF! | E10: =SUM(E2:E9) -> #REF!
B11: Less : Westage | C11: =#REF! -> #REF! | D11: 0 | E11: =+C11*D11 -> #REF!
B12: Tape Production | C12: =+C10-C11 -> #REF! | D12: =+E12/C12 -> #REF! | E12: =+E10-E11 -> #REF!
B14: Power | C14: =SUMIF(#REF!,"Tape Plant",#REF!)+SUMIF(#REF!,"Utility",#REF!) -> #REF! | D14: 7.75 | E14: =+C14*D14 -> #REF!
B15: Labour | E15: =#REF!+#REF! -> #REF!
B17: Total Cost | C17: =+C12 -> #REF! | D17: =+E17/C17 -> #REF! | E17: =+E12+E14+E15 -> #REF!
D18: =#REF! -> #REF!
D19: =+D18-D17 -> #REF!
B26: PP | C26: =C2 -> #REF! | D26: =D2 -> #REF! | E26: =C26*D26 -> #REF!
B27: Filler | C27: =C3 -> #REF! | D27: =D3 -> #REF! | E27: =C27*D27 -> #REF!
B28: MB | C28: =C4 -> #REF! | D28: =D4 -> #REF! | E28: =C28*D28 -> #REF!
B29: UV | C29: =C5 -> #REF! | D29: =D5 -> #REF! | E29: =C29*D29 -> #REF!
B30: HDPE | C30: =C6 -> #REF! | D30: =D6 -> #REF! | E30: =C30*D30 -> #REF!
B31: LLDPE | C31: =C7 -> #REF! | D31: =D7 -> #REF! | E31: =C31*D31 -> #REF!
B32: RP | C32: =C8 -> #REF! | D32: =D8 -> 42 | E32: =C32*D32 -> #REF!
B33: Yarn | C33: =20508+18614.9-15122.24 -> 24000.66 | D33: =Yarn!AB6 -> #REF! | E33: =C33*D33 -> #REF!
B34: PP | C34: 34032.8 | D34: =#REF! -> #REF! | E34: =C34*D34 -> #REF!
B35: LDPE | C35: 6689.6 | D35: =LLDP!Z6 -> #REF! | E35: =C35*D35 -> #REF!
B36: MB | C36: 262 | D36: =D28 -> #REF! | E36: =C36*D36 -> #REF!
B37: Filler | C37: 325 | D37: =D27 -> #REF! | E37: =C37*D37 -> #REF!
C45: =SUM(C26:C44) -> #REF! | D45: =E45/C45 -> #REF! | E45: =SUM(E26:E44) -> #REF!
C46: 562614.08
C47: =C46-C45 -> #REF!

Sheet Fabric
B2: Tape | C2: =#REF! -> #REF! | D2: ='Tape (2)'!D17 -> #REF! | E2: =+C2*D2 -> #REF!
C8: =SUM(C2:C7) -> #REF! | D8: =+E8/C8 -> #REF! | E8: =SUM(E2:E7) -> #REF!
B9: Less : Westage | C9: =#REF! -> #REF! | D9: 0 | E9: =+C9*D9 -> #REF!
B10: Tape Production | C10: =+C8-C9 -> #REF! | D10: =+E10/C10 -> #REF! | E10: =+E8-E9 -> #REF!
B12: Power | C12: =SUMIF(#REF!,"Loom",#REF!) -> #REF! | D12: 7.75 | E12: =+C12*D12 -> #REF!
B13: Labour | E13: =#REF! -> #REF!
B15: Total Cost | C15: =+C10 -> #REF! | D15: =+E15/C15 -> #REF! | E15: =+E10+E12+E13 -> #REF!
D16: =#REF! -> #REF!
D17: =+D16-D15 -> #REF!

Sheet Webbing (2)
B2: Yarn | C2: =#REF! -> #REF! | D2: =Yarn!AB6 -> #REF! | E2: =+C2*D2 -> #REF!
B3: Tape | C3: =#REF! -> #REF! | D3: ='Tape (2)'!D17 -> #REF! | E3: =+C3*D3 -> #REF!
C10: =SUM(C2:C9) -> #REF! | D10: =+E10/C10 -> #REF! | E10: =SUM(E2:E9) -> #REF!
B11: Less : Westage | C11: =#REF! -> #REF! | D11: 0 | E11: =+C11*D11 -> #REF!
B12: Tape Production | C12: =+C10-C11 -> #REF! | D12: =+E12/C12 -> #REF! | E12: =+E10-E11 -> #REF!
B14: Power | C14: 0 | D14: 7.75 | E14: =+C14*D14 -> 0
B15: Labour | E15: =#REF! -> #REF!
B17: Total Cost | C17: =+C12 -> #REF! | D17: =+E17/C17 -> #REF! | E17: =+E12+E14+E15 -> #REF!
D18: =#REF! -> #REF!
D19: =+D18-D17 -> #REF!

Sheet FIBC (2)
B2: Fabric | C2: =#REF! -> #REF! | D2: =Fabric!D15 -> #REF! | E2: =+C2*D2 -> #REF!
B3: Laminated Fabric | C3: =#REF! -> #REF! | D3: =D2 -> #REF! | E3: =+C3*D3 -> #REF!
B4: Liner | C4: =#REF! -> #REF! | D4: 0 | E4: =+C4*D4 -> #REF!
B5: Webbing | C5: =#REF! -> #REF! | D5: ='Webbing (2)'!D17 -> #REF! | E5: =+C5*D5 -> #REF!
B6: Yarn | C6: =#REF! -> #REF! | D6: =Yarn!AB6 -> #REF! | E6: =+C6*D6 -> #REF!
B7: Others | C7: =#REF! -> #REF! | D7: =D2 -> #REF! | E7: =+C7*D7 -> #REF!
B8: Ink | C8: =#REF! -> #REF! | E8: =+C8*D8 -> #REF!
B9: Thinner | C9: =#REF! -> #REF! | E9: =+C9*D9 -> #REF!
C13: =SUM(C2:C12) -> #REF! | D13: =+E13/C13 -> #REF! | E13: =SUM(E2:E12) -> #REF!
B14: Less : Westage | C14: =#REF! -> #REF! | D14: 0 | E14: =+C14*D14 -> #REF!
B15: Bag Production | C15: =+C13-C14 -> #REF! | D15: =+E15/C15 -> #REF! | E15: =+E13-E14 -> #REF!
B17: Power | C17: =SUMIF(#REF!,"FIBC",#REF!) -> #REF! | D17: 7.75 | E17: =+C17*D17 -> #REF!
B18: Labour | E18: =#REF! -> #REF!
B20: Total Cost | C20: =+C15 -> #REF! | D20: =+E20/C20 -> #REF! | E20: =+E15+E17+E18 -> #REF!
D21: =#REF! -> #REF!
D22: =+D21-D20 -> #REF!

Sheet Laminated Fabric
B2: Fabric | C2: 192702.9 | D2: =Fabric!D15 -> #REF! | E2: =+C2*D2 -> #REF!
B3: PP | C3: 34294.79 | D3: 83.928805 | E3: =+C3*D3 -> 2878320.7
B4: LDPE | C4: 7124.51 | D4: 94 | E4: =+C4*D4 -> 669703.94
B5: MB | C5: 175 | D5: 163 | E5: =+C5*D5 -> 28525
B6: Filler | C6: 204.8 | D6: 29.720197 | E6: =+C6*D6 -> 6086.6964
C8: =SUM(C2:C7) -> 234502 | D8: =+E8/C8 -> #REF! | E8: =SUM(E2:E7) -> #REF!
B9: Less : Westage | C9: 8113 | D9: 0 | E9: =+C9*D9 -> 0
B10: Tape Production | C10: =+C8-C9 -> 226389 | D10: =+E10/C10 -> #REF! | E10: =+E8-E9 -> #REF!
B12: Power | C12: =SUMIF(#REF!,"Lamination",#REF!) -> #REF! | D12: 7.75 | E12: =+C12*D12 -> #REF!
B13: Labour | E13: =#REF! -> #REF!
B15: Total Cost | C15: =+C10 -> 226389 | D15: =+E15/C15 -> #REF! | E15: =+E10+E12+E13 -> #REF!
D16: 114
D17: =+D16-D15 -> #REF!

Sheet RP (2)
B2: Wastage | C2: 183024.5 | D2: 15 | E2: =+C2*D2 -> 2745367.5
C10: =SUM(C2:C9) -> 183024.5 | D10: =+E10/C10 -> 15 | E10: =SUM(E2:E9) -> 2745367.5
B11: Less : Westage | D11: 0 | E11: =+C11*D11 -> 0
B12: Tape Production | C12: =+C10-C11 -> 183024.5 | D12: =+E12/C12 -> 15 | E12: =+E10-E11 -> 2745367.5
B14: Power | C14: =SUMIF(#REF!,"RP PLANT",#REF!) -> #REF! | D14: 7.75 | E14: =+C14*D14 -> #REF!
B15: Labour | E15: =#REF! -> #REF!
B17: Total Cost | C17: =+C12 -> 183024.5 | D17: =+E17/C17 -> #REF! | E17: =+E12+E14+E15 -> #REF!
D18: 42
D19: =+D18-D17 -> #REF!

Sheet Yarn (2)
B2: Tape | D2: 93 | E2: =+C2*D2 -> 0
C10: =SUM(C2:C9) -> 0 | D10: =+E10/C10 -> #DIV/0! | E10: =SUM(E2:E9) -> 0
B11: Less : Westage | D11: 0 | E11: =+C11*D11 -> 0
B12: Tape Production | C12: =+C10-C11 -> 0 | D12: =+E12/C12 -> #DIV/0! | E12: =+E10-E11 -> 0
B14: Power | D14: 7.75 | E14: =+C14*D14 -> 0
B15: Labour | E15: 3010
B17: Total Cost | C17: =+C12 -> 0 | D17: =+E17/C17 -> #DIV/0! | E17: =+E12+E14+E15 -> 3010
D18: 122
D19: =+D18-D17 -> #DIV/0!
