Workbook

Sheet ERP Data
C1: 1 | D1: 2 | E1: 3 | F1: 4 | G1: 5 | H1: 6 | I1: 7 | J1: 8 | K1: 9 | L1: 10 | M1: 11 | N1: 12 | O1: 13 | P1: 14 | Q1: 15 | R1: 16 | S1: 17 | T1: 18 | U1: 19 | V1: 20 | W1: 21 | X1: 22 | Y1: 23 | Z1: 24 | AA1: 25
A2: CompanyName | B2: MainGroup | C2: SubGroupName | D2: Op.Factory Owned | E2: Op.Factory JW (Others) | F2: Op.At JW (Own) | G2: Branch Tfr Recd | H2: Purchase | I2: Warehouse Inwards | J2: Recd from JW (Own) | K2: Recd For JW (Others) | L2: Sales | M2: Br Transfer Sent | N2: Sent for JW (Own) | O2: Return JW(Others) | P2: Total Production Own+JW | Q2: Total Consumption Own+JW | R2: Production at JW | S2: Consumption At JW | T2: Production Of JW | U2: Consumption Of JW | V2: Stock Adjustment Entry | W2: Net Production Own | X2: Net Consumption Own | Y2: Cl.Factory Owned | Z2: Cl.Factory JW (Others) | AA2: Cl.At JW (Own)
A3: K.P. WOVEN PRIVATE LIMITED | B3: RM | C3: FIBC Accessories | D3: 13723.2 | E3: 0 | F3: 0 | G3: 0 | H3: 1699.3 | I3: 0 | J3: 0 | K3: 0 | L3: 203.5 | M3: 0 | N3: 0 | O3: 0 | P3: 0 | Q3: 0 | R3: 0 | S3: 0 | T3: 0 | U3: 0 | V3: 0 | W3: 0 | X3: 0 | Y3: 15219 | Z3: 0 | AA3: 0
A4: K.P. WOVEN PRIVATE LIMITED | B4: RM | C4: Filler | D4: 9644.448 | E4: 0 | F4: 35 | G4: 0 | H4: 30000 | I4: 0 | J4: 0 | K4: 0 | L4: 0 | M4: 0 | N4: 140 | O4: 0 | P4: 0 | Q4: 16902.86 | R4: 0 | S4: 121.17 | T4: 0 | U4: 0 | V4: 0 | W4: 0 | X4: 16902.86 | Y4: 22601.588 | Z4: 0 | AA4: 53.83
A5: K.P. WOVEN PRIVATE LIMITED | B5: RM | C5: LDPE Granules | D5: -25907.87 | E5: 100500 | F5: 18 | G5: 0 | H5: 0 | I5: 0 | J5: 0 | K5: 0 | L5: 0 | M5: 0 | N5: 0 | O5: 0 | P5: 0 | Q5: 8480.8 | R5: 0 | S5: 0 | T5: 0 | U5: 1924.4 | V5: 0 | W5: 0 | X5: 6556.4 | Y5: -32464.27 | Z5: 98575.6 | AA5: 18
A6: K.P. WOVEN PRIVATE LIMITED | B6: RM | C6: LLDPE Granules | D6: 6669.387 | E6: 87401.23 | F6: 2666.8 | G6: 0 | H6: 33000 | I6: 0 | J6: 0 | K6: 0 | L6: 0 | M6: 0 | N6: 0 | O6: 0 | P6: 0 | Q6: 19671.74 | R6: 0 | S6: 0 | T6: 0 | U6: 0 | V6: 0 | W6: 0 | X6: 19671.74 | Y6: 19997.647 | Z6: 87401.23 | AA6: 2666.8
A7: K.P. WOVEN PRIVATE LIMITED | B7: RM | C7: Masterbatch | D7: 4286.33 | E7: 0 | F7: 0 | G7: 0 | H7: 3000 | I7: 0 | J7: 0 | K7: 0 | L7: 585 | M7: 0 | N7: 0 | O7: 0 | P7: 0 | Q7: 2082.22 | R7: 0 | S7: 0 | T7: 0 | U7: 0 | V7: 0 | W7: 0 | X7: 2082.22 | Y7: 4619.11 | Z7: 0 | AA7: 0
A8: K.P. WOVEN PRIVATE LIMITED | B8: RM | C8: PP Granules | D8: -57419 | E8: 345682.6 | F8: 135921.79 | G8: 0 | H8: 666050 | I8: 0 | J8: 1500 | K8: 93267 | L8: 337250 | M8: 0 | N8: 6685 | O8: 133500 | P8: 0 | Q8: 440267.2 | R8: 1500 | S8: 62675.73 | T8: 0 | U8: 64245.8 | V8: 0 | W8: 0 | X8: 376021.4 | Y8: -109825.4 | Z8: 241203.8 | AA8: 79931.06
A9: K.P. WOVEN PRIVATE LIMITED | B9: RM | C9: UV MB | D9: 9810.977 | E9: 33000.2 | F9: 67 | G9: 0 | H9: 5100 | I9: 0 | J9: 0 | K9: 2000 | L9: 0 | M9: 0 | N9: 175 | O9: 0 | P9: 0 | Q9: 13476.49 | R9: 0 | S9: 147.64 | T9: 0 | U9: 0 | V9: 0 | W9: 0 | X9: 13476.49 | Y9: 1259.487 | Z9: 35000.2 | AA9: 94.36
A10: K.P. WOVEN PRIVATE LIMITED | B10: SF | C10: HD Lam Fabric | D10: 8302.1 | E10: 0 | F10: 0 | G10: 0 | H10: 1166 | I10: 0 | J10: 0 | K10: 0 | L10: 0 | M10: 0 | N10: 0 | O10: 0 | P10: 0 | Q10: 0 | R10: 0 | S10: 0 | T10: 0 | U10: 0 | V10: 0 | W10: 0 | X10: 0 | Y10: 9468.1 | Z10: 0 | AA10: 0
A11: K.P. WOVEN PRIVATE LIMITED | B11: SF | C11: HD UL Fabric | D11: 5296.7 | E11: 0 | F11: 0 | G11: 0 | H11: 2268.7 | I11: 0 | J11: 7077.4 | K11: 0 | L11: 0 | M11: 0 | N11: 0 | O11: 0 | P11: 9222.9 | Q11: 8182.3 | R11: 7077.4 | S11: 0 | T11: 0 | U11: 0 | V11: 0 | W11: 9222.9 | X11: 8182.3 | Y11: 15683.4 | Z11: 0 | AA11: 0
A12: K.P. WOVEN PRIVATE LIMITED | B12: SF | C12: LDPE/LLDPE Bags | D12: 295706.26 | E12: 0 | F12: 0 | G12: 0 | H12: 39998.89 | I12: 0 | J12: 0 | K12: 0 | L12: 529 | M12: 0 | N12: 0 | O12: 0 | P12: 0 | Q12: 0 | R12: 0 | S12: 0 | T12: 0 | U12: 0 | V12: 0 | W12: 0 | X12: 0 | Y12: 335176.15 | Z12: 0 | AA12: 0
A13: K.P. WOVEN PRIVATE LIMITED | B13: SF | C13: PE Film | D13: -17219.6 | E13: 0 | F13: 0 | G13: 0 | H13: 605 | I13: 0 | J13: 0 | K13: 0 | L13: 0 | M13: 0 | N13: 0 | O13: 0 | P13: 0 | Q13: 0 | R13: 0 | S13: 0 | T13: 0 | U13: 0 | V13: 0 | W13: 0 | X13: 0 | Y13: -16614.6 | Z13: 0 | AA13: 0
A14: K.P. WOVEN PRIVATE LIMITED | B14: SF | C14: Polyester Yarn | D14: 4075.56 | E14: 0 | F14: 0 | G14: 0 | H14: 1550.3 | I14: 0 | J14: 0 | K14: 0 | L14: 212 | M14: 0 | N14: 0 | O14: 0 | P14: 0 | Q14: 0 | R14: 0 | S14: 0 | T14: 0 | U14: 0 | V14: 0 | W14: 0 | X14: 0 | Y14: 5413.86 | Z14: 0 | AA14: 0
... A27: K.P. WOVEN PRIVATE LIMITED | B27: FG | C27: Trading Items | D27: 7.3 | E27: 0 | F27: 0 | G27: 0 | H27: 0 | I27: 0 | J27: 0 | K27: 0 | L27: 0 | M27: 0 | N27: 0 | O27: 0 | P27: 0 | Q27: 0 | R27: 0 | S27: 0 | T27: 0 | U27: 0 | V27: 0 | W27: 0 | X27: 0 | Y27: 7.3 | Z27: 0 | AA27: 0
A28: Total | C28: 0 | D28: 1843054.9 | E28: 570835.75 | F28: 167448.64 | G28: 0 | H28: 1420068.1 | I28: 0 | J28: 73596.33 | K28: 95438.55 | L28: 1283156.1 | M28: 0 | N28: 20775.12 | O28: 199752.51 | P28: 2541871.9 | Q28: 2541402.9 | R28: 73596.33 | S28: 73596.33 | T28: 66170.2 | U28: 66170.2 | V28: 0 | W28: 2475701.7 | X28: 2475232.7 | Y28: 2033257.2 | Z28: 466521.79 | AA28: 114627.43
A29: K.P. WOVEN PRIVATE LIMITED | B29: RM Consumables | C29: FIBC Accessories | D29: 6875.735 | E29: 0 | F29: 0 | G29: 0 | H29: 467.1 | I29: 0 | J29: 0 | K29: 0 | L29: 0 | M29: 0 | N29: 0 | O29: 0 | P29: 0 | Q29: 0 | R29: 0 | S29: 0 | T29: 0 | U29: 0 | V29: 0 | W29: 0 | X29: 0 | Y29: 7342.835 | Z29: 0 | AA29: 0
A30: K.P. WOVEN PRIVATE LIMITED | B30: RM Consumables | C30: Ink | D30: 2600 | E30: 0 | F30: 0 | G30: 0 | H30: 250 | I30: 0 | J30: 0 | K30: 0 | L30: 25 | M30: 0 | N30: 0 | O30: 0 | P30: 0 | Q30: 0 | R30: 0 | S30: 0 | T30: 0 | U30: 0 | V30: 0 | W30: 0 | X30: 0 | Y30: 2825 | Z30: 0 | AA30: 0
A31: K.P. WOVEN PRIVATE LIMITED | B31: RM Consumables | C31: Thinner | D31: 12240 | E31: 0 | F31: 0 | G31: 0 | H31: 2550 | I31: 0 | J31: 0 | K31: 0 | L31: 680 | M31: 0 | N31: 0 | O31: 0 | P31: 0 | Q31: 0 | R31: 0 | S31: 0 | T31: 0 | U31: 0 | V31: 0 | W31: 0 | X31: 0 | Y31: 14110 | Z31: 0 | AA31: 0
A32: Total | C32: 0 | D32: 21715.735 | E32: 0 | F32: 0 | G32: 0 | H32: 3267.1 | I32: 0 | J32: 0 | K32: 0 | L32: 705 | M32: 0 | N32: 0 | O32: 0 | P32: 0 | Q32: 0 | R32: 0 | S32: 0 | T32: 0 | U32: 0 | V32: 0 | W32: 0 | X32: 0 | Y32: 24277.835 | Z32: 0 | AA32: 0

Sheet July - 26
B1: 46204
B2: 1 | C2: 2 | D2: 3 | E2: 4 | F2: 5 | G2: 6 | H2: 7 | I2: 8 | J2: 9 | K2: 10 | L2: 11 | M2: 12 | N2: 13 | O2: 14 | P2: 15 | Q2: 16 | R2: 17 | S2: 18 | T2: 19 | U2: 20 | V2: 21 | W2: 22 | X2: 23 | Y2: 24 | Z2: 25 | AA2: 26 | AB2: 27 | AC2: 28 | AD2: 29 | AE2: 30 | AF2: 31
B3: SubGroupName | C3: Op.Factory Owned | D3: Op.Factory JW (Others) | E3: Op.At JW (Own) | F3: Branch Tfr Recd | G3: Purchase | H3: Warehouse Inwards | I3: Recd from JW (Own) | J3: Recd For JW (Others) | K3: Sales | L3: Br Transfer Sent | M3: Sent for JW (Own) | N3: Return JW(Others) | O3: Total Production Own+JW | P3: Total Consumption Own+JW | Q3: Production at JW | R3: Consumption At JW | S3: Production Of JW | T3: Consumption Of JW | U3: Stock Adjustment Entry | V3: Net Production Own | W3: Net Consumption Own | X3: Cl.Factory Owned | Y3: Cl.Factory JW (Others) | Z3: Cl.At JW (Own) | AA3: RATE CONSIDER | AB3: RATE | AC3: CLOSING AMOUNT FACTORY | AD3: CLOSING AMOUNT JOB OWN | AE3: VALUE
A5: MainGroup | B5: SubGroupName | C5: Op.Factory Owned | D5: Op.Factory JW (Others) | E5: Op.At JW (Own) | F5: Branch Tfr Recd | G5: Purchase | H5: Warehouse Inwards | I5: Recd from JW (Own) | J5: Recd For JW (Others) | K5: Sales | L5: Br Transfer Sent | M5: Sent for JW (Own) | N5: Return JW(Others) | O5: Total Production Own+JW | P5: Total Consumption Own+JW | Q5: Production at JW | R5: Consumption At JW | S5: Production Of JW | T5: Consumption Of JW | U5: Stock Adjustment Entry | V5: Net Production Own | W5: Net Consumption Own | X5: Cl.Factory Owned | Y5: Cl.Factory JW (Others) | Z5: Cl.At JW (Own) | AA5: RATE CONSIDER | AB5: RATE | AC5: CLOSING AMOUNT FACTORY | AD5: CLOSING AMOUNT JOB OWN | AE5: VALUE
A6: RM | B6: FIBC Accessories | C6: 13506.2 | D6: 0 | E6: 0 | F6: 0 | G6: 1699.3 | H6: 0 | I6: 0 | J6: 0 | K6: 203.5 | L6: 0 | M6: 0 | N6: 0 | O6: 0 | P6: 0 | Q6: 0 | R6: 0 | S6: 0 | T6: 0 | U6: 0 | V6: =O6-S6 -> 0 | W6: =P6-T6 -> 0 | X6: =C6+F6+G6+I6-K6-L6-M6-W6+V6 -> 15002 | Y6: =D6+J6-N6+S6-T6 -> 0 | Z6: =E6-I6+M6+Q6-R6 -> 0 | AA6: PURCHASE | AB6: =Purchase!AP869 -> 150 | AC6: =X6*AB6 -> 2250300 | AD6: =Z6*AB6 -> 0
A7: RM | B7: Filler | C7: 9644.34 | D7: 0 | E7: -19.4 | F7: 0 | G7: 30000 | H7: 0 | I7: 0 | J7: 0 | K7: 0 | L7: 0 | M7: 140 | N7: 0 | O7: 0 | P7: 16902.86 | Q7: 0 | R7: 121.17 | S7: 0 | T7: 0 | U7: 0 | V7: =O7-S7 -> 0 | W7: =P7-T7 -> 16902.86 | X7: =C7+F7+G7+I7-K7-L7-M7-W7+V7 -> 22601.48 | Y7: =D7+J7-N7+S7-T7 -> 0 | Z7: =E7-I7+M7+Q7-R7 -> -0.57 | AA7: PURCHASE | AB7: =Purchase!AP871 -> 38 | AC7: =X7*AB7 -> 858856.24 | AD7: =Z7*AB7 -> -21.66
A8: RM | B8: HDPE Granules | C8: -100 | D8: 0 | E8: 0 | F8: 0 | G8: 0 | H8: 0 | I8: 0 | J8: 0 | K8: 0 | L8: 0 | M8: 0 | N8: 0 | O8: 0 | P8: 0 | Q8: 0 | R8: 0 | S8: 0 | T8: 0 | U8: 0 | V8: =O8-S8 -> 0 | W8: =P8-T8 -> 0 | X8: =C8+F8+G8+I8-K8-L8-M8-W8+V8 -> -100 | Y8: =D8+J8-N8+S8-T8 -> 0 | Z8: =E8-I8+M8+Q8-R8 -> 0 | AA8: PURCHASE | AB8: 120 | AC8: =X8*AB8 -> -12000 | AD8: =Z8*AB8 -> 0
A9: RM | B9: LDPE Granules | C9: -25907.87 | D9: 89488.87 | E9: 0 | F9: 0 | G9: 0 | H9: 0 | I9: 0 | J9: 0 | K9: 0 | L9: 0 | M9: 0 | N9: 0 | O9: 0 | P9: 8480.8 | Q9: 0 | R9: 0 | S9: 0 | T9: 1924.4 | U9: 0 | V9: =O9-S9 -> 0 | W9: =P9-T9 -> 6556.4 | X9: =C9+F9+G9+I9-K9-L9-M9-W9+V9 -> -32464.27 | Y9: =D9+J9-N9+S9-T9 -> 87564.47 | Z9: =E9-I9+M9+Q9-R9 -> 0 | AA9: PURCHASE | AB9: 180.76 | AC9: =X9*AB9 -> -5868241.4 | AD9: =Z9*AB9 -> 0
A10: RM | B10: LLDPE Granules | C10: 6669.3 | D10: 36557.3 | E10: 0 | F10: 0 | G10: 33000 | H10: 0 | I10: 0 | J10: 0 | K10: 0 | L10: 0 | M10: 0 | N10: 0 | O10: 0 | P10: 19671.74 | Q10: 0 | R10: 0 | S10: 0 | T10: 0 | U10: 0 | V10: =O10-S10 -> 0 | W10: =P10-T10 -> 19671.74 | X10: =C10+F10+G10+I10-K10-L10-M10-W10+V10 -> 19997.56 | Y10: =D10+J10-N10+S10-T10 -> 36557.3 | Z10: =E10-I10+M10+Q10-R10 -> 0 | AA10: PURCHASE | AB10: =Purchase!AP875 -> 125.52121 | AC10: =X10*AB10 -> 2510118 | AD10: =Z10*AB10 -> 0
A11: RM | B11: Masterbatch | C11: 4286.33 | D11: 0 | E11: 0 | F11: 0 | G11: 3000 | H11: 0 | I11: 0 | J11: 0 | K11: 585 | L11: 0 | M11: 0 | N11: 0 | O11: 0 | P11: 2082.22 | Q11: 0 | R11: 0 | S11: 0 | T11: 0 | U11: 0 | V11: =O11-S11 -> 0 | W11: =P11-T11 -> 2082.22 | X11: =C11+F11+G11+I11-K11-L11-M11-W11+V11 -> 4619.11 | Y11: =D11+J11-N11+S11-T11 -> 0 | Z11: =E11-I11+M11+Q11-R11 -> 0 | AA11: PURCHASE | AB11: =Purchase!AP876 -> 227.41183 | AC11: =X11*AB11 -> 1050440.3 | AD11: =Z11*AB11 -> 0
A12: RM | B12: PP Granules | C12: -57419 | D12: 336200.27 | E12: 135860.59 | F12: 0 | G12: 666050 | H12: 0 | I12: 1500 | J12: 93267 | K12: 337250 | L12: 0 | M12: 6685 | N12: 133500 | O12: 0 | P12: 440267.2 | Q12: 1500 | R12: 62675.73 | S12: 0 | T12: 64245.8 | U12: 0 | V12: =O12-S12 -> 0 | W12: =P12-T12 -> 376021.4 | X12: =C12+F12+G12+I12-K12-L12-M12-W12+V12 -> -109825.4 | Y12: =D12+J12-N12+S12-T12 -> 231721.47 | Z12: =E12-I12+M12+Q12-R12 -> 79869.86 | AA12: PURCHASE | AB12: =Purchase!AP881 -> 83.069598 | AC12: =X12*AB12 -> -9123151.8 | AD12: =Z12*AB12 -> 6634757.1
A13: RM | B13: UV MB | C13: 9810.9 | D13: 34064.2 | E13: 102.4 | F13: 0 | G13: 5100 | H13: 0 | I13: 0 | J13: 2000 | K13: 0 | L13: 0 | M13: 175 | N13: 0 | O13: 0 | P13: 13476.49 | Q13: 0 | R13: 147.64 | S13: 0 | T13: 0 | U13: 0 | V13: =O13-S13 -> 0 | W13: =P13-T13 -> 13476.49 | X13: =C13+F13+G13+I13-K13-L13-M13-W13+V13 -> 1259.41 | Y13: =D13+J13-N13+S13-T13 -> 36064.2 | Z13: =E13-I13+M13+Q13-R13 -> 129.76 | AA13: PURCHASE | AB13: =Purchase!AP886 -> 240 | AC13: =X13*AB13 -> 302258.4 | AD13: =Z13*AB13 -> 31142.4
A14: SF | B14: Films All | C14: -917.5 | D14: 0 | E14: 0 | F14: 0 | G14: 0 | H14: 0 | I14: 0 | J14: 0 | K14: 0 | L14: 0 | M14: 0 | N14: 0 | O14: 0 | P14: 0 | Q14: 0 | R14: 0 | S14: 0 | T14: 0 | U14: 0 | V14: =O14-S14 -> 0 | W14: =P14-T14 -> 0 | X14: =C14+F14+G14+I14-K14-L14-M14-W14+V14 -> -917.5 | Y14: =D14+J14-N14+S14-T14 -> 0 | Z14: =E14-I14+M14+Q14-R14 -> 0 | AB14: 158.62 | AC14: =X14*AB14 -> -145533.85 | AD14: =Z14*AB14 -> 0
A15: SF | B15: HD Lam Fabric | C15: 8302 | D15: 0 | E15: 0 | F15: 0 | G15: 1166 | H15: 0 | I15: 0 | J15: 0 | K15: 0 | L15: 0 | M15: 0 | N15: 0 | O15: 0 | P15: 0 | Q15: 0 | R15: 0 | S15: 0 | T15: 0 | U15: 0 | V15: =O15-S15 -> 0 | W15: =P15-T15 -> 0 | X15: =C15+F15+G15+I15-K15-L15-M15-W15+V15 -> 9468 | Y15: =D15+J15-N15+S15-T15 -> 0 | Z15: =E15-I15+M15+Q15-R15 -> 0 | AA15: PP+20 | AB15: =+AB12+20 -> 103.0696 | AC15: =X15*AB15 -> 975862.95 | AD15: =Z15*AB15 -> 0
A16: SF | B16: HD UL Fabric | C16: 1834.2 | D16: 0 | E16: 0 | F16: 0 | G16: 2268.7 | H16: 0 | I16: 7077.4 | J16: 0 | K16: 0 | L16: 0 | M16: 0 | N16: 0 | O16: 0 | P16: 8182.3 | Q16: 7077.4 | R16: 0 | S16: 0 | T16: 0 | U16: 0 | V16: =O16-S16 -> 0 | W16: =P16-T16 -> 8182.3 | X16: =C16+F16+G16+I16-K16-L16-M16-W16+V16 -> 2998 | Y16: =D16+J16-N16+S16-T16 -> 0 | Z16: =E16-I16+M16+Q16-R16 -> -9.094947e-13 | AA16: PP+20 | AB16: =+AB12+20 -> 103.0696 | AC16: =X16*AB16 -> 309002.65 | AD16: =Z16*AB16 -> -9.3741253e-11
A17: SF | B17: LDPE/LLDPE Bags | C17: 292265.74 | D17: 0 | E17: 0 | F17: 0 | G17: 39518.33 | H17: 0 | I17: 0 | J17: 0 | K17: 529 | L17: 0 | M17: 0 | N17: 0 | O17: 0 | P17: 0 | Q17: 0 | R17: 0 | S17: 0 | T17: 0 | U17: 0 | V17: =O17-S17 -> 0 | W17: =P17-T17 -> 0 | X17: =C17+F17+G17+I17-K17-L17-M17-W17+V17 -> 331255.07 | Y17: =D17+J17-N17+S17-T17 -> 0 | Z17: =E17-I17+M17+Q17-R17 -> 0 | AA17: PURCHASE | AB17: =Purchase!AP874 -> 208.72229 | AC17: =X17*AB17 -> 69140316 | AD17: =Z17*AB17 -> 0
A18: SF | B18: PE Film | C18: 59998.01 | D18: 0 | E18: 0 | F18: 0 | G18: 605 | H18: 0 | I18: 0 | J18: 0 | K18: 0 | L18: 0 | M18: 0 | N18: 0 | O18: 0 | P18: 0 | Q18: 0 | R18: 0 | S18: 0 | T18: 0 | U18: 0 | V18: =O18-S18 -> 0 | W18: =P18-T18 -> 0 | X18: =C18+F18+G18+I18-K18-L18-M18-W18+V18 -> 60603.01 | Y18: =D18+J18-N18+S18-T18 -> 0 | Z18: =E18-I18+M18+Q18-R18 -> 0 | AA18: PURCHASE | AB18: =Purchase!AP878 -> 169.2957 | AC18: =X18*AB18 -> 10259829 | AD18: =Z18*AB18 -> 0
A19: SF | B19: Polyester Yarn | C19: 4075.56 | D19: 0 | E19: 0 | F19: 0 | G19: 1550.3 | H19: 0 | I19: 0 | J19: 0 | K19: 212 | L19: 0 | M19: 0 | N19: 0 | O19: 0 | P19: 0 | Q19: 0 | R19: 0 | S19: 0 | T19: 0 | U19: 0 | V19: =O19-S19 -> 0 | W19: =P19-T19 -> 0 | X19: =C19+F19+G19+I19-K19-L19-M19-W19+V19 -> 5413.86 | Y19: =D19+J19-N19+S19-T19 -> 0 | Z19: =E19-I19+M19+Q19-R19 -> 0 | AB19: =Purchase!AP879 -> 182 | AC19: =X19*AB19 -> 985322.52 | AD19: =Z19*AB19 -> 0 | AE19: =X19*132 -> 714629.52
A20: SF | B20: PP Lam Fabric | C20: -99648.6 | D20: 0 | E20: 2217 | F20: 0 | G20: 55701.8 | H20: 0 | I20: 4759.7 | J20: 0 | K20: 31728.4 | L20: 0 | M20: 0 | N20: 0 | O20: 246154 | P20: 245908.6 | Q20: 4759.7 | R20: 0 | S20: 0 | T20: 0 | U20: 0 | V20: =O20-S20 -> 246154 | W20: =P20-T20 -> 245908.6 | X20: =C20+F20+G20+I20-K20-L20-M20-W20+V20 -> -70670.1 | Y20: =D20+J20-N20+S20-T20 -> 0 | Z20: =E20-I20+M20+Q20-R20 -> 2217 | AA20: ULF+5 | AB20: =+AB22+5 -> 108.0696 | AC20: =X20*AB20 -> -7637289.3 | AD20: =Z20*AB20 -> 239590.3
A21: SF | B21: PP Tapes | C21: 107725.5 | D21: 0 | E21: 0 | F21: 0 | G21: 0 | H21: 0 | I21: 0 | J21: 0 | K21: 0 | L21: 0 | M21: 0 | N21: 0 | O21: 470958.48 | P21: 383734.2 | Q21: 0 | R21: 0 | S21: 0 | T21: 0 | U21: 0 | V21: =O21-S21 -> 470958.48 | W21: =P21-T21 -> 383734.2 | X21: =C21+F21+G21+I21-K21-L21-M21-W21+V21 -> 194949.78 | Y21: =D21+J21-N21+S21-T21 -> 0 | Z21: =E21-I21+M21+Q21-R21 -> 0 | AA21: pp+10 | AB21: =+AB12+10 -> 93.069598 | AC21: =X21*AB21 -> 18143898 | AD21: =Z21*AB21 -> 0
A22: SF | B22: PP UL Fabric | C22: 652256.18 | D22: 11420 | E22: 71222.2 | F22: 0 | G22: 191637.66 | H22: 0 | I22: 50226.04 | J22: 0 | K22: 77733.5 | L22: 0 | M22: 0 | N22: 2484.8 | O22: 273437.2 | P22: 468444.44 | Q22: 50226.04 | R22: 0 | S22: 2484.8 | T22: 0 | U22: 0 | V22: =O22-S22 -> 270952.4 | W22: =P22-T22 -> 468444.44 | X22: =C22+F22+G22+I22-K22-L22-M22-W22+V22 -> 618894.34 | Y22: =D22+J22-N22+S22-T22 -> 11420 | Z22: =E22-I22+M22+Q22-R22 -> 71222.2 | AA22: pp+20 | AB22: =+AB12+20 -> 103.0696 | AC22: =X22*AB22 -> 63789191 | AD22: =Z22*AB22 -> 7340843.5
A23: SF | B23: PP Webbing | C23: 205768.5 | D23: 0 | E23: 5777 | F23: 0 | G23: 9180.6 | H23: 0 | I23: 0 | J23: 0 | K23: 30916.1 | L23: 0 | M23: 0 | N23: 0 | O23: 107879 | P23: 8048 | Q23: 0 | R23: 0 | S23: 0 | T23: 0 | U23: 0 | V23: =O23-S23 -> 107879 | W23: =P23-T23 -> 8048 | X23: =C23+F23+G23+I23-K23-L23-M23-W23+V23 -> 283864 | Y23: =D23+J23-N23+S23-T23 -> 0 | Z23: =E23-I23+M23+Q23-R23 -> 5777 | AA23: pp+20 | AB23: =+AB12+20 -> 103.0696 | AC23: =X23*AB23 -> 29257748 | AD23: =Z23*AB23 -> 595433.07
A24: SF | B24: PP Yarn | C24: 104536.52 | D24: 180.67 | E24: 8757.32 | F24: 0 | G24: 39194.36 | H24: 0 | I24: 9562.39 | J24: 171.55 | K24: 62955.3 | L24: 0 | M24: 13775.12 | N24: 82.31 | O24: 2598 | P24: 15631 | Q24: 9562.39 | R24: 10651.79 | S24: 0 | T24: 0 | U24: 0 | V24: =O24-S24 -> 2598 | W24: =P24-T24 -> 15631 | X24: =C24+F24+G24+I24-K24-L24-M24-W24+V24 -> 63529.85 | Y24: =D24+J24-N24+S24-T24 -> 269.91 | Z24: =E24-I24+M24+Q24-R24 -> 11880.65 | AA24: PURCHASE | AB24: =Purchase!AP885 -> 161.24086 | AC24: =X24*AB24 -> 10243608 | AD24: =Z24*AB24 -> 1915646.3
A25: SF | B25: RP Granules | C25: 55735.3 | D25: -449 | E25: 0 | F25: 0 | G25: 0 | H25: 0 | I25: 0 | J25: 0 | K25: 19000 | L25: 0 | M25: 0 | N25: 0 | O25: 58880 | P25: 29350.67 | Q25: 0 | R25: 0 | S25: 0 | T25: 0 | U25: 0 | V25: =O25-S25 -> 58880 | W25: =P25-T25 -> 29350.67 | X25: =C25+F25+G25+I25-K25-L25-M25-W25+V25 -> 66264.63 | Y25: =D25+J25-N25+S25-T25 -> -449 | Z25: =E25-I25+M25+Q25-R25 -> 0 | AA25: 65 | AB25: 65 | AC25: =X25*AB25 -> 4307201 | AD25: =Z25*AB25 -> 0
A26: SF | B26: Wastage/Scrap | C26: 100459.35 | D26: 0 | E26: 24132 | F26: 0 | G26: 0 | H26: 0 | I26: 470.8 | J26: 0 | K26: 9300 | L26: 0 | M26: 0 | N26: 0 | O26: 110196.6 | P26: 59325 | Q26: 470.8 | R26: 0 | S26: 0 | T26: 0 | U26: 0 | V26: =O26-S26 -> 110196.6 | W26: =P26-T26 -> 59325 | X26: =C26+F26+G26+I26-K26-L26-M26-W26+V26 -> 142501.75 | Y26: =D26+J26-N26+S26-T26 -> 0 | Z26: =E26-I26+M26+Q26-R26 -> 24132 | AA26: 15 | AB26: 15 | AC26: =X26*AB26 -> 2137526.2 | AD26: =Z26*AB26 -> 361980
A27: FG | B27: FIBC Bags | C27: 272370.87 | D27: 0 | E27: 4383 | F27: 0 | G27: 334889.15 | H27: 0 | I27: 0 | J27: 0 | K27: 778444.45 | L27: 0 | M27: 0 | N27: 63685.4 | O27: 521685.8 | P27: 0 | Q27: 0 | R27: 0 | S27: 63685.4 | T27: 0 | U27: 0 | V27: =O27-S27 -> 458000.4 | W27: =P27-T27 -> 0 | X27: =C27+F27+G27+I27-K27-L27-M27-W27+V27 -> 286815.97 | Y27: =D27+J27-N27+S27-T27 -> 0 | Z27: =E27-I27+M27+Q27-R27 -> 4383 | AA27: sale - 5% | AB27: =Purchase!AP870 -> 217.40842 | AC27: =X27*AB27 -> 62356208 | AD27: =Z27*AB27 -> 952901.12
A28: FG | B28: FIBC WIP | C28: 4803.97 | D28: 4016.25 | E28: 0 | F28: 0 | G28: 0 | H28: 0 | I28: 0 | J28: 0 | K28: 0 | L28: 0 | M28: 0 | N28: 0 | O28: 567729.64 | P28: 640013.2 | Q28: 0 | R28: 0 | S28: 0 | T28: 0 | U28: 0 | V28: =O28-S28 -> 567729.64 | W28: =P28-T28 -> 640013.2 | X28: =C28+F28+G28+I28-K28-L28-M28-W28+V28 -> -67479.59 | Y28: =D28+J28-N28+S28-T28 -> 4016.25 | Z28: =E28-I28+M28+Q28-R28 -> 0 | AA28: 125 | AB28: 125 | AC28: =X28*AB28 -> -8434948.7 | AD28: =Z28*AB28 -> 0
A29: FG | B29: HDPE Bags | C29: 559 | D29: 0 | E29: 0 | F29: 0 | G29: 0 | H29: 0 | I29: 0 | J29: 0 | K29: 0 | L29: 0 | M29: 0 | N29: 0 | O29: 0 | P29: 0 | Q29: 0 | R29: 0 | S29: 0 | T29: 0 | U29: 0 | V29: =O29-S29 -> 0 | W29: =P29-T29 -> 0 | X29: =C29+F29+G29+I29-K29-L29-M29-W29+V29 -> 559 | Y29: =D29+J29-N29+S29-T29 -> 0 | Z29: =E29-I29+M29+Q29-R29 -> 0 | AC29: =X29*AB29 -> 0 | AD29: =Z29*AB29 -> 0 | AE29: 74347
A30: FG | B30: PP Bags | C30: 52112.9 | D30: 0 | E30: 0 | F30: 0 | G30: 4.6 | H30: 0 | I30: 0 | J30: 0 | K30: 469 | L30: 0 | M30: 0 | N30: 0 | O30: 0 | P30: 0 | Q30: 0 | R30: 0 | S30: 0 | T30: 0 | U30: 0 | V30: =O30-S30 -> 0 | W30: =P30-T30 -> 0 | X30: =C30+F30+G30+I30-K30-L30-M30-W30+V30 -> 51648.5 | Y30: =D30+J30-N30+S30-T30 -> 0 | Z30: =E30-I30+M30+Q30-R30 -> 0 | AA30: purchase | AB30: =Purchase!AP880 -> 106.6 | AC30: =X30*AB30 -> 5505730.1 | AD30: =Z30*AB30 -> 0
A31: FG | B31: Small Bags WIP | C31: -1362.3 | D31: 0 | E31: 0 | F31: 0 | G31: 0 | H31: 0 | I31: 0 | J31: 0 | K31: 0 | L31: 0 | M31: 0 | N31: 0 | O31: 0 | P31: 0 | Q31: 0 | R31: 0 | S31: 0 | T31: 0 | U31: 0 | V31: =O31-S31 -> 0 | W31: =P31-T31 -> 0 | X31: =C31+F31+G31+I31-K31-L31-M31-W31+V31 -> -1362.3 | Y31: =D31+J31-N31+S31-T31 -> 0 | Z31: =E31-I31+M31+Q31-R31 -> 0 | AC31: =X31*AB31 -> 0 | AD31: =Z31*AB31 -> 0
C33: =SUM(C6:C32) -> 1781365.4 | D33: =SUM(D6:D32) -> 511478.56 | E33: =SUM(E6:E32) -> 252432.11 | F33: =SUM(F6:F32) -> 0 | G33: =SUBTOTAL(9,G6:G31) -> 1414565.8 | H33: =SUM(H6:H32) -> 0 | I33: =SUM(I6:I32) -> 73596.33 | J33: =SUM(J6:J32) -> 95438.55 | K33: =SUM(K6:K32) -> 1349326.3 | L33: =SUM(L6:L32) -> 0 | M33: =SUM(M6:M32) -> 20775.12 | N33: =SUM(N6:N32) -> 199752.51 | O33: =SUM(O6:O32) -> 2359518.7 | ... Y33: =SUM(Y6:Y32) -> 407164.6 | Z33: =E33-I33+M33+Q33-R33 -> 199610.9 | AA33: =SUM(AA6:AA32) -> 205 | AB33: =SUM(AB6:AB32) -> 3187.0675 | AC33: =SUM(AC6:AC32) -> 2.5316225e+08 | AD33: =SUM(AD6:AD31) -> 18072272 | AE33: =SUM(AE6:AE32) -> 788976.52
M35: =E33 -> 252432.11 | N35: =M33+Q33 -> 94371.45 | O35: =+I33+R33 -> 147192.66 | Q35: =M35+N35-(O35) -> 199610.9
M36: Op. | N36: IN | O36: OUT | P36: CL | V36: 2293348.5 | W36: 2293348.5 | X36: 1899426.2 | Y36: 407164.6 | Z36: 199610.9 | AA36: 205 | AB36: 3187.0675 | AC36: 2.5316225e+08 | AD36: 18072272 | AE36: 788976.52
M37: =M35/1000 -> 252.43211 | N37: =N35/1000 -> 94.37145 | O37: =O35/1000 -> 147.19266 | P37: =Q35/1000 -> 199.6109 | V37: PERTICULER | W37: OWN STOCK VALUE | X37: JOB STOCK VALUE | Y37: TOTAL | AD37: =AD36/AC36 -> 0.071386125
V38: RM STOCK | W38: =AC7+AC8+AC9+AC10+AC11+AC12+AC13+AC6 -> -8031420.3 | X38: =AD7+AD8+AD9+AD10+AD11+AD12+AD13+AD6 -> 6665877.9 | Y38: =+X38+W38 -> -1365542.5
V39: SF STOCK | W39: =AC15+AC16+AC17+AC18+AC19+AC20+AC21+AC22+AC23+AC24+AC25+AC26+AC14 -> 2.0176668e+08 | X39: =AD15+AD16+AD17+AD18+AD19+AD20+AD21+AD22+AD23+AD24+AD25+AD26+AD14 -> 10453493 | Y39: =+X39+W39 -> 2.1222017e+08
V40: FG STOCK | W40: =AC28+AC29+AC30+AC31+AC27 -> 59426989 | X40: =AD28+AD29+AD30+AD31+AD27 -> 952901.12 | Y40: =+X40+W40 -> 60379891
V41: TOTAL | W41: =+W40+W39+W38 -> 2.5316225e+08 | X41: =+X40+X39+X38 -> 18072272 | Y41: =+X41+W41 -> 2.7123452e+08
Z42: =+Y41-(AC33+AD33) -> 0

Sheet Stores
B2: 01.10.2025 To 31.11.2025
B3: deptt | C3: Openingstock | D3: OpRate | E3: OpValue | F3: InwardsQty | G3: InwdRate | H3: InwdValue | I3: OutWardsQty | J3: OutRate | K3: Outvalue | L3: closingStk | M3: LatestRate | N3: ClosingAmount | O3: companyname | P3: AvgClosingRate
B4: Packing Material | C4: -8843.35 | D4: 435.3647 | E4: 5392192.8 | F4: 34685.3 | G4: 226.87 | H4: 2090444.6 | I4: 20145.45 | J4: 176.1559 | K4: 1624135.4 | L4: 5696.5 | M4: 390.4271 | N4: 1635048.8 | O4: K.P. WOVEN PRIVATE LIMITED | P4: 1317.3975
B5: Consumables | C5: 3010.2 | D5: 275.7727 | E5: 1349416.4 | F5: 76076 | G5: 114.98 | H5: 906727.53 | I5: 13494.2 | J5: 120.5878 | K5: 399965.68 | L5: 65592 | M5: 306.5801 | N5: 2218849.7 | O5: K.P. WOVEN PRIVATE LIMITED | P5: 58.5955
B6: Stores/Spares | C6: 84168.45 | D6: 1324.5317 | E6: 9410433.4 | F6: 36840 | G6: 194.88 | H6: 1889559.1 | I6: 16711.35 | J6: 144.9915 | K6: 898321.57 | L6: 104297.1 | M6: 1373.6805 | N6: 10507500 | O6: K.P. WOVEN PRIVATE LIMITED | P6: 345.3428
B7: RM Consumables | C7: 646831 | D7: 238.5607 | E7: 2717717.7 | F7: 158770 | G7: 0.58 | H7: 537903 | I7: 116380 | J7: 70.6366 | K7: 533729.08 | L7: 689221 | M7: 269.4729 | N7: 3172400.5 | O7: K.P. WOVEN PRIVATE LIMITED | P7: 73.4612
E8: =+E7+E6+E5+E4 -> 18869760 | H8: =+H7+H6+H5+H4 -> 5424634.2 | K8: =+K7+K6+K5+K4 -> 3456151.7 | N8: =+N7+N6+N5+N4 -> 17533799
B10: 01.11.2025 TO 30.11.2025
B11: deptt | C11: Openingstock | D11: OpRate | E11: OpValue | F11: InwardsQty | G11: InwdRate | H11: InwdValue | I11: OutWardsQty | J11: OutRate | K11: Outvalue | L11: closingStk | M11: LatestRate | N11: ClosingAmount | O11: companyname | P11: AvgClosingRate
B12: Packing Material | C12: 5695.5 | D12: 422.9394 | E12: 3263295.2 | F12: 32099.74 | G12: 125.48 | H12: 1238005.4 | I12: 12897.5 | J12: 305.9244 | K12: 1523715 | L12: 24897.74 | M12: 395.9794 | N12: 1370752.6 | O12: K.P. WOVEN PRIVATE LIMITED | P12: 173.0755
B13: Consumables | C13: 44528 | D13: 226.8315 | E13: 1540114 | F13: 3422 | G13: 49.53 | H13: 600854.24 | I13: 12195 | J13: 83.4371 | K13: 1048254.9 | L13: 35755 | M13: 249.9614 | N13: 1617208.8 | O13: K.P. WOVEN PRIVATE LIMITED | P13: -94.7728
B14: Stores/Spares | C14: 103567.1 | D14: 1172.7689 | E14: 10195140 | F14: 60488.95 | G14: 61.13 | H14: 1890618.7 | I14: 41182.2 | J14: 124.8507 | K14: 1634077.9 | L14: 122873.85 | M14: 1231.2635 | N14: 10733336 | O14: K.P. WOVEN PRIVATE LIMITED | P14: 280.8507
B15: RM Consumables | C15: 689221 | D15: 231.71 | E15: 2794367.9 | F15: 268020 | G15: 48.8 | H15: 1245505.6 | I15: 229493 | J15: 37.1798 | K15: 981457 | L15: 727748 | M15: 257.4202 | N15: 3601710.8 | O15: K.P. WOVEN PRIVATE LIMITED | P15: 98.3583
E16: =+E15+E14+E13+E12 -> 17792917 | H16: =+H15+H14+H13+H12 -> 4974983.9 | K16: =+K15+K14+K13+K12 -> 5187504.8 | N16: =+N15+N14+N13+N12 -> 17323008
B18: 01.12.2025. to 31.12.2025
B19: deptt | C19: Openingstock | D19: OpRate | E19: OpValue | F19: InwardsQty | G19: InwdRate | H19: InwdValue | I19: OutWardsQty | J19: OutRate | K19: Outvalue | L19: closingStk | M19: LatestRate | N19: ClosingAmount | O19: companyname | P19: AvgClosingRate
B20: Packing Material | C20: 2711.74 | D20: 332.3615 | E20: 1219708.3 | F20: 33765 | G20: 168.05 | H20: 1483001.2 | I20: 26351 | J20: 397.1977 | K20: 2072395.8 | L20: 10125.74 | M20: 400.0762 | N20: 690143.5 | O20: K.P. WOVEN PRIVATE LIMITED | P20: 53.9743
B21: Consumables | C21: 12891 | D21: 255.0866 | E21: 1008687.2 | F21: 53760.5 | G21: 116.77 | H21: 750558.82 | I21: 34716.5 | J21: 137.4375 | K21: 1008137.1 | L21: 31935 | M21: 290.2816 | N21: 1166686.7 | O21: K.P. WOVEN PRIVATE LIMITED | P21: 99.4418
B22: Stores/Spares | C22: 121266.3 | D22: 1262.9044 | E22: 9634589.8 | F22: 95617.3 | G22: 343.15 | H22: 3187695.7 | I22: 55104 | J22: 289.2783 | K22: 2761997.5 | L22: 161779.6 | M22: 1381.9821 | N22: 10439864 | O22: K.P. WOVEN PRIVATE LIMITED | P22: 446.268
B23: RM Consumables | C23: 326561 | D23: 209.9592 | E23: 1637367.5 | F23: 293598 | G23: 13.91 | H23: 747755 | I23: 295232 | J23: 179.4073 | K23: 1425028.9 | L23: 324927 | M23: 259.5775 | N23: 1715751.5 | O23: K.P. WOVEN PRIVATE LIMITED | P23: 45.8502
E24: =+E23+E22+E21+E20 -> 13500353 | H24: =+H23+H22+H21+H20 -> 6169010.7 | K24: =+K23+K22+K21+K20 -> 7267559.3 | N24: =+N23+N22+N21+N20 -> 14012445
B26: 01.01.2026 to 31.01.2026
B27: deptt | C27: Openingstock | D27: OpRate | E27: OpValue | F27: InwardsQty | G27: InwdRate | H27: InwdValue | I27: OutWardsQty | J27: OutRate | K27: Outvalue | L27: closingStk | M27: LatestRate | N27: ClosingAmount | O27: companyname | P27: AvgClosingRate
B28: Packing Material | C28: 10845.74 | D28: 318.3153 | E28: 701182.11 | F28: 35489.94 | G28: 348.91 | H28: 1515454.3 | I28: 14185.85 | J28: 170.6153 | K28: 1734967.3 | L28: 32149.83 | M28: 357.4267 | N28: 557674.44 | O28: K.P. WOVEN PRIVATE LIMITED | P28: 275.6921
B29: Consumables | C29: 17349 | D29: 219.5386 | E29: 730520.06 | F29: 47949 | G29: 47.82 | H29: 755738.63 | I29: 16057 | J29: 42.8443 | K29: 571060.22 | L29: 49241 | M29: 242.1273 | N29: 1259255.8 | O29: K.P. WOVEN PRIVATE LIMITED | P29: -66.4835
B30: Stores/Spares | C30: 157773.8 | D30: 1237.3779 | E30: 9762502.5 | F30: 27495.5 | G30: 171.06 | H30: 2006644.6 | I30: 33667.35 | J30: 218.3359 | K30: 2324067.6 | L30: 151601.95 | M30: 1312.4359 | N30: 10025902 | O30: K.P. WOVEN PRIVATE LIMITED | P30: 336.0724
B31: RM Consumables | C31: 323837 | D31: 176.3803 | E31: 1212409.1 | F31: 329565 | G31: 71.04 | H31: 1799834.1 | I31: 253363 | J31: 58.1718 | K31: 842884 | L31: 400039 | M31: 211.3915 | N31: 2015954.5 | O31: K.P. WOVEN PRIVATE LIMITED | P31: 84.8423
E32: =+E31+E30+E29+E28 -> 12406614 | H32: =+H31+H30+H29+H28 -> 6077671.6 | K32: =+K31+K30+K29+K28 -> 5472979.1 | N32: =+N31+N30+N29+N28 -> 13858787
B34: 01.02.2026 TO 28.02.2026
B36: deptt | C36: Openingstock | D36: OpRate | E36: OpValue | F36: InwardsQty | G36: InwdRate | H36: InwdValue | I36: OutWardsQty | J36: OutRate | K36: Outvalue | L36: closingStk | M36: LatestRate | N36: ClosingAmount | O36: companyname | P36: AvgClosingRate
B37: Packing Material | C37: 32149.83 | D37: 258.3656 | E37: 484342.86 | F37: 20645.49 | G37: 135.39 | H37: 1660537.4 | I37: 34500.47 | J37: 256.6625 | K37: 1192686 | L37: 18294.85 | M37: 277.7494 | N37: 1035528.7 | O37: K.P. WOVEN PRIVATE LIMITED | P37: 71.557
B38: Consumables | C38: 49048 | D38: 447.4718 | E38: 914504.24 | F38: 41748 | G38: 312.06 | H38: 1176289.1 | I38: 21965 | J38: 245.7812 | K38: 682190.82 | L38: 68831 | M38: 483.4148 | N38: 1606419.8 | O38: K.P. WOVEN PRIVATE LIMITED | P38: 133.1592
B39: Stores/Spares | C39: 151538.95 | D39: 1206.6102 | E39: 9715646.4 | F39: 39702.33 | G39: 145.34 | H39: 2393465.6 | I39: 23230.1 | J39: 121.336 | K39: 1534427.4 | L39: 168011.18 | M39: 1266.023 | N39: 10981604 | O39: K.P. WOVEN PRIVATE LIMITED | P39: 336.0588
B40: RM Consumables | C40: 399739 | D40: 188.6454 | E40: 1901382 | F40: 157340 | G40: 53.49 | H40: 587768.1 | I40: 371480 | J40: 22.6027 | K40: 1177743.6 | L40: 185599 | M40: 208.4181 | N40: 1441266.4 | O40: K.P. WOVEN PRIVATE LIMITED | P40: 60.9754
E41: =+E37+E38+E39+E40 -> 13015876 | H41: =+H37+H38+H39+H40 -> 5818060.2 | K41: =+K37+K38+K39+K40 -> 4587047.8 | N41: =+N37+N38+N39+N40 -> 15064819
B43: 01.03.2026 to 31.03.2026
B45: deptt | C45: Openingstock | D45: OpRate | E45: OpValue | F45: InwardsQty | G45: InwdRate | H45: InwdValue | I45: OutWardsQty | J45: OutRate | K45: Outvalue | L45: closingStk | M45: LatestRate | N45: ClosingAmount | O45: companyname | P45: AvgClosingRate
B46: Packing Material | C46: 16213.85 | D46: 364.3247 | E46: -3785.56 | F46: 33812.9 | G46: 364.2 | H46: 2170218.2 | I46: 31145.45 | J46: 336.0663 | K46: 1782710.9 | L46: 18881.3 | M46: 380.7926 | N46: 488304.12 | O46: K.P. WOVEN PRIVATE LIMITED | P46: 64.2989
B47: Consumables | C47: 54415.6 | D47: 503.4206 | E47: 1078472.5 | F47: 21963 | G47: 493.17 | H47: 1152708 | I47: 50911 | J47: 429.9613 | K47: 925828.39 | L47: 25467.6 | M47: 647.4132 | N47: 1588563.3 | O47: K.P. WOVEN PRIVATE LIMITED | P47: 277.9983
B48: Stores/Spares | C48: 146325.18 | D48: 1191.602 | E48: 8740342.4 | F48: 41404.6 | G48: 349.91 | H48: 4468463.9 | I48: 48423.93 | J48: 332.6879 | K48: 3317479.6 | L48: 139305.85 | M48: 1309.0951 | N48: 9937508.3 | O48: K.P. WOVEN PRIVATE LIMITED | P48: 375.3867
B49: RM Consumables | C49: 184619 | D49: 149.1411 | E49: 1108808.1 | F49: 293800 | G49: 3.67 | H49: 968480 | I49: 378346 | J49: 180.7 | K49: 1584155.8 | L49: 100073 | M49: 215.7054 | N49: 883904.25 | O49: K.P. WOVEN PRIVATE LIMITED | P49: 8.063
E50: =+E49+E48+E47+E46 -> 10923838 | H50: =+H49+H48+H47+H46 -> 8759870.1 | K50: =+K49+K48+K47+K46 -> 7610174.7 | N50: =+N49+N48+N47+N46 -> 12898280
B52: 01.04.2026 to 30.04.2026
B53: deptt | C53: Openingstock | D53: OpRate | E53: OpValue | F53: InwardsQty | G53: InwdRate | H53: InwdValue | I53: OutWardsQty | J53: OutRate | K53: Outvalue | L53: closingStk | M53: LatestRate | N53: ClosingAmount | O53: companyname | P53: AvgClosingRate
B54: Packing Material | C54: 26661.3 | D54: 216.8206 | E54: -769.06 | F54: 29873.6 | G54: 139.48 | H54: 578011.38 | I54: 9220 | J54: 55.1818 | K54: 447832.29 | L54: 47314.9 | M54: 231.7912 | N54: 353979.82 | O54: K.P. WOVEN PRIVATE LIMITED | P54: -32.0058
B55: Consumables | C55: 27405.3 | D55: 616.1507 | E55: 1173812.6 | F55: 112992 | G55: 164.15 | H55: 692994.58 | I55: 55086 | J55: 66.4328 | K55: 478567.63 | L55: 85311.3 | M55: 703.9698 | N55: 1766649.3 | O55: K.P. WOVEN PRIVATE LIMITED | P55: 262.0283
B56: Stores/Spares | C56: 139864.15 | D56: 1194.3535 | E56: 9870727.5 | F56: 39254.5 | G56: 198.94 | H56: 2805073.1 | I56: 35995.7 | J56: 123.9138 | K56: 1421527.6 | L56: 143122.95 | M56: 1268.7592 | N56: 11535625 | O56: K.P. WOVEN PRIVATE LIMITED | P56: 429.6511
B57: RM Consumables | C57: 241275.1 | D57: 131.7712 | E57: 1227315.4 | F57: 334290 | G57: 78.4 | H57: 1640492.5 | I57: 144290 | J57: 43.7776 | K57: 690954.3 | L57: 431275.1 | M57: 189.9353 | N57: 2279497.8 | O57: K.P. WOVEN PRIVATE LIMITED | P57: 80.5221
E58: =+E57+E56+E55+E54 -> 12271086 | H58: =+H57+H56+H55+H54 -> 5716571.5 | K58: =+K57+K56+K55+K54 -> 3038881.8 | N58: =+N57+N56+N55+N54 -> 15935752
B60: 01.05.2026 to 31.05.2026
B61: deptt | C61: Openingstock | D61: OpRate | E61: OpValue | F61: InwardsQty | G61: InwdRate | H61: InwdValue | I61: OutWardsQty | J61: OutRate | K61: Outvalue | L61: closingStk | M61: LatestRate | N61: ClosingAmount | O61: companyname | P61: AvgClosingRate
B62: Packing Material | C62: 47313.9 | D62: 186.8675 | E62: 251765.53 | F62: 5938.85 | G62: 105.94 | H62: 1342834.5 | I62: 47124.6 | J62: 90.705 | K62: 622938.2 | L62: 6128.15 | M62: 249.8544 | N62: 1003779.4 | O62: K.P. WOVEN PRIVATE LIMITED | P62: 159.8306
B63: Consumables | C63: 85298.3 | D63: 630.3825 | E63: 1686173.6 | F63: 32393 | G63: 120.86 | H63: 1265167.5 | I63: 17130 | J63: 130.8386 | K63: 926208.75 | L63: 100561.3 | M63: 717.9196 | N63: 2110797.6 | O63: K.P. WOVEN PRIVATE LIMITED | P63: 152.7805
B64: Stores/Spares | C64: 142865.95 | D64: 1242.56 | E64: 10906638 | F64: 30120.85 | G64: 163.22 | H64: 2655084.4 | I64: 37729.4 | J64: 194.1613 | K64: 2971763.3 | L64: 135257.4 | M64: 1311.9973 | N64: 11150909 | O64: K.P. WOVEN PRIVATE LIMITED | P64: 322.5557
B65: RM Consumables | C65: 431080.1 | D65: 138.982 | E65: 1907400.4 | F65: 284565 | G65: 29.54 | H65: 1230686.3 | I65: 138517 | J65: 74.1937 | K65: 701563.6 | L65: 577128.1 | M65: 176.4111 | N65: 2909404.4 | O65: K.P. WOVEN PRIVATE LIMITED | P65: 38.6734
E66: =SUM(E62:E65) -> 14751977 | H66: =SUM(H62:H65) -> 6493772.7 | K66: =SUM(K62:K65) -> 5222473.9 | N66: =SUM(N62:N65) -> 17174890
N68: =N66/10000000 -> 1.717489 | O68: Cr.
B69: 01.06.2026 to 30.06.2026
B70: deptt | C70: Openingstock | D70: OpRate | E70: OpValue | F70: InwardsQty | G70: InwdRate | H70: InwdValue | I70: OutWardsQty | J70: OutRate | K70: Outvalue | L70: closingStk | M70: LatestRate | N70: ClosingAmount | O70: companyname | P70: AvgClosingRate
B71: Packing Material | C71: 5371.3 | D71: 265.7444 | E71: 664534.29 | F71: 29615 | G71: 183.97 | H71: 867153.5 | I71: 28498 | J71: 207.475 | K71: 1443588.2 | L71: 6488.3 | M71: 280.0506 | N71: 333225.04 | O71: K.P. WOVEN PRIVATE LIMITED | P71: 61.6238
B72: Consumables | C72: 84289.6 | D72: 523.9811 | E72: 1847105.5 | F72: 22248 | G72: 62.28 | H72: 565182.12 | I72: 46160 | J72: 71.4494 | K72: 679940.57 | L72: 60377.6 | M72: 583.7952 | N72: 1406169.4 | O72: K.P. WOVEN PRIVATE LIMITED | P72: 49.9338
B73: Stores/Spares | C73: 129505.4 | D73: 1188.6654 | E73: 10323228 | F73: 42544.33 | G73: 83.7 | H73: 2050114.1 | I73: 22132.1 | J73: 145.4436 | K73: 1459706.9 | L73: 149917.63 | M73: 1250.7467 | N73: 11343358 | O73: K.P. WOVEN PRIVATE LIMITED | P73: 301.5508
B74: RM Consumables | C74: 403500.1 | D74: 131.0679 | E74: 1795648.7 | F74: 416236 | G74: 23.64 | H74: 1293779.1 | I74: 135943 | J74: 107.1461 | K74: 701991.16 | L74: 683793.1 | M74: 175.9295 | N74: 2842094.6 | O74: K.P. WOVEN PRIVATE LIMITED | P74: 16.7856
E75: =SUM(E71:E74) -> 14630516 | H75: =SUM(H71:H74) -> 4776228.8 | K75: =SUM(K71:K74) -> 4285226.9 | N75: =SUM(N71:N74) -> 15924847
N77: =N75/10000000 -> 1.5924847 | O77: Cr.
N78: =N75/100000 -> 159.24847
B79: 01.07.2026 to 31.07.2026
B81: deptt | C81: Openingstock | D81: OpRate | E81: OpValue | F81: InwardsQty | G81: InwdRate | H81: InwdValue | I81: OutWardsQty | J81: OutRate | K81: Outvalue | L81: closingStk | M81: LatestRate | N81: ClosingAmount | O81: companyname | P81: AvgClosingRate
B82: Packing Material | C82: 6488.3 | D82: 215.6778 | E82: 228672.92 | F82: 38166.48 | G82: 234.51 | H82: 1942428.2 | I82: 9924.6 | J82: 233.2217 | K82: 1786327.1 | L82: 34730.18 | M82: 259.7478 | N82: 517683.72 | O82: K.P. WOVEN PRIVATE LIMITED | P82: 78.2207
B83: Consumables | C83: 56574.6 | D83: 574.412 | E83: 972525.59 | F83: 44593 | G83: 208.56 | H83: 1036274 | I83: 31536 | J83: 99.3643 | K83: 781635.98 | L83: 69631.6 | M83: 629.1046 | N83: 1597467.2 | O83: K.P. WOVEN PRIVATE LIMITED | P83: 179.1957
B84: Stores/Spares | C84: 147238.63 | D84: 1189.7647 | E84: 10647112 | F84: 30566.63 | G84: 190.99 | H84: 2369988.2 | I84: 42089.43 | J84: 118.5547 | K84: 1820867.9 | L84: 135715.83 | M84: 1258.8645 | N84: 11695294 | O84: K.P. WOVEN PRIVATE LIMITED | P84: 401.3165
B85: RM Consumables | C85: 280452.1 | D85: 136.6992 | E85: 1857186.5 | F85: 148141 | G85: 31.54 | H85: 1738661.9 | I85: 339693 | J85: 34.5746 | K85: 1239762.2 | L85: 88900.1 | M85: 186.1419 | N85: 1109453.8 | O85: K.P. WOVEN PRIVATE LIMITED | P85: 92.0049
E86: =SUM(E82:E85) -> 13705497 | H86: =SUM(H82:H85) -> 7087352.2 | K86: =SUM(K82:K85) -> 5628593.2 | N86: =SUM(N82:N85) -> 14919898
N88: =N86/10000000 -> 1.4919898 | O88: Cr.
N89: =N86/100000 -> 149.19898
N92: =N78-N89 -> 10.049481

Sheet Purchase
N2: =SUBTOTAL(9,N4:N1000) -> 1414566 | O2: =SUBTOTAL(9,O4:O1000) -> 1.9130107e+08 | AF2: =SUBTOTAL(9,AF4:AF1000) -> 1414565.8 | AK2: =O2/N2 -> 135.23657
B3: Date | C3: Particular | D3: Voucher Type | E3: Voucher No | F3: Type | G3: Invoice No | H3: Invoice Date | I3: Main Grp | J3: Group Name | K3: Sub Grup | L3: purchase Group Name | M3: Item Name | N3: Quantity | O3: Amount | P3: Item Desc | Q3: Bill Amount | R3: CGST Rate | S3: CGST Amt | T3: SGST Rate | U3: SGST Amt | V3: IGST Rate | W3: IGST Amt | X3: Freight GST | Y3: Total GST | Z3: TCS | AA3: GST-IN | AB3: Unit | AC3: HSN Code | AD3: Currencty | AE3: Exc.Rate | AF3: Net Wt | AG3: Country | AH3: GROUP | AI3: 1 | AJ3: 1
B4: 46204 | C4: Eminent Globexim | D4: General Purchase | E4: GNCN 200 | F4: Purchase Withinstate- Stores, Spares & Consumable | G4: EG/2627/20 | H4: 46193 | I4: Packing Material | J4: Packaging Material | K4: Stores & Spares | L4: Consumables | M4: Pp Rope | N4: 262.1 | O4: 40887.6 | P4: Pp Rope | Q4: 43247 | R4: 2.5 | S4: 1029.69 | T4: 2.5 | U4: 1029.69 | V4: 0 | W4: 0 | X4: 0 | Y4: 2059.38 | Z4: 0 | AA4: 24AAIFE9434G1ZE | AB4: Kgs | AC4: 2853 | AD4: Rs. | AE4: 1 | AF4: 0 | AG4: India | AH4: N.A
B5: 46204 | C5: Ginza Machinery Mfg.Co. | D5: General Purchase | E5: GNSP 343 | F5: Purchase Withinstate- Stores, Spares & Consumable | G5: GINZA/26-27/0932 | H5: 46202 | I5: Stores/Spares | J5: Stitching Spares | K5: Stores & Spares | L5: stores & spares | M5: Needle Lever Connecting Rod ( Big Bkt.) # 502690 B | N5: 10 | O5: 5250 | P5: Needle Lever Connecting Rod ( Big Bkt.) # 502690 B | Q5: 18952 | R5: 2.5 | S5: 131.25 | T5: 2.5 | U5: 131.25 | V5: 0 | W5: 0 | X5: 0 | Y5: 262.5 | Z5: 0 | AA5: 24AAAFG5650J1ZJ | AB5: Pcs | AC5: 84529099 | AD5: Rs. | AE5: 1 | AF5: 0 | AG5: India | AH5: N.A
B6: 46204 | C6: Ginza Machinery Mfg.Co. | D6: General Purchase | E6: GNSP 343 | F6: Purchase Withinstate- Stores, Spares & Consumable | G6: GINZA/26-27/0932 | H6: 46202 | I6: Stores/Spares | J6: Stitching Spares | K6: Stores & Spares | L6: stores & spares | M6: Feed Bar Bracket 603616 | N6: 10 | O6: 5250 | P6: Feed Bar Bracket 603616 | Q6: 0 | R6: 2.5 | S6: 131.25 | T6: 2.5 | U6: 131.25 | V6: 0 | W6: 0 | X6: 0 | Y6: 262.5 | Z6: 0 | AA6: 24AAAFG5650J1ZJ | AB6: Pcs | AC6: 84529099 | AD6: Rs. | AE6: 1 | AF6: 0 | AG6: India | AH6: N.A
B7: 46204 | C7: Ginza Machinery Mfg.Co. | D7: General Purchase | E7: GNSP 343 | F7: Purchase Withinstate- Stores, Spares & Consumable | G7: GINZA/26-27/0932 | H7: 46202 | I7: Stores/Spares | J7: Stitching Spares | K7: Stores & Spares | L7: stores & spares | M7: 502683 (Needle Lever Conn. Rod Bkt. (Small ) | N7: 10 | O7: 4550 | P7: 502683 (Needle Lever Conn. Rod Bkt. (Small ) | Q7: 0 | R7: 2.5 | S7: 113.75 | T7: 2.5 | U7: 113.75 | V7: 0 | W7: 0 | X7: 0 | Y7: 227.5 | Z7: 0 | AA7: 24AAAFG5650J1ZJ | AB7: Pcs | AC7: 845290 | AD7: Rs. | AE7: 1 | AF7: 0 | AG7: India | AH7: N.A
B8: 46204 | C8: Ginza Machinery Mfg.Co. | D8: General Purchase | E8: GNSP 343 | F8: Purchase Withinstate- Stores, Spares & Consumable | G8: GINZA/26-27/0932 | H8: 46202 | I8: Stores/Spares | J8: Stitching Spares | K8: Stores & Spares | L8: stores & spares | M8: Looper Avoid Eccentric Fork 603516 | N8: 5 | O8: 2100 | P8: Looper Avoid Eccentric Fork 603516 | Q8: 0 | R8: 2.5 | S8: 75 | T8: 2.5 | U8: 75 | V8: 0 | W8: 0 | X8: 0 | Y8: 150 | Z8: 0 | AA8: 24AAAFG5650J1ZJ | AB8: Pcs | AC8: 84529099 | AD8: Rs. | AE8: 1 | AF8: 0 | AG8: India | AH8: N.A
B9: 46204 | C9: HCP Plastene Bulkpack Limited - Purchase | D9: R.M.P. | E9: RM 239 | F9: Purchase Withinstate - Raw Material | G9: HPBL/D/328 | H9: 46203 | I9: SF | J9: PP/PE Fabric | K9: PP UL Fabric | L9: PP WOVEN FABRIC | M9: PP UL Fabric With UV | N9: 317 | O9: 70342.3 | P9: PP UL Fabric With UV | Q9: 1084907.1 | R9: 9 | S9: 6330.81 | T9: 9 | U9: 6330.81 | V9: 0 | W9: 0 | X9: 0 | Y9: 12661.62 | Z9: 0 | AA9: 24AABCG1282C2Z6 | AB9: Kgs | AC9: 39269080 | AD9: Rs. | AE9: 1 | AF9: 317 | AG9: India | AH9: PP UL Fabric
B10: 46204 | C10: HCP Plastene Bulkpack Limited - Purchase | D10: R.M.P. | E10: RM 239 | F10: Purchase Withinstate - Raw Material | G10: HPBL/D/328 | H10: 46203 | I10: SF | J10: PP/PE Fabric | K10: PP UL Fabric | L10: PP WOVEN FABRIC | M10: PP UL Fabric With UV | N10: 629 | O10: 100577.1 | P10: PP UL Fabric With UV | Q10: 0 | R10: 9 | S10: 9051.94 | T10: 9 | U10: 9051.94 | V10: 0 | W10: 0 | X10: 0 | Y10: 18103.88 | Z10: 0 | AA10: 24AABCG1282C2Z6 | AB10: Kgs | AC10: 39269080 | AD10: Rs. | AE10: 1 | AF10: 629 | AG10: India | AH10: PP UL Fabric
B11: 46204 | C11: HCP Plastene Bulkpack Limited - Purchase | D11: R.M.P. | E11: RM 239 | F11: Purchase Withinstate - Raw Material | G11: HPBL/D/328 | H11: 46203 | I11: SF | J11: PP/PE Fabric | K11: PP UL Fabric | L11: PP WOVEN FABRIC | M11: PP UL Fabric With UV | N11: 4628 | O11: 749273.2 | P11: PP UL Fabric With UV | Q11: 0 | R11: 9 | S11: 67434.59 | T11: 9 | U11: 67434.59 | V11: 0 | W11: 0 | X11: 0 | Y11: 134869.18 | Z11: 0 | AA11: 24AABCG1282C2Z6 | AB11: Kgs | AC11: 39269080 | AD11: Rs. | AE11: 1 | AF11: 4628 | AG11: India | AH11: PP UL Fabric
B12: 46204 | C12: HCP Plastene Bulkpack Limited - Purchase | D12: R.M.P. | E12: RM 241 | F12: Purchase Withinstate - Raw Material | G12: HPBL/D/336 | H12: 46204 | I12: SF | J12: PP/PE Fabric | K12: PP UL Fabric | L12: PP WOVEN FABRIC | M12: PP UL Fabric With UV | N12: 657 | O12: 106368.3 | P12: PP UL Fabric With UV | Q12: 545314.62 | R12: 9 | S12: 9573.15 | T12: 9 | U12: 9573.15 | V12: 0 | W12: 0 | X12: 0 | Y12: 19146.3 | Z12: 0 | AA12: 24AABCG1282C2Z6 | AB12: Kgs | AC12: 39269080 | AD12: Rs. | AE12: 1 | AF12: 657 | AG12: India | AH12: PP UL Fabric
B13: 46204 | C13: HCP Plastene Bulkpack Limited - Purchase | D13: R.M.P. | E13: RM 241 | F13: Purchase Withinstate - Raw Material | G13: HPBL/D/336 | H13: 46204 | I13: SF | J13: PP/PE Fabric | K13: PP Lam Fabric | L13: PP LAMINETED FABRIC | M13: PP Lam Fabric With UV | N13: 2173 | O13: 356154.7 | P13: PP Lam Fabric With UV | Q13: 0 | R13: 9 | S13: 32053.92 | T13: 9 | U13: 32053.92 | V13: 0 | W13: 0 | X13: 0 | Y13: 64107.84 | Z13: 0 | AA13: 24AABCG1282C2Z6 | AB13: Kgs | AC13: 63053300 | AD13: Rs. | AE13: 1 | AF13: 2173 | AG13: India | AH13: PP Lam Fabric
B14: 46204 | C14: Labbdhi Paper Tubes Pvt Ltd | D14: General Purchase | E14: GNPK 121 | F14: Purchase Withinstate- Packing Material | G14: 407/2026-27 | H14: 46203 | I14: Packing Material | J14: Paper Cores | K14: Packing Materials | L14: Packing Materials | M14: Paper Core | N14: 1845 | O14: 66420 | P14: Paper Core | Q14: 78376 | R14: 9 | S14: 5977.8 | T14: 9 | U14: 5977.8 | V14: 0 | W14: 0 | X14: 0 | Y14: 11955.6 | Z14: 0 | AA14: 24AACCL4303N1ZM | AB14: Kgs | AC14: 482290 | AD14: Rs. | AE14: 1 | AF14: 0 | AG14: India | AH14: N.A
B15: 46204 | C15: Lohia Corp Limited - 09AAKCK2932Q1ZU - UP | D15: General Purchase | E15: GNSP 341 | F15: Purchase Interstate- Stores, Spares & Consumable | G15: TG0926110178 | H15: 46199 | I15: Stores/Spares | J15: Cutting Machine Spares | K15: Stores & Spares | L15: stores & spares | M15: Top Pinch Roller Shaft 11169158800 | N15: 1 | O15: 11875 | P15: Top Pinch Roller Shaft 11169158800 | Q15: 26985.42 | R15: 0 | S15: 0 | T15: 0 | U15: 0 | V15: 18 | W15: 2137.5 | X15: 166.32 | Y15: 2303.82 | Z15: 0 | AA15: 09AAKCK2932Q1ZU | AB15: Pcs | AC15: 84799090 | AD15: Rs. | AE15: 1 | AF15: 0 | AG15: India | AH15: N.A
... B28: 46204 | C28: Satyam Stationery Mart | D28: General Purchase | E28: GNPK 124 | F28: Purchase Withinstate- Packing Material | G28: SSM01911 | H28: 46202 | I28: Stores/Spares | J28: Cutter Blades | K28: Packing Materials | L28: Packing Materials | M28: Scissor Plastic Handle | N28: 20 | O28: 1240 | P28: Scissor Plastic Handle | Q28: 1463 | R28: 9 | S28: 111.6 | T28: 9 | U28: 111.6 | V28: 0 | W28: 0 | X28: 0 | Y28: 223.2 | Z28: 0 | AA28: 24AGUPL9792N1Z6 | AB28: Pcs | AC28: 82130000 | AD28: Rs. | AE28: 1 | AF28: 0 | AG28: India | AH28: N.A
B29: 46204 | C29: Shree Ganesh Stereo | D29: General Purchase | E29: GNCN 201 | F29: Purchase Withinstate- Stores, Spares & Consumable | G29: 1184 | H29: 46200 | I29: Consumables | J29: Rubber/Polymer Stereo | K29: Stores & Spares | L29: Consumables | M29: Rubber Stereo | N29: 1 | O29: 84 | P29: Rubber Stereo | Q29: 1010 | R29: 9 | S29: 7.56 | T29: 9 | U29: 7.56 | V29: 0 | W29: 0 | X29: 0 | Y29: 15.12 | Z29: 0 | AA29: 24AHDPC2510M1ZU | AB29: PCS | AC29: 400200 | AD29: Rs. | AE29: 1 | AF29: 0 | AG29: India | AH29: N.A
B30: 46204 | C30: Shree Ganesh Stereo | D30: General Purchase | E30: GNCN 201 | F30: Purchase Withinstate- Stores, Spares & Consumable | G30: 1184 | H30: 46200 | I30: Consumables | J30: Rubber/Polymer Stereo | K30: Stores & Spares | L30: Consumables | M30: Rubber Stereo | N30: 1 | O30: 771.75 | P30: Rubber Stereo | Q30: 0 | R30: 9 | S30: 69.46 | T30: 9 | U30: 69.46 | V30: 0 | W30: 0 | X30: 0 | Y30: 138.92 | Z30: 0 | AA30: 24AHDPC2510M1ZU | AB30: PCS | AC30: 400200 | AD30: Rs. | AE30: 1 | AF30: 0 | AG30: India | AH30: N.A
B31: 46204 | C31: Shree Meter & Heater | D31: General Purchase | E31: GNSP 342 | F31: Purchase Withinstate- Stores, Spares & Consumable | G31: G/0219 | H31: 46203 | I31: Stores/Spares | J31: Heaters | K31: Stores & Spares | L31: stores & spares | M31: Ceramic Heater 300mm(D)X45mm(L) 240 V A.C.2000 W | N31: 5 | O31: 10900 | P31: Ceramic Heater 300mm(D)X45mm(L) 240 V A.C.2000 W | Q31: 13511 | R31: 9 | S31: 981 | T31: 9 | U31: 981 | V31: 0 | W31: 0 | X31: 99 | Y31: 2061 | Z31: 0 | AA31: 24BEGPR0567G1ZH | AB31: Pcs | AC31: 851680 | AD31: Rs. | AE31: 1 | AF31: 0 | AG31: India | AH31: N.A
B32: 46204 | C32: Shree Salareshwar Wood Packers Private Limited. | D32: Purchase | E32: GNPK 122 | F32: Purchase Withinstate- Packing Material | G32: SS/SL/26-27/189 | H32: 46204 | I32: Packing Material | J32: Pallets | K32: Pallets | L32: Packing Materials | M32: Pine Wooden Pallet Design Code STD90110 | N32: 150 | O32: 108750 | P32: Pine Wooden Pallet Design Code STD90110 | Q32: 114188 | R32: 2.5 | S32: 2718.75 | T32: 2.5 | U32: 2718.75 | V32: 0 | W32: 0 | X32: 0 | Y32: 5437.5 | Z32: 0 | AA32: 24ABLCS6579H1ZR | AB32: Pcs | AC32: 44152000 | AD32: Rs. | AE32: 1 | AF32: 0 | AG32: India | AH32: N.A
B33: 46204 | C33: West India Forklift Services | D33: General Purchase | E33: GNSP 344 | F33: Purchase Withinstate- Stores, Spares & Consumable | G33: WI2627/0148 | H33: 46202 | I33: Stores/Spares | J33: Forklift Spares | K33: Stores & Spares | L33: stores & spares | M33: Fog Lamp For Forklift Head Light | N33: 4 | O33: 13040 | P33: Fog Lamp For Forklift Head Light | Q33: 15387 | R33: 9 | S33: 1173.6 | T33: 9 | U33: 1173.6 | V33: 0 | W33: 0 | X33: 0 | Y33: 2347.2 | Z33: 0 | AA33: 24AOQPC4561C2Z7 | AB33: PCS | AC33: 85399090 | AD33: Rs. | AE33: 1 | AF33: 0 | AG33: India | AH33: N.A
B34: 46205 | C34: Arham Cams Pvt Ltd | D34: General Purchase | E34: GNSP 345 | F34: Purchase Withinstate- Stores, Spares & Consumable | G34: GST/50. | H34: 46144 | I34: Stores/Spares | J34: Sulzer Machine Spares | K34: Stores & Spares | L34: stores & spares | M34: Sliding Catch For P7100 Part no.911.801.104 | N34: 100 | O34: 8000 | P34: Sliding Catch For P7100 Part no.911.801.104 | Q34: 26845 | R34: 9 | S34: 720 | T34: 9 | U34: 720 | V34: 0 | W34: 0 | X34: 72 | Y34: 1512 | Z34: 0 | AA34: 24AAICA0799H1ZK | AB34: Pcs | AC34: 844810 | AD34: Rs. | AE34: 1 | AF34: 0 | AG34: India | AH34: N.A
B35: 46205 | C35: Arham Cams Pvt Ltd | D35: General Purchase | E35: GNSP 345 | F35: Purchase Withinstate- Stores, Spares & Consumable | G35: GST/50. | H35: 46144 | I35: Stores/Spares | J35: Sulzer Machine Spares | K35: Stores & Spares | L35: stores & spares | M35: Drive shaft p7100, 911803136 | N35: 1 | O35: 14350 | P35: Drive shaft p7100, 911803136 | Q35: 0 | R35: 9 | S35: 1291.5 | T35: 9 | U35: 1291.5 | V35: 0 | W35: 0 | X35: 72 | Y35: 2655 | Z35: 0 | AA35: 24AAICA0799H1ZK | AB35: Pcs | AC35: 84484990 | AD35: Rs. | AE35: 1 | AF35: 0 | AG35: India | AH35: N.A
B36: 46205 | C36: Dynamic Wooltex | D36: R.M.P. | E36: RM 246 | F36: Purchase Withinstate - Raw Material | G36: 13524 | H36: 46202 | I36: RM | J36: FIBC Accessories | K36: FIBC Accessories | L36: PP WOVEN FABRIC | M36: Non Woven Fabric (Felt) 170Gsm.Pati Cut Length- 2" ( 5 Cm ) (Food Grade Quality) | N36: 1699.3 | O36: 254895 | P36: Non Woven Fabric (Felt) 170Gsm.Pati Cut Length- 2" ( 5 Cm ) (Food Grade Quality) | Q36: 283389.75 | R36: 0 | S36: 0 | T36: 0 | U36: 0 | V36: 5 | W36: 12744.75 | X36: 750 | Y36: 13494.75 | Z36: 0 | AA36: 08ABFPB2251A1ZI | AB36: Kgs | AC36: 58079010 | AD36: Rs. | AE36: 1 | AF36: 1699.3 | AG36: India | AH36: FIBC Accessories
B37: 46205 | C37: J J Plastalloy Pvt Ltd | D37: R.M.P. | E37: RM 245 | F37: Purchase Withinstate - Raw Material | G37: DG-261002398 | H37: 46203 | I37: RM | J37: Granules | K37: Masterbatch | L37: Master batch | M37: MB JJ White WE9381PT | N37: 500 | O37: 89000 | P37: MB JJ White WE9381PT | Q37: 105020 | R37: 9 | S37: 8010 | T37: 9 | U37: 8010 | V37: 0 | W37: 0 | X37: 0 | Y37: 16020 | Z37: 0 | AA37: 24AAACJ5701E1Z5 | AB37: Kgs | AC37: 32064990 | AD37: Rs. | AE37: 1 | AF37: 500 | AG37: India | AH37: Masterbatch
B38: 46205 | C38: Plastene India ltd - Unit 1-Purchase | D38: Purchase | E38: GNPK 125 | F38: Purchase Withinstate- Packing Material | G38: PIL1/D/880 | H38: 46204 | I38: Stores/Spares | J38: MS Structure Items | K38: Packing Materials | L38: Packing Materials | M38: MS Pipe 4 C Class | N38: 255 | O38: 12240 | P38: MS Pipe 4 C Class | Q38: 14430.96 | R38: 9 | S38: 1101.6 | T38: 9 | U38: 1101.6 | V38: 0 | W38: 0 | X38: 0 | Y38: 2203.2 | Z38: 0 | AA38: 24AAACO3087C1ZT | AB38: Kgs | AC38: 73063090 | AD38: Rs. | AE38: 1 | AF38: 0 | AG38: India | AH38: N.A
B39: 46205 | C39: Plastene India ltd - Unit 1-Purchase | D39: R.M.P. | E39: RM 243 | F39: Purchase Withinstate - Raw Material | G39: PIL1/D/879 | H39: 46204 | I39: RM | J39: Granules | K39: PP Granules | L39: PP Granuals | M39: PP Basell 462S | N39: 2000 | O39: 300000 | P39: PP Basell 462S | Q39: 353700 | R39: 9 | S39: 27000 | T39: 9 | U39: 27000 | V39: 0 | W39: 0 | X39: 0 | Y39: 54000 | Z39: 0 | AA39: 24AAACO3087C1ZT | AB39: Kgs | AC39: 39021000 | AD39: Rs. | AE39: 1 | AF39: 2000 | AG39: India | AH39: PP Granules
B40: 46205 | C40: Plastene India ltd - Unit 1-Purchase | D40: R.M.P. | E40: RM 244 | F40: Purchase Withinstate - Raw Material | G40: PIL1/D/881 | H40: 46204 | I40: SF | J40: Liners | K40: LDPE/LLDPE Bags | L40: LLDPE BAGS | M40: LDPE/LLDPE Bags/Liner | N40: 949 | O40: 175707.35 | P40: LDPE/LLDPE Bags/Liner | Q40: 212925.5 | R40: 9 | S40: 15813.66 | T40: 9 | U40: 15813.66 | V40: 0 | W40: 0 | X40: 0 | Y40: 31627.32 | Z40: 0 | AA40: 24AAACO3087C1ZT | AB40: Kgs | AC40: 39200000 | AD40: Rs. | AE40: 1 | AF40: 949 | AG40: India | AH40: LDPE/LLDPE Bags
B41: 46205 | C41: Plastene India ltd - Unit 1-Purchase | D41: R.M.P. | E41: RM 244 | F41: Purchase Withinstate - Raw Material | G41: PIL1/D/881 | H41: 46204 | I41: SF | J41: Liners | K41: LDPE/LLDPE Bags | L41: LLDPE BAGS | M41: LDPE/LLDPE Bags/Liner | N41: 27 | O41: 4891.05 | P41: LDPE/LLDPE Bags/Liner | Q41: 0 | R41: 9 | S41: 440.19 | T41: 9 | U41: 440.19 | V41: 0 | W41: 0 | X41: 0 | Y41: 880.38 | Z41: 0 | AA41: 24AAACO3087C1ZT | AB41: Kgs | AC41: 39200000 | AD41: Rs. | AE41: 1 | AF41: 27 | AG41: India | AH41: LDPE/LLDPE Bags
B42: 46205 | C42: Shree Ganesh Stereo | D42: General Purchase | E42: GNCN 202 | F42: Purchase Withinstate- Stores, Spares & Consumable | G42: 1214 | H42: 46202 | I42: Consumables | J42: Rubber/Polymer Stereo | K42: Stores & Spares | L42: Consumables | M42: Rubber Stereo | N42: 1 | O42: 2832.9 | P42: Rubber Stereo | Q42: 5785 | R42: 9 | S42: 254.96 | T42: 9 | U42: 254.96 | V42: 0 | W42: 0 | X42: 0 | Y42: 509.92 | Z42: 0 | AA42: 24AHDPC2510M1ZU | AB42: PCS | AC42: 400200 | AD42: Rs. | AE42: 1 | AF42: 0 | AG42: India | AH42: N.A
B43: 46205 | C43: Shree Ganesh Stereo | D43: General Purchase | E43: GNCN 202 | F43: Purchase Withinstate- Stores, Spares & Consumable | G43: 1214 | H43: 46202 | I43: Consumables | J43: Rubber/Polymer Stereo | K43: Stores & Spares | L43: Consumables | M43: Rubber Stereo | N43: 1 | O43: 2069.55 | P43: Rubber Stereo | Q43: 0 | R43: 9 | S43: 186.26 | T43: 9 | U43: 186.26 | V43: 0 | W43: 0 | X43: 0 | Y43: 372.52 | Z43: 0 | AA43: 24AHDPC2510M1ZU | AB43: PCS | AC43: 400200 | AD43: Rs. | AE43: 1 | AF43: 0 | AG43: India | AH43: N.A
B44: 46205 | C44: Shri Nakoda Transmission & Electric Co. | D44: General Purchase | E44: GNSP 346 | F44: Purchase Withinstate- Stores, Spares & Consumable | G44: VTV/26-27/1591 | H44: 46197 | I44: Stores/Spares | J44: IT Spares | K44: Stores & Spares | L44: stores & spares | M44: 8 Port Dlink Switch | N44: 20 | O44: 1100 | P44: 8 Port Dlink Switch | Q44: 8575 | R44: 9 | S44: 99 | T44: 9 | U44: 99 | V44: 0 | W44: 0 | X44: 36 | Y44: 234 | Z44: 0 | AA44: 24AFGFS2586E1ZX | AB44: Pcs | AC44: 85176990 | AD44: Rs. | AE44: 1 | AF44: 0 | AG44: India | AH44: N.A
B45: 46205 | C45: Shri Nakoda Transmission & Electric Co. | D45: General Purchase | E45: GNSP 346 | F45: Purchase Withinstate- Stores, Spares & Consumable | G45: VTV/26-27/1591 | H45: 46197 | I45: Stores/Spares | J45: IT Spares | K45: Stores & Spares | L45: stores & spares | M45: 8 Port Dlink Switch | N45: 6 | O45: 342 | P45: 8 Port Dlink Switch | Q45: 0 | R45: 9 | S45: 30.78 | T45: 9 | U45: 30.78 | V45: 0 | W45: 0 | X45: 36 | Y45: 97.56 | Z45: 0 | AA45: 24AFGFS2586E1ZX | AB45: Pcs | AC45: 85176990 | AD45: Rs. | AE45: 1 | AF45: 0 | AG45: India | AH45: N.A
B46: 46205 | C46: Shri Nakoda Transmission & Electric Co. | D46: General Purchase | E46: GNSP 346 | F46: Purchase Withinstate- Stores, Spares & Consumable | G46: VTV/26-27/1591 | H46: 46197 | I46: Stores/Spares | J46: IT Spares | K46: Stores & Spares | L46: stores & spares | M46: 8 Port Dlink Switch | N46: 45 | O46: 5625 | P46: 8 Port Dlink Switch | Q46: 0 | R46: 9 | S46: 506.25 | T46: 9 | U46: 506.25 | V46: 0 | W46: 0 | X46: 36 | Y46: 1048.5 | Z46: 0 | AA46: 24AFGFS2586E1ZX | AB46: Pcs | AC46: 85176990 | AD46: Rs. | AE46: 1 | AF46: 0 | AG46: India | AH46: N.A
B47: 46206 | C47: Axle Steel & Fasteners | D47: General Purchase | E47: GNSP 348 | F47: Purchase Withinstate- Stores, Spares & Consumable | G47: 0524/26-27 | H47: 46204 | I47: Stores/Spares | J47: Hardware Items | K47: Stores & Spares | L47: stores & spares | M47: Allen Bolt 12X40 mm | N47: 30 | O47: 407.232 | P47: Allen Bolt 12X40 mm | Q47: 3507 | R47: 9 | S47: 36.6509 | T47: 9 | U47: 36.6509 | V47: 0 | W47: 0 | X47: 32.4 | Y47: 105.70176 | Z47: 0 | AA47: 24AAYFA5084G1Z4 | AB47: PCS | AC47: 73181500 | AD47: Rs. | AE47: 1 | AF47: 0 | AG47: India | AH47: N.A
B48: 46206 | C48: Axle Steel & Fasteners | D48: General Purchase | E48: GNSP 348 | F48: Purchase Withinstate- Stores, Spares & Consumable | G48: 0524/26-27 | H48: 46204 | I48: Stores/Spares | J48: Hardware Items | K48: Stores & Spares | L48: stores & spares | M48: Grub Screw 12X30 mm ( Ub / Tvs ) | N48: 50 | O48: 422.52 | P48: Grub Screw 12X30 mm ( Ub / Tvs ) | Q48: 0 | R48: 9 | S48: 38.0268 | T48: 9 | U48: 38.0268 | V48: 0 | W48: 0 | X48: 32.4 | Y48: 108.4536 | Z48: 0 | AA48: 24AAYFA5084G1Z4 | AB48: Pcs | AC48: 73181900 | AD48: Rs. | AE48: 1 | AF48: 0 | AG48: India | AH48: N.A
B49: 46206 | C49: Axle Steel & Fasteners | D49: General Purchase | E49: GNSP 348 | F49: Purchase Withinstate- Stores, Spares & Consumable | G49: 0524/26-27 | H49: 46204 | I49: Stores/Spares | J49: Hardware Items | K49: Stores & Spares | L49: stores & spares | M49: Allen Bolt 14X40 mm | N49: 30 | O49: 923.454 | P49: Allen Bolt 14X40 mm | Q49: 0 | R49: 9 | S49: 83.1109 | T49: 9 | U49: 83.1109 | V49: 0 | W49: 0 | X49: 32.4 | Y49: 198.62172 | Z49: 0 | AA49: 24AAYFA5084G1Z4 | AB49: Pcs | AC49: 731819 | AD49: Rs. | AE49: 1 | AF49: 0 | AG49: India | AH49: N.A
B50: 46206 | C50: Axle Steel & Fasteners | D50: General Purchase | E50: GNSP 348 | F50: Purchase Withinstate- Stores, Spares & Consumable | G50: 0524/26-27 | H50: 46204 | I50: Stores/Spares | J50: Hardware Items | K50: Stores & Spares | L50: stores & spares | M50: MS Hex Nipple 1/2" | N50: 3 | O50: 66 | P50: MS Hex Nipple 1/2" | Q50: 0 | R50: 9 | S50: 5.94 | T50: 9 | U50: 5.94 | V50: 0 | W50: 0 | X50: 32.4 | Y50: 44.28 | Z50: 0 | AA50: 24AAYFA5084G1Z4 | AB50: PCS | AC50: 730799 | AD50: Rs. | AE50: 1 | AF50: 0 | AG50: India | AH50: N.A
B51: 46206 | C51: Axle Steel & Fasteners | D51: General Purchase | E51: GNSP 348 | F51: Purchase Withinstate- Stores, Spares & Consumable | G51: 0524/26-27 | H51: 46204 | I51: Stores/Spares | J51: Hardware Items | K51: Stores & Spares | L51: stores & spares | M51: Hyd. Hex Nipple 1" | N51: 3 | O51: 126 | P51: Hyd. Hex Nipple 1" | Q51: 0 | R51: 9 | S51: 11.34 | T51: 9 | U51: 11.34 | V51: 0 | W51: 0 | X51: 32.4 | Y51: 55.08 | Z51: 0 | AA51: 24AAYFA5084G1Z4 | AB51: Pcs | AC51: 73079190 | AD51: Rs. | AE51: 1 | AF51: 0 | AG51: India | AH51: N.A
B52: 46206 | C52: Axle Steel & Fasteners | D52: General Purchase | E52: GNSP 348 | F52: Purchase Withinstate- Stores, Spares & Consumable | G52: 0524/26-27 | H52: 46204 | I52: Stores/Spares | J52: Hardware Items | K52: Stores & Spares | L52: stores & spares | M52: Hydraulic Hex Nipple 2" | N52: 3 | O52: 525 | P52: Hydraulic Hex Nipple 2" | Q52: 0 | R52: 9 | S52: 47.25 | T52: 9 | U52: 47.25 | V52: 0 | W52: 0 | X52: 32.4 | Y52: 126.9 | Z52: 0 | AA52: 24AAYFA5084G1Z4 | AB52: Pcs | AC52: 730700 | AD52: Rs. | AE52: 1 | AF52: 0 | AG52: India | AH52: N.A
B53: 46206 | C53: Axle Steel & Fasteners | D53: General Purchase | E53: GNSP 348 | F53: Purchase Withinstate- Stores, Spares & Consumable | G53: 0524/26-27 | H53: 46204 | I53: Stores/Spares | J53: Hardware Items | K53: Stores & Spares | L53: stores & spares | M53: Grub Screw 10X15 | N53: 100 | O53: 322.14 | P53: Grub Screw 10X15 | Q53: 0 | R53: 9 | S53: 28.9926 | T53: 9 | U53: 28.9926 | V53: 0 | W53: 0 | X53: 32.4 | Y53: 90.3852 | Z53: 0 | AA53: 24AAYFA5084G1Z4 | AB53: Pcs | AC53: 73181900 | AD53: Rs. | AE53: 1 | AF53: 0 | AG53: India | AH53: N.A
B54: 46206 | C54: HCP Plastene Bulkpack Limited - Purchase | D54: R.M.P. | E54: RM 247 | F54: Purchase Withinstate - Raw Material | G54: HPBL/D/342 | H54: 46206 | I54: SF | J54: Liners | K54: LDPE/LLDPE Bags | L54: LLDPE BAGS | M54: DOC Pouch | N54: 627 | O54: 121004.73 | P54: DOC Pouch | Q54: 1452008.8 | R54: 9 | S54: 10890.43 | T54: 9 | U54: 10890.43 | V54: 0 | W54: 0 | X54: 0 | Y54: 21780.86 | Z54: 0 | AA54: 24AABCG1282C2Z6 | AB54: Kgs | AC54: 39232100 | AD54: Rs. | AE54: 1 | AF54: 627 | AG54: India | AH54: LDPE/LLDPE Bags
B55: 46206 | C55: HCP Plastene Bulkpack Limited - Purchase | D55: R.M.P. | E55: RM 247 | F55: Purchase Withinstate - Raw Material | G55: HPBL/D/342 | H55: 46206 | I55: SF | J55: PP/PE Fabric | K55: PP UL Fabric | L55: PP WOVEN FABRIC | M55: PP UL Fabric With UV | N55: 5320 | O55: 861308 | P55: PP UL Fabric With UV | Q55: 0 | R55: 9 | S55: 77517.72 | T55: 9 | U55: 77517.72 | V55: 0 | W55: 0 | X55: 0 | Y55: 155035.44 | Z55: 0 | AA55: 24AABCG1282C2Z6 | AB55: Kgs | AC55: 39269080 | AD55: Rs. | AE55: 1 | AF55: 5320 | AG55: India | AH55: PP UL Fabric
... B64: 46206 | C64: United Transmission | D64: General Purchase | E64: GNSP 349 | F64: Purchase Withinstate- Stores, Spares & Consumable | G64: UT/2700621 | H64: 46204 | I64: Stores/Spares | J64: Gear Box | K64: Stores & Spares | L64: stores & spares | M64: Worm Gearbox Make:Elecon,Model :3Nu | N64: 1 | O64: 7500 | P64: Worm Gearbox Make:Elecon,Model :3Nu | Q64: 9204 | R64: 9 | S64: 702 | T64: 9 | U64: 702 | V64: 0 | W64: 0 | X64: 0 | Y64: 1404 | Z64: 0 | AA64: 24AACFU1059P1ZW | AB64: Pcs | AC64: 848340 | AD64: Rs. | AE64: 1 | AF64: 0 | AG64: India | AH64: N.A
B65: 46207 | C65: Brahmani Labels | D65: General Purchase | E65: GNCN 204 | F65: Purchase Withinstate- Stores, Spares & Consumable | G65: 278 | H65: 46205 | I65: SF | J65: Liners | K65: LDPE/LLDPE Bags | L65: Consumables | M65: PE Labels (Pcs) | N65: 29.1 | O65: 11479 | P65: PE Labels (Pcs) | Q65: 69229 | R65: 9 | S65: 1033.11 | T65: 9 | U65: 1033.11 | V65: 0 | W65: 0 | X65: 0 | Y65: 2066.22 | Z65: 0 | AA65: 24CIAPP4681A1ZK | AB65: Kgs | AC65: 392300 | AD65: Rs. | AE65: 1 | AF65: 29.1 | AH65: N.A
B66: 46207 | C66: Brahmani Labels | D66: General Purchase | E66: GNCN 204 | F66: Purchase Withinstate- Stores, Spares & Consumable | G66: 278 | H66: 46205 | I66: SF | J66: Liners | K66: LDPE/LLDPE Bags | L66: Consumables | M66: PE Labels (Pcs) | N66: 101.5 | O66: 39988 | P66: PE Labels (Pcs) | Q66: 0 | R66: 9 | S66: 3598.92 | T66: 9 | U66: 3598.92 | V66: 0 | W66: 0 | X66: 0 | Y66: 7197.84 | Z66: 0 | AA66: 24CIAPP4681A1ZK | AB66: Kgs | AC66: 392300 | AD66: Rs. | AE66: 1 | AF66: 101.5 | AH66: N.A
B67: 46207 | C67: Brahmani Labels | D67: General Purchase | E67: GNCN 204 | F67: Purchase Withinstate- Stores, Spares & Consumable | G67: 278 | H67: 46205 | I67: SF | J67: Liners | K67: LDPE/LLDPE Bags | L67: Consumables | M67: PE Labels (Pcs) | N67: 8.5 | O67: 3367 | P67: PE Labels (Pcs) | Q67: 0 | R67: 9 | S67: 303.03 | T67: 9 | U67: 303.03 | V67: 0 | W67: 0 | X67: 0 | Y67: 606.06 | Z67: 0 | AA67: 24CIAPP4681A1ZK | AB67: Kgs | AC67: 392300 | AD67: Rs. | AE67: 1 | AF67: 8.5 | AH67: N.A
B68: 46207 | C68: Brahmani Labels | D68: General Purchase | E68: GNCN 204 | F68: Purchase Withinstate- Stores, Spares & Consumable | G68: 278 | H68: 46205 | I68: SF | J68: Liners | K68: LDPE/LLDPE Bags | L68: Consumables | M68: PE Labels (Pcs) | N68: 8.5 | O68: 3835 | P68: PE Labels (Pcs) | Q68: 0 | R68: 9 | S68: 345.15 | T68: 9 | U68: 345.15 | V68: 0 | W68: 0 | X68: 0 | Y68: 690.3 | Z68: 0 | AA68: 24CIAPP4681A1ZK | AB68: Kgs | AC68: 392300 | AD68: Rs. | AE68: 1 | AF68: 8.5 | AH68: N.A
B69: 46207 | C69: Brahmani Printers | D69: General Purchase | E69: GNCN 203 | F69: Purchase Withinstate- Stores, Spares & Consumable | G69: 304 | H69: 46205 | I69: RM Consumables | J69: FIBC Accessories | K69: FIBC Accessories | L69: Consumables | M69: Tyvek Labels (Pcs) | N69: 600 | O69: 840 | P69: Tyvek Labels (Pcs) | Q69: 4531 | R69: 9 | S69: 75.6 | T69: 9 | U69: 75.6 | V69: 0 | W69: 0 | X69: 90 | Y69: 241.2 | Z69: 0 | AA69: 24CSJPP6974M1ZU | AB69: Pcs | AC69: 58079010 | AD69: Rs. | AE69: 1 | AF69: 1.9 | AG69: India | AH69: N.A
B70: 46207 | C70: Brahmani Printers | D70: General Purchase | E70: GNCN 203 | F70: Purchase Withinstate- Stores, Spares & Consumable | G70: 304 | H70: 46205 | I70: RM Consumables | J70: FIBC Accessories | K70: FIBC Accessories | L70: Consumables | M70: Tyvek Labels (Pcs) | N70: 5000 | O70: 2500 | P70: Tyvek Labels (Pcs) | Q70: 0 | R70: 9 | S70: 225 | T70: 9 | U70: 225 | V70: 0 | W70: 0 | X70: 90 | Y70: 540 | Z70: 0 | AA70: 24CSJPP6974M1ZU | AB70: Pcs | AC70: 58079010 | AD70: Rs. | AE70: 1 | AF70: 16.5 | AG70: India | AH70: N.A
B71: 46207 | C71: HCP Plastene Bulkpack Limited - Purchase | D71: R.M.P. | E71: RM 249 | F71: Purchase Withinstate - Raw Material | G71: HPBL/D/345 | H71: 46207 | I71: FG | J71: FIBC Bags | K71: FIBC Bags | L71: PP WOVEN BIG BAGS / SACKS | M71: FIBC Bags With UV Without Liner | N71: 19817.4 | O71: 3885003.1 | P71: FIBC Bags With UV Without Liner | Q71: 4580418.7 | R71: 9 | S71: 349650.28 | T71: 9 | U71: 349650.28 | V71: 0 | W71: 0 | X71: 0 | Y71: 699300.56 | Z71: 0 | AA71: 24AABCG1282C2Z6 | AB71: Kgs | AC71: 63053200 | AD71: Rs. | AE71: 1 | AF71: 19817.4 | AG71: India | AH71: FIBC Bags
B72: 46207 | C72: Hcp Plastene Bulkpack Ltd Vadodara-Sales | D72: R.M.P. | E72: RM 248 | F72: Purchase Withinstate - Raw Material | G72: HPBLV/D/29 | H72: 46207 | I72: FG | J72: FIBC Bags | K72: FIBC Bags | L72: PP WOVEN BIG BAGS / SACKS | M72: FIBC Bags With UV Without Liner | N72: 279.5 | O72: 68625.635 | P72: FIBC Bags With UV Without Liner | Q72: 80978.26 | R72: 9 | S72: 6176.31 | T72: 9 | U72: 6176.31 | V72: 0 | W72: 0 | X72: 0 | Y72: 12352.62 | Z72: 0 | AA72: 24AABCG1282C2Z6 | AB72: Kgs | AC72: 63053200 | AD72: Rs. | AE72: 1 | AF72: =N72 -> 279.5 | AG72: India | AH72: FIBC Bags
B73: 46207 | C73: Hi Flex Hydraulics Pvt Ltd | D73: General Purchase | E73: GNSP 350 | F73: Purchase Withinstate- Stores, Spares & Consumable | G73: S/01673 | H73: 46188 | I73: Stores/Spares | J73: Pump | K73: Stores & Spares | L73: stores & spares | M73: Radial Piston Pump Model No.1Rce7B-50 (Sp) | N73: 2 | O73: 21090 | P73: Radial Piston Pump Model No.1Rce7B-50 (Sp) | Q73: 25181 | R73: 9 | S73: 1920.6 | T73: 9 | U73: 1920.6 | V73: 0 | W73: 0 | X73: 0 | Y73: 3841.2 | Z73: 0 | AA73: 24AABCH4875J1ZE | AB73: Pcs | AC73: 8413812 | AD73: Rs. | AE73: 1 | AF73: 0 | AG73: India | AH73: N.A
B74: 46207 | C74: Ivict(Singapore) Pte. Ltd. | D74: IMP-RM | E74: RMIMP 21 | F74: Purchase Raw Material - High Seas | G74: ZTFA/26002TN.. [BOE/BOL:2026894/COSU6441186480] | H74: 46076 | I74: RM | J74: Granules | K74: PP Granules | L74: PP Granuals | M74: PP Advanced H312 | N74: 24750 | O74: 1910526.8 | P74: PP Advanced H312 | Q74: 1910526.8 | R74: 0 | S74: 0 | T74: 0 | U74: 0 | V74: 0 | W74: 0 | X74: 0 | Y74: 0 | Z74: 0 | AA74: N.A. | AB74: Kgs | AC74: 39021000 | AD74: Rs. | AE74: 1 | AF74: 24750 | AG74: Singapore | AH74: PP Granules
B75: 46207 | C75: Ivict(Singapore) Pte. Ltd. | D75: IMP-RM | E75: RMIMP 22 | F75: Purchase Raw Material - High Seas | G75: ZTFA/26002TN., [BOE/BOL:2026894/COSU6441186480] | H75: 46076 | I75: RM | J75: Granules | K75: PP Granules | L75: PP Granuals | M75: PP Advanced H312 | N75: 24750 | O75: 1910526.8 | P75: PP Advanced H312 | Q75: 1910526.8 | R75: 0 | S75: 0 | T75: 0 | U75: 0 | V75: 0 | W75: 0 | X75: 0 | Y75: 0 | Z75: 0 | AA75: N.A. | AB75: Kgs | AC75: 39021000 | AD75: Rs. | AE75: 1 | AF75: 24750 | AG75: Singapore | AH75: PP Granules
B76: 46207 | C76: Ivict(Singapore) Pte. Ltd. | D76: IMP-RM | E76: RMIMP 23 | F76: Purchase Raw Material - High Seas | G76: ZTFA/26002TN [BOE/BOL:2026894/COSU6441186480] | H76: 46076 | I76: RM | J76: Granules | K76: PP Granules | L76: PP Granuals | M76: PP Advanced H312 | N76: 123750 | O76: 9552633.8 | P76: PP Advanced H312 | Q76: 9552633.8 | R76: 0 | S76: 0 | T76: 0 | U76: 0 | V76: 0 | W76: 0 | X76: 0 | Y76: 0 | Z76: 0 | AA76: N.A. | AB76: Kgs | AC76: 39021000 | AD76: Rs. | AE76: 1 | AF76: 123750 | AG76: Singapore | AH76: PP Granules
B77: 46208 | C77: Arham Cams Pvt Ltd | D77: General Purchase | E77: GNSP 351 | F77: Purchase Withinstate- Stores, Spares & Consumable | G77: GST/136 | H77: 46205 | I77: Stores/Spares | J77: Sulzer Machine Spares | K77: Stores & Spares | L77: stores & spares | M77: Projectile Body (D2) | N77: 15 | O77: 5775 | P77: Projectile Body (D2) | Q77: 6874 | R77: 9 | S77: 524.25 | T77: 9 | U77: 524.25 | V77: 0 | W77: 0 | X77: 0 | Y77: 1048.5 | Z77: 0 | AA77: 24AAICA0799H1ZK | AB77: Pcs | AC77: 844810 | AD77: Rs. | AE77: 1 | AF77: 0 | AG77: India | AH77: N.A
B78: 46208 | C78: Arham Cams Pvt Ltd | D78: General Purchase | E78: GNSP 352 | F78: Purchase Withinstate- Stores, Spares & Consumable | G78: GST/137 | H78: 46205 | I78: Stores/Spares | J78: Sulzer Machine Spares | K78: Stores & Spares | L78: stores & spares | M78: Splined Shaft (For Sulzer Teckup) -911110162 | N78: 3 | O78: 2175 | P78: Splined Shaft (For Sulzer Teckup) -911110162 | Q78: 5381 | R78: 9 | S78: 195.75 | T78: 9 | U78: 195.75 | V78: 0 | W78: 0 | X78: 0 | Y78: 391.5 | Z78: 0 | AA78: 24AAICA0799H1ZK | AB78: Pcs | AC78: 844849 | AD78: Rs. | AE78: 1 | AF78: 0 | AG78: India | AH78: N.A
B79: 46208 | C79: Arham Cams Pvt Ltd | D79: General Purchase | E79: GNSP 352 | F79: Purchase Withinstate- Stores, Spares & Consumable | G79: GST/137 | H79: 46205 | I79: Stores/Spares | J79: Sulzer Machine Spares | K79: Stores & Spares | L79: stores & spares | M79: Splined Shaft (For Sulzer Teckup) -911110162 | N79: 3 | O79: 2085 | P79: Splined Shaft (For Sulzer Teckup) -911110162 | Q79: 0 | R79: 9 | S79: 214.65 | T79: 9 | U79: 214.65 | V79: 0 | W79: 0 | X79: 0 | Y79: 429.3 | Z79: 0 | AA79: 24AAICA0799H1ZK | AB79: Pcs | AC79: 844849 | AD79: Rs. | AE79: 1 | AF79: 0 | AG79: India | AH79: N.A
B80: 46208 | C80: Global Industries | D80: General Purchase | E80: GNSP 353 | F80: Purchase Withinstate- Stores, Spares & Consumable | G80: GIGST3592627 | H80: 46205 | I80: Stores/Spares | J80: Needle Loom Spares | K80: Stores & Spares | L80: stores & spares | M80: Guide 9063 | N80: 30 | O80: 6570 | P80: Guide 9063 | Q80: 18169 | R80: 9 | S80: 591.3 | T80: 9 | U80: 591.3 | V80: 0 | W80: 0 | X80: 0 | Y80: 1182.6 | Z80: 0 | AA80: 24AADFG7242B1ZX | AB80: PCS | AC80: 844630 | AD80: Rs. | AE80: 1 | AF80: 0 | AG80: India | AH80: N.A
B81: 46208 | C81: Global Industries | D81: General Purchase | E81: GNSP 353 | F81: Purchase Withinstate- Stores, Spares & Consumable | G81: GIGST3592627 | H81: 46205 | I81: Stores/Spares | J81: Needle Loom Spares | K81: Stores & Spares | L81: stores & spares | M81: Pinion Intermediate 8234 | N81: 10 | O81: 5110 | P81: Pinion Intermediate 8234 | Q81: 0 | R81: 9 | S81: 459.9 | T81: 9 | U81: 459.9 | V81: 0 | W81: 0 | X81: 0 | Y81: 919.8 | Z81: 0 | AA81: 24AADFG7242B1ZX | AB81: Pcs | AC81: 844649 | AD81: Rs. | AE81: 1 | AF81: 0 | AG81: India | AH81: N.A
B82: 46208 | C82: Global Industries | D82: General Purchase | E82: GNSP 353 | F82: Purchase Withinstate- Stores, Spares & Consumable | G82: GIGST3592627 | H82: 46205 | I82: Stores/Spares | J82: Needle Loom Spares | K82: Stores & Spares | L82: stores & spares | M82: Ceramic 9034 | N82: 100 | O82: 1460 | P82: Ceramic 9034 | Q82: 0 | R82: 9 | S82: 131.4 | T82: 9 | U82: 131.4 | V82: 0 | W82: 0 | X82: 0 | Y82: 262.8 | Z82: 0 | AA82: 24AADFG7242B1ZX | AB82: Pcs | AC82: 844630 | AD82: Rs. | AE82: 1 | AF82: 0 | AG82: India | AH82: N.A
B83: 46208 | C83: Global Industries | D83: General Purchase | E83: GNSP 353 | F83: Purchase Withinstate- Stores, Spares & Consumable | G83: GIGST3592627 | H83: 46205 | I83: Stores/Spares | J83: Needle Loom Spares | K83: Stores & Spares | L83: stores & spares | M83: Change Gear 8219 | N83: 5 | O83: 2007.5 | P83: Change Gear 8219 | Q83: 0 | R83: 9 | S83: 203.18 | T83: 9 | U83: 203.18 | V83: 0 | W83: 0 | X83: 0 | Y83: 406.36 | Z83: 0 | AA83: 24AADFG7242B1ZX | AB83: Pcs | AC83: 84490000 | AD83: Rs. | AE83: 1 | AF83: 0 | AG83: India | AH83: N.A
B84: 46208 | C84: HCP Plastene Bulkpack Limited - Purchase | D84: R.M.P. | E84: RM 254 | F84: Purchase Withinstate - Raw Material | G84: HPBL/D/346 | H84: 46207 | I84: SF | J84: PP/PE Fabric | K84: PP UL Fabric | L84: PP WOVEN FABRIC | M84: PP UL Fabric With UV | N84: 858 | O84: 190390.2 | P84: PP UL Fabric With UV | Q84: 1253765.4 | R84: 9 | S84: 17135.12 | T84: 9 | U84: 17135.12 | V84: 0 | W84: 0 | X84: 0 | Y84: 34270.24 | Z84: 0 | AA84: 24AABCG1282C2Z6 | AB84: Kgs | AC84: 39269080 | AD84: Rs. | AE84: 1 | AF84: =N84 -> 858 | AG84: India | AH84: PP UL Fabric
B85: 46208 | C85: HCP Plastene Bulkpack Limited - Purchase | D85: R.M.P. | E85: RM 254 | F85: Purchase Withinstate - Raw Material | G85: HPBL/D/346 | H85: 46207 | I85: SF | J85: PP/PE Fabric | K85: PP UL Fabric | L85: PP WOVEN FABRIC | M85: PP UL Fabric With UV | N85: 327 | O85: 52287.3 | P85: PP UL Fabric With UV | Q85: 0 | R85: 9 | S85: 4705.86 | T85: 9 | U85: 4705.86 | V85: 0 | W85: 0 | X85: 0 | Y85: 9411.72 | Z85: 0 | AA85: 24AABCG1282C2Z6 | AB85: Kgs | AC85: 39269080 | AD85: Rs. | AE85: 1 | AF85: =N85 -> 327 | AG85: India | AH85: PP UL Fabric
B86: 46208 | C86: HCP Plastene Bulkpack Limited - Purchase | D86: R.M.P. | E86: RM 254 | F86: Purchase Withinstate - Raw Material | G86: HPBL/D/346 | H86: 46207 | I86: SF | J86: PP/PE Fabric | K86: PP UL Fabric | L86: PP WOVEN FABRIC | M86: PP UL Fabric With UV | N86: 4559 | O86: 738102.1 | P86: PP UL Fabric With UV | Q86: 0 | R86: 9 | S86: 66429.19 | T86: 9 | U86: 66429.19 | V86: 0 | W86: 0 | X86: 0 | Y86: 132858.38 | Z86: 0 | AA86: 24AABCG1282C2Z6 | AB86: Kgs | AC86: 39269080 | AD86: Rs. | AE86: 1 | AF86: =N86 -> 4559 | AG86: India | AH86: PP UL Fabric
B87: 46208 | C87: HCP Plastene Bulkpack Limited - Purchase | D87: R.M.P. | E87: RM 254 | F87: Purchase Withinstate - Raw Material | G87: HPBL/D/346 | H87: 46207 | I87: SF | J87: Liners | K87: LDPE/LLDPE Bags | L87: LLDPE Film | M87: DOC Pouch | N87: 247 | O87: 47668.53 | P87: DOC Pouch | Q87: 0 | R87: 9 | S87: 4290.17 | T87: 9 | U87: 4290.17 | V87: 0 | W87: 0 | X87: 0 | Y87: 8580.34 | Z87: 0 | AA87: 24AABCG1282C2Z6 | AB87: Kgs | AC87: 39232100 | AD87: Rs. | AE87: 1 | AF87: =N87 -> 247 | AG87: India | AH87: LDPE/LLDPE Bags
B88: 46208 | C88: HCP Plastene Bulkpack Limited - Purchase | D88: R.M.P. | E88: RM 254 | F88: Purchase Withinstate - Raw Material | G88: HPBL/D/346 | H88: 46207 | I88: SF | J88: Films All (SF) | K88: PE Film | L88: LLDPE Film | M88: LDPE/LLDPE Film – Conductive | N88: 186 | O88: 34966.14 | P88: LDPE/LLDPE Film – Conductive | Q88: 0 | R88: 9 | S88: 3146.95 | T88: 9 | U88: 3146.95 | V88: 0 | W88: 0 | X88: 0 | Y88: 6293.9 | Z88: 0 | AA88: 24AABCG1282C2Z6 | AB88: Kgs | AC88: 39201019 | AD88: Rs. | AE88: 1 | AF88: =N88 -> 186 | AG88: India | AH88: PE Film
B89: 46208 | C89: Olive Industries | D89: R.M.P. | E89: RM 253 | F89: Purchase Withinstate - Raw Material | G89: TI/420 | H89: 46207 | I89: SF | J89: Yarn All | K89: PP Yarn | L89: PP MF Yarn | M89: Monofilament Yarn 840 Denier | N89: 3055.84 | O89: 626431.92 | P89: Monofilament Yarn 840 Denier | Q89: 657754 | R89: 2.5 | S89: 15660.8 | T89: 2.5 | U89: 15660.8 | V89: 0 | W89: 0 | X89: 0 | Y89: 31321.6 | Z89: 0 | AA89: 24AAEFO9994M1ZE | AB89: Kgs | AC89: 12345678 | AD89: Rs. | AE89: 1 | AF89: 3055.6 | AG89: India | AH89: PP Yarn
B90: 46208 | C90: Plastene India ltd - Unit 1-Purchase | D90: Purchase | E90: GNPK 127 | F90: Purchase Withinstate- Packing Material | G90: PIL1/D/913 | H90: 46207 | I90: Stores/Spares | J90: MS Structure Items | K90: Packing Materials | L90: Packing Materials | M90: MS Pipe 4 C Class | N90: 278 | O90: 13344 | P90: MS Pipe 4 C Class | Q90: 15732.58 | R90: 9 | S90: 1200.96 | T90: 9 | U90: 1200.96 | V90: 0 | W90: 0 | X90: 0 | Y90: 2401.92 | Z90: 0 | AA90: 24AAACO3087C1ZT | AB90: Kgs | AC90: 73063090 | AD90: Rs. | AE90: 1 | AF90: 0 | AG90: India | AH90: N.A
B91: 46208 | C91: Plastene India ltd - Unit 1-Purchase | D91: R.M.P. | E91: RM 251 | F91: Purchase Withinstate - Raw Material | G91: PIL1/D/917 | H91: 46207 | I91: SF | J91: Liners | K91: LDPE/LLDPE Bags | L91: LLDPE BAGS | M91: LDPE/LLDPE Bags/Liner | N91: 878 | O91: 163992.84 | P91: LDPE/LLDPE Bags/Liner | Q91: 193347.57 | R91: 9 | S91: 14759.36 | T91: 9 | U91: 14759.36 | V91: 0 | W91: 0 | X91: 0 | Y91: 29518.72 | Z91: 0 | AA91: 24AAACO3087C1ZT | AB91: Kgs | AC91: 39200000 | AD91: Rs. | AE91: 1 | AF91: 878 | AG91: India | AH91: LDPE/LLDPE Bags
B92: 46208 | C92: Plastene India ltd - Unit 2-Purchase | D92: R.M.P. | E92: RM 250 | F92: Purchase Withinstate - Raw Material | G92: PIL2/D/335 | H92: 46207 | I92: RM | J92: Granules | K92: PP Granules | L92: PP Granuals | M92: PP HPCL Y35GR | N92: 5000 | O92: 696750 | P92: PP HPCL Y35GR | Q92: 821468.25 | R92: 9 | S92: 62707.5 | T92: 9 | U92: 62707.5 | V92: 0 | W92: 0 | X92: 0 | Y92: 125415 | Z92: 0 | AA92: 24AAACO3087C1ZT | AB92: Kgs | AC92: 39021000 | AD92: Rs. | AE92: 1 | AF92: 5000 | AG92: India | AH92: PP Granules
B93: 46209 | C93: Alok Master Batches Private Limited- Dadra | D93: R.M.P. | E93: RM 257 | F93: Purchase Interstate - Raw Material | G93: AMD/26-27/01773 | H93: 46205 | I93: RM | J93: Granules | K93: Masterbatch | L93: Master batch | M93: MB Alok Blue AM10430 Pantone 072C | N93: 250 | O93: 124500 | P93: MB Alok Blue AM10430 Pantone 072C | Q93: 146910 | R93: 0 | S93: 0 | T93: 0 | U93: 0 | V93: 18 | W93: 22410 | X93: 0 | Y93: 22410 | Z93: 0 | AA93: 26AAACA6143K1ZR | AB93: Kgs | AC93: 32041990 | AD93: Rs. | AE93: 1 | AF93: 250 | AG93: India | AH93: Masterbatch
B94: 46209 | C94: Bright Rubber | D94: General Purchase | E94: GNSP 356 | F94: Purchase Withinstate- Stores, Spares & Consumable | G94: G24088 | H94: 46205 | I94: Consumables | J94: Oil Seal | K94: Stores & Spares | L94: stores & spares | M94: O Ring Pu 95 X 5 mm | N94: 100 | O94: 5000 | P94: O Ring Pu 95 X 5 mm | Q94: 5994 | R94: 9 | S94: 450 | T94: 9 | U94: 450 | V94: 0 | W94: 0 | X94: 14.4 | Y94: 914.4 | Z94: 0 | AA94: 24AACFB1249A1ZA | AB94: Pcs | AC94: 40169330 | AD94: Rs. | AE94: 1 | AF94: 0 | AG94: India | AH94: N.A
B95: 46209 | C95: Green Traders | D95: General Purchase | E95: GNSP 355 | F95: Purchase Withinstate- Stores, Spares & Consumable | G95: G-0155 | H95: 46151 | I95: Stores/Spares | J95: Fuses | K95: Stores & Spares | L95: stores & spares | M95: Fuse Hrc 630 Amp. Sb 03 Standard | N95: 3 | O95: 4644 | P95: Fuse Hrc 630 Amp. Sb 03 Standard | Q95: 11074 | R95: 9 | S95: 417.96 | T95: 9 | U95: 417.96 | V95: 0 | W95: 0 | X95: 0 | Y95: 835.92 | Z95: 0 | AA95: 24ACFPS7268D1ZG | AB95: PCS | AC95: 853610 | AD95: Rs. | AE95: 1 | AF95: 0 | AG95: India | AH95: N.A
B96: 46209 | C96: Green Traders | D96: General Purchase | E96: GNSP 355 | F96: Purchase Withinstate- Stores, Spares & Consumable | G96: G-0155 | H96: 46151 | I96: Stores/Spares | J96: Fuses | K96: Stores & Spares | L96: stores & spares | M96: Fuse Link 400 Amp , Hrc Type-Hn,Size-Ii L&T Make | N96: 3 | O96: 4740.96 | P96: Fuse Link 400 Amp , Hrc Type-Hn,Size-Ii L&T Make | Q96: 0 | R96: 9 | S96: 426.69 | T96: 9 | U96: 426.69 | V96: 0 | W96: 0 | X96: 0 | Y96: 853.38 | Z96: 0 | AA96: 24ACFPS7268D1ZG | AB96: Pcs | AC96: 853690 | AD96: Rs. | AE96: 1 | AF96: 0 | AG96: India | AH96: N.A
B97: 46209 | C97: Ivict(Singapore) Pte. Ltd. | D97: IMP-RM | E97: RMIMP 24 | F97: Purchase Raw Material - High Seas | G97: ZTFA/26002TN,,, [BOE/BOL:2026894/COSU6441186480] | H97: 46076 | I97: RM | J97: Granules | K97: PP Granules | L97: PP Granuals | M97: PP Advanced H312 | N97: 99000 | O97: 7642107 | P97: PP Advanced H312 | Q97: 7642107 | R97: 0 | S97: 0 | T97: 0 | U97: 0 | V97: 0 | W97: 0 | X97: 0 | Y97: 0 | Z97: 0 | AA97: N.A. | AB97: Kgs | AC97: 39021000 | AD97: Rs. | AE97: 1 | AF97: 99000 | AG97: Singapore | AH97: PP Granules
B98: 46209 | C98: Karnavati Polyblends Pvt Ltd | D98: R.M.P. | E98: RM 258 | F98: Purchase Withinstate - Raw Material | G98: KPPL/26-27/706 | H98: 46209 | I98: RM | J98: Granules | K98: Masterbatch | L98: Master batch | M98: MB Karnavati New Chrome Yellow | N98: 100 | O98: 23280 | P98: MB Karnavati New Chrome Yellow | Q98: 488916 | R98: 9 | S98: 2095.2 | T98: 9 | U98: 2095.2 | V98: 0 | W98: 0 | X98: 0 | Y98: 4190.4 | Z98: 0 | AA98: 24AAACK9111D1Z2 | AB98: Kgs | AC98: 32064990 | AD98: Rs. | AE98: 1 | AF98: 100 | AG98: India | AH98: Masterbatch
B99: 46209 | C99: Karnavati Polyblends Pvt Ltd | D99: R.M.P. | E99: RM 258 | F99: Purchase Withinstate - Raw Material | G99: KPPL/26-27/706 | H99: 46209 | I99: RM | J99: Granules | K99: Masterbatch | L99: Master batch | M99: MB Karnavati Leaf Green | N99: 300 | O99: 68385 | P99: MB Karnavati Leaf Green | Q99: 0 | R99: 9 | S99: 6154.65 | T99: 9 | U99: 6154.65 | V99: 0 | W99: 0 | X99: 0 | Y99: 12309.3 | Z99: 0 | AA99: 24AAACK9111D1Z2 | AB99: Kgs | AC99: 32064990 | AD99: Rs. | AE99: 1 | AF99: 300 | AG99: India | AH99: Masterbatch
B100: 46209 | C100: Karnavati Polyblends Pvt Ltd | D100: R.M.P. | E100: RM 258 | F100: Purchase Withinstate - Raw Material | G100: KPPL/26-27/706 | H100: 46209 | I100: RM | J100: Granules | K100: Masterbatch | L100: Master batch | M100: MB Karnavati Polyplast Blue | N100: 500 | O100: 127555 | P100: MB Karnavati Polyplast Blue | Q100: 0 | R100: 9 | S100: 11479.95 | T100: 9 | U100: 11479.95 | V100: 0 | W100: 0 | X100: 0 | Y100: 22959.9 | Z100: 0 | AA100: 24AAACK9111D1Z2 | AB100: Kgs | AC100: 320649 | AD100: Rs. | AE100: 1 | AF100: 500 | AG100: India | AH100: Masterbatch
... B103: 46209 | C103: Plastene India ltd - Unit 1-Purchase | D103: Purchase | E103: GNPK 129 | F103: Purchase Withinstate- Packing Material | G103: PIL1/D/929 | H103: 46208 | I103: Stores/Spares | J103: MS Structure Items | K103: Packing Materials | L103: Packing Materials | M103: MS Pipe 4 C Class | N103: 106 | O103: 5088 | P103: MS Pipe 4 C Class | Q103: 5998.75 | R103: 9 | S103: 457.92 | T103: 9 | U103: 457.92 | V103: 0 | W103: 0 | X103: 0 | Y103: 915.84 | Z103: 0 | AA103: 24AAACO3087C1ZT | AB103: Kgs | AC103: 73063090 | AD103: Rs. | AE103: 1 | AF103: 0 | AG103: India | AH103: N.A
B104: 46209 | C104: Plastene India ltd - Unit 1-Purchase | D104: R.M.P. | E104: RM 256 | F104: Purchase Withinstate - Raw Material | G104: PIL1/D/931 | H104: 46208 | I104: SF | J104: Liners | K104: LDPE/LLDPE Bags | L104: LLDPE BAGS | M104: LDPE/LLDPE Bags/Liner | N104: 1731.8 | O104: 358101.6 | P104: LDPE/LLDPE Bags/Liner | Q104: 1239152.4 | R104: 9 | S104: 32229.14 | T104: 9 | U104: 32229.14 | V104: 0 | W104: 0 | X104: 0 | Y104: 64458.28 | Z104: 0 | AA104: 24AAACO3087C1ZT | AB104: Kgs | AC104: 39200000 | AD104: Rs. | AE104: 1 | AF104: =N104 -> 1731.8 | AG104: India | AH104: LDPE/LLDPE Bags
B105: 46209 | C105: Plastene India ltd - Unit 1-Purchase | D105: R.M.P. | E105: RM 256 | F105: Purchase Withinstate - Raw Material | G105: PIL1/D/931 | H105: 46208 | I105: SF | J105: Liners | K105: LDPE/LLDPE Bags | L105: LLDPE BAGS | M105: LDPE/LLDPE Bags/Liner | N105: 1376.8 | O105: 339642.79 | P105: LDPE/LLDPE Bags/Liner | Q105: 0 | R105: 9 | S105: 30567.85 | T105: 9 | U105: 30567.85 | V105: 0 | W105: 0 | X105: 0 | Y105: 61135.7 | Z105: 0 | AA105: 24AAACO3087C1ZT | AB105: Kgs | AC105: 39200000 | AD105: Rs. | AE105: 1 | AF105: =N105 -> 1376.8 | AG105: India | AH105: LDPE/LLDPE Bags
B106: 46209 | C106: Plastene India ltd - Unit 1-Purchase | D106: R.M.P. | E106: RM 256 | F106: Purchase Withinstate - Raw Material | G106: PIL1/D/931 | H106: 46208 | I106: SF | J106: Liners | K106: LDPE/LLDPE Bags | L106: LLDPE BAGS | M106: LDPE/LLDPE Bags/Liner | N106: 1861.5 | O106: 353275.47 | P106: LDPE/LLDPE Bags/Liner | Q106: 0 | R106: 9 | S106: 31794.79 | T106: 9 | U106: 31794.79 | V106: 0 | W106: 0 | X106: 0 | Y106: 63589.58 | Z106: 0 | AA106: 24AAACO3087C1ZT | AB106: Kgs | AC106: 39200000 | AD106: Rs. | AE106: 1 | AF106: =N106 -> 1861.5 | AG106: India | AH106: LDPE/LLDPE Bags
B107: 46209 | C107: Plastene India ltd - Unit 2-Purchase | D107: Purchase | E107: GNPK 128 | F107: Purchase Withinstate- Packing Material | G107: PIL2/D/340 | H107: 46208 | I107: Stores/Spares | J107: MS Structure Items | K107: Packing Materials | L107: Packing Materials | M107: MS Pipe | N107: 196 | O107: 9408 | P107: MS Pipe | Q107: 11092.03 | R107: 9 | S107: 846.72 | T107: 9 | U107: 846.72 | V107: 0 | W107: 0 | X107: 0 | Y107: 1693.44 | Z107: 0 | AA107: 24AAACO3087C1ZT | AB107: KGS | AC107: 7306309 | AD107: Rs. | AE107: 1 | AF107: 0 | AG107: India | AH107: N.A
B108: 46209 | C108: Plastene India ltd - Unit 2-Purchase | D108: R.M.P. | E108: RM 255 | F108: Purchase Withinstate - Raw Material | G108: PIL2/D/339 | H108: 46209 | I108: SF | J108: PP/PE Fabric | K108: PP UL Fabric | L108: PP WOVEN FABRIC | M108: PP UL Fabric With UV | N108: 5793 | O108: 617533.8 | P108: PP UL Fabric With UV | Q108: 883040.49 | R108: 9 | S108: 55578.04 | T108: 9 | U108: 55578.04 | V108: 0 | W108: 0 | X108: 0 | Y108: 111156.08 | Z108: 0 | AA108: 24AAACO3087C1ZT | AB108: Kgs | AC108: 39269080 | AD108: Rs. | AE108: 1 | AF108: =N108 -> 5793 | AG108: India | AH108: PP UL Fabric
B109: 46209 | C109: Plastene India ltd - Unit 2-Purchase | D109: R.M.P. | E109: RM 255 | F109: Purchase Withinstate - Raw Material | G109: PIL2/D/339 | H109: 46209 | I109: SF | J109: Webbing | K109: PP Webbing | L109: PP WEBBING | M109: Webbing MF | N109: 1014.2 | O109: 131440.32 | P109: Webbing MF | Q109: 0 | R109: 9 | S109: 11829.63 | T109: 9 | U109: 11829.63 | V109: 0 | W109: 0 | X109: 0 | Y109: 23659.26 | Z109: 0 | AA109: 24AAACO3087C1ZT | AB109: Kgs | AC109: 39269080 | AD109: Rs. | AE109: 1 | AF109: =N109 -> 1014.2 | AG109: India | AH109: PP Webbing
B110: 46209 | C110: Satyam Stationery Mart | D110: General Purchase | E110: GNCN 205 | F110: Purchase Withinstate- Stores, Spares & Consumable | G110: SSM02052 | H110: 46207 | I110: Stores/Spares | J110: Cutter Blades | K110: Stores & Spares | L110: stores & spares | M110: Alfa Blade For Sdi Cutter Knife. Size;-18mm No.1404H | N110: 1000 | O110: 7150 | P110: Alfa Blade For Sdi Cutter Knife. Size;-18mm No.1404H | Q110: 8437 | R110: 9 | S110: 643.5 | T110: 9 | U110: 643.5 | V110: 0 | W110: 0 | X110: 0 | Y110: 1287 | Z110: 0 | AA110: 24AGUPL9792N1Z6 | AB110: Pcs | AC110: 82089090 | AD110: Rs. | AE110: 1 | AF110: 0 | AG110: India | AH110: N.A
B111: 46209 | C111: Vivek Industrial Service | D111: General Purchase | E111: GNSP 354 | F111: Purchase Withinstate- Stores, Spares & Consumable | G111: 445 | H111: 46205 | I111: Stores/Spares | J111: utility | K111: Stores & Spares | L111: stores & spares | M111: Hot Air Gun | N111: 10 | O111: 24200 | P111: Hot Air Gun | Q111: 29028 | R111: 9 | S111: 2178 | T111: 9 | U111: 2178 | V111: 0 | W111: 0 | X111: 72 | Y111: 4428 | Z111: 0 | AA111: 24AKZPB7901L1ZR | AB111: Pcs | AC111: 841989 | AD111: Rs. | AE111: 1 | AF111: 0 | AG111: India | AH111: N.A
B112: 46210 | C112: Arham Cams Pvt Ltd | D112: General Purchase | E112: GNSP 362 | F112: Purchase Withinstate- Stores, Spares & Consumable | G112: GST/125 | H112: 46200 | I112: Stores/Spares | J112: Sulzer Machine Spares | K112: Stores & Spares | L112: stores & spares | M112: Foot Round For Beam KB support 911.806.329 | N112: 5 | O112: 840 | P112: Foot Round For Beam KB support 911.806.329 | Q112: 4171 | R112: 9 | S112: 75.6 | T112: 9 | U112: 75.6 | V112: 0 | W112: 0 | X112: 18 | Y112: 169.2 | Z112: 0 | AA112: 24AAICA0799H1ZK | AB112: NOS | AC112: 84484990 | AD112: Rs. | AE112: 1 | AF112: 0 | AG112: India | AH112: N.A
B113: 46210 | C113: Arham Cams Pvt Ltd | D113: General Purchase | E113: GNSP 362 | F113: Purchase Withinstate- Stores, Spares & Consumable | G113: GST/125 | H113: 46200 | I113: Stores/Spares | J113: Sulzer Machine Spares | K113: Stores & Spares | L113: stores & spares | M113: Hexagonal Nut M16 For Beam KB support 921.509.900 | N113: 10 | O113: 120 | P113: Hexagonal Nut M16 For Beam KB support 921.509.900 | Q113: 0 | R113: 9 | S113: 10.8 | T113: 9 | U113: 10.8 | V113: 0 | W113: 0 | X113: 18 | Y113: 39.6 | Z113: 0 | AA113: 24AAICA0799H1ZK | AB113: NOS | AC113: 84484990 | AD113: Rs. | AE113: 1 | AF113: 0 | AG113: India | AH113: N.A
B114: 46210 | C114: Arham Cams Pvt Ltd | D114: General Purchase | E114: GNSP 362 | F114: Purchase Withinstate- Stores, Spares & Consumable | G114: GST/125 | H114: 46200 | I114: Stores/Spares | J114: Sulzer Machine Spares | K114: Stores & Spares | L114: stores & spares | M114: Bolt M16x145 For Beam KB support 911.113.479 | N114: 5 | O114: 1210 | P114: Bolt M16x145 For Beam KB support 911.113.479 | Q114: 0 | R114: 9 | S114: 108.9 | T114: 9 | U114: 108.9 | V114: 0 | W114: 0 | X114: 18 | Y114: 235.8 | Z114: 0 | AA114: 24AAICA0799H1ZK | AB114: NOS | AC114: 84484990 | AD114: Rs. | AE114: 1 | AF114: 0 | AG114: India | AH114: N.A
B115: 46210 | C115: Arham Cams Pvt Ltd | D115: General Purchase | E115: GNSP 362 | F115: Purchase Withinstate- Stores, Spares & Consumable | G115: GST/125 | H115: 46200 | I115: Stores/Spares | J115: Sulzer Machine Spares | K115: Stores & Spares | L115: stores & spares | M115: Support Bolt M16x285 For Beam KB support 911.164.201 | N115: 5 | O115: 840 | P115: Support Bolt M16x285 For Beam KB support 911.164.201 | Q115: 0 | R115: 9 | S115: 75.6 | T115: 9 | U115: 75.6 | V115: 0 | W115: 0 | X115: 18 | Y115: 169.2 | Z115: 0 | AA115: 24AAICA0799H1ZK | AB115: NOS | AC115: 84484990 | AD115: Rs. | AE115: 1 | AF115: 0 | AG115: India | AH115: N.A
B116: 46210 | C116: Arham Cams Pvt Ltd | D116: General Purchase | E116: GNSP 362 | F116: Purchase Withinstate- Stores, Spares & Consumable | G116: GST/125 | H116: 46200 | I116: Stores/Spares | J116: Sulzer Machine Spares | K116: Stores & Spares | L116: stores & spares | M116: Disc Left-Hand Thread (40x30, M16) For Beam KB support 911.006.227 | N116: 5 | O116: 425 | P116: Disc Left-Hand Thread (40x30, M16) For Beam KB support 911.006.227 | Q116: 0 | R116: 9 | S116: 38.25 | T116: 9 | U116: 38.25 | V116: 0 | W116: 0 | X116: 18 | Y116: 94.5 | Z116: 0 | AA116: 24AAICA0799H1ZK | AB116: NOS | AC116: 84484990 | AD116: Rs. | AE116: 1 | AF116: 0 | AG116: India | AH116: N.A
B117: 46210 | C117: Arham Cams Pvt Ltd | D117: General Purchase | E117: GNSP 366 | F117: Purchase Withinstate- Stores, Spares & Consumable | G117: GST/128 | H117: 46200 | I117: Stores/Spares | J117: Sulzer Machine Spares | K117: Stores & Spares | L117: stores & spares | M117: Guide Tooth D1 | N117: 2000 | O117: 21300 | P117: Guide Tooth D1 | Q117: 33512 | R117: 9 | S117: 1917 | T117: 9 | U117: 1917 | V117: 0 | W117: 0 | X117: 0 | Y117: 3834 | Z117: 0 | AA117: 24AAICA0799H1ZK | AB117: Pcs | AC117: 844810 | AD117: Rs. | AE117: 1 | AF117: 0 | AG117: India | AH117: N.A
B118: 46210 | C118: Arham Cams Pvt Ltd | D118: General Purchase | E118: GNSP 366 | F118: Purchase Withinstate- Stores, Spares & Consumable | G118: GST/128 | H118: 46200 | I118: Stores/Spares | J118: Sulzer Machine Spares | K118: Stores & Spares | L118: stores & spares | M118: Conveyr Chain Cover | N118: 100 | O118: 3400 | P118: Conveyr Chain Cover | Q118: 0 | R118: 9 | S118: 333 | T118: 9 | U118: 333 | V118: 0 | W118: 0 | X118: 0 | Y118: 666 | Z118: 0 | AA118: 24AAICA0799H1ZK | AB118: PCS | AC118: 844849 | AD118: Rs. | AE118: 1 | AF118: 0 | AG118: India | AH118: N.A
B119: 46210 | C119: Arham Cams Pvt Ltd | D119: General Purchase | E119: GNSP 366 | F119: Purchase Withinstate- Stores, Spares & Consumable | G119: GST/128 | H119: 46200 | I119: Stores/Spares | J119: Sulzer Machine Spares | K119: Stores & Spares | L119: stores & spares | M119: Conveyr Chain Cover | N119: 100 | O119: 3400 | P119: Conveyr Chain Cover | Q119: 0 | R119: 9 | S119: 306 | T119: 9 | U119: 306 | V119: 0 | W119: 0 | X119: 0 | Y119: 612 | Z119: 0 | AA119: 24AAICA0799H1ZK | AB119: PCS | AC119: 844849 | AD119: Rs. | AE119: 1 | AF119: 0 | AG119: India | AH119: N.A
B120: 46210 | C120: Arham Cams Pvt Ltd | D120: General Purchase | E120: GNSP 367 | F120: Purchase Withinstate- Stores, Spares & Consumable | G120: GST/126 | H120: 46200 | I120: Stores/Spares | J120: Sulzer Machine Spares | K120: Stores & Spares | L120: stores & spares | M120: Hexagon socket counter Sunk Screw M6x20, 921.011.504 | N120: 30 | O120: 360 | P120: Hexagon socket counter Sunk Screw M6x20, 921.011.504 | Q120: 1841 | R120: 9 | S120: 36.9 | T120: 9 | U120: 36.9 | V120: 0 | W120: 0 | X120: 0 | Y120: 73.8 | Z120: 0 | AA120: 24AAICA0799H1ZK | AB120: NOS | AC120: 84484990 | AD120: Rs. | AE120: 1 | AF120: 0 | AG120: India | AH120: N.A
B121: 46210 | C121: Arham Cams Pvt Ltd | D121: General Purchase | E121: GNSP 367 | F121: Purchase Withinstate- Stores, Spares & Consumable | G121: GST/126 | H121: 46200 | I121: Stores/Spares | J121: Sulzer Machine Spares | K121: Stores & Spares | L121: stores & spares | M121: Upper Guide Plate D1 P7100, 911.316.659 | N121: 5 | O121: 575 | P121: Upper Guide Plate D1 P7100, 911.316.659 | Q121: 0 | R121: 9 | S121: 51.75 | T121: 9 | U121: 51.75 | V121: 0 | W121: 0 | X121: 0 | Y121: 103.5 | Z121: 0 | AA121: 24AAICA0799H1ZK | AB121: NOS | AC121: 84484990 | AD121: Rs. | AE121: 1 | AF121: 0 | AG121: India | AH121: N.A
B122: 46210 | C122: Arham Cams Pvt Ltd | D122: General Purchase | E122: GNSP 367 | F122: Purchase Withinstate- Stores, Spares & Consumable | G122: GST/126 | H122: 46200 | I122: Stores/Spares | J122: Sulzer Machine Spares | K122: Stores & Spares | L122: stores & spares | M122: Upper Guide Plate D1 PU 911.116.150 | N122: 5 | O122: 575 | P122: Upper Guide Plate D1 PU 911.116.150 | Q122: 0 | R122: 9 | S122: 51.75 | T122: 9 | U122: 51.75 | V122: 0 | W122: 0 | X122: 0 | Y122: 103.5 | Z122: 0 | AA122: 24AAICA0799H1ZK | AB122: NOS | AC122: 84484990 | AD122: Rs. | AE122: 1 | AF122: 0 | AG122: India | AH122: N.A
B123: 46210 | C123: Arham Cams Pvt Ltd | D123: General Purchase | E123: GNSP 368 | F123: Purchase Withinstate- Stores, Spares & Consumable | G123: GST/127 | H123: 46200 | I123: Stores/Spares | J123: Sulzer Machine Spares | K123: Stores & Spares | L123: stores & spares | M123: Brass Rivet Small (For Sulzer Harness) | N123: 200 | O123: 400 | P123: Brass Rivet Small (For Sulzer Harness) | Q123: 472 | R123: 9 | S123: 36 | T123: 9 | U123: 36 | V123: 0 | W123: 0 | X123: 0 | Y123: 72 | Z123: 0 | AA123: 24AAICA0799H1ZK | AB123: Pcs | AC123: 844810 | AD123: Rs. | AE123: 1 | AF123: 0 | AG123: India | AH123: N.A
...

Sheet Sales
N1: 1283156 | O1: =N2-N1 -> 66170.25
N2: =SUBTOTAL(9,N4:N388) -> 1349326.3 | O2: =SUBTOTAL(9,O4:O388) -> 2.4852181e+08 | AF2: =SUBTOTAL(9,AF4:AF388) -> 1349326.3
B3: Date | C3: Particular | D3: Voucher Type | E3: Voucher No | F3: Type | G3: Invoice No | H3: Invoice Date | I3: Main Grp | J3: Group Name | K3: Sub Grup | L3: sales Group Name | M3: Item Name | N3: Quantity | O3: Amount | P3: Item Desc | Q3: Bill Amount | R3: CGST Rate | S3: CGST Amt | T3: SGST Rate | U3: SGST Amt | V3: IGST Rate | W3: IGST Amt | X3: Freight GST | Y3: Total GST | Z3: TCS | AA3: GST-IN | AB3: Unit | AC3: HSN Code | AD3: Currencty | AE3: Exc.Rate | AF3: Net Wt | AG3: Country | AH3: GROUP | AI3: 1
B4: 46204 | C4: Plastene India ltd - Unit 1-Sales | D4: Sales | E4: 380 | F4: Sales - Within State Manufactured Goods | G4: KPV/D/380 | H4: 46204 | I4: SF | J4: Yarn All | K4: PP Yarn | L4: PP Tape | M4: PP Fibrillated Tape Twisted 3200 MW | N4: 1210 | O4: 182891.5 | P4: MW | Q4: 215629.09 | R4: 9 | S4: 16460.24 | T4: 9 | U4: 16460.24 | V4: 0 | W4: 0 | X4: 0 | Y4: 32920.48 | Z4: 0 | AA4: 24AAACO3087C1ZT | AB4: KGS | AC4: 39199090 | AD4: Rs. | AE4: 1 | AF4: 1210 | AG4: India | AH4: PP Yarn
B5: 46204 | C5: Plastene India ltd - Unit 1-Sales | D5: Sales | E5: 382 | F5: Sales - Within State Manufactured Goods | G5: KPV/D/382 | H5: 46204 | I5: FG | J5: FIBC Bags | K5: FIBC Bags | L5: PP WOVEN BIG BAGS / SACKS | M5: FIBC Bags With UV With Liner | N5: 1241 | O5: 411019.2 | P5: 26.19378/67004952-UN | Q5: 1588073.1 | R5: 9 | S5: 36991.73 | T5: 9 | U5: 36991.73 | V5: 0 | W5: 0 | X5: 0 | Y5: 73983.46 | Z5: 0 | AA5: 24AAACO3087C1ZT | AB5: KGS | AC5: 63053200 | AD5: Rs. | AE5: 1 | AF5: 1241 | AG5: India | AH5: FIBC Bags
B6: 46204 | C6: Plastene India ltd - Unit 1-Sales | D6: Sales | E6: 382 | F6: Sales - Within State Manufactured Goods | G6: KPV/D/382 | H6: 46204 | I6: FG | J6: FIBC Bags | K6: FIBC Bags | L6: PP WOVEN BIG BAGS / SACKS | M6: FIBC Bags With UV Without Liner | N6: 2700.6 | O6: 935946.94 | P6: 26/80122/26131/15.1657-18 | Q6: 0 | R6: 9 | S6: 84235.22 | T6: 9 | U6: 84235.22 | V6: 0 | W6: 0 | X6: 0 | Y6: 168470.44 | Z6: 0 | AA6: 24AAACO3087C1ZT | AB6: KGS | AC6: 63053200 | AD6: Rs. | AE6: 1 | AF6: 2700.6 | AG6: India | AH6: FIBC Bags
B7: 46204 | C7: Plastene India ltd - Unit 1-Sales | D7: Sales | E7: 383 | F7: Sales - Within State Manufactured Goods | G7: KPV/D/383 | H7: 46204 | I7: FG | J7: FIBC Bags | K7: FIBC Bags | L7: PP WOVEN BIG BAGS / SACKS | M7: FIBC Bags With UV Without Liner | N7: 410 | O7: 98748.5 | P7: PIR-260149/4IBC-085-O010 | Q7: 116424.47 | R7: 9 | S7: 8887.36 | T7: 9 | U7: 8887.36 | V7: 0 | W7: 0 | X7: 0 | Y7: 17774.72 | Z7: 0 | AA7: 24AAACO3087C1ZT | AB7: KGS | AC7: 63053200 | AD7: Rs. | AE7: 1 | AF7: 410 | AG7: India | AH7: FIBC Bags
B8: 46204 | C8: Rudra Trading Co. | D8: Sales | E8: 381 | F8: Sales - Interstate - Manufactured Goods | G8: KPV/D/381 | H8: 46204 | I8: SF | J8: RP Granules | K8: RP Granules | L8: PP Granuals | M8: RP Granules | N8: 19000 | O8: 1280600 | P8: RP Granules GRAY | Q8: 1509827.4 | R8: 0 | S8: 0 | T8: 0 | U8: 0 | V8: 18 | W8: 230508 | X8: 0 | Y8: 230508 | Z8: 0 | AA8: 27BCGPD5673M1Z7 | AB8: KGS | AC8: 39029000 | AD8: Rs. | AE8: 1 | AF8: 19000 | AG8: India | AH8: RP Granules
B9: 46204 | C9: Yuan Da Plastic Fabric Corporation | D9: Export Sales | E9: KPW/E/88/26-27 | F9: Sales - Direct Export - Mfg - U/R | G9: KPW/E/88/26-27 | H9: 46204 | I9: FG | J9: FIBC Bags | K9: FIBC Bags | L9: PP WOVEN BIG BAGS / SACKS | M9: FIBC Bags With UV Without Liner | N9: 19021.4 | O9: 4308595.2 | P9: PP WOVEN BIG BAG | Q9: 4308595.2 | R9: 0 | S9: 0 | T9: 0 | U9: 0 | V9: 18 | W9: 775547.14 | X9: 0.17 | Y9: 775547.31 | Z9: 0 | AA9: N.A. | AB9: KGS | AC9: 63053200 | AD9: $ | AE9: 93.6 | AF9: 19021.4 | AG9: USA | AH9: FIBC Bags
B10: 46205 | C10: Conrop S.R.O. | D10: Export Sales | E10: KPW/E/89/26-27 | F10: Sales - Direct Export - Mfg - U/R | G10: KPW/E/89/26-27 | H10: 46205 | I10: SF | J10: PP/PE Fabric | K10: PP UL Fabric | L10: PP WOVEN FABRIC | M10: PP UL Fabric With UV | N10: 20346.2 | O10: 3798377.2 | P10: P WOVEN FABRIC | Q10: 4098074.6 | R10: 0 | S10: 0 | T10: 0 | U10: 0 | V10: 18 | W10: 683707.92 | X10: 53576.66 | Y10: 737284.58 | Z10: 0 | AA10: N.A. | AB10: KGS | AC10: 39269080 | AD10: € | AE10: 106.9 | AF10: 20346.2 | AG10: Czech Republic | AH10: PP UL Fabric
B11: 46205 | C11: HCP Plastene Bulkpack Limited - Sales | D11: Sales | E11: 385 | F11: Sales - Within State - Traded Goods | G11: KPV/D/385 | H11: 46205 | I11: Consumables | J11: Oil & Greases | K11: Stores & Spares | L11: Consumables | M11: White Oil:- 12 No | N11: 420 | O11: 54600 | P11: White Oil:- 12 No | Q11: 64373.4 | R11: 9 | S11: 4914 | T11: 9 | U11: 4914 | V11: 0 | W11: 0 | X11: 0 | Y11: 9828 | Z11: 0 | AA11: 24AABCG1282C2Z6 | AB11: KGS | AC11: 271019 | AD11: Rs. | AE11: 1 | AF11: 420 | AG11: India | AH11: N.A
B12: 46205 | C12: HCP Plastene Bulkpack Limited - Sales | D12: Job Invoice | E12: KPV/D/388 | F12: Job Work Income | G12: KPV/D/388 | H12: 46205 | I12: FG | J12: FIBC Bags | K12: FIBC Bags | L12: PP WOVEN BIG BAGS / SACKS | M12: FIBC Bags With UV Without Liner | N12: 2377.3 | O12: 461695.43 | P12: 26.19398/BH-C573EXP-1 (PP BIG BAGS) | Q12: 4585006.1 | R12: 9 | S12: 41552.59 | T12: 9 | U12: 41552.59 | V12: 0 | W12: 0 | X12: 0 | Y12: 83105.18 | Z12: 0 | AA12: 24AABCG1282C2Z6 | AB12: KGS | AC12: 998852 | AD12: Rs. | AE12: 1 | AF12: 2377.3 | AG12: India | AH12: FIBC Bags
B13: 46205 | C13: HCP Plastene Bulkpack Limited - Sales | D13: Job Invoice | E13: KPV/D/388 | F13: Job Work Income | G13: KPV/D/388 | H13: 46205 | I13: FG | J13: FIBC Bags | K13: FIBC Bags | L13: PP WOVEN BIG BAGS / SACKS | M13: FIBC Bags With UV Without Liner | N13: 5064 | O13: 1004191.2 | P13: 26.19397/BH-C573H (PP BIG BAGS) | Q13: 0 | R13: 9 | S13: 90377.21 | T13: 9 | U13: 90377.21 | V13: 0 | W13: 0 | X13: 0 | Y13: 180754.42 | Z13: 0 | AA13: 24AABCG1282C2Z6 | AB13: KGS | AC13: 998852 | AD13: Rs. | AE13: 1 | AF13: 5064 | AG13: India | AH13: FIBC Bags
B14: 46205 | C14: HCP Plastene Bulkpack Limited - Sales | D14: Job Invoice | E14: KPV/D/388 | F14: Job Work Income | G14: KPV/D/388 | H14: 46205 | I14: FG | J14: FIBC Bags | K14: FIBC Bags | L14: PP WOVEN BIG BAGS / SACKS | M14: FIBC Bags With UV Without Liner | N14: 10334.3 | O14: 2004027.5 | P14: 26.19399/BH-C573SL (PP BIG BAGS) | Q14: 0 | R14: 9 | S14: 180362.47 | T14: 9 | U14: 180362.47 | V14: 0 | W14: 0 | X14: 0 | Y14: 360724.94 | Z14: 0 | AA14: 24AABCG1282C2Z6 | AB14: KGS | AC14: 998852 | AD14: Rs. | AE14: 1 | AF14: 10334.3 | AG14: India | AH14: FIBC Bags
B15: 46205 | C15: HCP Plastene Bulkpack Limited - Sales | D15: Job Invoice | E15: KPV/D/388 | F15: Job Work Income | G15: KPV/D/388 | H15: 46205 | I15: FG | J15: FIBC Bags | K15: FIBC Bags | L15: PP WOVEN BIG BAGS / SACKS | M15: FIBC Bags With UV Without Liner | N15: 835.2 | O15: 165620.16 | P15: 26.19397/BH-C573H (PP BIG BAGS) | Q15: 0 | R15: 9 | S15: 14905.81 | T15: 9 | U15: 14905.81 | V15: 0 | W15: 0 | X15: 0 | Y15: 29811.62 | Z15: 0 | AA15: 24AABCG1282C2Z6 | AB15: KGS | AC15: 998852 | AD15: Rs. | AE15: 1 | AF15: 835.2 | AG15: India | AH15: FIBC Bags
B16: 46205 | C16: HCP Plastene Bulkpack Limited - Sales | D16: Job Invoice | E16: KPV/D/388 | F16: Job Work Income | G16: KPV/D/388 | H16: 46205 | I16: FG | J16: FIBC Bags | K16: FIBC Bags | L16: PP WOVEN BIG BAGS / SACKS | M16: FIBC Bags With UV Without Liner | N16: 421.2 | O16: 82765.8 | P16: 26.19396/BH-C573FL (PP BIG BAGS) | Q16: 0 | R16: 9 | S16: 7448.92 | T16: 9 | U16: 7448.92 | V16: 0 | W16: 0 | X16: 0 | Y16: 14897.84 | Z16: 0 | AA16: 24AABCG1282C2Z6 | AB16: KGS | AC16: 998852 | AD16: Rs. | AE16: 1 | AF16: 421.2 | AG16: India | AH16: FIBC Bags
B17: 46205 | C17: HCP Plastene Bulkpack Limited - Sales | D17: Job Invoice | E17: KPV/D/388 | F17: Job Work Income | G17: KPV/D/388 | H17: 46205 | I17: FG | J17: FIBC Bags | K17: FIBC Bags | L17: PP WOVEN BIG BAGS / SACKS | M17: FIBC Bags With UV Without Liner | N17: 1181.5 | O17: 234291.45 | P17: 26.19397/BH-C573H (PP BIG BAGS) | Q17: 0 | R17: 9 | S17: 21086.23 | T17: 9 | U17: 21086.23 | V17: 0 | W17: 0 | X17: 0 | Y17: 42172.46 | Z17: 0 | AA17: 24AABCG1282C2Z6 | AB17: KGS | AC17: 998852 | AD17: Rs. | AE17: 1 | AF17: 1181.5 | AG17: India | AH17: FIBC Bags
B18: 46205 | C18: Plastene India ltd - Unit 2-Sales | D18: Sales | E18: 386 | F18: Sales - Within State Manufactured Goods | G18: KPV/D/386 | H18: 46205 | I18: SF | J18: Yarn All | K18: PP Yarn | L18: PP FABRILLATED YARN | M18: PP Fibrillated Tape Twisted 3200 MW | N18: 800 | O18: 123520 | P18: MW | Q18: 1038954.6 | R18: 2.5 | S18: 3088 | T18: 2.5 | U18: 3088 | V18: 0 | W18: 0 | X18: 0 | Y18: 6176 | Z18: 0 | AA18: 24AAACO3087C1ZT | AB18: KGS | AC18: 54026930 | AD18: Rs. | AE18: 1 | AF18: 800 | AG18: India | AH18: PP Yarn
B19: 46205 | C19: Plastene India ltd - Unit 2-Sales | D19: Sales | E19: 386 | F19: Sales - Within State Manufactured Goods | G19: KPV/D/386 | H19: 46205 | I19: SF | J19: PP/PE Fabric | K19: PP UL Fabric | L19: PP WOVEN FABRIC | M19: PP UL Fabric With UV | N19: 3493.4 | O19: 574314.96 | P19: . | Q19: 0 | R19: 9 | S19: 51688.35 | T19: 9 | U19: 51688.35 | V19: 0 | W19: 0 | X19: 0 | Y19: 103376.7 | Z19: 0 | AA19: 24AAACO3087C1ZT | AB19: KGS | AC19: 39269080 | AD19: Rs. | AE19: 1 | AF19: 3493.4 | AG19: India | AH19: PP UL Fabric
B20: 46205 | C20: Plastene India ltd - Unit 2-Sales | D20: Sales | E20: 386 | F20: Sales - Within State Manufactured Goods | G20: KPV/D/386 | H20: 46205 | I20: SF | J20: PP/PE Fabric | K20: PP UL Fabric | L20: PP WOVEN FABRIC | M20: PP UL Fabric With UV | N20: 1142.7 | O20: 197001.48 | P20: VENT | Q20: 0 | R20: 9 | S20: 17730.13 | T20: 9 | U20: 17730.13 | V20: 0 | W20: 0 | X20: 0 | Y20: 35460.26 | Z20: 0 | AA20: 24AAACO3087C1ZT | AB20: KGS | AC20: 39269080 | AD20: Rs. | AE20: 1 | AF20: 1142.7 | AG20: India | AH20: PP UL Fabric
B21: 46205 | C21: Plastene India ltd - Unit 2-Sales | D21: Sales | E21: 387 | F21: Sales - Within State - Traded Goods | G21: KPV/D/387 | H21: 46205 | I21: Stores/Spares | J21: MS Structure Items | K21: Capital Work in Progress | L21: MS PIPE | M21: MS Pipe | N21: 195 | O21: 9360 | P21: . | Q21: 11035.44 | R21: 9 | S21: 842.4 | T21: 9 | U21: 842.4 | V21: 0 | W21: 0 | X21: 0 | Y21: 1684.8 | Z21: 0 | AA21: 24AAACO3087C1ZT | AB21: KGS | AC21: 73063090 | AD21: Rs. | AE21: 1 | AF21: 195 | AG21: India | AH21: N.A
B22: 46205 | C22: Umasree Texplast Pvt Ltd - Sales | D22: Job Invoice | E22: KPV/D/384 | F22: Job Work Income | G22: KPV/D/384 | H22: 46205 | I22: SF | J22: PP/PE Fabric | K22: PP UL Fabric | L22: PP WOVEN FABRIC | M22: PP UL Fabric With UV | N22: 652.8 | O22: 31334.4 | P22: PP UL Fabric Ventilated | Q22: 36347.91 | R22: 9 | S22: 2820.1 | T22: 9 | U22: 2820.1 | V22: 0 | W22: 0 | X22: 0 | Y22: 5640.2 | Z22: 0 | AA22: 24AAACU6665Q1ZO | AB22: KGS | AC22: 998852 | AD22: Rs. | AE22: 1 | AF22: 652.8 | AG22: India | AH22: PP UL Fabric
B23: 46205 | C23: Umasree Texplast Pvt Ltd - Sales | D23: Job Invoice | E23: KPV/D/389 | F23: Job Work Income | G23: KPV/D/389 | H23: 46205 | I23: SF | J23: PP/PE Fabric | K23: PP UL Fabric | L23: PP WOVEN FABRIC | M23: PP UL Fabric With UV | N23: 1564 | O23: 75072 | P23: PP UL Fabric Ventilated | Q23: 87083.52 | R23: 9 | S23: 6756.48 | T23: 9 | U23: 6756.48 | V23: 0 | W23: 0 | X23: 0 | Y23: 13512.96 | Z23: 0 | AA23: 24AAACU6665Q1ZO | AB23: KGS | AC23: 998852 | AD23: Rs. | AE23: 1 | AF23: 1564 | AG23: India | AH23: PP UL Fabric
B24: 46206 | C24: HCP Plastene Bulkpack Limited - Sales | D24: Sales | E24: 391 | F24: Sales - Within State Manufactured Goods | G24: KPV/D/391 | H24: 46206 | I24: FG | J24: FIBC Bags | K24: FIBC Bags | L24: PP WOVEN BIG BAGS / SACKS | M24: FIBC Bags With UV Without Liner | N24: 7738.2 | O24: 1752160.6 | P24: 20-5658/4057-A | Q24: 2065797.4 | R24: 9 | S24: 157694.46 | T24: 9 | U24: 157694.46 | V24: 0 | W24: 0 | X24: 0 | Y24: 315388.92 | Z24: 0 | AA24: 24AABCG1282C2Z6 | AB24: KGS | AC24: 63053200 | AD24: Rs. | AE24: 1 | AF24: 7738.2 | AG24: India | AH24: FIBC Bags
B25: 46206 | C25: HCP Plastene Bulkpack Limited - Sales | D25: Sales | E25: 394 | F25: Sales - Within State Manufactured Goods | G25: KPV/D/394 | H25: 46206 | I25: SF | J25: PP/PE Fabric | K25: PP Lam Fabric | L25: PP WOVEN FABRIC | M25: PP Lam Fabric With UV | N25: 463 | O25: 72760.45 | P25: FIBC Fabric Coated (Less Then 90+20 GSM)_x000D_ | Q25: 92369.76 | R25: 9 | S25: 6548.44 | T25: 9 | U25: 6548.44 | V25: 0 | W25: 0 | X25: 0 | Y25: 13096.88 | Z25: 0 | AA25: 24AABCG1282C2Z6 | AB25: KGS | AC25: 39269080 | AD25: Rs. | AE25: 1 | AF25: 463 | AG25: India | AH25: PP Lam Fabric
B26: 46206 | C26: HCP Plastene Bulkpack Limited - Sales | D26: Sales | E26: 394 | F26: Sales - Within State Manufactured Goods | G26: KPV/D/394 | H26: 46206 | I26: SF | J26: Webbing | K26: PP Webbing | L26: PP WEBBING | M26: Webbing | N26: 36 | O26: 5585.4 | P26: Webbing Tie MW | Q26: 0 | R26: 9 | S26: 502.69 | T26: 9 | U26: 502.69 | V26: 0 | W26: 0 | X26: 0 | Y26: 1005.38 | Z26: 0 | AA26: 24AABCG1282C2Z6 | AB26: KGS | AC26: 39269080 | AD26: Rs. | AE26: 1 | AF26: 36 | AG26: India | AH26: PP Webbing
B27: 46206 | C27: HCP Plastene Bulkpack Limited - Sales | D27: Sales | E27: 395 | F27: Sales - Within State - Traded Goods | G27: KPV/D/395 | H27: 46206 | I27: Stores/Spares | J27: MS Structure Items | K27: Capital Work in Progress | L27: MS PIPE | M27: MS Pipe | N27: 8 | O27: 384 | P27: . | Q27: 452.74 | R27: 9 | S27: 34.56 | T27: 9 | U27: 34.56 | V27: 0 | W27: 0 | X27: 0 | Y27: 69.12 | Z27: 0 | AA27: 24AABCG1282C2Z6 | AB27: KGS | AC27: 73063090 | AD27: Rs. | AE27: 1 | AF27: 8 | AG27: India | AH27: N.A
B28: 46206 | C28: HCP Plastene Bulkpack Limited - Sales | D28: Sales | E28: 396 | F28: Sales - Within State Manufactured Goods | G28: KPV/D/396 | H28: 46206 | I28: SF | J28: Webbing | K28: PP Webbing | L28: PP WEBBING | M28: Webbing | N28: 780 | O28: 123357 | P28: Webbing BLUE / COLOR | Q28: 483032.58 | R28: 9 | S28: 11102.13 | T28: 9 | U28: 11102.13 | V28: 0 | W28: 0 | X28: 0 | Y28: 22204.26 | Z28: 0 | AA28: 24AABCG1282C2Z6 | AB28: KGS | AC28: 39269080 | AD28: Rs. | AE28: 1 | AF28: 780 | AG28: India | AH28: PP Webbing
B29: 46206 | C29: HCP Plastene Bulkpack Limited - Sales | D29: Sales | E29: 396 | F29: Sales - Within State Manufactured Goods | G29: KPV/D/396 | H29: 46206 | I29: SF | J29: Webbing | K29: PP Webbing | L29: PP WEBBING | M29: Webbing | N29: 685 | O29: 106277.75 | P29: Webbing MW | Q29: 0 | R29: 9 | S29: 9565 | T29: 9 | U29: 9565 | V29: 0 | W29: 0 | X29: 0 | Y29: 19130 | Z29: 0 | AA29: 24AABCG1282C2Z6 | AB29: KGS | AC29: 39269080 | AD29: Rs. | AE29: 1 | AF29: 685 | AG29: India | AH29: PP Webbing
B30: 46206 | C30: HCP Plastene Bulkpack Limited - Sales | D30: Sales | E30: 396 | F30: Sales - Within State Manufactured Goods | G30: KPV/D/396 | H30: 46206 | I30: SF | J30: PP/PE Fabric | K30: PP UL Fabric | L30: PP WOVEN FABRIC | M30: PP UL Fabric With UV | N30: 836.3 | O30: 153168.34 | P30: Sulzer Conductive Fabric_x000D_ | Q30: 0 | R30: 9 | S30: 13785.15 | T30: 9 | U30: 13785.15 | V30: 0 | W30: 0 | X30: 0 | Y30: 27570.3 | Z30: 0 | AA30: 24AABCG1282C2Z6 | AB30: KGS | AC30: 39269080 | AD30: Rs. | AE30: 1 | AF30: 836.3 | AG30: India | AH30: PP UL Fabric
B31: 46206 | C31: HCP Plastene Bulkpack Limited - Sales | D31: Sales | E31: 396 | F31: Sales - Within State Manufactured Goods | G31: KPV/D/396 | H31: 46206 | I31: SF | J31: PP/PE Fabric | K31: PP UL Fabric | L31: PP WOVEN FABRIC | M31: PP UL Fabric With UV | N31: 125 | O31: 26893.75 | P31: Conductive Fabric-Spout (Coated/Uncoated) Till 90 GSM Total_x000D_ | Q31: 0 | R31: 9 | S31: 2420.44 | T31: 9 | U31: 2420.44 | V31: 0 | W31: 0 | X31: 0 | Y31: 4840.88 | Z31: 0 | AA31: 24AABCG1282C2Z6 | AB31: KGS | AC31: 39269080 | AD31: Rs. | AE31: 1 | AF31: 125 | AG31: India | AH31: PP UL Fabric
B32: 46206 | C32: HCP Plastene Bulkpack Limited - Sales | D32: Sales | E32: 397 | F32: Sales - Within State - Traded Goods | G32: KPV/D/397 | H32: 46206 | I32: Stores/Spares | J32: MS Structure Items | K32: Capital Work in Progress | L32: MS PIPE | M32: MS Pipe | N32: 28 | O32: 1344 | P32: . | Q32: 1584.58 | R32: 9 | S32: 120.96 | T32: 9 | U32: 120.96 | V32: 0 | W32: 0 | X32: 0 | Y32: 241.92 | Z32: 0 | AA32: 24AABCG1282C2Z6 | AB32: KGS | AC32: 73063090 | AD32: Rs. | AE32: 1 | AF32: 28 | AG32: India | AH32: N.A
B33: 46206 | C33: HCP Plastene Bulkpack Limited - Sales | D33: Job Invoice | E33: KPV/D/390 | F33: Job Work Income | G33: KPV/D/390 | H33: 46206 | I33: FG | J33: FIBC Bags | K33: FIBC Bags | L33: PP WOVEN BIG BAGS / SACKS | M33: FIBC Bags With UV Without Liner | N33: 1342.6 | O33: 299238.69 | P33: PP WOVEN BIG BAG (26.19244/67291111-1) | Q33: 5126424.5 | R33: 9 | S33: 26931.48 | T33: 9 | U33: 26931.48 | V33: 0 | W33: 0 | X33: 0 | Y33: 53862.96 | Z33: 0 | AA33: 24AABCG1282C2Z6 | AB33: KGS | AC33: 998852 | AD33: Rs. | AE33: 1 | AF33: 1342.6 | AG33: India | AH33: FIBC Bags
B34: 46206 | C34: HCP Plastene Bulkpack Limited - Sales | D34: Job Invoice | E34: KPV/D/390 | F34: Job Work Income | G34: KPV/D/390 | H34: 46206 | I34: FG | J34: FIBC Bags | K34: FIBC Bags | L34: PP WOVEN BIG BAGS / SACKS | M34: FIBC Bags With UV Without Liner | N34: 18485.7 | O34: 4120092.8 | P34: PP WOVEN BIG BAG (26.19244/67291111-1) | Q34: 0 | R34: 9 | S34: 370808.35 | T34: 9 | U34: 370808.35 | V34: 0 | W34: 0 | X34: 0 | Y34: 741616.7 | Z34: 0 | AA34: 24AABCG1282C2Z6 | AB34: KGS | AC34: 998852 | AD34: Rs. | AE34: 1 | AF34: 18485.7 | AG34: India | AH34: FIBC Bags
B35: 46206 | C35: Plastene India ltd - Unit 1-Sales | D35: Sales | E35: 393 | F35: Sales - Within State Manufactured Goods | G35: KPV/D/393 | H35: 46206 | I35: SF | J35: Yarn All | K35: PP Yarn | L35: PP Tape | M35: PP Fibrillated Tape Twisted 3200 MW | N35: 1480 | O35: 223702 | P35: MW | Q35: 829327.65 | R35: 9 | S35: 20133.18 | T35: 9 | U35: 20133.18 | V35: 0 | W35: 0 | X35: 0 | Y35: 40266.36 | Z35: 0 | AA35: 24AAACO3087C1ZT | AB35: KGS | AC35: 39199090 | AD35: Rs. | AE35: 1 | AF35: 1480 | AG35: India | AH35: PP Yarn
B36: 46206 | C36: Plastene India ltd - Unit 1-Sales | D36: Sales | E36: 393 | F36: Sales - Within State Manufactured Goods | G36: KPV/D/393 | H36: 46206 | I36: SF | J36: PP/PE Fabric | K36: PP UL Fabric | L36: PP WOVEN FABRIC | M36: PP UL Fabric With UV | N36: 2210.6 | O36: 365080.59 | P36: PP UL Fabric FG | Q36: 0 | R36: 9 | S36: 32857.25 | T36: 9 | U36: 32857.25 | V36: 0 | W36: 0 | X36: 0 | Y36: 65714.5 | Z36: 0 | AA36: 24AAACO3087C1ZT | AB36: KGS | AC36: 39269080 | AD36: Rs. | AE36: 1 | AF36: 2210.6 | AG36: India | AH36: PP UL Fabric
B37: 46206 | C37: Plastene India ltd - Unit 1-Sales | D37: Sales | E37: 393 | F37: Sales - Within State Manufactured Goods | G37: KPV/D/393 | H37: 46206 | I37: SF | J37: PP/PE Fabric | K37: PP UL Fabric | L37: PP WOVEN FABRIC | M37: PP UL Fabric With UV | N37: 625.9 | O37: 114633.58 | P37: Sulzer Conductive Fabric_x000D_ | Q37: 0 | R37: 9 | S37: 10317.02 | T37: 9 | U37: 10317.02 | V37: 0 | W37: 0 | X37: 0 | Y37: 20634.04 | Z37: 0 | AA37: 24AAACO3087C1ZT | AB37: KGS | AC37: 39269080 | AD37: Rs. | AE37: 1 | AF37: 625.9 | AG37: India | AH37: PP UL Fabric
B38: 46206 | C38: Plastene India ltd - Unit 1-Sales | D38: Sales | E38: 398 | F38: Sales - Within State Manufactured Goods | G38: KPV/D/398 | H38: 46206 | I38: FG | J38: FIBC Bags | K38: FIBC Bags | L38: PP WOVEN BIG BAGS / SACKS | M38: FIBC Bags With UV With Liner | N38: 835 | O38: 272953.15 | P38: 26.19378/67004952-UN | Q38: 321811.76 | R38: 9 | S38: 24565.78 | T38: 9 | U38: 24565.78 | V38: 0 | W38: 0 | X38: 0 | Y38: 49131.56 | Z38: 0 | AA38: 24AAACO3087C1ZT | AB38: KGS | AC38: 63053200 | AD38: Rs. | AE38: 1 | AF38: 835 | AG38: India | AH38: FIBC Bags
B39: 46206 | C39: Plastene Polyfilms Ltd-Sales | D39: Sales | E39: 392 | F39: Sales - Within State Manufactured Goods | G39: KPV/D/392 | H39: 46206 | I39: RM | J39: Granules | K39: PP Granules | L39: PP Granuals | M39: PP Advanced H312 | N39: 49500 | O39: 3821053.5 | P39: PP Advanced H312 | Q39: 4505022.1 | R39: 9 | S39: 343894.82 | T39: 9 | U39: 343894.82 | V39: 0 | W39: 0 | X39: 0 | Y39: 687789.64 | Z39: 0 | AA39: 24AAFCP2956A1ZR | AB39: KGS | AC39: 39021000 | AD39: Rs. | AE39: 1 | AF39: 49500 | AG39: India | AH39: PP Granules
B40: 46207 | C40: Flexochem Ventures Private Limited | D40: Sales | E40: 402 | F40: Sales - Within State Manufactured Goods | G40: KPV/D/402 | H40: 46207 | I40: FG | J40: FIBC Bags | K40: FIBC Bags | L40: PP WOVEN BIG BAGS / SACKS | M40: FIBC Bags With UV Without Liner | N40: 279.5 | O40: 67800 | P40: 90X90X70 | Q40: 80004 | R40: 9 | S40: 6102 | T40: 9 | U40: 6102 | V40: 0 | W40: 0 | X40: 0 | Y40: 12204 | Z40: 0 | AA40: 24AAFCF0504J1Z2 | AB40: KGS | AC40: 63053200 | AD40: Rs. | AE40: 1 | AF40: 279.5 | AG40: India | AH40: FIBC Bags
B41: 46207 | C41: Hcp Plastene Bulkpack Ltd (Unit Iv) - Sales | D41: Sales | E41: 404 | F41: Sales - Within State Manufactured Goods | G41: KPV/D/404 | H41: 46207 | I41: SF | J41: Yarn All | K41: PP Yarn | L41: PP FABRILLATED YARN | M41: PP Fibrillated Tape Twisted 3200 Blue | N41: 1340 | O41: 206561 | P41: BLUE | Q41: 297546.21 | R41: 2.5 | S41: 5164.02 | T41: 2.5 | U41: 5164.02 | V41: 0 | W41: 0 | X41: 0 | Y41: 10328.04 | Z41: 0 | AA41: 24AABCG1282C2Z6 | AB41: KGS | AC41: 54026930 | AD41: Rs. | AE41: 1 | AF41: 1340 | AG41: India | AH41: PP Yarn
B42: 46207 | C42: Hcp Plastene Bulkpack Ltd (Unit Iv) - Sales | D42: Sales | E42: 404 | F42: Sales - Within State Manufactured Goods | G42: KPV/D/404 | H42: 46207 | I42: SF | J42: Yarn All | K42: PP Yarn | L42: PP FABRILLATED YARN | M42: PP Fibrillated Tape Twisted 3200 MW | N42: 510 | O42: 77086.5 | P42: MW | Q42: 0 | R42: 2.5 | S42: 1927.16 | T42: 2.5 | U42: 1927.16 | V42: 0 | W42: 0 | X42: 0 | Y42: 3854.32 | Z42: 0 | AA42: 24AABCG1282C2Z6 | AB42: KGS | AC42: 54026930 | AD42: Rs. | AE42: 1 | AF42: 510 | AG42: India | AH42: PP Yarn
B43: 46207 | C43: Plastene India ltd - Unit 1-Sales | D43: Sales | E43: 399 | F43: Sales - Within State Manufactured Goods | G43: KPV/D/399 | H43: 46207 | I43: RM | J43: Granules | K43: PP Granules | L43: PP Granuals | M43: PP Advanced H312 | N43: 90750 | O43: 7005264.8 | P43: PP Advanced H312 | Q43: 8259207.2 | R43: 9 | S43: 630473.83 | T43: 9 | U43: 630473.83 | V43: 0 | W43: 0 | X43: 0 | Y43: 1260947.7 | Z43: 0 | AA43: 24AAACO3087C1ZT | AB43: KGS | AC43: 39021000 | AD43: Rs. | AE43: 1 | AF43: 90750 | AG43: India | AH43: PP Granules
B44: 46207 | C44: Plastene India ltd - Unit 2-Sales | D44: Sales | E44: 400 | F44: Sales - Within State Manufactured Goods | G44: KPV/D/400 | H44: 46207 | I44: SF | J44: Yarn All | K44: PP Yarn | L44: PP FABRILLATED YARN | M44: PP Fibrillated Tape Twisted 3200 MW | N44: 1520 | O44: 229748 | P44: MW | Q44: 897775.77 | R44: 2.5 | S44: 5743.7 | T44: 2.5 | U44: 5743.7 | V44: 0 | W44: 0 | X44: 0 | Y44: 11487.4 | Z44: 0 | AA44: 24AAACO3087C1ZT | AB44: KGS | AC44: 54026930 | AD44: Rs. | AE44: 1 | AF44: 1520 | AG44: India | AH44: PP Yarn
B45: 46207 | C45: Plastene India ltd - Unit 2-Sales | D45: Sales | E45: 400 | F45: Sales - Within State Manufactured Goods | G45: KPV/D/400 | H45: 46207 | I45: SF | J45: Yarn All | K45: PP Yarn | L45: PP FABRILLATED YARN | M45: PP Fibrillated Tape Twisted 3200 Blue | N45: 460 | O45: 70909 | P45: BLUE | Q45: 0 | R45: 2.5 | S45: 1772.72 | T45: 2.5 | U45: 1772.72 | V45: 0 | W45: 0 | X45: 0 | Y45: 3545.44 | Z45: 0 | AA45: 24AAACO3087C1ZT | AB45: KGS | AC45: 54026930 | AD45: Rs. | AE45: 1 | AF45: 460 | AG45: India | AH45: PP Yarn
B46: 46207 | C46: Plastene India ltd - Unit 2-Sales | D46: Sales | E46: 400 | F46: Sales - Within State Manufactured Goods | G46: KPV/D/400 | H46: 46207 | I46: SF | J46: Webbing | K46: PP Webbing | L46: PP WEBBING | M46: Webbing | N46: 3183.8 | O46: 493966.57 | P46: Webbing MW | Q46: 0 | R46: 9 | S46: 44456.99 | T46: 9 | U46: 44456.99 | V46: 0 | W46: 0 | X46: 0 | Y46: 88913.98 | Z46: 0 | AA46: 24AAACO3087C1ZT | AB46: KGS | AC46: 39269080 | AD46: Rs. | AE46: 1 | AF46: 3183.8 | AG46: India | AH46: PP Webbing
... B48: 46207 | C48: Plastene Polyfilms Ltd-Sales | D48: Sales | E48: 403 | F48: Sales - Within State Manufactured Goods | G48: KPV/D/403 | H48: 46207 | I48: SF | J48: Yarn All | K48: PP Yarn | L48: PP FABRILLATED YARN | M48: PP Fibrillated Tape Twisted 3200 MW | N48: 3250 | O48: 491237.5 | P48: MW | Q48: 515308.14 | R48: 2.5 | S48: 12280.94 | T48: 2.5 | U48: 12280.94 | V48: 0 | W48: 0 | X48: 0 | Y48: 24561.88 | Z48: 0 | AA48: 24AAFCP2956A1ZR | AB48: KGS | AC48: 54026930 | AD48: Rs. | AE48: 1 | AF48: 3250 | AG48: India | AH48: PP Yarn
B49: 46207 | C49: Tecnopacking | D49: Export Sales | E49: KPW/E/90/26-27 | F49: Sales - Direct Export - Mfg - U/R | G49: KPW/E/90/26-27 | H49: 46207 | I49: FG | J49: FIBC Bags | K49: FIBC Bags | L49: PP WOVEN BIG BAGS / SACKS | M49: FIBC Bags With UV Without Liner | N49: 19817.4 | O49: 3751968 | P49: PP WOVEN BIG BAG | Q49: 3751968 | R49: 0 | S49: 0 | T49: 0 | U49: 0 | V49: 18 | W49: 675354.24 | X49: 0.17 | Y49: 675354.41 | Z49: 0 | AA49: N.A. | AB49: KGS | AC49: 63053200 | AD49: $ | AE49: 93.5 | AF49: 19817.4 | AG49: Spain | AH49: FIBC Bags
B50: 46208 | C50: HCP Plastene Bulkpack Limited - Sales | D50: Sales | E50: 405 | F50: Sales - Within State Manufactured Goods | G50: KPV/D/405 | H50: 46208 | I50: SF | J50: Webbing | K50: PP Webbing | L50: PP WEBBING | M50: Webbing | N50: 261 | O50: 41277.15 | P50: Webbing BLUE | Q50: 496051.52 | R50: 9 | S50: 3714.94 | T50: 9 | U50: 3714.94 | V50: 0 | W50: 0 | X50: 0 | Y50: 7429.88 | Z50: 0 | AA50: 24AABCG1282C2Z6 | AB50: KGS | AC50: 39269080 | AD50: Rs. | AE50: 1 | AF50: 261 | AG50: India | AH50: PP Webbing
B51: 46208 | C51: HCP Plastene Bulkpack Limited - Sales | D51: Sales | E51: 405 | F51: Sales - Within State Manufactured Goods | G51: KPV/D/405 | H51: 46208 | I51: SF | J51: Webbing | K51: PP Webbing | L51: PP WEBBING | M51: Webbing | N51: 971 | O51: 153563.65 | P51: Webbing BLACK | Q51: 0 | R51: 9 | S51: 13820.73 | T51: 9 | U51: 13820.73 | V51: 0 | W51: 0 | X51: 0 | Y51: 27641.46 | Z51: 0 | AA51: 24AABCG1282C2Z6 | AB51: KGS | AC51: 39269080 | AD51: Rs. | AE51: 1 | AF51: 971 | AG51: India | AH51: PP Webbing
B52: 46208 | C52: HCP Plastene Bulkpack Limited - Sales | D52: Sales | E52: 405 | F52: Sales - Within State Manufactured Goods | G52: KPV/D/405 | H52: 46208 | I52: SF | J52: Webbing | K52: PP Webbing | L52: PP WEBBING | M52: Webbing | N52: 1456 | O52: 225898.4 | P52: Webbing MW | Q52: 0 | R52: 9 | S52: 20330.86 | T52: 9 | U52: 20330.86 | V52: 0 | W52: 0 | X52: 0 | Y52: 40661.72 | Z52: 0 | AA52: 24AABCG1282C2Z6 | AB52: KGS | AC52: 39269080 | AD52: Rs. | AE52: 1 | AF52: 1456 | AG52: India | AH52: PP Webbing
B53: 46208 | C53: HCP Plastene Bulkpack Limited - Sales | D53: Sales | E53: 406 | F53: Sales - Within State - Traded Goods | G53: KPV/D/406 | H53: 46208 | I53: Stores/Spares | J53: MS Structure Items | K53: Capital Work in Progress | L53: MS PIPE | M53: MS Pipe 4 C Class | N53: 1022 | O53: 49056 | P53: . | Q53: 57837.02 | R53: 9 | S53: 4415.04 | T53: 9 | U53: 4415.04 | V53: 0 | W53: 0 | X53: 0 | Y53: 8830.08 | Z53: 0 | AA53: 24AABCG1282C2Z6 | AB53: KGS | AC53: 73063090 | AD53: Rs. | AE53: 1 | AF53: 1022 | AG53: India | AH53: N.A
B54: 46208 | C54: Plastene India ltd - Unit 1-Sales | D54: Sales | E54: 407 | F54: Sales - Within State Manufactured Goods | G54: KPV/D/407 | H54: 46208 | I54: FG | J54: FIBC Bags | K54: FIBC Bags | L54: PP WOVEN BIG BAGS / SACKS | M54: FIBC Bags With UV With Liner | N54: 1923 | O54: 828178.41 | P54: 25/80334/25687/15.4719-18 | Q54: 2759451.3 | R54: 9 | S54: 74536.06 | T54: 9 | U54: 74536.06 | V54: 0 | W54: 0 | X54: 0 | Y54: 149072.12 | Z54: 0 | AA54: 24AAACO3087C1ZT | AB54: KGS | AC54: 63053200 | AD54: Rs. | AE54: 1 | AF54: 1923 | AG54: India | AH54: FIBC Bags
B55: 46208 | C55: Plastene India ltd - Unit 1-Sales | D55: Sales | E55: 407 | F55: Sales - Within State Manufactured Goods | G55: KPV/D/407 | H55: 46208 | I55: FG | J55: FIBC Bags | K55: FIBC Bags | L55: PP WOVEN BIG BAGS / SACKS | M55: FIBC Bags With UV Without Liner | N55: 817 | O55: 124666.03 | P55: 25/80122/25618/15.2622-18 | Q55: 0 | R55: 9 | S55: 11219.94 | T55: 9 | U55: 11219.94 | V55: 0 | W55: 0 | X55: 0 | Y55: 22439.88 | Z55: 0 | AA55: 24AAACO3087C1ZT | AB55: KGS | AC55: 63053200 | AD55: Rs. | AE55: 1 | AF55: 817 | AG55: India | AH55: FIBC Bags
B56: 46208 | C56: Plastene India ltd - Unit 1-Sales | D56: Sales | E56: 407 | F56: Sales - Within State Manufactured Goods | G56: KPV/D/407 | H56: 46208 | I56: FG | J56: FIBC Bags | K56: FIBC Bags | L56: PP WOVEN BIG BAGS / SACKS | M56: FIBC Bags With UV Without Liner | N56: 4582.6 | O56: 1387657.1 | P56: 26/80122/26131/15.1657-18 | Q56: 0 | R56: 9 | S56: 124889.14 | T56: 9 | U56: 124889.14 | V56: 0 | W56: 0 | X56: 0 | Y56: 249778.28 | Z56: 0 | AA56: 24AAACO3087C1ZT | AB56: KGS | AC56: 63053200 | AD56: Rs. | AE56: 1 | AF56: 4582.6 | AG56: India | AH56: FIBC Bags
B57: 46209 | C57: HCP Plastene Bulkpack Limited - Sales | D57: Sales | E57: 409 | F57: Sales - Within State Manufactured Goods | G57: KPV/D/409 | H57: 46209 | I57: FG | J57: FIBC Bags | K57: FIBC Bags | L57: PP WOVEN BIG BAGS / SACKS | M57: FIBC Bags With UV Without Liner | N57: 5172.5 | O57: 1462576.1 | P57: 202600223/006789 | Q57: 6186574.8 | R57: 9 | S57: 131631.85 | T57: 9 | U57: 131631.85 | V57: 0 | W57: 0 | X57: 0 | Y57: 263263.7 | Z57: 0 | AA57: 24AABCG1282C2Z6 | AB57: KGS | AC57: 63053200 | AD57: Rs. | AE57: 1 | AF57: 5172.5 | AG57: India | AH57: FIBC Bags
B58: 46209 | C58: HCP Plastene Bulkpack Limited - Sales | D58: Sales | E58: 409 | F58: Sales - Within State Manufactured Goods | G58: KPV/D/409 | H58: 46209 | I58: FG | J58: FIBC Bags | K58: FIBC Bags | L58: PP WOVEN BIG BAGS / SACKS | M58: FIBC Bags With UV Without Liner | N58: 889 | O58: 238865.41 | P58: 202600237/010144 | Q58: 0 | R58: 9 | S58: 21497.89 | T58: 9 | U58: 21497.89 | V58: 0 | W58: 0 | X58: 0 | Y58: 42995.78 | Z58: 0 | AA58: 24AABCG1282C2Z6 | AB58: KGS | AC58: 63053200 | AD58: Rs. | AE58: 1 | AF58: 889 | AG58: India | AH58: FIBC Bags
B59: 46209 | C59: HCP Plastene Bulkpack Limited - Sales | D59: Sales | E59: 409 | F59: Sales - Within State Manufactured Goods | G59: KPV/D/409 | H59: 46209 | I59: FG | J59: FIBC Bags | K59: FIBC Bags | L59: PP WOVEN BIG BAGS / SACKS | M59: FIBC Bags With UV Without Liner | N59: 2236.8 | O59: 597270.34 | P59: 202600237/010145 | Q59: 0 | R59: 9 | S59: 53754.33 | T59: 9 | U59: 53754.33 | V59: 0 | W59: 0 | X59: 0 | Y59: 107508.66 | Z59: 0 | AA59: 24AABCG1282C2Z6 | AB59: KGS | AC59: 63053200 | AD59: Rs. | AE59: 1 | AF59: 2236.8 | AG59: India | AH59: FIBC Bags
B60: 46209 | C60: HCP Plastene Bulkpack Limited - Sales | D60: Sales | E60: 409 | F60: Sales - Within State Manufactured Goods | G60: KPV/D/409 | H60: 46209 | I60: FG | J60: FIBC Bags | K60: FIBC Bags | L60: PP WOVEN BIG BAGS / SACKS | M60: FIBC Bags With UV Without Liner | N60: 2164.7 | O60: 565138.23 | P60: 202600237/010146 | Q60: 0 | R60: 9 | S60: 50862.44 | T60: 9 | U60: 50862.44 | V60: 0 | W60: 0 | X60: 0 | Y60: 101724.88 | Z60: 0 | AA60: 24AABCG1282C2Z6 | AB60: KGS | AC60: 63053200 | AD60: Rs. | AE60: 1 | AF60: 2164.7 | AG60: India | AH60: FIBC Bags
B61: 46209 | C61: HCP Plastene Bulkpack Limited - Sales | D61: Sales | E61: 409 | F61: Sales - Within State Manufactured Goods | G61: KPV/D/409 | H61: 46209 | I61: FG | J61: FIBC Bags | K61: FIBC Bags | L61: PP WOVEN BIG BAGS / SACKS | M61: FIBC Bags With UV Without Liner | N61: 4235.3 | O61: 1074665 | P61: 202600237/010147 | Q61: 0 | R61: 9 | S61: 96719.85 | T61: 9 | U61: 96719.85 | V61: 0 | W61: 0 | X61: 0 | Y61: 193439.7 | Z61: 0 | AA61: 24AABCG1282C2Z6 | AB61: KGS | AC61: 63053200 | AD61: Rs. | AE61: 1 | AF61: 4235.3 | AG61: India | AH61: FIBC Bags
... B73: 46209 | C73: Plastene Polyfilms Ltd-Sales | D73: Sales | E73: 414 | F73: Sales - Within State Manufactured Goods | G73: KPV/D/414 | H73: 46209 | I73: FG | J73: FIBC Bags | K73: FIBC Bags | L73: PP WOVEN BIG BAGS / SACKS | M73: FIBC Bags With UV Without Liner | N73: 19278.4 | O73: 4570715.9 | P73: PO-9211/MFGCL404856DSFOOD | Q73: 5388874 | R73: 9 | S73: 411364.43 | T73: 9 | U73: 411364.43 | V73: 0 | W73: 0 | X73: 0 | Y73: 822728.86 | Z73: 0 | AA73: 24AAFCP2956A1ZR | AB73: KGS | AC73: 63053200 | AD73: Rs. | AE73: 1 | AF73: 19278.4 | AG73: India | AH73: FIBC Bags
B74: 46210 | C74: Ameriglobe LLC | D74: Export Sales | E74: KPW/E/91/26-27 | F74: Sales - Direct Export - Mfg - U/R | G74: KPW/E/91/26-27 | H74: 46210 | I74: FG | J74: FIBC Bags | K74: FIBC Bags | L74: PP WOVEN BIG BAGS / SACKS | M74: FIBC Bags With UV With Liner | N74: 17484.7 | O74: 4957444.8 | P74: PP WOVEN BIG BAG | Q74: 4957444.8 | R74: 0 | S74: 0 | T74: 0 | U74: 0 | V74: 18 | W74: 892340.06 | X74: 0.17 | Y74: 892340.23 | Z74: 0 | AA74: N.A. | AB74: KGS | AC74: 63053200 | AD74: $ | AE74: 93.5 | AF74: 17484.7 | AG74: USA | AH74: FIBC Bags
B75: 46210 | C75: Bulk Lift International LLC | D75: Export Sales | E75: KPW/E/92/26-27 | F75: Sales - Direct Export - Mfg - U/R | G75: KPW/E/92/26-27 | H75: 46210 | I75: FG | J75: FIBC Bags | K75: FIBC Bags | L75: PP WOVEN BIG BAGS / SACKS | M75: FIBC Bags With UV With Liner | N75: 4320.7 | O75: 1246658.9 | P75: PP WOVEN BIG BAG | Q75: 4825974.5 | R75: 0 | S75: 0 | T75: 0 | U75: 0 | V75: 18 | W75: 224398.13 | X75: 0.17 | Y75: 224398.3 | Z75: 0 | AA75: N.A. | AB75: KGS | AC75: 63053200 | AD75: $ | AE75: 93.5 | AF75: 4320.7 | AG75: USA | AH75: FIBC Bags
B76: 46210 | C76: Bulk Lift International LLC | D76: Export Sales | E76: KPW/E/92/26-27 | F76: Sales - Direct Export - Mfg - U/R | G76: KPW/E/92/26-27 | H76: 46210 | I76: FG | J76: FIBC Bags | K76: FIBC Bags | L76: PP WOVEN BIG BAGS / SACKS | M76: FIBC Bags With UV Without Liner | N76: 12732.8 | O76: 3579315.6 | P76: PP WOVEN BIG BAG | Q76: 0 | R76: 0 | S76: 0 | T76: 0 | U76: 0 | V76: 18 | W76: 644276.71 | X76: 0.17 | Y76: 644276.88 | Z76: 0 | AA76: N.A. | AB76: KGS | AC76: 63053200 | AD76: $ | AE76: 93.5 | AF76: 12732.8 | AG76: USA | AH76: FIBC Bags
B77: 46210 | C77: HCP Plastene Bulkpack Limited - Sales | D77: Sales | E77: 415 | F77: Sales - Within State - Traded Goods | G77: KPV/D/415 | H77: 46210 | I77: Consumables | J77: Consumables | K77: Consumables | L77: PP WOVEN FABRIC | M77: Hotmelt ( Glue ) | N77: 200 | O77: 64000 | P77: Hotmelt ( Glue ) | Q77: 75456 | R77: 9 | S77: 5760 | T77: 9 | U77: 5760 | V77: 0 | W77: 0 | X77: 0 | Y77: 11520 | Z77: 0 | AA77: 24AABCG1282C2Z6 | AB77: KGS | AC77: 350610 | AD77: Rs. | AE77: 1 | AF77: 200 | AG77: India | AH77: N.A
B78: 46211 | C78: HCP Plastene Bulkpack Limited - Sales | D78: Job Invoice | E78: KPV/D/416 | F78: Job Work Income | G78: KPV/D/416 | H78: 46211 | I78: FG | J78: FIBC Bags | K78: FIBC Bags | L78: PP WOVEN BIG BAGS / SACKS | M78: FIBC Bags With UV Without Liner | N78: 20260.7 | O78: 4441550.7 | P78: PO26045/0015-15CS(4)-REV08 (PP BIG BAGS) | Q78: 5152198.8 | R78: 9 | S78: 399739.56 | T78: 9 | U78: 399739.56 | V78: 0 | W78: 0 | X78: 0 | Y78: 799479.12 | Z78: 0 | AA78: 24AABCG1282C2Z6 | AB78: KGS | AC78: 998852 | AD78: Rs. | AE78: 1 | AF78: 20260.7 | AG78: India | AH78: FIBC Bags
B79: 46211 | C79: Plastene India ltd - Unit 1-Sales | D79: Sales | E79: 418 | F79: Sales - Within State Manufactured Goods | G79: KPV/D/418 | H79: 46211 | I79: SF | J79: Yarn All | K79: PP Yarn | L79: PP FABRILLATED YARN | M79: PP Fibrillated Tape Twisted 3200 Blue | N79: 1063.2 | O79: 163892.28 | P79: BLUE | Q79: 334252.99 | R79: 2.5 | S79: 4097.31 | T79: 2.5 | U79: 4097.31 | V79: 0 | W79: 0 | X79: 0 | Y79: 8194.62 | Z79: 0 | AA79: 24AAACO3087C1ZT | AB79: KGS | AC79: 54026930 | AD79: Rs. | AE79: 1 | AF79: 1063.2 | AG79: India | AH79: PP Yarn
B80: 46211 | C80: Plastene India ltd - Unit 1-Sales | D80: Sales | E80: 418 | F80: Sales - Within State Manufactured Goods | G80: KPV/D/418 | H80: 46211 | I80: SF | J80: Yarn All | K80: PP Yarn | L80: PP FABRILLATED YARN | M80: PP Fibrillated Tape Twisted 3200 MW | N80: 1023.8 | O80: 154747.37 | P80: MW | Q80: 0 | R80: 2.5 | S80: 3868.68 | T80: 2.5 | U80: 3868.68 | V80: 0 | W80: 0 | X80: 0 | Y80: 7737.36 | Z80: 0 | AA80: 24AAACO3087C1ZT | AB80: KGS | AC80: 54026930 | AD80: Rs. | AE80: 1 | AF80: 1023.8 | AG80: India | AH80: PP Yarn
B81: 46211 | C81: Plastene India ltd - Unit 1-Sales | D81: Sales | E81: 419 | F81: Sales - Within State - Traded Goods | G81: KPV/D/419 | H81: 46211 | I81: Stores/Spares | J81: MS Structure Items | K81: Capital Work in Progress | L81: MS PIPE | M81: MS Pipe 4 C Class | N81: 1068 | O81: 51264 | P81: . | Q81: 60440.26 | R81: 9 | S81: 4613.76 | T81: 9 | U81: 4613.76 | V81: 0 | W81: 0 | X81: 0 | Y81: 9227.52 | Z81: 0 | AA81: 24AAACO3087C1ZT | AB81: KGS | AC81: 73063090 | AD81: Rs. | AE81: 1 | AF81: 1068 | AG81: India | AH81: N.A
B82: 46211 | C82: Plastene India ltd - Unit 1-Sales | D82: Sales | E82: 420 | F82: Sales - Within State Manufactured Goods | G82: KPV/D/420 | H82: 46211 | I82: SF | J82: Yarn All | K82: PP Yarn | L82: PP FABRILLATED YARN | M82: PP Fibrillated Tape Twisted 3200 Blue | N82: 727.1 | O82: 112082.47 | P82: BLUE | Q82: 474535.58 | R82: 9 | S82: 10087.42 | T82: 9 | U82: 10087.42 | V82: 0 | W82: 0 | X82: 0 | Y82: 20174.84 | Z82: 0 | AA82: 24AAACO3087C1ZT | AB82: KGS | AC82: 39199090 | AD82: Rs. | AE82: 1 | AF82: 727.1 | AG82: India | AH82: PP Yarn
B83: 46211 | C83: Plastene India ltd - Unit 1-Sales | D83: Sales | E83: 420 | F83: Sales - Within State Manufactured Goods | G83: KPV/D/420 | H83: 46211 | I83: SF | J83: Yarn All | K83: PP Yarn | L83: PP FABRILLATED YARN | M83: PP Fibrillated Tape Twisted 3200 MW | N83: 1034 | O83: 156289.1 | P83: MW | Q83: 0 | R83: 9 | S83: 14066.02 | T83: 9 | U83: 14066.02 | V83: 0 | W83: 0 | X83: 0 | Y83: 28132.04 | Z83: 0 | AA83: 24AAACO3087C1ZT | AB83: KGS | AC83: 39199090 | AD83: Rs. | AE83: 1 | AF83: 1034 | AG83: India | AH83: PP Yarn
B84: 46211 | C84: Plastene India ltd - Unit 1-Sales | D84: Sales | E84: 420 | F84: Sales - Within State Manufactured Goods | G84: KPV/D/420 | H84: 46211 | I84: SF | J84: PP/PE Fabric | K84: PP UL Fabric | L84: PP WOVEN FABRIC | M84: PP UL Fabric With UV | N84: 812.1 | O84: 134118.32 | P84: F.G | Q84: 0 | R84: 9 | S84: 12070.65 | T84: 9 | U84: 12070.65 | V84: 0 | W84: 0 | X84: 0 | Y84: 24141.3 | Z84: 0 | AA84: 24AAACO3087C1ZT | AB84: KGS | AC84: 39269080 | AD84: Rs. | AE84: 1 | AF84: 812.1 | AG84: India | AH84: PP UL Fabric
B85: 46211 | C85: Sacos Durcal S.A | D85: Export Sales | E85: KPW/E/93/26-27 | F85: Sales - Direct Export - Mfg - U/R | G85: KPW/E/93/26-27 | H85: 46211 | I85: FG | J85: FIBC Bags | K85: FIBC Bags | L85: PP WOVEN BIG BAGS / SACKS | M85: FIBC Bags With UV Without Liner | N85: 22144.85 | O85: 4679354.2 | P85: PP WOVEN BIG BAG | Q85: 4999754.4 | R85: 0 | S85: 0 | T85: 0 | U85: 0 | V85: 18 | W85: 842283.76 | X85: 57222.02 | Y85: 899505.78 | Z85: 0 | AA85: N.A. | AB85: KGS | AC85: 63053200 | AD85: € | AE85: 105.4 | AF85: 22144.85 | AG85: Spain | AH85: FIBC Bags
B86: 46212 | C86: HCP Plastene Bulkpack Limited - Sales | D86: Sales | E86: 426 | F86: Sales - Within State Manufactured Goods | G86: KPV/D/426 | H86: 46212 | I86: SF | J86: Webbing | K86: PP Webbing | L86: PP WEBBING | M86: Webbing | N86: 243 | O86: 38430.45 | P86: BLUE | Q86: 506821.7 | R86: 9 | S86: 3458.74 | T86: 9 | U86: 3458.74 | V86: 0 | W86: 0 | X86: 0 | Y86: 6917.48 | Z86: 0 | AA86: 24AABCG1282C2Z6 | AB86: KGS | AC86: 39269080 | AD86: Rs. | AE86: 1 | AF86: 243 | AG86: India | AH86: PP Webbing
B87: 46212 | C87: HCP Plastene Bulkpack Limited - Sales | D87: Sales | E87: 426 | F87: Sales - Within State Manufactured Goods | G87: KPV/D/426 | H87: 46212 | I87: SF | J87: Webbing | K87: PP Webbing | L87: PP WEBBING | M87: Webbing | N87: 662 | O87: 102709.3 | P87: MW | Q87: 0 | R87: 9 | S87: 9243.84 | T87: 9 | U87: 9243.84 | V87: 0 | W87: 0 | X87: 0 | Y87: 18487.68 | Z87: 0 | AA87: 24AABCG1282C2Z6 | AB87: KGS | AC87: 39269080 | AD87: Rs. | AE87: 1 | AF87: 662 | AG87: India | AH87: PP Webbing
B88: 46212 | C88: HCP Plastene Bulkpack Limited - Sales | D88: Sales | E88: 426 | F88: Sales - Within State Manufactured Goods | G88: KPV/D/426 | H88: 46212 | I88: SF | J88: Webbing | K88: PP Webbing | L88: PP WEBBING | M88: Webbing | N88: 1825.7 | O88: 288734.46 | P88: BLACK | Q88: 0 | R88: 9 | S88: 25986.1 | T88: 9 | U88: 25986.1 | V88: 0 | W88: 0 | X88: 0 | Y88: 51972.2 | Z88: 0 | AA88: 24AABCG1282C2Z6 | AB88: KGS | AC88: 39269080 | AD88: Rs. | AE88: 1 | AF88: 1825.7 | AG88: India | AH88: PP Webbing
B89: 46212 | C89: Hcp Plastene Bulkpack Ltd Vadodara-Sales | D89: Sales | E89: 430 | F89: Sales - Within State Manufactured Goods | G89: KPV/D/430 | H89: 46212 | I89: SF | J89: Yarn All | K89: PP Yarn | L89: PP FABRILLATED YARN | M89: PP Fibrillated Tape Twisted 3200 Blue | N89: 630 | O89: 97114.5 | P89: BLUE | Q89: 635227.49 | R89: 2.5 | S89: 2427.86 | T89: 2.5 | U89: 2427.86 | V89: 0 | W89: 0 | X89: 0 | Y89: 4855.72 | Z89: 0 | AA89: 24AABCG1282C2Z6 | AB89: KGS | AC89: 54026930 | AD89: Rs. | AE89: 1 | AF89: 630 | AG89: India | AH89: PP Yarn
B90: 46212 | C90: Hcp Plastene Bulkpack Ltd Vadodara-Sales | D90: Sales | E90: 430 | F90: Sales - Within State Manufactured Goods | G90: KPV/D/430 | H90: 46212 | I90: SF | J90: Yarn All | K90: PP Yarn | L90: PP FABRILLATED YARN | M90: PP Fibrillated Tape Twisted 3200 MW | N90: 530 | O90: 80109.5 | P90: MW | Q90: 0 | R90: 2.5 | S90: 2002.74 | T90: 2.5 | U90: 2002.74 | V90: 0 | W90: 0 | X90: 0 | Y90: 4005.48 | Z90: 0 | AA90: 24AABCG1282C2Z6 | AB90: KGS | AC90: 54026930 | AD90: Rs. | AE90: 1 | AF90: 530 | AG90: India | AH90: PP Yarn
B91: 46212 | C91: Hcp Plastene Bulkpack Ltd Vadodara-Sales | D91: Sales | E91: 430 | F91: Sales - Within State Manufactured Goods | G91: KPV/D/430 | H91: 46212 | I91: SF | J91: Yarn All | K91: Polyester Yarn | L91: PP MF Yarn | M91: Polyester Yarn Twisted | N91: 80 | O91: 10640 | P91: Polyester Yarn Twisted | Q91: 0 | R91: 2.5 | S91: 266 | T91: 2.5 | U91: 266 | V91: 0 | W91: 0 | X91: 0 | Y91: 532 | Z91: 0 | AA91: 24AABCG1282C2Z6 | AB91: KGS | AC91: 54026990 | AD91: Rs. | AE91: 1 | AF91: 80 | AG91: India | AH91: Polyester Yarn
B92: 46212 | C92: Hcp Plastene Bulkpack Ltd Vadodara-Sales | D92: Sales | E92: 430 | F92: Sales - Within State Manufactured Goods | G92: KPV/D/430 | H92: 46212 | I92: SF | J92: Yarn All | K92: PP Yarn | L92: Filler code | M92: Filler Cord | N92: 307 | O92: 51161.55 | P92: Filler Cord | Q92: 0 | R92: 2.5 | S92: 1279.04 | T92: 2.5 | U92: 1279.04 | V92: 0 | W92: 0 | X92: 0 | Y92: 2558.08 | Z92: 0 | AA92: 24AABCG1282C2Z6 | AB92: KGS | AC92: 54026930 | AD92: Rs. | AE92: 1 | AF92: 307 | AG92: India | AH92: PP Yarn
B93: 46212 | C93: Hcp Plastene Bulkpack Ltd Vadodara-Sales | D93: Sales | E93: 430 | F93: Sales - Within State Manufactured Goods | G93: KPV/D/430 | H93: 46212 | I93: SF | J93: PP/PE Fabric | K93: PP Lam Fabric | L93: PP LAMINETED FABRIC | M93: PP Lam Fabric With UV | N93: 817 | O93: 147182.55 | P93: Conductive Fabric-FIBC Heavy GSM (More then 90 GSM Total)_x000D_ | Q93: 0 | R93: 9 | S93: 13246.43 | T93: 9 | U93: 13246.43 | V93: 0 | W93: 0 | X93: 0 | Y93: 26492.86 | Z93: 0 | AA93: 24AABCG1282C2Z6 | AB93: KGS | AC93: 39269080 | AD93: Rs. | AE93: 1 | AF93: 817 | AG93: India | AH93: PP Lam Fabric
B94: 46212 | C94: Hcp Plastene Bulkpack Ltd Vadodara-Sales | D94: Sales | E94: 430 | F94: Sales - Within State Manufactured Goods | G94: KPV/D/430 | H94: 46212 | I94: SF | J94: PP/PE Fabric | K94: PP Lam Fabric | L94: PP LAMINETED FABRIC | M94: PP Lam Fabric With UV | N94: 241 | O94: 38114.15 | P94: PP Lam Fabric BLUE | Q94: 0 | R94: 9 | S94: 3430.27 | T94: 9 | U94: 3430.27 | V94: 0 | W94: 0 | X94: 0 | Y94: 6860.54 | Z94: 0 | AA94: 24AABCG1282C2Z6 | AB94: KGS | AC94: 39269080 | AD94: Rs. | AE94: 1 | AF94: 241 | AG94: India | AH94: PP Lam Fabric
B95: 46212 | C95: Hcp Plastene Bulkpack Ltd Vadodara-Sales | D95: Sales | E95: 430 | F95: Sales - Within State Manufactured Goods | G95: KPV/D/430 | H95: 46212 | I95: SF | J95: PP/PE Fabric | K95: PP Lam Fabric | L95: PP LAMINETED FABRIC | M95: PP Lam Fabric With UV | N95: 164 | O95: 25772.6 | P95: FIBC Fabric Coated (Less Then 90+20 GSM)_x000D_ | Q95: 0 | R95: 9 | S95: 2319.53 | T95: 9 | U95: 2319.53 | V95: 0 | W95: 0 | X95: 0 | Y95: 4639.06 | Z95: 0 | AA95: 24AABCG1282C2Z6 | AB95: KGS | AC95: 39269080 | AD95: Rs. | AE95: 1 | AF95: 164 | AG95: India | AH95: PP Lam Fabric
B96: 46212 | C96: Hcp Plastene Bulkpack Ltd Vadodara-Sales | D96: Sales | E96: 430 | F96: Sales - Within State Manufactured Goods | G96: KPV/D/430 | H96: 46212 | I96: SF | J96: Webbing | K96: PP Webbing | L96: PP WEBBING | M96: Webbing | N96: 492 | O96: 77809.8 | P96: Webbing GREEN | Q96: 0 | R96: 9 | S96: 7002.88 | T96: 9 | U96: 7002.88 | V96: 0 | W96: 0 | X96: 0 | Y96: 14005.76 | Z96: 0 | AA96: 24AABCG1282C2Z6 | AB96: KGS | AC96: 39269080 | AD96: Rs. | AE96: 1 | AF96: 492 | AG96: India | AH96: PP Webbing
B97: 46212 | C97: Hcp Plastene Bulkpack Ltd Vadodara-Sales | D97: Sales | E97: 430 | F97: Sales - Within State Manufactured Goods | G97: KPV/D/430 | H97: 46212 | I97: SF | J97: Webbing | K97: PP Webbing | L97: PP WEBBING | M97: Webbing | N97: 240 | O97: 37236 | P97: Webbing MW TIE | Q97: 0 | R97: 9 | S97: 3351.24 | T97: 9 | U97: 3351.24 | V97: 0 | W97: 0 | X97: 0 | Y97: 6702.48 | Z97: 0 | AA97: 24AABCG1282C2Z6 | AB97: KGS | AC97: 39269080 | AD97: Rs. | AE97: 1 | AF97: 240 | AG97: India | AH97: PP Webbing
... B108: 46212 | C108: Plastene India ltd - Unit 2-Sales | D108: Sales | E108: 424 | F108: Sales - Within State - Traded Goods | G108: KPV/D/424 | H108: 46212 | I108: Stores/Spares | J108: MS Structure Items | K108: Capital Work in Progress | L108: MS PIPE | M108: MS Pipe | N108: 66 | O108: 3168 | P108: . | Q108: 3735.07 | R108: 9 | S108: 285.12 | T108: 9 | U108: 285.12 | V108: 0 | W108: 0 | X108: 0 | Y108: 570.24 | Z108: 0 | AA108: 24AAACO3087C1ZT | AB108: KGS | AC108: 73063090 | AD108: Rs. | AE108: 1 | AF108: 66 | AG108: India | AH108: N.A
B109: 46212 | C109: Plastene India ltd - Unit 2-Sales | D109: Job Invoice | E109: KPV/D/422 | F109: Job Work Income | G109: KPV/D/422 | H109: 46212 | I109: FG | J109: FIBC Bags | K109: FIBC Bags | L109: PP WOVEN BIG BAGS / SACKS | M109: FIBC Bags With UV Without Liner | N109: 1924.4 | O109: 419711.64 | P109: 6125/JS-14502C (PP WOVEN BIG BAGS) | Q109: 876466.74 | R109: 9 | S109: 37774.05 | T109: 9 | U109: 37774.05 | V109: 0 | W109: 0 | X109: 0 | Y109: 75548.1 | Z109: 0 | AA109: 24AAACO3087C1ZT | AB109: KGS | AC109: 998852 | AD109: Rs. | AE109: 1 | AF109: 1924.4 | AG109: India | AH109: FIBC Bags
B110: 46212 | C110: Plastene India ltd - Unit 2-Sales | D110: Job Invoice | E110: KPV/D/422 | F110: Job Work Income | G110: KPV/D/422 | H110: 46212 | I110: FG | J110: FIBC Bags | K110: FIBC Bags | L110: PP WOVEN BIG BAGS / SACKS | M110: FIBC Bags With UV Without Liner | N110: 676.6 | O110: 150232.26 | P110: 6126/JS-14504 (PP WOVEN BIG BAGS) | Q110: 0 | R110: 9 | S110: 13520.9 | T110: 9 | U110: 13520.9 | V110: 0 | W110: 0 | X110: 0 | Y110: 27041.8 | Z110: 0 | AA110: 24AAACO3087C1ZT | AB110: KGS | AC110: 998852 | AD110: Rs. | AE110: 1 | AF110: 676.6 | AG110: India | AH110: FIBC Bags
B111: 46212 | C111: Plastene India ltd - Unit 2-Sales | D111: Job Invoice | E111: KPV/D/422 | F111: Job Work Income | G111: KPV/D/422 | H111: 46212 | I111: FG | J111: FIBC Bags | K111: FIBC Bags | L111: PP WOVEN BIG BAGS / SACKS | M111: FIBC Bags With UV Without Liner | N111: 781.9 | O111: 185630.88 | P111: 6138/JS-15030 (PP WOVEN BIG BAGS) | Q111: 0 | R111: 9 | S111: 16706.78 | T111: 9 | U111: 16706.78 | V111: 0 | W111: 0 | X111: 0 | Y111: 33413.56 | Z111: 0 | AA111: 24AAACO3087C1ZT | AB111: KGS | AC111: 998852 | AD111: Rs. | AE111: 1 | AF111: 781.9 | AG111: India | AH111: FIBC Bags
B112: 46212 | C112: Plastene Polyfilms Ltd-Sales | D112: Sales | E112: 429 | F112: Sales - Within State Manufactured Goods | G112: KPV/D/429 | H112: 46212 | I112: SF | J112: Yarn All | K112: PP Yarn | L112: PP FABRILLATED YARN | M112: PP Fibrillated Tape Twisted 3200 MW | N112: 980 | O112: 148127 | P112: MW | Q112: 313854.53 | R112: 2.5 | S112: 3703.18 | T112: 2.5 | U112: 3703.18 | V112: 0 | W112: 0 | X112: 0 | Y112: 7406.36 | Z112: 0 | AA112: 24AAFCP2956A1ZR | AB112: KGS | AC112: 54026930 | AD112: Rs. | AE112: 1 | AF112: 980 | AG112: India | AH112: PP Yarn
B113: 46212 | C113: Plastene Polyfilms Ltd-Sales | D113: Sales | E113: 429 | F113: Sales - Within State Manufactured Goods | G113: KPV/D/429 | H113: 46212 | I113: SF | J113: Yarn All | K113: PP Yarn | L113: PP FABRILLATED YARN | M113: PP Fibrillated Tape Twisted 3200 Blue | N113: 980 | O113: 151067 | P113: BLUE | Q113: 0 | R113: 2.5 | S113: 3776.68 | T113: 2.5 | U113: 3776.68 | V113: 0 | W113: 0 | X113: 0 | Y113: 7553.36 | Z113: 0 | AA113: 24AAFCP2956A1ZR | AB113: KGS | AC113: 54026930 | AD113: Rs. | AE113: 1 | AF113: 980 | AG113: India | AH113: PP Yarn
B114: 46212 | C114: Southern Packaging Lp | D114: Export Sales | E114: KPW/E/94/26-27 | F114: Sales - Direct Export - Mfg - U/R | G114: KPW/E/94/26-27 | H114: 46212 | I114: FG | J114: FIBC Bags | K114: FIBC Bags | L114: PP WOVEN BIG BAGS / SACKS | M114: FIBC Bags With UV Without Liner | N114: 20435.3 | O114: 4578208.8 | P114: PP WOVEN BIG BAG | Q114: 4578208.8 | R114: 0 | S114: 0 | T114: 0 | U114: 0 | V114: 18 | W114: 824077.58 | X114: 0.17 | Y114: 824077.75 | Z114: 0 | AA114: N.A. | AB114: KGS | AC114: 63053200 | AD114: $ | AE114: 93.5 | AF114: 20435.3 | AG114: USA | AH114: FIBC Bags
B115: 46213 | C115: Ameriglobe LLC | D115: Export Sales | E115: KPW/E/95/26-27 | F115: Sales - Direct Export - Mfg - U/R | G115: KPW/E/95/26-27 | H115: 46213 | I115: FG | J115: FIBC Bags | K115: FIBC Bags | L115: PP WOVEN BIG BAGS / SACKS | M115: FIBC Bags With UV With Liner | N115: 17564.8 | O115: 4812931.2 | P115: PP WOVEN BIG BAG | Q115: 4812931.2 | R115: 0 | S115: 0 | T115: 0 | U115: 0 | V115: 18 | W115: 866327.62 | X115: 0.17 | Y115: 866327.79 | Z115: 0 | AA115: N.A. | AB115: KGS | AC115: 63053200 | AD115: $ | AE115: 93.5 | AF115: 17564.8 | AG115: USA | AH115: FIBC Bags
B116: 46213 | C116: Hcp Plastene Bulkpack Ltd Vadodara-Sales | D116: Sales | E116: 434 | F116: Sales - Within State Manufactured Goods | G116: KPV/D/434 | H116: 46213 | I116: RM | J116: FIBC Accessories | K116: FIBC Accessories | L116: PP LAMINETED FABRIC | M116: Non Woven Fabric (Felt) | N116: 203.5 | O116: 26862 | P116: . | Q116: 28178.24 | R116: 2.5 | S116: 671.55 | T116: 2.5 | U116: 671.55 | V116: 0 | W116: 0 | X116: 0 | Y116: 1343.1 | Z116: 0 | AA116: 24AABCG1282C2Z6 | AB116: KGS | AC116: 58079010 | AD116: Rs. | AE116: 1 | AF116: 203.5 | AG116: India | AH116: FIBC Accessories
B117: 46213 | C117: Oswal Extrusion Ltd- KASEZ-Sales | D117: SALES (FOREX) | E117: KPW/E/97/26-27 | F117: Sales - Kasez - Trading - U/B | G117: KPW/E/97/26-27 | H117: 46213 | I117: Consumables | J117: Consumables | K117: Consumables | L117: Consumables | M117: Hotmelt ( Glue ) | N117: 90 | O117: 28800 | P117: Hotmelt ( Glue ) | Q117: 28800 | R117: 0 | S117: 0 | T117: 0 | U117: 0 | V117: 0 | W117: 0 | X117: 0 | Y117: 0 | Z117: 0 | AA117: 24AAACO7290H4ZB | AB117: KGS | AC117: 350610 | AD117: Rs. | AE117: 1 | AF117: 90 | AG117: India | AH117: N.A
B118: 46213 | C118: Plastene India ltd - Unit 1-Sales | D118: Sales | E118: 435 | F118: Sales - Waste & Scrape | G118: KPV/D/435 | H118: 46213 | I118: SF | J118: Wastage/Scrap | K118: Wastage/Scrap | L118: Waste | M118: PP/HD Wastage/Scrap | N118: 7410 | O118: 629850 | P118: PP/HD Wastage/Scrap | Q118: 758087.46 | R118: 9 | S118: 56686.5 | T118: 9 | U118: 56686.5 | V118: 0 | W118: 0 | X118: 0 | Y118: 113373 | Z118: 14864.46 | AA118: 24AAACO3087C1ZT | AB118: KGS | AC118: 39159029 | AD118: Rs. | AE118: 1 | AF118: 7410 | AG118: India | AH118: Wastage/Scrap
B119: 46213 | C119: Plastene India ltd - Unit 1-Sales | D119: Sales | E119: 436 | F119: Sales - Within State Manufactured Goods | G119: KPV/D/436 | H119: 46213 | I119: FG | J119: FIBC Bags | K119: FIBC Bags | L119: PP WOVEN BIG BAGS / SACKS | M119: FIBC Bags With UV Without Liner | N119: 229 | O119: 70335.06 | P119: 1500020866/01 | Q119: 2055166.3 | R119: 9 | S119: 6330.16 | T119: 9 | U119: 6330.16 | V119: 0 | W119: 0 | X119: 0 | Y119: 12660.32 | Z119: 0 | AA119: 24AAACO3087C1ZT | AB119: KGS | AC119: 63053200 | AD119: Rs. | AE119: 1 | AF119: 229 | AG119: India | AH119: FIBC Bags
B120: 46213 | C120: Plastene India ltd - Unit 1-Sales | D120: Sales | E120: 436 | F120: Sales - Within State Manufactured Goods | G120: KPV/D/436 | H120: 46213 | I120: FG | J120: FIBC Bags | K120: FIBC Bags | L120: PP WOVEN BIG BAGS / SACKS | M120: FIBC Bags With UV Without Liner | N120: 1234.2 | O120: 325544.93 | P120: 26.19389/MERCER-16 | Q120: 0 | R120: 9 | S120: 29299.04 | T120: 9 | U120: 29299.04 | V120: 0 | W120: 0 | X120: 0 | Y120: 58598.08 | Z120: 0 | AA120: 24AAACO3087C1ZT | AB120: KGS | AC120: 63053200 | AD120: Rs. | AE120: 1 | AF120: 1234.2 | AG120: India | AH120: FIBC Bags
B121: 46213 | C121: Plastene India ltd - Unit 1-Sales | D121: Sales | E121: 436 | F121: Sales - Within State Manufactured Goods | G121: KPV/D/436 | H121: 46213 | I121: FG | J121: FIBC Bags | K121: FIBC Bags | L121: PP WOVEN BIG BAGS / SACKS | M121: FIBC Bags With UV Without Liner | N121: 1236 | O121: 325537.68 | P121: 26.19390/MERCER-15 | Q121: 0 | R121: 9 | S121: 29298.39 | T121: 9 | U121: 29298.39 | V121: 0 | W121: 0 | X121: 0 | Y121: 58596.78 | Z121: 0 | AA121: 24AAACO3087C1ZT | AB121: KGS | AC121: 63053200 | AD121: Rs. | AE121: 1 | AF121: 1236 | AG121: India | AH121: FIBC Bags
B122: 46213 | C122: Plastene India ltd - Unit 1-Sales | D122: Sales | E122: 436 | F122: Sales - Within State Manufactured Goods | G122: KPV/D/436 | H122: 46213 | I122: FG | J122: FIBC Bags | K122: FIBC Bags | L122: PP WOVEN BIG BAGS / SACKS | M122: FIBC Bags With UV Without Liner | N122: 906.1 | O122: 240841.38 | P122: 26/80334/26167/15.4716-18 | Q122: 0 | R122: 9 | S122: 21675.72 | T122: 9 | U122: 21675.72 | V122: 0 | W122: 0 | X122: 0 | Y122: 43351.44 | Z122: 0 | AA122: 24AAACO3087C1ZT | AB122: KGS | AC122: 63053200 | AD122: Rs. | AE122: 1 | AF122: 906.1 | AG122: India | AH122: FIBC Bags
...

Sheet Job In
N2: =SUBTOTAL(9,N4:N79) -> 73596.33 | BP2: =SUBTOTAL(9,BP4:BP79) -> 73596.33
A3: CompanyName | C3: Date | D3: srno | E3: Itemcode | F3: Itemname | G3: Indentsubcode | H3: PoNO | I3: OrderQty | J3: Challanqty | K3: Unit | L3: Recdqty | M3: PendingQty | N3: Acceptedqty | O3: Vehicalno | P3: Partyname | Q3: Suppliername | R3: ChallanNo | S3: Challan Date | T3: category | U3: subcategory | V3: MRno | W3: Rate | X3: Amount | Y3: BillNo | Z3: Bill Date | AA3: ItemRemarks | AB3: Remarks | AC3: Note | AD3: Transportname | AE3: Lrnodate | AF3: Discamt | AG3: Discamt1 | AH3: ExciseAmount | AI3: EducessAmount | AJ3: HiEducessamount | AK3: InwardVatType | AL3: Vatamount | AM3: Addvatamount | AN3: Frieght | AO3: Pkgfwd | AP3: Otherchg | AQ3: Spdutyname | AR3: Spdutyamt | AS3: Additionalduty | AT3: Billamount | AU3: Deptt | AV3: GroupName | AW3: SubGroupName | AX3: Deptt Po Indent | AY3: LoginName | AZ3: servicetax | BA3: Basic Amount | BB3: GateInwardNo | BC3: GateInwardDate | BD3: VendorGST | BE3: MRN User | BF3: POUserName | BG3: CGSTPer | BH3: CGSTAmount | BI3: SGSTPer | BJ3: SGSTAmount | BK3: IGSTPer | BL3: IGSTAmount | BM3: RBIllmount | BN3: EWayNo | BO3: EWayDt | BP3: netwt | BQ3: GROUP
A4: K.P. WOVEN PRIVATE LIMITED | C4: 46204 | D4: KPV/26-27/SII01166 | E4: WIP00023 | F4: PP UL Fabric With UV | G4: No Subcode | H4: No PO | I4: 0 | J4: 569 | K4: Kgs | L4: 569 | M4: 0 | N4: 569 | O4: GJ16Z8614 | P4: Plastene India ltd - Unit 1-Purchase | Q4: Plastene India ltd - Unit 1-Purchase | R4: PIL1/SC/104 | S4: 46203 | T4: JOB IN | U4: SELF | V4: JBIN-SE 114 | W4: 31 | X4: 0 | Y4: PIL1/SC/104 | Z4: 46203 | AA4: CROSS CORNER FABRIC COLOR HQS 1 ROLL | AB4: PP Woven Fabrics, | AD4: PATEL TRANSPORT. | AE4: 3906 | AF4: 0 | AG4: 0 | AH4: 0 | AI4: 0 | AJ4: 0 | AK4: VAT | AL4: 0 | AM4: 0 | AN4: 0 | AO4: 0 | AP4: 0 | AR4: -249676.4 | AS4: 0 | AT4: 0 | AU4: SF | AV4: PP/PE Fabric | AW4: PP UL Fabric | AX4: SF | AY4: erp | AZ4: 0 | BA4: 0 | BB4: R-361 | BC4: 46204 | BD4: 24AAACO3087C1ZT | BE4: kpstore | BG4: 0 | BH4: 0 | BI4: 0 | BJ4: 0 | BK4: 0 | BL4: 0 | BM4: 0 | BN4: 602137742244 | BO4: 46203.656 | BP4: 569 | BQ4: PP UL Fabric
A5: K.P. WOVEN PRIVATE LIMITED | C5: 46204 | D5: KPV/26-27/SII01166 | E5: WIP00023 | F5: PP UL Fabric With UV | G5: No Subcode | H5: No PO | I5: 0 | J5: 638 | K5: Kgs | L5: 638 | M5: 0 | N5: 638 | O5: GJ16Z8614 | P5: Plastene India ltd - Unit 1-Purchase | Q5: Plastene India ltd - Unit 1-Purchase | R5: PIL1/SC/104 | S5: 46203 | T5: JOB IN | U5: SELF | V5: JBIN-SE 114 | W5: 25 | X5: 0 | Y5: PIL1/SC/104 | Z5: 46203 | AA5: CROSS CORNER FABRIC 1 ROLL | AB5: PP Woven Fabrics, | AD5: PATEL TRANSPORT. | AE5: 3906 | AF5: 0 | AG5: 0 | AH5: 0 | AI5: 0 | AJ5: 0 | AK5: VAT | AL5: 0 | AM5: 0 | AN5: 0 | AO5: 0 | AP5: 0 | AR5: -249676.4 | AS5: 0 | AT5: 0 | AU5: SF | AV5: PP/PE Fabric | AW5: PP UL Fabric | AX5: SF | AY5: erp | AZ5: 0 | BA5: 0 | BB5: R-361 | BC5: 46204 | BD5: 24AAACO3087C1ZT | BE5: kpstore | BG5: 0 | BH5: 0 | BI5: 0 | BJ5: 0 | BK5: 0 | BL5: 0 | BM5: 0 | BN5: 602137742244 | BO5: 46203.656 | BP5: 638 | BQ5: PP UL Fabric
A6: K.P. WOVEN PRIVATE LIMITED | C6: 46204 | D6: KPV/26-27/SII01166 | E6: WIP00023 | F6: PP UL Fabric With UV | G6: No Subcode | H6: No PO | I6: 0 | J6: 1367 | K6: Kgs | L6: 1367 | M6: 0 | N6: 1367 | O6: GJ16Z8614 | P6: Plastene India ltd - Unit 1-Purchase | Q6: Plastene India ltd - Unit 1-Purchase | R6: PIL1/SC/104 | S6: 46203 | T6: JOB IN | U6: SELF | V6: JBIN-SE 114 | W6: 28 | X6: 0 | Y6: PIL1/SC/104 | Z6: 46203 | AA6: CROSS CORNER FABRIC HQS 2 ROLL | AB6: PP Woven Fabrics, | AD6: PATEL TRANSPORT. | AE6: 3906 | AF6: 0 | AG6: 0 | AH6: 0 | AI6: 0 | AJ6: 0 | AK6: VAT | AL6: 0 | AM6: 0 | AN6: 0 | AO6: 0 | AP6: 0 | AR6: -249676.4 | AS6: 0 | AT6: 0 | AU6: SF | AV6: PP/PE Fabric | AW6: PP UL Fabric | AX6: SF | AY6: erp | AZ6: 0 | BA6: 0 | BB6: R-361 | BC6: 46204 | BD6: 24AAACO3087C1ZT | BE6: kpstore | BG6: 0 | BH6: 0 | BI6: 0 | BJ6: 0 | BK6: 0 | BL6: 0 | BM6: 0 | BN6: 602137742244 | BO6: 46203.656 | BP6: 1367 | BQ6: PP UL Fabric
A7: K.P. WOVEN PRIVATE LIMITED | C7: 46204 | D7: KPV/26-27/SII01166 | E7: WIP00023 | F7: PP UL Fabric With UV | G7: No Subcode | H7: No PO | I7: 0 | J7: 355 | K7: Kgs | L7: 355 | M7: 0 | N7: 355 | O7: GJ16Z8614 | P7: Plastene India ltd - Unit 1-Purchase | Q7: Plastene India ltd - Unit 1-Purchase | R7: PIL1/SC/104 | S7: 46203 | T7: JOB IN | U7: SELF | V7: JBIN-SE 114 | W7: 26 | X7: 0 | Y7: PIL1/SC/104 | Z7: 46203 | AA7: MORE THEN 90GSM HQS 1 ROLL | AB7: PP Woven Fabrics, | AD7: PATEL TRANSPORT. | AE7: 3906 | AF7: 0 | AG7: 0 | AH7: 0 | AI7: 0 | AJ7: 0 | AK7: VAT | AL7: 0 | AM7: 0 | AN7: 0 | AO7: 0 | AP7: 0 | AR7: -249676.4 | AS7: 0 | AT7: 0 | AU7: SF | AV7: PP/PE Fabric | AW7: PP UL Fabric | AX7: SF | AY7: erp | AZ7: 0 | BA7: 0 | BB7: R-361 | BC7: 46204 | BD7: 24AAACO3087C1ZT | BE7: kpstore | BG7: 0 | BH7: 0 | BI7: 0 | BJ7: 0 | BK7: 0 | BL7: 0 | BM7: 0 | BN7: 602137742244 | BO7: 46203.656 | BP7: 355 | BQ7: PP UL Fabric
A8: K.P. WOVEN PRIVATE LIMITED | C8: 46204 | D8: KPV/26-27/SII01166 | E8: WIP00023 | F8: PP UL Fabric With UV | G8: No Subcode | H8: No PO | I8: 0 | J8: 441 | K8: Kgs | L8: 441 | M8: 0 | N8: 441 | O8: GJ16Z8614 | P8: Plastene India ltd - Unit 1-Purchase | Q8: Plastene India ltd - Unit 1-Purchase | R8: PIL1/SC/104 | S8: 46203 | T8: JOB IN | U8: SELF | V8: JBIN-SE 114 | W8: 20 | X8: 0 | Y8: PIL1/SC/104 | Z8: 46203 | AA8: MORE THEN 90GSM MW 2 ROLL | AB8: PP Woven Fabrics, | AD8: PATEL TRANSPORT. | AE8: 3906 | AF8: 0 | AG8: 0 | AH8: 0 | AI8: 0 | AJ8: 0 | AK8: VAT | AL8: 0 | AM8: 0 | AN8: 0 | AO8: 0 | AP8: 0 | AR8: -249676.4 | AS8: 0 | AT8: 0 | AU8: SF | AV8: PP/PE Fabric | AW8: PP UL Fabric | AX8: SF | AY8: erp | AZ8: 0 | BA8: 0 | BB8: R-361 | BC8: 46204 | BD8: 24AAACO3087C1ZT | BE8: kpstore | BG8: 0 | BH8: 0 | BI8: 0 | BJ8: 0 | BK8: 0 | BL8: 0 | BM8: 0 | BN8: 602137742244 | BO8: 46203.656 | BP8: 441 | BQ8: PP UL Fabric
A9: K.P. WOVEN PRIVATE LIMITED | C9: 46204 | D9: KPV/26-27/SII01166 | E9: WIP00023 | F9: PP UL Fabric With UV | G9: No Subcode | H9: No PO | I9: 0 | J9: 1241 | K9: Kgs | L9: 1241 | M9: 0 | N9: 1241 | O9: GJ16Z8614 | P9: Plastene India ltd - Unit 1-Purchase | Q9: Plastene India ltd - Unit 1-Purchase | R9: PIL1/SC/104 | S9: 46203 | T9: JOB IN | U9: SELF | V9: JBIN-SE 114 | W9: 23 | X9: 0 | Y9: PIL1/SC/104 | Z9: 46203 | AA9: MORE THEN 90GSM MW HQS 4 ROLL | AB9: PP Woven Fabrics, | AD9: PATEL TRANSPORT. | AE9: 3906 | AF9: 0 | AG9: 0 | AH9: 0 | AI9: 0 | AJ9: 0 | AK9: VAT | AL9: 0 | AM9: 0 | AN9: 0 | AO9: 0 | AP9: 0 | AR9: -249676.4 | AS9: 0 | AT9: 0 | AU9: SF | AV9: PP/PE Fabric | AW9: PP UL Fabric | AX9: SF | AY9: erp | AZ9: 0 | BA9: 0 | BB9: R-361 | BC9: 46204 | BD9: 24AAACO3087C1ZT | BE9: kpstore | BG9: 0 | BH9: 0 | BI9: 0 | BJ9: 0 | BK9: 0 | BL9: 0 | BM9: 0 | BN9: 602137742244 | BO9: 46203.656 | BP9: 1241 | BQ9: PP UL Fabric
A10: K.P. WOVEN PRIVATE LIMITED | C10: 46204 | D10: KPV/26-27/SII01166 | E10: WIP00023 | F10: PP UL Fabric With UV | G10: No Subcode | H10: No PO | I10: 0 | J10: 900 | K10: Kgs | L10: 900 | M10: 0 | N10: 900 | O10: GJ16Z8614 | P10: Plastene India ltd - Unit 1-Purchase | Q10: Plastene India ltd - Unit 1-Purchase | R10: PIL1/SC/104 | S10: 46203 | T10: JOB IN | U10: SELF | V10: JBIN-SE 114 | W10: 47 | X10: 0 | Y10: PIL1/SC/104 | Z10: 46203 | AA10: MORE THEN 90GSM MW HQS CONDUCTIVE 3 ROLL | AB10: PP Woven Fabrics, | AD10: PATEL TRANSPORT. | AE10: 3906 | AF10: 0 | AG10: 0 | AH10: 0 | AI10: 0 | AJ10: 0 | AK10: VAT | AL10: 0 | AM10: 0 | AN10: 0 | AO10: 0 | AP10: 0 | AR10: -249676.4 | AS10: 0 | AT10: 0 | AU10: SF | AV10: PP/PE Fabric | AW10: PP UL Fabric | AX10: SF | AY10: erp | AZ10: 0 | BA10: 0 | BB10: R-361 | BC10: 46204 | BD10: 24AAACO3087C1ZT | BE10: kpstore | BG10: 0 | BH10: 0 | BI10: 0 | BJ10: 0 | BK10: 0 | BL10: 0 | BM10: 0 | BN10: 602137742244 | BO10: 46203.656 | BP10: 900 | BQ10: PP UL Fabric
A11: K.P. WOVEN PRIVATE LIMITED | C11: 46204 | D11: KPV/26-27/SII01166 | E11: WIP00025 | F11: PP Lam Fabric With UV | G11: No Subcode | H11: No PO | I11: 0 | J11: 780 | K11: Kgs | L11: 780 | M11: 0 | N11: 780 | O11: GJ16Z8614 | P11: Plastene India ltd - Unit 1-Purchase | Q11: Plastene India ltd - Unit 1-Purchase | R11: PIL1/SC/104 | S11: 46203 | T11: JOB IN | U11: SELF | V11: JBIN-SE 114 | W11: 24 | X11: 0 | Y11: PIL1/SC/104 | Z11: 46203 | AA11: LESS THEN 90GSM MW 1 ROLL | AB11: PP Woven Fabrics, | AD11: PATEL TRANSPORT. | AE11: 3906 | AF11: 0 | AG11: 0 | AH11: 0 | AI11: 0 | AJ11: 0 | AK11: VAT | AL11: 0 | AM11: 0 | AN11: 0 | AO11: 0 | AP11: 0 | AR11: -249676.4 | AS11: 0 | AT11: 0 | AU11: SF | AV11: PP/PE Fabric | AW11: PP Lam Fabric | AX11: SF | AY11: erp | AZ11: 0 | BA11: 0 | BB11: R-361 | BC11: 46204 | BD11: 24AAACO3087C1ZT | BE11: kpstore | BG11: 0 | BH11: 0 | BI11: 0 | BJ11: 0 | BK11: 0 | BL11: 0 | BM11: 0 | BN11: 602137742244 | BO11: 46203.656 | BP11: 780 | BQ11: PP Lam Fabric
A12: K.P. WOVEN PRIVATE LIMITED | C12: 46204 | D12: KPV/26-27/SII01166 | E12: WIP00151 | F12: PP MF Yarn Twisted 1000 UV NW | G12: No Subcode | H12: No PO | I12: 0 | J12: 2193.7 | K12: KGS | L12: 2193.7 | M12: 0 | N12: 2193.7 | O12: GJ16Z8614 | P12: Plastene India ltd - Unit 1-Purchase | Q12: Plastene India ltd - Unit 1-Purchase | R12: PIL1/SC/104 | S12: 46203 | T12: JOB IN | U12: SELF | V12: JBIN-SE 114 | W12: 32 | X12: 0 | Y12: PIL1/SC/104 | Z12: 46203 | AA12: 54 BUN. | AB12: PP Woven Fabrics, | AD12: PATEL TRANSPORT. | AE12: 3906 | AF12: 0 | AG12: 0 | AH12: 0 | AI12: 0 | AJ12: 0 | AK12: VAT | AL12: 0 | AM12: 0 | AN12: 0 | AO12: 0 | AP12: 0 | AR12: -249676.4 | AS12: 0 | AT12: 0 | AU12: SF | AV12: Yarn All | AW12: PP Yarn | AX12: SF | AZ12: 0 | BA12: 0 | BB12: R-361 | BC12: 46204 | BD12: 24AAACO3087C1ZT | BE12: kpstore | BG12: 0 | BH12: 0 | BI12: 0 | BJ12: 0 | BK12: 0 | BL12: 0 | BM12: 0 | BN12: 602137742244 | BO12: 46203.656 | BP12: 2193.7 | BQ12: PP Yarn
A13: K.P. WOVEN PRIVATE LIMITED | C13: 46205 | D13: KPV/26-27/SII01187 | E13: WIP00023 | F13: PP UL Fabric With UV | G13: No Subcode | H13: No PO | I13: 0 | J13: 1244 | K13: Kgs | L13: 1244 | M13: 0 | N13: 1244 | O13: GJ06BT5602 | P13: Plastene India ltd - Unit 1-Purchase | Q13: Plastene India ltd - Unit 1-Purchase | R13: PIL1/SC/106 | S13: 46204 | T13: JOB IN | U13: SELF | V13: JBIN-SE 115 | W13: 31 | X13: 0 | Y13: PIL1/SC/106 | Z13: 46204 | AA13: 2ROLL, CHROSS CORNNER | AB13: PP Woven Fabrics, | AD13: 0 | AE13: 0 | AF13: 0 | AG13: 0 | AH13: 0 | AI13: 0 | AJ13: 0 | AK13: VAT | AL13: 0 | AM13: 0 | AN13: 0 | AO13: 0 | AP13: 0 | AR13: -202802 | AS13: 0 | AT13: 0 | AU13: SF | AV13: PP/PE Fabric | AW13: PP UL Fabric | AX13: SF | AY13: erp | AZ13: 0 | BA13: 0 | BB13: R 366 | BC13: 46205 | BD13: 24AAACO3087C1ZT | BE13: kpstore | BG13: 0 | BH13: 0 | BI13: 0 | BJ13: 0 | BK13: 0 | BL13: 0 | BM13: 0 | BN13: 612138354377 | BO13: 46204.642 | BP13: 1244 | BQ13: PP UL Fabric
A14: K.P. WOVEN PRIVATE LIMITED | C14: 46205 | D14: KPV/26-27/SII01187 | E14: WIP00023 | F14: PP UL Fabric With UV | G14: No Subcode | H14: No PO | I14: 0 | J14: 2509 | K14: Kgs | L14: 2509 | M14: 0 | N14: 2509 | O14: GJ06BT5602 | P14: Plastene India ltd - Unit 1-Purchase | Q14: Plastene India ltd - Unit 1-Purchase | R14: PIL1/SC/106 | S14: 46204 | T14: JOB IN | U14: SELF | V14: JBIN-SE 115 | W14: 28 | X14: 0 | Y14: PIL1/SC/106 | Z14: 46204 | AA14: 4ROLL CROSS CORNNER | AB14: PP Woven Fabrics, | AD14: 0 | AE14: 0 | AF14: 0 | AG14: 0 | AH14: 0 | AI14: 0 | AJ14: 0 | AK14: VAT | AL14: 0 | AM14: 0 | AN14: 0 | AO14: 0 | AP14: 0 | AR14: -202802 | AS14: 0 | AT14: 0 | AU14: SF | AV14: PP/PE Fabric | AW14: PP UL Fabric | AX14: SF | AY14: erp | AZ14: 0 | BA14: 0 | BB14: R 366 | BC14: 46205 | BD14: 24AAACO3087C1ZT | BE14: kpstore | BG14: 0 | BH14: 0 | BI14: 0 | BJ14: 0 | BK14: 0 | BL14: 0 | BM14: 0 | BN14: 612138354377 | BO14: 46204.642 | BP14: 2509 | BQ14: PP UL Fabric
A15: K.P. WOVEN PRIVATE LIMITED | C15: 46205 | D15: KPV/26-27/SII01187 | E15: WIP00023 | F15: PP UL Fabric With UV | G15: No Subcode | H15: No PO | I15: 0 | J15: 479 | K15: Kgs | L15: 479 | M15: 0 | N15: 479 | O15: GJ06BT5602 | P15: Plastene India ltd - Unit 1-Purchase | Q15: Plastene India ltd - Unit 1-Purchase | R15: PIL1/SC/106 | S15: 46204 | T15: JOB IN | U15: SELF | V15: JBIN-SE 115 | W15: 26 | X15: 0 | Y15: PIL1/SC/106 | Z15: 46204 | AA15: 2ROLL MORE THEN 90 GSM COLOR HCQ | AB15: PP Woven Fabrics, | AD15: 0 | AE15: 0 | AF15: 0 | AG15: 0 | AH15: 0 | AI15: 0 | AJ15: 0 | AK15: VAT | AL15: 0 | AM15: 0 | AN15: 0 | AO15: 0 | AP15: 0 | AR15: -202802 | AS15: 0 | AT15: 0 | AU15: SF | AV15: PP/PE Fabric | AW15: PP UL Fabric | AX15: SF | AY15: erp | AZ15: 0 | BA15: 0 | BB15: R 366 | BC15: 46205 | BD15: 24AAACO3087C1ZT | BE15: kpstore | BG15: 0 | BH15: 0 | BI15: 0 | BJ15: 0 | BK15: 0 | BL15: 0 | BM15: 0 | BN15: 612138354377 | BO15: 46204.642 | BP15: 479 | BQ15: PP UL Fabric
A16: K.P. WOVEN PRIVATE LIMITED | C16: 46205 | D16: KPV/26-27/SII01187 | E16: WIP00023 | F16: PP UL Fabric With UV | G16: No Subcode | H16: No PO | I16: 0 | J16: 1450 | K16: Kgs | L16: 1450 | M16: 0 | N16: 1450 | O16: GJ06BT5602 | P16: Plastene India ltd - Unit 1-Purchase | Q16: Plastene India ltd - Unit 1-Purchase | R16: PIL1/SC/106 | S16: 46204 | T16: JOB IN | U16: SELF | V16: JBIN-SE 115 | W16: 20 | X16: 0 | Y16: PIL1/SC/106 | Z16: 46204 | AA16: 3ROLL MORE THEN 90GSM MW | AB16: PP Woven Fabrics, | AD16: 0 | AE16: 0 | AF16: 0 | AG16: 0 | AH16: 0 | AI16: 0 | AJ16: 0 | AK16: VAT | AL16: 0 | AM16: 0 | AN16: 0 | AO16: 0 | AP16: 0 | AR16: -202802 | AS16: 0 | AT16: 0 | AU16: SF | AV16: PP/PE Fabric | AW16: PP UL Fabric | AX16: SF | AY16: erp | AZ16: 0 | BA16: 0 | BB16: R 366 | BC16: 46205 | BD16: 24AAACO3087C1ZT | BE16: kpstore | BG16: 0 | BH16: 0 | BI16: 0 | BJ16: 0 | BK16: 0 | BL16: 0 | BM16: 0 | BN16: 612138354377 | BO16: 46204.642 | BP16: 1450 | BQ16: PP UL Fabric
A17: K.P. WOVEN PRIVATE LIMITED | C17: 46205 | D17: KPV/26-27/SII01187 | E17: WIP00023 | F17: PP UL Fabric With UV | G17: No Subcode | H17: No PO | I17: 0 | J17: 2284 | K17: Kgs | L17: 2284 | M17: 0 | N17: 2284 | O17: GJ06BT5602 | P17: Plastene India ltd - Unit 1-Purchase | Q17: Plastene India ltd - Unit 1-Purchase | R17: PIL1/SC/106 | S17: 46204 | T17: JOB IN | U17: SELF | V17: JBIN-SE 115 | W17: 23 | X17: 0 | Y17: PIL1/SC/106 | Z17: 46204 | AA17: 6ROLL MORE THEN 90 GSM HQS | AB17: PP Woven Fabrics, | AD17: 0 | AE17: 0 | AF17: 0 | AG17: 0 | AH17: 0 | AI17: 0 | AJ17: 0 | AK17: VAT | AL17: 0 | AM17: 0 | AN17: 0 | AO17: 0 | AP17: 0 | AR17: -202802 | AS17: 0 | AT17: 0 | AU17: SF | AV17: PP/PE Fabric | AW17: PP UL Fabric | AX17: SF | AY17: erp | AZ17: 0 | BA17: 0 | BB17: R 366 | BC17: 46205 | BD17: 24AAACO3087C1ZT | BE17: kpstore | BG17: 0 | BH17: 0 | BI17: 0 | BJ17: 0 | BK17: 0 | BL17: 0 | BM17: 0 | BN17: 612138354377 | BO17: 46204.642 | BP17: 2284 | BQ17: PP UL Fabric
A18: K.P. WOVEN PRIVATE LIMITED | C18: 46206 | D18: KPV/26-27/SII01191 | E18: SMF00247 | F18: HD UL Monofilament Fabric (Kg) | G18: No Subcode | H18: No PO | I18: 0 | J18: 1832.4 | K18: Kgs | L18: 1832.4 | M18: 0 | N18: 1832.4 | O18: GJ27TG8278 | P18: Kayel Syntex Limited | Q18: Kayel Syntex Limited | R18: 52 | S18: 46204 | T18: JOB IN | U18: SELF | V18: JBIN-SE 116 | W18: 28 | X18: 0 | Y18: 52 | Z18: 46204 | AA18: 6ROLL, 4686MTR, 845.3KGS, 850BLACK 110CM, | AB18: Monofilament Yarn, | AD18: 0 | AE18: 0 | AF18: 0 | AG18: 0 | AH18: 0 | AI18: 0 | AJ18: 0 | AK18: VAT | AL18: 0 | AM18: 0 | AN18: 0 | AO18: 0 | AP18: 0 | AR18: -51307.2 | AS18: 0 | AT18: 0 | AU18: SF | AV18: PP/PE Fabric | AW18: HD UL Fabric | AX18: SF | AY18: erp | AZ18: 0 | BA18: 0 | BB18: R 364 | BC18: 46204 | BD18: 24AAACK8589P1ZP | BE18: kpstore | BG18: 0 | BH18: 0 | BI18: 0 | BJ18: 0 | BK18: 0 | BL18: 0 | BM18: 0 | BN18: 692138038798 | BO18: 46204.462 | BP18: 1832.4 | BQ18: HD UL Fabric
A19: K.P. WOVEN PRIVATE LIMITED | C19: 46206 | D19: KPV/26-27/SII01193 | E19: WIP00023 | F19: PP UL Fabric With UV | G19: No Subcode | H19: No PO | I19: 0 | J19: 584 | K19: Kgs | L19: 584 | M19: 0 | N19: 584 | O19: GJ01KT9275 | P19: Plastene India ltd - Unit 1-Purchase | Q19: Plastene India ltd - Unit 1-Purchase | R19: PIL1/SC/109 | S19: 46205 | T19: JOB IN | U19: SELF | V19: JBIN-SE 117 | W19: 31 | X19: 0 | Y19: PIL1/SC/109 | Z19: 46205 | AA19: CROSS CORNER FABRIC COLOR HQS 1 ROLL | AB19: PP Woven Fabrics, | AD19: PATEL TRANSPORT | AE19: 3910 | AF19: 0 | AG19: 0 | AH19: 0 | AI19: 0 | AJ19: 0 | AK19: VAT | AL19: 0 | AM19: 0 | AN19: 0 | AO19: 0 | AP19: 0 | AR19: -168101 | AS19: 0 | AT19: 0 | AU19: SF | AV19: PP/PE Fabric | AW19: PP UL Fabric | AX19: SF | AY19: erp | AZ19: 0 | BA19: 0 | BB19: R-370 | BC19: 46206 | BD19: 24AAACO3087C1ZT | BE19: kpstore | BG19: 0 | BH19: 0 | BI19: 0 | BJ19: 0 | BK19: 0 | BL19: 0 | BM19: 0 | BN19: 662138875196 | BO19: 46206.603 | BP19: 584 | BQ19: PP UL Fabric
A20: K.P. WOVEN PRIVATE LIMITED | C20: 46206 | D20: KPV/26-27/SII01193 | E20: WIP00023 | F20: PP UL Fabric With UV | G20: No Subcode | H20: No PO | I20: 0 | J20: 3075 | K20: Kgs | L20: 3075 | M20: 0 | N20: 3075 | O20: GJ01KT9275 | P20: Plastene India ltd - Unit 1-Purchase | Q20: Plastene India ltd - Unit 1-Purchase | R20: PIL1/SC/109 | S20: 46205 | T20: JOB IN | U20: SELF | V20: JBIN-SE 117 | W20: 25 | X20: 0 | Y20: PIL1/SC/109 | Z20: 46205 | AA20: CROSS CORNER FABRIC MW 5 ROLL | AB20: PP Woven Fabrics, | AD20: PATEL TRANSPORT | AE20: 3910 | AF20: 0 | AG20: 0 | AH20: 0 | AI20: 0 | AJ20: 0 | AK20: VAT | AL20: 0 | AM20: 0 | AN20: 0 | AO20: 0 | AP20: 0 | AR20: -168101 | AS20: 0 | AT20: 0 | AU20: SF | AV20: PP/PE Fabric | AW20: PP UL Fabric | AX20: SF | AY20: erp | AZ20: 0 | BA20: 0 | BB20: R-370 | BC20: 46206 | BD20: 24AAACO3087C1ZT | BE20: kpstore | BG20: 0 | BH20: 0 | BI20: 0 | BJ20: 0 | BK20: 0 | BL20: 0 | BM20: 0 | BN20: 662138875196 | BO20: 46206.603 | BP20: 3075 | BQ20: PP UL Fabric
A21: K.P. WOVEN PRIVATE LIMITED | C21: 46206 | D21: KPV/26-27/SII01193 | E21: WIP00023 | F21: PP UL Fabric With UV | G21: No Subcode | H21: No PO | I21: 0 | J21: 502 | K21: Kgs | L21: 502 | M21: 0 | N21: 502 | O21: GJ01KT9275 | P21: Plastene India ltd - Unit 1-Purchase | Q21: Plastene India ltd - Unit 1-Purchase | R21: PIL1/SC/109 | S21: 46205 | T21: JOB IN | U21: SELF | V21: JBIN-SE 117 | W21: 28 | X21: 0 | Y21: PIL1/SC/109 | Z21: 46205 | AA21: CROSS CORNER FABRIC MW HQS 1 ROLL | AB21: PP Woven Fabrics, | AD21: PATEL TRANSPORT | AE21: 3910 | AF21: 0 | AG21: 0 | AH21: 0 | AI21: 0 | AJ21: 0 | AK21: VAT | AL21: 0 | AM21: 0 | AN21: 0 | AO21: 0 | AP21: 0 | AR21: -168101 | AS21: 0 | AT21: 0 | AU21: SF | AV21: PP/PE Fabric | AW21: PP UL Fabric | AX21: SF | AY21: erp | AZ21: 0 | BA21: 0 | BB21: R-370 | BC21: 46206 | BD21: 24AAACO3087C1ZT | BE21: kpstore | BG21: 0 | BH21: 0 | BI21: 0 | BJ21: 0 | BK21: 0 | BL21: 0 | BM21: 0 | BN21: 662138875196 | BO21: 46206.603 | BP21: 502 | BQ21: PP UL Fabric
A22: K.P. WOVEN PRIVATE LIMITED | C22: 46206 | D22: KPV/26-27/SII01193 | E22: WIP00023 | F22: PP UL Fabric With UV | G22: No Subcode | H22: No PO | I22: 0 | J22: 2422 | K22: Kgs | L22: 2422 | M22: 0 | N22: 2422 | O22: GJ01KT9275 | P22: Plastene India ltd - Unit 1-Purchase | Q22: Plastene India ltd - Unit 1-Purchase | R22: PIL1/SC/109 | S22: 46205 | T22: JOB IN | U22: SELF | V22: JBIN-SE 117 | W22: 20 | X22: 0 | Y22: PIL1/SC/109 | Z22: 46205 | AA22: MORE THEN 90GSM MW 5 ROLL | AB22: PP Woven Fabrics, | AD22: PATEL TRANSPORT | AE22: 3910 | AF22: 0 | AG22: 0 | AH22: 0 | AI22: 0 | AJ22: 0 | AK22: VAT | AL22: 0 | AM22: 0 | AN22: 0 | AO22: 0 | AP22: 0 | AR22: -168101 | AS22: 0 | AT22: 0 | AU22: SF | AV22: PP/PE Fabric | AW22: PP UL Fabric | AX22: SF | AY22: erp | AZ22: 0 | BA22: 0 | BB22: R-370 | BC22: 46206 | BD22: 24AAACO3087C1ZT | BE22: kpstore | BG22: 0 | BH22: 0 | BI22: 0 | BJ22: 0 | BK22: 0 | BL22: 0 | BM22: 0 | BN22: 662138875196 | BO22: 46206.603 | BP22: 2422 | BQ22: PP UL Fabric
A23: K.P. WOVEN PRIVATE LIMITED | C23: 46206 | D23: KPV/26-27/SII01193 | E23: WIP00023 | F23: PP UL Fabric With UV | G23: No Subcode | H23: No PO | I23: 0 | J23: 462 | K23: Kgs | L23: 462 | M23: 0 | N23: 462 | O23: GJ01KT9275 | P23: Plastene India ltd - Unit 1-Purchase | Q23: Plastene India ltd - Unit 1-Purchase | R23: PIL1/SC/109 | S23: 46205 | T23: JOB IN | U23: SELF | V23: JBIN-SE 117 | W23: 23 | X23: 0 | Y23: PIL1/SC/109 | Z23: 46205 | AA23: MORE THEN 90GSM MW HQS 1 ROLL | AB23: PP Woven Fabrics, | AD23: PATEL TRANSPORT | AE23: 3910 | AF23: 0 | AG23: 0 | AH23: 0 | AI23: 0 | AJ23: 0 | AK23: VAT | AL23: 0 | AM23: 0 | AN23: 0 | AO23: 0 | AP23: 0 | AR23: -168101 | AS23: 0 | AT23: 0 | AU23: SF | AV23: PP/PE Fabric | AW23: PP UL Fabric | AX23: SF | AY23: erp | AZ23: 0 | BA23: 0 | BB23: R-370 | BC23: 46206 | BD23: 24AAACO3087C1ZT | BE23: kpstore | BG23: 0 | BH23: 0 | BI23: 0 | BJ23: 0 | BK23: 0 | BL23: 0 | BM23: 0 | BN23: 662138875196 | BO23: 46206.603 | BP23: 462 | BQ23: PP UL Fabric
A24: K.P. WOVEN PRIVATE LIMITED | C24: 46207 | D24: KPV/26-27/SII01205 | E24: WIP00023 | F24: PP UL Fabric With UV | G24: No Subcode | H24: No PO | I24: 0 | J24: 1203.3 | K24: Kgs | L24: 1203.3 | M24: 0 | N24: 1203.3 | O24: GJ23AW7180 | P24: Indralok Fabrics Pvt Ltd - Purchase | Q24: Indralok Fabrics Pvt Ltd - Purchase | R24: 12 | S24: 46206 | T24: JOB IN | U24: SELF | V24: JBIN-SE 118 | W24: 43 | X24: 0 | Y24: 12 | Z24: 46206 | AA24: 11ROLL | AB24: PP Woven Fabrics,LENO FABICS, | AD24: 0 | AE24: 0 | AF24: 0 | AG24: 0 | AH24: 0 | AI24: 0 | AJ24: 0 | AK24: VAT | AL24: 0 | AM24: 0 | AN24: 0 | AO24: 0 | AP24: 0 | AR24: -51747.7 | AS24: 0 | AT24: 0 | AU24: SF | AV24: PP/PE Fabric | AW24: PP UL Fabric | AX24: SF | AY24: erp | AZ24: 0 | BA24: 0 | BB24: R-375 | BC24: 46206 | BD24: 24AAACI4240F1Z4 | BE24: kpstore | BG24: 0 | BH24: 0 | BI24: 0 | BJ24: 0 | BK24: 0 | BL24: 0 | BM24: 0 | BN24: 612139263957 | BO24: 46206.542 | BP24: 1203.3 | BQ24: PP UL Fabric
A25: K.P. WOVEN PRIVATE LIMITED | C25: 46207 | D25: KPV/26-27/SII01205 | E25: WIP00031 | F25: PP/HD Wastage/Scrap | G25: No Subcode | H25: No PO | I25: 0 | J25: 58 | K25: Kgs | L25: 58 | M25: 0 | N25: 58 | O25: GJ23AW7180 | P25: Indralok Fabrics Pvt Ltd - Purchase | Q25: Indralok Fabrics Pvt Ltd - Purchase | R25: 12 | S25: 46206 | T25: JOB IN | U25: SELF | V25: JBIN-SE 118 | W25: 0.1 | X25: 0 | Y25: 12 | Z25: 46206 | AA25: 4BORA | AB25: PP Woven Fabrics,LENO FABICS, | AD25: 0 | AE25: 0 | AF25: 0 | AG25: 0 | AH25: 0 | AI25: 0 | AJ25: 0 | AK25: VAT | AL25: 0 | AM25: 0 | AN25: 0 | AO25: 0 | AP25: 0 | AR25: -51747.7 | AS25: 0 | AT25: 0 | AU25: SF | AV25: Wastage/Scrap | AW25: Wastage/Scrap | AX25: SF | AY25: erp | AZ25: 0 | BA25: 0 | BB25: R-375 | BC25: 46206 | BD25: 24AAACI4240F1Z4 | BE25: kpstore | BG25: 0 | BH25: 0 | BI25: 0 | BJ25: 0 | BK25: 0 | BL25: 0 | BM25: 0 | BN25: 612139263957 | BO25: 46206.542 | BP25: 58 | BQ25: Wastage/Scrap
A26: K.P. WOVEN PRIVATE LIMITED | C26: 46207 | D26: KPV/26-27/SII01211 | E26: SMF00255 | F26: PP Texene Chromiq PY0003S | G26: 1 | H26: No PO | I26: 0 | J26: 89.24 | K26: Kgs | L26: 89.24 | M26: 0 | N26: 89.24 | O26: GJ27X2343 | P26: Plastene India ltd - Unit 1-Purchase | Q26: Plastene India ltd - Unit 1-Purchase | R26: PIL1/JW/39 | S26: 46207 | T26: JOB IN | U26: OTHER | V26: JBIN-OT 16 | W26: 26652.25 | X26: 0 | Y26: PIL1/JW/39 | Z26: 46207 | AA26: BEAM CHROHMIQ R TWSTD | AB26: . | AD26: self | AE26: 39 29-06-2026 | AF26: 0 | AG26: 0 | AH26: 0 | AI26: 0 | AJ26: 0 | AK26: VAT | AL26: 0 | AM26: 0 | AN26: 0 | AO26: 0 | AP26: 0 | AR26: -4572193.5 | AS26: 0 | AT26: 0 | AU26: SF | AV26: Yarn All | AW26: PP Yarn | AX26: SF | AY26: erp | AZ26: 0 | BA26: 0 | BB26: R-378 | BC26: 46207 | BD26: 24AAACO3087C1ZT | BE26: kpstore | BG26: 0 | BH26: 0 | BI26: 0 | BJ26: 0 | BK26: 0 | BL26: 0 | BM26: 0 | BN26: 662134688105 | BO26: 46207.728 | BP26: 89.24 | BQ26: N.A
A27: K.P. WOVEN PRIVATE LIMITED | C27: 46207 | D27: KPV/26-27/SII01211 | E27: SMF00267 | F27: PP Texene Chromiq PY0001SL | G27: 2 | H27: No PO | I27: 0 | J27: 82.31 | K27: Kgs | L27: 82.31 | M27: 0 | N27: 82.31 | O27: GJ27X2343 | P27: Plastene India ltd - Unit 1-Purchase | Q27: Plastene India ltd - Unit 1-Purchase | R27: PIL1/JW/39 | S27: 46207 | T27: JOB IN | U27: OTHER | V27: JBIN-OT 16 | W27: 26652.25 | X27: 0 | Y27: PIL1/JW/39 | Z27: 46207 | AA27: SINGLE CHROMIQ R END YARN | AB27: . | AD27: self | AE27: 39 29-06-2026 | AF27: 0 | AG27: 0 | AH27: 0 | AI27: 0 | AJ27: 0 | AK27: VAT | AL27: 0 | AM27: 0 | AN27: 0 | AO27: 0 | AP27: 0 | AR27: -4572193.5 | AS27: 0 | AT27: 0 | AU27: SF | AV27: Yarn All | AW27: PP Yarn | AX27: SF | AZ27: 0 | BA27: 0 | BB27: R-378 | BC27: 46207 | BD27: 24AAACO3087C1ZT | BE27: kpstore | BG27: 0 | BH27: 0 | BI27: 0 | BJ27: 0 | BK27: 0 | BL27: 0 | BM27: 0 | BN27: 662134688105 | BO27: 46207.728 | BP27: 82.31 | BQ27: N.A
A28: K.P. WOVEN PRIVATE LIMITED | C28: 46208 | D28: KPV/26-27/SII01215 | E28: WIP00151 | F28: PP MF Yarn Twisted 1000 UV NW | G28: No Subcode | H28: No PO | I28: 0 | J28: 1632.4 | K28: KGS | L28: 1632.4 | M28: 0 | N28: 1632.4 | O28: GJ16Z8614 | P28: Plastene India ltd - Unit 1-Purchase | Q28: Plastene India ltd - Unit 1-Purchase | R28: PIL1/SC/110 | S28: 46207 | T28: JOB IN | U28: SELF | V28: JBIN-SE 119 | W28: 32 | X28: 0 | Y28: PIL1/SC/110 | Z28: 46207 | AA28: 40BUN, | AB28: PP Woven Fabrics, | AD28: 0 | AE28: 0 | AF28: 0 | AG28: 0 | AH28: 0 | AI28: 0 | AJ28: 0 | AK28: VAT | AL28: 0 | AM28: 0 | AN28: 0 | AO28: 0 | AP28: 0 | AR28: -261401.8 | AS28: 0 | AT28: 0 | AU28: SF | AV28: Yarn All | AW28: PP Yarn | AX28: SF | AZ28: 0 | BA28: 0 | BB28: R-380 | BC28: 46208 | BD28: 24AAACO3087C1ZT | BE28: kpstore | BG28: 0 | BH28: 0 | BI28: 0 | BJ28: 0 | BK28: 0 | BL28: 0 | BM28: 0 | BN28: 622140021491 | BO28: 46207.53 | BP28: 1632.4 | BQ28: PP Yarn
A29: K.P. WOVEN PRIVATE LIMITED | C29: 46208 | D29: KPV/26-27/SII01215 | E29: WIP00023 | F29: PP UL Fabric With UV | G29: No Subcode | H29: No PO | I29: 0 | J29: 621 | K29: Kgs | L29: 621 | M29: 0 | N29: 621 | O29: GJ16Z8614 | P29: Plastene India ltd - Unit 1-Purchase | Q29: Plastene India ltd - Unit 1-Purchase | R29: PIL1/SC/110 | S29: 46207 | T29: JOB IN | U29: SELF | V29: JBIN-SE 119 | W29: 31 | X29: 0 | Y29: PIL1/SC/110 | Z29: 46207 | AA29: 1ROLLCROSS CORNNER COLOR HQS | AB29: PP Woven Fabrics, | AD29: 0 | AE29: 0 | AF29: 0 | AG29: 0 | AH29: 0 | AI29: 0 | AJ29: 0 | AK29: VAT | AL29: 0 | AM29: 0 | AN29: 0 | AO29: 0 | AP29: 0 | AR29: -261401.8 | AS29: 0 | AT29: 0 | AU29: SF | AV29: PP/PE Fabric | AW29: PP UL Fabric | AX29: SF | AY29: erp | AZ29: 0 | BA29: 0 | BB29: R-380 | BC29: 46208 | BD29: 24AAACO3087C1ZT | BE29: kpstore | BG29: 0 | BH29: 0 | BI29: 0 | BJ29: 0 | BK29: 0 | BL29: 0 | BM29: 0 | BN29: 622140021491 | BO29: 46207.53 | BP29: 621 | BQ29: PP UL Fabric
A30: K.P. WOVEN PRIVATE LIMITED | C30: 46208 | D30: KPV/26-27/SII01215 | E30: WIP00023 | F30: PP UL Fabric With UV | G30: No Subcode | H30: No PO | I30: 0 | J30: 1190 | K30: Kgs | L30: 1190 | M30: 0 | N30: 1190 | O30: GJ16Z8614 | P30: Plastene India ltd - Unit 1-Purchase | Q30: Plastene India ltd - Unit 1-Purchase | R30: PIL1/SC/110 | S30: 46207 | T30: JOB IN | U30: SELF | V30: JBIN-SE 119 | W30: 25 | X30: 0 | Y30: PIL1/SC/110 | Z30: 46207 | AA30: 2ROLL, CROSS CORNNR | AB30: PP Woven Fabrics, | AD30: 0 | AE30: 0 | AF30: 0 | AG30: 0 | AH30: 0 | AI30: 0 | AJ30: 0 | AK30: VAT | AL30: 0 | AM30: 0 | AN30: 0 | AO30: 0 | AP30: 0 | AR30: -261401.8 | AS30: 0 | AT30: 0 | AU30: SF | AV30: PP/PE Fabric | AW30: PP UL Fabric | AX30: SF | AY30: erp | AZ30: 0 | BA30: 0 | BB30: R-380 | BC30: 46208 | BD30: 24AAACO3087C1ZT | BE30: kpstore | BG30: 0 | BH30: 0 | BI30: 0 | BJ30: 0 | BK30: 0 | BL30: 0 | BM30: 0 | BN30: 622140021491 | BO30: 46207.53 | BP30: 1190 | BQ30: PP UL Fabric
A31: K.P. WOVEN PRIVATE LIMITED | C31: 46208 | D31: KPV/26-27/SII01215 | E31: WIP00023 | F31: PP UL Fabric With UV | G31: No Subcode | H31: No PO | I31: 0 | J31: 2371 | K31: Kgs | L31: 2371 | M31: 0 | N31: 2371 | O31: GJ16Z8614 | P31: Plastene India ltd - Unit 1-Purchase | Q31: Plastene India ltd - Unit 1-Purchase | R31: PIL1/SC/110 | S31: 46207 | T31: JOB IN | U31: SELF | V31: JBIN-SE 119 | W31: 28 | X31: 0 | Y31: PIL1/SC/110 | Z31: 46207 | AA31: 4ROLL CROSS CORNNER HQS | AB31: PP Woven Fabrics, | AD31: 0 | AE31: 0 | AF31: 0 | AG31: 0 | AH31: 0 | AI31: 0 | AJ31: 0 | AK31: VAT | AL31: 0 | AM31: 0 | AN31: 0 | AO31: 0 | AP31: 0 | AR31: -261401.8 | AS31: 0 | AT31: 0 | AU31: SF | AV31: PP/PE Fabric | AW31: PP UL Fabric | AX31: SF | AY31: erp | AZ31: 0 | BA31: 0 | BB31: R-380 | BC31: 46208 | BD31: 24AAACO3087C1ZT | BE31: kpstore | BG31: 0 | BH31: 0 | BI31: 0 | BJ31: 0 | BK31: 0 | BL31: 0 | BM31: 0 | BN31: 622140021491 | BO31: 46207.53 | BP31: 2371 | BQ31: PP UL Fabric
A32: K.P. WOVEN PRIVATE LIMITED | C32: 46208 | D32: KPV/26-27/SII01215 | E32: WIP00023 | F32: PP UL Fabric With UV | G32: No Subcode | H32: No PO | I32: 0 | J32: 355 | K32: Kgs | L32: 355 | M32: 0 | N32: 355 | O32: GJ16Z8614 | P32: Plastene India ltd - Unit 1-Purchase | Q32: Plastene India ltd - Unit 1-Purchase | R32: PIL1/SC/110 | S32: 46207 | T32: JOB IN | U32: SELF | V32: JBIN-SE 119 | W32: 26 | X32: 0 | Y32: PIL1/SC/110 | Z32: 46207 | AA32: 1ROLL, MORE THEN 90GSM COLOR HQS | AB32: PP Woven Fabrics, | AD32: 0 | AE32: 0 | AF32: 0 | AG32: 0 | AH32: 0 | AI32: 0 | AJ32: 0 | AK32: VAT | AL32: 0 | AM32: 0 | AN32: 0 | AO32: 0 | AP32: 0 | AR32: -261401.8 | AS32: 0 | AT32: 0 | AU32: SF | AV32: PP/PE Fabric | AW32: PP UL Fabric | AX32: SF | AY32: erp | AZ32: 0 | BA32: 0 | BB32: R-380 | BC32: 46208 | BD32: 24AAACO3087C1ZT | BE32: kpstore | BG32: 0 | BH32: 0 | BI32: 0 | BJ32: 0 | BK32: 0 | BL32: 0 | BM32: 0 | BN32: 622140021491 | BO32: 46207.53 | BP32: 355 | BQ32: PP UL Fabric
A33: K.P. WOVEN PRIVATE LIMITED | C33: 46208 | D33: KPV/26-27/SII01215 | E33: WIP00023 | F33: PP UL Fabric With UV | G33: No Subcode | H33: No PO | I33: 0 | J33: 1396 | K33: Kgs | L33: 1396 | M33: 0 | N33: 1396 | O33: GJ16Z8614 | P33: Plastene India ltd - Unit 1-Purchase | Q33: Plastene India ltd - Unit 1-Purchase | R33: PIL1/SC/110 | S33: 46207 | T33: JOB IN | U33: SELF | V33: JBIN-SE 119 | W33: 20 | X33: 0 | Y33: PIL1/SC/110 | Z33: 46207 | AA33: 3ROLL, MORE THEN 90GSM COLOR, HQS | AB33: PP Woven Fabrics, | AD33: 0 | AE33: 0 | AF33: 0 | AG33: 0 | AH33: 0 | AI33: 0 | AJ33: 0 | AK33: VAT | AL33: 0 | AM33: 0 | AN33: 0 | AO33: 0 | AP33: 0 | AR33: -261401.8 | AS33: 0 | AT33: 0 | AU33: SF | AV33: PP/PE Fabric | AW33: PP UL Fabric | AX33: SF | AY33: erp | AZ33: 0 | BA33: 0 | BB33: R-380 | BC33: 46208 | BD33: 24AAACO3087C1ZT | BE33: kpstore | BG33: 0 | BH33: 0 | BI33: 0 | BJ33: 0 | BK33: 0 | BL33: 0 | BM33: 0 | BN33: 622140021491 | BO33: 46207.53 | BP33: 1396 | BQ33: PP UL Fabric
A34: K.P. WOVEN PRIVATE LIMITED | C34: 46208 | D34: KPV/26-27/SII01215 | E34: WIP00023 | F34: PP UL Fabric With UV | G34: No Subcode | H34: No PO | I34: 0 | J34: 2462 | K34: Kgs | L34: 2462 | M34: 0 | N34: 2462 | O34: GJ16Z8614 | P34: Plastene India ltd - Unit 1-Purchase | Q34: Plastene India ltd - Unit 1-Purchase | R34: PIL1/SC/110 | S34: 46207 | T34: JOB IN | U34: SELF | V34: JBIN-SE 119 | W34: 23 | X34: 0 | Y34: PIL1/SC/110 | Z34: 46207 | AA34: 6ROLL MORE THEN 90GSM HQS | AB34: PP Woven Fabrics, | AD34: 0 | AE34: 0 | AF34: 0 | AG34: 0 | AH34: 0 | AI34: 0 | AJ34: 0 | AK34: VAT | AL34: 0 | AM34: 0 | AN34: 0 | AO34: 0 | AP34: 0 | AR34: -261401.8 | AS34: 0 | AT34: 0 | AU34: SF | AV34: PP/PE Fabric | AW34: PP UL Fabric | AX34: SF | AY34: erp | AZ34: 0 | BA34: 0 | BB34: R-380 | BC34: 46208 | BD34: 24AAACO3087C1ZT | BE34: kpstore | BG34: 0 | BH34: 0 | BI34: 0 | BJ34: 0 | BK34: 0 | BL34: 0 | BM34: 0 | BN34: 622140021491 | BO34: 46207.53 | BP34: 2462 | BQ34: PP UL Fabric
A35: K.P. WOVEN PRIVATE LIMITED | C35: 46209 | D35: KPV/26-27/SII01233 | E35: WIP00023 | F35: PP UL Fabric With UV | G35: No Subcode | H35: No PO | I35: 0 | J35: 641 | K35: Kgs | L35: 641 | M35: 0 | N35: 641 | O35: GJ16AY4240 | P35: Plastene India ltd - Unit 1-Purchase | Q35: Plastene India ltd - Unit 1-Purchase | R35: PIL1/SC/112 | S35: 46208 | T35: JOB IN | U35: SELF | V35: JBIN-SE 120 | W35: 31 | X35: 0 | Y35: PIL1/SC/112 | Z35: 46208 | AA35: CORNER FABRIC COLOR HQS 1 ROLL | AB35: PP Woven Fabrics, | AD35: PATEL TRANSPORT | AE35: 3915 | AF35: 0 | AG35: 0 | AH35: 0 | AI35: 0 | AJ35: 0 | AK35: VAT | AL35: 0 | AM35: 0 | AN35: 0 | AO35: 0 | AP35: 0 | AR35: -80636 | AS35: 0 | AT35: 0 | AU35: SF | AV35: PP/PE Fabric | AW35: PP UL Fabric | AX35: SF | AY35: erp | AZ35: 0 | BA35: 0 | BB35: R-385 | BC35: 46209 | BD35: 24AAACO3087C1ZT | BE35: kpstore | BG35: 0 | BH35: 0 | BI35: 0 | BJ35: 0 | BK35: 0 | BL35: 0 | BM35: 0 | BN35: 642140302587 | BO35: 46208.692 | BP35: 641 | BQ35: PP UL Fabric
A36: K.P. WOVEN PRIVATE LIMITED | C36: 46209 | D36: KPV/26-27/SII01233 | E36: WIP00023 | F36: PP UL Fabric With UV | G36: No Subcode | H36: No PO | I36: 0 | J36: 2085 | K36: Kgs | L36: 2085 | M36: 0 | N36: 2085 | O36: GJ16AY4240 | P36: Plastene India ltd - Unit 1-Purchase | Q36: Plastene India ltd - Unit 1-Purchase | R36: PIL1/SC/112 | S36: 46208 | T36: JOB IN | U36: SELF | V36: JBIN-SE 120 | W36: 25 | X36: 0 | Y36: PIL1/SC/112 | Z36: 46208 | AA36: CROSS CORNER FABRIC MW 3 ROLL | AB36: PP Woven Fabrics, | AD36: PATEL TRANSPORT | AE36: 3915 | AF36: 0 | AG36: 0 | AH36: 0 | AI36: 0 | AJ36: 0 | AK36: VAT | AL36: 0 | AM36: 0 | AN36: 0 | AO36: 0 | AP36: 0 | AR36: -80636 | AS36: 0 | AT36: 0 | AU36: SF | AV36: PP/PE Fabric | AW36: PP UL Fabric | AX36: SF | AY36: erp | AZ36: 0 | BA36: 0 | BB36: R-385 | BC36: 46209 | BD36: 24AAACO3087C1ZT | BE36: kpstore | BG36: 0 | BH36: 0 | BI36: 0 | BJ36: 0 | BK36: 0 | BL36: 0 | BM36: 0 | BN36: 642140302587 | BO36: 46208.692 | BP36: 2085 | BQ36: PP UL Fabric
A37: K.P. WOVEN PRIVATE LIMITED | C37: 46209 | D37: KPV/26-27/SII01233 | E37: WIP00023 | F37: PP UL Fabric With UV | G37: No Subcode | H37: No PO | I37: 0 | J37: 432 | K37: Kgs | L37: 432 | M37: 0 | N37: 432 | O37: GJ16AY4240 | P37: Plastene India ltd - Unit 1-Purchase | Q37: Plastene India ltd - Unit 1-Purchase | R37: PIL1/SC/112 | S37: 46208 | T37: JOB IN | U37: SELF | V37: JBIN-SE 120 | W37: 20 | X37: 0 | Y37: PIL1/SC/112 | Z37: 46208 | AA37: MORE THEN 90GSM MW 1 ROLL | AB37: PP Woven Fabrics, | AD37: PATEL TRANSPORT | AE37: 3915 | AF37: 0 | AG37: 0 | AH37: 0 | AI37: 0 | AJ37: 0 | AK37: VAT | AL37: 0 | AM37: 0 | AN37: 0 | AO37: 0 | AP37: 0 | AR37: -80636 | AS37: 0 | AT37: 0 | AU37: SF | AV37: PP/PE Fabric | AW37: PP UL Fabric | AX37: SF | AY37: erp | AZ37: 0 | BA37: 0 | BB37: R-385 | BC37: 46209 | BD37: 24AAACO3087C1ZT | BE37: kpstore | BG37: 0 | BH37: 0 | BI37: 0 | BJ37: 0 | BK37: 0 | BL37: 0 | BM37: 0 | BN37: 642140302587 | BO37: 46208.692 | BP37: 432 | BQ37: PP UL Fabric
A38: K.P. WOVEN PRIVATE LIMITED | C38: 46210 | D38: KPV/26-27/SII01237 | E38: WIP00023 | F38: PP UL Fabric With UV | G38: No Subcode | H38: No PO | I38: 0 | J38: 1148 | K38: Kgs | L38: 1148 | M38: 0 | N38: 1148 | O38: GJ02XX9133 | P38: Plastene India ltd - Unit 1-Purchase | Q38: Plastene India ltd - Unit 1-Purchase | R38: PIL1/SC/113 | S38: 46210 | T38: JOB IN | U38: SELF | V38: JBIN-SE 121 | W38: 31 | X38: 0 | Y38: PIL1/SC/113 | Z38: 46210 | AA38: 2 ROLL | AB38: PP Woven Fabrics, | AD38: . | AE38: . | AF38: 0 | AG38: 0 | AH38: 0 | AI38: 0 | AJ38: 0 | AK38: VAT | AL38: 0 | AM38: 0 | AN38: 0 | AO38: 0 | AP38: 0 | AR38: -154429 | AS38: 0 | AT38: 0 | AU38: SF | AV38: PP/PE Fabric | AW38: PP UL Fabric | AX38: SF | AY38: erp | AZ38: 0 | BA38: 0 | BB38: R-392 | BC38: 46210 | BD38: 24AAACO3087C1ZT | BE38: kpstore | BG38: 0 | BH38: 0 | BI38: 0 | BJ38: 0 | BK38: 0 | BL38: 0 | BM38: 0 | BN38: 652140822215 | BO38: 46209.628 | BP38: 1148 | BQ38: PP UL Fabric
A39: K.P. WOVEN PRIVATE LIMITED | C39: 46210 | D39: KPV/26-27/SII01237 | E39: WIP00023 | F39: PP UL Fabric With UV | G39: No Subcode | H39: No PO | I39: 0 | J39: 2627 | K39: Kgs | L39: 2627 | M39: 0 | N39: 2627 | O39: GJ02XX9133 | P39: Plastene India ltd - Unit 1-Purchase | Q39: Plastene India ltd - Unit 1-Purchase | R39: PIL1/SC/113 | S39: 46210 | T39: JOB IN | U39: SELF | V39: JBIN-SE 121 | W39: 25 | X39: 0 | Y39: PIL1/SC/113 | Z39: 46210 | AA39: 4 ROLL | AB39: PP Woven Fabrics, | AD39: . | AE39: . | AF39: 0 | AG39: 0 | AH39: 0 | AI39: 0 | AJ39: 0 | AK39: VAT | AL39: 0 | AM39: 0 | AN39: 0 | AO39: 0 | AP39: 0 | AR39: -154429 | AS39: 0 | AT39: 0 | AU39: SF | AV39: PP/PE Fabric | AW39: PP UL Fabric | AX39: SF | AY39: erp | AZ39: 0 | BA39: 0 | BB39: R-392 | BC39: 46210 | BD39: 24AAACO3087C1ZT | BE39: kpstore | BG39: 0 | BH39: 0 | BI39: 0 | BJ39: 0 | BK39: 0 | BL39: 0 | BM39: 0 | BN39: 652140822215 | BO39: 46209.628 | BP39: 2627 | BQ39: PP UL Fabric
A40: K.P. WOVEN PRIVATE LIMITED | C40: 46210 | D40: KPV/26-27/SII01237 | E40: WIP00023 | F40: PP UL Fabric With UV | G40: No Subcode | H40: No PO | I40: 0 | J40: 353 | K40: Kgs | L40: 353 | M40: 0 | N40: 353 | O40: GJ02XX9133 | P40: Plastene India ltd - Unit 1-Purchase | Q40: Plastene India ltd - Unit 1-Purchase | R40: PIL1/SC/113 | S40: 46210 | T40: JOB IN | U40: SELF | V40: JBIN-SE 121 | W40: 26 | X40: 0 | Y40: PIL1/SC/113 | Z40: 46210 | AA40: 1 ROLL | AB40: PP Woven Fabrics, | AD40: . | AE40: . | AF40: 0 | AG40: 0 | AH40: 0 | AI40: 0 | AJ40: 0 | AK40: VAT | AL40: 0 | AM40: 0 | AN40: 0 | AO40: 0 | AP40: 0 | AR40: -154429 | AS40: 0 | AT40: 0 | AU40: SF | AV40: PP/PE Fabric | AW40: PP UL Fabric | AX40: SF | AY40: erp | AZ40: 0 | BA40: 0 | BB40: R-392 | BC40: 46210 | BD40: 24AAACO3087C1ZT | BE40: kpstore | BG40: 0 | BH40: 0 | BI40: 0 | BJ40: 0 | BK40: 0 | BL40: 0 | BM40: 0 | BN40: 652140822215 | BO40: 46209.628 | BP40: 353 | BQ40: PP UL Fabric
A41: K.P. WOVEN PRIVATE LIMITED | C41: 46210 | D41: KPV/26-27/SII01237 | E41: WIP00023 | F41: PP UL Fabric With UV | G41: No Subcode | H41: No PO | I41: 0 | J41: 985 | K41: Kgs | L41: 985 | M41: 0 | N41: 985 | O41: GJ02XX9133 | P41: Plastene India ltd - Unit 1-Purchase | Q41: Plastene India ltd - Unit 1-Purchase | R41: PIL1/SC/113 | S41: 46210 | T41: JOB IN | U41: SELF | V41: JBIN-SE 121 | W41: 20 | X41: 0 | Y41: PIL1/SC/113 | Z41: 46210 | AA41: 2 ROLL | AB41: PP Woven Fabrics, | AD41: . | AE41: . | AF41: 0 | AG41: 0 | AH41: 0 | AI41: 0 | AJ41: 0 | AK41: VAT | AL41: 0 | AM41: 0 | AN41: 0 | AO41: 0 | AP41: 0 | AR41: -154429 | AS41: 0 | AT41: 0 | AU41: SF | AV41: PP/PE Fabric | AW41: PP UL Fabric | AX41: SF | AY41: erp | AZ41: 0 | BA41: 0 | BB41: R-392 | BC41: 46210 | BD41: 24AAACO3087C1ZT | BE41: kpstore | BG41: 0 | BH41: 0 | BI41: 0 | BJ41: 0 | BK41: 0 | BL41: 0 | BM41: 0 | BN41: 652140822215 | BO41: 46209.628 | BP41: 985 | BQ41: PP UL Fabric
A42: K.P. WOVEN PRIVATE LIMITED | C42: 46210 | D42: KPV/26-27/SII01237 | E42: WIP00023 | F42: PP UL Fabric With UV | G42: No Subcode | H42: No PO | I42: 0 | J42: 1056 | K42: Kgs | L42: 1056 | M42: 0 | N42: 1056 | O42: GJ02XX9133 | P42: Plastene India ltd - Unit 1-Purchase | Q42: Plastene India ltd - Unit 1-Purchase | R42: PIL1/SC/113 | S42: 46210 | T42: JOB IN | U42: SELF | V42: JBIN-SE 121 | W42: 23 | X42: 0 | Y42: PIL1/SC/113 | Z42: 46210 | AA42: 3 ROLL | AB42: PP Woven Fabrics, | AD42: . | AE42: . | AF42: 0 | AG42: 0 | AH42: 0 | AI42: 0 | AJ42: 0 | AK42: VAT | AL42: 0 | AM42: 0 | AN42: 0 | AO42: 0 | AP42: 0 | AR42: -154429 | AS42: 0 | AT42: 0 | AU42: SF | AV42: PP/PE Fabric | AW42: PP UL Fabric | AX42: SF | AY42: erp | AZ42: 0 | BA42: 0 | BB42: R-392 | BC42: 46210 | BD42: 24AAACO3087C1ZT | BE42: kpstore | BG42: 0 | BH42: 0 | BI42: 0 | BJ42: 0 | BK42: 0 | BL42: 0 | BM42: 0 | BN42: 652140822215 | BO42: 46209.628 | BP42: 1056 | BQ42: PP UL Fabric
A43: K.P. WOVEN PRIVATE LIMITED | C43: 46210 | D43: KPV/26-27/SII01260 | E43: RAW05130 | F43: PP Basell 462S | G43: No Subcode | H43: No PO | I43: 0 | J43: 1500 | K43: Kgs | L43: 1500 | M43: 0 | N43: 1500 | O43: GJ18BW4749 | P43: Plastene India ltd - Unit 2-Purchase | Q43: Plastene India ltd - Unit 2-Purchase | R43: PIL2/SC/52 | S43: 46210 | T43: JOB IN | U43: SELF | V43: JBIN-SE 122 | W43: 127 | X43: 0 | Y43: PIL2/SC/52 | Z43: 46210 | AA43: 60 BAGS | AB43: PP Woven Fabrics, | AD43: . | AE43: . | AF43: 0 | AG43: 0 | AH43: 0 | AI43: 0 | AJ43: 0 | AK43: VAT | AL43: 0 | AM43: 0 | AN43: 0 | AO43: 0 | AP43: 0 | AR43: -190500 | AS43: 0 | AT43: 0 | AU43: RM | AV43: Granules | AW43: PP Granules | AX43: RM | AY43: erp | AZ43: 0 | BA43: 0 | BB43: R-396 | BC43: 46210 | BD43: 24AAACO3087C1ZT | BE43: kpstore | BG43: 0 | BH43: 0 | BI43: 0 | BJ43: 0 | BK43: 0 | BL43: 0 | BM43: 0 | BN43: 632141335860 | BO43: 46210.455 | BP43: 1500 | BQ43: PP Granules
A44: K.P. WOVEN PRIVATE LIMITED | C44: 46211 | D44: KPV/26-27/SII01265 | E44: RAW05516 | F44: UV Arguvin FG 626 LD | G44: 1 | H44: No PO | I44: 0 | J44: 2000 | K44: Kgs | L44: 2000 | M44: 0 | N44: 2000 | O44: GJ24X8795 | P44: Plastene India ltd - Unit 1-Purchase | Q44: Plastene India ltd - Unit 1-Purchase | R44: PIL1/JW/45 | S44: 46210 | T44: JOB IN | U44: OTHER | V44: JBIN-OT 17 | W44: 194.99 | X44: 0 | Y44: PIL1/JW/45 | Z44: 46210 | AA44: 80 BAGS | AD44: PATEL TRANSPORT | AE44: 3919 07-07-2026 | AF44: 0 | AG44: 0 | AH44: 0 | AI44: 0 | AJ44: 0 | AK44: VAT | AL44: 0 | AM44: 0 | AN44: 0 | AO44: 0 | AP44: 0 | AR44: -389980 | AS44: 0 | AT44: 0 | AU44: RM | AV44: Granules | AW44: UV MB | AX44: RM | AY44: erp | AZ44: 0 | BA44: 0 | BB44: R-401 | BC44: 46211 | BD44: 24AAACO3087C1ZT | BE44: kpstore | BG44: 0 | BH44: 0 | BI44: 0 | BJ44: 0 | BK44: 0 | BL44: 0 | BM44: 0 | BN44: 662141302256 | BO44: 46210.612 | BP44: 2000 | BQ44: N.A
A45: K.P. WOVEN PRIVATE LIMITED | C45: 46211 | D45: KPV/26-27/SII01271 | E45: WIP00031 | F45: PP/HD Wastage/Scrap | G45: No Subcode | H45: No PO | I45: 0 | J45: 296.4 | K45: Kgs | L45: 296.4 | M45: 0 | N45: 296.4 | O45: GJ27TG8278 | P45: Kayel Syntex Limited | Q45: Kayel Syntex Limited | R45: 53 | S45: 46209 | T45: JOB IN | U45: SELF | V45: JBIN-SE 123 | W45: 28 | X45: 0 | Y45: 53 | Z45: 46209 | AB45: PP Woven Fabrics,Monofilament Yarn, | AD45: . | AE45: . | AF45: 0 | AG45: 0 | AH45: 0 | AI45: 0 | AJ45: 0 | AK45: VAT | AL45: 0 | AM45: 0 | AN45: 0 | AO45: 0 | AP45: 0 | AR45: -57170.4 | AS45: 0 | AT45: 0 | AU45: SF | AV45: Wastage/Scrap | AW45: Wastage/Scrap | AX45: SF | AY45: erp | AZ45: 0 | BA45: 0 | BB45: R-390 | BC45: 46209 | BD45: 24AAACK8589P1ZP | BE45: kpstore | BG45: 0 | BH45: 0 | BI45: 0 | BJ45: 0 | BK45: 0 | BL45: 0 | BM45: 0 | BN45: 672140725006 | BO45: 46210.649 | BP45: 296.4 | BQ45: Wastage/Scrap
A46: K.P. WOVEN PRIVATE LIMITED | C46: 46211 | D46: KPV/26-27/SII01271 | E46: SMF00253 | F46: Monofilament Yarn 840 Denier | G46: No Subcode | H46: No PO | I46: 0 | J46: 1210.2 | K46: Kgs | L46: 1210.2 | M46: 0 | N46: 1210.2 | O46: GJ27TG8278 | P46: Kayel Syntex Limited | Q46: Kayel Syntex Limited | R46: 53 | S46: 46209 | T46: JOB IN | U46: SELF | V46: JBIN-SE 123 | W46: 28 | X46: 0 | Y46: 53 | Z46: 46209 | AA46: 10 ROLL | AB46: PP Woven Fabrics,Monofilament Yarn, | AD46: . | AE46: . | AF46: 0 | AG46: 0 | AH46: 0 | AI46: 0 | AJ46: 0 | AK46: VAT | AL46: 0 | AM46: 0 | AN46: 0 | AO46: 0 | AP46: 0 | AR46: -57170.4 | AS46: 0 | AT46: 0 | AU46: SF | AV46: Yarn All | AW46: PP Yarn | AX46: SF | AY46: erp | AZ46: 0 | BA46: 0 | BB46: R-390 | BC46: 46209 | BD46: 24AAACK8589P1ZP | BE46: kpstore | BG46: 0 | BH46: 0 | BI46: 0 | BJ46: 0 | BK46: 0 | BL46: 0 | BM46: 0 | BN46: 672140725006 | BO46: 46210.649 | BP46: 1210.2 | BQ46: PP Yarn
A47: K.P. WOVEN PRIVATE LIMITED | C47: 46211 | D47: KPV/26-27/SII01271 | E47: SMF00253 | F47: Monofilament Yarn 840 Denier | G47: No Subcode | H47: No PO | I47: 0 | J47: 535.2 | K47: Kgs | L47: 535.2 | M47: 0 | N47: 535.2 | O47: GJ27TG8278 | P47: Kayel Syntex Limited | Q47: Kayel Syntex Limited | R47: 53 | S47: 46209 | T47: JOB IN | U47: SELF | V47: JBIN-SE 123 | W47: 28 | X47: 0 | Y47: 53 | Z47: 46209 | AA47: 3 ROLL EMPTY COPES 33 BAGS QTY-644 NOS | AB47: PP Woven Fabrics,Monofilament Yarn, | AD47: . | AE47: . | AF47: 0 | AG47: 0 | AH47: 0 | AI47: 0 | AJ47: 0 | AK47: VAT | AL47: 0 | AM47: 0 | AN47: 0 | AO47: 0 | AP47: 0 | AR47: -57170.4 | AS47: 0 | AT47: 0 | AU47: SF | AV47: Yarn All | AW47: PP Yarn | AX47: SF | AY47: erp | AZ47: 0 | BA47: 0 | BB47: R-390 | BC47: 46209 | BD47: 24AAACK8589P1ZP | BE47: kpstore | BG47: 0 | BH47: 0 | BI47: 0 | BJ47: 0 | BK47: 0 | BL47: 0 | BM47: 0 | BN47: 672140725006 | BO47: 46210.649 | BP47: 535.2 | BQ47: PP Yarn
A48: K.P. WOVEN PRIVATE LIMITED | C48: 46212 | D48: KPV/26-27/SII01279 | E48: WIP00023 | F48: PP UL Fabric With UV | G48: No Subcode | H48: No PO | I48: 0 | J48: 1250 | K48: Kgs | L48: 1250 | M48: 0 | N48: 1250 | O48: GJ24X8795 | P48: Plastene India ltd - Unit 1-Purchase | Q48: Plastene India ltd - Unit 1-Purchase | R48: PIL1/SC/115 | S48: 46210 | T48: JOB IN | U48: SELF | V48: JBIN-SE 124 | W48: 25 | X48: 0 | Y48: PIL1/SC/115 | Z48: 46210 | AA48: 2 ROLL | AB48: . | AD48: . | AE48: . | AF48: 0 | AG48: 0 | AH48: 0 | AI48: 0 | AJ48: 0 | AK48: VAT | AL48: 0 | AM48: 0 | AN48: 0 | AO48: 0 | AP48: 0 | AR48: -69932 | AS48: 0 | AT48: 0 | AU48: SF | AV48: PP/PE Fabric | AW48: PP UL Fabric | AX48: SF | AY48: erp | AZ48: 0 | BA48: 0 | BB48: R-399 | BC48: 46211 | BD48: 24AAACO3087C1ZT | BE48: kpstore | BG48: 0 | BH48: 0 | BI48: 0 | BJ48: 0 | BK48: 0 | BL48: 0 | BM48: 0 | BN48: 662141322027 | BO48: 46210.529 | BP48: 1250 | BQ48: PP UL Fabric
A49: K.P. WOVEN PRIVATE LIMITED | C49: 46212 | D49: KPV/26-27/SII01279 | E49: WIP00023 | F49: PP UL Fabric With UV | G49: No Subcode | H49: No PO | I49: 0 | J49: 365 | K49: Kgs | L49: 365 | M49: 0 | N49: 365 | O49: GJ24X8795 | P49: Plastene India ltd - Unit 1-Purchase | Q49: Plastene India ltd - Unit 1-Purchase | R49: PIL1/SC/115 | S49: 46210 | T49: JOB IN | U49: SELF | V49: JBIN-SE 124 | W49: 26 | X49: 0 | Y49: PIL1/SC/115 | Z49: 46210 | AA49: 1 ROLL | AB49: . | AD49: . | AE49: . | AF49: 0 | AG49: 0 | AH49: 0 | AI49: 0 | AJ49: 0 | AK49: VAT | AL49: 0 | AM49: 0 | AN49: 0 | AO49: 0 | AP49: 0 | AR49: -69932 | AS49: 0 | AT49: 0 | AU49: SF | AV49: PP/PE Fabric | AW49: PP UL Fabric | AX49: SF | AY49: erp | AZ49: 0 | BA49: 0 | BB49: R-399 | BC49: 46211 | BD49: 24AAACO3087C1ZT | BE49: kpstore | BG49: 0 | BH49: 0 | BI49: 0 | BJ49: 0 | BK49: 0 | BL49: 0 | BM49: 0 | BN49: 662141322027 | BO49: 46210.529 | BP49: 365 | BQ49: PP UL Fabric
A50: K.P. WOVEN PRIVATE LIMITED | C50: 46212 | D50: KPV/26-27/SII01279 | E50: WIP00023 | F50: PP UL Fabric With UV | G50: No Subcode | H50: No PO | I50: 0 | J50: 719 | K50: Kgs | L50: 719 | M50: 0 | N50: 719 | O50: GJ24X8795 | P50: Plastene India ltd - Unit 1-Purchase | Q50: Plastene India ltd - Unit 1-Purchase | R50: PIL1/SC/115 | S50: 46210 | T50: JOB IN | U50: SELF | V50: JBIN-SE 124 | W50: 20 | X50: 0 | Y50: PIL1/SC/115 | Z50: 46210 | AA50: 2 ROLL | AB50: . | AD50: . | AE50: . | AF50: 0 | AG50: 0 | AH50: 0 | AI50: 0 | AJ50: 0 | AK50: VAT | AL50: 0 | AM50: 0 | AN50: 0 | AO50: 0 | AP50: 0 | AR50: -69932 | AS50: 0 | AT50: 0 | AU50: SF | AV50: PP/PE Fabric | AW50: PP UL Fabric | AX50: SF | AY50: erp | AZ50: 0 | BA50: 0 | BB50: R-399 | BC50: 46211 | BD50: 24AAACO3087C1ZT | BE50: kpstore | BG50: 0 | BH50: 0 | BI50: 0 | BJ50: 0 | BK50: 0 | BL50: 0 | BM50: 0 | BN50: 662141322027 | BO50: 46210.529 | BP50: 719 | BQ50: PP UL Fabric
A51: K.P. WOVEN PRIVATE LIMITED | C51: 46212 | D51: KPV/26-27/SII01279 | E51: WIP00023 | F51: PP UL Fabric With UV | G51: No Subcode | H51: No PO | I51: 0 | J51: 644 | K51: Kgs | L51: 644 | M51: 0 | N51: 644 | O51: GJ24X8795 | P51: Plastene India ltd - Unit 1-Purchase | Q51: Plastene India ltd - Unit 1-Purchase | R51: PIL1/SC/115 | S51: 46210 | T51: JOB IN | U51: SELF | V51: JBIN-SE 124 | W51: 23 | X51: 0 | Y51: PIL1/SC/115 | Z51: 46210 | AA51: 2 ROLL | AB51: . | AD51: . | AE51: . | AF51: 0 | AG51: 0 | AH51: 0 | AI51: 0 | AJ51: 0 | AK51: VAT | AL51: 0 | AM51: 0 | AN51: 0 | AO51: 0 | AP51: 0 | AR51: -69932 | AS51: 0 | AT51: 0 | AU51: SF | AV51: PP/PE Fabric | AW51: PP UL Fabric | AX51: SF | AY51: erp | AZ51: 0 | BA51: 0 | BB51: R-399 | BC51: 46211 | BD51: 24AAACO3087C1ZT | BE51: kpstore | BG51: 0 | BH51: 0 | BI51: 0 | BJ51: 0 | BK51: 0 | BL51: 0 | BM51: 0 | BN51: 662141322027 | BO51: 46210.529 | BP51: 644 | BQ51: PP UL Fabric
A52: K.P. WOVEN PRIVATE LIMITED | C52: 46212 | D52: KPV/26-27/SII01283 | E52: WIP00151 | F52: PP MF Yarn Twisted 1000 UV NW | G52: No Subcode | H52: No PO | I52: 0 | J52: 1213.3 | K52: KGS | L52: 1213.3 | M52: 0 | N52: 1213.3 | O52: GJ18BX0314 | P52: Plastene India ltd - Unit 1-Purchase | Q52: Plastene India ltd - Unit 1-Purchase | R52: PIL1/SC/116 | S52: 46211 | T52: JOB IN | U52: SELF | V52: JBIN-SE 125 | W52: 32 | X52: 0 | Y52: PIL1/SC/116 | Z52: 46211 | AA52: 30 BUN. | AB52: PP Woven Fabrics, | AD52: . | AE52: . | AF52: 0 | AG52: 0 | AH52: 0 | AI52: 0 | AJ52: 0 | AK52: VAT | AL52: 0 | AM52: 0 | AN52: 0 | AO52: 0 | AP52: 0 | AR52: -82799.6 | AS52: 0 | AT52: 0 | AU52: SF | AV52: Yarn All | AW52: PP Yarn | AX52: SF | AZ52: 0 | BA52: 0 | BB52: R-404 | BC52: 46212 | BD52: 24AAACO3087C1ZT | BE52: kpstore | BG52: 0 | BH52: 0 | BI52: 0 | BJ52: 0 | BK52: 0 | BL52: 0 | BM52: 0 | BN52: 622141806590 | BO52: 46211 | BP52: 1213.3 | BQ52: PP Yarn
A53: K.P. WOVEN PRIVATE LIMITED | C53: 46212 | D53: KPV/26-27/SII01283 | E53: WIP00181 | F53: PP MF Yarn Twisted 2500 Denier UV NW | G53: No Subcode | H53: No PO | I53: 0 | J53: 1256.4 | K53: KGS | L53: 1256.4 | M53: 0 | N53: 1256.4 | O53: GJ18BX0314 | P53: Plastene India ltd - Unit 1-Purchase | Q53: Plastene India ltd - Unit 1-Purchase | R53: PIL1/SC/116 | S53: 46211 | T53: JOB IN | U53: SELF | V53: JBIN-SE 125 | W53: 35 | X53: 0 | Y53: PIL1/SC/116 | Z53: 46211 | AA53: 30 BUN. | AB53: PP Woven Fabrics, | AD53: . | AE53: . | AF53: 0 | AG53: 0 | AH53: 0 | AI53: 0 | AJ53: 0 | AK53: VAT | AL53: 0 | AM53: 0 | AN53: 0 | AO53: 0 | AP53: 0 | AR53: -82799.6 | AS53: 0 | AT53: 0 | AU53: SF | AV53: Yarn All | AW53: PP Yarn | AX53: SF | AZ53: 0 | BA53: 0 | BB53: R-404 | BC53: 46212 | BD53: 24AAACO3087C1ZT | BE53: kpstore | BG53: 0 | BH53: 0 | BI53: 0 | BJ53: 0 | BK53: 0 | BL53: 0 | BM53: 0 | BN53: 622141806590 | BO53: 46211 | BP53: 1256.4 | BQ53: PP Yarn
A54: K.P. WOVEN PRIVATE LIMITED | C54: 46213 | D54: KPV/26-27/SII01295 | E54: WIP00025 | F54: PP Lam Fabric With UV | G54: No Subcode | H54: No PO | I54: 0 | J54: 1521.2 | K54: Kgs | L54: 1521.2 | M54: 0 | N54: 1521.2 | O54: GJ16Z8614 | P54: Plastene India ltd - Unit 1-Purchase | Q54: Plastene India ltd - Unit 1-Purchase | R54: PIL1/SC/117 | S54: 46212 | T54: JOB IN | U54: SELF | V54: JBIN-SE 126 | W54: 33 | X54: 0 | Y54: PIL1/SC/117 | Z54: 46212 | AA54: 12ROLL COATED SULZER FABRIC | AB54: PP Woven Fabrics, | AD54: 0 | AE54: 0 | AF54: 0 | AG54: 0 | AH54: 0 | AI54: 0 | AJ54: 0 | AK54: VAT | AL54: 0 | AM54: 0 | AN54: 0 | AO54: 0 | AP54: 0 | AR54: -202609.1 | AS54: 0 | AT54: 0 | AU54: SF | AV54: PP/PE Fabric | AW54: PP Lam Fabric | AX54: SF | AY54: erp | AZ54: 0 | BA54: 0 | BB54: R 407 | BC54: 46213 | BD54: 24AAACO3087C1ZT | BE54: kpstore | BG54: 0 | BH54: 0 | BI54: 0 | BJ54: 0 | BK54: 0 | BL54: 0 | BM54: 0 | BN54: 672142391975 | BO54: 46212.575 | BP54: 1521.2 | BQ54: PP Lam Fabric
A55: K.P. WOVEN PRIVATE LIMITED | C55: 46213 | D55: KPV/26-27/SII01295 | E55: WIP00025 | F55: PP Lam Fabric With UV | G55: No Subcode | H55: No PO | I55: 0 | J55: 2458.5 | K55: Kgs | L55: 2458.5 | M55: 0 | N55: 2458.5 | O55: GJ16Z8614 | P55: Plastene India ltd - Unit 1-Purchase | Q55: Plastene India ltd - Unit 1-Purchase | R55: PIL1/SC/117 | S55: 46212 | T55: JOB IN | U55: SELF | V55: JBIN-SE 126 | W55: 30 | X55: 0 | Y55: PIL1/SC/117 | Z55: 46212 | AA55: 16ROLL COATED SULZER FABRIC | AB55: PP Woven Fabrics, | AD55: 0 | AE55: 0 | AF55: 0 | AG55: 0 | AH55: 0 | AI55: 0 | AJ55: 0 | AK55: VAT | AL55: 0 | AM55: 0 | AN55: 0 | AO55: 0 | AP55: 0 | AR55: -202609.1 | AS55: 0 | AT55: 0 | AU55: SF | AV55: PP/PE Fabric | AW55: PP Lam Fabric | AX55: SF | AY55: erp | AZ55: 0 | BA55: 0 | BB55: R 407 | BC55: 46213 | BD55: 24AAACO3087C1ZT | BE55: kpstore | BG55: 0 | BH55: 0 | BI55: 0 | BJ55: 0 | BK55: 0 | BL55: 0 | BM55: 0 | BN55: 672142391975 | BO55: 46212.575 | BP55: 2458.5 | BQ55: PP Lam Fabric
A56: K.P. WOVEN PRIVATE LIMITED | C56: 46213 | D56: KPV/26-27/SII01295 | E56: WIP00023 | F56: PP UL Fabric With UV | G56: No Subcode | H56: No PO | I56: 0 | J56: 480 | K56: Kgs | L56: 480 | M56: 0 | N56: 480 | O56: GJ16Z8614 | P56: Plastene India ltd - Unit 1-Purchase | Q56: Plastene India ltd - Unit 1-Purchase | R56: PIL1/SC/117 | S56: 46212 | T56: JOB IN | U56: SELF | V56: JBIN-SE 126 | W56: 31 | X56: 0 | Y56: PIL1/SC/117 | Z56: 46212 | AA56: 1ROLL CROSS CORNNER COLOR HQS | AB56: PP Woven Fabrics, | AD56: 0 | AE56: 0 | AF56: 0 | AG56: 0 | AH56: 0 | AI56: 0 | AJ56: 0 | AK56: VAT | AL56: 0 | AM56: 0 | AN56: 0 | AO56: 0 | AP56: 0 | AR56: -202609.1 | AS56: 0 | AT56: 0 | AU56: SF | AV56: PP/PE Fabric | AW56: PP UL Fabric | AX56: SF | AY56: erp | AZ56: 0 | BA56: 0 | BB56: R 407 | BC56: 46213 | BD56: 24AAACO3087C1ZT | BE56: kpstore | BG56: 0 | BH56: 0 | BI56: 0 | BJ56: 0 | BK56: 0 | BL56: 0 | BM56: 0 | BN56: 672142391975 | BO56: 46212.575 | BP56: 480 | BQ56: PP UL Fabric
