Workbook
Name __xlnm._FilterDatabase: #REF!
Name __xlnm._FilterDatabase_1: #REF!
Name __xlnm._FilterDatabase_2: #REF!
Name __xlnm.Print_Titles: #REF!
Name __xlnm.Print_Titles_1: #REF!
Name Excel_BuiltIn__FilterDatabase: [1]Debtors!$A$30:$G$221

Sheet JOB OUT
A1: Row Labels | B1: Sum of ItemQty
A2: (blank)
A3: (blank)
A4: Grand Total
E11: companyname | F11: ChallanNo | G11: sysdate | H11: Company Name | I11: NatureProc | J11: DescriptionGoods | K11: Deptt | L11: GroupName | M11: SubGroupName | N11: itemcode | O11: itemname | P11: Identification | Q11: QtyDesc | R11: ItemUnit | S11: ItemQty | T11: ItemValue | U11: TotalAmt | V11: VehicalNo | W11: LRNo | X11: TransportName

Sheet JOB-IN
A1: Row Labels | B1: Sum of Acceptedqty
A2: Parsva Trading | B2: 162.34
A3: Saru Plastics | B3: 848.3
A4: (blank)
A5: Grand Total | B5: 1010.64
G8: CompanyName | H8: Date | I8: srno | J8: Itemcode | K8: Itemname | L8: Indentsubcode | M8: PoNO | N8: OrderQty | O8: Challanqty | P8: Unit | Q8: Recdqty | R8: PendingQty | S8: Acceptedqty | T8: Vehicalno | U8: Partyname | V8: Suppliername | W8: ChallanNo | X8: Challan Date | Y8: category | Z8: subcategory | AA8: MRno | AB8: Rate | AC8: Amount | AD8: BillNo | AE8: Bill Date | AF8: ItemRemarks | AG8: Remarks | AH8: Note | AI8: Transportname | AJ8: Lrnodate | AK8: Discamt | AL8: Discamt1 | AM8: ExciseAmount | AN8: EducessAmount | AO8: HiEducessamount | AP8: InwardVatType | AQ8: Vatamount | AR8: Addvatamount | AS8: Frieght | AT8: Pkgfwd | AU8: Otherchg | AV8: Spdutyname | AW8: Spdutyamt | AX8: Additionalduty | AY8: Billamount | AZ8: Deptt | BA8: GroupName | BB8: SubGroupName | BC8: Deptt Po Indent | BD8: LoginName | BE8: servicetax | BF8: Basic Amount | BG8: GateInwardNo | BH8: GateInwardDate | BI8: VendorGST | BJ8: MRN User | BK8: POUserName | BL8: CGSTPer | BM8: CGSTAmount | BN8: SGSTPer | BO8: SGSTAmount | BP8: IGSTPer | BQ8: IGSTAmount | BR8: RBIllmount | BS8: EWayNo | BT8: EWayDt | BU8: netwt
G9: HCP Plastene Bulkpack Ltd (Unit - IV) | H9: 15-07-2026 | I9: HPBL4/26-27/SII00901 | J9: SMF00147 | K9: PE Labels (Kgs) | L9: No Subcode | M9: No PO | N9: 0 | O9: 102 | P9: Kgs | Q9: 102 | R9: 0 | S9: 102 | T9: GJ24V1087 | U9: Saru Plastics | V9: Saru Plastics | W9: SARU52 | X9: 27-06-2026 | Y9: JOB IN | Z9: SELF | AA9: JBIN-SE 34 | AB9: 0 | AC9: 0 | AD9: SARU52 | AE9: 27-06-2026 | AF9: 0 | AG9: PP Woven Big Bags, | AI9: OWN Vehical | AJ9: . | AK9: 0 | AL9: 0 | AM9: 0 | AN9: 0 | AO9: 0 | AP9: VAT | AQ9: 0 | AR9: 0 | AS9: 0 | AT9: 0 | AU9: 0 | AW9: 0 | AX9: 0 | AY9: 0 | AZ9: SF | BA9: Liners | BB9: LDPE/LLDPE Bags | BC9: SERVICES | BD9: erp | BE9: 0 | BF9: 0 | BG9: JW35 | BH9: 46029 | BI9: 24ACHPM5973F1ZG | BJ9: storepil6 | BL9: 0 | BM9: 0 | BN9: 0 | BO9: 0 | BP9: 0 | BQ9: 0 | BR9: 0 | BS9: . | BT9: 46218.681 | BU9: 102
G10: HCP Plastene Bulkpack Ltd (Unit - IV) | H10: 16-07-2026 | I10: HPBL4/26-27/SII00903 | J10: SMF00147 | K10: PE Labels (Kgs) | L10: No Subcode | M10: No PO | N10: 0 | O10: 72.1 | P10: Kgs | Q10: 72.1 | R10: 0 | S10: 72.1 | T10: GJ24V1087 | U10: Parsva Trading | V10: Parsva Trading | W10: 20 | X10: 46149 | Y10: JOB IN | Z10: SELF | AA10: JBIN-SE 35 | AB10: 0 | AC10: 0 | AD10: 20 | AE10: 46149 | AF10: 0 | AG10: PP Woven Big Bags, | AI10: OWN VEHICLE | AJ10: - | AK10: 0 | AL10: 0 | AM10: 0 | AN10: 0 | AO10: 0 | AP10: VAT | AQ10: 0 | AR10: 0 | AS10: 0 | AT10: 0 | AU10: 0 | AW10: 0 | AX10: 0 | AY10: 0 | AZ10: SF | BA10: Liners | BB10: LDPE/LLDPE Bags | BC10: SERVICES | BD10: erp | BE10: 0 | BF10: 0 | BG10: JW37 | BH10: 46302 | BI10: 24AMOPG6602J2Z0 | BJ10: storepil6 | BL10: 0 | BM10: 0 | BN10: 0 | BO10: 0 | BP10: 0 | BQ10: 0 | BR10: 0 | BS10: - | BT10: 46219.476 | BU10: 72.1
G11: HCP Plastene Bulkpack Ltd (Unit - IV) | H11: 16-07-2026 | I11: HPBL4/26-27/SII00907 | J11: SMF00147 | K11: PE Labels (Kgs) | L11: No Subcode | M11: No PO | N11: 0 | O11: 25 | P11: Kgs | Q11: 25 | R11: 0 | S11: 25 | T11: GJ24V1087 | U11: Saru Plastics | V11: Saru Plastics | W11: SARU054 | X11: 29-06-2026 | Y11: JOB IN | Z11: SELF | AA11: JBIN-SE 36 | AB11: 0 | AC11: 0 | AD11: SARU054 | AE11: 29-06-2026 | AF11: 0 | AG11: PP Woven Big Bags, | AI11: OWN VEHICLE | AJ11: - | AK11: 0 | AL11: 0 | AM11: 0 | AN11: 0 | AO11: 0 | AP11: VAT | AQ11: 0 | AR11: 0 | AS11: 0 | AT11: 0 | AU11: 0 | AW11: 0 | AX11: 0 | AY11: 0 | AZ11: SF | BA11: Liners | BB11: LDPE/LLDPE Bags | BC11: SERVICES | BD11: erp | BE11: 0 | BF11: 0 | BG11: JW36 | BH11: 46029 | BI11: 24ACHPM5973F1ZG | BJ11: storepil6 | BL11: 0 | BM11: 0 | BN11: 0 | BO11: 0 | BP11: 0 | BQ11: 0 | BR11: 0 | BS11: - | BT11: 46219.669 | BU11: 25
G12: HCP Plastene Bulkpack Ltd (Unit - IV) | H12: 16-07-2026 | I12: HPBL4/26-27/SII00908 | J12: SMF00147 | K12: PE Labels (Kgs) | L12: No Subcode | M12: No PO | N12: 0 | O12: 145 | P12: Kgs | Q12: 145 | R12: 0 | S12: 145 | T12: GJ24V1087 | U12: Saru Plastics | V12: Saru Plastics | W12: SARU055 | X12: 46060 | Y12: JOB IN | Z12: SELF | AA12: JBIN-SE 37 | AB12: 0 | AC12: 0 | AD12: SARU055 | AE12: 46060 | AF12: 0 | AG12: PP Woven Big Bags, | AI12: OWN VEHICLE | AJ12: - | AK12: 0 | AL12: 0 | AM12: 0 | AN12: 0 | AO12: 0 | AP12: VAT | AQ12: 0 | AR12: 0 | AS12: 0 | AT12: 0 | AU12: 0 | AW12: 0 | AX12: 0 | AY12: 0 | AZ12: SF | BA12: Liners | BB12: LDPE/LLDPE Bags | BC12: SERVICES | BD12: erp | BE12: 0 | BF12: 0 | BG12: JW38 | BH12: 46302 | BI12: 24ACHPM5973F1ZG | BJ12: storepil6 | BL12: 0 | BM12: 0 | BN12: 0 | BO12: 0 | BP12: 0 | BQ12: 0 | BR12: 0 | BS12: - | BT12: 46219 | BU12: 145
G13: HCP Plastene Bulkpack Ltd (Unit - IV) | H13: 16-07-2026 | I13: HPBL4/26-27/SII00909 | J13: SMF00147 | K13: PE Labels (Kgs) | L13: No Subcode | M13: No PO | N13: 0 | O13: 29 | P13: Kgs | Q13: 29 | R13: 0 | S13: 29 | T13: GJ24V1087 | U13: Saru Plastics | V13: Saru Plastics | W13: SARU057 | X13: 46088 | Y13: JOB IN | Z13: SELF | AA13: JBIN-SE 38 | AB13: 0 | AC13: 0 | AD13: SARU057 | AE13: 46088 | AF13: 0 | AG13: PP Woven Big Bags, | AI13: OWN Vehical | AJ13: . | AK13: 0 | AL13: 0 | AM13: 0 | AN13: 0 | AO13: 0 | AP13: VAT | AQ13: 0 | AR13: 0 | AS13: 0 | AT13: 0 | AU13: 0 | AW13: 0 | AX13: 0 | AY13: 0 | AZ13: SF | BA13: Liners | BB13: LDPE/LLDPE Bags | BC13: SERVICES | BD13: erp | BE13: 0 | BF13: 0 | BG13: JW39 | BH13: 46302 | BI13: 24ACHPM5973F1ZG | BJ13: storepil6 | BL13: 0 | BM13: 0 | BN13: 0 | BO13: 0 | BP13: 0 | BQ13: 0 | BR13: 0 | BS13: . | BT13: 46219 | BU13: 29
G14: HCP Plastene Bulkpack Ltd (Unit - IV) | H14: 16-07-2026 | I14: HPBL4/26-27/SII00910 | J14: SMF00147 | K14: PE Labels (Kgs) | L14: No Subcode | M14: No PO | N14: 0 | O14: 45.3 | P14: Kgs | Q14: 45.3 | R14: 0 | S14: 45.3 | T14: GJ24V1087 | U14: Saru Plastics | V14: Saru Plastics | W14: SARU058 | X14: 46119 | Y14: JOB IN | Z14: SELF | AA14: JBIN-SE 39 | AB14: 0 | AC14: 0 | AD14: SARU058 | AE14: 46119 | AF14: 0 | AG14: PP Woven Big Bags, | AI14: OWN Vehical | AJ14: . | AK14: 0 | AL14: 0 | AM14: 0 | AN14: 0 | AO14: 0 | AP14: VAT | AQ14: 0 | AR14: 0 | AS14: 0 | AT14: 0 | AU14: 0 | AW14: 0 | AX14: 0 | AY14: 0 | AZ14: SF | BA14: Liners | BB14: LDPE/LLDPE Bags | BC14: SERVICES | BD14: erp | BE14: 0 | BF14: 0 | BG14: JW39. | BH14: 46302 | BI14: 24ACHPM5973F1ZG | BJ14: storepil6 | BL14: 0 | BM14: 0 | BN14: 0 | BO14: 0 | BP14: 0 | BQ14: 0 | BR14: 0 | BS14: . | BT14: 46219.717 | BU14: 45.3
G15: HCP Plastene Bulkpack Ltd (Unit - IV) | H15: 16-07-2026 | I15: HPBL4/26-27/SII00911 | J15: SMF00147 | K15: PE Labels (Kgs) | L15: No Subcode | M15: No PO | N15: 0 | O15: 131 | P15: Kgs | Q15: 131 | R15: 0 | S15: 131 | T15: GJ24V1087 | U15: Saru Plastics | V15: Saru Plastics | W15: SARU060 | X15: 46241 | Y15: JOB IN | Z15: SELF | AA15: JBIN-SE 40 | AB15: 0 | AC15: 0 | AD15: SARU060 | AE15: 46241 | AF15: 0 | AG15: PP Woven Big Bags, | AI15: OWN Vehical | AJ15: . | AK15: 0 | AL15: 0 | AM15: 0 | AN15: 0 | AO15: 0 | AP15: VAT | AQ15: 0 | AR15: 0 | AS15: 0 | AT15: 0 | AU15: 0 | AW15: 0 | AX15: 0 | AY15: 0 | AZ15: SF | BA15: Liners | BB15: LDPE/LLDPE Bags | BC15: SERVICES | BD15: erp | BE15: 0 | BF15: 0 | BG15: JW40 | BH15: 46302 | BI15: 24ACHPM5973F1ZG | BJ15: storepil6 | BL15: 0 | BM15: 0 | BN15: 0 | BO15: 0 | BP15: 0 | BQ15: 0 | BR15: 0 | BS15: . | BT15: 46219 | BU15: 131
G16: HCP Plastene Bulkpack Ltd (Unit - IV) | H16: 18-07-2026 | I16: HPBL4/26-27/SII00936 | J16: SMF00147 | K16: PE Labels (Kgs) | L16: No Subcode | M16: No PO | N16: 0 | O16: 28 | P16: Kgs | Q16: 28 | R16: 0 | S16: 28 | T16: GJ24V1087 | U16: Saru Plastics | V16: Saru Plastics | W16: SARU061 | X16: 14-07-2026 | Y16: JOB IN | Z16: SELF | AA16: JBIN-SE 41 | AB16: 0 | AC16: 0 | AD16: SARU061 | AE16: 14-07-2026 | AF16: 0 | AG16: PP Woven Big Bags, | AI16: OWN Vehical | AJ16: . | AK16: 0 | AL16: 0 | AM16: 0 | AN16: 0 | AO16: 0 | AP16: VAT | AQ16: 0 | AR16: 0 | AS16: 0 | AT16: 0 | AU16: 0 | AW16: 0 | AX16: 0 | AY16: 0 | AZ16: SF | BA16: Liners | BB16: LDPE/LLDPE Bags | BC16: SERVICES | BD16: erp | BE16: 0 | BF16: 0 | BG16: 41 | BH16: 18-07-2026 | BI16: 24ACHPM5973F1ZG | BJ16: storepil6 | BL16: 0 | BM16: 0 | BN16: 0 | BO16: 0 | BP16: 0 | BQ16: 0 | BR16: 0 | BS16: . | BT16: 46221.646 | BU16: 28
G17: HCP Plastene Bulkpack Ltd (Unit - IV) | H17: 22-07-2026 | I17: HPBL4/26-27/SII00974 | J17: SMF00147 | K17: PE Labels (Kgs) | L17: No Subcode | M17: No PO | N17: 0 | O17: 37 | P17: Kgs | Q17: 37 | R17: 0 | S17: 37 | T17: GJ24V1087 | U17: Saru Plastics | V17: Saru Plastics | W17: SARU063 | X17: 18-07-2026 | Y17: JOB IN | Z17: SELF | AA17: JBIN-SE 42 | AB17: 0 | AC17: 0 | AD17: SARU063 | AE17: 18-07-2026 | AF17: 0 | AG17: PP Woven Big Bags, | AI17: OWN Vehical | AJ17: . | AK17: 0 | AL17: 0 | AM17: 0 | AN17: 0 | AO17: 0 | AP17: VAT | AQ17: 0 | AR17: 0 | AS17: 0 | AT17: 0 | AU17: 0 | AW17: 0 | AX17: 0 | AY17: 0 | AZ17: SF | BA17: Liners | BB17: LDPE/LLDPE Bags | BC17: SF | BD17: erp | BE17: 0 | BF17: 0 | BG17: 43 | BH17: 22-07-2026 | BI17: 24ACHPM5973F1ZG | BJ17: storepil6 | BL17: 0 | BM17: 0 | BN17: 0 | BO17: 0 | BP17: 0 | BQ17: 0 | BR17: 0 | BS17: . | BT17: 46225.726 | BU17: 37
G18: HCP Plastene Bulkpack Ltd (Unit - IV) | H18: 22-07-2026 | I18: HPBL4/26-27/SII00975 | J18: SMF00147 | K18: PE Labels (Kgs) | L18: No Subcode | M18: No PO | N18: 0 | O18: 69 | P18: Kgs | Q18: 69 | R18: 0 | S18: 69 | T18: GJ24V1087 | U18: Saru Plastics | V18: Saru Plastics | W18: SARU064 | X18: 20-07-2026 | Y18: JOB IN | Z18: SELF | AA18: JBIN-SE 43 | AB18: 0 | AC18: 0 | AD18: SARU064 | AE18: 20-07-2026 | AF18: 0 | AG18: PP Woven Big Bags, | AI18: OWN Vehical | AJ18: . | AK18: 0 | AL18: 0 | AM18: 0 | AN18: 0 | AO18: 0 | AP18: VAT | AQ18: 0 | AR18: 0 | AS18: 0 | AT18: 0 | AU18: 0 | AW18: 0 | AX18: 0 | AY18: 0 | AZ18: SF | BA18: Liners | BB18: LDPE/LLDPE Bags | BC18: SERVICES | BD18: erp | BE18: 0 | BF18: 0 | BG18: 42 | BH18: 21-07-2026 | BI18: 24ACHPM5973F1ZG | BJ18: storepil6 | BL18: 0 | BM18: 0 | BN18: 0 | BO18: 0 | BP18: 0 | BQ18: 0 | BR18: 0 | BS18: . | BT18: 46225.738 | BU18: 0
G19: HCP Plastene Bulkpack Ltd (Unit - IV) | H19: 29-07-2026 | I19: HPBL4/26-27/SII01032 | J19: SMF00147 | K19: PE Labels (Kgs) | L19: No Subcode | M19: No PO | N19: 0 | O19: 112 | P19: Kgs | Q19: 112 | R19: 0 | S19: 112 | T19: GJ12X5422 | U19: Saru Plastics | V19: Saru Plastics | W19: SARU068 | X19: 25-07-2026 | Y19: JOB IN | Z19: SELF | AA19: JBIN-SE 44 | AB19: 0 | AC19: 0 | AD19: SARU068 | AE19: 25-07-2026 | AF19: 0 | AG19: PP Woven Big Bags, | AI19: OWN Vehical | AJ19: . | AK19: 0 | AL19: 0 | AM19: 0 | AN19: 0 | AO19: 0 | AP19: VAT | AQ19: 0 | AR19: 0 | AS19: 0 | AT19: 0 | AU19: 0 | AW19: 0 | AX19: 0 | AY19: 0 | AZ19: SF | BA19: Liners | BB19: LDPE/LLDPE Bags | BC19: SERVICES | BD19: erp | BE19: 0 | BF19: 0 | BG19: 966 | BH19: 25-07-2026 | BI19: 24ACHPM5973F1ZG | BJ19: storepil6 | BL19: 0 | BM19: 0 | BN19: 0 | BO19: 0 | BP19: 0 | BQ19: 0 | BR19: 0 | BS19: . | BT19: 46232.671 | BU19: 112
G20: HCP Plastene Bulkpack Ltd (Unit - IV) | H20: 31-07-2026 | I20: HPBL4/26-27/SII01058 | J20: SMF00147 | K20: PE Labels (Kgs) | L20: No Subcode | M20: No PO | N20: 0 | O20: 61 | P20: Kgs | Q20: 61 | R20: 0 | S20: 61 | T20: GJ24V1087 | U20: Saru Plastics | V20: Saru Plastics | W20: SARU072 | X20: 28-07-2026 | Y20: JOB IN | Z20: SELF | AA20: JBIN-SE 45 | AB20: 0 | AC20: 0 | AD20: SARU072 | AE20: 28-07-2026 | AF20: 0 | AG20: PP Woven Big Bags, | AI20: OWN Vehical | AJ20: . | AK20: 0 | AL20: 0 | AM20: 0 | AN20: 0 | AO20: 0 | AP20: VAT | AQ20: 0 | AR20: 0 | AS20: 0 | AT20: 0 | AU20: 0 | AW20: 0 | AX20: 0 | AY20: 0 | AZ20: SF | BA20: Liners | BB20: LDPE/LLDPE Bags | BC20: SERVICES | BD20: erp | BE20: 0 | BF20: 0 | BG20: 45 | BH20: 30-07-2026 | BI20: 24ACHPM5973F1ZG | BJ20: storepil6 | BL20: 0 | BM20: 0 | BN20: 0 | BO20: 0 | BP20: 0 | BQ20: 0 | BR20: 0 | BS20: . | BT20: 46234.587 | BU20: 0
G21: HCP Plastene Bulkpack Ltd (Unit - IV) | H21: 31-07-2026 | I21: HPBL4/26-27/SII01059 | J21: SMF00147 | K21: PE Labels (Kgs) | L21: No Subcode | M21: No PO | N21: 0 | O21: 48 | P21: Kgs | Q21: 48 | R21: 0 | S21: 48 | T21: GJ24V1087 | U21: Saru Plastics | V21: Saru Plastics | W21: SARU073 | X21: 29-07-2026 | Y21: JOB IN | Z21: SELF | AA21: JBIN-SE 46 | AB21: 0 | AC21: 0 | AD21: SARU073 | AE21: 29-07-2026 | AF21: 0 | AG21: PP Woven Big Bags, | AI21: OWN Vehical | AJ21: . | AK21: 0 | AL21: 0 | AM21: 0 | AN21: 0 | AO21: 0 | AP21: VAT | AQ21: 0 | AR21: 0 | AS21: 0 | AT21: 0 | AU21: 0 | AW21: 0 | AX21: 0 | AY21: 0 | AZ21: SF | BA21: Liners | BB21: LDPE/LLDPE Bags | BC21: SERVICES | BD21: erp | BE21: 0 | BF21: 0 | BG21: 46 | BH21: 30-07-2026 | BI21: 24ACHPM5973F1ZG | BJ21: storepil6 | BL21: 0 | BM21: 0 | BN21: 0 | BO21: 0 | BP21: 0 | BQ21: 0 | BR21: 0 | BS21: . | BT21: 46234.592 | BU21: 0
G22: HCP Plastene Bulkpack Ltd (Unit - IV) | H22: 31-07-2026 | I22: HPBL4/26-27/SII01060 | J22: SMF00147 | K22: PE Labels (Kgs) | L22: No Subcode | M22: No PO | N22: 0 | O22: 16 | P22: Kgs | Q22: 16 | R22: 0 | S22: 16 | T22: GJ24V1087 | U22: Saru Plastics | V22: Saru Plastics | W22: SARU074 | X22: 30-07-2026 | Y22: JOB IN | Z22: SELF | AA22: JBIN-SE 47 | AB22: 0 | AC22: 0 | AD22: SARU074 | AE22: 30-07-2026 | AF22: 0 | AG22: PP Woven Big Bags, | AI22: OWN Vehical | AJ22: . | AK22: 0 | AL22: 0 | AM22: 0 | AN22: 0 | AO22: 0 | AP22: VAT | AQ22: 0 | AR22: 0 | AS22: 0 | AT22: 0 | AU22: 0 | AW22: 0 | AX22: 0 | AY22: 0 | AZ22: SF | BA22: Liners | BB22: LDPE/LLDPE Bags | BC22: SERVICES | BD22: erp | BE22: 0 | BF22: 0 | BG22: 44 | BH22: 30-07-2026 | BI22: 24ACHPM5973F1ZG | BJ22: storepil6 | BL22: 0 | BM22: 0 | BN22: 0 | BO22: 0 | BP22: 0 | BQ22: 0 | BR22: 0 | BS22: . | BT22: 46234.606 | BU22: 0
G23: HCP Plastene Bulkpack Ltd (Unit - IV) | H23: 31-07-2026 | I23: HPBL4/26-27/SII01071 | J23: SMF00147 | K23: PE Labels (Kgs) | L23: No Subcode | M23: No PO | N23: 0 | O23: 90.24 | P23: Kgs | Q23: 90.24 | R23: 0 | S23: 90.24 | T23: gj24v1087 | U23: Parsva Trading | V23: Parsva Trading | W23: 22 | X23: 22-07-2026 | Y23: JOB IN | Z23: SELF | AA23: JBIN-SE 48 | AB23: 0 | AC23: 0 | AD23: 22 | AE23: 22-07-2026 | AF23: 0 | AG23: PP Woven Big Bags, | AI23: OWN Vehical | AJ23: . | AK23: 0 | AL23: 0 | AM23: 0 | AN23: 0 | AO23: 0 | AP23: VAT | AQ23: 0 | AR23: 0 | AS23: 0 | AT23: 0 | AU23: 0 | AW23: 0 | AX23: 0 | AY23: 0 | AZ23: SF | BA23: Liners | BB23: LDPE/LLDPE Bags | BC23: SERVICES | BD23: erp | BE23: 0 | BF23: 0 | BG23: 47.. | BH23: 31-07-2026 | BI23: 24AMOPG6602J2Z0 | BJ23: storepil6 | BL23: 0 | BM23: 0 | BN23: 0 | BO23: 0 | BP23: 0 | BQ23: 0 | BR23: 0 | BS23: . | BT23: 46234.454 | BU23: 0

Sheet Provision & Prepaid Exp
A1: July-2026 Salary and Expense Provision Sheet | H1: PARTICULARS | J1: MT | L1: Avg. Rate
A2: Expense Head | B2: Gross Value | C2: CONTRACTOR SALARY | H2: BUDGETED / PLANNED | J2: 400
A3: Labour Charges | B3: 958550 | C3: LILI MANI CHHUAL SINGH (BKS) | H3: PRODUCTION
B4: 85442 | C4: BHABESH CHHUAL SINGH | H4: FIBC | J4: 481.055 | L4: 228.05 | M4: =+L4*0.95 -> 216.6475
B5: 300087 | C5: DHARAMVEER KUMAR PASWAN | H5: Fabric (Liner Mtr)
B6: 2055603 | C6: DHARAMVEER KUMAR PASWAN (LINE C)
B7: 1151040 | C7: DINESHBHAI KHUMABHAI DESAI | H7: DISPATCH
B8: 109307 | C8: JITENDRASINH B. ZALA | H8: FIBC | J8: 595.287 | L8: 228.05 | M8: =+L8*0.95 -> 216.6475
B9: 800315 | C9: RATAN CHANDRA SARKAR | H9: Fabric
B10: 799650 | C10: SUDHANSHU BARMAN
B11: 1754987 | C11: SAHDEVSINH FATEHSINH JADEJA | H11: PURCHASE
B12: 548964 | C12: RASIDUL MONDAL | H12: Fabric | J12: 382.735 | L12: 145.68118
B13: 0 | C13: DIVYANSHU ENTERPRISES | H13: PP Granules
C14: COMPANY SALARY
H15: Consumable/Store Spares | J15: 5822557.5
A16: Expense Head | B16: Gross Value | C16: Party Name | H16: Packing Material | J16: 1649149.4
A17: P.F. Contribution - Employer | B17: =36500+3200 -> 39700 | C17: Month of July 2026 | D17: Approx
A18: Advocate Fees Exp. | B18: 7500 | C18: Joshi Brothers
A19: Staff Welfare Exp. | B19: 0 | C19: Rahul Govindram
A20: Freight Outward Expense (With GST) | B20: 7189365 | C20: SHIPPING LINE | D20: Approx
A21: C & F Charges-Export | B21: 559820 | C21: SHIPPING LINE | D21: Approx
A22: Freight outward Expenses (RCM_Withinstate) | B22: 12200 | C22: Giriraj Tempo Service
A23: House Keeping Expense | B23: 0 | C23: Laxman Murjibhai Lakhwana
A24: Medical Expense | B24: 2260 | C24: NIMAVAT HOSPITAL
A25: Incentive Expense - Production | B25: 11000 | C25: SS
A26: Mobile & Telephone Expense | B26: 6998 | C26: Vihaan Telecomunication
A27: Freight outward Expenses (RCM_Withinstate) | B27: 0 | C27: Laxman B
A28: Water Charges | B28: 131100 | C28: Krishna Enterprise
A29: FUMIGATION EXPENSES | B29: 0 | C29: SENSATION PEST
A30: Repairs & Maintenance Exp - Computer & Printers | B30: 7050 | C30: VISHWAS ENTERPRISES
A31: VEHICLE HIRE CHARGES | B31: 0 | C31: ARVIND CHAUHAN
A32: WEIGHMENT CHARGES | B32: 0 | C32: SHREE SHYAM WEIGH BRIDGE
A33: SECURITY CHARGES | B33: 0 | C33: INDIAN SECURITY
A34: Testing Charges | B34: =29000+52200 -> 81200 | C34: INDIAN INSTITUE OF PACKAGING-AHMD
A35: Repair & Maintance- Plant & M/c | B35: 0 | C35: Shree Krishnam Rubtech LLP
A36: Freight outward Expenses (RCM_Withinstate) | B36: 9400 | C36: Pareshbhai Khumabhai Desai
B37: =SUM(B3:B36) -> 16621538 | C37: TOTAL AMOUNT

Sheet Sheet7
B2: Delta Conversion Rate for the M/o.Feb-2024
B3: A-SALES | F3: SALES RATE
C5: ITEM NAME | D5: QTY. | E5: AMOUNT | F5: RATE/KGS.
C6: JUMBO BAGS | D6: 406016.1 | E6: 61264012 | F6: =+E6/D6 -> 150.8906
F7: PURCHASE RATE
B9: B-PURCHASE | C9: ITEM NAME | D9: QTY. | E9: AMOUNT | F9: RATE/KGS.
C10: LLDPE BAGS | D10: 49687.4 | E10: 6118732.2 | F10: =+E10/D10 -> 123.14454
C11: LLDPE DOC | D11: 846.1 | E11: 102637.23 | F11: =+E11/D11 -> 121.30626
C12: LLDPE FILM | D12: 909.7 | E12: 104412.64 | F12: =+E12/D12 -> 114.777
C13: PP FILAMENT YARN | D13: 10591.2 | E13: 1396913.7 | F13: =+E13/D13 -> 131.89381
C14: PP LAMINATED WOVEN FABRIC | D14: 31724.2 | E14: 3839698.8 | F14: =+E14/D14 -> 121.03375
C15: PP WOVEN FABRIC | D15: 264543.8 | E15: 30961911 | F15: =+E15/D15 -> 117.03888
C16: PP WEBBING | D16: 57892.5 | E16: 6893788.5 | F16: =+E16/D16 -> 119.07913
D17: =SUM(D10:D16) -> 416194.9 | E17: =SUM(E10:E16) -> 49418094 | F17: =+E17/D17 -> 118.73786
D19: DIFFERENCE (A-B) DELTA | F19: =+F6-F17 -> 32.152733
B21: Month Wise Conversion Rate Sheet-PIL-VI
B22: 2023-24 | C22: RAW MATERIAL PURCHASE | F22: FINISHED FIBC SALES | I22: Delta
B23: Month | C23: QTY | D23: Rate | E23: Amount | F23: QTY | G23: Rate | H23: Amount | I23: Conversion
B24: Nov.23 | C24: 396215.1 | D24: =+E24/C24 -> 111.94216 | E24: 44353173 | F24: 422404.1 | G24: =+H24/F24 -> 162.14543 | H24: 68490895 | I24: =+G24-D24 -> 50.203275
B25: Dec.23 | C25: 425293.1 | D25: =+E25/C25 -> 112.11408 | E25: 47681346 | F25: 308715.72 | G25: =+H25/F25 -> 159.86059 | H25: 49351478 | I25: =+G25-D25 -> 47.746509
B26: Jan.24 | C26: 365699.21 | D26: =+E26/C26 -> 116.0993 | E26: 42457424 | F26: 472444 | G26: =+H26/F26 -> 153.16551 | H26: 72362124 | I26: =+G26-D26 -> 37.066201
B27: Feb.24 | C27: 416194.9 | D27: =+E27/C27 -> 118.73786 | E27: 49418094 | F27: 406016.1 | G27: =+H27/F27 -> 150.8906 | H27: 61264012 | I27: =+G27-D27 -> 32.152733
B28: Mar.24
B29: Total/Av. | C29: =SUM(C24:C28) -> 1603402.3 | D29: =+E29/C29 -> 114.69987 | E29: =SUM(E24:E28) -> 1.8391004e+08 | F29: =SUM(F24:F28) -> 1609579.9 | G29: =+H29/F29 -> 156.23238 | H29: =SUM(H24:H28) -> 2.5146851e+08 | I29: =+G29-D29 -> 41.532515

Sheet Rate Diference
S1: 2024-25 | T1: RAW MATERIAL PURCHASE | W1: FINISHED FIBC SALES | Z1: DELTA | AA1: Production | AB1: FIBC-Sales
B2: RATE DIFF SHEET – JULY-26 | J2: 2026-27 | K2: RAW MATERIAL PURCHASE | N2: FINISHED FIBC SALES | Q2: DELTA | S2: Apr.24 | T2: 456298.1 | U2: =+V2/T2 -> 117.1409 | V2: 53451171 | W2: 498791.3 | X2: =+Y2/W2 -> 158.02997 | Y2: 78823974 | Z2: =+X2-U2 -> 40.889068 | AA2: 356072 | AB2: 498791.3
B3: HPBL-IV to KPW-3 | C3: W LINER (FG) | D3: 0 | J3: Month | K3: QTY | L3: Rate | M3: Amount | N3: QTY | O3: Rate | P3: Amount | Q3: Conversion | S3: May.24 | T3: 434014.46 | U3: =+V3/T3 -> 117.83357 | V3: 51141473 | W3: 469980.3 | X3: =+Y3/W3 -> 160.54472 | Y3: 75452854 | Z3: =+X3-U3 -> 42.711149 | AA3: 407666 | AB3: 469980.3
C4: W/O LINER (FG) | D4: 0 | E4: =+D3+D4 -> 0 | J4: Mar.26 | K4: 499128.4 | L4: 148.6568 | M4: 74198830 | N4: 578392.7 | O4: 180.78847 | P4: 1.0456673e+08 | Q4: 32.131674 | R4: HPBL-IV | S4: June.24 | T4: 522544.44 | U4: =+V4/T4 -> 119.40562 | V4: 62394742 | W4: 418456.2 | X4: =+Y4/W4 -> 160.25586 | Y4: 67060060 | Z4: =+X4-U4 -> 40.850244 | AA4: 415459 | AB4: 418456.2
B5: PIL TO HPBL-IV | C5: FIBC BAGS | D5: 0 | J5: Apr.26 | K5: 506866.58 | L5: =+M5/K5 -> 165.44926 | M5: 83860700 | N5: 405825 | O5: =+P5/N5 -> 220.19842 | P5: 89362024 | Q5: =+O5-L5 -> 54.749163 | R5: HPBL-IV | S5: July.24 | T5: 526452.8 | U5: =+V5/T5 -> 121.73334 | V5: 64086856 | W5: =498942.6-2212 -> 496730.6 | X5: =+Y5/W5 -> 156.90634 | Y5: =77966725.42-26544 -> 77940181 | Z5: =+X5-U5 -> 35.173004 | AA5: 406477 | AB5: 498942.6
B6: OEL to HPBL-IV | C6: RM DIFF (OEL) | D6: 0 | J6: May.26 | K6: 428496.94 | L6: =+M6/K6 -> 129.78421 | M6: 55612136 | N6: 487917 | O6: =+P6/N6 -> 250.40064 | P6: 1.2217473e+08 | Q6: =+O6-L6 -> 120.61644 | R6: HPBL-IV | S6: Aug.24 | T6: 476002.36 | U6: =+V6/T6 -> 119.99106 | V6: 57116029 | W6: 456757 | X6: =+Y6/W6 -> 157.19353 | Y6: 71799243 | Z6: =+X6-U6 -> 37.202464 | AA6: 374454 | AB6: 456757
B7: KPW to HPBL-IV | C7: FG DIFF (KPW) | D7: 0 | E7: =+D6+D7+D5 -> 0 | J7: June.26 | K7: 473714.14 | L7: =+M7/K7 -> 151.75376 | M7: 71887902 | N7: 332726 | O7: =+P7/N7 -> 248.41289 | P7: 82653428 | Q7: =+O7-L7 -> 96.659134 | R7: HPBL-IV | S7: Sept.24 | T7: 565051.98 | U7: =+V7/T7 -> 117.2838 | V7: 66271444 | W7: 755511.4 | X7: =+Y7/W7 -> 167.73592 | Y7: 1.267264e+08 | Z7: =+X7-U7 -> 50.452124 | AA7: 476185 | AB7: 750187.2
C8: NET DIFF | D8: =+E4+E7 -> 0 | E8: OEL/KPW3/KPW-1 | J8: July.26 | K8: 547753.42 | L8: =+M8/K8 -> 152.92043 | M8: 83762688 | N8: 595287.7 | O8: =+P8/N8 -> 228.04789 | P8: 1.357541e+08 | Q8: =+O8-L8 -> 75.127457 | R8: HPBL-IV | S8: Oct.24 | T8: 604520.36 | U8: =+V8/T8 -> 117.82276 | V8: 71226258 | W8: 594994.1 | X8: =+Y8/W8 -> 173.88636 | Y8: 1.0346136e+08 | Z8: =+X8-U8 -> 56.063599 | AA8: 465076 | AB8: 594994.1
C9: Wastage Rate Diff. | D9: 1127835 | J9: Total/Av. | K9: =SUM(K5:K8) -> 1956831.1 | L9: =+M9/K9 -> 150.81702 | M9: =SUM(M5:M8) -> 2.9512343e+08 | N9: =SUM(N5:N8) -> 1821755.7 | O9: =+P9/N9 -> 236.00546 | P9: =SUM(P5:P8) -> 4.2994428e+08 | Q9: =+O9-L9 -> 85.18844 | R9: HPBL-IV | S9: Nov.24 | T9: 498019.1 | U9: =+V9/T9 -> 117.73229 | V9: 58632930 | W9: 599632.9 | X9: =+Y9/W9 -> 171.99244 | Y9: 1.0313232e+08 | Z9: =+X9-U9 -> 54.260143 | AA9: 463388 | AB9: 599632.9
C10: LC Pack. Wastage | D10: 0 | S10: Dec.24 | T10: 609575.11 | U10: =+V10/T10 -> 115.59297 | V10: 70462597 | W10: 546433.9 | X10: =+Y10/W10 -> 165.24191 | Y10: 90293780 | Z10: =+X10-U10 -> 49.648939 | AA10: 530455 | AB10: 546433.9
C11: Total Rate Diff. | D11: =+D8+D9+D10 -> 1127835 | E11: Rate Difference to be consider | S11: Jan.25 | T11: 564302.03 | U11: =+V11/T11 -> 117.80843 | V11: 66479538 | W11: 743253.8 | X11: =+Y11/W11 -> 165.12415 | Y11: 1.2272915e+08 | Z11: =+X11-U11 -> 47.315718 | AA11: 505763 | AB11: 743253.8
S12: Feb.25 | T12: 591945.54 | U12: =+V12/T12 -> 121.73734 | V12: 72061876 | W12: 715664.9 | X12: =+Y12/W12 -> 174.93486 | Y12: 1.2519474e+08 | Z12: =+X12-U12 -> 53.197523 | AA12: 467210 | AB12: 715664.9
S13: Mar.25 | T13: 517056.39 | U13: =+V13/T13 -> 124.09667 | V13: 64164978 | W13: 560251.9 | X13: =+Y13/W13 -> 189.87025 | Y13: 1.0637517e+08 | Z13: =+X13-U13 -> 65.773572 | AA13: 459730 | AB13: 560251.9
B14: Wastage Rate Difference Sheet-JULY-2026 | S14: TOTAL | T14: =SUM(T2:T13) -> 6365782.7 | U14: =+V14/T14 -> 118.99399 | V14: =SUM(V2:V13) -> 7.5748989e+08 | W14: =SUM(W2:W13) -> 6856458.3 | X14: =+Y14/W14 -> 167.57766 | Y14: =SUM(Y2:Y13) -> 1.1489892e+09 | Z14: =+X14-U14 -> 48.583668 | AA14: =SUM(AA2:AA13) -> 5327935 | AB14: =SUM(AB2:AB13) -> 6853346.1
S15: 2025-26 | T15: HPBL-IV
B16: WASTAGE SALE - JULY'26 | S16: Apr.25 | T16: 756969.15 | U16: =+V16/T16 -> 121.37935 | V16: 91880426 | W16: 292137.2 | X16: =+Y16/W16 -> 176.28738 | Y16: 51500101 | Z16: =+X16-U16 -> 54.908025 | AA16: 464875 | AB16: 292137.2
B17: DATE | C17: NO.1 | D17: NO.2 | E17: NO.3 | F17: NO.4 | G17: TOTAL | H17: Invoice | S17: May.25 | T17: 473583.37 | U17: =+V17/T17 -> 117.22124 | V17: 55514030 | W17: 459832 | X17: =+Y17/W17 -> 178.56896 | Y17: 82111722 | Z17: =+X17-U17 -> 61.34772 | AA17: 407546 | AB17: 459832
B18: 46060 | C18: 1198 | D18: 728 | E18: 152 | F18: 0 | G18: =+C18+D18+E18+F18 -> 2078 | H18: HPBL4/D/140 | S18: June.25 | T18: 430845.64 | U18: =+V18/T18 -> 117.47757 | V18: 50614698 | W18: 444822.5 | X18: =+Y18/W18 -> 191.32588 | Y18: 85106054 | Z18: =+X18-U18 -> 73.848308 | AA18: 410451 | AB18: 444822.5
B19: 46119 | C19: 1736 | D19: 1096 | E19: 315 | F19: 0 | G19: =+C19+D19+E19+F19 -> 3147 | H19: HPBL4/D/145 | S19: July.25 | T19: 572685.4 | U19: =+V19/T19 -> 118.07103 | V19: 67617554 | W19: 510650.3 | X19: =+Y19/W19 -> 186.37147 | Y19: 95170646 | Z19: =+X19-U19 -> 68.300441 | AA19: 533251 | AB19: 510650.3
B20: 46210 | C20: 662 | D20: 1068 | E20: 154 | F20: 0 | G20: =+C20+D20+E20+F20 -> 1884 | H20: HPBL4/D/153 | S20: Aug.25 | T20: 573966.8 | U20: =+V20/T20 -> 117.56081 | V20: 67475999 | W20: 479775.9 | X20: =+Y20/W20 -> 179.13429 | Y20: 85944313 | Z20: =+X20-U20 -> 61.57348 | AA20: 494357 | AB20: 479775.9
B21: 46333 | C21: 1086 | D21: 2078 | E21: 329 | F21: 0 | G21: =+C21+D21+E21+F21 -> 3493 | H21: HPBL4/D/160 | S21: Sept.25 | T21: 565461.8 | U21: =+V21/T21 -> 113.57263 | V21: 64220984 | W21: 690216.1 | X21: =+Y21/W21 -> 186.14542 | Y21: 1.2848057e+08 | Z21: =+X21-U21 -> 72.572792 | AA21: 522545 | AB21: 690216.1
B22: 14/07/2026 | C22: 1770 | D22: 1132 | E22: 0 | F22: 0 | G22: =+C22+D22+E22+F22 -> 2902 | H22: HPBL4/D/162 | S22: Oct.25 | T22: 571721.2 | U22: =+V22/T22 -> 112.24911 | V22: 64175198 | W22: 537984.8 | X22: =+Y22/W22 -> 178.59256 | Y22: 96080085 | Z22: =+X22-U22 -> 66.343451 | AA22: 539698 | AB22: 537984.8
B23: 15/07/2026 | C23: 969 | D23: 1160 | E23: 231 | F23: 0 | G23: =+C23+D23+E23+F23 -> 2360 | H23: HPBL4/D/166 | S23: Nov.25 | T23: 440596.55 | U23: =+V23/T23 -> 110.86507 | V23: 48846765 | W23: 477558.5 | X23: =+Y23/W23 -> 171.66995 | Y23: 81982444 | Z23: =+X23-U23 -> 60.804885 | AA23: 428097 | AB23: 477558.5
B24: 18/07/2026 | C24: 1245 | D24: 985 | E24: 30 | F24: 0 | G24: =+C24+D24+E24+F24 -> 2260 | H24: HPBL4/D/169 | S24: Dec.25 | T24: 515991.28 | U24: =+V24/T24 -> 109.27315 | V24: 56383992 | W24: 626206.1 | X24: =+Y24/W24 -> 178.13698 | Y24: 1.1155047e+08 | Z24: =+X24-U24 -> 68.863836 | AA24: 482833 | AB24: 626206.1
B25: 19/07/2026 | C25: 1081 | D25: 893 | E25: 0 | F25: 0 | G25: =+C25+D25+E25+F25 -> 1974 | H25: HPBL4/D/171 | S25: Jan.26 | T25: 579217.78 | U25: =+V25/T25 -> 110.21485 | V25: 63838403 | W25: 473359.8 | X25: =+Y25/W25 -> 177.36297 | Y25: 83956500 | Z25: =+X25-U25 -> 67.148116 | AA25: 475054 | AB25: 473359.8
B26: 21/07/2026 | C26: 1134 | D26: 1042 | E26: 250 | F26: 0 | G26: =+C26+D26+E26+F26 -> 2426 | H26: HPBL4/D/175 | S26: Feb.26 | T26: 507669.08 | U26: =+V26/T26 -> 116.50724 | V26: 59147123 | W26: 462589.4 | X26: =+Y26/W26 -> 174.85136 | Y26: 80884384 | Z26: =+X26-U26 -> 58.344116 | AA26: 404462 | AB26: 462589
B27: 26/07/2026 | C27: 3203 | D27: 2048 | E27: 0 | F27: 0 | G27: =+C27+D27+E27+F27 -> 5251 | H27: HPBL4/D/183 | S27: Mar.26 | T27: 499128.4 | U27: =+V27/T27 -> 148.6568 | V27: 74198830 | W27: 578392.7 | X27: =+Y27/W27 -> 180.78847 | Y27: 1.0456673e+08 | Z27: =+X27-U27 -> 32.131674 | AA27: 514365 | AB27: 578392.7
B28: TOTAL | C28: =SUM(C18:C27) -> 14084 | D28: =SUM(D18:D27) -> 12230 | E28: =SUM(E18:E27) -> 1461 | F28: =SUM(F18:F27) -> 0 | G28: =SUM(G18:G27) -> 27775 | S28: TOTAL | T28: =SUM(T16:T27) -> 6487836.5 | U28: =+V28/T28 -> 117.74557 | V28: =SUM(V16:V27) -> 7.63914e+08 | W28: =SUM(W16:W27) -> 6033525.3 | X28: =+Y28/W28 -> 180.21537 | Y28: =SUM(Y16:Y27) -> 1.087334e+09 | Z28: =+X28-U28 -> 62.469803 | AA28: =SUM(AA16:AA27) -> 5677534 | AB28: =SUM(AB16:AB27) -> 6033524.9
C29: 60 | D29: 45 | E29: 45 | F29: 18 | S29: 2026-27
C30: =+C28*C29 -> 845040 | D30: =+D28*D29 -> 550350 | E30: =+E28*E29 -> 65745 | F30: =+F28*F29 -> 0 | G30: =+G28*12 -> 333300 | S30: Apr.26 | T30: 506866.58 | U30: =+V30/T30 -> 165.44926 | V30: 83860700 | W30: 405825 | X30: =+Y30/W30 -> 220.19842 | Y30: 89362024 | Z30: =+X30-U30 -> 54.749163 | AA30: 416165 | AB30: 405825
G31: =+F32-G30 -> 1127835 | H31: Rate Difference To be consider | S31: May.26 | T31: 428496.94 | U31: =+V31/T31 -> 129.78421 | V31: 55612136 | W31: 487917 | X31: =+Y31/W31 -> 250.40064 | Y31: 1.2217473e+08 | Z31: =+X31-U31 -> 120.61644 | AA31: 419864 | AB31: 487917
F32: =+C30+D30+E30+F30 -> 1461135 | S32: June.26 | T32: 473714.14 | U32: =+V32/T32 -> 151.75376 | V32: 71887902 | W32: 332726 | X32: =+Y32/W32 -> 248.41289 | Y32: 82653428 | Z32: =+X32-U32 -> 96.659134 | AA32: 413289 | AB32: 332726
S33: July.26 | T33: 547753.42 | U33: =+V33/T33 -> 152.92043 | V33: 83762688 | W33: 595287.7 | X33: =+Y33/W33 -> 228.04789 | Y33: 1.357541e+08 | Z33: =+X33-U33 -> 75.127457 | AA33: 481055 | AB33: 595287.7
S34: TOTAL | T34: =SUM(T30:T33) -> 1956831.1 | U34: =+V34/T34 -> 150.81702 | V34: =SUM(V30:V33) -> 2.9512343e+08 | W34: =SUM(W30:W33) -> 1821755.7 | X34: =+Y34/W34 -> 236.00546 | Y34: =SUM(Y30:Y33) -> 4.2994428e+08 | Z34: =+X34-U34 -> 85.18844 | AA34: =SUM(AA30:AA33) -> 1730373 | AB34: =SUM(AB30:AB33) -> 1821755.7

Sheet Purchase Register
A1: Particular | B1: (All)
A3: Row Labels | B3: Sum of Quantity | C3: Sum of Amount
A4: JUMBO BAG | B4: 43346.7 | C4: 8447671.8 | D4: =+GETPIVOTDATA("Sum of Amount",$A$3,"purchase Group Name","JUMBO BAG")/GETPIVOTDATA("Sum of Quantity",$A$3,"purchase Group Name","JUMBO BAG") -> 194.88616 | H4: Raw Material | I4: Qty. | J4: Amount | K4: Rate/Kgs.
A5: LLDPE Bags | B5: 92085.96 | C5: 16914527 | D5: =+GETPIVOTDATA("Sum of Amount",$A$3,"purchase Group Name","LLDPE Bags")/GETPIVOTDATA("Sum of Quantity",$A$3,"purchase Group Name","LLDPE Bags") -> 183.68193 | E5: =+GETPIVOTDATA("Sum of Quantity",$A$3,"purchase Group Name","LLDPE Bags")+GETPIVOTDATA("Sum of Quantity",$A$3,"purchase Group Name","LLDPE Doc") -> 94528.46 | H5: LLDPE Bags | I5: =+GETPIVOTDATA("Sum of Quantity",$A$3,"purchase Group Name","LLDPE Bags") -> 92085.96 | J5: =+GETPIVOTDATA("Sum of Amount",$A$3,"purchase Group Name","LLDPE Bags") -> 16914527 | K5: =+J5/I5 -> 183.68193
A6: LLDPE Doc | B6: 2442.5 | C6: 441380 | D6: =+GETPIVOTDATA("Sum of Amount",$A$3,"purchase Group Name","LLDPE Doc")/GETPIVOTDATA("Sum of Quantity",$A$3,"purchase Group Name","LLDPE Doc") -> 180.70829 | E6: =+GETPIVOTDATA("Sum of Amount",$A$3,"purchase Group Name","LLDPE Bags")+GETPIVOTDATA("Sum of Amount",$A$3,"purchase Group Name","LLDPE Doc") -> 17355907 | F6: =+E6/E5 -> 183.60509 | H6: LLDPE Doc | I6: =+GETPIVOTDATA("Sum of Quantity",$A$3,"purchase Group Name","LLDPE Doc") -> 2442.5 | J6: =+GETPIVOTDATA("Sum of Amount",$A$3,"purchase Group Name","LLDPE Doc") -> 441380 | K6: =+J6/I6 -> 180.70829
A7: PP Filament Yarn | B7: 11028.86 | C7: 1715238.3 | D7: =+GETPIVOTDATA("Sum of Amount",$A$3,"purchase Group Name","PP Filament Yarn")/GETPIVOTDATA("Sum of Quantity",$A$3,"purchase Group Name","PP Filament Yarn") -> 155.52272 | H7: PP Filament Yarn | I7: =+GETPIVOTDATA("Sum of Quantity",$A$3,"purchase Group Name","PP Filament Yarn") -> 11028.86 | J7: =+GETPIVOTDATA("Sum of Amount",$A$3,"purchase Group Name","PP Filament Yarn") -> 1715238.3 | K7: =+J7/I7 -> 155.52272
A8: PP Laminated Woven Fabric | B8: 51178.8 | C8: 7699730.1 | D8: =+GETPIVOTDATA("Sum of Amount",$A$3,"purchase Group Name","PP Laminated Woven Fabric")/GETPIVOTDATA("Sum of Quantity",$A$3,"purchase Group Name","PP Laminated Woven Fabric") -> 150.44765 | H8: PP Laminated Woven Fabric | I8: =+GETPIVOTDATA("Sum of Quantity",$A$3,"purchase Group Name","PP Laminated Woven Fabric") -> 51178.8 | J8: =+GETPIVOTDATA("Sum of Amount",$A$3,"purchase Group Name","PP Laminated Woven Fabric") -> 7699730.1 | K8: =+J8/I8 -> 150.44765
A9: PP Webbing | B9: 50926.8 | C9: 7599377.8 | D9: =+GETPIVOTDATA("Sum of Amount",$A$3,"purchase Group Name","PP Webbing")/GETPIVOTDATA("Sum of Quantity",$A$3,"purchase Group Name","PP Webbing") -> 149.22159 | E9: =+GETPIVOTDATA("Sum of Amount",$A$3,"purchase Group Name","PP Laminated Woven Fabric")+GETPIVOTDATA("Sum of Amount",$A$3,"purchase Group Name","PP Woven Fabric") -> 55757303 | H9: PP Webbing | I9: =+GETPIVOTDATA("Sum of Quantity",$A$3,"purchase Group Name","PP Webbing") -> 50926.8 | J9: =+GETPIVOTDATA("Sum of Amount",$A$3,"purchase Group Name","PP Webbing") -> 7599377.8 | K9: =+J9/I9 -> 149.22159
A10: PP Woven Fabric | B10: 331556.3 | C10: 48057573 | D10: =+GETPIVOTDATA("Sum of Amount",$A$3,"purchase Group Name","PP Woven Fabric")/GETPIVOTDATA("Sum of Quantity",$A$3,"purchase Group Name","PP Woven Fabric") -> 144.94544 | E10: =+GETPIVOTDATA("Sum of Quantity",$A$3,"purchase Group Name","PP Laminated Woven Fabric")+GETPIVOTDATA("Sum of Quantity",$A$3,"purchase Group Name","PP Woven Fabric") -> 382735.1 | F10: =+E9/E10 -> 145.68118 | H10: PP Woven Fabric | I10: =+GETPIVOTDATA("Sum of Quantity",$A$3,"purchase Group Name","PP Woven Fabric")+GETPIVOTDATA("Sum of Quantity",$A$3,"purchase Group Name","FIBC WIP") -> 340008 | J10: =+GETPIVOTDATA("Sum of Amount",$A$3,"purchase Group Name","PP Woven Fabric")+GETPIVOTDATA("Sum of Amount",$A$3,"purchase Group Name","FIBC WIP") -> 49371709 | K10: =+J10/I10 -> 145.20749
A11: LLDPE FILM | B11: 82.5 | C11: 20726 | D11: =+GETPIVOTDATA("Sum of Amount",$A$3,"purchase Group Name","LLDPE FILM")/GETPIVOTDATA("Sum of Quantity",$A$3,"purchase Group Name","LLDPE FILM") -> 251.22424 | H11: LLDPE FILM | I11: =+GETPIVOTDATA("Sum of Quantity",$A$3,"purchase Group Name","LLDPE FILM") -> 82.5 | J11: =+GETPIVOTDATA("Sum of Amount",$A$3,"purchase Group Name","LLDPE FILM") -> 20726 | K11: =+J11/I11 -> 251.22424
A12: Thinner | B12: 5489 | C12: 622392 | D12: =+GETPIVOTDATA("Sum of Amount",$A$3,"purchase Group Name","Thinner")/GETPIVOTDATA("Sum of Quantity",$A$3,"purchase Group Name","Thinner") -> 113.38896 | H12: Total : | I12: =SUM(I5:I11) -> 547753.42 | J12: =SUM(J5:J11) -> 83762688 | K12: =+J12/I12 -> 152.92043
A13: Printing Inks | B13: 1150 | C13: 305250 | D13: =+GETPIVOTDATA("Sum of Amount",$A$3,"purchase Group Name","Printing Inks")/GETPIVOTDATA("Sum of Quantity",$A$3,"purchase Group Name","Printing Inks") -> 265.43478
A14: FIBC WIP | B14: 8451.7 | C14: 1314136.1 | D14: =+GETPIVOTDATA("Sum of Amount",$A$3,"purchase Group Name","FIBC WIP")/GETPIVOTDATA("Sum of Quantity",$A$3,"purchase Group Name","FIBC WIP") -> 155.48778 | I14: 0 | J14: FABRIC CUT PCS.
A15: Grand Total | B15: 597739.12 | C15: 93138002 | I15: =+I13+I14 -> 0
A18: RAW MATERIAL COST | B18: =+GETPIVOTDATA("Sum of Quantity",$A$3,"purchase Group Name","LLDPE Bags")+GETPIVOTDATA("Sum of Quantity",$A$3,"purchase Group Name","LLDPE Doc")+GETPIVOTDATA("Sum of Quantity",$A$3,"purchase Group Name","PP Filament Yarn")+GETPIVOTDATA("Sum of Quantity",$A$3,"purchase Group Name","PP Laminated Woven Fabric")+GETPIVOTDATA("Sum of Quantity",$A$3,"purchase Group Name","PP Webbing")+GETPIVOTDATA("Sum of Quantity",$A$3,"purchase Group Name","PP Woven Fabric")+GETPIVOTDATA("Sum of Quantity",$A$3,"purchase Group Name","LLDPE FILM") -> 539301.72 | C18: =+GETPIVOTDATA("Sum of Amount",$A$3,"purchase Group Name","LLDPE Bags")+GETPIVOTDATA("Sum of Amount",$A$3,"purchase Group Name","LLDPE Doc")+GETPIVOTDATA("Sum of Amount",$A$3,"purchase Group Name","PP Filament Yarn")+GETPIVOTDATA("Sum of Amount",$A$3,"purchase Group Name","PP Laminated Woven Fabric")+GETPIVOTDATA("Sum of Amount",$A$3,"purchase Group Name","PP Webbing")+GETPIVOTDATA("Sum of Amount",$A$3,"purchase Group Name","PP Woven Fabric")+GETPIVOTDATA("Sum of Amount",$A$3,"purchase Group Name","LLDPE FILM") -> 82448552 | D18: =+C18/B18 -> 152.88019
A19: FABRIC COST | B19: =+GETPIVOTDATA("Sum of Quantity",$A$3,"purchase Group Name","PP Woven Fabric")+GETPIVOTDATA("Sum of Quantity",$A$3,"purchase Group Name","PP Laminated Woven Fabric") -> 382735.1 | C19: =+GETPIVOTDATA("Sum of Amount",$A$3,"purchase Group Name","PP Woven Fabric")+GETPIVOTDATA("Sum of Amount",$A$3,"purchase Group Name","PP Laminated Woven Fabric") -> 55757303 | D19: =+C19/B19 -> 145.68118
A22: Purchase value reco with Trail Balance Value
A23: Row Labels | B23: Sum of Amount | C23: AS PER T/B | D23: DIFFERENCE | H23: Date | I23: Particular | J23: Voucher Type | K23: Voucher No | L23: Type | M23: Invoice No | N23: Invoice Date | O23: Main Grp | P23: Group Name | Q23: Sub Grup | R23: purchase Group Name | S23: Item Name | T23: Quantity | U23: Amount | V23: Item Desc | W23: Bill Amount | X23: CGST Rate | Y23: CGST Amt | Z23: SGST Rate | AA23: SGST Amt | AB23: IGST Rate | AC23: IGST Amt | AD23: Freight GST | AE23: Total GST | AF23: TCS | AG23: GST-IN | AH23: Unit | AI23: HSN Code | AJ23: Currencty | AK23: Exc.Rate | AL23: Net Wt | AM23: Country
A24: Branch Transfer In - Raw Material | B24: 737284.43 | C24: =+'Trail Balance-JULY26'!C68 -> 737284.43 | D24: =+GETPIVOTDATA("Amount",$A$23,"Type","Branch Transfer In - Raw Material")-C24 -> 0 | H24: 46029 | I24: Plastene India ltd - Unit 1-Purchase | J24: General Purchase | K24: GNCN 234 | L24: Purchase Withinstate- Stores, Spares & Consumable | M24: PIL1/D/875 | N24: 46029 | O24: Stores/Spares | P24: MS Structure Items | Q24: Spares & Stores | R24: Stores & Consumables | S24: MS Pipe 4 C Class | T24: 354 | U24: 16992 | V24: MS Pipe 4 C Class | W24: 20033.57 | X24: 9 | Y24: 1529.28 | Z24: 9 | AA24: 1529.28 | AB24: 0 | AC24: 0 | AD24: 0 | AE24: 3058.56 | AF24: 0 | AG24: 24AAACO3087C1ZT | AH24: Kgs | AI24: 73063090 | AJ24: Rs. | AK24: 1 | AL24: 0 | AM24: India
A25: Purchase Withinstate - Raw Material | B25: 89309381 | C25: =+'Trail Balance-JULY26'!C72 -> 89309381 | D25: =+GETPIVOTDATA("Amount",$A$23,"Type","Purchase Withinstate - Raw Material")-C25 -> 0 | H25: 46029 | I25: Plastene India ltd - Unit 1-Purchase | J25: R.M.P. | K25: RM 324 | L25: Purchase Withinstate - Raw Material | M25: PIL1/D/874 | N25: 46029 | O25: SF | P25: PP/PE Fabric | Q25: PP Lam Fabric | R25: PP Laminated Woven Fabric | S25: PP Lam Fabric With UV | T25: 289 | U25: 44719.86 | V25: PP Lam Fabric With UV | W25: 1727090.3 | X25: 9 | Y25: 4024.79 | Z25: 9 | AA25: 4024.79 | AB25: 0 | AC25: 0 | AD25: 0 | AE25: 8049.58 | AF25: 0 | AG25: 24AAACO3087C1ZT | AH25: Kgs | AI25: 63053300 | AJ25: Rs. | AK25: 1 | AL25: 289 | AM25: India
A26: Purchase Withinstate - Traded Goods | B26: 2224616.5 | C26: =+'Trail Balance-JULY26'!C76 -> 2224616.5 | D26: =+GETPIVOTDATA("Amount",$A$23,"Type","Purchase Withinstate - Traded Goods")-C26 -> 0 | H26: 46029 | I26: Plastene India ltd - Unit 1-Purchase | J26: R.M.P. | K26: RM 324 | L26: Purchase Withinstate - Raw Material | M26: PIL1/D/874 | N26: 46029 | O26: SF | P26: PP/PE Fabric | Q26: PP UL Fabric | R26: PP Woven Fabric | S26: PP UL Fabric With UV | T26: 2836 | U26: 424662.64 | V26: PP UL Fabric With UV | W26: 0 | X26: 9 | Y26: 38219.64 | Z26: 9 | AA26: 38219.64 | AB26: 0 | AC26: 0 | AD26: 0 | AE26: 76439.28 | AF26: 0 | AG26: 24AAACO3087C1ZT | AH26: Kgs | AI26: 39269080 | AJ26: Rs. | AK26: 1 | AL26: 2836 | AM26: India
A27: Purchase Interstate - Raw Material | B27: 849175 | C27: =+'Trail Balance-JULY26'!C71 -> 849175 | D27: =+GETPIVOTDATA("Amount",$A$23,"Type","Purchase Interstate - Raw Material")-C27 -> 0 | H27: 46029 | I27: Plastene India ltd - Unit 1-Purchase | J27: R.M.P. | K27: RM 324 | L27: Purchase Withinstate - Raw Material | M27: PIL1/D/874 | N27: 46029 | O27: SF | P27: PP/PE Fabric | Q27: PP UL Fabric | R27: PP Woven Fabric | S27: PP UL Fabric With UV | T27: 6027 | U27: 890428.98 | V27: PP UL Fabric With UV | W27: 0 | X27: 9 | Y27: 80138.61 | Z27: 9 | AA27: 80138.61 | AB27: 0 | AC27: 0 | AD27: 0 | AE27: 160277.22 | AF27: 0 | AG27: 24AAACO3087C1ZT | AH27: Kgs | AI27: 39269080 | AJ27: Rs. | AK27: 1 | AL27: 6027 | AM27: India
A28: Branch Transfer In - Trading | B28: 394723.71 | C28: =+'Trail Balance-JULY26'!C69 -> 394723.71 | D28: =+GETPIVOTDATA("Amount",$A$23,"Type","Branch Transfer In - Trading")-C28 -> 0 | H28: 46029 | I28: Plastene India ltd - Unit 1-Purchase | J28: R.M.P. | K28: RM 324 | L28: Purchase Withinstate - Raw Material | M28: PIL1/D/874 | N28: 46029 | O28: SF | P28: PP/PE Fabric | Q28: PP UL Fabric | R28: PP Woven Fabric | S28: PP UL Fabric With UV | T28: 697 | U28: 105065.78 | V28: PP UL Fabric With UV | W28: 0 | X28: 9 | Y28: 9455.92 | Z28: 9 | AA28: 9455.92 | AB28: 0 | AC28: 0 | AD28: 0 | AE28: 18911.84 | AF28: 0 | AG28: 24AAACO3087C1ZT | AH28: Kgs | AI28: 39269080 | AJ28: Rs. | AK28: 1 | AL28: 697 | AM28: India
A29: Grand Total | B29: 93515181 | H29: 46029 | I29: Plastene India ltd - Unit 1-Purchase | J29: R.M.P. | K29: RM 325 | L29: Purchase Withinstate - Raw Material | M29: PIL1/D/876 | N29: 46029 | O29: SF | P29: Liners | Q29: LDPE/LLDPE Bags | R29: LLDPE Bags | S29: LDPE/LLDPE Bags/Liner | T29: 3917 | U29: 709564.55 | V29: LDPE/LLDPE Bags/Liner | W29: 1322447.8 | X29: 9 | Y29: 63860.81 | Z29: 9 | AA29: 63860.81 | AB29: 0 | AC29: 0 | AD29: 0 | AE29: 127721.62 | AF29: 0 | AG29: 24AAACO3087C1ZT | AH29: Kgs | AI29: 39200000 | AJ29: Rs. | AK29: 1 | AL29: 3917 | AM29: India
H30: 46029 | I30: Plastene India ltd - Unit 1-Purchase | J30: R.M.P. | K30: RM 325 | L30: Purchase Withinstate - Raw Material | M30: PIL1/D/876 | N30: 46029 | O30: SF | P30: PP/PE Fabric | Q30: PP Lam Fabric | R30: PP Laminated Woven Fabric | S30: PP Lam Fabric With UV | T30: 571 | U30: 88356.54 | V30: PP Lam Fabric With UV | W30: 0 | X30: 9 | Y30: 7952.09 | Z30: 9 | AA30: 7952.09 | AB30: 0 | AC30: 0 | AD30: 0 | AE30: 15904.18 | AF30: 0 | AG30: 24AAACO3087C1ZT | AH30: Kgs | AI30: 63053300 | AJ30: Rs. | AK30: 1 | AL30: 571 | AM30: India
H31: 46029 | I31: Plastene India ltd - Unit 1-Purchase | J31: R.M.P. | K31: RM 325 | L31: Purchase Withinstate - Raw Material | M31: PIL1/D/876 | N31: 46029 | O31: SF | P31: PP/PE Fabric | Q31: PP Lam Fabric | R31: PP Laminated Woven Fabric | S31: PP Lam Fabric With UV | T31: 400 | U31: 61896 | V31: PP Lam Fabric With UV | W31: 0 | X31: 9 | Y31: 5570.64 | Z31: 9 | AA31: 5570.64 | AB31: 0 | AC31: 0 | AD31: 0 | AE31: 11141.28 | AF31: 0 | AG31: 24AAACO3087C1ZT | AH31: Kgs | AI31: 63053300 | AJ31: Rs. | AK31: 1 | AL31: 400 | AM31: India
H32: 46029 | I32: Plastene India ltd - Unit 1-Purchase | J32: R.M.P. | K32: RM 325 | L32: Purchase Withinstate - Raw Material | M32: PIL1/D/876 | N32: 46029 | O32: SF | P32: Webbing | Q32: PP Webbing | R32: PP Webbing | S32: Webbing | T32: 236.8 | U32: 35458.43 | V32: Webbing | W32: 0 | X32: 9 | Y32: 3191.26 | Z32: 9 | AA32: 3191.26 | AB32: 0 | AC32: 0 | AD32: 0 | AE32: 6382.52 | AF32: 0 | AG32: 24AAACO3087C1ZT | AH32: Kgs | AI32: 3926908 | AJ32: Rs. | AK32: 1 | AL32: 236.8 | AM32: India
H33: 46029 | I33: Plastene India ltd - Unit 1-Purchase | J33: R.M.P. | K33: RM 325 | L33: Purchase Withinstate - Raw Material | M33: PIL1/D/876 | N33: 46029 | O33: SF | P33: Webbing | Q33: PP Webbing | R33: PP Webbing | S33: Webbing | T33: 1091.9 | U33: 166776.81 | V33: Webbing | W33: 0 | X33: 9 | Y33: 15009.91 | Z33: 9 | AA33: 15009.91 | AB33: 0 | AC33: 0 | AD33: 0 | AE33: 30019.82 | AF33: 0 | AG33: 24AAACO3087C1ZT | AH33: Kgs | AI33: 3926908 | AJ33: Rs. | AK33: 1 | AL33: 1091.9 | AM33: India
H34: 46029 | I34: Plastene India ltd - Unit 1-Purchase | J34: R.M.P. | K34: RM 325 | L34: Purchase Withinstate - Raw Material | M34: PIL1/D/876 | N34: 46029 | O34: SF | P34: Webbing | Q34: PP Webbing | R34: PP Webbing | S34: Webbing | T34: 9.8 | U34: 1702.65 | V34: Webbing | W34: 0 | X34: 9 | Y34: 153.24 | Z34: 9 | AA34: 153.24 | AB34: 0 | AC34: 0 | AD34: 0 | AE34: 306.48 | AF34: 0 | AG34: 24AAACO3087C1ZT | AH34: Kgs | AI34: 3926908 | AJ34: Rs. | AK34: 1 | AL34: 9.8 | AM34: India
H35: 46029 | I35: Plastene India ltd - Unit 1-Purchase | J35: R.M.P. | K35: RM 325 | L35: Purchase Withinstate - Raw Material | M35: PIL1/D/876 | N35: 46029 | O35: SF | P35: PP/PE Fabric | Q35: PP UL Fabric | R35: PP Woven Fabric | S35: PP UL Fabric With UV | T35: 392 | U35: 57914.08 | V35: PP UL Fabric With UV | W35: 0 | X35: 9 | Y35: 5212.27 | Z35: 9 | AA35: 5212.27 | AB35: 0 | AC35: 0 | AD35: 0 | AE35: 10424.54 | AF35: 0 | AG35: 24AAACO3087C1ZT | AH35: Kgs | AI35: 39269080 | AJ35: Rs. | AK35: 1 | AL35: 392 | AM35: India
H36: 46060 | I36: Plastene India ltd - Unit 1-Purchase | J36: General Purchase | K36: GNCN 235 | L36: Purchase Withinstate- Stores, Spares & Consumable | M36: PIL1/D/887 | N36: 46060 | O36: Stores/Spares | P36: MS Structure Items | Q36: Spares & Stores | R36: Stores & Consumables | S36: MS Pipe 4 C Class | T36: 194 | U36: 9312 | V36: MS Pipe 4 C Class | W36: 10978.85 | X36: 9 | Y36: 838.08 | Z36: 9 | AA36: 838.08 | AB36: 0 | AC36: 0 | AD36: 0 | AE36: 1676.16 | AF36: 0 | AG36: 24AAACO3087C1ZT | AH36: Kgs | AI36: 73063090 | AJ36: Rs. | AK36: 1 | AL36: 0 | AM36: India
H37: 46060 | I37: Plastene India ltd - Unit 1-Purchase | J37: R.M.P. | K37: RM 326 | L37: Purchase Withinstate - Raw Material | M37: PIL1/D/877 | N37: 46029 | O37: SF | P37: PP/PE Fabric | Q37: PP UL Fabric | R37: PP Woven Fabric | S37: PP UL Fabric With UV | T37: 491 | U37: 73522.34 | V37: PP UL Fabric With UV | W37: 355449.38 | X37: 9 | Y37: 6617.01 | Z37: 9 | AA37: 6617.01 | AB37: 0 | AC37: 0 | AD37: 0 | AE37: 13234.02 | AF37: 0 | AG37: 24AAACO3087C1ZT | AH37: Kgs | AI37: 39269080 | AJ37: Rs. | AK37: 1 | AL37: 491 | AM37: India
H38: 46060 | I38: Plastene India ltd - Unit 1-Purchase | J38: R.M.P. | K38: RM 326 | L38: Purchase Withinstate - Raw Material | M38: PIL1/D/877 | N38: 46029 | O38: FG | P38: FIBC WIP | Q38: FIBC WIP | R38: FIBC WIP | S38: PP Woven Fabric | T38: 500 | U38: 78870 | V38: FIBC WIP | W38: 0 | X38: 9 | Y38: 7098.3 | Z38: 9 | AA38: 7098.3 | AB38: 0 | AC38: 0 | AD38: 0 | AE38: 14196.6 | AF38: 0 | AG38: 24AAACO3087C1ZT | AH38: Kgs | AI38: 39269080 | AJ38: Rs. | AK38: 1 | AL38: 500 | AM38: India
H39: 46060 | I39: Plastene India ltd - Unit 1-Purchase | J39: R.M.P. | K39: RM 326 | L39: Purchase Withinstate - Raw Material | M39: PIL1/D/877 | N39: 46029 | O39: FG | P39: FIBC WIP | Q39: FIBC WIP | R39: FIBC WIP | S39: PP Woven Fabric | T39: 594 | U39: 94885.56 | V39: FIBC WIP | W39: 0 | X39: 9 | Y39: 8539.7 | Z39: 9 | AA39: 8539.7 | AB39: 0 | AC39: 0 | AD39: 0 | AE39: 17079.4 | AF39: 0 | AG39: 24AAACO3087C1ZT | AH39: Kgs | AI39: 39269080 | AJ39: Rs. | AK39: 1 | AL39: 594 | AM39: India
H40: 46060 | I40: Plastene India ltd - Unit 1-Purchase | J40: R.M.P. | K40: RM 326 | L40: Purchase Withinstate - Raw Material | M40: PIL1/D/877 | N40: 46029 | O40: SF | P40: PP/PE Fabric | Q40: PP Lam Fabric | R40: PP Laminated Woven Fabric | S40: PP Lam Fabric With UV | T40: 362 | U40: 54205.88 | V40: PP Lam Fabric With UV | W40: 0 | X40: 9 | Y40: 4878.53 | Z40: 9 | AA40: 4878.53 | AB40: 0 | AC40: 0 | AD40: 0 | AE40: 9757.06 | AF40: 0 | AG40: 24AAACO3087C1ZT | AH40: Kgs | AI40: 63053300 | AJ40: Rs. | AK40: 1 | AL40: 362 | AM40: India
H41: 46060 | I41: Plastene India ltd - Unit 1-Purchase | J41: R.M.P. | K41: RM 327 | L41: Purchase Withinstate - Raw Material | M41: PIL1/D/884 | N41: 46060 | O41: SF | P41: Liners | Q41: LDPE/LLDPE Bags | R41: LLDPE Bags | S41: LDPE/LLDPE Bags/Liner | T41: 435 | U41: 78800.25 | V41: LDPE/LLDPE Bags/Liner | W41: 1680961 | X41: 9 | Y41: 7092.02 | Z41: 9 | AA41: 7092.02 | AB41: 0 | AC41: 0 | AD41: 0 | AE41: 14184.04 | AF41: 0 | AG41: 24AAACO3087C1ZT | AH41: Kgs | AI41: 39200000 | AJ41: Rs. | AK41: 1 | AL41: 435 | AM41: India
... H54: 46060 | I54: Plastene Polyfilms Ltd-Purchase | J54: R.M.P. | K54: RM 329 | L54: Purchase Withinstate - Raw Material | M54: PPL/D/303 | N54: 46060 | O54: SF | P54: Liners | Q54: LDPE/LLDPE Bags | R54: LLDPE Bags | S54: LDPE/LLDPE Bags/Liner | T54: 60 | U54: 11580 | V54: LDPE/LLDPE Bags/Liner | W54: 13652.82 | X54: 9 | Y54: 1042.2 | Z54: 9 | AA54: 1042.2 | AB54: 0 | AC54: 0 | AD54: 0 | AE54: 2084.4 | AF54: 0 | AG54: 24AAFCP2956A1ZR | AH54: Kgs | AI54: 39200000 | AJ54: Rs. | AK54: 1 | AL54: 60 | AM54: India
H55: 46088 | I55: Accurate Rub Tech | J55: General Purchase | K55: GNSP 110 | L55: Purchase Withinstate- Stores, Spares & Consumable | M55: 240 | N55: 26-06-2026 | O55: Stores/Spares | P55: Lamination Plant Spares | Q55: Spares & Stores | R55: Stores & Consumables | S55: Coating Steel Roller | T55: 2 | U55: 26200 | V55: Coating Steel Roller | W55: 30916 | X55: 9 | Y55: 2358 | Z55: 9 | AA55: 2358 | AB55: 0 | AC55: 0 | AD55: 0 | AE55: 4716 | AF55: 0 | AG55: 24ABNFA9143N1ZY | AH55: Pcs | AI55: 84779000 | AJ55: Rs. | AK55: 1 | AL55: 0 | AM55: India
H56: 46088 | I56: Chandan Electric Store | J56: General Purchase | K56: GNSP 108 | L56: Purchase Withinstate- Stores, Spares & Consumable | M56: CES/26-27/776 | N56: 30-06-2026 | O56: Stores/Spares | P56: PVC Fittings | Q56: Spares & Stores | R56: Stores & Consumables | S56: Pvc Flexible Pipe 25 mm | T56: 200 | U56: 2400 | V56: Pvc Flexible Pipe 25 mm | W56: 2832 | X56: 9 | Y56: 216 | Z56: 9 | AA56: 216 | AB56: 0 | AC56: 0 | AD56: 0 | AE56: 432 | AF56: 0 | AG56: 24AAIPH7590J1ZE | AH56: MTR | AI56: 391731 | AJ56: Rs. | AK56: 1 | AL56: 0 | AM56: India
H57: 46088 | I57: Chandan Electric Store | J57: General Purchase | K57: GNSP 109 | L57: Purchase Withinstate- Stores, Spares & Consumable | M57: CES/26-27/777 | N57: 30-06-2026 | O57: Stores/Spares | P57: Capacitors | Q57: Spares & Stores | R57: Stores & Consumables | S57: Capacitor 2.5 Mfd | T57: 70 | U57: 1680 | V57: Capacitor 2.5 Mfd | W57: 1982 | X57: 9 | Y57: 151.2 | Z57: 9 | AA57: 151.2 | AB57: 0 | AC57: 0 | AD57: 0 | AE57: 302.4 | AF57: 0 | AG57: 24AAIPH7590J1ZE | AH57: PCS | AI57: 85322500 | AJ57: Rs. | AK57: 1 | AL57: 0 | AM57: India
H58: 46088 | I58: Plastene India ltd - Unit 1-Purchase | J58: General Purchase | K58: GNCN 236 | L58: Purchase Withinstate- Stores, Spares & Consumable | M58: PIL1/D/895 | N58: 46088 | O58: Stores/Spares | P58: MS Structure Items | Q58: Spares & Stores | R58: Stores & Consumables | S58: MS Pipe 4 C Class | T58: 205 | U58: 9840 | V58: MS Pipe 4 C Class | W58: 11601.36 | X58: 9 | Y58: 885.6 | Z58: 9 | AA58: 885.6 | AB58: 0 | AC58: 0 | AD58: 0 | AE58: 1771.2 | AF58: 0 | AG58: 24AAACO3087C1ZT | AH58: Kgs | AI58: 73063090 | AJ58: Rs. | AK58: 1 | AL58: 0 | AM58: India
H59: 46088 | I59: Plastene India ltd - Unit 1-Purchase | J59: R.M.P. | K59: RM 331 | L59: Purchase Withinstate - Raw Material | M59: PIL1/D/893 | N59: 46088 | O59: SF | P59: PP/PE Fabric | Q59: PP UL Fabric | R59: PP Woven Fabric | S59: PP UL Fabric With UV | T59: 554 | U59: 83509.96 | V59: PP UL Fabric With UV | W59: 1308699.1 | X59: 9 | Y59: 7515.9 | Z59: 9 | AA59: 7515.9 | AB59: 0 | AC59: 0 | AD59: 0 | AE59: 15031.8 | AF59: 0 | AG59: 24AAACO3087C1ZT | AH59: Kgs | AI59: 39269080 | AJ59: Rs. | AK59: 1 | AL59: 554 | AM59: India
H60: 46088 | I60: Plastene India ltd - Unit 1-Purchase | J60: R.M.P. | K60: RM 331 | L60: Purchase Withinstate - Raw Material | M60: PIL1/D/893 | N60: 46088 | O60: SF | P60: PP/PE Fabric | Q60: PP UL Fabric | R60: PP Woven Fabric | S60: PP UL Fabric With UV | T60: 3472 | U60: 519897.28 | V60: PP UL Fabric With UV | W60: 0 | X60: 9 | Y60: 46790.76 | Z60: 9 | AA60: 46790.76 | AB60: 0 | AC60: 0 | AD60: 0 | AE60: 93581.52 | AF60: 0 | AG60: 24AAACO3087C1ZT | AH60: Kgs | AI60: 39269080 | AJ60: Rs. | AK60: 1 | AL60: 3472 | AM60: India
H61: 46088 | I61: Plastene India ltd - Unit 1-Purchase | J61: R.M.P. | K61: RM 331 | L61: Purchase Withinstate - Raw Material | M61: PIL1/D/893 | N61: 46088 | O61: SF | P61: PP/PE Fabric | Q61: PP UL Fabric | R61: PP Woven Fabric | S61: PP UL Fabric With UV | T61: 3429 | U61: 506600.46 | V61: PP UL Fabric With UV | W61: 0 | X61: 9 | Y61: 45594.04 | Z61: 9 | AA61: 45594.04 | AB61: 0 | AC61: 0 | AD61: 0 | AE61: 91188.08 | AF61: 0 | AG61: 24AAACO3087C1ZT | AH61: Kgs | AI61: 39269080 | AJ61: Rs. | AK61: 1 | AL61: 3429 | AM61: India
H62: 46088 | I62: Plastene India ltd - Unit 1-Purchase | J62: R.M.P. | K62: RM 332 | L62: Purchase Withinstate - Raw Material | M62: PIL1/D/896 | N62: 46088 | O62: SF | P62: Liners | Q62: LDPE/LLDPE Bags | R62: LLDPE Bags | S62: LDPE/LLDPE Bags/Liner | T62: 3398 | U62: 615547.7 | V62: LDPE/LLDPE Bags/Liner | W62: 1694395.9 | X62: 9 | Y62: 55399.29 | Z62: 9 | AA62: 55399.29 | AB62: 0 | AC62: 0 | AD62: 0 | AE62: 110798.58 | AF62: 0 | AG62: 24AAACO3087C1ZT | AH62: Kgs | AI62: 39200000 | AJ62: Rs. | AK62: 1 | AL62: 3398 | AM62: India
H63: 46088 | I63: Plastene India ltd - Unit 1-Purchase | J63: R.M.P. | K63: RM 332 | L63: Purchase Withinstate - Raw Material | M63: PIL1/D/896 | N63: 46088 | O63: SF | P63: Liners | Q63: LDPE/LLDPE Bags | R63: LLDPE Bags | S63: LDPE/LLDPE Bags/Liner | T63: 1730 | U63: 320309.5 | V63: LDPE/LLDPE Bags/Liner | W63: 0 | X63: 9 | Y63: 28827.86 | Z63: 9 | AA63: 28827.86 | AB63: 0 | AC63: 0 | AD63: 0 | AE63: 57655.72 | AF63: 0 | AG63: 24AAACO3087C1ZT | AH63: Kgs | AI63: 39200000 | AJ63: Rs. | AK63: 1 | AL63: 1730 | AM63: India
H64: 46088 | I64: Plastene India ltd - Unit 1-Purchase | J64: R.M.P. | K64: RM 332 | L64: Purchase Withinstate - Raw Material | M64: PIL1/D/896 | N64: 46088 | O64: SF | P64: PP/PE Fabric | Q64: PP UL Fabric | R64: PP Woven Fabric | S64: PP UL Fabric With UV | T64: 1648 | U64: 243475.52 | V64: PP UL Fabric With UV | W64: 0 | X64: 9 | Y64: 21912.8 | Z64: 9 | AA64: 21912.8 | AB64: 0 | AC64: 0 | AD64: 0 | AE64: 43825.6 | AF64: 0 | AG64: 24AAACO3087C1ZT | AH64: Kgs | AI64: 39269080 | AJ64: Rs. | AK64: 1 | AL64: 1648 | AM64: India
H65: 46088 | I65: Plastene India ltd - Unit 1-Purchase | J65: R.M.P. | K65: RM 332 | L65: Purchase Withinstate - Raw Material | M65: PIL1/D/896 | N65: 46088 | O65: SF | P65: Webbing | Q65: PP Webbing | R65: PP Webbing | S65: Webbing | T65: 192.1 | U65: 28765.05 | V65: Webbing | W65: 0 | X65: 9 | Y65: 2588.85 | Z65: 9 | AA65: 2588.85 | AB65: 0 | AC65: 0 | AD65: 0 | AE65: 5177.7 | AF65: 0 | AG65: 24AAACO3087C1ZT | AH65: Kgs | AI65: 3926908 | AJ65: Rs. | AK65: 1 | AL65: 192.1 | AM65: India
H66: 46088 | I66: Plastene India ltd - Unit 1-Purchase | J66: R.M.P. | K66: RM 332 | L66: Purchase Withinstate - Raw Material | M66: PIL1/D/896 | N66: 46088 | O66: SF | P66: Webbing | Q66: PP Webbing | R66: PP Webbing | S66: Webbing | T66: 1499.6 | U66: 229048.9 | V66: Webbing | W66: 0 | X66: 9 | Y66: 20614.4 | Z66: 9 | AA66: 20614.4 | AB66: 0 | AC66: 0 | AD66: 0 | AE66: 41228.8 | AF66: 0 | AG66: 24AAACO3087C1ZT | AH66: Kgs | AI66: 3926908 | AJ66: Rs. | AK66: 1 | AL66: 1499.6 | AM66: India
H67: 46088 | I67: Plastene Polyfilms Ltd-Purchase | J67: R.M.P. | K67: RM 330 | L67: Purchase Withinstate - Raw Material | M67: PPL/D/304 | N67: 46088 | O67: SF | P67: Films All (SF) | Q67: PE Film | R67: LLDPE FILM | S67: LDPE/LLDPE Film | T67: 44.5 | U67: 11036 | V67: LDPE/LLDPE Film | W67: 13011.44 | X67: 9 | Y67: 993.24 | Z67: 9 | AA67: 993.24 | AB67: 0 | AC67: 0 | AD67: 0 | AE67: 1986.48 | AF67: 0 | AG67: 24AAFCP2956A1ZR | AH67: Kgs | AI67: 3920101 | AJ67: Rs. | AK67: 1 | AL67: 44.5 | AM67: India
H68: 46119 | I68: Plastene India ltd - Unit 1-Purchase | J68: R.M.P. | K68: RM 333 | L68: Purchase Withinstate - Raw Material | M68: PIL1/D/907 | N68: 46119 | O68: SF | P68: Liners | Q68: LDPE/LLDPE Bags | R68: LLDPE Bags | S68: LDPE/LLDPE Bags/Liner | T68: 6269 | U68: 1135629.4 | V68: LDPE/LLDPE Bags/Liner | W68: 1486254 | X68: 9 | Y68: 102206.64 | Z68: 9 | AA68: 102206.64 | AB68: 0 | AC68: 0 | AD68: 0 | AE68: 204413.28 | AF68: 0 | AG68: 24AAACO3087C1ZT | AH68: Kgs | AI68: 39200000 | AJ68: Rs. | AK68: 1 | AL68: 0 | AM68: India
H69: 46119 | I69: Plastene India ltd - Unit 1-Purchase | J69: R.M.P. | K69: RM 333 | L69: Purchase Withinstate - Raw Material | M69: PIL1/D/907 | N69: 46119 | O69: SF | P69: Liners | Q69: LDPE/LLDPE Bags | R69: LLDPE Bags | S69: LDPE/LLDPE Bags/Liner | T69: 675 | U69: 124976.25 | V69: LDPE/LLDPE Bags/Liner | W69: 0 | X69: 9 | Y69: 11247.86 | Z69: 9 | AA69: 11247.86 | AB69: 0 | AC69: 0 | AD69: 0 | AE69: 22495.72 | AF69: 0 | AG69: 24AAACO3087C1ZT | AH69: Kgs | AI69: 39200000 | AJ69: Rs. | AK69: 1 | AL69: 0 | AM69: India
... H82: 46119 | I82: Plastene Polyfilms Ltd-Purchase | J82: R.M.P. | K82: RM 334 | L82: Purchase Withinstate - Raw Material | M82: PPL/D/309 | N82: 46119 | O82: FG | P82: FIBC WIP | Q82: FIBC WIP | R82: FIBC WIP | S82: PP Woven Fabric | T82: 560 | U82: 83669.6 | V82: FIBC WIP | W82: 98646.45 | X82: 9 | Y82: 7530.26 | Z82: 9 | AA82: 7530.26 | AB82: 0 | AC82: 0 | AD82: 0 | AE82: 15060.52 | AF82: 0 | AG82: 24AAFCP2956A1ZR | AH82: Kgs | AI82: 39269080 | AJ82: Rs. | AK82: 1 | AL82: 0 | AM82: India
H83: 46119 | I83: Plus Logistics Ltd. | J83: General Purchase | K83: GNCN 237 | L83: Purchase Withinstate- Stores, Spares & Consumable | M83: SLZ/0035/26-27 | N83: 30-06-2026 | O83: RM Consumables | P83: FIBC Accessories | Q83: FIBC Accessories | R83: Stores & Consumables | S83: Zipper Bags | T83: 3500 | U83: 7350 | V83: Zipper Bags | W83: 8673 | X83: 0 | Y83: 0 | Z83: 0 | AA83: 0 | AB83: 18 | AC83: 1323 | AD83: 0 | AE83: 1323 | AF83: 0 | AG83: 23AAECS3438H1ZI | AH83: Pcs | AI83: 39239090 | AJ83: Rs. | AK83: 1 | AL83: 3500 | AM83: India
H84: 46149 | I84: HCP Plastene Bulkpack Limited - Purchase | J84: Branch Transfer In | K84: RM 341 | L84: Branch Transfer In - Raw Material | M84: HPBL/DC/15 | N84: 46088 | O84: SF | P84: Liners | Q84: LDPE/LLDPE Bags | R84: LLDPE Doc | S84: DOC Pouch | T84: 407 | U84: 78546.93 | V84: DOC Pouch | W84: 78546.93 | X84: 0 | Y84: 0 | Z84: 0 | AA84: 0 | AB84: 0 | AC84: 0 | AD84: 0 | AE84: 0 | AF84: 0 | AG84: 24AABCG1282C2Z6 | AH84: Kgs | AI84: 39232100 | AJ84: Rs. | AK84: 1 | AL84: 0 | AM84: India
H85: 46149 | I85: K.P. Woven Pvt Ltd-Purchase | J85: R.M.P. | K85: RM 340 | L85: Purchase Withinstate - Raw Material | M85: KPV/D/404 | N85: 46119 | O85: SF | P85: Yarn All | Q85: PP Yarn | R85: PP Filament Yarn | S85: PP Fibrillated Tape Twisted 3200 Blue | T85: 1340 | U85: 206561 | V85: PP Fibrillated Tape Twisted 3200 Blue | W85: 297546.21 | X85: 2.5 | Y85: 5164.02 | Z85: 2.5 | AA85: 5164.02 | AB85: 0 | AC85: 0 | AD85: 0 | AE85: 10328.04 | AF85: 0 | AG85: 24AAECK6307M1ZF | AH85: Kgs | AI85: 54026930 | AJ85: Rs. | AK85: 1 | AL85: 0 | AM85: India
H86: 46149 | I86: K.P. Woven Pvt Ltd-Purchase | J86: R.M.P. | K86: RM 340 | L86: Purchase Withinstate - Raw Material | M86: KPV/D/404 | N86: 46119 | O86: SF | P86: Yarn All | Q86: PP Yarn | R86: PP Filament Yarn | S86: PP Fibrillated Tape Twisted 3200 MW | T86: 510 | U86: 77086.5 | V86: PP Fibrillated Tape Twisted 3200 MW | W86: 0 | X86: 2.5 | Y86: 1927.16 | Z86: 2.5 | AA86: 1927.16 | AB86: 0 | AC86: 0 | AD86: 0 | AE86: 3854.32 | AF86: 0 | AG86: 24AAECK6307M1ZF | AH86: Kgs | AI86: 54026930 | AJ86: Rs. | AK86: 1 | AL86: 0 | AM86: India
H87: 46149 | I87: Plastene India ltd - Unit 1-Purchase | J87: General Purchase | K87: GNCN 238 | L87: Purchase Withinstate- Stores, Spares & Consumable | M87: PIL1/D/919 | N87: 46149 | O87: Stores/Spares | P87: MS Structure Items | Q87: Spares & Stores | R87: Stores & Consumables | S87: MS Pipe 4 C Class | T87: 349 | U87: 16752 | V87: MS Pipe 4 C Class | W87: 19750.61 | X87: 9 | Y87: 1507.68 | Z87: 9 | AA87: 1507.68 | AB87: 0 | AC87: 0 | AD87: 0 | AE87: 3015.36 | AF87: 0 | AG87: 24AAACO3087C1ZT | AH87: Kgs | AI87: 73063090 | AJ87: Rs. | AK87: 1 | AL87: 0 | AM87: India
H88: 46149 | I88: Plastene India ltd - Unit 1-Purchase | J88: R.M.P. | K88: RM 338 | L88: Purchase Withinstate - Raw Material | M88: PIL1/D/908 | N88: 46119 | O88: SF | P88: PP/PE Fabric | Q88: PP UL Fabric | R88: PP Woven Fabric | S88: PP UL Fabric With UV | T88: 601 | U88: 89993.74 | V88: PP UL Fabric With UV | W88: 106102.63 | X88: 9 | Y88: 8099.44 | Z88: 9 | AA88: 8099.44 | AB88: 0 | AC88: 0 | AD88: 0 | AE88: 16198.88 | AF88: 0 | AG88: 24AAACO3087C1ZT | AH88: Kgs | AI88: 39269080 | AJ88: Rs. | AK88: 1 | AL88: 0 | AM88: India
H89: 46149 | I89: Plastene India ltd - Unit 1-Purchase | J89: R.M.P. | K89: RM 339 | L89: Purchase Withinstate - Raw Material | M89: PIL1/D/928 | N89: 46149 | O89: SF | P89: PP/PE Fabric | Q89: PP UL Fabric | R89: PP Woven Fabric | S89: PP UL Fabric With UV | T89: 433 | U89: 62564.17 | V89: PP UL Fabric With UV | W89: 177018.32 | X89: 9 | Y89: 5630.78 | Z89: 9 | AA89: 5630.78 | AB89: 0 | AC89: 0 | AD89: 0 | AE89: 11261.56 | AF89: 0 | AG89: 24AAACO3087C1ZT | AH89: Kgs | AI89: 39269080 | AJ89: Rs. | AK89: 1 | AL89: 0 | AM89: India
H90: 46149 | I90: Plastene India ltd - Unit 1-Purchase | J90: R.M.P. | K90: RM 339 | L90: Purchase Withinstate - Raw Material | M90: PIL1/D/928 | N90: 46149 | O90: SF | P90: PP/PE Fabric | Q90: PP UL Fabric | R90: PP Woven Fabric | S90: PP UL Fabric With UV | T90: 238 | U90: 34864.62 | V90: PP UL Fabric With UV | W90: 0 | X90: 9 | Y90: 3137.82 | Z90: 9 | AA90: 3137.82 | AB90: 0 | AC90: 0 | AD90: 0 | AE90: 6275.64 | AF90: 0 | AG90: 24AAACO3087C1ZT | AH90: Kgs | AI90: 39269080 | AJ90: Rs. | AK90: 1 | AL90: 0 | AM90: India
H91: 46149 | I91: Plastene India ltd - Unit 1-Purchase | J91: R.M.P. | K91: RM 339 | L91: Purchase Withinstate - Raw Material | M91: PIL1/D/928 | N91: 46149 | O91: SF | P91: PP/PE Fabric | Q91: PP Lam Fabric | R91: PP Laminated Woven Fabric | S91: PP Lam Fabric With UV | T91: 355 | U91: 52713.95 | V91: PP Lam Fabric With UV | W91: 0 | X91: 9 | Y91: 4744.26 | Z91: 9 | AA91: 4744.26 | AB91: 0 | AC91: 0 | AD91: 0 | AE91: 9488.52 | AF91: 0 | AG91: 24AAACO3087C1ZT | AH91: Kgs | AI91: 63053300 | AJ91: Rs. | AK91: 1 | AL91: 0 | AM91: India
H92: 46149 | I92: Plastene India ltd - Unit 1-Purchase | J92: R.M.P. | K92: RM 342 | L92: Purchase Withinstate - Raw Material | M92: PIL1/D/926 | N92: 46149 | O92: RM Consumables | P92: FIBC Accessories | Q92: FIBC Accessories | R92: Stores & Consumables | S92: Zip Lock Bags | T92: 10300 | U92: 36554.7 | V92: Zip Lock Bags | W92: 2137498.1 | X92: 9 | Y92: 3289.92 | Z92: 9 | AA92: 3289.92 | AB92: 0 | AC92: 0 | AD92: 0 | AE92: 6579.84 | AF92: 0 | AG92: 24AAACO3087C1ZT | AH92: Pcs | AI92: 39232100 | AJ92: Rs. | AK92: 1 | AL92: 10300 | AM92: India
H93: 46149 | I93: Plastene India ltd - Unit 1-Purchase | J93: R.M.P. | K93: RM 342 | L93: Purchase Withinstate - Raw Material | M93: PIL1/D/926 | N93: 46149 | O93: SF | P93: Liners | Q93: LDPE/LLDPE Bags | R93: LLDPE Bags | S93: LDPE/LLDPE Bags/Liner | T93: 23 | U93: 4456.94 | V93: LDPE/LLDPE Bags/Liner | W93: 0 | X93: 9 | Y93: 401.12 | Z93: 9 | AA93: 401.12 | AB93: 0 | AC93: 0 | AD93: 0 | AE93: 802.24 | AF93: 0 | AG93: 24AAACO3087C1ZT | AH93: Kgs | AI93: 39200000 | AJ93: Rs. | AK93: 1 | AL93: 23 | AM93: India
H94: 46149 | I94: Plastene India ltd - Unit 1-Purchase | J94: R.M.P. | K94: RM 342 | L94: Purchase Withinstate - Raw Material | M94: PIL1/D/926 | N94: 46149 | O94: SF | P94: Liners | Q94: LDPE/LLDPE Bags | R94: LLDPE Bags | S94: LDPE/LLDPE Bags/Liner | T94: 9208 | U94: 1719870.2 | V94: LDPE/LLDPE Bags/Liner | W94: 0 | X94: 9 | Y94: 154788.32 | Z94: 9 | AA94: 154788.32 | AB94: 0 | AC94: 0 | AD94: 0 | AE94: 309576.64 | AF94: 0 | AG94: 24AAACO3087C1ZT | AH94: Kgs | AI94: 39200000 | AJ94: Rs. | AK94: 1 | AL94: 9208 | AM94: India
H95: 46149 | I95: Plastene India ltd - Unit 1-Purchase | J95: R.M.P. | K95: RM 342 | L95: Purchase Withinstate - Raw Material | M95: PIL1/D/926 | N95: 46149 | O95: SF | P95: Liners | Q95: LDPE/LLDPE Bags | R95: LLDPE Bags | S95: LDPE/LLDPE Bags/Liner | T95: 285 | U95: 52092.3 | V95: LDPE/LLDPE Bags/Liner | W95: 0 | X95: 9 | Y95: 4688.31 | Z95: 9 | AA95: 4688.31 | AB95: 0 | AC95: 0 | AD95: 0 | AE95: 9376.62 | AF95: 0 | AG95: 24AAACO3087C1ZT | AH95: Kgs | AI95: 39200000 | AJ95: Rs. | AK95: 1 | AL95: 285 | AM95: India
... H114: 46180 | I114: Bhagwati Impex | J114: Purchase | K114: GNPK 64 | L114: Purchase Withinstate- Packing Material | M114: BI/26-27/059 | N114: 46180 | O114: Packing Material | P114: Pallets | Q114: Pallets | R114: Packing Material | S114: Pine Wooden Pallet Design Code STD90110 | T114: 100 | U114: 77500 | V114: Pine Wooden Pallet Design Code STD90110 | W114: 81375 | X114: 2.5 | Y114: 1937.5 | Z114: 2.5 | AA114: 1937.5 | AB114: 0 | AC114: 0 | AD114: 0 | AE114: 3875 | AF114: 0 | AG114: 24AXVPT0296P1ZD | AH114: Pcs | AI114: 44152000 | AJ114: Rs. | AK114: 1 | AL114: 0 | AM114: India
H115: 46180 | I115: Disha Trading | J115: General Purchase | K115: GNCN 239 | L115: Purchase Withinstate- Stores, Spares & Consumable | M115: 869 | N115: 46119 | O115: Consumables | P115: Housekeeping Material | Q115: Spares & Stores | R115: Stores & Consumables | S115: Cotton Waste | T115: 600 | U115: 9600 | V115: Cotton Waste | W115: 10080 | X115: 2.5 | Y115: 240 | Z115: 2.5 | AA115: 240 | AB115: 0 | AC115: 0 | AD115: 0 | AE115: 480 | AF115: 0 | AG115: 24AFUPA6072K1Z6 | AH115: Kgs | AI115: 631090 | AJ115: Rs. | AK115: 1 | AL115: 0 | AM115: India
H116: 46180 | I116: Jay Jagannath Industries- 24GKEPP9703F1Z1 | J116: General Purchase | K116: GNSP 111 | L116: Purchase Withinstate- Stores, Spares & Consumable | M116: GST-098 | N116: 16-06-2026 | O116: Stores/Spares | P116: Sprocket | Q116: Spares & Stores | R116: Stores & Consumables | S116: Chain Sprocket 5/8" 24 Teeth Duplex Boss Size | T116: 3 | U116: 2460 | V116: Chain Sprocket 5/8" 24 Teeth Duplex Boss Size | W116: 5587 | X116: 9 | Y116: 221.4 | Z116: 9 | AA116: 221.4 | AB116: 0 | AC116: 0 | AD116: 0 | AE116: 442.8 | AF116: 0 | AG116: 24GKEPP9703F1Z1 | AH116: Pcs | AI116: 848382 | AJ116: Rs. | AK116: 1 | AL116: 0 | AM116: India
H117: 46180 | I117: Jay Jagannath Industries- 24GKEPP9703F1Z1 | J117: General Purchase | K117: GNSP 111 | L117: Purchase Withinstate- Stores, Spares & Consumable | M117: GST-098 | N117: 16-06-2026 | O117: Stores/Spares | P117: Sprocket | Q117: Spares & Stores | R117: Stores & Consumables | S117: Chain Sprocket 5/8" 24 Teeth Duplex Boss Size | T117: 3 | U117: 2190 | V117: Chain Sprocket 5/8" 24 Teeth Duplex Boss Size | W117: 0 | X117: 9 | Y117: 197.1 | Z117: 9 | AA117: 197.1 | AB117: 0 | AC117: 0 | AD117: 0 | AE117: 394.2 | AF117: 0 | AG117: 24GKEPP9703F1Z1 | AH117: Pcs | AI117: 848382 | AJ117: Rs. | AK117: 1 | AL117: 0 | AM117: India
H118: 46180 | I118: Plastene India ltd - Unit 1-Purchase | J118: General Purchase | K118: GNCN 243 | L118: Purchase Withinstate- Stores, Spares & Consumable | M118: PIL1/D/933 | N118: 46180 | O118: Stores/Spares | P118: MS Structure Items | Q118: Spares & Stores | R118: Stores & Consumables | S118: MS Pipe 4 C Class | T118: 244 | U118: 11712 | V118: MS Pipe 4 C Class | W118: 13808.45 | X118: 9 | Y118: 1054.08 | Z118: 9 | AA118: 1054.08 | AB118: 0 | AC118: 0 | AD118: 0 | AE118: 2108.16 | AF118: 0 | AG118: 24AAACO3087C1ZT | AH118: Kgs | AI118: 73063090 | AJ118: Rs. | AK118: 1 | AL118: 0 | AM118: India
H119: 46180 | I119: Plastene India ltd - Unit 1-Purchase | J119: R.M.P. | K119: RM 345 | L119: Purchase Withinstate - Raw Material | M119: PIL1/D/934 | N119: 46180 | O119: SF | P119: Liners | Q119: LDPE/LLDPE Bags | R119: LLDPE Bags | S119: LDPE/LLDPE Bags/Liner | T119: 3556.1 | U119: 649983.96 | V119: LDPE/LLDPE Bags/Liner | W119: 803808.91 | X119: 9 | Y119: 58498.56 | Z119: 9 | AA119: 58498.56 | AB119: 0 | AC119: 0 | AD119: 0 | AE119: 116997.12 | AF119: 0 | AG119: 24AAACO3087C1ZT | AH119: Kgs | AI119: 39200000 | AJ119: Rs. | AK119: 1 | AL119: 0 | AM119: India
H120: 46180 | I120: Plastene India ltd - Unit 1-Purchase | J120: R.M.P. | K120: RM 345 | L120: Purchase Withinstate - Raw Material | M120: PIL1/D/934 | N120: 46180 | O120: SF | P120: PP/PE Fabric | Q120: PP UL Fabric | R120: PP Woven Fabric | S120: PP UL Fabric With UV | T120: 220 | U120: 31787.8 | V120: PP UL Fabric With UV | W120: 0 | X120: 9 | Y120: 2860.9 | Z120: 9 | AA120: 2860.9 | AB120: 0 | AC120: 0 | AD120: 0 | AE120: 5721.8 | AF120: 0 | AG120: 24AAACO3087C1ZT | AH120: Kgs | AI120: 39269080 | AJ120: Rs. | AK120: 1 | AL120: 0 | AM120: India
H121: 46180 | I121: Plastene India ltd - Unit 1-Purchase | J121: R.M.P. | K121: RM 346 | L121: Purchase Withinstate - Raw Material | M121: PIL1/D/932 | N121: 46180 | O121: SF | P121: PP/PE Fabric | Q121: PP UL Fabric | R121: PP Woven Fabric | S121: PP UL Fabric With UV | T121: 2826 | U121: 413980.74 | V121: PP UL Fabric With UV | W121: 1567298.8 | X121: 9 | Y121: 37258.27 | Z121: 9 | AA121: 37258.27 | AB121: 0 | AC121: 0 | AD121: 0 | AE121: 74516.54 | AF121: 0 | AG121: 24AAACO3087C1ZT | AH121: Kgs | AI121: 39269080 | AJ121: Rs. | AK121: 1 | AL121: 0 | AM121: India
H122: 46180 | I122: Plastene India ltd - Unit 1-Purchase | J122: R.M.P. | K122: RM 346 | L122: Purchase Withinstate - Raw Material | M122: PIL1/D/932 | N122: 46180 | O122: SF | P122: Webbing | Q122: PP Webbing | R122: PP Webbing | S122: Webbing | T122: 5.8 | U122: 988.84 | V122: Webbing | W122: 0 | X122: 9 | Y122: 89 | Z122: 9 | AA122: 89 | AB122: 0 | AC122: 0 | AD122: 0 | AE122: 178 | AF122: 0 | AG122: 24AAACO3087C1ZT | AH122: Kgs | AI122: 3926908 | AJ122: Rs. | AK122: 1 | AL122: 0 | AM122: India
H123: 46180 | I123: Plastene India ltd - Unit 1-Purchase | J123: R.M.P. | K123: RM 346 | L123: Purchase Withinstate - Raw Material | M123: PIL1/D/932 | N123: 46180 | O123: SF | P123: Webbing | Q123: PP Webbing | R123: PP Webbing | S123: Webbing | T123: 706.1 | U123: 103436.59 | V123: Webbing | W123: 0 | X123: 9 | Y123: 9309.29 | Z123: 9 | AA123: 9309.29 | AB123: 0 | AC123: 0 | AD123: 0 | AE123: 18618.58 | AF123: 0 | AG123: 24AAACO3087C1ZT | AH123: Kgs | AI123: 3926908 | AJ123: Rs. | AK123: 1 | AL123: 0 | AM123: India
H124: 46180 | I124: Plastene India ltd - Unit 1-Purchase | J124: R.M.P. | K124: RM 346 | L124: Purchase Withinstate - Raw Material | M124: PIL1/D/932 | N124: 46180 | O124: SF | P124: Webbing | Q124: PP Webbing | R124: PP Webbing | S124: Webbing | T124: 1181.6 | U124: 176637.38 | V124: Webbing | W124: 0 | X124: 9 | Y124: 15897.36 | Z124: 9 | AA124: 15897.36 | AB124: 0 | AC124: 0 | AD124: 0 | AE124: 31794.72 | AF124: 0 | AG124: 24AAACO3087C1ZT | AH124: Kgs | AI124: 3926908 | AJ124: Rs. | AK124: 1 | AL124: 0 | AM124: India
H125: 46180 | I125: Plastene India ltd - Unit 1-Purchase | J125: R.M.P. | K125: RM 346 | L125: Purchase Withinstate - Raw Material | M125: PIL1/D/932 | N125: 46180 | O125: SF | P125: PP/PE Fabric | Q125: PP UL Fabric | R125: PP Woven Fabric | S125: PP UL Fabric With UV | T125: 3213 | U125: 464246.37 | V125: PP UL Fabric With UV | W125: 0 | X125: 9 | Y125: 41782.17 | Z125: 9 | AA125: 41782.17 | AB125: 0 | AC125: 0 | AD125: 0 | AE125: 83564.34 | AF125: 0 | AG125: 24AAACO3087C1ZT | AH125: Kgs | AI125: 39269080 | AJ125: Rs. | AK125: 1 | AL125: 0 | AM125: India
H126: 46180 | I126: Plastene India ltd - Unit 1-Purchase | J126: R.M.P. | K126: RM 346 | L126: Purchase Withinstate - Raw Material | M126: PIL1/D/932 | N126: 46180 | O126: SF | P126: PP/PE Fabric | Q126: PP UL Fabric | R126: PP Woven Fabric | S126: PP UL Fabric With UV | T126: 1153 | U126: 170055.97 | V126: PP UL Fabric With UV | W126: 0 | X126: 9 | Y126: 15305.04 | Z126: 9 | AA126: 15305.04 | AB126: 0 | AC126: 0 | AD126: 0 | AE126: 30610.08 | AF126: 0 | AG126: 24AAACO3087C1ZT | AH126: Kgs | AI126: 39269080 | AJ126: Rs. | AK126: 1 | AL126: 0 | AM126: India
H127: 46180 | I127: Plastene Polyfilms Ltd-Purchase | J127: General Purchase | K127: GNCN 241 | L127: Purchase Withinstate- Stores, Spares & Consumable | M127: PPL/D/312 | N127: 46180 | O127: Stores/Spares | P127: MS Structure Items | Q127: Spares & Stores | R127: Stores & Consumables | S127: MS Pipe 4 C Class | T127: 12 | U127: 576 | V127: MS Pipe 4 C Class | W127: 679.1 | X127: 9 | Y127: 51.84 | Z127: 9 | AA127: 51.84 | AB127: 0 | AC127: 0 | AD127: 0 | AE127: 103.68 | AF127: 0 | AG127: 24AAFCP2956A1ZR | AH127: Kgs | AI127: 73063090 | AJ127: Rs. | AK127: 1 | AL127: 0 | AM127: India
H128: 46180 | I128: Plastene Polyfilms Ltd-Purchase | J128: General Purchase | K128: GNCN 242 | L128: Purchase Withinstate- Stores, Spares & Consumable | M128: PPL/D/313 | N128: 46180 | O128: Consumables | P128: Oil & Greases | Q128: Spares & Stores | R128: Stores & Consumables | S128: Oil 20W/40 | T128: 20 | U128: 2760 | V128: Oil 20W/40 | W128: 3254.04 | X128: 9 | Y128: 248.4 | Z128: 9 | AA128: 248.4 | AB128: 0 | AC128: 0 | AD128: 0 | AE128: 496.8 | AF128: 0 | AG128: 24AAFCP2956A1ZR | AH128: LTR | AI128: 27109900 | AJ128: Rs. | AK128: 1 | AL128: 0 | AM128: India
H129: 46180 | I129: Plastene Polyfilms Ltd-Purchase | J129: R.M.P. | K129: RM 344 | L129: Purchase Withinstate - Raw Material | M129: PPL/D/314 | N129: 46180 | O129: FG | P129: FIBC WIP | Q129: FIBC WIP | R129: FIBC WIP | S129: PP Woven Fabric | T129: 411 | U129: 63598.14 | V129: FIBC WIP | W129: 116943.05 | X129: 9 | Y129: 5723.83 | Z129: 9 | AA129: 5723.83 | AB129: 0 | AC129: 0 | AD129: 0 | AE129: 11447.66 | AF129: 0 | AG129: 24AAFCP2956A1ZR | AH129: Kgs | AI129: 39269080 | AJ129: Rs. | AK129: 1 | AL129: 0 | AM129: India
... H151: 46241 | I151: HCP Plastene Bulkpack Limited - Purchase | J151: Branch Transfer In | K151: GNCN 247 | L151: Branch Transfer In - Raw Material | M151: HPBL/DC/18 | N151: 46210 | O151: Consumables | P151: Consumables | Q151: Consumables | R151: Stores & Consumables | S151: Hotmelt ( Glue ) | T151: 200 | U151: 64000 | V151: Hotmelt ( Glue ) | W151: 64000 | X151: 0 | Y151: 0 | Z151: 0 | AA151: 0 | AB151: 0 | AC151: 0 | AD151: 0 | AE151: 0 | AF151: 0 | AG151: 24AABCG1282C2Z6 | AH151: Kgs | AI151: 35052000 | AJ151: Rs. | AK151: 1 | AL151: 0 | AM151: India
H152: 46241 | I152: HCP Plastene Bulkpack Limited - Purchase | J152: Branch Transfer In | K152: RM 362 | L152: Branch Transfer In - Raw Material | M152: HPBL/DC/13 | N152: 27-06-2026 | O152: SF | P152: Liners | Q152: LDPE/LLDPE Bags | R152: LLDPE Doc | S152: DOC Pouch | T152: 930 | U152: 179480.7 | V152: DOC Pouch | W152: 179480.7 | X152: 0 | Y152: 0 | Z152: 0 | AA152: 0 | AB152: 0 | AC152: 0 | AD152: 0 | AE152: 0 | AF152: 0 | AG152: 24AABCG1282C2Z6 | AH152: Kgs | AI152: 39232100 | AJ152: Rs. | AK152: 1 | AL152: 0 | AM152: India
H153: 46241 | I153: Plastene India ltd - Unit 1-Purchase | J153: General Purchase | K153: GNCN 248 | L153: Purchase Withinstate- Stores, Spares & Consumable | M153: PIL1/D/965 | N153: 46241 | O153: Stores/Spares | P153: MS Structure Items | Q153: Spares & Stores | R153: Stores & Consumables | S153: MS Pipe 4 C Class | T153: 222 | U153: 10656 | V153: MS Pipe 4 C Class | W153: 12563.42 | X153: 9 | Y153: 959.04 | Z153: 9 | AA153: 959.04 | AB153: 0 | AC153: 0 | AD153: 0 | AE153: 1918.08 | AF153: 0 | AG153: 24AAACO3087C1ZT | AH153: Kgs | AI153: 73063090 | AJ153: Rs. | AK153: 1 | AL153: 0 | AM153: India
H154: 46241 | I154: Plastene India ltd - Unit 1-Purchase | J154: R.M.P. | K154: RM 355 | L154: Purchase Withinstate - Raw Material | M154: PIL1/D/976 | N154: 46241 | O154: SF | P154: Liners | Q154: LDPE/LLDPE Bags | R154: LLDPE Bags | S154: LDPE/LLDPE Bags/Liner | T154: 1155 | U154: 211110.9 | V154: LDPE/LLDPE Bags/Liner | W154: 248899.75 | X154: 9 | Y154: 18999.98 | Z154: 9 | AA154: 18999.98 | AB154: 0 | AC154: 0 | AD154: 0 | AE154: 37999.96 | AF154: 0 | AG154: 24AAACO3087C1ZT | AH154: Kgs | AI154: 39200000 | AJ154: Rs. | AK154: 1 | AL154: 0 | AM154: India
H155: 46241 | I155: Plastene India ltd - Unit 1-Purchase | J155: R.M.P. | K155: RM 357 | L155: Purchase Withinstate - Raw Material | M155: PIL1/D/966 | N155: 46241 | O155: SF | P155: Liners | Q155: LDPE/LLDPE Bags | R155: LLDPE Bags | S155: LDPE/LLDPE Bags/Liner | T155: 2566 | U155: 469013.48 | V155: LDPE/LLDPE Bags/Liner | W155: 552966.89 | X155: 9 | Y155: 42211.21 | Z155: 9 | AA155: 42211.21 | AB155: 0 | AC155: 0 | AD155: 0 | AE155: 84422.42 | AF155: 0 | AG155: 24AAACO3087C1ZT | AH155: Kgs | AI155: 39200000 | AJ155: Rs. | AK155: 1 | AL155: 0 | AM155: India
H156: 46241 | I156: Plastene India ltd - Unit 1-Purchase | J156: R.M.P. | K156: RM 358 | L156: Purchase Withinstate - Raw Material | M156: PIL1/D/968 | N156: 46241 | O156: SF | P156: Liners | Q156: LDPE/LLDPE Bags | R156: LLDPE Bags | S156: LDPE/LLDPE Bags/Liner | T156: 745 | U156: 136171.1 | V156: LDPE/LLDPE Bags/Liner | W156: 160545.73 | X156: 9 | Y156: 12255.4 | Z156: 9 | AA156: 12255.4 | AB156: 0 | AC156: 0 | AD156: 0 | AE156: 24510.8 | AF156: 0 | AG156: 24AAACO3087C1ZT | AH156: Kgs | AI156: 39200000 | AJ156: Rs. | AK156: 1 | AL156: 0 | AM156: India
H157: 46241 | I157: Plastene India ltd - Unit 1-Purchase | J157: R.M.P. | K157: RM 359 | L157: Purchase Withinstate - Raw Material | M157: PIL1/D/962 | N157: 46241 | O157: SF | P157: PP/PE Fabric | Q157: PP UL Fabric | R157: PP Woven Fabric | S157: PP UL Fabric With UV | T157: 2569 | U157: 376332.81 | V157: PP UL Fabric With UV | W157: 1232235 | X157: 9 | Y157: 33869.95 | Z157: 9 | AA157: 33869.95 | AB157: 0 | AC157: 0 | AD157: 0 | AE157: 67739.9 | AF157: 0 | AG157: 24AAACO3087C1ZT | AH157: Kgs | AI157: 39269080 | AJ157: Rs. | AK157: 1 | AL157: 0 | AM157: India
H158: 46241 | I158: Plastene India ltd - Unit 1-Purchase | J158: R.M.P. | K158: RM 359 | L158: Purchase Withinstate - Raw Material | M158: PIL1/D/962 | N158: 46241 | O158: SF | P158: PP/PE Fabric | Q158: PP UL Fabric | R158: PP Woven Fabric | S158: PP UL Fabric With UV | T158: 907 | U158: 133773.43 | V158: PP UL Fabric With UV | W158: 0 | X158: 9 | Y158: 12039.61 | Z158: 9 | AA158: 12039.61 | AB158: 0 | AC158: 0 | AD158: 0 | AE158: 24079.22 | AF158: 0 | AG158: 24AAACO3087C1ZT | AH158: Kgs | AI158: 39269080 | AJ158: Rs. | AK158: 1 | AL158: 0 | AM158: India
H159: 46241 | I159: Plastene India ltd - Unit 1-Purchase | J159: R.M.P. | K159: RM 359 | L159: Purchase Withinstate - Raw Material | M159: PIL1/D/962 | N159: 46241 | O159: SF | P159: PP/PE Fabric | Q159: PP UL Fabric | R159: PP Woven Fabric | S159: PP UL Fabric With UV | T159: 3703 | U159: 535046.47 | V159: PP UL Fabric With UV | W159: 0 | X159: 9 | Y159: 48154.18 | Z159: 9 | AA159: 48154.18 | AB159: 0 | AC159: 0 | AD159: 0 | AE159: 96308.36 | AF159: 0 | AG159: 24AAACO3087C1ZT | AH159: Kgs | AI159: 39269080 | AJ159: Rs. | AK159: 1 | AL159: 0 | AM159: India
H160: 46241 | I160: Plastene India ltd - Unit 1-Purchase | J160: R.M.P. | K160: RM 360 | L160: Purchase Withinstate - Raw Material | M160: PIL1/D/967 | N160: 46241 | O160: SF | P160: PP/PE Fabric | Q160: PP Lam Fabric | R160: PP Laminated Woven Fabric | S160: PP Lam Fabric With UV | T160: 320 | U160: 46876.8 | V160: PP Lam Fabric With UV | W160: 301290.55 | X160: 9 | Y160: 4218.91 | Z160: 9 | AA160: 4218.91 | AB160: 0 | AC160: 0 | AD160: 0 | AE160: 8437.82 | AF160: 0 | AG160: 24AAACO3087C1ZT | AH160: Kgs | AI160: 63053300 | AJ160: Rs. | AK160: 1 | AL160: 0 | AM160: India
H161: 46241 | I161: Plastene India ltd - Unit 1-Purchase | J161: R.M.P. | K161: RM 360 | L161: Purchase Withinstate - Raw Material | M161: PIL1/D/967 | N161: 46241 | O161: SF | P161: PP/PE Fabric | Q161: PP UL Fabric | R161: PP Woven Fabric | S161: PP UL Fabric With UV | T161: 220 | U161: 31787.8 | V161: PP UL Fabric With UV | W161: 0 | X161: 9 | Y161: 2860.9 | Z161: 9 | AA161: 2860.9 | AB161: 0 | AC161: 0 | AD161: 0 | AE161: 5721.8 | AF161: 0 | AG161: 24AAACO3087C1ZT | AH161: Kgs | AI161: 39269080 | AJ161: Rs. | AK161: 1 | AL161: 0 | AM161: India
H162: 46241 | I162: Plastene India ltd - Unit 1-Purchase | J162: R.M.P. | K162: RM 360 | L162: Purchase Withinstate - Raw Material | M162: PIL1/D/967 | N162: 46241 | O162: SF | P162: PP/PE Fabric | Q162: PP UL Fabric | R162: PP Woven Fabric | S162: PP UL Fabric With UV | T162: 990 | U162: 145025.1 | V162: PP UL Fabric With UV | W162: 0 | X162: 9 | Y162: 13052.26 | Z162: 9 | AA162: 13052.26 | AB162: 0 | AC162: 0 | AD162: 0 | AE162: 26104.52 | AF162: 0 | AG162: 24AAACO3087C1ZT | AH162: Kgs | AI162: 39269080 | AJ162: Rs. | AK162: 1 | AL162: 0 | AM162: India
H163: 46241 | I163: Plastene India ltd - Unit 1-Purchase | J163: R.M.P. | K163: RM 360 | L163: Purchase Withinstate - Raw Material | M163: PIL1/D/967 | N163: 46241 | O163: SF | P163: PP/PE Fabric | Q163: PP UL Fabric | R163: PP Woven Fabric | S163: PP UL Fabric With UV | T163: 216 | U163: 31857.84 | V163: PP UL Fabric With UV | W163: 0 | X163: 9 | Y163: 2867.21 | Z163: 9 | AA163: 2867.21 | AB163: 0 | AC163: 0 | AD163: 0 | AE163: 5734.42 | AF163: 0 | AG163: 24AAACO3087C1ZT | AH163: Kgs | AI163: 39269080 | AJ163: Rs. | AK163: 1 | AL163: 0 | AM163: India
H164: 46241 | I164: Plastene India ltd - Unit 1-Purchase | J164: R.M.P. | K164: RM 361 | L164: Purchase Withinstate - Raw Material | M164: PIL1/D/964 | N164: 46241 | O164: SF | P164: Webbing | Q164: PP Webbing | R164: PP Webbing | S164: Webbing | T164: 1020.7 | U164: 152584.44 | V164: Webbing | W164: 691478.36 | X164: 9 | Y164: 13732.6 | Z164: 9 | AA164: 13732.6 | AB164: 0 | AC164: 0 | AD164: 0 | AE164: 27465.2 | AF164: 0 | AG164: 24AAACO3087C1ZT | AH164: Kgs | AI164: 3926908 | AJ164: Rs. | AK164: 1 | AL164: 0 | AM164: India
... H228: 46333 | I228: Quality Prepress Pvt Ltd | J228: General Purchase | K228: GNCN 260 | L228: Purchase Withinstate- Stores, Spares & Consumable | M228: 2211/2026-27 | N228: 46029 | O228: Consumables | P228: Rubber/Polymer Stereo | Q228: Spares & Stores | R228: Stores & Consumables | S228: Polymer Stereo | T228: 483 | U228: 724.5 | V228: Polymer Stereo | W228: 973 | X228: 9 | Y228: 65.205 | Z228: 9 | AA228: 65.205 | AB228: 0 | AC228: 0 | AD228: 18 | AE228: 148.41 | AF228: 0 | AG228: 24AAACQ5321R1Z7 | AH228: CMS | AI228: 37013000 | AJ228: Rs. | AK228: 1 | AL228: 0 | AM228: India
H229: 46333 | I229: Quality Prepress Pvt Ltd | J229: General Purchase | K229: GNCN 261 | L229: Purchase Withinstate- Stores, Spares & Consumable | M229: 2062/2026-27 | N229: 28-06-2026 | O229: Consumables | P229: Rubber/Polymer Stereo | Q229: Spares & Stores | R229: Stores & Consumables | S229: Polymer Stereo | T229: 297 | U229: 445.5 | V229: Polymer Stereo | W229: 644 | X229: 9 | Y229: 40.1 | Z229: 9 | AA229: 40.1 | AB229: 0 | AC229: 0 | AD229: 18 | AE229: 98.2 | AF229: 0 | AG229: 24AAACQ5321R1Z7 | AH229: CMS | AI229: 37013000 | AJ229: Rs. | AK229: 1 | AL229: 0 | AM229: India
H230: 46333 | I230: S.R.Sewing Tech | J230: General Purchase | K230: GNSP 120 | L230: Purchase Interstate- Stores, Spares & Consumable | M230: SR/512/26-27 | N230: 46241 | O230: Stores/Spares | P230: Stitching Spares | Q230: Spares & Stores | R230: Stores & Consumables | S230: Looper For Double Locked Stitch (41308 C) | T230: 5 | U230: 7000 | V230: Looper For Double Locked Stitch (41308 C) | W230: 33605 | X230: 0 | Y230: 0 | Z230: 0 | AA230: 0 | AB230: 5 | AC230: 350 | AD230: 0 | AE230: 350 | AF230: 0 | AG230: 19AORPR0945L1Z4 | AH230: Pcs | AI230: 84529099 | AJ230: Rs. | AK230: 1 | AL230: 0 | AM230: India
H231: 46333 | I231: S.R.Sewing Tech | J231: General Purchase | K231: GNSP 120 | L231: Purchase Interstate- Stores, Spares & Consumable | M231: SR/512/26-27 | N231: 46241 | O231: Stores/Spares | P231: Stitching Spares | Q231: Spares & Stores | R231: Stores & Consumables | S231: Spreader, Upper For Overedge Stitching (81507) | T231: 10 | U231: 10500 | V231: Spreader, Upper For Overedge Stitching (81507) | W231: 0 | X231: 0 | Y231: 0 | Z231: 0 | AA231: 0 | AB231: 5 | AC231: 525 | AD231: 0 | AE231: 525 | AF231: 0 | AG231: 19AORPR0945L1Z4 | AH231: Pcs | AI231: 84529099 | AJ231: Rs. | AK231: 1 | AL231: 0 | AM231: India
...

Sheet Sales Register
A1: Row Labels | B1: Sum of Quantity | C1: Sum of Amount
A2: HDPE/PP Plastik Waste | B2: 27775 | C2: 333300 | D2: =+GETPIVOTDATA("Sum of Amount",$A$1,"sales Group Name","HDPE/PP Plastik Waste")/GETPIVOTDATA("Sum of Quantity",$A$1,"sales Group Name","HDPE/PP Plastik Waste") -> 12
A3: JUMBO BAG | B3: 595287.7 | C3: 1.357541e+08 | D3: =+GETPIVOTDATA("Sum of Amount",$A$1,"sales Group Name","JUMBO BAG")/GETPIVOTDATA("Sum of Quantity",$A$1,"sales Group Name","JUMBO BAG") -> 228.04789
A4: PP Woven Fabric | B4: 1850 | C4: 286960.25 | D4: =+GETPIVOTDATA("Sum of Amount",$A$1,"sales Group Name","PP Woven Fabric")/GETPIVOTDATA("Sum of Quantity",$A$1,"sales Group Name","PP Woven Fabric") -> 155.11365
A5: LLDPE Bags | B5: 26 | C5: 4709.9 | D5: =+GETPIVOTDATA("Sum of Amount",$A$1,"sales Group Name","LLDPE Bags")/GETPIVOTDATA("Sum of Quantity",$A$1,"sales Group Name","LLDPE Bags") -> 181.15 | F5: =+D3*0.95 -> 216.64549
A6: PP Filament Yarn | B6: 132 | C6: 21338.68 | D6: =+GETPIVOTDATA("Sum of Amount",$A$1,"sales Group Name","PP Filament Yarn")/GETPIVOTDATA("Sum of Quantity",$A$1,"sales Group Name","PP Filament Yarn") -> 161.65667
A7: Thinner | B7: 510 | C7: 84660 | D7: =+GETPIVOTDATA("Sum of Amount",$A$1,"sales Group Name","Thinner")/GETPIVOTDATA("Sum of Quantity",$A$1,"sales Group Name","Thinner") -> 166
A8: PP Webbing | B8: 191.9 | C8: 28687.13 | D8: =+GETPIVOTDATA("Sum of Amount",$A$1,"sales Group Name","PP Webbing")/GETPIVOTDATA("Sum of Quantity",$A$1,"sales Group Name","PP Webbing") -> 149.48999
A9: FIBC WIP | B9: 9077 | C9: 261688.38 | D9: =+GETPIVOTDATA("Sum of Amount",$A$1,"sales Group Name","FIBC WIP")/GETPIVOTDATA("Sum of Quantity",$A$1,"sales Group Name","FIBC WIP") -> 28.829831
A10: Grand Total | B10: 634849.6 | C10: 1.3677545e+08
A15: Sales value reco with Trail Balance Value
A16: Row Labels | B16: Sum of Amount | C16: AS PER T/B | D16: DIFFERENCE | H16: Date | I16: Particular | J16: Voucher Type | K16: Voucher No | L16: Type | M16: Invoice No | N16: Invoice Date | O16: Main Grp | P16: Group Name | Q16: Sub Grup | R16: sales Group Name | S16: Item Name | T16: Quantity | U16: Amount | V16: Item Desc | W16: Bill Amount | X16: CGST Rate | Y16: CGST Amt | Z16: SGST Rate | AA16: SGST Amt | AB16: IGST Rate | AC16: IGST Amt | AD16: Freight GST | AE16: Total GST | AF16: TCS | AG16: GST-IN | AH16: Unit | AI16: HSN Code | AJ16: Currencty | AK16: Exc.Rate | AL16: Net Wt | AM16: Country
A17: Sales - Kasez - Mfg - U/B | B17: 2058957 | C17: =+'Trail Balance-JULY26'!D128 -> 2058957 | D17: =+GETPIVOTDATA("Amount",$A$16,"Type","Sales - Kasez - Mfg - U/B")-C17 -> 0.01 | H17: 46029 | I17: Plastene India ltd - Unit 1-Sales | J17: Sales | K17: 137 | L17: Sales - Within State Manufactured Goods | M17: HPBL4/D/137 | N17: 46029 | O17: FG | P17: FIBC Bags | Q17: FIBC Bags | R17: JUMBO BAG | S17: FIBC Bags With UV With Liner | T17: 855 | U17: 179746.65 | V17: 87x87x87 | W17: 1449554.6 | X17: 9 | Y17: 16177.2 | Z17: 9 | AA17: 16177.2 | AB17: 0 | AC17: 0 | AD17: 0 | AE17: 32354.4 | AF17: 0 | AG17: 24AAACO3087C1ZT | AH17: KGS | AI17: 63053200 | AJ17: Rs. | AK17: 1 | AL17: 855 | AM17: India
A18: Sales - Within State - Traded Goods | B18: 3117803.8 | C18: =+'Trail Balance-JULY26'!D137 -> 3117803.8 | D18: =+GETPIVOTDATA("Amount",$A$16,"Type","Sales - Within State - Traded Goods")-C18 -> 0 | H18: 46029 | I18: Plastene India ltd - Unit 1-Sales | J18: Sales | K18: 137 | L18: Sales - Within State Manufactured Goods | M18: HPBL4/D/137 | N18: 46029 | O18: FG | P18: FIBC Bags | Q18: FIBC Bags | R18: JUMBO BAG | S18: FIBC Bags With UV Without Liner | T18: 415 | U18: 110618.25 | V18: 85x85x85 | W18: 0 | X18: 9 | Y18: 9955.64 | Z18: 9 | AA18: 9955.64 | AB18: 0 | AC18: 0 | AD18: 0 | AE18: 19911.28 | AF18: 0 | AG18: 24AAACO3087C1ZT | AH18: KGS | AI18: 63053200 | AJ18: Rs. | AK18: 1 | AL18: 415 | AM18: India
A19: Sales - Within State Manufactured Goods | B19: 19349307 | C19: =+'Trail Balance-JULY26'!D130 -> 19349307 | D19: =+GETPIVOTDATA("Amount",$A$16,"Type","Sales - Within State Manufactured Goods")-C19 -> 0 | H19: 46029 | I19: Plastene India ltd - Unit 1-Sales | J19: Sales | K19: 137 | L19: Sales - Within State Manufactured Goods | M19: HPBL4/D/137 | N19: 46029 | O19: FG | P19: FIBC Bags | Q19: FIBC Bags | R19: JUMBO BAG | S19: FIBC Bags With UV Without Liner | T19: 431 | U19: 109780.01 | V19: 90x90x90 | W19: 0 | X19: 9 | Y19: 9880.2 | Z19: 9 | AA19: 9880.2 | AB19: 0 | AC19: 0 | AD19: 0 | AE19: 19760.4 | AF19: 0 | AG19: 24AAACO3087C1ZT | AH19: KGS | AI19: 63053200 | AJ19: Rs. | AK19: 1 | AL19: 431 | AM19: India
A20: Sales - Direct Export - Mfg - U/R | B20: 49412158 | C20: =+'Trail Balance-JULY26'!D132 -> 49412158 | D20: =+GETPIVOTDATA("Amount",$A$16,"Type","Sales - Direct Export - Mfg - U/R")-C20 -> 0 | H20: 46029 | I20: Plastene India ltd - Unit 1-Sales | J20: Sales | K20: 137 | L20: Sales - Within State Manufactured Goods | M20: HPBL4/D/137 | N20: 46029 | O20: FG | P20: FIBC Bags | Q20: FIBC Bags | R20: JUMBO BAG | S20: FIBC Bags With UV Without Liner | T20: 462 | U20: 115786.44 | V20: 85x85x85 | W20: 0 | X20: 9 | Y20: 10420.78 | Z20: 9 | AA20: 10420.78 | AB20: 0 | AC20: 0 | AD20: 0 | AE20: 20841.56 | AF20: 0 | AG20: 24AAACO3087C1ZT | AH20: KGS | AI20: 63053200 | AJ20: Rs. | AK20: 1 | AL20: 462 | AM20: India
A21: Sales - Waste & Scrape | B21: 383952 | C21: =+'Trail Balance-JULY26'!D138 -> 383952 | D21: =+GETPIVOTDATA("Amount",$A$16,"Type","Sales - Waste & Scrape")-C21 -> 0 | H21: 46029 | I21: Plastene India ltd - Unit 1-Sales | J21: Sales | K21: 137 | L21: Sales - Within State Manufactured Goods | M21: HPBL4/D/137 | N21: 46029 | O21: FG | P21: FIBC Bags | Q21: FIBC Bags | R21: JUMBO BAG | S21: FIBC Bags With UV Without Liner | T21: 838 | U21: 203809.98 | V21: 90x90x90 | W21: 0 | X21: 9 | Y21: 18342.9 | Z21: 9 | AA21: 18342.9 | AB21: 0 | AC21: 0 | AD21: 0 | AE21: 36685.8 | AF21: 0 | AG21: 24AAACO3087C1ZT | AH21: KGS | AI21: 63053200 | AJ21: Rs. | AK21: 1 | AL21: 838 | AM21: India
A22: Sales - Merchant Export | B22: 12043513 | C22: =+'Trail Balance-JULY26'!D129 -> 12043513 | D22: =+GETPIVOTDATA("Amount",$A$16,"Type","Sales - Merchant Export")-C22 -> 0 | H22: 46029 | I22: Plastene India ltd - Unit 1-Sales | J22: Sales | K22: 137 | L22: Sales - Within State Manufactured Goods | M22: HPBL4/D/137 | N22: 46029 | O22: FG | P22: FIBC Bags | Q22: FIBC Bags | R22: JUMBO BAG | S22: FIBC Bags With UV Without Liner | T22: 1329 | U22: 311025.87 | V22: 85x85x85 | W22: 0 | X22: 9 | Y22: 27992.33 | Z22: 9 | AA22: 27992.33 | AB22: 0 | AC22: 0 | AD22: 0 | AE22: 55984.66 | AF22: 0 | AG22: 24AAACO3087C1ZT | AH22: KGS | AI22: 63053200 | AJ22: Rs. | AK22: 1 | AL22: 1329 | AM22: India
A23: Sales - Direct Export - Mfg - U/B | B23: 50894795 | C23: =+'Trail Balance-JULY26'!D131 -> 50894795 | D23: =+GETPIVOTDATA("Amount",$A$16,"Type","Sales - Direct Export - Mfg - U/B")-C23 -> 0 | H23: 46029 | I23: Plastene India ltd - Unit 1-Sales | J23: Sales | K23: 137 | L23: Sales - Within State Manufactured Goods | M23: HPBL4/D/137 | N23: 46029 | O23: FG | P23: FIBC Bags | Q23: FIBC Bags | R23: JUMBO BAG | S23: FIBC Bags With UV Without Liner | T23: 826 | U23: 198710.82 | V23: 90x90x90 | W23: 0 | X23: 9 | Y23: 17883.97 | Z23: 9 | AA23: 17883.97 | AB23: 0 | AC23: 0 | AD23: 0 | AE23: 35767.94 | AF23: 0 | AG23: 24AAACO3087C1ZT | AH23: KGS | AI23: 63053200 | AJ23: Rs. | AK23: 1 | AL23: 826 | AM23: India
A24: Sales - Kasez - Trading - U/B | B24: 48000 | C24: =+'Trail Balance-JULY26'!D136 -> 48000 | D24: =+GETPIVOTDATA("Amount",$A$16,"Type","Sales - Kasez - Trading - U/B")-C24 -> 0 | H24: 46029 | I24: Plastene India ltd - Unit 1-Sales | J24: Sales | K24: 138 | L24: Sales - Within State - Traded Goods | M24: HPBL4/D/138 | N24: 46029 | O24: SF | P24: Yarn All | Q24: PP Yarn | R24: PP Filament Yarn | S24: PP MF Yarn Twisted 3000 Denier UV Deep Blue | T24: 88 | U24: 14321.12 | V24: PP MF Yarn Twisted 3000 Denier UV Deep Blue | W24: 15022.86 | X24: 2.5 | Y24: 358.03 | Z24: 2.5 | AA24: 358.03 | AB24: 0 | AC24: 0 | AD24: 0 | AE24: 716.06 | AF24: 0 | AG24: 24AAACO3087C1ZT | AH24: KGS | AI24: 54026300 | AJ24: Rs. | AK24: 1 | AL24: 88 | AM24: India
A25: Grand Total | B25: 1.3730849e+08 | H25: 46029 | I25: Qpac Ltd | J25: Export Sales | K25: HPBL4/E/52/26-27 | L25: Sales - Direct Export - Mfg - U/R | M25: HPBL4/E/52/26-27 | N25: 46029 | O25: FG | P25: FIBC Bags | Q25: FIBC Bags | R25: JUMBO BAG | S25: FIBC Bags With UV Without Liner | T25: 19351 | U25: 4855238.6 | V25: PP WOVEN BIG BAGS/SACKS | W25: 5166701.6 | X25: 0 | Y25: 0 | Z25: 0 | AA25: 0 | AB25: 18 | AC25: 873942.97 | AD25: 0 | AE25: 873942.97 | AF25: 0 | AG25: N.A. | AH25: KGS | AI25: 63053200 | AJ25: GBP | AK25: 123.7 | AL25: 19351 | AM25: United Kingdom
H26: 46029 | I26: Qpac Ltd | J26: Export Sales | K26: HPBL4/E/53/26-27 | L26: Sales - Direct Export - Mfg - U/R | M26: HPBL4/E/53/26-27 | N26: 46029 | O26: FG | P26: FIBC Bags | Q26: FIBC Bags | R26: JUMBO BAG | S26: FIBC Bags With UV Without Liner | T26: 19049 | U26: 4503569.4 | V26: PP WOVEN BIG BAGS/SACKS | W26: 4814856.7 | X26: 0 | Y26: 0 | Z26: 0 | AA26: 0 | AB26: 18 | AC26: 810642.47 | AD26: 0 | AE26: 810642.47 | AF26: 0 | AG26: N.A. | AH26: KGS | AI26: 63053200 | AJ26: GBP | AK26: 123.7 | AL26: 19049 | AM26: United Kingdom
H27: 46060 | I27: Plastene India ltd - Unit 1-Sales | J27: Sales | K27: 139 | L27: Sales - Within State - Traded Goods | M27: HPBL4/D/139 | N27: 46060 | O27: Stores/Spares | P27: MS Structure Items | Q27: Spares & Stores | R27: Stores & Consumables | S27: MS Pipe 4 C Class | T27: 1480 | U27: 71040 | V27: OLD/USED FABRIC ROLL PIPE | W27: 83756.16 | X27: 9 | Y27: 6393.6 | Z27: 9 | AA27: 6393.6 | AB27: 0 | AC27: 0 | AD27: 0 | AE27: 12787.2 | AF27: 0 | AG27: 24AAACO3087C1ZT | AH27: KGS | AI27: 73063090 | AJ27: Rs. | AK27: 1 | AL27: 1480 | AM27: India
H28: 46060 | I28: Plastene India ltd - Unit 1-Sales | J28: Sales | K28: 140 | L28: Sales - Waste & Scrape | M28: HPBL4/D/140 | N28: 46060 | O28: SF | P28: Wastage/Scrap | Q28: Wastage/Scrap | R28: HDPE/PP Plastik Waste | S28: PP/HD Wastage/Scrap | T28: 2078 | U28: 24936 | V28: PP/HD Wastage/Scrap | W28: 30012.97 | X28: 9 | Y28: 2244.24 | Z28: 9 | AA28: 2244.24 | AB28: 0 | AC28: 0 | AD28: 0 | AE28: 4488.48 | AF28: 588.49 | AG28: 24AAACO3087C1ZT | AH28: KGS | AI28: 39159029 | AJ28: Rs. | AK28: 1 | AL28: 2078 | AM28: India
H29: 46088 | I29: Plastene India ltd - Unit 1-Sales | J29: Sales | K29: 141 | L29: Sales - Within State - Traded Goods | M29: HPBL4/D/141 | N29: 46088 | O29: SF | P29: PP/PE Fabric | Q29: PP UL Fabric | R29: PP Woven Fabric | S29: PP UL Fabric With UV | T29: 291 | U29: 42992.34 | V29: MW 135 GSM | W29: 50687.97 | X29: 9 | Y29: 3869.31 | Z29: 9 | AA29: 3869.31 | AB29: 0 | AC29: 0 | AD29: 0 | AE29: 7738.62 | AF29: 0 | AG29: 24AAACO3087C1ZT | AH29: KGS | AI29: 39269080 | AJ29: Rs. | AK29: 1 | AL29: 291 | AM29: India
H30: 46088 | I30: Plastene India ltd - Unit 1-Sales | J30: Sales | K30: 142 | L30: Sales - Within State - Traded Goods | M30: HPBL4/D/142 | N30: 46088 | O30: SF | P30: Liners | Q30: LDPE/LLDPE Bags | R30: LLDPE Bags | S30: LDPE/LLDPE Bags/Liner | T30: 26 | U30: 4709.9 | V30: 135X266X67 MIC M/W | W30: 5552.97 | X30: 9 | Y30: 423.89 | Z30: 9 | AA30: 423.89 | AB30: 0 | AC30: 0 | AD30: 0 | AE30: 847.78 | AF30: 0 | AG30: 24AAACO3087C1ZT | AH30: KGS | AI30: 39232100 | AJ30: Rs. | AK30: 1 | AL30: 26 | AM30: India
H31: 46119 | I31: Plastene India ltd - Unit 1-Sales | J31: Sales | K31: 143 | L31: Sales - Within State Manufactured Goods | M31: HPBL4/D/143 | N31: 46119 | O31: FG | P31: FIBC Bags | Q31: FIBC Bags | R31: JUMBO BAG | S31: FIBC Bags With UV Without Liner | T31: 9965 | U31: 2073218.2 | V31: 86X86X108 | W31: 2444324.3 | X31: 9 | Y31: 186589.64 | Z31: 9 | AA31: 186589.64 | AB31: 0 | AC31: 0 | AD31: 0 | AE31: 373179.28 | AF31: 0 | AG31: 24AAACO3087C1ZT | AH31: KGS | AI31: 63053200 | AJ31: Rs. | AK31: 1 | AL31: 9965 | AM31: India
H32: 46119 | I32: Plastene India ltd - Unit 1-Sales | J32: Sales | K32: 144 | L32: Sales - Within State Manufactured Goods | M32: HPBL4/D/144 | N32: 46119 | O32: FG | P32: FIBC Bags | Q32: FIBC Bags | R32: JUMBO BAG | S32: FIBC Bags With UV Without Liner | T32: 2634 | U32: 585669.9 | V32: 85X85X90 | W32: 5614673.8 | X32: 9 | Y32: 52710.29 | Z32: 9 | AA32: 52710.29 | AB32: 0 | AC32: 0 | AD32: 0 | AE32: 105420.58 | AF32: 0 | AG32: 24AAACO3087C1ZT | AH32: KGS | AI32: 63053200 | AJ32: Rs. | AK32: 1 | AL32: 2634 | AM32: India
H33: 46119 | I33: Plastene India ltd - Unit 1-Sales | J33: Sales | K33: 144 | L33: Sales - Within State Manufactured Goods | M33: HPBL4/D/144 | N33: 46119 | O33: FG | P33: FIBC Bags | Q33: FIBC Bags | R33: JUMBO BAG | S33: FIBC Bags With UV Without Liner | T33: 4150 | U33: 932422 | V33: 90X90X90 | W33: 0 | X33: 9 | Y33: 83917.98 | Z33: 9 | AA33: 83917.98 | AB33: 0 | AC33: 0 | AD33: 0 | AE33: 167835.96 | AF33: 0 | AG33: 24AAACO3087C1ZT | AH33: KGS | AI33: 63053200 | AJ33: Rs. | AK33: 1 | AL33: 4150 | AM33: India
H34: 46119 | I34: Plastene India ltd - Unit 1-Sales | J34: Sales | K34: 144 | L34: Sales - Within State Manufactured Goods | M34: HPBL4/D/144 | N34: 46119 | O34: FG | P34: FIBC Bags | Q34: FIBC Bags | R34: JUMBO BAG | S34: FIBC Bags With UV Without Liner | T34: 875 | U34: 202781.25 | V34: 90X90X90 | W34: 0 | X34: 9 | Y34: 18250.31 | Z34: 9 | AA34: 18250.31 | AB34: 0 | AC34: 0 | AD34: 0 | AE34: 36500.62 | AF34: 0 | AG34: 24AAACO3087C1ZT | AH34: KGS | AI34: 63053200 | AJ34: Rs. | AK34: 1 | AL34: 875 | AM34: India
H35: 46119 | I35: Plastene India ltd - Unit 1-Sales | J35: Sales | K35: 144 | L35: Sales - Within State Manufactured Goods | M35: HPBL4/D/144 | N35: 46119 | O35: FG | P35: FIBC Bags | Q35: FIBC Bags | R35: JUMBO BAG | S35: FIBC Bags With UV Without Liner | T35: 433 | U35: 101360.97 | V35: 90X90X90 | W35: 0 | X35: 9 | Y35: 9122.49 | Z35: 9 | AA35: 9122.49 | AB35: 0 | AC35: 0 | AD35: 0 | AE35: 18244.98 | AF35: 0 | AG35: 24AAACO3087C1ZT | AH35: KGS | AI35: 63053200 | AJ35: Rs. | AK35: 1 | AL35: 433 | AM35: India
H36: 46119 | I36: Plastene India ltd - Unit 1-Sales | J36: Sales | K36: 144 | L36: Sales - Within State Manufactured Goods | M36: HPBL4/D/144 | N36: 46119 | O36: FG | P36: FIBC Bags | Q36: FIBC Bags | R36: JUMBO BAG | S36: FIBC Bags With UV Without Liner | T36: 878 | U36: 202800.44 | V36: 90X90X90 | W36: 0 | X36: 9 | Y36: 18252.04 | Z36: 9 | AA36: 18252.04 | AB36: 0 | AC36: 0 | AD36: 0 | AE36: 36504.08 | AF36: 0 | AG36: 24AAACO3087C1ZT | AH36: KGS | AI36: 63053200 | AJ36: Rs. | AK36: 1 | AL36: 878 | AM36: India
H37: 46119 | I37: Plastene India ltd - Unit 1-Sales | J37: Sales | K37: 144 | L37: Sales - Within State Manufactured Goods | M37: HPBL4/D/144 | N37: 46119 | O37: FG | P37: FIBC Bags | Q37: FIBC Bags | R37: JUMBO BAG | S37: FIBC Bags With UV Without Liner | T37: 895 | U37: 202914.4 | V37: 90X90X90 | W37: 0 | X37: 9 | Y37: 18262.3 | Z37: 9 | AA37: 18262.3 | AB37: 0 | AC37: 0 | AD37: 0 | AE37: 36524.6 | AF37: 0 | AG37: 24AAACO3087C1ZT | AH37: KGS | AI37: 63053200 | AJ37: Rs. | AK37: 1 | AL37: 895 | AM37: India
H38: 46119 | I38: Plastene India ltd - Unit 1-Sales | J38: Sales | K38: 144 | L38: Sales - Within State Manufactured Goods | M38: HPBL4/D/144 | N38: 46119 | O38: FG | P38: FIBC Bags | Q38: FIBC Bags | R38: JUMBO BAG | S38: FIBC Bags With UV Without Liner | T38: 1733 | U38: 405435.35 | V38: 90X90X90 | W38: 0 | X38: 9 | Y38: 36489.18 | Z38: 9 | AA38: 36489.18 | AB38: 0 | AC38: 0 | AD38: 0 | AE38: 72978.36 | AF38: 0 | AG38: 24AAACO3087C1ZT | AH38: KGS | AI38: 63053200 | AJ38: Rs. | AK38: 1 | AL38: 1733 | AM38: India
... H44: 46119 | I44: Plastene India ltd - Unit 1-Sales | J44: Sales | K44: 147 | L44: Sales - Within State Manufactured Goods | M44: HPBL4/D/147 | N44: 46119 | O44: FG | P44: FIBC Bags | Q44: FIBC Bags | R44: JUMBO BAG | S44: FIBC Bags With UV Without Liner | T44: 3736 | U44: 777274.8 | V44: 86X86X108 | W44: 0 | X44: 9 | Y44: 69954.73 | Z44: 9 | AA44: 69954.73 | AB44: 0 | AC44: 0 | AD44: 0 | AE44: 139909.46 | AF44: 0 | AG44: 24AAACO3087C1ZT | AH44: KGS | AI44: 63053200 | AJ44: Rs. | AK44: 1 | AL44: 3736 | AM44: India
H45: 46149 | I45: Agroszemek Kft | J45: Export Sales | K45: HPBL4/E/54/26-27 | L45: Sales - Direct Export - Mfg - U/R | M45: HPBL4/E/54/26-27 | N45: 46149 | O45: FG | P45: FIBC Bags | Q45: FIBC Bags | R45: JUMBO BAG | S45: FIBC Bags With UV With Liner | T45: 18272 | U45: 4039200 | V45: PP WOVEN BIG BAGS/SACKS WITH LINER | W45: 4039200 | X45: 0 | Y45: 0 | Z45: 0 | AA45: 0 | AB45: 18 | AC45: 727056 | AD45: 0 | AE45: 727056 | AF45: 0 | AG45: N.A. | AH45: KGS | AI45: 63053200 | AJ45: $ | AK45: 93.5 | AL45: 18272 | AM45: Hungary
H46: 46149 | I46: Plastene India ltd - Unit 1-Sales | J46: Sales | K46: 148 | L46: Sales - Within State Manufactured Goods | M46: HPBL4/D/148 | N46: 46149 | O46: FG | P46: FIBC Bags | Q46: FIBC Bags | R46: JUMBO BAG | S46: FIBC Bags With UV With Liner | T46: 4615 | U46: 990517.45 | V46: 62.5X62.5X145 | W46: 2291739.3 | X46: 9 | Y46: 89146.57 | Z46: 9 | AA46: 89146.57 | AB46: 0 | AC46: 0 | AD46: 0 | AE46: 178293.14 | AF46: 0 | AG46: 24AAACO3087C1ZT | AH46: KGS | AI46: 63053200 | AJ46: Rs. | AK46: 1 | AL46: 4615 | AM46: India
H47: 46149 | I47: Plastene India ltd - Unit 1-Sales | J47: Sales | K47: 148 | L47: Sales - Within State Manufactured Goods | M47: HPBL4/D/148 | N47: 46149 | O47: FG | P47: FIBC Bags | Q47: FIBC Bags | R47: JUMBO BAG | S47: FIBC Bags With UV With Liner | T47: 4525 | U47: 953281.75 | V47: 62.5X62.5X170 | W47: 0 | X47: 9 | Y47: 85795.36 | Z47: 9 | AA47: 85795.36 | AB47: 0 | AC47: 0 | AD47: 0 | AE47: 171590.72 | AF47: 0 | AG47: 24AAACO3087C1ZT | AH47: KGS | AI47: 63053200 | AJ47: Rs. | AK47: 1 | AL47: 4525 | AM47: India
H48: 46149 | I48: Plastene India ltd - Unit 1-Sales | J48: Sales | K48: 149 | L48: Sales - Within State - Traded Goods | M48: HPBL4/D/149 | N48: 46149 | O48: FG | P48: FIBC WIP | Q48: FIBC WIP | R48: FIBC WIP | S48: PP Woven Fabric | T48: 710 | U48: 19880 | V48: DEAD STOCK FABRIC RP PURPOSE | W48: 23438.52 | X48: 9 | Y48: 1789.2 | Z48: 9 | AA48: 1789.2 | AB48: 0 | AC48: 0 | AD48: 0 | AE48: 3578.4 | AF48: 0 | AG48: 24AAACO3087C1ZT | AH48: KGS | AI48: 39269080 | AJ48: Rs. | AK48: 1 | AL48: 710 | AM48: India
H49: 46149 | I49: Plastene India ltd - Unit 1-Sales | J49: Sales | K49: 150 | L49: Sales - Within State Manufactured Goods | M49: HPBL4/D/150 | N49: 46149 | O49: FG | P49: FIBC Bags | Q49: FIBC Bags | R49: JUMBO BAG | S49: FIBC Bags With UV With Liner | T49: 10138 | U49: 2095423.2 | V49: 62.5X62.5X150 | W49: 2470504 | X49: 9 | Y49: 188588.09 | Z49: 9 | AA49: 188588.09 | AB49: 0 | AC49: 0 | AD49: 0 | AE49: 377176.18 | AF49: 0 | AG49: 24AAACO3087C1ZT | AH49: KGS | AI49: 63053200 | AJ49: Rs. | AK49: 1 | AL49: 10138 | AM49: India
H50: 46180 | I50: Plastene India ltd - Unit 1-Sales | J50: Sales | K50: 151 | L50: Sales - Within State - Traded Goods | M50: HPBL4/D/151 | N50: 46180 | O50: RM Consumables | P50: Ink | Q50: Thinner | R50: Thinner | S50: Thinner Vyankatesh Thinner | T50: 170 | U50: 18360 | V50: Thinner Vyankatesh Thinner | W50: 21646.44 | X50: 9 | Y50: 1652.4 | Z50: 9 | AA50: 1652.4 | AB50: 0 | AC50: 0 | AD50: 0 | AE50: 3304.8 | AF50: 0 | AG50: 24AAACO3087C1ZT | AH50: KGS | AI50: 38140011 | AJ50: Rs. | AK50: 1 | AL50: 170 | AM50: India
H51: 46210 | I51: Plastene India ltd - Unit 1-Sales | J51: Sales | K51: 152 | L51: Sales - Within State - Traded Goods | M51: HPBL4/D/152 | N51: 46210 | O51: Stores/Spares | P51: MS Structure Items | Q51: Spares & Stores | R51: Stores & Consumables | S51: MS Pipe 4 C Class | T51: 1291 | U51: 61968 | V51: OLD/USED FABRIC ROLL PIPE | W51: 73060.27 | X51: 9 | Y51: 5577.12 | Z51: 9 | AA51: 5577.12 | AB51: 0 | AC51: 0 | AD51: 0 | AE51: 11154.24 | AF51: 0 | AG51: 24AAACO3087C1ZT | AH51: KGS | AI51: 73063090 | AJ51: Rs. | AK51: 1 | AL51: 1291 | AM51: India
H52: 46210 | I52: Plastene India ltd - Unit 1-Sales | J52: Sales | K52: 153 | L52: Sales - Waste & Scrape | M52: HPBL4/D/153 | N52: 46210 | O52: SF | P52: Wastage/Scrap | Q52: Wastage/Scrap | R52: HDPE/PP Plastik Waste | S52: PP/HD Wastage/Scrap | T52: 1884 | U52: 22608 | V52: PP/HD Wastage/Scrap | W52: 27210.99 | X52: 9 | Y52: 2034.72 | Z52: 9 | AA52: 2034.72 | AB52: 0 | AC52: 0 | AD52: 0 | AE52: 4069.44 | AF52: 533.55 | AG52: 24AAACO3087C1ZT | AH52: KGS | AI52: 39159029 | AJ52: Rs. | AK52: 1 | AL52: 1884 | AM52: India
H53: 46210 | I53: Plastene India ltd - Unit 1-Sales | J53: Sales | K53: 154 | L53: Sales - Within State - Traded Goods | M53: HPBL4/D/154 | N53: 46210 | O53: FG | P53: FIBC WIP | Q53: FIBC WIP | R53: FIBC WIP | S53: PP Woven Fabric | T53: 795 | U53: 22260 | V53: dead stock fabric rp purpose | W53: 26244.54 | X53: 9 | Y53: 2003.4 | Z53: 9 | AA53: 2003.4 | AB53: 0 | AC53: 0 | AD53: 0 | AE53: 4006.8 | AF53: 0 | AG53: 24AAACO3087C1ZT | AH53: KGS | AI53: 39269080 | AJ53: Rs. | AK53: 1 | AL53: 795 | AM53: India
H54: 46210 | I54: Plastene India ltd - Unit 1-Sales | J54: Sales | K54: 155 | L54: Sales - Within State Manufactured Goods | M54: HPBL4/D/155 | N54: 46210 | O54: FG | P54: FIBC Bags | Q54: FIBC Bags | R54: JUMBO BAG | S54: FIBC Bags With UV Without Liner | T54: 2705 | U54: 556878.35 | V54: 75X80X95 | W54: 2709620.2 | X54: 9 | Y54: 50119.05 | Z54: 9 | AA54: 50119.05 | AB54: 0 | AC54: 0 | AD54: 0 | AE54: 100238.1 | AF54: 0 | AG54: 24AAACO3087C1ZT | AH54: KGS | AI54: 63053200 | AJ54: Rs. | AK54: 1 | AL54: 2705 | AM54: India
H55: 46210 | I55: Plastene India ltd - Unit 1-Sales | J55: Sales | K55: 155 | L55: Sales - Within State Manufactured Goods | M55: HPBL4/D/155 | N55: 46210 | O55: FG | P55: FIBC Bags | Q55: FIBC Bags | R55: JUMBO BAG | S55: FIBC Bags With UV Without Liner | T55: 1357 | U55: 286639.11 | V55: 75X80X95 | W55: 0 | X55: 9 | Y55: 25797.52 | Z55: 9 | AA55: 25797.52 | AB55: 0 | AC55: 0 | AD55: 0 | AE55: 51595.04 | AF55: 0 | AG55: 24AAACO3087C1ZT | AH55: KGS | AI55: 63053200 | AJ55: Rs. | AK55: 1 | AL55: 1357 | AM55: India
H56: 46210 | I56: Plastene India ltd - Unit 1-Sales | J56: Sales | K56: 155 | L56: Sales - Within State Manufactured Goods | M56: HPBL4/D/155 | N56: 46210 | O56: FG | P56: FIBC Bags | Q56: FIBC Bags | R56: JUMBO BAG | S56: FIBC Bags With UV Without Liner | T56: 1819 | U56: 382062.76 | V56: 75X80X95 | W56: 0 | X56: 9 | Y56: 34385.65 | Z56: 9 | AA56: 34385.65 | AB56: 0 | AC56: 0 | AD56: 0 | AE56: 68771.3 | AF56: 0 | AG56: 24AAACO3087C1ZT | AH56: KGS | AI56: 63053200 | AJ56: Rs. | AK56: 1 | AL56: 1819 | AM56: India
H57: 46210 | I57: Plastene India ltd - Unit 1-Sales | J57: Sales | K57: 155 | L57: Sales - Within State Manufactured Goods | M57: HPBL4/D/155 | N57: 46210 | O57: FG | P57: FIBC Bags | Q57: FIBC Bags | R57: JUMBO BAG | S57: FIBC Bags With UV Without Liner | T57: 891 | U57: 191262.06 | V57: 75X80X95 | W57: 0 | X57: 9 | Y57: 17213.59 | Z57: 9 | AA57: 17213.59 | AB57: 0 | AC57: 0 | AD57: 0 | AE57: 34427.18 | AF57: 0 | AG57: 24AAACO3087C1ZT | AH57: KGS | AI57: 63053200 | AJ57: Rs. | AK57: 1 | AL57: 891 | AM57: India
... H59: 46210 | I59: Plastene India ltd - Unit 1-Sales | J59: Sales | K59: 155 | L59: Sales - Within State Manufactured Goods | M59: HPBL4/D/155 | N59: 46210 | O59: FG | P59: FIBC Bags | Q59: FIBC Bags | R59: JUMBO BAG | S59: FIBC Bags With UV Without Liner | T59: 508 | U59: 100589.08 | V59: 75X80X95 | W59: 0 | X59: 9 | Y59: 9053.02 | Z59: 9 | AA59: 9053.02 | AB59: 0 | AC59: 0 | AD59: 0 | AE59: 18106.04 | AF59: 0 | AG59: 24AAACO3087C1ZT | AH59: KGS | AI59: 63053200 | AJ59: Rs. | AK59: 1 | AL59: 508 | AM59: India
H60: 46272 | I60: Agroszemek Kft | J60: Export Sales | K60: HPBL4/E/56/26-27 | L60: Sales - Direct Export - Mfg - U/B | M60: HPBL4/E/56/26-27 | N60: 46272 | O60: FG | P60: FIBC Bags | Q60: FIBC Bags | R60: JUMBO BAG | S60: FIBC Bags With UV With Liner | T60: 18338 | U60: 4443120 | V60: PP WOVEN BIG BAGS/SACKS WITH LINER | W60: 4443120 | X60: 0 | Y60: 0 | Z60: 0 | AA60: 0 | AB60: 0 | AC60: 0 | AD60: 0 | AE60: 0 | AF60: 0 | AG60: N.A. | AH60: KGS | AI60: 63053200 | AJ60: $ | AK60: 93.5 | AL60: 18338 | AM60: Hungary
H61: 46272 | I61: Cesur France | J61: Export Sales | K61: HPBL4/E/55/26-27 | L61: Sales - Direct Export - Mfg - U/B | M61: HPBL4/E/55/26-27 | N61: 46272 | O61: FG | P61: FIBC Bags | Q61: FIBC Bags | R61: JUMBO BAG | S61: FIBC Bags With UV With Liner | T61: 15412 | U61: 4082257.9 | V61: PP WOVEN BIG BAGS/SACKS WITH LINER | W61: 4444454.5 | X61: 0 | Y61: 0 | Z61: 0 | AA61: 0 | AB61: 0 | AC61: 0 | AD61: 0 | AE61: 0 | AF61: 0 | AG61: N.A. | AH61: KGS | AI61: 63053200 | AK61: 105.4 | AL61: 15412 | AM61: France
H62: 46272 | I62: Oswal Extrusion Ltd- KASEZ-Sales | J62: SALES (FOREX) | K62: HPBL4/E/57/26-27 | L62: Sales - Kasez - Trading - U/B | M62: HPBL4/E/57/26-27 | N62: 46272 | O62: Consumables | P62: Consumables | Q62: Consumables | R62: Stores & Consumables | S62: Hotmelt ( Glue ) | T62: 100 | U62: 32000 | V62: HOTMELT GLUE 100 KG | W62: 31968 | X62: 0 | Y62: 0 | Z62: 0 | AA62: 0 | AB62: 0 | AC62: 0 | AD62: 0 | AE62: 0 | AF62: 0 | AG62: 24AAACO7290H4ZB | AH62: KGS | AI62: 35069999 | AJ62: Rs. | AK62: 1 | AL62: 100 | AM62: India
H63: 46272 | I63: Plastene India ltd - Unit 1-Sales | J63: Sales | K63: 156 | L63: Sales - Within State - Traded Goods | M63: HPBL4/D/156 | N63: 46272 | O63: FG | P63: FIBC WIP | Q63: FIBC WIP | R63: FIBC WIP | S63: PP Webbing | T63: 62 | U63: 9268.38 | V63: COLOUR WEBBING | W63: 10927.41 | X63: 9 | Y63: 834.15 | Z63: 9 | AA63: 834.15 | AB63: 0 | AC63: 0 | AD63: 0 | AE63: 1668.3 | AF63: 0 | AG63: 24AAACO3087C1ZT | AH63: KGS | AI63: 39269080 | AJ63: Rs. | AK63: 1 | AL63: 62 | AM63: India
H64: 46272 | I64: Rafia Industrial S.A. | J64: Export Sales | K64: HPBL4/E/58/26-27 | L64: Sales - Direct Export - Mfg - U/B | M64: HPBL4/E/58/26-27 | N64: 46272 | O64: FG | P64: FIBC Bags | Q64: FIBC Bags | R64: JUMBO BAG | S64: FIBC Bags With UV With Liner | T64: 18962 | U64: 4924424.3 | V64: PP WOVEN BIG BAGS/SACKS WITH LINER | W64: 5317124.3 | X64: 0 | Y64: 0 | Z64: 0 | AA64: 0 | AB64: 0 | AC64: 0 | AD64: 0 | AE64: 0 | AF64: 0 | AG64: N.A. | AH64: KGS | AI64: 63053200 | AJ64: $ | AK64: 93.5 | AL64: 18962 | AM64: SPAIN
H65: 46272 | I65: Rafia Industrial S.A. | J65: Export Sales | K65: HPBL4/E/59/26-27 | L65: Sales - Direct Export - Mfg - U/B | M65: HPBL4/E/59/26-27 | N65: 46272 | O65: FG | P65: FIBC Bags | Q65: FIBC Bags | R65: JUMBO BAG | S65: FIBC Bags With UV Without Liner | T65: 18805 | U65: 4186182 | V65: PP WOVEN BIG BAGS/SACKS | W65: 4578882 | X65: 0 | Y65: 0 | Z65: 0 | AA65: 0 | AB65: 0 | AC65: 0 | AD65: 0 | AE65: 0 | AF65: 0 | AG65: N.A. | AH65: KGS | AI65: 63053200 | AJ65: $ | AK65: 93.5 | AL65: 18805 | AM65: SPAIN
H66: 46272 | I66: Rafia Industrial S.A. | J66: Export Sales | K66: HPBL4/E/60/26-27 | L66: Sales - Direct Export - Mfg - U/B | M66: HPBL4/E/60/26-27 | N66: 46272 | O66: FG | P66: FIBC Bags | Q66: FIBC Bags | R66: JUMBO BAG | S66: FIBC Bags With UV With Liner | T66: 19241 | U66: 4767508.9 | V66: PP WOVEN BIG BAGS/SACKS WITH LINER | W66: 5160208.9 | X66: 0 | Y66: 0 | Z66: 0 | AA66: 0 | AB66: 0 | AC66: 0 | AD66: 0 | AE66: 0 | AF66: 0 | AG66: N.A. | AH66: KGS | AI66: 63053200 | AJ66: $ | AK66: 93.5 | AL66: 19241 | AM66: SPAIN
H67: 46272 | I67: Rafia Industrial S.A. | J67: Export Sales | K67: HPBL4/E/61/26-27 | L67: Sales - Direct Export - Mfg - U/B | M67: HPBL4/E/61/26-27 | N67: 46272 | O67: FG | P67: FIBC Bags | Q67: FIBC Bags | R67: JUMBO BAG | S67: FIBC Bags With UV With Liner | T67: 18985 | U67: 3107940 | V67: PP WOVEN BIG BAGS/SACKS WITH LINER | W67: 3500640 | X67: 0 | Y67: 0 | Z67: 0 | AA67: 0 | AB67: 0 | AC67: 0 | AD67: 0 | AE67: 0 | AF67: 0 | AG67: N.A. | AH67: KGS | AI67: 63053200 | AJ67: $ | AK67: 93.5 | AL67: 18985 | AM67: SPAIN
H68: 46272 | I68: Rafia Industrial S.A. | J68: Export Sales | K68: HPBL4/E/62/26-27 | L68: Sales - Direct Export - Mfg - U/B | M68: HPBL4/E/62/26-27 | N68: 46272 | O68: FG | P68: FIBC Bags | Q68: FIBC Bags | R68: JUMBO BAG | S68: FIBC Bags With UV With Liner | T68: 19141 | U68: 4303898.5 | V68: PP WOVEN BIG BAGS/SACKS WITH LINER | W68: 4696598.5 | X68: 0 | Y68: 0 | Z68: 0 | AA68: 0 | AB68: 0 | AC68: 0 | AD68: 0 | AE68: 0 | AF68: 0 | AG68: N.A. | AH68: KGS | AI68: 63053200 | AJ68: $ | AK68: 93.5 | AL68: 19141 | AM68: SPAIN
H69: 46302 | I69: Industria Sulfuria S.A. | J69: Export Sales | K69: HPBL4/E/63/26-27 | L69: Sales - Direct Export - Mfg - U/B | M69: HPBL4/E/63/26-27 | N69: 46302 | O69: FG | P69: FIBC Bags | Q69: FIBC Bags | R69: JUMBO BAG | S69: FIBC Bags With UV With Liner | T69: 20148 | U69: 4623909.7 | V69: PP WOVEN BIG BAGS/SACKS WITH LINER | W69: 5313792 | X69: 0 | Y69: 0 | Z69: 0 | AA69: 0 | AB69: 0 | AC69: 0 | AD69: 0 | AE69: 0 | AF69: 0 | AG69: N.A. | AH69: KGS | AI69: 63053200 | AJ69: $ | AK69: 93.5 | AL69: 20148 | AM69: Uruguay
H70: 46302 | I70: Plastene India ltd - Unit 1-Sales | J70: Sales | K70: 157 | L70: Sales - Within State - Traded Goods | M70: HPBL4/D/157 | N70: 46302 | O70: SF | P70: Webbing | Q70: PP Webbing | R70: PP Webbing | S70: Webbing | T70: 191.9 | U70: 28687.13 | V70: COLOUR WEBBING | W70: 33822.12 | X70: 9 | Y70: 2581.84 | Z70: 9 | AA70: 2581.84 | AB70: 0 | AC70: 0 | AD70: 0 | AE70: 5163.68 | AF70: 0 | AG70: 24AAACO3087C1ZT | AH70: KGS | AI70: 39269080 | AJ70: Rs. | AK70: 1 | AL70: 191.9 | AM70: India
H71: 46302 | I71: Plastene India ltd - Unit 1-Sales | J71: Sales | K71: 158 | L71: Sales - Within State - Traded Goods | M71: HPBL4/D/158 | N71: 46302 | O71: SF | P71: Yarn All | Q71: PP Yarn | R71: PP Filament Yarn | S71: PP MF Yarn Twisted 3000 Denier UV Deep Blue | T71: 44 | U71: 7017.56 | V71: PP MF Yarn Twisted 3000 Denier UV Deep Blue | W71: 7361.42 | X71: 2.5 | Y71: 175.44 | Z71: 2.5 | AA71: 175.44 | AB71: 0 | AC71: 0 | AD71: 0 | AE71: 350.88 | AF71: 0 | AG71: 24AAACO3087C1ZT | AH71: KGS | AI71: 54026930 | AJ71: Rs. | AK71: 1 | AL71: 44 | AM71: India
H72: 46333 | I72: Plastene India ltd - Unit 1-Sales | J72: Sales | K72: 159 | L72: Sales - Within State - Traded Goods | M72: HPBL4/D/159 | N72: 46333 | O72: Stores/Spares | P72: MS Structure Items | Q72: Spares & Stores | R72: Stores & Consumables | S72: MS Pipe 4 C Class | T72: 1047 | U72: 50256 | V72: OLD/USED FABRIC MS PIP | W72: 59251.82 | X72: 9 | Y72: 4523.04 | Z72: 9 | AA72: 4523.04 | AB72: 0 | AC72: 0 | AD72: 0 | AE72: 9046.08 | AF72: 0 | AG72: 24AAACO3087C1ZT | AH72: KGS | AI72: 73063090 | AJ72: Rs. | AK72: 1 | AL72: 1047 | AM72: India
H73: 46333 | I73: Plastene India ltd - Unit 1-Sales | J73: Sales | K73: 160 | L73: Sales - Waste & Scrape | M73: HPBL4/D/160 | N73: 46333 | O73: SF | P73: Wastage/Scrap | Q73: Wastage/Scrap | R73: HDPE/PP Plastik Waste | S73: PP/HD Wastage/Scrap | T73: 3493 | U73: 41916 | V73: PP/HD Wastage/Scrap | W73: 50450.1 | X73: 9 | Y73: 3772.44 | Z73: 9 | AA73: 3772.44 | AB73: 0 | AC73: 0 | AD73: 0 | AE73: 7544.88 | AF73: 989.22 | AG73: 24AAACO3087C1ZT | AH73: KGS | AI73: 39159029 | AJ73: Rs. | AK73: 1 | AL73: 3493 | AM73: India
H74: 46333 | I74: Plastene India ltd - Unit 1-Sales | J74: Sales | K74: 161 | L74: Sales - Within State Manufactured Goods | M74: HPBL4/D/161 | N74: 46333 | O74: FG | P74: FIBC Bags | Q74: FIBC Bags | R74: JUMBO BAG | S74: FIBC Bags With UV With Liner | T74: 1421 | U74: 303980.32 | V74: 62.5X62.5X150 | W74: 1869394.2 | X74: 9 | Y74: 27358.23 | Z74: 9 | AA74: 27358.23 | AB74: 0 | AC74: 0 | AD74: 0 | AE74: 54716.46 | AF74: 0 | AG74: 24AAACO3087C1ZT | AH74: KGS | AI74: 63053200 | AJ74: Rs. | AK74: 1 | AL74: 1421 | AM74: India
H75: 46333 | I75: Plastene India ltd - Unit 1-Sales | J75: Sales | K75: 161 | L75: Sales - Within State Manufactured Goods | M75: HPBL4/D/161 | N75: 46333 | O75: FG | P75: FIBC Bags | Q75: FIBC Bags | R75: JUMBO BAG | S75: FIBC Bags With UV With Liner | T75: 1725 | U75: 403339.5 | V75: 90X90X150 | W75: 0 | X75: 9 | Y75: 36300.56 | Z75: 9 | AA75: 36300.56 | AB75: 0 | AC75: 0 | AD75: 0 | AE75: 72601.12 | AF75: 0 | AG75: 24AAACO3087C1ZT | AH75: KGS | AI75: 63053200 | AJ75: Rs. | AK75: 1 | AL75: 1725 | AM75: India
H76: 46333 | I76: Plastene India ltd - Unit 1-Sales | J76: Sales | K76: 161 | L76: Sales - Within State Manufactured Goods | M76: HPBL4/D/161 | N76: 46333 | O76: FG | P76: FIBC Bags | Q76: FIBC Bags | R76: JUMBO BAG | S76: FIBC Bags With UV Without Liner | T76: 4532 | U76: 878256.28 | V76: 75X80X95 | W76: 0 | X76: 9 | Y76: 79043.07 | Z76: 9 | AA76: 79043.07 | AB76: 0 | AC76: 0 | AD76: 0 | AE76: 158086.14 | AF76: 0 | AG76: 24AAACO3087C1ZT | AH76: KGS | AI76: 63053200 | AJ76: Rs. | AK76: 1 | AL76: 4532 | AM76: India
H77: 13-07-2026 | I77: Rafia Industrial S.A. | J77: Export Sales | K77: HPBL4/E/64/26-27 | L77: Sales - Direct Export - Mfg - U/B | M77: HPBL4/E/64/26-27 | N77: 13-07-2026 | O77: FG | P77: FIBC Bags | Q77: FIBC Bags | R77: JUMBO BAG | S77: FIBC Bags With UV With Liner | T77: 18757 | U77: 4084080 | V77: PP WOVEN BIG BAGS/SACKS WITH LINER | W77: 4476780 | X77: 0 | Y77: 0 | Z77: 0 | AA77: 0 | AB77: 0 | AC77: 0 | AD77: 0 | AE77: 0 | AF77: 0 | AG77: N.A. | AH77: KGS | AI77: 63053200 | AJ77: $ | AK77: 93.5 | AL77: 18757 | AM77: SPAIN
H78: 14-07-2026 | I78: K.P. Woven Pvt Ltd - Unit 3 -Sales | J78: Export Sales | K78: HPBL4/E/66/26-27 | L78: Sales - Kasez - Mfg - U/B | M78: HPBL4/E/66/26-27 | N78: 14-07-2026 | O78: FG | P78: FIBC Bags | Q78: FIBC Bags | R78: JUMBO BAG | S78: FIBC Bags With UV With Liner | T78: 3974 | U78: 833652.55 | V78: PP WOVEN BIG BAGS | W78: 2056898.1 | X78: 0 | Y78: 0 | Z78: 0 | AA78: 0 | AB78: 0 | AC78: 0 | AD78: 0 | AE78: 0 | AF78: 0 | AG78: 24AAECK6307M2ZE | AH78: KGS | AI78: 63053200 | AJ78: $ | AK78: 93.5 | AL78: 3974 | AM78: India
H79: 14-07-2026 | I79: K.P. Woven Pvt Ltd - Unit 3 -Sales | J79: Export Sales | K79: HPBL4/E/66/26-27 | L79: Sales - Kasez - Mfg - U/B | M79: HPBL4/E/66/26-27 | N79: 14-07-2026 | O79: FG | P79: FIBC Bags | Q79: FIBC Bags | R79: JUMBO BAG | S79: FIBC Bags With UV Without Liner | T79: 4993 | U79: 1047414.1 | V79: PP WOVEN BIG BAGS | W79: 0 | X79: 0 | Y79: 0 | Z79: 0 | AA79: 0 | AB79: 0 | AC79: 0 | AD79: 0 | AE79: 0 | AF79: 0 | AG79: 24AAECK6307M2ZE | AH79: KGS | AI79: 63053200 | AJ79: $ | AK79: 93.5 | AL79: 4993 | AM79: India
H80: 14-07-2026 | I80: K.P. Woven Pvt Ltd - Unit 3 -Sales | J80: Export Sales | K80: HPBL4/E/66/26-27 | L80: Sales - Kasez - Mfg - U/B | M80: HPBL4/E/66/26-27 | N80: 14-07-2026 | O80: FG | P80: FIBC Bags | Q80: FIBC Bags | R80: JUMBO BAG | S80: FIBC Bags With UV Without Liner | T80: 848 | U80: 177890.3 | V80: PP WOVEN BIG BAGS | W80: 0 | X80: 0 | Y80: 0 | Z80: 0 | AA80: 0 | AB80: 0 | AC80: 0 | AD80: 0 | AE80: 0 | AF80: 0 | AG80: 24AAECK6307M2ZE | AH80: KGS | AI80: 63053200 | AJ80: $ | AK80: 93.5 | AL80: 848 | AM80: India
H81: 14-07-2026 | I81: Oswal Extrusion Ltd- KASEZ-Sales | J81: SALES (FOREX) | K81: HPBL4/E/65/26-27 | L81: Sales - Kasez - Trading - U/B | M81: HPBL4/E/65/26-27 | N81: 14-07-2026 | O81: Consumables | P81: Consumables | Q81: Consumables | R81: Stores & Consumables | S81: Hotmelt ( Glue ) | T81: 50 | U81: 16000 | V81: Hotmelt ( Glue ) | W81: 15984 | Y81: 0 | AA81: 0 | AC81: 0 | AD81: 0 | AE81: 0 | AF81: 0 | AG81: 24AAACO7290H4ZB | AH81: KGS | AI81: 35069999 | AJ81: Rs. | AK81: 1 | AL81: 50 | AM81: India
H82: 14-07-2026 | I82: Plastene India ltd - Unit 1-Sales | J82: Sales | K82: 162 | L82: Sales - Waste & Scrape | M82: HPBL4/D/162 | N82: 14-07-2026 | O82: SF | P82: Wastage/Scrap | Q82: Wastage/Scrap | R82: HDPE/PP Plastik Waste | S82: PP/HD Wastage/Scrap | T82: 2902 | U82: 34824 | V82: PP/HD Wastage/Scrap | W82: 41914.17 | X82: 9 | Y82: 3134.16 | Z82: 9 | AA82: 3134.16 | AB82: 0 | AC82: 0 | AD82: 0 | AE82: 6268.32 | AF82: 821.85 | AG82: 24AAACO3087C1ZT | AH82: KGS | AI82: 39159029 | AJ82: Rs. | AK82: 1 | AL82: 2902 | AM82: India
H83: 14-07-2026 | I83: Plastene India ltd - Unit 1-Sales | J83: Sales | K83: 163 | L83: Sales - Within State - Traded Goods | M83: HPBL4/D/163 | N83: 14-07-2026 | O83: FG | P83: FIBC WIP | Q83: FIBC WIP | R83: FIBC WIP | S83: PP Woven Fabric | T83: 2018 | U83: 56504 | V83: DEAD STOCK FABRIC RP PURPOSE | W83: 66618.22 | X83: 9 | Y83: 5085.36 | Z83: 9 | AA83: 5085.36 | AB83: 0 | AC83: 0 | AD83: 0 | AE83: 10170.72 | AF83: 0 | AG83: 24AAACO3087C1ZT | AH83: KGS | AI83: 39269080 | AJ83: Rs. | AK83: 1 | AL83: 2018 | AM83: India
H84: 15-07-2026 | I84: Plastene India ltd - Unit 1-Sales | J84: Sales | K84: 164 | L84: Sales - Within State Manufactured Goods | M84: HPBL4/D/164 | N84: 15-07-2026 | O84: FG | P84: FIBC Bags | Q84: FIBC Bags | R84: JUMBO BAG | S84: FIBC Bags With UV Without Liner | T84: 893 | U84: 191235.95 | V84: 75X80X95 | W84: 1697947.1 | X84: 9 | Y84: 17211.24 | Z84: 9 | AA84: 17211.24 | AB84: 0 | AC84: 0 | AD84: 0 | AE84: 34422.48 | AF84: 0 | AG84: 24AAACO3087C1ZT | AH84: KGS | AI84: 63053200 | AJ84: Rs. | AK84: 1 | AL84: 893 | AM84: India
H85: 15-07-2026 | I85: Plastene India ltd - Unit 1-Sales | J85: Sales | K85: 164 | L85: Sales - Within State Manufactured Goods | M85: HPBL4/D/164 | N85: 15-07-2026 | O85: FG | P85: FIBC Bags | Q85: FIBC Bags | R85: JUMBO BAG | S85: FIBC Bags With UV Without Liner | T85: 1795 | U85: 382370.9 | V85: 75X80X95 | W85: 0 | X85: 9 | Y85: 34413.38 | Z85: 9 | AA85: 34413.38 | AB85: 0 | AC85: 0 | AD85: 0 | AE85: 68826.76 | AF85: 0 | AG85: 24AAACO3087C1ZT | AH85: KGS | AI85: 63053200 | AJ85: Rs. | AK85: 1 | AL85: 1795 | AM85: India
H86: 15-07-2026 | I86: Plastene India ltd - Unit 1-Sales | J86: Sales | K86: 164 | L86: Sales - Within State Manufactured Goods | M86: HPBL4/D/164 | N86: 15-07-2026 | O86: FG | P86: FIBC Bags | Q86: FIBC Bags | R86: JUMBO BAG | S86: FIBC Bags With UV Without Liner | T86: 1006 | U86: 195184.12 | V86: 75X80X95 | W86: 0 | X86: 9 | Y86: 17566.57 | Z86: 9 | AA86: 17566.57 | AB86: 0 | AC86: 0 | AD86: 0 | AE86: 35133.14 | AF86: 0 | AG86: 24AAACO3087C1ZT | AH86: KGS | AI86: 63053200 | AJ86: Rs. | AK86: 1 | AL86: 1006 | AM86: India
H87: 15-07-2026 | I87: Plastene India ltd - Unit 1-Sales | J87: Sales | K87: 164 | L87: Sales - Within State Manufactured Goods | M87: HPBL4/D/164 | N87: 15-07-2026 | O87: FG | P87: FIBC Bags | Q87: FIBC Bags | R87: JUMBO BAG | S87: FIBC Bags With UV Without Liner | T87: 504 | U87: 100638.72 | V87: 75X80X95 | W87: 0 | X87: 9 | Y87: 9057.48 | Z87: 9 | AA87: 9057.48 | AB87: 0 | AC87: 0 | AD87: 0 | AE87: 18114.96 | AF87: 0 | AG87: 24AAACO3087C1ZT | AH87: KGS | AI87: 63053200 | AJ87: Rs. | AK87: 1 | AL87: 504 | AM87: India
H88: 15-07-2026 | I88: Plastene India ltd - Unit 1-Sales | J88: Sales | K88: 164 | L88: Sales - Within State Manufactured Goods | M88: HPBL4/D/164 | N88: 15-07-2026 | O88: FG | P88: FIBC Bags | Q88: FIBC Bags | R88: JUMBO BAG | S88: FIBC Bags With UV Without Liner | T88: 448 | U88: 92848 | V88: 75X80X95 | W88: 0 | X88: 9 | Y88: 8356.32 | Z88: 9 | AA88: 8356.32 | AB88: 0 | AC88: 0 | AD88: 0 | AE88: 16712.64 | AF88: 0 | AG88: 24AAACO3087C1ZT | AH88: KGS | AI88: 63053200 | AJ88: Rs. | AK88: 1 | AL88: 448 | AM88: India
H89: 15-07-2026 | I89: Plastene India ltd - Unit 1-Sales | J89: Sales | K89: 164 | L89: Sales - Within State Manufactured Goods | M89: HPBL4/D/164 | N89: 15-07-2026 | O89: FG | P89: FIBC Bags | Q89: FIBC Bags | R89: JUMBO BAG | S89: FIBC Bags With UV Without Liner | T89: 450 | U89: 95575.5 | V89: 75X80X95 | W89: 0 | X89: 9 | Y89: 8601.8 | Z89: 9 | AA89: 8601.8 | AB89: 0 | AC89: 0 | AD89: 0 | AE89: 17203.6 | AF89: 0 | AG89: 24AAACO3087C1ZT | AH89: KGS | AI89: 63053200 | AJ89: Rs. | AK89: 1 | AL89: 450 | AM89: India
H90: 15-07-2026 | I90: Plastene India ltd - Unit 1-Sales | J90: Sales | K90: 164 | L90: Sales - Within State Manufactured Goods | M90: HPBL4/D/164 | N90: 15-07-2026 | O90: FG | P90: FIBC Bags | Q90: FIBC Bags | R90: JUMBO BAG | S90: FIBC Bags With UV Without Liner | T90: 1799 | U90: 382305.49 | V90: 75X80X95 | W90: 0 | X90: 9 | Y90: 34407.49 | Z90: 9 | AA90: 34407.49 | AB90: 0 | AC90: 0 | AD90: 0 | AE90: 68814.98 | AF90: 0 | AG90: 24AAACO3087C1ZT | AH90: KGS | AI90: 63053200 | AJ90: Rs. | AK90: 1 | AL90: 1799 | AM90: India
H91: 15-07-2026 | I91: Plastene India ltd - Unit 1-Sales | J91: Sales | K91: 165 | L91: Sales - Within State - Traded Goods | M91: HPBL4/D/165 | N91: 15-07-2026 | O91: Stores/Spares | P91: MS Structure Items | Q91: Spares & Stores | R91: Stores & Consumables | S91: MS Pipe 4 C Class | T91: 964 | U91: 46272 | V91: OLD/USED FABRIC ROLL PIPE | W91: 54554.69 | X91: 9 | Y91: 4164.48 | Z91: 9 | AA91: 4164.48 | AB91: 0 | AC91: 0 | AD91: 0 | AE91: 8328.96 | AF91: 0 | AG91: 24AAACO3087C1ZT | AH91: KGS | AI91: 73063090 | AJ91: Rs. | AK91: 1 | AL91: 964 | AM91: India
H92: 15-07-2026 | I92: Plastene India ltd - Unit 1-Sales | J92: Sales | K92: 166 | L92: Sales - Waste & Scrape | M92: HPBL4/D/166 | N92: 15-07-2026 | O92: SF | P92: Wastage/Scrap | Q92: Wastage/Scrap | R92: HDPE/PP Plastik Waste | S92: PP/HD Wastage/Scrap | T92: 2360 | U92: 28320 | V92: PP/HD Wastage/Scrap | W92: 34085.95 | X92: 9 | Y92: 2548.8 | Z92: 9 | AA92: 2548.8 | AB92: 0 | AC92: 0 | AD92: 0 | AE92: 5097.6 | AF92: 668.35 | AG92: 24AAACO3087C1ZT | AH92: KGS | AI92: 39159029 | AJ92: Rs. | AK92: 1 | AL92: 2360 | AM92: India
H93: 16-07-2026 | I93: Agroszemek Kft | J93: Export Sales | K93: HPBL4/E/67/26-27 | L93: Sales - Direct Export - Mfg - U/B | M93: HPBL4/E/67/26-27 | N93: 16-07-2026 | O93: FG | P93: FIBC Bags | Q93: FIBC Bags | R93: JUMBO BAG | S93: FIBC Bags With UV With Liner | T93: 7665 | U93: 1683000 | V93: PP WOVEN BIG BAGS/SACKS WITH LINERS | W93: 4133756.5 | X93: 0 | Y93: 0 | Z93: 0 | AA93: 0 | AB93: 0 | AC93: 0 | AD93: 0 | AE93: 0 | AF93: 0 | AG93: N.A. | AH93: KGS | AI93: 63053200 | AJ93: $ | AK93: 93.5 | AL93: 7665 | AM93: Hungary
H94: 16-07-2026 | I94: Agroszemek Kft | J94: Export Sales | K94: HPBL4/E/67/26-27 | L94: Sales - Direct Export - Mfg - U/B | M94: HPBL4/E/67/26-27 | N94: 16-07-2026 | O94: FG | P94: FIBC Bags | Q94: FIBC Bags | R94: JUMBO BAG | S94: FIBC Bags With UV Without Liner | T94: 11283 | U94: 2450756.5 | V94: PP WOVEN BIG BAGS/SACKS | W94: 0 | X94: 0 | Y94: 0 | Z94: 0 | AA94: 0 | AB94: 0 | AC94: 0 | AD94: 0 | AE94: 0 | AF94: 0 | AG94: N.A. | AH94: KGS | AI94: 63053200 | AJ94: $ | AK94: 93.5 | AL94: 11283 | AM94: Hungary
H95: 17-07-2026 | I95: Plastene India ltd - Unit 1-Sales | J95: Sales | K95: 167 | L95: Sales - Within State - Traded Goods | M95: HPBL4/D/167 | N95: 17-07-2026 | O95: SF | P95: PP/PE Fabric | Q95: PP UL Fabric | R95: PP Woven Fabric | S95: PP UL Fabric With UV | T95: 1559 | U95: 243967.91 | V95: MW 90 GSM | W95: 287882.13 | X95: 9 | Y95: 21957.11 | Z95: 9 | AA95: 21957.11 | AB95: 0 | AC95: 0 | AD95: 0 | AE95: 43914.22 | AF95: 0 | AG95: 24AAACO3087C1ZT | AH95: KGS | AI95: 39269080 | AJ95: Rs. | AK95: 1 | AL95: 1559 | AM95: India
H96: 17-07-2026 | I96: Rafia Industrial S.A. | J96: Export Sales | K96: HPBL4/E/68/26-27 | L96: Sales - Direct Export - Mfg - U/B | M96: HPBL4/E/68/26-27 | N96: 17-07-2026 | O96: FG | P96: FIBC Bags | Q96: FIBC Bags | R96: JUMBO BAG | S96: FIBC Bags With UV With Liner | T96: 18525 | U96: 4118858.4 | V96: PP WOVEN BIG BAGS/SACKS WITH LINER | W96: 4567473.4 | X96: 0 | Y96: 0 | Z96: 0 | AA96: 0 | AB96: 0 | AC96: 0 | AD96: 0 | AE96: 0 | AF96: 0 | AG96: N.A. | AH96: KGS | AI96: 63053200 | AJ96: $ | AK96: 95.45 | AL96: 18525 | AM96: SPAIN
H97: 18-07-2026 | I97: Plastene India ltd - Unit 1-Sales | J97: Sales | K97: 168 | L97: Sales - Within State - Traded Goods | M97: HPBL4/D/168 | N97: 18-07-2026 | O97: Stores/Spares | P97: MS Structure Items | Q97: Spares & Stores | R97: Stores & Consumables | S97: MS Pipe 4 C Class | T97: 675 | U97: 32400 | V97: OLD/USED FABRIC ROLL PIPE | W97: 38199.6 | X97: 9 | Y97: 2916 | Z97: 9 | AA97: 2916 | AB97: 0 | AC97: 0 | AD97: 0 | AE97: 5832 | AF97: 0 | AG97: 24AAACO3087C1ZT | AH97: KGS | AI97: 73063090 | AJ97: Rs. | AK97: 1 | AL97: 675 | AM97: India
H98: 18-07-2026 | I98: Plastene India ltd - Unit 1-Sales | J98: Sales | K98: 169 | L98: Sales - Waste & Scrape | M98: HPBL4/D/169 | N98: 18-07-2026 | O98: SF | P98: Wastage/Scrap | Q98: Wastage/Scrap | R98: HDPE/PP Plastik Waste | S98: PP/HD Wastage/Scrap | T98: 2260 | U98: 27120 | V98: PP/HD Wastage/Scrap | W98: 32641.63 | X98: 9 | Y98: 2440.8 | Z98: 9 | AA98: 2440.8 | AB98: 0 | AC98: 0 | AD98: 0 | AE98: 4881.6 | AF98: 640.03 | AG98: 24AAACO3087C1ZT | AH98: KGS | AI98: 39159029 | AJ98: Rs. | AK98: 1 | AL98: 2260 | AM98: India
H99: 18-07-2026 | I99: Rafia Industrial S.A. | J99: Export Sales | K99: HPBL4/E/69/26-27 | L99: Sales - Direct Export - Mfg - U/B | M99: HPBL4/E/69/26-27 | N99: 18-07-2026 | O99: FG | P99: FIBC Bags | Q99: FIBC Bags | R99: JUMBO BAG | S99: FIBC Bags With UV With Liner | T99: 18648 | U99: 4118858.4 | V99: PP WOVEN BIG BAGS/SACKS WITH LINER | W99: 4567473.4 | X99: 0 | Y99: 0 | Z99: 0 | AA99: 0 | AB99: 0 | AC99: 0 | AD99: 0 | AE99: 0 | AF99: 0 | AG99: N.A. | AH99: KGS | AI99: 63053200 | AJ99: $ | AK99: 95.45 | AL99: 18648 | AM99: SPAIN
H100: 19-07-2026 | I100: Plastene India ltd - Unit 1-Sales | J100: Sales | K100: 170 | L100: Sales - Within State - Traded Goods | M100: HPBL4/D/170 | N100: 19-07-2026 | O100: FG | P100: FIBC WIP | Q100: FIBC WIP | R100: FIBC WIP | S100: PP Woven Fabric | T100: 1866 | U100: 52248 | V100: DEAD STOCK FABRIC RP PURPOSE | W100: 61600.39 | X100: 9 | Y100: 4702.32 | Z100: 9 | AA100: 4702.32 | AB100: 0 | AC100: 0 | AD100: 0 | AE100: 9404.64 | AF100: 0 | AG100: 24AAACO3087C1ZT | AH100: KGS | AI100: 39269080 | AJ100: Rs. | AK100: 1 | AL100: 1866 | AM100: India
H101: 19-07-2026 | I101: Plastene India ltd - Unit 1-Sales | J101: Sales | K101: 171 | L101: Sales - Waste & Scrape | M101: HPBL4/D/171 | N101: 19-07-2026 | O101: SF | P101: Wastage/Scrap | Q101: Wastage/Scrap | R101: HDPE/PP Plastik Waste | S101: PP/HD Wastage/Scrap | T101: 1974 | U101: 23688 | V101: PP/HD Wastage/Scrap | W101: 28510.88 | X101: 9 | Y101: 2131.92 | Z101: 9 | AA101: 2131.92 | AB101: 0 | AC101: 0 | AD101: 0 | AE101: 4263.84 | AF101: 559.04 | AG101: 24AAACO3087C1ZT | AH101: KGS | AI101: 39159029 | AJ101: Rs. | AK101: 1 | AL101: 1974 | AM101: India
H102: 20-07-2026 | I102: Plastene India ltd - Unit 1-Sales | J102: Sales | K102: 172 | L102: Sales - Within State - Traded Goods | M102: HPBL4/D/172 | N102: 20-07-2026 | O102: Stores/Spares | P102: MS Structure Items | Q102: Spares & Stores | R102: Stores & Consumables | S102: MS Pipe 4 C Class | T102: 731 | U102: 35088 | V102: OLD/USED FABRIC ROLL PIPE | W102: 41368.75 | X102: 9 | Y102: 3157.92 | Z102: 9 | AA102: 3157.92 | AB102: 0 | AC102: 0 | AD102: 0 | AE102: 6315.84 | AF102: 0 | AG102: 24AAACO3087C1ZT | AH102: KGS | AI102: 73063090 | AJ102: Rs. | AK102: 1 | AL102: 731 | AM102: India
H103: 20-07-2026 | I103: Plastene Polyfilms Ltd-Sales | J103: Sales | K103: 173 | L103: Sales - Within State - Traded Goods | M103: HPBL4/D/173 | N103: 20-07-2026 | O103: RM Consumables | P103: Ink | Q103: Thinner | R103: Thinner | S103: Thinner Vyankatesh Thinner | T103: 170 | U103: 47940 | V103: Thinner Vyankatesh Thinner | W103: 56521.26 | X103: 9 | Y103: 4314.6 | Z103: 9 | AA103: 4314.6 | AB103: 0 | AC103: 0 | AD103: 0 | AE103: 8629.2 | AF103: 0 | AG103: 24AAFCP2956A1ZR | AH103: KGS | AI103: 38140011 | AJ103: Rs. | AK103: 1 | AL103: 170 | AM103: India
H104: 20-07-2026 | I104: Rafia Industrial S.A. | J104: Export Sales | K104: HPBL4/E/70/26-27 | L104: Sales - Direct Export - Mfg - U/R | M104: HPBL4/E/70/26-27 | N104: 20-07-2026 | O104: FG | P104: FIBC Bags | Q104: FIBC Bags | R104: JUMBO BAG | S104: FIBC Bags With UV Without Liner | T104: 18455 | U104: 4727638.5 | V104: PP WOVEN BIG BAGS/SACKS | W104: 5176253.5 | X104: 0 | Y104: 0 | Z104: 0 | AA104: 0 | AB104: 18 | AC104: 850974.93 | AD104: 0 | AE104: 850974.93 | AF104: 0 | AG104: N.A. | AH104: KGS | AI104: 63053200 | AJ104: $ | AK104: 95.45 | AL104: 18455 | AM104: SPAIN
H105: 21-07-2026 | I105: Plastene India ltd - Unit 1-Sales | J105: Sales | K105: 174 | L105: Sales - Within State - Traded Goods | M105: HPBL4/D/174 | N105: 21-07-2026 | O105: Stores/Spares | P105: MS Structure Items | Q105: Spares & Stores | R105: Stores & Consumables | S105: MS Pipe 4 C Class | T105: 704 | U105: 33792 | V105: OLD/USED FABRIC ROLL PIPE | W105: 39840.77 | X105: 9 | Y105: 3041.28 | Z105: 9 | AA105: 3041.28 | AB105: 0 | AC105: 0 | AD105: 0 | AE105: 6082.56 | AF105: 0 | AG105: 24AAACO3087C1ZT | AH105: KGS | AI105: 73063090 | AJ105: Rs. | AK105: 1 | AL105: 704 | AM105: India
H106: 21-07-2026 | I106: Plastene India ltd - Unit 1-Sales | J106: Sales | K106: 175 | L106: Sales - Waste & Scrape | M106: HPBL4/D/175 | N106: 21-07-2026 | O106: SF | P106: Wastage/Scrap | Q106: Wastage/Scrap | R106: HDPE/PP Plastik Waste | S106: PP/HD Wastage/Scrap | T106: 2426 | U106: 29112 | V106: PP/HD Wastage/Scrap | W106: 35039.2 | X106: 9 | Y106: 2620.08 | Z106: 9 | AA106: 2620.08 | AB106: 0 | AC106: 0 | AD106: 0 | AE106: 5240.16 | AF106: 687.04 | AG106: 24AAACO3087C1ZT | AH106: KGS | AI106: 39159029 | AJ106: Rs. | AK106: 1 | AL106: 2426 | AM106: India
H107: 21-07-2026 | I107: Plastene India ltd - Unit 1-Sales | J107: Sales | K107: 176 | L107: Sales - Within State - Traded Goods | M107: HPBL4/D/176 | N107: 21-07-2026 | O107: FG | P107: FIBC WIP | Q107: FIBC WIP | R107: FIBC WIP | S107: PP Woven Fabric | T107: 1534 | U107: 42952 | V107: DEAD STOCK FABRIC RP PURPOSE | W107: 50640.41 | X107: 9 | Y107: 3865.68 | Z107: 9 | AA107: 3865.68 | AB107: 0 | AC107: 0 | AD107: 0 | AE107: 7731.36 | AF107: 0 | AG107: 24AAACO3087C1ZT | AH107: KGS | AI107: 39269080 | AJ107: Rs. | AK107: 1 | AL107: 1534 | AM107: India
H108: 21-07-2026 | I108: Plastene India ltd - Unit 1-Sales | J108: Sales | K108: 177 | L108: Sales - Within State Manufactured Goods | M108: HPBL4/D/177 | N108: 21-07-2026 | O108: FG | P108: FIBC Bags | Q108: FIBC Bags | R108: JUMBO BAG | S108: FIBC Bags With UV Without Liner | T108: 1031 | U108: 199333.54 | V108: 91X91X180 | W108: 833629.68 | X108: 9 | Y108: 17940.02 | Z108: 9 | AA108: 17940.02 | AB108: 0 | AC108: 0 | AD108: 0 | AE108: 35880.04 | AF108: 0 | AG108: 24AAACO3087C1ZT | AH108: KGS | AI108: 63053200 | AJ108: Rs. | AK108: 1 | AL108: 1031 | AM108: India
H109: 21-07-2026 | I109: Plastene India ltd - Unit 1-Sales | J109: Sales | K109: 177 | L109: Sales - Within State Manufactured Goods | M109: HPBL4/D/177 | N109: 21-07-2026 | O109: FG | P109: FIBC Bags | Q109: FIBC Bags | R109: JUMBO BAG | S109: FIBC Bags With UV Without Liner | T109: 837 | U109: 175945.77 | V109: 86X86X108 | W109: 0 | X109: 9 | Y109: 15835.12 | Z109: 9 | AA109: 15835.12 | AB109: 0 | AC109: 0 | AD109: 0 | AE109: 31670.24 | AF109: 0 | AG109: 24AAACO3087C1ZT | AH109: KGS | AI109: 63053200 | AJ109: Rs. | AK109: 1 | AL109: 837 | AM109: India
H110: 21-07-2026 | I110: Plastene India ltd - Unit 1-Sales | J110: Sales | K110: 177 | L110: Sales - Within State Manufactured Goods | M110: HPBL4/D/177 | N110: 21-07-2026 | O110: FG | P110: FIBC Bags | Q110: FIBC Bags | R110: JUMBO BAG | S110: FIBC Bags With UV Without Liner | T110: 788 | U110: 175936.76 | V110: 95X95X110 | W110: 0 | X110: 9 | Y110: 15834.31 | Z110: 9 | AA110: 15834.31 | AB110: 0 | AC110: 0 | AD110: 0 | AE110: 31668.62 | AF110: 0 | AG110: 24AAACO3087C1ZT | AH110: KGS | AI110: 63053200 | AJ110: Rs. | AK110: 1 | AL110: 788 | AM110: India
...

Sheet Trail Balance-JULY26
B1: HCP Plastene Bulkpack Ltd (Unit - IV)
A2: Perticulars | B2: 01-Jul-2026 31-Jul-2026
B3: Opening | C3: Transaction | E3: Closing
C4: Debit | D4: Credit
A5: Tds Receivable 2025-26 | B5: 742627.38 | E5: 742627.38
A6: Tds Receivable 2026-27 | B6: 86338.15 | C6: 36373.51 | E6: 122711.66
A7: Insurance Claim Receivable | B7: 47453 | E7: 47453
A8: CGST Input | B8: -0.01 | C8: 9074912.8 | D8: 90 | E8: 9074822.8
A9: GST Credit-Non Eligible | C9: 98 | D9: 98
A10: IGST Input | C10: 305084.77 | E10: 305084.77
A11: SGST Input | B11: -0.01 | C11: 9074912.5 | D11: 90 | E11: 9074822.5
A12: HCP Plastene Bulkpack Limited - For Gst Only | B12: 33848589 | E12: 33848589
A13: IGST Refund Receivable Under Rebate | B13: 60425028 | C13: 8894188.4 | E13: 69319217
A14: Plastene India Ltd - Unit 6-For Gst Balance Only | B14: 12386 | E14: 12386
A15: Provident Fund On Behalf Of Contractors | B15: 7588 | C15: 7716 | D15: 7588 | E15: 7716
A16: Prepaid Insurance | B16: 271713.94 | C16: 16225 | E16: 287938.94
A17: Security deposit- Rent | B17: 1690000 | E17: 1690000
A18: Advance for Travel & Others | B18: 10000 | E18: 10000
A19: Advance Salary Paid | B19: -38500 | C19: 53500 | E19: 15000
A20: Harchanda Ram Imprest A/c | D20: 36817 | E20: -36817
A21: Pravin Chauhan Imprest A/c | B21: 26091 | C21: 51291 | D21: 47206 | E21: 30176
A22: HCP Plastene Bulkpack Limited - Sales | B22: 84715498 | E22: 84715498
A23: Hcp Plastene Bulkpack Ltd Vadodara-Sales | B23: 932117.04 | E23: 932117.04
A24: K.P. Woven Pvt Ltd - Unit 3 -Sales | B24: 25161008 | C24: 2056898.1 | D24: 5603716.1 | E24: 21614190
A25: K.P. Woven Pvt Ltd-Sales | B25: 1.2665864e+08 | C25: 12043513 | E25: 1.3870216e+08
A26: Plastene India ltd - Unit 1-Sales | C26: 26891797 | E26: 26891797
A27: Plastene India ltd - Unit 2-Sales
A28: Plastene India ltd - Unit 6-Sales | B28: -2750310.8 | D28: 408766.61 | E28: -3159077.4
A29: Plastene Polyfilms Ltd-Sales | B29: 49783549 | C29: 56521.26 | E29: 49840070
A30: Rfbl Flexi Pack Limited | B30: -497207 | E30: -497207
A31: Agroszemek Kft | B31: 39291785 | C31: 12616077 | D31: 42812821 | E31: 9095040.2
A32: Cesur France | C32: 4444454.5 | E32: 4444454.5
A33: Fibco Plastic Industry Llc | B33: 3729278.6 | E33: 3729278.6
A34: Industria Sulfuria S.A. | B34: 10837862 | C34: 5313792 | D34: 10833810 | E34: 5317844.4
A35: Oswal Extrusion Ltd- KASEZ-Sales | B35: 22079.83 | C35: 47952 | E35: 70031.83
A36: Qpac Ltd | B36: 12825328 | C36: 14424850 | E36: 27250179
A37: Rafia Industrial S.A. | B37: 16644009 | C37: 62200059 | D37: 20844116 | E37: 57999952
A38: Rugo Bags Gmbh
A39: Safesack Finland Oy
A40: Safesack Scandinavia Ab | B40: 18891733 | C40: 10337779 | D40: 18891733 | E40: 10337779
A41: SO Bag | B41: 4745520 | D41: 4745520
A42: Hydraulic Hand Pallet Truck | B42: 10000 | E42: 10000
A43: Plant & Machinery | B43: 100000 | E43: 100000
A44: DG Set | B44: 1681000 | E44: 1681000
A45: Pnumatic Strapping Machine | B45: 14000 | E45: 14000
A46: Computers & Printers | B46: 34492.44 | E46: 34492.44
A47: Packing Forwading & Cartage Expense | B47: 52886 | C47: 100 | E47: 52986
A48: Round Off - Purchases | B48: 12.42 | C48: 13.18 | D48: 7.33 | E48: 18.27
A49: C & F Charges - Import | B49: 10163.38 | E49: 10163.38
A50: Custom Duty & Charges | B50: 75199 | E50: 75199
A51: Freight Inward Expense (RCM) | B51: 16350 | C51: 2480 | E51: 18830
A52: Freight Inward Expense (With GST) | B52: 27171.62 | C52: 6392.24 | E52: 33563.86
A53: Freight Inward Expense (Without Gst) | B53: 4880 | C53: 3020 | E53: 7900
A54: Consumables, Tools & Spare Expense | B54: -16840 | D54: 1550 | E54: -18390
A55: Electricity Exp (Staff Colony) | B55: 43281.5 | C55: 22806.99 | D55: 24150 | E55: 41938.49
A56: Labour Charges | B56: 14348537 | C56: 7562933 | E56: 21911470
A57: Power Expense | B57: 1417249.9 | C57: 408766.61 | E57: 1826016.5
A58: Rent Expense - Factory | B58: 1181250 | C58: 393750 | E58: 1575000
A59: Rent Expense Colony With Gst | B59: 439032 | C59: 146344 | E59: 585376
A60: Insurance Expenses - Plant | C60: 46775 | E60: 46775
A61: Internal Transportation Expense / Reimbursement | B61: 47400 | C61: 26350 | E61: 73750
A62: Job Charges | B62: 323363.5 | C62: 102838.5 | E62: 426202
A63: Loading & Unloading Expense | B63: 4630 | C63: 4590 | E63: 9220
A64: Testing Charges | B64: 3300 | E64: 3300
A65: Water Charges | B65: 233330 | C65: 148340 | E65: 381670
A66: Weighment Expense | B66: 18780 | C66: 8500 | E66: 27280
A67: Repairs & Maintenance Exp - Plant & Machinery | B67: 179734.06 | C67: 22600 | E67: 202334.06
A68: Branch Transfer In - Raw Material | B68: 556815.4 | C68: 737284.43 | E68: 1294099.8
A69: Branch Transfer In - Trading | B69: 1543316.7 | C69: 394723.71 | E69: 1938040.4
A70: Purchase Withinstate- Packing Material | B70: 4516367.9 | C70: 1190255 | E70: 5706622.9
A71: Purchase Interstate - Raw Material | B71: 2265210 | C71: 849175 | E71: 3114385
A72: Purchase Withinstate - Raw Material | B72: 2.2916126e+08 | C72: 89309381 | E72: 3.1847064e+08
A73: Purchase - Import - Stores, Spares & Consumable | B73: 858116.82 | E73: 858116.82
A74: Purchase Interstate- Stores, Spares & Consumable | B74: 405232 | C74: 344891 | E74: 750123
A75: Purchase Withinstate- Stores, Spares & Consumable | B75: 3717541.6 | C75: 1235657.4 | E75: 4953199.1
A76: Purchase Withinstate - Traded Goods | B76: 2901319.5 | C76: 2224616.5 | E76: 5125936
A77: Conveyance Expenses | B77: 51980 | C77: 19080 | E77: 71060
A78: House Keeping Expense | B78: 106400 | C78: 41800 | E78: 148200
A79: Mobile & Telephone Expense | C79: 10497 | E79: 10497
A80: Office Expenses | B80: 1327 | C80: 499 | E80: 1826
A81: Penalty (Legal) - Expense | B81: 928 | C81: 300 | E81: 1228
A82: Petrol & Diesel Expense - Other Vehicles | B82: 3900 | C82: 2060 | E82: 5960
A83: Postage & Courier Expense | B83: 5909 | C83: 7068.8 | E83: 12977.8
A84: Printing & Stationery Expense | B84: 1310 | C84: 474 | E84: 1784
A85: Rent Expense - Office | B85: 236250 | C85: 78750 | E85: 315000
A86: Round Off | B86: -25.76 | C86: 3.31 | D86: 7.49 | E86: -29.94
A87: Security Expenses | B87: 140870 | C87: 55677 | E87: 196547
A88: Repairs & Maintenance Exp - Building | B88: 35145.64 | C88: 805.92 | E88: 35951.56
A89: Repairs & Maintenance Exp - Computer & Printers | B89: 7960 | C89: 6000 | E89: 13960
A90: Repairs & Maintenance Exp - Electric | B90: 66210 | C90: 11274 | E90: 77484
A91: Repairs & Maintenance Exp - Other Vehicles | B91: 6850 | C91: 1730 | E91: 8580
A92: Repairs & Maintenance Exp - Others | B92: 47967.25 | C92: 184807.5 | E92: 232774.75
A93: Vehicle Hire Charges - RCM | B93: 527240 | C93: 163170 | E93: 690410
A94: P.F. Admin. Charge | B94: 5356 | C94: 2794 | E94: 8150
A95: P.F. Contribution - Employer | B95: 96842 | C95: 33221 | E95: 130063
A96: Allowance - Canteen | B96: 467790 | E96: 467790
A97: Allowance - House Rent | B97: 779601 | E97: 779601
A98: Allowance - Other | B98: 1385 | E98: 1385
A99: Allowance - Special | B99: 208223 | E99: 208223
A100: Allowance - Washing | B100: 311845 | E100: 311845
...

Sheet Inward Summary
B3: Row Labels | C3: Sum of Recdqty
B4: DOC Pouch | C4: 2442.5 | D4: LLDPE BAGS/LINNER/DOC
B5: FIBC Bags With UV Without Liner | C5: 43346.7 | D5: JUMBO BAGS
B6: LDPE/LLDPE Bags/Liner | C6: 92085.96 | D6: LLDPE BAGS/LINNER/DOC
B7: PP UL Fabric With UV | C7: 330428.3 | D7: UNLAMINATED FABRIC
B8: Webbing | C8: 50926.8 | D8: WEBBING
B9: PP Lam Fabric With UV | C9: 51178.8 | D9: LAMINATED FABRIC
B10: PP MF Yarn Twisted 3000 Denier UV NW | C10: 3305 | D10: YARN
B11: PP Fibrillated Tape Twisted 3200 Blue | C11: 4079.5
B12: Thinner Vyankatesh Thinner | C12: 5489 | D12: THINNER
B13: Zip Lock Bags | C13: 71500 | D13: ZIP LOCK BAGS
B14: PP MF Yarn Twisted 3000 Denier UV Deep Blue | C14: 1922.56 | D14: YARN
B15: LDPE/LLDPE Film | C15: 82.5 | D15: LLDPE BAGS/LINNER/DOC
B16: FIBC WIP | C16: 8451.7 | D16: FIBC WIP
B17: Ink Vyankatesh Poly Opaque White OPEQUE WHITE VLX 624 | C17: 200 | D17: INK
B18: Ink Vyankatesh Poly Process Yellow VLX 671 | C18: 150
B19: Ink Vyankatesh Poly Red Pantone 032C | C19: 75
B20: Ink Vyankatesh Poly Green 355C VLX 619 | C20: 100
B21: Ink Vyankatesh Red 485c | C21: 150
B22: PP Fibrillated Tape Twisted 3200 MW | C22: 1721.8 | D22: YARN
B23: Ink Vyankatesh Poly Process Blue VLX 643 | C23: 100 | D23: INK
B24: Ink Vyankatesh Poly Black VLX 579 | C24: 300
B25: Ink Vyankatesh Poly Robbin Red VLX 876 | C25: 75
B26: PP UL Fabric Without UV | C26: 1128 | D26: UNLAMINATED FABRIC
B27: Jute Fabric | C27: 2000 | D27: JUTE FABRIC
B28: Grand Total | C28: 671239.12

Sheet Inward Register
B1: CompanyName | C1: Date | D1: srno | E1: Itemcode | F1: Itemname | G1: Indentsubcode | H1: PoNO | I1: OrderQty | J1: Challanqty | K1: Unit | L1: Recdqty | M1: PendingQty | N1: Acceptedqty | O1: Vehicalno | P1: Partyname | Q1: Suppliername | R1: ChallanNo | S1: Challan Date | T1: category | U1: subcategory | V1: MRno | W1: Rate | X1: Amount | Y1: BillNo | Z1: Bill Date | AA1: ItemRemarks | AB1: Remarks | AC1: Note | AD1: Transportname | AE1: Lrnodate | AF1: Discamt | AG1: Discamt1 | AH1: ExciseAmount | AI1: EducessAmount | AJ1: HiEducessamount | AK1: InwardVatType | AL1: Vatamount | AM1: Addvatamount | AN1: Frieght | AO1: Pkgfwd | AP1: Otherchg | AQ1: Spdutyname | AR1: Spdutyamt | AS1: Additionalduty | AT1: Billamount | AU1: Deptt | AV1: GroupName | AW1: SubGroupName | AX1: Deptt Po Indent | AY1: LoginName | AZ1: servicetax | BA1: Basic Amount | BB1: GateInwardNo | BC1: GateInwardDate | BD1: VendorGST | BE1: MRN User | BF1: POUserName | BG1: CGSTPer | BH1: CGSTAmount | BI1: SGSTPer | BJ1: SGSTAmount | BK1: IGSTPer | BL1: IGSTAmount | BM1: RBIllmount | BN1: EWayNo | BO1: EWayDt | BP1: netwt
B2: HCP Plastene Bulkpack Ltd (Unit - IV) | C2: 46029 | D2: HPBL4/26-27/SII00777 | E2: WIP00023 | F2: PP UL Fabric With UV | H2: HPBL4/RAW/26-27/287 | I2: 70000 | J2: 2836 | K2: Kgs | L2: 2836 | M2: 46103 | N2: 2836 | O2: GJ12BY0479 | P2: Plastene India ltd - Unit 1-Purchase | Q2: Plastene India ltd - Unit 1-Purchase | R2: PIL1/D/874 | S2: 46029 | T2: RAW MATERIAL | U2: INDIGENOUS | V2: RM 324 | W2: 149.74 | X2: 149.74 | Y2: PIL1/D/874 | Z2: 46029 | AB2: - | AD2: LAXMAN B BAKUTRA | AE2: 171 DT 01/07/2026 | AF2: 0 | AG2: 0 | AH2: 0 | AI2: 0 | AJ2: 0 | AK2: VAT | AL2: 0 | AM2: 0 | AN2: 0 | AO2: 0 | AP2: 0 | AR2: 0 | AS2: 0 | AT2: 1728555.2 | AU2: SF | AV2: PP/PE Fabric | AW2: PP UL Fabric | AX2: RM | AY2: erp | AZ2: 0 | BA2: 424662.64 | BB2: 739 | BC2: 46029 | BD2: 24AAACO3087C1ZT | BE2: storepil6 | BF2: storepil6 | BG2: 9 | BH2: 38219.64 | BI2: 9 | BJ2: 38219.64 | BK2: 0 | BL2: 0 | BM2: 1728555.2 | BN2: 602137996771 | BO2: 46204 | BP2: 0
B3: HCP Plastene Bulkpack Ltd (Unit - IV) | C3: 46029 | D3: HPBL4/26-27/SII00777 | E3: WIP00023 | F3: PP UL Fabric With UV | H3: HPBL4/RAW/26-27/287 | I3: 150000 | J3: 6027 | K3: Kgs | L3: 6027 | M3: 92868 | N3: 6027 | O3: GJ12BY0479 | P3: Plastene India ltd - Unit 1-Purchase | Q3: Plastene India ltd - Unit 1-Purchase | R3: PIL1/D/874 | S3: 46029 | T3: RAW MATERIAL | U3: INDIGENOUS | V3: RM 324 | W3: 147.74 | X3: 147.74 | Y3: PIL1/D/874 | Z3: 46029 | AB3: - | AD3: LAXMAN B BAKUTRA | AE3: 171 DT 01/07/2026 | AF3: 0 | AG3: 0 | AH3: 0 | AI3: 0 | AJ3: 0 | AK3: VAT | AL3: 0 | AM3: 0 | AN3: 0 | AO3: 0 | AP3: 0 | AR3: 0 | AS3: 0 | AT3: 1728555.2 | AU3: SF | AV3: PP/PE Fabric | AW3: PP UL Fabric | AX3: RM | AY3: erp | AZ3: 0 | BA3: 890428.98 | BB3: 739 | BC3: 46029 | BD3: 24AAACO3087C1ZT | BE3: storepil6 | BF3: storepil6 | BG3: 9 | BH3: 80138.61 | BI3: 9 | BJ3: 80138.61 | BK3: 0 | BL3: 0 | BM3: 0 | BN3: 602137996771 | BO3: 46204 | BP3: 0
B4: HCP Plastene Bulkpack Ltd (Unit - IV) | C4: 46029 | D4: HPBL4/26-27/SII00777 | E4: WIP00023 | F4: PP UL Fabric With UV | H4: HPBL4/RAW/26-27/287 | I4: 40000 | J4: 697 | K4: Kgs | L4: 697 | M4: 34467 | N4: 697 | O4: GJ12BY0479 | P4: Plastene India ltd - Unit 1-Purchase | Q4: Plastene India ltd - Unit 1-Purchase | R4: PIL1/D/874 | S4: 46029 | T4: RAW MATERIAL | U4: INDIGENOUS | V4: RM 324 | W4: 150.74 | X4: 150.74 | Y4: PIL1/D/874 | Z4: 46029 | AB4: - | AD4: LAXMAN B BAKUTRA | AE4: 171 DT 01/07/2026 | AF4: 0 | AG4: 0 | AH4: 0 | AI4: 0 | AJ4: 0 | AK4: VAT | AL4: 0 | AM4: 0 | AN4: 0 | AO4: 0 | AP4: 0 | AR4: 0 | AS4: 0 | AT4: 1728555.2 | AU4: SF | AV4: PP/PE Fabric | AW4: PP UL Fabric | AX4: RM | AY4: erp | AZ4: 0 | BA4: 105065.78 | BB4: 739 | BC4: 46029 | BD4: 24AAACO3087C1ZT | BE4: storepil6 | BF4: storepil6 | BG4: 9 | BH4: 9455.92 | BI4: 9 | BJ4: 9455.92 | BK4: 0 | BL4: 0 | BM4: 0 | BN4: 602137996771 | BO4: 46204 | BP4: 0
B5: HCP Plastene Bulkpack Ltd (Unit - IV) | C5: 46029 | D5: HPBL4/26-27/SII00777 | E5: WIP00025 | F5: PP Lam Fabric With UV | H5: HPBL4/RAW/26-27/287 | I5: 8000 | J5: 289 | K5: Kgs | L5: 289 | M5: 5058 | N5: 289 | O5: GJ12BY0479 | P5: Plastene India ltd - Unit 1-Purchase | Q5: Plastene India ltd - Unit 1-Purchase | R5: PIL1/D/874 | S5: 46029 | T5: RAW MATERIAL | U5: INDIGENOUS | V5: RM 324 | W5: 154.74 | X5: 154.74 | Y5: PIL1/D/874 | Z5: 46029 | AB5: - | AD5: LAXMAN B BAKUTRA | AE5: 171 DT 01/07/2026 | AF5: 0 | AG5: 0 | AH5: 0 | AI5: 0 | AJ5: 0 | AK5: VAT | AL5: 0 | AM5: 0 | AN5: 0 | AO5: 0 | AP5: 0 | AR5: 0 | AS5: 0 | AT5: 1728555.2 | AU5: SF | AV5: PP/PE Fabric | AW5: PP Lam Fabric | AX5: RM | AY5: erp | AZ5: 0 | BA5: 44719.86 | BB5: 739 | BC5: 46029 | BD5: 24AAACO3087C1ZT | BE5: storepil6 | BF5: storepil6 | BG5: 9 | BH5: 4024.79 | BI5: 9 | BJ5: 4024.79 | BK5: 0 | BL5: 0 | BM5: 0 | BN5: 602137996771 | BO5: 46204 | BP5: 0
B6: HCP Plastene Bulkpack Ltd (Unit - IV) | C6: 46029 | D6: HPBL4/26-27/SII00779 | E6: WIP00025 | F6: PP Lam Fabric With UV | H6: HPBL4/RAW/26-27/287 | I6: 8000 | J6: 400 | K6: Kgs | L6: 400 | M6: 4658 | N6: 400 | O6: GJ12BT2409 | P6: Plastene India ltd - Unit 1-Purchase | Q6: Plastene India ltd - Unit 1-Purchase | R6: PIL1/D/876 | S6: 46029 | T6: RAW MATERIAL | U6: INDIGENOUS | V6: RM 325 | W6: 154.74 | X6: 154.74 | Y6: PIL1/D/876 | Z6: 46029 | AB6: - | AD6: OWN VEHICLE | AE6: - | AF6: 0 | AG6: 0 | AH6: 0 | AI6: 0 | AJ6: 0 | AK6: VAT | AL6: 0 | AM6: 0 | AN6: 0 | AO6: 0 | AP6: 0 | AR6: 0 | AS6: 0 | AT6: 1323569.5 | AU6: SF | AV6: PP/PE Fabric | AW6: PP Lam Fabric | AX6: RM | AY6: erp | AZ6: 0 | BA6: 61896 | BB6: 741 | BC6: 46029 | BD6: 24AAACO3087C1ZT | BE6: storepil6 | BF6: storepil6 | BG6: 9 | BH6: 5570.64 | BI6: 9 | BJ6: 5570.64 | BK6: 0 | BL6: 0 | BM6: 1323569.5 | BN6: 642138014933 | BO6: 46204 | BP6: 0
B7: HCP Plastene Bulkpack Ltd (Unit - IV) | C7: 46029 | D7: HPBL4/26-27/SII00779 | E7: WIP00025 | F7: PP Lam Fabric With UV | H7: HPBL4/RAW/26-27/306 | I7: 571 | J7: 571 | K7: Kgs | L7: 571 | M7: 0 | N7: 571 | O7: GJ12BT2409 | P7: Plastene India ltd - Unit 1-Purchase | Q7: Plastene India ltd - Unit 1-Purchase | R7: PIL1/D/876 | S7: 46029 | T7: RAW MATERIAL | U7: INDIGENOUS | V7: RM 325 | W7: 154.74 | X7: 154.74 | Y7: PIL1/D/876 | Z7: 46029 | AB7: - | AD7: OWN VEHICLE | AE7: - | AF7: 0 | AG7: 0 | AH7: 0 | AI7: 0 | AJ7: 0 | AK7: VAT | AL7: 0 | AM7: 0 | AN7: 0 | AO7: 0 | AP7: 0 | AR7: 0 | AS7: 0 | AT7: 1323569.5 | AU7: SF | AV7: PP/PE Fabric | AW7: PP Lam Fabric | AX7: RM | AY7: erp | AZ7: 0 | BA7: 88356.54 | BB7: 741 | BC7: 46029 | BD7: 24AAACO3087C1ZT | BE7: storepil6 | BF7: storepil6 | BG7: 9 | BH7: 7952.09 | BI7: 9 | BJ7: 7952.09 | BK7: 0 | BL7: 0 | BM7: 0 | BN7: 642138014933 | BO7: 46204 | BP7: 0
B8: HCP Plastene Bulkpack Ltd (Unit - IV) | C8: 46029 | D8: HPBL4/26-27/SII00779 | E8: WIP00023 | F8: PP UL Fabric With UV | H8: HPBL4/RAW/26-27/287 | I8: 150000 | J8: 392 | K8: Kgs | L8: 392 | M8: 92476 | N8: 392 | O8: GJ12BT2409 | P8: Plastene India ltd - Unit 1-Purchase | Q8: Plastene India ltd - Unit 1-Purchase | R8: PIL1/D/876 | S8: 46029 | T8: RAW MATERIAL | U8: INDIGENOUS | V8: RM 325 | W8: 147.74 | X8: 147.74 | Y8: PIL1/D/876 | Z8: 46029 | AB8: - | AD8: OWN VEHICLE | AE8: - | AF8: 0 | AG8: 0 | AH8: 0 | AI8: 0 | AJ8: 0 | AK8: VAT | AL8: 0 | AM8: 0 | AN8: 0 | AO8: 0 | AP8: 0 | AR8: 0 | AS8: 0 | AT8: 1323569.5 | AU8: SF | AV8: PP/PE Fabric | AW8: PP UL Fabric | AX8: RM | AY8: erp | AZ8: 0 | BA8: 57914.08 | BB8: 741 | BC8: 46029 | BD8: 24AAACO3087C1ZT | BE8: storepil6 | BF8: storepil6 | BG8: 9 | BH8: 5212.27 | BI8: 9 | BJ8: 5212.27 | BK8: 0 | BL8: 0 | BM8: 0 | BN8: 642138014933 | BO8: 46204 | BP8: 0
B9: HCP Plastene Bulkpack Ltd (Unit - IV) | C9: 46029 | D9: HPBL4/26-27/SII00779 | E9: WIP00013 | F9: LDPE/LLDPE Bags/Liner | H9: HPBL4/RAW/26-27/306 | I9: 3917 | J9: 3917 | K9: Kgs | L9: 3917 | M9: 0 | N9: 3917 | O9: GJ12BT2409 | P9: Plastene India ltd - Unit 1-Purchase | Q9: Plastene India ltd - Unit 1-Purchase | R9: PIL1/D/876 | S9: 46029 | T9: RAW MATERIAL | U9: INDIGENOUS | V9: RM 325 | W9: 181.15 | X9: 181.15 | Y9: PIL1/D/876 | Z9: 46029 | AB9: - | AD9: OWN VEHICLE | AE9: - | AF9: 0 | AG9: 0 | AH9: 0 | AI9: 0 | AJ9: 0 | AK9: VAT | AL9: 0 | AM9: 0 | AN9: 0 | AO9: 0 | AP9: 0 | AR9: 0 | AS9: 0 | AT9: 1323569.5 | AU9: SF | AV9: Liners | AW9: LDPE/LLDPE Bags | AX9: RM | AY9: erp | AZ9: 0 | BA9: 709564.55 | BB9: 741 | BC9: 46029 | BD9: 24AAACO3087C1ZT | BE9: storepil6 | BF9: storepil6 | BG9: 9 | BH9: 63860.81 | BI9: 9 | BJ9: 63860.81 | BK9: 0 | BL9: 0 | BM9: 0 | BN9: 642138014933 | BO9: 46204 | BP9: 0
B10: HCP Plastene Bulkpack Ltd (Unit - IV) | C10: 46029 | D10: HPBL4/26-27/SII00779 | E10: WIP00032 | F10: Webbing | H10: HPBL4/RAW/26-27/287 | I10: 15000 | J10: 236.8 | K10: Kgs | L10: 236.8 | M10: 11199.4 | N10: 236.8 | O10: GJ12BT2409 | P10: Plastene India ltd - Unit 1-Purchase | Q10: Plastene India ltd - Unit 1-Purchase | R10: PIL1/D/876 | S10: 46029 | T10: RAW MATERIAL | U10: INDIGENOUS | V10: RM 325 | W10: 149.74 | X10: 149.74 | Y10: PIL1/D/876 | Z10: 46029 | AB10: - | AD10: OWN VEHICLE | AE10: - | AF10: 0 | AG10: 0 | AH10: 0 | AI10: 0 | AJ10: 0 | AK10: VAT | AL10: 0 | AM10: 0 | AN10: 0 | AO10: 0 | AP10: 0 | AR10: 0 | AS10: 0 | AT10: 1323569.5 | AU10: SF | AV10: Webbing | AW10: PP Webbing | AX10: RM | AY10: erp | AZ10: 0 | BA10: 35458.43 | BB10: 741 | BC10: 46029 | BD10: 24AAACO3087C1ZT | BE10: storepil6 | BF10: storepil6 | BG10: 9 | BH10: 3191.26 | BI10: 9 | BJ10: 3191.26 | BK10: 0 | BL10: 0 | BM10: 0 | BN10: 642138014933 | BO10: 46204 | BP10: 0
B11: HCP Plastene Bulkpack Ltd (Unit - IV) | C11: 46029 | D11: HPBL4/26-27/SII00779 | E11: WIP00032 | F11: Webbing | H11: HPBL4/RAW/26-27/287 | I11: 30000 | J11: 1091.9 | K11: Kgs | L11: 1091.9 | M11: 17643.1 | N11: 1091.9 | O11: GJ12BT2409 | P11: Plastene India ltd - Unit 1-Purchase | Q11: Plastene India ltd - Unit 1-Purchase | R11: PIL1/D/876 | S11: 46029 | T11: RAW MATERIAL | U11: INDIGENOUS | V11: RM 325 | W11: 152.74 | X11: 152.74 | Y11: PIL1/D/876 | Z11: 46029 | AB11: - | AD11: OWN VEHICLE | AE11: - | AF11: 0 | AG11: 0 | AH11: 0 | AI11: 0 | AJ11: 0 | AK11: VAT | AL11: 0 | AM11: 0 | AN11: 0 | AO11: 0 | AP11: 0 | AR11: 0 | AS11: 0 | AT11: 1323569.5 | AU11: SF | AV11: Webbing | AW11: PP Webbing | AX11: RM | AY11: erp | AZ11: 0 | BA11: 166776.81 | BB11: 741 | BC11: 46029 | BD11: 24AAACO3087C1ZT | BE11: storepil6 | BF11: storepil6 | BG11: 9 | BH11: 15009.91 | BI11: 9 | BJ11: 15009.91 | BK11: 0 | BL11: 0 | BM11: 0 | BN11: 642138014933 | BO11: 46204 | BP11: 0
B12: HCP Plastene Bulkpack Ltd (Unit - IV) | C12: 46029 | D12: HPBL4/26-27/SII00779 | E12: WIP00032 | F12: Webbing | H12: HPBL4/RAW/26-27/287 | I12: 500 | J12: 9.8 | K12: Kgs | L12: 9.8 | M12: 486.8 | N12: 9.8 | O12: GJ12BT2409 | P12: Plastene India ltd - Unit 1-Purchase | Q12: Plastene India ltd - Unit 1-Purchase | R12: PIL1/D/876 | S12: 46029 | T12: RAW MATERIAL | U12: INDIGENOUS | V12: RM 325 | W12: 173.74 | X12: 173.74 | Y12: PIL1/D/876 | Z12: 46029 | AB12: - | AD12: OWN VEHICLE | AE12: - | AF12: 0 | AG12: 0 | AH12: 0 | AI12: 0 | AJ12: 0 | AK12: VAT | AL12: 0 | AM12: 0 | AN12: 0 | AO12: 0 | AP12: 0 | AR12: 0 | AS12: 0 | AT12: 1323569.5 | AU12: SF | AV12: Webbing | AW12: PP Webbing | AX12: RM | AY12: erp | AZ12: 0 | BA12: 1702.65 | BB12: 741 | BC12: 46029 | BD12: 24AAACO3087C1ZT | BE12: storepil6 | BF12: storepil6 | BG12: 9 | BH12: 153.24 | BI12: 9 | BJ12: 153.24 | BK12: 0 | BL12: 0 | BM12: 0 | BN12: 642138014933 | BO12: 46204 | BP12: 0
B13: HCP Plastene Bulkpack Ltd (Unit - IV) | C13: 46060 | D13: HPBL4/26-27/SII00780 | E13: FIG00001 | F13: FIBC WIP | H13: HPBL4/RAW/26-27/307 | I13: 500 | J13: 500 | K13: Kgs | L13: 500 | M13: 0 | N13: 500 | O13: - | P13: Plastene India ltd - Unit 1-Purchase | Q13: Plastene India ltd - Unit 1-Purchase | R13: PIL1/D/877 | S13: 46029 | T13: RAW MATERIAL | U13: INDIGENOUS | V13: RM 326 | W13: 157.74 | X13: 157.74 | Y13: PIL1/D/877 | Z13: 46029 | AB13: - | AD13: OWN VEHICLE | AE13: - | AF13: 0 | AG13: 0 | AH13: 0 | AI13: 0 | AJ13: 0 | AK13: VAT | AL13: 0 | AM13: 0 | AN13: 0 | AO13: 0 | AP13: 0 | AR13: 0 | AS13: 0 | AT13: 355750.86 | AU13: FG | AV13: FIBC WIP | AW13: FIBC WIP | AX13: RM | AY13: erp | AZ13: 0 | BA13: 78870 | BB13: 749 | BC13: 46060 | BD13: 24AAACO3087C1ZT | BE13: storepil6 | BF13: storepil6 | BG13: 9 | BH13: 7098.3 | BI13: 9 | BJ13: 7098.3 | BK13: 0 | BL13: 0 | BM13: 355750.86 | BN13: 652138107489 | BO13: 46204 | BP13: 0
... B112: HCP Plastene Bulkpack Ltd (Unit - IV) | C112: 46241 | D112: HPBL4/26-27/SII00839 | E112: SMF00052 | F112: PP Fibrillated Tape Twisted 3200 Blue | H112: HPBL4/RAW/26-27/341 | I112: 431.6 | J112: 431.6 | K112: Kgs | L112: 431.6 | M112: 0 | N112: 431.6 | O112: GJ12BT2409 | P112: Plastene India ltd - Unit 1-Purchase | Q112: Plastene India ltd - Unit 1-Purchase | R112: PIL1/D/964 | S112: 46241 | T112: RAW MATERIAL | U112: INDIGENOUS | V112: RM 361 | W112: 159.49 | X112: 159.49 | Y112: PIL1/D/964 | Z112: 46241 | AB112: . | AD112: . | AE112: . | AF112: 0 | AG112: 0 | AH112: 0 | AI112: 0 | AJ112: 0 | AK112: VAT | AL112: 0 | AM112: 0 | AN112: 0 | AO112: 0 | AP112: 0 | AR112: 0 | AS112: 0 | AT112: 692094.44 | AU112: SF | AV112: Yarn All | AW112: PP Yarn | AX112: RM | AY112: erp | AZ112: 0 | BA112: 68835.88 | BB112: 798 | BC112: 46241 | BD112: 24AAACO3087C1ZT | BE112: storepil6 | BF112: storepil6 | BG112: 2.5 | BH112: 1720.9 | BI112: 2.5 | BJ112: 1720.9 | BK112: 0 | BL112: 0 | BM112: 692094.44 | BN112: 622141554503 | BO112: 46211 | BP112: 0
B113: HCP Plastene Bulkpack Ltd (Unit - IV) | C113: 46241 | D113: HPBL4/26-27/SII00839 | E113: WIP00191 | F113: PP MF Yarn Twisted 3000 Denier UV NW | H113: HPBL4/RAW/26-27/341 | I113: 1274.8 | J113: 1274.8 | K113: KGS | L113: 1274.8 | M113: 0 | N113: 1274.8 | O113: GJ12BT2409 | P113: Plastene India ltd - Unit 1-Purchase | Q113: Plastene India ltd - Unit 1-Purchase | R113: PIL1/D/964 | S113: 46241 | T113: RAW MATERIAL | U113: INDIGENOUS | V113: RM 361 | W113: 156.49 | X113: 156.49 | Y113: PIL1/D/964 | Z113: 46241 | AB113: . | AD113: . | AE113: . | AF113: 0 | AG113: 0 | AH113: 0 | AI113: 0 | AJ113: 0 | AK113: VAT | AL113: 0 | AM113: 0 | AN113: 0 | AO113: 0 | AP113: 0 | AR113: 0 | AS113: 0 | AT113: 692094.44 | AU113: SF | AV113: Yarn All | AW113: PP Yarn | AX113: RM | AZ113: 0 | BA113: 199493.45 | BB113: 798 | BC113: 46241 | BD113: 24AAACO3087C1ZT | BE113: storepil6 | BF113: storepil6 | BG113: 2.5 | BH113: 4987.34 | BI113: 2.5 | BJ113: 4987.34 | BK113: 0 | BL113: 0 | BM113: 0 | BN113: 622141554503 | BO113: 46211 | BP113: 0
B114: HCP Plastene Bulkpack Ltd (Unit - IV) | C114: 46241 | D114: HPBL4/26-27/SII00839 | E114: WIP00032 | F114: Webbing | H114: HPBL4/RAW/26-27/341 | I114: 1020.7 | J114: 1020.7 | K114: Kgs | L114: 1020.7 | M114: 0 | N114: 1020.7 | O114: GJ12BT2409 | P114: Plastene India ltd - Unit 1-Purchase | Q114: Plastene India ltd - Unit 1-Purchase | R114: PIL1/D/964 | S114: 46241 | T114: RAW MATERIAL | U114: INDIGENOUS | V114: RM 361 | W114: 149.49 | X114: 149.49 | Y114: PIL1/D/964 | Z114: 46241 | AB114: . | AD114: . | AE114: . | AF114: 0 | AG114: 0 | AH114: 0 | AI114: 0 | AJ114: 0 | AK114: VAT | AL114: 0 | AM114: 0 | AN114: 0 | AO114: 0 | AP114: 0 | AR114: 0 | AS114: 0 | AT114: 692094.44 | AU114: SF | AV114: Webbing | AW114: PP Webbing | AX114: RM | AY114: erp | AZ114: 0 | BA114: 152584.44 | BB114: 798 | BC114: 46241 | BD114: 24AAACO3087C1ZT | BE114: storepil6 | BF114: storepil6 | BG114: 9 | BH114: 13732.6 | BI114: 9 | BJ114: 13732.6 | BK114: 0 | BL114: 0 | BM114: 0 | BN114: 622141554503 | BO114: 46211 | BP114: 0
B115: HCP Plastene Bulkpack Ltd (Unit - IV) | C115: 46241 | D115: HPBL4/26-27/SII00839 | E115: WIP00032 | F115: Webbing | H115: HPBL4/RAW/26-27/341 | I115: 1332.3 | J115: 1332.3 | K115: Kgs | L115: 1332.3 | M115: 0 | N115: 1332.3 | O115: GJ12BT2409 | P115: Plastene India ltd - Unit 1-Purchase | Q115: Plastene India ltd - Unit 1-Purchase | R115: PIL1/D/964 | S115: 46241 | T115: RAW MATERIAL | U115: INDIGENOUS | V115: RM 361 | W115: 146.49 | X115: 146.49 | Y115: PIL1/D/964 | Z115: 46241 | AB115: . | AD115: . | AE115: . | AF115: 0 | AG115: 0 | AH115: 0 | AI115: 0 | AJ115: 0 | AK115: VAT | AL115: 0 | AM115: 0 | AN115: 0 | AO115: 0 | AP115: 0 | AR115: 0 | AS115: 0 | AT115: 692094.44 | AU115: SF | AV115: Webbing | AW115: PP Webbing | AX115: RM | AY115: erp | AZ115: 0 | BA115: 195168.63 | BB115: 798 | BC115: 46241 | BD115: 24AAACO3087C1ZT | BE115: storepil6 | BF115: storepil6 | BG115: 9 | BH115: 17565.18 | BI115: 9 | BJ115: 17565.18 | BK115: 0 | BL115: 0 | BM115: 0 | BN115: 622141554503 | BO115: 46211 | BP115: 0
B116: HCP Plastene Bulkpack Ltd (Unit - IV) | C116: 46241 | D116: HPBL4/26-27/SII00840 | E116: SMF00146 | F116: DOC Pouch | H116: HPBL4/RAW/26-27/342 | I116: 930 | J116: 930 | K116: Kgs | L116: 930 | M116: 0 | N116: 930 | O116: GJ24X8795 | P116: HCP Plastene Bulkpack Limited - Purchase | Q116: HCP Plastene Bulkpack Limited - Purchase | R116: HPBL/DC/13 | S116: 27-06-2026 | T116: RAW MATERIAL | U116: INDIGENOUS | V116: RM 362 | W116: 192.99 | X116: 192.99 | Y116: HPBL/DC/13 | Z116: 27-06-2026 | AB116: RECD LATE INVOICE.... | AD116: SHREENA ROAD WAYS | AE116: . | AF116: 0 | AG116: 0 | AH116: 0 | AI116: 0 | AJ116: 0 | AK116: VAT | AL116: 0 | AM116: 0 | AN116: 0 | AO116: 0 | AP116: 0 | AR116: 0 | AS116: 0 | AT116: 179480.7 | AU116: SF | AV116: Liners | AW116: LDPE/LLDPE Bags | AX116: RM | AY116: erp | AZ116: 0 | BA116: 179480.7 | BB116: 11 | BC116: 46241 | BD116: 24AABCG1282C2Z6 | BE116: storepil6 | BF116: storepil6 | BG116: 0 | BH116: 0 | BI116: 0 | BJ116: 0 | BK116: 0 | BL116: 0 | BM116: 179480.7 | BN116: 682135986004 | BO116: 46200 | BP116: 0
B117: HCP Plastene Bulkpack Ltd (Unit - IV) | C117: 46272 | D117: HPBL4/26-27/SII00847 | E117: WIP00023 | F117: PP UL Fabric With UV | H117: HPBL4/RAW/26-27/343 | I117: 745 | J117: 745 | K117: Kgs | L117: 745 | M117: 0 | N117: 745 | O117: GJ35T2925 | P117: Plastene India ltd - Unit 1-Purchase | Q117: Plastene India ltd - Unit 1-Purchase | R117: PIL1/D/986 | S117: 46272 | T117: RAW MATERIAL | U117: INDIGENOUS | V117: RM 363 | W117: 144.49 | X117: 144.49 | Y117: PIL1/D/986 | Z117: 46272 | AB117: . | AD117: . | AE117: . | AF117: 0 | AG117: 0 | AH117: 0 | AI117: 0 | AJ117: 0 | AK117: VAT | AL117: 0 | AM117: 0 | AN117: 0 | AO117: 0 | AP117: 0 | AR117: 0 | AS117: 0 | AT117: 127021.15 | AU117: SF | AV117: PP/PE Fabric | AW117: PP UL Fabric | AX117: RM | AY117: erp | AZ117: 0 | BA117: 107645.05 | BB117: 813 | BC117: 46272 | BD117: 24AAACO3087C1ZT | BE117: storepil6 | BF117: storepil6 | BG117: 9 | BH117: 9688.05 | BI117: 9 | BJ117: 9688.05 | BK117: 0 | BL117: 0 | BM117: 127021.15 | BN117: 692142287612 | BO117: 46212 | BP117: 0
B118: HCP Plastene Bulkpack Ltd (Unit - IV) | C118: 46272 | D118: HPBL4/26-27/SII00848 | E118: WIP00023 | F118: PP UL Fabric With UV | H118: HPBL4/RAW/26-27/343 | I118: 3885 | J118: 3885 | K118: Kgs | L118: 3885 | M118: 0 | N118: 3885 | O118: GJ12BT2409 | P118: Plastene India ltd - Unit 1-Purchase | Q118: Plastene India ltd - Unit 1-Purchase | R118: PIL1/D/977 | S118: 46272 | T118: RAW MATERIAL | U118: INDIGENOUS | V118: RM 364 | W118: 146.49 | X118: 146.49 | Y118: PIL1/D/977 | Z118: 46272 | AB118: . | AD118: . | AE118: . | AF118: 0 | AG118: 0 | AH118: 0 | AI118: 0 | AJ118: 0 | AK118: VAT | AL118: 0 | AM118: 0 | AN118: 0 | AO118: 0 | AP118: 0 | AR118: 0 | AS118: 0 | AT118: 1274726.2 | AU118: SF | AV118: PP/PE Fabric | AW118: PP UL Fabric | AX118: RM | AY118: erp | AZ118: 0 | BA118: 569113.65 | BB118: 806 | BC118: 46272 | BD118: 24AAACO3087C1ZT | BE118: storepil6 | BF118: storepil6 | BG118: 9 | BH118: 51220.23 | BI118: 9 | BJ118: 51220.23 | BK118: 0 | BL118: 0 | BM118: 1274726.2 | BN118: 682141945536 | BO118: 46212 | BP118: 0
B119: HCP Plastene Bulkpack Ltd (Unit - IV) | C119: 46272 | D119: HPBL4/26-27/SII00848 | E119: WIP00023 | F119: PP UL Fabric With UV | H119: HPBL4/RAW/26-27/343 | I119: 660 | J119: 660 | K119: Kgs | L119: 660 | M119: 0 | N119: 660 | O119: GJ12BT2409 | P119: Plastene India ltd - Unit 1-Purchase | Q119: Plastene India ltd - Unit 1-Purchase | R119: PIL1/D/977 | S119: 46272 | T119: RAW MATERIAL | U119: INDIGENOUS | V119: RM 364 | W119: 147.49 | X119: 147.49 | Y119: PIL1/D/977 | Z119: 46272 | AB119: . | AD119: . | AE119: . | AF119: 0 | AG119: 0 | AH119: 0 | AI119: 0 | AJ119: 0 | AK119: VAT | AL119: 0 | AM119: 0 | AN119: 0 | AO119: 0 | AP119: 0 | AR119: 0 | AS119: 0 | AT119: 1274726.2 | AU119: SF | AV119: PP/PE Fabric | AW119: PP UL Fabric | AX119: RM | AY119: erp | AZ119: 0 | BA119: 97343.4 | BB119: 806 | BC119: 46272 | BD119: 24AAACO3087C1ZT | BE119: storepil6 | BF119: storepil6 | BG119: 9 | BH119: 8760.91 | BI119: 9 | BJ119: 8760.91 | BK119: 0 | BL119: 0 | BM119: 0 | BN119: 682141945536 | BO119: 46212 | BP119: 0
B120: HCP Plastene Bulkpack Ltd (Unit - IV) | C120: 46272 | D120: HPBL4/26-27/SII00848 | E120: WIP00023 | F120: PP UL Fabric With UV | H120: HPBL4/RAW/26-27/343 | I120: 2864 | J120: 2864 | K120: Kgs | L120: 2864 | M120: 0 | N120: 2864 | O120: GJ12BT2409 | P120: Plastene India ltd - Unit 1-Purchase | Q120: Plastene India ltd - Unit 1-Purchase | R120: PIL1/D/977 | S120: 46272 | T120: RAW MATERIAL | U120: INDIGENOUS | V120: RM 364 | W120: 144.49 | X120: 144.49 | Y120: PIL1/D/977 | Z120: 46272 | AB120: . | AD120: . | AE120: . | AF120: 0 | AG120: 0 | AH120: 0 | AI120: 0 | AJ120: 0 | AK120: VAT | AL120: 0 | AM120: 0 | AN120: 0 | AO120: 0 | AP120: 0 | AR120: 0 | AS120: 0 | AT120: 1274726.2 | AU120: SF | AV120: PP/PE Fabric | AW120: PP UL Fabric | AX120: RM | AY120: erp | AZ120: 0 | BA120: 413819.36 | BB120: 806 | BC120: 46272 | BD120: 24AAACO3087C1ZT | BE120: storepil6 | BF120: storepil6 | BG120: 9 | BH120: 37243.74 | BI120: 9 | BJ120: 37243.74 | BK120: 0 | BL120: 0 | BM120: 0 | BN120: 682141945536 | BO120: 46212 | BP120: 0
B121: HCP Plastene Bulkpack Ltd (Unit - IV) | C121: 46272 | D121: HPBL4/26-27/SII00850 | E121: WIP00023 | F121: PP UL Fabric With UV | H121: HPBL4/RAW/26-27/344 | I121: 391 | J121: 391 | K121: Kgs | L121: 391 | M121: 0 | N121: 391 | O121: GJ12BY0479 | P121: Plastene India ltd - Unit 1-Purchase | Q121: Plastene India ltd - Unit 1-Purchase | R121: PIL1/D/981 | S121: 46272 | T121: RAW MATERIAL | U121: INDIGENOUS | V121: RM 365 | W121: 146.49 | X121: 146.49 | Y121: PIL1/D/981 | Z121: 46272 | AB121: . | AD121: . | AE121: . | AF121: 0 | AG121: 0 | AH121: 0 | AI121: 0 | AJ121: 0 | AK121: VAT | AL121: 0 | AM121: 0 | AN121: 0 | AO121: 0 | AP121: 0 | AR121: 0 | AS121: 0 | AT121: 1492700.7 | AU121: SF | AV121: PP/PE Fabric | AW121: PP UL Fabric | AX121: RM | AY121: erp | AZ121: 0 | BA121: 57277.59 | BB121: 812 | BC121: 46272 | BD121: 24AAACO3087C1ZT | BE121: storepil6 | BF121: storepil6 | BG121: 9 | BH121: 5154.98 | BI121: 9 | BJ121: 5154.98 | BK121: 0 | BL121: 0 | BM121: 1492700.7 | BN121: 682142055933 | BO121: 46212 | BP121: 0
B122: HCP Plastene Bulkpack Ltd (Unit - IV) | C122: 46272 | D122: HPBL4/26-27/SII00850 | E122: WIP00023 | F122: PP UL Fabric With UV | H122: HPBL4/RAW/26-27/344 | I122: 1402 | J122: 1402 | K122: Kgs | L122: 1402 | M122: 0 | N122: 1402 | O122: GJ12BY0479 | P122: Plastene India ltd - Unit 1-Purchase | Q122: Plastene India ltd - Unit 1-Purchase | R122: PIL1/D/981 | S122: 46272 | T122: RAW MATERIAL | U122: INDIGENOUS | V122: RM 365 | W122: 144.49 | X122: 144.49 | Y122: PIL1/D/981 | Z122: 46272 | AB122: . | AD122: . | AE122: . | AF122: 0 | AG122: 0 | AH122: 0 | AI122: 0 | AJ122: 0 | AK122: VAT | AL122: 0 | AM122: 0 | AN122: 0 | AO122: 0 | AP122: 0 | AR122: 0 | AS122: 0 | AT122: 1492700.7 | AU122: SF | AV122: PP/PE Fabric | AW122: PP UL Fabric | AX122: RM | AY122: erp | AZ122: 0 | BA122: 202574.98 | BB122: 812 | BC122: 46272 | BD122: 24AAACO3087C1ZT | BE122: storepil6 | BF122: storepil6 | BG122: 9 | BH122: 18231.75 | BI122: 9 | BJ122: 18231.75 | BK122: 0 | BL122: 0 | BM122: 0 | BN122: 682142055933 | BO122: 46212 | BP122: 0
B123: HCP Plastene Bulkpack Ltd (Unit - IV) | C123: 46272 | D123: HPBL4/26-27/SII00850 | E123: WIP00025 | F123: PP Lam Fabric With UV | H123: HPBL4/RAW/26-27/344 | I123: 614 | J123: 614 | K123: Kgs | L123: 614 | M123: 0 | N123: 614 | O123: GJ12BY0479 | P123: Plastene India ltd - Unit 1-Purchase | Q123: Plastene India ltd - Unit 1-Purchase | R123: PIL1/D/981 | S123: 46272 | T123: RAW MATERIAL | U123: INDIGENOUS | V123: RM 365 | W123: 151.49 | X123: 151.49 | Y123: PIL1/D/981 | Z123: 46272 | AB123: . | AD123: . | AE123: . | AF123: 0 | AG123: 0 | AH123: 0 | AI123: 0 | AJ123: 0 | AK123: VAT | AL123: 0 | AM123: 0 | AN123: 0 | AO123: 0 | AP123: 0 | AR123: 0 | AS123: 0 | AT123: 1492700.7 | AU123: SF | AV123: PP/PE Fabric | AW123: PP Lam Fabric | AX123: RM | AY123: erp | AZ123: 0 | BA123: 93014.86 | BB123: 812 | BC123: 46272 | BD123: 24AAACO3087C1ZT | BE123: storepil6 | BF123: storepil6 | BG123: 9 | BH123: 8371.34 | BI123: 9 | BJ123: 8371.34 | BK123: 0 | BL123: 0 | BM123: 0 | BN123: 682142055933 | BO123: 46212 | BP123: 0
B124: HCP Plastene Bulkpack Ltd (Unit - IV) | C124: 46272 | D124: HPBL4/26-27/SII00850 | E124: WIP00013 | F124: LDPE/LLDPE Bags/Liner | H124: HPBL4/RAW/26-27/344 | I124: 3320 | J124: 3320 | K124: Kgs | L124: 3320 | M124: 0 | N124: 3320 | O124: GJ12BY0479 | P124: Plastene India ltd - Unit 1-Purchase | Q124: Plastene India ltd - Unit 1-Purchase | R124: PIL1/D/981 | S124: 46272 | T124: RAW MATERIAL | U124: INDIGENOUS | V124: RM 365 | W124: 182.78 | X124: 182.78 | Y124: PIL1/D/981 | Z124: 46272 | AB124: . | AD124: . | AE124: . | AF124: 0 | AG124: 0 | AH124: 0 | AI124: 0 | AJ124: 0 | AK124: VAT | AL124: 0 | AM124: 0 | AN124: 0 | AO124: 0 | AP124: 0 | AR124: 0 | AS124: 0 | AT124: 1492700.7 | AU124: SF | AV124: Liners | AW124: LDPE/LLDPE Bags | AX124: RM | AY124: erp | AZ124: 0 | BA124: 606829.6 | BB124: 812 | BC124: 46272 | BD124: 24AAACO3087C1ZT | BE124: storepil6 | BF124: storepil6 | BG124: 9 | BH124: 54614.66 | BI124: 9 | BJ124: 54614.66 | BK124: 0 | BL124: 0 | BM124: 0 | BN124: 682142055933 | BO124: 46212 | BP124: 0
B125: HCP Plastene Bulkpack Ltd (Unit - IV) | C125: 46272 | D125: HPBL4/26-27/SII00850 | E125: WIP00032 | F125: Webbing | H125: HPBL4/RAW/26-27/344 | I125: 1109.7 | J125: 1109.7 | K125: Kgs | L125: 1109.7 | M125: 0 | N125: 1109.7 | O125: GJ12BY0479 | P125: Plastene India ltd - Unit 1-Purchase | Q125: Plastene India ltd - Unit 1-Purchase | R125: PIL1/D/981 | S125: 46272 | T125: RAW MATERIAL | U125: INDIGENOUS | V125: RM 365 | W125: 149.49 | X125: 149.49 | Y125: PIL1/D/981 | Z125: 46272 | AB125: . | AD125: . | AE125: . | AF125: 0 | AG125: 0 | AH125: 0 | AI125: 0 | AJ125: 0 | AK125: VAT | AL125: 0 | AM125: 0 | AN125: 0 | AO125: 0 | AP125: 0 | AR125: 0 | AS125: 0 | AT125: 1492700.7 | AU125: SF | AV125: Webbing | AW125: PP Webbing | AX125: RM | AY125: erp | AZ125: 0 | BA125: 165889.05 | BB125: 812 | BC125: 46272 | BD125: 24AAACO3087C1ZT | BE125: storepil6 | BF125: storepil6 | BG125: 9 | BH125: 14930.01 | BI125: 9 | BJ125: 14930.01 | BK125: 0 | BL125: 0 | BM125: 0 | BN125: 682142055933 | BO125: 46212 | BP125: 0
B126: HCP Plastene Bulkpack Ltd (Unit - IV) | C126: 46272 | D126: HPBL4/26-27/SII00850 | E126: WIP00032 | F126: Webbing | H126: HPBL4/RAW/26-27/344 | I126: 951.7 | J126: 951.7 | K126: Kgs | L126: 951.7 | M126: 0 | N126: 951.7 | O126: GJ12BY0479 | P126: Plastene India ltd - Unit 1-Purchase | Q126: Plastene India ltd - Unit 1-Purchase | R126: PIL1/D/981 | S126: 46272 | T126: RAW MATERIAL | U126: INDIGENOUS | V126: RM 365 | W126: 146.49 | X126: 146.49 | Y126: PIL1/D/981 | Z126: 46272 | AB126: . | AD126: . | AE126: . | AF126: 0 | AG126: 0 | AH126: 0 | AI126: 0 | AJ126: 0 | AK126: VAT | AL126: 0 | AM126: 0 | AN126: 0 | AO126: 0 | AP126: 0 | AR126: 0 | AS126: 0 | AT126: 1492700.7 | AU126: SF | AV126: Webbing | AW126: PP Webbing | AX126: RM | AY126: erp | AZ126: 0 | BA126: 139414.53 | BB126: 812 | BC126: 46272 | BD126: 24AAACO3087C1ZT | BE126: storepil6 | BF126: storepil6 | BG126: 9 | BH126: 12547.31 | BI126: 9 | BJ126: 12547.31 | BK126: 0 | BL126: 0 | BM126: 0 | BN126: 682142055933 | BO126: 46212 | BP126: 0
B127: HCP Plastene Bulkpack Ltd (Unit - IV) | C127: 46302 | D127: HPBL4/26-27/SII00856 | E127: FIG00001 | F127: FIBC WIP | H127: HPBL4/RAW/26-27/346 | I127: 604 | J127: 604 | K127: Kgs | L127: 604 | M127: 0 | N127: 604 | O127: GJ35T2925 | P127: Plastene Polyfilms Ltd-Purchase | Q127: Plastene Polyfilms Ltd-Purchase | R127: PPL/D/327 | S127: 46272 | T127: RAW MATERIAL | U127: INDIGENOUS | V127: RM 366 | W127: 154.74 | X127: 154.74 | Y127: PPL/D/327 | Z127: 46272 | AB127: . | AD127: . | AE127: . | AF127: 0 | AG127: 0 | AH127: 0 | AI127: 0 | AJ127: 0 | AK127: VAT | AL127: 0 | AM127: 0 | AN127: 0 | AO127: 0 | AP127: 0 | AR127: 0 | AS127: 0 | AT127: 168935.23 | AU127: FG | AV127: FIBC WIP | AW127: FIBC WIP | AX127: RM | AY127: erp | AZ127: 0 | BA127: 93462.96 | BB127: 814 | BC127: 46302 | BD127: 24AAFCP2956A1ZR | BE127: storepil6 | BF127: storepil6 | BG127: 9 | BH127: 8411.67 | BI127: 9 | BJ127: 8411.67 | BK127: 0 | BL127: 0 | BM127: 168935.23 | BN127: 642142230596 | BO127: 46212 | BP127: 0
B128: HCP Plastene Bulkpack Ltd (Unit - IV) | C128: 46302 | D128: HPBL4/26-27/SII00856 | E128: WIP00023 | F128: PP UL Fabric With UV | H128: HPBL4/RAW/26-27/346 | I128: 321.2 | J128: 321.2 | K128: Kgs | L128: 321.2 | M128: 0 | N128: 321.2 | O128: GJ35T2925 | P128: Plastene Polyfilms Ltd-Purchase | Q128: Plastene Polyfilms Ltd-Purchase | R128: PPL/D/327 | S128: 46272 | T128: RAW MATERIAL | U128: INDIGENOUS | V128: RM 366 | W128: 154.74 | X128: 154.74 | Y128: PPL/D/327 | Z128: 46272 | AB128: . | AD128: . | AE128: . | AF128: 0 | AG128: 0 | AH128: 0 | AI128: 0 | AJ128: 0 | AK128: VAT | AL128: 0 | AM128: 0 | AN128: 0 | AO128: 0 | AP128: 0 | AR128: 0 | AS128: 0 | AT128: 168935.23 | AU128: SF | AV128: PP/PE Fabric | AW128: PP UL Fabric | AX128: RM | AY128: erp | AZ128: 0 | BA128: 49702.49 | BB128: 814 | BC128: 46302 | BD128: 24AAFCP2956A1ZR | BE128: storepil6 | BF128: storepil6 | BG128: 9 | BH128: 4473.22 | BI128: 9 | BJ128: 4473.22 | BK128: 0 | BL128: 0 | BM128: 0 | BN128: 642142230596 | BO128: 46212 | BP128: 0
... B170: HCP Plastene Bulkpack Ltd (Unit - IV) | C170: 46363 | D170: HPBL4/26-27/SII00881 | E170: WIP00032 | F170: Webbing | H170: HPBL4/RAW/26-27/359 | I170: 895 | J170: 895 | K170: Kgs | L170: 895 | M170: 0 | N170: 895 | O170: GJ12BY0479 | P170: Plastene India ltd - Unit 1-Purchase | Q170: Plastene India ltd - Unit 1-Purchase | R170: PIL1/D/1024 | S170: 46363 | T170: RAW MATERIAL | U170: INDIGENOUS | V170: RM 380 | W170: 146.49 | X170: 146.49 | Y170: PIL1/D/1024 | Z170: 46363 | AB170: . | AD170: . | AE170: . | AF170: 0 | AG170: 0 | AH170: 0 | AI170: 0 | AJ170: 0 | AK170: VAT | AL170: 0 | AM170: 0 | AN170: 0 | AO170: 0 | AP170: 0 | AR170: 0 | AS170: 0 | AT170: 1671828 | AU170: SF | AV170: Webbing | AW170: PP Webbing | AX170: RM | AY170: erp | AZ170: 0 | BA170: 131108.55 | BB170: 836 | BC170: 46363 | BD170: 24AAACO3087C1ZT | BE170: storepil6 | BF170: storepil6 | BG170: 9 | BH170: 11799.77 | BI170: 9 | BJ170: 11799.77 | BK170: 0 | BL170: 0 | BM170: 0 | BN170: 682143873699 | BO170: 46215 | BP170: 0
B171: HCP Plastene Bulkpack Ltd (Unit - IV) | C171: 13-07-2026 | D171: HPBL4/26-27/SII00882 | E171: WIP00023 | F171: PP UL Fabric With UV | H171: HPBL4/RAW/26-27/362 | I171: 914 | J171: 914 | K171: Kgs | L171: 914 | M171: 0 | N171: 914 | O171: GJ08AW4250 | P171: Plastene India ltd - Unit 2-Purchase | Q171: Plastene India ltd - Unit 2-Purchase | R171: PIL2/D/369 | S171: 13-07-2026 | T171: RAW MATERIAL | U171: INDIGENOUS | V171: RM 381 | W171: 111.6 | X171: 111.6 | Y171: PIL2/D/369 | Z171: 46363 | AB171: . | AD171: . | AE171: . | AF171: 0 | AG171: 0 | AH171: 0 | AI171: 0 | AJ171: 0 | AK171: VAT | AL171: 0 | AM171: 0 | AN171: 0 | AO171: 0 | AP171: 0 | AR171: 0 | AS171: 0 | AT171: 120362.84 | AU171: SF | AV171: PP/PE Fabric | AW171: PP UL Fabric | AX171: RM | AY171: erp | AZ171: 0 | BA171: 102002.4 | BB171: 846 | BC171: 13-07-2026 | BD171: 24AAACO3087C1ZT | BE171: storepil6 | BF171: storepil6 | BG171: 9 | BH171: 9180.22 | BI171: 9 | BJ171: 9180.22 | BK171: 0 | BL171: 0 | BM171: 120362.84 | BN171: 692143942190 | BO171: 46215 | BP171: 0
B172: HCP Plastene Bulkpack Ltd (Unit - IV) | C172: 13-07-2026 | D172: HPBL4/26-27/SII00883 | E172: WIP00013 | F172: LDPE/LLDPE Bags/Liner | H172: HPBL4/RAW/26-27/363 | I172: 4475 | J172: 4475 | K172: Kgs | L172: 4475 | M172: 0 | N172: 4475 | O172: GJ12BT2409 | P172: Plastene India ltd - Unit 1-Purchase | Q172: Plastene India ltd - Unit 1-Purchase | R172: PIL1/D/1033 | S172: 13-07-2026 | T172: RAW MATERIAL | U172: INDIGENOUS | V172: RM 382 | W172: 182.78 | X172: 182.78 | Y172: PIL1/D/1033 | Z172: 13-07-2026 | AB172: . | AD172: . | AE172: . | AF172: 0 | AG172: 0 | AH172: 0 | AI172: 0 | AJ172: 0 | AK172: VAT | AL172: 0 | AM172: 0 | AN172: 0 | AO172: 0 | AP172: 0 | AR172: 0 | AS172: 0 | AT172: 965169.78 | AU172: SF | AV172: Liners | AW172: LDPE/LLDPE Bags | AX172: RM | AY172: erp | AZ172: 0 | BA172: 817940.5 | BB172: 848 | BC172: 13-07-2026 | BD172: 24AAACO3087C1ZT | BE172: storepil6 | BF172: storepil6 | BG172: 9 | BH172: 73614.64 | BI172: 9 | BJ172: 73614.64 | BK172: 0 | BL172: 0 | BM172: 965169.78 | BN172: 682144172300 | BO172: 46216 | BP172: 0
B173: HCP Plastene Bulkpack Ltd (Unit - IV) | C173: 13-07-2026 | D173: HPBL4/26-27/SII00885 | E173: WIP00023 | F173: PP UL Fabric With UV | H173: HPBL4/RAW/26-27/364 | I173: 1080.1 | J173: 1080.1 | K173: Kgs | L173: 1080.1 | M173: 0 | N173: 1080.1 | O173: GJ12BZ4679 | P173: K.P. Woven Pvt Ltd-Purchase | Q173: K.P. Woven Pvt Ltd-Purchase | R173: KPV/D/445 | S173: 13-07-2026 | T173: RAW MATERIAL | U173: INDIGENOUS | V173: RM 383 | W173: 169.15 | X173: 169.15 | Y173: KPV/D/445 | Z173: 46363 | AB173: . | AD173: . | AE173: . | AF173: 0 | AG173: 0 | AH173: 0 | AI173: 0 | AJ173: 0 | AK173: VAT | AL173: 0 | AM173: 0 | AN173: 0 | AO173: 0 | AP173: 0 | AR173: 0 | AS173: 0 | AT173: 441466.74 | AU173: SF | AV173: PP/PE Fabric | AW173: PP UL Fabric | AX173: RM | AY173: erp | AZ173: 0 | BA173: 182698.91 | BB173: 844 | BC173: 13-07-2026 | BD173: 24AAECK6307M1ZF | BE173: storepil6 | BF173: storepil6 | BG173: 9 | BH173: 16442.9 | BI173: 9 | BJ173: 16442.9 | BK173: 0 | BL173: 0 | BM173: 441466.74 | BN173: 662143937126 | BO173: 46215 | BP173: 0
B174: HCP Plastene Bulkpack Ltd (Unit - IV) | C174: 13-07-2026 | D174: HPBL4/26-27/SII00885 | E174: SMF00052 | F174: PP Fibrillated Tape Twisted 3200 Blue | H174: HPBL4/RAW/26-27/364 | I174: 920 | J174: 920 | K174: Kgs | L174: 920 | M174: 0 | N174: 920 | O174: GJ12BZ4679 | P174: K.P. Woven Pvt Ltd-Purchase | Q174: K.P. Woven Pvt Ltd-Purchase | R174: KPV/D/445 | S174: 13-07-2026 | T174: RAW MATERIAL | U174: INDIGENOUS | V174: RM 383 | W174: 154.15 | X174: 154.15 | Y174: KPV/D/445 | Z174: 46363 | AB174: . | AD174: . | AE174: . | AF174: 0 | AG174: 0 | AH174: 0 | AI174: 0 | AJ174: 0 | AK174: VAT | AL174: 0 | AM174: 0 | AN174: 0 | AO174: 0 | AP174: 0 | AR174: 0 | AS174: 0 | AT174: 441466.74 | AU174: SF | AV174: Yarn All | AW174: PP Yarn | AX174: RM | AY174: erp | AZ174: 0 | BA174: 141818 | BB174: 844 | BC174: 13-07-2026 | BD174: 24AAECK6307M1ZF | BE174: storepil6 | BF174: storepil6 | BG174: 2.5 | BH174: 3545.45 | BI174: 2.5 | BJ174: 3545.45 | BK174: 0 | BL174: 0 | BM174: 0 | BN174: 662143937126 | BO174: 46215 | BP174: 0
B175: HCP Plastene Bulkpack Ltd (Unit - IV) | C175: 13-07-2026 | D175: HPBL4/26-27/SII00885 | E175: SMF00054 | F175: PP Fibrillated Tape Twisted 3200 MW | H175: HPBL4/RAW/26-27/364 | I175: 485 | J175: 485 | K175: Kgs | L175: 485 | M175: 0 | N175: 485 | O175: GJ12BZ4679 | P175: K.P. Woven Pvt Ltd-Purchase | Q175: K.P. Woven Pvt Ltd-Purchase | R175: KPV/D/445 | S175: 13-07-2026 | T175: RAW MATERIAL | U175: INDIGENOUS | V175: RM 383 | W175: 151.15 | X175: 151.15 | Y175: KPV/D/445 | Z175: 46363 | AB175: . | AD175: . | AE175: . | AF175: 0 | AG175: 0 | AH175: 0 | AI175: 0 | AJ175: 0 | AK175: VAT | AL175: 0 | AM175: 0 | AN175: 0 | AO175: 0 | AP175: 0 | AR175: 0 | AS175: 0 | AT175: 441466.74 | AU175: SF | AV175: Yarn All | AW175: PP Yarn | AX175: RM | AY175: erp | AZ175: 0 | BA175: 73307.75 | BB175: 844 | BC175: 13-07-2026 | BD175: 24AAECK6307M1ZF | BE175: storepil6 | BF175: storepil6 | BG175: 2.5 | BH175: 1832.69 | BI175: 2.5 | BJ175: 1832.69 | BK175: 0 | BL175: 0 | BM175: 0 | BN175: 662143937126 | BO175: 46215 | BP175: 0
B176: HCP Plastene Bulkpack Ltd (Unit - IV) | C176: 13-07-2026 | D176: HPBL4/26-27/SII00887 | E176: RAW05764 | F176: Thinner Vyankatesh Thinner | H176: HPBL4/RAW/26-27/366 | I176: 170 | J176: 170 | K176: Kgs | L176: 170 | M176: 0 | N176: 170 | O176: GJ12BZ4679 | P176: K.P. Woven Pvt Ltd-Purchase | Q176: K.P. Woven Pvt Ltd-Purchase | R176: KPV/D/442 | S176: 46363 | T176: RAW MATERIAL | U176: INDIGENOUS | V176: RM 385 | W176: 108 | X176: 108 | Y176: KPV/D/442 | Z176: 46363 | AB176: . | AD176: . | AE176: . | AF176: 0 | AG176: 0 | AH176: 0 | AI176: 0 | AJ176: 0 | AK176: VAT | AL176: 0 | AM176: 0 | AN176: 0 | AO176: 0 | AP176: 0 | AR176: 0 | AS176: 0 | AT176: 21664.8 | AU176: RM Consumables | AV176: Ink | AW176: Thinner | AX176: RM | AY176: erp | AZ176: 0 | BA176: 18360 | BB176: 842 | BC176: 13-07-2026 | BD176: 24AAECK6307M1ZF | BE176: storepil6 | BF176: storepil6 | BG176: 9 | BH176: 1652.4 | BI176: 9 | BJ176: 1652.4 | BK176: 0 | BL176: 0 | BM176: 21664.8 | BN176: 652143935804 | BO176: 46215 | BP176: 0
B177: HCP Plastene Bulkpack Ltd (Unit - IV) | C177: 13-07-2026 | D177: HPBL4/26-27/SII00889 | E177: WIP00025 | F177: PP Lam Fabric With UV | H177: HPBL4/RAW/26-27/368 | I177: 775 | J177: 775 | K177: Kgs | L177: 775 | M177: 0 | N177: 775 | O177: GJ12BY2409 | P177: Plastene India ltd - Unit 1-Purchase | Q177: Plastene India ltd - Unit 1-Purchase | R177: PIL1/D/1031 | S177: 13-07-2026 | T177: RAW MATERIAL | U177: INDIGENOUS | V177: RM 387 | W177: 151.49 | X177: 151.49 | Y177: PIL1/D/1031 | Z177: 13-07-2026 | AB177: . | AD177: . | AE177: . | AF177: 0 | AG177: 0 | AH177: 0 | AI177: 0 | AJ177: 0 | AK177: VAT | AL177: 0 | AM177: 0 | AN177: 0 | AO177: 0 | AP177: 0 | AR177: 0 | AS177: 0 | AT177: 2051501.3 | AU177: SF | AV177: PP/PE Fabric | AW177: PP Lam Fabric | AX177: RM | AY177: erp | AZ177: 0 | BA177: 117404.75 | BB177: 845 | BC177: 13-07-2026 | BD177: 24AAACO3087C1ZT | BE177: storepil6 | BF177: storepil6 | BG177: 9 | BH177: 10566.43 | BI177: 9 | BJ177: 10566.43 | BK177: 0 | BL177: 0 | BM177: 2051501.3 | BN177: 682144120648 | BO177: 46216 | BP177: 0
B178: HCP Plastene Bulkpack Ltd (Unit - IV) | C178: 13-07-2026 | D178: HPBL4/26-27/SII00889 | E178: WIP00025 | F178: PP Lam Fabric With UV | H178: HPBL4/RAW/26-27/368 | I178: 246 | J178: 246 | K178: Kgs | L178: 246 | M178: 0 | N178: 246 | O178: GJ12BY2409 | P178: Plastene India ltd - Unit 1-Purchase | Q178: Plastene India ltd - Unit 1-Purchase | R178: PIL1/D/1031 | S178: 13-07-2026 | T178: RAW MATERIAL | U178: INDIGENOUS | V178: RM 387 | W178: 148.49 | X178: 148.49 | Y178: PIL1/D/1031 | Z178: 13-07-2026 | AB178: . | AD178: . | AE178: . | AF178: 0 | AG178: 0 | AH178: 0 | AI178: 0 | AJ178: 0 | AK178: VAT | AL178: 0 | AM178: 0 | AN178: 0 | AO178: 0 | AP178: 0 | AR178: 0 | AS178: 0 | AT178: 2051501.3 | AU178: SF | AV178: PP/PE Fabric | AW178: PP Lam Fabric | AX178: RM | AY178: erp | AZ178: 0 | BA178: 36528.54 | BB178: 845 | BC178: 13-07-2026 | BD178: 24AAACO3087C1ZT | BE178: storepil6 | BF178: storepil6 | BG178: 9 | BH178: 3287.57 | BI178: 9 | BJ178: 3287.57 | BK178: 0 | BL178: 0 | BM178: 0 | BN178: 682144120648 | BO178: 46216 | BP178: 0
B179: HCP Plastene Bulkpack Ltd (Unit - IV) | C179: 13-07-2026 | D179: HPBL4/26-27/SII00889 | E179: WIP00023 | F179: PP UL Fabric With UV | H179: HPBL4/RAW/26-27/368 | I179: 2404 | J179: 2404 | K179: Kgs | L179: 2404 | M179: 0 | N179: 2404 | O179: GJ12BY2409 | P179: Plastene India ltd - Unit 1-Purchase | Q179: Plastene India ltd - Unit 1-Purchase | R179: PIL1/D/1031 | S179: 13-07-2026 | T179: RAW MATERIAL | U179: INDIGENOUS | V179: RM 387 | W179: 146.49 | X179: 146.49 | Y179: PIL1/D/1031 | Z179: 13-07-2026 | AB179: . | AD179: . | AE179: . | AF179: 0 | AG179: 0 | AH179: 0 | AI179: 0 | AJ179: 0 | AK179: VAT | AL179: 0 | AM179: 0 | AN179: 0 | AO179: 0 | AP179: 0 | AR179: 0 | AS179: 0 | AT179: 2051501.3 | AU179: SF | AV179: PP/PE Fabric | AW179: PP UL Fabric | AX179: RM | AY179: erp | AZ179: 0 | BA179: 352161.96 | BB179: 845 | BC179: 13-07-2026 | BD179: 24AAACO3087C1ZT | BE179: storepil6 | BF179: storepil6 | BG179: 9 | BH179: 31694.58 | BI179: 9 | BJ179: 31694.58 | BK179: 0 | BL179: 0 | BM179: 0 | BN179: 682144120648 | BO179: 46216 | BP179: 0
B180: HCP Plastene Bulkpack Ltd (Unit - IV) | C180: 13-07-2026 | D180: HPBL4/26-27/SII00889 | E180: WIP00023 | F180: PP UL Fabric With UV | H180: HPBL4/RAW/26-27/368 | I180: 242 | J180: 242 | K180: Kgs | L180: 242 | M180: 0 | N180: 242 | O180: GJ12BY2409 | P180: Plastene India ltd - Unit 1-Purchase | Q180: Plastene India ltd - Unit 1-Purchase | R180: PIL1/D/1031 | S180: 13-07-2026 | T180: RAW MATERIAL | U180: INDIGENOUS | V180: RM 387 | W180: 147.49 | X180: 147.49 | Y180: PIL1/D/1031 | Z180: 13-07-2026 | AB180: . | AD180: . | AE180: . | AF180: 0 | AG180: 0 | AH180: 0 | AI180: 0 | AJ180: 0 | AK180: VAT | AL180: 0 | AM180: 0 | AN180: 0 | AO180: 0 | AP180: 0 | AR180: 0 | AS180: 0 | AT180: 2051501.3 | AU180: SF | AV180: PP/PE Fabric | AW180: PP UL Fabric | AX180: RM | AY180: erp | AZ180: 0 | BA180: 35692.58 | BB180: 845 | BC180: 13-07-2026 | BD180: 24AAACO3087C1ZT | BE180: storepil6 | BF180: storepil6 | BG180: 9 | BH180: 3212.33 | BI180: 9 | BJ180: 3212.33 | BK180: 0 | BL180: 0 | BM180: 0 | BN180: 682144120648 | BO180: 46216 | BP180: 0
B181: HCP Plastene Bulkpack Ltd (Unit - IV) | C181: 13-07-2026 | D181: HPBL4/26-27/SII00889 | E181: WIP00023 | F181: PP UL Fabric With UV | H181: HPBL4/RAW/26-27/368 | I181: 5911 | J181: 5911 | K181: Kgs | L181: 5911 | M181: 0 | N181: 5911 | O181: GJ12BY2409 | P181: Plastene India ltd - Unit 1-Purchase | Q181: Plastene India ltd - Unit 1-Purchase | R181: PIL1/D/1031 | S181: 13-07-2026 | T181: RAW MATERIAL | U181: INDIGENOUS | V181: RM 387 | W181: 144.49 | X181: 144.49 | Y181: PIL1/D/1031 | Z181: 13-07-2026 | AB181: . | AD181: . | AE181: . | AF181: 0 | AG181: 0 | AH181: 0 | AI181: 0 | AJ181: 0 | AK181: VAT | AL181: 0 | AM181: 0 | AN181: 0 | AO181: 0 | AP181: 0 | AR181: 0 | AS181: 0 | AT181: 2051501.3 | AU181: SF | AV181: PP/PE Fabric | AW181: PP UL Fabric | AX181: RM | AY181: erp | AZ181: 0 | BA181: 854080.39 | BB181: 845 | BC181: 13-07-2026 | BD181: 24AAACO3087C1ZT | BE181: storepil6 | BF181: storepil6 | BG181: 9 | BH181: 76867.24 | BI181: 9 | BJ181: 76867.24 | BK181: 0 | BL181: 0 | BM181: 0 | BN181: 682144120648 | BO181: 46216 | BP181: 0
B182: HCP Plastene Bulkpack Ltd (Unit - IV) | C182: 13-07-2026 | D182: HPBL4/26-27/SII00889 | E182: WIP00032 | F182: Webbing | H182: HPBL4/RAW/26-27/368 | I182: 1501.8 | J182: 1501.8 | K182: Kgs | L182: 1501.8 | M182: 0 | N182: 1501.8 | O182: GJ12BY2409 | P182: Plastene India ltd - Unit 1-Purchase | Q182: Plastene India ltd - Unit 1-Purchase | R182: PIL1/D/1031 | S182: 13-07-2026 | T182: RAW MATERIAL | U182: INDIGENOUS | V182: RM 387 | W182: 149.49 | X182: 149.49 | Y182: PIL1/D/1031 | Z182: 13-07-2026 | AB182: . | AD182: . | AE182: . | AF182: 0 | AG182: 0 | AH182: 0 | AI182: 0 | AJ182: 0 | AK182: VAT | AL182: 0 | AM182: 0 | AN182: 0 | AO182: 0 | AP182: 0 | AR182: 0 | AS182: 0 | AT182: 2051501.3 | AU182: SF | AV182: Webbing | AW182: PP Webbing | AX182: RM | AY182: erp | AZ182: 0 | BA182: 224504.08 | BB182: 845 | BC182: 13-07-2026 | BD182: 24AAACO3087C1ZT | BE182: storepil6 | BF182: storepil6 | BG182: 9 | BH182: 20205.37 | BI182: 9 | BJ182: 20205.37 | BK182: 0 | BL182: 0 | BM182: 0 | BN182: 682144120648 | BO182: 46216 | BP182: 0
B183: HCP Plastene Bulkpack Ltd (Unit - IV) | C183: 13-07-2026 | D183: HPBL4/26-27/SII00889 | E183: WIP00032 | F183: Webbing | H183: HPBL4/RAW/26-27/368 | I183: 806.8 | J183: 806.8 | K183: Kgs | L183: 806.8 | M183: 0 | N183: 806.8 | O183: GJ12BY2409 | P183: Plastene India ltd - Unit 1-Purchase | Q183: Plastene India ltd - Unit 1-Purchase | R183: PIL1/D/1031 | S183: 13-07-2026 | T183: RAW MATERIAL | U183: INDIGENOUS | V183: RM 387 | W183: 146.49 | X183: 146.49 | Y183: PIL1/D/1031 | Z183: 13-07-2026 | AB183: . | AD183: . | AE183: . | AF183: 0 | AG183: 0 | AH183: 0 | AI183: 0 | AJ183: 0 | AK183: VAT | AL183: 0 | AM183: 0 | AN183: 0 | AO183: 0 | AP183: 0 | AR183: 0 | AS183: 0 | AT183: 2051501.3 | AU183: SF | AV183: Webbing | AW183: PP Webbing | AX183: RM | AY183: erp | AZ183: 0 | BA183: 118188.13 | BB183: 845 | BC183: 13-07-2026 | BD183: 24AAACO3087C1ZT | BE183: storepil6 | BF183: storepil6 | BG183: 9 | BH183: 10636.93 | BI183: 9 | BJ183: 10636.93 | BK183: 0 | BL183: 0 | BM183: 0 | BN183: 682144120648 | BO183: 46216 | BP183: 0
B184: HCP Plastene Bulkpack Ltd (Unit - IV) | C184: 13-07-2026 | D184: HPBL4/26-27/SII00891 | E184: RAW05764 | F184: Thinner Vyankatesh Thinner | H184: HPBL4/RAW/26-27/354 | I184: 170 | J184: 170 | K184: Kgs | L184: 170 | M184: 0 | N184: 170 | O184: GJ12BW0544 | P184: Plastene Polyfilms Ltd-Purchase | Q184: Plastene Polyfilms Ltd-Purchase | R184: PPL/D/347 | S184: 13-07-2026 | T184: RAW MATERIAL | U184: INDIGENOUS | V184: RM 388 | W184: 282 | X184: 282 | Y184: PPL/D/347 | Z184: 13-07-2026 | AB184: . | AD184: . | AE184: . | AF184: 0 | AG184: 0 | AH184: 0 | AI184: 0 | AJ184: 0 | AK184: VAT | AL184: 0 | AM184: 0 | AN184: 0 | AO184: 0 | AP184: 0 | AR184: 0 | AS184: 0 | AT184: 56569.2 | AU184: RM Consumables | AV184: Ink | AW184: Thinner | AX184: RM | AY184: erp | AZ184: 0 | BA184: 47940 | BB184: 858 | BC184: 14-07-2026 | BD184: 24AAFCP2956A1ZR | BE184: storepil6 | BF184: storepil6 | BG184: 9 | BH184: 4314.6 | BI184: 9 | BJ184: 4314.6 | BK184: 0 | BL184: 0 | BM184: 56569.2 | BN184: 602144116250 | BO184: 46216 | BP184: 0
B185: HCP Plastene Bulkpack Ltd (Unit - IV) | C185: 14-07-2026 | D185: HPBL4/26-27/SII00894 | E185: WIP00023 | F185: PP UL Fabric With UV | H185: HPBL4/RAW/26-27/361 | I185: 1071.5 | J185: 1071.5 | K185: Kgs | L185: 1071.5 | M185: 0 | N185: 1071.5 | O185: GJ39TB3634 | P185: Plastene Polyfilms Ltd-Purchase | Q185: Plastene Polyfilms Ltd-Purchase | R185: PPL/D/353 | S185: 14-07-2026 | T185: RAW MATERIAL | U185: INDIGENOUS | V185: RM 389 | W185: 154.74 | X185: 154.74 | Y185: PPL/D/353 | Z185: 14-07-2026 | AB185: . | AD185: . | AE185: . | AF185: 0 | AG185: 0 | AH185: 0 | AI185: 0 | AJ185: 0 | AK185: VAT | AL185: 0 | AM185: 0 | AN185: 0 | AO185: 0 | AP185: 0 | AR185: 0 | AS185: 0 | AT185: 207082.81 | AU185: SF | AV185: PP/PE Fabric | AW185: PP UL Fabric | AX185: RM | AY185: erp | AZ185: 0 | BA185: 165803.91 | BB185: 855 | BC185: 14-07-2026 | BD185: 24AAFCP2956A1ZR | BE185: storepil6 | BF185: storepil6 | BG185: 9 | BH185: 14922.35 | BI185: 9 | BJ185: 14922.35 | BK185: 0 | BL185: 0 | BM185: 207082.81 | BN185: 602144757819 | BO185: 46217 | BP185: 0
B186: HCP Plastene Bulkpack Ltd (Unit - IV) | C186: 14-07-2026 | D186: HPBL4/26-27/SII00894 | E186: RAW05124 | F186: LDPE/LLDPE Film | H186: HPBL4/RAW/26-27/361 | I186: 38 | J186: 38 | K186: Kgs | L186: 38 | M186: 0 | N186: 38 | O186: GJ39TB3634 | P186: Plastene Polyfilms Ltd-Purchase | Q186: Plastene Polyfilms Ltd-Purchase | R186: PPL/D/353 | S186: 14-07-2026 | T186: RAW MATERIAL | U186: INDIGENOUS | V186: RM 389 | W186: 255 | X186: 255 | Y186: PPL/D/353 | Z186: 14-07-2026 | AB186: . | AD186: . | AE186: . | AF186: 0 | AG186: 0 | AH186: 0 | AI186: 0 | AJ186: 0 | AK186: VAT | AL186: 0 | AM186: 0 | AN186: 0 | AO186: 0 | AP186: 0 | AR186: 0 | AS186: 0 | AT186: 207082.81 | AU186: SF | AV186: Films All (SF) | AW186: PE Film | AX186: RM | AY186: erp | AZ186: 0 | BA186: 9690 | BB186: 855 | BC186: 14-07-2026 | BD186: 24AAFCP2956A1ZR | BE186: storepil6 | BF186: storepil6 | BG186: 9 | BH186: 872.1 | BI186: 9 | BJ186: 872.1 | BK186: 0 | BL186: 0 | BM186: 0 | BN186: 602144757819 | BO186: 46217 | BP186: 0
B187: HCP Plastene Bulkpack Ltd (Unit - IV) | C187: 14-07-2026 | D187: HPBL4/26-27/SII00895 | E187: WIP00025 | F187: PP Lam Fabric With UV | H187: HPBL4/RAW/26-27/369 | I187: 1722 | J187: 1722 | K187: Kgs | L187: 1722 | M187: 0 | N187: 1722 | O187: GJ12BT2409 | P187: Plastene India ltd - Unit 1-Purchase | Q187: Plastene India ltd - Unit 1-Purchase | R187: PIL1/D/1048 | S187: 14-07-2026 | T187: RAW MATERIAL | U187: INDIGENOUS | V187: RM 390 | W187: 151.49 | X187: 151.49 | Y187: PIL1/D/1048 | Z187: 14-07-2026 | AB187: . | AD187: . | AE187: . | AF187: 0 | AG187: 0 | AH187: 0 | AI187: 0 | AJ187: 0 | AK187: VAT | AL187: 0 | AM187: 0 | AN187: 0 | AO187: 0 | AP187: 0 | AR187: 0 | AS187: 0 | AT187: 307821.62 | AU187: SF | AV187: PP/PE Fabric | AW187: PP Lam Fabric | AX187: RM | AY187: erp | AZ187: 0 | BA187: 260865.78 | BB187: 851 | BC187: 14-07-2026 | BD187: 24AAACO3087C1ZT | BE187: storepil6 | BF187: storepil6 | BG187: 9 | BH187: 23477.92 | BI187: 9 | BJ187: 23477.92 | BK187: 0 | BL187: 0 | BM187: 307821.62 | BN187: 682144880081 | BO187: 46217 | BP187: 0
B188: HCP Plastene Bulkpack Ltd (Unit - IV) | C188: 14-07-2026 | D188: HPBL4/26-27/SII00897 | E188: WIP00013 | F188: LDPE/LLDPE Bags/Liner | H188: HPBL4/RAW/26-27/370 | I188: 1655 | J188: 1655 | K188: Kgs | L188: 1655 | M188: 0 | N188: 1655 | O188: GJ12BT2409 | P188: Plastene India ltd - Unit 1-Purchase | Q188: Plastene India ltd - Unit 1-Purchase | R188: PIL1/D/1047 | S188: 14-07-2026 | T188: RAW MATERIAL | U188: INDIGENOUS | V188: RM 391 | W188: 182.78 | X188: 182.78 | Y188: PIL1/D/1047 | Z188: 14-07-2026 | AB188: . | AD188: . | AE188: . | AF188: 0 | AG188: 0 | AH188: 0 | AI188: 0 | AJ188: 0 | AK188: VAT | AL188: 0 | AM188: 0 | AN188: 0 | AO188: 0 | AP188: 0 | AR188: 0 | AS188: 0 | AT188: 639683.49 | AU188: SF | AV188: Liners | AW188: LDPE/LLDPE Bags | AX188: RM | AY188: erp | AZ188: 0 | BA188: 302500.9 | BB188: 850 | BC188: 14-07-2026 | BD188: 24AAACO3087C1ZT | BE188: storepil6 | BF188: storepil6 | BG188: 9 | BH188: 27225.08 | BI188: 9 | BJ188: 27225.08 | BK188: 0 | BL188: 0 | BM188: 639683.49 | BN188: 682144867620 | BO188: 46217 | BP188: 0
... B239: HCP Plastene Bulkpack Ltd (Unit - IV) | C239: 17-07-2026 | D239: HPBL4/26-27/SII00927 | E239: WIP00032 | F239: Webbing | H239: HPBL4/RAW/26-27/386 | I239: 705.8 | J239: 705.8 | K239: Kgs | L239: 705.8 | M239: 0 | N239: 705.8 | O239: GJ12BT2409 | P239: Plastene India ltd - Unit 1-Purchase | Q239: Plastene India ltd - Unit 1-Purchase | R239: PIL1/D/1085 | S239: 17-07-2026 | T239: RAW MATERIAL | U239: INDIGENOUS | V239: RM 406 | W239: 149.49 | X239: 149.49 | Y239: PIL1/D/1085 | Z239: 17-07-2026 | AB239: . | AD239: . | AE239: . | AF239: 0 | AG239: 0 | AH239: 0 | AI239: 0 | AJ239: 0 | AK239: VAT | AL239: 0 | AM239: 0 | AN239: 0 | AO239: 0 | AP239: 0 | AR239: 0 | AS239: 0 | AT239: 952014.48 | AU239: SF | AV239: Webbing | AW239: PP Webbing | AX239: RM | AY239: erp | AZ239: 0 | BA239: 105510.04 | BB239: 876 | BC239: 17-07-2026 | BD239: 24AAACO3087C1ZT | BE239: storepil6 | BF239: storepil6 | BG239: 9 | BH239: 9495.9 | BI239: 9 | BJ239: 9495.9 | BK239: 0 | BL239: 0 | BM239: 0 | BN239: 692146738749 | BO239: 46220 | BP239: 0
B240: HCP Plastene Bulkpack Ltd (Unit - IV) | C240: 18-07-2026 | D240: HPBL4/26-27/SII00935 | E240: SMF00256 | F240: Jute Fabric | G240: HPBL4/26-27/RWM00001/01 | H240: HPBL4/RAW/26-27/360 | I240: 2000 | J240: 2000 | K240: Yard | L240: 2000 | M240: 0 | N240: 2000 | O240: GJ24V1087 | P240: M B And Sons- Supplier | Q240: M B And Sons- Supplier | R240: 441 | S240: 15-07-2026 | T240: RAW MATERIAL | U240: INDIGENOUS | V240: RM 407 | W240: 34.5 | X240: 35.5 | Y240: 441 | Z240: 15-07-2026 | AB240: . | AD240: HARISH TRANSPORT CO | AE240: 4/10935 | AF240: 0 | AG240: 0 | AH240: 0 | AI240: 0 | AJ240: 0 | AK240: VAT | AL240: 0 | AM240: 0 | AN240: 0 | AO240: 2000 | AP240: 0 | AQ240: GST 5% | AR240: 100 | AS240: 0 | AT240: 74550 | AU240: SF | AV240: Jute Fabric | AX240: RM | AY240: mani | AZ240: 0 | BA240: 71000 | BB240: 880 | BC240: 18-07-2026 | BD240: 24AZSPS3924Q1ZE | BE240: storepil6 | BF240: rmp2 | BG240: 2.5 | BH240: 1725 | BI240: 2.5 | BJ240: 1725 | BK240: 0 | BL240: 0 | BM240: 74550 | BN240: 632145595923 | BO240: 46218 | BP240: 0
B241: HCP Plastene Bulkpack Ltd (Unit - IV) | C241: 18-07-2026 | D241: HPBL4/26-27/SII00937 | E241: WIP00023 | F241: PP UL Fabric With UV | H241: HPBL4/RAW/26-27/387 | I241: 6039 | J241: 6039 | K241: Kgs | L241: 6039 | M241: 0 | N241: 6039 | O241: GJ12BT2409 | P241: Plastene India ltd - Unit 1-Purchase | Q241: Plastene India ltd - Unit 1-Purchase | R241: PIL1/D/1098 | S241: 18-07-2026 | T241: RAW MATERIAL | U241: INDIGENOUS | V241: RM 408 | W241: 144.49 | X241: 144.49 | Y241: PIL1/D/1098 | Z241: 18-07-2026 | AB241: . | AD241: . | AE241: . | AF241: 0 | AG241: 0 | AH241: 0 | AI241: 0 | AJ241: 0 | AK241: VAT | AL241: 0 | AM241: 0 | AN241: 0 | AO241: 0 | AP241: 0 | AR241: 0 | AS241: 0 | AT241: 1374913.8 | AU241: SF | AV241: PP/PE Fabric | AW241: PP UL Fabric | AX241: RM | AY241: erp | AZ241: 0 | BA241: 872575.11 | BB241: 890 | BC241: 18-07-2026 | BD241: 24AAACO3087C1ZT | BE241: storepil6 | BF241: storepil6 | BG241: 9 | BH241: 78531.76 | BI241: 9 | BJ241: 78531.76 | BK241: 0 | BL241: 0 | BM241: 1374913.8 | BN241: 692147266661 | BO241: 46221 | BP241: 0
B242: HCP Plastene Bulkpack Ltd (Unit - IV) | C242: 18-07-2026 | D242: HPBL4/26-27/SII00937 | E242: WIP00023 | F242: PP UL Fabric With UV | H242: HPBL4/RAW/26-27/387 | I242: 505 | J242: 505 | K242: Kgs | L242: 505 | M242: 0 | N242: 505 | O242: GJ12BT2409 | P242: Plastene India ltd - Unit 1-Purchase | Q242: Plastene India ltd - Unit 1-Purchase | R242: PIL1/D/1098 | S242: 18-07-2026 | T242: RAW MATERIAL | U242: INDIGENOUS | V242: RM 408 | W242: 147.49 | X242: 147.49 | Y242: PIL1/D/1098 | Z242: 18-07-2026 | AB242: . | AD242: . | AE242: . | AF242: 0 | AG242: 0 | AH242: 0 | AI242: 0 | AJ242: 0 | AK242: VAT | AL242: 0 | AM242: 0 | AN242: 0 | AO242: 0 | AP242: 0 | AR242: 0 | AS242: 0 | AT242: 1374913.8 | AU242: SF | AV242: PP/PE Fabric | AW242: PP UL Fabric | AX242: RM | AY242: erp | AZ242: 0 | BA242: 74482.45 | BB242: 890 | BC242: 18-07-2026 | BD242: 24AAACO3087C1ZT | BE242: storepil6 | BF242: storepil6 | BG242: 9 | BH242: 6703.42 | BI242: 9 | BJ242: 6703.42 | BK242: 0 | BL242: 0 | BM242: 0 | BN242: 692147266661 | BO242: 46221 | BP242: 0
B243: HCP Plastene Bulkpack Ltd (Unit - IV) | C243: 18-07-2026 | D243: HPBL4/26-27/SII00937 | E243: WIP00023 | F243: PP UL Fabric With UV | H243: HPBL4/RAW/26-27/387 | I243: 1489 | J243: 1489 | K243: Kgs | L243: 1489 | M243: 0 | N243: 1489 | O243: GJ12BT2409 | P243: Plastene India ltd - Unit 1-Purchase | Q243: Plastene India ltd - Unit 1-Purchase | R243: PIL1/D/1098 | S243: 18-07-2026 | T243: RAW MATERIAL | U243: INDIGENOUS | V243: RM 408 | W243: 146.49 | X243: 146.49 | Y243: PIL1/D/1098 | Z243: 18-07-2026 | AB243: . | AD243: . | AE243: . | AF243: 0 | AG243: 0 | AH243: 0 | AI243: 0 | AJ243: 0 | AK243: VAT | AL243: 0 | AM243: 0 | AN243: 0 | AO243: 0 | AP243: 0 | AR243: 0 | AS243: 0 | AT243: 1374913.8 | AU243: SF | AV243: PP/PE Fabric | AW243: PP UL Fabric | AX243: RM | AY243: erp | AZ243: 0 | BA243: 218123.61 | BB243: 890 | BC243: 18-07-2026 | BD243: 24AAACO3087C1ZT | BE243: storepil6 | BF243: storepil6 | BG243: 9 | BH243: 19631.12 | BI243: 9 | BJ243: 19631.12 | BK243: 0 | BL243: 0 | BM243: 0 | BN243: 692147266661 | BO243: 46221 | BP243: 0
B244: HCP Plastene Bulkpack Ltd (Unit - IV) | C244: 18-07-2026 | D244: HPBL4/26-27/SII00938 | E244: WIP00023 | F244: PP UL Fabric With UV | H244: HPBL4/RAW/26-27/387 | I244: 424 | J244: 424 | K244: Kgs | L244: 424 | M244: 0 | N244: 424 | O244: GJ35T2925 | P244: Plastene India ltd - Unit 1-Purchase | Q244: Plastene India ltd - Unit 1-Purchase | R244: PIL1/D/1105 | S244: 18-07-2026 | T244: RAW MATERIAL | U244: INDIGENOUS | V244: RM 409 | W244: 144.49 | X244: 144.49 | Y244: PIL1/D/1105 | Z244: 18-07-2026 | AB244: . | AD244: . | AE244: . | AF244: 0 | AG244: 0 | AH244: 0 | AI244: 0 | AJ244: 0 | AK244: VAT | AL244: 0 | AM244: 0 | AN244: 0 | AO244: 0 | AP244: 0 | AR244: 0 | AS244: 0 | AT244: 171815.18 | AU244: SF | AV244: PP/PE Fabric | AW244: PP UL Fabric | AX244: RM | AY244: erp | AZ244: 0 | BA244: 61263.76 | BB244: 906 | BC244: 18-07-2026 | BD244: 24AAACO3087C1ZT | BE244: storepil6 | BF244: storepil6 | BG244: 9 | BH244: 5513.74 | BI244: 9 | BJ244: 5513.74 | BK244: 0 | BL244: 0 | BM244: 171815.18 | BN244: 632147750195 | BO244: 46221 | BP244: 0
B245: HCP Plastene Bulkpack Ltd (Unit - IV) | C245: 18-07-2026 | D245: HPBL4/26-27/SII00938 | E245: WIP00025 | F245: PP Lam Fabric With UV | H245: HPBL4/RAW/26-27/387 | I245: 568 | J245: 568 | K245: Kgs | L245: 568 | M245: 0 | N245: 568 | O245: GJ35T2925 | P245: Plastene India ltd - Unit 1-Purchase | Q245: Plastene India ltd - Unit 1-Purchase | R245: PIL1/D/1105 | S245: 18-07-2026 | T245: RAW MATERIAL | U245: INDIGENOUS | V245: RM 409 | W245: 148.49 | X245: 148.49 | Y245: PIL1/D/1105 | Z245: 18-07-2026 | AB245: . | AD245: . | AE245: . | AF245: 0 | AG245: 0 | AH245: 0 | AI245: 0 | AJ245: 0 | AK245: VAT | AL245: 0 | AM245: 0 | AN245: 0 | AO245: 0 | AP245: 0 | AR245: 0 | AS245: 0 | AT245: 171815.18 | AU245: SF | AV245: PP/PE Fabric | AW245: PP Lam Fabric | AX245: RM | AY245: erp | AZ245: 0 | BA245: 84342.32 | BB245: 906 | BC245: 18-07-2026 | BD245: 24AAACO3087C1ZT | BE245: storepil6 | BF245: storepil6 | BG245: 9 | BH245: 7590.81 | BI245: 9 | BJ245: 7590.81 | BK245: 0 | BL245: 0 | BM245: 0 | BN245: 632147750195 | BO245: 46221 | BP245: 0
